Workbook

Sheet _Données Employés
B4: Matricule | C4: Civilité | D4: Nom | E4: Prénom | F4: Département | G4: Poste | H4: Salaire Base (FCFA)
B5: EMP-001 | C5: M. | D5: Nganou | E5: Clarisse | F5: Cuisine & Restauration | G5: Chef cuisinier | H5: 450000
B6: EMP-002 | C6: M. | D6: Tchinda | E6: Armand | F6: Réception & Front Office | G6: Réceptionniste | H6: 220000
B7: EMP-003 | C7: Mme | D7: Fotso | E7: Marguerite | F7: Finance & Comptabilité | G7: Comptable senior | H7: 380000
B8: EMP-004 | C8: M. | D8: Nkoulou | E8: Mbarga | F8: Étage & Housekeeping | G8: Gouvernant | H8: 195000
B9: EMP-005 | C9: M. | D9: Kamga | E9: Paul | F9: Maintenance | G9: Technicien maintenance | H9: 165000
B10: EMP-006 | C10: Mme | D10: Ngo | E10: Delphine | F10: Service Client | G10: Conseiller clientèle | H10: 160000
B11: EMP-007 | C11: M. | D11: Essomba | E11: Serge | F11: Maintenance | G11: Agent entretien | H11: 130000
B12: EMP-008 | C12: M. | D12: Tchouankou | E12: Paul | F12: Commercial | G12: Commercial | H12: 150000
B13: EMP-009 | C13: M. | D13: Fokam | E13: Eric | F13: Maintenance | G13: Technicien | H13: 140000
B14: EMP-010 | C14: M. | D14: Tagne | E14: René | F14: Cuisine & Restauration | G14: Plongeur | H14: 90000
B15: EMP-011 | C15: M. | D15: Bouba | E15: Ahmed | F15: Sécurité | G15: Agent Sécurité | H15: 120000
B16: EMP-012 | C16: Mme | D16: Awa | E16: Fatou | F16: Réception & Front Office | G16: Standardiste | H16: 155000
... B18: EMP-029 | C18: M. | D18: Kamga | E18: Patrice | F18: Sécurité | G18: Chef Sécurité | H18: 210000

Sheet 1-Tableau de Bord
B2: DOMAINE 12 — DOCUMENTATION & ARCHIVAGE RH
B3: TABLEAU DE BORD — Vue synthetique de tous les indicateurs du domaine (mis a jour automatiquement)
B5: Documents suivis | E5: Dossiers employes | H5: Boites archives phys. | K5: Fiches numerisees
B6: =COUNTIF('2-Registre Documentation RH'!B5:B104,"<>") | E6: =COUNTIF('3-Gestion Dossiers Employes'!B5:B104,"<>") | H6: =COUNTIF('4-Archivage Physique'!B5:B104,"<>") | K6: =COUNTIF('5-Archivage Numerique'!B5:B104,"<>")
B9: Docs confidentiels | E9: Regles retention | H9: Documents versionnes | K9: Sorties documents
B10: =COUNTIF('6-Gest. Docs. Confidentiels'!B5:B104,"<>") | E10: =COUNTIF('7-Suivi Retention Docs'!B5:B104,"<>") | H10: =COUNTIF('9-Gestion Versions Docs'!B5:B104,"<>") | K10: =COUNTIF('10-Registre Sortie Docs'!B5:B104,"<>")
B13: Dossiers incomplets | E13: Destructions effectuees | H13: Volume numerique (Mo) | K13: Politiques archivage
B14: =COUNTIF('12-Suivi Dossiers Incomplets'!B5:B104,"<>") | E14: =COUNTIF('14-Hist. Destruction Docs'!B5:B104,"<>") | H14: =IFERROR(SUM('5-Archivage Numerique'!G5:G104)/1024,0) | K14: =COUNTIF('11-Politique Archivage'!B5:B104,"<>")
B18: ARCHIVAGE PAR TYPE & DOSSIERS PAR STATUT
B19: Type Document | C19: Nb Fiches
B20: Contrat travail | C20: =COUNTIF('2-Registre Documentation RH'!D5:D104,"*Contrat travail*")+COUNTIF('5-Archivage Numerique'!D5:D104,"*Contrat travail*")
B21: Bulletin paie | C21: =COUNTIF('2-Registre Documentation RH'!D5:D104,"*Bulletin paie*")+COUNTIF('5-Archivage Numerique'!D5:D104,"*Bulletin paie*")
B22: PV reunion | C22: =COUNTIF('2-Registre Documentation RH'!D5:D104,"*PV reunion*")+COUNTIF('5-Archivage Numerique'!D5:D104,"*PV reunion*")
B23: Formation | C23: =COUNTIF('2-Registre Documentation RH'!D5:D104,"*Formation*")+COUNTIF('5-Archivage Numerique'!D5:D104,"*Formation*")
B24: Reglementation | C24: =COUNTIF('2-Registre Documentation RH'!D5:D104,"*Reglementation*")+COUNTIF('5-Archivage Numerique'!D5:D104,"*Reglementation*")
B25: Autre | C25: =COUNTIF('2-Registre Documentation RH'!D5:D104,"*Autre*")+COUNTIF('5-Archivage Numerique'!D5:D104,"*Autre*")
H27: Statut Dossier | I27: Nombre
H28: Complet | I28: =COUNTIF('3-Gestion Dossiers Employes'!J5:J104,"Complet")
H29: Incomplet | I29: =COUNTIF('3-Gestion Dossiers Employes'!J5:J104,"Incomplet")
H30: A mettre a jour | I30: =COUNTIF('3-Gestion Dossiers Employes'!J5:J104,"A mettre a jour")
H31: En cours de constitution | I31: =COUNTIF('3-Gestion Dossiers Employes'!J5:J104,"En cours de constitution")

Sheet _Lists
B1: departement | C1: poste_hotel | D1: type_document | E1: support_archivage | F1: statut_document | G1: niveau_confidentialite | H1: duree_conservation | I1: type_classement | J1: format_document | K1: statut_version | L1: motif_sortie | M1: statut_sortie | N1: statut_dossier | O1: statut_politique | P1: mois | Q1: annee | R1: acces_niveau | S1: statut_action
B2: Direction Générale | C2: DG | D2: Contrat de travail | E2: Papier - Classeur | F2: En cours | G2: Public | H2: 1 an | I2: Alphabetique employe | J2: PDF | K2: Brouillon | L2: Consultation interne | M2: En cours | N2: Complet | O2: En vigueur | P2: Janvier | Q2: 2024 | R2: Lecture seule | S2: Planifiee
B3: Service Client | C3: DRH | D3: Avenant contrat | E3: Papier - Chemise | F3: Archive | G3: Interne | H3: 2 ans | I3: Numerique dossier | J3: Word (.docx) | K3: En revision | L3: Envoi organisme externe | M3: Restitue | N3: Incomplet | O3: En revision | P3: Fevrier | Q3: 2025 | R3: Lecture / Ecriture | S3: En cours
B4: Finance & Comptabilité | C4: Assistante RH | D4: Fiche de paie | E4: Papier - Boite archive | F4: A archiver | G4: Confidentiel | H4: 3 ans | I4: Chronologique | J4: Excel (.xlsx) | K4: Valide | L4: Audit externe | M4: En retard | N4: En cours de constitution | O4: A approuver | P4: Mars | Q4: 2026 | R4: Modification | S4: Terminee
B5: Marketing & Communication | C5: DAF | D5: Attestation travail | E5: Numerique - Serveur RH | F5: A detruire | G5: Tres confidentiel | H5: 5 ans | I5: Par departement | J5: Image (JPEG/PNG) | K5: Obsolete | L5: Expertise comptable | M5: Non restitue | N5: A mettre a jour | O5: Obsolette | P5: Avril | R5: Suppression | S5: Reportee
B6: Maintenance | C6: Comptable senior | D6: Certificat travail | E6: Numerique - Cloud | F6: Perdu | G6: Secret | H6: 10 ans | I6: Par type document | J6: Scan papier | K6: Archivé | L6: Inspection travail | N6: Cloture | O6: En elaboration | P6: Mai | R6: Administrateur | S6: Annulee
B7: Commercial | C7: Chef Comptable | D7: Bulletin paie | E7: Numerique - GED | F7: En restoration | H7: 30 ans | I7: Par annee | J7: Papier original | L7: Tribunal | P7: Juin
B8: Logistique & Approvisionnement | C8: Chef Marketing | D8: Decision promotion | E8: Hybride (papier + numerique) | F8: Extrait copie | H8: Durée du contrat + 5 ans | I8: Mixte | J8: Courriel imprime | L8: Photocopie employe | P8: Juillet
B9: Cuisine & Restauration | C9: Chef de service IT | D9: Decision mutation | E9: Microfilm | H9: Indéfinie | J9: Autre | L9: Pret temporaire | P9: Aout
B10: Réception & Front Office | C10: Technicien IT | D10: Proces-verbal disciplinaire | H10: A determiner | P10: Septembre
B11: Sécurité | C11: Chef Commercial | D11: Entretien annuel | P11: Octobre
B12: Étage & Housekeeping | C12: Agent Commercial | D12: Note de service | P12: Novembre
C13: Chef Logistique | D13: Reglement interieur | P13: Decembre
C14: Magasinier | D14: Politique RH
C15: Chef Reception | D15: Formulaire CNPS
C16: Receptionniste | D16: Formulaire impot
C17: Concierge | D17: Plan de formation
C18: Chef Cuisine | D18: Bilan social
C19: Sous-Chef | D19: PV reunion
C20: Cuisinier | D20: Courrier
C21: Plongeur | D21: Autre
C22: Chef Entretien
C23: Agent Entretien
C24: Chef Securite
C25: Agent Securite

Sheet 2-Registre Documentation RH
B2: REGISTRE DOCUMENTATION RH (#127)
B3: TABLEAU DYNAMIQUE — Saisissez dans la prochaine ligne jaune. Les calculs se mettent a jour automatiquement.
B4: N° | C4: Titre Document | D4: Type Document | E4: Categorie | F4: Date Creation | G4: Auteur | H4: Version | I4: Support | J4: Emplacement | K4: Statut
B5: DOC-001 | C5: Reglement interieur hotel | D5: Reglement interieur | E5: Reglementation | F5: 45458 | G5: DG + DRH | H5: V3.2 | I5: Papier - Classeur | J5: Armoire RH / Serveur RH | K5: En cours
B6: DOC-002 | C6: Grille salariale 2025 | D6: Politique RH | E6: Remuneration | F6: 45667 | G6: DRH + DAF | H6: V2.1 | I6: Numerique - Serveur RH | J6: Serveur RH / Grilles/ | K6: En cours
B7: DOC-003 | C7: Procedure de recrutement | D7: Politique RH | E7: Recrutement | F7: 45536 | G7: DRH | H7: V2.0 | I7: Numerique - Cloud | J7: Google Drive / Procedures/ | K7: En cours
B8: DOC-004 | C8: Charte ethique et conduite | D8: Politique RH | E8: Ethique | F8: 45352 | G8: DG | H8: V1.5 | I8: Papier - Classeur | J8: Armoire RH / Chartes/ | K8: En cours
B9: DOC-005 | C9: Plan formation annuel 2025 | D9: Plan de formation | E9: Formation | F9: 45662 | G9: DRH | H9: V1.0 | I9: Numerique - Serveur RH | J9: Serveur RH / Formation/ | K9: En cours
B10: =IF(C10="","DOC-"&TEXT(COUNTA($C$5:C10),"000"))
B11: =IF(C11="","DOC-"&TEXT(COUNTA($C$5:C11),"000"))
B12: =IF(C12="","DOC-"&TEXT(COUNTA($C$5:C12),"000"))
B13: =IF(C13="","DOC-"&TEXT(COUNTA($C$5:C13),"000"))
B14: =IF(C14="","DOC-"&TEXT(COUNTA($C$5:C14),"000"))
B15: =IF(C15="","DOC-"&TEXT(COUNTA($C$5:C15),"000"))
B16: =IF(C16="","DOC-"&TEXT(COUNTA($C$5:C16),"000"))
B17: =IF(C17="","DOC-"&TEXT(COUNTA($C$5:C17),"000"))
B18: =IF(C18="","DOC-"&TEXT(COUNTA($C$5:C18),"000"))
B19: =IF(C19="","DOC-"&TEXT(COUNTA($C$5:C19),"000"))
B20: =IF(C20="","DOC-"&TEXT(COUNTA($C$5:C20),"000"))
B21: =IF(C21="","DOC-"&TEXT(COUNTA($C$5:C21),"000"))
... B109: =IF(C109="","DOC-"&TEXT(COUNTA($C$5:C109),"000"))
B111: INDICATEURS (mis a jour automatiquement)
B112: Documents suivis | D112: En cours | F112: Archives
B113: =COUNTIF(B5:B104,"<>") | D113: =COUNTIF(K5:K104,"En cours") | F113: =COUNTIF(K5:K104,"Archive")

Sheet 3-Gestion Dossiers Employes
B2: GESTION DOSSIERS EMPLOYÉS (#128)
B3: TABLEAU DYNAMIQUE — Saisissez dans la prochaine ligne jaune. Les calculs se mettent a jour automatiquement.
B4: N° | C4: Employe | D4: Poste | E4: Departement | F4: N° Dossier | G4: Emplacement Physique | H4: Emplacement Numerique | I4: Nb Pieces Dossier | J4: Statut Dossier | K4: Derniere MAJ
B5: DOS-001 | C5: Nkoulou Mbarga P. | D5: Chef Reception | E5: Réception & Front Office | F5: DOSS-2019-001 | G5: Armoire A, Etagere 2, Chemise rouge | H5: Serveur RH / Employes / NKMBP/ | I5: 18 | J5: Complet | K5: 45823
B6: DOS-002 | C6: Biyong Jean M. | D6: Chef Cuisine | E6: Cuisine & Restauration | F6: DOSS-2017-003 | G6: Armoire A, Etagere 1, Chemise bleue | H6: Serveur RH / Employes / BJMJM/ | I6: 22 | J6: Complet | K6: 45797
B7: DOS-003 | C7: Kamga Patrice | D7: Receptionniste | E7: Réception & Front Office | F7: DOSS-2025-008 | G7: Armoire B, Etagere 1, Chemise jaune | H7: Serveur RH / Employes / KPATR/ | I7: 10 | J7: Incomplet | K7: 45809
B8: DOS-004 | C8: Tamo Eric | D8: Technicien IT | E8: Informatique | F8: DOSS-2022-012 | G8: Armoire B, Etagere 3, Chemise verte | H8: Serveur RH / Employes / TAMOE/ | I8: 14 | J8: Complet | K8: 45787
B9: DOS-005 | C9: Fouda M. | D9: Cuisinier | E9: Cuisine & Restauration | F9: DOSS-2023-015 | G9: Armoire A, Etagere 3, Chemise bleue | H9: Serveur RH / Employes / FOUDM/ | I9: 16 | J9: A mettre a jour | K9: 45717
B10: =IF(C10="","DOS-"&TEXT(COUNTA($C$5:C10),"000"))
B11: =IF(C11="","DOS-"&TEXT(COUNTA($C$5:C11),"000"))
B12: =IF(C12="","DOS-"&TEXT(COUNTA($C$5:C12),"000"))
B13: =IF(C13="","DOS-"&TEXT(COUNTA($C$5:C13),"000"))
B14: =IF(C14="","DOS-"&TEXT(COUNTA($C$5:C14),"000"))
B15: =IF(C15="","DOS-"&TEXT(COUNTA($C$5:C15),"000"))
B16: =IF(C16="","DOS-"&TEXT(COUNTA($C$5:C16),"000"))
B17: =IF(C17="","DOS-"&TEXT(COUNTA($C$5:C17),"000"))
B18: =IF(C18="","DOS-"&TEXT(COUNTA($C$5:C18),"000"))
B19: =IF(C19="","DOS-"&TEXT(COUNTA($C$5:C19),"000"))
B20: =IF(C20="","DOS-"&TEXT(COUNTA($C$5:C20),"000"))
B21: =IF(C21="","DOS-"&TEXT(COUNTA($C$5:C21),"000"))
... B109: =IF(C109="","DOS-"&TEXT(COUNTA($C$5:C109),"000"))
B111: INDICATEURS (mis a jour automatiquement)
B112: Dossiers total | D112: Complets | F112: Incomplets
B113: =COUNTIF(B5:B104,"<>") | D113: =COUNTIF(J5:J104,"Complet") | F113: =COUNTIF(J5:J104,"Incomplet")+COUNTIF(J5:J104,"A mettre a jour")

Sheet 4-Archivage Physique
B2: ARCHIVAGE PHYSIQUE (#129)
B3: TABLEAU DYNAMIQUE — Saisissez dans la prochaine ligne jaune. Les calculs se mettent a jour automatiquement.
B4: N° | C4: Designation Boite | D4: Localisation | E4: Type Contenu | F4: Annee Archives | G4: Nb Dossiers | H4: Date Archivage | I4: Duree Conservation | J4: Date Destruction Prev. | K4: Statut
B5: APH-001 | C5: BOITE-ARCH-2020-A | D5: Sous-sol, Rangee 1, Etagere A | E5: Contrats travail 2020 | F5: 2020 | G5: 25 | H5: 44211 | I5: Durée du contrat + 5 ans | J5: 47848 | K5: Archive
B6: APH-002 | C6: BOITE-ARCH-2021-B | D6: Sous-sol, Rangee 1, Etagere B | E6: Fiches de paie 2021 | F6: 2021 | G6: 85 | H6: 44593 | I6: 5 ans | J6: 46419 | K6: Archive
B7: APH-003 | C7: BOITE-ARCH-2022-A | D7: Sous-sol, Rangee 2, Etagere A | E7: Contrats + Avenants 2022 | F7: 2022 | G7: 30 | H7: 44946 | I7: Durée du contrat + 5 ans | J7: 48579 | K7: Archive
B8: APH-004 | C8: BOITE-ARCH-2023-A | D8: Sous-sol, Rangee 2, Etagere B | E8: Bullets paie 2023 | F8: 2023 | G8: 90 | H8: 45306 | I8: 5 ans | J8: 47133 | K8: Archive
B9: APH-005 | C9: BOITE-ARCH-2024-A | D9: Sous-sol, Rangee 3, Etagere A | E9: Declarations CNPS 2024 | F9: 2024 | G9: 24 | H9: 45689 | I9: 10 ans | J9: 49341 | K9: Archive
B10: =IF(C10="","APH-"&TEXT(COUNTA($C$5:C10),"000"))
B11: =IF(C11="","APH-"&TEXT(COUNTA($C$5:C11),"000"))
B12: =IF(C12="","APH-"&TEXT(COUNTA($C$5:C12),"000"))
B13: =IF(C13="","APH-"&TEXT(COUNTA($C$5:C13),"000"))
B14: =IF(C14="","APH-"&TEXT(COUNTA($C$5:C14),"000"))
B15: =IF(C15="","APH-"&TEXT(COUNTA($C$5:C15),"000"))
B16: =IF(C16="","APH-"&TEXT(COUNTA($C$5:C16),"000"))
B17: =IF(C17="","APH-"&TEXT(COUNTA($C$5:C17),"000"))
B18: =IF(C18="","APH-"&TEXT(COUNTA($C$5:C18),"000"))
B19: =IF(C19="","APH-"&TEXT(COUNTA($C$5:C19),"000"))
B20: =IF(C20="","APH-"&TEXT(COUNTA($C$5:C20),"000"))
B21: =IF(C21="","APH-"&TEXT(COUNTA($C$5:C21),"000"))
... B109: =IF(C109="","APH-"&TEXT(COUNTA($C$5:C109),"000"))
B111: TOTAL | G111: =SUM(G5:G104)
B113: INDICATEURS (mis a jour automatiquement)
B114: Boites archivees | D114: Total dossiers | F114: A detruire < 1 an
B115: =COUNTIF(B5:B104,"<>") | D115: =SUM(G5:G104) | F115: =COUNTIF(J5:J104,"<"&TODAY()+365)

Sheet 5-Archivage Numerique
B2: ARCHIVAGE NUMÉRIQUE (#130)
B3: TABLEAU DYNAMIQUE — Saisissez dans la prochaine ligne jaune. Les calculs se mettent a jour automatiquement.
B4: N° | C4: Document | D4: Type Document | E4: Format | F4: Emplacement Serveur | G4: Taille (Ko) | H4: Date Numérisation | I4: Qualite Scan | J4: Indexation | K4: Statut
B5: ANU-001 | C5: Contrat Nkoulou Mbarga P. | D5: Contrat de travail | E5: PDF | F5: Serveur RH / Contrats / 2019 / | G5: 450 | H5: 45361 | I5: Haute | J5: Employe + Type + Date | K5: Archive
B6: ANU-002 | C6: Bulletins paie Jan-Dec 2024 | D6: Bulletin paie | E6: PDF | F6: Serveur RH / Paie / 2024 / | G6: 2800 | H6: 45672 | I6: Haute | J6: Mois + Employe + Montant | K6: Archive
B7: ANU-003 | C7: PV reunion CSE 2025 | D7: PV reunion | E7: PDF | F7: Serveur RH / CSE / 2025 / | G7: 320 | H7: 45698 | I7: Moyenne | J7: Date + Type reunion | K7: En cours
B8: ANU-004 | C8: Formation HACCP niveau 2 | D8: Plan de formation | E8: PDF | F8: Cloud / Formation / HACCP / | G8: 1500 | H8: 45752 | I8: Haute | J8: Formation + Participant + Date | K8: En cours
B9: ANU-005 | C9: Declarations CNPS 2024 | D9: Formulaire CNPS | E9: PDF | F9: Serveur RH / CNPS / 2024 / | G9: 1200 | H9: 45677 | I9: Haute | J9: Mois + Montant + Reference | K9: Archive
B10: =IF(C10="","ANU-"&TEXT(COUNTA($C$5:C10),"000"))
B11: =IF(C11="","ANU-"&TEXT(COUNTA($C$5:C11),"000"))
B12: =IF(C12="","ANU-"&TEXT(COUNTA($C$5:C12),"000"))
B13: =IF(C13="","ANU-"&TEXT(COUNTA($C$5:C13),"000"))
B14: =IF(C14="","ANU-"&TEXT(COUNTA($C$5:C14),"000"))
B15: =IF(C15="","ANU-"&TEXT(COUNTA($C$5:C15),"000"))
B16: =IF(C16="","ANU-"&TEXT(COUNTA($C$5:C16),"000"))
B17: =IF(C17="","ANU-"&TEXT(COUNTA($C$5:C17),"000"))
B18: =IF(C18="","ANU-"&TEXT(COUNTA($C$5:C18),"000"))
B19: =IF(C19="","ANU-"&TEXT(COUNTA($C$5:C19),"000"))
B20: =IF(C20="","ANU-"&TEXT(COUNTA($C$5:C20),"000"))
B21: =IF(C21="","ANU-"&TEXT(COUNTA($C$5:C21),"000"))
... B109: =IF(C109="","ANU-"&TEXT(COUNTA($C$5:C109),"000"))
B111: TOTAL | G111: =SUM(G5:G104)
B113: INDICATEURS (mis a jour automatiquement)
B114: Fiches numerisees | D114: Volume total (Mo) | F114: En cours
B115: =COUNTIF(B5:B104,"<>") | D115: =IFERROR(SUM(G5:G104)/1024,0) | F115: =COUNTIF(K5:K104,"En cours")

Sheet 6-Gest. Docs. Confidentiels
B2: GESTION DOCUMENTS CONFIDENTIELS (#131)
B3: TABLEAU DYNAMIQUE — Saisissez dans la prochaine ligne jaune. Les calculs se mettent a jour automatiquement.
B4: N° | C4: Designation | D4: Type Document | E4: Niveau Confidentialite | F4: Emplacement | G4: Personnes Autorisees | H4: Date Classement | I4: Motif Confidentialite | J4: Date Declassement | K4: Statut
B5: DCO-001 | C5: Salaires bruts employes | D5: Fiche de paie | E5: Tres confidentiel | F5: Coffre-fort RH + Serveur securise | G5: DRH, DAF, DG | H5: 45292 | I5: Donnees personnelles sensibles | K5: En cours
B6: DCO-002 | C6: Rapport medicaux employes | D6: Autre | E6: Tres confidentiel | F6: Coffre-fort medical | G6: Medecin travail, DRH | H6: 45292 | I6: Secret medical | K6: En cours
B7: DCO-003 | C7: Dossier disciplinaire Tchouanku | D7: Proces-verbal disciplinaire | E7: Confidentiel | F7: Armoire verrouillee RH | G7: DRH, DG | H7: 45799 | I7: Litige en cours | J7: 46164 | K7: En cours
B8: DCO-004 | C8: Audit salaires internes | D8: Politique RH | E8: Confidentiel | F8: Serveur RH / Audits / | G8: DRH, DG, Commissaire aux comptes | H8: 45717 | I8: Audit interne en cours | J8: 46082 | K8: En cours
B9: DCO-005 | C9: Négociations salariales syndicats | D9: Note de service | E9: Confidentiel | F9: Coffre-fort RH | G9: DRH, DG | H9: 45762 | I9: Negociations confidentielles | J9: 46022 | K9: En cours
B10: =IF(C10="","DCO-"&TEXT(COUNTA($C$5:C10),"000"))
B11: =IF(C11="","DCO-"&TEXT(COUNTA($C$5:C11),"000"))
B12: =IF(C12="","DCO-"&TEXT(COUNTA($C$5:C12),"000"))
B13: =IF(C13="","DCO-"&TEXT(COUNTA($C$5:C13),"000"))
B14: =IF(C14="","DCO-"&TEXT(COUNTA($C$5:C14),"000"))
B15: =IF(C15="","DCO-"&TEXT(COUNTA($C$5:C15),"000"))
B16: =IF(C16="","DCO-"&TEXT(COUNTA($C$5:C16),"000"))
B17: =IF(C17="","DCO-"&TEXT(COUNTA($C$5:C17),"000"))
B18: =IF(C18="","DCO-"&TEXT(COUNTA($C$5:C18),"000"))
B19: =IF(C19="","DCO-"&TEXT(COUNTA($C$5:C19),"000"))
B20: =IF(C20="","DCO-"&TEXT(COUNTA($C$5:C20),"000"))
B21: =IF(C21="","DCO-"&TEXT(COUNTA($C$5:C21),"000"))
... B109: =IF(C109="","DCO-"&TEXT(COUNTA($C$5:C109),"000"))
B111: INDICATEURS (mis a jour automatiquement)
B112: Docs confidentiels | D112: Tres confidentiels | F112: En cours
B113: =COUNTIF(B5:B104,"<>") | D113: =COUNTIF(E5:E104,"Tres confidentiel") | F113: =COUNTIF(K5:K104,"En cours")

Sheet 7-Suivi Retention Docs
B2: SUIVI RÉTENTION DOCUMENTS (#132)
B3: TABLEAU DYNAMIQUE — Saisissez dans la prochaine ligne jaune. Les calculs se mettent a jour automatiquement.
B4: N° | C4: Type Document | D4: Categorie | E4: Duree Conservation | F4: Date Debut | G4: Date Fin Conservation | H4: Jours Restants | I4: Nb Exemplaires | J4: Action Prevue | K4: Statut
B5: SRE-001 | C5: Bulletin de paie | D5: Paie | E5: 5 ans | F5: 43831 | G5: 46022 | I5: 120 | J5: Destruction programmee | K5: En cours
B6: SRE-002 | C6: Contrat CDD Kamga | D6: Contrat travail | E6: Durée du contrat + 5 ans | F6: 45658 | G6: 47664 | I6: 2 | J6: Conservation courante | K6: En cours
B7: SRE-003 | C7: Declarations CNPS 2020 | D7: Formulaire CNPS | E7: 10 ans | F7: 43831 | G7: 47848 | I7: 24 | J7: Conservation courante | K7: En cours
B8: SRE-004 | C8: PV disciplinaire 2020 | D8: Proces-verbal disciplinaire | E8: Durée du contrat + 5 ans | F8: 43905 | G8: 45731 | I8: 3 | J8: Destruction programmee | K8: En cours
B9: SRE-005 | C9: Bilan social 2020 | D9: Bilan social | E9: 3 ans | F9: 44196 | G9: 45291 | I9: 5 | J9: Destruction programmee | K9: A detruire
B10: =IF(C10="","SRE-"&TEXT(COUNTA($C$5:C10),"000")) | H10: =IF(OR(G10="",""),G10-TODAY())
B11: =IF(C11="","SRE-"&TEXT(COUNTA($C$5:C11),"000")) | H11: =IF(OR(G11="",""),G11-TODAY())
B12: =IF(C12="","SRE-"&TEXT(COUNTA($C$5:C12),"000")) | H12: =IF(OR(G12="",""),G12-TODAY())
B13: =IF(C13="","SRE-"&TEXT(COUNTA($C$5:C13),"000")) | H13: =IF(OR(G13="",""),G13-TODAY())
B14: =IF(C14="","SRE-"&TEXT(COUNTA($C$5:C14),"000")) | H14: =IF(OR(G14="",""),G14-TODAY())
B15: =IF(C15="","SRE-"&TEXT(COUNTA($C$5:C15),"000")) | H15: =IF(OR(G15="",""),G15-TODAY())
B16: =IF(C16="","SRE-"&TEXT(COUNTA($C$5:C16),"000")) | H16: =IF(OR(G16="",""),G16-TODAY())
B17: =IF(C17="","SRE-"&TEXT(COUNTA($C$5:C17),"000")) | H17: =IF(OR(G17="",""),G17-TODAY())
B18: =IF(C18="","SRE-"&TEXT(COUNTA($C$5:C18),"000")) | H18: =IF(OR(G18="",""),G18-TODAY())
B19: =IF(C19="","SRE-"&TEXT(COUNTA($C$5:C19),"000")) | H19: =IF(OR(G19="",""),G19-TODAY())
B20: =IF(C20="","SRE-"&TEXT(COUNTA($C$5:C20),"000")) | H20: =IF(OR(G20="",""),G20-TODAY())
B21: =IF(C21="","SRE-"&TEXT(COUNTA($C$5:C21),"000")) | H21: =IF(OR(G21="",""),G21-TODAY())
... B109: =IF(C109="","SRE-"&TEXT(COUNTA($C$5:C109),"000")) | H109: =IF(OR(G109="",""),G109-TODAY())
B111: INDICATEURS (mis a jour automatiquement)
B112: Documents suivis | D112: A detruire | F112: Expiration < 6 mois
B113: =COUNTIF(B5:B104,"<>") | D113: =COUNTIF(K5:K104,"A detruire") | F113: =COUNTIF(H5:H104,"<"&180)-COUNTIF(H5:H104,"<"&0)

Sheet 8-Plan Classement RH
B2: PLAN DE CLASSEMENT RH (#133)
B3: TABLEAU DYNAMIQUE — Saisissez dans la prochaine ligne jaune. Les calculs se mettent a jour automatiquement.
B4: N° | C4: Categorie | D4: Sous-Categorie | E4: Type Classement | F4: Code | G4: Emplacement Physique | H4: Emplacement Numerique | I4: Responsable | J4: Derniere MAJ
B5: CL-001 | C5: Employes | D5: Dossiers individuels | E5: Alphabetique employe | F5: EMP-001 | G5: Armoire A, Etagere 1-3 | H5: Serveur RH / Employes / | I5: Assistante RH | J5: 45823
B6: CL-002 | C6: Paie | D6: Bulletins de paie | E6: Chronologique | F6: PAIE-001 | G6: Armoire B, Etagere 1 | H6: Serveur RH / Paie / | I6: Comptable senior | J6: 45809
B7: CL-003 | C7: Contrats | D7: Contrats de travail | E7: Numerique dossier | F7: CTR-001 | G7: Coffre-fort RH | H7: Serveur RH / Contrats / | I7: DRH | J7: 45797
B8: CL-004 | C8: Formation | D8: Plans & Attestations | E8: Par annee | F8: FORM-001 | G8: Armoire C, Etagere 1 | H8: Cloud / Formation / | I8: Assistante RH | J8: 45787
B9: CL-005 | C9: Reglementation | D9: Textes legaux & PV | E9: Par type document | F9: REG-001 | G9: Armoire D, Etagere 1-2 | H9: Serveur RH / Reglementation / | I9: DRH | J9: 45748
B10: =IF(C10="","CL-"&TEXT(COUNTA($C$5:C10),"000"))
B11: =IF(C11="","CL-"&TEXT(COUNTA($C$5:C11),"000"))
B12: =IF(C12="","CL-"&TEXT(COUNTA($C$5:C12),"000"))
B13: =IF(C13="","CL-"&TEXT(COUNTA($C$5:C13),"000"))
B14: =IF(C14="","CL-"&TEXT(COUNTA($C$5:C14),"000"))
B15: =IF(C15="","CL-"&TEXT(COUNTA($C$5:C15),"000"))
B16: =IF(C16="","CL-"&TEXT(COUNTA($C$5:C16),"000"))
B17: =IF(C17="","CL-"&TEXT(COUNTA($C$5:C17),"000"))
B18: =IF(C18="","CL-"&TEXT(COUNTA($C$5:C18),"000"))
B19: =IF(C19="","CL-"&TEXT(COUNTA($C$5:C19),"000"))
B20: =IF(C20="","CL-"&TEXT(COUNTA($C$5:C20),"000"))
B21: =IF(C21="","CL-"&TEXT(COUNTA($C$5:C21),"000"))
... B109: =IF(C109="","CL-"&TEXT(COUNTA($C$5:C109),"000"))
B111: INDICATEURS (mis a jour automatiquement)
B112: Categories
B113: =COUNTIF(B5:B104,"<>")

Sheet 9-Gestion Versions Docs
B2: GESTION VERSIONS DOCUMENTS (#134)
B3: TABLEAU DYNAMIQUE — Saisissez dans la prochaine ligne jaune. Les calculs se mettent a jour automatiquement.
B4: N° | C4: Document | D4: Version Actuelle | E4: Date Version | F4: Auteur Version | G4: Modifications | H4: Version Precedente | I4: Emplacement Archive | J4: Statut
B5: VER-001 | C5: Reglement interieur | D5: V3.2 | E5: 45458 | F5: DG + DRH | G5: Ajout volet numerique + teletravail | H5: V3.1 | I5: Archive / Reglement interieur / V3.1 | J5: Valide
B6: VER-002 | C6: Grille salariale | D6: V2.1 | E6: 45667 | F6: DRH + DAF | G6: Integre nouveau SMIG 2025 | H6: V2.0 | I6: Archive / Grilles / V2.0 | J6: Valide
B7: VER-003 | C7: Procedure recrutement | D7: V2.0 | E7: 45536 | F7: DRH | G7: Ajout test technique obligatoire | H7: V1.0 | I7: Archive / Procedures / V1.0 | J7: Valide
B8: VER-004 | C8: Charte ethique | D8: V1.5 | E8: 45352 | F8: DG | G8: Ajout volet reseaux sociaux | H8: V1.4 | I8: Archive / Chartes / V1.4 | J8: Valide
B9: VER-005 | C9: Politique diversite | D9: V1.0 | E9: 45689 | F9: DG + DRH | G9: Creation initiale | J9: En cours
B10: =IF(C10="","VER-"&TEXT(COUNTA($C$5:C10),"000"))
B11: =IF(C11="","VER-"&TEXT(COUNTA($C$5:C11),"000"))
B12: =IF(C12="","VER-"&TEXT(COUNTA($C$5:C12),"000"))
B13: =IF(C13="","VER-"&TEXT(COUNTA($C$5:C13),"000"))
B14: =IF(C14="","VER-"&TEXT(COUNTA($C$5:C14),"000"))
B15: =IF(C15="","VER-"&TEXT(COUNTA($C$5:C15),"000"))
B16: =IF(C16="","VER-"&TEXT(COUNTA($C$5:C16),"000"))
B17: =IF(C17="","VER-"&TEXT(COUNTA($C$5:C17),"000"))
B18: =IF(C18="","VER-"&TEXT(COUNTA($C$5:C18),"000"))
B19: =IF(C19="","VER-"&TEXT(COUNTA($C$5:C19),"000"))
B20: =IF(C20="","VER-"&TEXT(COUNTA($C$5:C20),"000"))
B21: =IF(C21="","VER-"&TEXT(COUNTA($C$5:C21),"000"))
... B109: =IF(C109="","VER-"&TEXT(COUNTA($C$5:C109),"000"))
B111: INDICATEURS (mis a jour automatiquement)
B112: Documents versionnes | D112: Versions valides | F112: En revision
B113: =COUNTIF(B5:B104,"<>") | D113: =COUNTIF(J5:J104,"Valide") | F113: =COUNTIF(J5:J104,"En revision")

Sheet 10-Registre Sortie Docs
B2: REGISTRE SORTIE DOCUMENTS (#135)
B3: TABLEAU DYNAMIQUE — Saisissez dans la prochaine ligne jaune. Les calculs se mettent a jour automatiquement.
B4: N° | C4: Document | D4: Type Document | E4: Date Sortie | F4: Motif Sortie | G4: Destinataire | H4: Nbr Exemplaires | I4: Date Retour Prev. | J4: Date Retour Reel | K4: Statut
B5: SOR-001 | C5: Contrat Tchouanku G. | D5: Contrat de travail | E5: 45809 | F5: Tribunal | G5: Tribunal de travail Douala | H5: 1 | K5: En cours
B6: SOR-002 | C6: Bulletins paie Q1 2025 | D6: Bulletin paie | E6: 45762 | F6: Expertise comptable | G6: Cabinet FIDECA | H6: 1 | I6: 45792 | J6: 45787 | K6: Restitue
B7: SOR-003 | C7: Bilan social 2024 | D7: Bilan social | E7: 45717 | F7: Envoi organisme externe | G7: Inspection du travail | H7: 2 | K7: En cours
B8: SOR-004 | C8: Attestation travail Nkoulou | D8: Attestation travail | E8: 45797 | F8: Photocopie employe | G8: Nkoulou Mbarga P. | H8: 1 | I8: 45797 | J8: 45797 | K8: Restitue
B9: SOR-005 | C9: PV reunion CSE fevrier | D9: PV reunion | E9: 45726 | F9: Consultation interne | G9: Syndicat CSE | H9: 1 | I9: 45757 | J9: 45755 | K9: Restitue
B10: =IF(C10="","SOR-"&TEXT(COUNTA($C$5:C10),"000"))
B11: =IF(C11="","SOR-"&TEXT(COUNTA($C$5:C11),"000"))
B12: =IF(C12="","SOR-"&TEXT(COUNTA($C$5:C12),"000"))
B13: =IF(C13="","SOR-"&TEXT(COUNTA($C$5:C13),"000"))
B14: =IF(C14="","SOR-"&TEXT(COUNTA($C$5:C14),"000"))
B15: =IF(C15="","SOR-"&TEXT(COUNTA($C$5:C15),"000"))
B16: =IF(C16="","SOR-"&TEXT(COUNTA($C$5:C16),"000"))
B17: =IF(C17="","SOR-"&TEXT(COUNTA($C$5:C17),"000"))
B18: =IF(C18="","SOR-"&TEXT(COUNTA($C$5:C18),"000"))
B19: =IF(C19="","SOR-"&TEXT(COUNTA($C$5:C19),"000"))
B20: =IF(C20="","SOR-"&TEXT(COUNTA($C$5:C20),"000"))
B21: =IF(C21="","SOR-"&TEXT(COUNTA($C$5:C21),"000"))
... B109: =IF(C109="","SOR-"&TEXT(COUNTA($C$5:C109),"000"))
B111: INDICATEURS (mis a jour automatiquement)
B112: Sorties total | D112: Restitues | F112: En cours
B113: =COUNTIF(B5:B104,"<>") | D113: =COUNTIF(K5:K104,"Restitue") | F113: =COUNTIF(K5:K104,"En cours")

Sheet 11-Politique Archivage
B2: POLITIQUE ARCHIVAGE & CONSERVATION (#136)
B3: TABLEAU DYNAMIQUE — Saisissez dans la prochaine ligne jaune. Les calculs se mettent a jour automatiquement.
B4: N° | C4: Politique / Regle | D4: Type Document | E4: Duree Conservation | F4: Support Obligatoire | G4: Conditions Destruction | H4: Responsable | I4: Date Approbation | J4: Prochaine Revision | K4: Statut
B5: PAR-001 | C5: Conservation contrats travail | D5: Contrat de travail | E5: Contrat + 5 ans apres fin | F5: Hybride (papier + numerique) | G5: PV destruction + temoin | H5: DRH | I5: 45301 | J5: 46032 | K5: En vigueur
B6: PAR-002 | C6: Conservation bulletins paie | D6: Bulletin paie | E6: 5 ans | F6: Numerique - Serveur RH | G6: Suppression logique + PV | H6: DAF | I6: 45301 | J6: 46032 | K6: En vigueur
B7: PAR-003 | C7: Archivage documents medicaux | D7: Autre | E7: Indefinie | F7: Papier - Classeur | G7: Jamais (conservation permanente) | H7: Medecin travail | I7: 45301 | J7: 46032 | K7: En vigueur
B8: PAR-004 | C8: Conservation PV disciplinaires | D8: Proces-verbal disciplinaire | E8: Contrat + 5 ans | F8: Papier - Boite archive | G8: PV destruction + autorisation DRH | H8: DRH | I8: 45301 | J8: 46032 | K8: En vigueur
B9: PAR-005 | C9: Archivage bilans sociaux | D9: Bilan social | E9: 10 ans | F9: Numerique - Serveur RH | G9: Suppression logique apres 10 ans | H9: DRH + DAF | I9: 45301 | J9: 46032 | K9: En vigueur
B10: =IF(C10="","PAR-"&TEXT(COUNTA($C$5:C10),"000"))
B11: =IF(C11="","PAR-"&TEXT(COUNTA($C$5:C11),"000"))
B12: =IF(C12="","PAR-"&TEXT(COUNTA($C$5:C12),"000"))
B13: =IF(C13="","PAR-"&TEXT(COUNTA($C$5:C13),"000"))
B14: =IF(C14="","PAR-"&TEXT(COUNTA($C$5:C14),"000"))
B15: =IF(C15="","PAR-"&TEXT(COUNTA($C$5:C15),"000"))
B16: =IF(C16="","PAR-"&TEXT(COUNTA($C$5:C16),"000"))
B17: =IF(C17="","PAR-"&TEXT(COUNTA($C$5:C17),"000"))
B18: =IF(C18="","PAR-"&TEXT(COUNTA($C$5:C18),"000"))
B19: =IF(C19="","PAR-"&TEXT(COUNTA($C$5:C19),"000"))
B20: =IF(C20="","PAR-"&TEXT(COUNTA($C$5:C20),"000"))
B21: =IF(C21="","PAR-"&TEXT(COUNTA($C$5:C21),"000"))
... B109: =IF(C109="","PAR-"&TEXT(COUNTA($C$5:C109),"000"))
B111: INDICATEURS (mis a jour automatiquement)
B112: Regles definies | D112: En vigueur
B113: =COUNTIF(B5:B104,"<>") | D113: =COUNTIF(K5:K104,"En vigueur")

Sheet 12-Suivi Dossiers Incomplets
B2: SUIVI DOSSIERS INCOMPLETS
B3: TABLEAU DYNAMIQUE — Saisissez dans la prochaine ligne jaune. Les calculs se mettent a jour automatiquement.
B4: N° | C4: Employe | D4: Poste | E4: Departement | F4: Pieces Manquantes | G4: Nb Pieces Manquantes | H4: Date Detection | I4: Relance Effectuee | J4: Echeance Regularisation | K4: Statut
B5: SDI-001 | C5: Kamga Patrice | D5: Receptionniste | E5: Réception & Front Office | F5: Extrait casier judiciaire, Certificat travail precedent | G5: 2 | H5: 45792 | I5: Oui | J5: 45853 | K5: En cours
B6: SDI-002 | C6: Fouda M. | D6: Cuisinier | E6: Cuisine & Restauration | F6: Certificat HACCP niveau 2, Photo d'identite | G6: 2 | H6: 45767 | I6: Oui | J6: 45828 | K6: En retard
B7: SDI-003 | C7: Nganou D. | D7: Receptionniste | E7: Réception & Front Office | F7: Copie CNI, Formulaire CNPS | G7: 2 | H7: 45778 | I7: Oui | J7: 45839 | K7: En cours
B8: SDI-004 | C8: Bekolo A. | D8: Agent Entretien | E8: Maintenance | F8: Attestation de travail, Certificat scolaire | G8: 2 | H8: 45809 | I8: Non | J8: 45870 | K8: En cours
B9: =IF(C9="","SDI-"&TEXT(COUNTA($C$5:C9),"000"))
B10: =IF(C10="","SDI-"&TEXT(COUNTA($C$5:C10),"000"))
B11: =IF(C11="","SDI-"&TEXT(COUNTA($C$5:C11),"000"))
B12: =IF(C12="","SDI-"&TEXT(COUNTA($C$5:C12),"000"))
B13: =IF(C13="","SDI-"&TEXT(COUNTA($C$5:C13),"000"))
B14: =IF(C14="","SDI-"&TEXT(COUNTA($C$5:C14),"000"))
B15: =IF(C15="","SDI-"&TEXT(COUNTA($C$5:C15),"000"))
B16: =IF(C16="","SDI-"&TEXT(COUNTA($C$5:C16),"000"))
B17: =IF(C17="","SDI-"&TEXT(COUNTA($C$5:C17),"000"))
B18: =IF(C18="","SDI-"&TEXT(COUNTA($C$5:C18),"000"))
B19: =IF(C19="","SDI-"&TEXT(COUNTA($C$5:C19),"000"))
B20: =IF(C20="","SDI-"&TEXT(COUNTA($C$5:C20),"000"))
... B108: =IF(C108="","SDI-"&TEXT(COUNTA($C$5:C108),"000"))
B110: INDICATEURS (mis a jour automatiquement)
B111: Dossiers incomplets | D111: Total pieces manq. | F111: En retard
B112: =COUNTIF(B5:B104,"<>") | D112: =SUM(G5:G104) | F112: =COUNTIF(K5:K104,"En retard")

Sheet 13-Indicateurs Archivage
B2: INDICATEURS D'ARCHIVAGE — Mensuel
B3: TABLEAU DYNAMIQUE — Saisissez dans la prochaine ligne jaune. Les calculs se mettent a jour automatiquement.
B4: N° | C4: Mois | D4: Annee | E4: Nb Docs. Numerises | F4: Nb Docs. Archives Phys. | G4: Nb Sorties Documents | H4: Nb Dossiers Incomplets | I4: Taux Completude (%)
B5: IA-001 | C5: Janvier | D5: 2025 | E5: 45 | F5: 20 | G5: 5 | H5: 3
B6: IA-002 | C6: Fevrier | D6: 2025 | E6: 52 | F6: 15 | G6: 4 | H6: 2
B7: IA-003 | C7: Mars | D7: 2025 | E7: 38 | F7: 25 | G7: 8 | H7: 4
B8: IA-004 | C8: Avril | D8: 2025 | E8: 60 | F8: 10 | G8: 3 | H8: 3
B9: IA-005 | C9: Mai | D9: 2025 | E9: 55 | F9: 18 | G9: 6 | H9: 4
B10: =IF(C10="","IA-"&TEXT(COUNTA($C$5:C10),"000")) | I10: =IF(89=0,"",1-H10/89)
B11: =IF(C11="","IA-"&TEXT(COUNTA($C$5:C11),"000")) | I11: =IF(89=0,"",1-H11/89)
B12: =IF(C12="","IA-"&TEXT(COUNTA($C$5:C12),"000")) | I12: =IF(89=0,"",1-H12/89)
B13: =IF(C13="","IA-"&TEXT(COUNTA($C$5:C13),"000")) | I13: =IF(89=0,"",1-H13/89)
B14: =IF(C14="","IA-"&TEXT(COUNTA($C$5:C14),"000")) | I14: =IF(89=0,"",1-H14/89)
B15: =IF(C15="","IA-"&TEXT(COUNTA($C$5:C15),"000")) | I15: =IF(89=0,"",1-H15/89)
B16: =IF(C16="","IA-"&TEXT(COUNTA($C$5:C16),"000")) | I16: =IF(89=0,"",1-H16/89)
B17: =IF(C17="","IA-"&TEXT(COUNTA($C$5:C17),"000")) | I17: =IF(89=0,"",1-H17/89)
B18: =IF(C18="","IA-"&TEXT(COUNTA($C$5:C18),"000")) | I18: =IF(89=0,"",1-H18/89)
B19: =IF(C19="","IA-"&TEXT(COUNTA($C$5:C19),"000")) | I19: =IF(89=0,"",1-H19/89)
B20: =IF(C20="","IA-"&TEXT(COUNTA($C$5:C20),"000")) | I20: =IF(89=0,"",1-H20/89)
B21: =IF(C21="","IA-"&TEXT(COUNTA($C$5:C21),"000")) | I21: =IF(89=0,"",1-H21/89)
... B109: =IF(C109="","IA-"&TEXT(COUNTA($C$5:C109),"000")) | I109: =IF(89=0,"",1-H109/89)
B111: TOTAL | E111: =SUM(E5:E104) | F111: =SUM(F5:F104) | G111: =SUM(G5:G104) | H111: =SUM(H5:H104)
B113: INDICATEURS (mis a jour automatiquement)
B114: Total numerises | D114: Total archives phys. | F114: Completude moy.
B115: =SUM(E5:E104) | D115: =SUM(F5:F104) | F115: =IFERROR(AVERAGE(I5:I104),0)

Sheet 14-Hist. Destruction Docs
B2: HISTORIQUE DESTRUCTION DOCUMENTS
B3: TABLEAU DYNAMIQUE — Saisissez dans la prochaine ligne jaune. Les calculs se mettent a jour automatiquement.
B4: N° | C4: Type Document | D4: Annee Documents | E4: Quantite Detruite | F4: Date Destruction | G4: Mode Destruction | H4: Temoin Destruction | I4: Autorise Par | J4: PV Destruction | K4: Statut
B5: HDD-001 | C5: Bulletin de paie | D5: 2019 | E5: 180 | F5: 45677 | G5: Broyage confid. | H5: DRH + DAF | I5: DG | J5: PV-DEST-2025-001 | K5: Terminee
B6: HDD-002 | C6: Declarations CNPS | D6: 2014 | E6: 24 | F6: 45703 | G6: Broyage confid. | H6: DAF + DRH | I6: DG | J6: PV-DEST-2025-002 | K6: Terminee
B7: HDD-003 | C7: Notes service obsoletes | D7: 2020 | E7: 35 | F7: 45726 | G7: Pulverisation | H7: DRH | I7: DRH | J7: PV-DEST-2025-003 | K7: Terminee
B8: HDD-004 | C8: PV reunions obsoletes | D8: 2019 | E8: 20 | F8: 45752 | G8: Pulverisation | H8: Assistante RH | I8: DRH | J8: PV-DEST-2025-004 | K8: Terminee
B9: =IF(C9="","HDD-"&TEXT(COUNTA($C$5:C9),"000"))
B10: =IF(C10="","HDD-"&TEXT(COUNTA($C$5:C10),"000"))
B11: =IF(C11="","HDD-"&TEXT(COUNTA($C$5:C11),"000"))
B12: =IF(C12="","HDD-"&TEXT(COUNTA($C$5:C12),"000"))
B13: =IF(C13="","HDD-"&TEXT(COUNTA($C$5:C13),"000"))
B14: =IF(C14="","HDD-"&TEXT(COUNTA($C$5:C14),"000"))
B15: =IF(C15="","HDD-"&TEXT(COUNTA($C$5:C15),"000"))
B16: =IF(C16="","HDD-"&TEXT(COUNTA($C$5:C16),"000"))
B17: =IF(C17="","HDD-"&TEXT(COUNTA($C$5:C17),"000"))
B18: =IF(C18="","HDD-"&TEXT(COUNTA($C$5:C18),"000"))
B19: =IF(C19="","HDD-"&TEXT(COUNTA($C$5:C19),"000"))
B20: =IF(C20="","HDD-"&TEXT(COUNTA($C$5:C20),"000"))
... B108: =IF(C108="","HDD-"&TEXT(COUNTA($C$5:C108),"000"))
B110: TOTAL | E110: =SUM(E5:E104)
B112: INDICATEURS (mis a jour automatiquement)
B113: Destructions total | D113: Total documents detruits | F113: PV emis
B114: =COUNTIF(B5:B104,"<>") | D114: =SUM(E5:E104) | F114: =COUNTIF(J5:J104,"<>")

Sheet 15-Suivi Docs. Confidentiels
B2: SUIVI DOCUMENTS CONFIDENTIELS
B3: TABLEAU DYNAMIQUE — Saisissez dans la prochaine ligne jaune. Les calculs se mettent a jour automatiquement.
B4: N° | C4: Designation | D4: Niveau Confidentialite | E4: Nb Consultations | F4: Derniere Consultation | G4: Consultant | H4: Jours depuis Derniere Consult. | I4: Prochaine Revue | J4: Statut
B5: SDC-001 | C5: Grille salariale complete | D5: Tres confidentiel | E5: 5 | F5: 45818 | G5: DRH | I5: 45910 | J5: En cours
B6: SDC-002 | C6: Dossier litige Tchouanku | D6: Confidentiel | E6: 8 | F6: 45820 | G6: DG + Avocat | I6: 45850 | J6: En cours
B7: SDC-003 | C7: Rapport audit salaires | D7: Confidentiel | E7: 3 | F7: 45797 | G7: DRH | I7: 45889 | J7: En cours
B8: SDC-004 | C8: Negociations syndicales | D8: Confidentiel | E8: 4 | F8: 45813 | G8: DRH + DG | I8: 45905 | J8: En cours
B9: =IF(C9="","SDC-"&TEXT(COUNTA($C$5:C9),"000")) | H9: =IF(G9="","",TODAY()-G9)
B10: =IF(C10="","SDC-"&TEXT(COUNTA($C$5:C10),"000")) | H10: =IF(G10="","",TODAY()-G10)
B11: =IF(C11="","SDC-"&TEXT(COUNTA($C$5:C11),"000")) | H11: =IF(G11="","",TODAY()-G11)
B12: =IF(C12="","SDC-"&TEXT(COUNTA($C$5:C12),"000")) | H12: =IF(G12="","",TODAY()-G12)
B13: =IF(C13="","SDC-"&TEXT(COUNTA($C$5:C13),"000")) | H13: =IF(G13="","",TODAY()-G13)
B14: =IF(C14="","SDC-"&TEXT(COUNTA($C$5:C14),"000")) | H14: =IF(G14="","",TODAY()-G14)
B15: =IF(C15="","SDC-"&TEXT(COUNTA($C$5:C15),"000")) | H15: =IF(G15="","",TODAY()-G15)
B16: =IF(C16="","SDC-"&TEXT(COUNTA($C$5:C16),"000")) | H16: =IF(G16="","",TODAY()-G16)
B17: =IF(C17="","SDC-"&TEXT(COUNTA($C$5:C17),"000")) | H17: =IF(G17="","",TODAY()-G17)
B18: =IF(C18="","SDC-"&TEXT(COUNTA($C$5:C18),"000")) | H18: =IF(G18="","",TODAY()-G18)
B19: =IF(C19="","SDC-"&TEXT(COUNTA($C$5:C19),"000")) | H19: =IF(G19="","",TODAY()-G19)
B20: =IF(C20="","SDC-"&TEXT(COUNTA($C$5:C20),"000")) | H20: =IF(G20="","",TODAY()-G20)
... B108: =IF(C108="","SDC-"&TEXT(COUNTA($C$5:C108),"000")) | H108: =IF(G108="","",TODAY()-G108)
B110: INDICATEURS (mis a jour automatiquement)
B111: Docs suivis | D111: Tres confidentiels | F111: Total consultations
B112: =COUNTIF(B5:B104,"<>") | D112: =COUNTIF(D5:D104,"Tres confidentiel") | F112: =SUM(E5:E104)

Sheet 16-Calendrier Archivage
B2: CALENDRIER ARCHIVAGE — Actions Planifiees
B3: TABLEAU DYNAMIQUE — Saisissez dans la prochaine ligne jaune. Les calculs se mettent a jour automatiquement.
B4: N° | C4: Action Archivage | D4: Type Document | E4: Priorite | F4: Echeance | G4: Jours Restants | H4: Responsable | I4: Volume Estime (pages) | J4: Statut
B5: CAR-001 | C5: Numerisation contrats 2020 | D5: Contrat de travail | E5: Haute | F5: 45869 | H5: Assistante RH | I5: 200 | J5: En cours
B6: CAR-002 | C6: Destruction bulletins 2019 | D6: Bulletin paie | E6: Moyenne | F6: 45838 | H6: Assistante RH | I6: 500 | J6: Terminee
B7: CAR-003 | C7: Archivage PV reunions 2024 | D7: PV reunion | E7: Basse | F7: 45930 | H7: Assistante RH | I7: 120 | J7: En cours
B8: CAR-004 | C8: Numerisation declarations CNPS | D8: Formulaire CNPS | E8: Haute | F8: 45900 | H8: Comptable senior | I8: 300 | J8: En cours
B9: CAR-005 | C9: Classement dossiers nouveaux | D9: Contrat de travail | E9: Haute | F9: 45853 | H9: Assistante RH | I9: 80 | J9: En cours
B10: =IF(C10="","CAR-"&TEXT(COUNTA($C$5:C10),"000")) | G10: =IF(F10="","",F10-TODAY())
B11: =IF(C11="","CAR-"&TEXT(COUNTA($C$5:C11),"000")) | G11: =IF(F11="","",F11-TODAY())
B12: =IF(C12="","CAR-"&TEXT(COUNTA($C$5:C12),"000")) | G12: =IF(F12="","",F12-TODAY())
B13: =IF(C13="","CAR-"&TEXT(COUNTA($C$5:C13),"000")) | G13: =IF(F13="","",F13-TODAY())
B14: =IF(C14="","CAR-"&TEXT(COUNTA($C$5:C14),"000")) | G14: =IF(F14="","",F14-TODAY())
B15: =IF(C15="","CAR-"&TEXT(COUNTA($C$5:C15),"000")) | G15: =IF(F15="","",F15-TODAY())
B16: =IF(C16="","CAR-"&TEXT(COUNTA($C$5:C16),"000")) | G16: =IF(F16="","",F16-TODAY())
B17: =IF(C17="","CAR-"&TEXT(COUNTA($C$5:C17),"000")) | G17: =IF(F17="","",F17-TODAY())
B18: =IF(C18="","CAR-"&TEXT(COUNTA($C$5:C18),"000")) | G18: =IF(F18="","",F18-TODAY())
B19: =IF(C19="","CAR-"&TEXT(COUNTA($C$5:C19),"000")) | G19: =IF(F19="","",F19-TODAY())
B20: =IF(C20="","CAR-"&TEXT(COUNTA($C$5:C20),"000")) | G20: =IF(F20="","",F20-TODAY())
B21: =IF(C21="","CAR-"&TEXT(COUNTA($C$5:C21),"000")) | G21: =IF(F21="","",F21-TODAY())
... B109: =IF(C109="","CAR-"&TEXT(COUNTA($C$5:C109),"000")) | G109: =IF(F109="","",F109-TODAY())
B111: INDICATEURS (mis a jour automatiquement)
B112: Actions planifiees | D112: En cours | F112: A echeance < 30j
B113: =COUNTIF(B5:B104,"<>") | D113: =COUNTIF(J5:J104,"En cours") | F113: =COUNTIF(G5:G104,"<"&30)-COUNTIF(G5:G104,"<"&0)

Sheet 17-Matrice Permissions
B2: MATRICE PERMISSIONS D'ACCÈS DOCUMENTS
B3: TABLEAU DYNAMIQUE — Saisissez dans la prochaine ligne jaune. Les calculs se mettent a jour automatiquement.
B4: N° | C4: Categorie Document | D4: DRH | E4: DG | F4: DAF | G4: Assistante RH | H4: Chef de Service | I4: Employe Concerne | J4: Observations
B5: PER-001 | C5: Contrats de travail | D5: Lecture / Ecriture | E5: Lecture / Ecriture | F5: Lecture seule | G5: Lecture / Ecriture | H5: Lecture seule | I5: Lecture seule | J5: Modification soumise a validation DG
B6: PER-002 | C6: Fiches de paie | D6: Lecture / Ecriture | E6: Lecture seule | F6: Lecture / Ecriture | G6: Lecture seule | H6: Aucun acces | I6: Lecture seule | J6: Acces individuel uniquement a sa fiche
B7: PER-003 | C7: Dossiers disciplinaires | D7: Lecture / Ecriture | E7: Lecture seule | F7: Aucun acces | G7: Aucun acces | H7: Aucun acces | I7: Lecture seule | J7: Sensible, acces restreint DG + DRH
B8: PER-004 | C8: Bilan social | D8: Lecture / Ecriture | E8: Lecture seule | F8: Lecture seule | G8: Lecture seule | H8: Aucun acces | I8: Aucun acces | J8: Diffusion restreinte direction
B9: PER-005 | C9: Reglement interieur | D9: Lecture / Ecriture | E9: Lecture seule | F9: Lecture seule | G9: Lecture seule | H9: Lecture seule | I9: Lecture seule | J9: Document public, acces lecture tous
B10: =IF(C10="","PER-"&TEXT(COUNTA($C$5:C10),"000"))
B11: =IF(C11="","PER-"&TEXT(COUNTA($C$5:C11),"000"))
B12: =IF(C12="","PER-"&TEXT(COUNTA($C$5:C12),"000"))
B13: =IF(C13="","PER-"&TEXT(COUNTA($C$5:C13),"000"))
B14: =IF(C14="","PER-"&TEXT(COUNTA($C$5:C14),"000"))
B15: =IF(C15="","PER-"&TEXT(COUNTA($C$5:C15),"000"))
B16: =IF(C16="","PER-"&TEXT(COUNTA($C$5:C16),"000"))
B17: =IF(C17="","PER-"&TEXT(COUNTA($C$5:C17),"000"))
B18: =IF(C18="","PER-"&TEXT(COUNTA($C$5:C18),"000"))
B19: =IF(C19="","PER-"&TEXT(COUNTA($C$5:C19),"000"))
B20: =IF(C20="","PER-"&TEXT(COUNTA($C$5:C20),"000"))
B21: =IF(C21="","PER-"&TEXT(COUNTA($C$5:C21),"000"))
... B109: =IF(C109="","PER-"&TEXT(COUNTA($C$5:C109),"000"))
B111: INDICATEURS (mis a jour automatiquement)
B112: Categories definies
B113: =COUNTIF(B5:B104,"<>")

Sheet 18-Suivi MAJ Documents
B2: SUIVI MISES À JOUR DOCUMENTS
B3: TABLEAU DYNAMIQUE — Saisissez dans la prochaine ligne jaune. Les calculs se mettent a jour automatiquement.
B4: N° | C4: Document | D4: Type Document | E4: Derniere MAJ | F4: Frequence MAJ | G4: Jours depuis MAJ | H4: Prochaine MAJ Prevue | I4: Jours avant Prochaine | J4: Responsable | K4: Statut
B5: MAJ-001 | C5: Reglement interieur | D5: Reglement interieur | E5: 45458 | F5: Annuelle | H5: 45823 | J5: DRH | K5: En retard
B6: MAJ-002 | C6: Grille salariale | D6: Politique RH | E6: 45667 | F6: Annuelle | H6: 46032 | J6: DRH + DAF | K6: En cours
B7: MAJ-003 | C7: Plan formation annuel | D7: Plan de formation | E7: 45662 | F7: Annuelle | H7: 46027 | J7: DRH | K7: En cours
B8: MAJ-004 | C8: Organigramme hotel | D8: Note de service | E8: 45717 | F8: Semestrielle | H8: 45901 | J8: DRH | K8: En cours
B9: MAJ-005 | C9: Liste contacts urgences | D9: Autre | E9: 45778 | F9: Trimestrielle | H9: 45870 | J9: Assistante RH | K9: En cours
B10: =IF(C10="","MAJ-"&TEXT(COUNTA($C$5:C10),"000")) | G10: =IF(F10="","",TODAY()-F10) | I10: =IF(H10="","",H10-TODAY())
B11: =IF(C11="","MAJ-"&TEXT(COUNTA($C$5:C11),"000")) | G11: =IF(F11="","",TODAY()-F11) | I11: =IF(H11="","",H11-TODAY())
B12: =IF(C12="","MAJ-"&TEXT(COUNTA($C$5:C12),"000")) | G12: =IF(F12="","",TODAY()-F12) | I12: =IF(H12="","",H12-TODAY())
B13: =IF(C13="","MAJ-"&TEXT(COUNTA($C$5:C13),"000")) | G13: =IF(F13="","",TODAY()-F13) | I13: =IF(H13="","",H13-TODAY())
B14: =IF(C14="","MAJ-"&TEXT(COUNTA($C$5:C14),"000")) | G14: =IF(F14="","",TODAY()-F14) | I14: =IF(H14="","",H14-TODAY())
B15: =IF(C15="","MAJ-"&TEXT(COUNTA($C$5:C15),"000")) | G15: =IF(F15="","",TODAY()-F15) | I15: =IF(H15="","",H15-TODAY())
B16: =IF(C16="","MAJ-"&TEXT(COUNTA($C$5:C16),"000")) | G16: =IF(F16="","",TODAY()-F16) | I16: =IF(H16="","",H16-TODAY())
B17: =IF(C17="","MAJ-"&TEXT(COUNTA($C$5:C17),"000")) | G17: =IF(F17="","",TODAY()-F17) | I17: =IF(H17="","",H17-TODAY())
B18: =IF(C18="","MAJ-"&TEXT(COUNTA($C$5:C18),"000")) | G18: =IF(F18="","",TODAY()-F18) | I18: =IF(H18="","",H18-TODAY())
B19: =IF(C19="","MAJ-"&TEXT(COUNTA($C$5:C19),"000")) | G19: =IF(F19="","",TODAY()-F19) | I19: =IF(H19="","",H19-TODAY())
B20: =IF(C20="","MAJ-"&TEXT(COUNTA($C$5:C20),"000")) | G20: =IF(F20="","",TODAY()-F20) | I20: =IF(H20="","",H20-TODAY())
B21: =IF(C21="","MAJ-"&TEXT(COUNTA($C$5:C21),"000")) | G21: =IF(F21="","",TODAY()-F21) | I21: =IF(H21="","",H21-TODAY())
... B109: =IF(C109="","MAJ-"&TEXT(COUNTA($C$5:C109),"000")) | G109: =IF(F109="","",TODAY()-F109) | I109: =IF(H109="","",H109-TODAY())
B111: INDICATEURS (mis a jour automatiquement)
B112: Documents suivis | D112: En retard | F112: A MAJ < 30j
B113: =COUNTIF(B5:B104,"<>") | D113: =COUNTIF(K5:K104,"En retard") | F113: =COUNTIF(I5:I104,"<"&30)-COUNTIF(I5:I104,"<"&0)

Sheet 19-Analyse Vol. Archivage
B2: ANALYSE VOLUME ARCHIVAGE
B3: TABLEAU DYNAMIQUE — Saisissez dans la prochaine ligne jaune. Les calculs se mettent a jour automatiquement.
B4: N° | C4: Type Document | D4: Volume Physique (unites) | E4: Volume Numerique (fichiers) | F4: Volume Numerique (Mo) | G4: Espace Stockage Utilise (Go) | H4: Taux Numerisation (%) | I4: Cout Stockage Estime (FCFA)
B5: AVA-001 | C5: Contrats de travail | D5: 85 | E5: 85 | F5: 42 | G5: 0.04 | I5: 5000
B6: AVA-002 | C6: Bulletins de paie | D6: 12 | E6: 850 | F6: 240 | G6: 0.23 | I6: 15000
B7: AVA-003 | C7: PV reunions | D7: 8 | E7: 40 | F7: 16 | G7: 0.02 | I7: 3000
B8: AVA-004 | C8: Formations & Attestations | D8: 15 | E8: 120 | F8: 60 | G8: 0.06 | I8: 8000
B9: AVA-005 | C9: Reglementation | D9: 25 | E9: 75 | F9: 35 | G9: 0.03 | I9: 4000
B10: =IF(C10="","AVA-"&TEXT(COUNTA($C$5:C10),"000")) | H10: =IF(OR(D10="",E10=""),"",IF(D10+E10=0,"",E10/(D10+E10)))
B11: =IF(C11="","AVA-"&TEXT(COUNTA($C$5:C11),"000")) | H11: =IF(OR(D11="",E11=""),"",IF(D11+E11=0,"",E11/(D11+E11)))
B12: =IF(C12="","AVA-"&TEXT(COUNTA($C$5:C12),"000")) | H12: =IF(OR(D12="",E12=""),"",IF(D12+E12=0,"",E12/(D12+E12)))
B13: =IF(C13="","AVA-"&TEXT(COUNTA($C$5:C13),"000")) | H13: =IF(OR(D13="",E13=""),"",IF(D13+E13=0,"",E13/(D13+E13)))
B14: =IF(C14="","AVA-"&TEXT(COUNTA($C$5:C14),"000")) | H14: =IF(OR(D14="",E14=""),"",IF(D14+E14=0,"",E14/(D14+E14)))
B15: =IF(C15="","AVA-"&TEXT(COUNTA($C$5:C15),"000")) | H15: =IF(OR(D15="",E15=""),"",IF(D15+E15=0,"",E15/(D15+E15)))
B16: =IF(C16="","AVA-"&TEXT(COUNTA($C$5:C16),"000")) | H16: =IF(OR(D16="",E16=""),"",IF(D16+E16=0,"",E16/(D16+E16)))
B17: =IF(C17="","AVA-"&TEXT(COUNTA($C$5:C17),"000")) | H17: =IF(OR(D17="",E17=""),"",IF(D17+E17=0,"",E17/(D17+E17)))
B18: =IF(C18="","AVA-"&TEXT(COUNTA($C$5:C18),"000")) | H18: =IF(OR(D18="",E18=""),"",IF(D18+E18=0,"",E18/(D18+E18)))
B19: =IF(C19="","AVA-"&TEXT(COUNTA($C$5:C19),"000")) | H19: =IF(OR(D19="",E19=""),"",IF(D19+E19=0,"",E19/(D19+E19)))
B20: =IF(C20="","AVA-"&TEXT(COUNTA($C$5:C20),"000")) | H20: =IF(OR(D20="",E20=""),"",IF(D20+E20=0,"",E20/(D20+E20)))
B21: =IF(C21="","AVA-"&TEXT(COUNTA($C$5:C21),"000")) | H21: =IF(OR(D21="",E21=""),"",IF(D21+E21=0,"",E21/(D21+E21)))
... B109: =IF(C109="","AVA-"&TEXT(COUNTA($C$5:C109),"000")) | H109: =IF(OR(D109="",E109=""),"",IF(D109+E109=0,"",E109/(D109+E109)))
B111: TOTAL | D111: =SUM(D5:D104) | E111: =SUM(E5:E104) | F111: =SUM(F5:F104) | I111: =SUM(I5:I104)
B113: INDICATEURS (mis a jour automatiquement)
B114: Total unites physiques | D114: Total fichiers numeriques | F114: Taux numerisation moy.
B115: =SUM(D5:D104) | D115: =SUM(E5:E104) | F115: =IFERROR(AVERAGE(H5:H104),0)
