Workbook

Sheet _Données Employés
B4: Matricule | C4: Civilité | D4: Nom | E4: Prénom | F4: Département | G4: Poste | H4: Salaire Base (FCFA)
B5: EMP-001 | C5: M. | D5: Nganou | E5: Clarisse | F5: Cuisine & Restauration | G5: Chef cuisinier | H5: 450000
B6: EMP-002 | C6: M. | D6: Tchinda | E6: Armand | F6: Réception & Front Office | G6: Réceptionniste | H6: 220000
B7: EMP-003 | C7: Mme | D7: Fotso | E7: Marguerite | F7: Finance & Comptabilité | G7: Comptable senior | H7: 380000
B8: EMP-004 | C8: M. | D8: Nkoulou | E8: Mbarga | F8: Étage & Housekeeping | G8: Gouvernant | H8: 195000
B9: EMP-005 | C9: M. | D9: Kamga | E9: Paul | F9: Maintenance | G9: Technicien maintenance | H9: 165000
B10: EMP-006 | C10: Mme | D10: Ngo | E10: Delphine | F10: Service Client | G10: Conseiller clientèle | H10: 160000
B11: EMP-007 | C11: M. | D11: Essomba | E11: Serge | F11: Maintenance | G11: Agent entretien | H11: 130000
B12: EMP-008 | C12: M. | D12: Tchouankou | E12: Paul | F12: Commercial | G12: Commercial | H12: 150000
B13: EMP-009 | C13: M. | D13: Fokam | E13: Eric | F13: Maintenance | G13: Technicien | H13: 140000
B14: EMP-010 | C14: M. | D14: Tagne | E14: René | F14: Cuisine & Restauration | G14: Plongeur | H14: 90000
B15: EMP-011 | C15: M. | D15: Bouba | E15: Ahmed | F15: Sécurité | G15: Agent Sécurité | H15: 120000
B16: EMP-012 | C16: Mme | D16: Awa | E16: Fatou | F16: Réception & Front Office | G16: Standardiste | H16: 155000
... B18: EMP-029 | C18: M. | D18: Kamga | E18: Patrice | F18: Sécurité | G18: Chef Sécurité | H18: 210000

Sheet 1-Tableau de Bord
B2: DOMAINE 10 — GESTION DES TALENTS & MOBILITE INTERNE
B3: TABLEAU DE BORD — Vue synthetique de tous les indicateurs du domaine (mis a jour automatiquement)
B5: Talents identifies | E5: Plans de carriere | H5: Mobilites internes | K5: Successeurs designes
B6: =COUNTIF('2-Cartographie Talents'!B5:B104,"<>") | E6: =COUNTIF('3-Plans de Carriere'!B5:B104,"<>") | H6: =COUNTIF('4-Mobilite Interne'!B5:B104,"<>") | K6: =COUNTIF('5-Successeurs & Releve'!B5:B104,"<>")
B9: HiPo identifies | E9: Programmes mentorat | H9: Actions retention | K9: Cout retention (M FCFA)
B10: =COUNTIF('7-Hauts Potentiels HiPo'!B5:B104,"<>") | E10: =COUNTIF('6-Programmes Mentorat'!B5:B104,"<>") | H10: =COUNTIF('8-Plan de Retention'!B5:B104,"<>") | K10: =IFERROR(SUM('8-Plan de Retention'!I5:I104)/1000000,0)
B13: Entretiens pro realises | E13: Bilans competences | H13: Expatries en poste | K13: Postes cles couverts
B14: =COUNTIF('9-Entretiens Professionnels'!B5:B104,"<>") | E14: =COUNTIF('10-Bilan Competences'!B5:B104,"<>") | H14: =COUNTIF('11-Gestion Expatries'!B5:B104,"<>") | K14: =COUNTIF('18-Suivi Successeurs'!B5:B104,"<>")
B18: MOBILITE INTERNE PAR DEPARTEMENT & CATEGORIES TALENTS
B19: Type Mobilite | C19: Nombre
B20: Promotion | C20: =COUNTIF('4-Mobilite Interne'!H5:H104,"Promotion")
B21: Mutation laterale | C21: =COUNTIF('4-Mobilite Interne'!H5:H104,"Mutation laterale")
B22: Rotation poste | C22: =COUNTIF('4-Mobilite Interne'!H5:H104,"Rotation poste")
B23: Detachement | C23: =COUNTIF('4-Mobilite Interne'!H5:H104,"Detachement")
B24: Mutation geographique | C24: =COUNTIF('4-Mobilite Interne'!H5:H104,"Mutation geographique")
H26: Categorie Talent | I26: Effectif
H27: Etoile montante | I27: =COUNTIF('2-Cartographie Talents'!J5:J104,"Etoile montante")
H28: Performeur stable | I28: =COUNTIF('2-Cartographie Talents'!J5:J104,"Performeur stable")
H29: Expert technique | I29: =COUNTIF('2-Cartographie Talents'!J5:J104,"Expert technique")
H30: Leader naturel | I30: =COUNTIF('2-Cartographie Talents'!J5:J104,"Leader naturel")
H31: Potentiel cache | I31: =COUNTIF('2-Cartographie Talents'!J5:J104,"Potentiel cache")
H32: A surveiller | I32: =COUNTIF('2-Cartographie Talents'!J5:J104,"A surveiller")

Sheet _Lists
B1: departement | C1: poste_hotel | D1: niveau_potentiel | E1: performance | F1: categorie_talent | G1: type_mobilite | H1: statut_mobilite | I1: type_mentorat | J1: statut_mentorat | K1: statut_releve | L1: niveau_risque_depart | M1: cause_risque | N1: frequence_entretien | O1: statut_entretien | P1: type_competence | Q1: niveau_competence | R1: ecart_competence | S1: statut_plan | T1: pays | U1: type_contrat_expatrie | V1: statut_expatrie | W1: mois | X1: annee | Y1: action_retention | Z1: statut_action_retention
B2: Direction Générale | C2: DG | D2: Faible | E2: Insuffisant | F2: Etoile montante | G2: Promotion | H2: En cours | I2: Mentorat classique | J2: En cours | K2: Candidat identifie | L2: Faible | M2: Insatisfaction salariale | N2: Annuel | O2: Planifie | P2: Technique | Q2: Debutant | R2: Acquis | S2: En elaboration | T2: Cameroun | U2: Detachement | V2: En poste | W2: Janvier | X2: 2024 | Y2: Augmentation salariale | Z2: Proposee
B3: Service Client | C3: DRH | D3: Moyen | E3: Moyen | F3: Performeur stable | G3: Mutation laterale | H3: Accepte | I3: Coaching | J3: Termine | K3: En formation | L3: Moyen | M3: Manque de perspective | N3: Semestriel | O3: Realise | P3: Comportementale | Q3: Intermediaire | R3: A developper | S3: Valide | T3: Cote d'Ivoire | U3: Expatriation classique | V3: En transit | W3: Fevrier | X3: 2025 | Y3: Promotion | Z3: Acceptee
B4: Finance & Comptabilité | C4: Assistante RH | D4: Eleve | E4: Bon | F4: Expert technique | G4: Rotation poste | H4: Realise | I4: Parrainage | J4: Suspendu | K4: Pret | L4: Eleve | M4: Conflit manager | N4: Trimestriel | O4: Reporte | P4: Manageriale | Q4: Avance | R4: A renforcer | S4: En cours | T4: Senegal | U4: Contrat local | V4: Rapatrie | W4: Mars | X4: 2026 | Y4: Formation qualifiante | Z4: En cours
B5: Marketing & Communication | C5: DAF | D5: Tres eleve | E5: Tres bon | F5: Leader naturel | G5: Detachement | H5: Refuse | I5: Tutorat | J5: En attente | K5: Nomme | L5: Critique | M5: Charge de travail | O5: Annule | P5: Linguistique | Q5: Expert | R5: Non acquis | S5: Evalue | T5: Gabon | U5: Mission courte duree | V5: En attente visa | W5: Avril | Y5: Avantages sociaux | Z5: Refusee
B6: Maintenance | C6: Comptable senior | E6: Excellent | F6: Potentiel cache | G6: Mutation geographique | H6: Reporte | I6: Shadowing | J6: Annule | K6: Non retenu | M6: Opportunite externe | P6: Numerique | Q6: Maitre | R6: En cours d'acquisition | S6: Archive | T6: Congo | V6: Contrat termine | W6: Mai | Y6: Flexibilite horaires | Z6: Terminee
B7: Commercial | C7: Chef Comptable | F7: A surveiller | H7: Annule | K7: En evaluation | M7: Raison personnelle | P7: Secteur hotelier | T7: Tchad | W7: Juin | Y7: Teletravail partiel | Z7: Non applicable
B8: Logistique & Approvisionnement | C8: Chef Marketing | M8: Mauvais climat social | T8: France | W8: Juillet | Y8: Prime de retention
B9: Cuisine & Restauration | C9: Chef de service IT | T9: Maroc | W9: Aout | Y9: Plan de carriere personnalise
B10: Réception & Front Office | C10: Technicien IT | T10: Tunisie | W10: Septembre | Y10: Amelioration conditions travail
B11: Sécurité | C11: Chef Commercial | T11: Turquie | W11: Octobre | Y11: Reconnaissance &表彰
B12: Étage & Housekeeping | C12: Agent Commercial | T12: Emirats Arabes Unis | W12: Novembre
C13: Chef Logistique | W13: Decembre
C14: Magasinier
C15: Chef Reception
C16: Receptionniste
C17: Concierge
C18: Chef Cuisine
C19: Sous-Chef
C20: Cuisinier
C21: Plongeur
C22: Chef Entretien
C23: Agent Entretien
C24: Chef Securite
C25: Agent Securite

Sheet 2-Cartographie Talents
B2: CARTOGRAPHIE DES TALENTS (#107)
B3: TABLEAU DYNAMIQUE — Saisissez dans la prochaine ligne jaune. Les calculs se mettent a jour automatiquement.
B4: N° | C4: Employe | D4: Poste Actuel | E4: Departement | F4: Anciennete (ans) | G4: Performance | H4: Potentiel | I4: Categorie Talent | J4: Competition Externe | K4: Risque Depart | L4: Action Prioritaire
B5: TAL-001 | C5: Nkoulou Mbarga P. | D5: Chef Reception | E5: Réception & Front Office | F5: 6 | G5: Excellent | H5: Eleve | I5: Etoile montante | J5: Eleve | K5: Eleve | L5: Formation manageriale + augmentation
B6: TAL-002 | C6: Fotsing Aude R. | D6: Sous-Chef | E6: Cuisine & Restauration | F6: 4 | G6: Tres bon | H6: Eleve | I6: Expert technique | J6: Moyen | K6: Faible | L6: Plan de carriere vers Chef Cuisine
B7: TAL-003 | C7: Tamo Eric | D7: Technicien IT | E7: Informatique | F7: 3 | G7: Bon | H7: Tres eleve | I7: Etoile montante | J7: Eleve | K7: Moyen | L7: Formation certifiante + prime
B8: TAL-004 | C8: Ouedraogo Issa | D8: Agent Commercial | E8: Commercial | F8: 5 | G8: Tres bon | H8: Moyen | I8: Performeur stable | J8: Moyen | K8: Faible | L8: Rotation vers Chef Commercial adjoint
B9: TAL-005 | C9: Nganou D. | D9: Receptionniste | E9: Réception & Front Office | F9: 2 | G9: Bon | H9: Eleve | I9: Leader naturel | J9: Eleve | K9: Moyen | L9: Programme mentorat + responsabilites
B10: =IF(C10="","TAL-"&TEXT(COUNTA($C$5:C10),"000"))
B11: =IF(C11="","TAL-"&TEXT(COUNTA($C$5:C11),"000"))
B12: =IF(C12="","TAL-"&TEXT(COUNTA($C$5:C12),"000"))
B13: =IF(C13="","TAL-"&TEXT(COUNTA($C$5:C13),"000"))
B14: =IF(C14="","TAL-"&TEXT(COUNTA($C$5:C14),"000"))
B15: =IF(C15="","TAL-"&TEXT(COUNTA($C$5:C15),"000"))
B16: =IF(C16="","TAL-"&TEXT(COUNTA($C$5:C16),"000"))
B17: =IF(C17="","TAL-"&TEXT(COUNTA($C$5:C17),"000"))
B18: =IF(C18="","TAL-"&TEXT(COUNTA($C$5:C18),"000"))
B19: =IF(C19="","TAL-"&TEXT(COUNTA($C$5:C19),"000"))
B20: =IF(C20="","TAL-"&TEXT(COUNTA($C$5:C20),"000"))
B21: =IF(C21="","TAL-"&TEXT(COUNTA($C$5:C21),"000"))
... B109: =IF(C109="","TAL-"&TEXT(COUNTA($C$5:C109),"000"))
B111: INDICATEURS (mis a jour automatiquement)
B112: Talents identifies | D112: Potentiel eleve | F112: Risque critique | H112: Etoiles montantes
B113: =COUNTIF(B5:B104,"<>") | D113: =COUNTIF(H5:H104,"Eleve")+COUNTIF(H5:H104,"Tres eleve") | F113: =COUNTIF(K5:K104,"Critique") | H113: =COUNTIF(I5:I104,"Etoile montante")

Sheet 3-Plans de Carriere
B2: PLANS DE CARRIÈRE (#108)
B3: TABLEAU DYNAMIQUE — Saisissez dans la prochaine ligne jaune. Les calculs se mettent a jour automatiquement.
B4: N° | C4: Employe | D4: Poste Actuel | E4: Objectif Carriere | F4: Echeance | G4: Competences Requises | H4: Formations Planifiees | I4: Statut | J4: Accompagnateur | K4: Observations
B5: CAR-001 | C5: Nkoulou Mbarga P. | D5: Chef Reception | E5: Responsable Front Office | F5: 46022 | G5: Management, Revenue Management, Anglais courant | H5: Certification Revenue Management + Coaching | I5: En cours | J5: DRH Fotso M. | K5: Candidat naturel pour succession
B6: CAR-002 | C6: Fotsing Aude R. | D6: Sous-Chef | E6: Chef Cuisine | F6: 46203 | G6: Gestion menu, management equipe, hygiene HACCP avance | H6: Formation HACCP niveau 3 + Management cuisine | I6: En cours | J6: Chef Cuisine Biyong J. | K6: Progression reguliere, bien parti
B7: CAR-003 | C7: Tamo Eric | D7: Technicien IT | E7: Chef de service IT | F7: 46112 | G7: Administration reseau, cybersécurite, gestion budget IT | H7: Certification Cisco + Formation gestion budget | I7: En elaboration | J7: DSI externe | K7: Potentiel fort, besoin encadrement management
B8: CAR-004 | C8: Ouedraogo Issa | D8: Agent Commercial | E8: Chef Commercial adjoint | F8: 45930 | G8: Negociation B2B, gestion portefeuille, anglais | H8: Formation vente hoteliere + Anglais intensif | I8: En cours | J8: Chef Commercial Manga S. | K8: Bonne dynamique commerciale
B9: CAR-005 | C9: Nganou D. | D9: Receptionniste | E9: Chef Reception adjoint | F9: 46203 | G9: Supervision, gestion plannings, PMS avance, service client | H9: Formation supervision + Certif. Opera PMS | I9: En elaboration | J9: Chef Reception Nkoulou P. | K9: Nouveau talent a developper
B10: =IF(C10="","CAR-"&TEXT(COUNTA($C$5:C10),"000"))
B11: =IF(C11="","CAR-"&TEXT(COUNTA($C$5:C11),"000"))
B12: =IF(C12="","CAR-"&TEXT(COUNTA($C$5:C12),"000"))
B13: =IF(C13="","CAR-"&TEXT(COUNTA($C$5:C13),"000"))
B14: =IF(C14="","CAR-"&TEXT(COUNTA($C$5:C14),"000"))
B15: =IF(C15="","CAR-"&TEXT(COUNTA($C$5:C15),"000"))
B16: =IF(C16="","CAR-"&TEXT(COUNTA($C$5:C16),"000"))
B17: =IF(C17="","CAR-"&TEXT(COUNTA($C$5:C17),"000"))
B18: =IF(C18="","CAR-"&TEXT(COUNTA($C$5:C18),"000"))
B19: =IF(C19="","CAR-"&TEXT(COUNTA($C$5:C19),"000"))
B20: =IF(C20="","CAR-"&TEXT(COUNTA($C$5:C20),"000"))
B21: =IF(C21="","CAR-"&TEXT(COUNTA($C$5:C21),"000"))
... B109: =IF(C109="","CAR-"&TEXT(COUNTA($C$5:C109),"000"))
B111: INDICATEURS (mis a jour automatiquement)
B112: Plans actifs | D112: En cours | F112: En elaboration
B113: =COUNTIF(B5:B104,"<>") | D113: =COUNTIF(I5:I104,"En cours") | F113: =COUNTIF(I5:I104,"En elaboration")

Sheet 4-Mobilite Interne
B2: MOBILITE INTERNE (#109)
B3: TABLEAU DYNAMIQUE — Saisissez dans la prochaine ligne jaune. Les calculs se mettent a jour automatiquement.
B4: N° | C4: Employe | D4: Poste Origine | E4: Dept. Origine | F4: Poste Destination | G4: Dept. Destination | H4: Type Mobilite | I4: Date Demande | J4: Date Effective | K4: Statut | L4: Motif
B5: MOB-001 | C5: Ngassa F. | D5: Agent Entretien | E5: Maintenance | F5: Magasinier | G5: Logistique & Approvisionnement | H5: Mutation laterale | I5: 45667 | J5: 45689 | K5: Realise | L5: Requalification professionnelle
B6: MOB-002 | C6: Kamga P. | D6: Receptionniste | E6: Réception & Front Office | F6: Agent Commercial | G6: Commercial | H6: Rotation poste | I6: 45717 | J6: 45748 | K6: Realise | L6: Developpement competences commerciales
B7: MOB-003 | C7: Bekolo A. | D7: Plongeur | E7: Cuisine & Restauration | F7: Agent Entretien | G7: Maintenance | H7: Mutation laterale | I7: 45792 | K7: En cours | L7: Demande de changement de domaine
B8: MOB-004 | C8: Meyong S. | D8: Agent Securite | E8: Sécurité | F8: Concierge | G8: Réception & Front Office | H8: Promotion | I8: 45748 | J8: 45778 | K8: Realise | L8: Evolution carriere + competences client
B9: MOB-005 | C9: Fouda M. | D9: Cuisinier | E9: Cuisine & Restauration | F9: Sous-Chef | G9: Cuisine & Restauration | H9: Promotion | I9: 45809 | K9: En cours | L9: Promotion interne meritee
B10: =IF(C10="","MOB-"&TEXT(COUNTA($C$5:C10),"000"))
B11: =IF(C11="","MOB-"&TEXT(COUNTA($C$5:C11),"000"))
B12: =IF(C12="","MOB-"&TEXT(COUNTA($C$5:C12),"000"))
B13: =IF(C13="","MOB-"&TEXT(COUNTA($C$5:C13),"000"))
B14: =IF(C14="","MOB-"&TEXT(COUNTA($C$5:C14),"000"))
B15: =IF(C15="","MOB-"&TEXT(COUNTA($C$5:C15),"000"))
B16: =IF(C16="","MOB-"&TEXT(COUNTA($C$5:C16),"000"))
B17: =IF(C17="","MOB-"&TEXT(COUNTA($C$5:C17),"000"))
B18: =IF(C18="","MOB-"&TEXT(COUNTA($C$5:C18),"000"))
B19: =IF(C19="","MOB-"&TEXT(COUNTA($C$5:C19),"000"))
B20: =IF(C20="","MOB-"&TEXT(COUNTA($C$5:C20),"000"))
B21: =IF(C21="","MOB-"&TEXT(COUNTA($C$5:C21),"000"))
... B109: =IF(C109="","MOB-"&TEXT(COUNTA($C$5:C109),"000"))
B111: INDICATEURS (mis a jour automatiquement)
B112: Mobilites | D112: Realisees | F112: En cours | H112: Promotions
B113: =COUNTIF(B5:B104,"<>") | D113: =COUNTIF(K5:K104,"Realise") | F113: =COUNTIF(K5:K104,"En cours") | H113: =COUNTIF(H5:H104,"Promotion")

Sheet 5-Successeurs & Releve
B2: SUCCESSEURS & RELÈVE (#110)
B3: TABLEAU DYNAMIQUE — Saisissez dans la prochaine ligne jaune. Les calculs se mettent a jour automatiquement.
B4: N° | C4: Poste Cle | D4: Titulaire Actuel | E4: Successeur Designe | F4: Departement | G4: Niveau de Pret | H4: Date Evaluation | I4: Ecart Competences | J4: Plan de Developp. | K4: Statut | L4: Date Prev. Prise Poste
B5: REL-001 | C5: Chef Reception | D5: Nkoulou Mbarga P. | E5: Nganou D. | F5: Réception & Front Office | G5: En formation | H5: 45792 | I5: Management, Revenue Mgmt | J5: Coaching + Formation Opera PMS | K5: En formation | L5: 46174
B6: REL-002 | C6: Chef Cuisine | D6: Biyong Jean M. | E6: Fotsing Aude R. | F6: Cuisine & Restauration | G6: En formation | H6: 45767 | I6: Gestion budget cuisine, creativity menu | J6: HACCP niv.3 + Stages externes | K6: En formation | L6: 46204
B7: REL-003 | C7: DRH | D7: Fotso M. | E7: Assistante RH Ngo M. | F7: Service Client | G7: Candidat identifie | H7: 45809 | I7: Droit travail avance, paie, relations sociales | J7: Formation DRH adjoint + tutorat | K7: Candidat identifie | L7: 46388
B8: REL-004 | C8: Chef Entretien | D8: Tchinda P. | E8: Fokam Ernest | F8: Maintenance | G8: En evaluation | H8: 45726 | I8: Technique CVC avance, gestion equipe | J8: Formation CVC + management | K8: En evaluation | L8: 46023
B9: REL-005 | C9: Chef Securite | D9: Nganmeni J. | E9: Wouamba A. | F9: Sécurité | G9: En formation | H9: 45778 | I9: Gestion crise, securite incendie avance | J9: Formation securite hoteliere niveau 2 | K9: En formation | L9: 46082
B10: =IF(C10="","REL-"&TEXT(COUNTA($C$5:C10),"000"))
B11: =IF(C11="","REL-"&TEXT(COUNTA($C$5:C11),"000"))
B12: =IF(C12="","REL-"&TEXT(COUNTA($C$5:C12),"000"))
B13: =IF(C13="","REL-"&TEXT(COUNTA($C$5:C13),"000"))
B14: =IF(C14="","REL-"&TEXT(COUNTA($C$5:C14),"000"))
B15: =IF(C15="","REL-"&TEXT(COUNTA($C$5:C15),"000"))
B16: =IF(C16="","REL-"&TEXT(COUNTA($C$5:C16),"000"))
B17: =IF(C17="","REL-"&TEXT(COUNTA($C$5:C17),"000"))
B18: =IF(C18="","REL-"&TEXT(COUNTA($C$5:C18),"000"))
B19: =IF(C19="","REL-"&TEXT(COUNTA($C$5:C19),"000"))
B20: =IF(C20="","REL-"&TEXT(COUNTA($C$5:C20),"000"))
B21: =IF(C21="","REL-"&TEXT(COUNTA($C$5:C21),"000"))
... B109: =IF(C109="","REL-"&TEXT(COUNTA($C$5:C109),"000"))
B111: INDICATEURS (mis a jour automatiquement)
B112: Postes cles couverts | D112: Prets | F112: En formation
B113: =COUNTIF(B5:B104,"<>") | D113: =COUNTIF(K5:K104,"Pret")+COUNTIF(K5:K104,"Nomme") | F113: =COUNTIF(K5:K104,"En formation")

Sheet 6-Programmes Mentorat
B2: PROGRAMMES DE MENTORAT (#111)
B3: TABLEAU DYNAMIQUE — Saisissez dans la prochaine ligne jaune. Les calculs se mettent a jour automatiquement.
B4: N° | C4: Mentore | D4: Poste Mentore | E4: Mentor | F4: Poste Mentor | G4: Type Mentorat | H4: Date Debut | I4: Date Fin | J4: Objectifs | K4: Statut | L4: Bilan
B5: MEN-001 | C5: Nganou D. | D5: Receptionniste | E5: Nkoulou Mbarga P. | F5: Chef Reception | G5: Mentorat classique | H5: 45689 | I5: 45870 | J5: Developper competences supervision et gestion plannings | K5: En cours | L5: Progression satisfaisante, confiance renforcee
B6: MEN-002 | C6: Fouda M. | D6: Cuisinier | E6: Biyong Jean M. | F6: Chef Cuisine | G6: Tutorat | H6: 45672 | I6: 45853 | J6: Maitrise gestion brigade, creation menus, gestion stocks | K6: En cours | L6: Bon apprenti, creative, discipline renforcee
B7: MEN-003 | C7: Assistante RH Ngo M. | D7: Assistante RH | E7: Fotso M. | F7: DRH | G7: Coaching | H7: 45717 | I7: 46022 | J7: Preparation au poste de DRH adjoint, droit travail avance | K7: En cours | L7: Autonome croissante, bonne capacite decisionnelle
B8: MEN-004 | C8: Tamo Eric | D8: Technicien IT | E8: Consultant externe | F8: Consultant IT senior | G8: Coaching | H8: 45748 | I8: 45931 | J8: Certification reseau et cybersecurite | K8: En cours | L8: Certification en bonne voie, motivation forte
B9: MEN-005 | C9: Bekolo A. | D9: Agent Entretien | E9: Tchinda P. | F9: Chef Entretien | G9: Shadowing | H9: 45778 | I9: 45870 | J9: Observation gestion equipe entretien et planning | K9: En cours | L9: Observation active, bonnes remarques
B10: =IF(C10="","MEN-"&TEXT(COUNTA($C$5:C10),"000"))
B11: =IF(C11="","MEN-"&TEXT(COUNTA($C$5:C11),"000"))
B12: =IF(C12="","MEN-"&TEXT(COUNTA($C$5:C12),"000"))
B13: =IF(C13="","MEN-"&TEXT(COUNTA($C$5:C13),"000"))
B14: =IF(C14="","MEN-"&TEXT(COUNTA($C$5:C14),"000"))
B15: =IF(C15="","MEN-"&TEXT(COUNTA($C$5:C15),"000"))
B16: =IF(C16="","MEN-"&TEXT(COUNTA($C$5:C16),"000"))
B17: =IF(C17="","MEN-"&TEXT(COUNTA($C$5:C17),"000"))
B18: =IF(C18="","MEN-"&TEXT(COUNTA($C$5:C18),"000"))
B19: =IF(C19="","MEN-"&TEXT(COUNTA($C$5:C19),"000"))
B20: =IF(C20="","MEN-"&TEXT(COUNTA($C$5:C20),"000"))
B21: =IF(C21="","MEN-"&TEXT(COUNTA($C$5:C21),"000"))
... B109: =IF(C109="","MEN-"&TEXT(COUNTA($C$5:C109),"000"))
B111: INDICATEURS (mis a jour automatiquement)
B112: Programmes actifs | D112: En cours | F112: Termines
B113: =COUNTIF(B5:B104,"<>") | D113: =COUNTIF(K5:K104,"En cours") | F113: =COUNTIF(K5:K104,"Termine")

Sheet 7-Hauts Potentiels HiPo
B2: GESTION DES HAUTS POTENTIELS - HiPo (#112)
B3: TABLEAU DYNAMIQUE — Saisissez dans la prochaine ligne jaune. Les calculs se mettent a jour automatiquement.
B4: N° | C4: Employe | D4: Poste Actuel | E4: Departement | F4: Performance | G4: Potentiel | H4: Score Performance (sur 100) | I4: Score Potentiel (sur 100) | J4: Score Global | K4: Parcours Recommande | L4: Decision Comite
B5: HIP-001 | C5: Nkoulou Mbarga P. | D5: Chef Reception | E5: Réception & Front Office | F5: Excellent | G5: Tres eleve | H5: 92 | I5: 88 | K5: Programme haut potentiel 12 mois | L5: Valide DRH
B6: HIP-002 | C6: Tamo Eric | D6: Technicien IT | E6: Informatique | F6: Bon | G6: Tres eleve | H6: 80 | I6: 90 | K6: Fast-track vers Chef service IT | L6: Valide DRH
B7: HIP-003 | C7: Fotsing Aude R. | D7: Sous-Chef | E7: Cuisine & Restauration | F7: Tres bon | G7: Eleve | H7: 85 | I7: 82 | K7: Programme Chef Cuisine cible 18 mois | L7: Valide DRH
B8: HIP-004 | C8: Assistante RH Ngo M. | D8: Assistante RH | E8: Service Client | F8: Tres bon | G8: Eleve | H8: 83 | I8: 80 | K8: Preparation DRH adjoint | L8: Valide DRH
B9: HIP-005 | C9: Nganou D. | D9: Receptionniste | E9: Réception & Front Office | F9: Bon | G9: Eleve | H9: 78 | I9: 85 | K9: Mentorat + responsabilites croissantes | L9: En attente validation
B10: =IF(C10="","HIP-"&TEXT(COUNTA($C$5:C10),"000")) | J10: =IF(OR(H10="",I10=""),"",(H10+I10)/2)
B11: =IF(C11="","HIP-"&TEXT(COUNTA($C$5:C11),"000")) | J11: =IF(OR(H11="",I11=""),"",(H11+I11)/2)
B12: =IF(C12="","HIP-"&TEXT(COUNTA($C$5:C12),"000")) | J12: =IF(OR(H12="",I12=""),"",(H12+I12)/2)
B13: =IF(C13="","HIP-"&TEXT(COUNTA($C$5:C13),"000")) | J13: =IF(OR(H13="",I13=""),"",(H13+I13)/2)
B14: =IF(C14="","HIP-"&TEXT(COUNTA($C$5:C14),"000")) | J14: =IF(OR(H14="",I14=""),"",(H14+I14)/2)
B15: =IF(C15="","HIP-"&TEXT(COUNTA($C$5:C15),"000")) | J15: =IF(OR(H15="",I15=""),"",(H15+I15)/2)
B16: =IF(C16="","HIP-"&TEXT(COUNTA($C$5:C16),"000")) | J16: =IF(OR(H16="",I16=""),"",(H16+I16)/2)
B17: =IF(C17="","HIP-"&TEXT(COUNTA($C$5:C17),"000")) | J17: =IF(OR(H17="",I17=""),"",(H17+I17)/2)
B18: =IF(C18="","HIP-"&TEXT(COUNTA($C$5:C18),"000")) | J18: =IF(OR(H18="",I18=""),"",(H18+I18)/2)
B19: =IF(C19="","HIP-"&TEXT(COUNTA($C$5:C19),"000")) | J19: =IF(OR(H19="",I19=""),"",(H19+I19)/2)
B20: =IF(C20="","HIP-"&TEXT(COUNTA($C$5:C20),"000")) | J20: =IF(OR(H20="",I20=""),"",(H20+I20)/2)
B21: =IF(C21="","HIP-"&TEXT(COUNTA($C$5:C21),"000")) | J21: =IF(OR(H21="",I21=""),"",(H21+I21)/2)
... B109: =IF(C109="","HIP-"&TEXT(COUNTA($C$5:C109),"000")) | J109: =IF(OR(H109="",I109=""),"",(H109+I109)/2)
B111: INDICATEURS (mis a jour automatiquement)
B112: HiPo identifies | D112: Score moyen | F112: Potentiel Tres eleve
B113: =COUNTIF(B5:B104,"<>") | D113: =IFERROR(AVERAGE(J5:J104),0) | F113: =COUNTIF(G5:G104,"Tres eleve")

Sheet 8-Plan de Retention
B2: PLAN DE RÉTENTION (#113)
B3: TABLEAU DYNAMIQUE — Saisissez dans la prochaine ligne jaune. Les calculs se mettent a jour automatiquement.
B4: N° | C4: Employe | D4: Poste | E4: Departement | F4: Niveau Risque Depart | G4: Cause Principale | H4: Action Retention | I4: Cout Estime (FCFA) | J4: Date Mise en Place | K4: Statut | L4: Resultat
B5: RET-001 | C5: Nkoulou Mbarga P. | D5: Chef Reception | E5: Réception & Front Office | F5: Eleve | G5: Opportunite externe | H5: Augmentation + Plan carriere | I5: 350000 | J5: 45689 | K5: Acceptee | L5: Employe reste, motivation renforcee
B6: RET-002 | C6: Biyong Jean M. | D6: Chef Cuisine | E6: Cuisine & Restauration | F6: Moyen | G6: Insatisfaction salariale | H6: Revalorisation + Prime responsabilite | I6: 500000 | J6: 45731 | K6: Terminee | L6: Satisfaction retrouvé, engagement maintenu
B7: RET-003 | C7: Fotso M. | D7: DRH | E7: Service Client | F7: Faible | G7: Manque de perspective | H7: Elargissement perimetre + Formation exec. | I7: 200000 | J7: 45667 | K7: Terminee | L7: Fidelisation confirmee par contrat 3 ans
B8: RET-004 | C8: Tchinda P. | D8: Chef Entretien | E8: Maintenance | F8: Eleve | G8: Charge de travail | H8: Recrutement adjoint + Flexibilite | I8: 450000 | J8: 45748 | K8: En cours | L8: En attente recrutement adjoint
B9: RET-005 | C9: Kamga P. | D9: Agent Commercial | E9: Commercial | F9: Moyen | G9: Manque de perspective | H9: Formation qualifiante + prime objectif | I9: 150000 | J9: 45778 | K9: En cours | L9: Formation en cours, premier bilan positif
B10: =IF(C10="","RET-"&TEXT(COUNTA($C$5:C10),"000"))
B11: =IF(C11="","RET-"&TEXT(COUNTA($C$5:C11),"000"))
B12: =IF(C12="","RET-"&TEXT(COUNTA($C$5:C12),"000"))
B13: =IF(C13="","RET-"&TEXT(COUNTA($C$5:C13),"000"))
B14: =IF(C14="","RET-"&TEXT(COUNTA($C$5:C14),"000"))
B15: =IF(C15="","RET-"&TEXT(COUNTA($C$5:C15),"000"))
B16: =IF(C16="","RET-"&TEXT(COUNTA($C$5:C16),"000"))
B17: =IF(C17="","RET-"&TEXT(COUNTA($C$5:C17),"000"))
B18: =IF(C18="","RET-"&TEXT(COUNTA($C$5:C18),"000"))
B19: =IF(C19="","RET-"&TEXT(COUNTA($C$5:C19),"000"))
B20: =IF(C20="","RET-"&TEXT(COUNTA($C$5:C20),"000"))
B21: =IF(C21="","RET-"&TEXT(COUNTA($C$5:C21),"000"))
... B109: =IF(C109="","RET-"&TEXT(COUNTA($C$5:C109),"000"))
B111: TOTAL | I111: =SUM(I5:I104)
B113: INDICATEURS (mis a jour automatiquement)
B114: Employes suivis | D114: Actions acceptees | F114: Cout total (kFCFA)
B115: =COUNTIF(B5:B104,"<>") | D115: =COUNTIF(K5:K104,"Acceptee")+COUNTIF(K5:K104,"Terminee") | F115: =IFERROR(SUM(I5:I104)/1000,0)

Sheet 9-Entretiens Professionnels
B2: ENTRETIENS PROFESSIONNELS (#114)
B3: TABLEAU DYNAMIQUE — Saisissez dans la prochaine ligne jaune. Les calculs se mettent a jour automatiquement.
B4: N° | C4: Employe | D4: Poste | E4: Departement | F4: Type Entretien | G4: Frequence | H4: Date Entretien | I4: Evaluateur | J4: Points Forts | K4: Axes Amelioration | L4: Engagements | M4: Statut
B5: EP-001 | C5: Nkoulou Mbarga P. | D5: Chef Reception | E5: Réception & Front Office | F5: Entretien annuel | G5: Annuel | H5: 45677 | I5: DRH Fotso M. | J5: Leadership exemplaire, satisfaction client elevee | K5: Deleguer davantage, developper revenue management | L5: Formation RM d'ici mars 2025 | M5: Realise
B6: EP-002 | C6: Fotsing Aude R. | D6: Sous-Chef | E6: Cuisine & Restauration | F6: Entretien annuel | G6: Annuel | H6: 45679 | I6: Chef Cuisine Biyong J. | J6: Creativite culinaire, rigueur hygiene | K6: Gestion stress en service, communication equipe | L6: Formation gestion stress + feedback regulier | M6: Realise
B7: EP-003 | C7: Tamo Eric | D7: Technicien IT | E7: Informatique | F7: Entretien semestriel | G7: Semestriel | H7: 45731 | I7: DSI externe | J7: Resolutions rapides, proactivite | K7: Documentation procedures, formation utilisateurs | L7: Rediger 1 procedure/mois + formation equipe | M7: Realise
B8: EP-004 | C8: Ouedraogo Issa | D8: Agent Commercial | E8: Commercial | F8: Entretien annuel | G8: Annuel | H8: 45818 | I8: Chef Commercial Manga S. | J8: Prospection active, bonne relation clients | K8: Objectifs non atteints Q1, anglais insuffisant | L8: Formation vente + anglais intensif | M8: Planifie
B9: EP-005 | C9: Nganou D. | D9: Receptionniste | E9: Réception & Front Office | F9: Entretien semestriel | G9: Semestriel | H9: 45752 | I9: Chef Reception Nkoulou P. | J9: Accueil chaleureux, polyvalence | K9: Maitrise PMS avance, gestion conflits clients | L9: Formation PMS + scenario gestion conflits | M9: Realise
B10: =IF(C10="","EP-"&TEXT(COUNTA($C$5:C10),"000"))
B11: =IF(C11="","EP-"&TEXT(COUNTA($C$5:C11),"000"))
B12: =IF(C12="","EP-"&TEXT(COUNTA($C$5:C12),"000"))
B13: =IF(C13="","EP-"&TEXT(COUNTA($C$5:C13),"000"))
B14: =IF(C14="","EP-"&TEXT(COUNTA($C$5:C14),"000"))
B15: =IF(C15="","EP-"&TEXT(COUNTA($C$5:C15),"000"))
B16: =IF(C16="","EP-"&TEXT(COUNTA($C$5:C16),"000"))
B17: =IF(C17="","EP-"&TEXT(COUNTA($C$5:C17),"000"))
B18: =IF(C18="","EP-"&TEXT(COUNTA($C$5:C18),"000"))
B19: =IF(C19="","EP-"&TEXT(COUNTA($C$5:C19),"000"))
B20: =IF(C20="","EP-"&TEXT(COUNTA($C$5:C20),"000"))
B21: =IF(C21="","EP-"&TEXT(COUNTA($C$5:C21),"000"))
... B109: =IF(C109="","EP-"&TEXT(COUNTA($C$5:C109),"000"))
B111: INDICATEURS (mis a jour automatiquement)
B112: Entretiens | D112: Realises | F112: Planifies | H112: Taux realisation
B113: =COUNTIF(B5:B104,"<>") | D113: =COUNTIF(M5:M104,"Realise") | F113: =COUNTIF(M5:M104,"Planifie") | H113: =IFERROR(COUNTIF(M5:M104,"Realise")/COUNTIF(B5:B104,"<>"),0)

Sheet 10-Bilan Competences
B2: BILAN DE COMPÉTENCES (#115)
B3: TABLEAU DYNAMIQUE — Saisissez dans la prochaine ligne jaune. Les calculs se mettent a jour automatiquement.
B4: N° | C4: Employe | D4: Poste | E4: Departement | F4: Competence Evaluee | G4: Type Competence | H4: Niveau Actuel | I4: Niveau Requis | J4: Ecart | K4: Plan Action | L4: Statut
B5: BC-001 | C5: Nkoulou Mbarga P. | D5: Chef Reception | E5: Réception & Front Office | F5: Revenue Management | G5: Technique | H5: Intermediaire | I5: Avance | J5: A developper | K5: Formation RM certifiante + accompagnement DAF | L5: En cours d'acquisition
B6: BC-002 | C6: Fotsing Aude R. | D6: Sous-Chef | E6: Cuisine & Restauration | F6: Gestion budget cuisine | G6: Manageriale | H6: Debutant | I6: Avance | J6: Non acquis | K6: Formation gestion budget + mentorat Chef Cuisine | L6: A developper
B7: BC-003 | C7: Tamo Eric | D7: Technicien IT | E7: Informatique | F7: Cybersecurite | G7: Technique | H7: Intermediaire | I7: Expert | J7: A developper | K7: Certification CISCO cybersécurite | L7: A developper
B8: BC-004 | C8: Ouedraogo Issa | D8: Agent Commercial | E8: Commercial | F8: Anglais hotelier | G8: Linguistique | H8: Debutant | I8: Avance | J8: Non acquis | K8: Cours anglais intensif 6 mois | L8: A developper
B9: BC-005 | C9: Nganou D. | D9: Receptionniste | E9: Réception & Front Office | F9: Gestion conflits | G9: Comportementale | H9: Intermediaire | I9: Avance | J9: A developper | K9: Formation gestion conflits + mise en situation | L9: En cours d'acquisition
B10: =IF(C10="","BC-"&TEXT(COUNTA($C$5:C10),"000"))
B11: =IF(C11="","BC-"&TEXT(COUNTA($C$5:C11),"000"))
B12: =IF(C12="","BC-"&TEXT(COUNTA($C$5:C12),"000"))
B13: =IF(C13="","BC-"&TEXT(COUNTA($C$5:C13),"000"))
B14: =IF(C14="","BC-"&TEXT(COUNTA($C$5:C14),"000"))
B15: =IF(C15="","BC-"&TEXT(COUNTA($C$5:C15),"000"))
B16: =IF(C16="","BC-"&TEXT(COUNTA($C$5:C16),"000"))
B17: =IF(C17="","BC-"&TEXT(COUNTA($C$5:C17),"000"))
B18: =IF(C18="","BC-"&TEXT(COUNTA($C$5:C18),"000"))
B19: =IF(C19="","BC-"&TEXT(COUNTA($C$5:C19),"000"))
B20: =IF(C20="","BC-"&TEXT(COUNTA($C$5:C20),"000"))
B21: =IF(C21="","BC-"&TEXT(COUNTA($C$5:C21),"000"))
... B109: =IF(C109="","BC-"&TEXT(COUNTA($C$5:C109),"000"))
B111: INDICATEURS (mis a jour automatiquement)
B112: Evaluations | D112: Competences acquises | F112: A developper | H112: Non acquises
B113: =COUNTIF(B5:B104,"<>") | D113: =COUNTIF(L5:L104,"Acquis") | F113: =COUNTIF(J5:J104,"A developper")+COUNTIF(L5:L104,"A developper") | H113: =COUNTIF(J5:J104,"Non acquis")

Sheet 11-Gestion Expatries
B2: GESTION EXPATRIÉS (#116)
B3: TABLEAU DYNAMIQUE — Saisissez dans la prochaine ligne jaune. Les calculs se mettent a jour automatiquement.
B4: N° | C4: Employe | D4: Poste | E4: Pays d'Origine | F4: Pays d'Affectation | G4: Type Contrat | H4: Date Depart | I4: Date Retour Prev. | J4: Salaire Mensuel (FCFA) | K4: Indemnite Expatriation | L4: Statut
B5: EXP-001 | C5: Dupont Marc | D5: Chef Cuisine Executive | E5: France | F5: Cameroun | G5: Expatriation classique | H5: 45306 | I5: 46037 | J5: 2500000 | K5: 800000 | L5: En poste
B6: EXP-002 | C6: Turker Ahmet | D6: Directeur Commercial | E6: Turquie | F6: Cameroun | G6: Detachement | H6: 45444 | I6: 46174 | J6: 2800000 | K6: 600000 | L6: En poste
B7: EXP-003 | C7: Dubois Claire | D7: Directrice Revenue Management | E7: France | F7: Cote d'Ivoire | G7: Mission courte duree | H7: 45717 | I7: 45901 | J7: 3200000 | K7: 500000 | L7: En poste
B8: EXP-004 | C8: Al Farsi Hassan | D8: Gestionnaire SPA | E8: Emirats Arabes Unis | F8: Senegal | G8: Contrat local | H8: 45667 | I8: 46397 | J8: 1800000 | K8: 300000 | L8: En poste
B9: EXP-005 | C9: Moreau Laurent | D9: Consultant IT | E9: France | F9: Cameroun | G9: Mission courte duree | H9: 45689 | I9: 45870 | J9: 3500000 | K9: 400000 | L9: Contrat termine
B10: =IF(C10="","EXP-"&TEXT(COUNTA($C$5:C10),"000"))
B11: =IF(C11="","EXP-"&TEXT(COUNTA($C$5:C11),"000"))
B12: =IF(C12="","EXP-"&TEXT(COUNTA($C$5:C12),"000"))
B13: =IF(C13="","EXP-"&TEXT(COUNTA($C$5:C13),"000"))
B14: =IF(C14="","EXP-"&TEXT(COUNTA($C$5:C14),"000"))
B15: =IF(C15="","EXP-"&TEXT(COUNTA($C$5:C15),"000"))
B16: =IF(C16="","EXP-"&TEXT(COUNTA($C$5:C16),"000"))
B17: =IF(C17="","EXP-"&TEXT(COUNTA($C$5:C17),"000"))
B18: =IF(C18="","EXP-"&TEXT(COUNTA($C$5:C18),"000"))
B19: =IF(C19="","EXP-"&TEXT(COUNTA($C$5:C19),"000"))
B20: =IF(C20="","EXP-"&TEXT(COUNTA($C$5:C20),"000"))
B21: =IF(C21="","EXP-"&TEXT(COUNTA($C$5:C21),"000"))
... B109: =IF(C109="","EXP-"&TEXT(COUNTA($C$5:C109),"000"))
B111: TOTAL | J111: =SUM(J5:J104) | K111: =SUM(K5:K104)
B113: INDICATEURS (mis a jour automatiquement)
B114: Expatries en poste | D114: Masse salariale (M) | F114: Total indem. (M)
B115: =COUNTIF(L5:L104,"En poste") | D115: =IFERROR(SUM(J5:J104)/1000000,0) | F115: =IFERROR(SUM(K5:K104)/1000000,0)

Sheet 12-Suivi Plans Carriere
B2: SUIVI PLANS DE CARRIÈRE — Progression
B3: TABLEAU DYNAMIQUE — Saisissez dans la prochaine ligne jaune. Les calculs se mettent a jour automatiquement.
B4: N° | C4: Employe | D4: Poste Actuel | E4: Objectif Carriere | F4: Echeance | G4: Jours Restants | H4: Etapes Realisees | I4: Etapes Totales | J4: Progression (%) | K4: Statut
B5: SPC-001 | C5: Nkoulou Mbarga P. | D5: Chef Reception | E5: Responsable Front Office | F5: 46022 | H5: 3 | I5: 5 | K5: En cours
B6: SPC-002 | C6: Fotsing Aude R. | D6: Sous-Chef | E6: Chef Cuisine | F6: 46203 | H6: 2 | I6: 4 | K6: En cours
B7: SPC-003 | C7: Tamo Eric | D7: Technicien IT | E7: Chef de service IT | F7: 46112 | H7: 1 | I7: 4 | K7: En elaboration
B8: SPC-004 | C8: Ouedraogo Issa | D8: Agent Commercial | E8: Chef Commercial adjoint | F8: 45930 | H8: 2 | I8: 3 | K8: En cours
B9: =IF(C9="","SPC-"&TEXT(COUNTA($C$5:C9),"000")) | G9: =IF(F9="","",F9-TODAY()) | J9: =IF(OR(H9="",I9=""),"",H9/I9)
B10: =IF(C10="","SPC-"&TEXT(COUNTA($C$5:C10),"000")) | G10: =IF(F10="","",F10-TODAY()) | J10: =IF(OR(H10="",I10=""),"",H10/I10)
B11: =IF(C11="","SPC-"&TEXT(COUNTA($C$5:C11),"000")) | G11: =IF(F11="","",F11-TODAY()) | J11: =IF(OR(H11="",I11=""),"",H11/I11)
B12: =IF(C12="","SPC-"&TEXT(COUNTA($C$5:C12),"000")) | G12: =IF(F12="","",F12-TODAY()) | J12: =IF(OR(H12="",I12=""),"",H12/I12)
B13: =IF(C13="","SPC-"&TEXT(COUNTA($C$5:C13),"000")) | G13: =IF(F13="","",F13-TODAY()) | J13: =IF(OR(H13="",I13=""),"",H13/I13)
B14: =IF(C14="","SPC-"&TEXT(COUNTA($C$5:C14),"000")) | G14: =IF(F14="","",F14-TODAY()) | J14: =IF(OR(H14="",I14=""),"",H14/I14)
B15: =IF(C15="","SPC-"&TEXT(COUNTA($C$5:C15),"000")) | G15: =IF(F15="","",F15-TODAY()) | J15: =IF(OR(H15="",I15=""),"",H15/I15)
B16: =IF(C16="","SPC-"&TEXT(COUNTA($C$5:C16),"000")) | G16: =IF(F16="","",F16-TODAY()) | J16: =IF(OR(H16="",I16=""),"",H16/I16)
B17: =IF(C17="","SPC-"&TEXT(COUNTA($C$5:C17),"000")) | G17: =IF(F17="","",F17-TODAY()) | J17: =IF(OR(H17="",I17=""),"",H17/I17)
B18: =IF(C18="","SPC-"&TEXT(COUNTA($C$5:C18),"000")) | G18: =IF(F18="","",F18-TODAY()) | J18: =IF(OR(H18="",I18=""),"",H18/I18)
B19: =IF(C19="","SPC-"&TEXT(COUNTA($C$5:C19),"000")) | G19: =IF(F19="","",F19-TODAY()) | J19: =IF(OR(H19="",I19=""),"",H19/I19)
B20: =IF(C20="","SPC-"&TEXT(COUNTA($C$5:C20),"000")) | G20: =IF(F20="","",F20-TODAY()) | J20: =IF(OR(H20="",I20=""),"",H20/I20)
... B108: =IF(C108="","SPC-"&TEXT(COUNTA($C$5:C108),"000")) | G108: =IF(F108="","",F108-TODAY()) | J108: =IF(OR(H108="",I108=""),"",H108/I108)
B110: INDICATEURS (mis a jour automatiquement)
B111: Plans suivis | D111: Taux moy. progression | F111: A echeance < 90j
B112: =COUNTIF(B5:B104,"<>") | D112: =IFERROR(AVERAGE(J5:J104),0) | F112: =COUNTIF(G5:G104,"<"&90)

Sheet 13-Taux Mobilite Interne
B2: TAUX DE MOBILITÉ INTERNE — Mensuel
B3: TABLEAU DYNAMIQUE — Saisissez dans la prochaine ligne jaune. Les calculs se mettent a jour automatiquement.
B4: N° | C4: Mois | D4: Annee | E4: Effectif Total | F4: Mouvements Internes | G4: Promotions | H4: Mutations Laterales | I4: Rotations Poste | J4: Taux Mobilite (%)
B5: TMI-001 | C5: Janvier | D5: 2025 | E5: 85 | F5: 3 | G5: 1 | H5: 1 | I5: 1
B6: TMI-002 | C6: Fevrier | D6: 2025 | E6: 87 | F6: 2 | G6: 0 | H6: 1 | I6: 1
B7: TMI-003 | C7: Mars | D7: 2025 | E7: 88 | F7: 4 | G7: 2 | H7: 1 | I7: 1
B8: TMI-004 | C8: Avril | D8: 2025 | E8: 86 | F8: 3 | G8: 1 | H8: 2 | I8: 0
B9: TMI-005 | C9: Mai | D9: 2025 | E9: 89 | F9: 2 | G9: 1 | H9: 0 | I9: 1
B10: =IF(C10="","TMI-"&TEXT(COUNTA($C$5:C10),"000")) | J10: =IF(OR(E10="",E10=0),"",F10/E10)
B11: =IF(C11="","TMI-"&TEXT(COUNTA($C$5:C11),"000")) | J11: =IF(OR(E11="",E11=0),"",F11/E11)
B12: =IF(C12="","TMI-"&TEXT(COUNTA($C$5:C12),"000")) | J12: =IF(OR(E12="",E12=0),"",F12/E12)
B13: =IF(C13="","TMI-"&TEXT(COUNTA($C$5:C13),"000")) | J13: =IF(OR(E13="",E13=0),"",F13/E13)
B14: =IF(C14="","TMI-"&TEXT(COUNTA($C$5:C14),"000")) | J14: =IF(OR(E14="",E14=0),"",F14/E14)
B15: =IF(C15="","TMI-"&TEXT(COUNTA($C$5:C15),"000")) | J15: =IF(OR(E15="",E15=0),"",F15/E15)
B16: =IF(C16="","TMI-"&TEXT(COUNTA($C$5:C16),"000")) | J16: =IF(OR(E16="",E16=0),"",F16/E16)
B17: =IF(C17="","TMI-"&TEXT(COUNTA($C$5:C17),"000")) | J17: =IF(OR(E17="",E17=0),"",F17/E17)
B18: =IF(C18="","TMI-"&TEXT(COUNTA($C$5:C18),"000")) | J18: =IF(OR(E18="",E18=0),"",F18/E18)
B19: =IF(C19="","TMI-"&TEXT(COUNTA($C$5:C19),"000")) | J19: =IF(OR(E19="",E19=0),"",F19/E19)
B20: =IF(C20="","TMI-"&TEXT(COUNTA($C$5:C20),"000")) | J20: =IF(OR(E20="",E20=0),"",F20/E20)
B21: =IF(C21="","TMI-"&TEXT(COUNTA($C$5:C21),"000")) | J21: =IF(OR(E21="",E21=0),"",F21/E21)
... B109: =IF(C109="","TMI-"&TEXT(COUNTA($C$5:C109),"000")) | J109: =IF(OR(E109="",E109=0),"",F109/E109)
B111: INDICATEURS (mis a jour automatiquement)
B112: Moy. mobilite/mois | D112: Total mouvements | F112: Total promotions
B113: =IFERROR(AVERAGE(J5:J104),0) | D113: =SUM(F5:F104) | F113: =SUM(G5:G104)

Sheet 14-Matrice Potentiel 9Box
B2: MATRICE POTENTIEL 9-BOX — Positionnement
B3: TABLEAU DYNAMIQUE — Saisissez dans la prochaine ligne jaune. Les calculs se mettent a jour automatiquement.
B4: N° | C4: Employe | D4: Poste | E4: Departement | F4: Performance | G4: Potentiel | H4: Position 9-Box | I4: Recommandation
B5: 9B-001 | C5: Nkoulou Mbarga P. | D5: Chef Reception | E5: Réception & Front Office | F5: Excellent | G5: Tres eleve | H5: Etoile / Talent cle | I5: Accelerer developpement + promotion rapide
B6: 9B-002 | C6: Tamo Eric | D6: Technicien IT | E6: Informatique | F6: Bon | G6: Tres eleve | H6: Etoile montante | I6: Programme fast-track vers management
B7: 9B-003 | C7: Fotsing Aude R. | D7: Sous-Chef | E7: Cuisine & Restauration | F7: Tres bon | G7: Eleve | H7: Performeur a potentiel | I7: Formation manageriale + responsabilites
B8: 9B-004 | C8: Ouedraogo Issa | D8: Agent Commercial | E8: Commercial | F8: Tres bon | G8: Moyen | H8: Expert dans son domaine | I8: Specialisation + mentorat technique
B9: 9B-005 | C9: Bekolo A. | D9: Agent Entretien | E9: Maintenance | F9: Bon | G9: Eleve | H9: Enorme potentiel non exploite | I9: Mentorat + rotation pour exposition
B10: 9B-006 | C10: Kamga P. | D10: Receptionniste | E10: Réception & Front Office | F10: Moyen | G10: Moyen | H10: Solide contributeur | I10: Maintenir engagement + formations ponctuelles
B11: 9B-007 | C11: Meyong S. | D11: Concierge | E11: Réception & Front Office | F11: Bon | G11: Faible | H11: Performeur stable | I11: Reconnaissances + stabiliser dans le poste
B12: =IF(C12="","9B-"&TEXT(COUNTA($C$5:C12),"000"))
B13: =IF(C13="","9B-"&TEXT(COUNTA($C$5:C13),"000"))
B14: =IF(C14="","9B-"&TEXT(COUNTA($C$5:C14),"000"))
B15: =IF(C15="","9B-"&TEXT(COUNTA($C$5:C15),"000"))
B16: =IF(C16="","9B-"&TEXT(COUNTA($C$5:C16),"000"))
B17: =IF(C17="","9B-"&TEXT(COUNTA($C$5:C17),"000"))
B18: =IF(C18="","9B-"&TEXT(COUNTA($C$5:C18),"000"))
B19: =IF(C19="","9B-"&TEXT(COUNTA($C$5:C19),"000"))
B20: =IF(C20="","9B-"&TEXT(COUNTA($C$5:C20),"000"))
B21: =IF(C21="","9B-"&TEXT(COUNTA($C$5:C21),"000"))
B22: =IF(C22="","9B-"&TEXT(COUNTA($C$5:C22),"000"))
B23: =IF(C23="","9B-"&TEXT(COUNTA($C$5:C23),"000"))
... B111: =IF(C111="","9B-"&TEXT(COUNTA($C$5:C111),"000"))
B113: INDICATEURS (mis a jour automatiquement)
B114: Talents cles | D114: A potentiel eleve | F114: Positionnes
B115: =COUNTIF(H5:H104,"*Talent cle*")+COUNTIF(H5:H104,"*Etoile*") | D115: =COUNTIF(G5:G104,"Eleve")+COUNTIF(G5:G104,"Tres eleve") | F115: =COUNTIF(B5:B104,"<>")

Sheet 15-Historique Mentorat
B2: HISTORIQUE MENTORAT — Bilans
B3: TABLEAU DYNAMIQUE — Saisissez dans la prochaine ligne jaune. Les calculs se mettent a jour automatiquement.
B4: N° | C4: Mentore | D4: Mentor | E4: Type Mentorat | F4: Date Debut | G4: Date Fin | H4: Duree (mois) | I4: Objectif Principal | J4: Statut | K4: Appreciation Globale
B5: HM-001 | C5: Nganou D. | D5: Nkoulou Mbarga P. | E5: Mentorat classique | F5: 45536 | G5: 45716 | H5: 6 | I5: Developper competences supervision | J5: Termine | K5: Tres bon
B6: HM-002 | C6: Fouda M. | D6: Biyong Jean M. | E6: Tutorat | F6: 45566 | G6: 45747 | H6: 6 | I6: Maitrise gestion brigade cuisine | J6: Termine | K6: Bon
B7: HM-003 | C7: Assistante RH Ngo M. | D7: Fotso M. | E7: Coaching | F7: 45717 | I7: Preparation DRH adjoint | J7: En cours
B8: HM-004 | C8: Tamo Eric | D8: Consultant externe | E8: Coaching | F8: 45748 | I8: Certification reseau et cybersecurite | J8: En cours
B9: =IF(C9="","HM-"&TEXT(COUNTA($C$5:C9),"000")) | H9: =IF(OR(F9="",G9="",G9<F9),"",(G9-F9)/30)
B10: =IF(C10="","HM-"&TEXT(COUNTA($C$5:C10),"000")) | H10: =IF(OR(F10="",G10="",G10<F10),"",(G10-F10)/30)
B11: =IF(C11="","HM-"&TEXT(COUNTA($C$5:C11),"000")) | H11: =IF(OR(F11="",G11="",G11<F11),"",(G11-F11)/30)
B12: =IF(C12="","HM-"&TEXT(COUNTA($C$5:C12),"000")) | H12: =IF(OR(F12="",G12="",G12<F12),"",(G12-F12)/30)
B13: =IF(C13="","HM-"&TEXT(COUNTA($C$5:C13),"000")) | H13: =IF(OR(F13="",G13="",G13<F13),"",(G13-F13)/30)
B14: =IF(C14="","HM-"&TEXT(COUNTA($C$5:C14),"000")) | H14: =IF(OR(F14="",G14="",G14<F14),"",(G14-F14)/30)
B15: =IF(C15="","HM-"&TEXT(COUNTA($C$5:C15),"000")) | H15: =IF(OR(F15="",G15="",G15<F15),"",(G15-F15)/30)
B16: =IF(C16="","HM-"&TEXT(COUNTA($C$5:C16),"000")) | H16: =IF(OR(F16="",G16="",G16<F16),"",(G16-F16)/30)
B17: =IF(C17="","HM-"&TEXT(COUNTA($C$5:C17),"000")) | H17: =IF(OR(F17="",G17="",G17<F17),"",(G17-F17)/30)
B18: =IF(C18="","HM-"&TEXT(COUNTA($C$5:C18),"000")) | H18: =IF(OR(F18="",G18="",G18<F18),"",(G18-F18)/30)
B19: =IF(C19="","HM-"&TEXT(COUNTA($C$5:C19),"000")) | H19: =IF(OR(F19="",G19="",G19<F19),"",(G19-F19)/30)
B20: =IF(C20="","HM-"&TEXT(COUNTA($C$5:C20),"000")) | H20: =IF(OR(F20="",G20="",G20<F20),"",(G20-F20)/30)
... B108: =IF(C108="","HM-"&TEXT(COUNTA($C$5:C108),"000")) | H108: =IF(OR(F108="",G108="",G108<F108),"",(G108-F108)/30)
B110: INDICATEURS (mis a jour automatiquement)
B111: Programmes total | D111: Termines | F111: En cours
B112: =COUNTIF(B5:B104,"<>") | D112: =COUNTIF(J5:J104,"Termine") | F112: =COUNTIF(J5:J104,"En cours")

Sheet 16-Indicateurs Retention
B2: INDICATEURS DE RÉTENTION — Mensuel
B3: TABLEAU DYNAMIQUE — Saisissez dans la prochaine ligne jaune. Les calculs se mettent a jour automatiquement.
B4: N° | C4: Mois | D4: Annee | E4: Effectif Debut Mois | F4: Recrutements | G4: Departs Volontaires | H4: Departs Involontaires | I4: Effectif Fin Mois | J4: Taux Rotation (%) | K4: Taux Retention (%)
B5: IR-001 | C5: Janvier | D5: 2025 | E5: 85 | F5: 3 | G5: 1 | H5: 0 | I5: 87
B6: IR-002 | C6: Fevrier | D6: 2025 | E6: 87 | F6: 2 | G6: 0 | H6: 1 | I6: 88
B7: IR-003 | C7: Mars | D7: 2025 | E7: 88 | F7: 4 | G7: 2 | H7: 0 | I7: 90
B8: IR-004 | C8: Avril | D8: 2025 | E8: 90 | F8: 1 | G8: 1 | H8: 0 | I8: 90
B9: IR-005 | C9: Mai | D9: 2025 | E9: 90 | F9: 3 | G9: 1 | H9: 0 | I9: 92
B10: =IF(C10="","IR-"&TEXT(COUNTA($C$5:C10),"000")) | J10: =IF(E10="","",(G10+H10)/E10) | K10: =IF(E10="","",I10/E10)
B11: =IF(C11="","IR-"&TEXT(COUNTA($C$5:C11),"000")) | J11: =IF(E11="","",(G11+H11)/E11) | K11: =IF(E11="","",I11/E11)
B12: =IF(C12="","IR-"&TEXT(COUNTA($C$5:C12),"000")) | J12: =IF(E12="","",(G12+H12)/E12) | K12: =IF(E12="","",I12/E12)
B13: =IF(C13="","IR-"&TEXT(COUNTA($C$5:C13),"000")) | J13: =IF(E13="","",(G13+H13)/E13) | K13: =IF(E13="","",I13/E13)
B14: =IF(C14="","IR-"&TEXT(COUNTA($C$5:C14),"000")) | J14: =IF(E14="","",(G14+H14)/E14) | K14: =IF(E14="","",I14/E14)
B15: =IF(C15="","IR-"&TEXT(COUNTA($C$5:C15),"000")) | J15: =IF(E15="","",(G15+H15)/E15) | K15: =IF(E15="","",I15/E15)
B16: =IF(C16="","IR-"&TEXT(COUNTA($C$5:C16),"000")) | J16: =IF(E16="","",(G16+H16)/E16) | K16: =IF(E16="","",I16/E16)
B17: =IF(C17="","IR-"&TEXT(COUNTA($C$5:C17),"000")) | J17: =IF(E17="","",(G17+H17)/E17) | K17: =IF(E17="","",I17/E17)
B18: =IF(C18="","IR-"&TEXT(COUNTA($C$5:C18),"000")) | J18: =IF(E18="","",(G18+H18)/E18) | K18: =IF(E18="","",I18/E18)
B19: =IF(C19="","IR-"&TEXT(COUNTA($C$5:C19),"000")) | J19: =IF(E19="","",(G19+H19)/E19) | K19: =IF(E19="","",I19/E19)
B20: =IF(C20="","IR-"&TEXT(COUNTA($C$5:C20),"000")) | J20: =IF(E20="","",(G20+H20)/E20) | K20: =IF(E20="","",I20/E20)
B21: =IF(C21="","IR-"&TEXT(COUNTA($C$5:C21),"000")) | J21: =IF(E21="","",(G21+H21)/E21) | K21: =IF(E21="","",I21/E21)
... B109: =IF(C109="","IR-"&TEXT(COUNTA($C$5:C109),"000")) | J109: =IF(E109="","",(G109+H109)/E109) | K109: =IF(E109="","",I109/E109)
B111: INDICATEURS (mis a jour automatiquement)
B112: Taux rot. moyen | D112: Taux ret. moyen | F112: Total departs vol.
B113: =IFERROR(AVERAGE(J5:J104),0) | D113: =IFERROR(AVERAGE(K5:K104),0) | F113: =SUM(G5:G104)

Sheet 17-Calendrier Entretiens
B2: CALENDRIER ENTRETIENS PROFESSIONNELS
B3: TABLEAU DYNAMIQUE — Saisissez dans la prochaine ligne jaune. Les calculs se mettent a jour automatiquement.
B4: N° | C4: Employe | D4: Poste | E4: Departement | F4: Type Entretien | G4: Date Prevue | H4: Date Realisee | I4: Retard (jours) | J4: Evaluateur | K4: Statut
B5: CEP-001 | C5: Nkoulou Mbarga P. | D5: Chef Reception | E5: Réception & Front Office | F5: Annuel | G5: 45672 | H5: 45677 | J5: DRH Fotso M. | K5: Realise
B6: CEP-002 | C6: Fotsing Aude R. | D6: Sous-Chef | E6: Cuisine & Restauration | F6: Annuel | G6: 45677 | H6: 45679 | J6: Chef Cuisine Biyong J. | K6: Realise
B7: CEP-003 | C7: Tamo Eric | D7: Technicien IT | E7: Informatique | F7: Semestriel | G7: 45726 | H7: 45731 | J7: DSI externe | K7: Realise
B8: CEP-004 | C8: Ouedraogo Issa | D8: Agent Commercial | E8: Commercial | F8: Annuel | G8: 45809 | J8: Chef Commercial Manga S. | K8: Planifie
B9: CEP-005 | C9: Nganou D. | D9: Receptionniste | E9: Réception & Front Office | F9: Semestriel | G9: 45748 | H9: 45752 | J9: Chef Reception Nkoulou P. | K9: Realise
B10: =IF(C10="","CEP-"&TEXT(COUNTA($C$5:C10),"000")) | I10: =IF(OR(H10="",G10=""),"",H10-G10)
B11: =IF(C11="","CEP-"&TEXT(COUNTA($C$5:C11),"000")) | I11: =IF(OR(H11="",G11=""),"",H11-G11)
B12: =IF(C12="","CEP-"&TEXT(COUNTA($C$5:C12),"000")) | I12: =IF(OR(H12="",G12=""),"",H12-G12)
B13: =IF(C13="","CEP-"&TEXT(COUNTA($C$5:C13),"000")) | I13: =IF(OR(H13="",G13=""),"",H13-G13)
B14: =IF(C14="","CEP-"&TEXT(COUNTA($C$5:C14),"000")) | I14: =IF(OR(H14="",G14=""),"",H14-G14)
B15: =IF(C15="","CEP-"&TEXT(COUNTA($C$5:C15),"000")) | I15: =IF(OR(H15="",G15=""),"",H15-G15)
B16: =IF(C16="","CEP-"&TEXT(COUNTA($C$5:C16),"000")) | I16: =IF(OR(H16="",G16=""),"",H16-G16)
B17: =IF(C17="","CEP-"&TEXT(COUNTA($C$5:C17),"000")) | I17: =IF(OR(H17="",G17=""),"",H17-G17)
B18: =IF(C18="","CEP-"&TEXT(COUNTA($C$5:C18),"000")) | I18: =IF(OR(H18="",G18=""),"",H18-G18)
B19: =IF(C19="","CEP-"&TEXT(COUNTA($C$5:C19),"000")) | I19: =IF(OR(H19="",G19=""),"",H19-G19)
B20: =IF(C20="","CEP-"&TEXT(COUNTA($C$5:C20),"000")) | I20: =IF(OR(H20="",G20=""),"",H20-G20)
B21: =IF(C21="","CEP-"&TEXT(COUNTA($C$5:C21),"000")) | I21: =IF(OR(H21="",G21=""),"",H21-G21)
... B109: =IF(C109="","CEP-"&TEXT(COUNTA($C$5:C109),"000")) | I109: =IF(OR(H109="",G109=""),"",H109-G109)
B111: INDICATEURS (mis a jour automatiquement)
B112: Entretiens total | D112: Realises | F112: En retard
B113: =COUNTIF(B5:B104,"<>") | D113: =COUNTIF(K5:K104,"Realise") | F113: =COUNTIF(I5:I104,">"&0)

Sheet 18-Suivi Successeurs
B2: SUIVI SUCCESSEURS — Indicateurs de Relève
B3: TABLEAU DYNAMIQUE — Saisissez dans la prochaine ligne jaune. Les calculs se mettent a jour automatiquement.
B4: N° | C4: Poste Cle | D4: Titulaire | E4: Age Titulaire | F4: Anciennete Titulaire (ans) | G4: Successeur | H4: Niveau de Pret | I4: Annees Prev. Depart | J4: Urgence Relève | K4: Statut
B5: SS-001 | C5: Chef Reception | D5: Nkoulou Mbarga P. | E5: 34 | F5: 6 | G5: Nganou D. | H5: En formation | I5: 5 | J5: Moyenne | K5: En formation
B6: SS-002 | C6: Chef Cuisine | D6: Biyong Jean M. | E6: 48 | F6: 12 | G6: Fotsing Aude R. | H6: En formation | I6: 3 | J6: Haute | K6: En formation
B7: SS-003 | C7: DRH | D7: Fotso M. | E7: 52 | F7: 8 | G7: Assistante RH Ngo M. | H7: Candidat identifie | I7: 2 | J7: Haute | K7: Candidat identifie
B8: SS-004 | C8: Chef Entretien | D8: Tchinda P. | E8: 45 | F8: 10 | G8: Fokam Ernest | H8: En evaluation | I8: 4 | J8: Moyenne | K8: En evaluation
B9: SS-005 | C9: Chef Securite | D9: Nganmeni J. | E9: 40 | F9: 7 | G9: Wouamba A. | H9: En formation | I9: 5 | J9: Moyenne | K9: En formation
B10: =IF(C10="","SS-"&TEXT(COUNTA($C$5:C10),"000"))
B11: =IF(C11="","SS-"&TEXT(COUNTA($C$5:C11),"000"))
B12: =IF(C12="","SS-"&TEXT(COUNTA($C$5:C12),"000"))
B13: =IF(C13="","SS-"&TEXT(COUNTA($C$5:C13),"000"))
B14: =IF(C14="","SS-"&TEXT(COUNTA($C$5:C14),"000"))
B15: =IF(C15="","SS-"&TEXT(COUNTA($C$5:C15),"000"))
B16: =IF(C16="","SS-"&TEXT(COUNTA($C$5:C16),"000"))
B17: =IF(C17="","SS-"&TEXT(COUNTA($C$5:C17),"000"))
B18: =IF(C18="","SS-"&TEXT(COUNTA($C$5:C18),"000"))
B19: =IF(C19="","SS-"&TEXT(COUNTA($C$5:C19),"000"))
B20: =IF(C20="","SS-"&TEXT(COUNTA($C$5:C20),"000"))
B21: =IF(C21="","SS-"&TEXT(COUNTA($C$5:C21),"000"))
... B109: =IF(C109="","SS-"&TEXT(COUNTA($C$5:C109),"000"))
B111: INDICATEURS (mis a jour automatiquement)
B112: Postes cles | D112: Urgence haute | F112: Prets / Nommes
B113: =COUNTIF(B5:B104,"<>") | D113: =COUNTIF(J5:J104,"Haute") | F113: =COUNTIF(K5:K104,"Pret")+COUNTIF(K5:K104,"Nomme")

Sheet 19-Analyse Ecarts Compet.
B2: ANALYSE ÉCARTS DE COMPÉTENCES — Par Département
B3: TABLEAU DYNAMIQUE — Saisissez dans la prochaine ligne jaune. Les calculs se mettent a jour automatiquement.
B4: N° | C4: Departement | D4: Competence Critique | E4: Niveau Moyen Actuel | F4: Niveau Cible | G4: Ecart Moyen | H4: Nb Employes Evalues | I4: Nb Acquis | J4: Nb A Developper | K4: Taux Couverture (%)
B5: AEC-001 | C5: Réception & Front Office | D5: Revenue Management | E5: 2.2 | F5: 4 | H5: 5 | I5: 2 | J5: 3
B6: AEC-002 | C6: Cuisine & Restauration | D6: Gestion budget cuisine | E6: 1.8 | F6: 4 | H6: 4 | I6: 0 | J6: 4
B7: AEC-003 | C7: Informatique | D7: Cybersecurite | E7: 2.5 | F7: 4 | H7: 3 | I7: 0 | J7: 3
B8: AEC-004 | C8: Commercial | D8: Anglais hotelier | E8: 1.5 | F8: 3 | H8: 4 | I8: 0 | J8: 4
B9: AEC-005 | C9: Maintenance | D9: Technique CVC | E9: 2.8 | F9: 4 | H9: 3 | I9: 1 | J9: 2
B10: =IF(C10="","AEC-"&TEXT(COUNTA($C$5:C10),"000")) | G10: =IF(OR(E10="",F10=""),"",E10-F10) | K10: =IF(H10="", "",I10/H10)
B11: =IF(C11="","AEC-"&TEXT(COUNTA($C$5:C11),"000")) | G11: =IF(OR(E11="",F11=""),"",E11-F11) | K11: =IF(H11="", "",I11/H11)
B12: =IF(C12="","AEC-"&TEXT(COUNTA($C$5:C12),"000")) | G12: =IF(OR(E12="",F12=""),"",E12-F12) | K12: =IF(H12="", "",I12/H12)
B13: =IF(C13="","AEC-"&TEXT(COUNTA($C$5:C13),"000")) | G13: =IF(OR(E13="",F13=""),"",E13-F13) | K13: =IF(H13="", "",I13/H13)
B14: =IF(C14="","AEC-"&TEXT(COUNTA($C$5:C14),"000")) | G14: =IF(OR(E14="",F14=""),"",E14-F14) | K14: =IF(H14="", "",I14/H14)
B15: =IF(C15="","AEC-"&TEXT(COUNTA($C$5:C15),"000")) | G15: =IF(OR(E15="",F15=""),"",E15-F15) | K15: =IF(H15="", "",I15/H15)
B16: =IF(C16="","AEC-"&TEXT(COUNTA($C$5:C16),"000")) | G16: =IF(OR(E16="",F16=""),"",E16-F16) | K16: =IF(H16="", "",I16/H16)
B17: =IF(C17="","AEC-"&TEXT(COUNTA($C$5:C17),"000")) | G17: =IF(OR(E17="",F17=""),"",E17-F17) | K17: =IF(H17="", "",I17/H17)
B18: =IF(C18="","AEC-"&TEXT(COUNTA($C$5:C18),"000")) | G18: =IF(OR(E18="",F18=""),"",E18-F18) | K18: =IF(H18="", "",I18/H18)
B19: =IF(C19="","AEC-"&TEXT(COUNTA($C$5:C19),"000")) | G19: =IF(OR(E19="",F19=""),"",E19-F19) | K19: =IF(H19="", "",I19/H19)
B20: =IF(C20="","AEC-"&TEXT(COUNTA($C$5:C20),"000")) | G20: =IF(OR(E20="",F20=""),"",E20-F20) | K20: =IF(H20="", "",I20/H20)
B21: =IF(C21="","AEC-"&TEXT(COUNTA($C$5:C21),"000")) | G21: =IF(OR(E21="",F21=""),"",E21-F21) | K21: =IF(H21="", "",I21/H21)
... B109: =IF(C109="","AEC-"&TEXT(COUNTA($C$5:C109),"000")) | G109: =IF(OR(E109="",F109=""),"",E109-F109) | K109: =IF(H109="", "",I109/H109)
B111: TOTAL | H111: =SUM(H5:H104) | I111: =SUM(I5:I104) | J111: =SUM(J5:J104)
B113: INDICATEURS (mis a jour automatiquement)
B114: Competences critiques | D114: Ecart moy. global | F114: Taux couv. moyen
B115: =COUNTIF(B5:B104,"<>") | D115: =IFERROR(AVERAGE(G5:G104),0) | F115: =IFERROR(AVERAGE(K5:K104),0)
