Workbook

Sheet _Données Employés
B4: Matricule | C4: Civilité | D4: Nom | E4: Prénom | F4: Département | G4: Poste | H4: Salaire Base (FCFA)
B5: EMP-001 | C5: M. | D5: Nganou | E5: Clarisse | F5: Cuisine & Restauration | G5: Chef cuisinier | H5: 450000
B6: EMP-002 | C6: M. | D6: Tchinda | E6: Armand | F6: Réception & Front Office | G6: Réceptionniste | H6: 220000
B7: EMP-003 | C7: Mme | D7: Fotso | E7: Marguerite | F7: Finance & Comptabilité | G7: Comptable senior | H7: 380000
B8: EMP-004 | C8: M. | D8: Nkoulou | E8: Mbarga | F8: Étage & Housekeeping | G8: Gouvernant | H8: 195000
B9: EMP-005 | C9: M. | D9: Kamga | E9: Paul | F9: Maintenance | G9: Technicien maintenance | H9: 165000
B10: EMP-006 | C10: Mme | D10: Ngo | E10: Delphine | F10: Service Client | G10: Conseiller clientèle | H10: 160000
B11: EMP-007 | C11: M. | D11: Essomba | E11: Serge | F11: Maintenance | G11: Agent entretien | H11: 130000
B12: EMP-008 | C12: M. | D12: Tchouankou | E12: Paul | F12: Commercial | G12: Commercial | H12: 150000
B13: EMP-009 | C13: M. | D13: Fokam | E13: Eric | F13: Maintenance | G13: Technicien | H13: 140000
B14: EMP-010 | C14: M. | D14: Tagne | E14: René | F14: Cuisine & Restauration | G14: Plongeur | H14: 90000
B15: EMP-011 | C15: M. | D15: Bouba | E15: Ahmed | F15: Sécurité | G15: Agent Sécurité | H15: 120000
B16: EMP-012 | C16: Mme | D16: Awa | E16: Fatou | F16: Réception & Front Office | G16: Standardiste | H16: 155000
... B18: EMP-029 | C18: M. | D18: Kamga | E18: Patrice | F18: Sécurité | G18: Chef Sécurité | H18: 210000

Sheet 1-Tableau de Bord
B2: DOMAINE 14 — REPORTING, TABLEAUX DE BORD & ANALYSE
B3: TABLEAU DE BORD — Vue synthetique de tous les indicateurs du domaine (mis a jour automatiquement)
B5: Effectif total | E5: Masse salariale (M) | H5: Cout turnover | K5: Delai recrut. moyen
B6: =IFERROR(SUM('4-Pyramide des Ages'!F5:F9),0) | E6: =IFERROR(SUM('8-Analyse Masse Salariale'!J5:J10)/1000000,0) | H6: =IFERROR(SUM('6-Cout du Turnover'!L5:L8)/1000000,0) | K6: =IFERROR(AVERAGE('7-Delai Recrutement'!J5:J8),0)
B9: Turnover YTD | E9: Ratio MS/CA moyen | H9: Satisfaction client moy. | K9: Indicateurs previsionnels
B10: =IFERROR(AVERAGE('5-Analyse Turnover'!I5:I10),0) | E10: =IFERROR(AVERAGE('9-Ratio Masse Salariale CA'!F5:F10),0) | H10: =IFERROR(AVERAGE('14-Enquetes Sat. Client Eff.'!E5:E10),0) | K10: =COUNTIF('12-TdB Previsionnel RH'!B5:B104,"<>")
B14: MASSE SALARIALE PAR MOIS & EFFECTIF PAR SERVICE
B15: Mois | C15: Masse Salariale (M FCFA)
B16: Janvier | C16: =IFERROR(INDEX('8-Analyse Masse Salariale'!J:J,MATCH("Janvier",'8-Analyse Masse Salariale'!C:C,0)),0)/1000000
B17: Fevrier | C17: =IFERROR(INDEX('8-Analyse Masse Salariale'!J:J,MATCH("Fevrier",'8-Analyse Masse Salariale'!C:C,0)),0)/1000000
B18: Mars | C18: =IFERROR(INDEX('8-Analyse Masse Salariale'!J:J,MATCH("Mars",'8-Analyse Masse Salariale'!C:C,0)),0)/1000000
B19: Avril | C19: =IFERROR(INDEX('8-Analyse Masse Salariale'!J:J,MATCH("Avril",'8-Analyse Masse Salariale'!C:C,0)),0)/1000000
B20: Mai | C20: =IFERROR(INDEX('8-Analyse Masse Salariale'!J:J,MATCH("Mai",'8-Analyse Masse Salariale'!C:C,0)),0)/1000000
B21: Juin | C21: =IFERROR(INDEX('8-Analyse Masse Salariale'!J:J,MATCH("Juin",'8-Analyse Masse Salariale'!C:C,0)),0)/1000000
H23: Service | I23: Effectif
H24: Direction Generale | I24: =IFERROR(INDEX('3-TdB par Service'!D:D,MATCH("Direction Generale",'3-TdB par Service'!C:C,0)),0)
H25: Service Client | I25: =IFERROR(INDEX('3-TdB par Service'!D:D,MATCH("Service Client",'3-TdB par Service'!C:C,0)),0)
H26: Réception & Front Office | I26: =IFERROR(INDEX('3-TdB par Service'!D:D,MATCH("Réception & Front Office",'3-TdB par Service'!C:C,0)),0)
H27: Cuisine & Restauration | I27: =IFERROR(INDEX('3-TdB par Service'!D:D,MATCH("Cuisine & Restauration",'3-TdB par Service'!C:C,0)),0)
H28: Maintenance | I28: =IFERROR(INDEX('3-TdB par Service'!D:D,MATCH("Maintenance",'3-TdB par Service'!C:C,0)),0)
H29: Sécurité | I29: =IFERROR(INDEX('3-TdB par Service'!D:D,MATCH("Sécurité",'3-TdB par Service'!C:C,0)),0)

Sheet _Lists
B1: departement | C1: poste_hotel | D1: categorie_pro | E1: genre | F1: mois | G1: annee | H1: tranche_age | I1: type_indicateur | J1: statut_rapport | K1: statut_benchmark | L1: motif_depart | M1: statut_recrutement | N1: source_candidat | O1: statut_action | P1: tendance | Q1: unite_indicateur | R1: positionnement
B2: Direction Générale | C2: DG | D2: Cadre dirigeant | E2: Homme | F2: Janvier | G2: 2024 | H2: 18-25 ans | I2: Effectif | J2: En cours | K2: En cours | L2: Demission | M2: En cours | N2: Candidature spontanee | O2: Planifiee | P2: Hausse | Q2: % | R2: Au-dessus
B3: Service Client | C3: DRH | D3: Cadre | E3: Femme | F3: Fevrier | G3: 2025 | H3: 26-35 ans | I3: Turnover | J3: Termine | K3: Termine | L3: Licenciement | M3: Pourvu | N3: Site emploi | O3: En cours | P3: Baisse | Q3: FCFA | R3: Dans la moyenne
B4: Finance & Comptabilité | C4: Assistante RH | D4: Agent de maitrise | F4: Mars | G4: 2026 | H4: 36-45 ans | I4: Absentéisme | J4: En attente validation | K4: En attente donnees | L4: Fin CDD | M4: Annule | N4: Recommandation | O4: Terminee | P4: Stable | Q4: M FCFA | R4: En dessous
B5: Marketing & Communication | C5: DAF | D5: Employe | F5: Avril | H5: 46-55 ans | I5: Formation | J5: Valide | K5: Non comparable | L5: Depart retraite | M5: Reporte | N5: Reseau social | O5: Reportee | Q5: jours | R5: Leader
B6: Maintenance | C6: Comptable senior | D6: Stagiaire | F6: Mai | H6: 56 ans et + | I6: Paie | J6: Diffuse | K6: Differe | L6: Mutation interne | M6: En attente validation | N6: Presse | O6: Annulee | Q6: heures | R6: Très en dessous
B7: Commercial | C7: Chef Comptable | F7: Juin | I7: Recrutement | J7: Archive | L7: Resiliation amiable | N7: Cabinet recrutement | Q7: heures/employé/an
B8: Logistique & Approvisionnement | C8: Chef Marketing | F8: Juillet | I8: Performance | L8: Abandon de poste | N8: Interne (promotion) | Q8: ratio
B9: Cuisine & Restauration | C9: Chef de service IT | F9: Aout | I9: Cout RH | L9: Autre | N9: Autre | Q9: note /5
B10: Réception & Front Office | C10: Technicien IT | F10: Septembre | I10: Satisfaction | Q10: note /10
B11: Sécurité | C11: Chef Commercial | F11: Octobre | I11: Conformite | Q11: nb
B12: Étage & Housekeeping | C12: Agent Commercial | F12: Novembre | I12: Diversite
C13: Chef Logistique | F13: Decembre | I13: Autre
C14: Magasinier
C15: Chef Reception
C16: Receptionniste
C17: Concierge
C18: Chef Cuisine
C19: Sous-Chef
C20: Cuisinier
C21: Plongeur
C22: Chef Entretien
C23: Agent Entretien
C24: Chef Securite
C25: Agent Securite

Sheet 2-TdB RH Mensuel DG
B2: TdB RH MENSUEL — DIRECTION GENERALE (#136)
B3: TABLEAU DYNAMIQUE — Saisissez dans la prochaine ligne jaune. Les calculs se mettent a jour automatiquement.
B4: N° | C4: Indicateur | D4: Type Indicateur | E4: Mois | F4: Annee | G4: Valeur | H4: Objectif | I4: Ecart | J4: Tendance | K4: Statut
B5: TDB-001 | C5: Effectif total | D5: Effectif | E5: Juin | F5: 2025 | G5: 89 | H5: 92 | K5: En cours
B6: TDB-002 | C6: Taux turnover mensuel | D6: Turnover | E6: Juin | F6: 2025 | G6: 0.022 | H6: 0.025 | K6: En cours
B7: TDB-003 | C7: Taux absentéisme | D7: Absentéisme | E7: Juin | F7: 2025 | G7: 0.038 | H7: 0.03 | K7: En cours
B8: TDB-004 | C8: Heures formation / employe | D8: Formation | E8: Juin | F8: 2025 | G8: 4.5 | H8: 6 | K8: En cours
B9: TDB-005 | C9: Masse salariale (M FCFA) | D9: Paie | E9: Juin | F9: 2025 | G9: 28.5 | H9: 30 | K9: En cours
B10: TDB-006 | C10: Delai moyen recrutement (j) | D10: Recrutement | E10: Juin | F10: 2025 | G10: 28 | H10: 21 | K10: En cours
B11: TDB-007 | C11: Nb postes vacants | D11: Recrutement | E11: Juin | F11: 2025 | G11: 4 | H11: 2 | K11: En cours
B12: TDB-008 | C12: Taux satisfaction employes | D12: Satisfaction | E12: Juin | F12: 2025 | G12: 0.72 | H12: 0.8 | K12: En cours
B13: =IF(C13="","TDB-"&TEXT(COUNTA($C$5:C13),"000")) | I13: =IF(OR(G13="",H13=""),"",H13-G13)
B14: =IF(C14="","TDB-"&TEXT(COUNTA($C$5:C14),"000")) | I14: =IF(OR(G14="",H14=""),"",H14-G14)
B15: =IF(C15="","TDB-"&TEXT(COUNTA($C$5:C15),"000")) | I15: =IF(OR(G15="",H15=""),"",H15-G15)
B16: =IF(C16="","TDB-"&TEXT(COUNTA($C$5:C16),"000")) | I16: =IF(OR(G16="",H16=""),"",H16-G16)
B17: =IF(C17="","TDB-"&TEXT(COUNTA($C$5:C17),"000")) | I17: =IF(OR(G17="",H17=""),"",H17-G17)
B18: =IF(C18="","TDB-"&TEXT(COUNTA($C$5:C18),"000")) | I18: =IF(OR(G18="",H18=""),"",H18-G18)
B19: =IF(C19="","TDB-"&TEXT(COUNTA($C$5:C19),"000")) | I19: =IF(OR(G19="",H19=""),"",H19-G19)
B20: =IF(C20="","TDB-"&TEXT(COUNTA($C$5:C20),"000")) | I20: =IF(OR(G20="",H20=""),"",H20-G20)
B21: =IF(C21="","TDB-"&TEXT(COUNTA($C$5:C21),"000")) | I21: =IF(OR(G21="",H21=""),"",H21-G21)
B22: =IF(C22="","TDB-"&TEXT(COUNTA($C$5:C22),"000")) | I22: =IF(OR(G22="",H22=""),"",H22-G22)
B23: =IF(C23="","TDB-"&TEXT(COUNTA($C$5:C23),"000")) | I23: =IF(OR(G23="",H23=""),"",H23-G23)
B24: =IF(C24="","TDB-"&TEXT(COUNTA($C$5:C24),"000")) | I24: =IF(OR(G24="",H24=""),"",H24-G24)
... B112: =IF(C112="","TDB-"&TEXT(COUNTA($C$5:C112),"000")) | I112: =IF(OR(G112="",H112=""),"",H112-G112)
B114: INDICATEURS (mis a jour automatiquement)
B115: Indicateurs suivis | D115: Objectifs atteints
B116: =COUNTIF(B5:B104,"<>") | D116: =COUNTIF(K5:K104,"Atteint")+COUNTIF(K5:K104,"Depasse")

Sheet 3-TdB par Service
B2: TdB PAR SERVICE (#137)
B3: TABLEAU DYNAMIQUE — Saisissez dans la prochaine ligne jaune. Les calculs se mettent a jour automatiquement.
B4: N° | C4: Service | D4: Effectif | E4: Hommes | F4: Femmes | G4: Cadres | H4: Masse Salariale (FCFA) | I4: Nb Depart Mois | J4: Nb Entrees Mois | K4: Taux Absenteisme (%) | L4: Statut
B5: SVR-001 | C5: Direction Generale | D5: 4 | E5: 3 | F5: 1 | G5: 4 | H5: 3200000 | I5: 0 | J5: 0 | K5: 0.01 | L5: En cours
B6: SVR-002 | C6: Service Client | D6: 3 | E6: 1 | F6: 2 | G6: 2 | H6: 1050000 | I6: 0 | J6: 1 | K6: 0.02 | L6: En cours
B7: SVR-003 | C7: Réception & Front Office | D7: 14 | E7: 6 | F7: 8 | G7: 3 | H7: 3150000 | I7: 1 | J7: 2 | K7: 0.045 | L7: En cours
B8: SVR-004 | C8: Cuisine & Restauration | D8: 22 | E8: 15 | F8: 7 | G8: 4 | H8: 4950000 | I8: 2 | J8: 1 | K8: 0.05 | L8: En cours
B9: SVR-005 | C9: Maintenance | D9: 10 | E9: 8 | F9: 2 | G9: 2 | H9: 2100000 | I9: 0 | J9: 0 | K9: 0.03 | L9: En cours
B10: =IF(C10="","SVR-"&TEXT(COUNTA($C$5:C10),"000"))
B11: =IF(C11="","SVR-"&TEXT(COUNTA($C$5:C11),"000"))
B12: =IF(C12="","SVR-"&TEXT(COUNTA($C$5:C12),"000"))
B13: =IF(C13="","SVR-"&TEXT(COUNTA($C$5:C13),"000"))
B14: =IF(C14="","SVR-"&TEXT(COUNTA($C$5:C14),"000"))
B15: =IF(C15="","SVR-"&TEXT(COUNTA($C$5:C15),"000"))
B16: =IF(C16="","SVR-"&TEXT(COUNTA($C$5:C16),"000"))
B17: =IF(C17="","SVR-"&TEXT(COUNTA($C$5:C17),"000"))
B18: =IF(C18="","SVR-"&TEXT(COUNTA($C$5:C18),"000"))
B19: =IF(C19="","SVR-"&TEXT(COUNTA($C$5:C19),"000"))
B20: =IF(C20="","SVR-"&TEXT(COUNTA($C$5:C20),"000"))
B21: =IF(C21="","SVR-"&TEXT(COUNTA($C$5:C21),"000"))
... B109: =IF(C109="","SVR-"&TEXT(COUNTA($C$5:C109),"000"))
B111: TOTAL | D111: =SUM(D5:D104) | E111: =SUM(E5:E104) | F111: =SUM(F5:F104) | G111: =SUM(G5:G104) | H111: =SUM(H5:H104) | I111: =SUM(I5:I104) | J111: =SUM(J5:J104)
B113: INDICATEURS (mis a jour automatiquement)
B114: Services | D114: Effectif total | F114: Masse salariale
B115: =COUNTIF(B5:B104,"<>") | D115: =SUM(D5:D104) | F115: =SUM(H5:H104)

Sheet 4-Pyramide des Ages
B2: PYRAMIDE DES AGES & DEMOGRAPHIE (#138)
B3: TABLEAU DYNAMIQUE — Saisissez dans la prochaine ligne jaune. Les calculs se mettent a jour automatiquement.
B4: N° | C4: Tranche d'Age | D4: Hommes | E4: Femmes | F4: Total | G4: % Total | H4: Nb Cadres | I4: Anciennete Moy. (ans)
B5: PAM-001 | C5: 18-25 ans | D5: 8 | E5: 10 | F5: 18 | H5: 1 | I5: 1.2
B6: PAM-002 | C6: 26-35 ans | D6: 22 | E6: 18 | F6: 40 | H6: 8 | I6: 4.5
B7: PAM-003 | C7: 36-45 ans | D7: 12 | E7: 6 | F7: 18 | H7: 5 | I7: 10.3
B8: PAM-004 | C8: 46-55 ans | D8: 5 | E8: 3 | F8: 8 | H8: 2 | I8: 18.7
B9: PAM-005 | C9: 56 ans et + | D9: 3 | E9: 2 | F9: 5 | H9: 1 | I9: 25
B10: =IF(C10="","PAM-"&TEXT(COUNTA($C$5:C10),"000")) | F10: =D10+E10 | G10: =IF(F10="","",IF(SUM(F5:F104)=0,"",F10/SUM(F5:F104)))
B11: =IF(C11="","PAM-"&TEXT(COUNTA($C$5:C11),"000")) | F11: =D11+E11 | G11: =IF(F11="","",IF(SUM(F5:F104)=0,"",F11/SUM(F5:F104)))
B12: =IF(C12="","PAM-"&TEXT(COUNTA($C$5:C12),"000")) | F12: =D12+E12 | G12: =IF(F12="","",IF(SUM(F5:F104)=0,"",F12/SUM(F5:F104)))
B13: =IF(C13="","PAM-"&TEXT(COUNTA($C$5:C13),"000")) | F13: =D13+E13 | G13: =IF(F13="","",IF(SUM(F5:F104)=0,"",F13/SUM(F5:F104)))
B14: =IF(C14="","PAM-"&TEXT(COUNTA($C$5:C14),"000")) | F14: =D14+E14 | G14: =IF(F14="","",IF(SUM(F5:F104)=0,"",F14/SUM(F5:F104)))
B15: =IF(C15="","PAM-"&TEXT(COUNTA($C$5:C15),"000")) | F15: =D15+E15 | G15: =IF(F15="","",IF(SUM(F5:F104)=0,"",F15/SUM(F5:F104)))
B16: =IF(C16="","PAM-"&TEXT(COUNTA($C$5:C16),"000")) | F16: =D16+E16 | G16: =IF(F16="","",IF(SUM(F5:F104)=0,"",F16/SUM(F5:F104)))
B17: =IF(C17="","PAM-"&TEXT(COUNTA($C$5:C17),"000")) | F17: =D17+E17 | G17: =IF(F17="","",IF(SUM(F5:F104)=0,"",F17/SUM(F5:F104)))
B18: =IF(C18="","PAM-"&TEXT(COUNTA($C$5:C18),"000")) | F18: =D18+E18 | G18: =IF(F18="","",IF(SUM(F5:F104)=0,"",F18/SUM(F5:F104)))
B19: =IF(C19="","PAM-"&TEXT(COUNTA($C$5:C19),"000")) | F19: =D19+E19 | G19: =IF(F19="","",IF(SUM(F5:F104)=0,"",F19/SUM(F5:F104)))
B20: =IF(C20="","PAM-"&TEXT(COUNTA($C$5:C20),"000")) | F20: =D20+E20 | G20: =IF(F20="","",IF(SUM(F5:F104)=0,"",F20/SUM(F5:F104)))
B21: =IF(C21="","PAM-"&TEXT(COUNTA($C$5:C21),"000")) | F21: =D21+E21 | G21: =IF(F21="","",IF(SUM(F5:F104)=0,"",F21/SUM(F5:F104)))
B22: =IF(C22="","PAM-"&TEXT(COUNTA($C$5:C22),"000")) | F22: =D22+E22 | G22: =IF(F22="","",IF(SUM(F5:F104)=0,"",F22/SUM(F5:F104)))
B23: =IF(C23="","PAM-"&TEXT(COUNTA($C$5:C23),"000")) | F23: =D23+E23 | G23: =IF(F23="","",IF(SUM(F5:F104)=0,"",F23/SUM(F5:F104)))
B24: =IF(C24="","PAM-"&TEXT(COUNTA($C$5:C24),"000")) | F24: =D24+E24 | G24: =IF(F24="","",IF(SUM(F5:F104)=0,"",F24/SUM(F5:F104)))
B25: =IF(C25="","PAM-"&TEXT(COUNTA($C$5:C25),"000")) | F25: =D25+E25 | G25: =IF(F25="","",IF(SUM(F5:F104)=0,"",F25/SUM(F5:F104)))
B26: =IF(C26="","PAM-"&TEXT(COUNTA($C$5:C26),"000")) | F26: =D26+E26 | G26: =IF(F26="","",IF(SUM(F5:F104)=0,"",F26/SUM(F5:F104)))
B27: =IF(C27="","PAM-"&TEXT(COUNTA($C$5:C27),"000")) | F27: =D27+E27 | G27: =IF(F27="","",IF(SUM(F5:F104)=0,"",F27/SUM(F5:F104)))
B28: =IF(C28="","PAM-"&TEXT(COUNTA($C$5:C28),"000")) | F28: =D28+E28 | G28: =IF(F28="","",IF(SUM(F5:F104)=0,"",F28/SUM(F5:F104)))
B29: =IF(C29="","PAM-"&TEXT(COUNTA($C$5:C29),"000")) | F29: =D29+E29 | G29: =IF(F29="","",IF(SUM(F5:F104)=0,"",F29/SUM(F5:F104)))
B30: =IF(C30="","PAM-"&TEXT(COUNTA($C$5:C30),"000")) | F30: =D30+E30 | G30: =IF(F30="","",IF(SUM(F5:F104)=0,"",F30/SUM(F5:F104)))
B31: =IF(C31="","PAM-"&TEXT(COUNTA($C$5:C31),"000")) | F31: =D31+E31 | G31: =IF(F31="","",IF(SUM(F5:F104)=0,"",F31/SUM(F5:F104)))
B32: =IF(C32="","PAM-"&TEXT(COUNTA($C$5:C32),"000")) | F32: =D32+E32 | G32: =IF(F32="","",IF(SUM(F5:F104)=0,"",F32/SUM(F5:F104)))
B33: =IF(C33="","PAM-"&TEXT(COUNTA($C$5:C33),"000")) | F33: =D33+E33 | G33: =IF(F33="","",IF(SUM(F5:F104)=0,"",F33/SUM(F5:F104)))
B34: =IF(C34="","PAM-"&TEXT(COUNTA($C$5:C34),"000")) | F34: =D34+E34 | G34: =IF(F34="","",IF(SUM(F5:F104)=0,"",F34/SUM(F5:F104)))
B35: =IF(C35="","PAM-"&TEXT(COUNTA($C$5:C35),"000")) | F35: =D35+E35 | G35: =IF(F35="","",IF(SUM(F5:F104)=0,"",F35/SUM(F5:F104)))
B36: =IF(C36="","PAM-"&TEXT(COUNTA($C$5:C36),"000")) | F36: =D36+E36 | G36: =IF(F36="","",IF(SUM(F5:F104)=0,"",F36/SUM(F5:F104)))
B37: =IF(C37="","PAM-"&TEXT(COUNTA($C$5:C37),"000")) | F37: =D37+E37 | G37: =IF(F37="","",IF(SUM(F5:F104)=0,"",F37/SUM(F5:F104)))
B38: =IF(C38="","PAM-"&TEXT(COUNTA($C$5:C38),"000")) | F38: =D38+E38 | G38: =IF(F38="","",IF(SUM(F5:F104)=0,"",F38/SUM(F5:F104)))
B39: =IF(C39="","PAM-"&TEXT(COUNTA($C$5:C39),"000")) | F39: =D39+E39 | G39: =IF(F39="","",IF(SUM(F5:F104)=0,"",F39/SUM(F5:F104)))
B40: =IF(C40="","PAM-"&TEXT(COUNTA($C$5:C40),"000")) | F40: =D40+E40 | G40: =IF(F40="","",IF(SUM(F5:F104)=0,"",F40/SUM(F5:F104)))
B41: =IF(C41="","PAM-"&TEXT(COUNTA($C$5:C41),"000")) | F41: =D41+E41 | G41: =IF(F41="","",IF(SUM(F5:F104)=0,"",F41/SUM(F5:F104)))
B42: =IF(C42="","PAM-"&TEXT(COUNTA($C$5:C42),"000")) | F42: =D42+E42 | G42: =IF(F42="","",IF(SUM(F5:F104)=0,"",F42/SUM(F5:F104)))
B43: =IF(C43="","PAM-"&TEXT(COUNTA($C$5:C43),"000")) | F43: =D43+E43 | G43: =IF(F43="","",IF(SUM(F5:F104)=0,"",F43/SUM(F5:F104)))
B44: =IF(C44="","PAM-"&TEXT(COUNTA($C$5:C44),"000")) | F44: =D44+E44 | G44: =IF(F44="","",IF(SUM(F5:F104)=0,"",F44/SUM(F5:F104)))
B45: =IF(C45="","PAM-"&TEXT(COUNTA($C$5:C45),"000")) | F45: =D45+E45 | G45: =IF(F45="","",IF(SUM(F5:F104)=0,"",F45/SUM(F5:F104)))
B46: =IF(C46="","PAM-"&TEXT(COUNTA($C$5:C46),"000")) | F46: =D46+E46 | G46: =IF(F46="","",IF(SUM(F5:F104)=0,"",F46/SUM(F5:F104)))
B47: =IF(C47="","PAM-"&TEXT(COUNTA($C$5:C47),"000")) | F47: =D47+E47 | G47: =IF(F47="","",IF(SUM(F5:F104)=0,"",F47/SUM(F5:F104)))
B48: =IF(C48="","PAM-"&TEXT(COUNTA($C$5:C48),"000")) | F48: =D48+E48 | G48: =IF(F48="","",IF(SUM(F5:F104)=0,"",F48/SUM(F5:F104)))
B49: =IF(C49="","PAM-"&TEXT(COUNTA($C$5:C49),"000")) | F49: =D49+E49 | G49: =IF(F49="","",IF(SUM(F5:F104)=0,"",F49/SUM(F5:F104)))
B50: =IF(C50="","PAM-"&TEXT(COUNTA($C$5:C50),"000")) | F50: =D50+E50 | G50: =IF(F50="","",IF(SUM(F5:F104)=0,"",F50/SUM(F5:F104)))
B51: =IF(C51="","PAM-"&TEXT(COUNTA($C$5:C51),"000")) | F51: =D51+E51 | G51: =IF(F51="","",IF(SUM(F5:F104)=0,"",F51/SUM(F5:F104)))
B52: =IF(C52="","PAM-"&TEXT(COUNTA($C$5:C52),"000")) | F52: =D52+E52 | G52: =IF(F52="","",IF(SUM(F5:F104)=0,"",F52/SUM(F5:F104)))
B53: =IF(C53="","PAM-"&TEXT(COUNTA($C$5:C53),"000")) | F53: =D53+E53 | G53: =IF(F53="","",IF(SUM(F5:F104)=0,"",F53/SUM(F5:F104)))
B54: =IF(C54="","PAM-"&TEXT(COUNTA($C$5:C54),"000")) | F54: =D54+E54 | G54: =IF(F54="","",IF(SUM(F5:F104)=0,"",F54/SUM(F5:F104)))
B55: =IF(C55="","PAM-"&TEXT(COUNTA($C$5:C55),"000")) | F55: =D55+E55 | G55: =IF(F55="","",IF(SUM(F5:F104)=0,"",F55/SUM(F5:F104)))
B56: =IF(C56="","PAM-"&TEXT(COUNTA($C$5:C56),"000")) | F56: =D56+E56 | G56: =IF(F56="","",IF(SUM(F5:F104)=0,"",F56/SUM(F5:F104)))
B57: =IF(C57="","PAM-"&TEXT(COUNTA($C$5:C57),"000")) | F57: =D57+E57 | G57: =IF(F57="","",IF(SUM(F5:F104)=0,"",F57/SUM(F5:F104)))
B58: =IF(C58="","PAM-"&TEXT(COUNTA($C$5:C58),"000")) | F58: =D58+E58 | G58: =IF(F58="","",IF(SUM(F5:F104)=0,"",F58/SUM(F5:F104)))
B59: =IF(C59="","PAM-"&TEXT(COUNTA($C$5:C59),"000")) | F59: =D59+E59 | G59: =IF(F59="","",IF(SUM(F5:F104)=0,"",F59/SUM(F5:F104)))
B60: =IF(C60="","PAM-"&TEXT(COUNTA($C$5:C60),"000")) | F60: =D60+E60 | G60: =IF(F60="","",IF(SUM(F5:F104)=0,"",F60/SUM(F5:F104)))
B61: =IF(C61="","PAM-"&TEXT(COUNTA($C$5:C61),"000")) | F61: =D61+E61 | G61: =IF(F61="","",IF(SUM(F5:F104)=0,"",F61/SUM(F5:F104)))
B62: =IF(C62="","PAM-"&TEXT(COUNTA($C$5:C62),"000")) | F62: =D62+E62 | G62: =IF(F62="","",IF(SUM(F5:F104)=0,"",F62/SUM(F5:F104)))
B63: =IF(C63="","PAM-"&TEXT(COUNTA($C$5:C63),"000")) | F63: =D63+E63 | G63: =IF(F63="","",IF(SUM(F5:F104)=0,"",F63/SUM(F5:F104)))
B64: =IF(C64="","PAM-"&TEXT(COUNTA($C$5:C64),"000")) | F64: =D64+E64 | G64: =IF(F64="","",IF(SUM(F5:F104)=0,"",F64/SUM(F5:F104)))
B65: =IF(C65="","PAM-"&TEXT(COUNTA($C$5:C65),"000")) | F65: =D65+E65 | G65: =IF(F65="","",IF(SUM(F5:F104)=0,"",F65/SUM(F5:F104)))
B66: =IF(C66="","PAM-"&TEXT(COUNTA($C$5:C66),"000")) | F66: =D66+E66 | G66: =IF(F66="","",IF(SUM(F5:F104)=0,"",F66/SUM(F5:F104)))
B67: =IF(C67="","PAM-"&TEXT(COUNTA($C$5:C67),"000")) | F67: =D67+E67 | G67: =IF(F67="","",IF(SUM(F5:F104)=0,"",F67/SUM(F5:F104)))
B68: =IF(C68="","PAM-"&TEXT(COUNTA($C$5:C68),"000")) | F68: =D68+E68 | G68: =IF(F68="","",IF(SUM(F5:F104)=0,"",F68/SUM(F5:F104)))
B69: =IF(C69="","PAM-"&TEXT(COUNTA($C$5:C69),"000")) | F69: =D69+E69 | G69: =IF(F69="","",IF(SUM(F5:F104)=0,"",F69/SUM(F5:F104)))
B70: =IF(C70="","PAM-"&TEXT(COUNTA($C$5:C70),"000")) | F70: =D70+E70 | G70: =IF(F70="","",IF(SUM(F5:F104)=0,"",F70/SUM(F5:F104)))
B71: =IF(C71="","PAM-"&TEXT(COUNTA($C$5:C71),"000")) | F71: =D71+E71 | G71: =IF(F71="","",IF(SUM(F5:F104)=0,"",F71/SUM(F5:F104)))
B72: =IF(C72="","PAM-"&TEXT(COUNTA($C$5:C72),"000")) | F72: =D72+E72 | G72: =IF(F72="","",IF(SUM(F5:F104)=0,"",F72/SUM(F5:F104)))
B73: =IF(C73="","PAM-"&TEXT(COUNTA($C$5:C73),"000")) | F73: =D73+E73 | G73: =IF(F73="","",IF(SUM(F5:F104)=0,"",F73/SUM(F5:F104)))
B74: =IF(C74="","PAM-"&TEXT(COUNTA($C$5:C74),"000")) | F74: =D74+E74 | G74: =IF(F74="","",IF(SUM(F5:F104)=0,"",F74/SUM(F5:F104)))
B75: =IF(C75="","PAM-"&TEXT(COUNTA($C$5:C75),"000")) | F75: =D75+E75 | G75: =IF(F75="","",IF(SUM(F5:F104)=0,"",F75/SUM(F5:F104)))
B76: =IF(C76="","PAM-"&TEXT(COUNTA($C$5:C76),"000")) | F76: =D76+E76 | G76: =IF(F76="","",IF(SUM(F5:F104)=0,"",F76/SUM(F5:F104)))
B77: =IF(C77="","PAM-"&TEXT(COUNTA($C$5:C77),"000")) | F77: =D77+E77 | G77: =IF(F77="","",IF(SUM(F5:F104)=0,"",F77/SUM(F5:F104)))
B78: =IF(C78="","PAM-"&TEXT(COUNTA($C$5:C78),"000")) | F78: =D78+E78 | G78: =IF(F78="","",IF(SUM(F5:F104)=0,"",F78/SUM(F5:F104)))
B79: =IF(C79="","PAM-"&TEXT(COUNTA($C$5:C79),"000")) | F79: =D79+E79 | G79: =IF(F79="","",IF(SUM(F5:F104)=0,"",F79/SUM(F5:F104)))
B80: =IF(C80="","PAM-"&TEXT(COUNTA($C$5:C80),"000")) | F80: =D80+E80 | G80: =IF(F80="","",IF(SUM(F5:F104)=0,"",F80/SUM(F5:F104)))
B81: =IF(C81="","PAM-"&TEXT(COUNTA($C$5:C81),"000")) | F81: =D81+E81 | G81: =IF(F81="","",IF(SUM(F5:F104)=0,"",F81/SUM(F5:F104)))
B82: =IF(C82="","PAM-"&TEXT(COUNTA($C$5:C82),"000")) | F82: =D82+E82 | G82: =IF(F82="","",IF(SUM(F5:F104)=0,"",F82/SUM(F5:F104)))
B83: =IF(C83="","PAM-"&TEXT(COUNTA($C$5:C83),"000")) | F83: =D83+E83 | G83: =IF(F83="","",IF(SUM(F5:F104)=0,"",F83/SUM(F5:F104)))
B84: =IF(C84="","PAM-"&TEXT(COUNTA($C$5:C84),"000")) | F84: =D84+E84 | G84: =IF(F84="","",IF(SUM(F5:F104)=0,"",F84/SUM(F5:F104)))
B85: =IF(C85="","PAM-"&TEXT(COUNTA($C$5:C85),"000")) | F85: =D85+E85 | G85: =IF(F85="","",IF(SUM(F5:F104)=0,"",F85/SUM(F5:F104)))
B86: =IF(C86="","PAM-"&TEXT(COUNTA($C$5:C86),"000")) | F86: =D86+E86 | G86: =IF(F86="","",IF(SUM(F5:F104)=0,"",F86/SUM(F5:F104)))
B87: =IF(C87="","PAM-"&TEXT(COUNTA($C$5:C87),"000")) | F87: =D87+E87 | G87: =IF(F87="","",IF(SUM(F5:F104)=0,"",F87/SUM(F5:F104)))
B88: =IF(C88="","PAM-"&TEXT(COUNTA($C$5:C88),"000")) | F88: =D88+E88 | G88: =IF(F88="","",IF(SUM(F5:F104)=0,"",F88/SUM(F5:F104)))
B89: =IF(C89="","PAM-"&TEXT(COUNTA($C$5:C89),"000")) | F89: =D89+E89 | G89: =IF(F89="","",IF(SUM(F5:F104)=0,"",F89/SUM(F5:F104)))
B90: =IF(C90="","PAM-"&TEXT(COUNTA($C$5:C90),"000")) | F90: =D90+E90 | G90: =IF(F90="","",IF(SUM(F5:F104)=0,"",F90/SUM(F5:F104)))
B91: =IF(C91="","PAM-"&TEXT(COUNTA($C$5:C91),"000")) | F91: =D91+E91 | G91: =IF(F91="","",IF(SUM(F5:F104)=0,"",F91/SUM(F5:F104)))
B92: =IF(C92="","PAM-"&TEXT(COUNTA($C$5:C92),"000")) | F92: =D92+E92 | G92: =IF(F92="","",IF(SUM(F5:F104)=0,"",F92/SUM(F5:F104)))
B93: =IF(C93="","PAM-"&TEXT(COUNTA($C$5:C93),"000")) | F93: =D93+E93 | G93: =IF(F93="","",IF(SUM(F5:F104)=0,"",F93/SUM(F5:F104)))
B94: =IF(C94="","PAM-"&TEXT(COUNTA($C$5:C94),"000")) | F94: =D94+E94 | G94: =IF(F94="","",IF(SUM(F5:F104)=0,"",F94/SUM(F5:F104)))
B95: =IF(C95="","PAM-"&TEXT(COUNTA($C$5:C95),"000")) | F95: =D95+E95 | G95: =IF(F95="","",IF(SUM(F5:F104)=0,"",F95/SUM(F5:F104)))
B96: =IF(C96="","PAM-"&TEXT(COUNTA($C$5:C96),"000")) | F96: =D96+E96 | G96: =IF(F96="","",IF(SUM(F5:F104)=0,"",F96/SUM(F5:F104)))
B97: =IF(C97="","PAM-"&TEXT(COUNTA($C$5:C97),"000")) | F97: =D97+E97 | G97: =IF(F97="","",IF(SUM(F5:F104)=0,"",F97/SUM(F5:F104)))
B98: =IF(C98="","PAM-"&TEXT(COUNTA($C$5:C98),"000")) | F98: =D98+E98 | G98: =IF(F98="","",IF(SUM(F5:F104)=0,"",F98/SUM(F5:F104)))
B99: =IF(C99="","PAM-"&TEXT(COUNTA($C$5:C99),"000")) | F99: =D99+E99 | G99: =IF(F99="","",IF(SUM(F5:F104)=0,"",F99/SUM(F5:F104)))
B100: =IF(C100="","PAM-"&TEXT(COUNTA($C$5:C100),"000")) | F100: =D100+E100 | G100: =IF(F100="","",IF(SUM(F5:F104)=0,"",F100/SUM(F5:F104)))
B101: =IF(C101="","PAM-"&TEXT(COUNTA($C$5:C101),"000")) | F101: =D101+E101 | G101: =IF(F101="","",IF(SUM(F5:F104)=0,"",F101/SUM(F5:F104)))
...

Sheet 5-Analyse Turnover
B2: ANALYSE DU TURNOVER (#139)
B3: TABLEAU DYNAMIQUE — Saisissez dans la prochaine ligne jaune. Les calculs se mettent a jour automatiquement.
B4: N° | C4: Mois | D4: Annee | E4: Effectif Debut Mois | F4: Entrees | G4: Sorties | H4: Effectif Fin Mois | I4: Taux Turnover (%) | J4: Taux Turnover YTD (%)
B5: TUR-001 | C5: Janvier | D5: 2025 | E5: 87 | F5: 5 | G5: 3
B6: TUR-002 | C6: Fevrier | D6: 2025 | E6: 89 | F6: 2 | G6: 1
B7: TUR-003 | C7: Mars | D7: 2025 | E7: 90 | F7: 3 | G7: 4
B8: TUR-004 | C8: Avril | D8: 2025 | E8: 89 | F8: 1 | G8: 2
B9: TUR-005 | C9: Mai | D9: 2025 | E9: 88 | F9: 3 | G9: 2
B10: TUR-006 | C10: Juin | D10: 2025 | E10: 89 | F10: 2 | G10: 2
B11: =IF(C11="","TUR-"&TEXT(COUNTA($C$5:C11),"000")) | H11: =E11+F11-G11 | I11: =IF(E11="","",(G11+F11)/(E11+F11)/2) | J11: =IF(E5="","",SUM(G5:G11)/AVERAGE(E5:E11))
B12: =IF(C12="","TUR-"&TEXT(COUNTA($C$5:C12),"000")) | H12: =E12+F12-G12 | I12: =IF(E12="","",(G12+F12)/(E12+F12)/2) | J12: =IF(E5="","",SUM(G5:G12)/AVERAGE(E5:E12))
B13: =IF(C13="","TUR-"&TEXT(COUNTA($C$5:C13),"000")) | H13: =E13+F13-G13 | I13: =IF(E13="","",(G13+F13)/(E13+F13)/2) | J13: =IF(E5="","",SUM(G5:G13)/AVERAGE(E5:E13))
B14: =IF(C14="","TUR-"&TEXT(COUNTA($C$5:C14),"000")) | H14: =E14+F14-G14 | I14: =IF(E14="","",(G14+F14)/(E14+F14)/2) | J14: =IF(E5="","",SUM(G5:G14)/AVERAGE(E5:E14))
B15: =IF(C15="","TUR-"&TEXT(COUNTA($C$5:C15),"000")) | H15: =E15+F15-G15 | I15: =IF(E15="","",(G15+F15)/(E15+F15)/2) | J15: =IF(E5="","",SUM(G5:G15)/AVERAGE(E5:E15))
B16: =IF(C16="","TUR-"&TEXT(COUNTA($C$5:C16),"000")) | H16: =E16+F16-G16 | I16: =IF(E16="","",(G16+F16)/(E16+F16)/2) | J16: =IF(E5="","",SUM(G5:G16)/AVERAGE(E5:E16))
B17: =IF(C17="","TUR-"&TEXT(COUNTA($C$5:C17),"000")) | H17: =E17+F17-G17 | I17: =IF(E17="","",(G17+F17)/(E17+F17)/2) | J17: =IF(E5="","",SUM(G5:G17)/AVERAGE(E5:E17))
B18: =IF(C18="","TUR-"&TEXT(COUNTA($C$5:C18),"000")) | H18: =E18+F18-G18 | I18: =IF(E18="","",(G18+F18)/(E18+F18)/2) | J18: =IF(E5="","",SUM(G5:G18)/AVERAGE(E5:E18))
B19: =IF(C19="","TUR-"&TEXT(COUNTA($C$5:C19),"000")) | H19: =E19+F19-G19 | I19: =IF(E19="","",(G19+F19)/(E19+F19)/2) | J19: =IF(E5="","",SUM(G5:G19)/AVERAGE(E5:E19))
B20: =IF(C20="","TUR-"&TEXT(COUNTA($C$5:C20),"000")) | H20: =E20+F20-G20 | I20: =IF(E20="","",(G20+F20)/(E20+F20)/2) | J20: =IF(E5="","",SUM(G5:G20)/AVERAGE(E5:E20))
B21: =IF(C21="","TUR-"&TEXT(COUNTA($C$5:C21),"000")) | H21: =E21+F21-G21 | I21: =IF(E21="","",(G21+F21)/(E21+F21)/2) | J21: =IF(E5="","",SUM(G5:G21)/AVERAGE(E5:E21))
B22: =IF(C22="","TUR-"&TEXT(COUNTA($C$5:C22),"000")) | H22: =E22+F22-G22 | I22: =IF(E22="","",(G22+F22)/(E22+F22)/2) | J22: =IF(E5="","",SUM(G5:G22)/AVERAGE(E5:E22))
B23: =IF(C23="","TUR-"&TEXT(COUNTA($C$5:C23),"000")) | H23: =E23+F23-G23 | I23: =IF(E23="","",(G23+F23)/(E23+F23)/2) | J23: =IF(E5="","",SUM(G5:G23)/AVERAGE(E5:E23))
B24: =IF(C24="","TUR-"&TEXT(COUNTA($C$5:C24),"000")) | H24: =E24+F24-G24 | I24: =IF(E24="","",(G24+F24)/(E24+F24)/2) | J24: =IF(E5="","",SUM(G5:G24)/AVERAGE(E5:E24))
B25: =IF(C25="","TUR-"&TEXT(COUNTA($C$5:C25),"000")) | H25: =E25+F25-G25 | I25: =IF(E25="","",(G25+F25)/(E25+F25)/2) | J25: =IF(E5="","",SUM(G5:G25)/AVERAGE(E5:E25))
B26: =IF(C26="","TUR-"&TEXT(COUNTA($C$5:C26),"000")) | H26: =E26+F26-G26 | I26: =IF(E26="","",(G26+F26)/(E26+F26)/2) | J26: =IF(E5="","",SUM(G5:G26)/AVERAGE(E5:E26))
B27: =IF(C27="","TUR-"&TEXT(COUNTA($C$5:C27),"000")) | H27: =E27+F27-G27 | I27: =IF(E27="","",(G27+F27)/(E27+F27)/2) | J27: =IF(E5="","",SUM(G5:G27)/AVERAGE(E5:E27))
B28: =IF(C28="","TUR-"&TEXT(COUNTA($C$5:C28),"000")) | H28: =E28+F28-G28 | I28: =IF(E28="","",(G28+F28)/(E28+F28)/2) | J28: =IF(E5="","",SUM(G5:G28)/AVERAGE(E5:E28))
B29: =IF(C29="","TUR-"&TEXT(COUNTA($C$5:C29),"000")) | H29: =E29+F29-G29 | I29: =IF(E29="","",(G29+F29)/(E29+F29)/2) | J29: =IF(E5="","",SUM(G5:G29)/AVERAGE(E5:E29))
B30: =IF(C30="","TUR-"&TEXT(COUNTA($C$5:C30),"000")) | H30: =E30+F30-G30 | I30: =IF(E30="","",(G30+F30)/(E30+F30)/2) | J30: =IF(E5="","",SUM(G5:G30)/AVERAGE(E5:E30))
B31: =IF(C31="","TUR-"&TEXT(COUNTA($C$5:C31),"000")) | H31: =E31+F31-G31 | I31: =IF(E31="","",(G31+F31)/(E31+F31)/2) | J31: =IF(E5="","",SUM(G5:G31)/AVERAGE(E5:E31))
B32: =IF(C32="","TUR-"&TEXT(COUNTA($C$5:C32),"000")) | H32: =E32+F32-G32 | I32: =IF(E32="","",(G32+F32)/(E32+F32)/2) | J32: =IF(E5="","",SUM(G5:G32)/AVERAGE(E5:E32))
B33: =IF(C33="","TUR-"&TEXT(COUNTA($C$5:C33),"000")) | H33: =E33+F33-G33 | I33: =IF(E33="","",(G33+F33)/(E33+F33)/2) | J33: =IF(E5="","",SUM(G5:G33)/AVERAGE(E5:E33))
B34: =IF(C34="","TUR-"&TEXT(COUNTA($C$5:C34),"000")) | H34: =E34+F34-G34 | I34: =IF(E34="","",(G34+F34)/(E34+F34)/2) | J34: =IF(E5="","",SUM(G5:G34)/AVERAGE(E5:E34))
B35: =IF(C35="","TUR-"&TEXT(COUNTA($C$5:C35),"000")) | H35: =E35+F35-G35 | I35: =IF(E35="","",(G35+F35)/(E35+F35)/2) | J35: =IF(E5="","",SUM(G5:G35)/AVERAGE(E5:E35))
B36: =IF(C36="","TUR-"&TEXT(COUNTA($C$5:C36),"000")) | H36: =E36+F36-G36 | I36: =IF(E36="","",(G36+F36)/(E36+F36)/2) | J36: =IF(E5="","",SUM(G5:G36)/AVERAGE(E5:E36))
B37: =IF(C37="","TUR-"&TEXT(COUNTA($C$5:C37),"000")) | H37: =E37+F37-G37 | I37: =IF(E37="","",(G37+F37)/(E37+F37)/2) | J37: =IF(E5="","",SUM(G5:G37)/AVERAGE(E5:E37))
B38: =IF(C38="","TUR-"&TEXT(COUNTA($C$5:C38),"000")) | H38: =E38+F38-G38 | I38: =IF(E38="","",(G38+F38)/(E38+F38)/2) | J38: =IF(E5="","",SUM(G5:G38)/AVERAGE(E5:E38))
B39: =IF(C39="","TUR-"&TEXT(COUNTA($C$5:C39),"000")) | H39: =E39+F39-G39 | I39: =IF(E39="","",(G39+F39)/(E39+F39)/2) | J39: =IF(E5="","",SUM(G5:G39)/AVERAGE(E5:E39))
B40: =IF(C40="","TUR-"&TEXT(COUNTA($C$5:C40),"000")) | H40: =E40+F40-G40 | I40: =IF(E40="","",(G40+F40)/(E40+F40)/2) | J40: =IF(E5="","",SUM(G5:G40)/AVERAGE(E5:E40))
B41: =IF(C41="","TUR-"&TEXT(COUNTA($C$5:C41),"000")) | H41: =E41+F41-G41 | I41: =IF(E41="","",(G41+F41)/(E41+F41)/2) | J41: =IF(E5="","",SUM(G5:G41)/AVERAGE(E5:E41))
B42: =IF(C42="","TUR-"&TEXT(COUNTA($C$5:C42),"000")) | H42: =E42+F42-G42 | I42: =IF(E42="","",(G42+F42)/(E42+F42)/2) | J42: =IF(E5="","",SUM(G5:G42)/AVERAGE(E5:E42))
B43: =IF(C43="","TUR-"&TEXT(COUNTA($C$5:C43),"000")) | H43: =E43+F43-G43 | I43: =IF(E43="","",(G43+F43)/(E43+F43)/2) | J43: =IF(E5="","",SUM(G5:G43)/AVERAGE(E5:E43))
B44: =IF(C44="","TUR-"&TEXT(COUNTA($C$5:C44),"000")) | H44: =E44+F44-G44 | I44: =IF(E44="","",(G44+F44)/(E44+F44)/2) | J44: =IF(E5="","",SUM(G5:G44)/AVERAGE(E5:E44))
B45: =IF(C45="","TUR-"&TEXT(COUNTA($C$5:C45),"000")) | H45: =E45+F45-G45 | I45: =IF(E45="","",(G45+F45)/(E45+F45)/2) | J45: =IF(E5="","",SUM(G5:G45)/AVERAGE(E5:E45))
B46: =IF(C46="","TUR-"&TEXT(COUNTA($C$5:C46),"000")) | H46: =E46+F46-G46 | I46: =IF(E46="","",(G46+F46)/(E46+F46)/2) | J46: =IF(E5="","",SUM(G5:G46)/AVERAGE(E5:E46))
B47: =IF(C47="","TUR-"&TEXT(COUNTA($C$5:C47),"000")) | H47: =E47+F47-G47 | I47: =IF(E47="","",(G47+F47)/(E47+F47)/2) | J47: =IF(E5="","",SUM(G5:G47)/AVERAGE(E5:E47))
B48: =IF(C48="","TUR-"&TEXT(COUNTA($C$5:C48),"000")) | H48: =E48+F48-G48 | I48: =IF(E48="","",(G48+F48)/(E48+F48)/2) | J48: =IF(E5="","",SUM(G5:G48)/AVERAGE(E5:E48))
B49: =IF(C49="","TUR-"&TEXT(COUNTA($C$5:C49),"000")) | H49: =E49+F49-G49 | I49: =IF(E49="","",(G49+F49)/(E49+F49)/2) | J49: =IF(E5="","",SUM(G5:G49)/AVERAGE(E5:E49))
B50: =IF(C50="","TUR-"&TEXT(COUNTA($C$5:C50),"000")) | H50: =E50+F50-G50 | I50: =IF(E50="","",(G50+F50)/(E50+F50)/2) | J50: =IF(E5="","",SUM(G5:G50)/AVERAGE(E5:E50))
B51: =IF(C51="","TUR-"&TEXT(COUNTA($C$5:C51),"000")) | H51: =E51+F51-G51 | I51: =IF(E51="","",(G51+F51)/(E51+F51)/2) | J51: =IF(E5="","",SUM(G5:G51)/AVERAGE(E5:E51))
B52: =IF(C52="","TUR-"&TEXT(COUNTA($C$5:C52),"000")) | H52: =E52+F52-G52 | I52: =IF(E52="","",(G52+F52)/(E52+F52)/2) | J52: =IF(E5="","",SUM(G5:G52)/AVERAGE(E5:E52))
B53: =IF(C53="","TUR-"&TEXT(COUNTA($C$5:C53),"000")) | H53: =E53+F53-G53 | I53: =IF(E53="","",(G53+F53)/(E53+F53)/2) | J53: =IF(E5="","",SUM(G5:G53)/AVERAGE(E5:E53))
B54: =IF(C54="","TUR-"&TEXT(COUNTA($C$5:C54),"000")) | H54: =E54+F54-G54 | I54: =IF(E54="","",(G54+F54)/(E54+F54)/2) | J54: =IF(E5="","",SUM(G5:G54)/AVERAGE(E5:E54))
B55: =IF(C55="","TUR-"&TEXT(COUNTA($C$5:C55),"000")) | H55: =E55+F55-G55 | I55: =IF(E55="","",(G55+F55)/(E55+F55)/2) | J55: =IF(E5="","",SUM(G5:G55)/AVERAGE(E5:E55))
B56: =IF(C56="","TUR-"&TEXT(COUNTA($C$5:C56),"000")) | H56: =E56+F56-G56 | I56: =IF(E56="","",(G56+F56)/(E56+F56)/2) | J56: =IF(E5="","",SUM(G5:G56)/AVERAGE(E5:E56))
B57: =IF(C57="","TUR-"&TEXT(COUNTA($C$5:C57),"000")) | H57: =E57+F57-G57 | I57: =IF(E57="","",(G57+F57)/(E57+F57)/2) | J57: =IF(E5="","",SUM(G5:G57)/AVERAGE(E5:E57))
B58: =IF(C58="","TUR-"&TEXT(COUNTA($C$5:C58),"000")) | H58: =E58+F58-G58 | I58: =IF(E58="","",(G58+F58)/(E58+F58)/2) | J58: =IF(E5="","",SUM(G5:G58)/AVERAGE(E5:E58))
B59: =IF(C59="","TUR-"&TEXT(COUNTA($C$5:C59),"000")) | H59: =E59+F59-G59 | I59: =IF(E59="","",(G59+F59)/(E59+F59)/2) | J59: =IF(E5="","",SUM(G5:G59)/AVERAGE(E5:E59))
B60: =IF(C60="","TUR-"&TEXT(COUNTA($C$5:C60),"000")) | H60: =E60+F60-G60 | I60: =IF(E60="","",(G60+F60)/(E60+F60)/2) | J60: =IF(E5="","",SUM(G5:G60)/AVERAGE(E5:E60))
B61: =IF(C61="","TUR-"&TEXT(COUNTA($C$5:C61),"000")) | H61: =E61+F61-G61 | I61: =IF(E61="","",(G61+F61)/(E61+F61)/2) | J61: =IF(E5="","",SUM(G5:G61)/AVERAGE(E5:E61))
B62: =IF(C62="","TUR-"&TEXT(COUNTA($C$5:C62),"000")) | H62: =E62+F62-G62 | I62: =IF(E62="","",(G62+F62)/(E62+F62)/2) | J62: =IF(E5="","",SUM(G5:G62)/AVERAGE(E5:E62))
B63: =IF(C63="","TUR-"&TEXT(COUNTA($C$5:C63),"000")) | H63: =E63+F63-G63 | I63: =IF(E63="","",(G63+F63)/(E63+F63)/2) | J63: =IF(E5="","",SUM(G5:G63)/AVERAGE(E5:E63))
B64: =IF(C64="","TUR-"&TEXT(COUNTA($C$5:C64),"000")) | H64: =E64+F64-G64 | I64: =IF(E64="","",(G64+F64)/(E64+F64)/2) | J64: =IF(E5="","",SUM(G5:G64)/AVERAGE(E5:E64))
B65: =IF(C65="","TUR-"&TEXT(COUNTA($C$5:C65),"000")) | H65: =E65+F65-G65 | I65: =IF(E65="","",(G65+F65)/(E65+F65)/2) | J65: =IF(E5="","",SUM(G5:G65)/AVERAGE(E5:E65))
B66: =IF(C66="","TUR-"&TEXT(COUNTA($C$5:C66),"000")) | H66: =E66+F66-G66 | I66: =IF(E66="","",(G66+F66)/(E66+F66)/2) | J66: =IF(E5="","",SUM(G5:G66)/AVERAGE(E5:E66))
B67: =IF(C67="","TUR-"&TEXT(COUNTA($C$5:C67),"000")) | H67: =E67+F67-G67 | I67: =IF(E67="","",(G67+F67)/(E67+F67)/2) | J67: =IF(E5="","",SUM(G5:G67)/AVERAGE(E5:E67))
B68: =IF(C68="","TUR-"&TEXT(COUNTA($C$5:C68),"000")) | H68: =E68+F68-G68 | I68: =IF(E68="","",(G68+F68)/(E68+F68)/2) | J68: =IF(E5="","",SUM(G5:G68)/AVERAGE(E5:E68))
B69: =IF(C69="","TUR-"&TEXT(COUNTA($C$5:C69),"000")) | H69: =E69+F69-G69 | I69: =IF(E69="","",(G69+F69)/(E69+F69)/2) | J69: =IF(E5="","",SUM(G5:G69)/AVERAGE(E5:E69))
B70: =IF(C70="","TUR-"&TEXT(COUNTA($C$5:C70),"000")) | H70: =E70+F70-G70 | I70: =IF(E70="","",(G70+F70)/(E70+F70)/2) | J70: =IF(E5="","",SUM(G5:G70)/AVERAGE(E5:E70))
B71: =IF(C71="","TUR-"&TEXT(COUNTA($C$5:C71),"000")) | H71: =E71+F71-G71 | I71: =IF(E71="","",(G71+F71)/(E71+F71)/2) | J71: =IF(E5="","",SUM(G5:G71)/AVERAGE(E5:E71))
B72: =IF(C72="","TUR-"&TEXT(COUNTA($C$5:C72),"000")) | H72: =E72+F72-G72 | I72: =IF(E72="","",(G72+F72)/(E72+F72)/2) | J72: =IF(E5="","",SUM(G5:G72)/AVERAGE(E5:E72))
B73: =IF(C73="","TUR-"&TEXT(COUNTA($C$5:C73),"000")) | H73: =E73+F73-G73 | I73: =IF(E73="","",(G73+F73)/(E73+F73)/2) | J73: =IF(E5="","",SUM(G5:G73)/AVERAGE(E5:E73))
B74: =IF(C74="","TUR-"&TEXT(COUNTA($C$5:C74),"000")) | H74: =E74+F74-G74 | I74: =IF(E74="","",(G74+F74)/(E74+F74)/2) | J74: =IF(E5="","",SUM(G5:G74)/AVERAGE(E5:E74))
B75: =IF(C75="","TUR-"&TEXT(COUNTA($C$5:C75),"000")) | H75: =E75+F75-G75 | I75: =IF(E75="","",(G75+F75)/(E75+F75)/2) | J75: =IF(E5="","",SUM(G5:G75)/AVERAGE(E5:E75))
B76: =IF(C76="","TUR-"&TEXT(COUNTA($C$5:C76),"000")) | H76: =E76+F76-G76 | I76: =IF(E76="","",(G76+F76)/(E76+F76)/2) | J76: =IF(E5="","",SUM(G5:G76)/AVERAGE(E5:E76))
B77: =IF(C77="","TUR-"&TEXT(COUNTA($C$5:C77),"000")) | H77: =E77+F77-G77 | I77: =IF(E77="","",(G77+F77)/(E77+F77)/2) | J77: =IF(E5="","",SUM(G5:G77)/AVERAGE(E5:E77))
B78: =IF(C78="","TUR-"&TEXT(COUNTA($C$5:C78),"000")) | H78: =E78+F78-G78 | I78: =IF(E78="","",(G78+F78)/(E78+F78)/2) | J78: =IF(E5="","",SUM(G5:G78)/AVERAGE(E5:E78))
B79: =IF(C79="","TUR-"&TEXT(COUNTA($C$5:C79),"000")) | H79: =E79+F79-G79 | I79: =IF(E79="","",(G79+F79)/(E79+F79)/2) | J79: =IF(E5="","",SUM(G5:G79)/AVERAGE(E5:E79))
B80: =IF(C80="","TUR-"&TEXT(COUNTA($C$5:C80),"000")) | H80: =E80+F80-G80 | I80: =IF(E80="","",(G80+F80)/(E80+F80)/2) | J80: =IF(E5="","",SUM(G5:G80)/AVERAGE(E5:E80))
B81: =IF(C81="","TUR-"&TEXT(COUNTA($C$5:C81),"000")) | H81: =E81+F81-G81 | I81: =IF(E81="","",(G81+F81)/(E81+F81)/2) | J81: =IF(E5="","",SUM(G5:G81)/AVERAGE(E5:E81))
B82: =IF(C82="","TUR-"&TEXT(COUNTA($C$5:C82),"000")) | H82: =E82+F82-G82 | I82: =IF(E82="","",(G82+F82)/(E82+F82)/2) | J82: =IF(E5="","",SUM(G5:G82)/AVERAGE(E5:E82))
B83: =IF(C83="","TUR-"&TEXT(COUNTA($C$5:C83),"000")) | H83: =E83+F83-G83 | I83: =IF(E83="","",(G83+F83)/(E83+F83)/2) | J83: =IF(E5="","",SUM(G5:G83)/AVERAGE(E5:E83))
B84: =IF(C84="","TUR-"&TEXT(COUNTA($C$5:C84),"000")) | H84: =E84+F84-G84 | I84: =IF(E84="","",(G84+F84)/(E84+F84)/2) | J84: =IF(E5="","",SUM(G5:G84)/AVERAGE(E5:E84))
B85: =IF(C85="","TUR-"&TEXT(COUNTA($C$5:C85),"000")) | H85: =E85+F85-G85 | I85: =IF(E85="","",(G85+F85)/(E85+F85)/2) | J85: =IF(E5="","",SUM(G5:G85)/AVERAGE(E5:E85))
B86: =IF(C86="","TUR-"&TEXT(COUNTA($C$5:C86),"000")) | H86: =E86+F86-G86 | I86: =IF(E86="","",(G86+F86)/(E86+F86)/2) | J86: =IF(E5="","",SUM(G5:G86)/AVERAGE(E5:E86))
B87: =IF(C87="","TUR-"&TEXT(COUNTA($C$5:C87),"000")) | H87: =E87+F87-G87 | I87: =IF(E87="","",(G87+F87)/(E87+F87)/2) | J87: =IF(E5="","",SUM(G5:G87)/AVERAGE(E5:E87))
B88: =IF(C88="","TUR-"&TEXT(COUNTA($C$5:C88),"000")) | H88: =E88+F88-G88 | I88: =IF(E88="","",(G88+F88)/(E88+F88)/2) | J88: =IF(E5="","",SUM(G5:G88)/AVERAGE(E5:E88))
B89: =IF(C89="","TUR-"&TEXT(COUNTA($C$5:C89),"000")) | H89: =E89+F89-G89 | I89: =IF(E89="","",(G89+F89)/(E89+F89)/2) | J89: =IF(E5="","",SUM(G5:G89)/AVERAGE(E5:E89))
B90: =IF(C90="","TUR-"&TEXT(COUNTA($C$5:C90),"000")) | H90: =E90+F90-G90 | I90: =IF(E90="","",(G90+F90)/(E90+F90)/2) | J90: =IF(E5="","",SUM(G5:G90)/AVERAGE(E5:E90))
B91: =IF(C91="","TUR-"&TEXT(COUNTA($C$5:C91),"000")) | H91: =E91+F91-G91 | I91: =IF(E91="","",(G91+F91)/(E91+F91)/2) | J91: =IF(E5="","",SUM(G5:G91)/AVERAGE(E5:E91))
B92: =IF(C92="","TUR-"&TEXT(COUNTA($C$5:C92),"000")) | H92: =E92+F92-G92 | I92: =IF(E92="","",(G92+F92)/(E92+F92)/2) | J92: =IF(E5="","",SUM(G5:G92)/AVERAGE(E5:E92))
B93: =IF(C93="","TUR-"&TEXT(COUNTA($C$5:C93),"000")) | H93: =E93+F93-G93 | I93: =IF(E93="","",(G93+F93)/(E93+F93)/2) | J93: =IF(E5="","",SUM(G5:G93)/AVERAGE(E5:E93))
B94: =IF(C94="","TUR-"&TEXT(COUNTA($C$5:C94),"000")) | H94: =E94+F94-G94 | I94: =IF(E94="","",(G94+F94)/(E94+F94)/2) | J94: =IF(E5="","",SUM(G5:G94)/AVERAGE(E5:E94))
B95: =IF(C95="","TUR-"&TEXT(COUNTA($C$5:C95),"000")) | H95: =E95+F95-G95 | I95: =IF(E95="","",(G95+F95)/(E95+F95)/2) | J95: =IF(E5="","",SUM(G5:G95)/AVERAGE(E5:E95))
B96: =IF(C96="","TUR-"&TEXT(COUNTA($C$5:C96),"000")) | H96: =E96+F96-G96 | I96: =IF(E96="","",(G96+F96)/(E96+F96)/2) | J96: =IF(E5="","",SUM(G5:G96)/AVERAGE(E5:E96))
B97: =IF(C97="","TUR-"&TEXT(COUNTA($C$5:C97),"000")) | H97: =E97+F97-G97 | I97: =IF(E97="","",(G97+F97)/(E97+F97)/2) | J97: =IF(E5="","",SUM(G5:G97)/AVERAGE(E5:E97))
B98: =IF(C98="","TUR-"&TEXT(COUNTA($C$5:C98),"000")) | H98: =E98+F98-G98 | I98: =IF(E98="","",(G98+F98)/(E98+F98)/2) | J98: =IF(E5="","",SUM(G5:G98)/AVERAGE(E5:E98))
B99: =IF(C99="","TUR-"&TEXT(COUNTA($C$5:C99),"000")) | H99: =E99+F99-G99 | I99: =IF(E99="","",(G99+F99)/(E99+F99)/2) | J99: =IF(E5="","",SUM(G5:G99)/AVERAGE(E5:E99))
B100: =IF(C100="","TUR-"&TEXT(COUNTA($C$5:C100),"000")) | H100: =E100+F100-G100 | I100: =IF(E100="","",(G100+F100)/(E100+F100)/2) | J100: =IF(E5="","",SUM(G5:G100)/AVERAGE(E5:E100))
B101: =IF(C101="","TUR-"&TEXT(COUNTA($C$5:C101),"000")) | H101: =E101+F101-G101 | I101: =IF(E101="","",(G101+F101)/(E101+F101)/2) | J101: =IF(E5="","",SUM(G5:G101)/AVERAGE(E5:E101))
...

Sheet 6-Cout du Turnover
B2: COUT DU TURNOVER (#140)
B3: TABLEAU DYNAMIQUE — Saisissez dans la prochaine ligne jaune. Les calculs se mettent a jour automatiquement.
B4: N° | C4: Employe | D4: Poste | E4: Service | F4: Motif Depart | G4: Date Depart | H4: Salaire Brut Mensuel | I4: Cout Recrutement | J4: Cout Formation | K4: Cout Integration | L4: Cout Total Depart (FCFA)
B5: CTU-001 | C5: Ngassa A. | D5: Receptionniste | E5: Réception & Front Office | F5: Demission | G5: 45731 | H5: 180000 | I5: 150000 | J5: 50000 | K5: 30000
B6: CTU-002 | C6: Eyenga M. | D6: Cuisinier | E6: Cuisine & Restauration | F6: Licenciement | G6: 45748 | H6: 220000 | I6: 200000 | J6: 75000 | K6: 0
B7: CTU-003 | C7: Moukouri D. | D7: Agent Entretien | E7: Maintenance | F7: Fin CDD | G7: 45808 | H7: 145000 | I7: 0 | J7: 25000 | K7: 0
B8: CTU-004 | C8: Fotso R. | D8: Sous-Chef | E8: Cuisine & Restauration | F8: Demission | G8: 45818 | H8: 280000 | I8: 250000 | J8: 100000 | K8: 50000
B9: =IF(C9="","CTU-"&TEXT(COUNTA($C$5:C9),"000")) | L9: =IF(OR(H9="",I9=""),"",(H9*2)+I9+J9+K9)
B10: =IF(C10="","CTU-"&TEXT(COUNTA($C$5:C10),"000")) | L10: =IF(OR(H10="",I10=""),"",(H10*2)+I10+J10+K10)
B11: =IF(C11="","CTU-"&TEXT(COUNTA($C$5:C11),"000")) | L11: =IF(OR(H11="",I11=""),"",(H11*2)+I11+J11+K11)
B12: =IF(C12="","CTU-"&TEXT(COUNTA($C$5:C12),"000")) | L12: =IF(OR(H12="",I12=""),"",(H12*2)+I12+J12+K12)
B13: =IF(C13="","CTU-"&TEXT(COUNTA($C$5:C13),"000")) | L13: =IF(OR(H13="",I13=""),"",(H13*2)+I13+J13+K13)
B14: =IF(C14="","CTU-"&TEXT(COUNTA($C$5:C14),"000")) | L14: =IF(OR(H14="",I14=""),"",(H14*2)+I14+J14+K14)
B15: =IF(C15="","CTU-"&TEXT(COUNTA($C$5:C15),"000")) | L15: =IF(OR(H15="",I15=""),"",(H15*2)+I15+J15+K15)
B16: =IF(C16="","CTU-"&TEXT(COUNTA($C$5:C16),"000")) | L16: =IF(OR(H16="",I16=""),"",(H16*2)+I16+J16+K16)
B17: =IF(C17="","CTU-"&TEXT(COUNTA($C$5:C17),"000")) | L17: =IF(OR(H17="",I17=""),"",(H17*2)+I17+J17+K17)
B18: =IF(C18="","CTU-"&TEXT(COUNTA($C$5:C18),"000")) | L18: =IF(OR(H18="",I18=""),"",(H18*2)+I18+J18+K18)
B19: =IF(C19="","CTU-"&TEXT(COUNTA($C$5:C19),"000")) | L19: =IF(OR(H19="",I19=""),"",(H19*2)+I19+J19+K19)
B20: =IF(C20="","CTU-"&TEXT(COUNTA($C$5:C20),"000")) | L20: =IF(OR(H20="",I20=""),"",(H20*2)+I20+J20+K20)
... B108: =IF(C108="","CTU-"&TEXT(COUNTA($C$5:C108),"000")) | L108: =IF(OR(H108="",I108=""),"",(H108*2)+I108+J108+K108)
B110: TOTAL | I110: =SUM(I5:I104) | J110: =SUM(J5:J104) | K110: =SUM(K5:K104) | L110: =SUM(L5:L104)
B112: INDICATEURS (mis a jour automatiquement)
B113: Departs suivis | D113: Cout total turnover | F113: Cout moyen / depart
B114: =COUNTIF(B5:B104,"<>") | D114: =SUM(L5:L104) | F114: =IFERROR(SUM(L5:L104)/COUNTIF(B5:B104,"<>"),0)

Sheet 7-Delai Recrutement
B2: SUIVI DELAI DE RECRUTEMENT (#141)
B3: TABLEAU DYNAMIQUE — Saisissez dans la prochaine ligne jaune. Les calculs se mettent a jour automatiquement.
B4: N° | C4: Poste | D4: Service | E4: Date Besoin | F4: Date Publication | G4: Date 1er Entretien | H4: Date Decision | I4: Date Prise de Poste | J4: Delai Total (j) | K4: Source Candidat | L4: Statut
B5: DLR-001 | C5: Receptionniste | D5: Réception & Front Office | E5: 45717 | F5: 45721 | G5: 45734 | H5: 45741 | I5: 45748 | K5: Site emploi | L5: Pourvu
B6: DLR-002 | C6: Chef Reception | D6: Réception & Front Office | E6: 45703 | F6: 45708 | G6: 45726 | H6: 45736 | I6: 45748 | K6: Recommandation | L6: Pourvu
B7: DLR-003 | C7: Cuisinier | D7: Cuisine & Restauration | E7: 45778 | F7: 45782 | G7: 45797 | H7: 45809 | K7: Presse | L7: En cours
B8: DLR-004 | C8: Agent Securite | D8: Sécurité | E8: 45809 | F8: 45813 | G8: 45826 | K8: Reseau social | L8: En cours
B9: =IF(C9="","DLR-"&TEXT(COUNTA($C$5:C9),"000")) | J9: =IF(OR(F9="",I9=""),"",I9-F9)
B10: =IF(C10="","DLR-"&TEXT(COUNTA($C$5:C10),"000")) | J10: =IF(OR(F10="",I10=""),"",I10-F10)
B11: =IF(C11="","DLR-"&TEXT(COUNTA($C$5:C11),"000")) | J11: =IF(OR(F11="",I11=""),"",I11-F11)
B12: =IF(C12="","DLR-"&TEXT(COUNTA($C$5:C12),"000")) | J12: =IF(OR(F12="",I12=""),"",I12-F12)
B13: =IF(C13="","DLR-"&TEXT(COUNTA($C$5:C13),"000")) | J13: =IF(OR(F13="",I13=""),"",I13-F13)
B14: =IF(C14="","DLR-"&TEXT(COUNTA($C$5:C14),"000")) | J14: =IF(OR(F14="",I14=""),"",I14-F14)
B15: =IF(C15="","DLR-"&TEXT(COUNTA($C$5:C15),"000")) | J15: =IF(OR(F15="",I15=""),"",I15-F15)
B16: =IF(C16="","DLR-"&TEXT(COUNTA($C$5:C16),"000")) | J16: =IF(OR(F16="",I16=""),"",I16-F16)
B17: =IF(C17="","DLR-"&TEXT(COUNTA($C$5:C17),"000")) | J17: =IF(OR(F17="",I17=""),"",I17-F17)
B18: =IF(C18="","DLR-"&TEXT(COUNTA($C$5:C18),"000")) | J18: =IF(OR(F18="",I18=""),"",I18-F18)
B19: =IF(C19="","DLR-"&TEXT(COUNTA($C$5:C19),"000")) | J19: =IF(OR(F19="",I19=""),"",I19-F19)
B20: =IF(C20="","DLR-"&TEXT(COUNTA($C$5:C20),"000")) | J20: =IF(OR(F20="",I20=""),"",I20-F20)
... B108: =IF(C108="","DLR-"&TEXT(COUNTA($C$5:C108),"000")) | J108: =IF(OR(F108="",I108=""),"",I108-F108)
B110: INDICATEURS (mis a jour automatiquement)
B111: Recrutements suivis | D111: Delai moyen (j) | F111: Pourvus
B112: =COUNTIF(B5:B104,"<>") | D112: =IFERROR(AVERAGE(J5:J104),0) | F112: =COUNTIF(L5:L104,"Pourvu")

Sheet 8-Analyse Masse Salariale
B2: ANALYSE DE LA MASSE SALARIALE (#142)
B3: TABLEAU DYNAMIQUE — Saisissez dans la prochaine ligne jaune. Les calculs se mettent a jour automatiquement.
B4: N° | C4: Mois | D4: Annee | E4: Salaires de Base (FCFA) | F4: Primes (FCFA) | G4: Heures Sup. (FCFA) | H4: Cotisations Patronales | I4: Autres Charges (FCFA) | J4: Masse Salariale Totale | K4: Variation vs Mois Prec.
B5: MSS-001 | C5: Janvier | D5: 2025 | E5: 22000000 | F5: 1850000 | G5: 620000 | H5: 3960000 | I5: 350000
B6: MSS-002 | C6: Fevrier | D6: 2025 | E6: 22100000 | F6: 1900000 | G6: 580000 | H6: 3978000 | I6: 355000
B7: MSS-003 | C7: Mars | D7: 2025 | E7: 22300000 | F7: 1920000 | G7: 710000 | H7: 4014000 | I7: 360000
B8: MSS-004 | C8: Avril | D8: 2025 | E8: 22200000 | F8: 1880000 | G8: 540000 | H8: 3996000 | I8: 350000
B9: MSS-005 | C9: Mai | D9: 2025 | E9: 22500000 | F9: 1950000 | G9: 680000 | H9: 4050000 | I9: 370000
B10: MSS-006 | C10: Juin | D10: 2025 | E10: 22700000 | F10: 2000000 | G10: 750000 | H10: 4086000 | I10: 380000
B11: =IF(C11="","MSS-"&TEXT(COUNTA($C$5:C11),"000")) | J11: =E11+F11+G11+H11+I11 | K11: =IF(OR(J11="",ROW()=5),"",(J11-INDIRECT("J"&(ROW()-1)))/INDIRECT("J"&(ROW()-1)))
B12: =IF(C12="","MSS-"&TEXT(COUNTA($C$5:C12),"000")) | J12: =E12+F12+G12+H12+I12 | K12: =IF(OR(J12="",ROW()=5),"",(J12-INDIRECT("J"&(ROW()-1)))/INDIRECT("J"&(ROW()-1)))
B13: =IF(C13="","MSS-"&TEXT(COUNTA($C$5:C13),"000")) | J13: =E13+F13+G13+H13+I13 | K13: =IF(OR(J13="",ROW()=5),"",(J13-INDIRECT("J"&(ROW()-1)))/INDIRECT("J"&(ROW()-1)))
B14: =IF(C14="","MSS-"&TEXT(COUNTA($C$5:C14),"000")) | J14: =E14+F14+G14+H14+I14 | K14: =IF(OR(J14="",ROW()=5),"",(J14-INDIRECT("J"&(ROW()-1)))/INDIRECT("J"&(ROW()-1)))
B15: =IF(C15="","MSS-"&TEXT(COUNTA($C$5:C15),"000")) | J15: =E15+F15+G15+H15+I15 | K15: =IF(OR(J15="",ROW()=5),"",(J15-INDIRECT("J"&(ROW()-1)))/INDIRECT("J"&(ROW()-1)))
B16: =IF(C16="","MSS-"&TEXT(COUNTA($C$5:C16),"000")) | J16: =E16+F16+G16+H16+I16 | K16: =IF(OR(J16="",ROW()=5),"",(J16-INDIRECT("J"&(ROW()-1)))/INDIRECT("J"&(ROW()-1)))
B17: =IF(C17="","MSS-"&TEXT(COUNTA($C$5:C17),"000")) | J17: =E17+F17+G17+H17+I17 | K17: =IF(OR(J17="",ROW()=5),"",(J17-INDIRECT("J"&(ROW()-1)))/INDIRECT("J"&(ROW()-1)))
B18: =IF(C18="","MSS-"&TEXT(COUNTA($C$5:C18),"000")) | J18: =E18+F18+G18+H18+I18 | K18: =IF(OR(J18="",ROW()=5),"",(J18-INDIRECT("J"&(ROW()-1)))/INDIRECT("J"&(ROW()-1)))
B19: =IF(C19="","MSS-"&TEXT(COUNTA($C$5:C19),"000")) | J19: =E19+F19+G19+H19+I19 | K19: =IF(OR(J19="",ROW()=5),"",(J19-INDIRECT("J"&(ROW()-1)))/INDIRECT("J"&(ROW()-1)))
B20: =IF(C20="","MSS-"&TEXT(COUNTA($C$5:C20),"000")) | J20: =E20+F20+G20+H20+I20 | K20: =IF(OR(J20="",ROW()=5),"",(J20-INDIRECT("J"&(ROW()-1)))/INDIRECT("J"&(ROW()-1)))
B21: =IF(C21="","MSS-"&TEXT(COUNTA($C$5:C21),"000")) | J21: =E21+F21+G21+H21+I21 | K21: =IF(OR(J21="",ROW()=5),"",(J21-INDIRECT("J"&(ROW()-1)))/INDIRECT("J"&(ROW()-1)))
B22: =IF(C22="","MSS-"&TEXT(COUNTA($C$5:C22),"000")) | J22: =E22+F22+G22+H22+I22 | K22: =IF(OR(J22="",ROW()=5),"",(J22-INDIRECT("J"&(ROW()-1)))/INDIRECT("J"&(ROW()-1)))
... B110: =IF(C110="","MSS-"&TEXT(COUNTA($C$5:C110),"000")) | J110: =E110+F110+G110+H110+I110 | K110: =IF(OR(J110="",ROW()=5),"",(J110-INDIRECT("J"&(ROW()-1)))/INDIRECT("J"&(ROW()-1)))
B112: TOTAL | E112: =SUM(E5:E104) | F112: =SUM(F5:F104) | G112: =SUM(G5:G104) | H112: =SUM(H5:H104) | I112: =SUM(I5:I104) | J112: =SUM(J5:J104)
B114: INDICATEURS (mis a jour automatiquement)
B115: Masse totale | D115: Masse moy. mensuelle
B116: =SUM(J5:J104) | D116: =IFERROR(AVERAGE(J5:J104),0)

Sheet 9-Ratio Masse Salariale CA
B2: RATIO MASSE SALARIALE / CA (#143)
B3: TABLEAU DYNAMIQUE — Saisissez dans la prochaine ligne jaune. Les calculs se mettent a jour automatiquement.
B4: N° | C4: Mois | D4: Annee | E4: Masse Salariale (FCFA) | F4: Chiffre d'Affaires (FCFA) | G4: Ratio MS/CA (%) | H4: Ratio Objectif (%) | I4: Ecart (pts) | J4: Tendance
B5: RMC-001 | C5: Janvier | D5: 2025 | E5: 28780000 | F5: 85000000 | H5: 0.35
B6: RMC-002 | C6: Fevrier | D6: 2025 | E6: 28913000 | F6: 78000000 | H6: 0.35
B7: RMC-003 | C7: Mars | D7: 2025 | E7: 29324000 | F7: 92000000 | H7: 0.35
B8: RMC-004 | C8: Avril | D8: 2025 | E8: 29006000 | F8: 88000000 | H8: 0.35
B9: RMC-005 | C9: Mai | D9: 2025 | E9: 29550000 | F9: 95000000 | H9: 0.35
B10: RMC-006 | C10: Juin | D10: 2025 | E10: 29916000 | F10: 102000000 | H10: 0.35
B11: =IF(C11="","RMC-"&TEXT(COUNTA($C$5:C11),"000")) | G11: =IF(OR(E11="",F11=""),"",E11/F11) | I11: =IF(OR(G11="",H11=""),"",H11-G11)
B12: =IF(C12="","RMC-"&TEXT(COUNTA($C$5:C12),"000")) | G12: =IF(OR(E12="",F12=""),"",E12/F12) | I12: =IF(OR(G12="",H12=""),"",H12-G12)
B13: =IF(C13="","RMC-"&TEXT(COUNTA($C$5:C13),"000")) | G13: =IF(OR(E13="",F13=""),"",E13/F13) | I13: =IF(OR(G13="",H13=""),"",H13-G13)
B14: =IF(C14="","RMC-"&TEXT(COUNTA($C$5:C14),"000")) | G14: =IF(OR(E14="",F14=""),"",E14/F14) | I14: =IF(OR(G14="",H14=""),"",H14-G14)
B15: =IF(C15="","RMC-"&TEXT(COUNTA($C$5:C15),"000")) | G15: =IF(OR(E15="",F15=""),"",E15/F15) | I15: =IF(OR(G15="",H15=""),"",H15-G15)
B16: =IF(C16="","RMC-"&TEXT(COUNTA($C$5:C16),"000")) | G16: =IF(OR(E16="",F16=""),"",E16/F16) | I16: =IF(OR(G16="",H16=""),"",H16-G16)
B17: =IF(C17="","RMC-"&TEXT(COUNTA($C$5:C17),"000")) | G17: =IF(OR(E17="",F17=""),"",E17/F17) | I17: =IF(OR(G17="",H17=""),"",H17-G17)
B18: =IF(C18="","RMC-"&TEXT(COUNTA($C$5:C18),"000")) | G18: =IF(OR(E18="",F18=""),"",E18/F18) | I18: =IF(OR(G18="",H18=""),"",H18-G18)
B19: =IF(C19="","RMC-"&TEXT(COUNTA($C$5:C19),"000")) | G19: =IF(OR(E19="",F19=""),"",E19/F19) | I19: =IF(OR(G19="",H19=""),"",H19-G19)
B20: =IF(C20="","RMC-"&TEXT(COUNTA($C$5:C20),"000")) | G20: =IF(OR(E20="",F20=""),"",E20/F20) | I20: =IF(OR(G20="",H20=""),"",H20-G20)
B21: =IF(C21="","RMC-"&TEXT(COUNTA($C$5:C21),"000")) | G21: =IF(OR(E21="",F21=""),"",E21/F21) | I21: =IF(OR(G21="",H21=""),"",H21-G21)
B22: =IF(C22="","RMC-"&TEXT(COUNTA($C$5:C22),"000")) | G22: =IF(OR(E22="",F22=""),"",E22/F22) | I22: =IF(OR(G22="",H22=""),"",H22-G22)
... B110: =IF(C110="","RMC-"&TEXT(COUNTA($C$5:C110),"000")) | G110: =IF(OR(E110="",F110=""),"",E110/F110) | I110: =IF(OR(G110="",H110=""),"",H110-G110)
B112: INDICATEURS (mis a jour automatiquement)
B113: Ratio moyen | D113: Mois hors objectif
B114: =IFERROR(AVERAGE(G5:G104),0) | D114: =COUNTIF(G5:G104,">"&0.35)

Sheet 10-Cout Complet Employe
B2: COUT COMPLET PAR EMPLOYE (#144)
B3: TABLEAU DYNAMIQUE — Saisissez dans la prochaine ligne jaune. Les calculs se mettent a jour automatiquement.
B4: N° | C4: Employe | D4: Poste | E4: Salaire Brut Annuel | F4: Primes Annuelles | G4: Cotisations Patronales | H4: Formation (FCFA) | I4: Avantages en Nature | J4: Cout Complet Total | K4: Cout Mensuel Moyen
B5: CCE-001 | C5: Nkoulou Mbarga P. | D5: Chef Reception | E5: 3240000 | F5: 360000 | G5: 583200 | H5: 120000 | I5: 180000
B6: CCE-002 | C6: Biyong Jean M. | D6: Chef Cuisine | E6: 3960000 | F6: 480000 | G6: 712800 | H6: 150000 | I6: 240000
B7: CCE-003 | C7: Tchinda R. | D7: DRH | E7: 5400000 | F7: 600000 | G7: 972000 | H7: 200000 | I7: 300000
B8: CCE-004 | C8: Nganou D. | D8: Receptionniste | E8: 2160000 | F8: 240000 | G8: 388800 | H8: 60000 | I8: 120000
B9: CCE-005 | C9: Fouda M. | D9: Cuisinier | E9: 2640000 | F9: 288000 | G9: 475200 | H9: 75000 | I9: 180000
B10: =IF(C10="","CCE-"&TEXT(COUNTA($C$5:C10),"000")) | J10: =E10+F10+G10+H10+I10 | K10: =IF(J10="","",J10/12)
B11: =IF(C11="","CCE-"&TEXT(COUNTA($C$5:C11),"000")) | J11: =E11+F11+G11+H11+I11 | K11: =IF(J11="","",J11/12)
B12: =IF(C12="","CCE-"&TEXT(COUNTA($C$5:C12),"000")) | J12: =E12+F12+G12+H12+I12 | K12: =IF(J12="","",J12/12)
B13: =IF(C13="","CCE-"&TEXT(COUNTA($C$5:C13),"000")) | J13: =E13+F13+G13+H13+I13 | K13: =IF(J13="","",J13/12)
B14: =IF(C14="","CCE-"&TEXT(COUNTA($C$5:C14),"000")) | J14: =E14+F14+G14+H14+I14 | K14: =IF(J14="","",J14/12)
B15: =IF(C15="","CCE-"&TEXT(COUNTA($C$5:C15),"000")) | J15: =E15+F15+G15+H15+I15 | K15: =IF(J15="","",J15/12)
B16: =IF(C16="","CCE-"&TEXT(COUNTA($C$5:C16),"000")) | J16: =E16+F16+G16+H16+I16 | K16: =IF(J16="","",J16/12)
B17: =IF(C17="","CCE-"&TEXT(COUNTA($C$5:C17),"000")) | J17: =E17+F17+G17+H17+I17 | K17: =IF(J17="","",J17/12)
B18: =IF(C18="","CCE-"&TEXT(COUNTA($C$5:C18),"000")) | J18: =E18+F18+G18+H18+I18 | K18: =IF(J18="","",J18/12)
B19: =IF(C19="","CCE-"&TEXT(COUNTA($C$5:C19),"000")) | J19: =E19+F19+G19+H19+I19 | K19: =IF(J19="","",J19/12)
B20: =IF(C20="","CCE-"&TEXT(COUNTA($C$5:C20),"000")) | J20: =E20+F20+G20+H20+I20 | K20: =IF(J20="","",J20/12)
B21: =IF(C21="","CCE-"&TEXT(COUNTA($C$5:C21),"000")) | J21: =E21+F21+G21+H21+I21 | K21: =IF(J21="","",J21/12)
... B109: =IF(C109="","CCE-"&TEXT(COUNTA($C$5:C109),"000")) | J109: =E109+F109+G109+H109+I109 | K109: =IF(J109="","",J109/12)
B111: TOTAL | E111: =SUM(E5:E104) | F111: =SUM(F5:F104) | G111: =SUM(G5:G104) | H111: =SUM(H5:H104) | I111: =SUM(I5:I104) | J111: =SUM(J5:J104)
B113: INDICATEURS (mis a jour automatiquement)
B114: Employes | D114: Cout total equipe | F114: Cout moyen / employe
B115: =COUNTIF(B5:B104,"<>") | D115: =SUM(J5:J104) | F115: =IFERROR(SUM(J5:J104)/COUNTIF(B5:B104,"<>"),0)

Sheet 11-Bilan Social Annuel
B2: RAPPORT SOCIAL ANNUEL / BILAN SOCIAL (#145)
B3: TABLEAU DYNAMIQUE — Saisissez dans la prochaine ligne jaune. Les calculs se mettent a jour automatiquement.
B4: N° | C4: Rubrique Bilan Social | D4: Annee | E4: Valeur | F4: Annee Precedente | G4: Variation (%) | H4: Observations
B5: BSO-001 | C5: Effectif au 31/12 | D5: 2025 | E5: 89 | F5: 85 | H5: Hausse liee a l'expansion
B6: BSO-002 | C6: Masse salariale brute (M FCFA) | D6: 2025 | E6: 348 | F6: 320 | H6: Augmentation salariale 5%
B7: BSO-003 | C7: Taux turnover annuel | D7: 2025 | E7: 0.18 | F7: 0.22 | H7: Amelioration retenue
B8: BSO-004 | C8: Heures formation totales | D8: 2025 | E8: 420 | F8: 380 | H8: +10.5% vs N-1
B9: BSO-005 | C9: Nb accidents de travail | D9: 2025 | E9: 3 | F9: 5 | H9: Baisse appreciable
B10: BSO-006 | C10: Taux absentéisme | D10: 2025 | E10: 0.042 | F10: 0.048 | H10: Politique presentialite
B11: BSO-007 | C11: Nb recrutements | D11: 2025 | E11: 18 | F11: 14 | H11: Rotation et expansion
B12: BSO-008 | C12: Ratio MS/CA | D12: 2025 | E12: 0.32 | F12: 0.34 | H12: Objectif 35% atteint
B13: =IF(C13="","BSO-"&TEXT(COUNTA($C$5:C13),"000")) | G13: =IF(OR(F13="",F13=0),"",(G13-F13)/F13)
B14: =IF(C14="","BSO-"&TEXT(COUNTA($C$5:C14),"000")) | G14: =IF(OR(F14="",F14=0),"",(G14-F14)/F14)
B15: =IF(C15="","BSO-"&TEXT(COUNTA($C$5:C15),"000")) | G15: =IF(OR(F15="",F15=0),"",(G15-F15)/F15)
B16: =IF(C16="","BSO-"&TEXT(COUNTA($C$5:C16),"000")) | G16: =IF(OR(F16="",F16=0),"",(G16-F16)/F16)
B17: =IF(C17="","BSO-"&TEXT(COUNTA($C$5:C17),"000")) | G17: =IF(OR(F17="",F17=0),"",(G17-F17)/F17)
B18: =IF(C18="","BSO-"&TEXT(COUNTA($C$5:C18),"000")) | G18: =IF(OR(F18="",F18=0),"",(G18-F18)/F18)
B19: =IF(C19="","BSO-"&TEXT(COUNTA($C$5:C19),"000")) | G19: =IF(OR(F19="",F19=0),"",(G19-F19)/F19)
B20: =IF(C20="","BSO-"&TEXT(COUNTA($C$5:C20),"000")) | G20: =IF(OR(F20="",F20=0),"",(G20-F20)/F20)
B21: =IF(C21="","BSO-"&TEXT(COUNTA($C$5:C21),"000")) | G21: =IF(OR(F21="",F21=0),"",(G21-F21)/F21)
B22: =IF(C22="","BSO-"&TEXT(COUNTA($C$5:C22),"000")) | G22: =IF(OR(F22="",F22=0),"",(G22-F22)/F22)
B23: =IF(C23="","BSO-"&TEXT(COUNTA($C$5:C23),"000")) | G23: =IF(OR(F23="",F23=0),"",(G23-F23)/F23)
B24: =IF(C24="","BSO-"&TEXT(COUNTA($C$5:C24),"000")) | G24: =IF(OR(F24="",F24=0),"",(G24-F24)/F24)
... B112: =IF(C112="","BSO-"&TEXT(COUNTA($C$5:C112),"000")) | G112: =IF(OR(F112="",F112=0),"",(G112-F112)/F112)
B114: INDICATEURS (mis a jour automatiquement)
B115: Rubriques | D115: Rubriques en hausse
B116: =COUNTIF(B5:B104,"<>") | D116: =COUNTIF(G5:G104,">"&0)

Sheet 12-TdB Previsionnel RH
B2: TdB PREVISIONNEL RH (#146)
B3: TABLEAU DYNAMIQUE — Saisissez dans la prochaine ligne jaune. Les calculs se mettent a jour automatiquement.
B4: N° | C4: Indicateur | D4: Valeur Actuelle | E4: Prevision T+1 | F4: Prevision T+2 | G4: Prevision T+3 | H4: Tendance | I4: Hypothese
B5: PRE-001 | C5: Effectif prevu | D5: 89 | E5: 95 | F5: 102 | G5: 108 | H5: Hausse | I5: Expansion hoteliere + nouvelles chambres
B6: PRE-002 | C6: Masse salariale (M FCFA) | D6: 348 | E6: 375 | F6: 405 | G6: 438 | H6: Hausse | I6: Embauches + augmentations 3%/an
B7: PRE-003 | C7: Taux turnover prevu | D7: 0.18 | E7: 0.16 | F7: 0.14 | G7: 0.12 | H7: Baisse | I7: Amelioration conditions travail
B8: PRE-004 | C8: Budget formation (M FCFA) | D8: 4.2 | E8: 5 | F8: 6 | G8: 7.2 | H8: Hausse | I8: Renforcement competences
B9: PRE-005 | C9: Ratio MS/CA prevu | D9: 0.32 | E9: 0.31 | F9: 0.3 | G9: 0.29 | H9: Baisse | I9: CA croit plus vite que MS
B10: =IF(C10="","PRE-"&TEXT(COUNTA($C$5:C10),"000"))
B11: =IF(C11="","PRE-"&TEXT(COUNTA($C$5:C11),"000"))
B12: =IF(C12="","PRE-"&TEXT(COUNTA($C$5:C12),"000"))
B13: =IF(C13="","PRE-"&TEXT(COUNTA($C$5:C13),"000"))
B14: =IF(C14="","PRE-"&TEXT(COUNTA($C$5:C14),"000"))
B15: =IF(C15="","PRE-"&TEXT(COUNTA($C$5:C15),"000"))
B16: =IF(C16="","PRE-"&TEXT(COUNTA($C$5:C16),"000"))
B17: =IF(C17="","PRE-"&TEXT(COUNTA($C$5:C17),"000"))
B18: =IF(C18="","PRE-"&TEXT(COUNTA($C$5:C18),"000"))
B19: =IF(C19="","PRE-"&TEXT(COUNTA($C$5:C19),"000"))
B20: =IF(C20="","PRE-"&TEXT(COUNTA($C$5:C20),"000"))
B21: =IF(C21="","PRE-"&TEXT(COUNTA($C$5:C21),"000"))
... B109: =IF(C109="","PRE-"&TEXT(COUNTA($C$5:C109),"000"))
B111: INDICATEURS (mis a jour automatiquement)
B112: Indicateurs previsionnels
B113: =COUNTIF(B5:B104,"<>")

Sheet 13-Benchmarking RH
B2: BENCHMARKING RH (#147)
B3: TABLEAU DYNAMIQUE — Saisissez dans la prochaine ligne jaune. Les calculs se mettent a jour automatiquement.
B4: N° | C4: Indicateur | D4: Unite | E4: Notre Hotel | F4: Concurent A | G4: Concurent B | H4: Moyenne Secteur | I4: Positionnement | J4: Ecart vs Moy. Secteur | K4: Statut
B5: BNK-001 | C5: Taux turnover | D5: % | E5: 18 | F5: 22 | G5: 15 | H5: 20 | K5: En cours
B6: BNK-002 | C6: Ratio MS/CA | D6: % | E6: 32 | F6: 35 | G6: 30 | H6: 33 | K6: En cours
B7: BNK-003 | C7: Delai recrutement | D7: jours | E7: 28 | F7: 35 | G7: 22 | H7: 30 | K7: En cours
B8: BNK-004 | C8: Heures form./employe/an | D8: heures | E8: 5.2 | F8: 4 | G8: 6.5 | H8: 5 | K8: En cours
B9: BNK-005 | C9: Taux absentéisme | D9: % | E9: 4.2 | F9: 5.1 | G9: 3.8 | H9: 4.5 | K9: En cours
B10: =IF(C10="","BNK-"&TEXT(COUNTA($C$5:C10),"000")) | J10: =IF(OR(I10="",I10=0),"",G10-I10)
B11: =IF(C11="","BNK-"&TEXT(COUNTA($C$5:C11),"000")) | J11: =IF(OR(I11="",I11=0),"",G11-I11)
B12: =IF(C12="","BNK-"&TEXT(COUNTA($C$5:C12),"000")) | J12: =IF(OR(I12="",I12=0),"",G12-I12)
B13: =IF(C13="","BNK-"&TEXT(COUNTA($C$5:C13),"000")) | J13: =IF(OR(I13="",I13=0),"",G13-I13)
B14: =IF(C14="","BNK-"&TEXT(COUNTA($C$5:C14),"000")) | J14: =IF(OR(I14="",I14=0),"",G14-I14)
B15: =IF(C15="","BNK-"&TEXT(COUNTA($C$5:C15),"000")) | J15: =IF(OR(I15="",I15=0),"",G15-I15)
B16: =IF(C16="","BNK-"&TEXT(COUNTA($C$5:C16),"000")) | J16: =IF(OR(I16="",I16=0),"",G16-I16)
B17: =IF(C17="","BNK-"&TEXT(COUNTA($C$5:C17),"000")) | J17: =IF(OR(I17="",I17=0),"",G17-I17)
B18: =IF(C18="","BNK-"&TEXT(COUNTA($C$5:C18),"000")) | J18: =IF(OR(I18="",I18=0),"",G18-I18)
B19: =IF(C19="","BNK-"&TEXT(COUNTA($C$5:C19),"000")) | J19: =IF(OR(I19="",I19=0),"",G19-I19)
B20: =IF(C20="","BNK-"&TEXT(COUNTA($C$5:C20),"000")) | J20: =IF(OR(I20="",I20=0),"",G20-I20)
B21: =IF(C21="","BNK-"&TEXT(COUNTA($C$5:C21),"000")) | J21: =IF(OR(I21="",I21=0),"",G21-I21)
... B109: =IF(C109="","BNK-"&TEXT(COUNTA($C$5:C109),"000")) | J109: =IF(OR(I109="",I109=0),"",G109-I109)
B111: INDICATEURS (mis a jour automatiquement)
B112: Indicateurs compares | D112: Au dessus moyenne
B113: =COUNTIF(B5:B104,"<>") | D113: =COUNTIF(J5:J104,">"&0)

Sheet 14-Enquetes Sat. Client Eff.
B2: ENQUETES SATISFACTION CLIENT vs. EFFECTIFS (#148)
B3: TABLEAU DYNAMIQUE — Saisissez dans la prochaine ligne jaune. Les calculs se mettent a jour automatiquement.
B4: N° | C4: Mois | D4: Annee | E4: Note Satisfaction Client (/10) | F4: Effectif Service | G4: Taux Absenteisme (%) | H4: Taux Turnover (%) | I4: Heures Formation | J4: Correlation Client/Effectif
B5: ESC-001 | C5: Janvier | D5: 2025 | E5: 8.2 | F5: 89 | G5: 3.8 | H5: 2.2 | I5: 35
B6: ESC-002 | C6: Fevrier | D6: 2025 | E6: 7.9 | F6: 89 | G6: 4.1 | H6: 1.1 | I6: 42
B7: ESC-003 | C7: Mars | D7: 2025 | E7: 7.5 | F7: 90 | G7: 4.5 | H7: 3.3 | I7: 38
B8: ESC-004 | C8: Avril | D8: 2025 | E8: 8 | F8: 89 | G8: 3.9 | H8: 2.2 | I8: 50
B9: ESC-005 | C9: Mai | D9: 2025 | E9: 8.4 | F9: 88 | G9: 3.5 | H9: 2.3 | I9: 55
B10: ESC-006 | C10: Juin | D10: 2025 | E10: 8.6 | F10: 89 | G10: 3.2 | H10: 2.2 | I10: 60
B11: =IF(C11="","ESC-"&TEXT(COUNTA($C$5:C11),"000"))
B12: =IF(C12="","ESC-"&TEXT(COUNTA($C$5:C12),"000"))
B13: =IF(C13="","ESC-"&TEXT(COUNTA($C$5:C13),"000"))
B14: =IF(C14="","ESC-"&TEXT(COUNTA($C$5:C14),"000"))
B15: =IF(C15="","ESC-"&TEXT(COUNTA($C$5:C15),"000"))
B16: =IF(C16="","ESC-"&TEXT(COUNTA($C$5:C16),"000"))
B17: =IF(C17="","ESC-"&TEXT(COUNTA($C$5:C17),"000"))
B18: =IF(C18="","ESC-"&TEXT(COUNTA($C$5:C18),"000"))
B19: =IF(C19="","ESC-"&TEXT(COUNTA($C$5:C19),"000"))
B20: =IF(C20="","ESC-"&TEXT(COUNTA($C$5:C20),"000"))
B21: =IF(C21="","ESC-"&TEXT(COUNTA($C$5:C21),"000"))
B22: =IF(C22="","ESC-"&TEXT(COUNTA($C$5:C22),"000"))
... B110: =IF(C110="","ESC-"&TEXT(COUNTA($C$5:C110),"000"))
B112: INDICATEURS (mis a jour automatiquement)
B113: Mois analyses | D113: Satisfaction moy. | F113: Effectif moy.
B114: =COUNTIF(B5:B104,"<>") | D114: =IFERROR(AVERAGE(E5:E104),0) | F114: =IFERROR(AVERAGE(F5:F104),0)
