Workbook

Sheet _Données Employés
A1: Matricule | B1: Nom | C1: Prénom | D1: Département | E1: Poste | F1: Salaire Brut | G1: Genre | H1: Date Embauche
A2: EMP-001 | B2: Nganou | C2: Clarisse | D2: Cuisine & Restauration | E2: Chef | F2: 450000 | G2: F | H2: 2020-01-15
A3: EMP-002 | B3: Tagne | C3: René | D3: Réception & Front Office | E3: Réceptionniste | F3: 165000 | G3: H | H3: 2019-06-01
A4: EMP-003 | B4: Fotso | C4: Camille | D4: Cuisine & Restauration | E4: Cuisinier | F4: 180000 | G4: H | H4: 2021-03-10
A5: EMP-004 | B5: Tchinda | C5: Arlette | D5: Service Client | E5: Assistante RH | F5: 200000 | G5: F | H5: 2022-09-01
A6: EMP-005 | B6: Ngansop | C6: Sylvie | D6: Finance & Comptabilité | E6: Comptable senior | F6: 250000 | G6: F | H6: 2018-02-20
A7: EMP-006 | B7: Fokam | C7: Eric | D7: Réception & Front Office | E7: Chef Réception | F7: 280000 | G7: H | H7: 2017-08-15
A8: EMP-007 | B8: Tchouankou | C8: Paul | D8: Étage & Housekeeping | E8: Chef Étage | F8: 230000 | G8: H | H8: 2020-11-01
A9: EMP-008 | B9: Awa | C9: Fatou | D9: Commercial | E9: Agent Commercial | F9: 155000 | G9: F | H9: 2023-01-15
A10: EMP-009 | B10: Bouba | C10: Ahmed | D10: Cuisine & Restauration | E10: Sous-Chef | F10: 210000 | G10: H | H10: 2019-04-01
A11: EMP-010 | B11: Kamga | C11: Patrice | D11: Sécurité | E11: Chef Sécurité | F11: 210000 | G11: H | H11: 2021-07-01
A12: EMP-011 | B12: Ngo | C12: Delphine | D12: Marketing & Communication | E12: Chef Marketing | F12: 300000 | G12: F | H12: 2018-05-15
A13: EMP-012 | B13: Tamo | C13: Elvis | D13: Logistique & Approvisionnement | E13: Chef Logistique | F13: 240000 | G13: H | H13: 2022-03-01
... A15: EMP-014 | B15: Kane | C15: Adama | D15: Direction Générale | E15: DAF | F15: 350000 | G15: H | H15: 2016-01-10

Sheet 1-Tableau de Bord
B2: DOMAINE 18 — RSE & DEVELOPPEMENT DURABLE RH
B3: TABLEAU DE BORD — Vue synthetique de tous les indicateurs du domaine (mis a jour automatiquement)
B5: Politiques RSE | E5: Actions environnementales | H5: Initiatives diversite | K5: Amenagements handicap
B6: =COUNTIF('2-Politique RSE Hotel'!B5:B104,"<>") | E6: =COUNTIF('3-Actions Environnementales'!B5:B104,"<>") | H6: =COUNTIF('4-Diversite & Inclusion'!B5:B104,"<>") | K6: =COUNTIF('5-Handicap & Amenag. Poste'!B5:B104,"<>")
B9: Initiatives bien-etre | E9: Actions sociales | H9: Formations RSE | K9: Sources CO2
B10: =COUNTIF('6-Bien-Etre au Travail'!B5:B104,"<>") | E10: =COUNTIF('7-Actions Sociales & Solid.'!B5:B104,"<>") | H10: =COUNTIF('8-Formation RSE'!B5:B104,"<>") | K10: =COUNTIF('9-Bilan Carbone RH'!B5:B104,"<>")
B13: Partenariats actifs | E13: Indicateurs RSE | H13: Emissions totales (tCO2) | K13: Budget enviro. (FCFA)
B14: =COUNTIF('10-Partenariats Communaute'!B5:B104,"<>") | E14: =COUNTIF('11-Indicateurs RSE'!B5:B104,"<>") | H14: =IFERROR(SUM('9-Bilan Carbone RH'!K5:K104),0) | K14: =IFERROR(SUM('3-Actions Environnementales'!J5:J104),0)
B18: ACTIONS RSE PAR AXE & PARTENARIATS PAR STATUT
B19: Axe RSE | C19: Nombre
B20: Environnement | C20: =COUNTIF('12-Suivi Actions RSE'!D5:D104,"Environnement")
B21: Social | C21: =COUNTIF('12-Suivi Actions RSE'!D5:D104,"Social")
B22: Diversite & Inclusion | C22: =COUNTIF('12-Suivi Actions RSE'!D5:D104,"Diversite & Inclusion")
B23: Bien-etre | C23: =COUNTIF('12-Suivi Actions RSE'!D5:D104,"Bien-etre")
B24: Communaute | C24: =COUNTIF('12-Suivi Actions RSE'!D5:D104,"Communaute")
B25: Formation | C25: =COUNTIF('12-Suivi Actions RSE'!D5:D104,"Formation")
B26: Governance | C26: =COUNTIF('12-Suivi Actions RSE'!D5:D104,"Governance")
H28: Statut Partenariat | I28: Nombre
H29: Actif | I29: =COUNTIF('10-Partenariats Communaute'!K5:K104,"Actif")
H30: En negotation | I30: =COUNTIF('10-Partenariats Communaute'!K5:K104,"En negotation")
H31: En pause | I31: =COUNTIF('10-Partenariats Communaute'!K5:K104,"En pause")
H32: Termine | I32: =COUNTIF('10-Partenariats Communaute'!K5:K104,"Termine")
H33: Non renouvele | I33: =COUNTIF('10-Partenariats Communaute'!K5:K104,"Non renouvele")

Sheet _Lists
B1: departement | C1: poste_hotel | D1: axe_rse | E1: type_action_rse | F1: statut_action_rse | G1: type_handicap | H1: niveau_amenagement | I1: type_bien_etre | J1: statut_bien_etre | K1: type_formation_rse | L1: statut_formation | M1: type_partenariat | N1: statut_partenariat | O1: periode_ods | P1: statut_indicateur_rse | Q1: echelle_satisfaction | R1: statut_action | S1: source_financement_rse | T1: annee | U1: mois_annee
B2: Direction Générale | C2: DG | D2: Environnement | E2: Reduction dechets | F2: Planifiee | G2: Moteur | H2: Aucun amenagement | I2: Santé physique | J2: En cours | K2: Eco-gestes | L2: Planifiee | M2: Ecole / Universite | N2: En negotation | O2: Mensuelle | P2: En cours | Q2: Tres insatisfait | R2: Planifiee | S2: Budget hotel | T2: 2020 | U2: Janvier 2025
B3: Service Client | C3: DRH | D3: Social | E3: Economie energie | F3: En cours | G3: Visuel | H3: Amenagement leger | I3: Santé mentale | J3: Planifie | K3: Tri selectif | L3: En cours | M3: ONG locale | N3: Actif | O3: Trimestrielle | P3: Atteint | Q3: Insatisfait | R3: En cours | S3: Subvention | T3: 2021 | U3: Fevrier 2025
B4: Finance & Comptabilité | C4: Assistante RH | D4: Governance | E4: Economie eau | F4: Terminee | G4: Auditif | H4: Amenagement modere | I4: Activite sportive | J4: Termine | K4: Economie d'energie | L4: Terminee | M4: Association | N4: En pause | O4: Semestrielle | P4: Non atteint | Q4: Neutre | R4: Terminee | S4: Partenariat | T4: 2022 | U4: Mars 2025
B5: Marketing & Communication | C5: DAF | D5: Diversite & Inclusion | E5: Tri selectif | F5: Reportee | G5: Mental | H5: Amenagement important | I5: Alimentation saine | J5: Recurrent | K5: Sensibilisation RSE | L5: Reportee | M5: Collectivite locale | N5: Termine | O5: Annuelle | P5: En amelioration | Q5: Satisfait | R5: Reportee | S5: Fondation | T5: 2023 | U5: Avril 2025
B6: Maintenance | C6: Comptable senior | D6: Bien-etre | E6: Mobilite durable | F6: Annulee | G6: Maladie chronique | H6: Amenagement complet | I6: Gestion du stress | J6: Suspendu | K6: Diversite & inclusion | L6: Annulee | M6: Fournisseur local | N6: Non renouvele | O6: Ponctuelle | P6: Non mesure | Q6: Tres satisfait | R6: Annulee | S6: Bénévolat | T6: 2024 | U6: Mai 2025
B7: Commercial | C7: Chef Comptable | D7: Communaute | E7: Sensibilisation | F7: En evaluation | G7: Autre | I7: Mediation | J7: Annule | K7: Gestion du stress | M7: Autre hotel | S7: Autre | T7: 2025 | U7: Juin 2025
B8: Logistique & Approvisionnement | C8: Chef Marketing | D8: Formation & Developpement | E8: Partenariat local | F8: En amelioration | I8: Conseiller bien-etre | K8: Premiers secours | M8: Chambre de metier | T8: 2026 | U8: Juillet 2025
B9: Cuisine & Restauration | C9: Chef de service IT | D9: Ethique | E9: Action sociale | I9: Amenagement horaires | K9: Sécurité au travail | M9: Organisme de formation | T9: 2027 | U9: Aout 2025
B10: Réception & Front Office | C10: Technicien IT | E10: Formation RSE | I10: Teletravail | K10: Ethique professionnelle | M10: Autre | U10: Septembre 2025
B11: Sécurité | C11: Chef Commercial | E11: Amenagement espace | I11: Espace detente | K11: Developpement durable | U11: Octobre 2025
B12: Étage & Housekeeping | C12: Agent Commercial | E12: Santé & Sécurité | I12: Formation sensibilisation | K12: Autre | U12: Novembre 2025
C13: Chef Logistique | E13: Diversite recrutement | I13: Autre | U13: Decembre 2025
C14: Agent Logistique | E14: Inclusion handicap | U14: Janvier 2026
C15: Chef Production | E15: Equilibre vie pro/perso | U15: Fevrier 2026
C16: Responsable Service Client | E16: Autre | U16: Mars 2026
C17: Conseiller Client | U17: Avril 2026
C18: Chef Reception | U18: Mai 2026
C19: Receptionniste | U19: Juin 2026
C20: Chef Cuisine
C21: Cuisinier
C22: Plongeur
C23: Chef Entretien
C24: Technicien Maintenance
C25: Agent Sécurité
C26: Stagiaire RH
C27: Stagiaire
C28: Autre

Sheet 2-Politique RSE Hotel
B2: POLITIQUE RSE HOTEL (#147)
B3: TABLEAU DYNAMIQUE — Saisissez dans la prochaine ligne jaune. Les calculs se mettent a jour automatiquement.
B4: N° | C4: Engagement / Politique | D4: Axe RSE | E4: Description | F4: Objectif Mesurable | G4: Responsable | H4: Date Adoption | I4: Date Revision | J4: Statut | K4: Observations
B5: RSE-001 | C5: Charte environnement hotel | D5: Environnement | E5: Reduction de 20% de la consommation d'eau d'ici 2026 | F5: Conso. eau -20% vs 2024 | G5: DG | H5: 45306 | I5: 46037 | J5: En vigueur | K5: Capteurs eau installes salle de bain
B6: RSE-002 | C6: Politique diversite et inclusion | D6: Diversite & Inclusion | E6: Atteindre 40% de femmes cadres d'ici 2027 | F6: 40% femmes cadres | G6: DRH | H6: 45444 | I6: 46539 | J6: En vigueur | K6: Programme mentorat femmes en place
B7: RSE-003 | C7: Politique bien-etre employes | D7: Bien-etre | E7: Score bien-etre >= 4.0/5 dans enquetes annuelles | F7: Score >= 4.0/5 | G7: DRH | H7: 45352 | I7: 46022 | J7: En vigueur | K7: Enquete Q1 2025 planifiee
B8: =IF(C8="","RSE-"&TEXT(COUNTA($C$5:C8),"000"))
B9: =IF(C9="","RSE-"&TEXT(COUNTA($C$5:C9),"000"))
B10: =IF(C10="","RSE-"&TEXT(COUNTA($C$5:C10),"000"))
B11: =IF(C11="","RSE-"&TEXT(COUNTA($C$5:C11),"000"))
B12: =IF(C12="","RSE-"&TEXT(COUNTA($C$5:C12),"000"))
B13: =IF(C13="","RSE-"&TEXT(COUNTA($C$5:C13),"000"))
B14: =IF(C14="","RSE-"&TEXT(COUNTA($C$5:C14),"000"))
B15: =IF(C15="","RSE-"&TEXT(COUNTA($C$5:C15),"000"))
B16: =IF(C16="","RSE-"&TEXT(COUNTA($C$5:C16),"000"))
B17: =IF(C17="","RSE-"&TEXT(COUNTA($C$5:C17),"000"))
B18: =IF(C18="","RSE-"&TEXT(COUNTA($C$5:C18),"000"))
B19: =IF(C19="","RSE-"&TEXT(COUNTA($C$5:C19),"000"))
... B107: =IF(C107="","RSE-"&TEXT(COUNTA($C$5:C107),"000"))
B109: INDICATEURS (mis a jour automatiquement)
B110: Engagements RSE | D110: En vigueur | F110: En amelioration
B111: =COUNTIF(B5:B104,"<>") | D111: =COUNTIF(J5:J104,"En vigueur") | F111: =COUNTIF(J5:J104,"En amelioration")

Sheet 3-Actions Environnementales
B2: ACTIONS ENVIRONNEMENTALES RH (#148)
B3: TABLEAU DYNAMIQUE — Saisissez dans la prochaine ligne jaune. Les calculs se mettent a jour automatiquement.
B4: N° | C4: Action Environnementale | D4: Type Action | E4: Departement Concerne | F4: Description | G4: Date Debut | H4: Date Fin | I4: Responsable | J4: Budget (FCFA) | K4: Economies Estimees (FCFA/an) | L4: Statut
B5: ENV-001 | C5: Installation eclairage LED | D5: Economie energie | E5: Maintenance | F5: Remplacement ampoules par LED dans toutes les chambres | G5: 45667 | H5: 45747 | I5: Chef Entretien | J5: 2500000 | K5: 800000 | L5: En cours
B6: ENV-002 | C6: Tri selectif dechets cuisine | D6: Tri selectif | E6: Cuisine & Restauration | F6: Mise en place bacs de tri dans la cuisine et restau | G6: 45689 | H6: 45716 | I6: Chef Cuisine | J6: 150000 | K6: 200000 | L6: Terminee
B7: ENV-003 | C7: Reduction gaspillage alimentaire | D7: Reduction dechets | E7: Cuisine & Restauration | F7: Programme de gestion des portions et dons alimentaires | G7: 45717 | H7: 46022 | I7: Chef Cuisine | J7: 300000 | K7: 600000 | L7: Planifiee
B8: =IF(C8="","ENV-"&TEXT(COUNTA($C$5:C8),"000"))
B9: =IF(C9="","ENV-"&TEXT(COUNTA($C$5:C9),"000"))
B10: =IF(C10="","ENV-"&TEXT(COUNTA($C$5:C10),"000"))
B11: =IF(C11="","ENV-"&TEXT(COUNTA($C$5:C11),"000"))
B12: =IF(C12="","ENV-"&TEXT(COUNTA($C$5:C12),"000"))
B13: =IF(C13="","ENV-"&TEXT(COUNTA($C$5:C13),"000"))
B14: =IF(C14="","ENV-"&TEXT(COUNTA($C$5:C14),"000"))
B15: =IF(C15="","ENV-"&TEXT(COUNTA($C$5:C15),"000"))
B16: =IF(C16="","ENV-"&TEXT(COUNTA($C$5:C16),"000"))
B17: =IF(C17="","ENV-"&TEXT(COUNTA($C$5:C17),"000"))
B18: =IF(C18="","ENV-"&TEXT(COUNTA($C$5:C18),"000"))
B19: =IF(C19="","ENV-"&TEXT(COUNTA($C$5:C19),"000"))
... B107: =IF(C107="","ENV-"&TEXT(COUNTA($C$5:C107),"000"))
B109: INDICATEURS (mis a jour automatiquement)
B110: Actions environnementales | D110: Budget total (FCFA) | F110: Economies estimees/an
B111: =COUNTIF(B5:B104,"<>") | D111: =SUM(J5:J104) | F111: =SUM(K5:K104)

Sheet 4-Diversite & Inclusion
B2: DIVERSITE & INCLUSION (#149)
B3: TABLEAU DYNAMIQUE — Saisissez dans la prochaine ligne jaune. Les calculs se mettent a jour automatiquement.
B4: N° | C4: Initiative Diversite | D4: Type Action | E4: Groupe Cible | F4: Objectif | G4: Responsable | H4: Date Lancement | I4: Nb Beneficiaires | J4: Resultat Observe | K4: Statut | L4: Observations
B5: DIV-001 | C5: Recrutement equitable | D5: Diversite recrutement | E5: Femmes, Minorites | F5: 50% femmes parmi les candidats retenus | G5: DRH | H5: 45658 | I5: 8 | J5: 42% femmes | K5: En cours | L5: En hausse vs 2024 (35%)
B6: DIV-002 | C6: Mentorat femmes cadres | D6: Diversite recrutement | E6: Femmes cadres | F6: Promouvoir 5 femmes cadres en 2025 | G6: DRH | H6: 45689 | I6: 12 | J6: 2 promotions T1 | K6: En cours | L6: Programme en bonne voie
B7: DIV-003 | C7: Sensibilisation culturelle | D7: Sensibilisation | E7: Tous les employes | F7: 100% employes formes d'ici dec 2025 | G7: DRH | H7: 45717 | I7: 45 | J7: 45 formes T1 | K7: En cours | L7: Formation par module de 2h
B8: =IF(C8="","DIV-"&TEXT(COUNTA($C$5:C8),"000"))
B9: =IF(C9="","DIV-"&TEXT(COUNTA($C$5:C9),"000"))
B10: =IF(C10="","DIV-"&TEXT(COUNTA($C$5:C10),"000"))
B11: =IF(C11="","DIV-"&TEXT(COUNTA($C$5:C11),"000"))
B12: =IF(C12="","DIV-"&TEXT(COUNTA($C$5:C12),"000"))
B13: =IF(C13="","DIV-"&TEXT(COUNTA($C$5:C13),"000"))
B14: =IF(C14="","DIV-"&TEXT(COUNTA($C$5:C14),"000"))
B15: =IF(C15="","DIV-"&TEXT(COUNTA($C$5:C15),"000"))
B16: =IF(C16="","DIV-"&TEXT(COUNTA($C$5:C16),"000"))
B17: =IF(C17="","DIV-"&TEXT(COUNTA($C$5:C17),"000"))
B18: =IF(C18="","DIV-"&TEXT(COUNTA($C$5:C18),"000"))
B19: =IF(C19="","DIV-"&TEXT(COUNTA($C$5:C19),"000"))
... B107: =IF(C107="","DIV-"&TEXT(COUNTA($C$5:C107),"000"))
B109: INDICATEURS (mis a jour automatiquement)
B110: Initiatives diversite | D110: Total beneficiaires | F110: En cours
B111: =COUNTIF(B5:B104,"<>") | D111: =SUM(I5:I104) | F111: =COUNTIF(K5:K104,"En cours")

Sheet 5-Handicap & Amenag. Poste
B2: HANDICAP & AMENAGEMENT POSTE (#150)
B3: TABLEAU DYNAMIQUE — Saisissez dans la prochaine ligne jaune. Les calculs se mettent a jour automatiquement.
B4: N° | C4: Nom Employe | D4: Poste | E4: Departement | F4: Type Handicap | G4: Niveau Amenagement | H4: Description Amenagement | I4: Date Demande | J4: Date Mise en Place | K4: Cout (FCFA) | L4: Statut | M4: Observations
B5: HAN-001 | C5: Eyenga | D5: Standardiste | E5: Réception & Front Office | F5: Auditif | G5: Amenagement leger | H5: Amplificateur telephonique et signal visuel sonnerie | I5: 45672 | J5: 45698 | K5: 85000 | L5: En cours | M5: Equipement commande
B6: HAN-002 | C6: Ngo Mbeleck | D6: Agent d'accueil | E6: Réception & Front Office | F6: Moteur | G6: Amenagement modere | H6: Rampe d'acces et chaise ergonomique | I6: 45597 | J6: 45677 | K6: 350000 | L6: Terminee | M6: Rampe installee par entretien
B7: HAN-003 | C7: Tchouankou | D7: Plongeur | E7: Cuisine & Restauration | F7: Moteur | G7: Amenagement leger | H7: Tapis antifatigue et chaussures de securite orthopediques | I7: 45689 | K7: 45000 | L7: En cours | M7: En attente fournisseur
B8: =IF(C8="","HAN-"&TEXT(COUNTA($C$5:C8),"000"))
B9: =IF(C9="","HAN-"&TEXT(COUNTA($C$5:C9),"000"))
B10: =IF(C10="","HAN-"&TEXT(COUNTA($C$5:C10),"000"))
B11: =IF(C11="","HAN-"&TEXT(COUNTA($C$5:C11),"000"))
B12: =IF(C12="","HAN-"&TEXT(COUNTA($C$5:C12),"000"))
B13: =IF(C13="","HAN-"&TEXT(COUNTA($C$5:C13),"000"))
B14: =IF(C14="","HAN-"&TEXT(COUNTA($C$5:C14),"000"))
B15: =IF(C15="","HAN-"&TEXT(COUNTA($C$5:C15),"000"))
B16: =IF(C16="","HAN-"&TEXT(COUNTA($C$5:C16),"000"))
B17: =IF(C17="","HAN-"&TEXT(COUNTA($C$5:C17),"000"))
B18: =IF(C18="","HAN-"&TEXT(COUNTA($C$5:C18),"000"))
B19: =IF(C19="","HAN-"&TEXT(COUNTA($C$5:C19),"000"))
... B107: =IF(C107="","HAN-"&TEXT(COUNTA($C$5:C107),"000"))
B109: INDICATEURS (mis a jour automatiquement)
B110: Dossiers handicap | D110: Amenagements realises | F110: Cout total (FCFA)
B111: =COUNTIF(B5:B104,"<>") | D111: =COUNTIF(L5:L104,"Terminee") | F111: =SUM(K5:K104)

Sheet 6-Bien-Etre au Travail
B2: BIEN-ETRE AU TRAVAIL (#151)
B3: TABLEAU DYNAMIQUE — Saisissez dans la prochaine ligne jaune. Les calculs se mettent a jour automatiquement.
B4: N° | C4: Initiative Bien-Etre | D4: Type | E4: Public Cible | F4: Frequence | G4: Lieu | H4: Date Prochaine Session | I4: Intervenant | J4: Nb Participants | K4: Budget (FCFA) | L4: Statut
B5: BET-001 | C5: Yoga hebdomadaire | D5: Activite sportive | E5: Tous les employes | F5: Hebdomadaire | G5: Salle polyvalente | H5: 45721 | I5: M. Fotso (coach) | J5: 25 | K5: 150000 | L5: Recurrent
B6: BET-002 | C6: Consultation psychologique | D6: Santé mentale | E6: Tous les employes | F6: Mensuelle | G6: Cabinet medical | H6: 45728 | I6: Dr. Ngassa | J6: 10 | K6: 200000 | L6: Recurrent
B7: BET-003 | C7: Atelier gestion du stress | D7: Gestion du stress | E7: Cadres et managers | F7: Trimestrielle | G7: Salle formation | H7: 45762 | I7: Mme. Manga (psy) | J7: 20 | K7: 100000 | L7: Planifie
B8: BET-004 | C8: Semaine alimentation saine | D8: Alimentation saine | E8: Tous les employes | F8: Ponctuelle | G8: Cuisine + Restaurant | H8: 45789 | I8: Chef Cuisine + Dieteticien | J8: 150 | K8: 500000 | L8: Planifie
B9: =IF(C9="","BET-"&TEXT(COUNTA($C$5:C9),"000"))
B10: =IF(C10="","BET-"&TEXT(COUNTA($C$5:C10),"000"))
B11: =IF(C11="","BET-"&TEXT(COUNTA($C$5:C11),"000"))
B12: =IF(C12="","BET-"&TEXT(COUNTA($C$5:C12),"000"))
B13: =IF(C13="","BET-"&TEXT(COUNTA($C$5:C13),"000"))
B14: =IF(C14="","BET-"&TEXT(COUNTA($C$5:C14),"000"))
B15: =IF(C15="","BET-"&TEXT(COUNTA($C$5:C15),"000"))
B16: =IF(C16="","BET-"&TEXT(COUNTA($C$5:C16),"000"))
B17: =IF(C17="","BET-"&TEXT(COUNTA($C$5:C17),"000"))
B18: =IF(C18="","BET-"&TEXT(COUNTA($C$5:C18),"000"))
B19: =IF(C19="","BET-"&TEXT(COUNTA($C$5:C19),"000"))
B20: =IF(C20="","BET-"&TEXT(COUNTA($C$5:C20),"000"))
... B108: =IF(C108="","BET-"&TEXT(COUNTA($C$5:C108),"000"))
B110: INDICATEURS (mis a jour automatiquement)
B111: Initiatives bien-etre | D111: Budget total (FCFA) | F111: Sessions recurrentes
B112: =COUNTIF(B5:B104,"<>") | D112: =SUM(K5:K104) | F112: =COUNTIF(L5:L104,"Recurrent")

Sheet 7-Actions Sociales & Solid.
B2: ACTIONS SOCIALES & SOLIDARITE (#152)
B3: TABLEAU DYNAMIQUE — Saisissez dans la prochaine ligne jaune. Les calculs se mettent a jour automatiquement.
B4: N° | C4: Action Sociale | D4: Type | E4: Beneficiaires | F4: Description | G4: Source Financement | H4: Budget (FCFA) | I4: Montant Deploye (FCFA) | J4: Date Realisation | K4: Nb Beneficiaires Directs | L4: Statut
B5: SOC-001 | C5: Dons fournitures scolaires | D5: Action sociale | E5: Enfants employes | F5: Distribution kits scolaires aux enfants du personnel | G5: Budget hotel | H5: 500000 | I5: 450000 | J5: 45677 | K5: 65 | L5: Terminee
B6: SOC-002 | C6: Journée sante employes | D6: Action sociale | E6: Employes et familles | F6: Consultations medicales gratuites et depistage | G6: Budget hotel | H6: 750000 | I6: 720000 | J6: 45703 | K6: 180 | L6: Terminee
B7: SOC-003 | C7: Soutien orphelinat local | D7: Action sociale | E7: Orphelinat Kribi | F7: Dons alimentaires et vestimentaires mensuels | G7: Budget hotel | H7: 300000 | I7: 150000 | J7: 45716 | K7: 40 | L7: En cours
B8: SOC-004 | C8: Bourse etude meritante | D8: Action sociale | E8: Enfants employes | F8: Bourse pour 3 meilleurs eleves du personnel | G8: Fondation | H8: 900000 | I8: 0 | K8: 3 | L8: Planifiee
B9: =IF(C9="","SOC-"&TEXT(COUNTA($C$5:C9),"000")) | I9: =IF(H9="","",I9/H9)
B10: =IF(C10="","SOC-"&TEXT(COUNTA($C$5:C10),"000")) | I10: =IF(H10="","",I10/H10)
B11: =IF(C11="","SOC-"&TEXT(COUNTA($C$5:C11),"000")) | I11: =IF(H11="","",I11/H11)
B12: =IF(C12="","SOC-"&TEXT(COUNTA($C$5:C12),"000")) | I12: =IF(H12="","",I12/H12)
B13: =IF(C13="","SOC-"&TEXT(COUNTA($C$5:C13),"000")) | I13: =IF(H13="","",I13/H13)
B14: =IF(C14="","SOC-"&TEXT(COUNTA($C$5:C14),"000")) | I14: =IF(H14="","",I14/H14)
B15: =IF(C15="","SOC-"&TEXT(COUNTA($C$5:C15),"000")) | I15: =IF(H15="","",I15/H15)
B16: =IF(C16="","SOC-"&TEXT(COUNTA($C$5:C16),"000")) | I16: =IF(H16="","",I16/H16)
B17: =IF(C17="","SOC-"&TEXT(COUNTA($C$5:C17),"000")) | I17: =IF(H17="","",I17/H17)
B18: =IF(C18="","SOC-"&TEXT(COUNTA($C$5:C18),"000")) | I18: =IF(H18="","",I18/H18)
B19: =IF(C19="","SOC-"&TEXT(COUNTA($C$5:C19),"000")) | I19: =IF(H19="","",I19/H19)
B20: =IF(C20="","SOC-"&TEXT(COUNTA($C$5:C20),"000")) | I20: =IF(H20="","",I20/H20)
... B108: =IF(C108="","SOC-"&TEXT(COUNTA($C$5:C108),"000")) | I108: =IF(H108="","",I108/H108)
B110: TOTAL | H110: =SUM(H5:H104) | I110: =SUM(I5:I104) | K110: =SUM(K5:K104)
B112: INDICATEURS (mis a jour automatiquement)
B113: Actions sociales | D113: Budget total (FCFA) | F113: Beneficiaires totaux
B114: =COUNTIF(B5:B104,"<>") | D114: =SUM(H5:H104) | F114: =SUM(K5:K104)

Sheet 8-Formation RSE
B2: FORMATION RSE & ECO-GESTES (#153)
B3: TABLEAU DYNAMIQUE — Saisissez dans la prochaine ligne jaune. Les calculs se mettent a jour automatiquement.
B4: N° | C4: Formation | D4: Type Formation | E4: Public Cible | F4: Formateur | G4: Date Formation | H4: Duree (heures) | I4: Nb Participants | J4: Nb Certifies | K4: Taux Reussite (%) | L4: Cout (FCFA) | M4: Statut
B5: FOR-001 | C5: Eco-gestes au quotidien | D5: Eco-gestes | E5: Tous les employes | F5: Consultant RSE | G5: 45677 | H5: 3 | I5: 120 | J5: 118 | L5: 200000 | M5: Terminee
B6: FOR-002 | C6: Tri selectif avance | D6: Tri selectif | E6: Cuisine & Entretien | F6: ONG environnement | G6: 45703 | H6: 2 | I6: 35 | J6: 35 | L6: 75000 | M6: Terminee
B7: FOR-003 | C7: Sensibilisation diversite | D7: Diversite & inclusion | E7: Cadres et managers | F7: DRH | G7: 45726 | H7: 4 | I7: 25 | J7: 0 | L7: 100000 | M7: Planifiee
B8: FOR-004 | C8: Premiers secours | D8: Premiers secours | E8: Equipes de securite | F8: Croix-Rouge | G8: 45752 | H8: 8 | I8: 15 | J8: 0 | L8: 300000 | M8: Planifiee
B9: =IF(C9="","FOR-"&TEXT(COUNTA($C$5:C9),"000")) | K9: =IF(OR(I9="",J9=""),"",J9/I9)
B10: =IF(C10="","FOR-"&TEXT(COUNTA($C$5:C10),"000")) | K10: =IF(OR(I10="",J10=""),"",J10/I10)
B11: =IF(C11="","FOR-"&TEXT(COUNTA($C$5:C11),"000")) | K11: =IF(OR(I11="",J11=""),"",J11/I11)
B12: =IF(C12="","FOR-"&TEXT(COUNTA($C$5:C12),"000")) | K12: =IF(OR(I12="",J12=""),"",J12/I12)
B13: =IF(C13="","FOR-"&TEXT(COUNTA($C$5:C13),"000")) | K13: =IF(OR(I13="",J13=""),"",J13/I13)
B14: =IF(C14="","FOR-"&TEXT(COUNTA($C$5:C14),"000")) | K14: =IF(OR(I14="",J14=""),"",J14/I14)
B15: =IF(C15="","FOR-"&TEXT(COUNTA($C$5:C15),"000")) | K15: =IF(OR(I15="",J15=""),"",J15/I15)
B16: =IF(C16="","FOR-"&TEXT(COUNTA($C$5:C16),"000")) | K16: =IF(OR(I16="",J16=""),"",J16/I16)
B17: =IF(C17="","FOR-"&TEXT(COUNTA($C$5:C17),"000")) | K17: =IF(OR(I17="",J17=""),"",J17/I17)
B18: =IF(C18="","FOR-"&TEXT(COUNTA($C$5:C18),"000")) | K18: =IF(OR(I18="",J18=""),"",J18/I18)
B19: =IF(C19="","FOR-"&TEXT(COUNTA($C$5:C19),"000")) | K19: =IF(OR(I19="",J19=""),"",J19/I19)
B20: =IF(C20="","FOR-"&TEXT(COUNTA($C$5:C20),"000")) | K20: =IF(OR(I20="",J20=""),"",J20/I20)
... B108: =IF(C108="","FOR-"&TEXT(COUNTA($C$5:C108),"000")) | K108: =IF(OR(I108="",J108=""),"",J108/I108)
B110: INDICATEURS (mis a jour automatiquement)
B111: Formations RSE | D111: Participants totaux | F111: Cout total (FCFA)
B112: =COUNTIF(B5:B104,"<>") | D112: =SUM(I5:I104) | F112: =SUM(L5:L104)

Sheet 9-Bilan Carbone RH
B2: BILAN CARBONE RH (#154)
B3: TABLEAU DYNAMIQUE — Saisissez dans la prochaine ligne jaune. Les calculs se mettent a jour automatiquement.
B4: N° | C4: Source Emission | D4: Categorie | E4: Poste Comptable | F4: Unite Mesure | G4: Consommation 2024 | H4: Consommation 2025 | I4: Evolution (%) | J4: Facteur Emission | K4: Emissions CO2 (tonnes) | L4: Statut
B5: CAR-001 | C5: Electricite hotel | D5: Energie | E5: Chauffage, eclairage, CVC | F5: kWh | G5: 480000 | H5: 456000 | J5: 0.075 | L5: En cours
B6: CAR-002 | C6: Dechets menagers | D6: Dechets | E6: Dechets non recycles | F6: kg | G6: 24000 | H6: 21000 | J6: 0.5 | L6: En cours
B7: CAR-003 | C7: Deplacements employes | D7: Transport | E7: Trajets domicile-travail | F7: km | G7: 360000 | H7: 340000 | J7: 0.21 | L7: En cours
B8: CAR-004 | C8: Consommation eau | D8: Eau | E8: Eau potable et processus | F8: m3 | G8: 12000 | H8: 10800 | J8: 0.0003 | L8: En cours
B9: CAR-005 | C9: Carburant vehicules | D9: Transport | E9: Vehicules service hotel | F9: litres | G9: 15000 | H9: 14200 | J9: 2.3 | L9: En cours
B10: =IF(C10="","CAR-"&TEXT(COUNTA($C$5:C10),"000")) | I10: =IF(G10="","",(H10-G10)/G10) | K10: =IF(OR(H10="",J10=""),"",H10*J10/1000)
B11: =IF(C11="","CAR-"&TEXT(COUNTA($C$5:C11),"000")) | I11: =IF(G11="","",(H11-G11)/G11) | K11: =IF(OR(H11="",J11=""),"",H11*J11/1000)
B12: =IF(C12="","CAR-"&TEXT(COUNTA($C$5:C12),"000")) | I12: =IF(G12="","",(H12-G12)/G12) | K12: =IF(OR(H12="",J12=""),"",H12*J12/1000)
B13: =IF(C13="","CAR-"&TEXT(COUNTA($C$5:C13),"000")) | I13: =IF(G13="","",(H13-G13)/G13) | K13: =IF(OR(H13="",J13=""),"",H13*J13/1000)
B14: =IF(C14="","CAR-"&TEXT(COUNTA($C$5:C14),"000")) | I14: =IF(G14="","",(H14-G14)/G14) | K14: =IF(OR(H14="",J14=""),"",H14*J14/1000)
B15: =IF(C15="","CAR-"&TEXT(COUNTA($C$5:C15),"000")) | I15: =IF(G15="","",(H15-G15)/G15) | K15: =IF(OR(H15="",J15=""),"",H15*J15/1000)
B16: =IF(C16="","CAR-"&TEXT(COUNTA($C$5:C16),"000")) | I16: =IF(G16="","",(H16-G16)/G16) | K16: =IF(OR(H16="",J16=""),"",H16*J16/1000)
B17: =IF(C17="","CAR-"&TEXT(COUNTA($C$5:C17),"000")) | I17: =IF(G17="","",(H17-G17)/G17) | K17: =IF(OR(H17="",J17=""),"",H17*J17/1000)
B18: =IF(C18="","CAR-"&TEXT(COUNTA($C$5:C18),"000")) | I18: =IF(G18="","",(H18-G18)/G18) | K18: =IF(OR(H18="",J18=""),"",H18*J18/1000)
B19: =IF(C19="","CAR-"&TEXT(COUNTA($C$5:C19),"000")) | I19: =IF(G19="","",(H19-G19)/G19) | K19: =IF(OR(H19="",J19=""),"",H19*J19/1000)
B20: =IF(C20="","CAR-"&TEXT(COUNTA($C$5:C20),"000")) | I20: =IF(G20="","",(H20-G20)/G20) | K20: =IF(OR(H20="",J20=""),"",H20*J20/1000)
B21: =IF(C21="","CAR-"&TEXT(COUNTA($C$5:C21),"000")) | I21: =IF(G21="","",(H21-G21)/G21) | K21: =IF(OR(H21="",J21=""),"",H21*J21/1000)
... B109: =IF(C109="","CAR-"&TEXT(COUNTA($C$5:C109),"000")) | I109: =IF(G109="","",(H109-G109)/G109) | K109: =IF(OR(H109="",J109=""),"",H109*J109/1000)
B111: INDICATEURS (mis a jour automatiquement)
B112: Sources suivies | D112: Total emissions (tCO2) | F112: Evolution moyenne
B113: =COUNTIF(B5:B104,"<>") | D113: =SUM(K5:K104) | F113: =IFERROR(AVERAGE(I5:I104),0)

Sheet 10-Partenariats Communaute
B2: PARTENARIATS COMMUNAUTE (#155)
B3: TABLEAU DYNAMIQUE — Saisissez dans la prochaine ligne jaune. Les calculs se mettent a jour automatiquement.
B4: N° | C4: Partenaire | D4: Type Partenariat | E4: Objet | F4: Contact Partenaire | G4: Date Debut | H4: Date Fin | I4: Valeur Echangee (FCFA) | J4: Nb Employes Implicites | K4: Statut | L4: Observations
B5: PAR-001 | C5: Universite de Douala | D5: Ecole / Universite | E5: Stages et recrutement jeunes diplomes | F5: M. Ntone (resp. stage) | G5: 45536 | H5: 45900 | I5: 0 | J5: 8 | K5: Actif | L5: Convention renouvelable annuellement
B6: PAR-002 | C6: ONG Vert du Cameroun | D6: ONG locale | E6: Sensibilisation environnementale et eco-gestes | F6: Mme. Eyenga (coordinateur) | G6: 45658 | H6: 46022 | I6: 500000 | J6: 120 | K6: Actif | L6: Formation gratuite pour 120 employes
B7: PAR-003 | C7: Croix-Rouge camerounaise | D7: Association | E7: Formation premiers secours | F7: Dr. Kamga | G7: 45689 | H7: 46053 | I7: 300000 | J7: 15 | K7: Actif | L7: 2 sessions par an prevues
B8: =IF(C8="","PAR-"&TEXT(COUNTA($C$5:C8),"000"))
B9: =IF(C9="","PAR-"&TEXT(COUNTA($C$5:C9),"000"))
B10: =IF(C10="","PAR-"&TEXT(COUNTA($C$5:C10),"000"))
B11: =IF(C11="","PAR-"&TEXT(COUNTA($C$5:C11),"000"))
B12: =IF(C12="","PAR-"&TEXT(COUNTA($C$5:C12),"000"))
B13: =IF(C13="","PAR-"&TEXT(COUNTA($C$5:C13),"000"))
B14: =IF(C14="","PAR-"&TEXT(COUNTA($C$5:C14),"000"))
B15: =IF(C15="","PAR-"&TEXT(COUNTA($C$5:C15),"000"))
B16: =IF(C16="","PAR-"&TEXT(COUNTA($C$5:C16),"000"))
B17: =IF(C17="","PAR-"&TEXT(COUNTA($C$5:C17),"000"))
B18: =IF(C18="","PAR-"&TEXT(COUNTA($C$5:C18),"000"))
B19: =IF(C19="","PAR-"&TEXT(COUNTA($C$5:C19),"000"))
... B107: =IF(C107="","PAR-"&TEXT(COUNTA($C$5:C107),"000"))
B109: INDICATEURS (mis a jour automatiquement)
B110: Partenariats | D110: Partenaires actifs | F110: Employes implicites
B111: =COUNTIF(B5:B104,"<>") | D111: =COUNTIF(K5:K104,"Actif") | F111: =SUM(J5:J104)

Sheet 11-Indicateurs RSE
B2: INDICATEURS RSE (#156)
B3: TABLEAU DYNAMIQUE — Saisissez dans la prochaine ligne jaune. Les calculs se mettent a jour automatiquement.
B4: N° | C4: Indicateur | D4: Axe RSE | E4: Objectif / Cible | F4: Valeur Actuelle | G4: Unite | H4: Ecart | I4: Tendance | J4: Frequence Mesure | K4: Responsable | L4: Date Mesure | M4: Statut
B5: IRD-001 | C5: Taux reduction dechets | D5: Environnement | E5: Reduction 15% | F5: -0.12 | G5: % | I5: En hausse | J5: Trimestrielle | K5: Chef Logistique | L5: 45747 | M5: En amelioration
B6: IRD-002 | C6: Part femmes cadres | D6: Diversite & Inclusion | E6: >= 40% | F6: 0.38 | G6: % | I6: En hausse | J6: Semestrielle | K6: DRH | L6: 45838 | M6: En amelioration
B7: IRD-003 | C7: Score bien-etre employes | D7: Bien-etre | E7: >= 4.0/5 | F7: 3.8 | G7: /5 | I7: En hausse | J7: Annuelle | K7: DRH | L7: 45688 | M7: En amelioration
B8: IRD-004 | C8: Heures formation RSE / employe | D8: Formation | E8: >= 8h/an | F8: 5.2 | G8: heures | I8: En hausse | J8: Annuelle | K8: DRH | L8: 45688 | M8: En amelioration
B9: IRD-005 | C9: Nb actions sociales / an | D9: Communaute | E9: >= 10 | F9: 7 | G9: actions | I9: En hausse | J9: Annuelle | K9: DRH | L9: 46022 | M9: En cours
B10: =IF(C10="","IRD-"&TEXT(COUNTA($C$5:C10),"000")) | H10: =IF(OR(E10="",F10=""),"",F10-E10)
B11: =IF(C11="","IRD-"&TEXT(COUNTA($C$5:C11),"000")) | H11: =IF(OR(E11="",F11=""),"",F11-E11)
B12: =IF(C12="","IRD-"&TEXT(COUNTA($C$5:C12),"000")) | H12: =IF(OR(E12="",F12=""),"",F12-E12)
B13: =IF(C13="","IRD-"&TEXT(COUNTA($C$5:C13),"000")) | H13: =IF(OR(E13="",F13=""),"",F13-E13)
B14: =IF(C14="","IRD-"&TEXT(COUNTA($C$5:C14),"000")) | H14: =IF(OR(E14="",F14=""),"",F14-E14)
B15: =IF(C15="","IRD-"&TEXT(COUNTA($C$5:C15),"000")) | H15: =IF(OR(E15="",F15=""),"",F15-E15)
B16: =IF(C16="","IRD-"&TEXT(COUNTA($C$5:C16),"000")) | H16: =IF(OR(E16="",F16=""),"",F16-E16)
B17: =IF(C17="","IRD-"&TEXT(COUNTA($C$5:C17),"000")) | H17: =IF(OR(E17="",F17=""),"",F17-E17)
B18: =IF(C18="","IRD-"&TEXT(COUNTA($C$5:C18),"000")) | H18: =IF(OR(E18="",F18=""),"",F18-E18)
B19: =IF(C19="","IRD-"&TEXT(COUNTA($C$5:C19),"000")) | H19: =IF(OR(E19="",F19=""),"",F19-E19)
B20: =IF(C20="","IRD-"&TEXT(COUNTA($C$5:C20),"000")) | H20: =IF(OR(E20="",F20=""),"",F20-E20)
B21: =IF(C21="","IRD-"&TEXT(COUNTA($C$5:C21),"000")) | H21: =IF(OR(E21="",F21=""),"",F21-E21)
... B109: =IF(C109="","IRD-"&TEXT(COUNTA($C$5:C109),"000")) | H109: =IF(OR(E109="",F109=""),"",F109-E109)
B111: INDICATEURS (mis a jour automatiquement)
B112: Indicateurs suivis | D112: Objectifs atteints | F112: En amelioration
B113: =COUNTIF(B5:B104,"<>") | D113: =COUNTIF(M5:M104,"Atteint") | F113: =COUNTIF(M5:M104,"En amelioration")

Sheet 12-Suivi Actions RSE
B2: SUIVI ACTIONS RSE
B3: TABLEAU DYNAMIQUE — Saisissez dans la prochaine ligne jaune. Les calculs se mettent a jour automatiquement.
B4: N° | C4: Action | D4: Axe RSE | E4: Responsable | F4: Date Debut | G4: Date Fin Prevue | H4: Avancement (%) | I4: Budget Prevu (FCFA) | J4: Budget Consomme (FCFA) | K4: Ecart Budget (FCFA) | L4: Statut
B5: SAR-001 | C5: LED chambres etages 1-3 | D5: Environnement | E5: Chef Entretien | F5: 45667 | G5: 45747 | H5: 0.65 | I5: 2500000 | J5: 1500000 | L5: En cours
B6: SAR-002 | C6: Tri selectif cuisine | D6: Environnement | E6: Chef Cuisine | F6: 45689 | G6: 45716 | H6: 1 | I6: 150000 | J6: 140000 | L6: Terminee
B7: SAR-003 | C7: Formation eco-gestes Q1 | D7: Environnement | E7: DRH | F7: 45677 | G7: 45679 | H7: 1 | I7: 200000 | J7: 200000 | L7: Terminee
B8: SAR-004 | C8: Mentorat femmes cadres | D8: Diversite & Inclusion | E8: DRH | F8: 45689 | G8: 46022 | H8: 0.15 | I8: 100000 | J8: 15000 | L8: En cours
B9: =IF(C9="","SAR-"&TEXT(COUNTA($C$5:C9),"000")) | K9: =IF(I9="","",I9-J9)
B10: =IF(C10="","SAR-"&TEXT(COUNTA($C$5:C10),"000")) | K10: =IF(I10="","",I10-J10)
B11: =IF(C11="","SAR-"&TEXT(COUNTA($C$5:C11),"000")) | K11: =IF(I11="","",I11-J11)
B12: =IF(C12="","SAR-"&TEXT(COUNTA($C$5:C12),"000")) | K12: =IF(I12="","",I12-J12)
B13: =IF(C13="","SAR-"&TEXT(COUNTA($C$5:C13),"000")) | K13: =IF(I13="","",I13-J13)
B14: =IF(C14="","SAR-"&TEXT(COUNTA($C$5:C14),"000")) | K14: =IF(I14="","",I14-J14)
B15: =IF(C15="","SAR-"&TEXT(COUNTA($C$5:C15),"000")) | K15: =IF(I15="","",I15-J15)
B16: =IF(C16="","SAR-"&TEXT(COUNTA($C$5:C16),"000")) | K16: =IF(I16="","",I16-J16)
B17: =IF(C17="","SAR-"&TEXT(COUNTA($C$5:C17),"000")) | K17: =IF(I17="","",I17-J17)
B18: =IF(C18="","SAR-"&TEXT(COUNTA($C$5:C18),"000")) | K18: =IF(I18="","",I18-J18)
B19: =IF(C19="","SAR-"&TEXT(COUNTA($C$5:C19),"000")) | K19: =IF(I19="","",I19-J19)
B20: =IF(C20="","SAR-"&TEXT(COUNTA($C$5:C20),"000")) | K20: =IF(I20="","",I20-J20)
... B108: =IF(C108="","SAR-"&TEXT(COUNTA($C$5:C108),"000")) | K108: =IF(I108="","",I108-J108)
B110: INDICATEURS (mis a jour automatiquement)
B111: Actions en cours | D111: Budget total prevu | F111: Taux avancement moyen
B112: =COUNTIF(B5:B104,"<>") | D112: =SUM(I5:I104) | F112: =IFERROR(AVERAGE(H5:H104),0)

Sheet 13-Analyse Diversite
B2: ANALYSE DIVERSITE
B3: TABLEAU DYNAMIQUE — Saisissez dans la prochaine ligne jaune. Les calculs se mettent a jour automatiquement.
B4: N° | C4: Categorie Diversite | D4: Effectif Total | E4: Hommes | F4: Femmes | G4: Part Femmes (%) | H4: Cadres Hommes | I4: Cadres Femmes | J4: Part Femmes Cadres (%) | K4: < 30 ans | L4: 30-50 ans | M4: > 50 ans
B5: DIV-A1 | C5: Direction Générale | D5: 3 | E5: 2 | F5: 1 | H5: 2 | I5: 1 | K5: 0 | L5: 2 | M5: 1
B6: DIV-A2 | C6: Service Client | D6: 8 | E6: 2 | F6: 6 | H6: 1 | I6: 2 | K6: 3 | L6: 4 | M6: 1
B7: DIV-A3 | C7: Réception & Front Office | D7: 22 | E7: 8 | F7: 14 | H7: 2 | I7: 3 | K7: 12 | L7: 8 | M7: 2
B8: DIV-A4 | C8: Cuisine & Restauration | D8: 45 | E8: 30 | F8: 15 | H8: 3 | I8: 1 | K8: 15 | L8: 22 | M8: 8
B9: DIV-A5 | C9: Maintenance | D9: 18 | E9: 16 | F9: 2 | H9: 2 | I9: 0 | K9: 5 | L9: 10 | M9: 3
B10: DIV-A6 | C10: TOTAL HOTEL | D10: 160 | E10: 85 | F10: 75 | H10: 14 | I10: 9 | K10: 50 | L10: 78 | M10: 32
B11: =IF(C11="","DIV-"&TEXT(COUNTA($C$5:C11),"000")) | G11: =IF(D11="","",E11/D11) | J11: =IF(OR(H11="",I11=""),"",I11/(H11+I11))
B12: =IF(C12="","DIV-"&TEXT(COUNTA($C$5:C12),"000")) | G12: =IF(D12="","",E12/D12) | J12: =IF(OR(H12="",I12=""),"",I12/(H12+I12))
B13: =IF(C13="","DIV-"&TEXT(COUNTA($C$5:C13),"000")) | G13: =IF(D13="","",E13/D13) | J13: =IF(OR(H13="",I13=""),"",I13/(H13+I13))
B14: =IF(C14="","DIV-"&TEXT(COUNTA($C$5:C14),"000")) | G14: =IF(D14="","",E14/D14) | J14: =IF(OR(H14="",I14=""),"",I14/(H14+I14))
B15: =IF(C15="","DIV-"&TEXT(COUNTA($C$5:C15),"000")) | G15: =IF(D15="","",E15/D15) | J15: =IF(OR(H15="",I15=""),"",I15/(H15+I15))
B16: =IF(C16="","DIV-"&TEXT(COUNTA($C$5:C16),"000")) | G16: =IF(D16="","",E16/D16) | J16: =IF(OR(H16="",I16=""),"",I16/(H16+I16))
B17: =IF(C17="","DIV-"&TEXT(COUNTA($C$5:C17),"000")) | G17: =IF(D17="","",E17/D17) | J17: =IF(OR(H17="",I17=""),"",I17/(H17+I17))
B18: =IF(C18="","DIV-"&TEXT(COUNTA($C$5:C18),"000")) | G18: =IF(D18="","",E18/D18) | J18: =IF(OR(H18="",I18=""),"",I18/(H18+I18))
B19: =IF(C19="","DIV-"&TEXT(COUNTA($C$5:C19),"000")) | G19: =IF(D19="","",E19/D19) | J19: =IF(OR(H19="",I19=""),"",I19/(H19+I19))
B20: =IF(C20="","DIV-"&TEXT(COUNTA($C$5:C20),"000")) | G20: =IF(D20="","",E20/D20) | J20: =IF(OR(H20="",I20=""),"",I20/(H20+I20))
B21: =IF(C21="","DIV-"&TEXT(COUNTA($C$5:C21),"000")) | G21: =IF(D21="","",E21/D21) | J21: =IF(OR(H21="",I21=""),"",I21/(H21+I21))
B22: =IF(C22="","DIV-"&TEXT(COUNTA($C$5:C22),"000")) | G22: =IF(D22="","",E22/D22) | J22: =IF(OR(H22="",I22=""),"",I22/(H22+I22))
... B110: =IF(C110="","DIV-"&TEXT(COUNTA($C$5:C110),"000")) | G110: =IF(D110="","",E110/D110) | J110: =IF(OR(H110="",I110=""),"",I110/(H110+I110))
B112: INDICATEURS (mis a jour automatiquement)
B113: Effectif total | D113: Part femmes globale | F113: Part femmes cadres
B114: =SUM(D5:D104) | D114: =IFERROR(AVERAGE(G5:G104),0) | F114: =IFERROR(AVERAGE(J5:J104),0)

Sheet 14-Suivi Bien-Etre
B2: SUIVI BIEN-ETRE
B3: TABLEAU DYNAMIQUE — Saisissez dans la prochaine ligne jaune. Les calculs se mettent a jour automatiquement.
B4: N° | C4: Periode | D4: Initiative | E4: Nb Sessions | F4: Nb Participants Total | G4: Score Satisfaction / 5 | H4: Taux Participation (%) | I4: Cout Total (FCFA) | J4: Cout par Participant | K4: Observations
B5: SBE-001 | C5: Janvier 2025 | D5: Yoga hebdomadaire | E5: 4 | F5: 85 | G5: 4.3 | I5: 60000 | K5: Excellente frequentation
B6: SBE-002 | C6: Fevrier 2025 | D6: Yoga + Consultation psy | E6: 5 | F6: 110 | G6: 4.1 | I6: 140000 | K6: Consultation psy completement reservée
B7: SBE-003 | C7: Janvier 2025 | D7: Atelier nutrition | E7: 1 | F7: 45 | G7: 3.8 | I7: 50000 | K7: Premiere session bien accueillie
B8: =IF(C8="","SBE-"&TEXT(COUNTA($C$5:C8),"000")) | H8: =IF(F8="","",F8/160) | J8: =IF(OR(F8="",I8=""),"",I8/F8)
B9: =IF(C9="","SBE-"&TEXT(COUNTA($C$5:C9),"000")) | H9: =IF(F9="","",F9/160) | J9: =IF(OR(F9="",I9=""),"",I9/F9)
B10: =IF(C10="","SBE-"&TEXT(COUNTA($C$5:C10),"000")) | H10: =IF(F10="","",F10/160) | J10: =IF(OR(F10="",I10=""),"",I10/F10)
B11: =IF(C11="","SBE-"&TEXT(COUNTA($C$5:C11),"000")) | H11: =IF(F11="","",F11/160) | J11: =IF(OR(F11="",I11=""),"",I11/F11)
B12: =IF(C12="","SBE-"&TEXT(COUNTA($C$5:C12),"000")) | H12: =IF(F12="","",F12/160) | J12: =IF(OR(F12="",I12=""),"",I12/F12)
B13: =IF(C13="","SBE-"&TEXT(COUNTA($C$5:C13),"000")) | H13: =IF(F13="","",F13/160) | J13: =IF(OR(F13="",I13=""),"",I13/F13)
B14: =IF(C14="","SBE-"&TEXT(COUNTA($C$5:C14),"000")) | H14: =IF(F14="","",F14/160) | J14: =IF(OR(F14="",I14=""),"",I14/F14)
B15: =IF(C15="","SBE-"&TEXT(COUNTA($C$5:C15),"000")) | H15: =IF(F15="","",F15/160) | J15: =IF(OR(F15="",I15=""),"",I15/F15)
B16: =IF(C16="","SBE-"&TEXT(COUNTA($C$5:C16),"000")) | H16: =IF(F16="","",F16/160) | J16: =IF(OR(F16="",I16=""),"",I16/F16)
B17: =IF(C17="","SBE-"&TEXT(COUNTA($C$5:C17),"000")) | H17: =IF(F17="","",F17/160) | J17: =IF(OR(F17="",I17=""),"",I17/F17)
B18: =IF(C18="","SBE-"&TEXT(COUNTA($C$5:C18),"000")) | H18: =IF(F18="","",F18/160) | J18: =IF(OR(F18="",I18=""),"",I18/F18)
B19: =IF(C19="","SBE-"&TEXT(COUNTA($C$5:C19),"000")) | H19: =IF(F19="","",F19/160) | J19: =IF(OR(F19="",I19=""),"",I19/F19)
... B107: =IF(C107="","SBE-"&TEXT(COUNTA($C$5:C107),"000")) | H107: =IF(F107="","",F107/160) | J107: =IF(OR(F107="",I107=""),"",I107/F107)
B109: INDICATEURS (mis a jour automatiquement)
B110: Sessions totales | D110: Participants totaux | F110: Satisfaction moyenne
B111: =SUM(E5:E104) | D111: =SUM(F5:F104) | F111: =IFERROR(AVERAGE(G5:G104),0)

Sheet 15-Hist. Actions Sociales
B2: HISTORIQUE ACTIONS SOCIALES
B3: TABLEAU DYNAMIQUE — Saisissez dans la prochaine ligne jaune. Les calculs se mettent a jour automatiquement.
B4: N° | C4: Annee | D4: Nb Actions Realisees | E4: Budget Total (FCFA) | F4: Montant Deploye (FCFA) | G4: Taux Utilisation (%) | H4: Nb Beneficiaires | I4: Partenaires Impliques | J4: Action Phare
B5: HAS-001 | C5: 2022 | D5: 6 | E5: 1500000 | F5: 1350000 | H5: 180 | I5: 2 | J5: Dons fournitures scolaires
B6: HAS-002 | C6: 2023 | D6: 8 | E6: 2200000 | F6: 2000000 | H6: 250 | I6: 3 | J6: Journee sante employes
B7: HAS-003 | C7: 2024 | D7: 10 | E7: 3500000 | F7: 3200000 | H7: 420 | I7: 4 | J7: Bourse etude + Sante
B8: =IF(C8="","HAS-"&TEXT(COUNTA($C$5:C8),"000")) | G8: =IF(E8="","",F8/E8)
B9: =IF(C9="","HAS-"&TEXT(COUNTA($C$5:C9),"000")) | G9: =IF(E9="","",F9/E9)
B10: =IF(C10="","HAS-"&TEXT(COUNTA($C$5:C10),"000")) | G10: =IF(E10="","",F10/E10)
B11: =IF(C11="","HAS-"&TEXT(COUNTA($C$5:C11),"000")) | G11: =IF(E11="","",F11/E11)
B12: =IF(C12="","HAS-"&TEXT(COUNTA($C$5:C12),"000")) | G12: =IF(E12="","",F12/E12)
B13: =IF(C13="","HAS-"&TEXT(COUNTA($C$5:C13),"000")) | G13: =IF(E13="","",F13/E13)
B14: =IF(C14="","HAS-"&TEXT(COUNTA($C$5:C14),"000")) | G14: =IF(E14="","",F14/E14)
B15: =IF(C15="","HAS-"&TEXT(COUNTA($C$5:C15),"000")) | G15: =IF(E15="","",F15/E15)
B16: =IF(C16="","HAS-"&TEXT(COUNTA($C$5:C16),"000")) | G16: =IF(E16="","",F16/E16)
B17: =IF(C17="","HAS-"&TEXT(COUNTA($C$5:C17),"000")) | G17: =IF(E17="","",F17/E17)
B18: =IF(C18="","HAS-"&TEXT(COUNTA($C$5:C18),"000")) | G18: =IF(E18="","",F18/E18)
B19: =IF(C19="","HAS-"&TEXT(COUNTA($C$5:C19),"000")) | G19: =IF(E19="","",F19/E19)
... B107: =IF(C107="","HAS-"&TEXT(COUNTA($C$5:C107),"000")) | G107: =IF(E107="","",F107/E107)
B109: INDICATEURS (mis a jour automatiquement)
B110: Total actions (tous ans) | D110: Budget cumule (FCFA) | F110: Beneficiaires totaux
B111: =SUM(D5:D104) | D111: =SUM(E5:E104) | F111: =SUM(H5:H104)

Sheet 16-Calendrier RSE
B2: CALENDRIER RSE
B3: TABLEAU DYNAMIQUE — Saisissez dans la prochaine ligne jaune. Les calculs se mettent a jour automatiquement.
B4: N° | C4: Action RSE | D4: Axe RSE | E4: Date Prevue | F4: Responsable | G4: Public Cible | H4: Lieu | I4: Budget Estime (FCFA) | J4: Statut | K4: Rappel
B5: CRS-001 | C5: Semaine environnement | D5: Environnement | E5: 45813 | F5: DRH | G5: Tous les employes | H5: Hotel | I5: 500000 | J5: Planifiee | K5: 01/06/2025
B6: CRS-002 | C6: Journee diversite | D6: Diversite & Inclusion | E6: 45737 | F6: DRH | G6: Tous les employes | H6: Salle conf. | I6: 200000 | J6: Planifiee | K6: 14/03/2025
B7: CRS-003 | C7: Collecte dechets quartier | D7: Communaute | E7: 45766 | F7: Chef Logistique | G7: Volontaires + communaute | H7: Quartier | I7: 100000 | J7: Planifiee | K7: 12/04/2025
B8: CRS-004 | C8: Formation premiers secours | D8: Formation | E8: 45752 | F8: DRH | G8: Equipes securite | H8: Salle form. | I8: 300000 | J8: Planifiee | K8: 29/03/2025
B9: CRS-005 | C9: Don alimentaire orphelinat | D9: Communaute | E9: 45792 | F9: DRH | G9: Orphelinat Kribi | H9: Orphelinat | I9: 200000 | J9: Planifiee | K9: 08/05/2025
B10: =IF(C10="","CRS-"&TEXT(COUNTA($C$5:C10),"000"))
B11: =IF(C11="","CRS-"&TEXT(COUNTA($C$5:C11),"000"))
B12: =IF(C12="","CRS-"&TEXT(COUNTA($C$5:C12),"000"))
B13: =IF(C13="","CRS-"&TEXT(COUNTA($C$5:C13),"000"))
B14: =IF(C14="","CRS-"&TEXT(COUNTA($C$5:C14),"000"))
B15: =IF(C15="","CRS-"&TEXT(COUNTA($C$5:C15),"000"))
B16: =IF(C16="","CRS-"&TEXT(COUNTA($C$5:C16),"000"))
B17: =IF(C17="","CRS-"&TEXT(COUNTA($C$5:C17),"000"))
B18: =IF(C18="","CRS-"&TEXT(COUNTA($C$5:C18),"000"))
B19: =IF(C19="","CRS-"&TEXT(COUNTA($C$5:C19),"000"))
B20: =IF(C20="","CRS-"&TEXT(COUNTA($C$5:C20),"000"))
B21: =IF(C21="","CRS-"&TEXT(COUNTA($C$5:C21),"000"))
... B109: =IF(C109="","CRS-"&TEXT(COUNTA($C$5:C109),"000"))
B111: INDICATEURS (mis a jour automatiquement)
B112: Actions planifiees | D112: Budget total estime | F112: Planifiees
B113: =COUNTIF(B5:B104,"<>") | D113: =SUM(I5:I104) | F113: =COUNTIF(J5:J104,"Planifiee")

Sheet 17-Matrice Part. Prenantes
B2: MATRICE PARTIES PRENANTES
B3: TABLEAU DYNAMIQUE — Saisissez dans la prochaine ligne jaune. Les calculs se mettent a jour automatiquement.
B4: N° | C4: Partie Prenante | D4: Categorie | E4: Interet RSE | F4: Influence | G4: Niveau Engagement | H4: Attentes Principales | I4: Actions Envisagees | J4: Frequence Echange | K4: Dernier Contact
B5: MPP-001 | C5: Employes | D5: Interne | E5: Eleve | F5: Eleve | G5: Actif | H5: Meilleures conditions, bien-etre, formation | I5: Enquetes, CSE, formations | J5: Mensuelle | K5: 45716
B6: MPP-002 | C6: Clients | D6: Externe | E6: Moyen | F6: Eleve | G6: Modere | H6: Hotels responsables, eco-labels | I6: Communication ME, eco-label | J6: Trimestrielle | K6: 45672
B7: MPP-003 | C7: Fournisseurs | D7: Externe | E7: Moyen | F7: Moyen | G7: Modere | H7: Achats locaux, commerce equitable | I7: Charte fournisseur, audit | J7: Semestrielle | K7: 45698
B8: MPP-004 | C8: Collectivite locale | D8: Externe | E8: Eleve | F8: Eleve | G8: Actif | H8: Emploi local, respect reglementation | I8: Partenariats, reporting | J8: Trimestrielle | K8: 45717
B9: MPP-005 | C9: ONG environnement | D9: Externe | E9: Eleve | F9: Moyen | G9: Actif | H9: Reduction empreinte ecologique | I9: Formations, audits, labels | J9: Mensuelle | K9: 45708
B10: =IF(C10="","MPP-"&TEXT(COUNTA($C$5:C10),"000"))
B11: =IF(C11="","MPP-"&TEXT(COUNTA($C$5:C11),"000"))
B12: =IF(C12="","MPP-"&TEXT(COUNTA($C$5:C12),"000"))
B13: =IF(C13="","MPP-"&TEXT(COUNTA($C$5:C13),"000"))
B14: =IF(C14="","MPP-"&TEXT(COUNTA($C$5:C14),"000"))
B15: =IF(C15="","MPP-"&TEXT(COUNTA($C$5:C15),"000"))
B16: =IF(C16="","MPP-"&TEXT(COUNTA($C$5:C16),"000"))
B17: =IF(C17="","MPP-"&TEXT(COUNTA($C$5:C17),"000"))
B18: =IF(C18="","MPP-"&TEXT(COUNTA($C$5:C18),"000"))
B19: =IF(C19="","MPP-"&TEXT(COUNTA($C$5:C19),"000"))
B20: =IF(C20="","MPP-"&TEXT(COUNTA($C$5:C20),"000"))
B21: =IF(C21="","MPP-"&TEXT(COUNTA($C$5:C21),"000"))
... B109: =IF(C109="","MPP-"&TEXT(COUNTA($C$5:C109),"000"))
B111: INDICATEURS (mis a jour automatiquement)
B112: Parties prenantes | D112: Engagement actif | F112: Interet eleve
B113: =COUNTIF(B5:B104,"<>") | D113: =COUNTIF(G5:G104,"Actif") | F113: =COUNTIF(E5:E104,"Eleve")

Sheet 18-Suivi Formation RSE
B2: SUIVI FORMATION RSE
B3: TABLEAU DYNAMIQUE — Saisissez dans la prochaine ligne jaune. Les calculs se mettent a jour automatiquement.
B4: N° | C4: Mois | D4: Nb Formations RSE | E4: Nb Participants | F4: Heures Formation | G4: Cout Total (FCFA) | H4: Cout Moyen / Participant | I4: Taux Satisfaction Moy. | J4: Nb Certifies | K4: Taux Certification (%)
B5: SFR-001 | C5: Janvier 2025 | D5: 2 | E5: 165 | F5: 500 | G5: 250000 | I5: 4.1 | J5: 153
B6: SFR-002 | C6: Fevrier 2025 | D6: 1 | E6: 35 | F6: 70 | G6: 75000 | I6: 4.5 | J6: 35
B7: SFR-003 | C7: Mars 2025 | D7: 1 | E7: 25 | F7: 100 | G7: 100000 | J7: 0
B8: =IF(C8="","SFR-"&TEXT(COUNTA($C$5:C8),"000")) | H8: =IF(F8="","",I8/F8) | K8: =IF(F8="","",J8/F8)
B9: =IF(C9="","SFR-"&TEXT(COUNTA($C$5:C9),"000")) | H9: =IF(F9="","",I9/F9) | K9: =IF(F9="","",J9/F9)
B10: =IF(C10="","SFR-"&TEXT(COUNTA($C$5:C10),"000")) | H10: =IF(F10="","",I10/F10) | K10: =IF(F10="","",J10/F10)
B11: =IF(C11="","SFR-"&TEXT(COUNTA($C$5:C11),"000")) | H11: =IF(F11="","",I11/F11) | K11: =IF(F11="","",J11/F11)
B12: =IF(C12="","SFR-"&TEXT(COUNTA($C$5:C12),"000")) | H12: =IF(F12="","",I12/F12) | K12: =IF(F12="","",J12/F12)
B13: =IF(C13="","SFR-"&TEXT(COUNTA($C$5:C13),"000")) | H13: =IF(F13="","",I13/F13) | K13: =IF(F13="","",J13/F13)
B14: =IF(C14="","SFR-"&TEXT(COUNTA($C$5:C14),"000")) | H14: =IF(F14="","",I14/F14) | K14: =IF(F14="","",J14/F14)
B15: =IF(C15="","SFR-"&TEXT(COUNTA($C$5:C15),"000")) | H15: =IF(F15="","",I15/F15) | K15: =IF(F15="","",J15/F15)
B16: =IF(C16="","SFR-"&TEXT(COUNTA($C$5:C16),"000")) | H16: =IF(F16="","",I16/F16) | K16: =IF(F16="","",J16/F16)
B17: =IF(C17="","SFR-"&TEXT(COUNTA($C$5:C17),"000")) | H17: =IF(F17="","",I17/F17) | K17: =IF(F17="","",J17/F17)
B18: =IF(C18="","SFR-"&TEXT(COUNTA($C$5:C18),"000")) | H18: =IF(F18="","",I18/F18) | K18: =IF(F18="","",J18/F18)
B19: =IF(C19="","SFR-"&TEXT(COUNTA($C$5:C19),"000")) | H19: =IF(F19="","",I19/F19) | K19: =IF(F19="","",J19/F19)
... B107: =IF(C107="","SFR-"&TEXT(COUNTA($C$5:C107),"000")) | H107: =IF(F107="","",I107/F107) | K107: =IF(F107="","",J107/F107)
B109: INDICATEURS (mis a jour automatiquement)
B110: Total formations | D110: Total heures | F110: Cout total (FCFA)
B111: =SUM(D5:D104) | D111: =SUM(F5:F104) | F111: =SUM(G5:G104)

Sheet 19-Analyse Indic. RSE
B2: ANALYSE INDICATEURS RSE
B3: TABLEAU DYNAMIQUE — Saisissez dans la prochaine ligne jaune. Les calculs se mettent a jour automatiquement.
B4: N° | C4: Indicateur | D4: Axe RSE | E4: Annee Precedente | F4: Annee Courante | G4: Evolution (pts ou %) | H4: Objectif | I4: Ecart vs Objectif | J4: Statut | K4: Commentaire
B5: AIR-001 | C5: Taux reduction dechets | D5: Environnement | E5: -0.08 | F5: -0.12 | H5: -0.15 | J5: En amelioration | K5: Bonne progression, objectif atteignable
B6: AIR-002 | C6: Part femmes cadres | D6: Diversite & Inclusion | E6: 0.33 | F6: 0.38 | H6: 0.4 | J6: En amelioration | K6: 2 promotions prevues T2
B7: AIR-003 | C7: Score bien-etre | D7: Bien-etre | E7: 3.5 | F7: 3.8 | H7: 4 | J7: En amelioration | K7: Enquete Q1 prevue mars
B8: AIR-004 | C8: H formation RSE / employe | D8: Formation | E8: 3.2 | F8: 5.2 | H8: 8 | J8: En amelioration | K8: Programme formation renforce
B9: AIR-005 | C9: Emissions CO2 (tonnes) | D9: Environnement | E9: 52.5 | F9: 48.2 | H9: 40 | J9: En amelioration | K9: LED + tri contribuent
B10: =IF(C10="","AIR-"&TEXT(COUNTA($C$5:C10),"000")) | G10: =IF(OR(E10="",F10=""),"",F10-E10) | I10: =IF(OR(F10="",H10=""),"",F10-H10)
B11: =IF(C11="","AIR-"&TEXT(COUNTA($C$5:C11),"000")) | G11: =IF(OR(E11="",F11=""),"",F11-E11) | I11: =IF(OR(F11="",H11=""),"",F11-H11)
B12: =IF(C12="","AIR-"&TEXT(COUNTA($C$5:C12),"000")) | G12: =IF(OR(E12="",F12=""),"",F12-E12) | I12: =IF(OR(F12="",H12=""),"",F12-H12)
B13: =IF(C13="","AIR-"&TEXT(COUNTA($C$5:C13),"000")) | G13: =IF(OR(E13="",F13=""),"",F13-E13) | I13: =IF(OR(F13="",H13=""),"",F13-H13)
B14: =IF(C14="","AIR-"&TEXT(COUNTA($C$5:C14),"000")) | G14: =IF(OR(E14="",F14=""),"",F14-E14) | I14: =IF(OR(F14="",H14=""),"",F14-H14)
B15: =IF(C15="","AIR-"&TEXT(COUNTA($C$5:C15),"000")) | G15: =IF(OR(E15="",F15=""),"",F15-E15) | I15: =IF(OR(F15="",H15=""),"",F15-H15)
B16: =IF(C16="","AIR-"&TEXT(COUNTA($C$5:C16),"000")) | G16: =IF(OR(E16="",F16=""),"",F16-E16) | I16: =IF(OR(F16="",H16=""),"",F16-H16)
B17: =IF(C17="","AIR-"&TEXT(COUNTA($C$5:C17),"000")) | G17: =IF(OR(E17="",F17=""),"",F17-E17) | I17: =IF(OR(F17="",H17=""),"",F17-H17)
B18: =IF(C18="","AIR-"&TEXT(COUNTA($C$5:C18),"000")) | G18: =IF(OR(E18="",F18=""),"",F18-E18) | I18: =IF(OR(F18="",H18=""),"",F18-H18)
B19: =IF(C19="","AIR-"&TEXT(COUNTA($C$5:C19),"000")) | G19: =IF(OR(E19="",F19=""),"",F19-E19) | I19: =IF(OR(F19="",H19=""),"",F19-H19)
B20: =IF(C20="","AIR-"&TEXT(COUNTA($C$5:C20),"000")) | G20: =IF(OR(E20="",F20=""),"",F20-E20) | I20: =IF(OR(F20="",H20=""),"",F20-H20)
B21: =IF(C21="","AIR-"&TEXT(COUNTA($C$5:C21),"000")) | G21: =IF(OR(E21="",F21=""),"",F21-E21) | I21: =IF(OR(F21="",H21=""),"",F21-H21)
... B109: =IF(C109="","AIR-"&TEXT(COUNTA($C$5:C109),"000")) | G109: =IF(OR(E109="",F109=""),"",F109-E109) | I109: =IF(OR(F109="",H109=""),"",F109-H109)
B111: INDICATEURS (mis a jour automatiquement)
B112: Indicateurs analyses | D112: En amelioration | F112: Objectifs atteints
B113: =COUNTIF(B5:B104,"<>") | D113: =COUNTIF(J5:J104,"En amelioration") | F113: =COUNTIF(J5:J104,"Atteint")
