Workbook

Sheet _Données Employés
B4: Matricule | C4: Civilité | D4: Nom | E4: Prénom | F4: Département | G4: Poste | H4: Salaire Base (FCFA)
B5: EMP-001 | C5: M. | D5: Nganou | E5: Clarisse | F5: Cuisine & Restauration | G5: Chef cuisinier | H5: 450000
B6: EMP-002 | C6: M. | D6: Tchinda | E6: Armand | F6: Réception & Front Office | G6: Réceptionniste | H6: 220000
B7: EMP-003 | C7: Mme | D7: Fotso | E7: Marguerite | F7: Finance & Comptabilité | G7: Comptable senior | H7: 380000
B8: EMP-004 | C8: M. | D8: Nkoulou | E8: Mbarga | F8: Étage & Housekeeping | G8: Gouvernant | H8: 195000
B9: EMP-005 | C9: M. | D9: Kamga | E9: Paul | F9: Maintenance | G9: Technicien maintenance | H9: 165000
B10: EMP-006 | C10: Mme | D10: Ngo | E10: Delphine | F10: Service Client | G10: Conseiller clientèle | H10: 160000
B11: EMP-007 | C11: M. | D11: Essomba | E11: Serge | F11: Maintenance | G11: Agent entretien | H11: 130000
B12: EMP-008 | C12: M. | D12: Tchouankou | E12: Paul | F12: Commercial | G12: Commercial | H12: 150000
B13: EMP-009 | C13: M. | D13: Fokam | E13: Eric | F13: Maintenance | G13: Technicien | H13: 140000
B14: EMP-010 | C14: M. | D14: Tagne | E14: René | F14: Cuisine & Restauration | G14: Plongeur | H14: 90000
B15: EMP-011 | C15: M. | D15: Bouba | E15: Ahmed | F15: Sécurité | G15: Agent Sécurité | H15: 120000
B16: EMP-012 | C16: Mme | D16: Awa | E16: Fatou | F16: Réception & Front Office | G16: Standardiste | H16: 155000
... B18: EMP-029 | C18: M. | D18: Kamga | E18: Patrice | F18: Sécurité | G18: Chef Sécurité | H18: 210000

Sheet 1-Tableau de Bord
B2: DOMAINE 11 — DROIT DU TRAVAIL & CONFORMITÉ
B3: TABLEAU DE BORD — Vue synthetique de tous les indicateurs du domaine (mis a jour automatiquement)
B5: Exigences juridiques | E5: Contrats travail | H5: Avenants | K5: Procedures discipl.
B6: =COUNTIF('2-Registre Conformite Jurid.'!B5:B104,"<>") | E6: =COUNTIF('3-Contrats de Travail'!B5:B104,"<>") | H6: =COUNTIF('4-Avenants Contrats'!B5:B104,"<>") | K6: =COUNTIF('5-Proc. Discip. Juridiques'!B5:B104,"<>")
B9: Declarations sociales | E9: Textes legaux suivis | H9: Audits conformite | K9: Litiges ouverts
B10: =COUNTIF('6-Declarations CNPS Impots'!B5:B104,"<>") | E10: =COUNTIF('7-Suivi Legislation Travail'!B5:B104,"<>") | H10: =COUNTIF('8-Audit Conformite RH'!B5:B104,"<>") | K10: =COUNTIF('9-Gestion Litiges Contentieux'!B5:B104,"<>")
B13: Visites inspection | E13: Politiques RH | H13: Non-conformites | K13: Penalites totales (FCFA)
B14: =COUNTIF('10-Registre Visites Inspect.'!B5:B104,"<>") | E14: =COUNTIF('11-Politiques Procedures RH'!B5:B104,"<>") | H14: =COUNTIF('2-Registre Conformite Jurid.'!F5:F104,"Non conforme") | K14: =SUM('6-Declarations CNPS Impots'!I5:I104)
B18: NON-CONFORMITES PAR DOMAINE & TYPE DE LITIGES
B19: Domaine | C19: Nb Non-Conformites
B20: Contrat travail | C20: =COUNTIF('2-Registre Conformite Jurid.'!C5:C104,"*Contrat travail*")+COUNTIF('13-Indicateurs Conformite'!H5:H104,">"&0)
B21: Conditions travail | C21: =COUNTIF('2-Registre Conformite Jurid.'!C5:C104,"*Conditions travail*")+COUNTIF('13-Indicateurs Conformite'!H5:H104,">"&0)
B22: Securite sociale | C22: =COUNTIF('2-Registre Conformite Jurid.'!C5:C104,"*Securite sociale*")+COUNTIF('13-Indicateurs Conformite'!H5:H104,">"&0)
B23: Hygiene securite | C23: =COUNTIF('2-Registre Conformite Jurid.'!C5:C104,"*Hygiene securite*")+COUNTIF('13-Indicateurs Conformite'!H5:H104,">"&0)
B24: Discipline | C24: =COUNTIF('2-Registre Conformite Jurid.'!C5:C104,"*Discipline*")+COUNTIF('13-Indicateurs Conformite'!H5:H104,">"&0)
H26: Type Litige | I26: Nombre
H27: Licenciement abusif | I27: =COUNTIF('9-Gestion Litiges Contentieux'!E5:E104,"*Licenciement abusif*")
H28: Heures supplementaires | I28: =COUNTIF('9-Gestion Litiges Contentieux'!E5:E104,"*Heures supplementaires*")
H29: Conditions travail | I29: =COUNTIF('9-Gestion Litiges Contentieux'!E5:E104,"*Conditions travail*")
H30: Harcèlement | I30: =COUNTIF('9-Gestion Litiges Contentieux'!E5:E104,"*Harcèlement*")
H31: Autre | I31: =COUNTIF('9-Gestion Litiges Contentieux'!E5:E104,"*Autre*")

Sheet _Lists
B1: departement | C1: poste_hotel | D1: type_contrat | E1: statut_contrat | F1: type_avenant | G1: type_infraction | H1: type_sanction | I1: organe_institution | J1: type_declaration | K1: statut_declaration | L1: type_texte_legal | M1: domaine_legal | N1: statut_conformite | O1: gravite_non_conformite | P1: type_litige | Q1: statut_litige | R1: type_politique | S1: statut_politique | T1: priorite_action_conf | U1: mois | V1: annee
B2: Direction Générale | C2: DG | D2: CDI | E2: En cours | F2: Augmentation salariale | G2: Absence injustifiee | H2: Avertissement verbal | I2: CNPS | J2: CNPS mensuelle | K2: Effectuee | L2: Code du travail | M2: Contrat de travail | N2: Conforme | O2: Mineure | P2: Licenciement abusif | Q2: En cours | R2: Reglement interieur | S2: En vigueur | T2: Haute | U2: Janvier | V2: 2024
B3: Service Client | C3: DRH | D3: CDD | E3: Suspendu | F3: Changement de poste | G3: Retard repetes | H3: Avertissement ecrit | I3: Inspection du travail | J3: IR mensuel | K3: En retard | L3: Convention collective | M3: Conditions travail | N3: Non conforme | O3: Moyenne | P3: Harcèlement | Q3: En conciliation | R3: Politique remuneration | S3: En revision | T3: Moyenne | U3: Fevrier | V3: 2025
B4: Finance & Comptabilité | C4: Assistante RH | D4: Contrat d'apprentissage | E4: Resilie | F4: Modification horaires | G4: Insubordination | H4: Blame | I4: Tribunal de travail | J4: Declaration annuelle | K4: En attente | L4: Decret | M4: Securite sociale | N4: Partiellement conforme | O4: Majeure | P4: Salaires impayes | Q4: Assigne tribunal | R4: Charte ethique | S4: A approuver | T4: Basse | U4: Mars | V4: 2026
B5: Marketing & Communication | C5: DAF | D5: Stage | E5: Expire | F5: Renouvellement CDD | G5: Vol | H5: Mise a pied disciplinaire | I5: Ministere du Travail | J5: Bilan social | K5: Non effectuee | L5: Arrete | M5: Impots | N5: En mise en conformite | O5: Critique | P5: Heures supplementaires | Q5: Mediation | R5: Politique formation | S5: Obsolette | U5: Avril
B6: Maintenance | C6: Comptable senior | D6: Interim | E6: En renouvellement | F6: Transformation CDD-CDI | G6: Harcèlement | H6: Licenciement pour faute | I6: Direction regionale travail | J6: Taxe d'apprentissage | K6: En cours de preparation | L6: Circulaire | M6: Hygiene securite | N6: Non evalue | P6: Conditions travail | Q6: Resolu | R6: Politique evaluation | S6: En elaboration | U6: Mai
B7: Commercial | C7: Chef Comptable | D7: Contrat projet | F7: Rupture amiable | G7: Ivresse au travail | H7: Licenciement faute lourde | I7: ONRT | J7: Formation professionnelle | L7: Loi | M7: Conges payes | P7: Discrimination | Q7: Perdu | R7: Procedure recrutement | U7: Juin
B8: Logistique & Approvisionnement | C8: Chef Marketing | F8: Autre | G8: Non respect reglement | H8: Rappel a l'ordre | I8: Fonds de garantie | J8: Impot sur salaires | L8: Reglement interieur | M8: Licenciement | P8: Accident travail | Q8: Gagne | R8: Politique hygiene securite | U8: Juillet
B9: Cuisine & Restauration | C9: Chef de service IT | G9: Faute lourde | M9: Discipline | P9: Autre | Q9: Abandonne | R9: Politique diversite | U9: Aout
B10: Réception & Front Office | C10: Technicien IT | G10: Negligence | M10: Formation | U10: Septembre
B11: Sécurité | C11: Chef Commercial | G11: Conduite dangereuse | M11: Egalite professionnelle | U11: Octobre
B12: Étage & Housekeeping | C12: Agent Commercial | U12: Novembre
C13: Chef Logistique | U13: Decembre
C14: Magasinier
C15: Chef Reception
C16: Receptionniste
C17: Concierge
C18: Chef Cuisine
C19: Sous-Chef
C20: Cuisinier
C21: Plongeur
C22: Chef Entretien
C23: Agent Entretien
C24: Chef Securite
C25: Agent Securite

Sheet 2-Registre Conformite Jurid.
B2: REGISTRE CONFORMITE JURIDIQUE (#117)
B3: TABLEAU DYNAMIQUE — Saisissez dans la prochaine ligne jaune. Les calculs se mettent a jour automatiquement.
B4: N° | C4: Domaine Legal | D4: Exigence Reglementaire | E4: Reference Texte | F4: Statut Conformite | G4: Gravite Non-Conformite | H4: Action Corrective | I4: Responsable | J4: Echeance | K4: Observations
B5: CON-001 | C5: Contrat de travail | D5: Contrat ecrit pour tout employe | E5: Code du travail Art. 23 | F5: Conforme | I5: DRH Fotso M. | K5: Tous les contrats a jour
B6: CON-002 | C6: Securite sociale | D6: Affiliation CNPS sous 8 jours | E6: Code CSS Art. 12 | F6: Non conforme | G6: Majeure | H6: Regulariser les 3 dossiers en attente | I6: Assistante RH Ngo M. | J6: 45853 | K6: 3 nouveaux employes non affilie
B7: CON-003 | C7: Hygiene securite | D7: Registre SST tenu a jour | E7: Code du travail Art. 95 | F7: Conforme | I7: Chef Securite Nganmeni J. | K7: Registre a jour, dernier controle OK
B8: CON-004 | C8: Conditions travail | D8: Duree max 40h/semaine | E8: Code du travail Art. 45 | F8: Partiellement conforme | G8: Moyenne | H8: Verifier heures supp. cuisine et entretien | I8: DRH Fotso M. | J8: 45868 | K8: Depassement ponctuel en cuisine
B9: CON-005 | C9: Discipline | D9: Procedure disciplinaire respectee | E9: Code du travail Art. 38 | F9: Conforme | I9: DRH Fotso M. | K9: Procedure en 3 etapes toujours respectee
B10: =IF(C10="","CON-"&TEXT(COUNTA($C$5:C10),"000"))
B11: =IF(C11="","CON-"&TEXT(COUNTA($C$5:C11),"000"))
B12: =IF(C12="","CON-"&TEXT(COUNTA($C$5:C12),"000"))
B13: =IF(C13="","CON-"&TEXT(COUNTA($C$5:C13),"000"))
B14: =IF(C14="","CON-"&TEXT(COUNTA($C$5:C14),"000"))
B15: =IF(C15="","CON-"&TEXT(COUNTA($C$5:C15),"000"))
B16: =IF(C16="","CON-"&TEXT(COUNTA($C$5:C16),"000"))
B17: =IF(C17="","CON-"&TEXT(COUNTA($C$5:C17),"000"))
B18: =IF(C18="","CON-"&TEXT(COUNTA($C$5:C18),"000"))
B19: =IF(C19="","CON-"&TEXT(COUNTA($C$5:C19),"000"))
B20: =IF(C20="","CON-"&TEXT(COUNTA($C$5:C20),"000"))
B21: =IF(C21="","CON-"&TEXT(COUNTA($C$5:C21),"000"))
... B109: =IF(C109="","CON-"&TEXT(COUNTA($C$5:C109),"000"))
B111: INDICATEURS (mis a jour automatiquement)
B112: Exigences suivies | D112: Conformes | F112: Non conformes | H112: Partiellement conf.
B113: =COUNTIF(B5:B104,"<>") | D113: =COUNTIF(F5:F104,"Conforme") | F113: =COUNTIF(F5:F104,"Non conforme") | H113: =COUNTIF(F5:F104,"Partiellement conforme")

Sheet 3-Contrats de Travail
B2: CONTRATS DE TRAVAIL (#118)
B3: TABLEAU DYNAMIQUE — Saisissez dans la prochaine ligne jaune. Les calculs se mettent a jour automatiquement.
B4: N° | C4: Employe | D4: Poste | E4: Departement | F4: Type Contrat | G4: Date Debut | H4: Date Fin | I4: Salaire Brut (FCFA) | J4: Statut | K4: Observations
B5: CT-001 | C5: Nkoulou Mbarga P. | D5: Chef Reception | E5: Réception & Front Office | F5: CDI | G5: 43525 | I5: 350000 | J5: En cours | K5: Cadre, convention collective hotellerie
B6: CT-002 | C6: Biyong Jean M. | D6: Chef Cuisine | E6: Cuisine & Restauration | F6: CDI | G6: 42901 | I6: 420000 | J6: En cours | K6: Cadre, anciennete 8 ans
B7: CT-003 | C7: Kamga Patrice | D7: Receptionniste | E7: Réception & Front Office | F7: CDD | G7: 45658 | H7: 45838 | I7: 180000 | J7: En renouvellement | K7: CDD 6 mois, renouvellement prevu
B8: CT-004 | C8: Fouda M. | D8: Cuisinier | E8: Cuisine & Restauration | F8: CDI | G8: 45170 | I8: 220000 | J8: En cours | K8: Promotion en cours
B9: CT-005 | C9: Tchinda P. | D9: Chef Entretien | E9: Maintenance | F9: CDI | G9: 43132 | I9: 310000 | J9: En cours | K9: Cadre, qualification electrique
B10: =IF(C10="","CT-"&TEXT(COUNTA($C$5:C10),"000"))
B11: =IF(C11="","CT-"&TEXT(COUNTA($C$5:C11),"000"))
B12: =IF(C12="","CT-"&TEXT(COUNTA($C$5:C12),"000"))
B13: =IF(C13="","CT-"&TEXT(COUNTA($C$5:C13),"000"))
B14: =IF(C14="","CT-"&TEXT(COUNTA($C$5:C14),"000"))
B15: =IF(C15="","CT-"&TEXT(COUNTA($C$5:C15),"000"))
B16: =IF(C16="","CT-"&TEXT(COUNTA($C$5:C16),"000"))
B17: =IF(C17="","CT-"&TEXT(COUNTA($C$5:C17),"000"))
B18: =IF(C18="","CT-"&TEXT(COUNTA($C$5:C18),"000"))
B19: =IF(C19="","CT-"&TEXT(COUNTA($C$5:C19),"000"))
B20: =IF(C20="","CT-"&TEXT(COUNTA($C$5:C20),"000"))
B21: =IF(C21="","CT-"&TEXT(COUNTA($C$5:C21),"000"))
... B109: =IF(C109="","CT-"&TEXT(COUNTA($C$5:C109),"000"))
B111: TOTAL | I111: =SUM(I5:I104)
B113: INDICATEURS (mis a jour automatiquement)
B114: Contrats total | D114: CDI | F114: CDD | H114: Masse salariale (M)
B115: =COUNTIF(B5:B104,"<>") | D115: =COUNTIF(F5:F104,"CDI") | F115: =COUNTIF(F5:F104,"CDD") | H115: =IFERROR(SUM(I5:I104)/1000000,0)

Sheet 4-Avenants Contrats
B2: AVENANTS & MODIFICATIONS CONTRATS (#119)
B3: TABLEAU DYNAMIQUE — Saisissez dans la prochaine ligne jaune. Les calculs se mettent a jour automatiquement.
B4: N° | C4: Employe | D4: Poste | E4: Type Avenant | F4: Date Avenant | G4: Ancienne Condition | H4: Nouvelle Condition | I4: Motif | J4: Statut | K4: Signe le
B5: AV-001 | C5: Nkoulou Mbarga P. | D5: Chef Reception | E5: Augmentation salariale | F5: 45689 | G5: 320 000 FCFA | H5: 350 000 FCFA | I5: Augmentation merit et inflation | J5: Signe | K5: 45689
B6: AV-002 | C6: Kamga Patrice | D6: Receptionniste | E6: Renouvellement CDD | F6: 45833 | G6: Fin 30/06/2025 | H6: Fin 31/12/2025 | I6: Continuite mission | J6: En cours
B7: AV-003 | C7: Fouda M. | D7: Cuisinier | E7: Augmentation salariale | F7: 45748 | G7: 200 000 FCFA | H7: 220 000 FCFA | I7: Promotion interne | J7: Signe | K7: 45748
B8: AV-004 | C8: Nganou D. | D8: Receptionniste | E8: Changement de poste | F8: 45778 | G8: Agent Entretien | H8: Receptionniste | I8: Mutation laterale demande | J8: Signe | K8: 45775
B9: AV-005 | C9: Meyong S. | D9: Agent Securite | E9: Changement de poste | F9: 45778 | G9: Agent Securite | H9: Concierge | I9: Promotion interne | J9: Signe | K9: 45777
B10: =IF(C10="","AV-"&TEXT(COUNTA($C$5:C10),"000"))
B11: =IF(C11="","AV-"&TEXT(COUNTA($C$5:C11),"000"))
B12: =IF(C12="","AV-"&TEXT(COUNTA($C$5:C12),"000"))
B13: =IF(C13="","AV-"&TEXT(COUNTA($C$5:C13),"000"))
B14: =IF(C14="","AV-"&TEXT(COUNTA($C$5:C14),"000"))
B15: =IF(C15="","AV-"&TEXT(COUNTA($C$5:C15),"000"))
B16: =IF(C16="","AV-"&TEXT(COUNTA($C$5:C16),"000"))
B17: =IF(C17="","AV-"&TEXT(COUNTA($C$5:C17),"000"))
B18: =IF(C18="","AV-"&TEXT(COUNTA($C$5:C18),"000"))
B19: =IF(C19="","AV-"&TEXT(COUNTA($C$5:C19),"000"))
B20: =IF(C20="","AV-"&TEXT(COUNTA($C$5:C20),"000"))
B21: =IF(C21="","AV-"&TEXT(COUNTA($C$5:C21),"000"))
... B109: =IF(C109="","AV-"&TEXT(COUNTA($C$5:C109),"000"))
B111: INDICATEURS (mis a jour automatiquement)
B112: Avenants total | D112: Signes | F112: En cours
B113: =COUNTIF(B5:B104,"<>") | D113: =COUNTIF(J5:J104,"Signe") | F113: =COUNTIF(J5:J104,"En cours")

Sheet 5-Proc. Discip. Juridiques
B2: PROCÉDURES DISCIPLINAIRES - VOLET JURIDIQUE (#120)
B3: TABLEAU DYNAMIQUE — Saisissez dans la prochaine ligne jaune. Les calculs se mettent a jour automatiquement.
B4: N° | C4: Employe | D4: Poste | E4: Departement | F4: Type Infraction | G4: Date Infraction | H4: Description Faits | I4: Sanction Prononcee | J4: Date Notification | K4: Statut | L4: Voie Recours
B5: PDJ-001 | C5: Abdou B. | D5: Plongeur | E5: Cuisine & Restauration | F5: Absence injustifiee | G5: 45726 | H5: Absence 3 jours consecutifs sans justificatif | I5: Mise a pied disciplinaire 5j | J5: 45731 | K5: Clos | L5: Non exercee
B6: PDJ-002 | C6: Esso M. | D6: Agent Entretien | E6: Maintenance | F6: Retard repetes | G6: 45752 | H6: 5 retards > 30 min en 1 mois | I6: Avertissement ecrit | J6: 45755 | K6: Clos | L6: Non exercee
B7: PDJ-003 | C7: Tchouanku G. | D7: Agent Securite | E7: Sécurité | F7: Ivresse au travail | G7: 45797 | H7: Agent retrouve en etat d'ebriete poste nuit | I7: Licenciement pour faute | J7: 45799 | K7: Clos | L7: Saisie Inspection travail
B8: PDJ-004 | C8: Nana C. | D8: Receptionniste | E8: Réception & Front Office | F8: Insubordination | G8: 45810 | H8: Refus d'executer consignes N+1 a 3 reprises | I8: Avertissement ecrit | J8: 45813 | K8: Clos | L8: Non exercee
B9: =IF(C9="","PDJ-"&TEXT(COUNTA($C$5:C9),"000"))
B10: =IF(C10="","PDJ-"&TEXT(COUNTA($C$5:C10),"000"))
B11: =IF(C11="","PDJ-"&TEXT(COUNTA($C$5:C11),"000"))
B12: =IF(C12="","PDJ-"&TEXT(COUNTA($C$5:C12),"000"))
B13: =IF(C13="","PDJ-"&TEXT(COUNTA($C$5:C13),"000"))
B14: =IF(C14="","PDJ-"&TEXT(COUNTA($C$5:C14),"000"))
B15: =IF(C15="","PDJ-"&TEXT(COUNTA($C$5:C15),"000"))
B16: =IF(C16="","PDJ-"&TEXT(COUNTA($C$5:C16),"000"))
B17: =IF(C17="","PDJ-"&TEXT(COUNTA($C$5:C17),"000"))
B18: =IF(C18="","PDJ-"&TEXT(COUNTA($C$5:C18),"000"))
B19: =IF(C19="","PDJ-"&TEXT(COUNTA($C$5:C19),"000"))
B20: =IF(C20="","PDJ-"&TEXT(COUNTA($C$5:C20),"000"))
... B108: =IF(C108="","PDJ-"&TEXT(COUNTA($C$5:C108),"000"))
B110: INDICATEURS (mis a jour automatiquement)
B111: Procedures | D111: Cloturees | F111: Fautes graves
B112: =COUNTIF(B5:B104,"<>") | D112: =COUNTIF(K5:K104,"Clos") | F112: =COUNTIF(I5:I104,"*Licenciement*")

Sheet 6-Declarations CNPS Impots
B2: DÉCLARATIONS CNPS / IMPÔTS (#121)
B3: TABLEAU DYNAMIQUE — Saisissez dans la prochaine ligne jaune. Les calculs se mettent a jour automatiquement.
B4: N° | C4: Type Declaration | D4: Mois / Periode | E4: Annee | F4: Montant Declare (FCFA) | G4: Date Echeance | H4: Date Paiement | I4: Penalites (FCFA) | J4: Statut | K4: Reference
B5: DEC-001 | C5: CNPS mensuelle | D5: Janvier | E5: 2025 | F5: 1850000 | G5: 45703 | H5: 45700 | I5: 0 | J5: Effectuee | K5: CNPS-2025-001
B6: DEC-002 | C6: IR mensuel | D6: Janvier | E6: 2025 | F6: 620000 | G6: 45703 | H6: 45702 | I6: 0 | J6: Effectuee | K6: DGI-2025-001
B7: DEC-003 | C7: CNPS mensuelle | D7: Fevrier | E7: 2025 | F7: 1870000 | G7: 45731 | H7: 45734 | I7: 45000 | J7: Effectuee | K7: CNPS-2025-002
B8: DEC-004 | C8: IR mensuel | D8: Fevrier | E8: 2025 | F8: 635000 | G8: 45731 | H8: 45731 | I8: 0 | J8: Effectuee | K8: DGI-2025-002
B9: DEC-005 | C9: CNPS mensuelle | D9: Mars | E9: 2025 | F9: 1890000 | G9: 45762 | I9: 0 | J9: En retard | K9: CNPS-2025-003
B10: =IF(C10="","DEC-"&TEXT(COUNTA($C$5:C10),"000"))
B11: =IF(C11="","DEC-"&TEXT(COUNTA($C$5:C11),"000"))
B12: =IF(C12="","DEC-"&TEXT(COUNTA($C$5:C12),"000"))
B13: =IF(C13="","DEC-"&TEXT(COUNTA($C$5:C13),"000"))
B14: =IF(C14="","DEC-"&TEXT(COUNTA($C$5:C14),"000"))
B15: =IF(C15="","DEC-"&TEXT(COUNTA($C$5:C15),"000"))
B16: =IF(C16="","DEC-"&TEXT(COUNTA($C$5:C16),"000"))
B17: =IF(C17="","DEC-"&TEXT(COUNTA($C$5:C17),"000"))
B18: =IF(C18="","DEC-"&TEXT(COUNTA($C$5:C18),"000"))
B19: =IF(C19="","DEC-"&TEXT(COUNTA($C$5:C19),"000"))
B20: =IF(C20="","DEC-"&TEXT(COUNTA($C$5:C20),"000"))
B21: =IF(C21="","DEC-"&TEXT(COUNTA($C$5:C21),"000"))
... B109: =IF(C109="","DEC-"&TEXT(COUNTA($C$5:C109),"000"))
B111: TOTAL | F111: =SUM(F5:F104) | I111: =SUM(I5:I104)
B113: INDICATEURS (mis a jour automatiquement)
B114: Declarations total | D114: En retard | F114: Total penalites
B115: =COUNTIF(B5:B104,"<>") | D115: =COUNTIF(J5:J104,"En retard") | F115: =SUM(I5:I104)

Sheet 7-Suivi Legislation Travail
B2: SUIVI LÉGISLATION DU TRAVAIL (#122)
B3: TABLEAU DYNAMIQUE — Saisissez dans la prochaine ligne jaune. Les calculs se mettent a jour automatiquement.
B4: N° | C4: Texte Legal | D4: Domaine | E4: Date Publication | F4: Date Entree Vig. | G4: Impact sur Hotel | H4: Actions Requises | I4: Responsable | J4: Statut | K4: Observations
B5: LEG-001 | C5: Loi 2024-012 salaire minimum | D5: Conditions travail | E5: 45641 | F5: 45658 | G5: Revalorisation salariale 15% minimum | H5: Ajuster grille salariale + informer employes | I5: DRH Fotso M. + DAF | J5: En cours | K5: Budget a revoir pour Q2 2025
B6: LEG-002 | C6: Arrete hygiene restauration | D6: Hygiene securite | E6: 45677 | F6: 45689 | G6: Nouvelles normes HACCP renforcees cuisine | H6: Formation equipe + mise aux normes equipements | I6: Chef Cuisine + DRH | J6: En cours | K6: Formation HACCP niveau 3 planifiee
B7: LEG-003 | C7: Decret CNPS cotisations 2025 | D7: Securite sociale | E7: 45656 | F7: 45658 | G7: Augmentation taux cotisation patronale de 0.5% | H7: Mettre a jour parametres paie + budget previsionnel | I7: DAF + DRH | J7: Termine | K7: Taux actualises dans logiciel paie
B8: LEG-004 | C8: Code du travail revision Art. 45 | D8: Conditions travail | E8: 45726 | F8: 45809 | G8: Flexibilisation heures supplementaires max 12h/semaine | H8: Reviser plannings + informer managers | I8: DRH Fotso M. | J8: En cours | K8: Consultation syndicats en cours
B9: LEG-005 | C9: Circulaire inspection travail | D9: Contrat de travail | E9: 45748 | F9: 45762 | G9: Obligation contrat ecrit meme pour CDD < 6 mois | H9: Verifier tous les contrats en cours | I9: Assistante RH | J9: En cours | K9: Audit en cours, 2 CDD a regulariser
B10: =IF(C10="","LEG-"&TEXT(COUNTA($C$5:C10),"000"))
B11: =IF(C11="","LEG-"&TEXT(COUNTA($C$5:C11),"000"))
B12: =IF(C12="","LEG-"&TEXT(COUNTA($C$5:C12),"000"))
B13: =IF(C13="","LEG-"&TEXT(COUNTA($C$5:C13),"000"))
B14: =IF(C14="","LEG-"&TEXT(COUNTA($C$5:C14),"000"))
B15: =IF(C15="","LEG-"&TEXT(COUNTA($C$5:C15),"000"))
B16: =IF(C16="","LEG-"&TEXT(COUNTA($C$5:C16),"000"))
B17: =IF(C17="","LEG-"&TEXT(COUNTA($C$5:C17),"000"))
B18: =IF(C18="","LEG-"&TEXT(COUNTA($C$5:C18),"000"))
B19: =IF(C19="","LEG-"&TEXT(COUNTA($C$5:C19),"000"))
B20: =IF(C20="","LEG-"&TEXT(COUNTA($C$5:C20),"000"))
B21: =IF(C21="","LEG-"&TEXT(COUNTA($C$5:C21),"000"))
... B109: =IF(C109="","LEG-"&TEXT(COUNTA($C$5:C109),"000"))
B111: INDICATEURS (mis a jour automatiquement)
B112: Textes suivis | D112: En cours | F112: Termine
B113: =COUNTIF(B5:B104,"<>") | D113: =COUNTIF(J5:J104,"En cours") | F113: =COUNTIF(J5:J104,"Termine")

Sheet 8-Audit Conformite RH
B2: AUDIT CONFORMITÉ RH (#123)
B3: TABLEAU DYNAMIQUE — Saisissez dans la prochaine ligne jaune. Les calculs se mettent a jour automatiquement.
B4: N° | C4: Domaine Audit | D4: Date Audit | E4: Auditeur | F4: Points Controles | G4: Conformes | H4: Non Conformes | I4: Taux Conformite (%) | J4: Observations | K4: Plan Action
B5: AUD-001 | C5: Contrats de travail | D5: 45677 | E5: DRH Fotso M. | F5: 25 | G5: 22 | H5: 3 | J5: 3 CDD sans contrat ecrit formel | K5: Regulariser sous 30 jours
B6: AUD-002 | C6: Declarations sociales | D6: 45703 | E6: DAF + DRH | F6: 12 | G6: 10 | H6: 2 | J6: 2 declarations CNPS en retard fevrier | K6: Mettre en place echeancier automatique
B7: AUD-003 | C7: Hygiene securite cuisine | D7: 45726 | E7: Chef Cuisine + Securite | F7: 30 | G7: 26 | H7: 4 | J7: EPI manquants, formation HACCP incomplete | K7: Commander EPI + planifier formation
B8: AUD-004 | C8: Registres obligatoires | D8: 45752 | E8: DRH Fotso M. | F8: 15 | G8: 14 | H8: 1 | J8: Registre unique du personnel incomplet | K8: Mettre a jour registre sous 15 jours
B9: AUD-005 | C9: Duree du travail | D9: 45778 | E9: DRH + DAF | F9: 20 | G9: 17 | H9: 3 | J9: Depassement heures cuisine et entretien | K9: Reviser plannings + recruter renfort
B10: =IF(C10="","AUD-"&TEXT(COUNTA($C$5:C10),"000")) | I10: =IF(OR(F10="",F10=0),"",G10/F10)
B11: =IF(C11="","AUD-"&TEXT(COUNTA($C$5:C11),"000")) | I11: =IF(OR(F11="",F11=0),"",G11/F11)
B12: =IF(C12="","AUD-"&TEXT(COUNTA($C$5:C12),"000")) | I12: =IF(OR(F12="",F12=0),"",G12/F12)
B13: =IF(C13="","AUD-"&TEXT(COUNTA($C$5:C13),"000")) | I13: =IF(OR(F13="",F13=0),"",G13/F13)
B14: =IF(C14="","AUD-"&TEXT(COUNTA($C$5:C14),"000")) | I14: =IF(OR(F14="",F14=0),"",G14/F14)
B15: =IF(C15="","AUD-"&TEXT(COUNTA($C$5:C15),"000")) | I15: =IF(OR(F15="",F15=0),"",G15/F15)
B16: =IF(C16="","AUD-"&TEXT(COUNTA($C$5:C16),"000")) | I16: =IF(OR(F16="",F16=0),"",G16/F16)
B17: =IF(C17="","AUD-"&TEXT(COUNTA($C$5:C17),"000")) | I17: =IF(OR(F17="",F17=0),"",G17/F17)
B18: =IF(C18="","AUD-"&TEXT(COUNTA($C$5:C18),"000")) | I18: =IF(OR(F18="",F18=0),"",G18/F18)
B19: =IF(C19="","AUD-"&TEXT(COUNTA($C$5:C19),"000")) | I19: =IF(OR(F19="",F19=0),"",G19/F19)
B20: =IF(C20="","AUD-"&TEXT(COUNTA($C$5:C20),"000")) | I20: =IF(OR(F20="",F20=0),"",G20/F20)
B21: =IF(C21="","AUD-"&TEXT(COUNTA($C$5:C21),"000")) | I21: =IF(OR(F21="",F21=0),"",G21/F21)
... B109: =IF(C109="","AUD-"&TEXT(COUNTA($C$5:C109),"000")) | I109: =IF(OR(F109="",F109=0),"",G109/F109)
B111: INDICATEURS (mis a jour automatiquement)
B112: Audits realises | D112: Taux moy. conformite | F112: Total non conformes
B113: =COUNTIF(B5:B104,"<>") | D113: =IFERROR(AVERAGE(I5:I104),0) | F113: =SUM(H5:H104)

Sheet 9-Gestion Litiges Contentieux
B2: GESTION LITIGES & CONTENTIEUX (#124)
B3: TABLEAU DYNAMIQUE — Saisissez dans la prochaine ligne jaune. Les calculs se mettent a jour automatiquement.
B4: N° | C4: Plaignant | D4: Poste | E4: Type Litige | F4: Date Ouverture | G4: Description | H4: Montant Reclame (FCFA) | I4: Avocat / Conseil | J4: Statut | K4: Date Cloture | L4: Issue
B5: LIT-001 | C5: Tchouanku G. | D5: Agent Securite | E5: Licenciement abusif | F5: 45802 | G5: Contestation licenciement pour faute, allegation procedure irreguliere | H5: 3500000 | I5: Me. Ngando | J5: En cours
B6: LIT-002 | C6: Abdou B. | D6: Plongeur | E6: Heures supplementaires | F6: 45698 | G6: Reclamation paiement 45 heures supplementaires non payees | H6: 180000 | I6: Conciliation interne DRH | J6: Resolu | K6: 45731 | L6: Accord transactionnel 150000 FCFA
B7: LIT-003 | C7: Ex-employe Manga K. | D7: Ancien Cuisinier | E7: Conditions travail | F7: 45597 | G7: Demolition pour conditions de travail dangereuses en cuisine | H7: 5000000 | I7: Me. Ngando | J7: Assigne tribunal
B8: LIT-004 | C8: Nana C. | D8: Receptionniste | E8: Harcèlement | F8: 45818 | G8: Allegation harcelement moral par N+1 | H8: 8000000 | I8: Mediateur interne | J8: En conciliation
B9: =IF(C9="","LIT-"&TEXT(COUNTA($C$5:C9),"000"))
B10: =IF(C10="","LIT-"&TEXT(COUNTA($C$5:C10),"000"))
B11: =IF(C11="","LIT-"&TEXT(COUNTA($C$5:C11),"000"))
B12: =IF(C12="","LIT-"&TEXT(COUNTA($C$5:C12),"000"))
B13: =IF(C13="","LIT-"&TEXT(COUNTA($C$5:C13),"000"))
B14: =IF(C14="","LIT-"&TEXT(COUNTA($C$5:C14),"000"))
B15: =IF(C15="","LIT-"&TEXT(COUNTA($C$5:C15),"000"))
B16: =IF(C16="","LIT-"&TEXT(COUNTA($C$5:C16),"000"))
B17: =IF(C17="","LIT-"&TEXT(COUNTA($C$5:C17),"000"))
B18: =IF(C18="","LIT-"&TEXT(COUNTA($C$5:C18),"000"))
B19: =IF(C19="","LIT-"&TEXT(COUNTA($C$5:C19),"000"))
B20: =IF(C20="","LIT-"&TEXT(COUNTA($C$5:C20),"000"))
... B108: =IF(C108="","LIT-"&TEXT(COUNTA($C$5:C108),"000"))
B110: TOTAL | H110: =SUM(H5:H104)
B112: INDICATEURS (mis a jour automatiquement)
B113: Litiges total | D113: En cours | F113: Montant total (M)
B114: =COUNTIF(B5:B104,"<>") | D114: =COUNTIF(J5:J104,"En cours")+COUNTIF(J5:J104,"En conciliation")+COUNTIF(J5:J104,"Assigne tribunal") | F114: =IFERROR(SUM(H5:H104)/1000000,0)

Sheet 10-Registre Visites Inspect.
B2: REGISTRE VISITES D'INSPECTION (#125)
B3: TABLEAU DYNAMIQUE — Saisissez dans la prochaine ligne jaune. Les calculs se mettent a jour automatiquement.
B4: N° | C4: Organisme | D4: Type Visite | E4: Date Visite | F4: Inspecteur | G4: Domaine Verifie | H4: Constats | I4: Mises en Demeure | J4: Echeance Reponse | K4: Statut
B5: VIS-001 | C5: Inspection du travail | D5: Visite inopinee | E5: 45672 | F5: Inspecteur Nganou | G5: Contrats travail + registres | H5: 2 CDD irreguliers detectes | I5: 1 mise en demeure | J5: 45703 | K5: Resolu
B6: VIS-002 | C6: CNPS | D6: Controle cotisations | E6: 45736 | F6: Controleur Fotso | G6: Cotisations sociales | H6: Retard declaration fevrier | I6: Avertissement | J6: 45767 | K6: Resolu
B7: VIS-003 | C7: Inspection du travail | D7: Visite de routine | E7: 45787 | F7: Inspecteur Kamga | G7: Duree travail + repos hebdo | H7: Depassement heures cuisine | I7: 0 | K7: Resolu
B8: VIS-004 | C8: Ministere du Travail | D8: Audit securite hotel | E8: 45809 | F8: Equipe ministerielle | G8: Hygiene securite generale | H8: Extincteurs perimes etage 2 | I8: 1 mise en demeure | J8: 45839 | K8: En cours
B9: =IF(C9="","VIS-"&TEXT(COUNTA($C$5:C9),"000"))
B10: =IF(C10="","VIS-"&TEXT(COUNTA($C$5:C10),"000"))
B11: =IF(C11="","VIS-"&TEXT(COUNTA($C$5:C11),"000"))
B12: =IF(C12="","VIS-"&TEXT(COUNTA($C$5:C12),"000"))
B13: =IF(C13="","VIS-"&TEXT(COUNTA($C$5:C13),"000"))
B14: =IF(C14="","VIS-"&TEXT(COUNTA($C$5:C14),"000"))
B15: =IF(C15="","VIS-"&TEXT(COUNTA($C$5:C15),"000"))
B16: =IF(C16="","VIS-"&TEXT(COUNTA($C$5:C16),"000"))
B17: =IF(C17="","VIS-"&TEXT(COUNTA($C$5:C17),"000"))
B18: =IF(C18="","VIS-"&TEXT(COUNTA($C$5:C18),"000"))
B19: =IF(C19="","VIS-"&TEXT(COUNTA($C$5:C19),"000"))
B20: =IF(C20="","VIS-"&TEXT(COUNTA($C$5:C20),"000"))
... B108: =IF(C108="","VIS-"&TEXT(COUNTA($C$5:C108),"000"))
B110: INDICATEURS (mis a jour automatiquement)
B111: Visites total | D111: Resolues | F111: Mises en demeure
B112: =COUNTIF(B5:B104,"<>") | D112: =COUNTIF(K5:K104,"Resolu") | F112: =COUNTIF(I5:I104,"*mise*")+COUNTIF(I5:I104,"1")+COUNTIF(I5:I104,"2")

Sheet 11-Politiques Procedures RH
B2: POLITIQUES & PROCÉDURES RH (#126)
B3: TABLEAU DYNAMIQUE — Saisissez dans la prochaine ligne jaune. Les calculs se mettent a jour automatiquement.
B4: N° | C4: Politique / Procedure | D4: Type | E4: Version | F4: Date Approbation | G4: Approuve Par | H4: Diffusion | I4: Statut | J4: Prochaine Revision | K4: Observations
B5: POL-001 | C5: Reglement interieur de l'hotel | D5: Reglement interieur | E5: V3.2 | F5: 45458 | G5: DG + CSE | H5: Affichage + remise individuel | I5: En vigueur | J5: 45823 | K5: Mise a jour annuelle prevue juin 2025
B6: POL-002 | C6: Politique de remuneration | D6: Politique remuneration | E6: V2.1 | F6: 45667 | G6: DG + DRH | H6: Communication a tous les managers | I6: En vigueur | J6: 46032 | K6: Integrer nouveau salaire minimum
B7: POL-003 | C7: Charte ethique et conduite | D7: Charte ethique | E7: V1.5 | F7: 45352 | G7: DG | H7: Remise a tout nouvel employe | I7: En vigueur | J7: 45901 | K7: A enrichir avec volet digital
B8: POL-004 | C8: Procedure de recrutement | D8: Procedure recrutement | E8: V2.0 | F8: 45536 | G8: DRH | H8: Partage service RH + managers | I8: En vigueur | J8: 45901 | K8: Ajouter etapes test technique
B9: POL-005 | C9: Politique diversite et inclusion | D9: Politique diversite | E9: V1.0 | F9: 45689 | G9: DG + DRH | H9: Communication interne | I9: En vigueur | J9: 46054 | K9: Nouvelle politique, suivi prevu
B10: =IF(C10="","POL-"&TEXT(COUNTA($C$5:C10),"000"))
B11: =IF(C11="","POL-"&TEXT(COUNTA($C$5:C11),"000"))
B12: =IF(C12="","POL-"&TEXT(COUNTA($C$5:C12),"000"))
B13: =IF(C13="","POL-"&TEXT(COUNTA($C$5:C13),"000"))
B14: =IF(C14="","POL-"&TEXT(COUNTA($C$5:C14),"000"))
B15: =IF(C15="","POL-"&TEXT(COUNTA($C$5:C15),"000"))
B16: =IF(C16="","POL-"&TEXT(COUNTA($C$5:C16),"000"))
B17: =IF(C17="","POL-"&TEXT(COUNTA($C$5:C17),"000"))
B18: =IF(C18="","POL-"&TEXT(COUNTA($C$5:C18),"000"))
B19: =IF(C19="","POL-"&TEXT(COUNTA($C$5:C19),"000"))
B20: =IF(C20="","POL-"&TEXT(COUNTA($C$5:C20),"000"))
B21: =IF(C21="","POL-"&TEXT(COUNTA($C$5:C21),"000"))
... B109: =IF(C109="","POL-"&TEXT(COUNTA($C$5:C109),"000"))
B111: INDICATEURS (mis a jour automatiquement)
B112: Documents total | D112: En vigueur | F112: A reviser < 90j
B113: =COUNTIF(B5:B104,"<>") | D113: =COUNTIF(I5:I104,"En vigueur") | F113: =COUNTIF(J5:J104,"<"&TODAY()+90)

Sheet 12-Suivi Echeances Legales
B2: SUIVI ÉCHÉANCES LÉGALES
B3: TABLEAU DYNAMIQUE — Saisissez dans la prochaine ligne jaune. Les calculs se mettent a jour automatiquement.
B4: N° | C4: Echeance | D4: Type | E4: Periodicite | F4: Date Echeance | G4: Jours Restants | H4: Responsable | I4: Statut | J4: Montant Estime (FCFA)
B5: ECH-001 | C5: Declaration CNPS juin | D5: CNPS mensuelle | E5: Mensuelle | F5: 45853 | H5: DAF | I5: En cours | J5: 1890000
B6: ECH-002 | C6: IR mensuel juin | D6: IR mensuel | E6: Mensuelle | F6: 45853 | H6: DAF | I6: En cours | J6: 640000
B7: ECH-003 | C7: Bilan social 2025 | D7: Bilan social | E7: Annuelle | F7: 46112 | H7: DRH | I7: En attente | J7: 0
B8: ECH-004 | C8: Taxe d'apprentissage | D8: Taxe d'apprentissage | E8: Annuelle | F8: 46053 | H8: DAF + DRH | I8: En attente | J8: 450000
B9: ECH-005 | C9: Renouvellement CDD Kamga | D9: Contrat travail | E9: Ponctuelle | F9: 45838 | H9: DRH | I9: En cours | J9: 0
B10: =IF(C10="","ECH-"&TEXT(COUNTA($C$5:C10),"000")) | G10: =IF(F10="","",F10-TODAY())
B11: =IF(C11="","ECH-"&TEXT(COUNTA($C$5:C11),"000")) | G11: =IF(F11="","",F11-TODAY())
B12: =IF(C12="","ECH-"&TEXT(COUNTA($C$5:C12),"000")) | G12: =IF(F12="","",F12-TODAY())
B13: =IF(C13="","ECH-"&TEXT(COUNTA($C$5:C13),"000")) | G13: =IF(F13="","",F13-TODAY())
B14: =IF(C14="","ECH-"&TEXT(COUNTA($C$5:C14),"000")) | G14: =IF(F14="","",F14-TODAY())
B15: =IF(C15="","ECH-"&TEXT(COUNTA($C$5:C15),"000")) | G15: =IF(F15="","",F15-TODAY())
B16: =IF(C16="","ECH-"&TEXT(COUNTA($C$5:C16),"000")) | G16: =IF(F16="","",F16-TODAY())
B17: =IF(C17="","ECH-"&TEXT(COUNTA($C$5:C17),"000")) | G17: =IF(F17="","",F17-TODAY())
B18: =IF(C18="","ECH-"&TEXT(COUNTA($C$5:C18),"000")) | G18: =IF(F18="","",F18-TODAY())
B19: =IF(C19="","ECH-"&TEXT(COUNTA($C$5:C19),"000")) | G19: =IF(F19="","",F19-TODAY())
B20: =IF(C20="","ECH-"&TEXT(COUNTA($C$5:C20),"000")) | G20: =IF(F20="","",F20-TODAY())
B21: =IF(C21="","ECH-"&TEXT(COUNTA($C$5:C21),"000")) | G21: =IF(F21="","",F21-TODAY())
... B109: =IF(C109="","ECH-"&TEXT(COUNTA($C$5:C109),"000")) | G109: =IF(F109="","",F109-TODAY())
B111: INDICATEURS (mis a jour automatiquement)
B112: Echeances total | D112: A venir < 30j | F112: En retard
B113: =COUNTIF(B5:B104,"<>") | D113: =COUNTIF(G5:G104,"<"&30)-COUNTIF(G5:G104,"<"&0) | F113: =COUNTIF(G5:G104,"<"&0)

Sheet 13-Indicateurs Conformite
B2: INDICATEURS DE CONFORMITÉ — Mensuel
B3: TABLEAU DYNAMIQUE — Saisissez dans la prochaine ligne jaune. Les calculs se mettent a jour automatiquement.
B4: N° | C4: Mois | D4: Annee | E4: Taux Conformite Contrats (%) | F4: Taux Conformite Decl. (%) | G4: Taux Respect Delais (%) | H4: Nb Non-Conformites | I4: Nb Litiges Ouverts | J4: Cout Penalites (FCFA)
B5: IC-001 | C5: Janvier | D5: 2025 | E5: 96 | F5: 100 | G5: 100 | H5: 0 | I5: 1 | J5: 0
B6: IC-002 | C6: Fevrier | D6: 2025 | E6: 96 | F6: 92 | G6: 92 | H6: 2 | I6: 1 | J6: 45000
B7: IC-003 | C7: Mars | D7: 2025 | E7: 98 | F7: 100 | G7: 96 | H7: 1 | I7: 2 | J7: 0
B8: IC-004 | C8: Avril | D8: 2025 | E8: 94 | F8: 100 | G8: 100 | H8: 2 | I8: 1 | J8: 0
B9: IC-005 | C9: Mai | D9: 2025 | E9: 92 | F9: 92 | G9: 88 | H9: 3 | I9: 3 | J9: 45000
B10: =IF(C10="","IC-"&TEXT(COUNTA($C$5:C10),"000"))
B11: =IF(C11="","IC-"&TEXT(COUNTA($C$5:C11),"000"))
B12: =IF(C12="","IC-"&TEXT(COUNTA($C$5:C12),"000"))
B13: =IF(C13="","IC-"&TEXT(COUNTA($C$5:C13),"000"))
B14: =IF(C14="","IC-"&TEXT(COUNTA($C$5:C14),"000"))
B15: =IF(C15="","IC-"&TEXT(COUNTA($C$5:C15),"000"))
B16: =IF(C16="","IC-"&TEXT(COUNTA($C$5:C16),"000"))
B17: =IF(C17="","IC-"&TEXT(COUNTA($C$5:C17),"000"))
B18: =IF(C18="","IC-"&TEXT(COUNTA($C$5:C18),"000"))
B19: =IF(C19="","IC-"&TEXT(COUNTA($C$5:C19),"000"))
B20: =IF(C20="","IC-"&TEXT(COUNTA($C$5:C20),"000"))
B21: =IF(C21="","IC-"&TEXT(COUNTA($C$5:C21),"000"))
... B109: =IF(C109="","IC-"&TEXT(COUNTA($C$5:C109),"000"))
B111: TOTAL | H111: =SUM(H5:H104) | I111: =SUM(I5:I104) | J111: =SUM(J5:J104)
B113: INDICATEURS (mis a jour automatiquement)
B114: Conformite moy. contrats | D114: Total non-conformites | F114: Cout total penalites
B115: =IFERROR(AVERAGE(E5:E104),0) | D115: =SUM(H5:H104) | F115: =SUM(J5:J104)

Sheet 14-Hist. Modif. Legales
B2: HISTORIQUE MODIFICATIONS LÉGALES
B3: TABLEAU DYNAMIQUE — Saisissez dans la prochaine ligne jaune. Les calculs se mettent a jour automatiquement.
B4: N° | C4: Date Modification | D4: Texte Legal | E4: Nature Modification | F4: Impact Hotel | G4: Action Menee | H4: Responsable | I4: Cout Impact (FCFA) | J4: Statut
B5: HML-001 | C5: 45658 | D5: Decret CNPS cotisations 2025 | E5: Augmentation taux cotisation | F5: Augmentation charge patronale 0.5% | G5: Mise a jour logiciel paie + budget previsionnel | H5: DAF | I5: 150000 | J5: Termine
B6: HML-002 | C6: 45689 | D6: Arrete hygiene restauration | E6: Renforcement normes HACCP | F6: Formation obligatoire equipe cuisine | G6: Planification formation HACCP niveau 3 | H6: Chef Cuisine | I6: 350000 | J6: En cours
B7: HML-003 | C7: 45762 | D7: Circulaire inspection travail | E7: Obligation contrat ecrit CDD | F7: 3 contrats a regulariser | G7: Redaction et signature avenants | H7: Assistante RH | I7: 0 | J7: En cours
B8: HML-004 | C8: 45809 | D8: Code du travail Art. 45 revision | E8: Flexibilisation heures supp. | F8: Revision plannings cuisine et entretien | G8: Consultation syndicats + nouveau planning | H8: DRH | I8: 200000 | J8: En cours
B9: =IF(C9="","HML-"&TEXT(COUNTA($C$5:C9),"000"))
B10: =IF(C10="","HML-"&TEXT(COUNTA($C$5:C10),"000"))
B11: =IF(C11="","HML-"&TEXT(COUNTA($C$5:C11),"000"))
B12: =IF(C12="","HML-"&TEXT(COUNTA($C$5:C12),"000"))
B13: =IF(C13="","HML-"&TEXT(COUNTA($C$5:C13),"000"))
B14: =IF(C14="","HML-"&TEXT(COUNTA($C$5:C14),"000"))
B15: =IF(C15="","HML-"&TEXT(COUNTA($C$5:C15),"000"))
B16: =IF(C16="","HML-"&TEXT(COUNTA($C$5:C16),"000"))
B17: =IF(C17="","HML-"&TEXT(COUNTA($C$5:C17),"000"))
B18: =IF(C18="","HML-"&TEXT(COUNTA($C$5:C18),"000"))
B19: =IF(C19="","HML-"&TEXT(COUNTA($C$5:C19),"000"))
B20: =IF(C20="","HML-"&TEXT(COUNTA($C$5:C20),"000"))
... B108: =IF(C108="","HML-"&TEXT(COUNTA($C$5:C108),"000"))
B110: TOTAL | I110: =SUM(I5:I104)
B112: INDICATEURS (mis a jour automatiquement)
B113: Modifications total | D113: Cout total impact (k) | F113: En cours
B114: =COUNTIF(B5:B104,"<>") | D114: =IFERROR(SUM(I5:I104)/1000,0) | F114: =COUNTIF(J5:J104,"En cours")

Sheet 15-Suivi Contentieux
B2: SUIVI CONTENTIEUX — Dossiers Juridiques
B3: TABLEAU DYNAMIQUE — Saisissez dans la prochaine ligne jaune. Les calculs se mettent a jour automatiquement.
B4: N° | C4: Dossier | D4: Type Litige | E4: Date Ouverture | F4: Phase Actuelle | G4: Jours depuis Ouverture | H4: Prochaine Echeance | I4: Cout Avocat (FCFA) | J4: Montant Enjeu (FCFA) | K4: Statut
B5: SC-001 | C5: Tchouanku c/ Hotel | D5: Licenciement abusif | E5: 45802 | F5: En instruction | H5: 45884 | I5: 200000 | J5: 3500000 | K5: En cours
B6: SC-002 | C6: Abdou B. - Heures supp. | D6: Heures supplementaires | E6: 45698 | F6: Conciliation | I6: 0 | J6: 180000 | K6: Resolu
B7: SC-003 | C7: Manga K. c/ Hotel | D7: Conditions travail | E7: 45597 | F7: Assigne tribunal | H7: 45910 | I7: 500000 | J7: 5000000 | K7: Assigne tribunal
B8: SC-004 | C8: Nana C. - Harcelement | D8: Harcèlement | E8: 45818 | F8: Conciliation interne | H8: 45870 | I8: 0 | J8: 8000000 | K8: En conciliation
B9: =IF(C9="","SC-"&TEXT(COUNTA($C$5:C9),"000")) | G9: =IF(F9="","",TODAY()-F9)
B10: =IF(C10="","SC-"&TEXT(COUNTA($C$5:C10),"000")) | G10: =IF(F10="","",TODAY()-F10)
B11: =IF(C11="","SC-"&TEXT(COUNTA($C$5:C11),"000")) | G11: =IF(F11="","",TODAY()-F11)
B12: =IF(C12="","SC-"&TEXT(COUNTA($C$5:C12),"000")) | G12: =IF(F12="","",TODAY()-F12)
B13: =IF(C13="","SC-"&TEXT(COUNTA($C$5:C13),"000")) | G13: =IF(F13="","",TODAY()-F13)
B14: =IF(C14="","SC-"&TEXT(COUNTA($C$5:C14),"000")) | G14: =IF(F14="","",TODAY()-F14)
B15: =IF(C15="","SC-"&TEXT(COUNTA($C$5:C15),"000")) | G15: =IF(F15="","",TODAY()-F15)
B16: =IF(C16="","SC-"&TEXT(COUNTA($C$5:C16),"000")) | G16: =IF(F16="","",TODAY()-F16)
B17: =IF(C17="","SC-"&TEXT(COUNTA($C$5:C17),"000")) | G17: =IF(F17="","",TODAY()-F17)
B18: =IF(C18="","SC-"&TEXT(COUNTA($C$5:C18),"000")) | G18: =IF(F18="","",TODAY()-F18)
B19: =IF(C19="","SC-"&TEXT(COUNTA($C$5:C19),"000")) | G19: =IF(F19="","",TODAY()-F19)
B20: =IF(C20="","SC-"&TEXT(COUNTA($C$5:C20),"000")) | G20: =IF(F20="","",TODAY()-F20)
... B108: =IF(C108="","SC-"&TEXT(COUNTA($C$5:C108),"000")) | G108: =IF(F108="","",TODAY()-F108)
B110: TOTAL | I110: =SUM(I5:I104) | J110: =SUM(J5:J104)
B112: INDICATEURS (mis a jour automatiquement)
B113: Dossiers ouverts | D113: Total enjeux (M FCFA) | F113: Total frais avocat
B114: =COUNTIF(B5:B104,"<>") | D114: =IFERROR(SUM(J5:J104)/1000000,0) | F114: =SUM(I5:I104)

Sheet 16-Calendrier Decl. Sociales
B2: CALENDRIER DÉCLARATIONS SOCIALES
B3: TABLEAU DYNAMIQUE — Saisissez dans la prochaine ligne jaune. Les calculs se mettent a jour automatiquement.
B4: N° | C4: Type Declaration | D4: Mois | E4: Annee | F4: Date Echeance | G4: Date Paiement Effectif | H4: Retard (jours) | I4: Montant (FCFA) | J4: Penalites (FCFA) | K4: Statut
B5: CDS-001 | C5: CNPS mensuelle | D5: Janvier | E5: 2025 | F5: 45703 | G5: 45700 | I5: 1850000 | J5: 0 | K5: Effectuee
B6: CDS-002 | C6: IR mensuel | D6: Janvier | E6: 2025 | F6: 45703 | G6: 45702 | I6: 620000 | J6: 0 | K6: Effectuee
B7: CDS-003 | C7: CNPS mensuelle | D7: Fevrier | E7: 2025 | F7: 45731 | G7: 45734 | I7: 1870000 | J7: 45000 | K7: Effectuee
B8: CDS-004 | C8: IR mensuel | D8: Fevrier | E8: 2025 | F8: 45731 | G8: 45731 | I8: 635000 | J8: 0 | K8: Effectuee
B9: CDS-005 | C9: CNPS mensuelle | D9: Mars | E9: 2025 | F9: 45762 | I9: 1890000 | J9: 0 | K9: En retard
B10: =IF(C10="","CDS-"&TEXT(COUNTA($C$5:C10),"000")) | H10: =IF(OR(G10="",F10=""),"",IF(G10>F10,G10-F10,0))
B11: =IF(C11="","CDS-"&TEXT(COUNTA($C$5:C11),"000")) | H11: =IF(OR(G11="",F11=""),"",IF(G11>F11,G11-F11,0))
B12: =IF(C12="","CDS-"&TEXT(COUNTA($C$5:C12),"000")) | H12: =IF(OR(G12="",F12=""),"",IF(G12>F12,G12-F12,0))
B13: =IF(C13="","CDS-"&TEXT(COUNTA($C$5:C13),"000")) | H13: =IF(OR(G13="",F13=""),"",IF(G13>F13,G13-F13,0))
B14: =IF(C14="","CDS-"&TEXT(COUNTA($C$5:C14),"000")) | H14: =IF(OR(G14="",F14=""),"",IF(G14>F14,G14-F14,0))
B15: =IF(C15="","CDS-"&TEXT(COUNTA($C$5:C15),"000")) | H15: =IF(OR(G15="",F15=""),"",IF(G15>F15,G15-F15,0))
B16: =IF(C16="","CDS-"&TEXT(COUNTA($C$5:C16),"000")) | H16: =IF(OR(G16="",F16=""),"",IF(G16>F16,G16-F16,0))
B17: =IF(C17="","CDS-"&TEXT(COUNTA($C$5:C17),"000")) | H17: =IF(OR(G17="",F17=""),"",IF(G17>F17,G17-F17,0))
B18: =IF(C18="","CDS-"&TEXT(COUNTA($C$5:C18),"000")) | H18: =IF(OR(G18="",F18=""),"",IF(G18>F18,G18-F18,0))
B19: =IF(C19="","CDS-"&TEXT(COUNTA($C$5:C19),"000")) | H19: =IF(OR(G19="",F19=""),"",IF(G19>F19,G19-F19,0))
B20: =IF(C20="","CDS-"&TEXT(COUNTA($C$5:C20),"000")) | H20: =IF(OR(G20="",F20=""),"",IF(G20>F20,G20-F20,0))
B21: =IF(C21="","CDS-"&TEXT(COUNTA($C$5:C21),"000")) | H21: =IF(OR(G21="",F21=""),"",IF(G21>F21,G21-F21,0))
... B109: =IF(C109="","CDS-"&TEXT(COUNTA($C$5:C109),"000")) | H109: =IF(OR(G109="",F109=""),"",IF(G109>F109,G109-F109,0))
B111: TOTAL | I111: =SUM(I5:I104) | J111: =SUM(J5:J104)
B113: INDICATEURS (mis a jour automatiquement)
B114: Declarations total | D114: En retard | F114: Total penalites
B115: =COUNTIF(B5:B104,"<>") | D115: =COUNTIF(K5:K104,"En retard") | F115: =SUM(J5:J104)

Sheet 17-Matrice Risques Jurid.
B2: MATRICE RISQUES JURIDIQUES
B3: TABLEAU DYNAMIQUE — Saisissez dans la prochaine ligne jaune. Les calculs se mettent a jour automatiquement.
B4: N° | C4: Risque Juridique | D4: Domaine | E4: Probabilite | F4: Impact Financier | G4: Niveau Risque | H4: Mesures Prevention | I4: Responsable | J4: Statut
B5: MRJ-001 | C5: Non-paiement CNPS | D5: Securite sociale | E5: Elevee | F5: Eleve | G5: Critique | H5: Echeancier automatique + controle mensuel DAF | I5: DAF | J5: En cours
B6: MRJ-002 | C6: Licenciement abuseif | D6: Contrat de travail | E6: Moyenne | F6: Eleve | G6: Eleve | H6: Procedure stricte 3 etapes + avis juridique | I6: DRH | J6: En cours
B7: MRJ-003 | C7: Accident travail non declare | D7: Hygiene securite | E7: Faible | F7: Critique | G7: Eleve | H7: Formation equipe + registre SST rigoureux | I7: Chef Securite | J7: En cours
B8: MRJ-004 | C8: Heures supplementaires depassement | D8: Conditions travail | E8: Elevee | F8: Moyenne | G8: Eleve | H8: Pointage automatique + alerte 40h | I8: DRH + Managers | J8: En cours
B9: MRJ-005 | C9: Discrimination recrutement | D9: Contrat de travail | E9: Faible | F9: Moyenne | G9: Moyen | H9: Grille evaluation objective + double validation | I9: DRH | J9: En cours
B10: MRJ-006 | C10: Non respect repos hebdomadaire | D10: Conditions travail | E10: Moyenne | F10: Moyenne | G10: Eleve | H10: Planning automatique + controle pointage | I10: DRH + Managers | J10: En cours
B11: =IF(C11="","MRJ-"&TEXT(COUNTA($C$5:C11),"000"))
B12: =IF(C12="","MRJ-"&TEXT(COUNTA($C$5:C12),"000"))
B13: =IF(C13="","MRJ-"&TEXT(COUNTA($C$5:C13),"000"))
B14: =IF(C14="","MRJ-"&TEXT(COUNTA($C$5:C14),"000"))
B15: =IF(C15="","MRJ-"&TEXT(COUNTA($C$5:C15),"000"))
B16: =IF(C16="","MRJ-"&TEXT(COUNTA($C$5:C16),"000"))
B17: =IF(C17="","MRJ-"&TEXT(COUNTA($C$5:C17),"000"))
B18: =IF(C18="","MRJ-"&TEXT(COUNTA($C$5:C18),"000"))
B19: =IF(C19="","MRJ-"&TEXT(COUNTA($C$5:C19),"000"))
B20: =IF(C20="","MRJ-"&TEXT(COUNTA($C$5:C20),"000"))
B21: =IF(C21="","MRJ-"&TEXT(COUNTA($C$5:C21),"000"))
B22: =IF(C22="","MRJ-"&TEXT(COUNTA($C$5:C22),"000"))
... B110: =IF(C110="","MRJ-"&TEXT(COUNTA($C$5:C110),"000"))
B112: INDICATEURS (mis a jour automatiquement)
B113: Risques identifies | D113: Risques critiques | F113: Risques eleves
B114: =COUNTIF(B5:B104,"<>") | D114: =COUNTIF(G5:G104,"Critique") | F114: =COUNTIF(G5:G104,"Eleve")

Sheet 18-Suivi Avenants Contrats
B2: SUIVI AVENANTS CONTRATS — Conformité
B3: TABLEAU DYNAMIQUE — Saisissez dans la prochaine ligne jaune. Les calculs se mettent a jour automatiquement.
B4: N° | C4: Employe | D4: Poste | E4: Type Avenant | F4: Date Avenant | G4: Impact Salarial (FCFA) | H4: Delai Traitement (j) | I4: Conforme Procedure | J4: Statut
B5: SAV-001 | C5: Nkoulou Mbarga P. | D5: Chef Reception | E5: Augmentation salariale | F5: 45689 | G5: 30000 | H5: 5 | I5: Oui | J5: Signe
B6: SAV-002 | C6: Kamga Patrice | D6: Receptionniste | E6: Renouvellement CDD | F6: 45833 | G6: 0 | H6: 10 | I6: Oui | J6: En cours
B7: SAV-003 | C7: Fouda M. | D7: Cuisinier | E7: Augmentation salariale | F7: 45748 | G7: 20000 | H7: 7 | I7: Oui | J7: Signe
B8: SAV-004 | C8: Nganou D. | D8: Receptionniste | E8: Changement de poste | F8: 45778 | G8: 0 | H8: 12 | I8: Oui | J8: Signe
B9: SAV-005 | C9: Meyong S. | D9: Concierge | E9: Changement de poste | F9: 45778 | G9: 15000 | H9: 8 | I9: Oui | J9: Signe
B10: =IF(C10="","SAV-"&TEXT(COUNTA($C$5:C10),"000"))
B11: =IF(C11="","SAV-"&TEXT(COUNTA($C$5:C11),"000"))
B12: =IF(C12="","SAV-"&TEXT(COUNTA($C$5:C12),"000"))
B13: =IF(C13="","SAV-"&TEXT(COUNTA($C$5:C13),"000"))
B14: =IF(C14="","SAV-"&TEXT(COUNTA($C$5:C14),"000"))
B15: =IF(C15="","SAV-"&TEXT(COUNTA($C$5:C15),"000"))
B16: =IF(C16="","SAV-"&TEXT(COUNTA($C$5:C16),"000"))
B17: =IF(C17="","SAV-"&TEXT(COUNTA($C$5:C17),"000"))
B18: =IF(C18="","SAV-"&TEXT(COUNTA($C$5:C18),"000"))
B19: =IF(C19="","SAV-"&TEXT(COUNTA($C$5:C19),"000"))
B20: =IF(C20="","SAV-"&TEXT(COUNTA($C$5:C20),"000"))
B21: =IF(C21="","SAV-"&TEXT(COUNTA($C$5:C21),"000"))
... B109: =IF(C109="","SAV-"&TEXT(COUNTA($C$5:C109),"000"))
B111: TOTAL | G111: =SUM(G5:G104)
B113: INDICATEURS (mis a jour automatiquement)
B114: Avenants total | D114: Impact salarial total | F114: Delai moyen (j)
B115: =COUNTIF(B5:B104,"<>") | D115: =SUM(G5:G104) | F115: =IFERROR(AVERAGE(H5:H104),0)

Sheet 19-Analyse Couts Non-Conform.
B2: ANALYSE COÛTS NON-CONFORMITÉ
B3: TABLEAU DYNAMIQUE — Saisissez dans la prochaine ligne jaune. Les calculs se mettent a jour automatiquement.
B4: N° | C4: Type de Coût | D4: Mois | E4: Annee | F4: Montant (FCFA) | G4: Origine | H4: Departement Concerne | I4: Action Corrective | J4: Statut
B5: ACN-001 | C5: Penalites retard CNPS | D5: Fevrier | E5: 2025 | F5: 45000 | G5: Retard declaration fevrier | H5: Finance & Comptabilité | I5: Echeancier automatique mis en place | J5: Resolu
B6: ACN-002 | C6: Honoraires avocat | D6: Mai | E6: 2025 | F6: 200000 | G6: Litige Tchouanku | H6: Réception & Front Office | I6: Dossier en cours de defense | J6: En cours
B7: ACN-003 | C7: Formation mise en conformite | D7: Mars | E7: 2025 | F7: 350000 | G7: Arrete hygiene restauration | H7: Cuisine & Restauration | I7: Formation HACCP niveau 3 planifiee | J7: En cours
B8: ACN-004 | C8: Regularisation contrats | D8: Avril | E8: 2025 | F8: 50000 | G8: Circulaire contrat ecrit CDD | H8: Service Client | I8: Redaction avenants en cours | J8: En cours
B9: ACN-005 | C9: Penalites retard CNPS | D9: Mai | E9: 2025 | F9: 50000 | G9: Retard declaration mai | H9: Finance & Comptabilité | I9: Processus de controle renforce | J9: En cours
B10: =IF(C10="","ACN-"&TEXT(COUNTA($C$5:C10),"000"))
B11: =IF(C11="","ACN-"&TEXT(COUNTA($C$5:C11),"000"))
B12: =IF(C12="","ACN-"&TEXT(COUNTA($C$5:C12),"000"))
B13: =IF(C13="","ACN-"&TEXT(COUNTA($C$5:C13),"000"))
B14: =IF(C14="","ACN-"&TEXT(COUNTA($C$5:C14),"000"))
B15: =IF(C15="","ACN-"&TEXT(COUNTA($C$5:C15),"000"))
B16: =IF(C16="","ACN-"&TEXT(COUNTA($C$5:C16),"000"))
B17: =IF(C17="","ACN-"&TEXT(COUNTA($C$5:C17),"000"))
B18: =IF(C18="","ACN-"&TEXT(COUNTA($C$5:C18),"000"))
B19: =IF(C19="","ACN-"&TEXT(COUNTA($C$5:C19),"000"))
B20: =IF(C20="","ACN-"&TEXT(COUNTA($C$5:C20),"000"))
B21: =IF(C21="","ACN-"&TEXT(COUNTA($C$5:C21),"000"))
... B109: =IF(C109="","ACN-"&TEXT(COUNTA($C$5:C109),"000"))
B111: TOTAL | F111: =SUM(F5:F104)
B113: INDICATEURS (mis a jour automatiquement)
B114: Cout total (FCFA) | D114: Cout total (kFCFA) | F114: Nb lignes de cout
B115: =SUM(F5:F104) | D115: =IFERROR(SUM(F5:F104)/1000,0) | F115: =COUNTIF(B5:B104,"<>")
