Workbook

Sheet F01 - _Données Centrales
A2: DOMAINE 28 — GESTION DE LA MOBILITÉ PROFESSIONNELLE, PLAN DE CARRIÈRE ET SUCCESSION
A3: DONNÉES CENTRALES — Base de référence (toutes les feuilles s'y réfèrent)
A5: Code Employé | B5: Nom & Prénoms | C5: Département | D5: Poste Actuel | E5: Grade | F5: Échelon | G5: Ancienneté (ans) | H5: Date Dernière Promotion | I5: Potentiel | J5: Performance | K5: Statut Carrière | L5: Successeur Désigné | M5: Plan Mobilité | N5: Budget Formation (FCFA) | O5: Manager | P5: Statut
A6: EMP-001 | B6: M. Nkoulou Paul | C6: Direction Générale | D6: Directeur Général | E6: A1 | F6: Éch. 5 | G6: 22 | H6: 2023-01-15 | I6: Très élevé | J6: Excellent | K6: En poste | L6: M. Eyenga | M6: Maintien | N6: 5000000 | O6: Conseil Administration | P6: Actif
A7: EMP-002 | B7: Mme. Mbarga Claire | C7: Ressources Humaines | D7: DRH | E7: B1 | F7: Éch. 4 | G7: 15 | H7: 2022-06-01 | I7: Élevé | J7: Excellent | K7: En poste | L7: Mme. Essomba | M7: Promotion DG | N7: 3500000 | O7: DG | P7: Actif
A8: EMP-003 | B8: M. Eyenga René | C8: Finance & Comptabilité | D8: DAF | E8: B1 | F8: Éch. 4 | G8: 18 | H8: 2022-09-01 | I8: Élevé | J8: Très bon | K8: En poste | L8: M. Fotso | M8: Promotion DG | N8: 3000000 | O8: DG | P8: Actif
A9: EMP-004 | B9: M. Tchinda Jean | C9: Cuisine & Restauration | D9: Chef Cuisinier | E9: C2 | F9: Éch. 3 | G9: 8 | H9: 2023-03-10 | I9: Moyen | J9: Bon | K9: Mobilité demandée | M9: Mutation Technique | N9: 800000 | O9: DRH | P9: Actif
A10: EMP-005 | B10: Mme. Ngassa Marie | C10: Réception & Front Office | D10: Responsable Réception | E10: C1 | F10: Éch. 3 | G10: 10 | H10: 2023-07-01 | I10: Élevé | J10: Bon | K10: En poste | L10: M. Obama | M10: Promotion | N10: 1200000 | O10: DRH | P10: Actif
A11: EMP-006 | B11: M. Ondo Ferdinand | C11: Maintenance & Technique | D11: Chef Maintenance | E11: C1 | F11: Éch. 3 | G11: 12 | H11: 2022-12-15 | I11: Élevé | J11: Très bon | K11: En poste | L11: M. Ndong | M11: Maintien | N11: 1000000 | O11: DG | P11: Actif
A12: EMP-007 | B12: Mme. Essomba Sylvie | C12: Ressources Humaines | D12: Resp. Recrutement | E12: D1 | F12: Éch. 2 | G12: 6 | H12: 2024-01-10 | I12: Très élevé | J12: Excellent | K12: Succession prête | M12: Promotion DRH | N12: 2000000 | O12: DRH | P12: Actif
A13: EMP-008 | B13: M. Fotso Alain | C13: Finance & Comptabilité | D13: Chef Comptable | E13: D1 | F13: Éch. 2 | G13: 7 | H13: 2023-11-01 | I13: Élevé | J13: Très bon | K13: En poste | M13: Promotion DAF | N13: 1500000 | O13: DAF | P13: Actif
A14: EMP-009 | B14: M. Obama Samuel | C14: Réception & Front Office | D14: Réceptionniste Senior | E14: D2 | F14: Éch. 1 | G14: 4 | H14: 2024-03-01 | I14: Moyen | J14: Bon | K14: Mobilité demandée | M14: Mutation Réception | N14: 500000 | O14: Resp. Réception | P14: Actif
A15: EMP-010 | B15: M. Ndong Aurélien | C15: Maintenance & Technique | D15: Technicien Senior | E15: D2 | F15: Éch. 1 | G15: 5 | H15: 2024-02-15 | I15: Moyen | J15: Bon | K15: En formation | M15: Promotion Chef | N15: 700000 | O15: Chef Maint. | P15: Actif
A16: EMP-011 | B16: Mme. Beyala Aïcha | C16: Ressources Humaines | D16: Assistante RH | E16: E1 | F16: Éch. 1 | G16: 3 | H16: 2024-06-01 | I16: Élevé | J16: Très bon | K16: En poste | M16: Promotion | N16: 400000 | O16: DRH | P16: Actif
A17: EMP-012 | B17: M. Manga Patrick | C17: Cuisine & Restauration | D17: Second Cuisinier | E17: D2 | F17: Éch. 1 | G17: 5 | H17: 2023-08-20 | I17: Moyen | J17: Bon | K17: Mobilité demandée | M17: Mutation Resto | N17: 600000 | O17: Chef Cuisin. | P17: Actif
A18: EMP-013 | B18: Mme. Tchakounté Nadège | C18: Direction Générale | D18: Assistante de Direction | E18: D1 | F18: Éch. 2 | G18: 9 | H18: 2023-05-15 | I18: Élevé | J18: Excellent | K18: En poste | M18: Maintien | N18: 350000 | O18: DG | P18: Actif
A19: EMP-014 | B19: M. Nganou Eric | C19: Finance & Comptabilité | D19: Comptable Junior | E19: E2 | F19: Éch. 1 | G19: 2 | H19: 2024-09-01 | I19: Moyen | J19: Satisfaisant | K19: En formation | M19: Formation continue | N19: 300000 | O19: Chef Comptab. | P19: Actif
A20: EMP-015 | B20: Mme. Fomba Hélène | C20: Réception & Front Office | D20: Standardiste | E20: E1 | F20: Éch. 1 | G20: 1 | H20: 2025-01-10 | I20: À évaluer | J20: Satisfaisant | K20: Nouvellement recrutée | M20: Intégration | N20: 200000 | O20: Resp. Réception | P20: Actif

Sheet F02 - _Lists
A2: DOMAINE 28 — LISTES DE RÉFÉRENCE
A3: 21 listes déroulantes pour toutes les feuilles (colonnes A à U, lignes 6 à 35)
A5: Départements | B5: Postes | C5: Grades | D5: Potentiel | E5: Performance | F5: Statut Carrière | G5: Type Mobilité | H5: Motif Mobilité | I5: Priorité Succession | J5: Statut Formation | K5: Niveau Compétence | L5: Type Contrat International | M5: Statut Mentorat | N5: Fréquence Entretien | O5: Catégorie Budget | P5: Statut Demande | Q5: Risque Départ | R5: Action Plan | S5: Période Évaluation | T5: Statut Audit | U5: Conformité
A6: Direction Générale | B6: Directeur Général | C6: A1 | D6: Très élevé | E6: Excellent | F6: En poste | G6: Promotion | H6: Développement carrière | I6: Critique - 0-6 mois | J6: Planifiée | K6: Expert | L6: Expatriation | M6: Actif | N6: Mensuel | O6: Formation | P6: Approuvée | Q6: Très élevé | R6: Formation accélérée | S6: Q1 2025 | T6: Conforme | U6: 100%
A7: Ressources Humaines | B7: DRH | C7: A2 | D7: Élevé | E7: Très bon | F7: Mobilité demandée | G7: Mutation | H7: Élargissement compétences | I7: Élevée - 6-12 mois | J7: En cours | K7: Avancé | L7: Détachement | M7: En pause | N7: Trimestriel | O7: Mobilité | P7: En attente validation | Q7: Élevé | R7: Mentorat assigné | S7: Q2 2025 | T7: Non conforme | U7: 75-99%
A8: Finance & Comptabilité | B8: DAF | C8: B1 | D8: Moyen | E8: Bon | F8: Succession prête | G8: Mutation Technique | H8: Raisons personnelles | I8: Moyenne - 1-2 ans | J8: Terminée | K8: Intermédiaire | L8: Mission courte | M8: Terminé | N8: Semestriel | O8: Coaching | P8: Rejetée | Q8: Moyen | R8: Plan de transition | S8: Q3 2025 | T8: Partiellement conforme | U8: 50-74%
A9: Cuisine & Restauration | B9: Chef Cuisinier | C9: B2 | D9: Faible | E9: Satisfaisant | F9: En formation | G9: Détachement | H9: Réorganisation | I9: Faible - 2+ ans | J9: Reportée | K9: Débutant | L9: V.I.E. | M9: Planifié | N9: Annuel | O9: Mentorat | P9: En cours de traitement | Q9: Faible | R9: Recrutement externe | S9: Q4 2025 | T9: En cours de vérification | U9: 25-49%
A10: Réception & Front Office | B10: Responsable Réception | C10: C1 | D10: À évaluer | E10: Insuffisant | F10: Nouvellement recruté | G10: Mobilité Internationale | H10: Succession | I10: Non identifiée | J10: Annulée | K10: À développer | L10: Consultation technique | M10: Non démarré | N10: Bisannuel | O10: Audit externe | P10: Reportée | R10: Reclassification | S10: Annuel 2025 | T10: Non évalué | U10: < 25%
A11: Maintenance & Technique | B11: Chef Maintenance | C11: C2 | F11: En transition | G11: Rotation | H11: Performance | O11: Outils RH
A12: Service Commercial | B12: Resp. Recrutement | C12: D1 | F12: En attente | G12: Réintégration | H12: Initiative management | O12: Évaluation
A13: Service Juridique | B13: Chef Comptable | C13: D2 | G13: Maintien
B14: Réceptionniste Senior | C14: E1
B15: Technicien Senior | C15: E2
B16: Assistante RH
B17: Second Cuisinier
B18: Assistante Direction
B19: Comptable Junior
B20: Standardiste

Sheet F03 - 1-TdB Mobilité & Carrière
A2: DOMAINE 28 — TABLEAU DE BORD MOBILITÉ & CARRIÈRE
A3: Vue synthétique des indicateurs clés de mobilité et de gestion des carrières
A5: Effectif Total Suivi | B5: En Poste | C5: Mobilité Demandée | D5: Succession Prête | E5: En Formation | F5: Potentiel Élevé+ | G5: Performance Excellent/TB | H5: Budget Total Formation | I5: Taux Mobilité (%) | J5: Taux Successeurs (%)
A6: =COUNTA('F01 - _Données Centrales'!A6:A20) | B6: =COUNTIF('F01 - _Données Centrales'!K6:K20,"En poste") | C6: =COUNTIF('F01 - _Données Centrales'!K6:K20,"Mobilité demandée") | D6: =COUNTIF('F01 - _Données Centrales'!K6:K20,"Succession prête") | E6: =COUNTIF('F01 - _Données Centrales'!K6:K20,"En formation") | F6: =COUNTIF('F01 - _Données Centrales'!I6:I20,"Élevé")+COUNTIF('F01 - _Données Centrales'!I6:I20,"Très élevé") | G6: =COUNTIF('F01 - _Données Centrales'!J6:J20,"Excellent")+COUNTIF('F01 - _Données Centrales'!J6:J20,"Très bon") | H6: =SUM('F01 - _Données Centrales'!N6:N20) | I6: =IFERROR(C6/A6,0) | J6: =IFERROR(D6/A6,0)

Sheet F04 - 2-Registre Dem. Mobilité
A2: DOMAINE 28 — REGISTRE DES DEMANDES DE MOBILITÉ
A3: Suivi de toutes les demandes de mobilité interne et externe
A5: N° Demande | B5: Code Employé | C5: Nom Employé | D5: Département Origine | E5: Département Destination | F5: Type Mobilité | G5: Motif | H5: Date Demande | I5: Date Souhaitee | J5: Statut | K5: Priorité | L5: Validateur | M5: Observations
A6: DM-2025-001 | B6: EMP-004 | C6: =IFERROR(VLOOKUP(B6,'F01 - _Données Centrales'!A6:B20,2,FALSE),"") | D6: =IFERROR(VLOOKUP(B6,'F01 - _Données Centrales'!A6:C20,3,FALSE),"") | E6: Maintenance & Technique | F6: Mutation Technique | G6: Développement carrière | H6: 2025-01-15 | I6: 2025-04-01 | J6: Approuvée | K6: Normale | L6: DRH | M6: Élargissement vers technique
A7: DM-2025-002 | B7: EMP-009 | C7: =IFERROR(VLOOKUP(B7,'F01 - _Données Centrales'!A6:B20,2,FALSE),"") | D7: =IFERROR(VLOOKUP(B7,'F01 - _Données Centrales'!A6:C20,3,FALSE),"") | E7: Cuisine & Restauration | F7: Mutation | G7: Élargissement compétences | H7: 2025-02-01 | I7: 2025-05-01 | J7: En attente validation | K7: Haute | L7: DRH | M7: Polyvalence souhaitée
A8: DM-2025-003 | B8: EMP-012 | C8: =IFERROR(VLOOKUP(B8,'F01 - _Données Centrales'!A6:B20,2,FALSE),"") | D8: =IFERROR(VLOOKUP(B8,'F01 - _Données Centrales'!A6:C20,3,FALSE),"") | E8: Réception & Front Office | F8: Mutation | G8: Raisons personnelles | H8: 2025-03-10 | I8: 2025-06-01 | J8: En cours de traitement | K8: Normale | L8: DRH | M8: Rapprochement géographique
A9: DM-2025-004 | B9: EMP-007 | C9: =IFERROR(VLOOKUP(B9,'F01 - _Données Centrales'!A6:B20,2,FALSE),"") | D9: =IFERROR(VLOOKUP(B9,'F01 - _Données Centrales'!A6:C20,3,FALSE),"") | E9: Direction Générale | F9: Promotion | G9: Succession | H9: 2025-01-20 | I9: 2025-07-01 | J9: Approuvée | K9: Haute | L9: DG | M9: Plan de succession DRH
A10: DM-2025-005 | B10: EMP-010 | C10: =IFERROR(VLOOKUP(B10,'F01 - _Données Centrales'!A6:B20,2,FALSE),"") | D10: =IFERROR(VLOOKUP(B10,'F01 - _Données Centrales'!A6:C20,3,FALSE),"") | E10: Maintenance & Technique | F10: Promotion | G10: Développement carrière | H10: 2025-04-01 | I10: 2025-10-01 | J10: En attente validation | K10: Normale | L10: Chef Maint. | M10: Plan de transition 6 mois
A11: =IF(A10="","",A10) | C11: =IFERROR(VLOOKUP(B11,'F01 - _Données Centrales'!A6:B20,2,FALSE),"") | D11: =IFERROR(VLOOKUP(B11,'F01 - _Données Centrales'!A6:C20,3,FALSE),"")
A12: =IF(A11="","",A11) | C12: =IFERROR(VLOOKUP(B12,'F01 - _Données Centrales'!A6:B20,2,FALSE),"") | D12: =IFERROR(VLOOKUP(B12,'F01 - _Données Centrales'!A6:C20,3,FALSE),"")
A13: =IF(A12="","",A12) | C13: =IFERROR(VLOOKUP(B13,'F01 - _Données Centrales'!A6:B20,2,FALSE),"") | D13: =IFERROR(VLOOKUP(B13,'F01 - _Données Centrales'!A6:C20,3,FALSE),"")
A14: =IF(A13="","",A13) | C14: =IFERROR(VLOOKUP(B14,'F01 - _Données Centrales'!A6:B20,2,FALSE),"") | D14: =IFERROR(VLOOKUP(B14,'F01 - _Données Centrales'!A6:C20,3,FALSE),"")
A15: =IF(A14="","",A14) | C15: =IFERROR(VLOOKUP(B15,'F01 - _Données Centrales'!A6:B20,2,FALSE),"") | D15: =IFERROR(VLOOKUP(B15,'F01 - _Données Centrales'!A6:C20,3,FALSE),"")
A16: =IF(A15="","",A15) | C16: =IFERROR(VLOOKUP(B16,'F01 - _Données Centrales'!A6:B20,2,FALSE),"") | D16: =IFERROR(VLOOKUP(B16,'F01 - _Données Centrales'!A6:C20,3,FALSE),"")
A17: =IF(A16="","",A16) | C17: =IFERROR(VLOOKUP(B17,'F01 - _Données Centrales'!A6:B20,2,FALSE),"") | D17: =IFERROR(VLOOKUP(B17,'F01 - _Données Centrales'!A6:C20,3,FALSE),"")
A18: =IF(A17="","",A17) | C18: =IFERROR(VLOOKUP(B18,'F01 - _Données Centrales'!A6:B20,2,FALSE),"") | D18: =IFERROR(VLOOKUP(B18,'F01 - _Données Centrales'!A6:C20,3,FALSE),"")
A19: =IF(A18="","",A18) | C19: =IFERROR(VLOOKUP(B19,'F01 - _Données Centrales'!A6:B20,2,FALSE),"") | D19: =IFERROR(VLOOKUP(B19,'F01 - _Données Centrales'!A6:C20,3,FALSE),"")
A20: =IF(A19="","",A19) | C20: =IFERROR(VLOOKUP(B20,'F01 - _Données Centrales'!A6:B20,2,FALSE),"") | D20: =IFERROR(VLOOKUP(B20,'F01 - _Données Centrales'!A6:C20,3,FALSE),"")
A21: =IF(A20="","",A20) | C21: =IFERROR(VLOOKUP(B21,'F01 - _Données Centrales'!A6:B20,2,FALSE),"") | D21: =IFERROR(VLOOKUP(B21,'F01 - _Données Centrales'!A6:C20,3,FALSE),"")
A22: =IF(A21="","",A21) | C22: =IFERROR(VLOOKUP(B22,'F01 - _Données Centrales'!A6:B20,2,FALSE),"") | D22: =IFERROR(VLOOKUP(B22,'F01 - _Données Centrales'!A6:C20,3,FALSE),"")
A23: =IF(A22="","",A22) | C23: =IFERROR(VLOOKUP(B23,'F01 - _Données Centrales'!A6:B20,2,FALSE),"") | D23: =IFERROR(VLOOKUP(B23,'F01 - _Données Centrales'!A6:C20,3,FALSE),"")
A24: =IF(A23="","",A23) | C24: =IFERROR(VLOOKUP(B24,'F01 - _Données Centrales'!A6:B20,2,FALSE),"") | D24: =IFERROR(VLOOKUP(B24,'F01 - _Données Centrales'!A6:C20,3,FALSE),"")
A25: =IF(A24="","",A24) | C25: =IFERROR(VLOOKUP(B25,'F01 - _Données Centrales'!A6:B20,2,FALSE),"") | D25: =IFERROR(VLOOKUP(B25,'F01 - _Données Centrales'!A6:C20,3,FALSE),"")
A26: =IF(A25="","",A25) | C26: =IFERROR(VLOOKUP(B26,'F01 - _Données Centrales'!A6:B20,2,FALSE),"") | D26: =IFERROR(VLOOKUP(B26,'F01 - _Données Centrales'!A6:C20,3,FALSE),"")
A27: =IF(A26="","",A26) | C27: =IFERROR(VLOOKUP(B27,'F01 - _Données Centrales'!A6:B20,2,FALSE),"") | D27: =IFERROR(VLOOKUP(B27,'F01 - _Données Centrales'!A6:C20,3,FALSE),"")
A28: =IF(A27="","",A27) | C28: =IFERROR(VLOOKUP(B28,'F01 - _Données Centrales'!A6:B20,2,FALSE),"") | D28: =IFERROR(VLOOKUP(B28,'F01 - _Données Centrales'!A6:C20,3,FALSE),"")
A29: =IF(A28="","",A28) | C29: =IFERROR(VLOOKUP(B29,'F01 - _Données Centrales'!A6:B20,2,FALSE),"") | D29: =IFERROR(VLOOKUP(B29,'F01 - _Données Centrales'!A6:C20,3,FALSE),"")
A30: =IF(A29="","",A29) | C30: =IFERROR(VLOOKUP(B30,'F01 - _Données Centrales'!A6:B20,2,FALSE),"") | D30: =IFERROR(VLOOKUP(B30,'F01 - _Données Centrales'!A6:C20,3,FALSE),"")
A31: =IF(A30="","",A30) | C31: =IFERROR(VLOOKUP(B31,'F01 - _Données Centrales'!A6:B20,2,FALSE),"") | D31: =IFERROR(VLOOKUP(B31,'F01 - _Données Centrales'!A6:C20,3,FALSE),"")
A32: =IF(A31="","",A31) | C32: =IFERROR(VLOOKUP(B32,'F01 - _Données Centrales'!A6:B20,2,FALSE),"") | D32: =IFERROR(VLOOKUP(B32,'F01 - _Données Centrales'!A6:C20,3,FALSE),"")
A33: =IF(A32="","",A32) | C33: =IFERROR(VLOOKUP(B33,'F01 - _Données Centrales'!A6:B20,2,FALSE),"") | D33: =IFERROR(VLOOKUP(B33,'F01 - _Données Centrales'!A6:C20,3,FALSE),"")
A34: =IF(A33="","",A33) | C34: =IFERROR(VLOOKUP(B34,'F01 - _Données Centrales'!A6:B20,2,FALSE),"") | D34: =IFERROR(VLOOKUP(B34,'F01 - _Données Centrales'!A6:C20,3,FALSE),"")
A35: =IF(A34="","",A34) | C35: =IFERROR(VLOOKUP(B35,'F01 - _Données Centrales'!A6:B20,2,FALSE),"") | D35: =IFERROR(VLOOKUP(B35,'F01 - _Données Centrales'!A6:C20,3,FALSE),"")
A36: =IF(A35="","",A35) | C36: =IFERROR(VLOOKUP(B36,'F01 - _Données Centrales'!A6:B20,2,FALSE),"") | D36: =IFERROR(VLOOKUP(B36,'F01 - _Données Centrales'!A6:C20,3,FALSE),"")
A37: =IF(A36="","",A36) | C37: =IFERROR(VLOOKUP(B37,'F01 - _Données Centrales'!A6:B20,2,FALSE),"") | D37: =IFERROR(VLOOKUP(B37,'F01 - _Données Centrales'!A6:C20,3,FALSE),"")
A38: =IF(A37="","",A37) | C38: =IFERROR(VLOOKUP(B38,'F01 - _Données Centrales'!A6:B20,2,FALSE),"") | D38: =IFERROR(VLOOKUP(B38,'F01 - _Données Centrales'!A6:C20,3,FALSE),"")
A39: =IF(A38="","",A38) | C39: =IFERROR(VLOOKUP(B39,'F01 - _Données Centrales'!A6:B20,2,FALSE),"") | D39: =IFERROR(VLOOKUP(B39,'F01 - _Données Centrales'!A6:C20,3,FALSE),"")
A40: =IF(A39="","",A39) | C40: =IFERROR(VLOOKUP(B40,'F01 - _Données Centrales'!A6:B20,2,FALSE),"") | D40: =IFERROR(VLOOKUP(B40,'F01 - _Données Centrales'!A6:C20,3,FALSE),"")
A41: =IF(A40="","",A40) | C41: =IFERROR(VLOOKUP(B41,'F01 - _Données Centrales'!A6:B20,2,FALSE),"") | D41: =IFERROR(VLOOKUP(B41,'F01 - _Données Centrales'!A6:C20,3,FALSE),"")
A42: =IF(A41="","",A41) | C42: =IFERROR(VLOOKUP(B42,'F01 - _Données Centrales'!A6:B20,2,FALSE),"") | D42: =IFERROR(VLOOKUP(B42,'F01 - _Données Centrales'!A6:C20,3,FALSE),"")
A43: =IF(A42="","",A42) | C43: =IFERROR(VLOOKUP(B43,'F01 - _Données Centrales'!A6:B20,2,FALSE),"") | D43: =IFERROR(VLOOKUP(B43,'F01 - _Données Centrales'!A6:C20,3,FALSE),"")
A44: =IF(A43="","",A43) | C44: =IFERROR(VLOOKUP(B44,'F01 - _Données Centrales'!A6:B20,2,FALSE),"") | D44: =IFERROR(VLOOKUP(B44,'F01 - _Données Centrales'!A6:C20,3,FALSE),"")
A45: =IF(A44="","",A44) | C45: =IFERROR(VLOOKUP(B45,'F01 - _Données Centrales'!A6:B20,2,FALSE),"") | D45: =IFERROR(VLOOKUP(B45,'F01 - _Données Centrales'!A6:C20,3,FALSE),"")
A46: =IF(A45="","",A45) | C46: =IFERROR(VLOOKUP(B46,'F01 - _Données Centrales'!A6:B20,2,FALSE),"") | D46: =IFERROR(VLOOKUP(B46,'F01 - _Données Centrales'!A6:C20,3,FALSE),"")
A47: =IF(A46="","",A46) | C47: =IFERROR(VLOOKUP(B47,'F01 - _Données Centrales'!A6:B20,2,FALSE),"") | D47: =IFERROR(VLOOKUP(B47,'F01 - _Données Centrales'!A6:C20,3,FALSE),"")
A48: =IF(A47="","",A47) | C48: =IFERROR(VLOOKUP(B48,'F01 - _Données Centrales'!A6:B20,2,FALSE),"") | D48: =IFERROR(VLOOKUP(B48,'F01 - _Données Centrales'!A6:C20,3,FALSE),"")
A49: =IF(A48="","",A48) | C49: =IFERROR(VLOOKUP(B49,'F01 - _Données Centrales'!A6:B20,2,FALSE),"") | D49: =IFERROR(VLOOKUP(B49,'F01 - _Données Centrales'!A6:C20,3,FALSE),"")
A50: =IF(A49="","",A49) | C50: =IFERROR(VLOOKUP(B50,'F01 - _Données Centrales'!A6:B20,2,FALSE),"") | D50: =IFERROR(VLOOKUP(B50,'F01 - _Données Centrales'!A6:C20,3,FALSE),"")
A51: =IF(A50="","",A50) | C51: =IFERROR(VLOOKUP(B51,'F01 - _Données Centrales'!A6:B20,2,FALSE),"") | D51: =IFERROR(VLOOKUP(B51,'F01 - _Données Centrales'!A6:C20,3,FALSE),"")
A52: =IF(A51="","",A51) | C52: =IFERROR(VLOOKUP(B52,'F01 - _Données Centrales'!A6:B20,2,FALSE),"") | D52: =IFERROR(VLOOKUP(B52,'F01 - _Données Centrales'!A6:C20,3,FALSE),"")
A53: =IF(A52="","",A52) | C53: =IFERROR(VLOOKUP(B53,'F01 - _Données Centrales'!A6:B20,2,FALSE),"") | D53: =IFERROR(VLOOKUP(B53,'F01 - _Données Centrales'!A6:C20,3,FALSE),"")
A54: =IF(A53="","",A53) | C54: =IFERROR(VLOOKUP(B54,'F01 - _Données Centrales'!A6:B20,2,FALSE),"") | D54: =IFERROR(VLOOKUP(B54,'F01 - _Données Centrales'!A6:C20,3,FALSE),"")
A55: =IF(A54="","",A54) | C55: =IFERROR(VLOOKUP(B55,'F01 - _Données Centrales'!A6:B20,2,FALSE),"") | D55: =IFERROR(VLOOKUP(B55,'F01 - _Données Centrales'!A6:C20,3,FALSE),"")
A56: =IF(A55="","",A55) | C56: =IFERROR(VLOOKUP(B56,'F01 - _Données Centrales'!A6:B20,2,FALSE),"") | D56: =IFERROR(VLOOKUP(B56,'F01 - _Données Centrales'!A6:C20,3,FALSE),"")
A57: =IF(A56="","",A56) | C57: =IFERROR(VLOOKUP(B57,'F01 - _Données Centrales'!A6:B20,2,FALSE),"") | D57: =IFERROR(VLOOKUP(B57,'F01 - _Données Centrales'!A6:C20,3,FALSE),"")
A58: =IF(A57="","",A57) | C58: =IFERROR(VLOOKUP(B58,'F01 - _Données Centrales'!A6:B20,2,FALSE),"") | D58: =IFERROR(VLOOKUP(B58,'F01 - _Données Centrales'!A6:C20,3,FALSE),"")
A59: =IF(A58="","",A58) | C59: =IFERROR(VLOOKUP(B59,'F01 - _Données Centrales'!A6:B20,2,FALSE),"") | D59: =IFERROR(VLOOKUP(B59,'F01 - _Données Centrales'!A6:C20,3,FALSE),"")
A60: =IF(A59="","",A59) | C60: =IFERROR(VLOOKUP(B60,'F01 - _Données Centrales'!A6:B20,2,FALSE),"") | D60: =IFERROR(VLOOKUP(B60,'F01 - _Données Centrales'!A6:C20,3,FALSE),"")
A61: =IF(A60="","",A60) | C61: =IFERROR(VLOOKUP(B61,'F01 - _Données Centrales'!A6:B20,2,FALSE),"") | D61: =IFERROR(VLOOKUP(B61,'F01 - _Données Centrales'!A6:C20,3,FALSE),"")
A62: =IF(A61="","",A61) | C62: =IFERROR(VLOOKUP(B62,'F01 - _Données Centrales'!A6:B20,2,FALSE),"") | D62: =IFERROR(VLOOKUP(B62,'F01 - _Données Centrales'!A6:C20,3,FALSE),"")
A63: =IF(A62="","",A62) | C63: =IFERROR(VLOOKUP(B63,'F01 - _Données Centrales'!A6:B20,2,FALSE),"") | D63: =IFERROR(VLOOKUP(B63,'F01 - _Données Centrales'!A6:C20,3,FALSE),"")
A64: =IF(A63="","",A63) | C64: =IFERROR(VLOOKUP(B64,'F01 - _Données Centrales'!A6:B20,2,FALSE),"") | D64: =IFERROR(VLOOKUP(B64,'F01 - _Données Centrales'!A6:C20,3,FALSE),"")
A65: =IF(A64="","",A64) | C65: =IFERROR(VLOOKUP(B65,'F01 - _Données Centrales'!A6:B20,2,FALSE),"") | D65: =IFERROR(VLOOKUP(B65,'F01 - _Données Centrales'!A6:C20,3,FALSE),"")
A66: =IF(A65="","",A65) | C66: =IFERROR(VLOOKUP(B66,'F01 - _Données Centrales'!A6:B20,2,FALSE),"") | D66: =IFERROR(VLOOKUP(B66,'F01 - _Données Centrales'!A6:C20,3,FALSE),"")
A67: =IF(A66="","",A66) | C67: =IFERROR(VLOOKUP(B67,'F01 - _Données Centrales'!A6:B20,2,FALSE),"") | D67: =IFERROR(VLOOKUP(B67,'F01 - _Données Centrales'!A6:C20,3,FALSE),"")
A68: =IF(A67="","",A67) | C68: =IFERROR(VLOOKUP(B68,'F01 - _Données Centrales'!A6:B20,2,FALSE),"") | D68: =IFERROR(VLOOKUP(B68,'F01 - _Données Centrales'!A6:C20,3,FALSE),"")
A69: =IF(A68="","",A68) | C69: =IFERROR(VLOOKUP(B69,'F01 - _Données Centrales'!A6:B20,2,FALSE),"") | D69: =IFERROR(VLOOKUP(B69,'F01 - _Données Centrales'!A6:C20,3,FALSE),"")
A70: =IF(A69="","",A69) | C70: =IFERROR(VLOOKUP(B70,'F01 - _Données Centrales'!A6:B20,2,FALSE),"") | D70: =IFERROR(VLOOKUP(B70,'F01 - _Données Centrales'!A6:C20,3,FALSE),"")
A71: =IF(A70="","",A70) | C71: =IFERROR(VLOOKUP(B71,'F01 - _Données Centrales'!A6:B20,2,FALSE),"") | D71: =IFERROR(VLOOKUP(B71,'F01 - _Données Centrales'!A6:C20,3,FALSE),"")
A72: =IF(A71="","",A71) | C72: =IFERROR(VLOOKUP(B72,'F01 - _Données Centrales'!A6:B20,2,FALSE),"") | D72: =IFERROR(VLOOKUP(B72,'F01 - _Données Centrales'!A6:C20,3,FALSE),"")
A73: =IF(A72="","",A72) | C73: =IFERROR(VLOOKUP(B73,'F01 - _Données Centrales'!A6:B20,2,FALSE),"") | D73: =IFERROR(VLOOKUP(B73,'F01 - _Données Centrales'!A6:C20,3,FALSE),"")
A74: =IF(A73="","",A73) | C74: =IFERROR(VLOOKUP(B74,'F01 - _Données Centrales'!A6:B20,2,FALSE),"") | D74: =IFERROR(VLOOKUP(B74,'F01 - _Données Centrales'!A6:C20,3,FALSE),"")
A75: =IF(A74="","",A74) | C75: =IFERROR(VLOOKUP(B75,'F01 - _Données Centrales'!A6:B20,2,FALSE),"") | D75: =IFERROR(VLOOKUP(B75,'F01 - _Données Centrales'!A6:C20,3,FALSE),"")
A76: =IF(A75="","",A75) | C76: =IFERROR(VLOOKUP(B76,'F01 - _Données Centrales'!A6:B20,2,FALSE),"") | D76: =IFERROR(VLOOKUP(B76,'F01 - _Données Centrales'!A6:C20,3,FALSE),"")
A77: =IF(A76="","",A76) | C77: =IFERROR(VLOOKUP(B77,'F01 - _Données Centrales'!A6:B20,2,FALSE),"") | D77: =IFERROR(VLOOKUP(B77,'F01 - _Données Centrales'!A6:C20,3,FALSE),"")
A78: =IF(A77="","",A77) | C78: =IFERROR(VLOOKUP(B78,'F01 - _Données Centrales'!A6:B20,2,FALSE),"") | D78: =IFERROR(VLOOKUP(B78,'F01 - _Données Centrales'!A6:C20,3,FALSE),"")
A79: =IF(A78="","",A78) | C79: =IFERROR(VLOOKUP(B79,'F01 - _Données Centrales'!A6:B20,2,FALSE),"") | D79: =IFERROR(VLOOKUP(B79,'F01 - _Données Centrales'!A6:C20,3,FALSE),"")
A80: =IF(A79="","",A79) | C80: =IFERROR(VLOOKUP(B80,'F01 - _Données Centrales'!A6:B20,2,FALSE),"") | D80: =IFERROR(VLOOKUP(B80,'F01 - _Données Centrales'!A6:C20,3,FALSE),"")
A81: =IF(A80="","",A80) | C81: =IFERROR(VLOOKUP(B81,'F01 - _Données Centrales'!A6:B20,2,FALSE),"") | D81: =IFERROR(VLOOKUP(B81,'F01 - _Données Centrales'!A6:C20,3,FALSE),"")
A82: =IF(A81="","",A81) | C82: =IFERROR(VLOOKUP(B82,'F01 - _Données Centrales'!A6:B20,2,FALSE),"") | D82: =IFERROR(VLOOKUP(B82,'F01 - _Données Centrales'!A6:C20,3,FALSE),"")
A83: =IF(A82="","",A82) | C83: =IFERROR(VLOOKUP(B83,'F01 - _Données Centrales'!A6:B20,2,FALSE),"") | D83: =IFERROR(VLOOKUP(B83,'F01 - _Données Centrales'!A6:C20,3,FALSE),"")
A84: =IF(A83="","",A83) | C84: =IFERROR(VLOOKUP(B84,'F01 - _Données Centrales'!A6:B20,2,FALSE),"") | D84: =IFERROR(VLOOKUP(B84,'F01 - _Données Centrales'!A6:C20,3,FALSE),"")
A85: =IF(A84="","",A84) | C85: =IFERROR(VLOOKUP(B85,'F01 - _Données Centrales'!A6:B20,2,FALSE),"") | D85: =IFERROR(VLOOKUP(B85,'F01 - _Données Centrales'!A6:C20,3,FALSE),"")
A86: =IF(A85="","",A85) | C86: =IFERROR(VLOOKUP(B86,'F01 - _Données Centrales'!A6:B20,2,FALSE),"") | D86: =IFERROR(VLOOKUP(B86,'F01 - _Données Centrales'!A6:C20,3,FALSE),"")
A87: =IF(A86="","",A86) | C87: =IFERROR(VLOOKUP(B87,'F01 - _Données Centrales'!A6:B20,2,FALSE),"") | D87: =IFERROR(VLOOKUP(B87,'F01 - _Données Centrales'!A6:C20,3,FALSE),"")
A88: =IF(A87="","",A87) | C88: =IFERROR(VLOOKUP(B88,'F01 - _Données Centrales'!A6:B20,2,FALSE),"") | D88: =IFERROR(VLOOKUP(B88,'F01 - _Données Centrales'!A6:C20,3,FALSE),"")
A89: =IF(A88="","",A88) | C89: =IFERROR(VLOOKUP(B89,'F01 - _Données Centrales'!A6:B20,2,FALSE),"") | D89: =IFERROR(VLOOKUP(B89,'F01 - _Données Centrales'!A6:C20,3,FALSE),"")
A90: =IF(A89="","",A89) | C90: =IFERROR(VLOOKUP(B90,'F01 - _Données Centrales'!A6:B20,2,FALSE),"") | D90: =IFERROR(VLOOKUP(B90,'F01 - _Données Centrales'!A6:C20,3,FALSE),"")
A91: =IF(A90="","",A90) | C91: =IFERROR(VLOOKUP(B91,'F01 - _Données Centrales'!A6:B20,2,FALSE),"") | D91: =IFERROR(VLOOKUP(B91,'F01 - _Données Centrales'!A6:C20,3,FALSE),"")
A92: =IF(A91="","",A91) | C92: =IFERROR(VLOOKUP(B92,'F01 - _Données Centrales'!A6:B20,2,FALSE),"") | D92: =IFERROR(VLOOKUP(B92,'F01 - _Données Centrales'!A6:C20,3,FALSE),"")
A93: =IF(A92="","",A92) | C93: =IFERROR(VLOOKUP(B93,'F01 - _Données Centrales'!A6:B20,2,FALSE),"") | D93: =IFERROR(VLOOKUP(B93,'F01 - _Données Centrales'!A6:C20,3,FALSE),"")
A94: =IF(A93="","",A93) | C94: =IFERROR(VLOOKUP(B94,'F01 - _Données Centrales'!A6:B20,2,FALSE),"") | D94: =IFERROR(VLOOKUP(B94,'F01 - _Données Centrales'!A6:C20,3,FALSE),"")
A95: =IF(A94="","",A94) | C95: =IFERROR(VLOOKUP(B95,'F01 - _Données Centrales'!A6:B20,2,FALSE),"") | D95: =IFERROR(VLOOKUP(B95,'F01 - _Données Centrales'!A6:C20,3,FALSE),"")
A96: =IF(A95="","",A95) | C96: =IFERROR(VLOOKUP(B96,'F01 - _Données Centrales'!A6:B20,2,FALSE),"") | D96: =IFERROR(VLOOKUP(B96,'F01 - _Données Centrales'!A6:C20,3,FALSE),"")
A97: =IF(A96="","",A96) | C97: =IFERROR(VLOOKUP(B97,'F01 - _Données Centrales'!A6:B20,2,FALSE),"") | D97: =IFERROR(VLOOKUP(B97,'F01 - _Données Centrales'!A6:C20,3,FALSE),"")
A98: =IF(A97="","",A97) | C98: =IFERROR(VLOOKUP(B98,'F01 - _Données Centrales'!A6:B20,2,FALSE),"") | D98: =IFERROR(VLOOKUP(B98,'F01 - _Données Centrales'!A6:C20,3,FALSE),"")
A99: =IF(A98="","",A98) | C99: =IFERROR(VLOOKUP(B99,'F01 - _Données Centrales'!A6:B20,2,FALSE),"") | D99: =IFERROR(VLOOKUP(B99,'F01 - _Données Centrales'!A6:C20,3,FALSE),"")
A100: =IF(A99="","",A99) | C100: =IFERROR(VLOOKUP(B100,'F01 - _Données Centrales'!A6:B20,2,FALSE),"") | D100: =IFERROR(VLOOKUP(B100,'F01 - _Données Centrales'!A6:C20,3,FALSE),"")
A101: =IF(A100="","",A100) | C101: =IFERROR(VLOOKUP(B101,'F01 - _Données Centrales'!A6:B20,2,FALSE),"") | D101: =IFERROR(VLOOKUP(B101,'F01 - _Données Centrales'!A6:C20,3,FALSE),"")
A102: =IF(A101="","",A101) | C102: =IFERROR(VLOOKUP(B102,'F01 - _Données Centrales'!A6:B20,2,FALSE),"") | D102: =IFERROR(VLOOKUP(B102,'F01 - _Données Centrales'!A6:C20,3,FALSE),"")
...

Sheet F05 - 3-Plan de Succession
A2: DOMAINE 28 — PLAN DE SUCCESSION DES POSTES CLÉS
A3: Identification des successeurs potentiels pour les postes stratégiques
A5: Code Poste | B5: Poste | C5: Département | D5: Titulaire Actuel | E5: Grade Titulaire | F5: Successeur 1 | G5: Potentiel Succ. 1 | H5: Successeur 2 | I5: Potentiel Succ. 2 | J5: Priorité Succ. | K5: Date Disponibilité | L5: Action Plan | M5: Statut Préparation | N5: Écart Compétences
A6: POSTE-001 | B6: Directeur Général | C6: Direction Générale | D6: M. Nkoulou Paul | E6: A1 | F6: Mme. Mbarga Claire | G6: Élevé | H6: M. Eyenga René | I6: Élevé | J6: Critique - 0-6 mois | K6: 2026-01-01 | L6: Formation accélérée | M6: En cours | N6: Leadership stratégique
A7: POSTE-002 | B7: DRH | C7: Ressources Humaines | D7: Mme. Mbarga Claire | E7: B1 | F7: Mme. Essomba Sylvie | G7: Très élevé | H7: Mme. Beyala Aïcha | I7: Élevé | J7: Élevée - 6-12 mois | K7: 2025-12-01 | L7: Mentorat assigné | M7: Avancée | N7: Gestion de la DRH
A8: POSTE-003 | B8: DAF | C8: Finance & Comptabilité | D8: M. Eyenga René | E8: B1 | F8: M. Fotso Alain | G8: Élevé | H8: M. Nganou Eric | I8: Moyen | J8: Moyenne - 1-2 ans | K8: 2026-06-01 | L8: Plan de transition | M8: En cours | N8: Vision financière globale
A9: POSTE-004 | B9: Chef Cuisinier | C9: Cuisine & Restauration | D9: M. Tchinda Jean | E9: C2 | F9: M. Manga Patrick | G9: Moyen | J9: Faible - 2+ ans | K9: 2027-01-01 | L9: Formation accélérée | M9: Non démarré | N9: Gestion équipe cuisine
A10: POSTE-005 | B10: Resp. Réception | C10: Réception & Front Office | D10: Mme. Ngassa Marie | E10: C1 | F10: M. Obama Samuel | G10: Moyen | H10: Mme. Fomba Hélène | I10: À évaluer | J10: Moyenne - 1-2 ans | K10: 2026-03-01 | L10: Plan de transition | M10: En cours | N10: Gestion réception
A11: =IF(A10="","",A10)
A12: =IF(A11="","",A11)
A13: =IF(A12="","",A12)
A14: =IF(A13="","",A13)
A15: =IF(A14="","",A14)
A16: =IF(A15="","",A15)
A17: =IF(A16="","",A16)
A18: =IF(A17="","",A17)
A19: =IF(A18="","",A18)
A20: =IF(A19="","",A19)
A21: =IF(A20="","",A20)
A22: =IF(A21="","",A21)
... A115: =IF(A114="","",A114)

Sheet F06 - 4-Cartographie Postes C.
A2: DOMAINE 28 — CARTOGRAPHIE DES POSTES ET COMPÉTENCES
A3: Mapping des compétences requises par poste et niveau de maîtrise
A5: Code Poste | B5: Poste | C5: Département | D5: Compétence Clé 1 | E5: Niveau Req. 1 | F5: Compétence Clé 2 | G5: Niveau Req. 2 | H5: Compétence Clé 3 | I5: Niveau Req. 3 | J5: Nb Titulaires | K5: Écart Moyen | L5: Action Développement | M5: Priorité
A6: POSTE-001 | B6: Directeur Général | C6: Direction Générale | D6: Leadership stratégique | E6: Expert | F6: Vision financière | G6: Expert | H6: Gouvernance | I6: Expert | J6: 1 | K6: Faible | L6: Mentorat externe | M6: Haute
A7: POSTE-002 | B7: DRH | C7: Ressources Humaines | D7: Droit du travail | E7: Expert | F7: Gestion des talents | G7: Expert | H7: Stratégie RH | I7: Avancé | J7: 1 | K7: Faible | L7: Formation continue | M7: Haute
A8: POSTE-003 | B8: DAF | C8: Finance & Comptabilité | D8: Comptabilité analytique | E8: Expert | F8: Gestion trésorerie | G8: Expert | H8: Fiscalité | I8: Avancé | J8: 1 | K8: Moyen | L8: Certification | M8: Haute
A9: POSTE-004 | B9: Chef Cuisinier | C9: Cuisine & Restauration | D9: Gastronomie | E9: Expert | F9: Hygiène alimentaire | G9: Expert | H9: Gestion équipe | I9: Avancé | J9: 1 | K9: Moyen | L9: Formation HACCP | M9: Moyenne
A10: POSTE-005 | B10: Resp. Réception | C10: Réception & Front Office | D10: Accueil client | E10: Expert | F10: Réservation | G10: Avancé | H10: Anglais | I10: Intermédiaire | J10: 1 | K10: Moyen | L10: Formation langue | M10: Moyenne
A11: =IF(A10="","",A10)
A12: =IF(A11="","",A11)
A13: =IF(A12="","",A12)
A14: =IF(A13="","",A13)
A15: =IF(A14="","",A14)
A16: =IF(A15="","",A15)
A17: =IF(A16="","",A16)
A18: =IF(A17="","",A17)
A19: =IF(A18="","",A18)
A20: =IF(A19="","",A19)
A21: =IF(A20="","",A20)
A22: =IF(A21="","",A21)
... A115: =IF(A114="","",A114)

Sheet F07 - 5-Évaluations Potentiel
A2: DOMAINE 28 — ÉVALUATIONS DU POTENTIEL
A3: Évaluation du potentiel de progression et de la readiness des collaborateurs
A5: Code Employé | B5: Nom | C5: Département | D5: Potentiel | E5: Performance | F5: Score Potentiel (/100) | G5: Score Perf. (/100) | H5: Score Combiné | I5: Catégorie 9-Box | J5: Évaluateur | K5: Date Évaluation | L5: Période | M5: Commentaire | N5: Action Recommandée
A6: EMP-001 | B6: =IFERROR(VLOOKUP(A6,'F01 - _Données Centrales'!A6:B20,2,FALSE),"") | C6: =IFERROR(VLOOKUP(A6,'F01 - _Données Centrales'!A6:C20,3,FALSE),"") | D6: Très élevé | E6: Excellent | F6: 95 | G6: 92 | H6: =IFERROR((F6+G6)/2,0) | I6: =IF(OR(F6="",G6=""),"",IF(AND(F6>=80,G6>=80),"Étoile",IF(AND(F6>=80,G6<80),"Problème de perf.",IF(AND(F6<80,G6>=80),"Travailleur fiable","Sous-performeur")))) | J6: DG | K6: 2025-03-01 | L6: Q1 2025 | M6: Leader inspirant, vision claire | N6: Maintien position clé
A7: EMP-002 | B7: =IFERROR(VLOOKUP(A7,'F01 - _Données Centrales'!A6:B20,2,FALSE),"") | C7: =IFERROR(VLOOKUP(A7,'F01 - _Données Centrales'!A6:C20,3,FALSE),"") | D7: Élevé | E7: Excellent | F7: 88 | G7: 90 | H7: =IFERROR((F7+G7)/2,0) | I7: =IF(OR(F7="",G7=""),"",IF(AND(F7>=80,G7>=80),"Étoile",IF(AND(F7>=80,G7<80),"Problème de perf.",IF(AND(F7<80,G7>=80),"Travailleur fiable","Sous-performeur")))) | J7: DG | K7: 2025-03-01 | L7: Q1 2025 | M7: Prête pour DG adjoint | N7: Accélérer plan succession
A8: EMP-003 | B8: =IFERROR(VLOOKUP(A8,'F01 - _Données Centrales'!A6:B20,2,FALSE),"") | C8: =IFERROR(VLOOKUP(A8,'F01 - _Données Centrales'!A6:C20,3,FALSE),"") | D8: Élevé | E8: Très bon | F8: 85 | G8: 82 | H8: =IFERROR((F8+G8)/2,0) | I8: =IF(OR(F8="",G8=""),"",IF(AND(F8>=80,G8>=80),"Étoile",IF(AND(F8>=80,G8<80),"Problème de perf.",IF(AND(F8<80,G8>=80),"Travailleur fiable","Sous-performeur")))) | J8: DG | K8: 2025-03-15 | L8: Q1 2025 | M8: Solide techniquement | N8: Renforcer leadership
A9: EMP-007 | B9: =IFERROR(VLOOKUP(A9,'F01 - _Données Centrales'!A6:B20,2,FALSE),"") | C9: =IFERROR(VLOOKUP(A9,'F01 - _Données Centrales'!A6:C20,3,FALSE),"") | D9: Très élevé | E9: Excellent | F9: 92 | G9: 91 | H9: =IFERROR((F9+G9)/2,0) | I9: =IF(OR(F9="",G9=""),"",IF(AND(F9>=80,G9>=80),"Étoile",IF(AND(F9>=80,G9<80),"Problème de perf.",IF(AND(F9<80,G9>=80),"Travailleur fiable","Sous-performeur")))) | J9: DRH | K9: 2025-02-20 | L9: Q1 2025 | M9: Étoile montante RH | N9: Programme haut potentiel
A10: EMP-005 | B10: =IFERROR(VLOOKUP(A10,'F01 - _Données Centrales'!A6:B20,2,FALSE),"") | C10: =IFERROR(VLOOKUP(A10,'F01 - _Données Centrales'!A6:C20,3,FALSE),"") | D10: Élevé | E10: Bon | F10: 82 | G10: 78 | H10: =IFERROR((F10+G10)/2,0) | I10: =IF(OR(F10="",G10=""),"",IF(AND(F10>=80,G10>=80),"Étoile",IF(AND(F10>=80,G10<80),"Problème de perf.",IF(AND(F10<80,G10>=80),"Travailleur fiable","Sous-performeur")))) | J10: DRH | K10: 2025-03-01 | L10: Q1 2025 | M10: Bonne progression | N10: Formation management
B11: =IFERROR(VLOOKUP(A11,'F01 - _Données Centrales'!A6:B20,2,FALSE),"") | C11: =IFERROR(VLOOKUP(A11,'F01 - _Données Centrales'!A6:C20,3,FALSE),"") | H11: =IFERROR((F11+G11)/2,0) | I11: =IF(OR(F11="",G11=""),"",IF(AND(F11>=80,G11>=80),"Étoile",IF(AND(F11>=80,G11<80),"Problème de perf.",IF(AND(F11<80,G11>=80),"Travailleur fiable","Sous-performeur"))))
B12: =IFERROR(VLOOKUP(A12,'F01 - _Données Centrales'!A6:B20,2,FALSE),"") | C12: =IFERROR(VLOOKUP(A12,'F01 - _Données Centrales'!A6:C20,3,FALSE),"") | H12: =IFERROR((F12+G12)/2,0) | I12: =IF(OR(F12="",G12=""),"",IF(AND(F12>=80,G12>=80),"Étoile",IF(AND(F12>=80,G12<80),"Problème de perf.",IF(AND(F12<80,G12>=80),"Travailleur fiable","Sous-performeur"))))
B13: =IFERROR(VLOOKUP(A13,'F01 - _Données Centrales'!A6:B20,2,FALSE),"") | C13: =IFERROR(VLOOKUP(A13,'F01 - _Données Centrales'!A6:C20,3,FALSE),"") | H13: =IFERROR((F13+G13)/2,0) | I13: =IF(OR(F13="",G13=""),"",IF(AND(F13>=80,G13>=80),"Étoile",IF(AND(F13>=80,G13<80),"Problème de perf.",IF(AND(F13<80,G13>=80),"Travailleur fiable","Sous-performeur"))))
B14: =IFERROR(VLOOKUP(A14,'F01 - _Données Centrales'!A6:B20,2,FALSE),"") | C14: =IFERROR(VLOOKUP(A14,'F01 - _Données Centrales'!A6:C20,3,FALSE),"") | H14: =IFERROR((F14+G14)/2,0) | I14: =IF(OR(F14="",G14=""),"",IF(AND(F14>=80,G14>=80),"Étoile",IF(AND(F14>=80,G14<80),"Problème de perf.",IF(AND(F14<80,G14>=80),"Travailleur fiable","Sous-performeur"))))
B15: =IFERROR(VLOOKUP(A15,'F01 - _Données Centrales'!A6:B20,2,FALSE),"") | C15: =IFERROR(VLOOKUP(A15,'F01 - _Données Centrales'!A6:C20,3,FALSE),"") | H15: =IFERROR((F15+G15)/2,0) | I15: =IF(OR(F15="",G15=""),"",IF(AND(F15>=80,G15>=80),"Étoile",IF(AND(F15>=80,G15<80),"Problème de perf.",IF(AND(F15<80,G15>=80),"Travailleur fiable","Sous-performeur"))))
B16: =IFERROR(VLOOKUP(A16,'F01 - _Données Centrales'!A6:B20,2,FALSE),"") | C16: =IFERROR(VLOOKUP(A16,'F01 - _Données Centrales'!A6:C20,3,FALSE),"") | H16: =IFERROR((F16+G16)/2,0) | I16: =IF(OR(F16="",G16=""),"",IF(AND(F16>=80,G16>=80),"Étoile",IF(AND(F16>=80,G16<80),"Problème de perf.",IF(AND(F16<80,G16>=80),"Travailleur fiable","Sous-performeur"))))
B17: =IFERROR(VLOOKUP(A17,'F01 - _Données Centrales'!A6:B20,2,FALSE),"") | C17: =IFERROR(VLOOKUP(A17,'F01 - _Données Centrales'!A6:C20,3,FALSE),"") | H17: =IFERROR((F17+G17)/2,0) | I17: =IF(OR(F17="",G17=""),"",IF(AND(F17>=80,G17>=80),"Étoile",IF(AND(F17>=80,G17<80),"Problème de perf.",IF(AND(F17<80,G17>=80),"Travailleur fiable","Sous-performeur"))))
B18: =IFERROR(VLOOKUP(A18,'F01 - _Données Centrales'!A6:B20,2,FALSE),"") | C18: =IFERROR(VLOOKUP(A18,'F01 - _Données Centrales'!A6:C20,3,FALSE),"") | H18: =IFERROR((F18+G18)/2,0) | I18: =IF(OR(F18="",G18=""),"",IF(AND(F18>=80,G18>=80),"Étoile",IF(AND(F18>=80,G18<80),"Problème de perf.",IF(AND(F18<80,G18>=80),"Travailleur fiable","Sous-performeur"))))
B19: =IFERROR(VLOOKUP(A19,'F01 - _Données Centrales'!A6:B20,2,FALSE),"") | C19: =IFERROR(VLOOKUP(A19,'F01 - _Données Centrales'!A6:C20,3,FALSE),"") | H19: =IFERROR((F19+G19)/2,0) | I19: =IF(OR(F19="",G19=""),"",IF(AND(F19>=80,G19>=80),"Étoile",IF(AND(F19>=80,G19<80),"Problème de perf.",IF(AND(F19<80,G19>=80),"Travailleur fiable","Sous-performeur"))))
B20: =IFERROR(VLOOKUP(A20,'F01 - _Données Centrales'!A6:B20,2,FALSE),"") | C20: =IFERROR(VLOOKUP(A20,'F01 - _Données Centrales'!A6:C20,3,FALSE),"") | H20: =IFERROR((F20+G20)/2,0) | I20: =IF(OR(F20="",G20=""),"",IF(AND(F20>=80,G20>=80),"Étoile",IF(AND(F20>=80,G20<80),"Problème de perf.",IF(AND(F20<80,G20>=80),"Travailleur fiable","Sous-performeur"))))
B21: =IFERROR(VLOOKUP(A21,'F01 - _Données Centrales'!A6:B20,2,FALSE),"") | C21: =IFERROR(VLOOKUP(A21,'F01 - _Données Centrales'!A6:C20,3,FALSE),"") | H21: =IFERROR((F21+G21)/2,0) | I21: =IF(OR(F21="",G21=""),"",IF(AND(F21>=80,G21>=80),"Étoile",IF(AND(F21>=80,G21<80),"Problème de perf.",IF(AND(F21<80,G21>=80),"Travailleur fiable","Sous-performeur"))))
B22: =IFERROR(VLOOKUP(A22,'F01 - _Données Centrales'!A6:B20,2,FALSE),"") | C22: =IFERROR(VLOOKUP(A22,'F01 - _Données Centrales'!A6:C20,3,FALSE),"") | H22: =IFERROR((F22+G22)/2,0) | I22: =IF(OR(F22="",G22=""),"",IF(AND(F22>=80,G22>=80),"Étoile",IF(AND(F22>=80,G22<80),"Problème de perf.",IF(AND(F22<80,G22>=80),"Travailleur fiable","Sous-performeur"))))
B23: =IFERROR(VLOOKUP(A23,'F01 - _Données Centrales'!A6:B20,2,FALSE),"") | C23: =IFERROR(VLOOKUP(A23,'F01 - _Données Centrales'!A6:C20,3,FALSE),"") | H23: =IFERROR((F23+G23)/2,0) | I23: =IF(OR(F23="",G23=""),"",IF(AND(F23>=80,G23>=80),"Étoile",IF(AND(F23>=80,G23<80),"Problème de perf.",IF(AND(F23<80,G23>=80),"Travailleur fiable","Sous-performeur"))))
B24: =IFERROR(VLOOKUP(A24,'F01 - _Données Centrales'!A6:B20,2,FALSE),"") | C24: =IFERROR(VLOOKUP(A24,'F01 - _Données Centrales'!A6:C20,3,FALSE),"") | H24: =IFERROR((F24+G24)/2,0) | I24: =IF(OR(F24="",G24=""),"",IF(AND(F24>=80,G24>=80),"Étoile",IF(AND(F24>=80,G24<80),"Problème de perf.",IF(AND(F24<80,G24>=80),"Travailleur fiable","Sous-performeur"))))
B25: =IFERROR(VLOOKUP(A25,'F01 - _Données Centrales'!A6:B20,2,FALSE),"") | C25: =IFERROR(VLOOKUP(A25,'F01 - _Données Centrales'!A6:C20,3,FALSE),"") | H25: =IFERROR((F25+G25)/2,0) | I25: =IF(OR(F25="",G25=""),"",IF(AND(F25>=80,G25>=80),"Étoile",IF(AND(F25>=80,G25<80),"Problème de perf.",IF(AND(F25<80,G25>=80),"Travailleur fiable","Sous-performeur"))))
B26: =IFERROR(VLOOKUP(A26,'F01 - _Données Centrales'!A6:B20,2,FALSE),"") | C26: =IFERROR(VLOOKUP(A26,'F01 - _Données Centrales'!A6:C20,3,FALSE),"") | H26: =IFERROR((F26+G26)/2,0) | I26: =IF(OR(F26="",G26=""),"",IF(AND(F26>=80,G26>=80),"Étoile",IF(AND(F26>=80,G26<80),"Problème de perf.",IF(AND(F26<80,G26>=80),"Travailleur fiable","Sous-performeur"))))
B27: =IFERROR(VLOOKUP(A27,'F01 - _Données Centrales'!A6:B20,2,FALSE),"") | C27: =IFERROR(VLOOKUP(A27,'F01 - _Données Centrales'!A6:C20,3,FALSE),"") | H27: =IFERROR((F27+G27)/2,0) | I27: =IF(OR(F27="",G27=""),"",IF(AND(F27>=80,G27>=80),"Étoile",IF(AND(F27>=80,G27<80),"Problème de perf.",IF(AND(F27<80,G27>=80),"Travailleur fiable","Sous-performeur"))))
B28: =IFERROR(VLOOKUP(A28,'F01 - _Données Centrales'!A6:B20,2,FALSE),"") | C28: =IFERROR(VLOOKUP(A28,'F01 - _Données Centrales'!A6:C20,3,FALSE),"") | H28: =IFERROR((F28+G28)/2,0) | I28: =IF(OR(F28="",G28=""),"",IF(AND(F28>=80,G28>=80),"Étoile",IF(AND(F28>=80,G28<80),"Problème de perf.",IF(AND(F28<80,G28>=80),"Travailleur fiable","Sous-performeur"))))
B29: =IFERROR(VLOOKUP(A29,'F01 - _Données Centrales'!A6:B20,2,FALSE),"") | C29: =IFERROR(VLOOKUP(A29,'F01 - _Données Centrales'!A6:C20,3,FALSE),"") | H29: =IFERROR((F29+G29)/2,0) | I29: =IF(OR(F29="",G29=""),"",IF(AND(F29>=80,G29>=80),"Étoile",IF(AND(F29>=80,G29<80),"Problème de perf.",IF(AND(F29<80,G29>=80),"Travailleur fiable","Sous-performeur"))))
B30: =IFERROR(VLOOKUP(A30,'F01 - _Données Centrales'!A6:B20,2,FALSE),"") | C30: =IFERROR(VLOOKUP(A30,'F01 - _Données Centrales'!A6:C20,3,FALSE),"") | H30: =IFERROR((F30+G30)/2,0) | I30: =IF(OR(F30="",G30=""),"",IF(AND(F30>=80,G30>=80),"Étoile",IF(AND(F30>=80,G30<80),"Problème de perf.",IF(AND(F30<80,G30>=80),"Travailleur fiable","Sous-performeur"))))
B31: =IFERROR(VLOOKUP(A31,'F01 - _Données Centrales'!A6:B20,2,FALSE),"") | C31: =IFERROR(VLOOKUP(A31,'F01 - _Données Centrales'!A6:C20,3,FALSE),"") | H31: =IFERROR((F31+G31)/2,0) | I31: =IF(OR(F31="",G31=""),"",IF(AND(F31>=80,G31>=80),"Étoile",IF(AND(F31>=80,G31<80),"Problème de perf.",IF(AND(F31<80,G31>=80),"Travailleur fiable","Sous-performeur"))))
B32: =IFERROR(VLOOKUP(A32,'F01 - _Données Centrales'!A6:B20,2,FALSE),"") | C32: =IFERROR(VLOOKUP(A32,'F01 - _Données Centrales'!A6:C20,3,FALSE),"") | H32: =IFERROR((F32+G32)/2,0) | I32: =IF(OR(F32="",G32=""),"",IF(AND(F32>=80,G32>=80),"Étoile",IF(AND(F32>=80,G32<80),"Problème de perf.",IF(AND(F32<80,G32>=80),"Travailleur fiable","Sous-performeur"))))
B33: =IFERROR(VLOOKUP(A33,'F01 - _Données Centrales'!A6:B20,2,FALSE),"") | C33: =IFERROR(VLOOKUP(A33,'F01 - _Données Centrales'!A6:C20,3,FALSE),"") | H33: =IFERROR((F33+G33)/2,0) | I33: =IF(OR(F33="",G33=""),"",IF(AND(F33>=80,G33>=80),"Étoile",IF(AND(F33>=80,G33<80),"Problème de perf.",IF(AND(F33<80,G33>=80),"Travailleur fiable","Sous-performeur"))))
B34: =IFERROR(VLOOKUP(A34,'F01 - _Données Centrales'!A6:B20,2,FALSE),"") | C34: =IFERROR(VLOOKUP(A34,'F01 - _Données Centrales'!A6:C20,3,FALSE),"") | H34: =IFERROR((F34+G34)/2,0) | I34: =IF(OR(F34="",G34=""),"",IF(AND(F34>=80,G34>=80),"Étoile",IF(AND(F34>=80,G34<80),"Problème de perf.",IF(AND(F34<80,G34>=80),"Travailleur fiable","Sous-performeur"))))
B35: =IFERROR(VLOOKUP(A35,'F01 - _Données Centrales'!A6:B20,2,FALSE),"") | C35: =IFERROR(VLOOKUP(A35,'F01 - _Données Centrales'!A6:C20,3,FALSE),"") | H35: =IFERROR((F35+G35)/2,0) | I35: =IF(OR(F35="",G35=""),"",IF(AND(F35>=80,G35>=80),"Étoile",IF(AND(F35>=80,G35<80),"Problème de perf.",IF(AND(F35<80,G35>=80),"Travailleur fiable","Sous-performeur"))))
B36: =IFERROR(VLOOKUP(A36,'F01 - _Données Centrales'!A6:B20,2,FALSE),"") | C36: =IFERROR(VLOOKUP(A36,'F01 - _Données Centrales'!A6:C20,3,FALSE),"") | H36: =IFERROR((F36+G36)/2,0) | I36: =IF(OR(F36="",G36=""),"",IF(AND(F36>=80,G36>=80),"Étoile",IF(AND(F36>=80,G36<80),"Problème de perf.",IF(AND(F36<80,G36>=80),"Travailleur fiable","Sous-performeur"))))
B37: =IFERROR(VLOOKUP(A37,'F01 - _Données Centrales'!A6:B20,2,FALSE),"") | C37: =IFERROR(VLOOKUP(A37,'F01 - _Données Centrales'!A6:C20,3,FALSE),"") | H37: =IFERROR((F37+G37)/2,0) | I37: =IF(OR(F37="",G37=""),"",IF(AND(F37>=80,G37>=80),"Étoile",IF(AND(F37>=80,G37<80),"Problème de perf.",IF(AND(F37<80,G37>=80),"Travailleur fiable","Sous-performeur"))))
B38: =IFERROR(VLOOKUP(A38,'F01 - _Données Centrales'!A6:B20,2,FALSE),"") | C38: =IFERROR(VLOOKUP(A38,'F01 - _Données Centrales'!A6:C20,3,FALSE),"") | H38: =IFERROR((F38+G38)/2,0) | I38: =IF(OR(F38="",G38=""),"",IF(AND(F38>=80,G38>=80),"Étoile",IF(AND(F38>=80,G38<80),"Problème de perf.",IF(AND(F38<80,G38>=80),"Travailleur fiable","Sous-performeur"))))
B39: =IFERROR(VLOOKUP(A39,'F01 - _Données Centrales'!A6:B20,2,FALSE),"") | C39: =IFERROR(VLOOKUP(A39,'F01 - _Données Centrales'!A6:C20,3,FALSE),"") | H39: =IFERROR((F39+G39)/2,0) | I39: =IF(OR(F39="",G39=""),"",IF(AND(F39>=80,G39>=80),"Étoile",IF(AND(F39>=80,G39<80),"Problème de perf.",IF(AND(F39<80,G39>=80),"Travailleur fiable","Sous-performeur"))))
B40: =IFERROR(VLOOKUP(A40,'F01 - _Données Centrales'!A6:B20,2,FALSE),"") | C40: =IFERROR(VLOOKUP(A40,'F01 - _Données Centrales'!A6:C20,3,FALSE),"") | H40: =IFERROR((F40+G40)/2,0) | I40: =IF(OR(F40="",G40=""),"",IF(AND(F40>=80,G40>=80),"Étoile",IF(AND(F40>=80,G40<80),"Problème de perf.",IF(AND(F40<80,G40>=80),"Travailleur fiable","Sous-performeur"))))
B41: =IFERROR(VLOOKUP(A41,'F01 - _Données Centrales'!A6:B20,2,FALSE),"") | C41: =IFERROR(VLOOKUP(A41,'F01 - _Données Centrales'!A6:C20,3,FALSE),"") | H41: =IFERROR((F41+G41)/2,0) | I41: =IF(OR(F41="",G41=""),"",IF(AND(F41>=80,G41>=80),"Étoile",IF(AND(F41>=80,G41<80),"Problème de perf.",IF(AND(F41<80,G41>=80),"Travailleur fiable","Sous-performeur"))))
B42: =IFERROR(VLOOKUP(A42,'F01 - _Données Centrales'!A6:B20,2,FALSE),"") | C42: =IFERROR(VLOOKUP(A42,'F01 - _Données Centrales'!A6:C20,3,FALSE),"") | H42: =IFERROR((F42+G42)/2,0) | I42: =IF(OR(F42="",G42=""),"",IF(AND(F42>=80,G42>=80),"Étoile",IF(AND(F42>=80,G42<80),"Problème de perf.",IF(AND(F42<80,G42>=80),"Travailleur fiable","Sous-performeur"))))
B43: =IFERROR(VLOOKUP(A43,'F01 - _Données Centrales'!A6:B20,2,FALSE),"") | C43: =IFERROR(VLOOKUP(A43,'F01 - _Données Centrales'!A6:C20,3,FALSE),"") | H43: =IFERROR((F43+G43)/2,0) | I43: =IF(OR(F43="",G43=""),"",IF(AND(F43>=80,G43>=80),"Étoile",IF(AND(F43>=80,G43<80),"Problème de perf.",IF(AND(F43<80,G43>=80),"Travailleur fiable","Sous-performeur"))))
B44: =IFERROR(VLOOKUP(A44,'F01 - _Données Centrales'!A6:B20,2,FALSE),"") | C44: =IFERROR(VLOOKUP(A44,'F01 - _Données Centrales'!A6:C20,3,FALSE),"") | H44: =IFERROR((F44+G44)/2,0) | I44: =IF(OR(F44="",G44=""),"",IF(AND(F44>=80,G44>=80),"Étoile",IF(AND(F44>=80,G44<80),"Problème de perf.",IF(AND(F44<80,G44>=80),"Travailleur fiable","Sous-performeur"))))
B45: =IFERROR(VLOOKUP(A45,'F01 - _Données Centrales'!A6:B20,2,FALSE),"") | C45: =IFERROR(VLOOKUP(A45,'F01 - _Données Centrales'!A6:C20,3,FALSE),"") | H45: =IFERROR((F45+G45)/2,0) | I45: =IF(OR(F45="",G45=""),"",IF(AND(F45>=80,G45>=80),"Étoile",IF(AND(F45>=80,G45<80),"Problème de perf.",IF(AND(F45<80,G45>=80),"Travailleur fiable","Sous-performeur"))))
B46: =IFERROR(VLOOKUP(A46,'F01 - _Données Centrales'!A6:B20,2,FALSE),"") | C46: =IFERROR(VLOOKUP(A46,'F01 - _Données Centrales'!A6:C20,3,FALSE),"") | H46: =IFERROR((F46+G46)/2,0) | I46: =IF(OR(F46="",G46=""),"",IF(AND(F46>=80,G46>=80),"Étoile",IF(AND(F46>=80,G46<80),"Problème de perf.",IF(AND(F46<80,G46>=80),"Travailleur fiable","Sous-performeur"))))
B47: =IFERROR(VLOOKUP(A47,'F01 - _Données Centrales'!A6:B20,2,FALSE),"") | C47: =IFERROR(VLOOKUP(A47,'F01 - _Données Centrales'!A6:C20,3,FALSE),"") | H47: =IFERROR((F47+G47)/2,0) | I47: =IF(OR(F47="",G47=""),"",IF(AND(F47>=80,G47>=80),"Étoile",IF(AND(F47>=80,G47<80),"Problème de perf.",IF(AND(F47<80,G47>=80),"Travailleur fiable","Sous-performeur"))))
B48: =IFERROR(VLOOKUP(A48,'F01 - _Données Centrales'!A6:B20,2,FALSE),"") | C48: =IFERROR(VLOOKUP(A48,'F01 - _Données Centrales'!A6:C20,3,FALSE),"") | H48: =IFERROR((F48+G48)/2,0) | I48: =IF(OR(F48="",G48=""),"",IF(AND(F48>=80,G48>=80),"Étoile",IF(AND(F48>=80,G48<80),"Problème de perf.",IF(AND(F48<80,G48>=80),"Travailleur fiable","Sous-performeur"))))
B49: =IFERROR(VLOOKUP(A49,'F01 - _Données Centrales'!A6:B20,2,FALSE),"") | C49: =IFERROR(VLOOKUP(A49,'F01 - _Données Centrales'!A6:C20,3,FALSE),"") | H49: =IFERROR((F49+G49)/2,0) | I49: =IF(OR(F49="",G49=""),"",IF(AND(F49>=80,G49>=80),"Étoile",IF(AND(F49>=80,G49<80),"Problème de perf.",IF(AND(F49<80,G49>=80),"Travailleur fiable","Sous-performeur"))))
B50: =IFERROR(VLOOKUP(A50,'F01 - _Données Centrales'!A6:B20,2,FALSE),"") | C50: =IFERROR(VLOOKUP(A50,'F01 - _Données Centrales'!A6:C20,3,FALSE),"") | H50: =IFERROR((F50+G50)/2,0) | I50: =IF(OR(F50="",G50=""),"",IF(AND(F50>=80,G50>=80),"Étoile",IF(AND(F50>=80,G50<80),"Problème de perf.",IF(AND(F50<80,G50>=80),"Travailleur fiable","Sous-performeur"))))
B51: =IFERROR(VLOOKUP(A51,'F01 - _Données Centrales'!A6:B20,2,FALSE),"") | C51: =IFERROR(VLOOKUP(A51,'F01 - _Données Centrales'!A6:C20,3,FALSE),"") | H51: =IFERROR((F51+G51)/2,0) | I51: =IF(OR(F51="",G51=""),"",IF(AND(F51>=80,G51>=80),"Étoile",IF(AND(F51>=80,G51<80),"Problème de perf.",IF(AND(F51<80,G51>=80),"Travailleur fiable","Sous-performeur"))))
B52: =IFERROR(VLOOKUP(A52,'F01 - _Données Centrales'!A6:B20,2,FALSE),"") | C52: =IFERROR(VLOOKUP(A52,'F01 - _Données Centrales'!A6:C20,3,FALSE),"") | H52: =IFERROR((F52+G52)/2,0) | I52: =IF(OR(F52="",G52=""),"",IF(AND(F52>=80,G52>=80),"Étoile",IF(AND(F52>=80,G52<80),"Problème de perf.",IF(AND(F52<80,G52>=80),"Travailleur fiable","Sous-performeur"))))
B53: =IFERROR(VLOOKUP(A53,'F01 - _Données Centrales'!A6:B20,2,FALSE),"") | C53: =IFERROR(VLOOKUP(A53,'F01 - _Données Centrales'!A6:C20,3,FALSE),"") | H53: =IFERROR((F53+G53)/2,0) | I53: =IF(OR(F53="",G53=""),"",IF(AND(F53>=80,G53>=80),"Étoile",IF(AND(F53>=80,G53<80),"Problème de perf.",IF(AND(F53<80,G53>=80),"Travailleur fiable","Sous-performeur"))))
B54: =IFERROR(VLOOKUP(A54,'F01 - _Données Centrales'!A6:B20,2,FALSE),"") | C54: =IFERROR(VLOOKUP(A54,'F01 - _Données Centrales'!A6:C20,3,FALSE),"") | H54: =IFERROR((F54+G54)/2,0) | I54: =IF(OR(F54="",G54=""),"",IF(AND(F54>=80,G54>=80),"Étoile",IF(AND(F54>=80,G54<80),"Problème de perf.",IF(AND(F54<80,G54>=80),"Travailleur fiable","Sous-performeur"))))
B55: =IFERROR(VLOOKUP(A55,'F01 - _Données Centrales'!A6:B20,2,FALSE),"") | C55: =IFERROR(VLOOKUP(A55,'F01 - _Données Centrales'!A6:C20,3,FALSE),"") | H55: =IFERROR((F55+G55)/2,0) | I55: =IF(OR(F55="",G55=""),"",IF(AND(F55>=80,G55>=80),"Étoile",IF(AND(F55>=80,G55<80),"Problème de perf.",IF(AND(F55<80,G55>=80),"Travailleur fiable","Sous-performeur"))))
B56: =IFERROR(VLOOKUP(A56,'F01 - _Données Centrales'!A6:B20,2,FALSE),"") | C56: =IFERROR(VLOOKUP(A56,'F01 - _Données Centrales'!A6:C20,3,FALSE),"") | H56: =IFERROR((F56+G56)/2,0) | I56: =IF(OR(F56="",G56=""),"",IF(AND(F56>=80,G56>=80),"Étoile",IF(AND(F56>=80,G56<80),"Problème de perf.",IF(AND(F56<80,G56>=80),"Travailleur fiable","Sous-performeur"))))
B57: =IFERROR(VLOOKUP(A57,'F01 - _Données Centrales'!A6:B20,2,FALSE),"") | C57: =IFERROR(VLOOKUP(A57,'F01 - _Données Centrales'!A6:C20,3,FALSE),"") | H57: =IFERROR((F57+G57)/2,0) | I57: =IF(OR(F57="",G57=""),"",IF(AND(F57>=80,G57>=80),"Étoile",IF(AND(F57>=80,G57<80),"Problème de perf.",IF(AND(F57<80,G57>=80),"Travailleur fiable","Sous-performeur"))))
B58: =IFERROR(VLOOKUP(A58,'F01 - _Données Centrales'!A6:B20,2,FALSE),"") | C58: =IFERROR(VLOOKUP(A58,'F01 - _Données Centrales'!A6:C20,3,FALSE),"") | H58: =IFERROR((F58+G58)/2,0) | I58: =IF(OR(F58="",G58=""),"",IF(AND(F58>=80,G58>=80),"Étoile",IF(AND(F58>=80,G58<80),"Problème de perf.",IF(AND(F58<80,G58>=80),"Travailleur fiable","Sous-performeur"))))
B59: =IFERROR(VLOOKUP(A59,'F01 - _Données Centrales'!A6:B20,2,FALSE),"") | C59: =IFERROR(VLOOKUP(A59,'F01 - _Données Centrales'!A6:C20,3,FALSE),"") | H59: =IFERROR((F59+G59)/2,0) | I59: =IF(OR(F59="",G59=""),"",IF(AND(F59>=80,G59>=80),"Étoile",IF(AND(F59>=80,G59<80),"Problème de perf.",IF(AND(F59<80,G59>=80),"Travailleur fiable","Sous-performeur"))))
B60: =IFERROR(VLOOKUP(A60,'F01 - _Données Centrales'!A6:B20,2,FALSE),"") | C60: =IFERROR(VLOOKUP(A60,'F01 - _Données Centrales'!A6:C20,3,FALSE),"") | H60: =IFERROR((F60+G60)/2,0) | I60: =IF(OR(F60="",G60=""),"",IF(AND(F60>=80,G60>=80),"Étoile",IF(AND(F60>=80,G60<80),"Problème de perf.",IF(AND(F60<80,G60>=80),"Travailleur fiable","Sous-performeur"))))
B61: =IFERROR(VLOOKUP(A61,'F01 - _Données Centrales'!A6:B20,2,FALSE),"") | C61: =IFERROR(VLOOKUP(A61,'F01 - _Données Centrales'!A6:C20,3,FALSE),"") | H61: =IFERROR((F61+G61)/2,0) | I61: =IF(OR(F61="",G61=""),"",IF(AND(F61>=80,G61>=80),"Étoile",IF(AND(F61>=80,G61<80),"Problème de perf.",IF(AND(F61<80,G61>=80),"Travailleur fiable","Sous-performeur"))))
B62: =IFERROR(VLOOKUP(A62,'F01 - _Données Centrales'!A6:B20,2,FALSE),"") | C62: =IFERROR(VLOOKUP(A62,'F01 - _Données Centrales'!A6:C20,3,FALSE),"") | H62: =IFERROR((F62+G62)/2,0) | I62: =IF(OR(F62="",G62=""),"",IF(AND(F62>=80,G62>=80),"Étoile",IF(AND(F62>=80,G62<80),"Problème de perf.",IF(AND(F62<80,G62>=80),"Travailleur fiable","Sous-performeur"))))
B63: =IFERROR(VLOOKUP(A63,'F01 - _Données Centrales'!A6:B20,2,FALSE),"") | C63: =IFERROR(VLOOKUP(A63,'F01 - _Données Centrales'!A6:C20,3,FALSE),"") | H63: =IFERROR((F63+G63)/2,0) | I63: =IF(OR(F63="",G63=""),"",IF(AND(F63>=80,G63>=80),"Étoile",IF(AND(F63>=80,G63<80),"Problème de perf.",IF(AND(F63<80,G63>=80),"Travailleur fiable","Sous-performeur"))))
B64: =IFERROR(VLOOKUP(A64,'F01 - _Données Centrales'!A6:B20,2,FALSE),"") | C64: =IFERROR(VLOOKUP(A64,'F01 - _Données Centrales'!A6:C20,3,FALSE),"") | H64: =IFERROR((F64+G64)/2,0) | I64: =IF(OR(F64="",G64=""),"",IF(AND(F64>=80,G64>=80),"Étoile",IF(AND(F64>=80,G64<80),"Problème de perf.",IF(AND(F64<80,G64>=80),"Travailleur fiable","Sous-performeur"))))
B65: =IFERROR(VLOOKUP(A65,'F01 - _Données Centrales'!A6:B20,2,FALSE),"") | C65: =IFERROR(VLOOKUP(A65,'F01 - _Données Centrales'!A6:C20,3,FALSE),"") | H65: =IFERROR((F65+G65)/2,0) | I65: =IF(OR(F65="",G65=""),"",IF(AND(F65>=80,G65>=80),"Étoile",IF(AND(F65>=80,G65<80),"Problème de perf.",IF(AND(F65<80,G65>=80),"Travailleur fiable","Sous-performeur"))))
B66: =IFERROR(VLOOKUP(A66,'F01 - _Données Centrales'!A6:B20,2,FALSE),"") | C66: =IFERROR(VLOOKUP(A66,'F01 - _Données Centrales'!A6:C20,3,FALSE),"") | H66: =IFERROR((F66+G66)/2,0) | I66: =IF(OR(F66="",G66=""),"",IF(AND(F66>=80,G66>=80),"Étoile",IF(AND(F66>=80,G66<80),"Problème de perf.",IF(AND(F66<80,G66>=80),"Travailleur fiable","Sous-performeur"))))
B67: =IFERROR(VLOOKUP(A67,'F01 - _Données Centrales'!A6:B20,2,FALSE),"") | C67: =IFERROR(VLOOKUP(A67,'F01 - _Données Centrales'!A6:C20,3,FALSE),"") | H67: =IFERROR((F67+G67)/2,0) | I67: =IF(OR(F67="",G67=""),"",IF(AND(F67>=80,G67>=80),"Étoile",IF(AND(F67>=80,G67<80),"Problème de perf.",IF(AND(F67<80,G67>=80),"Travailleur fiable","Sous-performeur"))))
B68: =IFERROR(VLOOKUP(A68,'F01 - _Données Centrales'!A6:B20,2,FALSE),"") | C68: =IFERROR(VLOOKUP(A68,'F01 - _Données Centrales'!A6:C20,3,FALSE),"") | H68: =IFERROR((F68+G68)/2,0) | I68: =IF(OR(F68="",G68=""),"",IF(AND(F68>=80,G68>=80),"Étoile",IF(AND(F68>=80,G68<80),"Problème de perf.",IF(AND(F68<80,G68>=80),"Travailleur fiable","Sous-performeur"))))
B69: =IFERROR(VLOOKUP(A69,'F01 - _Données Centrales'!A6:B20,2,FALSE),"") | C69: =IFERROR(VLOOKUP(A69,'F01 - _Données Centrales'!A6:C20,3,FALSE),"") | H69: =IFERROR((F69+G69)/2,0) | I69: =IF(OR(F69="",G69=""),"",IF(AND(F69>=80,G69>=80),"Étoile",IF(AND(F69>=80,G69<80),"Problème de perf.",IF(AND(F69<80,G69>=80),"Travailleur fiable","Sous-performeur"))))
B70: =IFERROR(VLOOKUP(A70,'F01 - _Données Centrales'!A6:B20,2,FALSE),"") | C70: =IFERROR(VLOOKUP(A70,'F01 - _Données Centrales'!A6:C20,3,FALSE),"") | H70: =IFERROR((F70+G70)/2,0) | I70: =IF(OR(F70="",G70=""),"",IF(AND(F70>=80,G70>=80),"Étoile",IF(AND(F70>=80,G70<80),"Problème de perf.",IF(AND(F70<80,G70>=80),"Travailleur fiable","Sous-performeur"))))
B71: =IFERROR(VLOOKUP(A71,'F01 - _Données Centrales'!A6:B20,2,FALSE),"") | C71: =IFERROR(VLOOKUP(A71,'F01 - _Données Centrales'!A6:C20,3,FALSE),"") | H71: =IFERROR((F71+G71)/2,0) | I71: =IF(OR(F71="",G71=""),"",IF(AND(F71>=80,G71>=80),"Étoile",IF(AND(F71>=80,G71<80),"Problème de perf.",IF(AND(F71<80,G71>=80),"Travailleur fiable","Sous-performeur"))))
B72: =IFERROR(VLOOKUP(A72,'F01 - _Données Centrales'!A6:B20,2,FALSE),"") | C72: =IFERROR(VLOOKUP(A72,'F01 - _Données Centrales'!A6:C20,3,FALSE),"") | H72: =IFERROR((F72+G72)/2,0) | I72: =IF(OR(F72="",G72=""),"",IF(AND(F72>=80,G72>=80),"Étoile",IF(AND(F72>=80,G72<80),"Problème de perf.",IF(AND(F72<80,G72>=80),"Travailleur fiable","Sous-performeur"))))
B73: =IFERROR(VLOOKUP(A73,'F01 - _Données Centrales'!A6:B20,2,FALSE),"") | C73: =IFERROR(VLOOKUP(A73,'F01 - _Données Centrales'!A6:C20,3,FALSE),"") | H73: =IFERROR((F73+G73)/2,0) | I73: =IF(OR(F73="",G73=""),"",IF(AND(F73>=80,G73>=80),"Étoile",IF(AND(F73>=80,G73<80),"Problème de perf.",IF(AND(F73<80,G73>=80),"Travailleur fiable","Sous-performeur"))))
B74: =IFERROR(VLOOKUP(A74,'F01 - _Données Centrales'!A6:B20,2,FALSE),"") | C74: =IFERROR(VLOOKUP(A74,'F01 - _Données Centrales'!A6:C20,3,FALSE),"") | H74: =IFERROR((F74+G74)/2,0) | I74: =IF(OR(F74="",G74=""),"",IF(AND(F74>=80,G74>=80),"Étoile",IF(AND(F74>=80,G74<80),"Problème de perf.",IF(AND(F74<80,G74>=80),"Travailleur fiable","Sous-performeur"))))
B75: =IFERROR(VLOOKUP(A75,'F01 - _Données Centrales'!A6:B20,2,FALSE),"") | C75: =IFERROR(VLOOKUP(A75,'F01 - _Données Centrales'!A6:C20,3,FALSE),"") | H75: =IFERROR((F75+G75)/2,0) | I75: =IF(OR(F75="",G75=""),"",IF(AND(F75>=80,G75>=80),"Étoile",IF(AND(F75>=80,G75<80),"Problème de perf.",IF(AND(F75<80,G75>=80),"Travailleur fiable","Sous-performeur"))))
B76: =IFERROR(VLOOKUP(A76,'F01 - _Données Centrales'!A6:B20,2,FALSE),"") | C76: =IFERROR(VLOOKUP(A76,'F01 - _Données Centrales'!A6:C20,3,FALSE),"") | H76: =IFERROR((F76+G76)/2,0) | I76: =IF(OR(F76="",G76=""),"",IF(AND(F76>=80,G76>=80),"Étoile",IF(AND(F76>=80,G76<80),"Problème de perf.",IF(AND(F76<80,G76>=80),"Travailleur fiable","Sous-performeur"))))
B77: =IFERROR(VLOOKUP(A77,'F01 - _Données Centrales'!A6:B20,2,FALSE),"") | C77: =IFERROR(VLOOKUP(A77,'F01 - _Données Centrales'!A6:C20,3,FALSE),"") | H77: =IFERROR((F77+G77)/2,0) | I77: =IF(OR(F77="",G77=""),"",IF(AND(F77>=80,G77>=80),"Étoile",IF(AND(F77>=80,G77<80),"Problème de perf.",IF(AND(F77<80,G77>=80),"Travailleur fiable","Sous-performeur"))))
B78: =IFERROR(VLOOKUP(A78,'F01 - _Données Centrales'!A6:B20,2,FALSE),"") | C78: =IFERROR(VLOOKUP(A78,'F01 - _Données Centrales'!A6:C20,3,FALSE),"") | H78: =IFERROR((F78+G78)/2,0) | I78: =IF(OR(F78="",G78=""),"",IF(AND(F78>=80,G78>=80),"Étoile",IF(AND(F78>=80,G78<80),"Problème de perf.",IF(AND(F78<80,G78>=80),"Travailleur fiable","Sous-performeur"))))
B79: =IFERROR(VLOOKUP(A79,'F01 - _Données Centrales'!A6:B20,2,FALSE),"") | C79: =IFERROR(VLOOKUP(A79,'F01 - _Données Centrales'!A6:C20,3,FALSE),"") | H79: =IFERROR((F79+G79)/2,0) | I79: =IF(OR(F79="",G79=""),"",IF(AND(F79>=80,G79>=80),"Étoile",IF(AND(F79>=80,G79<80),"Problème de perf.",IF(AND(F79<80,G79>=80),"Travailleur fiable","Sous-performeur"))))
B80: =IFERROR(VLOOKUP(A80,'F01 - _Données Centrales'!A6:B20,2,FALSE),"") | C80: =IFERROR(VLOOKUP(A80,'F01 - _Données Centrales'!A6:C20,3,FALSE),"") | H80: =IFERROR((F80+G80)/2,0) | I80: =IF(OR(F80="",G80=""),"",IF(AND(F80>=80,G80>=80),"Étoile",IF(AND(F80>=80,G80<80),"Problème de perf.",IF(AND(F80<80,G80>=80),"Travailleur fiable","Sous-performeur"))))
B81: =IFERROR(VLOOKUP(A81,'F01 - _Données Centrales'!A6:B20,2,FALSE),"") | C81: =IFERROR(VLOOKUP(A81,'F01 - _Données Centrales'!A6:C20,3,FALSE),"") | H81: =IFERROR((F81+G81)/2,0) | I81: =IF(OR(F81="",G81=""),"",IF(AND(F81>=80,G81>=80),"Étoile",IF(AND(F81>=80,G81<80),"Problème de perf.",IF(AND(F81<80,G81>=80),"Travailleur fiable","Sous-performeur"))))
B82: =IFERROR(VLOOKUP(A82,'F01 - _Données Centrales'!A6:B20,2,FALSE),"") | C82: =IFERROR(VLOOKUP(A82,'F01 - _Données Centrales'!A6:C20,3,FALSE),"") | H82: =IFERROR((F82+G82)/2,0) | I82: =IF(OR(F82="",G82=""),"",IF(AND(F82>=80,G82>=80),"Étoile",IF(AND(F82>=80,G82<80),"Problème de perf.",IF(AND(F82<80,G82>=80),"Travailleur fiable","Sous-performeur"))))
B83: =IFERROR(VLOOKUP(A83,'F01 - _Données Centrales'!A6:B20,2,FALSE),"") | C83: =IFERROR(VLOOKUP(A83,'F01 - _Données Centrales'!A6:C20,3,FALSE),"") | H83: =IFERROR((F83+G83)/2,0) | I83: =IF(OR(F83="",G83=""),"",IF(AND(F83>=80,G83>=80),"Étoile",IF(AND(F83>=80,G83<80),"Problème de perf.",IF(AND(F83<80,G83>=80),"Travailleur fiable","Sous-performeur"))))
B84: =IFERROR(VLOOKUP(A84,'F01 - _Données Centrales'!A6:B20,2,FALSE),"") | C84: =IFERROR(VLOOKUP(A84,'F01 - _Données Centrales'!A6:C20,3,FALSE),"") | H84: =IFERROR((F84+G84)/2,0) | I84: =IF(OR(F84="",G84=""),"",IF(AND(F84>=80,G84>=80),"Étoile",IF(AND(F84>=80,G84<80),"Problème de perf.",IF(AND(F84<80,G84>=80),"Travailleur fiable","Sous-performeur"))))
B85: =IFERROR(VLOOKUP(A85,'F01 - _Données Centrales'!A6:B20,2,FALSE),"") | C85: =IFERROR(VLOOKUP(A85,'F01 - _Données Centrales'!A6:C20,3,FALSE),"") | H85: =IFERROR((F85+G85)/2,0) | I85: =IF(OR(F85="",G85=""),"",IF(AND(F85>=80,G85>=80),"Étoile",IF(AND(F85>=80,G85<80),"Problème de perf.",IF(AND(F85<80,G85>=80),"Travailleur fiable","Sous-performeur"))))
B86: =IFERROR(VLOOKUP(A86,'F01 - _Données Centrales'!A6:B20,2,FALSE),"") | C86: =IFERROR(VLOOKUP(A86,'F01 - _Données Centrales'!A6:C20,3,FALSE),"") | H86: =IFERROR((F86+G86)/2,0) | I86: =IF(OR(F86="",G86=""),"",IF(AND(F86>=80,G86>=80),"Étoile",IF(AND(F86>=80,G86<80),"Problème de perf.",IF(AND(F86<80,G86>=80),"Travailleur fiable","Sous-performeur"))))
B87: =IFERROR(VLOOKUP(A87,'F01 - _Données Centrales'!A6:B20,2,FALSE),"") | C87: =IFERROR(VLOOKUP(A87,'F01 - _Données Centrales'!A6:C20,3,FALSE),"") | H87: =IFERROR((F87+G87)/2,0) | I87: =IF(OR(F87="",G87=""),"",IF(AND(F87>=80,G87>=80),"Étoile",IF(AND(F87>=80,G87<80),"Problème de perf.",IF(AND(F87<80,G87>=80),"Travailleur fiable","Sous-performeur"))))
B88: =IFERROR(VLOOKUP(A88,'F01 - _Données Centrales'!A6:B20,2,FALSE),"") | C88: =IFERROR(VLOOKUP(A88,'F01 - _Données Centrales'!A6:C20,3,FALSE),"") | H88: =IFERROR((F88+G88)/2,0) | I88: =IF(OR(F88="",G88=""),"",IF(AND(F88>=80,G88>=80),"Étoile",IF(AND(F88>=80,G88<80),"Problème de perf.",IF(AND(F88<80,G88>=80),"Travailleur fiable","Sous-performeur"))))
B89: =IFERROR(VLOOKUP(A89,'F01 - _Données Centrales'!A6:B20,2,FALSE),"") | C89: =IFERROR(VLOOKUP(A89,'F01 - _Données Centrales'!A6:C20,3,FALSE),"") | H89: =IFERROR((F89+G89)/2,0) | I89: =IF(OR(F89="",G89=""),"",IF(AND(F89>=80,G89>=80),"Étoile",IF(AND(F89>=80,G89<80),"Problème de perf.",IF(AND(F89<80,G89>=80),"Travailleur fiable","Sous-performeur"))))
B90: =IFERROR(VLOOKUP(A90,'F01 - _Données Centrales'!A6:B20,2,FALSE),"") | C90: =IFERROR(VLOOKUP(A90,'F01 - _Données Centrales'!A6:C20,3,FALSE),"") | H90: =IFERROR((F90+G90)/2,0) | I90: =IF(OR(F90="",G90=""),"",IF(AND(F90>=80,G90>=80),"Étoile",IF(AND(F90>=80,G90<80),"Problème de perf.",IF(AND(F90<80,G90>=80),"Travailleur fiable","Sous-performeur"))))
B91: =IFERROR(VLOOKUP(A91,'F01 - _Données Centrales'!A6:B20,2,FALSE),"") | C91: =IFERROR(VLOOKUP(A91,'F01 - _Données Centrales'!A6:C20,3,FALSE),"") | H91: =IFERROR((F91+G91)/2,0) | I91: =IF(OR(F91="",G91=""),"",IF(AND(F91>=80,G91>=80),"Étoile",IF(AND(F91>=80,G91<80),"Problème de perf.",IF(AND(F91<80,G91>=80),"Travailleur fiable","Sous-performeur"))))
B92: =IFERROR(VLOOKUP(A92,'F01 - _Données Centrales'!A6:B20,2,FALSE),"") | C92: =IFERROR(VLOOKUP(A92,'F01 - _Données Centrales'!A6:C20,3,FALSE),"") | H92: =IFERROR((F92+G92)/2,0) | I92: =IF(OR(F92="",G92=""),"",IF(AND(F92>=80,G92>=80),"Étoile",IF(AND(F92>=80,G92<80),"Problème de perf.",IF(AND(F92<80,G92>=80),"Travailleur fiable","Sous-performeur"))))
B93: =IFERROR(VLOOKUP(A93,'F01 - _Données Centrales'!A6:B20,2,FALSE),"") | C93: =IFERROR(VLOOKUP(A93,'F01 - _Données Centrales'!A6:C20,3,FALSE),"") | H93: =IFERROR((F93+G93)/2,0) | I93: =IF(OR(F93="",G93=""),"",IF(AND(F93>=80,G93>=80),"Étoile",IF(AND(F93>=80,G93<80),"Problème de perf.",IF(AND(F93<80,G93>=80),"Travailleur fiable","Sous-performeur"))))
B94: =IFERROR(VLOOKUP(A94,'F01 - _Données Centrales'!A6:B20,2,FALSE),"") | C94: =IFERROR(VLOOKUP(A94,'F01 - _Données Centrales'!A6:C20,3,FALSE),"") | H94: =IFERROR((F94+G94)/2,0) | I94: =IF(OR(F94="",G94=""),"",IF(AND(F94>=80,G94>=80),"Étoile",IF(AND(F94>=80,G94<80),"Problème de perf.",IF(AND(F94<80,G94>=80),"Travailleur fiable","Sous-performeur"))))
B95: =IFERROR(VLOOKUP(A95,'F01 - _Données Centrales'!A6:B20,2,FALSE),"") | C95: =IFERROR(VLOOKUP(A95,'F01 - _Données Centrales'!A6:C20,3,FALSE),"") | H95: =IFERROR((F95+G95)/2,0) | I95: =IF(OR(F95="",G95=""),"",IF(AND(F95>=80,G95>=80),"Étoile",IF(AND(F95>=80,G95<80),"Problème de perf.",IF(AND(F95<80,G95>=80),"Travailleur fiable","Sous-performeur"))))
B96: =IFERROR(VLOOKUP(A96,'F01 - _Données Centrales'!A6:B20,2,FALSE),"") | C96: =IFERROR(VLOOKUP(A96,'F01 - _Données Centrales'!A6:C20,3,FALSE),"") | H96: =IFERROR((F96+G96)/2,0) | I96: =IF(OR(F96="",G96=""),"",IF(AND(F96>=80,G96>=80),"Étoile",IF(AND(F96>=80,G96<80),"Problème de perf.",IF(AND(F96<80,G96>=80),"Travailleur fiable","Sous-performeur"))))
B97: =IFERROR(VLOOKUP(A97,'F01 - _Données Centrales'!A6:B20,2,FALSE),"") | C97: =IFERROR(VLOOKUP(A97,'F01 - _Données Centrales'!A6:C20,3,FALSE),"") | H97: =IFERROR((F97+G97)/2,0) | I97: =IF(OR(F97="",G97=""),"",IF(AND(F97>=80,G97>=80),"Étoile",IF(AND(F97>=80,G97<80),"Problème de perf.",IF(AND(F97<80,G97>=80),"Travailleur fiable","Sous-performeur"))))
B98: =IFERROR(VLOOKUP(A98,'F01 - _Données Centrales'!A6:B20,2,FALSE),"") | C98: =IFERROR(VLOOKUP(A98,'F01 - _Données Centrales'!A6:C20,3,FALSE),"") | H98: =IFERROR((F98+G98)/2,0) | I98: =IF(OR(F98="",G98=""),"",IF(AND(F98>=80,G98>=80),"Étoile",IF(AND(F98>=80,G98<80),"Problème de perf.",IF(AND(F98<80,G98>=80),"Travailleur fiable","Sous-performeur"))))
B99: =IFERROR(VLOOKUP(A99,'F01 - _Données Centrales'!A6:B20,2,FALSE),"") | C99: =IFERROR(VLOOKUP(A99,'F01 - _Données Centrales'!A6:C20,3,FALSE),"") | H99: =IFERROR((F99+G99)/2,0) | I99: =IF(OR(F99="",G99=""),"",IF(AND(F99>=80,G99>=80),"Étoile",IF(AND(F99>=80,G99<80),"Problème de perf.",IF(AND(F99<80,G99>=80),"Travailleur fiable","Sous-performeur"))))
B100: =IFERROR(VLOOKUP(A100,'F01 - _Données Centrales'!A6:B20,2,FALSE),"") | C100: =IFERROR(VLOOKUP(A100,'F01 - _Données Centrales'!A6:C20,3,FALSE),"") | H100: =IFERROR((F100+G100)/2,0) | I100: =IF(OR(F100="",G100=""),"",IF(AND(F100>=80,G100>=80),"Étoile",IF(AND(F100>=80,G100<80),"Problème de perf.",IF(AND(F100<80,G100>=80),"Travailleur fiable","Sous-performeur"))))
B101: =IFERROR(VLOOKUP(A101,'F01 - _Données Centrales'!A6:B20,2,FALSE),"") | C101: =IFERROR(VLOOKUP(A101,'F01 - _Données Centrales'!A6:C20,3,FALSE),"") | H101: =IFERROR((F101+G101)/2,0) | I101: =IF(OR(F101="",G101=""),"",IF(AND(F101>=80,G101>=80),"Étoile",IF(AND(F101>=80,G101<80),"Problème de perf.",IF(AND(F101<80,G101>=80),"Travailleur fiable","Sous-performeur"))))
B102: =IFERROR(VLOOKUP(A102,'F01 - _Données Centrales'!A6:B20,2,FALSE),"") | C102: =IFERROR(VLOOKUP(A102,'F01 - _Données Centrales'!A6:C20,3,FALSE),"") | H102: =IFERROR((F102+G102)/2,0) | I102: =IF(OR(F102="",G102=""),"",IF(AND(F102>=80,G102>=80),"Étoile",IF(AND(F102>=80,G102<80),"Problème de perf.",IF(AND(F102<80,G102>=80),"Travailleur fiable","Sous-performeur"))))
...

Sheet F08 - 6-Parcours de Carrière
A2: DOMAINE 28 — PARCOURS DE CARRIÈRE
A3: Historique et planification des trajectoires professionnelles
A5: Code Employé | B5: Nom | C5: Département | D5: Poste Entrée | E5: Date Entrée | F5: Poste Actuel | G5: Date Poste Actuel | H5: Nb Promotions | I5: Nb Mobilités | J5: Prochain Palier | K5: Date Cible | L5: Délai Restant (mois) | M5: Statut Parcours
A6: EMP-001 | B6: =IFERROR(VLOOKUP(A6,'F01 - _Données Centrales'!A6:B20,2,FALSE),"") | C6: =IFERROR(VLOOKUP(A6,'F01 - _Données Centrales'!A6:C20,3,FALSE),"") | D6: Chef de Dept. | E6: 2003-01-15 | F6: Directeur Général | G6: 2015-01-15 | H6: 4 | I6: 2 | J6: Conseil Surveillance | K6: 2027-01-01 | L6: =IF(K6="","",MAX(0,ROUND((DATEVALUE(K6)-TODAY())/30,0))) | M6: En progression
A7: EMP-002 | B7: =IFERROR(VLOOKUP(A7,'F01 - _Données Centrales'!A6:B20,2,FALSE),"") | C7: =IFERROR(VLOOKUP(A7,'F01 - _Données Centrales'!A6:C20,3,FALSE),"") | D7: Assistante RH | E7: 2010-06-01 | F7: DRH | G7: 2018-06-01 | H7: 3 | I7: 1 | J7: DG Adjoint | K7: 2026-01-01 | L7: =IF(K7="","",MAX(0,ROUND((DATEVALUE(K7)-TODAY())/30,0))) | M7: En progression
A8: EMP-007 | B8: =IFERROR(VLOOKUP(A8,'F01 - _Données Centrales'!A6:B20,2,FALSE),"") | C8: =IFERROR(VLOOKUP(A8,'F01 - _Données Centrales'!A6:C20,3,FALSE),"") | D8: Assistante RH | E8: 2019-01-10 | F8: Resp. Recrutement | G8: 2022-01-10 | H8: 1 | I8: 0 | J8: DRH | K8: 2026-06-01 | L8: =IF(K8="","",MAX(0,ROUND((DATEVALUE(K8)-TODAY())/30,0))) | M8: Accéléré
A9: EMP-005 | B9: =IFERROR(VLOOKUP(A9,'F01 - _Données Centrales'!A6:B20,2,FALSE),"") | C9: =IFERROR(VLOOKUP(A9,'F01 - _Données Centrales'!A6:C20,3,FALSE),"") | D9: Réceptionniste | E9: 2015-07-01 | F9: Resp. Réception | G9: 2020-07-01 | H9: 2 | I9: 0 | J9: DRH Adjoint | K9: 2027-07-01 | L9: =IF(K9="","",MAX(0,ROUND((DATEVALUE(K9)-TODAY())/30,0))) | M9: En progression
A10: EMP-004 | B10: =IFERROR(VLOOKUP(A10,'F01 - _Données Centrales'!A6:B20,2,FALSE),"") | C10: =IFERROR(VLOOKUP(A10,'F01 - _Données Centrales'!A6:C20,3,FALSE),"") | D10: Commis Cuisine | E10: 2017-03-10 | F10: Chef Cuisinier | G10: 2021-03-10 | H10: 2 | I10: 1 | J10: Resp. Rest. Hôtellerie | K10: 2026-03-01 | L10: =IF(K10="","",MAX(0,ROUND((DATEVALUE(K10)-TODAY())/30,0))) | M10: En attente
B11: =IFERROR(VLOOKUP(A11,'F01 - _Données Centrales'!A6:B20,2,FALSE),"") | C11: =IFERROR(VLOOKUP(A11,'F01 - _Données Centrales'!A6:C20,3,FALSE),"") | L11: =IF(K11="","",MAX(0,ROUND((DATEVALUE(K11)-TODAY())/30,0)))
B12: =IFERROR(VLOOKUP(A12,'F01 - _Données Centrales'!A6:B20,2,FALSE),"") | C12: =IFERROR(VLOOKUP(A12,'F01 - _Données Centrales'!A6:C20,3,FALSE),"") | L12: =IF(K12="","",MAX(0,ROUND((DATEVALUE(K12)-TODAY())/30,0)))
B13: =IFERROR(VLOOKUP(A13,'F01 - _Données Centrales'!A6:B20,2,FALSE),"") | C13: =IFERROR(VLOOKUP(A13,'F01 - _Données Centrales'!A6:C20,3,FALSE),"") | L13: =IF(K13="","",MAX(0,ROUND((DATEVALUE(K13)-TODAY())/30,0)))
B14: =IFERROR(VLOOKUP(A14,'F01 - _Données Centrales'!A6:B20,2,FALSE),"") | C14: =IFERROR(VLOOKUP(A14,'F01 - _Données Centrales'!A6:C20,3,FALSE),"") | L14: =IF(K14="","",MAX(0,ROUND((DATEVALUE(K14)-TODAY())/30,0)))
B15: =IFERROR(VLOOKUP(A15,'F01 - _Données Centrales'!A6:B20,2,FALSE),"") | C15: =IFERROR(VLOOKUP(A15,'F01 - _Données Centrales'!A6:C20,3,FALSE),"") | L15: =IF(K15="","",MAX(0,ROUND((DATEVALUE(K15)-TODAY())/30,0)))
B16: =IFERROR(VLOOKUP(A16,'F01 - _Données Centrales'!A6:B20,2,FALSE),"") | C16: =IFERROR(VLOOKUP(A16,'F01 - _Données Centrales'!A6:C20,3,FALSE),"") | L16: =IF(K16="","",MAX(0,ROUND((DATEVALUE(K16)-TODAY())/30,0)))
B17: =IFERROR(VLOOKUP(A17,'F01 - _Données Centrales'!A6:B20,2,FALSE),"") | C17: =IFERROR(VLOOKUP(A17,'F01 - _Données Centrales'!A6:C20,3,FALSE),"") | L17: =IF(K17="","",MAX(0,ROUND((DATEVALUE(K17)-TODAY())/30,0)))
B18: =IFERROR(VLOOKUP(A18,'F01 - _Données Centrales'!A6:B20,2,FALSE),"") | C18: =IFERROR(VLOOKUP(A18,'F01 - _Données Centrales'!A6:C20,3,FALSE),"") | L18: =IF(K18="","",MAX(0,ROUND((DATEVALUE(K18)-TODAY())/30,0)))
B19: =IFERROR(VLOOKUP(A19,'F01 - _Données Centrales'!A6:B20,2,FALSE),"") | C19: =IFERROR(VLOOKUP(A19,'F01 - _Données Centrales'!A6:C20,3,FALSE),"") | L19: =IF(K19="","",MAX(0,ROUND((DATEVALUE(K19)-TODAY())/30,0)))
B20: =IFERROR(VLOOKUP(A20,'F01 - _Données Centrales'!A6:B20,2,FALSE),"") | C20: =IFERROR(VLOOKUP(A20,'F01 - _Données Centrales'!A6:C20,3,FALSE),"") | L20: =IF(K20="","",MAX(0,ROUND((DATEVALUE(K20)-TODAY())/30,0)))
B21: =IFERROR(VLOOKUP(A21,'F01 - _Données Centrales'!A6:B20,2,FALSE),"") | C21: =IFERROR(VLOOKUP(A21,'F01 - _Données Centrales'!A6:C20,3,FALSE),"") | L21: =IF(K21="","",MAX(0,ROUND((DATEVALUE(K21)-TODAY())/30,0)))
B22: =IFERROR(VLOOKUP(A22,'F01 - _Données Centrales'!A6:B20,2,FALSE),"") | C22: =IFERROR(VLOOKUP(A22,'F01 - _Données Centrales'!A6:C20,3,FALSE),"") | L22: =IF(K22="","",MAX(0,ROUND((DATEVALUE(K22)-TODAY())/30,0)))
B23: =IFERROR(VLOOKUP(A23,'F01 - _Données Centrales'!A6:B20,2,FALSE),"") | C23: =IFERROR(VLOOKUP(A23,'F01 - _Données Centrales'!A6:C20,3,FALSE),"") | L23: =IF(K23="","",MAX(0,ROUND((DATEVALUE(K23)-TODAY())/30,0)))
B24: =IFERROR(VLOOKUP(A24,'F01 - _Données Centrales'!A6:B20,2,FALSE),"") | C24: =IFERROR(VLOOKUP(A24,'F01 - _Données Centrales'!A6:C20,3,FALSE),"") | L24: =IF(K24="","",MAX(0,ROUND((DATEVALUE(K24)-TODAY())/30,0)))
B25: =IFERROR(VLOOKUP(A25,'F01 - _Données Centrales'!A6:B20,2,FALSE),"") | C25: =IFERROR(VLOOKUP(A25,'F01 - _Données Centrales'!A6:C20,3,FALSE),"") | L25: =IF(K25="","",MAX(0,ROUND((DATEVALUE(K25)-TODAY())/30,0)))
B26: =IFERROR(VLOOKUP(A26,'F01 - _Données Centrales'!A6:B20,2,FALSE),"") | C26: =IFERROR(VLOOKUP(A26,'F01 - _Données Centrales'!A6:C20,3,FALSE),"") | L26: =IF(K26="","",MAX(0,ROUND((DATEVALUE(K26)-TODAY())/30,0)))
B27: =IFERROR(VLOOKUP(A27,'F01 - _Données Centrales'!A6:B20,2,FALSE),"") | C27: =IFERROR(VLOOKUP(A27,'F01 - _Données Centrales'!A6:C20,3,FALSE),"") | L27: =IF(K27="","",MAX(0,ROUND((DATEVALUE(K27)-TODAY())/30,0)))
B28: =IFERROR(VLOOKUP(A28,'F01 - _Données Centrales'!A6:B20,2,FALSE),"") | C28: =IFERROR(VLOOKUP(A28,'F01 - _Données Centrales'!A6:C20,3,FALSE),"") | L28: =IF(K28="","",MAX(0,ROUND((DATEVALUE(K28)-TODAY())/30,0)))
B29: =IFERROR(VLOOKUP(A29,'F01 - _Données Centrales'!A6:B20,2,FALSE),"") | C29: =IFERROR(VLOOKUP(A29,'F01 - _Données Centrales'!A6:C20,3,FALSE),"") | L29: =IF(K29="","",MAX(0,ROUND((DATEVALUE(K29)-TODAY())/30,0)))
B30: =IFERROR(VLOOKUP(A30,'F01 - _Données Centrales'!A6:B20,2,FALSE),"") | C30: =IFERROR(VLOOKUP(A30,'F01 - _Données Centrales'!A6:C20,3,FALSE),"") | L30: =IF(K30="","",MAX(0,ROUND((DATEVALUE(K30)-TODAY())/30,0)))
B31: =IFERROR(VLOOKUP(A31,'F01 - _Données Centrales'!A6:B20,2,FALSE),"") | C31: =IFERROR(VLOOKUP(A31,'F01 - _Données Centrales'!A6:C20,3,FALSE),"") | L31: =IF(K31="","",MAX(0,ROUND((DATEVALUE(K31)-TODAY())/30,0)))
B32: =IFERROR(VLOOKUP(A32,'F01 - _Données Centrales'!A6:B20,2,FALSE),"") | C32: =IFERROR(VLOOKUP(A32,'F01 - _Données Centrales'!A6:C20,3,FALSE),"") | L32: =IF(K32="","",MAX(0,ROUND((DATEVALUE(K32)-TODAY())/30,0)))
B33: =IFERROR(VLOOKUP(A33,'F01 - _Données Centrales'!A6:B20,2,FALSE),"") | C33: =IFERROR(VLOOKUP(A33,'F01 - _Données Centrales'!A6:C20,3,FALSE),"") | L33: =IF(K33="","",MAX(0,ROUND((DATEVALUE(K33)-TODAY())/30,0)))
B34: =IFERROR(VLOOKUP(A34,'F01 - _Données Centrales'!A6:B20,2,FALSE),"") | C34: =IFERROR(VLOOKUP(A34,'F01 - _Données Centrales'!A6:C20,3,FALSE),"") | L34: =IF(K34="","",MAX(0,ROUND((DATEVALUE(K34)-TODAY())/30,0)))
B35: =IFERROR(VLOOKUP(A35,'F01 - _Données Centrales'!A6:B20,2,FALSE),"") | C35: =IFERROR(VLOOKUP(A35,'F01 - _Données Centrales'!A6:C20,3,FALSE),"") | L35: =IF(K35="","",MAX(0,ROUND((DATEVALUE(K35)-TODAY())/30,0)))
B36: =IFERROR(VLOOKUP(A36,'F01 - _Données Centrales'!A6:B20,2,FALSE),"") | C36: =IFERROR(VLOOKUP(A36,'F01 - _Données Centrales'!A6:C20,3,FALSE),"") | L36: =IF(K36="","",MAX(0,ROUND((DATEVALUE(K36)-TODAY())/30,0)))
B37: =IFERROR(VLOOKUP(A37,'F01 - _Données Centrales'!A6:B20,2,FALSE),"") | C37: =IFERROR(VLOOKUP(A37,'F01 - _Données Centrales'!A6:C20,3,FALSE),"") | L37: =IF(K37="","",MAX(0,ROUND((DATEVALUE(K37)-TODAY())/30,0)))
B38: =IFERROR(VLOOKUP(A38,'F01 - _Données Centrales'!A6:B20,2,FALSE),"") | C38: =IFERROR(VLOOKUP(A38,'F01 - _Données Centrales'!A6:C20,3,FALSE),"") | L38: =IF(K38="","",MAX(0,ROUND((DATEVALUE(K38)-TODAY())/30,0)))
B39: =IFERROR(VLOOKUP(A39,'F01 - _Données Centrales'!A6:B20,2,FALSE),"") | C39: =IFERROR(VLOOKUP(A39,'F01 - _Données Centrales'!A6:C20,3,FALSE),"") | L39: =IF(K39="","",MAX(0,ROUND((DATEVALUE(K39)-TODAY())/30,0)))
B40: =IFERROR(VLOOKUP(A40,'F01 - _Données Centrales'!A6:B20,2,FALSE),"") | C40: =IFERROR(VLOOKUP(A40,'F01 - _Données Centrales'!A6:C20,3,FALSE),"") | L40: =IF(K40="","",MAX(0,ROUND((DATEVALUE(K40)-TODAY())/30,0)))
B41: =IFERROR(VLOOKUP(A41,'F01 - _Données Centrales'!A6:B20,2,FALSE),"") | C41: =IFERROR(VLOOKUP(A41,'F01 - _Données Centrales'!A6:C20,3,FALSE),"") | L41: =IF(K41="","",MAX(0,ROUND((DATEVALUE(K41)-TODAY())/30,0)))
B42: =IFERROR(VLOOKUP(A42,'F01 - _Données Centrales'!A6:B20,2,FALSE),"") | C42: =IFERROR(VLOOKUP(A42,'F01 - _Données Centrales'!A6:C20,3,FALSE),"") | L42: =IF(K42="","",MAX(0,ROUND((DATEVALUE(K42)-TODAY())/30,0)))
B43: =IFERROR(VLOOKUP(A43,'F01 - _Données Centrales'!A6:B20,2,FALSE),"") | C43: =IFERROR(VLOOKUP(A43,'F01 - _Données Centrales'!A6:C20,3,FALSE),"") | L43: =IF(K43="","",MAX(0,ROUND((DATEVALUE(K43)-TODAY())/30,0)))
B44: =IFERROR(VLOOKUP(A44,'F01 - _Données Centrales'!A6:B20,2,FALSE),"") | C44: =IFERROR(VLOOKUP(A44,'F01 - _Données Centrales'!A6:C20,3,FALSE),"") | L44: =IF(K44="","",MAX(0,ROUND((DATEVALUE(K44)-TODAY())/30,0)))
B45: =IFERROR(VLOOKUP(A45,'F01 - _Données Centrales'!A6:B20,2,FALSE),"") | C45: =IFERROR(VLOOKUP(A45,'F01 - _Données Centrales'!A6:C20,3,FALSE),"") | L45: =IF(K45="","",MAX(0,ROUND((DATEVALUE(K45)-TODAY())/30,0)))
B46: =IFERROR(VLOOKUP(A46,'F01 - _Données Centrales'!A6:B20,2,FALSE),"") | C46: =IFERROR(VLOOKUP(A46,'F01 - _Données Centrales'!A6:C20,3,FALSE),"") | L46: =IF(K46="","",MAX(0,ROUND((DATEVALUE(K46)-TODAY())/30,0)))
B47: =IFERROR(VLOOKUP(A47,'F01 - _Données Centrales'!A6:B20,2,FALSE),"") | C47: =IFERROR(VLOOKUP(A47,'F01 - _Données Centrales'!A6:C20,3,FALSE),"") | L47: =IF(K47="","",MAX(0,ROUND((DATEVALUE(K47)-TODAY())/30,0)))
B48: =IFERROR(VLOOKUP(A48,'F01 - _Données Centrales'!A6:B20,2,FALSE),"") | C48: =IFERROR(VLOOKUP(A48,'F01 - _Données Centrales'!A6:C20,3,FALSE),"") | L48: =IF(K48="","",MAX(0,ROUND((DATEVALUE(K48)-TODAY())/30,0)))
B49: =IFERROR(VLOOKUP(A49,'F01 - _Données Centrales'!A6:B20,2,FALSE),"") | C49: =IFERROR(VLOOKUP(A49,'F01 - _Données Centrales'!A6:C20,3,FALSE),"") | L49: =IF(K49="","",MAX(0,ROUND((DATEVALUE(K49)-TODAY())/30,0)))
B50: =IFERROR(VLOOKUP(A50,'F01 - _Données Centrales'!A6:B20,2,FALSE),"") | C50: =IFERROR(VLOOKUP(A50,'F01 - _Données Centrales'!A6:C20,3,FALSE),"") | L50: =IF(K50="","",MAX(0,ROUND((DATEVALUE(K50)-TODAY())/30,0)))
B51: =IFERROR(VLOOKUP(A51,'F01 - _Données Centrales'!A6:B20,2,FALSE),"") | C51: =IFERROR(VLOOKUP(A51,'F01 - _Données Centrales'!A6:C20,3,FALSE),"") | L51: =IF(K51="","",MAX(0,ROUND((DATEVALUE(K51)-TODAY())/30,0)))
B52: =IFERROR(VLOOKUP(A52,'F01 - _Données Centrales'!A6:B20,2,FALSE),"") | C52: =IFERROR(VLOOKUP(A52,'F01 - _Données Centrales'!A6:C20,3,FALSE),"") | L52: =IF(K52="","",MAX(0,ROUND((DATEVALUE(K52)-TODAY())/30,0)))
B53: =IFERROR(VLOOKUP(A53,'F01 - _Données Centrales'!A6:B20,2,FALSE),"") | C53: =IFERROR(VLOOKUP(A53,'F01 - _Données Centrales'!A6:C20,3,FALSE),"") | L53: =IF(K53="","",MAX(0,ROUND((DATEVALUE(K53)-TODAY())/30,0)))
B54: =IFERROR(VLOOKUP(A54,'F01 - _Données Centrales'!A6:B20,2,FALSE),"") | C54: =IFERROR(VLOOKUP(A54,'F01 - _Données Centrales'!A6:C20,3,FALSE),"") | L54: =IF(K54="","",MAX(0,ROUND((DATEVALUE(K54)-TODAY())/30,0)))
B55: =IFERROR(VLOOKUP(A55,'F01 - _Données Centrales'!A6:B20,2,FALSE),"") | C55: =IFERROR(VLOOKUP(A55,'F01 - _Données Centrales'!A6:C20,3,FALSE),"") | L55: =IF(K55="","",MAX(0,ROUND((DATEVALUE(K55)-TODAY())/30,0)))
B56: =IFERROR(VLOOKUP(A56,'F01 - _Données Centrales'!A6:B20,2,FALSE),"") | C56: =IFERROR(VLOOKUP(A56,'F01 - _Données Centrales'!A6:C20,3,FALSE),"") | L56: =IF(K56="","",MAX(0,ROUND((DATEVALUE(K56)-TODAY())/30,0)))
B57: =IFERROR(VLOOKUP(A57,'F01 - _Données Centrales'!A6:B20,2,FALSE),"") | C57: =IFERROR(VLOOKUP(A57,'F01 - _Données Centrales'!A6:C20,3,FALSE),"") | L57: =IF(K57="","",MAX(0,ROUND((DATEVALUE(K57)-TODAY())/30,0)))
B58: =IFERROR(VLOOKUP(A58,'F01 - _Données Centrales'!A6:B20,2,FALSE),"") | C58: =IFERROR(VLOOKUP(A58,'F01 - _Données Centrales'!A6:C20,3,FALSE),"") | L58: =IF(K58="","",MAX(0,ROUND((DATEVALUE(K58)-TODAY())/30,0)))
B59: =IFERROR(VLOOKUP(A59,'F01 - _Données Centrales'!A6:B20,2,FALSE),"") | C59: =IFERROR(VLOOKUP(A59,'F01 - _Données Centrales'!A6:C20,3,FALSE),"") | L59: =IF(K59="","",MAX(0,ROUND((DATEVALUE(K59)-TODAY())/30,0)))
B60: =IFERROR(VLOOKUP(A60,'F01 - _Données Centrales'!A6:B20,2,FALSE),"") | C60: =IFERROR(VLOOKUP(A60,'F01 - _Données Centrales'!A6:C20,3,FALSE),"") | L60: =IF(K60="","",MAX(0,ROUND((DATEVALUE(K60)-TODAY())/30,0)))
B61: =IFERROR(VLOOKUP(A61,'F01 - _Données Centrales'!A6:B20,2,FALSE),"") | C61: =IFERROR(VLOOKUP(A61,'F01 - _Données Centrales'!A6:C20,3,FALSE),"") | L61: =IF(K61="","",MAX(0,ROUND((DATEVALUE(K61)-TODAY())/30,0)))
B62: =IFERROR(VLOOKUP(A62,'F01 - _Données Centrales'!A6:B20,2,FALSE),"") | C62: =IFERROR(VLOOKUP(A62,'F01 - _Données Centrales'!A6:C20,3,FALSE),"") | L62: =IF(K62="","",MAX(0,ROUND((DATEVALUE(K62)-TODAY())/30,0)))
B63: =IFERROR(VLOOKUP(A63,'F01 - _Données Centrales'!A6:B20,2,FALSE),"") | C63: =IFERROR(VLOOKUP(A63,'F01 - _Données Centrales'!A6:C20,3,FALSE),"") | L63: =IF(K63="","",MAX(0,ROUND((DATEVALUE(K63)-TODAY())/30,0)))
B64: =IFERROR(VLOOKUP(A64,'F01 - _Données Centrales'!A6:B20,2,FALSE),"") | C64: =IFERROR(VLOOKUP(A64,'F01 - _Données Centrales'!A6:C20,3,FALSE),"") | L64: =IF(K64="","",MAX(0,ROUND((DATEVALUE(K64)-TODAY())/30,0)))
B65: =IFERROR(VLOOKUP(A65,'F01 - _Données Centrales'!A6:B20,2,FALSE),"") | C65: =IFERROR(VLOOKUP(A65,'F01 - _Données Centrales'!A6:C20,3,FALSE),"") | L65: =IF(K65="","",MAX(0,ROUND((DATEVALUE(K65)-TODAY())/30,0)))
B66: =IFERROR(VLOOKUP(A66,'F01 - _Données Centrales'!A6:B20,2,FALSE),"") | C66: =IFERROR(VLOOKUP(A66,'F01 - _Données Centrales'!A6:C20,3,FALSE),"") | L66: =IF(K66="","",MAX(0,ROUND((DATEVALUE(K66)-TODAY())/30,0)))
B67: =IFERROR(VLOOKUP(A67,'F01 - _Données Centrales'!A6:B20,2,FALSE),"") | C67: =IFERROR(VLOOKUP(A67,'F01 - _Données Centrales'!A6:C20,3,FALSE),"") | L67: =IF(K67="","",MAX(0,ROUND((DATEVALUE(K67)-TODAY())/30,0)))
B68: =IFERROR(VLOOKUP(A68,'F01 - _Données Centrales'!A6:B20,2,FALSE),"") | C68: =IFERROR(VLOOKUP(A68,'F01 - _Données Centrales'!A6:C20,3,FALSE),"") | L68: =IF(K68="","",MAX(0,ROUND((DATEVALUE(K68)-TODAY())/30,0)))
B69: =IFERROR(VLOOKUP(A69,'F01 - _Données Centrales'!A6:B20,2,FALSE),"") | C69: =IFERROR(VLOOKUP(A69,'F01 - _Données Centrales'!A6:C20,3,FALSE),"") | L69: =IF(K69="","",MAX(0,ROUND((DATEVALUE(K69)-TODAY())/30,0)))
B70: =IFERROR(VLOOKUP(A70,'F01 - _Données Centrales'!A6:B20,2,FALSE),"") | C70: =IFERROR(VLOOKUP(A70,'F01 - _Données Centrales'!A6:C20,3,FALSE),"") | L70: =IF(K70="","",MAX(0,ROUND((DATEVALUE(K70)-TODAY())/30,0)))
B71: =IFERROR(VLOOKUP(A71,'F01 - _Données Centrales'!A6:B20,2,FALSE),"") | C71: =IFERROR(VLOOKUP(A71,'F01 - _Données Centrales'!A6:C20,3,FALSE),"") | L71: =IF(K71="","",MAX(0,ROUND((DATEVALUE(K71)-TODAY())/30,0)))
B72: =IFERROR(VLOOKUP(A72,'F01 - _Données Centrales'!A6:B20,2,FALSE),"") | C72: =IFERROR(VLOOKUP(A72,'F01 - _Données Centrales'!A6:C20,3,FALSE),"") | L72: =IF(K72="","",MAX(0,ROUND((DATEVALUE(K72)-TODAY())/30,0)))
B73: =IFERROR(VLOOKUP(A73,'F01 - _Données Centrales'!A6:B20,2,FALSE),"") | C73: =IFERROR(VLOOKUP(A73,'F01 - _Données Centrales'!A6:C20,3,FALSE),"") | L73: =IF(K73="","",MAX(0,ROUND((DATEVALUE(K73)-TODAY())/30,0)))
B74: =IFERROR(VLOOKUP(A74,'F01 - _Données Centrales'!A6:B20,2,FALSE),"") | C74: =IFERROR(VLOOKUP(A74,'F01 - _Données Centrales'!A6:C20,3,FALSE),"") | L74: =IF(K74="","",MAX(0,ROUND((DATEVALUE(K74)-TODAY())/30,0)))
B75: =IFERROR(VLOOKUP(A75,'F01 - _Données Centrales'!A6:B20,2,FALSE),"") | C75: =IFERROR(VLOOKUP(A75,'F01 - _Données Centrales'!A6:C20,3,FALSE),"") | L75: =IF(K75="","",MAX(0,ROUND((DATEVALUE(K75)-TODAY())/30,0)))
B76: =IFERROR(VLOOKUP(A76,'F01 - _Données Centrales'!A6:B20,2,FALSE),"") | C76: =IFERROR(VLOOKUP(A76,'F01 - _Données Centrales'!A6:C20,3,FALSE),"") | L76: =IF(K76="","",MAX(0,ROUND((DATEVALUE(K76)-TODAY())/30,0)))
B77: =IFERROR(VLOOKUP(A77,'F01 - _Données Centrales'!A6:B20,2,FALSE),"") | C77: =IFERROR(VLOOKUP(A77,'F01 - _Données Centrales'!A6:C20,3,FALSE),"") | L77: =IF(K77="","",MAX(0,ROUND((DATEVALUE(K77)-TODAY())/30,0)))
B78: =IFERROR(VLOOKUP(A78,'F01 - _Données Centrales'!A6:B20,2,FALSE),"") | C78: =IFERROR(VLOOKUP(A78,'F01 - _Données Centrales'!A6:C20,3,FALSE),"") | L78: =IF(K78="","",MAX(0,ROUND((DATEVALUE(K78)-TODAY())/30,0)))
B79: =IFERROR(VLOOKUP(A79,'F01 - _Données Centrales'!A6:B20,2,FALSE),"") | C79: =IFERROR(VLOOKUP(A79,'F01 - _Données Centrales'!A6:C20,3,FALSE),"") | L79: =IF(K79="","",MAX(0,ROUND((DATEVALUE(K79)-TODAY())/30,0)))
B80: =IFERROR(VLOOKUP(A80,'F01 - _Données Centrales'!A6:B20,2,FALSE),"") | C80: =IFERROR(VLOOKUP(A80,'F01 - _Données Centrales'!A6:C20,3,FALSE),"") | L80: =IF(K80="","",MAX(0,ROUND((DATEVALUE(K80)-TODAY())/30,0)))
B81: =IFERROR(VLOOKUP(A81,'F01 - _Données Centrales'!A6:B20,2,FALSE),"") | C81: =IFERROR(VLOOKUP(A81,'F01 - _Données Centrales'!A6:C20,3,FALSE),"") | L81: =IF(K81="","",MAX(0,ROUND((DATEVALUE(K81)-TODAY())/30,0)))
B82: =IFERROR(VLOOKUP(A82,'F01 - _Données Centrales'!A6:B20,2,FALSE),"") | C82: =IFERROR(VLOOKUP(A82,'F01 - _Données Centrales'!A6:C20,3,FALSE),"") | L82: =IF(K82="","",MAX(0,ROUND((DATEVALUE(K82)-TODAY())/30,0)))
B83: =IFERROR(VLOOKUP(A83,'F01 - _Données Centrales'!A6:B20,2,FALSE),"") | C83: =IFERROR(VLOOKUP(A83,'F01 - _Données Centrales'!A6:C20,3,FALSE),"") | L83: =IF(K83="","",MAX(0,ROUND((DATEVALUE(K83)-TODAY())/30,0)))
B84: =IFERROR(VLOOKUP(A84,'F01 - _Données Centrales'!A6:B20,2,FALSE),"") | C84: =IFERROR(VLOOKUP(A84,'F01 - _Données Centrales'!A6:C20,3,FALSE),"") | L84: =IF(K84="","",MAX(0,ROUND((DATEVALUE(K84)-TODAY())/30,0)))
B85: =IFERROR(VLOOKUP(A85,'F01 - _Données Centrales'!A6:B20,2,FALSE),"") | C85: =IFERROR(VLOOKUP(A85,'F01 - _Données Centrales'!A6:C20,3,FALSE),"") | L85: =IF(K85="","",MAX(0,ROUND((DATEVALUE(K85)-TODAY())/30,0)))
B86: =IFERROR(VLOOKUP(A86,'F01 - _Données Centrales'!A6:B20,2,FALSE),"") | C86: =IFERROR(VLOOKUP(A86,'F01 - _Données Centrales'!A6:C20,3,FALSE),"") | L86: =IF(K86="","",MAX(0,ROUND((DATEVALUE(K86)-TODAY())/30,0)))
B87: =IFERROR(VLOOKUP(A87,'F01 - _Données Centrales'!A6:B20,2,FALSE),"") | C87: =IFERROR(VLOOKUP(A87,'F01 - _Données Centrales'!A6:C20,3,FALSE),"") | L87: =IF(K87="","",MAX(0,ROUND((DATEVALUE(K87)-TODAY())/30,0)))
B88: =IFERROR(VLOOKUP(A88,'F01 - _Données Centrales'!A6:B20,2,FALSE),"") | C88: =IFERROR(VLOOKUP(A88,'F01 - _Données Centrales'!A6:C20,3,FALSE),"") | L88: =IF(K88="","",MAX(0,ROUND((DATEVALUE(K88)-TODAY())/30,0)))
B89: =IFERROR(VLOOKUP(A89,'F01 - _Données Centrales'!A6:B20,2,FALSE),"") | C89: =IFERROR(VLOOKUP(A89,'F01 - _Données Centrales'!A6:C20,3,FALSE),"") | L89: =IF(K89="","",MAX(0,ROUND((DATEVALUE(K89)-TODAY())/30,0)))
B90: =IFERROR(VLOOKUP(A90,'F01 - _Données Centrales'!A6:B20,2,FALSE),"") | C90: =IFERROR(VLOOKUP(A90,'F01 - _Données Centrales'!A6:C20,3,FALSE),"") | L90: =IF(K90="","",MAX(0,ROUND((DATEVALUE(K90)-TODAY())/30,0)))
B91: =IFERROR(VLOOKUP(A91,'F01 - _Données Centrales'!A6:B20,2,FALSE),"") | C91: =IFERROR(VLOOKUP(A91,'F01 - _Données Centrales'!A6:C20,3,FALSE),"") | L91: =IF(K91="","",MAX(0,ROUND((DATEVALUE(K91)-TODAY())/30,0)))
B92: =IFERROR(VLOOKUP(A92,'F01 - _Données Centrales'!A6:B20,2,FALSE),"") | C92: =IFERROR(VLOOKUP(A92,'F01 - _Données Centrales'!A6:C20,3,FALSE),"") | L92: =IF(K92="","",MAX(0,ROUND((DATEVALUE(K92)-TODAY())/30,0)))
B93: =IFERROR(VLOOKUP(A93,'F01 - _Données Centrales'!A6:B20,2,FALSE),"") | C93: =IFERROR(VLOOKUP(A93,'F01 - _Données Centrales'!A6:C20,3,FALSE),"") | L93: =IF(K93="","",MAX(0,ROUND((DATEVALUE(K93)-TODAY())/30,0)))
B94: =IFERROR(VLOOKUP(A94,'F01 - _Données Centrales'!A6:B20,2,FALSE),"") | C94: =IFERROR(VLOOKUP(A94,'F01 - _Données Centrales'!A6:C20,3,FALSE),"") | L94: =IF(K94="","",MAX(0,ROUND((DATEVALUE(K94)-TODAY())/30,0)))
B95: =IFERROR(VLOOKUP(A95,'F01 - _Données Centrales'!A6:B20,2,FALSE),"") | C95: =IFERROR(VLOOKUP(A95,'F01 - _Données Centrales'!A6:C20,3,FALSE),"") | L95: =IF(K95="","",MAX(0,ROUND((DATEVALUE(K95)-TODAY())/30,0)))
B96: =IFERROR(VLOOKUP(A96,'F01 - _Données Centrales'!A6:B20,2,FALSE),"") | C96: =IFERROR(VLOOKUP(A96,'F01 - _Données Centrales'!A6:C20,3,FALSE),"") | L96: =IF(K96="","",MAX(0,ROUND((DATEVALUE(K96)-TODAY())/30,0)))
B97: =IFERROR(VLOOKUP(A97,'F01 - _Données Centrales'!A6:B20,2,FALSE),"") | C97: =IFERROR(VLOOKUP(A97,'F01 - _Données Centrales'!A6:C20,3,FALSE),"") | L97: =IF(K97="","",MAX(0,ROUND((DATEVALUE(K97)-TODAY())/30,0)))
B98: =IFERROR(VLOOKUP(A98,'F01 - _Données Centrales'!A6:B20,2,FALSE),"") | C98: =IFERROR(VLOOKUP(A98,'F01 - _Données Centrales'!A6:C20,3,FALSE),"") | L98: =IF(K98="","",MAX(0,ROUND((DATEVALUE(K98)-TODAY())/30,0)))
B99: =IFERROR(VLOOKUP(A99,'F01 - _Données Centrales'!A6:B20,2,FALSE),"") | C99: =IFERROR(VLOOKUP(A99,'F01 - _Données Centrales'!A6:C20,3,FALSE),"") | L99: =IF(K99="","",MAX(0,ROUND((DATEVALUE(K99)-TODAY())/30,0)))
B100: =IFERROR(VLOOKUP(A100,'F01 - _Données Centrales'!A6:B20,2,FALSE),"") | C100: =IFERROR(VLOOKUP(A100,'F01 - _Données Centrales'!A6:C20,3,FALSE),"") | L100: =IF(K100="","",MAX(0,ROUND((DATEVALUE(K100)-TODAY())/30,0)))
B101: =IFERROR(VLOOKUP(A101,'F01 - _Données Centrales'!A6:B20,2,FALSE),"") | C101: =IFERROR(VLOOKUP(A101,'F01 - _Données Centrales'!A6:C20,3,FALSE),"") | L101: =IF(K101="","",MAX(0,ROUND((DATEVALUE(K101)-TODAY())/30,0)))
B102: =IFERROR(VLOOKUP(A102,'F01 - _Données Centrales'!A6:B20,2,FALSE),"") | C102: =IFERROR(VLOOKUP(A102,'F01 - _Données Centrales'!A6:C20,3,FALSE),"") | L102: =IF(K102="","",MAX(0,ROUND((DATEVALUE(K102)-TODAY())/30,0)))
...

Sheet F09 - 7-Mobilité Internationale
A2: DOMAINE 28 — MOBILITÉ INTERNATIONALE
A3: Gestion des expatriations, détachements et missions internationales
A5: N° Mission | B5: Code Employé | C5: Nom | D5: Pays Destination | E5: Ville | F5: Type Contrat | G5: Date Départ | H5: Date Retour | I5: Durée (mois) | J5: Coût Total (FCFA) | K5: Indemnité Expatriation | L5: Statut | M5: Logement | N5: Scolarité Enfants | O5: Observations
A6: INT-2025-001 | B6: EMP-003 | C6: =IFERROR(VLOOKUP(B6,'F01 - _Données Centrales'!A6:B20,2,FALSE),"") | D6: Côte d'Ivoire | E6: Abidjan | F6: Détachement | G6: 2025-04-01 | H6: 2026-04-01 | I6: 12 | J6: 25000000 | K6: 5000000 | L6: En cours | M6: Pris en charge | N6: Oui | O6: Ouverture filiale Abidjan
A7: INT-2025-002 | B7: EMP-007 | C7: =IFERROR(VLOOKUP(B7,'F01 - _Données Centrales'!A6:B20,2,FALSE),"") | D7: France | E7: Paris | F7: Mission courte | G7: 2025-06-15 | H7: 2025-07-15 | I7: 1 | J7: 3500000 | K7: 0 | L7: Planifié | M7: Hôtel | N7: Non | O7: Formation certifiante DRH
A8: INT-2025-003 | B8: EMP-002 | C8: =IFERROR(VLOOKUP(B8,'F01 - _Données Centrales'!A6:B20,2,FALSE),"") | D8: Cameroun | E8: Douala | F8: Consultation technique | G8: 2025-05-01 | H8: 2025-05-15 | I8: 0.5 | J8: 1500000 | K8: 0 | L8: Terminé | M8: Hôtel | N8: Non | O8: Audit RH filiale Douala
C9: =IFERROR(VLOOKUP(B9,'F01 - _Données Centrales'!A6:B20,2,FALSE),"")
C10: =IFERROR(VLOOKUP(B10,'F01 - _Données Centrales'!A6:B20,2,FALSE),"")
C11: =IFERROR(VLOOKUP(B11,'F01 - _Données Centrales'!A6:B20,2,FALSE),"")
C12: =IFERROR(VLOOKUP(B12,'F01 - _Données Centrales'!A6:B20,2,FALSE),"")
C13: =IFERROR(VLOOKUP(B13,'F01 - _Données Centrales'!A6:B20,2,FALSE),"")
C14: =IFERROR(VLOOKUP(B14,'F01 - _Données Centrales'!A6:B20,2,FALSE),"")
C15: =IFERROR(VLOOKUP(B15,'F01 - _Données Centrales'!A6:B20,2,FALSE),"")
C16: =IFERROR(VLOOKUP(B16,'F01 - _Données Centrales'!A6:B20,2,FALSE),"")
C17: =IFERROR(VLOOKUP(B17,'F01 - _Données Centrales'!A6:B20,2,FALSE),"")
C18: =IFERROR(VLOOKUP(B18,'F01 - _Données Centrales'!A6:B20,2,FALSE),"")
C19: =IFERROR(VLOOKUP(B19,'F01 - _Données Centrales'!A6:B20,2,FALSE),"")
C20: =IFERROR(VLOOKUP(B20,'F01 - _Données Centrales'!A6:B20,2,FALSE),"")
C21: =IFERROR(VLOOKUP(B21,'F01 - _Données Centrales'!A6:B20,2,FALSE),"")
C22: =IFERROR(VLOOKUP(B22,'F01 - _Données Centrales'!A6:B20,2,FALSE),"")
C23: =IFERROR(VLOOKUP(B23,'F01 - _Données Centrales'!A6:B20,2,FALSE),"")
C24: =IFERROR(VLOOKUP(B24,'F01 - _Données Centrales'!A6:B20,2,FALSE),"")
C25: =IFERROR(VLOOKUP(B25,'F01 - _Données Centrales'!A6:B20,2,FALSE),"")
C26: =IFERROR(VLOOKUP(B26,'F01 - _Données Centrales'!A6:B20,2,FALSE),"")
C27: =IFERROR(VLOOKUP(B27,'F01 - _Données Centrales'!A6:B20,2,FALSE),"")
C28: =IFERROR(VLOOKUP(B28,'F01 - _Données Centrales'!A6:B20,2,FALSE),"")
C29: =IFERROR(VLOOKUP(B29,'F01 - _Données Centrales'!A6:B20,2,FALSE),"")
C30: =IFERROR(VLOOKUP(B30,'F01 - _Données Centrales'!A6:B20,2,FALSE),"")
C31: =IFERROR(VLOOKUP(B31,'F01 - _Données Centrales'!A6:B20,2,FALSE),"")
C32: =IFERROR(VLOOKUP(B32,'F01 - _Données Centrales'!A6:B20,2,FALSE),"")
C33: =IFERROR(VLOOKUP(B33,'F01 - _Données Centrales'!A6:B20,2,FALSE),"")
C34: =IFERROR(VLOOKUP(B34,'F01 - _Données Centrales'!A6:B20,2,FALSE),"")
C35: =IFERROR(VLOOKUP(B35,'F01 - _Données Centrales'!A6:B20,2,FALSE),"")
C36: =IFERROR(VLOOKUP(B36,'F01 - _Données Centrales'!A6:B20,2,FALSE),"")
C37: =IFERROR(VLOOKUP(B37,'F01 - _Données Centrales'!A6:B20,2,FALSE),"")
C38: =IFERROR(VLOOKUP(B38,'F01 - _Données Centrales'!A6:B20,2,FALSE),"")
C39: =IFERROR(VLOOKUP(B39,'F01 - _Données Centrales'!A6:B20,2,FALSE),"")
C40: =IFERROR(VLOOKUP(B40,'F01 - _Données Centrales'!A6:B20,2,FALSE),"")
C41: =IFERROR(VLOOKUP(B41,'F01 - _Données Centrales'!A6:B20,2,FALSE),"")
C42: =IFERROR(VLOOKUP(B42,'F01 - _Données Centrales'!A6:B20,2,FALSE),"")
C43: =IFERROR(VLOOKUP(B43,'F01 - _Données Centrales'!A6:B20,2,FALSE),"")
C44: =IFERROR(VLOOKUP(B44,'F01 - _Données Centrales'!A6:B20,2,FALSE),"")
C45: =IFERROR(VLOOKUP(B45,'F01 - _Données Centrales'!A6:B20,2,FALSE),"")
C46: =IFERROR(VLOOKUP(B46,'F01 - _Données Centrales'!A6:B20,2,FALSE),"")
C47: =IFERROR(VLOOKUP(B47,'F01 - _Données Centrales'!A6:B20,2,FALSE),"")
C48: =IFERROR(VLOOKUP(B48,'F01 - _Données Centrales'!A6:B20,2,FALSE),"")
C49: =IFERROR(VLOOKUP(B49,'F01 - _Données Centrales'!A6:B20,2,FALSE),"")
C50: =IFERROR(VLOOKUP(B50,'F01 - _Données Centrales'!A6:B20,2,FALSE),"")
C51: =IFERROR(VLOOKUP(B51,'F01 - _Données Centrales'!A6:B20,2,FALSE),"")
C52: =IFERROR(VLOOKUP(B52,'F01 - _Données Centrales'!A6:B20,2,FALSE),"")
C53: =IFERROR(VLOOKUP(B53,'F01 - _Données Centrales'!A6:B20,2,FALSE),"")
C54: =IFERROR(VLOOKUP(B54,'F01 - _Données Centrales'!A6:B20,2,FALSE),"")
C55: =IFERROR(VLOOKUP(B55,'F01 - _Données Centrales'!A6:B20,2,FALSE),"")
C56: =IFERROR(VLOOKUP(B56,'F01 - _Données Centrales'!A6:B20,2,FALSE),"")
C57: =IFERROR(VLOOKUP(B57,'F01 - _Données Centrales'!A6:B20,2,FALSE),"")
C58: =IFERROR(VLOOKUP(B58,'F01 - _Données Centrales'!A6:B20,2,FALSE),"")
C59: =IFERROR(VLOOKUP(B59,'F01 - _Données Centrales'!A6:B20,2,FALSE),"")
C60: =IFERROR(VLOOKUP(B60,'F01 - _Données Centrales'!A6:B20,2,FALSE),"")
C61: =IFERROR(VLOOKUP(B61,'F01 - _Données Centrales'!A6:B20,2,FALSE),"")
C62: =IFERROR(VLOOKUP(B62,'F01 - _Données Centrales'!A6:B20,2,FALSE),"")
C63: =IFERROR(VLOOKUP(B63,'F01 - _Données Centrales'!A6:B20,2,FALSE),"")
C64: =IFERROR(VLOOKUP(B64,'F01 - _Données Centrales'!A6:B20,2,FALSE),"")
C65: =IFERROR(VLOOKUP(B65,'F01 - _Données Centrales'!A6:B20,2,FALSE),"")
C66: =IFERROR(VLOOKUP(B66,'F01 - _Données Centrales'!A6:B20,2,FALSE),"")
C67: =IFERROR(VLOOKUP(B67,'F01 - _Données Centrales'!A6:B20,2,FALSE),"")
C68: =IFERROR(VLOOKUP(B68,'F01 - _Données Centrales'!A6:B20,2,FALSE),"")
C69: =IFERROR(VLOOKUP(B69,'F01 - _Données Centrales'!A6:B20,2,FALSE),"")
C70: =IFERROR(VLOOKUP(B70,'F01 - _Données Centrales'!A6:B20,2,FALSE),"")
C71: =IFERROR(VLOOKUP(B71,'F01 - _Données Centrales'!A6:B20,2,FALSE),"")
C72: =IFERROR(VLOOKUP(B72,'F01 - _Données Centrales'!A6:B20,2,FALSE),"")
C73: =IFERROR(VLOOKUP(B73,'F01 - _Données Centrales'!A6:B20,2,FALSE),"")
C74: =IFERROR(VLOOKUP(B74,'F01 - _Données Centrales'!A6:B20,2,FALSE),"")
C75: =IFERROR(VLOOKUP(B75,'F01 - _Données Centrales'!A6:B20,2,FALSE),"")
C76: =IFERROR(VLOOKUP(B76,'F01 - _Données Centrales'!A6:B20,2,FALSE),"")
C77: =IFERROR(VLOOKUP(B77,'F01 - _Données Centrales'!A6:B20,2,FALSE),"")
C78: =IFERROR(VLOOKUP(B78,'F01 - _Données Centrales'!A6:B20,2,FALSE),"")
C79: =IFERROR(VLOOKUP(B79,'F01 - _Données Centrales'!A6:B20,2,FALSE),"")
C80: =IFERROR(VLOOKUP(B80,'F01 - _Données Centrales'!A6:B20,2,FALSE),"")
C81: =IFERROR(VLOOKUP(B81,'F01 - _Données Centrales'!A6:B20,2,FALSE),"")
C82: =IFERROR(VLOOKUP(B82,'F01 - _Données Centrales'!A6:B20,2,FALSE),"")
C83: =IFERROR(VLOOKUP(B83,'F01 - _Données Centrales'!A6:B20,2,FALSE),"")
C84: =IFERROR(VLOOKUP(B84,'F01 - _Données Centrales'!A6:B20,2,FALSE),"")
C85: =IFERROR(VLOOKUP(B85,'F01 - _Données Centrales'!A6:B20,2,FALSE),"")
C86: =IFERROR(VLOOKUP(B86,'F01 - _Données Centrales'!A6:B20,2,FALSE),"")
C87: =IFERROR(VLOOKUP(B87,'F01 - _Données Centrales'!A6:B20,2,FALSE),"")
C88: =IFERROR(VLOOKUP(B88,'F01 - _Données Centrales'!A6:B20,2,FALSE),"")
C89: =IFERROR(VLOOKUP(B89,'F01 - _Données Centrales'!A6:B20,2,FALSE),"")
C90: =IFERROR(VLOOKUP(B90,'F01 - _Données Centrales'!A6:B20,2,FALSE),"")
C91: =IFERROR(VLOOKUP(B91,'F01 - _Données Centrales'!A6:B20,2,FALSE),"")
C92: =IFERROR(VLOOKUP(B92,'F01 - _Données Centrales'!A6:B20,2,FALSE),"")
C93: =IFERROR(VLOOKUP(B93,'F01 - _Données Centrales'!A6:B20,2,FALSE),"")
C94: =IFERROR(VLOOKUP(B94,'F01 - _Données Centrales'!A6:B20,2,FALSE),"")
C95: =IFERROR(VLOOKUP(B95,'F01 - _Données Centrales'!A6:B20,2,FALSE),"")
C96: =IFERROR(VLOOKUP(B96,'F01 - _Données Centrales'!A6:B20,2,FALSE),"")
C97: =IFERROR(VLOOKUP(B97,'F01 - _Données Centrales'!A6:B20,2,FALSE),"")
C98: =IFERROR(VLOOKUP(B98,'F01 - _Données Centrales'!A6:B20,2,FALSE),"")
C99: =IFERROR(VLOOKUP(B99,'F01 - _Données Centrales'!A6:B20,2,FALSE),"")
C100: =IFERROR(VLOOKUP(B100,'F01 - _Données Centrales'!A6:B20,2,FALSE),"")
C101: =IFERROR(VLOOKUP(B101,'F01 - _Données Centrales'!A6:B20,2,FALSE),"")
C102: =IFERROR(VLOOKUP(B102,'F01 - _Données Centrales'!A6:B20,2,FALSE),"")
...

Sheet F10 - 8-Gest. Talents Haut Pot.
A2: DOMAINE 28 — GESTION DES TALENTS HAUT POTENTIEL
A3: Identification, développement et rétention des collaborateurs à haut potentiel
A5: Code Employé | B5: Nom | C5: Département | D5: Potentiel | E5: Performance | F5: Date Identification | G5: Programme Développement | H5: Mentor Assigné | I5: Budget Alloué (FCFA) | J5: Budget Consommé (FCFA) | K5: Taux Utilisation (%) | L5: Risque Départ | M5: Date Révision | N5: Statut Talent
A6: EMP-007 | B6: =IFERROR(VLOOKUP(A6,'F01 - _Données Centrales'!A6:B20,2,FALSE),"") | C6: =IFERROR(VLOOKUP(A6,'F01 - _Données Centrales'!A6:C20,3,FALSE),"") | D6: Très élevé | E6: Excellent | F6: 2024-01-15 | G6: Programme Émergence RH | H6: Mme. Mbarga | I6: 5000000 | J6: 3200000 | K6: =IFERROR(J6/I6,0) | L6: Élevé | M6: 2025-09-01 | N6: Actif
A7: EMP-002 | B7: =IFERROR(VLOOKUP(A7,'F01 - _Données Centrales'!A6:B20,2,FALSE),"") | C7: =IFERROR(VLOOKUP(A7,'F01 - _Données Centrales'!A6:C20,3,FALSE),"") | D7: Élevé | E7: Excellent | F7: 2023-06-01 | G7: Programme Leadership | H7: M. Nkoulou | I7: 8000000 | J7: 6400000 | K7: =IFERROR(J7/I7,0) | L7: Faible | M7: 2025-06-01 | N7: Actif
A8: EMP-003 | B8: =IFERROR(VLOOKUP(A8,'F01 - _Données Centrales'!A6:B20,2,FALSE),"") | C8: =IFERROR(VLOOKUP(A8,'F01 - _Données Centrales'!A6:C20,3,FALSE),"") | D8: Élevé | E8: Très bon | F8: 2023-09-01 | G8: Programme Finance Exec. | H8: DG Externe | I8: 6000000 | J8: 4500000 | K8: =IFERROR(J8/I8,0) | L8: Moyen | M8: 2025-12-01 | N8: Actif
A9: EMP-005 | B9: =IFERROR(VLOOKUP(A9,'F01 - _Données Centrales'!A6:B20,2,FALSE),"") | C9: =IFERROR(VLOOKUP(A9,'F01 - _Données Centrales'!A6:C20,3,FALSE),"") | D9: Élevé | E9: Bon | F9: 2024-07-01 | G9: Programme Management | H9: Mme. Mbarga | I9: 3000000 | J9: 1800000 | K9: =IFERROR(J9/I9,0) | L9: Moyen | M9: 2025-07-01 | N9: En observation
A10: EMP-013 | B10: =IFERROR(VLOOKUP(A10,'F01 - _Données Centrales'!A6:B20,2,FALSE),"") | C10: =IFERROR(VLOOKUP(A10,'F01 - _Données Centrales'!A6:C20,3,FALSE),"") | D10: Élevé | E10: Excellent | F10: 2024-03-01 | G10: Programme Adjoint Dir. | H10: M. Nkoulou | I10: 2500000 | J10: 1500000 | K10: =IFERROR(J10/I10,0) | L10: Faible | M10: 2025-09-01 | N10: Actif
B11: =IFERROR(VLOOKUP(A11,'F01 - _Données Centrales'!A6:B20,2,FALSE),"") | C11: =IFERROR(VLOOKUP(A11,'F01 - _Données Centrales'!A6:C20,3,FALSE),"") | K11: =IFERROR(J11/I11,0)
B12: =IFERROR(VLOOKUP(A12,'F01 - _Données Centrales'!A6:B20,2,FALSE),"") | C12: =IFERROR(VLOOKUP(A12,'F01 - _Données Centrales'!A6:C20,3,FALSE),"") | K12: =IFERROR(J12/I12,0)
B13: =IFERROR(VLOOKUP(A13,'F01 - _Données Centrales'!A6:B20,2,FALSE),"") | C13: =IFERROR(VLOOKUP(A13,'F01 - _Données Centrales'!A6:C20,3,FALSE),"") | K13: =IFERROR(J13/I13,0)
B14: =IFERROR(VLOOKUP(A14,'F01 - _Données Centrales'!A6:B20,2,FALSE),"") | C14: =IFERROR(VLOOKUP(A14,'F01 - _Données Centrales'!A6:C20,3,FALSE),"") | K14: =IFERROR(J14/I14,0)
B15: =IFERROR(VLOOKUP(A15,'F01 - _Données Centrales'!A6:B20,2,FALSE),"") | C15: =IFERROR(VLOOKUP(A15,'F01 - _Données Centrales'!A6:C20,3,FALSE),"") | K15: =IFERROR(J15/I15,0)
B16: =IFERROR(VLOOKUP(A16,'F01 - _Données Centrales'!A6:B20,2,FALSE),"") | C16: =IFERROR(VLOOKUP(A16,'F01 - _Données Centrales'!A6:C20,3,FALSE),"") | K16: =IFERROR(J16/I16,0)
B17: =IFERROR(VLOOKUP(A17,'F01 - _Données Centrales'!A6:B20,2,FALSE),"") | C17: =IFERROR(VLOOKUP(A17,'F01 - _Données Centrales'!A6:C20,3,FALSE),"") | K17: =IFERROR(J17/I17,0)
B18: =IFERROR(VLOOKUP(A18,'F01 - _Données Centrales'!A6:B20,2,FALSE),"") | C18: =IFERROR(VLOOKUP(A18,'F01 - _Données Centrales'!A6:C20,3,FALSE),"") | K18: =IFERROR(J18/I18,0)
B19: =IFERROR(VLOOKUP(A19,'F01 - _Données Centrales'!A6:B20,2,FALSE),"") | C19: =IFERROR(VLOOKUP(A19,'F01 - _Données Centrales'!A6:C20,3,FALSE),"") | K19: =IFERROR(J19/I19,0)
B20: =IFERROR(VLOOKUP(A20,'F01 - _Données Centrales'!A6:B20,2,FALSE),"") | C20: =IFERROR(VLOOKUP(A20,'F01 - _Données Centrales'!A6:C20,3,FALSE),"") | K20: =IFERROR(J20/I20,0)
B21: =IFERROR(VLOOKUP(A21,'F01 - _Données Centrales'!A6:B20,2,FALSE),"") | C21: =IFERROR(VLOOKUP(A21,'F01 - _Données Centrales'!A6:C20,3,FALSE),"") | K21: =IFERROR(J21/I21,0)
B22: =IFERROR(VLOOKUP(A22,'F01 - _Données Centrales'!A6:B20,2,FALSE),"") | C22: =IFERROR(VLOOKUP(A22,'F01 - _Données Centrales'!A6:C20,3,FALSE),"") | K22: =IFERROR(J22/I22,0)
B23: =IFERROR(VLOOKUP(A23,'F01 - _Données Centrales'!A6:B20,2,FALSE),"") | C23: =IFERROR(VLOOKUP(A23,'F01 - _Données Centrales'!A6:C20,3,FALSE),"") | K23: =IFERROR(J23/I23,0)
B24: =IFERROR(VLOOKUP(A24,'F01 - _Données Centrales'!A6:B20,2,FALSE),"") | C24: =IFERROR(VLOOKUP(A24,'F01 - _Données Centrales'!A6:C20,3,FALSE),"") | K24: =IFERROR(J24/I24,0)
B25: =IFERROR(VLOOKUP(A25,'F01 - _Données Centrales'!A6:B20,2,FALSE),"") | C25: =IFERROR(VLOOKUP(A25,'F01 - _Données Centrales'!A6:C20,3,FALSE),"") | K25: =IFERROR(J25/I25,0)
B26: =IFERROR(VLOOKUP(A26,'F01 - _Données Centrales'!A6:B20,2,FALSE),"") | C26: =IFERROR(VLOOKUP(A26,'F01 - _Données Centrales'!A6:C20,3,FALSE),"") | K26: =IFERROR(J26/I26,0)
B27: =IFERROR(VLOOKUP(A27,'F01 - _Données Centrales'!A6:B20,2,FALSE),"") | C27: =IFERROR(VLOOKUP(A27,'F01 - _Données Centrales'!A6:C20,3,FALSE),"") | K27: =IFERROR(J27/I27,0)
B28: =IFERROR(VLOOKUP(A28,'F01 - _Données Centrales'!A6:B20,2,FALSE),"") | C28: =IFERROR(VLOOKUP(A28,'F01 - _Données Centrales'!A6:C20,3,FALSE),"") | K28: =IFERROR(J28/I28,0)
B29: =IFERROR(VLOOKUP(A29,'F01 - _Données Centrales'!A6:B20,2,FALSE),"") | C29: =IFERROR(VLOOKUP(A29,'F01 - _Données Centrales'!A6:C20,3,FALSE),"") | K29: =IFERROR(J29/I29,0)
B30: =IFERROR(VLOOKUP(A30,'F01 - _Données Centrales'!A6:B20,2,FALSE),"") | C30: =IFERROR(VLOOKUP(A30,'F01 - _Données Centrales'!A6:C20,3,FALSE),"") | K30: =IFERROR(J30/I30,0)
B31: =IFERROR(VLOOKUP(A31,'F01 - _Données Centrales'!A6:B20,2,FALSE),"") | C31: =IFERROR(VLOOKUP(A31,'F01 - _Données Centrales'!A6:C20,3,FALSE),"") | K31: =IFERROR(J31/I31,0)
B32: =IFERROR(VLOOKUP(A32,'F01 - _Données Centrales'!A6:B20,2,FALSE),"") | C32: =IFERROR(VLOOKUP(A32,'F01 - _Données Centrales'!A6:C20,3,FALSE),"") | K32: =IFERROR(J32/I32,0)
B33: =IFERROR(VLOOKUP(A33,'F01 - _Données Centrales'!A6:B20,2,FALSE),"") | C33: =IFERROR(VLOOKUP(A33,'F01 - _Données Centrales'!A6:C20,3,FALSE),"") | K33: =IFERROR(J33/I33,0)
B34: =IFERROR(VLOOKUP(A34,'F01 - _Données Centrales'!A6:B20,2,FALSE),"") | C34: =IFERROR(VLOOKUP(A34,'F01 - _Données Centrales'!A6:C20,3,FALSE),"") | K34: =IFERROR(J34/I34,0)
B35: =IFERROR(VLOOKUP(A35,'F01 - _Données Centrales'!A6:B20,2,FALSE),"") | C35: =IFERROR(VLOOKUP(A35,'F01 - _Données Centrales'!A6:C20,3,FALSE),"") | K35: =IFERROR(J35/I35,0)
B36: =IFERROR(VLOOKUP(A36,'F01 - _Données Centrales'!A6:B20,2,FALSE),"") | C36: =IFERROR(VLOOKUP(A36,'F01 - _Données Centrales'!A6:C20,3,FALSE),"") | K36: =IFERROR(J36/I36,0)
B37: =IFERROR(VLOOKUP(A37,'F01 - _Données Centrales'!A6:B20,2,FALSE),"") | C37: =IFERROR(VLOOKUP(A37,'F01 - _Données Centrales'!A6:C20,3,FALSE),"") | K37: =IFERROR(J37/I37,0)
B38: =IFERROR(VLOOKUP(A38,'F01 - _Données Centrales'!A6:B20,2,FALSE),"") | C38: =IFERROR(VLOOKUP(A38,'F01 - _Données Centrales'!A6:C20,3,FALSE),"") | K38: =IFERROR(J38/I38,0)
B39: =IFERROR(VLOOKUP(A39,'F01 - _Données Centrales'!A6:B20,2,FALSE),"") | C39: =IFERROR(VLOOKUP(A39,'F01 - _Données Centrales'!A6:C20,3,FALSE),"") | K39: =IFERROR(J39/I39,0)
B40: =IFERROR(VLOOKUP(A40,'F01 - _Données Centrales'!A6:B20,2,FALSE),"") | C40: =IFERROR(VLOOKUP(A40,'F01 - _Données Centrales'!A6:C20,3,FALSE),"") | K40: =IFERROR(J40/I40,0)
B41: =IFERROR(VLOOKUP(A41,'F01 - _Données Centrales'!A6:B20,2,FALSE),"") | C41: =IFERROR(VLOOKUP(A41,'F01 - _Données Centrales'!A6:C20,3,FALSE),"") | K41: =IFERROR(J41/I41,0)
B42: =IFERROR(VLOOKUP(A42,'F01 - _Données Centrales'!A6:B20,2,FALSE),"") | C42: =IFERROR(VLOOKUP(A42,'F01 - _Données Centrales'!A6:C20,3,FALSE),"") | K42: =IFERROR(J42/I42,0)
B43: =IFERROR(VLOOKUP(A43,'F01 - _Données Centrales'!A6:B20,2,FALSE),"") | C43: =IFERROR(VLOOKUP(A43,'F01 - _Données Centrales'!A6:C20,3,FALSE),"") | K43: =IFERROR(J43/I43,0)
B44: =IFERROR(VLOOKUP(A44,'F01 - _Données Centrales'!A6:B20,2,FALSE),"") | C44: =IFERROR(VLOOKUP(A44,'F01 - _Données Centrales'!A6:C20,3,FALSE),"") | K44: =IFERROR(J44/I44,0)
B45: =IFERROR(VLOOKUP(A45,'F01 - _Données Centrales'!A6:B20,2,FALSE),"") | C45: =IFERROR(VLOOKUP(A45,'F01 - _Données Centrales'!A6:C20,3,FALSE),"") | K45: =IFERROR(J45/I45,0)
B46: =IFERROR(VLOOKUP(A46,'F01 - _Données Centrales'!A6:B20,2,FALSE),"") | C46: =IFERROR(VLOOKUP(A46,'F01 - _Données Centrales'!A6:C20,3,FALSE),"") | K46: =IFERROR(J46/I46,0)
B47: =IFERROR(VLOOKUP(A47,'F01 - _Données Centrales'!A6:B20,2,FALSE),"") | C47: =IFERROR(VLOOKUP(A47,'F01 - _Données Centrales'!A6:C20,3,FALSE),"") | K47: =IFERROR(J47/I47,0)
B48: =IFERROR(VLOOKUP(A48,'F01 - _Données Centrales'!A6:B20,2,FALSE),"") | C48: =IFERROR(VLOOKUP(A48,'F01 - _Données Centrales'!A6:C20,3,FALSE),"") | K48: =IFERROR(J48/I48,0)
B49: =IFERROR(VLOOKUP(A49,'F01 - _Données Centrales'!A6:B20,2,FALSE),"") | C49: =IFERROR(VLOOKUP(A49,'F01 - _Données Centrales'!A6:C20,3,FALSE),"") | K49: =IFERROR(J49/I49,0)
B50: =IFERROR(VLOOKUP(A50,'F01 - _Données Centrales'!A6:B20,2,FALSE),"") | C50: =IFERROR(VLOOKUP(A50,'F01 - _Données Centrales'!A6:C20,3,FALSE),"") | K50: =IFERROR(J50/I50,0)
B51: =IFERROR(VLOOKUP(A51,'F01 - _Données Centrales'!A6:B20,2,FALSE),"") | C51: =IFERROR(VLOOKUP(A51,'F01 - _Données Centrales'!A6:C20,3,FALSE),"") | K51: =IFERROR(J51/I51,0)
B52: =IFERROR(VLOOKUP(A52,'F01 - _Données Centrales'!A6:B20,2,FALSE),"") | C52: =IFERROR(VLOOKUP(A52,'F01 - _Données Centrales'!A6:C20,3,FALSE),"") | K52: =IFERROR(J52/I52,0)
B53: =IFERROR(VLOOKUP(A53,'F01 - _Données Centrales'!A6:B20,2,FALSE),"") | C53: =IFERROR(VLOOKUP(A53,'F01 - _Données Centrales'!A6:C20,3,FALSE),"") | K53: =IFERROR(J53/I53,0)
B54: =IFERROR(VLOOKUP(A54,'F01 - _Données Centrales'!A6:B20,2,FALSE),"") | C54: =IFERROR(VLOOKUP(A54,'F01 - _Données Centrales'!A6:C20,3,FALSE),"") | K54: =IFERROR(J54/I54,0)
B55: =IFERROR(VLOOKUP(A55,'F01 - _Données Centrales'!A6:B20,2,FALSE),"") | C55: =IFERROR(VLOOKUP(A55,'F01 - _Données Centrales'!A6:C20,3,FALSE),"") | K55: =IFERROR(J55/I55,0)
B56: =IFERROR(VLOOKUP(A56,'F01 - _Données Centrales'!A6:B20,2,FALSE),"") | C56: =IFERROR(VLOOKUP(A56,'F01 - _Données Centrales'!A6:C20,3,FALSE),"") | K56: =IFERROR(J56/I56,0)
B57: =IFERROR(VLOOKUP(A57,'F01 - _Données Centrales'!A6:B20,2,FALSE),"") | C57: =IFERROR(VLOOKUP(A57,'F01 - _Données Centrales'!A6:C20,3,FALSE),"") | K57: =IFERROR(J57/I57,0)
B58: =IFERROR(VLOOKUP(A58,'F01 - _Données Centrales'!A6:B20,2,FALSE),"") | C58: =IFERROR(VLOOKUP(A58,'F01 - _Données Centrales'!A6:C20,3,FALSE),"") | K58: =IFERROR(J58/I58,0)
B59: =IFERROR(VLOOKUP(A59,'F01 - _Données Centrales'!A6:B20,2,FALSE),"") | C59: =IFERROR(VLOOKUP(A59,'F01 - _Données Centrales'!A6:C20,3,FALSE),"") | K59: =IFERROR(J59/I59,0)
B60: =IFERROR(VLOOKUP(A60,'F01 - _Données Centrales'!A6:B20,2,FALSE),"") | C60: =IFERROR(VLOOKUP(A60,'F01 - _Données Centrales'!A6:C20,3,FALSE),"") | K60: =IFERROR(J60/I60,0)
B61: =IFERROR(VLOOKUP(A61,'F01 - _Données Centrales'!A6:B20,2,FALSE),"") | C61: =IFERROR(VLOOKUP(A61,'F01 - _Données Centrales'!A6:C20,3,FALSE),"") | K61: =IFERROR(J61/I61,0)
B62: =IFERROR(VLOOKUP(A62,'F01 - _Données Centrales'!A6:B20,2,FALSE),"") | C62: =IFERROR(VLOOKUP(A62,'F01 - _Données Centrales'!A6:C20,3,FALSE),"") | K62: =IFERROR(J62/I62,0)
B63: =IFERROR(VLOOKUP(A63,'F01 - _Données Centrales'!A6:B20,2,FALSE),"") | C63: =IFERROR(VLOOKUP(A63,'F01 - _Données Centrales'!A6:C20,3,FALSE),"") | K63: =IFERROR(J63/I63,0)
B64: =IFERROR(VLOOKUP(A64,'F01 - _Données Centrales'!A6:B20,2,FALSE),"") | C64: =IFERROR(VLOOKUP(A64,'F01 - _Données Centrales'!A6:C20,3,FALSE),"") | K64: =IFERROR(J64/I64,0)
B65: =IFERROR(VLOOKUP(A65,'F01 - _Données Centrales'!A6:B20,2,FALSE),"") | C65: =IFERROR(VLOOKUP(A65,'F01 - _Données Centrales'!A6:C20,3,FALSE),"") | K65: =IFERROR(J65/I65,0)
B66: =IFERROR(VLOOKUP(A66,'F01 - _Données Centrales'!A6:B20,2,FALSE),"") | C66: =IFERROR(VLOOKUP(A66,'F01 - _Données Centrales'!A6:C20,3,FALSE),"") | K66: =IFERROR(J66/I66,0)
B67: =IFERROR(VLOOKUP(A67,'F01 - _Données Centrales'!A6:B20,2,FALSE),"") | C67: =IFERROR(VLOOKUP(A67,'F01 - _Données Centrales'!A6:C20,3,FALSE),"") | K67: =IFERROR(J67/I67,0)
B68: =IFERROR(VLOOKUP(A68,'F01 - _Données Centrales'!A6:B20,2,FALSE),"") | C68: =IFERROR(VLOOKUP(A68,'F01 - _Données Centrales'!A6:C20,3,FALSE),"") | K68: =IFERROR(J68/I68,0)
B69: =IFERROR(VLOOKUP(A69,'F01 - _Données Centrales'!A6:B20,2,FALSE),"") | C69: =IFERROR(VLOOKUP(A69,'F01 - _Données Centrales'!A6:C20,3,FALSE),"") | K69: =IFERROR(J69/I69,0)
B70: =IFERROR(VLOOKUP(A70,'F01 - _Données Centrales'!A6:B20,2,FALSE),"") | C70: =IFERROR(VLOOKUP(A70,'F01 - _Données Centrales'!A6:C20,3,FALSE),"") | K70: =IFERROR(J70/I70,0)
B71: =IFERROR(VLOOKUP(A71,'F01 - _Données Centrales'!A6:B20,2,FALSE),"") | C71: =IFERROR(VLOOKUP(A71,'F01 - _Données Centrales'!A6:C20,3,FALSE),"") | K71: =IFERROR(J71/I71,0)
B72: =IFERROR(VLOOKUP(A72,'F01 - _Données Centrales'!A6:B20,2,FALSE),"") | C72: =IFERROR(VLOOKUP(A72,'F01 - _Données Centrales'!A6:C20,3,FALSE),"") | K72: =IFERROR(J72/I72,0)
B73: =IFERROR(VLOOKUP(A73,'F01 - _Données Centrales'!A6:B20,2,FALSE),"") | C73: =IFERROR(VLOOKUP(A73,'F01 - _Données Centrales'!A6:C20,3,FALSE),"") | K73: =IFERROR(J73/I73,0)
B74: =IFERROR(VLOOKUP(A74,'F01 - _Données Centrales'!A6:B20,2,FALSE),"") | C74: =IFERROR(VLOOKUP(A74,'F01 - _Données Centrales'!A6:C20,3,FALSE),"") | K74: =IFERROR(J74/I74,0)
B75: =IFERROR(VLOOKUP(A75,'F01 - _Données Centrales'!A6:B20,2,FALSE),"") | C75: =IFERROR(VLOOKUP(A75,'F01 - _Données Centrales'!A6:C20,3,FALSE),"") | K75: =IFERROR(J75/I75,0)
B76: =IFERROR(VLOOKUP(A76,'F01 - _Données Centrales'!A6:B20,2,FALSE),"") | C76: =IFERROR(VLOOKUP(A76,'F01 - _Données Centrales'!A6:C20,3,FALSE),"") | K76: =IFERROR(J76/I76,0)
B77: =IFERROR(VLOOKUP(A77,'F01 - _Données Centrales'!A6:B20,2,FALSE),"") | C77: =IFERROR(VLOOKUP(A77,'F01 - _Données Centrales'!A6:C20,3,FALSE),"") | K77: =IFERROR(J77/I77,0)
B78: =IFERROR(VLOOKUP(A78,'F01 - _Données Centrales'!A6:B20,2,FALSE),"") | C78: =IFERROR(VLOOKUP(A78,'F01 - _Données Centrales'!A6:C20,3,FALSE),"") | K78: =IFERROR(J78/I78,0)
B79: =IFERROR(VLOOKUP(A79,'F01 - _Données Centrales'!A6:B20,2,FALSE),"") | C79: =IFERROR(VLOOKUP(A79,'F01 - _Données Centrales'!A6:C20,3,FALSE),"") | K79: =IFERROR(J79/I79,0)
B80: =IFERROR(VLOOKUP(A80,'F01 - _Données Centrales'!A6:B20,2,FALSE),"") | C80: =IFERROR(VLOOKUP(A80,'F01 - _Données Centrales'!A6:C20,3,FALSE),"") | K80: =IFERROR(J80/I80,0)
B81: =IFERROR(VLOOKUP(A81,'F01 - _Données Centrales'!A6:B20,2,FALSE),"") | C81: =IFERROR(VLOOKUP(A81,'F01 - _Données Centrales'!A6:C20,3,FALSE),"") | K81: =IFERROR(J81/I81,0)
B82: =IFERROR(VLOOKUP(A82,'F01 - _Données Centrales'!A6:B20,2,FALSE),"") | C82: =IFERROR(VLOOKUP(A82,'F01 - _Données Centrales'!A6:C20,3,FALSE),"") | K82: =IFERROR(J82/I82,0)
B83: =IFERROR(VLOOKUP(A83,'F01 - _Données Centrales'!A6:B20,2,FALSE),"") | C83: =IFERROR(VLOOKUP(A83,'F01 - _Données Centrales'!A6:C20,3,FALSE),"") | K83: =IFERROR(J83/I83,0)
B84: =IFERROR(VLOOKUP(A84,'F01 - _Données Centrales'!A6:B20,2,FALSE),"") | C84: =IFERROR(VLOOKUP(A84,'F01 - _Données Centrales'!A6:C20,3,FALSE),"") | K84: =IFERROR(J84/I84,0)
B85: =IFERROR(VLOOKUP(A85,'F01 - _Données Centrales'!A6:B20,2,FALSE),"") | C85: =IFERROR(VLOOKUP(A85,'F01 - _Données Centrales'!A6:C20,3,FALSE),"") | K85: =IFERROR(J85/I85,0)
B86: =IFERROR(VLOOKUP(A86,'F01 - _Données Centrales'!A6:B20,2,FALSE),"") | C86: =IFERROR(VLOOKUP(A86,'F01 - _Données Centrales'!A6:C20,3,FALSE),"") | K86: =IFERROR(J86/I86,0)
B87: =IFERROR(VLOOKUP(A87,'F01 - _Données Centrales'!A6:B20,2,FALSE),"") | C87: =IFERROR(VLOOKUP(A87,'F01 - _Données Centrales'!A6:C20,3,FALSE),"") | K87: =IFERROR(J87/I87,0)
B88: =IFERROR(VLOOKUP(A88,'F01 - _Données Centrales'!A6:B20,2,FALSE),"") | C88: =IFERROR(VLOOKUP(A88,'F01 - _Données Centrales'!A6:C20,3,FALSE),"") | K88: =IFERROR(J88/I88,0)
B89: =IFERROR(VLOOKUP(A89,'F01 - _Données Centrales'!A6:B20,2,FALSE),"") | C89: =IFERROR(VLOOKUP(A89,'F01 - _Données Centrales'!A6:C20,3,FALSE),"") | K89: =IFERROR(J89/I89,0)
B90: =IFERROR(VLOOKUP(A90,'F01 - _Données Centrales'!A6:B20,2,FALSE),"") | C90: =IFERROR(VLOOKUP(A90,'F01 - _Données Centrales'!A6:C20,3,FALSE),"") | K90: =IFERROR(J90/I90,0)
B91: =IFERROR(VLOOKUP(A91,'F01 - _Données Centrales'!A6:B20,2,FALSE),"") | C91: =IFERROR(VLOOKUP(A91,'F01 - _Données Centrales'!A6:C20,3,FALSE),"") | K91: =IFERROR(J91/I91,0)
B92: =IFERROR(VLOOKUP(A92,'F01 - _Données Centrales'!A6:B20,2,FALSE),"") | C92: =IFERROR(VLOOKUP(A92,'F01 - _Données Centrales'!A6:C20,3,FALSE),"") | K92: =IFERROR(J92/I92,0)
B93: =IFERROR(VLOOKUP(A93,'F01 - _Données Centrales'!A6:B20,2,FALSE),"") | C93: =IFERROR(VLOOKUP(A93,'F01 - _Données Centrales'!A6:C20,3,FALSE),"") | K93: =IFERROR(J93/I93,0)
B94: =IFERROR(VLOOKUP(A94,'F01 - _Données Centrales'!A6:B20,2,FALSE),"") | C94: =IFERROR(VLOOKUP(A94,'F01 - _Données Centrales'!A6:C20,3,FALSE),"") | K94: =IFERROR(J94/I94,0)
B95: =IFERROR(VLOOKUP(A95,'F01 - _Données Centrales'!A6:B20,2,FALSE),"") | C95: =IFERROR(VLOOKUP(A95,'F01 - _Données Centrales'!A6:C20,3,FALSE),"") | K95: =IFERROR(J95/I95,0)
B96: =IFERROR(VLOOKUP(A96,'F01 - _Données Centrales'!A6:B20,2,FALSE),"") | C96: =IFERROR(VLOOKUP(A96,'F01 - _Données Centrales'!A6:C20,3,FALSE),"") | K96: =IFERROR(J96/I96,0)
B97: =IFERROR(VLOOKUP(A97,'F01 - _Données Centrales'!A6:B20,2,FALSE),"") | C97: =IFERROR(VLOOKUP(A97,'F01 - _Données Centrales'!A6:C20,3,FALSE),"") | K97: =IFERROR(J97/I97,0)
B98: =IFERROR(VLOOKUP(A98,'F01 - _Données Centrales'!A6:B20,2,FALSE),"") | C98: =IFERROR(VLOOKUP(A98,'F01 - _Données Centrales'!A6:C20,3,FALSE),"") | K98: =IFERROR(J98/I98,0)
B99: =IFERROR(VLOOKUP(A99,'F01 - _Données Centrales'!A6:B20,2,FALSE),"") | C99: =IFERROR(VLOOKUP(A99,'F01 - _Données Centrales'!A6:C20,3,FALSE),"") | K99: =IFERROR(J99/I99,0)
B100: =IFERROR(VLOOKUP(A100,'F01 - _Données Centrales'!A6:B20,2,FALSE),"") | C100: =IFERROR(VLOOKUP(A100,'F01 - _Données Centrales'!A6:C20,3,FALSE),"") | K100: =IFERROR(J100/I100,0)
B101: =IFERROR(VLOOKUP(A101,'F01 - _Données Centrales'!A6:B20,2,FALSE),"") | C101: =IFERROR(VLOOKUP(A101,'F01 - _Données Centrales'!A6:C20,3,FALSE),"") | K101: =IFERROR(J101/I101,0)
B102: =IFERROR(VLOOKUP(A102,'F01 - _Données Centrales'!A6:B20,2,FALSE),"") | C102: =IFERROR(VLOOKUP(A102,'F01 - _Données Centrales'!A6:C20,3,FALSE),"") | K102: =IFERROR(J102/I102,0)
...

Sheet F11 - 9-Entretiens Annu. Carr.
A2: DOMAINE 28 — ENTRETIENS ANNUELS DE CARRIÈRE
A3: Planification et suivi des entretiens individuels de carrière
A5: Code Employé | B5: Nom | C5: Département | D5: Date Entretien | E5: Évaluateur | F5: Fréquence | G5: Objectifs Fixés | H5: Actions Convenues | I5: Date Prochain Entretien | J5: Statut Réalisation | K5: Note Globale (/20) | L5: Évolution Poste | M5: Observations
A6: EMP-001 | B6: =IFERROR(VLOOKUP(A6,'F01 - _Données Centrales'!A6:B20,2,FALSE),"") | C6: =IFERROR(VLOOKUP(A6,'F01 - _Données Centrales'!A6:C20,3,FALSE),"") | D6: 2025-01-20 | E6: Conseil Administration | F6: Annuel | G6: Stratégie 2025-2027 | H6: Formation executive leadership | I6: 2026-01-20 | J6: Réalisé | K6: 18 | L6: Maintien DG | M6: Excellent leader, vision confirmée
A7: EMP-002 | B7: =IFERROR(VLOOKUP(A7,'F01 - _Données Centrales'!A6:B20,2,FALSE),"") | C7: =IFERROR(VLOOKUP(A7,'F01 - _Données Centrales'!A6:C20,3,FALSE),"") | D7: 2025-02-10 | E7: DG | F7: Annuel | G7: Préparation succession DG | H7: Programme haute direction | I7: 2026-02-10 | J7: Réalisé | K7: 17 | L7: Promotion DG Adjoint | M7: Prête pour niveau supérieur
A8: EMP-003 | B8: =IFERROR(VLOOKUP(A8,'F01 - _Données Centrales'!A6:B20,2,FALSE),"") | C8: =IFERROR(VLOOKUP(A8,'F01 - _Données Centrales'!A6:C20,3,FALSE),"") | D8: 2025-03-01 | E8: DG | F8: Annuel | G8: Optimisation fiscale 2025 | H8: Certification IFRS | I8: 2026-03-01 | J8: Réalisé | K8: 16 | L8: Maintien DAF | M8: Bonne progression technique
A9: EMP-007 | B9: =IFERROR(VLOOKUP(A9,'F01 - _Données Centrales'!A6:B20,2,FALSE),"") | C9: =IFERROR(VLOOKUP(A9,'F01 - _Données Centrales'!A6:C20,3,FALSE),"") | D9: 2025-02-20 | E9: DRH | F9: Semestriel | G9: Plan succession DRH | H9: Formation management avancé | I9: 2025-08-20 | J9: Planifié | K9: 17 | L9: Promotion DRH | M9: Talent émergent confirmé
A10: EMP-005 | B10: =IFERROR(VLOOKUP(A10,'F01 - _Données Centrales'!A6:B20,2,FALSE),"") | C10: =IFERROR(VLOOKUP(A10,'F01 - _Données Centrales'!A6:C20,3,FALSE),"") | D10: 2025-03-15 | E10: DRH | F10: Annuel | G10: Développer leadership | H10: Coaching externe | I10: 2026-03-15 | J10: Reporté | K10: 15 | L10: Promotion | M10: Potentiel confirmé, effort leadership
B11: =IFERROR(VLOOKUP(A11,'F01 - _Données Centrales'!A6:B20,2,FALSE),"") | C11: =IFERROR(VLOOKUP(A11,'F01 - _Données Centrales'!A6:C20,3,FALSE),"")
B12: =IFERROR(VLOOKUP(A12,'F01 - _Données Centrales'!A6:B20,2,FALSE),"") | C12: =IFERROR(VLOOKUP(A12,'F01 - _Données Centrales'!A6:C20,3,FALSE),"")
B13: =IFERROR(VLOOKUP(A13,'F01 - _Données Centrales'!A6:B20,2,FALSE),"") | C13: =IFERROR(VLOOKUP(A13,'F01 - _Données Centrales'!A6:C20,3,FALSE),"")
B14: =IFERROR(VLOOKUP(A14,'F01 - _Données Centrales'!A6:B20,2,FALSE),"") | C14: =IFERROR(VLOOKUP(A14,'F01 - _Données Centrales'!A6:C20,3,FALSE),"")
B15: =IFERROR(VLOOKUP(A15,'F01 - _Données Centrales'!A6:B20,2,FALSE),"") | C15: =IFERROR(VLOOKUP(A15,'F01 - _Données Centrales'!A6:C20,3,FALSE),"")
B16: =IFERROR(VLOOKUP(A16,'F01 - _Données Centrales'!A6:B20,2,FALSE),"") | C16: =IFERROR(VLOOKUP(A16,'F01 - _Données Centrales'!A6:C20,3,FALSE),"")
B17: =IFERROR(VLOOKUP(A17,'F01 - _Données Centrales'!A6:B20,2,FALSE),"") | C17: =IFERROR(VLOOKUP(A17,'F01 - _Données Centrales'!A6:C20,3,FALSE),"")
B18: =IFERROR(VLOOKUP(A18,'F01 - _Données Centrales'!A6:B20,2,FALSE),"") | C18: =IFERROR(VLOOKUP(A18,'F01 - _Données Centrales'!A6:C20,3,FALSE),"")
B19: =IFERROR(VLOOKUP(A19,'F01 - _Données Centrales'!A6:B20,2,FALSE),"") | C19: =IFERROR(VLOOKUP(A19,'F01 - _Données Centrales'!A6:C20,3,FALSE),"")
B20: =IFERROR(VLOOKUP(A20,'F01 - _Données Centrales'!A6:B20,2,FALSE),"") | C20: =IFERROR(VLOOKUP(A20,'F01 - _Données Centrales'!A6:C20,3,FALSE),"")
B21: =IFERROR(VLOOKUP(A21,'F01 - _Données Centrales'!A6:B20,2,FALSE),"") | C21: =IFERROR(VLOOKUP(A21,'F01 - _Données Centrales'!A6:C20,3,FALSE),"")
B22: =IFERROR(VLOOKUP(A22,'F01 - _Données Centrales'!A6:B20,2,FALSE),"") | C22: =IFERROR(VLOOKUP(A22,'F01 - _Données Centrales'!A6:C20,3,FALSE),"")
B23: =IFERROR(VLOOKUP(A23,'F01 - _Données Centrales'!A6:B20,2,FALSE),"") | C23: =IFERROR(VLOOKUP(A23,'F01 - _Données Centrales'!A6:C20,3,FALSE),"")
B24: =IFERROR(VLOOKUP(A24,'F01 - _Données Centrales'!A6:B20,2,FALSE),"") | C24: =IFERROR(VLOOKUP(A24,'F01 - _Données Centrales'!A6:C20,3,FALSE),"")
B25: =IFERROR(VLOOKUP(A25,'F01 - _Données Centrales'!A6:B20,2,FALSE),"") | C25: =IFERROR(VLOOKUP(A25,'F01 - _Données Centrales'!A6:C20,3,FALSE),"")
B26: =IFERROR(VLOOKUP(A26,'F01 - _Données Centrales'!A6:B20,2,FALSE),"") | C26: =IFERROR(VLOOKUP(A26,'F01 - _Données Centrales'!A6:C20,3,FALSE),"")
B27: =IFERROR(VLOOKUP(A27,'F01 - _Données Centrales'!A6:B20,2,FALSE),"") | C27: =IFERROR(VLOOKUP(A27,'F01 - _Données Centrales'!A6:C20,3,FALSE),"")
B28: =IFERROR(VLOOKUP(A28,'F01 - _Données Centrales'!A6:B20,2,FALSE),"") | C28: =IFERROR(VLOOKUP(A28,'F01 - _Données Centrales'!A6:C20,3,FALSE),"")
B29: =IFERROR(VLOOKUP(A29,'F01 - _Données Centrales'!A6:B20,2,FALSE),"") | C29: =IFERROR(VLOOKUP(A29,'F01 - _Données Centrales'!A6:C20,3,FALSE),"")
B30: =IFERROR(VLOOKUP(A30,'F01 - _Données Centrales'!A6:B20,2,FALSE),"") | C30: =IFERROR(VLOOKUP(A30,'F01 - _Données Centrales'!A6:C20,3,FALSE),"")
B31: =IFERROR(VLOOKUP(A31,'F01 - _Données Centrales'!A6:B20,2,FALSE),"") | C31: =IFERROR(VLOOKUP(A31,'F01 - _Données Centrales'!A6:C20,3,FALSE),"")
B32: =IFERROR(VLOOKUP(A32,'F01 - _Données Centrales'!A6:B20,2,FALSE),"") | C32: =IFERROR(VLOOKUP(A32,'F01 - _Données Centrales'!A6:C20,3,FALSE),"")
B33: =IFERROR(VLOOKUP(A33,'F01 - _Données Centrales'!A6:B20,2,FALSE),"") | C33: =IFERROR(VLOOKUP(A33,'F01 - _Données Centrales'!A6:C20,3,FALSE),"")
B34: =IFERROR(VLOOKUP(A34,'F01 - _Données Centrales'!A6:B20,2,FALSE),"") | C34: =IFERROR(VLOOKUP(A34,'F01 - _Données Centrales'!A6:C20,3,FALSE),"")
B35: =IFERROR(VLOOKUP(A35,'F01 - _Données Centrales'!A6:B20,2,FALSE),"") | C35: =IFERROR(VLOOKUP(A35,'F01 - _Données Centrales'!A6:C20,3,FALSE),"")
B36: =IFERROR(VLOOKUP(A36,'F01 - _Données Centrales'!A6:B20,2,FALSE),"") | C36: =IFERROR(VLOOKUP(A36,'F01 - _Données Centrales'!A6:C20,3,FALSE),"")
B37: =IFERROR(VLOOKUP(A37,'F01 - _Données Centrales'!A6:B20,2,FALSE),"") | C37: =IFERROR(VLOOKUP(A37,'F01 - _Données Centrales'!A6:C20,3,FALSE),"")
B38: =IFERROR(VLOOKUP(A38,'F01 - _Données Centrales'!A6:B20,2,FALSE),"") | C38: =IFERROR(VLOOKUP(A38,'F01 - _Données Centrales'!A6:C20,3,FALSE),"")
B39: =IFERROR(VLOOKUP(A39,'F01 - _Données Centrales'!A6:B20,2,FALSE),"") | C39: =IFERROR(VLOOKUP(A39,'F01 - _Données Centrales'!A6:C20,3,FALSE),"")
B40: =IFERROR(VLOOKUP(A40,'F01 - _Données Centrales'!A6:B20,2,FALSE),"") | C40: =IFERROR(VLOOKUP(A40,'F01 - _Données Centrales'!A6:C20,3,FALSE),"")
B41: =IFERROR(VLOOKUP(A41,'F01 - _Données Centrales'!A6:B20,2,FALSE),"") | C41: =IFERROR(VLOOKUP(A41,'F01 - _Données Centrales'!A6:C20,3,FALSE),"")
B42: =IFERROR(VLOOKUP(A42,'F01 - _Données Centrales'!A6:B20,2,FALSE),"") | C42: =IFERROR(VLOOKUP(A42,'F01 - _Données Centrales'!A6:C20,3,FALSE),"")
B43: =IFERROR(VLOOKUP(A43,'F01 - _Données Centrales'!A6:B20,2,FALSE),"") | C43: =IFERROR(VLOOKUP(A43,'F01 - _Données Centrales'!A6:C20,3,FALSE),"")
B44: =IFERROR(VLOOKUP(A44,'F01 - _Données Centrales'!A6:B20,2,FALSE),"") | C44: =IFERROR(VLOOKUP(A44,'F01 - _Données Centrales'!A6:C20,3,FALSE),"")
B45: =IFERROR(VLOOKUP(A45,'F01 - _Données Centrales'!A6:B20,2,FALSE),"") | C45: =IFERROR(VLOOKUP(A45,'F01 - _Données Centrales'!A6:C20,3,FALSE),"")
B46: =IFERROR(VLOOKUP(A46,'F01 - _Données Centrales'!A6:B20,2,FALSE),"") | C46: =IFERROR(VLOOKUP(A46,'F01 - _Données Centrales'!A6:C20,3,FALSE),"")
B47: =IFERROR(VLOOKUP(A47,'F01 - _Données Centrales'!A6:B20,2,FALSE),"") | C47: =IFERROR(VLOOKUP(A47,'F01 - _Données Centrales'!A6:C20,3,FALSE),"")
B48: =IFERROR(VLOOKUP(A48,'F01 - _Données Centrales'!A6:B20,2,FALSE),"") | C48: =IFERROR(VLOOKUP(A48,'F01 - _Données Centrales'!A6:C20,3,FALSE),"")
B49: =IFERROR(VLOOKUP(A49,'F01 - _Données Centrales'!A6:B20,2,FALSE),"") | C49: =IFERROR(VLOOKUP(A49,'F01 - _Données Centrales'!A6:C20,3,FALSE),"")
B50: =IFERROR(VLOOKUP(A50,'F01 - _Données Centrales'!A6:B20,2,FALSE),"") | C50: =IFERROR(VLOOKUP(A50,'F01 - _Données Centrales'!A6:C20,3,FALSE),"")
B51: =IFERROR(VLOOKUP(A51,'F01 - _Données Centrales'!A6:B20,2,FALSE),"") | C51: =IFERROR(VLOOKUP(A51,'F01 - _Données Centrales'!A6:C20,3,FALSE),"")
B52: =IFERROR(VLOOKUP(A52,'F01 - _Données Centrales'!A6:B20,2,FALSE),"") | C52: =IFERROR(VLOOKUP(A52,'F01 - _Données Centrales'!A6:C20,3,FALSE),"")
B53: =IFERROR(VLOOKUP(A53,'F01 - _Données Centrales'!A6:B20,2,FALSE),"") | C53: =IFERROR(VLOOKUP(A53,'F01 - _Données Centrales'!A6:C20,3,FALSE),"")
B54: =IFERROR(VLOOKUP(A54,'F01 - _Données Centrales'!A6:B20,2,FALSE),"") | C54: =IFERROR(VLOOKUP(A54,'F01 - _Données Centrales'!A6:C20,3,FALSE),"")
B55: =IFERROR(VLOOKUP(A55,'F01 - _Données Centrales'!A6:B20,2,FALSE),"") | C55: =IFERROR(VLOOKUP(A55,'F01 - _Données Centrales'!A6:C20,3,FALSE),"")
B56: =IFERROR(VLOOKUP(A56,'F01 - _Données Centrales'!A6:B20,2,FALSE),"") | C56: =IFERROR(VLOOKUP(A56,'F01 - _Données Centrales'!A6:C20,3,FALSE),"")
B57: =IFERROR(VLOOKUP(A57,'F01 - _Données Centrales'!A6:B20,2,FALSE),"") | C57: =IFERROR(VLOOKUP(A57,'F01 - _Données Centrales'!A6:C20,3,FALSE),"")
B58: =IFERROR(VLOOKUP(A58,'F01 - _Données Centrales'!A6:B20,2,FALSE),"") | C58: =IFERROR(VLOOKUP(A58,'F01 - _Données Centrales'!A6:C20,3,FALSE),"")
B59: =IFERROR(VLOOKUP(A59,'F01 - _Données Centrales'!A6:B20,2,FALSE),"") | C59: =IFERROR(VLOOKUP(A59,'F01 - _Données Centrales'!A6:C20,3,FALSE),"")
B60: =IFERROR(VLOOKUP(A60,'F01 - _Données Centrales'!A6:B20,2,FALSE),"") | C60: =IFERROR(VLOOKUP(A60,'F01 - _Données Centrales'!A6:C20,3,FALSE),"")
B61: =IFERROR(VLOOKUP(A61,'F01 - _Données Centrales'!A6:B20,2,FALSE),"") | C61: =IFERROR(VLOOKUP(A61,'F01 - _Données Centrales'!A6:C20,3,FALSE),"")
B62: =IFERROR(VLOOKUP(A62,'F01 - _Données Centrales'!A6:B20,2,FALSE),"") | C62: =IFERROR(VLOOKUP(A62,'F01 - _Données Centrales'!A6:C20,3,FALSE),"")
B63: =IFERROR(VLOOKUP(A63,'F01 - _Données Centrales'!A6:B20,2,FALSE),"") | C63: =IFERROR(VLOOKUP(A63,'F01 - _Données Centrales'!A6:C20,3,FALSE),"")
B64: =IFERROR(VLOOKUP(A64,'F01 - _Données Centrales'!A6:B20,2,FALSE),"") | C64: =IFERROR(VLOOKUP(A64,'F01 - _Données Centrales'!A6:C20,3,FALSE),"")
B65: =IFERROR(VLOOKUP(A65,'F01 - _Données Centrales'!A6:B20,2,FALSE),"") | C65: =IFERROR(VLOOKUP(A65,'F01 - _Données Centrales'!A6:C20,3,FALSE),"")
B66: =IFERROR(VLOOKUP(A66,'F01 - _Données Centrales'!A6:B20,2,FALSE),"") | C66: =IFERROR(VLOOKUP(A66,'F01 - _Données Centrales'!A6:C20,3,FALSE),"")
B67: =IFERROR(VLOOKUP(A67,'F01 - _Données Centrales'!A6:B20,2,FALSE),"") | C67: =IFERROR(VLOOKUP(A67,'F01 - _Données Centrales'!A6:C20,3,FALSE),"")
B68: =IFERROR(VLOOKUP(A68,'F01 - _Données Centrales'!A6:B20,2,FALSE),"") | C68: =IFERROR(VLOOKUP(A68,'F01 - _Données Centrales'!A6:C20,3,FALSE),"")
B69: =IFERROR(VLOOKUP(A69,'F01 - _Données Centrales'!A6:B20,2,FALSE),"") | C69: =IFERROR(VLOOKUP(A69,'F01 - _Données Centrales'!A6:C20,3,FALSE),"")
B70: =IFERROR(VLOOKUP(A70,'F01 - _Données Centrales'!A6:B20,2,FALSE),"") | C70: =IFERROR(VLOOKUP(A70,'F01 - _Données Centrales'!A6:C20,3,FALSE),"")
B71: =IFERROR(VLOOKUP(A71,'F01 - _Données Centrales'!A6:B20,2,FALSE),"") | C71: =IFERROR(VLOOKUP(A71,'F01 - _Données Centrales'!A6:C20,3,FALSE),"")
B72: =IFERROR(VLOOKUP(A72,'F01 - _Données Centrales'!A6:B20,2,FALSE),"") | C72: =IFERROR(VLOOKUP(A72,'F01 - _Données Centrales'!A6:C20,3,FALSE),"")
B73: =IFERROR(VLOOKUP(A73,'F01 - _Données Centrales'!A6:B20,2,FALSE),"") | C73: =IFERROR(VLOOKUP(A73,'F01 - _Données Centrales'!A6:C20,3,FALSE),"")
B74: =IFERROR(VLOOKUP(A74,'F01 - _Données Centrales'!A6:B20,2,FALSE),"") | C74: =IFERROR(VLOOKUP(A74,'F01 - _Données Centrales'!A6:C20,3,FALSE),"")
B75: =IFERROR(VLOOKUP(A75,'F01 - _Données Centrales'!A6:B20,2,FALSE),"") | C75: =IFERROR(VLOOKUP(A75,'F01 - _Données Centrales'!A6:C20,3,FALSE),"")
B76: =IFERROR(VLOOKUP(A76,'F01 - _Données Centrales'!A6:B20,2,FALSE),"") | C76: =IFERROR(VLOOKUP(A76,'F01 - _Données Centrales'!A6:C20,3,FALSE),"")
B77: =IFERROR(VLOOKUP(A77,'F01 - _Données Centrales'!A6:B20,2,FALSE),"") | C77: =IFERROR(VLOOKUP(A77,'F01 - _Données Centrales'!A6:C20,3,FALSE),"")
B78: =IFERROR(VLOOKUP(A78,'F01 - _Données Centrales'!A6:B20,2,FALSE),"") | C78: =IFERROR(VLOOKUP(A78,'F01 - _Données Centrales'!A6:C20,3,FALSE),"")
B79: =IFERROR(VLOOKUP(A79,'F01 - _Données Centrales'!A6:B20,2,FALSE),"") | C79: =IFERROR(VLOOKUP(A79,'F01 - _Données Centrales'!A6:C20,3,FALSE),"")
B80: =IFERROR(VLOOKUP(A80,'F01 - _Données Centrales'!A6:B20,2,FALSE),"") | C80: =IFERROR(VLOOKUP(A80,'F01 - _Données Centrales'!A6:C20,3,FALSE),"")
B81: =IFERROR(VLOOKUP(A81,'F01 - _Données Centrales'!A6:B20,2,FALSE),"") | C81: =IFERROR(VLOOKUP(A81,'F01 - _Données Centrales'!A6:C20,3,FALSE),"")
B82: =IFERROR(VLOOKUP(A82,'F01 - _Données Centrales'!A6:B20,2,FALSE),"") | C82: =IFERROR(VLOOKUP(A82,'F01 - _Données Centrales'!A6:C20,3,FALSE),"")
B83: =IFERROR(VLOOKUP(A83,'F01 - _Données Centrales'!A6:B20,2,FALSE),"") | C83: =IFERROR(VLOOKUP(A83,'F01 - _Données Centrales'!A6:C20,3,FALSE),"")
B84: =IFERROR(VLOOKUP(A84,'F01 - _Données Centrales'!A6:B20,2,FALSE),"") | C84: =IFERROR(VLOOKUP(A84,'F01 - _Données Centrales'!A6:C20,3,FALSE),"")
B85: =IFERROR(VLOOKUP(A85,'F01 - _Données Centrales'!A6:B20,2,FALSE),"") | C85: =IFERROR(VLOOKUP(A85,'F01 - _Données Centrales'!A6:C20,3,FALSE),"")
B86: =IFERROR(VLOOKUP(A86,'F01 - _Données Centrales'!A6:B20,2,FALSE),"") | C86: =IFERROR(VLOOKUP(A86,'F01 - _Données Centrales'!A6:C20,3,FALSE),"")
B87: =IFERROR(VLOOKUP(A87,'F01 - _Données Centrales'!A6:B20,2,FALSE),"") | C87: =IFERROR(VLOOKUP(A87,'F01 - _Données Centrales'!A6:C20,3,FALSE),"")
B88: =IFERROR(VLOOKUP(A88,'F01 - _Données Centrales'!A6:B20,2,FALSE),"") | C88: =IFERROR(VLOOKUP(A88,'F01 - _Données Centrales'!A6:C20,3,FALSE),"")
B89: =IFERROR(VLOOKUP(A89,'F01 - _Données Centrales'!A6:B20,2,FALSE),"") | C89: =IFERROR(VLOOKUP(A89,'F01 - _Données Centrales'!A6:C20,3,FALSE),"")
B90: =IFERROR(VLOOKUP(A90,'F01 - _Données Centrales'!A6:B20,2,FALSE),"") | C90: =IFERROR(VLOOKUP(A90,'F01 - _Données Centrales'!A6:C20,3,FALSE),"")
B91: =IFERROR(VLOOKUP(A91,'F01 - _Données Centrales'!A6:B20,2,FALSE),"") | C91: =IFERROR(VLOOKUP(A91,'F01 - _Données Centrales'!A6:C20,3,FALSE),"")
B92: =IFERROR(VLOOKUP(A92,'F01 - _Données Centrales'!A6:B20,2,FALSE),"") | C92: =IFERROR(VLOOKUP(A92,'F01 - _Données Centrales'!A6:C20,3,FALSE),"")
B93: =IFERROR(VLOOKUP(A93,'F01 - _Données Centrales'!A6:B20,2,FALSE),"") | C93: =IFERROR(VLOOKUP(A93,'F01 - _Données Centrales'!A6:C20,3,FALSE),"")
B94: =IFERROR(VLOOKUP(A94,'F01 - _Données Centrales'!A6:B20,2,FALSE),"") | C94: =IFERROR(VLOOKUP(A94,'F01 - _Données Centrales'!A6:C20,3,FALSE),"")
B95: =IFERROR(VLOOKUP(A95,'F01 - _Données Centrales'!A6:B20,2,FALSE),"") | C95: =IFERROR(VLOOKUP(A95,'F01 - _Données Centrales'!A6:C20,3,FALSE),"")
B96: =IFERROR(VLOOKUP(A96,'F01 - _Données Centrales'!A6:B20,2,FALSE),"") | C96: =IFERROR(VLOOKUP(A96,'F01 - _Données Centrales'!A6:C20,3,FALSE),"")
B97: =IFERROR(VLOOKUP(A97,'F01 - _Données Centrales'!A6:B20,2,FALSE),"") | C97: =IFERROR(VLOOKUP(A97,'F01 - _Données Centrales'!A6:C20,3,FALSE),"")
B98: =IFERROR(VLOOKUP(A98,'F01 - _Données Centrales'!A6:B20,2,FALSE),"") | C98: =IFERROR(VLOOKUP(A98,'F01 - _Données Centrales'!A6:C20,3,FALSE),"")
B99: =IFERROR(VLOOKUP(A99,'F01 - _Données Centrales'!A6:B20,2,FALSE),"") | C99: =IFERROR(VLOOKUP(A99,'F01 - _Données Centrales'!A6:C20,3,FALSE),"")
B100: =IFERROR(VLOOKUP(A100,'F01 - _Données Centrales'!A6:B20,2,FALSE),"") | C100: =IFERROR(VLOOKUP(A100,'F01 - _Données Centrales'!A6:C20,3,FALSE),"")
B101: =IFERROR(VLOOKUP(A101,'F01 - _Données Centrales'!A6:B20,2,FALSE),"") | C101: =IFERROR(VLOOKUP(A101,'F01 - _Données Centrales'!A6:C20,3,FALSE),"")
B102: =IFERROR(VLOOKUP(A102,'F01 - _Données Centrales'!A6:B20,2,FALSE),"") | C102: =IFERROR(VLOOKUP(A102,'F01 - _Données Centrales'!A6:C20,3,FALSE),"")
...

Sheet F12 - 10-Indic. Mobilité Carr.
A2: DOMAINE 28 — INDICATEURS DE MOBILITÉ ET CARRIÈRE
A3: Tableau de bord des KPI mobilité par département et par période
A5: Département | B5: Effectif | C5: Nb Promotions | D5: Nb Mobilités Internes | E5: Nb Mobilités Internationales | F5: Nb Départs | G5: Taux Promotion (%) | H5: Taux Mobilité Interne (%) | I5: Taux Rotation (%) | J5: Délai Moyen Promotion (mois) | K5: Taux Successeurs Identifiés (%) | L5: Score Potentiel Moyen | M5: Score Perf. Moyen | N5: Indice Mobilité Carrière | O5: Tendance | P5: Période
A6: Direction Générale | B6: 3 | C6: 0 | D6: 0 | E6: 0 | F6: 0 | G6: =IFERROR(C6/B6,0) | H6: =IFERROR(D6/B6,0) | I6: =IFERROR(E6/B6,0) | J6: 24 | K6: 67 | L6: 89 | M6: 88 | N6: =IFERROR((G6*3+H6*2+L6)/6,0) | O6: =IF(N6="","",IF(N6>0.7,"Hausse",IF(N6<0.4,"Baisse","Stable"))) | P6: Q1 2025
A7: Ressources Humaines | B7: 4 | C7: 1 | D7: 0 | E7: 1 | F7: 0 | G7: =IFERROR(C7/B7,0) | H7: =IFERROR(D7/B7,0) | I7: =IFERROR(E7/B7,0) | J7: 18 | K7: 50 | L7: 88 | M7: 90 | N7: =IFERROR((G7*3+H7*2+L7)/6,0) | O7: =IF(N7="","",IF(N7>0.7,"Hausse",IF(N7<0.4,"Baisse","Stable"))) | P7: Q1 2025
A8: Finance & Comptabilité | B8: 3 | C8: 0 | D8: 0 | E8: 1 | F8: 0 | G8: =IFERROR(C8/B8,0) | H8: =IFERROR(D8/B8,0) | I8: =IFERROR(E8/B8,0) | J8: 20 | K8: 33 | L8: 82 | M8: 82 | N8: =IFERROR((G8*3+H8*2+L8)/6,0) | O8: =IF(N8="","",IF(N8>0.7,"Hausse",IF(N8<0.4,"Baisse","Stable"))) | P8: Q1 2025
A9: Cuisine & Restauration | B9: 2 | C9: 0 | D9: 1 | E9: 0 | F9: 0 | G9: =IFERROR(C9/B9,0) | H9: =IFERROR(D9/B9,0) | I9: =IFERROR(E9/B9,0) | J9: 22 | K9: 0 | L9: 72 | M9: 78 | N9: =IFERROR((G9*3+H9*2+L9)/6,0) | O9: =IF(N9="","",IF(N9>0.7,"Hausse",IF(N9<0.4,"Baisse","Stable"))) | P9: Q1 2025
A10: Réception & Front Office | B10: 3 | C10: 0 | D10: 1 | E10: 0 | F10: 0 | G10: =IFERROR(C10/B10,0) | H10: =IFERROR(D10/B10,0) | I10: =IFERROR(E10/B10,0) | J10: 20 | K10: 33 | L10: 78 | M10: 80 | N10: =IFERROR((G10*3+H10*2+L10)/6,0) | O10: =IF(N10="","",IF(N10>0.7,"Hausse",IF(N10<0.4,"Baisse","Stable"))) | P10: Q1 2025
A11: Maintenance & Technique | B11: 2 | C11: 0 | D11: 0 | E11: 0 | F11: 0 | G11: =IFERROR(C11/B11,0) | H11: =IFERROR(D11/B11,0) | I11: =IFERROR(E11/B11,0) | J11: 24 | K11: 50 | L11: 78 | M11: 80 | N11: =IFERROR((G11*3+H11*2+L11)/6,0) | O11: =IF(N11="","",IF(N11>0.7,"Hausse",IF(N11<0.4,"Baisse","Stable"))) | P11: Q1 2025
G12: =IFERROR(C12/B12,0) | H12: =IFERROR(D12/B12,0) | I12: =IFERROR(E12/B12,0) | N12: =IFERROR((G12*3+H12*2+L12)/6,0) | O12: =IF(N12="","",IF(N12>0.7,"Hausse",IF(N12<0.4,"Baisse","Stable")))
G13: =IFERROR(C13/B13,0) | H13: =IFERROR(D13/B13,0) | I13: =IFERROR(E13/B13,0) | N13: =IFERROR((G13*3+H13*2+L13)/6,0) | O13: =IF(N13="","",IF(N13>0.7,"Hausse",IF(N13<0.4,"Baisse","Stable")))
G14: =IFERROR(C14/B14,0) | H14: =IFERROR(D14/B14,0) | I14: =IFERROR(E14/B14,0) | N14: =IFERROR((G14*3+H14*2+L14)/6,0) | O14: =IF(N14="","",IF(N14>0.7,"Hausse",IF(N14<0.4,"Baisse","Stable")))
G15: =IFERROR(C15/B15,0) | H15: =IFERROR(D15/B15,0) | I15: =IFERROR(E15/B15,0) | N15: =IFERROR((G15*3+H15*2+L15)/6,0) | O15: =IF(N15="","",IF(N15>0.7,"Hausse",IF(N15<0.4,"Baisse","Stable")))
G16: =IFERROR(C16/B16,0) | H16: =IFERROR(D16/B16,0) | I16: =IFERROR(E16/B16,0) | N16: =IFERROR((G16*3+H16*2+L16)/6,0) | O16: =IF(N16="","",IF(N16>0.7,"Hausse",IF(N16<0.4,"Baisse","Stable")))
G17: =IFERROR(C17/B17,0) | H17: =IFERROR(D17/B17,0) | I17: =IFERROR(E17/B17,0) | N17: =IFERROR((G17*3+H17*2+L17)/6,0) | O17: =IF(N17="","",IF(N17>0.7,"Hausse",IF(N17<0.4,"Baisse","Stable")))
G18: =IFERROR(C18/B18,0) | H18: =IFERROR(D18/B18,0) | I18: =IFERROR(E18/B18,0) | N18: =IFERROR((G18*3+H18*2+L18)/6,0) | O18: =IF(N18="","",IF(N18>0.7,"Hausse",IF(N18<0.4,"Baisse","Stable")))
G19: =IFERROR(C19/B19,0) | H19: =IFERROR(D19/B19,0) | I19: =IFERROR(E19/B19,0) | N19: =IFERROR((G19*3+H19*2+L19)/6,0) | O19: =IF(N19="","",IF(N19>0.7,"Hausse",IF(N19<0.4,"Baisse","Stable")))
G20: =IFERROR(C20/B20,0) | H20: =IFERROR(D20/B20,0) | I20: =IFERROR(E20/B20,0) | N20: =IFERROR((G20*3+H20*2+L20)/6,0) | O20: =IF(N20="","",IF(N20>0.7,"Hausse",IF(N20<0.4,"Baisse","Stable")))
G21: =IFERROR(C21/B21,0) | H21: =IFERROR(D21/B21,0) | I21: =IFERROR(E21/B21,0) | N21: =IFERROR((G21*3+H21*2+L21)/6,0) | O21: =IF(N21="","",IF(N21>0.7,"Hausse",IF(N21<0.4,"Baisse","Stable")))
G22: =IFERROR(C22/B22,0) | H22: =IFERROR(D22/B22,0) | I22: =IFERROR(E22/B22,0) | N22: =IFERROR((G22*3+H22*2+L22)/6,0) | O22: =IF(N22="","",IF(N22>0.7,"Hausse",IF(N22<0.4,"Baisse","Stable")))
G23: =IFERROR(C23/B23,0) | H23: =IFERROR(D23/B23,0) | I23: =IFERROR(E23/B23,0) | N23: =IFERROR((G23*3+H23*2+L23)/6,0) | O23: =IF(N23="","",IF(N23>0.7,"Hausse",IF(N23<0.4,"Baisse","Stable")))
... G115: =IFERROR(C115/B115,0) | H115: =IFERROR(D115/B115,0) | I115: =IFERROR(E115/B115,0) | N115: =IFERROR((G115*3+H115*2+L115)/6,0) | O115: =IF(N115="","",IF(N115>0.7,"Hausse",IF(N115<0.4,"Baisse","Stable")))

Sheet F13 - 11-Plan Format. Carrière
A2: DOMAINE 28 — PLAN DE FORMATION LIÉ À LA CARRIÈRE
A3: Formations planifiées pour le développement professionnel et la progression
A5: Code Formation | B5: Intitulé | C5: Département | D5: Formateur | E5: Nb Participants | F5: Coût Unit. (FCFA) | G5: Coût Total (FCFA) | H5: Date Début | I5: Date Fin | J5: Durée (heures) | K5: Statut | L5: Taux Réussite (%) | M5: Impact Carrière
A6: FCAR-001 | B6: Leadership Stratégique | C6: Direction Générale | D6: Cabinet Externe | E6: 2 | F6: 2500000 | G6: =E6*F6 | H6: 2025-04-01 | I6: 2025-06-30 | J6: 120 | K6: En cours | L6: =IF(K6="Terminée",IFERROR(ROUND(RAND()*20+75,1),0),0) | M6: Accès DG adjoint
A7: FCAR-002 | B7: Gestion des Talents RH | C7: Ressources Humaines | D7: Mme. Mbarga | E7: 3 | F7: 500000 | G7: =E7*F7 | H7: 2025-03-01 | I7: 2025-05-31 | J7: 80 | K7: Terminée | L7: =IF(K7="Terminée",IFERROR(ROUND(RAND()*20+75,1),0),0) | M7: Promotion interne
A8: FCAR-003 | B8: Certification IFRS | C8: Finance & Comptabilité | D8: Expert Comptable | E8: 2 | F8: 1500000 | G8: =E8*F8 | H8: 2025-05-01 | I8: 2025-11-30 | J8: 200 | K8: Planifiée | L8: =IF(K8="Terminée",IFERROR(ROUND(RAND()*20+75,1),0),0) | M8: Validation compétences
A9: FCAR-004 | B9: Management Hôtelier | C9: Réception & Front Office | D9: École Hôtellerie | E9: 3 | F9: 800000 | G9: =E9*F9 | H9: 2025-06-01 | I9: 2025-08-31 | J9: 100 | K9: Planifiée | L9: =IF(K9="Terminée",IFERROR(ROUND(RAND()*20+75,1),0),0) | M9: Promotion Resp.
A10: FCAR-005 | B10: HACCP Niveau 2 | C10: Cuisine & Restauration | D10: Bureau Veritas | E10: 2 | F10: 350000 | G10: =E10*F10 | H10: 2025-03-15 | I10: 2025-04-15 | J10: 40 | K10: Terminée | L10: =IF(K10="Terminée",IFERROR(ROUND(RAND()*20+75,1),0),0) | M10: Maintien poste
G11: =E11*F11 | L11: =IF(K11="Terminée",IFERROR(ROUND(RAND()*20+75,1),0),0)
G12: =E12*F12 | L12: =IF(K12="Terminée",IFERROR(ROUND(RAND()*20+75,1),0),0)
G13: =E13*F13 | L13: =IF(K13="Terminée",IFERROR(ROUND(RAND()*20+75,1),0),0)
G14: =E14*F14 | L14: =IF(K14="Terminée",IFERROR(ROUND(RAND()*20+75,1),0),0)
G15: =E15*F15 | L15: =IF(K15="Terminée",IFERROR(ROUND(RAND()*20+75,1),0),0)
G16: =E16*F16 | L16: =IF(K16="Terminée",IFERROR(ROUND(RAND()*20+75,1),0),0)
G17: =E17*F17 | L17: =IF(K17="Terminée",IFERROR(ROUND(RAND()*20+75,1),0),0)
G18: =E18*F18 | L18: =IF(K18="Terminée",IFERROR(ROUND(RAND()*20+75,1),0),0)
G19: =E19*F19 | L19: =IF(K19="Terminée",IFERROR(ROUND(RAND()*20+75,1),0),0)
G20: =E20*F20 | L20: =IF(K20="Terminée",IFERROR(ROUND(RAND()*20+75,1),0),0)
G21: =E21*F21 | L21: =IF(K21="Terminée",IFERROR(ROUND(RAND()*20+75,1),0),0)
G22: =E22*F22 | L22: =IF(K22="Terminée",IFERROR(ROUND(RAND()*20+75,1),0),0)
... G115: =E115*F115 | L115: =IF(K115="Terminée",IFERROR(ROUND(RAND()*20+75,1),0),0)

Sheet F14 - 12-Réseau Mentorat Coach.
A2: DOMAINE 28 — RÉSEAU DE MENTORAT ET COACHING
A3: Suivi des relations mentor-mentoré et des programmes de coaching
A5: N° Paire | B5: Code Mentoré | C5: Nom Mentoré | D5: Code Mentor | E5: Nom Mentor | F5: Département | G5: Type Accompagnement | H5: Date Début | I5: Date Fin | J5: Nb Sessions Planifiées | K5: Nb Sessions Réalisées | L5: Taux Complétion (%) | M5: Objectif Principal | N5: Statut | O5: Bilan
A6: MCO-001 | B6: EMP-007 | C6: Mme. Essomba Sylvie | D6: EMP-002 | E6: Mme. Mbarga Claire | F6: Ressources Humaines | G6: Mentorat | H6: 2024-06-01 | I6: 2025-12-31 | J6: 24 | K6: 14 | L6: =IFERROR(K6/J6,0) | M6: Préparation DRH | N6: Actif | O6: Progression remarquable
A7: MCO-002 | B7: EMP-005 | C7: Mme. Ngassa Marie | D7: EMP-002 | E7: Mme. Mbarga Claire | F7: Réception & Front Office | G7: Coaching | H7: 2025-01-01 | I7: 2025-12-31 | J7: 12 | K7: 4 | L7: =IFERROR(K7/J7,0) | M7: Leadership | N7: Actif | O7: Bonne dynamique
A8: MCO-003 | B8: EMP-010 | C8: M. Ndong Aurélien | D8: EMP-006 | E8: M. Ondo Ferdinand | F8: Maintenance & Technique | G8: Mentorat | H8: 2025-02-01 | I8: 2025-11-30 | J8: 18 | K8: 8 | L8: =IFERROR(K8/J8,0) | M8: Promotion Chef | N8: Actif | O8: Apprentissage technique
A9: MCO-004 | B9: EMP-003 | C9: M. Eyenga René | D9: EXT-001 | E9: Dr. Nganou (Ext.) | F9: Finance & Comptabilité | G9: Coaching Externe | H9: 2025-01-15 | I9: 2025-07-15 | J9: 12 | K9: 6 | L9: =IFERROR(K9/J9,0) | M9: Leadership DG | N9: Actif | O9: Renforcement vision
A10: MCO-005 | B10: EMP-004 | C10: M. Tchinda Jean | D10: EMP-006 | E10: M. Ondo Ferdinand | F10: Cuisine & Restauration | G10: Mentorat | H10: 2025-03-01 | I10: 2025-09-30 | J10: 12 | K10: 3 | L10: =IFERROR(K10/J10,0) | M10: Transition technique | N10: En pause | O10: Réorganisation en cours
L11: =IFERROR(K11/J11,0)
L12: =IFERROR(K12/J12,0)
L13: =IFERROR(K13/J13,0)
L14: =IFERROR(K14/J14,0)
L15: =IFERROR(K15/J15,0)
L16: =IFERROR(K16/J16,0)
L17: =IFERROR(K17/J17,0)
L18: =IFERROR(K18/J18,0)
L19: =IFERROR(K19/J19,0)
L20: =IFERROR(K20/J20,0)
L21: =IFERROR(K21/J21,0)
L22: =IFERROR(K22/J22,0)
... L115: =IFERROR(K115/J115,0)

Sheet F15 - 13-Budget Mobilité Carr.
A2: DOMAINE 28 — BUDGET MOBILITÉ & CARRIÈRE
A3: Suivi budgétaire par catégorie et par trimestre pour la mobilité et les carrières
A5: Code Budget | B5: Catégorie | C5: Département | D5: Q1 (FCFA) | E5: Q2 (FCFA) | F5: Q3 (FCFA) | G5: Q4 (FCFA) | H5: Total Annuel (FCFA) | I5: Consommé (FCFA) | J5: Reste (FCFA) | K5: Taux Consommation (%) | L5: Écart (FCFA) | M5: Statut
A6: BMC-001 | B6: Formation | C6: Ressources Humaines | D6: 4000000 | E6: 3500000 | F6: 3000000 | G6: 3500000 | H6: =SUM(D6:G6) | I6: 8500000 | J6: =H6-I6 | K6: =IFERROR(I6/H6,0) | L6: =H6-I6 | M6: En cours
A7: BMC-002 | B7: Formation | C7: Direction Générale | D7: 5000000 | E7: 3000000 | F7: 2000000 | G7: 3000000 | H7: =SUM(D7:G7) | I7: 7500000 | J7: =H7-I7 | K7: =IFERROR(I7/H7,0) | L7: =H7-I7 | M7: En cours
A8: BMC-003 | B8: Mobilité | C8: Tous départements | D8: 2000000 | E8: 1500000 | F8: 2500000 | G8: 2000000 | H8: =SUM(D8:G8) | I8: 4500000 | J8: =H8-I8 | K8: =IFERROR(I8/H8,0) | L8: =H8-I8 | M8: En cours
A9: BMC-004 | B9: Coaching | C9: Tous départements | D9: 1500000 | E9: 1000000 | F9: 1500000 | G9: 1000000 | H9: =SUM(D9:G9) | I9: 2800000 | J9: =H9-I9 | K9: =IFERROR(I9/H9,0) | L9: =H9-I9 | M9: En cours
A10: BMC-005 | B10: Mentorat | C10: Tous départements | D10: 500000 | E10: 500000 | F10: 500000 | G10: 500000 | H10: =SUM(D10:G10) | I10: 900000 | J10: =H10-I10 | K10: =IFERROR(I10/H10,0) | L10: =H10-I10 | M10: En cours
A11: BMC-006 | B11: Expatriation | C11: Finance & Comptabilité | D11: 6000000 | E11: 6000000 | F11: 6500000 | G11: 6500000 | H11: =SUM(D11:G11) | I11: 12000000 | J11: =H11-I11 | K11: =IFERROR(I11/H11,0) | L11: =H11-I11 | M11: En cours
A12: BMC-007 | B12: Évaluation | C12: Tous départements | D12: 300000 | E12: 200000 | F12: 300000 | G12: 200000 | H12: =SUM(D12:G12) | I12: 500000 | J12: =H12-I12 | K12: =IFERROR(I12/H12,0) | L12: =H12-I12 | M12: En cours
A13: BMC-008 | B13: Outils RH | C13: Ressources Humaines | D13: 1000000 | E13: 500000 | F13: 500000 | G13: 500000 | H13: =SUM(D13:G13) | I13: 1200000 | J13: =H13-I13 | K13: =IFERROR(I13/H13,0) | L13: =H13-I13 | M13: En cours
H14: =SUM(D14:G14) | J14: =H14-I14 | K14: =IFERROR(I14/H14,0) | L14: =H14-I14
H15: =SUM(D15:G15) | J15: =H15-I15 | K15: =IFERROR(I15/H15,0) | L15: =H15-I15
H16: =SUM(D16:G16) | J16: =H16-I16 | K16: =IFERROR(I16/H16,0) | L16: =H16-I16
H17: =SUM(D17:G17) | J17: =H17-I17 | K17: =IFERROR(I17/H17,0) | L17: =H17-I17
H18: =SUM(D18:G18) | J18: =H18-I18 | K18: =IFERROR(I18/H18,0) | L18: =H18-I18
H19: =SUM(D19:G19) | J19: =H19-I19 | K19: =IFERROR(I19/H19,0) | L19: =H19-I19
H20: =SUM(D20:G20) | J20: =H20-I20 | K20: =IFERROR(I20/H20,0) | L20: =H20-I20
H21: =SUM(D21:G21) | J21: =H21-I21 | K21: =IFERROR(I21/H21,0) | L21: =H21-I21
H22: =SUM(D22:G22) | J22: =H22-I22 | K22: =IFERROR(I22/H22,0) | L22: =H22-I22
H23: =SUM(D23:G23) | J23: =H23-I23 | K23: =IFERROR(I23/H23,0) | L23: =H23-I23
H24: =SUM(D24:G24) | J24: =H24-I24 | K24: =IFERROR(I24/H24,0) | L24: =H24-I24
H25: =SUM(D25:G25) | J25: =H25-I25 | K25: =IFERROR(I25/H25,0) | L25: =H25-I25
... H115: =SUM(D115:G115) | J115: =H115-I115 | K115: =IFERROR(I115/H115,0) | L115: =H115-I115

Sheet F16 - 14-Reporting Mensuel MC
A2: DOMAINE 28 — REPORTING MENSUEL MOBILITÉ & CARRIÈRE
A3: Synthèse mensuelle des activités de mobilité et de gestion des carrières
A5: Mois | B5: Nb Demandes Mobilité | C5: Nb Demandes Approuvées | D5: Nb Promotions Effectuées | E5: Nb Entretiens Réalisés | F5: Nb Formations Terminées | G5: Nb Sessions Mentorat | H5: Coût Total Mois (FCFA) | I5: Taux Satisfaction (%) | J5: Nb Départs | K5: Taux Rétention (%) | L5: Commentaires
A6: Janvier 2025 | B6: 3 | C6: 1 | D6: 0 | E6: 4 | F6: 0 | G6: 6 | H6: 3200000 | I6: 82 | J6: 0 | K6: =IFERROR((B6-J6)/B6,0) | L6: Démarrage année, planifications
A7: Février 2025 | B7: 2 | C7: 1 | D7: 0 | E7: 5 | F7: 1 | G7: 5 | H7: 2800000 | I7: 85 | J7: 0 | K7: =IFERROR((B7-J7)/B7,0) | L7: Premières formations terminées
A8: Mars 2025 | B8: 4 | C8: 2 | D8: 1 | E8: 6 | F8: 1 | G8: 7 | H8: 4100000 | I8: 88 | J8: 0 | K8: =IFERROR((B8-J8)/B8,0) | L8: Mobilité active, promotions Q1
A9: Avril 2025 | B9: 2 | C9: 0 | D9: 0 | E9: 3 | F9: 0 | G9: 5 | H9: 3500000 | I9: 80 | J9: 1 | K9: =IFERROR((B9-J9)/B9,0) | L9: Ralentissement congés Pâques
A10: Mai 2025 | B10: 3 | C10: 1 | D10: 0 | E10: 4 | F10: 0 | G10: 6 | H10: 2900000 | I10: 83 | J10: 0 | K10: =IFERROR((B10-J10)/B10,0) | L10: Reprise des activités
A11: Juin 2025 | B11: 5 | C11: 2 | D11: 1 | E11: 7 | F11: 2 | G11: 8 | H11: 5200000 | I11: 87 | J11: 0 | K11: =IFERROR((B11-J11)/B11,0) | L11: Bilan semestriel positif
K12: =IFERROR((B12-J12)/B12,0)
K13: =IFERROR((B13-J13)/B13,0)
K14: =IFERROR((B14-J14)/B14,0)
K15: =IFERROR((B15-J15)/B15,0)
K16: =IFERROR((B16-J16)/B16,0)
K17: =IFERROR((B17-J17)/B17,0)
K18: =IFERROR((B18-J18)/B18,0)
K19: =IFERROR((B19-J19)/B19,0)
K20: =IFERROR((B20-J20)/B20,0)
K21: =IFERROR((B21-J21)/B21,0)
K22: =IFERROR((B22-J22)/B22,0)
K23: =IFERROR((B23-J23)/B23,0)
... K115: =IFERROR((B115-J115)/B115,0)

Sheet F17 - 15-Analyse Coûts Départ.
A2: DOMAINE 28 — ANALYSE DES COÛTS PAR DÉPARTEMENT
A3: Ventilation des coûts de mobilité et de carrière par département
A5: Département | B5: Coût Formation (FCFA) | C5: Coût Mobilité (FCFA) | D5: Coût Coaching (FCFA) | E5: Coût Expatriation (FCFA) | F5: Coût Évaluation (FCFA) | G5: Total Coûts (FCFA) | H5: Effectif | I5: Coût Moyen/Personne (FCFA) | J5: % du Budget Total | K5: Écart vs Budget (FCFA) | L5: Écart vs Budget (%) | M5: Tendance
A6: Direction Générale | B6: 8000000 | C6: 0 | D6: 3000000 | E6: 0 | F6: 200000 | G6: =SUM(B6:F6) | H6: 3 | I6: =IFERROR(G6/H6,0) | J6: =IFERROR(G6/SUM(G$6:G$11),0) | K6: 8000000 | L6: =K6-G6 | M6: =IFERROR(L6/K6,0)
A7: Ressources Humaines | B7: 5000000 | C7: 500000 | D7: 1500000 | E7: 3500000 | F7: 150000 | G7: =SUM(B7:F7) | H7: 4 | I7: =IFERROR(G7/H7,0) | J7: =IFERROR(G7/SUM(G$6:G$11),0) | K7: 6000000 | L7: =K7-G7 | M7: =IFERROR(L7/K7,0)
A8: Finance & Comptabilité | B8: 3000000 | C8: 0 | D8: 1000000 | E8: 12000000 | F8: 100000 | G8: =SUM(B8:F8) | H8: 3 | I8: =IFERROR(G8/H8,0) | J8: =IFERROR(G8/SUM(G$6:G$11),0) | K8: 10000000 | L8: =K8-G8 | M8: =IFERROR(L8/K8,0)
A9: Cuisine & Restauration | B9: 700000 | C9: 300000 | D9: 0 | E9: 0 | F9: 50000 | G9: =SUM(B9:F9) | H9: 2 | I9: =IFERROR(G9/H9,0) | J9: =IFERROR(G9/SUM(G$6:G$11),0) | K9: 2000000 | L9: =K9-G9 | M9: =IFERROR(L9/K9,0)
A10: Réception & Front Office | B10: 1200000 | C10: 400000 | D10: 500000 | E10: 0 | F10: 80000 | G10: =SUM(B10:F10) | H10: 3 | I10: =IFERROR(G10/H10,0) | J10: =IFERROR(G10/SUM(G$6:G$11),0) | K10: 3000000 | L10: =K10-G10 | M10: =IFERROR(L10/K10,0)
A11: Maintenance & Technique | B11: 800000 | C11: 200000 | D11: 300000 | E11: 0 | F11: 70000 | G11: =SUM(B11:F11) | H11: 2 | I11: =IFERROR(G11/H11,0) | J11: =IFERROR(G11/SUM(G$6:G$11),0) | K11: 1500000 | L11: =K11-G11 | M11: =IFERROR(L11/K11,0)
G12: =SUM(B12:F12) | I12: =IFERROR(G12/H12,0) | J12: =IFERROR(G12/SUM(G$6:G$11),0) | L12: =K12-G12 | M12: =IFERROR(L12/K12,0) | N12: =IF(M12="","",IF(M12>0,"Sous-budget",IF(M12<0,"Sur-budget","Au budget")))
G13: =SUM(B13:F13) | I13: =IFERROR(G13/H13,0) | J13: =IFERROR(G13/SUM(G$6:G$11),0) | L13: =K13-G13 | M13: =IFERROR(L13/K13,0) | N13: =IF(M13="","",IF(M13>0,"Sous-budget",IF(M13<0,"Sur-budget","Au budget")))
G14: =SUM(B14:F14) | I14: =IFERROR(G14/H14,0) | J14: =IFERROR(G14/SUM(G$6:G$11),0) | L14: =K14-G14 | M14: =IFERROR(L14/K14,0) | N14: =IF(M14="","",IF(M14>0,"Sous-budget",IF(M14<0,"Sur-budget","Au budget")))
G15: =SUM(B15:F15) | I15: =IFERROR(G15/H15,0) | J15: =IFERROR(G15/SUM(G$6:G$11),0) | L15: =K15-G15 | M15: =IFERROR(L15/K15,0) | N15: =IF(M15="","",IF(M15>0,"Sous-budget",IF(M15<0,"Sur-budget","Au budget")))
G16: =SUM(B16:F16) | I16: =IFERROR(G16/H16,0) | J16: =IFERROR(G16/SUM(G$6:G$11),0) | L16: =K16-G16 | M16: =IFERROR(L16/K16,0) | N16: =IF(M16="","",IF(M16>0,"Sous-budget",IF(M16<0,"Sur-budget","Au budget")))
G17: =SUM(B17:F17) | I17: =IFERROR(G17/H17,0) | J17: =IFERROR(G17/SUM(G$6:G$11),0) | L17: =K17-G17 | M17: =IFERROR(L17/K17,0) | N17: =IF(M17="","",IF(M17>0,"Sous-budget",IF(M17<0,"Sur-budget","Au budget")))
G18: =SUM(B18:F18) | I18: =IFERROR(G18/H18,0) | J18: =IFERROR(G18/SUM(G$6:G$11),0) | L18: =K18-G18 | M18: =IFERROR(L18/K18,0) | N18: =IF(M18="","",IF(M18>0,"Sous-budget",IF(M18<0,"Sur-budget","Au budget")))
G19: =SUM(B19:F19) | I19: =IFERROR(G19/H19,0) | J19: =IFERROR(G19/SUM(G$6:G$11),0) | L19: =K19-G19 | M19: =IFERROR(L19/K19,0) | N19: =IF(M19="","",IF(M19>0,"Sous-budget",IF(M19<0,"Sur-budget","Au budget")))
G20: =SUM(B20:F20) | I20: =IFERROR(G20/H20,0) | J20: =IFERROR(G20/SUM(G$6:G$11),0) | L20: =K20-G20 | M20: =IFERROR(L20/K20,0) | N20: =IF(M20="","",IF(M20>0,"Sous-budget",IF(M20<0,"Sur-budget","Au budget")))
G21: =SUM(B21:F21) | I21: =IFERROR(G21/H21,0) | J21: =IFERROR(G21/SUM(G$6:G$11),0) | L21: =K21-G21 | M21: =IFERROR(L21/K21,0) | N21: =IF(M21="","",IF(M21>0,"Sous-budget",IF(M21<0,"Sur-budget","Au budget")))
G22: =SUM(B22:F22) | I22: =IFERROR(G22/H22,0) | J22: =IFERROR(G22/SUM(G$6:G$11),0) | L22: =K22-G22 | M22: =IFERROR(L22/K22,0) | N22: =IF(M22="","",IF(M22>0,"Sous-budget",IF(M22<0,"Sur-budget","Au budget")))
G23: =SUM(B23:F23) | I23: =IFERROR(G23/H23,0) | J23: =IFERROR(G23/SUM(G$6:G$11),0) | L23: =K23-G23 | M23: =IFERROR(L23/K23,0) | N23: =IF(M23="","",IF(M23>0,"Sous-budget",IF(M23<0,"Sur-budget","Au budget")))
... G115: =SUM(B115:F115) | I115: =IFERROR(G115/H115,0) | J115: =IFERROR(G115/SUM(G$6:G$11),0) | L115: =K115-G115 | M115: =IFERROR(L115/K115,0) | N115: =IF(M115="","",IF(M115>0,"Sous-budget",IF(M115<0,"Sur-budget","Au budget")))

Sheet F18 - 16-Simul. Scénar. MC
A2: DOMAINE 28 — SIMULATIONS DE SCÉNARIOS MOBILITÉ & CARRIÈRE
A3: Modélisation d'impact de différents scénarios de mobilité sur l'organisation
A5: Scénario | B5: Description | C5: Nb Promotions | D5: Nb Mobilités Internes | E5: Coût Estimé (FCFA) | F5: Impact Rétention (%) | G5: Impact Performance (%) | H5: Risque Organique | I5: Délai Mise en Œuvre (mois) | J5: Rentabilité | K5: Recommandation | L5: Statut
A6: SC-01 | B6: Plan de promotion massif | C6: 8 | D6: 5 | E6: 15000000 | F6: 15 | G6: 10 | H6: Moyen | I6: 3 | J6: Élevée | K6: Recommandé | L6: Étudié
A7: SC-02 | B7: Mobilité interne généralisée | C7: 3 | D7: 12 | E7: 8000000 | F7: 20 | G7: 5 | H7: Faible | I7: 6 | J7: Très élevée | K7: Fortement recommandé | L7: Étudié
A8: SC-03 | B8: Programme expatriation étendu | C8: 2 | D8: 2 | E8: 25000000 | F8: 10 | G8: 15 | H8: Élevé | I8: 12 | J8: Moyenne | K8: Conditionnel | L8: En analyse
A9: SC-04 | B9: Mentorat systématique | C9: 0 | D9: 0 | E9: 2000000 | F9: 25 | G9: 12 | H9: Faible | I9: 1 | J9: Très élevée | K9: Fortement recommandé | L9: Validé
A10: SC-05 | B10: Formation certification massive | C10: 0 | D10: 0 | E10: 12000000 | F10: 8 | G10: 18 | H10: Faible | I10: 6 | J10: Élevée | K10: Recommandé | L10: Étudié
A11: SC-06 | B11: Externalisation postes clés | C11: -5 | D11: 0 | E11: 5000000 | F11: -5 | G11: 8 | H11: Très élevé | I11: 2 | J11: Faible | K11: Non recommandé | L11: Rejeté
A12: SC-07 | B12: Gel des mobilités (statu quo) | C12: 0 | D12: 0 | E12: 500000 | F12: -15 | G12: -5 | H12: Élevé | I12: 0 | J12: Négative | K12: Déconseillé | L12: Rejeté
A13: =IF(A12="","",A12)
A14: =IF(A13="","",A13)
A15: =IF(A14="","",A14)
A16: =IF(A15="","",A15)
A17: =IF(A16="","",A16)
A18: =IF(A17="","",A17)
A19: =IF(A18="","",A18)
A20: =IF(A19="","",A19)
A21: =IF(A20="","",A20)
A22: =IF(A21="","",A21)
A23: =IF(A22="","",A22)
A24: =IF(A23="","",A23)
... A115: =IF(A114="","",A114)

Sheet F19 - 17-TdB Consolidé MC
A2: DOMAINE 28 — TABLEAU DE BORD CONSOLIDÉ MOBILITÉ & CARRIÈRE
A3: Vue consolidée trimestrielle de tous les indicateurs mobilité et carrière
A5: Trimestre | B5: Effectif Total | C5: Promotions | D5: Mobilités Internes | E5: Mobilités Internationales | F5: Départs | G5: Taux Mobilité (%) | H5: Taux Rétention (%) | I5: Coût Total (FCFA) | J5: Budget Consommé (%) | K5: Nb Formations | L5: Nb Sessions Mentorat | M5: Satisfaction Moyenne (%) | N5: Indice Santé Carrière | O5: Statut Global
A6: Q1 2025 | B6: 17 | C6: 1 | D6: 2 | E6: 1 | F6: 0 | G6: =IFERROR((C6+D6+E6)/B6,0) | H6: =IFERROR((B6-F6)/B6,0) | I6: 10100000 | J6: =IFERROR(I6/30500000,0) | K6: 2 | L6: 18 | M6: 85 | N6: =IFERROR((G6*3+H6*2+M6)/6,0) | O6: Bon
A7: Q2 2025 | B7: 17 | C7: 1 | D7: 1 | E7: 1 | F7: 1 | G7: =IFERROR((C7+D7+E7)/B7,0) | H7: =IFERROR((B7-F7)/B7,0) | I7: 11600000 | J7: =IFERROR(I7/30500000,0) | K7: 2 | L7: 19 | M7: 87 | N7: =IFERROR((G7*3+H7*2+M7)/6,0) | O7: Bon
A8: Q3 2025 | B8: 16 | C8: 0 | D8: 2 | E8: 0 | F8: 0 | G8: =IFERROR((C8+D8+E8)/B8,0) | H8: =IFERROR((B8-F8)/B8,0) | I8: 8400000 | J8: =IFERROR(I8/30500000,0) | K8: 1 | L8: 15 | M8: 84 | N8: =IFERROR((G8*3+H8*2+M8)/6,0) | O8: Moyen
A9: Q4 2025 | B9: 16 | C9: 1 | D9: 1 | E9: 1 | F9: 0 | G9: =IFERROR((C9+D9+E9)/B9,0) | H9: =IFERROR((B9-F9)/B9,0) | I9: 9500000 | J9: =IFERROR(I9/30500000,0) | K9: 2 | L9: 16 | M9: 86 | N9: =IFERROR((G9*3+H9*2+M9)/6,0) | O9: Bon
G10: =IFERROR((C10+D10+E10)/B10,0) | H10: =IFERROR((B10-F10)/B10,0) | J10: =IFERROR(I10/30500000,0) | N10: =IFERROR((G10*3+H10*2+M10)/6,0)
G11: =IFERROR((C11+D11+E11)/B11,0) | H11: =IFERROR((B11-F11)/B11,0) | J11: =IFERROR(I11/30500000,0) | N11: =IFERROR((G11*3+H11*2+M11)/6,0)
G12: =IFERROR((C12+D12+E12)/B12,0) | H12: =IFERROR((B12-F12)/B12,0) | J12: =IFERROR(I12/30500000,0) | N12: =IFERROR((G12*3+H12*2+M12)/6,0)
G13: =IFERROR((C13+D13+E13)/B13,0) | H13: =IFERROR((B13-F13)/B13,0) | J13: =IFERROR(I13/30500000,0) | N13: =IFERROR((G13*3+H13*2+M13)/6,0)
G14: =IFERROR((C14+D14+E14)/B14,0) | H14: =IFERROR((B14-F14)/B14,0) | J14: =IFERROR(I14/30500000,0) | N14: =IFERROR((G14*3+H14*2+M14)/6,0)
G15: =IFERROR((C15+D15+E15)/B15,0) | H15: =IFERROR((B15-F15)/B15,0) | J15: =IFERROR(I15/30500000,0) | N15: =IFERROR((G15*3+H15*2+M15)/6,0)
G16: =IFERROR((C16+D16+E16)/B16,0) | H16: =IFERROR((B16-F16)/B16,0) | J16: =IFERROR(I16/30500000,0) | N16: =IFERROR((G16*3+H16*2+M16)/6,0)
G17: =IFERROR((C17+D17+E17)/B17,0) | H17: =IFERROR((B17-F17)/B17,0) | J17: =IFERROR(I17/30500000,0) | N17: =IFERROR((G17*3+H17*2+M17)/6,0)
G18: =IFERROR((C18+D18+E18)/B18,0) | H18: =IFERROR((B18-F18)/B18,0) | J18: =IFERROR(I18/30500000,0) | N18: =IFERROR((G18*3+H18*2+M18)/6,0)
G19: =IFERROR((C19+D19+E19)/B19,0) | H19: =IFERROR((B19-F19)/B19,0) | J19: =IFERROR(I19/30500000,0) | N19: =IFERROR((G19*3+H19*2+M19)/6,0)
G20: =IFERROR((C20+D20+E20)/B20,0) | H20: =IFERROR((B20-F20)/B20,0) | J20: =IFERROR(I20/30500000,0) | N20: =IFERROR((G20*3+H20*2+M20)/6,0)
G21: =IFERROR((C21+D21+E21)/B21,0) | H21: =IFERROR((B21-F21)/B21,0) | J21: =IFERROR(I21/30500000,0) | N21: =IFERROR((G21*3+H21*2+M21)/6,0)
... G115: =IFERROR((C115+D115+E115)/B115,0) | H115: =IFERROR((B115-F115)/B115,0) | J115: =IFERROR(I115/30500000,0) | N115: =IFERROR((G115*3+H115*2+M115)/6,0)

Sheet F20 - 18-Indic. Performance MC
A2: DOMAINE 28 — INDICATEURS DE PERFORMANCE MOBILITÉ & CARRIÈRE
A3: 12 KPI stratégiques avec cibles, réalisations et écarts
A5: N° KPI | B5: Indicateur | C5: Cible | D5: Réalisation | E5: Écart | F5: Taux Atteinte (%) | G5: Tendance | H5: Responsable | I5: Action Corrective
A6: KPI-01 | B6: Taux de promotion annuel | C6: 15% | D6: 12% | E6: =IFERROR(D6-C6,0) | F6: =IFERROR(D6/C6,0) | G6: =IF(E6="","",IF(E6>0,"Hausse",IF(E6<0,"Baisse","Stable"))) | H6: DRH | I6: Accélérer promotions Q3-Q4
A7: KPI-02 | B7: Taux de mobilité interne | C7: 20% | D7: 18% | E7: =IFERROR(D7-C7,0) | F7: =IFERROR(D7/C7,0) | G7: =IF(E7="","",IF(E7>0,"Hausse",IF(E7<0,"Baisse","Stable"))) | H7: DRH | I7: Encourager les mutations
A8: KPI-03 | B8: Taux de rétention talents | C8: 90% | D8: 94% | E8: =IFERROR(D8-C8,0) | F8: =IFERROR(D8/C8,0) | G8: =IF(E8="","",IF(E8>0,"Hausse",IF(E8<0,"Baisse","Stable"))) | H8: DRH | I8: Maintenir les programmes actuels
A9: KPI-04 | B9: Successeurs identifiés (postes clés) | C9: 80% | D9: 50% | E9: =IFERROR(D9-C9,0) | F9: =IFERROR(D9/C9,0) | G9: =IF(E9="","",IF(E9>0,"Hausse",IF(E9<0,"Baisse","Stable"))) | H9: DRH | I9: Urgence plan succession
A10: KPI-05 | B10: Taux de complétion formations carrière | C10: 85% | D10: 78% | E10: =IFERROR(D10-C10,0) | F10: =IFERROR(D10/C10,0) | G10: =IF(E10="","",IF(E10>0,"Hausse",IF(E10<0,"Baisse","Stable"))) | H10: Resp. Formation | I10: Suivi renforcé
A11: KPI-06 | B11: Satisfaction entretiens carrière | C11: 80% | D11: 85% | E11: =IFERROR(D11-C11,0) | F11: =IFERROR(D11/C11,0) | G11: =IF(E11="","",IF(E11>0,"Hausse",IF(E11<0,"Baisse","Stable"))) | H11: DRH | I11: Poursuire le programme actuel
A12: KPI-07 | B12: Coût moyen formation/employé | C12: 150000 | D12: 175000 | E12: =IFERROR(D12-C12,0) | F12: =IFERROR(D12/C12,0) | G12: =IF(E12="","",IF(E12>0,"Hausse",IF(E12<0,"Baisse","Stable"))) | H12: DAF | I12: Optimiser coûts formations
A13: KPI-08 | B13: Délai moyen de promotion (mois) | C13: 18 | D13: 22 | E13: =IFERROR(D13-C13,0) | F13: =IFERROR(D13/C13,0) | G13: =IF(E13="","",IF(E13>0,"Hausse",IF(E13<0,"Baisse","Stable"))) | H13: DRH | I13: Réduire les délais décisionnels
A14: KPI-09 | B14: Taux de participation mentorat | C14: 60% | D14: 55% | E14: =IFERROR(D14-C14,0) | F14: =IFERROR(D14/C14,0) | G14: =IF(E14="","",IF(E14>0,"Hausse",IF(E14<0,"Baisse","Stable"))) | H14: DRH | I14: Élargir le réseau mentor
A15: KPI-10 | B15: Indice santé carrière global | C15: 0.75 | D15: 0.68 | E15: =IFERROR(D15-C15,0) | F15: =IFERROR(D15/C15,0) | G15: =IF(E15="","",IF(E15>0,"Hausse",IF(E15<0,"Baisse","Stable"))) | H15: DG | I15: Programme transversal carrières
A16: KPI-11 | B16: Nb mobilités internationales | C16: 4 | D16: 3 | E16: =IFERROR(D16-C16,0) | F16: =IFERROR(D16/C16,0) | G16: =IF(E16="","",IF(E16>0,"Hausse",IF(E16<0,"Baisse","Stable"))) | H16: DG | I16: Planifier Q4
A17: KPI-12 | B17: Conformité processus mobilité (%) | C17: 95% | D17: 88% | E17: =IFERROR(D17-C17,0) | F17: =IFERROR(D17/C17,0) | G17: =IF(E17="","",IF(E17>0,"Hausse",IF(E17<0,"Baisse","Stable"))) | H17: Juridique | I17: Mise à jour procédures
E18: =IFERROR(D18-C18,0) | F18: =IFERROR(D18/C18,0) | G18: =IF(E18="","",IF(E18>0,"Hausse",IF(E18<0,"Baisse","Stable")))
E19: =IFERROR(D19-C19,0) | F19: =IFERROR(D19/C19,0) | G19: =IF(E19="","",IF(E19>0,"Hausse",IF(E19<0,"Baisse","Stable")))
E20: =IFERROR(D20-C20,0) | F20: =IFERROR(D20/C20,0) | G20: =IF(E20="","",IF(E20>0,"Hausse",IF(E20<0,"Baisse","Stable")))
E21: =IFERROR(D21-C21,0) | F21: =IFERROR(D21/C21,0) | G21: =IF(E21="","",IF(E21>0,"Hausse",IF(E21<0,"Baisse","Stable")))
E22: =IFERROR(D22-C22,0) | F22: =IFERROR(D22/C22,0) | G22: =IF(E22="","",IF(E22>0,"Hausse",IF(E22<0,"Baisse","Stable")))
E23: =IFERROR(D23-C23,0) | F23: =IFERROR(D23/C23,0) | G23: =IF(E23="","",IF(E23>0,"Hausse",IF(E23<0,"Baisse","Stable")))
E24: =IFERROR(D24-C24,0) | F24: =IFERROR(D24/C24,0) | G24: =IF(E24="","",IF(E24>0,"Hausse",IF(E24<0,"Baisse","Stable")))
E25: =IFERROR(D25-C25,0) | F25: =IFERROR(D25/C25,0) | G25: =IF(E25="","",IF(E25>0,"Hausse",IF(E25<0,"Baisse","Stable")))
E26: =IFERROR(D26-C26,0) | F26: =IFERROR(D26/C26,0) | G26: =IF(E26="","",IF(E26>0,"Hausse",IF(E26<0,"Baisse","Stable")))
E27: =IFERROR(D27-C27,0) | F27: =IFERROR(D27/C27,0) | G27: =IF(E27="","",IF(E27>0,"Hausse",IF(E27<0,"Baisse","Stable")))
E28: =IFERROR(D28-C28,0) | F28: =IFERROR(D28/C28,0) | G28: =IF(E28="","",IF(E28>0,"Hausse",IF(E28<0,"Baisse","Stable")))
E29: =IFERROR(D29-C29,0) | F29: =IFERROR(D29/C29,0) | G29: =IF(E29="","",IF(E29>0,"Hausse",IF(E29<0,"Baisse","Stable")))
... E115: =IFERROR(D115-C115,0) | F115: =IFERROR(D115/C115,0) | G115: =IF(E115="","",IF(E115>0,"Hausse",IF(E115<0,"Baisse","Stable")))

Sheet F21 - 19-Audit Conform. Réglem.
A2: DOMAINE 28 — AUDIT DE CONFORMITÉ RÉGLEMENTAIRE
A3: Vérification de la conformité des processus de mobilité et de gestion des carrières
A5: N° Exigence | B5: Article / Référence | C5: Description Exigence | D5: Conformité | E5: Preuve | F5: Date Vérification | G5: Auditeur | H5: Non-Conformité | I5: Action Corrective | J5: Délai Correction | K5: Penalité Potentielle (FCFA) | L5: Statut | M5: Observations
A6: AUD-001 | B6: Art. L1221-1 CT | C6: Contrat de mobilité écrit obligatoire | D6: Conforme | E6: Contrats archivés | F6: 2025-01-15 | G6: Mme. Mbarga | K6: 0 | L6: Conforme | M6: Tous contrats à jour
A7: AUD-002 | B7: Art. L6312-1 CT | C7: Plan de formation annuel formalisé | D7: Conforme | E7: Plan 2025 approuvé | F7: 2025-02-01 | G7: M. Eyenga | K7: 0 | L7: Conforme | M7: Budget validé par DG
A8: AUD-003 | B8: Art. L1225-1 CT | C8: Égalité chances promotion | D8: Partiellement conforme | E8: Rapport parité | F8: 2025-03-01 | G8: Mme. Essomba | H8: Sous-représentation femmes cadres | I8: Plan parité Q3 | J8: 2025-09-30 | K8: 500000 | L8: En cours | M8: Action en cours
A9: AUD-004 | B9: Art. L3121-1 CT | C9: Durée légale respectée postes mutés | D9: Conforme | E9: Pointages RH | F9: 2025-01-20 | G9: Mme. Essomba | K9: 0 | L9: Conforme | M9: Pointage systématique
A10: AUD-005 | B10: Code Travail CH. VI | C10: Entretiens annuels obligatoires | D10: Conforme | E10: PV entretiens 2025 | F10: 2025-04-01 | G10: DRH | K10: 0 | L10: Conforme | M10: 100% des entretiens réalisés
A11: AUD-006 | B11: Convention Collective | C11: Procédure promotion respectée | D11: Partiellement conforme | E11: PV CSE | F11: 2025-03-15 | G11: M. Eyenga | H11: Critères non formalisés | I11: Grille critères Q2 | J11: 2025-06-30 | K11: 300000 | L11: En cours | M11: Grille en élaboration
A12: AUD-007 | B12: Art. L1222-1 CT | C12: Information préalable mutation | D12: Non conforme | E12: Enquête | F12: 2025-04-15 | G12: DRH | H12: 2 cas sans information | I12: Circulaire interne | J12: 2025-05-31 | K12: 1000000 | L12: Non conforme | M12: Urgence communication
A13: =IF(A12="","",A12)
A14: =IF(A13="","",A13)
A15: =IF(A14="","",A14)
A16: =IF(A15="","",A15)
A17: =IF(A16="","",A16)
A18: =IF(A17="","",A17)
A19: =IF(A18="","",A18)
A20: =IF(A19="","",A19)
A21: =IF(A20="","",A20)
A22: =IF(A21="","",A21)
A23: =IF(A22="","",A22)
A24: =IF(A23="","",A23)
... A115: =IF(A114="","",A114)
