Workbook

Sheet _Données Employés
B4: Matricule | C4: Civilité | D4: Nom | E4: Prénom | F4: Département | G4: Poste | H4: Salaire Base (FCFA)
B5: EMP-001 | C5: M. | D5: Nganou | E5: Clarisse | F5: Cuisine & Restauration | G5: Chef cuisinier | H5: 450000
B6: EMP-002 | C6: M. | D6: Tchinda | E6: Armand | F6: Réception & Front Office | G6: Réceptionniste | H6: 220000
B7: EMP-003 | C7: Mme | D7: Fotso | E7: Marguerite | F7: Finance & Comptabilité | G7: Comptable senior | H7: 380000
B8: EMP-004 | C8: M. | D8: Nkoulou | E8: Mbarga | F8: Étage & Housekeeping | G8: Gouvernant | H8: 195000
B9: EMP-005 | C9: M. | D9: Kamga | E9: Paul | F9: Maintenance | G9: Technicien maintenance | H9: 165000
B10: EMP-006 | C10: Mme | D10: Ngo | E10: Delphine | F10: Service Client | G10: Conseiller clientèle | H10: 160000
B11: EMP-007 | C11: M. | D11: Essomba | E11: Serge | F11: Maintenance | G11: Agent entretien | H11: 130000
B12: EMP-008 | C12: M. | D12: Tchouankou | E12: Paul | F12: Commercial | G12: Commercial | H12: 150000
B13: EMP-009 | C13: M. | D13: Fokam | E13: Eric | F13: Maintenance | G13: Technicien | H13: 140000
B14: EMP-010 | C14: M. | D14: Tagne | E14: René | F14: Cuisine & Restauration | G14: Plongeur | H14: 90000
B15: EMP-011 | C15: M. | D15: Bouba | E15: Ahmed | F15: Sécurité | G15: Agent Sécurité | H15: 120000
B16: EMP-012 | C16: Mme | D16: Awa | E16: Fatou | F16: Réception & Front Office | G16: Standardiste | H16: 155000
... B18: EMP-029 | C18: M. | D18: Kamga | E18: Patrice | F18: Sécurité | G18: Chef Sécurité | H18: 210000

Sheet 1-Tableau de Bord
B2: DOMAINE 15 — BUDGET & PILOTAGE FINANCIER RH
B3: TABLEAU DE BORD — Vue synthetique de tous les indicateurs du domaine (mis a jour automatiquement)
B5: Budget total annuel | E5: Conso S1 | H5: Ecart budget S1 | K5: Postes depasses
B6: =SUM('2-Budget RH Annuel'!D5:D104) | E6: =SUM('2-Budget RH Annuel'!K5:K104) | H6: =SUM('3-Suivi Budgetaire Mensuel'!H5:H104) | K6: =COUNTIF('3-Suivi Budgetaire Mensuel'!H5:H104,">"&0)
B9: Total provisions | E9: Cout recrutement total | H9: Cout formations total | K9: Simulations
B10: =SUM('4-Provisions & Reserves RH'!E5:E104) | E10: =SUM('5-Couts Recrutement'!K5:K104) | H10: =SUM('6-Rentabilite Formations'!H5:H104) | K10: =COUNTIF('7-Simulation Scenarios'!B5:B104,"<>")
B14: BUDGET PAR POSTE & COUTS FORMATIONS
B15: Poste Budgetaire | C15: Budget (M FCFA)
B16: Salaires de base | C16: =IFERROR(INDEX('2-Budget RH Annuel'!D:D,MATCH("Salaires de base",'2-Budget RH Annuel'!C:C,0)),0)/1000000
B17: Primes et indemnites | C17: =IFERROR(INDEX('2-Budget RH Annuel'!D:D,MATCH("Primes et indemnites",'2-Budget RH Annuel'!C:C,0)),0)/1000000
B18: Heures supplementaires | C18: =IFERROR(INDEX('2-Budget RH Annuel'!D:D,MATCH("Heures supplementaires",'2-Budget RH Annuel'!C:C,0)),0)/1000000
B19: Cotisations patronales | C19: =IFERROR(INDEX('2-Budget RH Annuel'!D:D,MATCH("Cotisations patronales",'2-Budget RH Annuel'!C:C,0)),0)/1000000
B20: Formation professionnelle | C20: =IFERROR(INDEX('2-Budget RH Annuel'!D:D,MATCH("Formation professionnelle",'2-Budget RH Annuel'!C:C,0)),0)/1000000
B21: Recrutement | C21: =IFERROR(INDEX('2-Budget RH Annuel'!D:D,MATCH("Recrutement",'2-Budget RH Annuel'!C:C,0)),0)/1000000
H23: Source Candidat | I23: Cout (FCFA)
H24: Site emploi | I24: =SUMIF('5-Couts Recrutement'!E:E,"Site emploi",'5-Couts Recrutement'!K:K)
H25: Recommandation | I25: =SUMIF('5-Couts Recrutement'!E:E,"Recommandation",'5-Couts Recrutement'!K:K)
H26: Presse | I26: =SUMIF('5-Couts Recrutement'!E:E,"Presse",'5-Couts Recrutement'!K:K)
H27: Reseau social | I27: =SUMIF('5-Couts Recrutement'!E:E,"Reseau social",'5-Couts Recrutement'!K:K)
H28: Cabinet recrutement | I28: =SUMIF('5-Couts Recrutement'!E:E,"Cabinet recrutement",'5-Couts Recrutement'!K:K)

Sheet _Lists
B1: poste_budget | C1: departement | D1: type_provision | E1: mois | F1: annee | G1: statut_budget | H1: statut_action | I1: source_candidat | J1: poste_hotel | K1: scnario_type
B2: Salaires de base | C2: Direction Generale | D2: Licenciement | E2: Janvier | F2: 2024 | G2: En cours | H2: Planifiee | I2: Candidature spontanee | J2: DG | K2: Hausse effectif 5%
B3: Primes et indemnites | C3: Service Client | D3: Depart volontaire | E3: Fevrier | F3: 2025 | G3: Valide | H3: En cours | I3: Site emploi | J3: DRH | K3: Hausse effectif 10%
B4: Heures supplementaires | C4: Finance & Comptabilité | D4: Indemnite conges | E4: Mars | F4: 2026 | G4: En attente validation | H4: Terminee | I4: Recommandation | J4: Assistante RH | K4: Baisse effectif 5%
B5: Cotisations sociales patronales | C5: Marketing & Communication | D5: Prime fin d'annee | E5: Avril | G5: Depasse | H5: Reportee | I5: Reseau social | J5: DAF | K5: Augmentation salariale 3%
B6: Assurances RH | C6: Maintenance | D6: Provision HSE | E6: Mai | G6: Ajuste | H6: Annulee | I6: Presse | J6: Comptable senior | K6: Augmentation salariale 5%
B7: Formation professionnelle | C7: Commercial | D7: Procontentieux | E7: Juin | G7: Cloture | I7: Cabinet recrutement | J7: Chef Comptable | K7: Augmentation salariale 10%
B8: Recrutement | C8: Logistique & Approvisionnement | D8: Autre | E8: Juillet | I8: Interne (promotion) | J8: Chef Marketing | K8: Stabilite
B9: Medecine du travail | C9: Cuisine & Restauration | E9: Aout | I9: Autre | J9: Chef de service IT | K9: Crise - reduction 10%
B10: Indemnites depart | C10: Réception & Front Office | E10: Septembre | J10: Technicien IT | K10: Expansion hoteliere +15%
B11: Charges de personnel diverses | C11: Sécurité | E11: Octobre | J11: Chef Commercial
B12: Logement personnel | C12: Étage & Housekeeping | E12: Novembre | J12: Agent Commercial
B13: Transport personnel | E13: Decembre | J13: Chef Logistique
B14: Recreation & bien-etre | J14: Magasinier
B15: Tenue de travail | J15: Chef Reception
B16: Autres charges RH | J16: Receptionniste
J17: Concierge
J18: Chef Cuisine
J19: Sous-Chef
J20: Cuisinier
J21: Plongeur
J22: Chef Entretien
J23: Agent Entretien
J24: Chef Securite
J25: Agent Securite

Sheet 2-Budget RH Annuel
B2: BUDGET RH ANNUEL DETAILLE (#149)
B3: TABLEAU DYNAMIQUE — Saisissez dans la prochaine ligne jaune. Les calculs se mettent a jour automatiquement.
B4: N° | C4: Poste Budgetaire | D4: Budget Annuel (FCFA) | E4: Janvier | F4: Fevrier | G4: Mars | H4: Avril | I4: Mai | J4: Juin | K4: Total S1 (FCFA) | L4: Statut
B5: BUD-001 | C5: Salaires de base | D5: 270000000 | E5: 22500000 | F5: 22500000 | G5: 22500000 | H5: 22500000 | I5: 22500000 | J5: 22500000 | L5: En cours
B6: BUD-002 | C6: Primes et indemnites | D6: 22000000 | E6: 1850000 | F6: 1900000 | G6: 1920000 | H6: 1880000 | I6: 1950000 | J6: 2000000 | L6: En cours
B7: BUD-003 | C7: Heures supplementaires | D7: 8000000 | E7: 620000 | F7: 580000 | G7: 710000 | H7: 540000 | I7: 680000 | J7: 750000 | L7: En cours
B8: BUD-004 | C8: Cotisations patronales | D8: 48600000 | E8: 4050000 | F8: 4050000 | G8: 4050000 | H8: 4050000 | I8: 4050000 | J8: 4050000 | L8: En cours
B9: BUD-005 | C9: Formation professionnelle | D9: 5000000 | E9: 300000 | F9: 350000 | G9: 500000 | H9: 400000 | I9: 450000 | J9: 500000 | L9: En cours
B10: BUD-006 | C10: Recrutement | D10: 3000000 | E10: 200000 | F10: 350000 | G10: 150000 | H10: 250000 | I10: 200000 | J10: 300000 | L10: En cours
B11: =IF(C11="","BUD-"&TEXT(COUNTA($C$5:C11),"000")) | K11: =E11+F11+G11+H11+I11+J11
B12: =IF(C12="","BUD-"&TEXT(COUNTA($C$5:C12),"000")) | K12: =E12+F12+G12+H12+I12+J12
B13: =IF(C13="","BUD-"&TEXT(COUNTA($C$5:C13),"000")) | K13: =E13+F13+G13+H13+I13+J13
B14: =IF(C14="","BUD-"&TEXT(COUNTA($C$5:C14),"000")) | K14: =E14+F14+G14+H14+I14+J14
B15: =IF(C15="","BUD-"&TEXT(COUNTA($C$5:C15),"000")) | K15: =E15+F15+G15+H15+I15+J15
B16: =IF(C16="","BUD-"&TEXT(COUNTA($C$5:C16),"000")) | K16: =E16+F16+G16+H16+I16+J16
B17: =IF(C17="","BUD-"&TEXT(COUNTA($C$5:C17),"000")) | K17: =E17+F17+G17+H17+I17+J17
B18: =IF(C18="","BUD-"&TEXT(COUNTA($C$5:C18),"000")) | K18: =E18+F18+G18+H18+I18+J18
B19: =IF(C19="","BUD-"&TEXT(COUNTA($C$5:C19),"000")) | K19: =E19+F19+G19+H19+I19+J19
B20: =IF(C20="","BUD-"&TEXT(COUNTA($C$5:C20),"000")) | K20: =E20+F20+G20+H20+I20+J20
B21: =IF(C21="","BUD-"&TEXT(COUNTA($C$5:C21),"000")) | K21: =E21+F21+G21+H21+I21+J21
B22: =IF(C22="","BUD-"&TEXT(COUNTA($C$5:C22),"000")) | K22: =E22+F22+G22+H22+I22+J22
... B110: =IF(C110="","BUD-"&TEXT(COUNTA($C$5:C110),"000")) | K110: =E110+F110+G110+H110+I110+J110
B112: TOTAL | E112: =SUM(E5:E104) | F112: =SUM(F5:F104) | G112: =SUM(G5:G104) | H112: =SUM(H5:H104) | I112: =SUM(I5:I104) | J112: =SUM(J5:J104) | K112: =SUM(K5:K104)
B114: INDICATEURS (mis a jour automatiquement)
B115: Postes budgetaires | D115: Budget total annuel | F115: Conso S1 (FCFA)
B116: =COUNTIF(B5:B104,"<>") | D116: =SUM(D5:D104) | F116: =SUM(K5:K104)

Sheet 3-Suivi Budgetaire Mensuel
B2: SUIVI BUDGETAIRE MENSUEL RH (#150)
B3: TABLEAU DYNAMIQUE — Saisissez dans la prochaine ligne jaune. Les calculs se mettent a jour automatiquement.
B4: N° | C4: Poste Budgetaire | D4: Mois | E4: Annee | F4: Budget Mensuel (FCFA) | G4: Realise (FCFA) | H4: Ecart (FCFA) | I4: Taux Realisation (%) | J4: Cumul Budget (FCFA) | K4: Cumul Realise (FCFA) | L4: Statut
B5: SBG-001 | C5: Salaires de base | D5: Juin | E5: 2025 | F5: 22500000 | G5: 22700000 | L5: En cours
B6: SBG-002 | C6: Primes et indemnites | D6: Juin | E6: 2025 | F6: 1900000 | G6: 2000000 | L6: En cours
B7: SBG-003 | C7: Heures supplementaires | D7: Juin | E7: 2025 | F7: 700000 | G7: 750000 | L7: En cours
B8: SBG-004 | C8: Cotisations patronales | D8: Juin | E8: 2025 | F8: 4050000 | G8: 4086000 | L8: En cours
B9: SBG-005 | C9: Formation | D9: Juin | E9: 2025 | F9: 500000 | G9: 600000 | L9: Depasse
B10: =IF(C10="","SBG-"&TEXT(COUNTA($C$5:C10),"000")) | H10: =G10-F10 | I10: =IF(F10="","",G10/F10)
B11: =IF(C11="","SBG-"&TEXT(COUNTA($C$5:C11),"000")) | H11: =G11-F11 | I11: =IF(F11="","",G11/F11)
B12: =IF(C12="","SBG-"&TEXT(COUNTA($C$5:C12),"000")) | H12: =G12-F12 | I12: =IF(F12="","",G12/F12)
B13: =IF(C13="","SBG-"&TEXT(COUNTA($C$5:C13),"000")) | H13: =G13-F13 | I13: =IF(F13="","",G13/F13)
B14: =IF(C14="","SBG-"&TEXT(COUNTA($C$5:C14),"000")) | H14: =G14-F14 | I14: =IF(F14="","",G14/F14)
B15: =IF(C15="","SBG-"&TEXT(COUNTA($C$5:C15),"000")) | H15: =G15-F15 | I15: =IF(F15="","",G15/F15)
B16: =IF(C16="","SBG-"&TEXT(COUNTA($C$5:C16),"000")) | H16: =G16-F16 | I16: =IF(F16="","",G16/F16)
B17: =IF(C17="","SBG-"&TEXT(COUNTA($C$5:C17),"000")) | H17: =G17-F17 | I17: =IF(F17="","",G17/F17)
B18: =IF(C18="","SBG-"&TEXT(COUNTA($C$5:C18),"000")) | H18: =G18-F18 | I18: =IF(F18="","",G18/F18)
B19: =IF(C19="","SBG-"&TEXT(COUNTA($C$5:C19),"000")) | H19: =G19-F19 | I19: =IF(F19="","",G19/F19)
B20: =IF(C20="","SBG-"&TEXT(COUNTA($C$5:C20),"000")) | H20: =G20-F20 | I20: =IF(F20="","",G20/F20)
B21: =IF(C21="","SBG-"&TEXT(COUNTA($C$5:C21),"000")) | H21: =G21-F21 | I21: =IF(F21="","",G21/F21)
... B109: =IF(C109="","SBG-"&TEXT(COUNTA($C$5:C109),"000")) | H109: =G109-F109 | I109: =IF(F109="","",G109/F109)
B111: TOTAL | F111: =SUM(F5:F104) | G111: =SUM(G5:G104) | H111: =SUM(H5:H104)
B113: INDICATEURS (mis a jour automatiquement)
B114: Lignes suivies | D114: Budget total | F114: Ecart total | H114: Postes depasses
B115: =COUNTIF(B5:B104,"<>") | D115: =SUM(F5:F104) | F115: =SUM(H5:H104) | H115: =COUNTIF(H5:H104,">"&0)

Sheet 4-Provisions & Reserves RH
B2: PROVISIONS & RESERVES RH (#151)
B3: TABLEAU DYNAMIQUE — Saisissez dans la prochaine ligne jaune. Les calculs se mettent a jour automatiquement.
B4: N° | C4: Type Provision | D4: Poste Comptable | E4: Montant Provision (FCFA) | F4: Montant Reel (FCFA) | G4: Ecart | H4: Date Constitution | I4: Date Utilisation | J4: Justification | K4: Statut
B5: PRV-001 | C5: Indemnite conges | D5: Provision conges | E5: 4500000 | F5: 3200000 | H5: 45658 | J5: Provision pour conges non pris | K5: En cours
B6: PRV-002 | C6: Prime fin d'annee | D6: Provision 13eme mois | E6: 22500000 | H6: 45658 | I6: 46006 | J6: Prime collective decembre | K6: En cours
B7: PRV-003 | C7: Procontentieux | D7: Provision litiges | E7: 1500000 | F7: 500000 | H7: 45672 | J7: Provision prud'hommes Tchouanku | K7: En cours
B8: PRV-004 | C8: Depart volontaire | D8: Provision licenciement | E8: 2000000 | H8: 45658 | J8: Provision restructuration eventuelle | K8: En cours
B9: PRV-005 | C9: Medecine du travail | D9: Provision sante | E9: 250000 | F9: 180000 | H9: 45658 | J9: Visites medicales annuelles | K9: En cours
B10: =IF(C10="","PRV-"&TEXT(COUNTA($C$5:C10),"000")) | G10: =IF(OR(E10="",F10=""),"",E10-F10)
B11: =IF(C11="","PRV-"&TEXT(COUNTA($C$5:C11),"000")) | G11: =IF(OR(E11="",F11=""),"",E11-F11)
B12: =IF(C12="","PRV-"&TEXT(COUNTA($C$5:C12),"000")) | G12: =IF(OR(E12="",F12=""),"",E12-F12)
B13: =IF(C13="","PRV-"&TEXT(COUNTA($C$5:C13),"000")) | G13: =IF(OR(E13="",F13=""),"",E13-F13)
B14: =IF(C14="","PRV-"&TEXT(COUNTA($C$5:C14),"000")) | G14: =IF(OR(E14="",F14=""),"",E14-F14)
B15: =IF(C15="","PRV-"&TEXT(COUNTA($C$5:C15),"000")) | G15: =IF(OR(E15="",F15=""),"",E15-F15)
B16: =IF(C16="","PRV-"&TEXT(COUNTA($C$5:C16),"000")) | G16: =IF(OR(E16="",F16=""),"",E16-F16)
B17: =IF(C17="","PRV-"&TEXT(COUNTA($C$5:C17),"000")) | G17: =IF(OR(E17="",F17=""),"",E17-F17)
B18: =IF(C18="","PRV-"&TEXT(COUNTA($C$5:C18),"000")) | G18: =IF(OR(E18="",F18=""),"",E18-F18)
B19: =IF(C19="","PRV-"&TEXT(COUNTA($C$5:C19),"000")) | G19: =IF(OR(E19="",F19=""),"",E19-F19)
B20: =IF(C20="","PRV-"&TEXT(COUNTA($C$5:C20),"000")) | G20: =IF(OR(E20="",F20=""),"",E20-F20)
B21: =IF(C21="","PRV-"&TEXT(COUNTA($C$5:C21),"000")) | G21: =IF(OR(E21="",F21=""),"",E21-F21)
... B109: =IF(C109="","PRV-"&TEXT(COUNTA($C$5:C109),"000")) | G109: =IF(OR(E109="",F109=""),"",E109-F109)
B111: TOTAL | E111: =SUM(E5:E104) | F111: =SUM(F5:F104) | G111: =SUM(G5:G104)
B113: INDICATEURS (mis a jour automatiquement)
B114: Provisions suivies | D114: Total provisions | F114: Total utilise
B115: =COUNTIF(B5:B104,"<>") | D115: =SUM(E5:E104) | F115: =SUM(F5:F104)

Sheet 5-Couts Recrutement
B2: SUIVI DES COUTS DE RECRUTEMENT (#152)
B3: TABLEAU DYNAMIQUE — Saisissez dans la prochaine ligne jaune. Les calculs se mettent a jour automatiquement.
B4: N° | C4: Poste a Pourvoir | D4: Service | E4: Source Candidat | F4: Cand. Presentes | G4: Cand. Entretien | H4: Frais Publication | I4: Honoraires Cabinet | J4: Cout Tests Selection | K4: Cout Total (FCFA) | L4: Statut
B5: CRU-001 | C5: Chef Reception | D5: Réception & Front Office | E5: Recommandation | F5: 8 | G5: 3 | H5: 50000 | I5: 250000 | J5: 75000 | L5: Pourvu
B6: CRU-002 | C6: Receptionniste | D6: Réception & Front Office | E6: Site emploi | F6: 25 | G6: 5 | H6: 100000 | I6: 0 | J6: 50000 | L6: Pourvu
B7: CRU-003 | C7: Cuisinier | D7: Cuisine & Restauration | E7: Presse | F7: 12 | G7: 4 | H7: 75000 | I7: 150000 | J7: 25000 | L7: En cours
B8: CRU-004 | C8: Agent Securite | D8: Sécurité | E8: Reseau social | F8: 18 | G8: 3 | H8: 0 | I8: 0 | J8: 20000 | L8: En cours
B9: =IF(C9="","CRU-"&TEXT(COUNTA($C$5:C9),"000")) | K9: =H9+I9+J9
B10: =IF(C10="","CRU-"&TEXT(COUNTA($C$5:C10),"000")) | K10: =H10+I10+J10
B11: =IF(C11="","CRU-"&TEXT(COUNTA($C$5:C11),"000")) | K11: =H11+I11+J11
B12: =IF(C12="","CRU-"&TEXT(COUNTA($C$5:C12),"000")) | K12: =H12+I12+J12
B13: =IF(C13="","CRU-"&TEXT(COUNTA($C$5:C13),"000")) | K13: =H13+I13+J13
B14: =IF(C14="","CRU-"&TEXT(COUNTA($C$5:C14),"000")) | K14: =H14+I14+J14
B15: =IF(C15="","CRU-"&TEXT(COUNTA($C$5:C15),"000")) | K15: =H15+I15+J15
B16: =IF(C16="","CRU-"&TEXT(COUNTA($C$5:C16),"000")) | K16: =H16+I16+J16
B17: =IF(C17="","CRU-"&TEXT(COUNTA($C$5:C17),"000")) | K17: =H17+I17+J17
B18: =IF(C18="","CRU-"&TEXT(COUNTA($C$5:C18),"000")) | K18: =H18+I18+J18
B19: =IF(C19="","CRU-"&TEXT(COUNTA($C$5:C19),"000")) | K19: =H19+I19+J19
B20: =IF(C20="","CRU-"&TEXT(COUNTA($C$5:C20),"000")) | K20: =H20+I20+J20
... B108: =IF(C108="","CRU-"&TEXT(COUNTA($C$5:C108),"000")) | K108: =H108+I108+J108
B110: TOTAL | F110: =SUM(F5:F104) | G110: =SUM(G5:G104) | H110: =SUM(H5:H104) | I110: =SUM(I5:I104) | J110: =SUM(J5:J104) | K110: =SUM(K5:K104)
B112: INDICATEURS (mis a jour automatiquement)
B113: Recrutements suivis | D113: Cout total recrutement | F113: Cout moyen / recrutement
B114: =COUNTIF(B5:B104,"<>") | D114: =SUM(K5:K104) | F114: =IFERROR(SUM(K5:K104)/COUNTIF(B5:B104,"<>"),0)

Sheet 6-Rentabilite Formations
B2: ANALYSE DE RENTABILITE DES FORMATIONS (#153)
B3: TABLEAU DYNAMIQUE — Saisissez dans la prochaine ligne jaune. Les calculs se mettent a jour automatiquement.
B4: N° | C4: Formation | D4: Formateur | E4: Nb Participants | F4: Cout Formation (FCFA) | G4: Cout Indirect (FCFA) | H4: Cout Total (FCFA) | I4: Gain Productivite Estime (FCFA/mois) | J4: ROI Mensuel (%) | K4: Delai Amortissement (mois) | L4: Statut
B5: RFO-001 | C5: HACCP Niveau 2 | D5: INPHB | E5: 12 | F5: 480000 | G5: 180000 | I5: 150000 | L5: En cours
B6: RFO-002 | C6: Accueil hotellerie | D6: Centre formation Douala | E6: 8 | F6: 320000 | G6: 120000 | I6: 100000 | L6: En cours
B7: RFO-003 | C7: Gestion stress & burnout | D7: Coach certifie | E7: 15 | F7: 375000 | G7: 150000 | I7: 80000 | L7: En cours
B8: RFO-004 | C8: Excel avance pour DAF | D8: Formateur independant | E8: 3 | F8: 150000 | G8: 45000 | I8: 60000 | L8: En cours
B9: RFO-005 | C9: Securite incendie | D9: Pompiers Douala | E9: 20 | F9: 200000 | G9: 200000 | I9: 50000 | L9: En cours
B10: =IF(C10="","RFO-"&TEXT(COUNTA($C$5:C10),"000")) | H10: =F10+G10 | J10: =IF(OR(H10="",I10=""),"",I10/H10) | K10: =IF(J10="","",IF(J10=0,"N/A",1/J10))
B11: =IF(C11="","RFO-"&TEXT(COUNTA($C$5:C11),"000")) | H11: =F11+G11 | J11: =IF(OR(H11="",I11=""),"",I11/H11) | K11: =IF(J11="","",IF(J11=0,"N/A",1/J11))
B12: =IF(C12="","RFO-"&TEXT(COUNTA($C$5:C12),"000")) | H12: =F12+G12 | J12: =IF(OR(H12="",I12=""),"",I12/H12) | K12: =IF(J12="","",IF(J12=0,"N/A",1/J12))
B13: =IF(C13="","RFO-"&TEXT(COUNTA($C$5:C13),"000")) | H13: =F13+G13 | J13: =IF(OR(H13="",I13=""),"",I13/H13) | K13: =IF(J13="","",IF(J13=0,"N/A",1/J13))
B14: =IF(C14="","RFO-"&TEXT(COUNTA($C$5:C14),"000")) | H14: =F14+G14 | J14: =IF(OR(H14="",I14=""),"",I14/H14) | K14: =IF(J14="","",IF(J14=0,"N/A",1/J14))
B15: =IF(C15="","RFO-"&TEXT(COUNTA($C$5:C15),"000")) | H15: =F15+G15 | J15: =IF(OR(H15="",I15=""),"",I15/H15) | K15: =IF(J15="","",IF(J15=0,"N/A",1/J15))
B16: =IF(C16="","RFO-"&TEXT(COUNTA($C$5:C16),"000")) | H16: =F16+G16 | J16: =IF(OR(H16="",I16=""),"",I16/H16) | K16: =IF(J16="","",IF(J16=0,"N/A",1/J16))
B17: =IF(C17="","RFO-"&TEXT(COUNTA($C$5:C17),"000")) | H17: =F17+G17 | J17: =IF(OR(H17="",I17=""),"",I17/H17) | K17: =IF(J17="","",IF(J17=0,"N/A",1/J17))
B18: =IF(C18="","RFO-"&TEXT(COUNTA($C$5:C18),"000")) | H18: =F18+G18 | J18: =IF(OR(H18="",I18=""),"",I18/H18) | K18: =IF(J18="","",IF(J18=0,"N/A",1/J18))
B19: =IF(C19="","RFO-"&TEXT(COUNTA($C$5:C19),"000")) | H19: =F19+G19 | J19: =IF(OR(H19="",I19=""),"",I19/H19) | K19: =IF(J19="","",IF(J19=0,"N/A",1/J19))
B20: =IF(C20="","RFO-"&TEXT(COUNTA($C$5:C20),"000")) | H20: =F20+G20 | J20: =IF(OR(H20="",I20=""),"",I20/H20) | K20: =IF(J20="","",IF(J20=0,"N/A",1/J20))
B21: =IF(C21="","RFO-"&TEXT(COUNTA($C$5:C21),"000")) | H21: =F21+G21 | J21: =IF(OR(H21="",I21=""),"",I21/H21) | K21: =IF(J21="","",IF(J21=0,"N/A",1/J21))
... B109: =IF(C109="","RFO-"&TEXT(COUNTA($C$5:C109),"000")) | H109: =F109+G109 | J109: =IF(OR(H109="",I109=""),"",I109/H109) | K109: =IF(J109="","",IF(J109=0,"N/A",1/J109))
B111: TOTAL | E111: =SUM(E5:E104) | F111: =SUM(F5:F104) | G111: =SUM(G5:G104) | H111: =SUM(H5:H104) | I111: =SUM(I5:I104)
B113: INDICATEURS (mis a jour automatiquement)
B114: Formations | D114: Cout total formations | F114: ROI moyen
B115: =COUNTIF(B5:B104,"<>") | D115: =SUM(H5:H104) | F115: =IFERROR(AVERAGE(J5:J104),0)

Sheet 7-Simulation Scenarios
B2: SIMULATION DE SCENARIOS BUDGETAIRES (#154)
B3: TABLEAU DYNAMIQUE — Saisissez dans la prochaine ligne jaune. Les calculs se mettent a jour automatiquement.
B4: N° | C4: Scenario | D4: Poste Budgetaire | E4: Budget Actuel (FCFA) | F4: Valeur Simulee (FCFA) | G4: Variation (FCFA) | H4: Variation (%) | I4: Impact MS Totale (FCFA) | J4: Ratio MS/CA Simule | K4: Statut
B5: SIM-001 | C5: Hausse effectif 5% | D5: Salaires de base | E5: 270000000 | F5: 283500000 | K5: En cours
B6: SIM-002 | C6: Hausse effectif 5% | D6: Cotisations patronales | E6: 48600000 | F6: 51030000 | K6: En cours
B7: SIM-003 | C7: Augmentation salariale 5% | D7: Salaires de base | E7: 270000000 | F7: 283500000 | K7: En cours
B8: SIM-004 | C8: Augmentation salariale 5% | D8: Primes | E8: 22000000 | F8: 23100000 | K8: En cours
B9: SIM-005 | C9: Crise - reduction 10% | D9: Salaires de base | E9: 270000000 | F9: 243000000 | K9: En cours
B10: SIM-006 | C10: Crise - reduction 10% | D10: Formation | E10: 5000000 | F10: 4000000 | K10: En cours
B11: =IF(C11="","SIM-"&TEXT(COUNTA($C$5:C11),"000")) | G11: =F11-E11 | H11: =IF(E11="","",(F11-E11)/E11)
B12: =IF(C12="","SIM-"&TEXT(COUNTA($C$5:C12),"000")) | G12: =F12-E12 | H12: =IF(E12="","",(F12-E12)/E12)
B13: =IF(C13="","SIM-"&TEXT(COUNTA($C$5:C13),"000")) | G13: =F13-E13 | H13: =IF(E13="","",(F13-E13)/E13)
B14: =IF(C14="","SIM-"&TEXT(COUNTA($C$5:C14),"000")) | G14: =F14-E14 | H14: =IF(E14="","",(F14-E14)/E14)
B15: =IF(C15="","SIM-"&TEXT(COUNTA($C$5:C15),"000")) | G15: =F15-E15 | H15: =IF(E15="","",(F15-E15)/E15)
B16: =IF(C16="","SIM-"&TEXT(COUNTA($C$5:C16),"000")) | G16: =F16-E16 | H16: =IF(E16="","",(F16-E16)/E16)
B17: =IF(C17="","SIM-"&TEXT(COUNTA($C$5:C17),"000")) | G17: =F17-E17 | H17: =IF(E17="","",(F17-E17)/E17)
B18: =IF(C18="","SIM-"&TEXT(COUNTA($C$5:C18),"000")) | G18: =F18-E18 | H18: =IF(E18="","",(F18-E18)/E18)
B19: =IF(C19="","SIM-"&TEXT(COUNTA($C$5:C19),"000")) | G19: =F19-E19 | H19: =IF(E19="","",(F19-E19)/E19)
B20: =IF(C20="","SIM-"&TEXT(COUNTA($C$5:C20),"000")) | G20: =F20-E20 | H20: =IF(E20="","",(F20-E20)/E20)
B21: =IF(C21="","SIM-"&TEXT(COUNTA($C$5:C21),"000")) | G21: =F21-E21 | H21: =IF(E21="","",(F21-E21)/E21)
B22: =IF(C22="","SIM-"&TEXT(COUNTA($C$5:C22),"000")) | G22: =F22-E22 | H22: =IF(E22="","",(F22-E22)/E22)
... B110: =IF(C110="","SIM-"&TEXT(COUNTA($C$5:C110),"000")) | G110: =F110-E110 | H110: =IF(E110="","",(F110-E110)/E110)
B112: TOTAL | E112: =SUM(E5:E104) | F112: =SUM(F5:F104) | G112: =SUM(G5:G104)
B114: INDICATEURS (mis a jour automatiquement)
B115: Simulations | D115: Variation totale
B116: =COUNTIF(B5:B104,"<>") | D116: =SUM(G5:G104)
