Workbook

Sheet ★ Bulletin de Paie
B2: HÔTEL 4 ÉTOILES — BULLETIN DE PAIE INDIVIDUEL
B3: Domaine 3 — Paie, Rémunération & Avantages Sociaux
B5: RECHERCHER UN EMPLOYÉ | D5: Matricule : | G5: Période :
B6: Employé sélectionné : | D6: =IF(E5="","⚠ Saisir un matricule ci-dessus",IFERROR(VLOOKUP(E5,'_Données Employés'!$B$5:$S$114,3,FALSE)&" "&VLOOKUP(E5,'_Données Employés'!$B$5:$S$114,4,FALSE),"Matricule non trouvé")) | G6: Département : | H6: =IF(E5="","",IFERROR(VLOOKUP(E5,'_Données Employés'!$B$5:$S$114,10,FALSE),""))
B8: IDENTITÉ DU SALARIÉ | G8: INFORMATIONS EMPLOI
B9: Matricule | C9: =IF(E5="","",E5) | D9: Civilité | E9: =IF(E5="","",IFERROR(VLOOKUP(E5,'_Données Employés'!$B$5:$S$114,2,FALSE),"")) | G9: Département | H9: =IF(E5="","",IFERROR(VLOOKUP(E5,'_Données Employés'!$B$5:$S$114,10,FALSE),"")) | I9: Poste | J9: =IF(E5="","",IFERROR(VLOOKUP(E5,'_Données Employés'!$B$5:$S$114,9,FALSE),""))
B10: Nom | C10: =IF(E5="","",IFERROR(VLOOKUP(E5,'_Données Employés'!$B$5:$S$114,3,FALSE),"")) | D10: Prénom | E10: =IF(E5="","",IFERROR(VLOOKUP(E5,'_Données Employés'!$B$5:$S$114,4,FALSE),"")) | G10: Type contrat | H10: =IF(E5="","",IFERROR(VLOOKUP(E5,'_Données Employés'!$B$5:$S$114,11,FALSE),"")) | I10: Régime travail | J10: =IF(E5="","",IFERROR(VLOOKUP(E5,'_Données Employés'!$B$5:$S$114,12,FALSE),""))
B11: Date naissance | C11: =IF(E5="","",IFERROR(VLOOKUP(E5,'_Données Employés'!$B$5:$S$114,5,FALSE),"")) | D11: Nationalité | E11: =IF(E5="","",IFERROR(VLOOKUP(E5,'_Données Employés'!$B$5:$S$114,7,FALSE),"")) | G11: Date embauche | H11: =IF(E5="","",IFERROR(VLOOKUP(E5,'_Données Employés'!$B$5:$S$114,13,FALSE),"")) | I11: Ancienneté | J11: =IF(E5="","",IFERROR(VLOOKUP(E5,'_Données Employés'!$B$5:$S$114,18,FALSE),""))
B12: Échelon | C12: =IF(E5="","",IFERROR(VLOOKUP(E5,'_Données Employés'!$B$5:$S$114,14,FALSE),"")) | D12: Statut | E12: =IF(E5="","",IFERROR(VLOOKUP(E5,'_Données Employés'!$B$5:$S$114,15,FALSE),"")) | G12: Catégorie | H12: =IF(E5="","",IFERROR(VLOOKUP(E5,'_Données Employés'!$B$5:$S$114,8,FALSE),"")) | I12: Salaire base | J12: =IF(E5="","",IFERROR(VLOOKUP(E5,'_Données Employés'!$B$5:$S$114,16,FALSE),""))
B14: DÉTAIL DE LA RÉMUNÉRATION
B15: RUBRIQUE (GAINS) | C15: Base (FCFA) | D15: Taux | E15: Montant (FCFA) | G15: RUBRIQUE (RETENUES) | H15: Base (FCFA) | I15: Taux | J15: Montant (FCFA)
B16: Salaire de base | C16: =IF(E5="","",IFERROR(VLOOKUP(E5,'_Données Employés'!$B$5:$S$114,16,FALSE),"")) | D16: 100% | E16: =IF(E5="","",IFERROR(VLOOKUP(E5,'_Données Employés'!$B$5:$S$114,16,FALSE),"")) | G16: CNPS Employé | H16: =IF(E5="","",E24) | I16: 2,8% | J16: =IF(E5="","",IFERROR(E24*0.028,0))
B17: Prime d'ancienneté | C17: =IF(E5="","",IFERROR(VLOOKUP(E5,'_Données Employés'!$B$5:$S$114,16,FALSE),"")) | D17: 5% | E17: =IF(E5="","",IFERROR(VLOOKUP(E5,'_Données Employés'!$B$5:$S$114,16,FALSE)*0.05,0)) | G17: CNAMGS Employé | H17: =IF(E5="","",E24) | I17: 1,5% | J17: =IF(E5="","",IFERROR(E24*0.015,0))
B18: Indemnité logement | C18: =IF(E5="","",IFERROR(VLOOKUP(E5,'_Données Employés'!$B$5:$S$114,16,FALSE),"")) | D18: 30% | E18: =IF(E5="","",IFERROR(VLOOKUP(E5,'_Données Employés'!$B$5:$S$114,16,FALSE)*0.3,0)) | G18: IR Salaires | H18: =IF(E5="","",E24) | I18: Barème progressif | J18: IF(E5="","",IFERROR(IF(E23<=62000,0,IF(E23<=146000,(E23-62000)*0.1,IF(E23<=236000,8400+(E23-146000)*0.15,IF(E23<=360000,21900+(E23-236000)*0.25,IF(E23<=550000,52900+(E23-360000)*0.35,119400+(E23-550000)*0.4))))),0))
B19: Prime transport | C19: =IF(E5="","",25000) | D19: Fixe | E19: =IF(E5="","",25000) | G19: Acomptes & avances | H19: =IF(E5="","",IFERROR(SUMPRODUCT(('7-Acomptes Avances'!$C$5:$C$104=E5)*('7-Acomptes Avances'!$H$5:$H$104)),0)) | I19: Variable | J19: =IF(E5="","",IFERROR(SUMPRODUCT(('7-Acomptes Avances'!$C$5:$C$104=E5)*('7-Acomptes Avances'!$H$5:$H$104)),0))
B20: Heures supplémentaires | C20: =IF(E5="","",IFERROR(SUMPRODUCT(('4-Heures Supplementaires'!$C$5:$C$104=E5)*('4-Heures Supplementaires'!$L$5:$L$104)),0)) | D20: Variable | E20: =IF(E5="","",IFERROR(SUMPRODUCT(('4-Heures Supplementaires'!$C$5:$C$104=E5)*('4-Heures Supplementaires'!$L$5:$L$104)),0)) | G20: Prêts personnels | H20: =IF(E5="","",IFERROR(SUMPRODUCT(('8-Prets Personnel'!$C$5:$C$104=E5)*('8-Prets Personnel'!$H$5:$H$104)),0)) | I20: Mensualité | J20: =IF(E5="","",IFERROR(SUMPRODUCT(('8-Prets Personnel'!$C$5:$C$104=E5)*('8-Prets Personnel'!$H$5:$H$104)),0))
B21: Primes & indemnités | C21: =IF(E5="","",IFERROR(SUMPRODUCT(('3-Primes & Indemnités'!$C$5:$C$104=E5)*('3-Primes & Indemnités'!$L$5:$L$104)),0)) | D21: Variable | E21: =IF(E5="","",IFERROR(SUMPRODUCT(('3-Primes & Indemnités'!$C$5:$C$104=E5)*('3-Primes & Indemnités'!$L$5:$L$104)),0)) | G21: Autres déductions | H21: =IF(E5="","",IFERROR(SUMPRODUCT(('6-Deductions Retenues'!$C$5:$C$104=E5)*('6-Deductions Retenues'!$H$5:$H$104)),0)) | I21: Variable | J21: =IF(E5="","",IFERROR(SUMPRODUCT(('6-Deductions Retenues'!$C$5:$C$104=E5)*('6-Deductions Retenues'!$H$5:$H$104)),0))
B22: Avantages en nature | C22: =IF(E5="","",IFERROR(SUMPRODUCT(('15-Avantages Nature'!$C$5:$C$104=E5)*('15-Avantages Nature'!$G$5:$G$104)),0)) | D22: Variable | E22: =IF(E5="","",IFERROR(SUMPRODUCT(('15-Avantages Nature'!$C$5:$C$104=E5)*('15-Avantages Nature'!$G$5:$G$104)),0)) | G22: Mutuelle/Prévoyance | H22: =IF(E5="","",IFERROR(SUMPRODUCT(('20-Mutuelle Prevoyance'!$C$5:$C$104=E5)*('20-Mutuelle Prevoyance'!$H$5:$H$104)),0)) | I22: Variable | J22: =IF(E5="","",IFERROR(SUMPRODUCT(('20-Mutuelle Prevoyance'!$C$5:$C$104=E5)*('20-Mutuelle Prevoyance'!$H$5:$H$104)),0))
B23: Variables & pourboires | C23: =IF(E5="","",IFERROR(SUMPRODUCT(('14-Variables Pourboires'!$C$5:$C$104=E5)*('14-Variables Pourboires'!$H$5:$H$104)),0)) | D23: Variable | E23: =IF(E5="","",IFERROR(SUMPRODUCT(('14-Variables Pourboires'!$C$5:$C$104=E5)*('14-Variables Pourboires'!$H$5:$H$104)),0)) | G23: TOTAL RETENUES | J23: =IF(E5="","",SUM(J16:J22))
B24: TOTAL BRUT | E24: =IF(E5="","",SUM(E16:E23))
B26: SALAIRE NET À PAYER | G26: COÛT TOTAL EMPLOYEUR
B27: =IF(E5="","",IFERROR(E24-J23,0)) | G27: =IF(E5="","",IFERROR(E24*1.082,0))
B29: RÉCAPITULATIF MENSUEL
B30: Salaire de base | G30: =IF(E5="","",IFERROR(VLOOKUP(E5,'_Données Employés'!$B$5:$S$114,16,FALSE),""))
B31: Total primes & indemnités réglementaires | G31: =IF(E5="","",IFERROR(SUM(E17:E20),0))
B32: Total primes variables & avantages | G32: =IF(E5="","",IFERROR(SUM(E21:E23),0))
B33: Salaire brut total | G33: =IF(E5="","",E24)
B34: Total cotisations sociales (CNPS+CNAMGS+IR) | G34: =IF(E5="","",IFERROR(SUM(J16:J18),0))
B35: Total déductions diverses | G35: =IF(E5="","",IFERROR(SUM(J19:J22),0))
B36: Total retenues | G36: =IF(E5="","",IFERROR(J23,0))
B37: NET À PAYER | G37: =IF(E5="","",IFERROR(E24-J23,0))
B38: Charges patronales (8,2%) | G38: =IF(E5="","",IFERROR(E24*0.082,0))
B39: Coût total pour l'hôtel | G39: =IF(E5="","",IFERROR(E24*1.082,0))
B41: Mode d'emploi : 1) Cliquer sur la cellule jaune « Matricule » en ligne 5 → 2) Choisir un employé dans la liste déroulante → 3) La fiche de paie se remplit automatiquement

Sheet Tableau de Bord
B2: DOMAINE 3 — PAIE, RÉMUNÉRATION & AVANTAGES SOCIAUX
B3: Tableau de bord — Vue synthétique (toutes les feuilles connectées automatiquement)
B5: Masse brute mensuelle (FCFA) | D5: Masse nette mensuelle (FCFA) | G5: Coût total employeur (FCFA) | I5: Effectif actif
B6: =SUM('2-Calcul des Salaires'!J5:J104) | D6: =SUM('2-Calcul des Salaires'!O5:O104) | G6: =SUM('2-Calcul des Salaires'!Q5:Q104) | I6: =COUNTA('_Données Employés'!B5:B114)
B8: Total primes (FCFA) | D8: Total HS nets (FCFA) | G8: Total cotisations (FCFA) | I8: Prêts en cours
B9: =SUM('3-Primes & Indemnités'!L5:L104) | D9: =SUM('4-Heures Supplementaires'!K5:K104) | G9: =SUM('5-Cotisations Salariales'!J5:J104) | I9: =COUNTIF('8-Prets Personnel'!K5:K104,"En cours")
B11: Avantages nature (FCFA) | D11: Tickets restaurant (FCFA) | G11: Valeur CET totale (FCFA) | I11: Notes de frais (FCFA)
B12: =SUM('15-Avantages Nature'!G5:G104) | D12: =SUM('16-Tickets Restaurant'!K5:K104) | G12: =SUM('17-Compte Epargne Temps'!L5:L104) | I12: =SUM('19-Notes de Frais'!H5:H104)
B15: RÉPARTITION PAR DÉPARTEMENT
B16: Département | C16: Masse Brute (FCFA) | D16: Effectif | G16: Type de Prime | H16: Montant (FCFA)
B17: Ressources Humaines | C17: =SUMPRODUCT(('_Données Employés'!$K$5:$K$114="Ressources Humaines")*('_Données Employés'!$R$5:$R$114)) | D17: =COUNTIF('_Données Employés'!$K$5:$K$114,"Ressources Humaines") | G17: Prime de responsabilite | H17: =SUMPRODUCT(('3-Primes & Indemnités'!$F$5:$F$104=H17)*('3-Primes & Indemnités'!$L$5:$L$104))
B18: Finance & Comptabilite | C18: =SUMPRODUCT(('_Données Employés'!$K$5:$K$114="Finance & Comptabilite")*('_Données Employés'!$R$5:$R$114)) | D18: =COUNTIF('_Données Employés'!$K$5:$K$114,"Finance & Comptabilite") | G18: Prime de rendement | H18: =SUMPRODUCT(('3-Primes & Indemnités'!$F$5:$F$104=H18)*('3-Primes & Indemnités'!$L$5:$L$104))
B19: Reception & Front Office | C19: =SUMPRODUCT(('_Données Employés'!$K$5:$K$114="Reception & Front Office")*('_Données Employés'!$R$5:$R$114)) | D19: =COUNTIF('_Données Employés'!$K$5:$K$114,"Reception & Front Office") | G19: Indemnite de danger | H19: =SUMPRODUCT(('3-Primes & Indemnités'!$F$5:$F$104=H19)*('3-Primes & Indemnités'!$L$5:$L$104))
B20: Cuisine & Restauration | C20: =SUMPRODUCT(('_Données Employés'!$K$5:$K$114="Cuisine & Restauration")*('_Données Employés'!$R$5:$R$114)) | D20: =COUNTIF('_Données Employés'!$K$5:$K$114,"Cuisine & Restauration") | G20: Prime exceptionnelle | H20: =SUMPRODUCT(('3-Primes & Indemnités'!$F$5:$F$104=H20)*('3-Primes & Indemnités'!$L$5:$L$104))
B21: Securite | C21: =SUMPRODUCT(('_Données Employés'!$K$5:$K$114="Securite")*('_Données Employés'!$R$5:$R$114)) | D21: =COUNTIF('_Données Employés'!$K$5:$K$114,"Securite") | G21: Prime d'anciennete | H21: =SUMPRODUCT(('3-Primes & Indemnités'!$F$5:$F$104=H21)*('3-Primes & Indemnités'!$L$5:$L$104))
B22: Entretien & Maintenance | C22: =SUMPRODUCT(('_Données Employés'!$K$5:$K$114="Entretien & Maintenance")*('_Données Employés'!$R$5:$R$114)) | D22: =COUNTIF('_Données Employés'!$K$5:$K$114,"Entretien & Maintenance")

Sheet 1-Grille Salariale
B2: PAIE — 1-Grille Salariale
B4: N° Grille | C4: Poste | D4: Département | E4: Catégorie | F4: Échelon | G4: Salaire Base (FCFA) | H4: Prime Ancienneté (FCFA) | I4: Salaire Total (FCFA) | J4: Nb Postes | K4: Masse Poste (FCFA) | L4: Salaire Marché (FCFA) | M4: Statut
B5: GR-001 | C5: DRH | D5: Ressources Humaines | E5: Cadre superieur | F5: Echelon 5 | G5: 635000 | H5: 31750 | I5: 666750 | J5: 1 | K5: 666750 | L5: 700000 | M5: Actif
B6: GR-002 | C6: Chef Comptable | D6: Finance & Comptabilite | E6: Cadre | F6: Echelon 4 | G6: 484000 | H6: 24200 | I6: 508200 | J6: 1 | K6: 508200 | L6: 520000 | M6: Actif
B7: GR-003 | C7: Receptionniste | D7: Reception & Front Office | E7: Employe | F7: Echelon 3 | G7: 207000 | H7: 10350 | I7: 217350 | J7: 6 | K7: 1304100 | L7: 220000 | M7: Actif
B8: GR-004 | C8: Chef cuisinier | D8: Cuisine & Restauration | E8: Maitrise | F8: Echelon 3 | G8: 253000 | H8: 12650 | I8: 265650 | J8: 5 | K8: 1328250 | L8: 260000 | M8: Actif
B9: GR-005 | C9: Agent securite | D9: Securite | E9: Ouvrier | F9: Echelon 2 | G9: 149500 | H9: 7475 | I9: 156975 | J9: 4 | K9: 627900 | L9: 145000 | M9: Actif
B10: =IF(C10="","GR"&TEXT(COUNTA($C$5:C10),"000")) | H10: =IF(F10="","",IFERROR(F10*0.05,0)) | I10: =IF(F10="","",IFERROR(F10+G10,0)) | K10: =IF(OR(F10="",I10=""),"",IFERROR(H10*I10,0))
B11: =IF(C11="","GR"&TEXT(COUNTA($C$5:C11),"000")) | H11: =IF(F11="","",IFERROR(F11*0.05,0)) | I11: =IF(F11="","",IFERROR(F11+G11,0)) | K11: =IF(OR(F11="",I11=""),"",IFERROR(H11*I11,0))
B12: =IF(C12="","GR"&TEXT(COUNTA($C$5:C12),"000")) | H12: =IF(F12="","",IFERROR(F12*0.05,0)) | I12: =IF(F12="","",IFERROR(F12+G12,0)) | K12: =IF(OR(F12="",I12=""),"",IFERROR(H12*I12,0))
B13: =IF(C13="","GR"&TEXT(COUNTA($C$5:C13),"000")) | H13: =IF(F13="","",IFERROR(F13*0.05,0)) | I13: =IF(F13="","",IFERROR(F13+G13,0)) | K13: =IF(OR(F13="",I13=""),"",IFERROR(H13*I13,0))
B14: =IF(C14="","GR"&TEXT(COUNTA($C$5:C14),"000")) | H14: =IF(F14="","",IFERROR(F14*0.05,0)) | I14: =IF(F14="","",IFERROR(F14+G14,0)) | K14: =IF(OR(F14="",I14=""),"",IFERROR(H14*I14,0))
B15: =IF(C15="","GR"&TEXT(COUNTA($C$5:C15),"000")) | H15: =IF(F15="","",IFERROR(F15*0.05,0)) | I15: =IF(F15="","",IFERROR(F15+G15,0)) | K15: =IF(OR(F15="",I15=""),"",IFERROR(H15*I15,0))
B16: =IF(C16="","GR"&TEXT(COUNTA($C$5:C16),"000")) | H16: =IF(F16="","",IFERROR(F16*0.05,0)) | I16: =IF(F16="","",IFERROR(F16+G16,0)) | K16: =IF(OR(F16="",I16=""),"",IFERROR(H16*I16,0))
B17: =IF(C17="","GR"&TEXT(COUNTA($C$5:C17),"000")) | H17: =IF(F17="","",IFERROR(F17*0.05,0)) | I17: =IF(F17="","",IFERROR(F17+G17,0)) | K17: =IF(OR(F17="",I17=""),"",IFERROR(H17*I17,0))
B18: =IF(C18="","GR"&TEXT(COUNTA($C$5:C18),"000")) | H18: =IF(F18="","",IFERROR(F18*0.05,0)) | I18: =IF(F18="","",IFERROR(F18+G18,0)) | K18: =IF(OR(F18="",I18=""),"",IFERROR(H18*I18,0))
B19: =IF(C19="","GR"&TEXT(COUNTA($C$5:C19),"000")) | H19: =IF(F19="","",IFERROR(F19*0.05,0)) | I19: =IF(F19="","",IFERROR(F19+G19,0)) | K19: =IF(OR(F19="",I19=""),"",IFERROR(H19*I19,0))
B20: =IF(C20="","GR"&TEXT(COUNTA($C$5:C20),"000")) | H20: =IF(F20="","",IFERROR(F20*0.05,0)) | I20: =IF(F20="","",IFERROR(F20+G20,0)) | K20: =IF(OR(F20="",I20=""),"",IFERROR(H20*I20,0))
B21: =IF(C21="","GR"&TEXT(COUNTA($C$5:C21),"000")) | H21: =IF(F21="","",IFERROR(F21*0.05,0)) | I21: =IF(F21="","",IFERROR(F21+G21,0)) | K21: =IF(OR(F21="",I21=""),"",IFERROR(H21*I21,0))
... B104: =IF(C104="","GR"&TEXT(COUNTA($C$5:C104),"000")) | H104: =IF(F104="","",IFERROR(F104*0.05,0)) | I104: =IF(F104="","",IFERROR(F104+G104,0)) | K104: =IF(OR(F104="",I104=""),"",IFERROR(H104*I104,0))
B107: KPI Postes actifs | C107: KPI Masse totale (FCFA) | D107: KPI Écart moyen marché (FCFA)
B108: =COUNTIF(M5:M104,"Actif") | C108: =SUM(K5:K104) | D108: =IFERROR(AVERAGE(L5:L104),0)

Sheet 2-Calcul des Salaires
B2: PAIE — Moteur de calcul des salaires (lié à _Données Employés)
B4: Matricule | C4: Nom Employé | D4: Mois | E4: Salaire Base | F4: Prime Ancienneté 5% | G4: Indemn. Logement 30% | H4: Prime Transport | I4: Total Primes | J4: Salaire Brut | K4: CNPS 2.8% | L4: CNAMGS 1.5% | M4: IR Salaires | N4: Total Retenues | O4: Salaire Net | P4: Charges Patron. 8.2% | Q4: Coût Total Emp.
B5: EMP-001 | C5: Nganou Clarisse | D5: Juin | E5: =VLOOKUP(B5,'_Données Employés'!$B$5:$S$114,16,FALSE) | F5: =IF(E5="","",E5*0.05) | G5: =IF(E5="","",E5*0.3) | H5: =IF(E5="","",25000) | I5: =IF(E5="","",SUM(F5:H5)) | J5: =IF(E5="","",E5+I5) | K5: =IF(J5="","",J5*0.028) | L5: =IF(J5="","",J5*0.015) | M5: =IF(J5="","",IFERROR(IF(J5<=62000,0,IF(J5<=146000,(J5-62000)*0.1,IF(J5<=236000,8400+(J5-146000)*0.15,IF(J5<=360000,21900+(J5-236000)*0.25,IF(J5<=550000,51900+(J5-360000)*0.35,118400+(J5-550000)*0.4))))),0)) | N5: =IF(J5="","",SUM(K5:M5)) | O5: =IF(J5="","",J5-N5) | P5: =IF(J5="","",J5*0.082) | Q5: =IF(J5="","",J5+P5)
B6: EMP-002 | C6: Tchinda Armand | D6: Juin | E6: =VLOOKUP(B6,'_Données Employés'!$B$5:$S$114,16,FALSE) | F6: =IF(E6="","",E6*0.05) | G6: =IF(E6="","",E6*0.3) | H6: =IF(E6="","",25000) | I6: =IF(E6="","",SUM(F6:H6)) | J6: =IF(E6="","",E6+I6) | K6: =IF(J6="","",J6*0.028) | L6: =IF(J6="","",J6*0.015) | M6: =IF(J6="","",IFERROR(IF(J6<=62000,0,IF(J6<=146000,(J6-62000)*0.1,IF(J6<=236000,8400+(J6-146000)*0.15,IF(J6<=360000,21900+(J6-236000)*0.25,IF(J6<=550000,51900+(J6-360000)*0.35,118400+(J6-550000)*0.4))))),0)) | N6: =IF(J6="","",SUM(K6:M6)) | O6: =IF(J6="","",J6-N6) | P6: =IF(J6="","",J6*0.082) | Q6: =IF(J6="","",J6+P6)
B7: EMP-003 | C7: Fotso Marguerite | D7: Juin | E7: =VLOOKUP(B7,'_Données Employés'!$B$5:$S$114,16,FALSE) | F7: =IF(E7="","",E7*0.05) | G7: =IF(E7="","",E7*0.3) | H7: =IF(E7="","",25000) | I7: =IF(E7="","",SUM(F7:H7)) | J7: =IF(E7="","",E7+I7) | K7: =IF(J7="","",J7*0.028) | L7: =IF(J7="","",J7*0.015) | M7: =IF(J7="","",IFERROR(IF(J7<=62000,0,IF(J7<=146000,(J7-62000)*0.1,IF(J7<=236000,8400+(J7-146000)*0.15,IF(J7<=360000,21900+(J7-236000)*0.25,IF(J7<=550000,51900+(J7-360000)*0.35,118400+(J7-550000)*0.4))))),0)) | N7: =IF(J7="","",SUM(K7:M7)) | O7: =IF(J7="","",J7-N7) | P7: =IF(J7="","",J7*0.082) | Q7: =IF(J7="","",J7+P7)
B8: EMP-004 | C8: Ouedraogo Ibrahim | D8: Juin | E8: =VLOOKUP(B8,'_Données Employés'!$B$5:$S$114,16,FALSE) | F8: =IF(E8="","",E8*0.05) | G8: =IF(E8="","",E8*0.3) | H8: =IF(E8="","",25000) | I8: =IF(E8="","",SUM(F8:H8)) | J8: =IF(E8="","",E8+I8) | K8: =IF(J8="","",J8*0.028) | L8: =IF(J8="","",J8*0.015) | M8: =IF(J8="","",IFERROR(IF(J8<=62000,0,IF(J8<=146000,(J8-62000)*0.1,IF(J8<=236000,8400+(J8-146000)*0.15,IF(J8<=360000,21900+(J8-236000)*0.25,IF(J8<=550000,51900+(J8-360000)*0.35,118400+(J8-550000)*0.4))))),0)) | N8: =IF(J8="","",SUM(K8:M8)) | O8: =IF(J8="","",J8-N8) | P8: =IF(J8="","",J8*0.082) | Q8: =IF(J8="","",J8+P8)
B9: EMP-005 | C9: Diallo Moussa | D9: Juin | E9: =VLOOKUP(B9,'_Données Employés'!$B$5:$S$114,16,FALSE) | F9: =IF(E9="","",E9*0.05) | G9: =IF(E9="","",E9*0.3) | H9: =IF(E9="","",25000) | I9: =IF(E9="","",SUM(F9:H9)) | J9: =IF(E9="","",E9+I9) | K9: =IF(J9="","",J9*0.028) | L9: =IF(J9="","",J9*0.015) | M9: =IF(J9="","",IFERROR(IF(J9<=62000,0,IF(J9<=146000,(J9-62000)*0.1,IF(J9<=236000,8400+(J9-146000)*0.15,IF(J9<=360000,21900+(J9-236000)*0.25,IF(J9<=550000,51900+(J9-360000)*0.35,118400+(J9-550000)*0.4))))),0)) | N9: =IF(J9="","",SUM(K9:M9)) | O9: =IF(J9="","",J9-N9) | P9: =IF(J9="","",J9*0.082) | Q9: =IF(J9="","",J9+P9)
B10: EMP-006 | C10: Ngassa Brigitte | D10: Juin | E10: =VLOOKUP(B10,'_Données Employés'!$B$5:$S$114,16,FALSE) | F10: =IF(E10="","",E10*0.05) | G10: =IF(E10="","",E10*0.3) | H10: =IF(E10="","",25000) | I10: =IF(E10="","",SUM(F10:H10)) | J10: =IF(E10="","",E10+I10) | K10: =IF(J10="","",J10*0.028) | L10: =IF(J10="","",J10*0.015) | M10: =IF(J10="","",IFERROR(IF(J10<=62000,0,IF(J10<=146000,(J10-62000)*0.1,IF(J10<=236000,8400+(J10-146000)*0.15,IF(J10<=360000,21900+(J10-236000)*0.25,IF(J10<=550000,51900+(J10-360000)*0.35,118400+(J10-550000)*0.4))))),0)) | N10: =IF(J10="","",SUM(K10:M10)) | O10: =IF(J10="","",J10-N10) | P10: =IF(J10="","",J10*0.082) | Q10: =IF(J10="","",J10+P10)
B11: EMP-007 | C11: Kamga Pierre | D11: Juin | E11: =VLOOKUP(B11,'_Données Employés'!$B$5:$S$114,16,FALSE) | F11: =IF(E11="","",E11*0.05) | G11: =IF(E11="","",E11*0.3) | H11: =IF(E11="","",25000) | I11: =IF(E11="","",SUM(F11:H11)) | J11: =IF(E11="","",E11+I11) | K11: =IF(J11="","",J11*0.028) | L11: =IF(J11="","",J11*0.015) | M11: =IF(J11="","",IFERROR(IF(J11<=62000,0,IF(J11<=146000,(J11-62000)*0.1,IF(J11<=236000,8400+(J11-146000)*0.15,IF(J11<=360000,21900+(J11-236000)*0.25,IF(J11<=550000,51900+(J11-360000)*0.35,118400+(J11-550000)*0.4))))),0)) | N11: =IF(J11="","",SUM(K11:M11)) | O11: =IF(J11="","",J11-N11) | P11: =IF(J11="","",J11*0.082) | Q11: =IF(J11="","",J11+P11)
B12: EMP-008 | C12: Ekode Aline | D12: Juin | E12: =VLOOKUP(B12,'_Données Employés'!$B$5:$S$114,16,FALSE) | F12: =IF(E12="","",E12*0.05) | G12: =IF(E12="","",E12*0.3) | H12: =IF(E12="","",25000) | I12: =IF(E12="","",SUM(F12:H12)) | J12: =IF(E12="","",E12+I12) | K12: =IF(J12="","",J12*0.028) | L12: =IF(J12="","",J12*0.015) | M12: =IF(J12="","",IFERROR(IF(J12<=62000,0,IF(J12<=146000,(J12-62000)*0.1,IF(J12<=236000,8400+(J12-146000)*0.15,IF(J12<=360000,21900+(J12-236000)*0.25,IF(J12<=550000,51900+(J12-360000)*0.35,118400+(J12-550000)*0.4))))),0)) | N12: =IF(J12="","",SUM(K12:M12)) | O12: =IF(J12="","",J12-N12) | P12: =IF(J12="","",J12*0.082) | Q12: =IF(J12="","",J12+P12)
B13: EMP-009 | C13: Bouba Hassan | D13: Juin | E13: =VLOOKUP(B13,'_Données Employés'!$B$5:$S$114,16,FALSE) | F13: =IF(E13="","",E13*0.05) | G13: =IF(E13="","",E13*0.3) | H13: =IF(E13="","",25000) | I13: =IF(E13="","",SUM(F13:H13)) | J13: =IF(E13="","",E13+I13) | K13: =IF(J13="","",J13*0.028) | L13: =IF(J13="","",J13*0.015) | M13: =IF(J13="","",IFERROR(IF(J13<=62000,0,IF(J13<=146000,(J13-62000)*0.1,IF(J13<=236000,8400+(J13-146000)*0.15,IF(J13<=360000,21900+(J13-236000)*0.25,IF(J13<=550000,51900+(J13-360000)*0.35,118400+(J13-550000)*0.4))))),0)) | N13: =IF(J13="","",SUM(K13:M13)) | O13: =IF(J13="","",J13-N13) | P13: =IF(J13="","",J13*0.082) | Q13: =IF(J13="","",J13+P13)
B14: EMP-010 | C14: Atangana Simon | D14: Juin | E14: =VLOOKUP(B14,'_Données Employés'!$B$5:$S$114,16,FALSE) | F14: =IF(E14="","",E14*0.05) | G14: =IF(E14="","",E14*0.3) | H14: =IF(E14="","",25000) | I14: =IF(E14="","",SUM(F14:H14)) | J14: =IF(E14="","",E14+I14) | K14: =IF(J14="","",J14*0.028) | L14: =IF(J14="","",J14*0.015) | M14: =IF(J14="","",IFERROR(IF(J14<=62000,0,IF(J14<=146000,(J14-62000)*0.1,IF(J14<=236000,8400+(J14-146000)*0.15,IF(J14<=360000,21900+(J14-236000)*0.25,IF(J14<=550000,51900+(J14-360000)*0.35,118400+(J14-550000)*0.4))))),0)) | N14: =IF(J14="","",SUM(K14:M14)) | O14: =IF(J14="","",J14-N14) | P14: =IF(J14="","",J14*0.082) | Q14: =IF(J14="","",J14+P14)
C15: =IF(B15="","",VLOOKUP(B15,'_Données Employés'!$B$5:$S$114,3,FALSE)) | E15: =IF(B15="","",VLOOKUP(B15,'_Données Employés'!$B$5:$S$114,16,FALSE)) | F15: =IF(E15="","",E15*0.05) | G15: =IF(E15="","",E15*0.3) | H15: =IF(E15="","",25000) | I15: =IF(E15="","",SUM(F15:H15)) | J15: =IF(E15="","",E15+I15) | K15: =IF(J15="","",J15*0.028) | L15: =IF(J15="","",J15*0.015) | M15: =IF(J15="","",IFERROR(IF(J15<=62000,0,IF(J15<=146000,(J15-62000)*0.1,IF(J15<=236000,8400+(J15-146000)*0.15,IF(J15<=360000,21900+(J15-236000)*0.25,IF(J15<=550000,51900+(J15-360000)*0.35,118400+(J15-550000)*0.4))))),0)) | N15: =IF(J15="","",SUM(K15:M15)) | O15: =IF(J15="","",J15-N15) | P15: =IF(J15="","",J15*0.082) | Q15: =IF(J15="","",J15+P15)
C16: =IF(B16="","",VLOOKUP(B16,'_Données Employés'!$B$5:$S$114,3,FALSE)) | E16: =IF(B16="","",VLOOKUP(B16,'_Données Employés'!$B$5:$S$114,16,FALSE)) | F16: =IF(E16="","",E16*0.05) | G16: =IF(E16="","",E16*0.3) | H16: =IF(E16="","",25000) | I16: =IF(E16="","",SUM(F16:H16)) | J16: =IF(E16="","",E16+I16) | K16: =IF(J16="","",J16*0.028) | L16: =IF(J16="","",J16*0.015) | M16: =IF(J16="","",IFERROR(IF(J16<=62000,0,IF(J16<=146000,(J16-62000)*0.1,IF(J16<=236000,8400+(J16-146000)*0.15,IF(J16<=360000,21900+(J16-236000)*0.25,IF(J16<=550000,51900+(J16-360000)*0.35,118400+(J16-550000)*0.4))))),0)) | N16: =IF(J16="","",SUM(K16:M16)) | O16: =IF(J16="","",J16-N16) | P16: =IF(J16="","",J16*0.082) | Q16: =IF(J16="","",J16+P16)
C17: =IF(B17="","",VLOOKUP(B17,'_Données Employés'!$B$5:$S$114,3,FALSE)) | E17: =IF(B17="","",VLOOKUP(B17,'_Données Employés'!$B$5:$S$114,16,FALSE)) | F17: =IF(E17="","",E17*0.05) | G17: =IF(E17="","",E17*0.3) | H17: =IF(E17="","",25000) | I17: =IF(E17="","",SUM(F17:H17)) | J17: =IF(E17="","",E17+I17) | K17: =IF(J17="","",J17*0.028) | L17: =IF(J17="","",J17*0.015) | M17: =IF(J17="","",IFERROR(IF(J17<=62000,0,IF(J17<=146000,(J17-62000)*0.1,IF(J17<=236000,8400+(J17-146000)*0.15,IF(J17<=360000,21900+(J17-236000)*0.25,IF(J17<=550000,51900+(J17-360000)*0.35,118400+(J17-550000)*0.4))))),0)) | N17: =IF(J17="","",SUM(K17:M17)) | O17: =IF(J17="","",J17-N17) | P17: =IF(J17="","",J17*0.082) | Q17: =IF(J17="","",J17+P17)
C18: =IF(B18="","",VLOOKUP(B18,'_Données Employés'!$B$5:$S$114,3,FALSE)) | E18: =IF(B18="","",VLOOKUP(B18,'_Données Employés'!$B$5:$S$114,16,FALSE)) | F18: =IF(E18="","",E18*0.05) | G18: =IF(E18="","",E18*0.3) | H18: =IF(E18="","",25000) | I18: =IF(E18="","",SUM(F18:H18)) | J18: =IF(E18="","",E18+I18) | K18: =IF(J18="","",J18*0.028) | L18: =IF(J18="","",J18*0.015) | M18: =IF(J18="","",IFERROR(IF(J18<=62000,0,IF(J18<=146000,(J18-62000)*0.1,IF(J18<=236000,8400+(J18-146000)*0.15,IF(J18<=360000,21900+(J18-236000)*0.25,IF(J18<=550000,51900+(J18-360000)*0.35,118400+(J18-550000)*0.4))))),0)) | N18: =IF(J18="","",SUM(K18:M18)) | O18: =IF(J18="","",J18-N18) | P18: =IF(J18="","",J18*0.082) | Q18: =IF(J18="","",J18+P18)
C19: =IF(B19="","",VLOOKUP(B19,'_Données Employés'!$B$5:$S$114,3,FALSE)) | E19: =IF(B19="","",VLOOKUP(B19,'_Données Employés'!$B$5:$S$114,16,FALSE)) | F19: =IF(E19="","",E19*0.05) | G19: =IF(E19="","",E19*0.3) | H19: =IF(E19="","",25000) | I19: =IF(E19="","",SUM(F19:H19)) | J19: =IF(E19="","",E19+I19) | K19: =IF(J19="","",J19*0.028) | L19: =IF(J19="","",J19*0.015) | M19: =IF(J19="","",IFERROR(IF(J19<=62000,0,IF(J19<=146000,(J19-62000)*0.1,IF(J19<=236000,8400+(J19-146000)*0.15,IF(J19<=360000,21900+(J19-236000)*0.25,IF(J19<=550000,51900+(J19-360000)*0.35,118400+(J19-550000)*0.4))))),0)) | N19: =IF(J19="","",SUM(K19:M19)) | O19: =IF(J19="","",J19-N19) | P19: =IF(J19="","",J19*0.082) | Q19: =IF(J19="","",J19+P19)
C20: =IF(B20="","",VLOOKUP(B20,'_Données Employés'!$B$5:$S$114,3,FALSE)) | E20: =IF(B20="","",VLOOKUP(B20,'_Données Employés'!$B$5:$S$114,16,FALSE)) | F20: =IF(E20="","",E20*0.05) | G20: =IF(E20="","",E20*0.3) | H20: =IF(E20="","",25000) | I20: =IF(E20="","",SUM(F20:H20)) | J20: =IF(E20="","",E20+I20) | K20: =IF(J20="","",J20*0.028) | L20: =IF(J20="","",J20*0.015) | M20: =IF(J20="","",IFERROR(IF(J20<=62000,0,IF(J20<=146000,(J20-62000)*0.1,IF(J20<=236000,8400+(J20-146000)*0.15,IF(J20<=360000,21900+(J20-236000)*0.25,IF(J20<=550000,51900+(J20-360000)*0.35,118400+(J20-550000)*0.4))))),0)) | N20: =IF(J20="","",SUM(K20:M20)) | O20: =IF(J20="","",J20-N20) | P20: =IF(J20="","",J20*0.082) | Q20: =IF(J20="","",J20+P20)
C21: =IF(B21="","",VLOOKUP(B21,'_Données Employés'!$B$5:$S$114,3,FALSE)) | E21: =IF(B21="","",VLOOKUP(B21,'_Données Employés'!$B$5:$S$114,16,FALSE)) | F21: =IF(E21="","",E21*0.05) | G21: =IF(E21="","",E21*0.3) | H21: =IF(E21="","",25000) | I21: =IF(E21="","",SUM(F21:H21)) | J21: =IF(E21="","",E21+I21) | K21: =IF(J21="","",J21*0.028) | L21: =IF(J21="","",J21*0.015) | M21: =IF(J21="","",IFERROR(IF(J21<=62000,0,IF(J21<=146000,(J21-62000)*0.1,IF(J21<=236000,8400+(J21-146000)*0.15,IF(J21<=360000,21900+(J21-236000)*0.25,IF(J21<=550000,51900+(J21-360000)*0.35,118400+(J21-550000)*0.4))))),0)) | N21: =IF(J21="","",SUM(K21:M21)) | O21: =IF(J21="","",J21-N21) | P21: =IF(J21="","",J21*0.082) | Q21: =IF(J21="","",J21+P21)
C22: =IF(B22="","",VLOOKUP(B22,'_Données Employés'!$B$5:$S$114,3,FALSE)) | E22: =IF(B22="","",VLOOKUP(B22,'_Données Employés'!$B$5:$S$114,16,FALSE)) | F22: =IF(E22="","",E22*0.05) | G22: =IF(E22="","",E22*0.3) | H22: =IF(E22="","",25000) | I22: =IF(E22="","",SUM(F22:H22)) | J22: =IF(E22="","",E22+I22) | K22: =IF(J22="","",J22*0.028) | L22: =IF(J22="","",J22*0.015) | M22: =IF(J22="","",IFERROR(IF(J22<=62000,0,IF(J22<=146000,(J22-62000)*0.1,IF(J22<=236000,8400+(J22-146000)*0.15,IF(J22<=360000,21900+(J22-236000)*0.25,IF(J22<=550000,51900+(J22-360000)*0.35,118400+(J22-550000)*0.4))))),0)) | N22: =IF(J22="","",SUM(K22:M22)) | O22: =IF(J22="","",J22-N22) | P22: =IF(J22="","",J22*0.082) | Q22: =IF(J22="","",J22+P22)
C23: =IF(B23="","",VLOOKUP(B23,'_Données Employés'!$B$5:$S$114,3,FALSE)) | E23: =IF(B23="","",VLOOKUP(B23,'_Données Employés'!$B$5:$S$114,16,FALSE)) | F23: =IF(E23="","",E23*0.05) | G23: =IF(E23="","",E23*0.3) | H23: =IF(E23="","",25000) | I23: =IF(E23="","",SUM(F23:H23)) | J23: =IF(E23="","",E23+I23) | K23: =IF(J23="","",J23*0.028) | L23: =IF(J23="","",J23*0.015) | M23: =IF(J23="","",IFERROR(IF(J23<=62000,0,IF(J23<=146000,(J23-62000)*0.1,IF(J23<=236000,8400+(J23-146000)*0.15,IF(J23<=360000,21900+(J23-236000)*0.25,IF(J23<=550000,51900+(J23-360000)*0.35,118400+(J23-550000)*0.4))))),0)) | N23: =IF(J23="","",SUM(K23:M23)) | O23: =IF(J23="","",J23-N23) | P23: =IF(J23="","",J23*0.082) | Q23: =IF(J23="","",J23+P23)
C24: =IF(B24="","",VLOOKUP(B24,'_Données Employés'!$B$5:$S$114,3,FALSE)) | E24: =IF(B24="","",VLOOKUP(B24,'_Données Employés'!$B$5:$S$114,16,FALSE)) | F24: =IF(E24="","",E24*0.05) | G24: =IF(E24="","",E24*0.3) | H24: =IF(E24="","",25000) | I24: =IF(E24="","",SUM(F24:H24)) | J24: =IF(E24="","",E24+I24) | K24: =IF(J24="","",J24*0.028) | L24: =IF(J24="","",J24*0.015) | M24: =IF(J24="","",IFERROR(IF(J24<=62000,0,IF(J24<=146000,(J24-62000)*0.1,IF(J24<=236000,8400+(J24-146000)*0.15,IF(J24<=360000,21900+(J24-236000)*0.25,IF(J24<=550000,51900+(J24-360000)*0.35,118400+(J24-550000)*0.4))))),0)) | N24: =IF(J24="","",SUM(K24:M24)) | O24: =IF(J24="","",J24-N24) | P24: =IF(J24="","",J24*0.082) | Q24: =IF(J24="","",J24+P24)
C25: =IF(B25="","",VLOOKUP(B25,'_Données Employés'!$B$5:$S$114,3,FALSE)) | E25: =IF(B25="","",VLOOKUP(B25,'_Données Employés'!$B$5:$S$114,16,FALSE)) | F25: =IF(E25="","",E25*0.05) | G25: =IF(E25="","",E25*0.3) | H25: =IF(E25="","",25000) | I25: =IF(E25="","",SUM(F25:H25)) | J25: =IF(E25="","",E25+I25) | K25: =IF(J25="","",J25*0.028) | L25: =IF(J25="","",J25*0.015) | M25: =IF(J25="","",IFERROR(IF(J25<=62000,0,IF(J25<=146000,(J25-62000)*0.1,IF(J25<=236000,8400+(J25-146000)*0.15,IF(J25<=360000,21900+(J25-236000)*0.25,IF(J25<=550000,51900+(J25-360000)*0.35,118400+(J25-550000)*0.4))))),0)) | N25: =IF(J25="","",SUM(K25:M25)) | O25: =IF(J25="","",J25-N25) | P25: =IF(J25="","",J25*0.082) | Q25: =IF(J25="","",J25+P25)
C26: =IF(B26="","",VLOOKUP(B26,'_Données Employés'!$B$5:$S$114,3,FALSE)) | E26: =IF(B26="","",VLOOKUP(B26,'_Données Employés'!$B$5:$S$114,16,FALSE)) | F26: =IF(E26="","",E26*0.05) | G26: =IF(E26="","",E26*0.3) | H26: =IF(E26="","",25000) | I26: =IF(E26="","",SUM(F26:H26)) | J26: =IF(E26="","",E26+I26) | K26: =IF(J26="","",J26*0.028) | L26: =IF(J26="","",J26*0.015) | M26: =IF(J26="","",IFERROR(IF(J26<=62000,0,IF(J26<=146000,(J26-62000)*0.1,IF(J26<=236000,8400+(J26-146000)*0.15,IF(J26<=360000,21900+(J26-236000)*0.25,IF(J26<=550000,51900+(J26-360000)*0.35,118400+(J26-550000)*0.4))))),0)) | N26: =IF(J26="","",SUM(K26:M26)) | O26: =IF(J26="","",J26-N26) | P26: =IF(J26="","",J26*0.082) | Q26: =IF(J26="","",J26+P26)
... C104: =IF(B104="","",VLOOKUP(B104,'_Données Employés'!$B$5:$S$114,3,FALSE)) | E104: =IF(B104="","",VLOOKUP(B104,'_Données Employés'!$B$5:$S$114,16,FALSE)) | F104: =IF(E104="","",E104*0.05) | G104: =IF(E104="","",E104*0.3) | H104: =IF(E104="","",25000) | I104: =IF(E104="","",SUM(F104:H104)) | J104: =IF(E104="","",E104+I104) | K104: =IF(J104="","",J104*0.028) | L104: =IF(J104="","",J104*0.015) | M104: =IF(J104="","",IFERROR(IF(J104<=62000,0,IF(J104<=146000,(J104-62000)*0.1,IF(J104<=236000,8400+(J104-146000)*0.15,IF(J104<=360000,21900+(J104-236000)*0.25,IF(J104<=550000,51900+(J104-360000)*0.35,118400+(J104-550000)*0.4))))),0)) | N104: =IF(J104="","",SUM(K104:M104)) | O104: =IF(J104="","",J104-N104) | P104: =IF(J104="","",J104*0.082) | Q104: =IF(J104="","",J104+P104)
B107: KPI Masse brute (FCFA) | D107: KPI Masse nette (FCFA) | F107: KPI Coût total employeur (FCFA) | H107: KPI Taux prélèvement moy.
B108: =SUM(J5:J104) | D108: =SUM(O5:O104) | F108: =SUM(Q5:Q104) | H108: =IFERROR(AVERAGE(N5:N104)/AVERAGE(J5:J104),0)

Sheet 3-Primes & Indemnités
B2: PAIE — 3-Primes & Indemnités
B4: N° | C4: Matricule | D4: Nom Employé | E4: Département | F4: Type Prime | G4: Mois | H4: Base Calcul (FCFA) | I4: Taux (%) | J4: Montant Brut (FCFA) | K4: Imposable | L4: Montant Net (FCFA) | M4: Statut
B5: PRI-001 | C5: EMP-001 | D5: Nganou Clarisse | E5: Ressources Humaines | F5: Prime de responsabilite | G5: Juin | H5: 635000 | I5: 10 | J5: 63500 | K5: Oui | L5: 53975 | M5: Approuve
B6: PRI-002 | C6: EMP-002 | D6: Tchinda Armand | E6: Finance & Comptabilite | F6: Prime de rendement | G6: Juin | H6: 484000 | I6: 5 | J6: 24200 | K6: Oui | L6: 20570 | M6: Approuve
B7: PRI-003 | C7: EMP-005 | D7: Diallo Moussa | E7: Cuisine & Restauration | F7: Indemnite de danger | G7: Juin | H7: 253000 | I7: 5 | J7: 12650 | K7: Oui | L7: 10752 | M7: Approuve
B8: PRI-004 | C8: EMP-004 | D8: Ouedraogo Ibrahim | E8: Reception & Front Office | F8: Prime exceptionnelle | G8: Juin | H8: 207000 | I8: 0 | J8: 15000 | K8: Oui | L8: 12750 | M8: Approuve
B9: =IF(C9="","PRI"&TEXT(COUNTA($C$5:C9),"000")) | D9: =IF(C9="","",VLOOKUP(C9,'_Données Employés'!$B$5:$S$114,3,FALSE)) | E9: =IF(C9="","",VLOOKUP(C9,'_Données Employés'!$B$5:$S$114,10,FALSE)) | J9: =IF(OR(G9="",H9=""),"",IFERROR(G9*H9/100,0)) | L9: =IF(I9="","",IF(I9="Non",I9,IFERROR(I9*0.85,0)))
B10: =IF(C10="","PRI"&TEXT(COUNTA($C$5:C10),"000")) | D10: =IF(C10="","",VLOOKUP(C10,'_Données Employés'!$B$5:$S$114,3,FALSE)) | E10: =IF(C10="","",VLOOKUP(C10,'_Données Employés'!$B$5:$S$114,10,FALSE)) | J10: =IF(OR(G10="",H10=""),"",IFERROR(G10*H10/100,0)) | L10: =IF(I10="","",IF(I10="Non",I10,IFERROR(I10*0.85,0)))
B11: =IF(C11="","PRI"&TEXT(COUNTA($C$5:C11),"000")) | D11: =IF(C11="","",VLOOKUP(C11,'_Données Employés'!$B$5:$S$114,3,FALSE)) | E11: =IF(C11="","",VLOOKUP(C11,'_Données Employés'!$B$5:$S$114,10,FALSE)) | J11: =IF(OR(G11="",H11=""),"",IFERROR(G11*H11/100,0)) | L11: =IF(I11="","",IF(I11="Non",I11,IFERROR(I11*0.85,0)))
B12: =IF(C12="","PRI"&TEXT(COUNTA($C$5:C12),"000")) | D12: =IF(C12="","",VLOOKUP(C12,'_Données Employés'!$B$5:$S$114,3,FALSE)) | E12: =IF(C12="","",VLOOKUP(C12,'_Données Employés'!$B$5:$S$114,10,FALSE)) | J12: =IF(OR(G12="",H12=""),"",IFERROR(G12*H12/100,0)) | L12: =IF(I12="","",IF(I12="Non",I12,IFERROR(I12*0.85,0)))
B13: =IF(C13="","PRI"&TEXT(COUNTA($C$5:C13),"000")) | D13: =IF(C13="","",VLOOKUP(C13,'_Données Employés'!$B$5:$S$114,3,FALSE)) | E13: =IF(C13="","",VLOOKUP(C13,'_Données Employés'!$B$5:$S$114,10,FALSE)) | J13: =IF(OR(G13="",H13=""),"",IFERROR(G13*H13/100,0)) | L13: =IF(I13="","",IF(I13="Non",I13,IFERROR(I13*0.85,0)))
B14: =IF(C14="","PRI"&TEXT(COUNTA($C$5:C14),"000")) | D14: =IF(C14="","",VLOOKUP(C14,'_Données Employés'!$B$5:$S$114,3,FALSE)) | E14: =IF(C14="","",VLOOKUP(C14,'_Données Employés'!$B$5:$S$114,10,FALSE)) | J14: =IF(OR(G14="",H14=""),"",IFERROR(G14*H14/100,0)) | L14: =IF(I14="","",IF(I14="Non",I14,IFERROR(I14*0.85,0)))
B15: =IF(C15="","PRI"&TEXT(COUNTA($C$5:C15),"000")) | D15: =IF(C15="","",VLOOKUP(C15,'_Données Employés'!$B$5:$S$114,3,FALSE)) | E15: =IF(C15="","",VLOOKUP(C15,'_Données Employés'!$B$5:$S$114,10,FALSE)) | J15: =IF(OR(G15="",H15=""),"",IFERROR(G15*H15/100,0)) | L15: =IF(I15="","",IF(I15="Non",I15,IFERROR(I15*0.85,0)))
B16: =IF(C16="","PRI"&TEXT(COUNTA($C$5:C16),"000")) | D16: =IF(C16="","",VLOOKUP(C16,'_Données Employés'!$B$5:$S$114,3,FALSE)) | E16: =IF(C16="","",VLOOKUP(C16,'_Données Employés'!$B$5:$S$114,10,FALSE)) | J16: =IF(OR(G16="",H16=""),"",IFERROR(G16*H16/100,0)) | L16: =IF(I16="","",IF(I16="Non",I16,IFERROR(I16*0.85,0)))
B17: =IF(C17="","PRI"&TEXT(COUNTA($C$5:C17),"000")) | D17: =IF(C17="","",VLOOKUP(C17,'_Données Employés'!$B$5:$S$114,3,FALSE)) | E17: =IF(C17="","",VLOOKUP(C17,'_Données Employés'!$B$5:$S$114,10,FALSE)) | J17: =IF(OR(G17="",H17=""),"",IFERROR(G17*H17/100,0)) | L17: =IF(I17="","",IF(I17="Non",I17,IFERROR(I17*0.85,0)))
B18: =IF(C18="","PRI"&TEXT(COUNTA($C$5:C18),"000")) | D18: =IF(C18="","",VLOOKUP(C18,'_Données Employés'!$B$5:$S$114,3,FALSE)) | E18: =IF(C18="","",VLOOKUP(C18,'_Données Employés'!$B$5:$S$114,10,FALSE)) | J18: =IF(OR(G18="",H18=""),"",IFERROR(G18*H18/100,0)) | L18: =IF(I18="","",IF(I18="Non",I18,IFERROR(I18*0.85,0)))
B19: =IF(C19="","PRI"&TEXT(COUNTA($C$5:C19),"000")) | D19: =IF(C19="","",VLOOKUP(C19,'_Données Employés'!$B$5:$S$114,3,FALSE)) | E19: =IF(C19="","",VLOOKUP(C19,'_Données Employés'!$B$5:$S$114,10,FALSE)) | J19: =IF(OR(G19="",H19=""),"",IFERROR(G19*H19/100,0)) | L19: =IF(I19="","",IF(I19="Non",I19,IFERROR(I19*0.85,0)))
B20: =IF(C20="","PRI"&TEXT(COUNTA($C$5:C20),"000")) | D20: =IF(C20="","",VLOOKUP(C20,'_Données Employés'!$B$5:$S$114,3,FALSE)) | E20: =IF(C20="","",VLOOKUP(C20,'_Données Employés'!$B$5:$S$114,10,FALSE)) | J20: =IF(OR(G20="",H20=""),"",IFERROR(G20*H20/100,0)) | L20: =IF(I20="","",IF(I20="Non",I20,IFERROR(I20*0.85,0)))
... B104: =IF(C104="","PRI"&TEXT(COUNTA($C$5:C104),"000")) | D104: =IF(C104="","",VLOOKUP(C104,'_Données Employés'!$B$5:$S$114,3,FALSE)) | E104: =IF(C104="","",VLOOKUP(C104,'_Données Employés'!$B$5:$S$114,10,FALSE)) | J104: =IF(OR(G104="",H104=""),"",IFERROR(G104*H104/100,0)) | L104: =IF(I104="","",IF(I104="Non",I104,IFERROR(I104*0.85,0)))
B107: KPI Total brut (FCFA) | C107: KPI Total net (FCFA) | D107: KPI Primes approuvées
B108: =SUM(J5:J104) | C108: =SUM(L5:L104) | D108: =COUNTIF(M5:M104,"Approuve")

Sheet 4-Heures Supplementaires
B2: PAIE — 4-Heures Supplementaires
B4: N° | C4: Matricule | D4: Nom Employé | E4: Mois | F4: Heures Normales | G4: Heures Supp | H4: Taux Majoration (%) | I4: Taux Horaire (FCFA) | J4: Montant Brut (FCFA) | K4: Cotisations (FCFA) | L4: Montant Net (FCFA) | M4: Statut
B5: HS-001 | C5: EMP-004 | D5: Ouedraogo Ibrahim | E5: Juin | F5: 173 | G5: 12 | H5: 25 | I5: 1197 | J5: 17955 | K5: 1796 | L5: 16160 | M5: Valide
B6: HS-002 | C6: EMP-005 | D6: Diallo Moussa | E6: Juin | F6: 173 | G6: 8 | H6: 25 | I6: 1462 | J6: 23392 | K6: 2339 | L6: 21053 | M6: Valide
B7: HS-003 | C7: EMP-010 | D7: Atangana Simon | E7: Juin | F7: 173 | G7: 10 | H7: 25 | I7: 931 | J7: 23275 | K7: 2328 | L7: 20948 | M7: Valide
B8: =IF(C8="","HS"&TEXT(COUNTA($C$5:C8),"000")) | D8: =IF(C8="","",VLOOKUP(C8,'_Données Employés'!$B$5:$S$114,3,FALSE)) | I8: =IF(OR(F8="",G8=""),"",IFERROR(E8/173,0)) | J8: =IF(H8="","",IFERROR(F8*H8*(1+G8/100)/100,0)) | K8: =IF(I8="","",IFERROR(I8*0.1,0)) | L8: =IF(I8="","",IFERROR(I8-J8,0))
B9: =IF(C9="","HS"&TEXT(COUNTA($C$5:C9),"000")) | D9: =IF(C9="","",VLOOKUP(C9,'_Données Employés'!$B$5:$S$114,3,FALSE)) | I9: =IF(OR(F9="",G9=""),"",IFERROR(E9/173,0)) | J9: =IF(H9="","",IFERROR(F9*H9*(1+G9/100)/100,0)) | K9: =IF(I9="","",IFERROR(I9*0.1,0)) | L9: =IF(I9="","",IFERROR(I9-J9,0))
B10: =IF(C10="","HS"&TEXT(COUNTA($C$5:C10),"000")) | D10: =IF(C10="","",VLOOKUP(C10,'_Données Employés'!$B$5:$S$114,3,FALSE)) | I10: =IF(OR(F10="",G10=""),"",IFERROR(E10/173,0)) | J10: =IF(H10="","",IFERROR(F10*H10*(1+G10/100)/100,0)) | K10: =IF(I10="","",IFERROR(I10*0.1,0)) | L10: =IF(I10="","",IFERROR(I10-J10,0))
B11: =IF(C11="","HS"&TEXT(COUNTA($C$5:C11),"000")) | D11: =IF(C11="","",VLOOKUP(C11,'_Données Employés'!$B$5:$S$114,3,FALSE)) | I11: =IF(OR(F11="",G11=""),"",IFERROR(E11/173,0)) | J11: =IF(H11="","",IFERROR(F11*H11*(1+G11/100)/100,0)) | K11: =IF(I11="","",IFERROR(I11*0.1,0)) | L11: =IF(I11="","",IFERROR(I11-J11,0))
B12: =IF(C12="","HS"&TEXT(COUNTA($C$5:C12),"000")) | D12: =IF(C12="","",VLOOKUP(C12,'_Données Employés'!$B$5:$S$114,3,FALSE)) | I12: =IF(OR(F12="",G12=""),"",IFERROR(E12/173,0)) | J12: =IF(H12="","",IFERROR(F12*H12*(1+G12/100)/100,0)) | K12: =IF(I12="","",IFERROR(I12*0.1,0)) | L12: =IF(I12="","",IFERROR(I12-J12,0))
B13: =IF(C13="","HS"&TEXT(COUNTA($C$5:C13),"000")) | D13: =IF(C13="","",VLOOKUP(C13,'_Données Employés'!$B$5:$S$114,3,FALSE)) | I13: =IF(OR(F13="",G13=""),"",IFERROR(E13/173,0)) | J13: =IF(H13="","",IFERROR(F13*H13*(1+G13/100)/100,0)) | K13: =IF(I13="","",IFERROR(I13*0.1,0)) | L13: =IF(I13="","",IFERROR(I13-J13,0))
B14: =IF(C14="","HS"&TEXT(COUNTA($C$5:C14),"000")) | D14: =IF(C14="","",VLOOKUP(C14,'_Données Employés'!$B$5:$S$114,3,FALSE)) | I14: =IF(OR(F14="",G14=""),"",IFERROR(E14/173,0)) | J14: =IF(H14="","",IFERROR(F14*H14*(1+G14/100)/100,0)) | K14: =IF(I14="","",IFERROR(I14*0.1,0)) | L14: =IF(I14="","",IFERROR(I14-J14,0))
B15: =IF(C15="","HS"&TEXT(COUNTA($C$5:C15),"000")) | D15: =IF(C15="","",VLOOKUP(C15,'_Données Employés'!$B$5:$S$114,3,FALSE)) | I15: =IF(OR(F15="",G15=""),"",IFERROR(E15/173,0)) | J15: =IF(H15="","",IFERROR(F15*H15*(1+G15/100)/100,0)) | K15: =IF(I15="","",IFERROR(I15*0.1,0)) | L15: =IF(I15="","",IFERROR(I15-J15,0))
B16: =IF(C16="","HS"&TEXT(COUNTA($C$5:C16),"000")) | D16: =IF(C16="","",VLOOKUP(C16,'_Données Employés'!$B$5:$S$114,3,FALSE)) | I16: =IF(OR(F16="",G16=""),"",IFERROR(E16/173,0)) | J16: =IF(H16="","",IFERROR(F16*H16*(1+G16/100)/100,0)) | K16: =IF(I16="","",IFERROR(I16*0.1,0)) | L16: =IF(I16="","",IFERROR(I16-J16,0))
B17: =IF(C17="","HS"&TEXT(COUNTA($C$5:C17),"000")) | D17: =IF(C17="","",VLOOKUP(C17,'_Données Employés'!$B$5:$S$114,3,FALSE)) | I17: =IF(OR(F17="",G17=""),"",IFERROR(E17/173,0)) | J17: =IF(H17="","",IFERROR(F17*H17*(1+G17/100)/100,0)) | K17: =IF(I17="","",IFERROR(I17*0.1,0)) | L17: =IF(I17="","",IFERROR(I17-J17,0))
B18: =IF(C18="","HS"&TEXT(COUNTA($C$5:C18),"000")) | D18: =IF(C18="","",VLOOKUP(C18,'_Données Employés'!$B$5:$S$114,3,FALSE)) | I18: =IF(OR(F18="",G18=""),"",IFERROR(E18/173,0)) | J18: =IF(H18="","",IFERROR(F18*H18*(1+G18/100)/100,0)) | K18: =IF(I18="","",IFERROR(I18*0.1,0)) | L18: =IF(I18="","",IFERROR(I18-J18,0))
B19: =IF(C19="","HS"&TEXT(COUNTA($C$5:C19),"000")) | D19: =IF(C19="","",VLOOKUP(C19,'_Données Employés'!$B$5:$S$114,3,FALSE)) | I19: =IF(OR(F19="",G19=""),"",IFERROR(E19/173,0)) | J19: =IF(H19="","",IFERROR(F19*H19*(1+G19/100)/100,0)) | K19: =IF(I19="","",IFERROR(I19*0.1,0)) | L19: =IF(I19="","",IFERROR(I19-J19,0))
... B104: =IF(C104="","HS"&TEXT(COUNTA($C$5:C104),"000")) | D104: =IF(C104="","",VLOOKUP(C104,'_Données Employés'!$B$5:$S$114,3,FALSE)) | I104: =IF(OR(F104="",G104=""),"",IFERROR(E104/173,0)) | J104: =IF(H104="","",IFERROR(F104*H104*(1+G104/100)/100,0)) | K104: =IF(I104="","",IFERROR(I104*0.1,0)) | L104: =IF(I104="","",IFERROR(I104-J104,0))
B107: KPI Total HS (h) | C107: KPI Montant brut HS (FCFA) | D107: KPI Montant net HS (FCFA)
B108: =SUM(G5:G104) | C108: =SUM(I5:I104) | D108: =SUM(K5:K104)

Sheet 5-Cotisations Salariales
B2: PAIE — 5-Cotisations Salariales
B4: N° | C4: Matricule | D4: Nom Employé | E4: Salaire Brut (FCFA) | F4: CNPS 2.8% | G4: CNAMGS 1.5% | H4: IR Salaires | I4: Acomptes (FCFA) | J4: Total Retenues (FCFA) | K4: Salaire Net (FCFA) | L4: Mois | M4: Statut
B5: RET-001 | C5: EMP-001 | D5: Nganou Clarisse | E5: 850750 | F5: 23821 | G5: 12761 | H5: 105400 | I5: 0 | J5: 141982 | K5: 708768 | L5: Juin | M5: Valide
B6: RET-002 | C6: EMP-002 | D6: Tchinda Armand | E6: 648100 | F6: 18147 | G6: 9722 | H6: 52000 | I6: 0 | J6: 79868 | K6: 568233 | L6: Juin | M6: Valide
B7: RET-003 | C7: EMP-003 | D7: Fotso Marguerite | E7: 383125 | F7: 10727 | G7: 5747 | H7: 20000 | I7: 0 | J7: 36474 | K7: 346651 | L7: Juin | M7: Valide
B8: =IF(C8="","RET"&TEXT(COUNTA($C$5:C8),"000")) | D8: =IF(C8="","",VLOOKUP(C8,'_Données Employés'!$B$5:$S$114,3,FALSE)) | J8: =IF(D8="","",IFERROR(SUM(E8:H8),0)) | K8: =IF(D8="","",IFERROR(D8-J8,0))
B9: =IF(C9="","RET"&TEXT(COUNTA($C$5:C9),"000")) | D9: =IF(C9="","",VLOOKUP(C9,'_Données Employés'!$B$5:$S$114,3,FALSE)) | J9: =IF(D9="","",IFERROR(SUM(E9:H9),0)) | K9: =IF(D9="","",IFERROR(D9-J9,0))
B10: =IF(C10="","RET"&TEXT(COUNTA($C$5:C10),"000")) | D10: =IF(C10="","",VLOOKUP(C10,'_Données Employés'!$B$5:$S$114,3,FALSE)) | J10: =IF(D10="","",IFERROR(SUM(E10:H10),0)) | K10: =IF(D10="","",IFERROR(D10-J10,0))
B11: =IF(C11="","RET"&TEXT(COUNTA($C$5:C11),"000")) | D11: =IF(C11="","",VLOOKUP(C11,'_Données Employés'!$B$5:$S$114,3,FALSE)) | J11: =IF(D11="","",IFERROR(SUM(E11:H11),0)) | K11: =IF(D11="","",IFERROR(D11-J11,0))
B12: =IF(C12="","RET"&TEXT(COUNTA($C$5:C12),"000")) | D12: =IF(C12="","",VLOOKUP(C12,'_Données Employés'!$B$5:$S$114,3,FALSE)) | J12: =IF(D12="","",IFERROR(SUM(E12:H12),0)) | K12: =IF(D12="","",IFERROR(D12-J12,0))
B13: =IF(C13="","RET"&TEXT(COUNTA($C$5:C13),"000")) | D13: =IF(C13="","",VLOOKUP(C13,'_Données Employés'!$B$5:$S$114,3,FALSE)) | J13: =IF(D13="","",IFERROR(SUM(E13:H13),0)) | K13: =IF(D13="","",IFERROR(D13-J13,0))
B14: =IF(C14="","RET"&TEXT(COUNTA($C$5:C14),"000")) | D14: =IF(C14="","",VLOOKUP(C14,'_Données Employés'!$B$5:$S$114,3,FALSE)) | J14: =IF(D14="","",IFERROR(SUM(E14:H14),0)) | K14: =IF(D14="","",IFERROR(D14-J14,0))
B15: =IF(C15="","RET"&TEXT(COUNTA($C$5:C15),"000")) | D15: =IF(C15="","",VLOOKUP(C15,'_Données Employés'!$B$5:$S$114,3,FALSE)) | J15: =IF(D15="","",IFERROR(SUM(E15:H15),0)) | K15: =IF(D15="","",IFERROR(D15-J15,0))
B16: =IF(C16="","RET"&TEXT(COUNTA($C$5:C16),"000")) | D16: =IF(C16="","",VLOOKUP(C16,'_Données Employés'!$B$5:$S$114,3,FALSE)) | J16: =IF(D16="","",IFERROR(SUM(E16:H16),0)) | K16: =IF(D16="","",IFERROR(D16-J16,0))
B17: =IF(C17="","RET"&TEXT(COUNTA($C$5:C17),"000")) | D17: =IF(C17="","",VLOOKUP(C17,'_Données Employés'!$B$5:$S$114,3,FALSE)) | J17: =IF(D17="","",IFERROR(SUM(E17:H17),0)) | K17: =IF(D17="","",IFERROR(D17-J17,0))
B18: =IF(C18="","RET"&TEXT(COUNTA($C$5:C18),"000")) | D18: =IF(C18="","",VLOOKUP(C18,'_Données Employés'!$B$5:$S$114,3,FALSE)) | J18: =IF(D18="","",IFERROR(SUM(E18:H18),0)) | K18: =IF(D18="","",IFERROR(D18-J18,0))
B19: =IF(C19="","RET"&TEXT(COUNTA($C$5:C19),"000")) | D19: =IF(C19="","",VLOOKUP(C19,'_Données Employés'!$B$5:$S$114,3,FALSE)) | J19: =IF(D19="","",IFERROR(SUM(E19:H19),0)) | K19: =IF(D19="","",IFERROR(D19-J19,0))
... B104: =IF(C104="","RET"&TEXT(COUNTA($C$5:C104),"000")) | D104: =IF(C104="","",VLOOKUP(C104,'_Données Employés'!$B$5:$S$114,3,FALSE)) | J104: =IF(D104="","",IFERROR(SUM(E104:H104),0)) | K104: =IF(D104="","",IFERROR(D104-J104,0))
B107: KPI Total retenues (FCFA) | C107: KPI Salaire net total (FCFA) | D107: KPI Taux prélèvement moy.
B108: =SUM(J5:J104) | C108: =SUM(K5:K104) | D108: =IFERROR(AVERAGE(J5:J104)/AVERAGE(D5:D104),0)

Sheet 6-Deductions Retenues
B2: PAIE — 6-Deductions Retenues
B4: N° | C4: Matricule | D4: Nom Employé | E4: Type Déduction | F4: Base Calcul (FCFA) | G4: Taux (%) | H4: Montant (FCFA) | I4: Mois | J4: Priorité | K4: Statut
B5: DED-001 | C5: EMP-001 | D5: Nganou Clarisse | E5: Acompte | F5: 635000 | G5: 10 | H5: 63500 | I5: Juin | J5: 1 | K5: Valide
B6: DED-002 | C6: EMP-003 | D6: Fotso Marguerite | E6: Pret personnel | F6: 287500 | G6: 5 | H6: 14375 | I6: Juin | J6: 2 | K6: Valide
B7: DED-003 | C7: EMP-007 | D7: Kamga Pierre | E7: Retard | F7: 149500 | G7: 2 | H7: 2990 | I7: Juin | J7: 3 | K7: Valide
B8: =IF(C8="","DED"&TEXT(COUNTA($C$5:C8),"000")) | D8: =IF(C8="","",VLOOKUP(C8,'_Données Employés'!$B$5:$S$114,3,FALSE)) | H8: =IF(OR(E8="",F8=""),"",IFERROR(E8*F8/100,0))
B9: =IF(C9="","DED"&TEXT(COUNTA($C$5:C9),"000")) | D9: =IF(C9="","",VLOOKUP(C9,'_Données Employés'!$B$5:$S$114,3,FALSE)) | H9: =IF(OR(E9="",F9=""),"",IFERROR(E9*F9/100,0))
B10: =IF(C10="","DED"&TEXT(COUNTA($C$5:C10),"000")) | D10: =IF(C10="","",VLOOKUP(C10,'_Données Employés'!$B$5:$S$114,3,FALSE)) | H10: =IF(OR(E10="",F10=""),"",IFERROR(E10*F10/100,0))
B11: =IF(C11="","DED"&TEXT(COUNTA($C$5:C11),"000")) | D11: =IF(C11="","",VLOOKUP(C11,'_Données Employés'!$B$5:$S$114,3,FALSE)) | H11: =IF(OR(E11="",F11=""),"",IFERROR(E11*F11/100,0))
B12: =IF(C12="","DED"&TEXT(COUNTA($C$5:C12),"000")) | D12: =IF(C12="","",VLOOKUP(C12,'_Données Employés'!$B$5:$S$114,3,FALSE)) | H12: =IF(OR(E12="",F12=""),"",IFERROR(E12*F12/100,0))
B13: =IF(C13="","DED"&TEXT(COUNTA($C$5:C13),"000")) | D13: =IF(C13="","",VLOOKUP(C13,'_Données Employés'!$B$5:$S$114,3,FALSE)) | H13: =IF(OR(E13="",F13=""),"",IFERROR(E13*F13/100,0))
B14: =IF(C14="","DED"&TEXT(COUNTA($C$5:C14),"000")) | D14: =IF(C14="","",VLOOKUP(C14,'_Données Employés'!$B$5:$S$114,3,FALSE)) | H14: =IF(OR(E14="",F14=""),"",IFERROR(E14*F14/100,0))
B15: =IF(C15="","DED"&TEXT(COUNTA($C$5:C15),"000")) | D15: =IF(C15="","",VLOOKUP(C15,'_Données Employés'!$B$5:$S$114,3,FALSE)) | H15: =IF(OR(E15="",F15=""),"",IFERROR(E15*F15/100,0))
B16: =IF(C16="","DED"&TEXT(COUNTA($C$5:C16),"000")) | D16: =IF(C16="","",VLOOKUP(C16,'_Données Employés'!$B$5:$S$114,3,FALSE)) | H16: =IF(OR(E16="",F16=""),"",IFERROR(E16*F16/100,0))
B17: =IF(C17="","DED"&TEXT(COUNTA($C$5:C17),"000")) | D17: =IF(C17="","",VLOOKUP(C17,'_Données Employés'!$B$5:$S$114,3,FALSE)) | H17: =IF(OR(E17="",F17=""),"",IFERROR(E17*F17/100,0))
B18: =IF(C18="","DED"&TEXT(COUNTA($C$5:C18),"000")) | D18: =IF(C18="","",VLOOKUP(C18,'_Données Employés'!$B$5:$S$114,3,FALSE)) | H18: =IF(OR(E18="",F18=""),"",IFERROR(E18*F18/100,0))
B19: =IF(C19="","DED"&TEXT(COUNTA($C$5:C19),"000")) | D19: =IF(C19="","",VLOOKUP(C19,'_Données Employés'!$B$5:$S$114,3,FALSE)) | H19: =IF(OR(E19="",F19=""),"",IFERROR(E19*F19/100,0))
... B104: =IF(C104="","DED"&TEXT(COUNTA($C$5:C104),"000")) | D104: =IF(C104="","",VLOOKUP(C104,'_Données Employés'!$B$5:$S$114,3,FALSE)) | H104: =IF(OR(E104="",F104=""),"",IFERROR(E104*F104/100,0))
B107: KPI Total déductions (FCFA) | C107: KPI Nombre retenues
B108: =SUM(G5:G104) | C108: =COUNTA(C5:C104)

Sheet 7-Acomptes Avances
B2: PAIE — 7-Acomptes Avances
B4: N° | C4: Matricule | D4: Nom Employé | E4: Type | F4: Montant Demandé (FCFA) | G4: Montant Accordé (FCFA) | H4: Date Demande | I4: Date Versement | J4: Statut
B5: ACO-001 | C5: EMP-004 | D5: Ouedraogo Ibrahim | E5: Avance salaire | F5: 50000 | G5: 50000 | H5: 2025-06-01 | I5: 2025-06-15 | J5: Approuve
B6: ACO-002 | C6: EMP-006 | D6: Ngassa Brigitte | E6: Acompte | F6: 30000 | G6: 25000 | H6: 2025-06-10 | I6: 2025-06-20 | J6: Approuve
B7: =IF(C7="","ACO"&TEXT(COUNTA($C$5:C7),"000")) | D7: =IF(C7="","",VLOOKUP(C7,'_Données Employés'!$B$5:$S$114,3,FALSE))
B8: =IF(C8="","ACO"&TEXT(COUNTA($C$5:C8),"000")) | D8: =IF(C8="","",VLOOKUP(C8,'_Données Employés'!$B$5:$S$114,3,FALSE))
B9: =IF(C9="","ACO"&TEXT(COUNTA($C$5:C9),"000")) | D9: =IF(C9="","",VLOOKUP(C9,'_Données Employés'!$B$5:$S$114,3,FALSE))
B10: =IF(C10="","ACO"&TEXT(COUNTA($C$5:C10),"000")) | D10: =IF(C10="","",VLOOKUP(C10,'_Données Employés'!$B$5:$S$114,3,FALSE))
B11: =IF(C11="","ACO"&TEXT(COUNTA($C$5:C11),"000")) | D11: =IF(C11="","",VLOOKUP(C11,'_Données Employés'!$B$5:$S$114,3,FALSE))
B12: =IF(C12="","ACO"&TEXT(COUNTA($C$5:C12),"000")) | D12: =IF(C12="","",VLOOKUP(C12,'_Données Employés'!$B$5:$S$114,3,FALSE))
B13: =IF(C13="","ACO"&TEXT(COUNTA($C$5:C13),"000")) | D13: =IF(C13="","",VLOOKUP(C13,'_Données Employés'!$B$5:$S$114,3,FALSE))
B14: =IF(C14="","ACO"&TEXT(COUNTA($C$5:C14),"000")) | D14: =IF(C14="","",VLOOKUP(C14,'_Données Employés'!$B$5:$S$114,3,FALSE))
B15: =IF(C15="","ACO"&TEXT(COUNTA($C$5:C15),"000")) | D15: =IF(C15="","",VLOOKUP(C15,'_Données Employés'!$B$5:$S$114,3,FALSE))
B16: =IF(C16="","ACO"&TEXT(COUNTA($C$5:C16),"000")) | D16: =IF(C16="","",VLOOKUP(C16,'_Données Employés'!$B$5:$S$114,3,FALSE))
B17: =IF(C17="","ACO"&TEXT(COUNTA($C$5:C17),"000")) | D17: =IF(C17="","",VLOOKUP(C17,'_Données Employés'!$B$5:$S$114,3,FALSE))
B18: =IF(C18="","ACO"&TEXT(COUNTA($C$5:C18),"000")) | D18: =IF(C18="","",VLOOKUP(C18,'_Données Employés'!$B$5:$S$114,3,FALSE))
... B104: =IF(C104="","ACO"&TEXT(COUNTA($C$5:C104),"000")) | D104: =IF(C104="","",VLOOKUP(C104,'_Données Employés'!$B$5:$S$114,3,FALSE))
B107: KPI Total accordé (FCFA) | C107: KPI Acomptes en attente
B108: =SUM(F5:F104) | C108: =COUNTIF(I5:I104,"En attente")

Sheet 8-Prets Personnel
B2: PAIE — 8-Prets Personnel
B4: N° | C4: Matricule | D4: Nom Employé | E4: Type Prêt | F4: Montant (FCFA) | G4: Taux Intérêt (%) | H4: Durée (mois) | I4: Mensualité (FCFA) | J4: Total Remboursé (FCFA) | K4: Capital Restant (FCFA) | L4: Statut
B5: PRET-001 | C5: EMP-003 | D5: Fotso Marguerite | E5: Pret logement | F5: 500000 | G5: 2 | H5: 24 | I5: 21540 | J5: 516960 | K5: 483040 | L5: En cours
B6: PRET-002 | C6: EMP-001 | D6: Nganou Clarisse | E6: Pret social | F6: 200000 | G6: 1.5 | H6: 12 | I6: 16928 | J6: 203136 | K6: 196864 | L6: En cours
B7: =IF(C7="","PRET"&TEXT(COUNTA($C$5:C7),"000")) | D7: =IF(C7="","",VLOOKUP(C7,'_Données Employés'!$B$5:$S$114,3,FALSE)) | I7: =IF(OR(F7="",G7=""),"",IFERROR((F7*(1+G7/100*H7/12))/H7,0)) | K7: =IF(F7="","",IFERROR(F7-I7,0))
B8: =IF(C8="","PRET"&TEXT(COUNTA($C$5:C8),"000")) | D8: =IF(C8="","",VLOOKUP(C8,'_Données Employés'!$B$5:$S$114,3,FALSE)) | I8: =IF(OR(F8="",G8=""),"",IFERROR((F8*(1+G8/100*H8/12))/H8,0)) | K8: =IF(F8="","",IFERROR(F8-I8,0))
B9: =IF(C9="","PRET"&TEXT(COUNTA($C$5:C9),"000")) | D9: =IF(C9="","",VLOOKUP(C9,'_Données Employés'!$B$5:$S$114,3,FALSE)) | I9: =IF(OR(F9="",G9=""),"",IFERROR((F9*(1+G9/100*H9/12))/H9,0)) | K9: =IF(F9="","",IFERROR(F9-I9,0))
B10: =IF(C10="","PRET"&TEXT(COUNTA($C$5:C10),"000")) | D10: =IF(C10="","",VLOOKUP(C10,'_Données Employés'!$B$5:$S$114,3,FALSE)) | I10: =IF(OR(F10="",G10=""),"",IFERROR((F10*(1+G10/100*H10/12))/H10,0)) | K10: =IF(F10="","",IFERROR(F10-I10,0))
B11: =IF(C11="","PRET"&TEXT(COUNTA($C$5:C11),"000")) | D11: =IF(C11="","",VLOOKUP(C11,'_Données Employés'!$B$5:$S$114,3,FALSE)) | I11: =IF(OR(F11="",G11=""),"",IFERROR((F11*(1+G11/100*H11/12))/H11,0)) | K11: =IF(F11="","",IFERROR(F11-I11,0))
B12: =IF(C12="","PRET"&TEXT(COUNTA($C$5:C12),"000")) | D12: =IF(C12="","",VLOOKUP(C12,'_Données Employés'!$B$5:$S$114,3,FALSE)) | I12: =IF(OR(F12="",G12=""),"",IFERROR((F12*(1+G12/100*H12/12))/H12,0)) | K12: =IF(F12="","",IFERROR(F12-I12,0))
B13: =IF(C13="","PRET"&TEXT(COUNTA($C$5:C13),"000")) | D13: =IF(C13="","",VLOOKUP(C13,'_Données Employés'!$B$5:$S$114,3,FALSE)) | I13: =IF(OR(F13="",G13=""),"",IFERROR((F13*(1+G13/100*H13/12))/H13,0)) | K13: =IF(F13="","",IFERROR(F13-I13,0))
B14: =IF(C14="","PRET"&TEXT(COUNTA($C$5:C14),"000")) | D14: =IF(C14="","",VLOOKUP(C14,'_Données Employés'!$B$5:$S$114,3,FALSE)) | I14: =IF(OR(F14="",G14=""),"",IFERROR((F14*(1+G14/100*H14/12))/H14,0)) | K14: =IF(F14="","",IFERROR(F14-I14,0))
B15: =IF(C15="","PRET"&TEXT(COUNTA($C$5:C15),"000")) | D15: =IF(C15="","",VLOOKUP(C15,'_Données Employés'!$B$5:$S$114,3,FALSE)) | I15: =IF(OR(F15="",G15=""),"",IFERROR((F15*(1+G15/100*H15/12))/H15,0)) | K15: =IF(F15="","",IFERROR(F15-I15,0))
B16: =IF(C16="","PRET"&TEXT(COUNTA($C$5:C16),"000")) | D16: =IF(C16="","",VLOOKUP(C16,'_Données Employés'!$B$5:$S$114,3,FALSE)) | I16: =IF(OR(F16="",G16=""),"",IFERROR((F16*(1+G16/100*H16/12))/H16,0)) | K16: =IF(F16="","",IFERROR(F16-I16,0))
B17: =IF(C17="","PRET"&TEXT(COUNTA($C$5:C17),"000")) | D17: =IF(C17="","",VLOOKUP(C17,'_Données Employés'!$B$5:$S$114,3,FALSE)) | I17: =IF(OR(F17="",G17=""),"",IFERROR((F17*(1+G17/100*H17/12))/H17,0)) | K17: =IF(F17="","",IFERROR(F17-I17,0))
B18: =IF(C18="","PRET"&TEXT(COUNTA($C$5:C18),"000")) | D18: =IF(C18="","",VLOOKUP(C18,'_Données Employés'!$B$5:$S$114,3,FALSE)) | I18: =IF(OR(F18="",G18=""),"",IFERROR((F18*(1+G18/100*H18/12))/H18,0)) | K18: =IF(F18="","",IFERROR(F18-I18,0))
... B104: =IF(C104="","PRET"&TEXT(COUNTA($C$5:C104),"000")) | D104: =IF(C104="","",VLOOKUP(C104,'_Données Employés'!$B$5:$S$114,3,FALSE)) | I104: =IF(OR(F104="",G104=""),"",IFERROR((F104*(1+G104/100*H104/12))/H104,0)) | K104: =IF(F104="","",IFERROR(F104-I104,0))
B107: KPI Total prêt en cours (FCFA) | C107: KPI Prêts en retard
B108: =SUM(J5:J104) | C108: =COUNTIF(K5:K104,"En retard")

Sheet 9-Historique Paie
B2: PAIE — 9-Historique Paie
B4: N° | C4: Mois | D4: Année | E4: Effectif Payé | F4: Masse Brute (FCFA) | G4: Total Cotisations (FCFA) | H4: Total Déductions (FCFA) | I4: Masse Nette (FCFA) | J4: Coût Employeur (FCFA) | K4: CA Hôtel (FCFA) | L4: Ratio Masse/CA | M4: Statut
B5: HIS-001 | C5: Janvier | D5: 2025 | E5: =IF(C5="","",COUNTIF('2-Calcul des Salaires'!D5:D104,C5)) | F5: =IF(C5="","",SUMIF('2-Calcul des Salaires'!D5:D104,C5,'2-Calcul des Salaires'!J5:J104)) | G5: =IF(C5="","",SUMIF('2-Calcul des Salaires'!D5:D104,C5,'2-Calcul des Salaires'!N5:N104)) | H5: =IF(C5="","",SUMIF('2-Calcul des Salaires'!D5:D104,C5,'2-Calcul des Salaires'!N5:N104)) | I5: =IF(C5="","",SUMIF('2-Calcul des Salaires'!D5:D104,C5,'2-Calcul des Salaires'!O5:O104)) | J5: =IF(C5="","",SUMIF('2-Calcul des Salaires'!D5:D104,C5,'2-Calcul des Salaires'!Q5:Q104)) | K5: 12000000 | M5: Valide
B6: HIS-002 | C6: Fevrier | D6: 2025 | E6: =IF(C6="","",COUNTIF('2-Calcul des Salaires'!D5:D104,C6)) | F6: =IF(C6="","",SUMIF('2-Calcul des Salaires'!D5:D104,C6,'2-Calcul des Salaires'!J5:J104)) | G6: =IF(C6="","",SUMIF('2-Calcul des Salaires'!D5:D104,C6,'2-Calcul des Salaires'!N5:N104)) | H6: =IF(C6="","",SUMIF('2-Calcul des Salaires'!D5:D104,C6,'2-Calcul des Salaires'!N5:N104)) | I6: =IF(C6="","",SUMIF('2-Calcul des Salaires'!D5:D104,C6,'2-Calcul des Salaires'!O5:O104)) | J6: =IF(C6="","",SUMIF('2-Calcul des Salaires'!D5:D104,C6,'2-Calcul des Salaires'!Q5:Q104)) | K6: 11500000 | M6: Valide
B7: HIS-003 | C7: Mars | D7: 2025 | E7: =IF(C7="","",COUNTIF('2-Calcul des Salaires'!D5:D104,C7)) | F7: =IF(C7="","",SUMIF('2-Calcul des Salaires'!D5:D104,C7,'2-Calcul des Salaires'!J5:J104)) | G7: =IF(C7="","",SUMIF('2-Calcul des Salaires'!D5:D104,C7,'2-Calcul des Salaires'!N5:N104)) | H7: =IF(C7="","",SUMIF('2-Calcul des Salaires'!D5:D104,C7,'2-Calcul des Salaires'!N5:N104)) | I7: =IF(C7="","",SUMIF('2-Calcul des Salaires'!D5:D104,C7,'2-Calcul des Salaires'!O5:O104)) | J7: =IF(C7="","",SUMIF('2-Calcul des Salaires'!D5:D104,C7,'2-Calcul des Salaires'!Q5:Q104)) | K7: 12500000 | M7: Valide
B8: =IF(C8="","HIS"&TEXT(COUNTA($C$5:C8),"000")) | E8: =IF(C8="","",COUNTIF('2-Calcul des Salaires'!D5:D104,C8)) | F8: =IF(C8="","",SUMIF('2-Calcul des Salaires'!D5:D104,C8,'2-Calcul des Salaires'!J5:J104)) | G8: =IF(C8="","",SUMIF('2-Calcul des Salaires'!D5:D104,C8,'2-Calcul des Salaires'!N5:N104)) | H8: =IF(C8="","",SUMIF('2-Calcul des Salaires'!D5:D104,C8,'2-Calcul des Salaires'!N5:N104)) | I8: =IF(C8="","",SUMIF('2-Calcul des Salaires'!D5:D104,C8,'2-Calcul des Salaires'!O5:O104)) | J8: =IF(C8="","",SUMIF('2-Calcul des Salaires'!D5:D104,C8,'2-Calcul des Salaires'!Q5:Q104)) | L8: =IF(OR(E8="",K8=""),"",IFERROR(E8/K8,0))
B9: =IF(C9="","HIS"&TEXT(COUNTA($C$5:C9),"000")) | E9: =IF(C9="","",COUNTIF('2-Calcul des Salaires'!D5:D104,C9)) | F9: =IF(C9="","",SUMIF('2-Calcul des Salaires'!D5:D104,C9,'2-Calcul des Salaires'!J5:J104)) | G9: =IF(C9="","",SUMIF('2-Calcul des Salaires'!D5:D104,C9,'2-Calcul des Salaires'!N5:N104)) | H9: =IF(C9="","",SUMIF('2-Calcul des Salaires'!D5:D104,C9,'2-Calcul des Salaires'!N5:N104)) | I9: =IF(C9="","",SUMIF('2-Calcul des Salaires'!D5:D104,C9,'2-Calcul des Salaires'!O5:O104)) | J9: =IF(C9="","",SUMIF('2-Calcul des Salaires'!D5:D104,C9,'2-Calcul des Salaires'!Q5:Q104)) | L9: =IF(OR(E9="",K9=""),"",IFERROR(E9/K9,0))
B10: =IF(C10="","HIS"&TEXT(COUNTA($C$5:C10),"000")) | E10: =IF(C10="","",COUNTIF('2-Calcul des Salaires'!D5:D104,C10)) | F10: =IF(C10="","",SUMIF('2-Calcul des Salaires'!D5:D104,C10,'2-Calcul des Salaires'!J5:J104)) | G10: =IF(C10="","",SUMIF('2-Calcul des Salaires'!D5:D104,C10,'2-Calcul des Salaires'!N5:N104)) | H10: =IF(C10="","",SUMIF('2-Calcul des Salaires'!D5:D104,C10,'2-Calcul des Salaires'!N5:N104)) | I10: =IF(C10="","",SUMIF('2-Calcul des Salaires'!D5:D104,C10,'2-Calcul des Salaires'!O5:O104)) | J10: =IF(C10="","",SUMIF('2-Calcul des Salaires'!D5:D104,C10,'2-Calcul des Salaires'!Q5:Q104)) | L10: =IF(OR(E10="",K10=""),"",IFERROR(E10/K10,0))
B11: =IF(C11="","HIS"&TEXT(COUNTA($C$5:C11),"000")) | E11: =IF(C11="","",COUNTIF('2-Calcul des Salaires'!D5:D104,C11)) | F11: =IF(C11="","",SUMIF('2-Calcul des Salaires'!D5:D104,C11,'2-Calcul des Salaires'!J5:J104)) | G11: =IF(C11="","",SUMIF('2-Calcul des Salaires'!D5:D104,C11,'2-Calcul des Salaires'!N5:N104)) | H11: =IF(C11="","",SUMIF('2-Calcul des Salaires'!D5:D104,C11,'2-Calcul des Salaires'!N5:N104)) | I11: =IF(C11="","",SUMIF('2-Calcul des Salaires'!D5:D104,C11,'2-Calcul des Salaires'!O5:O104)) | J11: =IF(C11="","",SUMIF('2-Calcul des Salaires'!D5:D104,C11,'2-Calcul des Salaires'!Q5:Q104)) | L11: =IF(OR(E11="",K11=""),"",IFERROR(E11/K11,0))
B12: =IF(C12="","HIS"&TEXT(COUNTA($C$5:C12),"000")) | E12: =IF(C12="","",COUNTIF('2-Calcul des Salaires'!D5:D104,C12)) | F12: =IF(C12="","",SUMIF('2-Calcul des Salaires'!D5:D104,C12,'2-Calcul des Salaires'!J5:J104)) | G12: =IF(C12="","",SUMIF('2-Calcul des Salaires'!D5:D104,C12,'2-Calcul des Salaires'!N5:N104)) | H12: =IF(C12="","",SUMIF('2-Calcul des Salaires'!D5:D104,C12,'2-Calcul des Salaires'!N5:N104)) | I12: =IF(C12="","",SUMIF('2-Calcul des Salaires'!D5:D104,C12,'2-Calcul des Salaires'!O5:O104)) | J12: =IF(C12="","",SUMIF('2-Calcul des Salaires'!D5:D104,C12,'2-Calcul des Salaires'!Q5:Q104)) | L12: =IF(OR(E12="",K12=""),"",IFERROR(E12/K12,0))
B13: =IF(C13="","HIS"&TEXT(COUNTA($C$5:C13),"000")) | E13: =IF(C13="","",COUNTIF('2-Calcul des Salaires'!D5:D104,C13)) | F13: =IF(C13="","",SUMIF('2-Calcul des Salaires'!D5:D104,C13,'2-Calcul des Salaires'!J5:J104)) | G13: =IF(C13="","",SUMIF('2-Calcul des Salaires'!D5:D104,C13,'2-Calcul des Salaires'!N5:N104)) | H13: =IF(C13="","",SUMIF('2-Calcul des Salaires'!D5:D104,C13,'2-Calcul des Salaires'!N5:N104)) | I13: =IF(C13="","",SUMIF('2-Calcul des Salaires'!D5:D104,C13,'2-Calcul des Salaires'!O5:O104)) | J13: =IF(C13="","",SUMIF('2-Calcul des Salaires'!D5:D104,C13,'2-Calcul des Salaires'!Q5:Q104)) | L13: =IF(OR(E13="",K13=""),"",IFERROR(E13/K13,0))
B14: =IF(C14="","HIS"&TEXT(COUNTA($C$5:C14),"000")) | E14: =IF(C14="","",COUNTIF('2-Calcul des Salaires'!D5:D104,C14)) | F14: =IF(C14="","",SUMIF('2-Calcul des Salaires'!D5:D104,C14,'2-Calcul des Salaires'!J5:J104)) | G14: =IF(C14="","",SUMIF('2-Calcul des Salaires'!D5:D104,C14,'2-Calcul des Salaires'!N5:N104)) | H14: =IF(C14="","",SUMIF('2-Calcul des Salaires'!D5:D104,C14,'2-Calcul des Salaires'!N5:N104)) | I14: =IF(C14="","",SUMIF('2-Calcul des Salaires'!D5:D104,C14,'2-Calcul des Salaires'!O5:O104)) | J14: =IF(C14="","",SUMIF('2-Calcul des Salaires'!D5:D104,C14,'2-Calcul des Salaires'!Q5:Q104)) | L14: =IF(OR(E14="",K14=""),"",IFERROR(E14/K14,0))
B15: =IF(C15="","HIS"&TEXT(COUNTA($C$5:C15),"000")) | E15: =IF(C15="","",COUNTIF('2-Calcul des Salaires'!D5:D104,C15)) | F15: =IF(C15="","",SUMIF('2-Calcul des Salaires'!D5:D104,C15,'2-Calcul des Salaires'!J5:J104)) | G15: =IF(C15="","",SUMIF('2-Calcul des Salaires'!D5:D104,C15,'2-Calcul des Salaires'!N5:N104)) | H15: =IF(C15="","",SUMIF('2-Calcul des Salaires'!D5:D104,C15,'2-Calcul des Salaires'!N5:N104)) | I15: =IF(C15="","",SUMIF('2-Calcul des Salaires'!D5:D104,C15,'2-Calcul des Salaires'!O5:O104)) | J15: =IF(C15="","",SUMIF('2-Calcul des Salaires'!D5:D104,C15,'2-Calcul des Salaires'!Q5:Q104)) | L15: =IF(OR(E15="",K15=""),"",IFERROR(E15/K15,0))
B16: =IF(C16="","HIS"&TEXT(COUNTA($C$5:C16),"000")) | E16: =IF(C16="","",COUNTIF('2-Calcul des Salaires'!D5:D104,C16)) | F16: =IF(C16="","",SUMIF('2-Calcul des Salaires'!D5:D104,C16,'2-Calcul des Salaires'!J5:J104)) | G16: =IF(C16="","",SUMIF('2-Calcul des Salaires'!D5:D104,C16,'2-Calcul des Salaires'!N5:N104)) | H16: =IF(C16="","",SUMIF('2-Calcul des Salaires'!D5:D104,C16,'2-Calcul des Salaires'!N5:N104)) | I16: =IF(C16="","",SUMIF('2-Calcul des Salaires'!D5:D104,C16,'2-Calcul des Salaires'!O5:O104)) | J16: =IF(C16="","",SUMIF('2-Calcul des Salaires'!D5:D104,C16,'2-Calcul des Salaires'!Q5:Q104)) | L16: =IF(OR(E16="",K16=""),"",IFERROR(E16/K16,0))
B17: =IF(C17="","HIS"&TEXT(COUNTA($C$5:C17),"000")) | E17: =IF(C17="","",COUNTIF('2-Calcul des Salaires'!D5:D104,C17)) | F17: =IF(C17="","",SUMIF('2-Calcul des Salaires'!D5:D104,C17,'2-Calcul des Salaires'!J5:J104)) | G17: =IF(C17="","",SUMIF('2-Calcul des Salaires'!D5:D104,C17,'2-Calcul des Salaires'!N5:N104)) | H17: =IF(C17="","",SUMIF('2-Calcul des Salaires'!D5:D104,C17,'2-Calcul des Salaires'!N5:N104)) | I17: =IF(C17="","",SUMIF('2-Calcul des Salaires'!D5:D104,C17,'2-Calcul des Salaires'!O5:O104)) | J17: =IF(C17="","",SUMIF('2-Calcul des Salaires'!D5:D104,C17,'2-Calcul des Salaires'!Q5:Q104)) | L17: =IF(OR(E17="",K17=""),"",IFERROR(E17/K17,0))
B18: =IF(C18="","HIS"&TEXT(COUNTA($C$5:C18),"000")) | E18: =IF(C18="","",COUNTIF('2-Calcul des Salaires'!D5:D104,C18)) | F18: =IF(C18="","",SUMIF('2-Calcul des Salaires'!D5:D104,C18,'2-Calcul des Salaires'!J5:J104)) | G18: =IF(C18="","",SUMIF('2-Calcul des Salaires'!D5:D104,C18,'2-Calcul des Salaires'!N5:N104)) | H18: =IF(C18="","",SUMIF('2-Calcul des Salaires'!D5:D104,C18,'2-Calcul des Salaires'!N5:N104)) | I18: =IF(C18="","",SUMIF('2-Calcul des Salaires'!D5:D104,C18,'2-Calcul des Salaires'!O5:O104)) | J18: =IF(C18="","",SUMIF('2-Calcul des Salaires'!D5:D104,C18,'2-Calcul des Salaires'!Q5:Q104)) | L18: =IF(OR(E18="",K18=""),"",IFERROR(E18/K18,0))
B19: =IF(C19="","HIS"&TEXT(COUNTA($C$5:C19),"000")) | E19: =IF(C19="","",COUNTIF('2-Calcul des Salaires'!D5:D104,C19)) | F19: =IF(C19="","",SUMIF('2-Calcul des Salaires'!D5:D104,C19,'2-Calcul des Salaires'!J5:J104)) | G19: =IF(C19="","",SUMIF('2-Calcul des Salaires'!D5:D104,C19,'2-Calcul des Salaires'!N5:N104)) | H19: =IF(C19="","",SUMIF('2-Calcul des Salaires'!D5:D104,C19,'2-Calcul des Salaires'!N5:N104)) | I19: =IF(C19="","",SUMIF('2-Calcul des Salaires'!D5:D104,C19,'2-Calcul des Salaires'!O5:O104)) | J19: =IF(C19="","",SUMIF('2-Calcul des Salaires'!D5:D104,C19,'2-Calcul des Salaires'!Q5:Q104)) | L19: =IF(OR(E19="",K19=""),"",IFERROR(E19/K19,0))
B20: =IF(C20="","HIS"&TEXT(COUNTA($C$5:C20),"000")) | E20: =IF(C20="","",COUNTIF('2-Calcul des Salaires'!D5:D104,C20)) | F20: =IF(C20="","",SUMIF('2-Calcul des Salaires'!D5:D104,C20,'2-Calcul des Salaires'!J5:J104)) | G20: =IF(C20="","",SUMIF('2-Calcul des Salaires'!D5:D104,C20,'2-Calcul des Salaires'!N5:N104)) | H20: =IF(C20="","",SUMIF('2-Calcul des Salaires'!D5:D104,C20,'2-Calcul des Salaires'!N5:N104)) | I20: =IF(C20="","",SUMIF('2-Calcul des Salaires'!D5:D104,C20,'2-Calcul des Salaires'!O5:O104)) | J20: =IF(C20="","",SUMIF('2-Calcul des Salaires'!D5:D104,C20,'2-Calcul des Salaires'!Q5:Q104)) | L20: =IF(OR(E20="",K20=""),"",IFERROR(E20/K20,0))
B21: =IF(C21="","HIS"&TEXT(COUNTA($C$5:C21),"000")) | E21: =IF(C21="","",COUNTIF('2-Calcul des Salaires'!D5:D104,C21)) | F21: =IF(C21="","",SUMIF('2-Calcul des Salaires'!D5:D104,C21,'2-Calcul des Salaires'!J5:J104)) | G21: =IF(C21="","",SUMIF('2-Calcul des Salaires'!D5:D104,C21,'2-Calcul des Salaires'!N5:N104)) | H21: =IF(C21="","",SUMIF('2-Calcul des Salaires'!D5:D104,C21,'2-Calcul des Salaires'!N5:N104)) | I21: =IF(C21="","",SUMIF('2-Calcul des Salaires'!D5:D104,C21,'2-Calcul des Salaires'!O5:O104)) | J21: =IF(C21="","",SUMIF('2-Calcul des Salaires'!D5:D104,C21,'2-Calcul des Salaires'!Q5:Q104)) | L21: =IF(OR(E21="",K21=""),"",IFERROR(E21/K21,0))
B22: =IF(C22="","HIS"&TEXT(COUNTA($C$5:C22),"000")) | E22: =IF(C22="","",COUNTIF('2-Calcul des Salaires'!D5:D104,C22)) | F22: =IF(C22="","",SUMIF('2-Calcul des Salaires'!D5:D104,C22,'2-Calcul des Salaires'!J5:J104)) | G22: =IF(C22="","",SUMIF('2-Calcul des Salaires'!D5:D104,C22,'2-Calcul des Salaires'!N5:N104)) | H22: =IF(C22="","",SUMIF('2-Calcul des Salaires'!D5:D104,C22,'2-Calcul des Salaires'!N5:N104)) | I22: =IF(C22="","",SUMIF('2-Calcul des Salaires'!D5:D104,C22,'2-Calcul des Salaires'!O5:O104)) | J22: =IF(C22="","",SUMIF('2-Calcul des Salaires'!D5:D104,C22,'2-Calcul des Salaires'!Q5:Q104)) | L22: =IF(OR(E22="",K22=""),"",IFERROR(E22/K22,0))
B23: =IF(C23="","HIS"&TEXT(COUNTA($C$5:C23),"000")) | E23: =IF(C23="","",COUNTIF('2-Calcul des Salaires'!D5:D104,C23)) | F23: =IF(C23="","",SUMIF('2-Calcul des Salaires'!D5:D104,C23,'2-Calcul des Salaires'!J5:J104)) | G23: =IF(C23="","",SUMIF('2-Calcul des Salaires'!D5:D104,C23,'2-Calcul des Salaires'!N5:N104)) | H23: =IF(C23="","",SUMIF('2-Calcul des Salaires'!D5:D104,C23,'2-Calcul des Salaires'!N5:N104)) | I23: =IF(C23="","",SUMIF('2-Calcul des Salaires'!D5:D104,C23,'2-Calcul des Salaires'!O5:O104)) | J23: =IF(C23="","",SUMIF('2-Calcul des Salaires'!D5:D104,C23,'2-Calcul des Salaires'!Q5:Q104)) | L23: =IF(OR(E23="",K23=""),"",IFERROR(E23/K23,0))
B24: =IF(C24="","HIS"&TEXT(COUNTA($C$5:C24),"000")) | E24: =IF(C24="","",COUNTIF('2-Calcul des Salaires'!D5:D104,C24)) | F24: =IF(C24="","",SUMIF('2-Calcul des Salaires'!D5:D104,C24,'2-Calcul des Salaires'!J5:J104)) | G24: =IF(C24="","",SUMIF('2-Calcul des Salaires'!D5:D104,C24,'2-Calcul des Salaires'!N5:N104)) | H24: =IF(C24="","",SUMIF('2-Calcul des Salaires'!D5:D104,C24,'2-Calcul des Salaires'!N5:N104)) | I24: =IF(C24="","",SUMIF('2-Calcul des Salaires'!D5:D104,C24,'2-Calcul des Salaires'!O5:O104)) | J24: =IF(C24="","",SUMIF('2-Calcul des Salaires'!D5:D104,C24,'2-Calcul des Salaires'!Q5:Q104)) | L24: =IF(OR(E24="",K24=""),"",IFERROR(E24/K24,0))
B25: =IF(C25="","HIS"&TEXT(COUNTA($C$5:C25),"000")) | E25: =IF(C25="","",COUNTIF('2-Calcul des Salaires'!D5:D104,C25)) | F25: =IF(C25="","",SUMIF('2-Calcul des Salaires'!D5:D104,C25,'2-Calcul des Salaires'!J5:J104)) | G25: =IF(C25="","",SUMIF('2-Calcul des Salaires'!D5:D104,C25,'2-Calcul des Salaires'!N5:N104)) | H25: =IF(C25="","",SUMIF('2-Calcul des Salaires'!D5:D104,C25,'2-Calcul des Salaires'!N5:N104)) | I25: =IF(C25="","",SUMIF('2-Calcul des Salaires'!D5:D104,C25,'2-Calcul des Salaires'!O5:O104)) | J25: =IF(C25="","",SUMIF('2-Calcul des Salaires'!D5:D104,C25,'2-Calcul des Salaires'!Q5:Q104)) | L25: =IF(OR(E25="",K25=""),"",IFERROR(E25/K25,0))
B26: =IF(C26="","HIS"&TEXT(COUNTA($C$5:C26),"000")) | E26: =IF(C26="","",COUNTIF('2-Calcul des Salaires'!D5:D104,C26)) | F26: =IF(C26="","",SUMIF('2-Calcul des Salaires'!D5:D104,C26,'2-Calcul des Salaires'!J5:J104)) | G26: =IF(C26="","",SUMIF('2-Calcul des Salaires'!D5:D104,C26,'2-Calcul des Salaires'!N5:N104)) | H26: =IF(C26="","",SUMIF('2-Calcul des Salaires'!D5:D104,C26,'2-Calcul des Salaires'!N5:N104)) | I26: =IF(C26="","",SUMIF('2-Calcul des Salaires'!D5:D104,C26,'2-Calcul des Salaires'!O5:O104)) | J26: =IF(C26="","",SUMIF('2-Calcul des Salaires'!D5:D104,C26,'2-Calcul des Salaires'!Q5:Q104)) | L26: =IF(OR(E26="",K26=""),"",IFERROR(E26/K26,0))
B27: =IF(C27="","HIS"&TEXT(COUNTA($C$5:C27),"000")) | E27: =IF(C27="","",COUNTIF('2-Calcul des Salaires'!D5:D104,C27)) | F27: =IF(C27="","",SUMIF('2-Calcul des Salaires'!D5:D104,C27,'2-Calcul des Salaires'!J5:J104)) | G27: =IF(C27="","",SUMIF('2-Calcul des Salaires'!D5:D104,C27,'2-Calcul des Salaires'!N5:N104)) | H27: =IF(C27="","",SUMIF('2-Calcul des Salaires'!D5:D104,C27,'2-Calcul des Salaires'!N5:N104)) | I27: =IF(C27="","",SUMIF('2-Calcul des Salaires'!D5:D104,C27,'2-Calcul des Salaires'!O5:O104)) | J27: =IF(C27="","",SUMIF('2-Calcul des Salaires'!D5:D104,C27,'2-Calcul des Salaires'!Q5:Q104)) | L27: =IF(OR(E27="",K27=""),"",IFERROR(E27/K27,0))
B28: =IF(C28="","HIS"&TEXT(COUNTA($C$5:C28),"000")) | E28: =IF(C28="","",COUNTIF('2-Calcul des Salaires'!D5:D104,C28)) | F28: =IF(C28="","",SUMIF('2-Calcul des Salaires'!D5:D104,C28,'2-Calcul des Salaires'!J5:J104)) | G28: =IF(C28="","",SUMIF('2-Calcul des Salaires'!D5:D104,C28,'2-Calcul des Salaires'!N5:N104)) | H28: =IF(C28="","",SUMIF('2-Calcul des Salaires'!D5:D104,C28,'2-Calcul des Salaires'!N5:N104)) | I28: =IF(C28="","",SUMIF('2-Calcul des Salaires'!D5:D104,C28,'2-Calcul des Salaires'!O5:O104)) | J28: =IF(C28="","",SUMIF('2-Calcul des Salaires'!D5:D104,C28,'2-Calcul des Salaires'!Q5:Q104)) | L28: =IF(OR(E28="",K28=""),"",IFERROR(E28/K28,0))
B29: =IF(C29="","HIS"&TEXT(COUNTA($C$5:C29),"000")) | E29: =IF(C29="","",COUNTIF('2-Calcul des Salaires'!D5:D104,C29)) | F29: =IF(C29="","",SUMIF('2-Calcul des Salaires'!D5:D104,C29,'2-Calcul des Salaires'!J5:J104)) | G29: =IF(C29="","",SUMIF('2-Calcul des Salaires'!D5:D104,C29,'2-Calcul des Salaires'!N5:N104)) | H29: =IF(C29="","",SUMIF('2-Calcul des Salaires'!D5:D104,C29,'2-Calcul des Salaires'!N5:N104)) | I29: =IF(C29="","",SUMIF('2-Calcul des Salaires'!D5:D104,C29,'2-Calcul des Salaires'!O5:O104)) | J29: =IF(C29="","",SUMIF('2-Calcul des Salaires'!D5:D104,C29,'2-Calcul des Salaires'!Q5:Q104)) | L29: =IF(OR(E29="",K29=""),"",IFERROR(E29/K29,0))
B30: =IF(C30="","HIS"&TEXT(COUNTA($C$5:C30),"000")) | E30: =IF(C30="","",COUNTIF('2-Calcul des Salaires'!D5:D104,C30)) | F30: =IF(C30="","",SUMIF('2-Calcul des Salaires'!D5:D104,C30,'2-Calcul des Salaires'!J5:J104)) | G30: =IF(C30="","",SUMIF('2-Calcul des Salaires'!D5:D104,C30,'2-Calcul des Salaires'!N5:N104)) | H30: =IF(C30="","",SUMIF('2-Calcul des Salaires'!D5:D104,C30,'2-Calcul des Salaires'!N5:N104)) | I30: =IF(C30="","",SUMIF('2-Calcul des Salaires'!D5:D104,C30,'2-Calcul des Salaires'!O5:O104)) | J30: =IF(C30="","",SUMIF('2-Calcul des Salaires'!D5:D104,C30,'2-Calcul des Salaires'!Q5:Q104)) | L30: =IF(OR(E30="",K30=""),"",IFERROR(E30/K30,0))
B31: =IF(C31="","HIS"&TEXT(COUNTA($C$5:C31),"000")) | E31: =IF(C31="","",COUNTIF('2-Calcul des Salaires'!D5:D104,C31)) | F31: =IF(C31="","",SUMIF('2-Calcul des Salaires'!D5:D104,C31,'2-Calcul des Salaires'!J5:J104)) | G31: =IF(C31="","",SUMIF('2-Calcul des Salaires'!D5:D104,C31,'2-Calcul des Salaires'!N5:N104)) | H31: =IF(C31="","",SUMIF('2-Calcul des Salaires'!D5:D104,C31,'2-Calcul des Salaires'!N5:N104)) | I31: =IF(C31="","",SUMIF('2-Calcul des Salaires'!D5:D104,C31,'2-Calcul des Salaires'!O5:O104)) | J31: =IF(C31="","",SUMIF('2-Calcul des Salaires'!D5:D104,C31,'2-Calcul des Salaires'!Q5:Q104)) | L31: =IF(OR(E31="",K31=""),"",IFERROR(E31/K31,0))
B32: =IF(C32="","HIS"&TEXT(COUNTA($C$5:C32),"000")) | E32: =IF(C32="","",COUNTIF('2-Calcul des Salaires'!D5:D104,C32)) | F32: =IF(C32="","",SUMIF('2-Calcul des Salaires'!D5:D104,C32,'2-Calcul des Salaires'!J5:J104)) | G32: =IF(C32="","",SUMIF('2-Calcul des Salaires'!D5:D104,C32,'2-Calcul des Salaires'!N5:N104)) | H32: =IF(C32="","",SUMIF('2-Calcul des Salaires'!D5:D104,C32,'2-Calcul des Salaires'!N5:N104)) | I32: =IF(C32="","",SUMIF('2-Calcul des Salaires'!D5:D104,C32,'2-Calcul des Salaires'!O5:O104)) | J32: =IF(C32="","",SUMIF('2-Calcul des Salaires'!D5:D104,C32,'2-Calcul des Salaires'!Q5:Q104)) | L32: =IF(OR(E32="",K32=""),"",IFERROR(E32/K32,0))
B33: =IF(C33="","HIS"&TEXT(COUNTA($C$5:C33),"000")) | E33: =IF(C33="","",COUNTIF('2-Calcul des Salaires'!D5:D104,C33)) | F33: =IF(C33="","",SUMIF('2-Calcul des Salaires'!D5:D104,C33,'2-Calcul des Salaires'!J5:J104)) | G33: =IF(C33="","",SUMIF('2-Calcul des Salaires'!D5:D104,C33,'2-Calcul des Salaires'!N5:N104)) | H33: =IF(C33="","",SUMIF('2-Calcul des Salaires'!D5:D104,C33,'2-Calcul des Salaires'!N5:N104)) | I33: =IF(C33="","",SUMIF('2-Calcul des Salaires'!D5:D104,C33,'2-Calcul des Salaires'!O5:O104)) | J33: =IF(C33="","",SUMIF('2-Calcul des Salaires'!D5:D104,C33,'2-Calcul des Salaires'!Q5:Q104)) | L33: =IF(OR(E33="",K33=""),"",IFERROR(E33/K33,0))
B34: =IF(C34="","HIS"&TEXT(COUNTA($C$5:C34),"000")) | E34: =IF(C34="","",COUNTIF('2-Calcul des Salaires'!D5:D104,C34)) | F34: =IF(C34="","",SUMIF('2-Calcul des Salaires'!D5:D104,C34,'2-Calcul des Salaires'!J5:J104)) | G34: =IF(C34="","",SUMIF('2-Calcul des Salaires'!D5:D104,C34,'2-Calcul des Salaires'!N5:N104)) | H34: =IF(C34="","",SUMIF('2-Calcul des Salaires'!D5:D104,C34,'2-Calcul des Salaires'!N5:N104)) | I34: =IF(C34="","",SUMIF('2-Calcul des Salaires'!D5:D104,C34,'2-Calcul des Salaires'!O5:O104)) | J34: =IF(C34="","",SUMIF('2-Calcul des Salaires'!D5:D104,C34,'2-Calcul des Salaires'!Q5:Q104)) | L34: =IF(OR(E34="",K34=""),"",IFERROR(E34/K34,0))
B35: =IF(C35="","HIS"&TEXT(COUNTA($C$5:C35),"000")) | E35: =IF(C35="","",COUNTIF('2-Calcul des Salaires'!D5:D104,C35)) | F35: =IF(C35="","",SUMIF('2-Calcul des Salaires'!D5:D104,C35,'2-Calcul des Salaires'!J5:J104)) | G35: =IF(C35="","",SUMIF('2-Calcul des Salaires'!D5:D104,C35,'2-Calcul des Salaires'!N5:N104)) | H35: =IF(C35="","",SUMIF('2-Calcul des Salaires'!D5:D104,C35,'2-Calcul des Salaires'!N5:N104)) | I35: =IF(C35="","",SUMIF('2-Calcul des Salaires'!D5:D104,C35,'2-Calcul des Salaires'!O5:O104)) | J35: =IF(C35="","",SUMIF('2-Calcul des Salaires'!D5:D104,C35,'2-Calcul des Salaires'!Q5:Q104)) | L35: =IF(OR(E35="",K35=""),"",IFERROR(E35/K35,0))
B36: =IF(C36="","HIS"&TEXT(COUNTA($C$5:C36),"000")) | E36: =IF(C36="","",COUNTIF('2-Calcul des Salaires'!D5:D104,C36)) | F36: =IF(C36="","",SUMIF('2-Calcul des Salaires'!D5:D104,C36,'2-Calcul des Salaires'!J5:J104)) | G36: =IF(C36="","",SUMIF('2-Calcul des Salaires'!D5:D104,C36,'2-Calcul des Salaires'!N5:N104)) | H36: =IF(C36="","",SUMIF('2-Calcul des Salaires'!D5:D104,C36,'2-Calcul des Salaires'!N5:N104)) | I36: =IF(C36="","",SUMIF('2-Calcul des Salaires'!D5:D104,C36,'2-Calcul des Salaires'!O5:O104)) | J36: =IF(C36="","",SUMIF('2-Calcul des Salaires'!D5:D104,C36,'2-Calcul des Salaires'!Q5:Q104)) | L36: =IF(OR(E36="",K36=""),"",IFERROR(E36/K36,0))
B37: =IF(C37="","HIS"&TEXT(COUNTA($C$5:C37),"000")) | E37: =IF(C37="","",COUNTIF('2-Calcul des Salaires'!D5:D104,C37)) | F37: =IF(C37="","",SUMIF('2-Calcul des Salaires'!D5:D104,C37,'2-Calcul des Salaires'!J5:J104)) | G37: =IF(C37="","",SUMIF('2-Calcul des Salaires'!D5:D104,C37,'2-Calcul des Salaires'!N5:N104)) | H37: =IF(C37="","",SUMIF('2-Calcul des Salaires'!D5:D104,C37,'2-Calcul des Salaires'!N5:N104)) | I37: =IF(C37="","",SUMIF('2-Calcul des Salaires'!D5:D104,C37,'2-Calcul des Salaires'!O5:O104)) | J37: =IF(C37="","",SUMIF('2-Calcul des Salaires'!D5:D104,C37,'2-Calcul des Salaires'!Q5:Q104)) | L37: =IF(OR(E37="",K37=""),"",IFERROR(E37/K37,0))
B38: =IF(C38="","HIS"&TEXT(COUNTA($C$5:C38),"000")) | E38: =IF(C38="","",COUNTIF('2-Calcul des Salaires'!D5:D104,C38)) | F38: =IF(C38="","",SUMIF('2-Calcul des Salaires'!D5:D104,C38,'2-Calcul des Salaires'!J5:J104)) | G38: =IF(C38="","",SUMIF('2-Calcul des Salaires'!D5:D104,C38,'2-Calcul des Salaires'!N5:N104)) | H38: =IF(C38="","",SUMIF('2-Calcul des Salaires'!D5:D104,C38,'2-Calcul des Salaires'!N5:N104)) | I38: =IF(C38="","",SUMIF('2-Calcul des Salaires'!D5:D104,C38,'2-Calcul des Salaires'!O5:O104)) | J38: =IF(C38="","",SUMIF('2-Calcul des Salaires'!D5:D104,C38,'2-Calcul des Salaires'!Q5:Q104)) | L38: =IF(OR(E38="",K38=""),"",IFERROR(E38/K38,0))
B39: =IF(C39="","HIS"&TEXT(COUNTA($C$5:C39),"000")) | E39: =IF(C39="","",COUNTIF('2-Calcul des Salaires'!D5:D104,C39)) | F39: =IF(C39="","",SUMIF('2-Calcul des Salaires'!D5:D104,C39,'2-Calcul des Salaires'!J5:J104)) | G39: =IF(C39="","",SUMIF('2-Calcul des Salaires'!D5:D104,C39,'2-Calcul des Salaires'!N5:N104)) | H39: =IF(C39="","",SUMIF('2-Calcul des Salaires'!D5:D104,C39,'2-Calcul des Salaires'!N5:N104)) | I39: =IF(C39="","",SUMIF('2-Calcul des Salaires'!D5:D104,C39,'2-Calcul des Salaires'!O5:O104)) | J39: =IF(C39="","",SUMIF('2-Calcul des Salaires'!D5:D104,C39,'2-Calcul des Salaires'!Q5:Q104)) | L39: =IF(OR(E39="",K39=""),"",IFERROR(E39/K39,0))
B40: =IF(C40="","HIS"&TEXT(COUNTA($C$5:C40),"000")) | E40: =IF(C40="","",COUNTIF('2-Calcul des Salaires'!D5:D104,C40)) | F40: =IF(C40="","",SUMIF('2-Calcul des Salaires'!D5:D104,C40,'2-Calcul des Salaires'!J5:J104)) | G40: =IF(C40="","",SUMIF('2-Calcul des Salaires'!D5:D104,C40,'2-Calcul des Salaires'!N5:N104)) | H40: =IF(C40="","",SUMIF('2-Calcul des Salaires'!D5:D104,C40,'2-Calcul des Salaires'!N5:N104)) | I40: =IF(C40="","",SUMIF('2-Calcul des Salaires'!D5:D104,C40,'2-Calcul des Salaires'!O5:O104)) | J40: =IF(C40="","",SUMIF('2-Calcul des Salaires'!D5:D104,C40,'2-Calcul des Salaires'!Q5:Q104)) | L40: =IF(OR(E40="",K40=""),"",IFERROR(E40/K40,0))
B41: =IF(C41="","HIS"&TEXT(COUNTA($C$5:C41),"000")) | E41: =IF(C41="","",COUNTIF('2-Calcul des Salaires'!D5:D104,C41)) | F41: =IF(C41="","",SUMIF('2-Calcul des Salaires'!D5:D104,C41,'2-Calcul des Salaires'!J5:J104)) | G41: =IF(C41="","",SUMIF('2-Calcul des Salaires'!D5:D104,C41,'2-Calcul des Salaires'!N5:N104)) | H41: =IF(C41="","",SUMIF('2-Calcul des Salaires'!D5:D104,C41,'2-Calcul des Salaires'!N5:N104)) | I41: =IF(C41="","",SUMIF('2-Calcul des Salaires'!D5:D104,C41,'2-Calcul des Salaires'!O5:O104)) | J41: =IF(C41="","",SUMIF('2-Calcul des Salaires'!D5:D104,C41,'2-Calcul des Salaires'!Q5:Q104)) | L41: =IF(OR(E41="",K41=""),"",IFERROR(E41/K41,0))
B42: =IF(C42="","HIS"&TEXT(COUNTA($C$5:C42),"000")) | E42: =IF(C42="","",COUNTIF('2-Calcul des Salaires'!D5:D104,C42)) | F42: =IF(C42="","",SUMIF('2-Calcul des Salaires'!D5:D104,C42,'2-Calcul des Salaires'!J5:J104)) | G42: =IF(C42="","",SUMIF('2-Calcul des Salaires'!D5:D104,C42,'2-Calcul des Salaires'!N5:N104)) | H42: =IF(C42="","",SUMIF('2-Calcul des Salaires'!D5:D104,C42,'2-Calcul des Salaires'!N5:N104)) | I42: =IF(C42="","",SUMIF('2-Calcul des Salaires'!D5:D104,C42,'2-Calcul des Salaires'!O5:O104)) | J42: =IF(C42="","",SUMIF('2-Calcul des Salaires'!D5:D104,C42,'2-Calcul des Salaires'!Q5:Q104)) | L42: =IF(OR(E42="",K42=""),"",IFERROR(E42/K42,0))
B43: =IF(C43="","HIS"&TEXT(COUNTA($C$5:C43),"000")) | E43: =IF(C43="","",COUNTIF('2-Calcul des Salaires'!D5:D104,C43)) | F43: =IF(C43="","",SUMIF('2-Calcul des Salaires'!D5:D104,C43,'2-Calcul des Salaires'!J5:J104)) | G43: =IF(C43="","",SUMIF('2-Calcul des Salaires'!D5:D104,C43,'2-Calcul des Salaires'!N5:N104)) | H43: =IF(C43="","",SUMIF('2-Calcul des Salaires'!D5:D104,C43,'2-Calcul des Salaires'!N5:N104)) | I43: =IF(C43="","",SUMIF('2-Calcul des Salaires'!D5:D104,C43,'2-Calcul des Salaires'!O5:O104)) | J43: =IF(C43="","",SUMIF('2-Calcul des Salaires'!D5:D104,C43,'2-Calcul des Salaires'!Q5:Q104)) | L43: =IF(OR(E43="",K43=""),"",IFERROR(E43/K43,0))
B44: =IF(C44="","HIS"&TEXT(COUNTA($C$5:C44),"000")) | E44: =IF(C44="","",COUNTIF('2-Calcul des Salaires'!D5:D104,C44)) | F44: =IF(C44="","",SUMIF('2-Calcul des Salaires'!D5:D104,C44,'2-Calcul des Salaires'!J5:J104)) | G44: =IF(C44="","",SUMIF('2-Calcul des Salaires'!D5:D104,C44,'2-Calcul des Salaires'!N5:N104)) | H44: =IF(C44="","",SUMIF('2-Calcul des Salaires'!D5:D104,C44,'2-Calcul des Salaires'!N5:N104)) | I44: =IF(C44="","",SUMIF('2-Calcul des Salaires'!D5:D104,C44,'2-Calcul des Salaires'!O5:O104)) | J44: =IF(C44="","",SUMIF('2-Calcul des Salaires'!D5:D104,C44,'2-Calcul des Salaires'!Q5:Q104)) | L44: =IF(OR(E44="",K44=""),"",IFERROR(E44/K44,0))
B45: =IF(C45="","HIS"&TEXT(COUNTA($C$5:C45),"000")) | E45: =IF(C45="","",COUNTIF('2-Calcul des Salaires'!D5:D104,C45)) | F45: =IF(C45="","",SUMIF('2-Calcul des Salaires'!D5:D104,C45,'2-Calcul des Salaires'!J5:J104)) | G45: =IF(C45="","",SUMIF('2-Calcul des Salaires'!D5:D104,C45,'2-Calcul des Salaires'!N5:N104)) | H45: =IF(C45="","",SUMIF('2-Calcul des Salaires'!D5:D104,C45,'2-Calcul des Salaires'!N5:N104)) | I45: =IF(C45="","",SUMIF('2-Calcul des Salaires'!D5:D104,C45,'2-Calcul des Salaires'!O5:O104)) | J45: =IF(C45="","",SUMIF('2-Calcul des Salaires'!D5:D104,C45,'2-Calcul des Salaires'!Q5:Q104)) | L45: =IF(OR(E45="",K45=""),"",IFERROR(E45/K45,0))
B46: =IF(C46="","HIS"&TEXT(COUNTA($C$5:C46),"000")) | E46: =IF(C46="","",COUNTIF('2-Calcul des Salaires'!D5:D104,C46)) | F46: =IF(C46="","",SUMIF('2-Calcul des Salaires'!D5:D104,C46,'2-Calcul des Salaires'!J5:J104)) | G46: =IF(C46="","",SUMIF('2-Calcul des Salaires'!D5:D104,C46,'2-Calcul des Salaires'!N5:N104)) | H46: =IF(C46="","",SUMIF('2-Calcul des Salaires'!D5:D104,C46,'2-Calcul des Salaires'!N5:N104)) | I46: =IF(C46="","",SUMIF('2-Calcul des Salaires'!D5:D104,C46,'2-Calcul des Salaires'!O5:O104)) | J46: =IF(C46="","",SUMIF('2-Calcul des Salaires'!D5:D104,C46,'2-Calcul des Salaires'!Q5:Q104)) | L46: =IF(OR(E46="",K46=""),"",IFERROR(E46/K46,0))
B47: =IF(C47="","HIS"&TEXT(COUNTA($C$5:C47),"000")) | E47: =IF(C47="","",COUNTIF('2-Calcul des Salaires'!D5:D104,C47)) | F47: =IF(C47="","",SUMIF('2-Calcul des Salaires'!D5:D104,C47,'2-Calcul des Salaires'!J5:J104)) | G47: =IF(C47="","",SUMIF('2-Calcul des Salaires'!D5:D104,C47,'2-Calcul des Salaires'!N5:N104)) | H47: =IF(C47="","",SUMIF('2-Calcul des Salaires'!D5:D104,C47,'2-Calcul des Salaires'!N5:N104)) | I47: =IF(C47="","",SUMIF('2-Calcul des Salaires'!D5:D104,C47,'2-Calcul des Salaires'!O5:O104)) | J47: =IF(C47="","",SUMIF('2-Calcul des Salaires'!D5:D104,C47,'2-Calcul des Salaires'!Q5:Q104)) | L47: =IF(OR(E47="",K47=""),"",IFERROR(E47/K47,0))
B48: =IF(C48="","HIS"&TEXT(COUNTA($C$5:C48),"000")) | E48: =IF(C48="","",COUNTIF('2-Calcul des Salaires'!D5:D104,C48)) | F48: =IF(C48="","",SUMIF('2-Calcul des Salaires'!D5:D104,C48,'2-Calcul des Salaires'!J5:J104)) | G48: =IF(C48="","",SUMIF('2-Calcul des Salaires'!D5:D104,C48,'2-Calcul des Salaires'!N5:N104)) | H48: =IF(C48="","",SUMIF('2-Calcul des Salaires'!D5:D104,C48,'2-Calcul des Salaires'!N5:N104)) | I48: =IF(C48="","",SUMIF('2-Calcul des Salaires'!D5:D104,C48,'2-Calcul des Salaires'!O5:O104)) | J48: =IF(C48="","",SUMIF('2-Calcul des Salaires'!D5:D104,C48,'2-Calcul des Salaires'!Q5:Q104)) | L48: =IF(OR(E48="",K48=""),"",IFERROR(E48/K48,0))
B49: =IF(C49="","HIS"&TEXT(COUNTA($C$5:C49),"000")) | E49: =IF(C49="","",COUNTIF('2-Calcul des Salaires'!D5:D104,C49)) | F49: =IF(C49="","",SUMIF('2-Calcul des Salaires'!D5:D104,C49,'2-Calcul des Salaires'!J5:J104)) | G49: =IF(C49="","",SUMIF('2-Calcul des Salaires'!D5:D104,C49,'2-Calcul des Salaires'!N5:N104)) | H49: =IF(C49="","",SUMIF('2-Calcul des Salaires'!D5:D104,C49,'2-Calcul des Salaires'!N5:N104)) | I49: =IF(C49="","",SUMIF('2-Calcul des Salaires'!D5:D104,C49,'2-Calcul des Salaires'!O5:O104)) | J49: =IF(C49="","",SUMIF('2-Calcul des Salaires'!D5:D104,C49,'2-Calcul des Salaires'!Q5:Q104)) | L49: =IF(OR(E49="",K49=""),"",IFERROR(E49/K49,0))
B50: =IF(C50="","HIS"&TEXT(COUNTA($C$5:C50),"000")) | E50: =IF(C50="","",COUNTIF('2-Calcul des Salaires'!D5:D104,C50)) | F50: =IF(C50="","",SUMIF('2-Calcul des Salaires'!D5:D104,C50,'2-Calcul des Salaires'!J5:J104)) | G50: =IF(C50="","",SUMIF('2-Calcul des Salaires'!D5:D104,C50,'2-Calcul des Salaires'!N5:N104)) | H50: =IF(C50="","",SUMIF('2-Calcul des Salaires'!D5:D104,C50,'2-Calcul des Salaires'!N5:N104)) | I50: =IF(C50="","",SUMIF('2-Calcul des Salaires'!D5:D104,C50,'2-Calcul des Salaires'!O5:O104)) | J50: =IF(C50="","",SUMIF('2-Calcul des Salaires'!D5:D104,C50,'2-Calcul des Salaires'!Q5:Q104)) | L50: =IF(OR(E50="",K50=""),"",IFERROR(E50/K50,0))
B51: =IF(C51="","HIS"&TEXT(COUNTA($C$5:C51),"000")) | E51: =IF(C51="","",COUNTIF('2-Calcul des Salaires'!D5:D104,C51)) | F51: =IF(C51="","",SUMIF('2-Calcul des Salaires'!D5:D104,C51,'2-Calcul des Salaires'!J5:J104)) | G51: =IF(C51="","",SUMIF('2-Calcul des Salaires'!D5:D104,C51,'2-Calcul des Salaires'!N5:N104)) | H51: =IF(C51="","",SUMIF('2-Calcul des Salaires'!D5:D104,C51,'2-Calcul des Salaires'!N5:N104)) | I51: =IF(C51="","",SUMIF('2-Calcul des Salaires'!D5:D104,C51,'2-Calcul des Salaires'!O5:O104)) | J51: =IF(C51="","",SUMIF('2-Calcul des Salaires'!D5:D104,C51,'2-Calcul des Salaires'!Q5:Q104)) | L51: =IF(OR(E51="",K51=""),"",IFERROR(E51/K51,0))
B52: =IF(C52="","HIS"&TEXT(COUNTA($C$5:C52),"000")) | E52: =IF(C52="","",COUNTIF('2-Calcul des Salaires'!D5:D104,C52)) | F52: =IF(C52="","",SUMIF('2-Calcul des Salaires'!D5:D104,C52,'2-Calcul des Salaires'!J5:J104)) | G52: =IF(C52="","",SUMIF('2-Calcul des Salaires'!D5:D104,C52,'2-Calcul des Salaires'!N5:N104)) | H52: =IF(C52="","",SUMIF('2-Calcul des Salaires'!D5:D104,C52,'2-Calcul des Salaires'!N5:N104)) | I52: =IF(C52="","",SUMIF('2-Calcul des Salaires'!D5:D104,C52,'2-Calcul des Salaires'!O5:O104)) | J52: =IF(C52="","",SUMIF('2-Calcul des Salaires'!D5:D104,C52,'2-Calcul des Salaires'!Q5:Q104)) | L52: =IF(OR(E52="",K52=""),"",IFERROR(E52/K52,0))
B53: =IF(C53="","HIS"&TEXT(COUNTA($C$5:C53),"000")) | E53: =IF(C53="","",COUNTIF('2-Calcul des Salaires'!D5:D104,C53)) | F53: =IF(C53="","",SUMIF('2-Calcul des Salaires'!D5:D104,C53,'2-Calcul des Salaires'!J5:J104)) | G53: =IF(C53="","",SUMIF('2-Calcul des Salaires'!D5:D104,C53,'2-Calcul des Salaires'!N5:N104)) | H53: =IF(C53="","",SUMIF('2-Calcul des Salaires'!D5:D104,C53,'2-Calcul des Salaires'!N5:N104)) | I53: =IF(C53="","",SUMIF('2-Calcul des Salaires'!D5:D104,C53,'2-Calcul des Salaires'!O5:O104)) | J53: =IF(C53="","",SUMIF('2-Calcul des Salaires'!D5:D104,C53,'2-Calcul des Salaires'!Q5:Q104)) | L53: =IF(OR(E53="",K53=""),"",IFERROR(E53/K53,0))
B54: =IF(C54="","HIS"&TEXT(COUNTA($C$5:C54),"000")) | E54: =IF(C54="","",COUNTIF('2-Calcul des Salaires'!D5:D104,C54)) | F54: =IF(C54="","",SUMIF('2-Calcul des Salaires'!D5:D104,C54,'2-Calcul des Salaires'!J5:J104)) | G54: =IF(C54="","",SUMIF('2-Calcul des Salaires'!D5:D104,C54,'2-Calcul des Salaires'!N5:N104)) | H54: =IF(C54="","",SUMIF('2-Calcul des Salaires'!D5:D104,C54,'2-Calcul des Salaires'!N5:N104)) | I54: =IF(C54="","",SUMIF('2-Calcul des Salaires'!D5:D104,C54,'2-Calcul des Salaires'!O5:O104)) | J54: =IF(C54="","",SUMIF('2-Calcul des Salaires'!D5:D104,C54,'2-Calcul des Salaires'!Q5:Q104)) | L54: =IF(OR(E54="",K54=""),"",IFERROR(E54/K54,0))
B55: =IF(C55="","HIS"&TEXT(COUNTA($C$5:C55),"000")) | E55: =IF(C55="","",COUNTIF('2-Calcul des Salaires'!D5:D104,C55)) | F55: =IF(C55="","",SUMIF('2-Calcul des Salaires'!D5:D104,C55,'2-Calcul des Salaires'!J5:J104)) | G55: =IF(C55="","",SUMIF('2-Calcul des Salaires'!D5:D104,C55,'2-Calcul des Salaires'!N5:N104)) | H55: =IF(C55="","",SUMIF('2-Calcul des Salaires'!D5:D104,C55,'2-Calcul des Salaires'!N5:N104)) | I55: =IF(C55="","",SUMIF('2-Calcul des Salaires'!D5:D104,C55,'2-Calcul des Salaires'!O5:O104)) | J55: =IF(C55="","",SUMIF('2-Calcul des Salaires'!D5:D104,C55,'2-Calcul des Salaires'!Q5:Q104)) | L55: =IF(OR(E55="",K55=""),"",IFERROR(E55/K55,0))
B56: =IF(C56="","HIS"&TEXT(COUNTA($C$5:C56),"000")) | E56: =IF(C56="","",COUNTIF('2-Calcul des Salaires'!D5:D104,C56)) | F56: =IF(C56="","",SUMIF('2-Calcul des Salaires'!D5:D104,C56,'2-Calcul des Salaires'!J5:J104)) | G56: =IF(C56="","",SUMIF('2-Calcul des Salaires'!D5:D104,C56,'2-Calcul des Salaires'!N5:N104)) | H56: =IF(C56="","",SUMIF('2-Calcul des Salaires'!D5:D104,C56,'2-Calcul des Salaires'!N5:N104)) | I56: =IF(C56="","",SUMIF('2-Calcul des Salaires'!D5:D104,C56,'2-Calcul des Salaires'!O5:O104)) | J56: =IF(C56="","",SUMIF('2-Calcul des Salaires'!D5:D104,C56,'2-Calcul des Salaires'!Q5:Q104)) | L56: =IF(OR(E56="",K56=""),"",IFERROR(E56/K56,0))
B57: =IF(C57="","HIS"&TEXT(COUNTA($C$5:C57),"000")) | E57: =IF(C57="","",COUNTIF('2-Calcul des Salaires'!D5:D104,C57)) | F57: =IF(C57="","",SUMIF('2-Calcul des Salaires'!D5:D104,C57,'2-Calcul des Salaires'!J5:J104)) | G57: =IF(C57="","",SUMIF('2-Calcul des Salaires'!D5:D104,C57,'2-Calcul des Salaires'!N5:N104)) | H57: =IF(C57="","",SUMIF('2-Calcul des Salaires'!D5:D104,C57,'2-Calcul des Salaires'!N5:N104)) | I57: =IF(C57="","",SUMIF('2-Calcul des Salaires'!D5:D104,C57,'2-Calcul des Salaires'!O5:O104)) | J57: =IF(C57="","",SUMIF('2-Calcul des Salaires'!D5:D104,C57,'2-Calcul des Salaires'!Q5:Q104)) | L57: =IF(OR(E57="",K57=""),"",IFERROR(E57/K57,0))
B58: =IF(C58="","HIS"&TEXT(COUNTA($C$5:C58),"000")) | E58: =IF(C58="","",COUNTIF('2-Calcul des Salaires'!D5:D104,C58)) | F58: =IF(C58="","",SUMIF('2-Calcul des Salaires'!D5:D104,C58,'2-Calcul des Salaires'!J5:J104)) | G58: =IF(C58="","",SUMIF('2-Calcul des Salaires'!D5:D104,C58,'2-Calcul des Salaires'!N5:N104)) | H58: =IF(C58="","",SUMIF('2-Calcul des Salaires'!D5:D104,C58,'2-Calcul des Salaires'!N5:N104)) | I58: =IF(C58="","",SUMIF('2-Calcul des Salaires'!D5:D104,C58,'2-Calcul des Salaires'!O5:O104)) | J58: =IF(C58="","",SUMIF('2-Calcul des Salaires'!D5:D104,C58,'2-Calcul des Salaires'!Q5:Q104)) | L58: =IF(OR(E58="",K58=""),"",IFERROR(E58/K58,0))
B59: =IF(C59="","HIS"&TEXT(COUNTA($C$5:C59),"000")) | E59: =IF(C59="","",COUNTIF('2-Calcul des Salaires'!D5:D104,C59)) | F59: =IF(C59="","",SUMIF('2-Calcul des Salaires'!D5:D104,C59,'2-Calcul des Salaires'!J5:J104)) | G59: =IF(C59="","",SUMIF('2-Calcul des Salaires'!D5:D104,C59,'2-Calcul des Salaires'!N5:N104)) | H59: =IF(C59="","",SUMIF('2-Calcul des Salaires'!D5:D104,C59,'2-Calcul des Salaires'!N5:N104)) | I59: =IF(C59="","",SUMIF('2-Calcul des Salaires'!D5:D104,C59,'2-Calcul des Salaires'!O5:O104)) | J59: =IF(C59="","",SUMIF('2-Calcul des Salaires'!D5:D104,C59,'2-Calcul des Salaires'!Q5:Q104)) | L59: =IF(OR(E59="",K59=""),"",IFERROR(E59/K59,0))
B60: =IF(C60="","HIS"&TEXT(COUNTA($C$5:C60),"000")) | E60: =IF(C60="","",COUNTIF('2-Calcul des Salaires'!D5:D104,C60)) | F60: =IF(C60="","",SUMIF('2-Calcul des Salaires'!D5:D104,C60,'2-Calcul des Salaires'!J5:J104)) | G60: =IF(C60="","",SUMIF('2-Calcul des Salaires'!D5:D104,C60,'2-Calcul des Salaires'!N5:N104)) | H60: =IF(C60="","",SUMIF('2-Calcul des Salaires'!D5:D104,C60,'2-Calcul des Salaires'!N5:N104)) | I60: =IF(C60="","",SUMIF('2-Calcul des Salaires'!D5:D104,C60,'2-Calcul des Salaires'!O5:O104)) | J60: =IF(C60="","",SUMIF('2-Calcul des Salaires'!D5:D104,C60,'2-Calcul des Salaires'!Q5:Q104)) | L60: =IF(OR(E60="",K60=""),"",IFERROR(E60/K60,0))
B61: =IF(C61="","HIS"&TEXT(COUNTA($C$5:C61),"000")) | E61: =IF(C61="","",COUNTIF('2-Calcul des Salaires'!D5:D104,C61)) | F61: =IF(C61="","",SUMIF('2-Calcul des Salaires'!D5:D104,C61,'2-Calcul des Salaires'!J5:J104)) | G61: =IF(C61="","",SUMIF('2-Calcul des Salaires'!D5:D104,C61,'2-Calcul des Salaires'!N5:N104)) | H61: =IF(C61="","",SUMIF('2-Calcul des Salaires'!D5:D104,C61,'2-Calcul des Salaires'!N5:N104)) | I61: =IF(C61="","",SUMIF('2-Calcul des Salaires'!D5:D104,C61,'2-Calcul des Salaires'!O5:O104)) | J61: =IF(C61="","",SUMIF('2-Calcul des Salaires'!D5:D104,C61,'2-Calcul des Salaires'!Q5:Q104)) | L61: =IF(OR(E61="",K61=""),"",IFERROR(E61/K61,0))
B62: =IF(C62="","HIS"&TEXT(COUNTA($C$5:C62),"000")) | E62: =IF(C62="","",COUNTIF('2-Calcul des Salaires'!D5:D104,C62)) | F62: =IF(C62="","",SUMIF('2-Calcul des Salaires'!D5:D104,C62,'2-Calcul des Salaires'!J5:J104)) | G62: =IF(C62="","",SUMIF('2-Calcul des Salaires'!D5:D104,C62,'2-Calcul des Salaires'!N5:N104)) | H62: =IF(C62="","",SUMIF('2-Calcul des Salaires'!D5:D104,C62,'2-Calcul des Salaires'!N5:N104)) | I62: =IF(C62="","",SUMIF('2-Calcul des Salaires'!D5:D104,C62,'2-Calcul des Salaires'!O5:O104)) | J62: =IF(C62="","",SUMIF('2-Calcul des Salaires'!D5:D104,C62,'2-Calcul des Salaires'!Q5:Q104)) | L62: =IF(OR(E62="",K62=""),"",IFERROR(E62/K62,0))
B63: =IF(C63="","HIS"&TEXT(COUNTA($C$5:C63),"000")) | E63: =IF(C63="","",COUNTIF('2-Calcul des Salaires'!D5:D104,C63)) | F63: =IF(C63="","",SUMIF('2-Calcul des Salaires'!D5:D104,C63,'2-Calcul des Salaires'!J5:J104)) | G63: =IF(C63="","",SUMIF('2-Calcul des Salaires'!D5:D104,C63,'2-Calcul des Salaires'!N5:N104)) | H63: =IF(C63="","",SUMIF('2-Calcul des Salaires'!D5:D104,C63,'2-Calcul des Salaires'!N5:N104)) | I63: =IF(C63="","",SUMIF('2-Calcul des Salaires'!D5:D104,C63,'2-Calcul des Salaires'!O5:O104)) | J63: =IF(C63="","",SUMIF('2-Calcul des Salaires'!D5:D104,C63,'2-Calcul des Salaires'!Q5:Q104)) | L63: =IF(OR(E63="",K63=""),"",IFERROR(E63/K63,0))
B64: =IF(C64="","HIS"&TEXT(COUNTA($C$5:C64),"000")) | E64: =IF(C64="","",COUNTIF('2-Calcul des Salaires'!D5:D104,C64)) | F64: =IF(C64="","",SUMIF('2-Calcul des Salaires'!D5:D104,C64,'2-Calcul des Salaires'!J5:J104)) | G64: =IF(C64="","",SUMIF('2-Calcul des Salaires'!D5:D104,C64,'2-Calcul des Salaires'!N5:N104)) | H64: =IF(C64="","",SUMIF('2-Calcul des Salaires'!D5:D104,C64,'2-Calcul des Salaires'!N5:N104)) | I64: =IF(C64="","",SUMIF('2-Calcul des Salaires'!D5:D104,C64,'2-Calcul des Salaires'!O5:O104)) | J64: =IF(C64="","",SUMIF('2-Calcul des Salaires'!D5:D104,C64,'2-Calcul des Salaires'!Q5:Q104)) | L64: =IF(OR(E64="",K64=""),"",IFERROR(E64/K64,0))
B65: =IF(C65="","HIS"&TEXT(COUNTA($C$5:C65),"000")) | E65: =IF(C65="","",COUNTIF('2-Calcul des Salaires'!D5:D104,C65)) | F65: =IF(C65="","",SUMIF('2-Calcul des Salaires'!D5:D104,C65,'2-Calcul des Salaires'!J5:J104)) | G65: =IF(C65="","",SUMIF('2-Calcul des Salaires'!D5:D104,C65,'2-Calcul des Salaires'!N5:N104)) | H65: =IF(C65="","",SUMIF('2-Calcul des Salaires'!D5:D104,C65,'2-Calcul des Salaires'!N5:N104)) | I65: =IF(C65="","",SUMIF('2-Calcul des Salaires'!D5:D104,C65,'2-Calcul des Salaires'!O5:O104)) | J65: =IF(C65="","",SUMIF('2-Calcul des Salaires'!D5:D104,C65,'2-Calcul des Salaires'!Q5:Q104)) | L65: =IF(OR(E65="",K65=""),"",IFERROR(E65/K65,0))
B66: =IF(C66="","HIS"&TEXT(COUNTA($C$5:C66),"000")) | E66: =IF(C66="","",COUNTIF('2-Calcul des Salaires'!D5:D104,C66)) | F66: =IF(C66="","",SUMIF('2-Calcul des Salaires'!D5:D104,C66,'2-Calcul des Salaires'!J5:J104)) | G66: =IF(C66="","",SUMIF('2-Calcul des Salaires'!D5:D104,C66,'2-Calcul des Salaires'!N5:N104)) | H66: =IF(C66="","",SUMIF('2-Calcul des Salaires'!D5:D104,C66,'2-Calcul des Salaires'!N5:N104)) | I66: =IF(C66="","",SUMIF('2-Calcul des Salaires'!D5:D104,C66,'2-Calcul des Salaires'!O5:O104)) | J66: =IF(C66="","",SUMIF('2-Calcul des Salaires'!D5:D104,C66,'2-Calcul des Salaires'!Q5:Q104)) | L66: =IF(OR(E66="",K66=""),"",IFERROR(E66/K66,0))
B67: =IF(C67="","HIS"&TEXT(COUNTA($C$5:C67),"000")) | E67: =IF(C67="","",COUNTIF('2-Calcul des Salaires'!D5:D104,C67)) | F67: =IF(C67="","",SUMIF('2-Calcul des Salaires'!D5:D104,C67,'2-Calcul des Salaires'!J5:J104)) | G67: =IF(C67="","",SUMIF('2-Calcul des Salaires'!D5:D104,C67,'2-Calcul des Salaires'!N5:N104)) | H67: =IF(C67="","",SUMIF('2-Calcul des Salaires'!D5:D104,C67,'2-Calcul des Salaires'!N5:N104)) | I67: =IF(C67="","",SUMIF('2-Calcul des Salaires'!D5:D104,C67,'2-Calcul des Salaires'!O5:O104)) | J67: =IF(C67="","",SUMIF('2-Calcul des Salaires'!D5:D104,C67,'2-Calcul des Salaires'!Q5:Q104)) | L67: =IF(OR(E67="",K67=""),"",IFERROR(E67/K67,0))
B68: =IF(C68="","HIS"&TEXT(COUNTA($C$5:C68),"000")) | E68: =IF(C68="","",COUNTIF('2-Calcul des Salaires'!D5:D104,C68)) | F68: =IF(C68="","",SUMIF('2-Calcul des Salaires'!D5:D104,C68,'2-Calcul des Salaires'!J5:J104)) | G68: =IF(C68="","",SUMIF('2-Calcul des Salaires'!D5:D104,C68,'2-Calcul des Salaires'!N5:N104)) | H68: =IF(C68="","",SUMIF('2-Calcul des Salaires'!D5:D104,C68,'2-Calcul des Salaires'!N5:N104)) | I68: =IF(C68="","",SUMIF('2-Calcul des Salaires'!D5:D104,C68,'2-Calcul des Salaires'!O5:O104)) | J68: =IF(C68="","",SUMIF('2-Calcul des Salaires'!D5:D104,C68,'2-Calcul des Salaires'!Q5:Q104)) | L68: =IF(OR(E68="",K68=""),"",IFERROR(E68/K68,0))
B69: =IF(C69="","HIS"&TEXT(COUNTA($C$5:C69),"000")) | E69: =IF(C69="","",COUNTIF('2-Calcul des Salaires'!D5:D104,C69)) | F69: =IF(C69="","",SUMIF('2-Calcul des Salaires'!D5:D104,C69,'2-Calcul des Salaires'!J5:J104)) | G69: =IF(C69="","",SUMIF('2-Calcul des Salaires'!D5:D104,C69,'2-Calcul des Salaires'!N5:N104)) | H69: =IF(C69="","",SUMIF('2-Calcul des Salaires'!D5:D104,C69,'2-Calcul des Salaires'!N5:N104)) | I69: =IF(C69="","",SUMIF('2-Calcul des Salaires'!D5:D104,C69,'2-Calcul des Salaires'!O5:O104)) | J69: =IF(C69="","",SUMIF('2-Calcul des Salaires'!D5:D104,C69,'2-Calcul des Salaires'!Q5:Q104)) | L69: =IF(OR(E69="",K69=""),"",IFERROR(E69/K69,0))
B70: =IF(C70="","HIS"&TEXT(COUNTA($C$5:C70),"000")) | E70: =IF(C70="","",COUNTIF('2-Calcul des Salaires'!D5:D104,C70)) | F70: =IF(C70="","",SUMIF('2-Calcul des Salaires'!D5:D104,C70,'2-Calcul des Salaires'!J5:J104)) | G70: =IF(C70="","",SUMIF('2-Calcul des Salaires'!D5:D104,C70,'2-Calcul des Salaires'!N5:N104)) | H70: =IF(C70="","",SUMIF('2-Calcul des Salaires'!D5:D104,C70,'2-Calcul des Salaires'!N5:N104)) | I70: =IF(C70="","",SUMIF('2-Calcul des Salaires'!D5:D104,C70,'2-Calcul des Salaires'!O5:O104)) | J70: =IF(C70="","",SUMIF('2-Calcul des Salaires'!D5:D104,C70,'2-Calcul des Salaires'!Q5:Q104)) | L70: =IF(OR(E70="",K70=""),"",IFERROR(E70/K70,0))
B71: =IF(C71="","HIS"&TEXT(COUNTA($C$5:C71),"000")) | E71: =IF(C71="","",COUNTIF('2-Calcul des Salaires'!D5:D104,C71)) | F71: =IF(C71="","",SUMIF('2-Calcul des Salaires'!D5:D104,C71,'2-Calcul des Salaires'!J5:J104)) | G71: =IF(C71="","",SUMIF('2-Calcul des Salaires'!D5:D104,C71,'2-Calcul des Salaires'!N5:N104)) | H71: =IF(C71="","",SUMIF('2-Calcul des Salaires'!D5:D104,C71,'2-Calcul des Salaires'!N5:N104)) | I71: =IF(C71="","",SUMIF('2-Calcul des Salaires'!D5:D104,C71,'2-Calcul des Salaires'!O5:O104)) | J71: =IF(C71="","",SUMIF('2-Calcul des Salaires'!D5:D104,C71,'2-Calcul des Salaires'!Q5:Q104)) | L71: =IF(OR(E71="",K71=""),"",IFERROR(E71/K71,0))
B72: =IF(C72="","HIS"&TEXT(COUNTA($C$5:C72),"000")) | E72: =IF(C72="","",COUNTIF('2-Calcul des Salaires'!D5:D104,C72)) | F72: =IF(C72="","",SUMIF('2-Calcul des Salaires'!D5:D104,C72,'2-Calcul des Salaires'!J5:J104)) | G72: =IF(C72="","",SUMIF('2-Calcul des Salaires'!D5:D104,C72,'2-Calcul des Salaires'!N5:N104)) | H72: =IF(C72="","",SUMIF('2-Calcul des Salaires'!D5:D104,C72,'2-Calcul des Salaires'!N5:N104)) | I72: =IF(C72="","",SUMIF('2-Calcul des Salaires'!D5:D104,C72,'2-Calcul des Salaires'!O5:O104)) | J72: =IF(C72="","",SUMIF('2-Calcul des Salaires'!D5:D104,C72,'2-Calcul des Salaires'!Q5:Q104)) | L72: =IF(OR(E72="",K72=""),"",IFERROR(E72/K72,0))
B73: =IF(C73="","HIS"&TEXT(COUNTA($C$5:C73),"000")) | E73: =IF(C73="","",COUNTIF('2-Calcul des Salaires'!D5:D104,C73)) | F73: =IF(C73="","",SUMIF('2-Calcul des Salaires'!D5:D104,C73,'2-Calcul des Salaires'!J5:J104)) | G73: =IF(C73="","",SUMIF('2-Calcul des Salaires'!D5:D104,C73,'2-Calcul des Salaires'!N5:N104)) | H73: =IF(C73="","",SUMIF('2-Calcul des Salaires'!D5:D104,C73,'2-Calcul des Salaires'!N5:N104)) | I73: =IF(C73="","",SUMIF('2-Calcul des Salaires'!D5:D104,C73,'2-Calcul des Salaires'!O5:O104)) | J73: =IF(C73="","",SUMIF('2-Calcul des Salaires'!D5:D104,C73,'2-Calcul des Salaires'!Q5:Q104)) | L73: =IF(OR(E73="",K73=""),"",IFERROR(E73/K73,0))
B74: =IF(C74="","HIS"&TEXT(COUNTA($C$5:C74),"000")) | E74: =IF(C74="","",COUNTIF('2-Calcul des Salaires'!D5:D104,C74)) | F74: =IF(C74="","",SUMIF('2-Calcul des Salaires'!D5:D104,C74,'2-Calcul des Salaires'!J5:J104)) | G74: =IF(C74="","",SUMIF('2-Calcul des Salaires'!D5:D104,C74,'2-Calcul des Salaires'!N5:N104)) | H74: =IF(C74="","",SUMIF('2-Calcul des Salaires'!D5:D104,C74,'2-Calcul des Salaires'!N5:N104)) | I74: =IF(C74="","",SUMIF('2-Calcul des Salaires'!D5:D104,C74,'2-Calcul des Salaires'!O5:O104)) | J74: =IF(C74="","",SUMIF('2-Calcul des Salaires'!D5:D104,C74,'2-Calcul des Salaires'!Q5:Q104)) | L74: =IF(OR(E74="",K74=""),"",IFERROR(E74/K74,0))
B75: =IF(C75="","HIS"&TEXT(COUNTA($C$5:C75),"000")) | E75: =IF(C75="","",COUNTIF('2-Calcul des Salaires'!D5:D104,C75)) | F75: =IF(C75="","",SUMIF('2-Calcul des Salaires'!D5:D104,C75,'2-Calcul des Salaires'!J5:J104)) | G75: =IF(C75="","",SUMIF('2-Calcul des Salaires'!D5:D104,C75,'2-Calcul des Salaires'!N5:N104)) | H75: =IF(C75="","",SUMIF('2-Calcul des Salaires'!D5:D104,C75,'2-Calcul des Salaires'!N5:N104)) | I75: =IF(C75="","",SUMIF('2-Calcul des Salaires'!D5:D104,C75,'2-Calcul des Salaires'!O5:O104)) | J75: =IF(C75="","",SUMIF('2-Calcul des Salaires'!D5:D104,C75,'2-Calcul des Salaires'!Q5:Q104)) | L75: =IF(OR(E75="",K75=""),"",IFERROR(E75/K75,0))
B76: =IF(C76="","HIS"&TEXT(COUNTA($C$5:C76),"000")) | E76: =IF(C76="","",COUNTIF('2-Calcul des Salaires'!D5:D104,C76)) | F76: =IF(C76="","",SUMIF('2-Calcul des Salaires'!D5:D104,C76,'2-Calcul des Salaires'!J5:J104)) | G76: =IF(C76="","",SUMIF('2-Calcul des Salaires'!D5:D104,C76,'2-Calcul des Salaires'!N5:N104)) | H76: =IF(C76="","",SUMIF('2-Calcul des Salaires'!D5:D104,C76,'2-Calcul des Salaires'!N5:N104)) | I76: =IF(C76="","",SUMIF('2-Calcul des Salaires'!D5:D104,C76,'2-Calcul des Salaires'!O5:O104)) | J76: =IF(C76="","",SUMIF('2-Calcul des Salaires'!D5:D104,C76,'2-Calcul des Salaires'!Q5:Q104)) | L76: =IF(OR(E76="",K76=""),"",IFERROR(E76/K76,0))
B77: =IF(C77="","HIS"&TEXT(COUNTA($C$5:C77),"000")) | E77: =IF(C77="","",COUNTIF('2-Calcul des Salaires'!D5:D104,C77)) | F77: =IF(C77="","",SUMIF('2-Calcul des Salaires'!D5:D104,C77,'2-Calcul des Salaires'!J5:J104)) | G77: =IF(C77="","",SUMIF('2-Calcul des Salaires'!D5:D104,C77,'2-Calcul des Salaires'!N5:N104)) | H77: =IF(C77="","",SUMIF('2-Calcul des Salaires'!D5:D104,C77,'2-Calcul des Salaires'!N5:N104)) | I77: =IF(C77="","",SUMIF('2-Calcul des Salaires'!D5:D104,C77,'2-Calcul des Salaires'!O5:O104)) | J77: =IF(C77="","",SUMIF('2-Calcul des Salaires'!D5:D104,C77,'2-Calcul des Salaires'!Q5:Q104)) | L77: =IF(OR(E77="",K77=""),"",IFERROR(E77/K77,0))
B78: =IF(C78="","HIS"&TEXT(COUNTA($C$5:C78),"000")) | E78: =IF(C78="","",COUNTIF('2-Calcul des Salaires'!D5:D104,C78)) | F78: =IF(C78="","",SUMIF('2-Calcul des Salaires'!D5:D104,C78,'2-Calcul des Salaires'!J5:J104)) | G78: =IF(C78="","",SUMIF('2-Calcul des Salaires'!D5:D104,C78,'2-Calcul des Salaires'!N5:N104)) | H78: =IF(C78="","",SUMIF('2-Calcul des Salaires'!D5:D104,C78,'2-Calcul des Salaires'!N5:N104)) | I78: =IF(C78="","",SUMIF('2-Calcul des Salaires'!D5:D104,C78,'2-Calcul des Salaires'!O5:O104)) | J78: =IF(C78="","",SUMIF('2-Calcul des Salaires'!D5:D104,C78,'2-Calcul des Salaires'!Q5:Q104)) | L78: =IF(OR(E78="",K78=""),"",IFERROR(E78/K78,0))
B79: =IF(C79="","HIS"&TEXT(COUNTA($C$5:C79),"000")) | E79: =IF(C79="","",COUNTIF('2-Calcul des Salaires'!D5:D104,C79)) | F79: =IF(C79="","",SUMIF('2-Calcul des Salaires'!D5:D104,C79,'2-Calcul des Salaires'!J5:J104)) | G79: =IF(C79="","",SUMIF('2-Calcul des Salaires'!D5:D104,C79,'2-Calcul des Salaires'!N5:N104)) | H79: =IF(C79="","",SUMIF('2-Calcul des Salaires'!D5:D104,C79,'2-Calcul des Salaires'!N5:N104)) | I79: =IF(C79="","",SUMIF('2-Calcul des Salaires'!D5:D104,C79,'2-Calcul des Salaires'!O5:O104)) | J79: =IF(C79="","",SUMIF('2-Calcul des Salaires'!D5:D104,C79,'2-Calcul des Salaires'!Q5:Q104)) | L79: =IF(OR(E79="",K79=""),"",IFERROR(E79/K79,0))
B80: =IF(C80="","HIS"&TEXT(COUNTA($C$5:C80),"000")) | E80: =IF(C80="","",COUNTIF('2-Calcul des Salaires'!D5:D104,C80)) | F80: =IF(C80="","",SUMIF('2-Calcul des Salaires'!D5:D104,C80,'2-Calcul des Salaires'!J5:J104)) | G80: =IF(C80="","",SUMIF('2-Calcul des Salaires'!D5:D104,C80,'2-Calcul des Salaires'!N5:N104)) | H80: =IF(C80="","",SUMIF('2-Calcul des Salaires'!D5:D104,C80,'2-Calcul des Salaires'!N5:N104)) | I80: =IF(C80="","",SUMIF('2-Calcul des Salaires'!D5:D104,C80,'2-Calcul des Salaires'!O5:O104)) | J80: =IF(C80="","",SUMIF('2-Calcul des Salaires'!D5:D104,C80,'2-Calcul des Salaires'!Q5:Q104)) | L80: =IF(OR(E80="",K80=""),"",IFERROR(E80/K80,0))
B81: =IF(C81="","HIS"&TEXT(COUNTA($C$5:C81),"000")) | E81: =IF(C81="","",COUNTIF('2-Calcul des Salaires'!D5:D104,C81)) | F81: =IF(C81="","",SUMIF('2-Calcul des Salaires'!D5:D104,C81,'2-Calcul des Salaires'!J5:J104)) | G81: =IF(C81="","",SUMIF('2-Calcul des Salaires'!D5:D104,C81,'2-Calcul des Salaires'!N5:N104)) | H81: =IF(C81="","",SUMIF('2-Calcul des Salaires'!D5:D104,C81,'2-Calcul des Salaires'!N5:N104)) | I81: =IF(C81="","",SUMIF('2-Calcul des Salaires'!D5:D104,C81,'2-Calcul des Salaires'!O5:O104)) | J81: =IF(C81="","",SUMIF('2-Calcul des Salaires'!D5:D104,C81,'2-Calcul des Salaires'!Q5:Q104)) | L81: =IF(OR(E81="",K81=""),"",IFERROR(E81/K81,0))
B82: =IF(C82="","HIS"&TEXT(COUNTA($C$5:C82),"000")) | E82: =IF(C82="","",COUNTIF('2-Calcul des Salaires'!D5:D104,C82)) | F82: =IF(C82="","",SUMIF('2-Calcul des Salaires'!D5:D104,C82,'2-Calcul des Salaires'!J5:J104)) | G82: =IF(C82="","",SUMIF('2-Calcul des Salaires'!D5:D104,C82,'2-Calcul des Salaires'!N5:N104)) | H82: =IF(C82="","",SUMIF('2-Calcul des Salaires'!D5:D104,C82,'2-Calcul des Salaires'!N5:N104)) | I82: =IF(C82="","",SUMIF('2-Calcul des Salaires'!D5:D104,C82,'2-Calcul des Salaires'!O5:O104)) | J82: =IF(C82="","",SUMIF('2-Calcul des Salaires'!D5:D104,C82,'2-Calcul des Salaires'!Q5:Q104)) | L82: =IF(OR(E82="",K82=""),"",IFERROR(E82/K82,0))
B83: =IF(C83="","HIS"&TEXT(COUNTA($C$5:C83),"000")) | E83: =IF(C83="","",COUNTIF('2-Calcul des Salaires'!D5:D104,C83)) | F83: =IF(C83="","",SUMIF('2-Calcul des Salaires'!D5:D104,C83,'2-Calcul des Salaires'!J5:J104)) | G83: =IF(C83="","",SUMIF('2-Calcul des Salaires'!D5:D104,C83,'2-Calcul des Salaires'!N5:N104)) | H83: =IF(C83="","",SUMIF('2-Calcul des Salaires'!D5:D104,C83,'2-Calcul des Salaires'!N5:N104)) | I83: =IF(C83="","",SUMIF('2-Calcul des Salaires'!D5:D104,C83,'2-Calcul des Salaires'!O5:O104)) | J83: =IF(C83="","",SUMIF('2-Calcul des Salaires'!D5:D104,C83,'2-Calcul des Salaires'!Q5:Q104)) | L83: =IF(OR(E83="",K83=""),"",IFERROR(E83/K83,0))
B84: =IF(C84="","HIS"&TEXT(COUNTA($C$5:C84),"000")) | E84: =IF(C84="","",COUNTIF('2-Calcul des Salaires'!D5:D104,C84)) | F84: =IF(C84="","",SUMIF('2-Calcul des Salaires'!D5:D104,C84,'2-Calcul des Salaires'!J5:J104)) | G84: =IF(C84="","",SUMIF('2-Calcul des Salaires'!D5:D104,C84,'2-Calcul des Salaires'!N5:N104)) | H84: =IF(C84="","",SUMIF('2-Calcul des Salaires'!D5:D104,C84,'2-Calcul des Salaires'!N5:N104)) | I84: =IF(C84="","",SUMIF('2-Calcul des Salaires'!D5:D104,C84,'2-Calcul des Salaires'!O5:O104)) | J84: =IF(C84="","",SUMIF('2-Calcul des Salaires'!D5:D104,C84,'2-Calcul des Salaires'!Q5:Q104)) | L84: =IF(OR(E84="",K84=""),"",IFERROR(E84/K84,0))
B85: =IF(C85="","HIS"&TEXT(COUNTA($C$5:C85),"000")) | E85: =IF(C85="","",COUNTIF('2-Calcul des Salaires'!D5:D104,C85)) | F85: =IF(C85="","",SUMIF('2-Calcul des Salaires'!D5:D104,C85,'2-Calcul des Salaires'!J5:J104)) | G85: =IF(C85="","",SUMIF('2-Calcul des Salaires'!D5:D104,C85,'2-Calcul des Salaires'!N5:N104)) | H85: =IF(C85="","",SUMIF('2-Calcul des Salaires'!D5:D104,C85,'2-Calcul des Salaires'!N5:N104)) | I85: =IF(C85="","",SUMIF('2-Calcul des Salaires'!D5:D104,C85,'2-Calcul des Salaires'!O5:O104)) | J85: =IF(C85="","",SUMIF('2-Calcul des Salaires'!D5:D104,C85,'2-Calcul des Salaires'!Q5:Q104)) | L85: =IF(OR(E85="",K85=""),"",IFERROR(E85/K85,0))
B86: =IF(C86="","HIS"&TEXT(COUNTA($C$5:C86),"000")) | E86: =IF(C86="","",COUNTIF('2-Calcul des Salaires'!D5:D104,C86)) | F86: =IF(C86="","",SUMIF('2-Calcul des Salaires'!D5:D104,C86,'2-Calcul des Salaires'!J5:J104)) | G86: =IF(C86="","",SUMIF('2-Calcul des Salaires'!D5:D104,C86,'2-Calcul des Salaires'!N5:N104)) | H86: =IF(C86="","",SUMIF('2-Calcul des Salaires'!D5:D104,C86,'2-Calcul des Salaires'!N5:N104)) | I86: =IF(C86="","",SUMIF('2-Calcul des Salaires'!D5:D104,C86,'2-Calcul des Salaires'!O5:O104)) | J86: =IF(C86="","",SUMIF('2-Calcul des Salaires'!D5:D104,C86,'2-Calcul des Salaires'!Q5:Q104)) | L86: =IF(OR(E86="",K86=""),"",IFERROR(E86/K86,0))
B87: =IF(C87="","HIS"&TEXT(COUNTA($C$5:C87),"000")) | E87: =IF(C87="","",COUNTIF('2-Calcul des Salaires'!D5:D104,C87)) | F87: =IF(C87="","",SUMIF('2-Calcul des Salaires'!D5:D104,C87,'2-Calcul des Salaires'!J5:J104)) | G87: =IF(C87="","",SUMIF('2-Calcul des Salaires'!D5:D104,C87,'2-Calcul des Salaires'!N5:N104)) | H87: =IF(C87="","",SUMIF('2-Calcul des Salaires'!D5:D104,C87,'2-Calcul des Salaires'!N5:N104)) | I87: =IF(C87="","",SUMIF('2-Calcul des Salaires'!D5:D104,C87,'2-Calcul des Salaires'!O5:O104)) | J87: =IF(C87="","",SUMIF('2-Calcul des Salaires'!D5:D104,C87,'2-Calcul des Salaires'!Q5:Q104)) | L87: =IF(OR(E87="",K87=""),"",IFERROR(E87/K87,0))
B88: =IF(C88="","HIS"&TEXT(COUNTA($C$5:C88),"000")) | E88: =IF(C88="","",COUNTIF('2-Calcul des Salaires'!D5:D104,C88)) | F88: =IF(C88="","",SUMIF('2-Calcul des Salaires'!D5:D104,C88,'2-Calcul des Salaires'!J5:J104)) | G88: =IF(C88="","",SUMIF('2-Calcul des Salaires'!D5:D104,C88,'2-Calcul des Salaires'!N5:N104)) | H88: =IF(C88="","",SUMIF('2-Calcul des Salaires'!D5:D104,C88,'2-Calcul des Salaires'!N5:N104)) | I88: =IF(C88="","",SUMIF('2-Calcul des Salaires'!D5:D104,C88,'2-Calcul des Salaires'!O5:O104)) | J88: =IF(C88="","",SUMIF('2-Calcul des Salaires'!D5:D104,C88,'2-Calcul des Salaires'!Q5:Q104)) | L88: =IF(OR(E88="",K88=""),"",IFERROR(E88/K88,0))
B89: =IF(C89="","HIS"&TEXT(COUNTA($C$5:C89),"000")) | E89: =IF(C89="","",COUNTIF('2-Calcul des Salaires'!D5:D104,C89)) | F89: =IF(C89="","",SUMIF('2-Calcul des Salaires'!D5:D104,C89,'2-Calcul des Salaires'!J5:J104)) | G89: =IF(C89="","",SUMIF('2-Calcul des Salaires'!D5:D104,C89,'2-Calcul des Salaires'!N5:N104)) | H89: =IF(C89="","",SUMIF('2-Calcul des Salaires'!D5:D104,C89,'2-Calcul des Salaires'!N5:N104)) | I89: =IF(C89="","",SUMIF('2-Calcul des Salaires'!D5:D104,C89,'2-Calcul des Salaires'!O5:O104)) | J89: =IF(C89="","",SUMIF('2-Calcul des Salaires'!D5:D104,C89,'2-Calcul des Salaires'!Q5:Q104)) | L89: =IF(OR(E89="",K89=""),"",IFERROR(E89/K89,0))
B90: =IF(C90="","HIS"&TEXT(COUNTA($C$5:C90),"000")) | E90: =IF(C90="","",COUNTIF('2-Calcul des Salaires'!D5:D104,C90)) | F90: =IF(C90="","",SUMIF('2-Calcul des Salaires'!D5:D104,C90,'2-Calcul des Salaires'!J5:J104)) | G90: =IF(C90="","",SUMIF('2-Calcul des Salaires'!D5:D104,C90,'2-Calcul des Salaires'!N5:N104)) | H90: =IF(C90="","",SUMIF('2-Calcul des Salaires'!D5:D104,C90,'2-Calcul des Salaires'!N5:N104)) | I90: =IF(C90="","",SUMIF('2-Calcul des Salaires'!D5:D104,C90,'2-Calcul des Salaires'!O5:O104)) | J90: =IF(C90="","",SUMIF('2-Calcul des Salaires'!D5:D104,C90,'2-Calcul des Salaires'!Q5:Q104)) | L90: =IF(OR(E90="",K90=""),"",IFERROR(E90/K90,0))
B91: =IF(C91="","HIS"&TEXT(COUNTA($C$5:C91),"000")) | E91: =IF(C91="","",COUNTIF('2-Calcul des Salaires'!D5:D104,C91)) | F91: =IF(C91="","",SUMIF('2-Calcul des Salaires'!D5:D104,C91,'2-Calcul des Salaires'!J5:J104)) | G91: =IF(C91="","",SUMIF('2-Calcul des Salaires'!D5:D104,C91,'2-Calcul des Salaires'!N5:N104)) | H91: =IF(C91="","",SUMIF('2-Calcul des Salaires'!D5:D104,C91,'2-Calcul des Salaires'!N5:N104)) | I91: =IF(C91="","",SUMIF('2-Calcul des Salaires'!D5:D104,C91,'2-Calcul des Salaires'!O5:O104)) | J91: =IF(C91="","",SUMIF('2-Calcul des Salaires'!D5:D104,C91,'2-Calcul des Salaires'!Q5:Q104)) | L91: =IF(OR(E91="",K91=""),"",IFERROR(E91/K91,0))
B92: =IF(C92="","HIS"&TEXT(COUNTA($C$5:C92),"000")) | E92: =IF(C92="","",COUNTIF('2-Calcul des Salaires'!D5:D104,C92)) | F92: =IF(C92="","",SUMIF('2-Calcul des Salaires'!D5:D104,C92,'2-Calcul des Salaires'!J5:J104)) | G92: =IF(C92="","",SUMIF('2-Calcul des Salaires'!D5:D104,C92,'2-Calcul des Salaires'!N5:N104)) | H92: =IF(C92="","",SUMIF('2-Calcul des Salaires'!D5:D104,C92,'2-Calcul des Salaires'!N5:N104)) | I92: =IF(C92="","",SUMIF('2-Calcul des Salaires'!D5:D104,C92,'2-Calcul des Salaires'!O5:O104)) | J92: =IF(C92="","",SUMIF('2-Calcul des Salaires'!D5:D104,C92,'2-Calcul des Salaires'!Q5:Q104)) | L92: =IF(OR(E92="",K92=""),"",IFERROR(E92/K92,0))
B93: =IF(C93="","HIS"&TEXT(COUNTA($C$5:C93),"000")) | E93: =IF(C93="","",COUNTIF('2-Calcul des Salaires'!D5:D104,C93)) | F93: =IF(C93="","",SUMIF('2-Calcul des Salaires'!D5:D104,C93,'2-Calcul des Salaires'!J5:J104)) | G93: =IF(C93="","",SUMIF('2-Calcul des Salaires'!D5:D104,C93,'2-Calcul des Salaires'!N5:N104)) | H93: =IF(C93="","",SUMIF('2-Calcul des Salaires'!D5:D104,C93,'2-Calcul des Salaires'!N5:N104)) | I93: =IF(C93="","",SUMIF('2-Calcul des Salaires'!D5:D104,C93,'2-Calcul des Salaires'!O5:O104)) | J93: =IF(C93="","",SUMIF('2-Calcul des Salaires'!D5:D104,C93,'2-Calcul des Salaires'!Q5:Q104)) | L93: =IF(OR(E93="",K93=""),"",IFERROR(E93/K93,0))
B94: =IF(C94="","HIS"&TEXT(COUNTA($C$5:C94),"000")) | E94: =IF(C94="","",COUNTIF('2-Calcul des Salaires'!D5:D104,C94)) | F94: =IF(C94="","",SUMIF('2-Calcul des Salaires'!D5:D104,C94,'2-Calcul des Salaires'!J5:J104)) | G94: =IF(C94="","",SUMIF('2-Calcul des Salaires'!D5:D104,C94,'2-Calcul des Salaires'!N5:N104)) | H94: =IF(C94="","",SUMIF('2-Calcul des Salaires'!D5:D104,C94,'2-Calcul des Salaires'!N5:N104)) | I94: =IF(C94="","",SUMIF('2-Calcul des Salaires'!D5:D104,C94,'2-Calcul des Salaires'!O5:O104)) | J94: =IF(C94="","",SUMIF('2-Calcul des Salaires'!D5:D104,C94,'2-Calcul des Salaires'!Q5:Q104)) | L94: =IF(OR(E94="",K94=""),"",IFERROR(E94/K94,0))
B95: =IF(C95="","HIS"&TEXT(COUNTA($C$5:C95),"000")) | E95: =IF(C95="","",COUNTIF('2-Calcul des Salaires'!D5:D104,C95)) | F95: =IF(C95="","",SUMIF('2-Calcul des Salaires'!D5:D104,C95,'2-Calcul des Salaires'!J5:J104)) | G95: =IF(C95="","",SUMIF('2-Calcul des Salaires'!D5:D104,C95,'2-Calcul des Salaires'!N5:N104)) | H95: =IF(C95="","",SUMIF('2-Calcul des Salaires'!D5:D104,C95,'2-Calcul des Salaires'!N5:N104)) | I95: =IF(C95="","",SUMIF('2-Calcul des Salaires'!D5:D104,C95,'2-Calcul des Salaires'!O5:O104)) | J95: =IF(C95="","",SUMIF('2-Calcul des Salaires'!D5:D104,C95,'2-Calcul des Salaires'!Q5:Q104)) | L95: =IF(OR(E95="",K95=""),"",IFERROR(E95/K95,0))
B96: =IF(C96="","HIS"&TEXT(COUNTA($C$5:C96),"000")) | E96: =IF(C96="","",COUNTIF('2-Calcul des Salaires'!D5:D104,C96)) | F96: =IF(C96="","",SUMIF('2-Calcul des Salaires'!D5:D104,C96,'2-Calcul des Salaires'!J5:J104)) | G96: =IF(C96="","",SUMIF('2-Calcul des Salaires'!D5:D104,C96,'2-Calcul des Salaires'!N5:N104)) | H96: =IF(C96="","",SUMIF('2-Calcul des Salaires'!D5:D104,C96,'2-Calcul des Salaires'!N5:N104)) | I96: =IF(C96="","",SUMIF('2-Calcul des Salaires'!D5:D104,C96,'2-Calcul des Salaires'!O5:O104)) | J96: =IF(C96="","",SUMIF('2-Calcul des Salaires'!D5:D104,C96,'2-Calcul des Salaires'!Q5:Q104)) | L96: =IF(OR(E96="",K96=""),"",IFERROR(E96/K96,0))
B97: =IF(C97="","HIS"&TEXT(COUNTA($C$5:C97),"000")) | E97: =IF(C97="","",COUNTIF('2-Calcul des Salaires'!D5:D104,C97)) | F97: =IF(C97="","",SUMIF('2-Calcul des Salaires'!D5:D104,C97,'2-Calcul des Salaires'!J5:J104)) | G97: =IF(C97="","",SUMIF('2-Calcul des Salaires'!D5:D104,C97,'2-Calcul des Salaires'!N5:N104)) | H97: =IF(C97="","",SUMIF('2-Calcul des Salaires'!D5:D104,C97,'2-Calcul des Salaires'!N5:N104)) | I97: =IF(C97="","",SUMIF('2-Calcul des Salaires'!D5:D104,C97,'2-Calcul des Salaires'!O5:O104)) | J97: =IF(C97="","",SUMIF('2-Calcul des Salaires'!D5:D104,C97,'2-Calcul des Salaires'!Q5:Q104)) | L97: =IF(OR(E97="",K97=""),"",IFERROR(E97/K97,0))
B98: =IF(C98="","HIS"&TEXT(COUNTA($C$5:C98),"000")) | E98: =IF(C98="","",COUNTIF('2-Calcul des Salaires'!D5:D104,C98)) | F98: =IF(C98="","",SUMIF('2-Calcul des Salaires'!D5:D104,C98,'2-Calcul des Salaires'!J5:J104)) | G98: =IF(C98="","",SUMIF('2-Calcul des Salaires'!D5:D104,C98,'2-Calcul des Salaires'!N5:N104)) | H98: =IF(C98="","",SUMIF('2-Calcul des Salaires'!D5:D104,C98,'2-Calcul des Salaires'!N5:N104)) | I98: =IF(C98="","",SUMIF('2-Calcul des Salaires'!D5:D104,C98,'2-Calcul des Salaires'!O5:O104)) | J98: =IF(C98="","",SUMIF('2-Calcul des Salaires'!D5:D104,C98,'2-Calcul des Salaires'!Q5:Q104)) | L98: =IF(OR(E98="",K98=""),"",IFERROR(E98/K98,0))
B99: =IF(C99="","HIS"&TEXT(COUNTA($C$5:C99),"000")) | E99: =IF(C99="","",COUNTIF('2-Calcul des Salaires'!D5:D104,C99)) | F99: =IF(C99="","",SUMIF('2-Calcul des Salaires'!D5:D104,C99,'2-Calcul des Salaires'!J5:J104)) | G99: =IF(C99="","",SUMIF('2-Calcul des Salaires'!D5:D104,C99,'2-Calcul des Salaires'!N5:N104)) | H99: =IF(C99="","",SUMIF('2-Calcul des Salaires'!D5:D104,C99,'2-Calcul des Salaires'!N5:N104)) | I99: =IF(C99="","",SUMIF('2-Calcul des Salaires'!D5:D104,C99,'2-Calcul des Salaires'!O5:O104)) | J99: =IF(C99="","",SUMIF('2-Calcul des Salaires'!D5:D104,C99,'2-Calcul des Salaires'!Q5:Q104)) | L99: =IF(OR(E99="",K99=""),"",IFERROR(E99/K99,0))
B100: =IF(C100="","HIS"&TEXT(COUNTA($C$5:C100),"000")) | E100: =IF(C100="","",COUNTIF('2-Calcul des Salaires'!D5:D104,C100)) | F100: =IF(C100="","",SUMIF('2-Calcul des Salaires'!D5:D104,C100,'2-Calcul des Salaires'!J5:J104)) | G100: =IF(C100="","",SUMIF('2-Calcul des Salaires'!D5:D104,C100,'2-Calcul des Salaires'!N5:N104)) | H100: =IF(C100="","",SUMIF('2-Calcul des Salaires'!D5:D104,C100,'2-Calcul des Salaires'!N5:N104)) | I100: =IF(C100="","",SUMIF('2-Calcul des Salaires'!D5:D104,C100,'2-Calcul des Salaires'!O5:O104)) | J100: =IF(C100="","",SUMIF('2-Calcul des Salaires'!D5:D104,C100,'2-Calcul des Salaires'!Q5:Q104)) | L100: =IF(OR(E100="",K100=""),"",IFERROR(E100/K100,0))
B101: =IF(C101="","HIS"&TEXT(COUNTA($C$5:C101),"000")) | E101: =IF(C101="","",COUNTIF('2-Calcul des Salaires'!D5:D104,C101)) | F101: =IF(C101="","",SUMIF('2-Calcul des Salaires'!D5:D104,C101,'2-Calcul des Salaires'!J5:J104)) | G101: =IF(C101="","",SUMIF('2-Calcul des Salaires'!D5:D104,C101,'2-Calcul des Salaires'!N5:N104)) | H101: =IF(C101="","",SUMIF('2-Calcul des Salaires'!D5:D104,C101,'2-Calcul des Salaires'!N5:N104)) | I101: =IF(C101="","",SUMIF('2-Calcul des Salaires'!D5:D104,C101,'2-Calcul des Salaires'!O5:O104)) | J101: =IF(C101="","",SUMIF('2-Calcul des Salaires'!D5:D104,C101,'2-Calcul des Salaires'!Q5:Q104)) | L101: =IF(OR(E101="",K101=""),"",IFERROR(E101/K101,0))
B102: =IF(C102="","HIS"&TEXT(COUNTA($C$5:C102),"000")) | E102: =IF(C102="","",COUNTIF('2-Calcul des Salaires'!D5:D104,C102)) | F102: =IF(C102="","",SUMIF('2-Calcul des Salaires'!D5:D104,C102,'2-Calcul des Salaires'!J5:J104)) | G102: =IF(C102="","",SUMIF('2-Calcul des Salaires'!D5:D104,C102,'2-Calcul des Salaires'!N5:N104)) | H102: =IF(C102="","",SUMIF('2-Calcul des Salaires'!D5:D104,C102,'2-Calcul des Salaires'!N5:N104)) | I102: =IF(C102="","",SUMIF('2-Calcul des Salaires'!D5:D104,C102,'2-Calcul des Salaires'!O5:O104)) | J102: =IF(C102="","",SUMIF('2-Calcul des Salaires'!D5:D104,C102,'2-Calcul des Salaires'!Q5:Q104)) | L102: =IF(OR(E102="",K102=""),"",IFERROR(E102/K102,0))
...

Sheet 10-Evolutions Salariales
B2: REMUNERATION — 10-Evolutions Salariales
B4: N° | C4: Matricule | D4: Nom Employé | E4: Poste | F4: Type Évolution | G4: Date Effet | H4: Ancien Salaire (FCFA) | I4: Nouveau Salaire (FCFA) | J4: Augmentation (FCFA) | K4: Taux Augmentation | L4: Motif | M4: Statut
B5: EVO-001 | C5: EMP-002 | D5: Tchinda Armand | E5: Chef Comptable | F5: Promotion | G5: 2025-07-01 | H5: 484000 | I5: 550000 | J5: 66000 | L5: Excellence | M5: Approuve
B6: EVO-002 | C6: EMP-004 | D6: Ouedraogo Ibrahim | E6: Receptionniste | F6: Augmentation | G6: 2025-07-01 | H6: 207000 | I6: 225000 | J6: 18000 | L6: Mérite | M6: En attente
B7: =IF(C7="","EVO"&TEXT(COUNTA($C$5:C7),"000")) | D7: =IF(C7="","",VLOOKUP(C7,'_Données Employés'!$B$5:$S$114,3,FALSE)) | E7: =IF(C7="","",VLOOKUP(C7,'_Données Employés'!$B$5:$S$114,9,FALSE)) | J7: =IF(OR(G7="",H7=""),"",IFERROR(H7-G7,0)) | K7: =IF(G7="","",IFERROR(I7/G7,0))
B8: =IF(C8="","EVO"&TEXT(COUNTA($C$5:C8),"000")) | D8: =IF(C8="","",VLOOKUP(C8,'_Données Employés'!$B$5:$S$114,3,FALSE)) | E8: =IF(C8="","",VLOOKUP(C8,'_Données Employés'!$B$5:$S$114,9,FALSE)) | J8: =IF(OR(G8="",H8=""),"",IFERROR(H8-G8,0)) | K8: =IF(G8="","",IFERROR(I8/G8,0))
B9: =IF(C9="","EVO"&TEXT(COUNTA($C$5:C9),"000")) | D9: =IF(C9="","",VLOOKUP(C9,'_Données Employés'!$B$5:$S$114,3,FALSE)) | E9: =IF(C9="","",VLOOKUP(C9,'_Données Employés'!$B$5:$S$114,9,FALSE)) | J9: =IF(OR(G9="",H9=""),"",IFERROR(H9-G9,0)) | K9: =IF(G9="","",IFERROR(I9/G9,0))
B10: =IF(C10="","EVO"&TEXT(COUNTA($C$5:C10),"000")) | D10: =IF(C10="","",VLOOKUP(C10,'_Données Employés'!$B$5:$S$114,3,FALSE)) | E10: =IF(C10="","",VLOOKUP(C10,'_Données Employés'!$B$5:$S$114,9,FALSE)) | J10: =IF(OR(G10="",H10=""),"",IFERROR(H10-G10,0)) | K10: =IF(G10="","",IFERROR(I10/G10,0))
B11: =IF(C11="","EVO"&TEXT(COUNTA($C$5:C11),"000")) | D11: =IF(C11="","",VLOOKUP(C11,'_Données Employés'!$B$5:$S$114,3,FALSE)) | E11: =IF(C11="","",VLOOKUP(C11,'_Données Employés'!$B$5:$S$114,9,FALSE)) | J11: =IF(OR(G11="",H11=""),"",IFERROR(H11-G11,0)) | K11: =IF(G11="","",IFERROR(I11/G11,0))
B12: =IF(C12="","EVO"&TEXT(COUNTA($C$5:C12),"000")) | D12: =IF(C12="","",VLOOKUP(C12,'_Données Employés'!$B$5:$S$114,3,FALSE)) | E12: =IF(C12="","",VLOOKUP(C12,'_Données Employés'!$B$5:$S$114,9,FALSE)) | J12: =IF(OR(G12="",H12=""),"",IFERROR(H12-G12,0)) | K12: =IF(G12="","",IFERROR(I12/G12,0))
B13: =IF(C13="","EVO"&TEXT(COUNTA($C$5:C13),"000")) | D13: =IF(C13="","",VLOOKUP(C13,'_Données Employés'!$B$5:$S$114,3,FALSE)) | E13: =IF(C13="","",VLOOKUP(C13,'_Données Employés'!$B$5:$S$114,9,FALSE)) | J13: =IF(OR(G13="",H13=""),"",IFERROR(H13-G13,0)) | K13: =IF(G13="","",IFERROR(I13/G13,0))
B14: =IF(C14="","EVO"&TEXT(COUNTA($C$5:C14),"000")) | D14: =IF(C14="","",VLOOKUP(C14,'_Données Employés'!$B$5:$S$114,3,FALSE)) | E14: =IF(C14="","",VLOOKUP(C14,'_Données Employés'!$B$5:$S$114,9,FALSE)) | J14: =IF(OR(G14="",H14=""),"",IFERROR(H14-G14,0)) | K14: =IF(G14="","",IFERROR(I14/G14,0))
B15: =IF(C15="","EVO"&TEXT(COUNTA($C$5:C15),"000")) | D15: =IF(C15="","",VLOOKUP(C15,'_Données Employés'!$B$5:$S$114,3,FALSE)) | E15: =IF(C15="","",VLOOKUP(C15,'_Données Employés'!$B$5:$S$114,9,FALSE)) | J15: =IF(OR(G15="",H15=""),"",IFERROR(H15-G15,0)) | K15: =IF(G15="","",IFERROR(I15/G15,0))
B16: =IF(C16="","EVO"&TEXT(COUNTA($C$5:C16),"000")) | D16: =IF(C16="","",VLOOKUP(C16,'_Données Employés'!$B$5:$S$114,3,FALSE)) | E16: =IF(C16="","",VLOOKUP(C16,'_Données Employés'!$B$5:$S$114,9,FALSE)) | J16: =IF(OR(G16="",H16=""),"",IFERROR(H16-G16,0)) | K16: =IF(G16="","",IFERROR(I16/G16,0))
B17: =IF(C17="","EVO"&TEXT(COUNTA($C$5:C17),"000")) | D17: =IF(C17="","",VLOOKUP(C17,'_Données Employés'!$B$5:$S$114,3,FALSE)) | E17: =IF(C17="","",VLOOKUP(C17,'_Données Employés'!$B$5:$S$114,9,FALSE)) | J17: =IF(OR(G17="",H17=""),"",IFERROR(H17-G17,0)) | K17: =IF(G17="","",IFERROR(I17/G17,0))
B18: =IF(C18="","EVO"&TEXT(COUNTA($C$5:C18),"000")) | D18: =IF(C18="","",VLOOKUP(C18,'_Données Employés'!$B$5:$S$114,3,FALSE)) | E18: =IF(C18="","",VLOOKUP(C18,'_Données Employés'!$B$5:$S$114,9,FALSE)) | J18: =IF(OR(G18="",H18=""),"",IFERROR(H18-G18,0)) | K18: =IF(G18="","",IFERROR(I18/G18,0))
... B104: =IF(C104="","EVO"&TEXT(COUNTA($C$5:C104),"000")) | D104: =IF(C104="","",VLOOKUP(C104,'_Données Employés'!$B$5:$S$114,3,FALSE)) | E104: =IF(C104="","",VLOOKUP(C104,'_Données Employés'!$B$5:$S$114,9,FALSE)) | J104: =IF(OR(G104="",H104=""),"",IFERROR(H104-G104,0)) | K104: =IF(G104="","",IFERROR(I104/G104,0))
B107: KPI Total augmentations (FCFA) | C107: KPI Évolutions approuvées
B108: =SUM(I5:I104) | C108: =COUNTIF(M5:M104,"Approuve")

Sheet 11-Cout Salarie
B2: REMUNERATION — 11-Cout Salarie
B4: N° | C4: Matricule | D4: Nom Employé | E4: Département | F4: Salaire Brut Mensuel (FCFA) | G4: Charges Patronales (FCFA) | H4: Avantages Nature (FCFA) | I4: Coût Total Employeur/mois (FCFA) | J4: Coût Annuel (FCFA) | K4: Ratio Coût/Brut (%)
B5: COUT-001 | C5: EMP-001 | D5: Nganou Clarisse | E5: Ressources Humaines | F5: 850750 | G5: 69762 | H5: 65000 | I5: 985512 | J5: 11826144
B6: COUT-002 | C6: EMP-002 | D6: Tchinda Armand | E6: Finance & Comptabilite | F6: 648100 | G6: 53144 | H6: 50000 | I6: 751244 | J6: 9014928
B7: COUT-003 | C7: EMP-003 | D7: Fotso Marguerite | E7: Finance & Comptabilite | F7: 383125 | G7: 31416 | H7: 0 | I7: 414541 | J7: 4974492
B8: =IF(C8="","COUT"&TEXT(COUNTA($C$5:C8),"000")) | D8: =IF(C8="","",VLOOKUP(C8,'_Données Employés'!$B$5:$S$114,3,FALSE)) | E8: =IF(C8="","",VLOOKUP(C8,'_Données Employés'!$B$5:$S$114,10,FALSE)) | I8: =IF(F8="","",IFERROR(F8+G8+H8,0)) | J8: =IF(I8="","",IFERROR(I8*12,0)) | K8: =IF(F8="","",IFERROR(I8/F8,0))
B9: =IF(C9="","COUT"&TEXT(COUNTA($C$5:C9),"000")) | D9: =IF(C9="","",VLOOKUP(C9,'_Données Employés'!$B$5:$S$114,3,FALSE)) | E9: =IF(C9="","",VLOOKUP(C9,'_Données Employés'!$B$5:$S$114,10,FALSE)) | I9: =IF(F9="","",IFERROR(F9+G9+H9,0)) | J9: =IF(I9="","",IFERROR(I9*12,0)) | K9: =IF(F9="","",IFERROR(I9/F9,0))
B10: =IF(C10="","COUT"&TEXT(COUNTA($C$5:C10),"000")) | D10: =IF(C10="","",VLOOKUP(C10,'_Données Employés'!$B$5:$S$114,3,FALSE)) | E10: =IF(C10="","",VLOOKUP(C10,'_Données Employés'!$B$5:$S$114,10,FALSE)) | I10: =IF(F10="","",IFERROR(F10+G10+H10,0)) | J10: =IF(I10="","",IFERROR(I10*12,0)) | K10: =IF(F10="","",IFERROR(I10/F10,0))
B11: =IF(C11="","COUT"&TEXT(COUNTA($C$5:C11),"000")) | D11: =IF(C11="","",VLOOKUP(C11,'_Données Employés'!$B$5:$S$114,3,FALSE)) | E11: =IF(C11="","",VLOOKUP(C11,'_Données Employés'!$B$5:$S$114,10,FALSE)) | I11: =IF(F11="","",IFERROR(F11+G11+H11,0)) | J11: =IF(I11="","",IFERROR(I11*12,0)) | K11: =IF(F11="","",IFERROR(I11/F11,0))
B12: =IF(C12="","COUT"&TEXT(COUNTA($C$5:C12),"000")) | D12: =IF(C12="","",VLOOKUP(C12,'_Données Employés'!$B$5:$S$114,3,FALSE)) | E12: =IF(C12="","",VLOOKUP(C12,'_Données Employés'!$B$5:$S$114,10,FALSE)) | I12: =IF(F12="","",IFERROR(F12+G12+H12,0)) | J12: =IF(I12="","",IFERROR(I12*12,0)) | K12: =IF(F12="","",IFERROR(I12/F12,0))
B13: =IF(C13="","COUT"&TEXT(COUNTA($C$5:C13),"000")) | D13: =IF(C13="","",VLOOKUP(C13,'_Données Employés'!$B$5:$S$114,3,FALSE)) | E13: =IF(C13="","",VLOOKUP(C13,'_Données Employés'!$B$5:$S$114,10,FALSE)) | I13: =IF(F13="","",IFERROR(F13+G13+H13,0)) | J13: =IF(I13="","",IFERROR(I13*12,0)) | K13: =IF(F13="","",IFERROR(I13/F13,0))
B14: =IF(C14="","COUT"&TEXT(COUNTA($C$5:C14),"000")) | D14: =IF(C14="","",VLOOKUP(C14,'_Données Employés'!$B$5:$S$114,3,FALSE)) | E14: =IF(C14="","",VLOOKUP(C14,'_Données Employés'!$B$5:$S$114,10,FALSE)) | I14: =IF(F14="","",IFERROR(F14+G14+H14,0)) | J14: =IF(I14="","",IFERROR(I14*12,0)) | K14: =IF(F14="","",IFERROR(I14/F14,0))
B15: =IF(C15="","COUT"&TEXT(COUNTA($C$5:C15),"000")) | D15: =IF(C15="","",VLOOKUP(C15,'_Données Employés'!$B$5:$S$114,3,FALSE)) | E15: =IF(C15="","",VLOOKUP(C15,'_Données Employés'!$B$5:$S$114,10,FALSE)) | I15: =IF(F15="","",IFERROR(F15+G15+H15,0)) | J15: =IF(I15="","",IFERROR(I15*12,0)) | K15: =IF(F15="","",IFERROR(I15/F15,0))
B16: =IF(C16="","COUT"&TEXT(COUNTA($C$5:C16),"000")) | D16: =IF(C16="","",VLOOKUP(C16,'_Données Employés'!$B$5:$S$114,3,FALSE)) | E16: =IF(C16="","",VLOOKUP(C16,'_Données Employés'!$B$5:$S$114,10,FALSE)) | I16: =IF(F16="","",IFERROR(F16+G16+H16,0)) | J16: =IF(I16="","",IFERROR(I16*12,0)) | K16: =IF(F16="","",IFERROR(I16/F16,0))
B17: =IF(C17="","COUT"&TEXT(COUNTA($C$5:C17),"000")) | D17: =IF(C17="","",VLOOKUP(C17,'_Données Employés'!$B$5:$S$114,3,FALSE)) | E17: =IF(C17="","",VLOOKUP(C17,'_Données Employés'!$B$5:$S$114,10,FALSE)) | I17: =IF(F17="","",IFERROR(F17+G17+H17,0)) | J17: =IF(I17="","",IFERROR(I17*12,0)) | K17: =IF(F17="","",IFERROR(I17/F17,0))
B18: =IF(C18="","COUT"&TEXT(COUNTA($C$5:C18),"000")) | D18: =IF(C18="","",VLOOKUP(C18,'_Données Employés'!$B$5:$S$114,3,FALSE)) | E18: =IF(C18="","",VLOOKUP(C18,'_Données Employés'!$B$5:$S$114,10,FALSE)) | I18: =IF(F18="","",IFERROR(F18+G18+H18,0)) | J18: =IF(I18="","",IFERROR(I18*12,0)) | K18: =IF(F18="","",IFERROR(I18/F18,0))
B19: =IF(C19="","COUT"&TEXT(COUNTA($C$5:C19),"000")) | D19: =IF(C19="","",VLOOKUP(C19,'_Données Employés'!$B$5:$S$114,3,FALSE)) | E19: =IF(C19="","",VLOOKUP(C19,'_Données Employés'!$B$5:$S$114,10,FALSE)) | I19: =IF(F19="","",IFERROR(F19+G19+H19,0)) | J19: =IF(I19="","",IFERROR(I19*12,0)) | K19: =IF(F19="","",IFERROR(I19/F19,0))
... B104: =IF(C104="","COUT"&TEXT(COUNTA($C$5:C104),"000")) | D104: =IF(C104="","",VLOOKUP(C104,'_Données Employés'!$B$5:$S$114,3,FALSE)) | E104: =IF(C104="","",VLOOKUP(C104,'_Données Employés'!$B$5:$S$114,10,FALSE)) | I104: =IF(F104="","",IFERROR(F104+G104+H104,0)) | J104: =IF(I104="","",IFERROR(I104*12,0)) | K104: =IF(F104="","",IFERROR(I104/F104,0))
B107: KPI Coût total annuel (FCFA) | C107: KPI Coût moyen/employé/mois (FCFA)
B108: =SUM(J5:J104) | C108: =IFERROR(AVERAGE(I5:I104),0)

Sheet 12-Masse Salariale
B2: REMUNERATION — 12-Masse Salariale
B4: N° | C4: Mois | D4: Année | E4: Effectif | F4: Masse Brute (FCFA) | G4: Masse Nette (FCFA) | H4: Charges Patronales (FCFA) | I4: Coût Total (FCFA) | J4: CA Hôtel (FCFA) | K4: Ratio Masse/CA | L4: Coût Moyen/Employé (FCFA)
B5: MS-001 | C5: Janvier | D5: 2025 | E5: =IF(C5="","",COUNTIF('2-Calcul des Salaires'!D5:D104,C5)) | F5: =IF(C5="","",SUMIF('2-Calcul des Salaires'!D5:D104,C5,'2-Calcul des Salaires'!J5:J104)) | G5: =IF(C5="","",SUMIF('2-Calcul des Salaires'!D5:D104,C5,'2-Calcul des Salaires'!O5:O104)) | H5: =IF(C5="","",SUMIF('2-Calcul des Salaires'!D5:D104,C5,'2-Calcul des Salaires'!Q5:Q104)-SUMIF('2-Calcul des Salaires'!D5:D104,C5,'2-Calcul des Salaires'!O5:O104)) | I5: =IF(C5="","",SUMIF('2-Calcul des Salaires'!D5:D104,C5,'2-Calcul des Salaires'!Q5:Q104)) | J5: 12000000 | L5: 448635
B6: MS-002 | C6: Fevrier | D6: 2025 | E6: =IF(C6="","",COUNTIF('2-Calcul des Salaires'!D5:D104,C6)) | F6: =IF(C6="","",SUMIF('2-Calcul des Salaires'!D5:D104,C6,'2-Calcul des Salaires'!J5:J104)) | G6: =IF(C6="","",SUMIF('2-Calcul des Salaires'!D5:D104,C6,'2-Calcul des Salaires'!O5:O104)) | H6: =IF(C6="","",SUMIF('2-Calcul des Salaires'!D5:D104,C6,'2-Calcul des Salaires'!Q5:Q104)-SUMIF('2-Calcul des Salaires'!D5:D104,C6,'2-Calcul des Salaires'!O5:O104)) | I6: =IF(C6="","",SUMIF('2-Calcul des Salaires'!D5:D104,C6,'2-Calcul des Salaires'!Q5:Q104)) | J6: 11500000 | L6: 448635
B7: MS-003 | C7: Mars | D7: 2025 | E7: =IF(C7="","",COUNTIF('2-Calcul des Salaires'!D5:D104,C7)) | F7: =IF(C7="","",SUMIF('2-Calcul des Salaires'!D5:D104,C7,'2-Calcul des Salaires'!J5:J104)) | G7: =IF(C7="","",SUMIF('2-Calcul des Salaires'!D5:D104,C7,'2-Calcul des Salaires'!O5:O104)) | H7: =IF(C7="","",SUMIF('2-Calcul des Salaires'!D5:D104,C7,'2-Calcul des Salaires'!Q5:Q104)-SUMIF('2-Calcul des Salaires'!D5:D104,C7,'2-Calcul des Salaires'!O5:O104)) | I7: =IF(C7="","",SUMIF('2-Calcul des Salaires'!D5:D104,C7,'2-Calcul des Salaires'!Q5:Q104)) | J7: 12500000 | L7: 452500
B8: =IF(C8="","MS"&TEXT(COUNTA($C$5:C8),"000")) | E8: =IF(C8="","",COUNTIF('2-Calcul des Salaires'!D5:D104,C8)) | F8: =IF(C8="","",SUMIF('2-Calcul des Salaires'!D5:D104,C8,'2-Calcul des Salaires'!J5:J104)) | G8: =IF(C8="","",SUMIF('2-Calcul des Salaires'!D5:D104,C8,'2-Calcul des Salaires'!O5:O104)) | H8: =IF(C8="","",SUMIF('2-Calcul des Salaires'!D5:D104,C8,'2-Calcul des Salaires'!Q5:Q104)-SUMIF('2-Calcul des Salaires'!D5:D104,C8,'2-Calcul des Salaires'!O5:O104)) | I8: =IF(C8="","",SUMIF('2-Calcul des Salaires'!D5:D104,C8,'2-Calcul des Salaires'!Q5:Q104)) | K8: =IF(OR(F8="",J8=""),"",IFERROR(F8/J8,0)) | L8: =IF(OR(E8="",I8=""),"",IFERROR(I8/E8,0))
B9: =IF(C9="","MS"&TEXT(COUNTA($C$5:C9),"000")) | E9: =IF(C9="","",COUNTIF('2-Calcul des Salaires'!D5:D104,C9)) | F9: =IF(C9="","",SUMIF('2-Calcul des Salaires'!D5:D104,C9,'2-Calcul des Salaires'!J5:J104)) | G9: =IF(C9="","",SUMIF('2-Calcul des Salaires'!D5:D104,C9,'2-Calcul des Salaires'!O5:O104)) | H9: =IF(C9="","",SUMIF('2-Calcul des Salaires'!D5:D104,C9,'2-Calcul des Salaires'!Q5:Q104)-SUMIF('2-Calcul des Salaires'!D5:D104,C9,'2-Calcul des Salaires'!O5:O104)) | I9: =IF(C9="","",SUMIF('2-Calcul des Salaires'!D5:D104,C9,'2-Calcul des Salaires'!Q5:Q104)) | K9: =IF(OR(F9="",J9=""),"",IFERROR(F9/J9,0)) | L9: =IF(OR(E9="",I9=""),"",IFERROR(I9/E9,0))
B10: =IF(C10="","MS"&TEXT(COUNTA($C$5:C10),"000")) | E10: =IF(C10="","",COUNTIF('2-Calcul des Salaires'!D5:D104,C10)) | F10: =IF(C10="","",SUMIF('2-Calcul des Salaires'!D5:D104,C10,'2-Calcul des Salaires'!J5:J104)) | G10: =IF(C10="","",SUMIF('2-Calcul des Salaires'!D5:D104,C10,'2-Calcul des Salaires'!O5:O104)) | H10: =IF(C10="","",SUMIF('2-Calcul des Salaires'!D5:D104,C10,'2-Calcul des Salaires'!Q5:Q104)-SUMIF('2-Calcul des Salaires'!D5:D104,C10,'2-Calcul des Salaires'!O5:O104)) | I10: =IF(C10="","",SUMIF('2-Calcul des Salaires'!D5:D104,C10,'2-Calcul des Salaires'!Q5:Q104)) | K10: =IF(OR(F10="",J10=""),"",IFERROR(F10/J10,0)) | L10: =IF(OR(E10="",I10=""),"",IFERROR(I10/E10,0))
B11: =IF(C11="","MS"&TEXT(COUNTA($C$5:C11),"000")) | E11: =IF(C11="","",COUNTIF('2-Calcul des Salaires'!D5:D104,C11)) | F11: =IF(C11="","",SUMIF('2-Calcul des Salaires'!D5:D104,C11,'2-Calcul des Salaires'!J5:J104)) | G11: =IF(C11="","",SUMIF('2-Calcul des Salaires'!D5:D104,C11,'2-Calcul des Salaires'!O5:O104)) | H11: =IF(C11="","",SUMIF('2-Calcul des Salaires'!D5:D104,C11,'2-Calcul des Salaires'!Q5:Q104)-SUMIF('2-Calcul des Salaires'!D5:D104,C11,'2-Calcul des Salaires'!O5:O104)) | I11: =IF(C11="","",SUMIF('2-Calcul des Salaires'!D5:D104,C11,'2-Calcul des Salaires'!Q5:Q104)) | K11: =IF(OR(F11="",J11=""),"",IFERROR(F11/J11,0)) | L11: =IF(OR(E11="",I11=""),"",IFERROR(I11/E11,0))
B12: =IF(C12="","MS"&TEXT(COUNTA($C$5:C12),"000")) | E12: =IF(C12="","",COUNTIF('2-Calcul des Salaires'!D5:D104,C12)) | F12: =IF(C12="","",SUMIF('2-Calcul des Salaires'!D5:D104,C12,'2-Calcul des Salaires'!J5:J104)) | G12: =IF(C12="","",SUMIF('2-Calcul des Salaires'!D5:D104,C12,'2-Calcul des Salaires'!O5:O104)) | H12: =IF(C12="","",SUMIF('2-Calcul des Salaires'!D5:D104,C12,'2-Calcul des Salaires'!Q5:Q104)-SUMIF('2-Calcul des Salaires'!D5:D104,C12,'2-Calcul des Salaires'!O5:O104)) | I12: =IF(C12="","",SUMIF('2-Calcul des Salaires'!D5:D104,C12,'2-Calcul des Salaires'!Q5:Q104)) | K12: =IF(OR(F12="",J12=""),"",IFERROR(F12/J12,0)) | L12: =IF(OR(E12="",I12=""),"",IFERROR(I12/E12,0))
B13: =IF(C13="","MS"&TEXT(COUNTA($C$5:C13),"000")) | E13: =IF(C13="","",COUNTIF('2-Calcul des Salaires'!D5:D104,C13)) | F13: =IF(C13="","",SUMIF('2-Calcul des Salaires'!D5:D104,C13,'2-Calcul des Salaires'!J5:J104)) | G13: =IF(C13="","",SUMIF('2-Calcul des Salaires'!D5:D104,C13,'2-Calcul des Salaires'!O5:O104)) | H13: =IF(C13="","",SUMIF('2-Calcul des Salaires'!D5:D104,C13,'2-Calcul des Salaires'!Q5:Q104)-SUMIF('2-Calcul des Salaires'!D5:D104,C13,'2-Calcul des Salaires'!O5:O104)) | I13: =IF(C13="","",SUMIF('2-Calcul des Salaires'!D5:D104,C13,'2-Calcul des Salaires'!Q5:Q104)) | K13: =IF(OR(F13="",J13=""),"",IFERROR(F13/J13,0)) | L13: =IF(OR(E13="",I13=""),"",IFERROR(I13/E13,0))
B14: =IF(C14="","MS"&TEXT(COUNTA($C$5:C14),"000")) | E14: =IF(C14="","",COUNTIF('2-Calcul des Salaires'!D5:D104,C14)) | F14: =IF(C14="","",SUMIF('2-Calcul des Salaires'!D5:D104,C14,'2-Calcul des Salaires'!J5:J104)) | G14: =IF(C14="","",SUMIF('2-Calcul des Salaires'!D5:D104,C14,'2-Calcul des Salaires'!O5:O104)) | H14: =IF(C14="","",SUMIF('2-Calcul des Salaires'!D5:D104,C14,'2-Calcul des Salaires'!Q5:Q104)-SUMIF('2-Calcul des Salaires'!D5:D104,C14,'2-Calcul des Salaires'!O5:O104)) | I14: =IF(C14="","",SUMIF('2-Calcul des Salaires'!D5:D104,C14,'2-Calcul des Salaires'!Q5:Q104)) | K14: =IF(OR(F14="",J14=""),"",IFERROR(F14/J14,0)) | L14: =IF(OR(E14="",I14=""),"",IFERROR(I14/E14,0))
B15: =IF(C15="","MS"&TEXT(COUNTA($C$5:C15),"000")) | E15: =IF(C15="","",COUNTIF('2-Calcul des Salaires'!D5:D104,C15)) | F15: =IF(C15="","",SUMIF('2-Calcul des Salaires'!D5:D104,C15,'2-Calcul des Salaires'!J5:J104)) | G15: =IF(C15="","",SUMIF('2-Calcul des Salaires'!D5:D104,C15,'2-Calcul des Salaires'!O5:O104)) | H15: =IF(C15="","",SUMIF('2-Calcul des Salaires'!D5:D104,C15,'2-Calcul des Salaires'!Q5:Q104)-SUMIF('2-Calcul des Salaires'!D5:D104,C15,'2-Calcul des Salaires'!O5:O104)) | I15: =IF(C15="","",SUMIF('2-Calcul des Salaires'!D5:D104,C15,'2-Calcul des Salaires'!Q5:Q104)) | K15: =IF(OR(F15="",J15=""),"",IFERROR(F15/J15,0)) | L15: =IF(OR(E15="",I15=""),"",IFERROR(I15/E15,0))
B16: =IF(C16="","MS"&TEXT(COUNTA($C$5:C16),"000")) | E16: =IF(C16="","",COUNTIF('2-Calcul des Salaires'!D5:D104,C16)) | F16: =IF(C16="","",SUMIF('2-Calcul des Salaires'!D5:D104,C16,'2-Calcul des Salaires'!J5:J104)) | G16: =IF(C16="","",SUMIF('2-Calcul des Salaires'!D5:D104,C16,'2-Calcul des Salaires'!O5:O104)) | H16: =IF(C16="","",SUMIF('2-Calcul des Salaires'!D5:D104,C16,'2-Calcul des Salaires'!Q5:Q104)-SUMIF('2-Calcul des Salaires'!D5:D104,C16,'2-Calcul des Salaires'!O5:O104)) | I16: =IF(C16="","",SUMIF('2-Calcul des Salaires'!D5:D104,C16,'2-Calcul des Salaires'!Q5:Q104)) | K16: =IF(OR(F16="",J16=""),"",IFERROR(F16/J16,0)) | L16: =IF(OR(E16="",I16=""),"",IFERROR(I16/E16,0))
B17: =IF(C17="","MS"&TEXT(COUNTA($C$5:C17),"000")) | E17: =IF(C17="","",COUNTIF('2-Calcul des Salaires'!D5:D104,C17)) | F17: =IF(C17="","",SUMIF('2-Calcul des Salaires'!D5:D104,C17,'2-Calcul des Salaires'!J5:J104)) | G17: =IF(C17="","",SUMIF('2-Calcul des Salaires'!D5:D104,C17,'2-Calcul des Salaires'!O5:O104)) | H17: =IF(C17="","",SUMIF('2-Calcul des Salaires'!D5:D104,C17,'2-Calcul des Salaires'!Q5:Q104)-SUMIF('2-Calcul des Salaires'!D5:D104,C17,'2-Calcul des Salaires'!O5:O104)) | I17: =IF(C17="","",SUMIF('2-Calcul des Salaires'!D5:D104,C17,'2-Calcul des Salaires'!Q5:Q104)) | K17: =IF(OR(F17="",J17=""),"",IFERROR(F17/J17,0)) | L17: =IF(OR(E17="",I17=""),"",IFERROR(I17/E17,0))
B18: =IF(C18="","MS"&TEXT(COUNTA($C$5:C18),"000")) | E18: =IF(C18="","",COUNTIF('2-Calcul des Salaires'!D5:D104,C18)) | F18: =IF(C18="","",SUMIF('2-Calcul des Salaires'!D5:D104,C18,'2-Calcul des Salaires'!J5:J104)) | G18: =IF(C18="","",SUMIF('2-Calcul des Salaires'!D5:D104,C18,'2-Calcul des Salaires'!O5:O104)) | H18: =IF(C18="","",SUMIF('2-Calcul des Salaires'!D5:D104,C18,'2-Calcul des Salaires'!Q5:Q104)-SUMIF('2-Calcul des Salaires'!D5:D104,C18,'2-Calcul des Salaires'!O5:O104)) | I18: =IF(C18="","",SUMIF('2-Calcul des Salaires'!D5:D104,C18,'2-Calcul des Salaires'!Q5:Q104)) | K18: =IF(OR(F18="",J18=""),"",IFERROR(F18/J18,0)) | L18: =IF(OR(E18="",I18=""),"",IFERROR(I18/E18,0))
B19: =IF(C19="","MS"&TEXT(COUNTA($C$5:C19),"000")) | E19: =IF(C19="","",COUNTIF('2-Calcul des Salaires'!D5:D104,C19)) | F19: =IF(C19="","",SUMIF('2-Calcul des Salaires'!D5:D104,C19,'2-Calcul des Salaires'!J5:J104)) | G19: =IF(C19="","",SUMIF('2-Calcul des Salaires'!D5:D104,C19,'2-Calcul des Salaires'!O5:O104)) | H19: =IF(C19="","",SUMIF('2-Calcul des Salaires'!D5:D104,C19,'2-Calcul des Salaires'!Q5:Q104)-SUMIF('2-Calcul des Salaires'!D5:D104,C19,'2-Calcul des Salaires'!O5:O104)) | I19: =IF(C19="","",SUMIF('2-Calcul des Salaires'!D5:D104,C19,'2-Calcul des Salaires'!Q5:Q104)) | K19: =IF(OR(F19="",J19=""),"",IFERROR(F19/J19,0)) | L19: =IF(OR(E19="",I19=""),"",IFERROR(I19/E19,0))
B20: =IF(C20="","MS"&TEXT(COUNTA($C$5:C20),"000")) | E20: =IF(C20="","",COUNTIF('2-Calcul des Salaires'!D5:D104,C20)) | F20: =IF(C20="","",SUMIF('2-Calcul des Salaires'!D5:D104,C20,'2-Calcul des Salaires'!J5:J104)) | G20: =IF(C20="","",SUMIF('2-Calcul des Salaires'!D5:D104,C20,'2-Calcul des Salaires'!O5:O104)) | H20: =IF(C20="","",SUMIF('2-Calcul des Salaires'!D5:D104,C20,'2-Calcul des Salaires'!Q5:Q104)-SUMIF('2-Calcul des Salaires'!D5:D104,C20,'2-Calcul des Salaires'!O5:O104)) | I20: =IF(C20="","",SUMIF('2-Calcul des Salaires'!D5:D104,C20,'2-Calcul des Salaires'!Q5:Q104)) | K20: =IF(OR(F20="",J20=""),"",IFERROR(F20/J20,0)) | L20: =IF(OR(E20="",I20=""),"",IFERROR(I20/E20,0))
B21: =IF(C21="","MS"&TEXT(COUNTA($C$5:C21),"000")) | E21: =IF(C21="","",COUNTIF('2-Calcul des Salaires'!D5:D104,C21)) | F21: =IF(C21="","",SUMIF('2-Calcul des Salaires'!D5:D104,C21,'2-Calcul des Salaires'!J5:J104)) | G21: =IF(C21="","",SUMIF('2-Calcul des Salaires'!D5:D104,C21,'2-Calcul des Salaires'!O5:O104)) | H21: =IF(C21="","",SUMIF('2-Calcul des Salaires'!D5:D104,C21,'2-Calcul des Salaires'!Q5:Q104)-SUMIF('2-Calcul des Salaires'!D5:D104,C21,'2-Calcul des Salaires'!O5:O104)) | I21: =IF(C21="","",SUMIF('2-Calcul des Salaires'!D5:D104,C21,'2-Calcul des Salaires'!Q5:Q104)) | K21: =IF(OR(F21="",J21=""),"",IFERROR(F21/J21,0)) | L21: =IF(OR(E21="",I21=""),"",IFERROR(I21/E21,0))
B22: =IF(C22="","MS"&TEXT(COUNTA($C$5:C22),"000")) | E22: =IF(C22="","",COUNTIF('2-Calcul des Salaires'!D5:D104,C22)) | F22: =IF(C22="","",SUMIF('2-Calcul des Salaires'!D5:D104,C22,'2-Calcul des Salaires'!J5:J104)) | G22: =IF(C22="","",SUMIF('2-Calcul des Salaires'!D5:D104,C22,'2-Calcul des Salaires'!O5:O104)) | H22: =IF(C22="","",SUMIF('2-Calcul des Salaires'!D5:D104,C22,'2-Calcul des Salaires'!Q5:Q104)-SUMIF('2-Calcul des Salaires'!D5:D104,C22,'2-Calcul des Salaires'!O5:O104)) | I22: =IF(C22="","",SUMIF('2-Calcul des Salaires'!D5:D104,C22,'2-Calcul des Salaires'!Q5:Q104)) | K22: =IF(OR(F22="",J22=""),"",IFERROR(F22/J22,0)) | L22: =IF(OR(E22="",I22=""),"",IFERROR(I22/E22,0))
B23: =IF(C23="","MS"&TEXT(COUNTA($C$5:C23),"000")) | E23: =IF(C23="","",COUNTIF('2-Calcul des Salaires'!D5:D104,C23)) | F23: =IF(C23="","",SUMIF('2-Calcul des Salaires'!D5:D104,C23,'2-Calcul des Salaires'!J5:J104)) | G23: =IF(C23="","",SUMIF('2-Calcul des Salaires'!D5:D104,C23,'2-Calcul des Salaires'!O5:O104)) | H23: =IF(C23="","",SUMIF('2-Calcul des Salaires'!D5:D104,C23,'2-Calcul des Salaires'!Q5:Q104)-SUMIF('2-Calcul des Salaires'!D5:D104,C23,'2-Calcul des Salaires'!O5:O104)) | I23: =IF(C23="","",SUMIF('2-Calcul des Salaires'!D5:D104,C23,'2-Calcul des Salaires'!Q5:Q104)) | K23: =IF(OR(F23="",J23=""),"",IFERROR(F23/J23,0)) | L23: =IF(OR(E23="",I23=""),"",IFERROR(I23/E23,0))
B24: =IF(C24="","MS"&TEXT(COUNTA($C$5:C24),"000")) | E24: =IF(C24="","",COUNTIF('2-Calcul des Salaires'!D5:D104,C24)) | F24: =IF(C24="","",SUMIF('2-Calcul des Salaires'!D5:D104,C24,'2-Calcul des Salaires'!J5:J104)) | G24: =IF(C24="","",SUMIF('2-Calcul des Salaires'!D5:D104,C24,'2-Calcul des Salaires'!O5:O104)) | H24: =IF(C24="","",SUMIF('2-Calcul des Salaires'!D5:D104,C24,'2-Calcul des Salaires'!Q5:Q104)-SUMIF('2-Calcul des Salaires'!D5:D104,C24,'2-Calcul des Salaires'!O5:O104)) | I24: =IF(C24="","",SUMIF('2-Calcul des Salaires'!D5:D104,C24,'2-Calcul des Salaires'!Q5:Q104)) | K24: =IF(OR(F24="",J24=""),"",IFERROR(F24/J24,0)) | L24: =IF(OR(E24="",I24=""),"",IFERROR(I24/E24,0))
B25: =IF(C25="","MS"&TEXT(COUNTA($C$5:C25),"000")) | E25: =IF(C25="","",COUNTIF('2-Calcul des Salaires'!D5:D104,C25)) | F25: =IF(C25="","",SUMIF('2-Calcul des Salaires'!D5:D104,C25,'2-Calcul des Salaires'!J5:J104)) | G25: =IF(C25="","",SUMIF('2-Calcul des Salaires'!D5:D104,C25,'2-Calcul des Salaires'!O5:O104)) | H25: =IF(C25="","",SUMIF('2-Calcul des Salaires'!D5:D104,C25,'2-Calcul des Salaires'!Q5:Q104)-SUMIF('2-Calcul des Salaires'!D5:D104,C25,'2-Calcul des Salaires'!O5:O104)) | I25: =IF(C25="","",SUMIF('2-Calcul des Salaires'!D5:D104,C25,'2-Calcul des Salaires'!Q5:Q104)) | K25: =IF(OR(F25="",J25=""),"",IFERROR(F25/J25,0)) | L25: =IF(OR(E25="",I25=""),"",IFERROR(I25/E25,0))
B26: =IF(C26="","MS"&TEXT(COUNTA($C$5:C26),"000")) | E26: =IF(C26="","",COUNTIF('2-Calcul des Salaires'!D5:D104,C26)) | F26: =IF(C26="","",SUMIF('2-Calcul des Salaires'!D5:D104,C26,'2-Calcul des Salaires'!J5:J104)) | G26: =IF(C26="","",SUMIF('2-Calcul des Salaires'!D5:D104,C26,'2-Calcul des Salaires'!O5:O104)) | H26: =IF(C26="","",SUMIF('2-Calcul des Salaires'!D5:D104,C26,'2-Calcul des Salaires'!Q5:Q104)-SUMIF('2-Calcul des Salaires'!D5:D104,C26,'2-Calcul des Salaires'!O5:O104)) | I26: =IF(C26="","",SUMIF('2-Calcul des Salaires'!D5:D104,C26,'2-Calcul des Salaires'!Q5:Q104)) | K26: =IF(OR(F26="",J26=""),"",IFERROR(F26/J26,0)) | L26: =IF(OR(E26="",I26=""),"",IFERROR(I26/E26,0))
B27: =IF(C27="","MS"&TEXT(COUNTA($C$5:C27),"000")) | E27: =IF(C27="","",COUNTIF('2-Calcul des Salaires'!D5:D104,C27)) | F27: =IF(C27="","",SUMIF('2-Calcul des Salaires'!D5:D104,C27,'2-Calcul des Salaires'!J5:J104)) | G27: =IF(C27="","",SUMIF('2-Calcul des Salaires'!D5:D104,C27,'2-Calcul des Salaires'!O5:O104)) | H27: =IF(C27="","",SUMIF('2-Calcul des Salaires'!D5:D104,C27,'2-Calcul des Salaires'!Q5:Q104)-SUMIF('2-Calcul des Salaires'!D5:D104,C27,'2-Calcul des Salaires'!O5:O104)) | I27: =IF(C27="","",SUMIF('2-Calcul des Salaires'!D5:D104,C27,'2-Calcul des Salaires'!Q5:Q104)) | K27: =IF(OR(F27="",J27=""),"",IFERROR(F27/J27,0)) | L27: =IF(OR(E27="",I27=""),"",IFERROR(I27/E27,0))
B28: =IF(C28="","MS"&TEXT(COUNTA($C$5:C28),"000")) | E28: =IF(C28="","",COUNTIF('2-Calcul des Salaires'!D5:D104,C28)) | F28: =IF(C28="","",SUMIF('2-Calcul des Salaires'!D5:D104,C28,'2-Calcul des Salaires'!J5:J104)) | G28: =IF(C28="","",SUMIF('2-Calcul des Salaires'!D5:D104,C28,'2-Calcul des Salaires'!O5:O104)) | H28: =IF(C28="","",SUMIF('2-Calcul des Salaires'!D5:D104,C28,'2-Calcul des Salaires'!Q5:Q104)-SUMIF('2-Calcul des Salaires'!D5:D104,C28,'2-Calcul des Salaires'!O5:O104)) | I28: =IF(C28="","",SUMIF('2-Calcul des Salaires'!D5:D104,C28,'2-Calcul des Salaires'!Q5:Q104)) | K28: =IF(OR(F28="",J28=""),"",IFERROR(F28/J28,0)) | L28: =IF(OR(E28="",I28=""),"",IFERROR(I28/E28,0))
B29: =IF(C29="","MS"&TEXT(COUNTA($C$5:C29),"000")) | E29: =IF(C29="","",COUNTIF('2-Calcul des Salaires'!D5:D104,C29)) | F29: =IF(C29="","",SUMIF('2-Calcul des Salaires'!D5:D104,C29,'2-Calcul des Salaires'!J5:J104)) | G29: =IF(C29="","",SUMIF('2-Calcul des Salaires'!D5:D104,C29,'2-Calcul des Salaires'!O5:O104)) | H29: =IF(C29="","",SUMIF('2-Calcul des Salaires'!D5:D104,C29,'2-Calcul des Salaires'!Q5:Q104)-SUMIF('2-Calcul des Salaires'!D5:D104,C29,'2-Calcul des Salaires'!O5:O104)) | I29: =IF(C29="","",SUMIF('2-Calcul des Salaires'!D5:D104,C29,'2-Calcul des Salaires'!Q5:Q104)) | K29: =IF(OR(F29="",J29=""),"",IFERROR(F29/J29,0)) | L29: =IF(OR(E29="",I29=""),"",IFERROR(I29/E29,0))
B30: =IF(C30="","MS"&TEXT(COUNTA($C$5:C30),"000")) | E30: =IF(C30="","",COUNTIF('2-Calcul des Salaires'!D5:D104,C30)) | F30: =IF(C30="","",SUMIF('2-Calcul des Salaires'!D5:D104,C30,'2-Calcul des Salaires'!J5:J104)) | G30: =IF(C30="","",SUMIF('2-Calcul des Salaires'!D5:D104,C30,'2-Calcul des Salaires'!O5:O104)) | H30: =IF(C30="","",SUMIF('2-Calcul des Salaires'!D5:D104,C30,'2-Calcul des Salaires'!Q5:Q104)-SUMIF('2-Calcul des Salaires'!D5:D104,C30,'2-Calcul des Salaires'!O5:O104)) | I30: =IF(C30="","",SUMIF('2-Calcul des Salaires'!D5:D104,C30,'2-Calcul des Salaires'!Q5:Q104)) | K30: =IF(OR(F30="",J30=""),"",IFERROR(F30/J30,0)) | L30: =IF(OR(E30="",I30=""),"",IFERROR(I30/E30,0))
B31: =IF(C31="","MS"&TEXT(COUNTA($C$5:C31),"000")) | E31: =IF(C31="","",COUNTIF('2-Calcul des Salaires'!D5:D104,C31)) | F31: =IF(C31="","",SUMIF('2-Calcul des Salaires'!D5:D104,C31,'2-Calcul des Salaires'!J5:J104)) | G31: =IF(C31="","",SUMIF('2-Calcul des Salaires'!D5:D104,C31,'2-Calcul des Salaires'!O5:O104)) | H31: =IF(C31="","",SUMIF('2-Calcul des Salaires'!D5:D104,C31,'2-Calcul des Salaires'!Q5:Q104)-SUMIF('2-Calcul des Salaires'!D5:D104,C31,'2-Calcul des Salaires'!O5:O104)) | I31: =IF(C31="","",SUMIF('2-Calcul des Salaires'!D5:D104,C31,'2-Calcul des Salaires'!Q5:Q104)) | K31: =IF(OR(F31="",J31=""),"",IFERROR(F31/J31,0)) | L31: =IF(OR(E31="",I31=""),"",IFERROR(I31/E31,0))
B32: =IF(C32="","MS"&TEXT(COUNTA($C$5:C32),"000")) | E32: =IF(C32="","",COUNTIF('2-Calcul des Salaires'!D5:D104,C32)) | F32: =IF(C32="","",SUMIF('2-Calcul des Salaires'!D5:D104,C32,'2-Calcul des Salaires'!J5:J104)) | G32: =IF(C32="","",SUMIF('2-Calcul des Salaires'!D5:D104,C32,'2-Calcul des Salaires'!O5:O104)) | H32: =IF(C32="","",SUMIF('2-Calcul des Salaires'!D5:D104,C32,'2-Calcul des Salaires'!Q5:Q104)-SUMIF('2-Calcul des Salaires'!D5:D104,C32,'2-Calcul des Salaires'!O5:O104)) | I32: =IF(C32="","",SUMIF('2-Calcul des Salaires'!D5:D104,C32,'2-Calcul des Salaires'!Q5:Q104)) | K32: =IF(OR(F32="",J32=""),"",IFERROR(F32/J32,0)) | L32: =IF(OR(E32="",I32=""),"",IFERROR(I32/E32,0))
B33: =IF(C33="","MS"&TEXT(COUNTA($C$5:C33),"000")) | E33: =IF(C33="","",COUNTIF('2-Calcul des Salaires'!D5:D104,C33)) | F33: =IF(C33="","",SUMIF('2-Calcul des Salaires'!D5:D104,C33,'2-Calcul des Salaires'!J5:J104)) | G33: =IF(C33="","",SUMIF('2-Calcul des Salaires'!D5:D104,C33,'2-Calcul des Salaires'!O5:O104)) | H33: =IF(C33="","",SUMIF('2-Calcul des Salaires'!D5:D104,C33,'2-Calcul des Salaires'!Q5:Q104)-SUMIF('2-Calcul des Salaires'!D5:D104,C33,'2-Calcul des Salaires'!O5:O104)) | I33: =IF(C33="","",SUMIF('2-Calcul des Salaires'!D5:D104,C33,'2-Calcul des Salaires'!Q5:Q104)) | K33: =IF(OR(F33="",J33=""),"",IFERROR(F33/J33,0)) | L33: =IF(OR(E33="",I33=""),"",IFERROR(I33/E33,0))
B34: =IF(C34="","MS"&TEXT(COUNTA($C$5:C34),"000")) | E34: =IF(C34="","",COUNTIF('2-Calcul des Salaires'!D5:D104,C34)) | F34: =IF(C34="","",SUMIF('2-Calcul des Salaires'!D5:D104,C34,'2-Calcul des Salaires'!J5:J104)) | G34: =IF(C34="","",SUMIF('2-Calcul des Salaires'!D5:D104,C34,'2-Calcul des Salaires'!O5:O104)) | H34: =IF(C34="","",SUMIF('2-Calcul des Salaires'!D5:D104,C34,'2-Calcul des Salaires'!Q5:Q104)-SUMIF('2-Calcul des Salaires'!D5:D104,C34,'2-Calcul des Salaires'!O5:O104)) | I34: =IF(C34="","",SUMIF('2-Calcul des Salaires'!D5:D104,C34,'2-Calcul des Salaires'!Q5:Q104)) | K34: =IF(OR(F34="",J34=""),"",IFERROR(F34/J34,0)) | L34: =IF(OR(E34="",I34=""),"",IFERROR(I34/E34,0))
B35: =IF(C35="","MS"&TEXT(COUNTA($C$5:C35),"000")) | E35: =IF(C35="","",COUNTIF('2-Calcul des Salaires'!D5:D104,C35)) | F35: =IF(C35="","",SUMIF('2-Calcul des Salaires'!D5:D104,C35,'2-Calcul des Salaires'!J5:J104)) | G35: =IF(C35="","",SUMIF('2-Calcul des Salaires'!D5:D104,C35,'2-Calcul des Salaires'!O5:O104)) | H35: =IF(C35="","",SUMIF('2-Calcul des Salaires'!D5:D104,C35,'2-Calcul des Salaires'!Q5:Q104)-SUMIF('2-Calcul des Salaires'!D5:D104,C35,'2-Calcul des Salaires'!O5:O104)) | I35: =IF(C35="","",SUMIF('2-Calcul des Salaires'!D5:D104,C35,'2-Calcul des Salaires'!Q5:Q104)) | K35: =IF(OR(F35="",J35=""),"",IFERROR(F35/J35,0)) | L35: =IF(OR(E35="",I35=""),"",IFERROR(I35/E35,0))
B36: =IF(C36="","MS"&TEXT(COUNTA($C$5:C36),"000")) | E36: =IF(C36="","",COUNTIF('2-Calcul des Salaires'!D5:D104,C36)) | F36: =IF(C36="","",SUMIF('2-Calcul des Salaires'!D5:D104,C36,'2-Calcul des Salaires'!J5:J104)) | G36: =IF(C36="","",SUMIF('2-Calcul des Salaires'!D5:D104,C36,'2-Calcul des Salaires'!O5:O104)) | H36: =IF(C36="","",SUMIF('2-Calcul des Salaires'!D5:D104,C36,'2-Calcul des Salaires'!Q5:Q104)-SUMIF('2-Calcul des Salaires'!D5:D104,C36,'2-Calcul des Salaires'!O5:O104)) | I36: =IF(C36="","",SUMIF('2-Calcul des Salaires'!D5:D104,C36,'2-Calcul des Salaires'!Q5:Q104)) | K36: =IF(OR(F36="",J36=""),"",IFERROR(F36/J36,0)) | L36: =IF(OR(E36="",I36=""),"",IFERROR(I36/E36,0))
B37: =IF(C37="","MS"&TEXT(COUNTA($C$5:C37),"000")) | E37: =IF(C37="","",COUNTIF('2-Calcul des Salaires'!D5:D104,C37)) | F37: =IF(C37="","",SUMIF('2-Calcul des Salaires'!D5:D104,C37,'2-Calcul des Salaires'!J5:J104)) | G37: =IF(C37="","",SUMIF('2-Calcul des Salaires'!D5:D104,C37,'2-Calcul des Salaires'!O5:O104)) | H37: =IF(C37="","",SUMIF('2-Calcul des Salaires'!D5:D104,C37,'2-Calcul des Salaires'!Q5:Q104)-SUMIF('2-Calcul des Salaires'!D5:D104,C37,'2-Calcul des Salaires'!O5:O104)) | I37: =IF(C37="","",SUMIF('2-Calcul des Salaires'!D5:D104,C37,'2-Calcul des Salaires'!Q5:Q104)) | K37: =IF(OR(F37="",J37=""),"",IFERROR(F37/J37,0)) | L37: =IF(OR(E37="",I37=""),"",IFERROR(I37/E37,0))
B38: =IF(C38="","MS"&TEXT(COUNTA($C$5:C38),"000")) | E38: =IF(C38="","",COUNTIF('2-Calcul des Salaires'!D5:D104,C38)) | F38: =IF(C38="","",SUMIF('2-Calcul des Salaires'!D5:D104,C38,'2-Calcul des Salaires'!J5:J104)) | G38: =IF(C38="","",SUMIF('2-Calcul des Salaires'!D5:D104,C38,'2-Calcul des Salaires'!O5:O104)) | H38: =IF(C38="","",SUMIF('2-Calcul des Salaires'!D5:D104,C38,'2-Calcul des Salaires'!Q5:Q104)-SUMIF('2-Calcul des Salaires'!D5:D104,C38,'2-Calcul des Salaires'!O5:O104)) | I38: =IF(C38="","",SUMIF('2-Calcul des Salaires'!D5:D104,C38,'2-Calcul des Salaires'!Q5:Q104)) | K38: =IF(OR(F38="",J38=""),"",IFERROR(F38/J38,0)) | L38: =IF(OR(E38="",I38=""),"",IFERROR(I38/E38,0))
B39: =IF(C39="","MS"&TEXT(COUNTA($C$5:C39),"000")) | E39: =IF(C39="","",COUNTIF('2-Calcul des Salaires'!D5:D104,C39)) | F39: =IF(C39="","",SUMIF('2-Calcul des Salaires'!D5:D104,C39,'2-Calcul des Salaires'!J5:J104)) | G39: =IF(C39="","",SUMIF('2-Calcul des Salaires'!D5:D104,C39,'2-Calcul des Salaires'!O5:O104)) | H39: =IF(C39="","",SUMIF('2-Calcul des Salaires'!D5:D104,C39,'2-Calcul des Salaires'!Q5:Q104)-SUMIF('2-Calcul des Salaires'!D5:D104,C39,'2-Calcul des Salaires'!O5:O104)) | I39: =IF(C39="","",SUMIF('2-Calcul des Salaires'!D5:D104,C39,'2-Calcul des Salaires'!Q5:Q104)) | K39: =IF(OR(F39="",J39=""),"",IFERROR(F39/J39,0)) | L39: =IF(OR(E39="",I39=""),"",IFERROR(I39/E39,0))
B40: =IF(C40="","MS"&TEXT(COUNTA($C$5:C40),"000")) | E40: =IF(C40="","",COUNTIF('2-Calcul des Salaires'!D5:D104,C40)) | F40: =IF(C40="","",SUMIF('2-Calcul des Salaires'!D5:D104,C40,'2-Calcul des Salaires'!J5:J104)) | G40: =IF(C40="","",SUMIF('2-Calcul des Salaires'!D5:D104,C40,'2-Calcul des Salaires'!O5:O104)) | H40: =IF(C40="","",SUMIF('2-Calcul des Salaires'!D5:D104,C40,'2-Calcul des Salaires'!Q5:Q104)-SUMIF('2-Calcul des Salaires'!D5:D104,C40,'2-Calcul des Salaires'!O5:O104)) | I40: =IF(C40="","",SUMIF('2-Calcul des Salaires'!D5:D104,C40,'2-Calcul des Salaires'!Q5:Q104)) | K40: =IF(OR(F40="",J40=""),"",IFERROR(F40/J40,0)) | L40: =IF(OR(E40="",I40=""),"",IFERROR(I40/E40,0))
B41: =IF(C41="","MS"&TEXT(COUNTA($C$5:C41),"000")) | E41: =IF(C41="","",COUNTIF('2-Calcul des Salaires'!D5:D104,C41)) | F41: =IF(C41="","",SUMIF('2-Calcul des Salaires'!D5:D104,C41,'2-Calcul des Salaires'!J5:J104)) | G41: =IF(C41="","",SUMIF('2-Calcul des Salaires'!D5:D104,C41,'2-Calcul des Salaires'!O5:O104)) | H41: =IF(C41="","",SUMIF('2-Calcul des Salaires'!D5:D104,C41,'2-Calcul des Salaires'!Q5:Q104)-SUMIF('2-Calcul des Salaires'!D5:D104,C41,'2-Calcul des Salaires'!O5:O104)) | I41: =IF(C41="","",SUMIF('2-Calcul des Salaires'!D5:D104,C41,'2-Calcul des Salaires'!Q5:Q104)) | K41: =IF(OR(F41="",J41=""),"",IFERROR(F41/J41,0)) | L41: =IF(OR(E41="",I41=""),"",IFERROR(I41/E41,0))
B42: =IF(C42="","MS"&TEXT(COUNTA($C$5:C42),"000")) | E42: =IF(C42="","",COUNTIF('2-Calcul des Salaires'!D5:D104,C42)) | F42: =IF(C42="","",SUMIF('2-Calcul des Salaires'!D5:D104,C42,'2-Calcul des Salaires'!J5:J104)) | G42: =IF(C42="","",SUMIF('2-Calcul des Salaires'!D5:D104,C42,'2-Calcul des Salaires'!O5:O104)) | H42: =IF(C42="","",SUMIF('2-Calcul des Salaires'!D5:D104,C42,'2-Calcul des Salaires'!Q5:Q104)-SUMIF('2-Calcul des Salaires'!D5:D104,C42,'2-Calcul des Salaires'!O5:O104)) | I42: =IF(C42="","",SUMIF('2-Calcul des Salaires'!D5:D104,C42,'2-Calcul des Salaires'!Q5:Q104)) | K42: =IF(OR(F42="",J42=""),"",IFERROR(F42/J42,0)) | L42: =IF(OR(E42="",I42=""),"",IFERROR(I42/E42,0))
B43: =IF(C43="","MS"&TEXT(COUNTA($C$5:C43),"000")) | E43: =IF(C43="","",COUNTIF('2-Calcul des Salaires'!D5:D104,C43)) | F43: =IF(C43="","",SUMIF('2-Calcul des Salaires'!D5:D104,C43,'2-Calcul des Salaires'!J5:J104)) | G43: =IF(C43="","",SUMIF('2-Calcul des Salaires'!D5:D104,C43,'2-Calcul des Salaires'!O5:O104)) | H43: =IF(C43="","",SUMIF('2-Calcul des Salaires'!D5:D104,C43,'2-Calcul des Salaires'!Q5:Q104)-SUMIF('2-Calcul des Salaires'!D5:D104,C43,'2-Calcul des Salaires'!O5:O104)) | I43: =IF(C43="","",SUMIF('2-Calcul des Salaires'!D5:D104,C43,'2-Calcul des Salaires'!Q5:Q104)) | K43: =IF(OR(F43="",J43=""),"",IFERROR(F43/J43,0)) | L43: =IF(OR(E43="",I43=""),"",IFERROR(I43/E43,0))
B44: =IF(C44="","MS"&TEXT(COUNTA($C$5:C44),"000")) | E44: =IF(C44="","",COUNTIF('2-Calcul des Salaires'!D5:D104,C44)) | F44: =IF(C44="","",SUMIF('2-Calcul des Salaires'!D5:D104,C44,'2-Calcul des Salaires'!J5:J104)) | G44: =IF(C44="","",SUMIF('2-Calcul des Salaires'!D5:D104,C44,'2-Calcul des Salaires'!O5:O104)) | H44: =IF(C44="","",SUMIF('2-Calcul des Salaires'!D5:D104,C44,'2-Calcul des Salaires'!Q5:Q104)-SUMIF('2-Calcul des Salaires'!D5:D104,C44,'2-Calcul des Salaires'!O5:O104)) | I44: =IF(C44="","",SUMIF('2-Calcul des Salaires'!D5:D104,C44,'2-Calcul des Salaires'!Q5:Q104)) | K44: =IF(OR(F44="",J44=""),"",IFERROR(F44/J44,0)) | L44: =IF(OR(E44="",I44=""),"",IFERROR(I44/E44,0))
B45: =IF(C45="","MS"&TEXT(COUNTA($C$5:C45),"000")) | E45: =IF(C45="","",COUNTIF('2-Calcul des Salaires'!D5:D104,C45)) | F45: =IF(C45="","",SUMIF('2-Calcul des Salaires'!D5:D104,C45,'2-Calcul des Salaires'!J5:J104)) | G45: =IF(C45="","",SUMIF('2-Calcul des Salaires'!D5:D104,C45,'2-Calcul des Salaires'!O5:O104)) | H45: =IF(C45="","",SUMIF('2-Calcul des Salaires'!D5:D104,C45,'2-Calcul des Salaires'!Q5:Q104)-SUMIF('2-Calcul des Salaires'!D5:D104,C45,'2-Calcul des Salaires'!O5:O104)) | I45: =IF(C45="","",SUMIF('2-Calcul des Salaires'!D5:D104,C45,'2-Calcul des Salaires'!Q5:Q104)) | K45: =IF(OR(F45="",J45=""),"",IFERROR(F45/J45,0)) | L45: =IF(OR(E45="",I45=""),"",IFERROR(I45/E45,0))
B46: =IF(C46="","MS"&TEXT(COUNTA($C$5:C46),"000")) | E46: =IF(C46="","",COUNTIF('2-Calcul des Salaires'!D5:D104,C46)) | F46: =IF(C46="","",SUMIF('2-Calcul des Salaires'!D5:D104,C46,'2-Calcul des Salaires'!J5:J104)) | G46: =IF(C46="","",SUMIF('2-Calcul des Salaires'!D5:D104,C46,'2-Calcul des Salaires'!O5:O104)) | H46: =IF(C46="","",SUMIF('2-Calcul des Salaires'!D5:D104,C46,'2-Calcul des Salaires'!Q5:Q104)-SUMIF('2-Calcul des Salaires'!D5:D104,C46,'2-Calcul des Salaires'!O5:O104)) | I46: =IF(C46="","",SUMIF('2-Calcul des Salaires'!D5:D104,C46,'2-Calcul des Salaires'!Q5:Q104)) | K46: =IF(OR(F46="",J46=""),"",IFERROR(F46/J46,0)) | L46: =IF(OR(E46="",I46=""),"",IFERROR(I46/E46,0))
B47: =IF(C47="","MS"&TEXT(COUNTA($C$5:C47),"000")) | E47: =IF(C47="","",COUNTIF('2-Calcul des Salaires'!D5:D104,C47)) | F47: =IF(C47="","",SUMIF('2-Calcul des Salaires'!D5:D104,C47,'2-Calcul des Salaires'!J5:J104)) | G47: =IF(C47="","",SUMIF('2-Calcul des Salaires'!D5:D104,C47,'2-Calcul des Salaires'!O5:O104)) | H47: =IF(C47="","",SUMIF('2-Calcul des Salaires'!D5:D104,C47,'2-Calcul des Salaires'!Q5:Q104)-SUMIF('2-Calcul des Salaires'!D5:D104,C47,'2-Calcul des Salaires'!O5:O104)) | I47: =IF(C47="","",SUMIF('2-Calcul des Salaires'!D5:D104,C47,'2-Calcul des Salaires'!Q5:Q104)) | K47: =IF(OR(F47="",J47=""),"",IFERROR(F47/J47,0)) | L47: =IF(OR(E47="",I47=""),"",IFERROR(I47/E47,0))
B48: =IF(C48="","MS"&TEXT(COUNTA($C$5:C48),"000")) | E48: =IF(C48="","",COUNTIF('2-Calcul des Salaires'!D5:D104,C48)) | F48: =IF(C48="","",SUMIF('2-Calcul des Salaires'!D5:D104,C48,'2-Calcul des Salaires'!J5:J104)) | G48: =IF(C48="","",SUMIF('2-Calcul des Salaires'!D5:D104,C48,'2-Calcul des Salaires'!O5:O104)) | H48: =IF(C48="","",SUMIF('2-Calcul des Salaires'!D5:D104,C48,'2-Calcul des Salaires'!Q5:Q104)-SUMIF('2-Calcul des Salaires'!D5:D104,C48,'2-Calcul des Salaires'!O5:O104)) | I48: =IF(C48="","",SUMIF('2-Calcul des Salaires'!D5:D104,C48,'2-Calcul des Salaires'!Q5:Q104)) | K48: =IF(OR(F48="",J48=""),"",IFERROR(F48/J48,0)) | L48: =IF(OR(E48="",I48=""),"",IFERROR(I48/E48,0))
B49: =IF(C49="","MS"&TEXT(COUNTA($C$5:C49),"000")) | E49: =IF(C49="","",COUNTIF('2-Calcul des Salaires'!D5:D104,C49)) | F49: =IF(C49="","",SUMIF('2-Calcul des Salaires'!D5:D104,C49,'2-Calcul des Salaires'!J5:J104)) | G49: =IF(C49="","",SUMIF('2-Calcul des Salaires'!D5:D104,C49,'2-Calcul des Salaires'!O5:O104)) | H49: =IF(C49="","",SUMIF('2-Calcul des Salaires'!D5:D104,C49,'2-Calcul des Salaires'!Q5:Q104)-SUMIF('2-Calcul des Salaires'!D5:D104,C49,'2-Calcul des Salaires'!O5:O104)) | I49: =IF(C49="","",SUMIF('2-Calcul des Salaires'!D5:D104,C49,'2-Calcul des Salaires'!Q5:Q104)) | K49: =IF(OR(F49="",J49=""),"",IFERROR(F49/J49,0)) | L49: =IF(OR(E49="",I49=""),"",IFERROR(I49/E49,0))
B50: =IF(C50="","MS"&TEXT(COUNTA($C$5:C50),"000")) | E50: =IF(C50="","",COUNTIF('2-Calcul des Salaires'!D5:D104,C50)) | F50: =IF(C50="","",SUMIF('2-Calcul des Salaires'!D5:D104,C50,'2-Calcul des Salaires'!J5:J104)) | G50: =IF(C50="","",SUMIF('2-Calcul des Salaires'!D5:D104,C50,'2-Calcul des Salaires'!O5:O104)) | H50: =IF(C50="","",SUMIF('2-Calcul des Salaires'!D5:D104,C50,'2-Calcul des Salaires'!Q5:Q104)-SUMIF('2-Calcul des Salaires'!D5:D104,C50,'2-Calcul des Salaires'!O5:O104)) | I50: =IF(C50="","",SUMIF('2-Calcul des Salaires'!D5:D104,C50,'2-Calcul des Salaires'!Q5:Q104)) | K50: =IF(OR(F50="",J50=""),"",IFERROR(F50/J50,0)) | L50: =IF(OR(E50="",I50=""),"",IFERROR(I50/E50,0))
B51: =IF(C51="","MS"&TEXT(COUNTA($C$5:C51),"000")) | E51: =IF(C51="","",COUNTIF('2-Calcul des Salaires'!D5:D104,C51)) | F51: =IF(C51="","",SUMIF('2-Calcul des Salaires'!D5:D104,C51,'2-Calcul des Salaires'!J5:J104)) | G51: =IF(C51="","",SUMIF('2-Calcul des Salaires'!D5:D104,C51,'2-Calcul des Salaires'!O5:O104)) | H51: =IF(C51="","",SUMIF('2-Calcul des Salaires'!D5:D104,C51,'2-Calcul des Salaires'!Q5:Q104)-SUMIF('2-Calcul des Salaires'!D5:D104,C51,'2-Calcul des Salaires'!O5:O104)) | I51: =IF(C51="","",SUMIF('2-Calcul des Salaires'!D5:D104,C51,'2-Calcul des Salaires'!Q5:Q104)) | K51: =IF(OR(F51="",J51=""),"",IFERROR(F51/J51,0)) | L51: =IF(OR(E51="",I51=""),"",IFERROR(I51/E51,0))
B52: =IF(C52="","MS"&TEXT(COUNTA($C$5:C52),"000")) | E52: =IF(C52="","",COUNTIF('2-Calcul des Salaires'!D5:D104,C52)) | F52: =IF(C52="","",SUMIF('2-Calcul des Salaires'!D5:D104,C52,'2-Calcul des Salaires'!J5:J104)) | G52: =IF(C52="","",SUMIF('2-Calcul des Salaires'!D5:D104,C52,'2-Calcul des Salaires'!O5:O104)) | H52: =IF(C52="","",SUMIF('2-Calcul des Salaires'!D5:D104,C52,'2-Calcul des Salaires'!Q5:Q104)-SUMIF('2-Calcul des Salaires'!D5:D104,C52,'2-Calcul des Salaires'!O5:O104)) | I52: =IF(C52="","",SUMIF('2-Calcul des Salaires'!D5:D104,C52,'2-Calcul des Salaires'!Q5:Q104)) | K52: =IF(OR(F52="",J52=""),"",IFERROR(F52/J52,0)) | L52: =IF(OR(E52="",I52=""),"",IFERROR(I52/E52,0))
B53: =IF(C53="","MS"&TEXT(COUNTA($C$5:C53),"000")) | E53: =IF(C53="","",COUNTIF('2-Calcul des Salaires'!D5:D104,C53)) | F53: =IF(C53="","",SUMIF('2-Calcul des Salaires'!D5:D104,C53,'2-Calcul des Salaires'!J5:J104)) | G53: =IF(C53="","",SUMIF('2-Calcul des Salaires'!D5:D104,C53,'2-Calcul des Salaires'!O5:O104)) | H53: =IF(C53="","",SUMIF('2-Calcul des Salaires'!D5:D104,C53,'2-Calcul des Salaires'!Q5:Q104)-SUMIF('2-Calcul des Salaires'!D5:D104,C53,'2-Calcul des Salaires'!O5:O104)) | I53: =IF(C53="","",SUMIF('2-Calcul des Salaires'!D5:D104,C53,'2-Calcul des Salaires'!Q5:Q104)) | K53: =IF(OR(F53="",J53=""),"",IFERROR(F53/J53,0)) | L53: =IF(OR(E53="",I53=""),"",IFERROR(I53/E53,0))
B54: =IF(C54="","MS"&TEXT(COUNTA($C$5:C54),"000")) | E54: =IF(C54="","",COUNTIF('2-Calcul des Salaires'!D5:D104,C54)) | F54: =IF(C54="","",SUMIF('2-Calcul des Salaires'!D5:D104,C54,'2-Calcul des Salaires'!J5:J104)) | G54: =IF(C54="","",SUMIF('2-Calcul des Salaires'!D5:D104,C54,'2-Calcul des Salaires'!O5:O104)) | H54: =IF(C54="","",SUMIF('2-Calcul des Salaires'!D5:D104,C54,'2-Calcul des Salaires'!Q5:Q104)-SUMIF('2-Calcul des Salaires'!D5:D104,C54,'2-Calcul des Salaires'!O5:O104)) | I54: =IF(C54="","",SUMIF('2-Calcul des Salaires'!D5:D104,C54,'2-Calcul des Salaires'!Q5:Q104)) | K54: =IF(OR(F54="",J54=""),"",IFERROR(F54/J54,0)) | L54: =IF(OR(E54="",I54=""),"",IFERROR(I54/E54,0))
B55: =IF(C55="","MS"&TEXT(COUNTA($C$5:C55),"000")) | E55: =IF(C55="","",COUNTIF('2-Calcul des Salaires'!D5:D104,C55)) | F55: =IF(C55="","",SUMIF('2-Calcul des Salaires'!D5:D104,C55,'2-Calcul des Salaires'!J5:J104)) | G55: =IF(C55="","",SUMIF('2-Calcul des Salaires'!D5:D104,C55,'2-Calcul des Salaires'!O5:O104)) | H55: =IF(C55="","",SUMIF('2-Calcul des Salaires'!D5:D104,C55,'2-Calcul des Salaires'!Q5:Q104)-SUMIF('2-Calcul des Salaires'!D5:D104,C55,'2-Calcul des Salaires'!O5:O104)) | I55: =IF(C55="","",SUMIF('2-Calcul des Salaires'!D5:D104,C55,'2-Calcul des Salaires'!Q5:Q104)) | K55: =IF(OR(F55="",J55=""),"",IFERROR(F55/J55,0)) | L55: =IF(OR(E55="",I55=""),"",IFERROR(I55/E55,0))
B56: =IF(C56="","MS"&TEXT(COUNTA($C$5:C56),"000")) | E56: =IF(C56="","",COUNTIF('2-Calcul des Salaires'!D5:D104,C56)) | F56: =IF(C56="","",SUMIF('2-Calcul des Salaires'!D5:D104,C56,'2-Calcul des Salaires'!J5:J104)) | G56: =IF(C56="","",SUMIF('2-Calcul des Salaires'!D5:D104,C56,'2-Calcul des Salaires'!O5:O104)) | H56: =IF(C56="","",SUMIF('2-Calcul des Salaires'!D5:D104,C56,'2-Calcul des Salaires'!Q5:Q104)-SUMIF('2-Calcul des Salaires'!D5:D104,C56,'2-Calcul des Salaires'!O5:O104)) | I56: =IF(C56="","",SUMIF('2-Calcul des Salaires'!D5:D104,C56,'2-Calcul des Salaires'!Q5:Q104)) | K56: =IF(OR(F56="",J56=""),"",IFERROR(F56/J56,0)) | L56: =IF(OR(E56="",I56=""),"",IFERROR(I56/E56,0))
B57: =IF(C57="","MS"&TEXT(COUNTA($C$5:C57),"000")) | E57: =IF(C57="","",COUNTIF('2-Calcul des Salaires'!D5:D104,C57)) | F57: =IF(C57="","",SUMIF('2-Calcul des Salaires'!D5:D104,C57,'2-Calcul des Salaires'!J5:J104)) | G57: =IF(C57="","",SUMIF('2-Calcul des Salaires'!D5:D104,C57,'2-Calcul des Salaires'!O5:O104)) | H57: =IF(C57="","",SUMIF('2-Calcul des Salaires'!D5:D104,C57,'2-Calcul des Salaires'!Q5:Q104)-SUMIF('2-Calcul des Salaires'!D5:D104,C57,'2-Calcul des Salaires'!O5:O104)) | I57: =IF(C57="","",SUMIF('2-Calcul des Salaires'!D5:D104,C57,'2-Calcul des Salaires'!Q5:Q104)) | K57: =IF(OR(F57="",J57=""),"",IFERROR(F57/J57,0)) | L57: =IF(OR(E57="",I57=""),"",IFERROR(I57/E57,0))
B58: =IF(C58="","MS"&TEXT(COUNTA($C$5:C58),"000")) | E58: =IF(C58="","",COUNTIF('2-Calcul des Salaires'!D5:D104,C58)) | F58: =IF(C58="","",SUMIF('2-Calcul des Salaires'!D5:D104,C58,'2-Calcul des Salaires'!J5:J104)) | G58: =IF(C58="","",SUMIF('2-Calcul des Salaires'!D5:D104,C58,'2-Calcul des Salaires'!O5:O104)) | H58: =IF(C58="","",SUMIF('2-Calcul des Salaires'!D5:D104,C58,'2-Calcul des Salaires'!Q5:Q104)-SUMIF('2-Calcul des Salaires'!D5:D104,C58,'2-Calcul des Salaires'!O5:O104)) | I58: =IF(C58="","",SUMIF('2-Calcul des Salaires'!D5:D104,C58,'2-Calcul des Salaires'!Q5:Q104)) | K58: =IF(OR(F58="",J58=""),"",IFERROR(F58/J58,0)) | L58: =IF(OR(E58="",I58=""),"",IFERROR(I58/E58,0))
B59: =IF(C59="","MS"&TEXT(COUNTA($C$5:C59),"000")) | E59: =IF(C59="","",COUNTIF('2-Calcul des Salaires'!D5:D104,C59)) | F59: =IF(C59="","",SUMIF('2-Calcul des Salaires'!D5:D104,C59,'2-Calcul des Salaires'!J5:J104)) | G59: =IF(C59="","",SUMIF('2-Calcul des Salaires'!D5:D104,C59,'2-Calcul des Salaires'!O5:O104)) | H59: =IF(C59="","",SUMIF('2-Calcul des Salaires'!D5:D104,C59,'2-Calcul des Salaires'!Q5:Q104)-SUMIF('2-Calcul des Salaires'!D5:D104,C59,'2-Calcul des Salaires'!O5:O104)) | I59: =IF(C59="","",SUMIF('2-Calcul des Salaires'!D5:D104,C59,'2-Calcul des Salaires'!Q5:Q104)) | K59: =IF(OR(F59="",J59=""),"",IFERROR(F59/J59,0)) | L59: =IF(OR(E59="",I59=""),"",IFERROR(I59/E59,0))
B60: =IF(C60="","MS"&TEXT(COUNTA($C$5:C60),"000")) | E60: =IF(C60="","",COUNTIF('2-Calcul des Salaires'!D5:D104,C60)) | F60: =IF(C60="","",SUMIF('2-Calcul des Salaires'!D5:D104,C60,'2-Calcul des Salaires'!J5:J104)) | G60: =IF(C60="","",SUMIF('2-Calcul des Salaires'!D5:D104,C60,'2-Calcul des Salaires'!O5:O104)) | H60: =IF(C60="","",SUMIF('2-Calcul des Salaires'!D5:D104,C60,'2-Calcul des Salaires'!Q5:Q104)-SUMIF('2-Calcul des Salaires'!D5:D104,C60,'2-Calcul des Salaires'!O5:O104)) | I60: =IF(C60="","",SUMIF('2-Calcul des Salaires'!D5:D104,C60,'2-Calcul des Salaires'!Q5:Q104)) | K60: =IF(OR(F60="",J60=""),"",IFERROR(F60/J60,0)) | L60: =IF(OR(E60="",I60=""),"",IFERROR(I60/E60,0))
B61: =IF(C61="","MS"&TEXT(COUNTA($C$5:C61),"000")) | E61: =IF(C61="","",COUNTIF('2-Calcul des Salaires'!D5:D104,C61)) | F61: =IF(C61="","",SUMIF('2-Calcul des Salaires'!D5:D104,C61,'2-Calcul des Salaires'!J5:J104)) | G61: =IF(C61="","",SUMIF('2-Calcul des Salaires'!D5:D104,C61,'2-Calcul des Salaires'!O5:O104)) | H61: =IF(C61="","",SUMIF('2-Calcul des Salaires'!D5:D104,C61,'2-Calcul des Salaires'!Q5:Q104)-SUMIF('2-Calcul des Salaires'!D5:D104,C61,'2-Calcul des Salaires'!O5:O104)) | I61: =IF(C61="","",SUMIF('2-Calcul des Salaires'!D5:D104,C61,'2-Calcul des Salaires'!Q5:Q104)) | K61: =IF(OR(F61="",J61=""),"",IFERROR(F61/J61,0)) | L61: =IF(OR(E61="",I61=""),"",IFERROR(I61/E61,0))
B62: =IF(C62="","MS"&TEXT(COUNTA($C$5:C62),"000")) | E62: =IF(C62="","",COUNTIF('2-Calcul des Salaires'!D5:D104,C62)) | F62: =IF(C62="","",SUMIF('2-Calcul des Salaires'!D5:D104,C62,'2-Calcul des Salaires'!J5:J104)) | G62: =IF(C62="","",SUMIF('2-Calcul des Salaires'!D5:D104,C62,'2-Calcul des Salaires'!O5:O104)) | H62: =IF(C62="","",SUMIF('2-Calcul des Salaires'!D5:D104,C62,'2-Calcul des Salaires'!Q5:Q104)-SUMIF('2-Calcul des Salaires'!D5:D104,C62,'2-Calcul des Salaires'!O5:O104)) | I62: =IF(C62="","",SUMIF('2-Calcul des Salaires'!D5:D104,C62,'2-Calcul des Salaires'!Q5:Q104)) | K62: =IF(OR(F62="",J62=""),"",IFERROR(F62/J62,0)) | L62: =IF(OR(E62="",I62=""),"",IFERROR(I62/E62,0))
B63: =IF(C63="","MS"&TEXT(COUNTA($C$5:C63),"000")) | E63: =IF(C63="","",COUNTIF('2-Calcul des Salaires'!D5:D104,C63)) | F63: =IF(C63="","",SUMIF('2-Calcul des Salaires'!D5:D104,C63,'2-Calcul des Salaires'!J5:J104)) | G63: =IF(C63="","",SUMIF('2-Calcul des Salaires'!D5:D104,C63,'2-Calcul des Salaires'!O5:O104)) | H63: =IF(C63="","",SUMIF('2-Calcul des Salaires'!D5:D104,C63,'2-Calcul des Salaires'!Q5:Q104)-SUMIF('2-Calcul des Salaires'!D5:D104,C63,'2-Calcul des Salaires'!O5:O104)) | I63: =IF(C63="","",SUMIF('2-Calcul des Salaires'!D5:D104,C63,'2-Calcul des Salaires'!Q5:Q104)) | K63: =IF(OR(F63="",J63=""),"",IFERROR(F63/J63,0)) | L63: =IF(OR(E63="",I63=""),"",IFERROR(I63/E63,0))
B64: =IF(C64="","MS"&TEXT(COUNTA($C$5:C64),"000")) | E64: =IF(C64="","",COUNTIF('2-Calcul des Salaires'!D5:D104,C64)) | F64: =IF(C64="","",SUMIF('2-Calcul des Salaires'!D5:D104,C64,'2-Calcul des Salaires'!J5:J104)) | G64: =IF(C64="","",SUMIF('2-Calcul des Salaires'!D5:D104,C64,'2-Calcul des Salaires'!O5:O104)) | H64: =IF(C64="","",SUMIF('2-Calcul des Salaires'!D5:D104,C64,'2-Calcul des Salaires'!Q5:Q104)-SUMIF('2-Calcul des Salaires'!D5:D104,C64,'2-Calcul des Salaires'!O5:O104)) | I64: =IF(C64="","",SUMIF('2-Calcul des Salaires'!D5:D104,C64,'2-Calcul des Salaires'!Q5:Q104)) | K64: =IF(OR(F64="",J64=""),"",IFERROR(F64/J64,0)) | L64: =IF(OR(E64="",I64=""),"",IFERROR(I64/E64,0))
B65: =IF(C65="","MS"&TEXT(COUNTA($C$5:C65),"000")) | E65: =IF(C65="","",COUNTIF('2-Calcul des Salaires'!D5:D104,C65)) | F65: =IF(C65="","",SUMIF('2-Calcul des Salaires'!D5:D104,C65,'2-Calcul des Salaires'!J5:J104)) | G65: =IF(C65="","",SUMIF('2-Calcul des Salaires'!D5:D104,C65,'2-Calcul des Salaires'!O5:O104)) | H65: =IF(C65="","",SUMIF('2-Calcul des Salaires'!D5:D104,C65,'2-Calcul des Salaires'!Q5:Q104)-SUMIF('2-Calcul des Salaires'!D5:D104,C65,'2-Calcul des Salaires'!O5:O104)) | I65: =IF(C65="","",SUMIF('2-Calcul des Salaires'!D5:D104,C65,'2-Calcul des Salaires'!Q5:Q104)) | K65: =IF(OR(F65="",J65=""),"",IFERROR(F65/J65,0)) | L65: =IF(OR(E65="",I65=""),"",IFERROR(I65/E65,0))
B66: =IF(C66="","MS"&TEXT(COUNTA($C$5:C66),"000")) | E66: =IF(C66="","",COUNTIF('2-Calcul des Salaires'!D5:D104,C66)) | F66: =IF(C66="","",SUMIF('2-Calcul des Salaires'!D5:D104,C66,'2-Calcul des Salaires'!J5:J104)) | G66: =IF(C66="","",SUMIF('2-Calcul des Salaires'!D5:D104,C66,'2-Calcul des Salaires'!O5:O104)) | H66: =IF(C66="","",SUMIF('2-Calcul des Salaires'!D5:D104,C66,'2-Calcul des Salaires'!Q5:Q104)-SUMIF('2-Calcul des Salaires'!D5:D104,C66,'2-Calcul des Salaires'!O5:O104)) | I66: =IF(C66="","",SUMIF('2-Calcul des Salaires'!D5:D104,C66,'2-Calcul des Salaires'!Q5:Q104)) | K66: =IF(OR(F66="",J66=""),"",IFERROR(F66/J66,0)) | L66: =IF(OR(E66="",I66=""),"",IFERROR(I66/E66,0))
B67: =IF(C67="","MS"&TEXT(COUNTA($C$5:C67),"000")) | E67: =IF(C67="","",COUNTIF('2-Calcul des Salaires'!D5:D104,C67)) | F67: =IF(C67="","",SUMIF('2-Calcul des Salaires'!D5:D104,C67,'2-Calcul des Salaires'!J5:J104)) | G67: =IF(C67="","",SUMIF('2-Calcul des Salaires'!D5:D104,C67,'2-Calcul des Salaires'!O5:O104)) | H67: =IF(C67="","",SUMIF('2-Calcul des Salaires'!D5:D104,C67,'2-Calcul des Salaires'!Q5:Q104)-SUMIF('2-Calcul des Salaires'!D5:D104,C67,'2-Calcul des Salaires'!O5:O104)) | I67: =IF(C67="","",SUMIF('2-Calcul des Salaires'!D5:D104,C67,'2-Calcul des Salaires'!Q5:Q104)) | K67: =IF(OR(F67="",J67=""),"",IFERROR(F67/J67,0)) | L67: =IF(OR(E67="",I67=""),"",IFERROR(I67/E67,0))
B68: =IF(C68="","MS"&TEXT(COUNTA($C$5:C68),"000")) | E68: =IF(C68="","",COUNTIF('2-Calcul des Salaires'!D5:D104,C68)) | F68: =IF(C68="","",SUMIF('2-Calcul des Salaires'!D5:D104,C68,'2-Calcul des Salaires'!J5:J104)) | G68: =IF(C68="","",SUMIF('2-Calcul des Salaires'!D5:D104,C68,'2-Calcul des Salaires'!O5:O104)) | H68: =IF(C68="","",SUMIF('2-Calcul des Salaires'!D5:D104,C68,'2-Calcul des Salaires'!Q5:Q104)-SUMIF('2-Calcul des Salaires'!D5:D104,C68,'2-Calcul des Salaires'!O5:O104)) | I68: =IF(C68="","",SUMIF('2-Calcul des Salaires'!D5:D104,C68,'2-Calcul des Salaires'!Q5:Q104)) | K68: =IF(OR(F68="",J68=""),"",IFERROR(F68/J68,0)) | L68: =IF(OR(E68="",I68=""),"",IFERROR(I68/E68,0))
B69: =IF(C69="","MS"&TEXT(COUNTA($C$5:C69),"000")) | E69: =IF(C69="","",COUNTIF('2-Calcul des Salaires'!D5:D104,C69)) | F69: =IF(C69="","",SUMIF('2-Calcul des Salaires'!D5:D104,C69,'2-Calcul des Salaires'!J5:J104)) | G69: =IF(C69="","",SUMIF('2-Calcul des Salaires'!D5:D104,C69,'2-Calcul des Salaires'!O5:O104)) | H69: =IF(C69="","",SUMIF('2-Calcul des Salaires'!D5:D104,C69,'2-Calcul des Salaires'!Q5:Q104)-SUMIF('2-Calcul des Salaires'!D5:D104,C69,'2-Calcul des Salaires'!O5:O104)) | I69: =IF(C69="","",SUMIF('2-Calcul des Salaires'!D5:D104,C69,'2-Calcul des Salaires'!Q5:Q104)) | K69: =IF(OR(F69="",J69=""),"",IFERROR(F69/J69,0)) | L69: =IF(OR(E69="",I69=""),"",IFERROR(I69/E69,0))
B70: =IF(C70="","MS"&TEXT(COUNTA($C$5:C70),"000")) | E70: =IF(C70="","",COUNTIF('2-Calcul des Salaires'!D5:D104,C70)) | F70: =IF(C70="","",SUMIF('2-Calcul des Salaires'!D5:D104,C70,'2-Calcul des Salaires'!J5:J104)) | G70: =IF(C70="","",SUMIF('2-Calcul des Salaires'!D5:D104,C70,'2-Calcul des Salaires'!O5:O104)) | H70: =IF(C70="","",SUMIF('2-Calcul des Salaires'!D5:D104,C70,'2-Calcul des Salaires'!Q5:Q104)-SUMIF('2-Calcul des Salaires'!D5:D104,C70,'2-Calcul des Salaires'!O5:O104)) | I70: =IF(C70="","",SUMIF('2-Calcul des Salaires'!D5:D104,C70,'2-Calcul des Salaires'!Q5:Q104)) | K70: =IF(OR(F70="",J70=""),"",IFERROR(F70/J70,0)) | L70: =IF(OR(E70="",I70=""),"",IFERROR(I70/E70,0))
B71: =IF(C71="","MS"&TEXT(COUNTA($C$5:C71),"000")) | E71: =IF(C71="","",COUNTIF('2-Calcul des Salaires'!D5:D104,C71)) | F71: =IF(C71="","",SUMIF('2-Calcul des Salaires'!D5:D104,C71,'2-Calcul des Salaires'!J5:J104)) | G71: =IF(C71="","",SUMIF('2-Calcul des Salaires'!D5:D104,C71,'2-Calcul des Salaires'!O5:O104)) | H71: =IF(C71="","",SUMIF('2-Calcul des Salaires'!D5:D104,C71,'2-Calcul des Salaires'!Q5:Q104)-SUMIF('2-Calcul des Salaires'!D5:D104,C71,'2-Calcul des Salaires'!O5:O104)) | I71: =IF(C71="","",SUMIF('2-Calcul des Salaires'!D5:D104,C71,'2-Calcul des Salaires'!Q5:Q104)) | K71: =IF(OR(F71="",J71=""),"",IFERROR(F71/J71,0)) | L71: =IF(OR(E71="",I71=""),"",IFERROR(I71/E71,0))
B72: =IF(C72="","MS"&TEXT(COUNTA($C$5:C72),"000")) | E72: =IF(C72="","",COUNTIF('2-Calcul des Salaires'!D5:D104,C72)) | F72: =IF(C72="","",SUMIF('2-Calcul des Salaires'!D5:D104,C72,'2-Calcul des Salaires'!J5:J104)) | G72: =IF(C72="","",SUMIF('2-Calcul des Salaires'!D5:D104,C72,'2-Calcul des Salaires'!O5:O104)) | H72: =IF(C72="","",SUMIF('2-Calcul des Salaires'!D5:D104,C72,'2-Calcul des Salaires'!Q5:Q104)-SUMIF('2-Calcul des Salaires'!D5:D104,C72,'2-Calcul des Salaires'!O5:O104)) | I72: =IF(C72="","",SUMIF('2-Calcul des Salaires'!D5:D104,C72,'2-Calcul des Salaires'!Q5:Q104)) | K72: =IF(OR(F72="",J72=""),"",IFERROR(F72/J72,0)) | L72: =IF(OR(E72="",I72=""),"",IFERROR(I72/E72,0))
B73: =IF(C73="","MS"&TEXT(COUNTA($C$5:C73),"000")) | E73: =IF(C73="","",COUNTIF('2-Calcul des Salaires'!D5:D104,C73)) | F73: =IF(C73="","",SUMIF('2-Calcul des Salaires'!D5:D104,C73,'2-Calcul des Salaires'!J5:J104)) | G73: =IF(C73="","",SUMIF('2-Calcul des Salaires'!D5:D104,C73,'2-Calcul des Salaires'!O5:O104)) | H73: =IF(C73="","",SUMIF('2-Calcul des Salaires'!D5:D104,C73,'2-Calcul des Salaires'!Q5:Q104)-SUMIF('2-Calcul des Salaires'!D5:D104,C73,'2-Calcul des Salaires'!O5:O104)) | I73: =IF(C73="","",SUMIF('2-Calcul des Salaires'!D5:D104,C73,'2-Calcul des Salaires'!Q5:Q104)) | K73: =IF(OR(F73="",J73=""),"",IFERROR(F73/J73,0)) | L73: =IF(OR(E73="",I73=""),"",IFERROR(I73/E73,0))
B74: =IF(C74="","MS"&TEXT(COUNTA($C$5:C74),"000")) | E74: =IF(C74="","",COUNTIF('2-Calcul des Salaires'!D5:D104,C74)) | F74: =IF(C74="","",SUMIF('2-Calcul des Salaires'!D5:D104,C74,'2-Calcul des Salaires'!J5:J104)) | G74: =IF(C74="","",SUMIF('2-Calcul des Salaires'!D5:D104,C74,'2-Calcul des Salaires'!O5:O104)) | H74: =IF(C74="","",SUMIF('2-Calcul des Salaires'!D5:D104,C74,'2-Calcul des Salaires'!Q5:Q104)-SUMIF('2-Calcul des Salaires'!D5:D104,C74,'2-Calcul des Salaires'!O5:O104)) | I74: =IF(C74="","",SUMIF('2-Calcul des Salaires'!D5:D104,C74,'2-Calcul des Salaires'!Q5:Q104)) | K74: =IF(OR(F74="",J74=""),"",IFERROR(F74/J74,0)) | L74: =IF(OR(E74="",I74=""),"",IFERROR(I74/E74,0))
B75: =IF(C75="","MS"&TEXT(COUNTA($C$5:C75),"000")) | E75: =IF(C75="","",COUNTIF('2-Calcul des Salaires'!D5:D104,C75)) | F75: =IF(C75="","",SUMIF('2-Calcul des Salaires'!D5:D104,C75,'2-Calcul des Salaires'!J5:J104)) | G75: =IF(C75="","",SUMIF('2-Calcul des Salaires'!D5:D104,C75,'2-Calcul des Salaires'!O5:O104)) | H75: =IF(C75="","",SUMIF('2-Calcul des Salaires'!D5:D104,C75,'2-Calcul des Salaires'!Q5:Q104)-SUMIF('2-Calcul des Salaires'!D5:D104,C75,'2-Calcul des Salaires'!O5:O104)) | I75: =IF(C75="","",SUMIF('2-Calcul des Salaires'!D5:D104,C75,'2-Calcul des Salaires'!Q5:Q104)) | K75: =IF(OR(F75="",J75=""),"",IFERROR(F75/J75,0)) | L75: =IF(OR(E75="",I75=""),"",IFERROR(I75/E75,0))
B76: =IF(C76="","MS"&TEXT(COUNTA($C$5:C76),"000")) | E76: =IF(C76="","",COUNTIF('2-Calcul des Salaires'!D5:D104,C76)) | F76: =IF(C76="","",SUMIF('2-Calcul des Salaires'!D5:D104,C76,'2-Calcul des Salaires'!J5:J104)) | G76: =IF(C76="","",SUMIF('2-Calcul des Salaires'!D5:D104,C76,'2-Calcul des Salaires'!O5:O104)) | H76: =IF(C76="","",SUMIF('2-Calcul des Salaires'!D5:D104,C76,'2-Calcul des Salaires'!Q5:Q104)-SUMIF('2-Calcul des Salaires'!D5:D104,C76,'2-Calcul des Salaires'!O5:O104)) | I76: =IF(C76="","",SUMIF('2-Calcul des Salaires'!D5:D104,C76,'2-Calcul des Salaires'!Q5:Q104)) | K76: =IF(OR(F76="",J76=""),"",IFERROR(F76/J76,0)) | L76: =IF(OR(E76="",I76=""),"",IFERROR(I76/E76,0))
B77: =IF(C77="","MS"&TEXT(COUNTA($C$5:C77),"000")) | E77: =IF(C77="","",COUNTIF('2-Calcul des Salaires'!D5:D104,C77)) | F77: =IF(C77="","",SUMIF('2-Calcul des Salaires'!D5:D104,C77,'2-Calcul des Salaires'!J5:J104)) | G77: =IF(C77="","",SUMIF('2-Calcul des Salaires'!D5:D104,C77,'2-Calcul des Salaires'!O5:O104)) | H77: =IF(C77="","",SUMIF('2-Calcul des Salaires'!D5:D104,C77,'2-Calcul des Salaires'!Q5:Q104)-SUMIF('2-Calcul des Salaires'!D5:D104,C77,'2-Calcul des Salaires'!O5:O104)) | I77: =IF(C77="","",SUMIF('2-Calcul des Salaires'!D5:D104,C77,'2-Calcul des Salaires'!Q5:Q104)) | K77: =IF(OR(F77="",J77=""),"",IFERROR(F77/J77,0)) | L77: =IF(OR(E77="",I77=""),"",IFERROR(I77/E77,0))
B78: =IF(C78="","MS"&TEXT(COUNTA($C$5:C78),"000")) | E78: =IF(C78="","",COUNTIF('2-Calcul des Salaires'!D5:D104,C78)) | F78: =IF(C78="","",SUMIF('2-Calcul des Salaires'!D5:D104,C78,'2-Calcul des Salaires'!J5:J104)) | G78: =IF(C78="","",SUMIF('2-Calcul des Salaires'!D5:D104,C78,'2-Calcul des Salaires'!O5:O104)) | H78: =IF(C78="","",SUMIF('2-Calcul des Salaires'!D5:D104,C78,'2-Calcul des Salaires'!Q5:Q104)-SUMIF('2-Calcul des Salaires'!D5:D104,C78,'2-Calcul des Salaires'!O5:O104)) | I78: =IF(C78="","",SUMIF('2-Calcul des Salaires'!D5:D104,C78,'2-Calcul des Salaires'!Q5:Q104)) | K78: =IF(OR(F78="",J78=""),"",IFERROR(F78/J78,0)) | L78: =IF(OR(E78="",I78=""),"",IFERROR(I78/E78,0))
B79: =IF(C79="","MS"&TEXT(COUNTA($C$5:C79),"000")) | E79: =IF(C79="","",COUNTIF('2-Calcul des Salaires'!D5:D104,C79)) | F79: =IF(C79="","",SUMIF('2-Calcul des Salaires'!D5:D104,C79,'2-Calcul des Salaires'!J5:J104)) | G79: =IF(C79="","",SUMIF('2-Calcul des Salaires'!D5:D104,C79,'2-Calcul des Salaires'!O5:O104)) | H79: =IF(C79="","",SUMIF('2-Calcul des Salaires'!D5:D104,C79,'2-Calcul des Salaires'!Q5:Q104)-SUMIF('2-Calcul des Salaires'!D5:D104,C79,'2-Calcul des Salaires'!O5:O104)) | I79: =IF(C79="","",SUMIF('2-Calcul des Salaires'!D5:D104,C79,'2-Calcul des Salaires'!Q5:Q104)) | K79: =IF(OR(F79="",J79=""),"",IFERROR(F79/J79,0)) | L79: =IF(OR(E79="",I79=""),"",IFERROR(I79/E79,0))
B80: =IF(C80="","MS"&TEXT(COUNTA($C$5:C80),"000")) | E80: =IF(C80="","",COUNTIF('2-Calcul des Salaires'!D5:D104,C80)) | F80: =IF(C80="","",SUMIF('2-Calcul des Salaires'!D5:D104,C80,'2-Calcul des Salaires'!J5:J104)) | G80: =IF(C80="","",SUMIF('2-Calcul des Salaires'!D5:D104,C80,'2-Calcul des Salaires'!O5:O104)) | H80: =IF(C80="","",SUMIF('2-Calcul des Salaires'!D5:D104,C80,'2-Calcul des Salaires'!Q5:Q104)-SUMIF('2-Calcul des Salaires'!D5:D104,C80,'2-Calcul des Salaires'!O5:O104)) | I80: =IF(C80="","",SUMIF('2-Calcul des Salaires'!D5:D104,C80,'2-Calcul des Salaires'!Q5:Q104)) | K80: =IF(OR(F80="",J80=""),"",IFERROR(F80/J80,0)) | L80: =IF(OR(E80="",I80=""),"",IFERROR(I80/E80,0))
B81: =IF(C81="","MS"&TEXT(COUNTA($C$5:C81),"000")) | E81: =IF(C81="","",COUNTIF('2-Calcul des Salaires'!D5:D104,C81)) | F81: =IF(C81="","",SUMIF('2-Calcul des Salaires'!D5:D104,C81,'2-Calcul des Salaires'!J5:J104)) | G81: =IF(C81="","",SUMIF('2-Calcul des Salaires'!D5:D104,C81,'2-Calcul des Salaires'!O5:O104)) | H81: =IF(C81="","",SUMIF('2-Calcul des Salaires'!D5:D104,C81,'2-Calcul des Salaires'!Q5:Q104)-SUMIF('2-Calcul des Salaires'!D5:D104,C81,'2-Calcul des Salaires'!O5:O104)) | I81: =IF(C81="","",SUMIF('2-Calcul des Salaires'!D5:D104,C81,'2-Calcul des Salaires'!Q5:Q104)) | K81: =IF(OR(F81="",J81=""),"",IFERROR(F81/J81,0)) | L81: =IF(OR(E81="",I81=""),"",IFERROR(I81/E81,0))
B82: =IF(C82="","MS"&TEXT(COUNTA($C$5:C82),"000")) | E82: =IF(C82="","",COUNTIF('2-Calcul des Salaires'!D5:D104,C82)) | F82: =IF(C82="","",SUMIF('2-Calcul des Salaires'!D5:D104,C82,'2-Calcul des Salaires'!J5:J104)) | G82: =IF(C82="","",SUMIF('2-Calcul des Salaires'!D5:D104,C82,'2-Calcul des Salaires'!O5:O104)) | H82: =IF(C82="","",SUMIF('2-Calcul des Salaires'!D5:D104,C82,'2-Calcul des Salaires'!Q5:Q104)-SUMIF('2-Calcul des Salaires'!D5:D104,C82,'2-Calcul des Salaires'!O5:O104)) | I82: =IF(C82="","",SUMIF('2-Calcul des Salaires'!D5:D104,C82,'2-Calcul des Salaires'!Q5:Q104)) | K82: =IF(OR(F82="",J82=""),"",IFERROR(F82/J82,0)) | L82: =IF(OR(E82="",I82=""),"",IFERROR(I82/E82,0))
B83: =IF(C83="","MS"&TEXT(COUNTA($C$5:C83),"000")) | E83: =IF(C83="","",COUNTIF('2-Calcul des Salaires'!D5:D104,C83)) | F83: =IF(C83="","",SUMIF('2-Calcul des Salaires'!D5:D104,C83,'2-Calcul des Salaires'!J5:J104)) | G83: =IF(C83="","",SUMIF('2-Calcul des Salaires'!D5:D104,C83,'2-Calcul des Salaires'!O5:O104)) | H83: =IF(C83="","",SUMIF('2-Calcul des Salaires'!D5:D104,C83,'2-Calcul des Salaires'!Q5:Q104)-SUMIF('2-Calcul des Salaires'!D5:D104,C83,'2-Calcul des Salaires'!O5:O104)) | I83: =IF(C83="","",SUMIF('2-Calcul des Salaires'!D5:D104,C83,'2-Calcul des Salaires'!Q5:Q104)) | K83: =IF(OR(F83="",J83=""),"",IFERROR(F83/J83,0)) | L83: =IF(OR(E83="",I83=""),"",IFERROR(I83/E83,0))
B84: =IF(C84="","MS"&TEXT(COUNTA($C$5:C84),"000")) | E84: =IF(C84="","",COUNTIF('2-Calcul des Salaires'!D5:D104,C84)) | F84: =IF(C84="","",SUMIF('2-Calcul des Salaires'!D5:D104,C84,'2-Calcul des Salaires'!J5:J104)) | G84: =IF(C84="","",SUMIF('2-Calcul des Salaires'!D5:D104,C84,'2-Calcul des Salaires'!O5:O104)) | H84: =IF(C84="","",SUMIF('2-Calcul des Salaires'!D5:D104,C84,'2-Calcul des Salaires'!Q5:Q104)-SUMIF('2-Calcul des Salaires'!D5:D104,C84,'2-Calcul des Salaires'!O5:O104)) | I84: =IF(C84="","",SUMIF('2-Calcul des Salaires'!D5:D104,C84,'2-Calcul des Salaires'!Q5:Q104)) | K84: =IF(OR(F84="",J84=""),"",IFERROR(F84/J84,0)) | L84: =IF(OR(E84="",I84=""),"",IFERROR(I84/E84,0))
B85: =IF(C85="","MS"&TEXT(COUNTA($C$5:C85),"000")) | E85: =IF(C85="","",COUNTIF('2-Calcul des Salaires'!D5:D104,C85)) | F85: =IF(C85="","",SUMIF('2-Calcul des Salaires'!D5:D104,C85,'2-Calcul des Salaires'!J5:J104)) | G85: =IF(C85="","",SUMIF('2-Calcul des Salaires'!D5:D104,C85,'2-Calcul des Salaires'!O5:O104)) | H85: =IF(C85="","",SUMIF('2-Calcul des Salaires'!D5:D104,C85,'2-Calcul des Salaires'!Q5:Q104)-SUMIF('2-Calcul des Salaires'!D5:D104,C85,'2-Calcul des Salaires'!O5:O104)) | I85: =IF(C85="","",SUMIF('2-Calcul des Salaires'!D5:D104,C85,'2-Calcul des Salaires'!Q5:Q104)) | K85: =IF(OR(F85="",J85=""),"",IFERROR(F85/J85,0)) | L85: =IF(OR(E85="",I85=""),"",IFERROR(I85/E85,0))
B86: =IF(C86="","MS"&TEXT(COUNTA($C$5:C86),"000")) | E86: =IF(C86="","",COUNTIF('2-Calcul des Salaires'!D5:D104,C86)) | F86: =IF(C86="","",SUMIF('2-Calcul des Salaires'!D5:D104,C86,'2-Calcul des Salaires'!J5:J104)) | G86: =IF(C86="","",SUMIF('2-Calcul des Salaires'!D5:D104,C86,'2-Calcul des Salaires'!O5:O104)) | H86: =IF(C86="","",SUMIF('2-Calcul des Salaires'!D5:D104,C86,'2-Calcul des Salaires'!Q5:Q104)-SUMIF('2-Calcul des Salaires'!D5:D104,C86,'2-Calcul des Salaires'!O5:O104)) | I86: =IF(C86="","",SUMIF('2-Calcul des Salaires'!D5:D104,C86,'2-Calcul des Salaires'!Q5:Q104)) | K86: =IF(OR(F86="",J86=""),"",IFERROR(F86/J86,0)) | L86: =IF(OR(E86="",I86=""),"",IFERROR(I86/E86,0))
B87: =IF(C87="","MS"&TEXT(COUNTA($C$5:C87),"000")) | E87: =IF(C87="","",COUNTIF('2-Calcul des Salaires'!D5:D104,C87)) | F87: =IF(C87="","",SUMIF('2-Calcul des Salaires'!D5:D104,C87,'2-Calcul des Salaires'!J5:J104)) | G87: =IF(C87="","",SUMIF('2-Calcul des Salaires'!D5:D104,C87,'2-Calcul des Salaires'!O5:O104)) | H87: =IF(C87="","",SUMIF('2-Calcul des Salaires'!D5:D104,C87,'2-Calcul des Salaires'!Q5:Q104)-SUMIF('2-Calcul des Salaires'!D5:D104,C87,'2-Calcul des Salaires'!O5:O104)) | I87: =IF(C87="","",SUMIF('2-Calcul des Salaires'!D5:D104,C87,'2-Calcul des Salaires'!Q5:Q104)) | K87: =IF(OR(F87="",J87=""),"",IFERROR(F87/J87,0)) | L87: =IF(OR(E87="",I87=""),"",IFERROR(I87/E87,0))
B88: =IF(C88="","MS"&TEXT(COUNTA($C$5:C88),"000")) | E88: =IF(C88="","",COUNTIF('2-Calcul des Salaires'!D5:D104,C88)) | F88: =IF(C88="","",SUMIF('2-Calcul des Salaires'!D5:D104,C88,'2-Calcul des Salaires'!J5:J104)) | G88: =IF(C88="","",SUMIF('2-Calcul des Salaires'!D5:D104,C88,'2-Calcul des Salaires'!O5:O104)) | H88: =IF(C88="","",SUMIF('2-Calcul des Salaires'!D5:D104,C88,'2-Calcul des Salaires'!Q5:Q104)-SUMIF('2-Calcul des Salaires'!D5:D104,C88,'2-Calcul des Salaires'!O5:O104)) | I88: =IF(C88="","",SUMIF('2-Calcul des Salaires'!D5:D104,C88,'2-Calcul des Salaires'!Q5:Q104)) | K88: =IF(OR(F88="",J88=""),"",IFERROR(F88/J88,0)) | L88: =IF(OR(E88="",I88=""),"",IFERROR(I88/E88,0))
B89: =IF(C89="","MS"&TEXT(COUNTA($C$5:C89),"000")) | E89: =IF(C89="","",COUNTIF('2-Calcul des Salaires'!D5:D104,C89)) | F89: =IF(C89="","",SUMIF('2-Calcul des Salaires'!D5:D104,C89,'2-Calcul des Salaires'!J5:J104)) | G89: =IF(C89="","",SUMIF('2-Calcul des Salaires'!D5:D104,C89,'2-Calcul des Salaires'!O5:O104)) | H89: =IF(C89="","",SUMIF('2-Calcul des Salaires'!D5:D104,C89,'2-Calcul des Salaires'!Q5:Q104)-SUMIF('2-Calcul des Salaires'!D5:D104,C89,'2-Calcul des Salaires'!O5:O104)) | I89: =IF(C89="","",SUMIF('2-Calcul des Salaires'!D5:D104,C89,'2-Calcul des Salaires'!Q5:Q104)) | K89: =IF(OR(F89="",J89=""),"",IFERROR(F89/J89,0)) | L89: =IF(OR(E89="",I89=""),"",IFERROR(I89/E89,0))
B90: =IF(C90="","MS"&TEXT(COUNTA($C$5:C90),"000")) | E90: =IF(C90="","",COUNTIF('2-Calcul des Salaires'!D5:D104,C90)) | F90: =IF(C90="","",SUMIF('2-Calcul des Salaires'!D5:D104,C90,'2-Calcul des Salaires'!J5:J104)) | G90: =IF(C90="","",SUMIF('2-Calcul des Salaires'!D5:D104,C90,'2-Calcul des Salaires'!O5:O104)) | H90: =IF(C90="","",SUMIF('2-Calcul des Salaires'!D5:D104,C90,'2-Calcul des Salaires'!Q5:Q104)-SUMIF('2-Calcul des Salaires'!D5:D104,C90,'2-Calcul des Salaires'!O5:O104)) | I90: =IF(C90="","",SUMIF('2-Calcul des Salaires'!D5:D104,C90,'2-Calcul des Salaires'!Q5:Q104)) | K90: =IF(OR(F90="",J90=""),"",IFERROR(F90/J90,0)) | L90: =IF(OR(E90="",I90=""),"",IFERROR(I90/E90,0))
B91: =IF(C91="","MS"&TEXT(COUNTA($C$5:C91),"000")) | E91: =IF(C91="","",COUNTIF('2-Calcul des Salaires'!D5:D104,C91)) | F91: =IF(C91="","",SUMIF('2-Calcul des Salaires'!D5:D104,C91,'2-Calcul des Salaires'!J5:J104)) | G91: =IF(C91="","",SUMIF('2-Calcul des Salaires'!D5:D104,C91,'2-Calcul des Salaires'!O5:O104)) | H91: =IF(C91="","",SUMIF('2-Calcul des Salaires'!D5:D104,C91,'2-Calcul des Salaires'!Q5:Q104)-SUMIF('2-Calcul des Salaires'!D5:D104,C91,'2-Calcul des Salaires'!O5:O104)) | I91: =IF(C91="","",SUMIF('2-Calcul des Salaires'!D5:D104,C91,'2-Calcul des Salaires'!Q5:Q104)) | K91: =IF(OR(F91="",J91=""),"",IFERROR(F91/J91,0)) | L91: =IF(OR(E91="",I91=""),"",IFERROR(I91/E91,0))
B92: =IF(C92="","MS"&TEXT(COUNTA($C$5:C92),"000")) | E92: =IF(C92="","",COUNTIF('2-Calcul des Salaires'!D5:D104,C92)) | F92: =IF(C92="","",SUMIF('2-Calcul des Salaires'!D5:D104,C92,'2-Calcul des Salaires'!J5:J104)) | G92: =IF(C92="","",SUMIF('2-Calcul des Salaires'!D5:D104,C92,'2-Calcul des Salaires'!O5:O104)) | H92: =IF(C92="","",SUMIF('2-Calcul des Salaires'!D5:D104,C92,'2-Calcul des Salaires'!Q5:Q104)-SUMIF('2-Calcul des Salaires'!D5:D104,C92,'2-Calcul des Salaires'!O5:O104)) | I92: =IF(C92="","",SUMIF('2-Calcul des Salaires'!D5:D104,C92,'2-Calcul des Salaires'!Q5:Q104)) | K92: =IF(OR(F92="",J92=""),"",IFERROR(F92/J92,0)) | L92: =IF(OR(E92="",I92=""),"",IFERROR(I92/E92,0))
B93: =IF(C93="","MS"&TEXT(COUNTA($C$5:C93),"000")) | E93: =IF(C93="","",COUNTIF('2-Calcul des Salaires'!D5:D104,C93)) | F93: =IF(C93="","",SUMIF('2-Calcul des Salaires'!D5:D104,C93,'2-Calcul des Salaires'!J5:J104)) | G93: =IF(C93="","",SUMIF('2-Calcul des Salaires'!D5:D104,C93,'2-Calcul des Salaires'!O5:O104)) | H93: =IF(C93="","",SUMIF('2-Calcul des Salaires'!D5:D104,C93,'2-Calcul des Salaires'!Q5:Q104)-SUMIF('2-Calcul des Salaires'!D5:D104,C93,'2-Calcul des Salaires'!O5:O104)) | I93: =IF(C93="","",SUMIF('2-Calcul des Salaires'!D5:D104,C93,'2-Calcul des Salaires'!Q5:Q104)) | K93: =IF(OR(F93="",J93=""),"",IFERROR(F93/J93,0)) | L93: =IF(OR(E93="",I93=""),"",IFERROR(I93/E93,0))
B94: =IF(C94="","MS"&TEXT(COUNTA($C$5:C94),"000")) | E94: =IF(C94="","",COUNTIF('2-Calcul des Salaires'!D5:D104,C94)) | F94: =IF(C94="","",SUMIF('2-Calcul des Salaires'!D5:D104,C94,'2-Calcul des Salaires'!J5:J104)) | G94: =IF(C94="","",SUMIF('2-Calcul des Salaires'!D5:D104,C94,'2-Calcul des Salaires'!O5:O104)) | H94: =IF(C94="","",SUMIF('2-Calcul des Salaires'!D5:D104,C94,'2-Calcul des Salaires'!Q5:Q104)-SUMIF('2-Calcul des Salaires'!D5:D104,C94,'2-Calcul des Salaires'!O5:O104)) | I94: =IF(C94="","",SUMIF('2-Calcul des Salaires'!D5:D104,C94,'2-Calcul des Salaires'!Q5:Q104)) | K94: =IF(OR(F94="",J94=""),"",IFERROR(F94/J94,0)) | L94: =IF(OR(E94="",I94=""),"",IFERROR(I94/E94,0))
B95: =IF(C95="","MS"&TEXT(COUNTA($C$5:C95),"000")) | E95: =IF(C95="","",COUNTIF('2-Calcul des Salaires'!D5:D104,C95)) | F95: =IF(C95="","",SUMIF('2-Calcul des Salaires'!D5:D104,C95,'2-Calcul des Salaires'!J5:J104)) | G95: =IF(C95="","",SUMIF('2-Calcul des Salaires'!D5:D104,C95,'2-Calcul des Salaires'!O5:O104)) | H95: =IF(C95="","",SUMIF('2-Calcul des Salaires'!D5:D104,C95,'2-Calcul des Salaires'!Q5:Q104)-SUMIF('2-Calcul des Salaires'!D5:D104,C95,'2-Calcul des Salaires'!O5:O104)) | I95: =IF(C95="","",SUMIF('2-Calcul des Salaires'!D5:D104,C95,'2-Calcul des Salaires'!Q5:Q104)) | K95: =IF(OR(F95="",J95=""),"",IFERROR(F95/J95,0)) | L95: =IF(OR(E95="",I95=""),"",IFERROR(I95/E95,0))
B96: =IF(C96="","MS"&TEXT(COUNTA($C$5:C96),"000")) | E96: =IF(C96="","",COUNTIF('2-Calcul des Salaires'!D5:D104,C96)) | F96: =IF(C96="","",SUMIF('2-Calcul des Salaires'!D5:D104,C96,'2-Calcul des Salaires'!J5:J104)) | G96: =IF(C96="","",SUMIF('2-Calcul des Salaires'!D5:D104,C96,'2-Calcul des Salaires'!O5:O104)) | H96: =IF(C96="","",SUMIF('2-Calcul des Salaires'!D5:D104,C96,'2-Calcul des Salaires'!Q5:Q104)-SUMIF('2-Calcul des Salaires'!D5:D104,C96,'2-Calcul des Salaires'!O5:O104)) | I96: =IF(C96="","",SUMIF('2-Calcul des Salaires'!D5:D104,C96,'2-Calcul des Salaires'!Q5:Q104)) | K96: =IF(OR(F96="",J96=""),"",IFERROR(F96/J96,0)) | L96: =IF(OR(E96="",I96=""),"",IFERROR(I96/E96,0))
B97: =IF(C97="","MS"&TEXT(COUNTA($C$5:C97),"000")) | E97: =IF(C97="","",COUNTIF('2-Calcul des Salaires'!D5:D104,C97)) | F97: =IF(C97="","",SUMIF('2-Calcul des Salaires'!D5:D104,C97,'2-Calcul des Salaires'!J5:J104)) | G97: =IF(C97="","",SUMIF('2-Calcul des Salaires'!D5:D104,C97,'2-Calcul des Salaires'!O5:O104)) | H97: =IF(C97="","",SUMIF('2-Calcul des Salaires'!D5:D104,C97,'2-Calcul des Salaires'!Q5:Q104)-SUMIF('2-Calcul des Salaires'!D5:D104,C97,'2-Calcul des Salaires'!O5:O104)) | I97: =IF(C97="","",SUMIF('2-Calcul des Salaires'!D5:D104,C97,'2-Calcul des Salaires'!Q5:Q104)) | K97: =IF(OR(F97="",J97=""),"",IFERROR(F97/J97,0)) | L97: =IF(OR(E97="",I97=""),"",IFERROR(I97/E97,0))
B98: =IF(C98="","MS"&TEXT(COUNTA($C$5:C98),"000")) | E98: =IF(C98="","",COUNTIF('2-Calcul des Salaires'!D5:D104,C98)) | F98: =IF(C98="","",SUMIF('2-Calcul des Salaires'!D5:D104,C98,'2-Calcul des Salaires'!J5:J104)) | G98: =IF(C98="","",SUMIF('2-Calcul des Salaires'!D5:D104,C98,'2-Calcul des Salaires'!O5:O104)) | H98: =IF(C98="","",SUMIF('2-Calcul des Salaires'!D5:D104,C98,'2-Calcul des Salaires'!Q5:Q104)-SUMIF('2-Calcul des Salaires'!D5:D104,C98,'2-Calcul des Salaires'!O5:O104)) | I98: =IF(C98="","",SUMIF('2-Calcul des Salaires'!D5:D104,C98,'2-Calcul des Salaires'!Q5:Q104)) | K98: =IF(OR(F98="",J98=""),"",IFERROR(F98/J98,0)) | L98: =IF(OR(E98="",I98=""),"",IFERROR(I98/E98,0))
B99: =IF(C99="","MS"&TEXT(COUNTA($C$5:C99),"000")) | E99: =IF(C99="","",COUNTIF('2-Calcul des Salaires'!D5:D104,C99)) | F99: =IF(C99="","",SUMIF('2-Calcul des Salaires'!D5:D104,C99,'2-Calcul des Salaires'!J5:J104)) | G99: =IF(C99="","",SUMIF('2-Calcul des Salaires'!D5:D104,C99,'2-Calcul des Salaires'!O5:O104)) | H99: =IF(C99="","",SUMIF('2-Calcul des Salaires'!D5:D104,C99,'2-Calcul des Salaires'!Q5:Q104)-SUMIF('2-Calcul des Salaires'!D5:D104,C99,'2-Calcul des Salaires'!O5:O104)) | I99: =IF(C99="","",SUMIF('2-Calcul des Salaires'!D5:D104,C99,'2-Calcul des Salaires'!Q5:Q104)) | K99: =IF(OR(F99="",J99=""),"",IFERROR(F99/J99,0)) | L99: =IF(OR(E99="",I99=""),"",IFERROR(I99/E99,0))
B100: =IF(C100="","MS"&TEXT(COUNTA($C$5:C100),"000")) | E100: =IF(C100="","",COUNTIF('2-Calcul des Salaires'!D5:D104,C100)) | F100: =IF(C100="","",SUMIF('2-Calcul des Salaires'!D5:D104,C100,'2-Calcul des Salaires'!J5:J104)) | G100: =IF(C100="","",SUMIF('2-Calcul des Salaires'!D5:D104,C100,'2-Calcul des Salaires'!O5:O104)) | H100: =IF(C100="","",SUMIF('2-Calcul des Salaires'!D5:D104,C100,'2-Calcul des Salaires'!Q5:Q104)-SUMIF('2-Calcul des Salaires'!D5:D104,C100,'2-Calcul des Salaires'!O5:O104)) | I100: =IF(C100="","",SUMIF('2-Calcul des Salaires'!D5:D104,C100,'2-Calcul des Salaires'!Q5:Q104)) | K100: =IF(OR(F100="",J100=""),"",IFERROR(F100/J100,0)) | L100: =IF(OR(E100="",I100=""),"",IFERROR(I100/E100,0))
B101: =IF(C101="","MS"&TEXT(COUNTA($C$5:C101),"000")) | E101: =IF(C101="","",COUNTIF('2-Calcul des Salaires'!D5:D104,C101)) | F101: =IF(C101="","",SUMIF('2-Calcul des Salaires'!D5:D104,C101,'2-Calcul des Salaires'!J5:J104)) | G101: =IF(C101="","",SUMIF('2-Calcul des Salaires'!D5:D104,C101,'2-Calcul des Salaires'!O5:O104)) | H101: =IF(C101="","",SUMIF('2-Calcul des Salaires'!D5:D104,C101,'2-Calcul des Salaires'!Q5:Q104)-SUMIF('2-Calcul des Salaires'!D5:D104,C101,'2-Calcul des Salaires'!O5:O104)) | I101: =IF(C101="","",SUMIF('2-Calcul des Salaires'!D5:D104,C101,'2-Calcul des Salaires'!Q5:Q104)) | K101: =IF(OR(F101="",J101=""),"",IFERROR(F101/J101,0)) | L101: =IF(OR(E101="",I101=""),"",IFERROR(I101/E101,0))
B102: =IF(C102="","MS"&TEXT(COUNTA($C$5:C102),"000")) | E102: =IF(C102="","",COUNTIF('2-Calcul des Salaires'!D5:D104,C102)) | F102: =IF(C102="","",SUMIF('2-Calcul des Salaires'!D5:D104,C102,'2-Calcul des Salaires'!J5:J104)) | G102: =IF(C102="","",SUMIF('2-Calcul des Salaires'!D5:D104,C102,'2-Calcul des Salaires'!O5:O104)) | H102: =IF(C102="","",SUMIF('2-Calcul des Salaires'!D5:D104,C102,'2-Calcul des Salaires'!Q5:Q104)-SUMIF('2-Calcul des Salaires'!D5:D104,C102,'2-Calcul des Salaires'!O5:O104)) | I102: =IF(C102="","",SUMIF('2-Calcul des Salaires'!D5:D104,C102,'2-Calcul des Salaires'!Q5:Q104)) | K102: =IF(OR(F102="",J102=""),"",IFERROR(F102/J102,0)) | L102: =IF(OR(E102="",I102=""),"",IFERROR(I102/E102,0))
...

Sheet 13-13eme Mois
B2: REMUNERATION — 13-13eme Mois
B4: N° | C4: Matricule | D4: Nom Employé | E4: Département | F4: Année | G4: Base 13ème Mois (FCFA) | H4: Prime Fin d'Année (FCFA) | I4: Total Dû (FCFA) | J4: Statut
B5: 13M-001 | C5: EMP-001 | D5: Nganou Clarisse | E5: Ressources Humaines | F5: 2025 | G5: 850750 | H5: 100000 | I5: 950750 | J5: En attente
B6: 13M-002 | C6: EMP-002 | D6: Tchinda Armand | E6: Finance & Comptabilite | F6: 2025 | G6: 648100 | H6: 75000 | I6: 723100 | J6: En attente
B7: 13M-003 | C7: EMP-005 | D7: Diallo Moussa | E7: Cuisine & Restauration | F7: 2025 | G7: 253000 | H7: 50000 | I7: 303000 | J7: En attente
B8: =IF(C8="","13M"&TEXT(COUNTA($C$5:C8),"000")) | D8: =IF(C8="","",VLOOKUP(C8,'_Données Employés'!$B$5:$S$114,3,FALSE)) | E8: =IF(C8="","",VLOOKUP(C8,'_Données Employés'!$B$5:$S$114,10,FALSE)) | I8: =IF(F8="","",IFERROR(F8+G8,0))
B9: =IF(C9="","13M"&TEXT(COUNTA($C$5:C9),"000")) | D9: =IF(C9="","",VLOOKUP(C9,'_Données Employés'!$B$5:$S$114,3,FALSE)) | E9: =IF(C9="","",VLOOKUP(C9,'_Données Employés'!$B$5:$S$114,10,FALSE)) | I9: =IF(F9="","",IFERROR(F9+G9,0))
B10: =IF(C10="","13M"&TEXT(COUNTA($C$5:C10),"000")) | D10: =IF(C10="","",VLOOKUP(C10,'_Données Employés'!$B$5:$S$114,3,FALSE)) | E10: =IF(C10="","",VLOOKUP(C10,'_Données Employés'!$B$5:$S$114,10,FALSE)) | I10: =IF(F10="","",IFERROR(F10+G10,0))
B11: =IF(C11="","13M"&TEXT(COUNTA($C$5:C11),"000")) | D11: =IF(C11="","",VLOOKUP(C11,'_Données Employés'!$B$5:$S$114,3,FALSE)) | E11: =IF(C11="","",VLOOKUP(C11,'_Données Employés'!$B$5:$S$114,10,FALSE)) | I11: =IF(F11="","",IFERROR(F11+G11,0))
B12: =IF(C12="","13M"&TEXT(COUNTA($C$5:C12),"000")) | D12: =IF(C12="","",VLOOKUP(C12,'_Données Employés'!$B$5:$S$114,3,FALSE)) | E12: =IF(C12="","",VLOOKUP(C12,'_Données Employés'!$B$5:$S$114,10,FALSE)) | I12: =IF(F12="","",IFERROR(F12+G12,0))
B13: =IF(C13="","13M"&TEXT(COUNTA($C$5:C13),"000")) | D13: =IF(C13="","",VLOOKUP(C13,'_Données Employés'!$B$5:$S$114,3,FALSE)) | E13: =IF(C13="","",VLOOKUP(C13,'_Données Employés'!$B$5:$S$114,10,FALSE)) | I13: =IF(F13="","",IFERROR(F13+G13,0))
B14: =IF(C14="","13M"&TEXT(COUNTA($C$5:C14),"000")) | D14: =IF(C14="","",VLOOKUP(C14,'_Données Employés'!$B$5:$S$114,3,FALSE)) | E14: =IF(C14="","",VLOOKUP(C14,'_Données Employés'!$B$5:$S$114,10,FALSE)) | I14: =IF(F14="","",IFERROR(F14+G14,0))
B15: =IF(C15="","13M"&TEXT(COUNTA($C$5:C15),"000")) | D15: =IF(C15="","",VLOOKUP(C15,'_Données Employés'!$B$5:$S$114,3,FALSE)) | E15: =IF(C15="","",VLOOKUP(C15,'_Données Employés'!$B$5:$S$114,10,FALSE)) | I15: =IF(F15="","",IFERROR(F15+G15,0))
B16: =IF(C16="","13M"&TEXT(COUNTA($C$5:C16),"000")) | D16: =IF(C16="","",VLOOKUP(C16,'_Données Employés'!$B$5:$S$114,3,FALSE)) | E16: =IF(C16="","",VLOOKUP(C16,'_Données Employés'!$B$5:$S$114,10,FALSE)) | I16: =IF(F16="","",IFERROR(F16+G16,0))
B17: =IF(C17="","13M"&TEXT(COUNTA($C$5:C17),"000")) | D17: =IF(C17="","",VLOOKUP(C17,'_Données Employés'!$B$5:$S$114,3,FALSE)) | E17: =IF(C17="","",VLOOKUP(C17,'_Données Employés'!$B$5:$S$114,10,FALSE)) | I17: =IF(F17="","",IFERROR(F17+G17,0))
B18: =IF(C18="","13M"&TEXT(COUNTA($C$5:C18),"000")) | D18: =IF(C18="","",VLOOKUP(C18,'_Données Employés'!$B$5:$S$114,3,FALSE)) | E18: =IF(C18="","",VLOOKUP(C18,'_Données Employés'!$B$5:$S$114,10,FALSE)) | I18: =IF(F18="","",IFERROR(F18+G18,0))
B19: =IF(C19="","13M"&TEXT(COUNTA($C$5:C19),"000")) | D19: =IF(C19="","",VLOOKUP(C19,'_Données Employés'!$B$5:$S$114,3,FALSE)) | E19: =IF(C19="","",VLOOKUP(C19,'_Données Employés'!$B$5:$S$114,10,FALSE)) | I19: =IF(F19="","",IFERROR(F19+G19,0))
... B104: =IF(C104="","13M"&TEXT(COUNTA($C$5:C104),"000")) | D104: =IF(C104="","",VLOOKUP(C104,'_Données Employés'!$B$5:$S$114,3,FALSE)) | E104: =IF(C104="","",VLOOKUP(C104,'_Données Employés'!$B$5:$S$114,10,FALSE)) | I104: =IF(F104="","",IFERROR(F104+G104,0))
B107: KPI Total 13ème mois (FCFA) | C107: KPI Bénéficiaires
B108: =SUM(H5:H104) | C108: =COUNTA(C5:C104)

Sheet 14-Variables Pourboires
B2: REMUNERATION — 14-Variables Pourboires
B4: N° | C4: Matricule | D4: Nom Employé | E4: Service | F4: Mois | G4: CA Service (FCFA) | H4: Taux Distribution (%) | I4: Pourboire Individuel (FCFA) | J4: Commission (FCFA) | K4: Variable Total (FCFA) | L4: Statut
B5: VAR-001 | C5: EMP-004 | D5: Ouedraogo Ibrahim | E5: Reception | F5: Juin | G5: 5000000 | H5: 2 | I5: 100000 | J5: 0 | K5: 100000 | L5: Approuve
B6: VAR-002 | C6: EMP-010 | D6: Atangana Simon | E6: Bar | F6: Juin | G6: 3000000 | H6: 3 | I6: 90000 | J6: 0 | K6: 90000 | L6: Approuve
B7: VAR-003 | C7: EMP-006 | D7: Ngassa Brigitte | E7: Restaurant | F7: Juin | G7: 4000000 | H7: 1.5 | I7: 60000 | J7: 0 | K7: 60000 | L7: Approuve
B8: =IF(C8="","VAR"&TEXT(COUNTA($C$5:C8),"000")) | D8: =IF(C8="","",VLOOKUP(C8,'_Données Employés'!$B$5:$S$114,3,FALSE)) | I8: =IF(OR(F8="",G8=""),"",IFERROR(F8*G8/100,0)) | K8: =IF(H8="","",IFERROR(H8+I8,0))
B9: =IF(C9="","VAR"&TEXT(COUNTA($C$5:C9),"000")) | D9: =IF(C9="","",VLOOKUP(C9,'_Données Employés'!$B$5:$S$114,3,FALSE)) | I9: =IF(OR(F9="",G9=""),"",IFERROR(F9*G9/100,0)) | K9: =IF(H9="","",IFERROR(H9+I9,0))
