Workbook

Sheet 1-Tableau de Bord
B2: DOMAINE 20 — PILOTAGE & REPORTING RH
B3: TABLEAU DE BORD — Vue synthetique de tous les indicateurs du domaine (mis a jour automatiquement)
B5: Indicateurs TdB Global | E5: Rapports mensuels | H5: KPI definis | K5: Postes budgetaires
B6: =COUNTIF('2-TdB RH Global'!B5:B104,"<>") | E6: =COUNTIF('3-Rapports Mensuels RH'!B5:B104,"<>") | H6: =COUNTIF('4-KPI RH'!B5:B104,"<>") | K6: =COUNTIF('5-Budget RH Annuel'!B5:B104,"<>")
B9: Activites plan charge | E9: Indicateurs DG | H9: Benchmarking | K9: Plans d'action
B10: =COUNTIF('6-Plan de Charge RH'!B5:B104,"<>") | E10: =COUNTIF('7-Reporting Direction Gen.'!B5:B104,"<>") | H10: =COUNTIF('8-Benchmarking RH Hotelier'!B5:B104,"<>") | K10: =COUNTIF('9-Plans d''Action RH'!B5:B104,"<>")
B13: Indicateurs bilan social | E13: Axes strategiques | H13: Budget total 2025 (M FCFA) | K13: Mois suivis KPI
B14: =COUNTIF('10-Bilan Social'!B5:B104,"<>") | E14: =COUNTIF('11-Feuille de Route Strat. RH'!B5:B104,"<>") | H14: =IFERROR(SUM('5-Budget RH Annuel'!E5:E104)/1000000,0) | K14: =COUNTIF('12-Suivi KPI RH Mensuel'!B5:B104,"<>")
B18: BUDGET PAR CATEGORIE & PLANS D'ACTION PAR STATUT
B19: Categorie Budget | C19: Budget (FCFA)
B20: Salaires & primes | C20: =SUMIF('5-Budget RH Annuel'!D5:D104,"Salaires & primes",'5-Budget RH Annuel'!E5:E104)
B21: Charges sociales | C21: =SUMIF('5-Budget RH Annuel'!D5:D104,"Charges sociales",'5-Budget RH Annuel'!E5:E104)
B22: Formation & developpement | C22: =SUMIF('5-Budget RH Annuel'!D5:D104,"Formation & developpement",'5-Budget RH Annuel'!E5:E104)
B23: Recrutement | C23: =SUMIF('5-Budget RH Annuel'!D5:D104,"Recrutement",'5-Budget RH Annuel'!E5:E104)
B24: Santé & sécurité | C24: =SUMIF('5-Budget RH Annuel'!D5:D104,"Santé & sécurité",'5-Budget RH Annuel'!E5:E104)
B25: Fonctionnement RH | C25: =SUMIF('5-Budget RH Annuel'!D5:D104,"Fonctionnement RH",'5-Budget RH Annuel'!E5:E104)
B26: Investissement digital | C26: =SUMIF('5-Budget RH Annuel'!D5:D104,"Investissement digital",'5-Budget RH Annuel'!E5:E104)
B27: Autre | C27: =SUMIF('5-Budget RH Annuel'!D5:D104,"Autre",'5-Budget RH Annuel'!E5:E104)
H29: Statut Plan d'Action | I29: Nombre
H30: En cours | I30: =COUNTIF('9-Plans d''Action RH'!K5:K104,"En cours")
H31: Terminee | I31: =COUNTIF('9-Plans d''Action RH'!K5:K104,"Terminee")
H32: Planifiee | I32: =COUNTIF('9-Plans d''Action RH'!K5:K104,"Planifiee")
H33: Reportee | I33: =COUNTIF('9-Plans d''Action RH'!K5:K104,"Reportee")
H34: Annulee | I34: =COUNTIF('9-Plans d''Action RH'!K5:K104,"Annulee")

Sheet _Données Employés
A1: Matricule | B1: Nom | C1: Prénom | D1: Département | E1: Poste | F1: Salaire Brut
A2: EMP-001 | B2: Nganou | C2: Clarisse | D2: Cuisine & Restauration | E2: Chef | F2: 450000
A3: EMP-002 | B3: Tagne | C3: René | D3: Réception & Front Office | E3: Réceptionniste | F3: 165000
A4: EMP-003 | B4: Fotso | C4: Camille | D4: Cuisine & Restauration | E4: Cuisinier | F4: 180000
A5: EMP-004 | B5: Tchinda | C5: Arlette | D5: Service Client | E5: Assistante RH | F5: 200000
A6: EMP-005 | B6: Ngansop | C6: Sylvie | D6: Finance & Comptabilité | E6: Comptable senior | F6: 250000
A7: EMP-006 | B7: Fokam | C7: Eric | D7: Réception & Front Office | E7: Chef Réception | F7: 280000
A8: EMP-007 | B8: Tchouankou | C8: Paul | D8: Étage & Housekeeping | E8: Chef Étage | F8: 230000
A9: EMP-008 | B9: Awa | C9: Fatou | D9: Commercial | E9: Agent Commercial | F9: 155000
A10: EMP-009 | B10: Bouba | C10: Ahmed | D10: Cuisine & Restauration | E10: Sous-Chef | F10: 210000
A11: EMP-010 | B11: Kamga | C11: Patrice | D11: Sécurité | E11: Chef Sécurité | F11: 210000
A12: EMP-011 | B12: Ngo | C12: Delphine | D12: Marketing & Communication | E12: Chef Marketing | F12: 300000
A13: EMP-012 | B13: Tamo | C13: Elvis | D13: Logistique & Approvisionnement | E13: Chef Logistique | F13: 240000
... A15: EMP-014 | B15: Kane | C15: Adama | D15: Direction Générale | E15: DAF | F15: 350000

Sheet _Lists
B1: departement | C1: poste_hotel | D1: frequence_reporting | E1: type_indicateur | F1: sens_indicateur | G1: categorie_budget | H1: statut_budget | I1: type_rapport | J1: destinataire_rapport | K1: niveau_urgence | L1: statut_objectif | M1: statut_plan_action | N1: source_donnee_bilan | O1: echelle_satisfaction | P1: periode_analyse | Q1: statut_kpi | R1: mois
B2: Direction Générale | C2: DG | D2: Hebdomadaire | E2: Quantitatif | F2: Hausse favorable | G2: Salaires & primes | H2: Vote | I2: Activite mensuelle | J2: DG | K2: Critique | L2: Non commence | M2: Planifiee | N2: SIRH | O2: Tres insatisfait | P2: Mensuel | Q2: Vert (OK) | R2: Janvier
B3: Service Client | C3: DRH | D3: Bimensuelle | E3: Qualitatif | F3: Baisse favorable | G3: Charges sociales | H3: En execution | I3: Bilan trimestriel | J3: Comite de direction | K3: Eleve | L3: En cours | M3: En cours | N3: Paie | O3: Insatisfait | P3: Trimestriel | Q3: Orange (Attention) | R3: Fevrier
B4: Finance & Comptabilité | C4: Assistante RH | D4: Mensuel | E4: Financier | F4: Cible a atteindre | G4: Formation & developpement | H4: Cloture | I4: Bilan social annuel | J4: DRH | K4: Moyen | L4: Atteint | M4: Terminee | N4: Comptabilite | O4: Neutre | P4: Semestriel | Q4: Rouge (Alerte) | R4: Mars
B5: Marketing & Communication | C5: DAF | D5: Trimestriel | E5: Temps | F5: Stable souhaitable | G5: Recrutement | H5: Depasse | I5: Rapport audit | J5: DAF | K5: Faible | L5: Depasse | M5: Reportee | N5: Enquetes internes | O5: Satisfait | P5: Annuel | Q5: Non disponible | R5: Avril
B6: Maintenance | C6: Comptable senior | D6: Semestriel | E6: Ratio | G6: Santé & sécurité | H6: Sous-consomme | I6: Etude speciale | J6: CSE / Representants du personnel | L6: En retard | M6: Annulee | N6: Donnees CNPS | O6: Tres satisfait | R6: Mai
B7: Commercial | C7: Chef Comptable | D7: Annuel | E7: Score | G7: Social & bien-etre | H7: Reporte | I7: Reporting DG | J7: Inspecteur du travail | L7: Abandonne | N7: Inspection du travail | R7: Juin
B8: Logistique & Approvisionnement | C8: Chef Marketing | G8: Fonctionnement RH | I8: Tableau de bord KPI | J8: Actionnaires | N8: Benchmark externe | R8: Juillet
B9: Cuisine & Restauration | C9: Chef de service IT | G9: Investissement digital | I9: Benchmark | J9: Tous les managers | N9: Enquetes satisfaction | R9: Aout
B10: Réception & Front Office | C10: Technicien IT | G10: Evenementiel RH | I10: Plan d'action | J10: Equipe RH | N10: Autre | R10: Septembre
B11: Sécurité | C11: Chef Commercial | G11: Audit & conseil | I11: Autre | J11: Autre | R11: Octobre
B12: Étage & Housekeeping | C12: Agent Commercial | G12: Autre | R12: Novembre
C13: Chef Reception | R13: Decembre
C14: Receptionniste
C15: Chef Cuisine
C16: Chef Rangement
C17: Gouvernante
C18: Femme de chambre
C19: Agent Sécurité
C20: Chauffeur
C21: Agent Entretien
C22: Plongeur
C23: Serveur
C24: Barman
C25: Laveur vaisselle
... C28: Bagagiste

Sheet 2-TdB RH Global
B2: TABLEAU DE BORD RH GLOBAL (#167)
B3: TABLEAU DYNAMIQUE — Saisissez dans la prochaine ligne jaune. Les calculs se mettent a jour automatiquement.
B4: N° | C4: Indicateur | D4: Categorie | E4: Objectif | F4: Valeur Actuelle | G4: Valeur Precedente | H4: Evolution | I4: Statut | J4: Frequence Suivi | K4: Responsable | L4: Observations
B5: TDB-001 | C5: Taux rotation global | D5: Mobilité | E5: <= 12% | F5: 0.18 | G5: 0.22 | I5: Orange (Attention) | J5: Mensuel | K5: DRH | L5: En baisse mais encore au-dessus de l'objectif
B6: TDB-002 | C6: Delai moyen embauche (j) | D6: Recrutement | E6: <= 30 | F6: 28 | G6: 35 | I6: Vert (OK) | J6: Mensuel | K6: Assistante RH | L6: ATS + IA ameliore le processus
B7: TDB-003 | C7: Cout moyen recrutement (FCFA) | D7: Recrutement | E7: <= 150000 | F7: 125000 | G7: 180000 | I7: Vert (OK) | J7: Trimestriel | K7: DRH | L7: Reduction via WTJ et cooptation
B8: TDB-004 | C8: Heures formation / employe | D8: Formation | E8: >= 20 | F8: 12.5 | G8: 8 | I8: Orange (Attention) | J8: Trimestriel | K8: DRH | L8: Programme e-learning renforce en cours
B9: TDB-005 | C9: Taux absentéisme | D9: Presence | E9: <= 5% | F9: 0.065 | G9: 0.058 | I9: Rouge (Alerte) | J9: Mensuel | K9: DRH | L9: Pic grippe fevrier, plan d'action en cours
B10: =IF(C10="","TDB-"&TEXT(COUNTA($C$5:C10),"000")) | H10: =IF(OR(F10="",G10=""),"",F10-G10)
B11: =IF(C11="","TDB-"&TEXT(COUNTA($C$5:C11),"000")) | H11: =IF(OR(F11="",G11=""),"",F11-G11)
B12: =IF(C12="","TDB-"&TEXT(COUNTA($C$5:C12),"000")) | H12: =IF(OR(F12="",G12=""),"",F12-G12)
B13: =IF(C13="","TDB-"&TEXT(COUNTA($C$5:C13),"000")) | H13: =IF(OR(F13="",G13=""),"",F13-G13)
B14: =IF(C14="","TDB-"&TEXT(COUNTA($C$5:C14),"000")) | H14: =IF(OR(F14="",G14=""),"",F14-G14)
B15: =IF(C15="","TDB-"&TEXT(COUNTA($C$5:C15),"000")) | H15: =IF(OR(F15="",G15=""),"",F15-G15)
B16: =IF(C16="","TDB-"&TEXT(COUNTA($C$5:C16),"000")) | H16: =IF(OR(F16="",G16=""),"",F16-G16)
B17: =IF(C17="","TDB-"&TEXT(COUNTA($C$5:C17),"000")) | H17: =IF(OR(F17="",G17=""),"",F17-G17)
B18: =IF(C18="","TDB-"&TEXT(COUNTA($C$5:C18),"000")) | H18: =IF(OR(F18="",G18=""),"",F18-G18)
B19: =IF(C19="","TDB-"&TEXT(COUNTA($C$5:C19),"000")) | H19: =IF(OR(F19="",G19=""),"",F19-G19)
B20: =IF(C20="","TDB-"&TEXT(COUNTA($C$5:C20),"000")) | H20: =IF(OR(F20="",G20=""),"",F20-G20)
B21: =IF(C21="","TDB-"&TEXT(COUNTA($C$5:C21),"000")) | H21: =IF(OR(F21="",G21=""),"",F21-G21)
... B109: =IF(C109="","TDB-"&TEXT(COUNTA($C$5:C109),"000")) | H109: =IF(OR(F109="",G109=""),"",F109-G109)
B111: INDICATEURS (mis a jour automatiquement)
B112: Indicateurs suivis | D112: Verts (OK) | F112: Rouges (Alerte)
B113: =COUNTIF(B5:B104,"<>") | D113: =COUNTIF(I5:I104,"Vert (OK)") | F113: =COUNTIF(I5:I104,"Rouge (Alerte)")

Sheet 3-Rapports Mensuels RH
B2: RAPPORTS MENSUELS RH (#168)
B3: TABLEAU DYNAMIQUE — Saisissez dans la prochaine ligne jaune. Les calculs se mettent a jour automatiquement.
B4: N° | C4: Rapport | D4: Type Rapport | E4: Destinataire | F4: Frequence | G4: Periode | H4: Date Emission | I4: Nb Pages | J4: Nb Graphiques | K4: Statut | L4: Observations
B5: RM-001 | C5: Activite RH mars 2025 | D5: Activite mensuelle | E5: DG | F5: Mensuel | G5: Mars 2025 | H5: 45752 | I5: 12 | J5: 8 | K5: Publie | L5: Delai respecte
B6: RM-002 | C6: Bilan recrutement T1 2025 | D6: Tableau de bord KPI | E6: Comite de direction | F6: Trimestriel | G6: T1 2025 | H6: 45757 | I6: 8 | J6: 5 | K6: Publie | L6: Indicateurs positifs
B7: RM-003 | C7: Rapport paie mars 2025 | D7: Reporting DG | E7: DAF | F7: Mensuel | G7: Mars 2025 | H7: 45750 | I7: 6 | J7: 3 | K7: Publie | L7: Aucun ecart significatif
B8: RM-004 | C8: Bilan formation T1 2025 | D8: Bilan trimestriel | E8: DRH | F8: Trimestriel | G8: T1 2025 | H8: 45755 | I8: 10 | J8: 4 | K8: En cours | L8: Compilation en cours
B9: =IF(C9="","RM-"&TEXT(COUNTA($C$5:C9),"000"))
B10: =IF(C10="","RM-"&TEXT(COUNTA($C$5:C10),"000"))
B11: =IF(C11="","RM-"&TEXT(COUNTA($C$5:C11),"000"))
B12: =IF(C12="","RM-"&TEXT(COUNTA($C$5:C12),"000"))
B13: =IF(C13="","RM-"&TEXT(COUNTA($C$5:C13),"000"))
B14: =IF(C14="","RM-"&TEXT(COUNTA($C$5:C14),"000"))
B15: =IF(C15="","RM-"&TEXT(COUNTA($C$5:C15),"000"))
B16: =IF(C16="","RM-"&TEXT(COUNTA($C$5:C16),"000"))
B17: =IF(C17="","RM-"&TEXT(COUNTA($C$5:C17),"000"))
B18: =IF(C18="","RM-"&TEXT(COUNTA($C$5:C18),"000"))
B19: =IF(C19="","RM-"&TEXT(COUNTA($C$5:C19),"000"))
B20: =IF(C20="","RM-"&TEXT(COUNTA($C$5:C20),"000"))
... B108: =IF(C108="","RM-"&TEXT(COUNTA($C$5:C108),"000"))
B110: INDICATEURS (mis a jour automatiquement)
B111: Rapports emis | D111: Publies | F111: Total pages
B112: =COUNTIF(B5:B104,"<>") | D112: =COUNTIF(K5:K104,"Publie") | F112: =SUM(I5:I104)

Sheet 4-KPI RH
B2: INDICATEURS CLES DE PERFORMANCE RH (#169)
B3: TABLEAU DYNAMIQUE — Saisissez dans la prochaine ligne jaune. Les calculs se mettent a jour automatiquement.
B4: N° | C4: KPI | D4: Categorie | E4: Type | F4: Sens | G4: Formule / Mode Calcul | H4: Seuil Vert | I4: Seuil Orange | J4: Seuil Rouge | K4: Frequence | L4: Proprietaire
B5: KPI-001 | C5: Taux rotation | D5: Mobilité | E5: Ratio | F5: Baisse favorable | G5: Nb departs / Effectif moyen x 100 | H5: <=12% | I5: 12-18% | J5: >18% | K5: Mensuel | L5: DRH
B6: KPI-002 | C6: Delai embauche | D6: Recrutement | E6: Temps | F6: Baisse favorable | G6: Date prise de poste - Date validation offre | H6: <=30j | I6: 30-45j | J6: >45j | K6: Mensuel | L6: Assistante RH
B7: KPI-003 | C7: Cout recrutement | D7: Recrutement | E7: Financier | F7: Baisse favorable | G7: (Frais annonce + honoraires) / Nb embauches | H7: <=150k | I7: 150-250k | J7: >250k | K7: Trimestriel | L7: DRH
B8: KPI-004 | C8: Taux formation | D8: Formation | E8: Ratio | F8: Hausse favorable | G8: H formation / Effectif | H8: >=20h | I8: 15-20h | J8: <15h | K8: Trimestriel | L8: DRH
B9: KPI-005 | C9: Absentéisme | D9: Presence | E9: Ratio | F9: Baisse favorable | G9: Jours absences / Jours ouvrables x 100 | H9: <=5% | I9: 5-8% | J9: >8% | K9: Mensuel | L9: DRH
B10: KPI-006 | C10: Satisfaction globale | D10: Climat social | E10: Score | F10: Hausse favorable | G10: Moyenne enquete satisfaction employes | H10: >=4.0 | I10: 3.5-4.0 | J10: <3.5 | K10: Semestriel | L10: DRH
B11: =IF(C11="","KPI-"&TEXT(COUNTA($C$5:C11),"000"))
B12: =IF(C12="","KPI-"&TEXT(COUNTA($C$5:C12),"000"))
B13: =IF(C13="","KPI-"&TEXT(COUNTA($C$5:C13),"000"))
B14: =IF(C14="","KPI-"&TEXT(COUNTA($C$5:C14),"000"))
B15: =IF(C15="","KPI-"&TEXT(COUNTA($C$5:C15),"000"))
B16: =IF(C16="","KPI-"&TEXT(COUNTA($C$5:C16),"000"))
B17: =IF(C17="","KPI-"&TEXT(COUNTA($C$5:C17),"000"))
B18: =IF(C18="","KPI-"&TEXT(COUNTA($C$5:C18),"000"))
B19: =IF(C19="","KPI-"&TEXT(COUNTA($C$5:C19),"000"))
B20: =IF(C20="","KPI-"&TEXT(COUNTA($C$5:C20),"000"))
B21: =IF(C21="","KPI-"&TEXT(COUNTA($C$5:C21),"000"))
B22: =IF(C22="","KPI-"&TEXT(COUNTA($C$5:C22),"000"))
... B110: =IF(C110="","KPI-"&TEXT(COUNTA($C$5:C110),"000"))
B112: INDICATEURS (mis a jour automatiquement)
B113: KPI definis | D113: KPI ratio | F113: KPI financier
B114: =COUNTIF(B5:B104,"<>") | D114: =COUNTIF(E5:E104,"Ratio") | F114: =COUNTIF(E5:E104,"Financier")

Sheet 5-Budget RH Annuel
B2: BUDGET RH ANNUEL (#170)
B3: TABLEAU DYNAMIQUE — Saisissez dans la prochaine ligne jaune. Les calculs se mettent a jour automatiquement.
B4: N° | C4: Poste Budgetaire | D4: Categorie | E4: Budget Annuel (FCFA) | F4: Realise (FCFA) | G4: Taux Realisation (%) | H4: Ecart (FCFA) | I4: Ecart (%) | J4: Prevision Fin d'Annee | K4: Statut | L4: Observations
B5: BDG-001 | C5: Salaires & primes | D5: Salaires & primes | E5: 96000000 | F5: 24500000 | K5: En execution | L5: T1 conforme aux previsions
B6: BDG-002 | C6: Charges sociales CNPS | D6: Charges sociales | E6: 11520000 | F6: 2940000 | K6: En execution | L6: Taux CNPS stable
B7: BDG-003 | C7: Formation & developpement | D7: Formation & developpement | E7: 4800000 | F7: 1200000 | K7: En execution | L7: E-learning reduit les couts
B8: BDG-004 | C8: Recrutement | D8: Recrutement | E8: 2400000 | F8: 850000 | K8: En execution | L8: Hausse due a 3 remplacements imprevus
B9: BDG-005 | C9: Santé & sécurité | D9: Santé & sécurité | E9: 1800000 | F9: 450000 | K9: En execution | L9: Visites medicales T1 effectuees
B10: =IF(C10="","BDG-"&TEXT(COUNTA($C$5:C10),"000")) | G10: =IF(E10="","",F10/E10) | H10: =IF(OR(E10="",F10=""),"",E10-F10) | I10: =IF(E10="","",H10/E10) | J10: =IF(E10="","",F10/3*12)
B11: =IF(C11="","BDG-"&TEXT(COUNTA($C$5:C11),"000")) | G11: =IF(E11="","",F11/E11) | H11: =IF(OR(E11="",F11=""),"",E11-F11) | I11: =IF(E11="","",H11/E11) | J11: =IF(E11="","",F11/3*12)
B12: =IF(C12="","BDG-"&TEXT(COUNTA($C$5:C12),"000")) | G12: =IF(E12="","",F12/E12) | H12: =IF(OR(E12="",F12=""),"",E12-F12) | I12: =IF(E12="","",H12/E12) | J12: =IF(E12="","",F12/3*12)
B13: =IF(C13="","BDG-"&TEXT(COUNTA($C$5:C13),"000")) | G13: =IF(E13="","",F13/E13) | H13: =IF(OR(E13="",F13=""),"",E13-F13) | I13: =IF(E13="","",H13/E13) | J13: =IF(E13="","",F13/3*12)
B14: =IF(C14="","BDG-"&TEXT(COUNTA($C$5:C14),"000")) | G14: =IF(E14="","",F14/E14) | H14: =IF(OR(E14="",F14=""),"",E14-F14) | I14: =IF(E14="","",H14/E14) | J14: =IF(E14="","",F14/3*12)
B15: =IF(C15="","BDG-"&TEXT(COUNTA($C$5:C15),"000")) | G15: =IF(E15="","",F15/E15) | H15: =IF(OR(E15="",F15=""),"",E15-F15) | I15: =IF(E15="","",H15/E15) | J15: =IF(E15="","",F15/3*12)
B16: =IF(C16="","BDG-"&TEXT(COUNTA($C$5:C16),"000")) | G16: =IF(E16="","",F16/E16) | H16: =IF(OR(E16="",F16=""),"",E16-F16) | I16: =IF(E16="","",H16/E16) | J16: =IF(E16="","",F16/3*12)
B17: =IF(C17="","BDG-"&TEXT(COUNTA($C$5:C17),"000")) | G17: =IF(E17="","",F17/E17) | H17: =IF(OR(E17="",F17=""),"",E17-F17) | I17: =IF(E17="","",H17/E17) | J17: =IF(E17="","",F17/3*12)
B18: =IF(C18="","BDG-"&TEXT(COUNTA($C$5:C18),"000")) | G18: =IF(E18="","",F18/E18) | H18: =IF(OR(E18="",F18=""),"",E18-F18) | I18: =IF(E18="","",H18/E18) | J18: =IF(E18="","",F18/3*12)
B19: =IF(C19="","BDG-"&TEXT(COUNTA($C$5:C19),"000")) | G19: =IF(E19="","",F19/E19) | H19: =IF(OR(E19="",F19=""),"",E19-F19) | I19: =IF(E19="","",H19/E19) | J19: =IF(E19="","",F19/3*12)
B20: =IF(C20="","BDG-"&TEXT(COUNTA($C$5:C20),"000")) | G20: =IF(E20="","",F20/E20) | H20: =IF(OR(E20="",F20=""),"",E20-F20) | I20: =IF(E20="","",H20/E20) | J20: =IF(E20="","",F20/3*12)
B21: =IF(C21="","BDG-"&TEXT(COUNTA($C$5:C21),"000")) | G21: =IF(E21="","",F21/E21) | H21: =IF(OR(E21="",F21=""),"",E21-F21) | I21: =IF(E21="","",H21/E21) | J21: =IF(E21="","",F21/3*12)
... B109: =IF(C109="","BDG-"&TEXT(COUNTA($C$5:C109),"000")) | G109: =IF(E109="","",F109/E109) | H109: =IF(OR(E109="",F109=""),"",E109-F109) | I109: =IF(E109="","",H109/E109) | J109: =IF(E109="","",F109/3*12)
B111: TOTAL | E111: =SUM(E5:E104) | F111: =SUM(F5:F104)
B113: INDICATEURS (mis a jour automatiquement)
B114: Postes budgetaires | D114: Budget total (FCFA) | F114: Taux real. moyen (%)
B115: =COUNTIF(B5:B104,"<>") | D115: =SUM(E5:E104) | F115: =IFERROR(AVERAGE(G5:G104),0)

Sheet 6-Plan de Charge RH
B2: PLAN DE CHARGE RH (#171)
B3: TABLEAU DYNAMIQUE — Saisissez dans la prochaine ligne jaune. Les calculs se mettent a jour automatiquement.
B4: N° | C4: Activite RH | D4: Responsable | E4: Departement | F4: Date Debut | G4: Date Fin | H4: Charge Prevue (h) | I4: Charge Consommee (h) | J4: Taux Avancement (%) | K4: Charge Restante (h) | L4: Statut | M4: Observations
B5: PCH-001 | C5: Recrutement saisonnier ete | D5: Assistante RH | E5: Service Client | F5: 45748 | G5: 45838 | H5: 120 | I5: 45 | L5: En cours | M5: 15 postes a pourvoir
B6: PCH-002 | C6: Bilan social 2024 | D6: DRH | E6: Service Client | F6: 45689 | G6: 45777 | H6: 80 | I6: 65 | L6: En cours | M6: Compilation donnees fin mars
B7: PCH-003 | C7: Formation continue Q2 | D7: DRH | E7: Service Client | F7: 45748 | G7: 45838 | H7: 60 | I7: 10 | L7: En cours | M7: Programme e-learning lance
B8: PCH-004 | C8: Audit paie annuel | D8: DAF | E8: Finance & Comptabilité | F8: 45731 | G8: 45792 | H8: 40 | I8: 20 | L8: En cours | M8: Audit externe en cours
B9: =IF(C9="","PCH-"&TEXT(COUNTA($C$5:C9),"000")) | J9: =IF(H9="","",I9/H9) | K9: =IF(H9="","",MAX(H9-I9,0))
B10: =IF(C10="","PCH-"&TEXT(COUNTA($C$5:C10),"000")) | J10: =IF(H10="","",I10/H10) | K10: =IF(H10="","",MAX(H10-I10,0))
B11: =IF(C11="","PCH-"&TEXT(COUNTA($C$5:C11),"000")) | J11: =IF(H11="","",I11/H11) | K11: =IF(H11="","",MAX(H11-I11,0))
B12: =IF(C12="","PCH-"&TEXT(COUNTA($C$5:C12),"000")) | J12: =IF(H12="","",I12/H12) | K12: =IF(H12="","",MAX(H12-I12,0))
B13: =IF(C13="","PCH-"&TEXT(COUNTA($C$5:C13),"000")) | J13: =IF(H13="","",I13/H13) | K13: =IF(H13="","",MAX(H13-I13,0))
B14: =IF(C14="","PCH-"&TEXT(COUNTA($C$5:C14),"000")) | J14: =IF(H14="","",I14/H14) | K14: =IF(H14="","",MAX(H14-I14,0))
B15: =IF(C15="","PCH-"&TEXT(COUNTA($C$5:C15),"000")) | J15: =IF(H15="","",I15/H15) | K15: =IF(H15="","",MAX(H15-I15,0))
B16: =IF(C16="","PCH-"&TEXT(COUNTA($C$5:C16),"000")) | J16: =IF(H16="","",I16/H16) | K16: =IF(H16="","",MAX(H16-I16,0))
B17: =IF(C17="","PCH-"&TEXT(COUNTA($C$5:C17),"000")) | J17: =IF(H17="","",I17/H17) | K17: =IF(H17="","",MAX(H17-I17,0))
B18: =IF(C18="","PCH-"&TEXT(COUNTA($C$5:C18),"000")) | J18: =IF(H18="","",I18/H18) | K18: =IF(H18="","",MAX(H18-I18,0))
B19: =IF(C19="","PCH-"&TEXT(COUNTA($C$5:C19),"000")) | J19: =IF(H19="","",I19/H19) | K19: =IF(H19="","",MAX(H19-I19,0))
B20: =IF(C20="","PCH-"&TEXT(COUNTA($C$5:C20),"000")) | J20: =IF(H20="","",I20/H20) | K20: =IF(H20="","",MAX(H20-I20,0))
... B108: =IF(C108="","PCH-"&TEXT(COUNTA($C$5:C108),"000")) | J108: =IF(H108="","",I108/H108) | K108: =IF(H108="","",MAX(H108-I108,0))
B110: TOTAL | H110: =SUM(H5:H104) | I110: =SUM(I5:I104)
B112: INDICATEURS (mis a jour automatiquement)
B113: Activites planifiees | D113: Charge totale (h) | F113: En cours
B114: =COUNTIF(B5:B104,"<>") | D114: =SUM(H5:H104) | F114: =COUNTIF(L5:L104,"En cours")

Sheet 7-Reporting Direction Gen.
B2: REPORTING DIRECTION GENERALE (#172)
B3: TABLEAU DYNAMIQUE — Saisissez dans la prochaine ligne jaune. Les calculs se mettent a jour automatiquement.
B4: N° | C4: Indicateur DG | D4: Domaine RH | E4: Valeur | F4: Objectif | G4: Tendance | H4: Statut | I4: Commentaire Action | J4: Date Reporting
B5: RDG-001 | C5: Effectif total | D5: Administration | E5: 185 | F5: 190 | G5: Stable | H5: Orange (Attention) | I5: 5 postes en cours de recrutement | J5: 45747
B6: RDG-002 | C6: Masse salariale (M FCFA) | D6: Paie | E6: 126.5 | F6: 120 | G6: Hausse | H6: Rouge (Alerte) | I6: Reviser grille en Q2 | J6: 45747
B7: RDG-003 | C7: Taux rotation | D7: Mobilité | E7: 18% | F7: <=12% | G7: Baisse | H7: Orange (Attention) | I7: Plan retention deploye | J7: 45747
B8: RDG-004 | C8: Score satisfaction | D8: Climat social | E8: 3.8 | F8: >=4.0 | G8: Hausse | H8: Orange (Attention) | I8: Enquete Q2 prevue juin | J8: 45747
B9: RDG-005 | C9: Nb formations / employe | D9: Formation | E9: 12.5h | F9: >=20h | G9: Hausse | H9: Rouge (Alerte) | I9: E-learning en deploiement | J9: 45747
B10: =IF(C10="","RDG-"&TEXT(COUNTA($C$5:C10),"000"))
B11: =IF(C11="","RDG-"&TEXT(COUNTA($C$5:C11),"000"))
B12: =IF(C12="","RDG-"&TEXT(COUNTA($C$5:C12),"000"))
B13: =IF(C13="","RDG-"&TEXT(COUNTA($C$5:C13),"000"))
B14: =IF(C14="","RDG-"&TEXT(COUNTA($C$5:C14),"000"))
B15: =IF(C15="","RDG-"&TEXT(COUNTA($C$5:C15),"000"))
B16: =IF(C16="","RDG-"&TEXT(COUNTA($C$5:C16),"000"))
B17: =IF(C17="","RDG-"&TEXT(COUNTA($C$5:C17),"000"))
B18: =IF(C18="","RDG-"&TEXT(COUNTA($C$5:C18),"000"))
B19: =IF(C19="","RDG-"&TEXT(COUNTA($C$5:C19),"000"))
B20: =IF(C20="","RDG-"&TEXT(COUNTA($C$5:C20),"000"))
B21: =IF(C21="","RDG-"&TEXT(COUNTA($C$5:C21),"000"))
... B109: =IF(C109="","RDG-"&TEXT(COUNTA($C$5:C109),"000"))
B111: INDICATEURS (mis a jour automatiquement)
B112: Indicateurs DG | D112: Alertes rouges | F112: Verts (OK)
B113: =COUNTIF(B5:B104,"<>") | D113: =COUNTIF(H5:H104,"Rouge (Alerte)") | F113: =COUNTIF(H5:H104,"Vert (OK)")

Sheet 8-Benchmarking RH Hotelier
B2: BENCHMARKING RH HOTELIER (#173)
B3: TABLEAU DYNAMIQUE — Saisissez dans la prochaine ligne jaune. Les calculs se mettent a jour automatiquement.
B4: N° | C4: Indicateur Benchmark | D4: Notre Hotel | E4: Moyenne 4 Etoiles | F4: Meilleur Pratique | G4: Ecart vs Moyenne | H4: Ecart vs Meilleur | I4: Classement | J4: Plan Action | K4: Priorite | L4: Observations
B5: BM-001 | C5: Taux rotation (%) | D5: 18 | E5: 22 | F5: 10 | I5: Bon | J5: Maintenir initiatives retention | K5: Moyenne | L5: Meilleur que la moyenne sectorielle
B6: BM-002 | C6: Delai embauche (j) | D6: 28 | E6: 35 | F6: 14 | I6: Bon | J6: Continuer IA recrutement | K6: Moyenne | L6: Objectif atteindre 21j d'ici fin annee
B7: BM-003 | C7: Heures form. / employe | D7: 12.5 | E7: 16 | F7: 30 | I7: Insuffisant | J7: Doubler le volume e-learning | K7: Haute | L7: Ecart critique vs meilleur pratique
B8: BM-004 | C8: Taux satisfaction | D8: 3.8 | E8: 3.5 | F8: 4.5 | I8: Bon | J8: Renforcer bien-etre | K8: Moyenne | L8: Objectif 4.2 en 2025
B9: BM-005 | C9: Absentéisme (%) | D9: 6.5 | E9: 7 | F9: 3.5 | I9: Moyen | J9: Plan sante et prevention | K9: Haute | L9: Programme soute T2 2025
B10: =IF(C10="","BM-"&TEXT(COUNTA($C$5:C10),"000")) | G10: =IF(OR(D10="",E10=""),"",D10-E10) | H10: =IF(OR(D10="",F10=""),"",D10-F10)
B11: =IF(C11="","BM-"&TEXT(COUNTA($C$5:C11),"000")) | G11: =IF(OR(D11="",E11=""),"",D11-E11) | H11: =IF(OR(D11="",F11=""),"",D11-F11)
B12: =IF(C12="","BM-"&TEXT(COUNTA($C$5:C12),"000")) | G12: =IF(OR(D12="",E12=""),"",D12-E12) | H12: =IF(OR(D12="",F12=""),"",D12-F12)
B13: =IF(C13="","BM-"&TEXT(COUNTA($C$5:C13),"000")) | G13: =IF(OR(D13="",E13=""),"",D13-E13) | H13: =IF(OR(D13="",F13=""),"",D13-F13)
B14: =IF(C14="","BM-"&TEXT(COUNTA($C$5:C14),"000")) | G14: =IF(OR(D14="",E14=""),"",D14-E14) | H14: =IF(OR(D14="",F14=""),"",D14-F14)
B15: =IF(C15="","BM-"&TEXT(COUNTA($C$5:C15),"000")) | G15: =IF(OR(D15="",E15=""),"",D15-E15) | H15: =IF(OR(D15="",F15=""),"",D15-F15)
B16: =IF(C16="","BM-"&TEXT(COUNTA($C$5:C16),"000")) | G16: =IF(OR(D16="",E16=""),"",D16-E16) | H16: =IF(OR(D16="",F16=""),"",D16-F16)
B17: =IF(C17="","BM-"&TEXT(COUNTA($C$5:C17),"000")) | G17: =IF(OR(D17="",E17=""),"",D17-E17) | H17: =IF(OR(D17="",F17=""),"",D17-F17)
B18: =IF(C18="","BM-"&TEXT(COUNTA($C$5:C18),"000")) | G18: =IF(OR(D18="",E18=""),"",D18-E18) | H18: =IF(OR(D18="",F18=""),"",D18-F18)
B19: =IF(C19="","BM-"&TEXT(COUNTA($C$5:C19),"000")) | G19: =IF(OR(D19="",E19=""),"",D19-E19) | H19: =IF(OR(D19="",F19=""),"",D19-F19)
B20: =IF(C20="","BM-"&TEXT(COUNTA($C$5:C20),"000")) | G20: =IF(OR(D20="",E20=""),"",D20-E20) | H20: =IF(OR(D20="",F20=""),"",D20-F20)
B21: =IF(C21="","BM-"&TEXT(COUNTA($C$5:C21),"000")) | G21: =IF(OR(D21="",E21=""),"",D21-E21) | H21: =IF(OR(D21="",F21=""),"",D21-F21)
... B109: =IF(C109="","BM-"&TEXT(COUNTA($C$5:C109),"000")) | G109: =IF(OR(D109="",E109=""),"",D109-E109) | H109: =IF(OR(D109="",F109=""),"",D109-F109)
B111: INDICATEURS (mis a jour automatiquement)
B112: Indicateurs benchmark | D112: Au-dessus moyenne | F112: Priorite haute
B113: =COUNTIF(B5:B104,"<>") | D113: =COUNTIF(G5:G104,"<0") | F113: =COUNTIF(K5:K104,"Haute")

Sheet 9-Plans d'Action RH
B2: PLANS D'ACTION RH (#174)
B3: TABLEAU DYNAMIQUE — Saisissez dans la prochaine ligne jaune. Les calculs se mettent a jour automatiquement.
B4: N° | C4: Plan d'Action | D4: Objectif Stratégique | E4: Responsable | F4: Date Debut | G4: Date Fin | H4: Budget Alloue (FCFA) | I4: Avancement (%) | J4: Resultat Attendu | K4: Statut | L4: Observations
B5: PA-001 | C5: Plan Retention 2025 | D5: Reduire taux rotation a 12% | E5: DRH | F5: 45658 | G5: 46022 | H5: 5000000 | I5: 0.25 | J5: Taux rotation <=12% | K5: En cours | L5: Mentorat + bien-etre en place
B6: PA-002 | C6: Digitalisation RH | D6: 100% processus digitaux | E6: Chef de service IT | F6: 45658 | G6: 46022 | H6: 12000000 | I6: 0.3 | J6: Tous processus automatises | K6: En cours | L6: SIRH cloud + app mobile en cours
B7: PA-003 | C7: Plan Formation Continue | D7: 20h formation / employe / an | E7: DRH | F7: 45658 | G7: 46022 | H7: 4800000 | I7: 0.2 | J7: Score >=4.0 satisfaction | K7: En cours | L7: E-learning + formations presentielles
B8: PA-004 | C8: Plan Diversite 2025 | D8: 40% femmes cadres | E8: DRH | F8: 45658 | G8: 46752 | H8: 1500000 | I8: 0.15 | J8: Promotion 5 femmes cadres | K8: En cours | L8: Mentorat et sensibilisation en cours
B9: =IF(C9="","PA-"&TEXT(COUNTA($C$5:C9),"000"))
B10: =IF(C10="","PA-"&TEXT(COUNTA($C$5:C10),"000"))
B11: =IF(C11="","PA-"&TEXT(COUNTA($C$5:C11),"000"))
B12: =IF(C12="","PA-"&TEXT(COUNTA($C$5:C12),"000"))
B13: =IF(C13="","PA-"&TEXT(COUNTA($C$5:C13),"000"))
B14: =IF(C14="","PA-"&TEXT(COUNTA($C$5:C14),"000"))
B15: =IF(C15="","PA-"&TEXT(COUNTA($C$5:C15),"000"))
B16: =IF(C16="","PA-"&TEXT(COUNTA($C$5:C16),"000"))
B17: =IF(C17="","PA-"&TEXT(COUNTA($C$5:C17),"000"))
B18: =IF(C18="","PA-"&TEXT(COUNTA($C$5:C18),"000"))
B19: =IF(C19="","PA-"&TEXT(COUNTA($C$5:C19),"000"))
B20: =IF(C20="","PA-"&TEXT(COUNTA($C$5:C20),"000"))
... B108: =IF(C108="","PA-"&TEXT(COUNTA($C$5:C108),"000"))
B110: TOTAL | H110: =SUM(H5:H104)
B112: INDICATEURS (mis a jour automatiquement)
B113: Plans d'action | D113: Budget total (FCFA) | F113: En cours
B114: =COUNTIF(B5:B104,"<>") | D114: =SUM(H5:H104) | F114: =COUNTIF(K5:K104,"En cours")

Sheet 10-Bilan Social
B2: BILAN SOCIAL (#175)
B3: TABLEAU DYNAMIQUE — Saisissez dans la prochaine ligne jaune. Les calculs se mettent a jour automatiquement.
B4: N° | C4: Indicateur Bilan Social | D4: Source de Donnees | E4: Annee N-1 | F4: Annee N | G4: Evolution | H4: Reference Legale | I4: Statut | J4: Observations
B5: BS-001 | C5: Effectif au 31/12 | D5: SIRH | E5: 175 | F5: 185 | H5: Art. L1221-3 CT | I5: En cours | J5: Hausse de 5.7% liee a l'extension
B6: BS-002 | C6: Taux rotation | D6: SIRH | E6: 0.22 | F6: 0.18 | H6: Convention collective | I6: En cours | J6: Amelioration significative
B7: BS-003 | C7: Nb embauches CDD | D7: SIRH | E7: 45 | F7: 38 | H7: Art. L1242-1 CT | I7: En cours | J7: Baisse des CDD au profit des CDI
B8: BS-004 | C8: Nb embauches CDI | D8: SIRH | E8: 22 | F8: 30 | H8: Art. L1221-2 CT | I8: En cours | J8: Politique de stabilisation
B9: BS-005 | C9: Total salaires bruts (M FCFA) | D9: Paie | E9: 105 | F9: 126.5 | H9: Art. L3231-1 CT | I9: En cours | J9: Hausse effectif + revalorisation
B10: BS-006 | C10: Nb jours de formation | D10: SIRH | E10: 1400 | F10: 2313 | H10: Art. L6311-1 CT | I10: En cours | J10: Objectif 3700h pour 2025
B11: BS-007 | C11: Nb accidents de travail | D11: Registre S&ST | E11: 8 | F11: 5 | H11: Art. L4121-1 CT | I11: En cours | J11: Plan securite porte ses fruits
B12: BS-008 | C12: Taux absentéisme | D12: SIRH + Paie | E12: 0.058 | F12: 0.065 | H12: Pas de ref. legale directe | I12: En cours | J12: Hausse liee a pic grippe fevrier
B13: =IF(C13="","BS-"&TEXT(COUNTA($C$5:C13),"000")) | G13: =IF(OR(E13="",F13=""),"",F13-E13)
B14: =IF(C14="","BS-"&TEXT(COUNTA($C$5:C14),"000")) | G14: =IF(OR(E14="",F14=""),"",F14-E14)
B15: =IF(C15="","BS-"&TEXT(COUNTA($C$5:C15),"000")) | G15: =IF(OR(E15="",F15=""),"",F15-E15)
B16: =IF(C16="","BS-"&TEXT(COUNTA($C$5:C16),"000")) | G16: =IF(OR(E16="",F16=""),"",F16-E16)
B17: =IF(C17="","BS-"&TEXT(COUNTA($C$5:C17),"000")) | G17: =IF(OR(E17="",F17=""),"",F17-E17)
B18: =IF(C18="","BS-"&TEXT(COUNTA($C$5:C18),"000")) | G18: =IF(OR(E18="",F18=""),"",F18-E18)
B19: =IF(C19="","BS-"&TEXT(COUNTA($C$5:C19),"000")) | G19: =IF(OR(E19="",F19=""),"",F19-E19)
B20: =IF(C20="","BS-"&TEXT(COUNTA($C$5:C20),"000")) | G20: =IF(OR(E20="",F20=""),"",F20-E20)
B21: =IF(C21="","BS-"&TEXT(COUNTA($C$5:C21),"000")) | G21: =IF(OR(E21="",F21=""),"",F21-E21)
B22: =IF(C22="","BS-"&TEXT(COUNTA($C$5:C22),"000")) | G22: =IF(OR(E22="",F22=""),"",F22-E22)
B23: =IF(C23="","BS-"&TEXT(COUNTA($C$5:C23),"000")) | G23: =IF(OR(E23="",F23=""),"",F23-E23)
B24: =IF(C24="","BS-"&TEXT(COUNTA($C$5:C24),"000")) | G24: =IF(OR(E24="",F24=""),"",F24-E24)
... B112: =IF(C112="","BS-"&TEXT(COUNTA($C$5:C112),"000")) | G112: =IF(OR(E112="",F112=""),"",F112-E112)
B114: INDICATEURS (mis a jour automatiquement)
B115: Indicateurs bilan | D115: Ameliorations | F115: En cours
B116: =COUNTIF(B5:B104,"<>") | D116: =COUNTIF(G5:G104,"<0") | F116: =COUNTIF(I5:I104,"En cours")

Sheet 11-Feuille de Route Strat. RH
B2: FEUILLE DE ROUTE STRATEGIQUE RH (#176)
B3: TABLEAU DYNAMIQUE — Saisissez dans la prochaine ligne jaune. Les calculs se mettent a jour automatiquement.
B4: N° | C4: Axe Strategique | D4: Objectif Strategique | E4: Indicateur de Succes | F4: Valeur Initiale | G4: Cible 2025 | H4: Valeur Actuelle | I4: Progression (%) | J4: Priorite | K4: Responsable | L4: Statut | M4: Observations
B5: FR-001 | C5: Employabilite | D5: Former 100% des employes en digital | E5: % employes formes digital | F5: 0.2 | G5: 0.8 | H5: 0.35 | J5: Haute | K5: DRH | L5: En cours | M5: E-learning digital lance T1
B6: FR-002 | C6: Attractivite | D6: Devenir employeur de reference | E6: Ranking Glassdoor / Indeed | F6: 3.2 | G6: 4 | H6: 3.5 | J6: Haute | K6: DRH | L6: En cours | M6: Marque employeur renforcee
B7: FR-003 | C7: Performance | D7: Automatiser 80% processus RH | E7: % processus automatises | F7: 0.3 | G7: 0.8 | H7: 0.45 | J7: Haute | K7: Chef de service IT | L7: En cours | M7: SIRH + Lucca + chatbot deploies
B8: FR-004 | C8: Bien-Etre | D8: Score satisfaction >= 4.0/5 | E8: Moyenne enquete satisfaction | F8: 3.5 | G8: 4 | H8: 3.8 | J8: Haute | K8: DRH | L8: En cours | M8: Enquete Q1 en hausse
B9: FR-005 | C9: Conformite | D9: 100% conformite RGPD & travail | E9: % audits sans non-conformite | F9: 0.85 | G9: 1 | H9: 0.9 | J9: Critique | K9: DRH | L9: En cours | M9: Audit Q1 conforme, dossier med. a numeriser
B10: =IF(C10="","FR-"&TEXT(COUNTA($C$5:C10),"000")) | I10: =IF(OR(F10="",G10="",H10=""),"",IF(G10=F10,"N/A",(H10-F10)/(G10-F10)))
B11: =IF(C11="","FR-"&TEXT(COUNTA($C$5:C11),"000")) | I11: =IF(OR(F11="",G11="",H11=""),"",IF(G11=F11,"N/A",(H11-F11)/(G11-F11)))
B12: =IF(C12="","FR-"&TEXT(COUNTA($C$5:C12),"000")) | I12: =IF(OR(F12="",G12="",H12=""),"",IF(G12=F12,"N/A",(H12-F12)/(G12-F12)))
B13: =IF(C13="","FR-"&TEXT(COUNTA($C$5:C13),"000")) | I13: =IF(OR(F13="",G13="",H13=""),"",IF(G13=F13,"N/A",(H13-F13)/(G13-F13)))
B14: =IF(C14="","FR-"&TEXT(COUNTA($C$5:C14),"000")) | I14: =IF(OR(F14="",G14="",H14=""),"",IF(G14=F14,"N/A",(H14-F14)/(G14-F14)))
B15: =IF(C15="","FR-"&TEXT(COUNTA($C$5:C15),"000")) | I15: =IF(OR(F15="",G15="",H15=""),"",IF(G15=F15,"N/A",(H15-F15)/(G15-F15)))
B16: =IF(C16="","FR-"&TEXT(COUNTA($C$5:C16),"000")) | I16: =IF(OR(F16="",G16="",H16=""),"",IF(G16=F16,"N/A",(H16-F16)/(G16-F16)))
B17: =IF(C17="","FR-"&TEXT(COUNTA($C$5:C17),"000")) | I17: =IF(OR(F17="",G17="",H17=""),"",IF(G17=F17,"N/A",(H17-F17)/(G17-F17)))
B18: =IF(C18="","FR-"&TEXT(COUNTA($C$5:C18),"000")) | I18: =IF(OR(F18="",G18="",H18=""),"",IF(G18=F18,"N/A",(H18-F18)/(G18-F18)))
B19: =IF(C19="","FR-"&TEXT(COUNTA($C$5:C19),"000")) | I19: =IF(OR(F19="",G19="",H19=""),"",IF(G19=F19,"N/A",(H19-F19)/(G19-F19)))
B20: =IF(C20="","FR-"&TEXT(COUNTA($C$5:C20),"000")) | I20: =IF(OR(F20="",G20="",H20=""),"",IF(G20=F20,"N/A",(H20-F20)/(G20-F20)))
B21: =IF(C21="","FR-"&TEXT(COUNTA($C$5:C21),"000")) | I21: =IF(OR(F21="",G21="",H21=""),"",IF(G21=F21,"N/A",(H21-F21)/(G21-F21)))
... B109: =IF(C109="","FR-"&TEXT(COUNTA($C$5:C109),"000")) | I109: =IF(OR(F109="",G109="",H109=""),"",IF(G109=F109,"N/A",(H109-F109)/(G109-F109)))
B111: INDICATEURS (mis a jour automatiquement)
B112: Axes strategiques | D112: Progression moy. (%) | F112: Priorite critique
B113: =COUNTIF(B5:B104,"<>") | D113: =IFERROR(AVERAGE(I5:I104),0) | F113: =COUNTIF(J5:J104,"Critique")

Sheet 12-Suivi KPI RH Mensuel
B2: SUIVI KPI RH MENSUEL
B3: TABLEAU DYNAMIQUE — Saisissez dans la prochaine ligne jaune. Les calculs se mettent a jour automatiquement.
B4: N° | C4: Mois | D4: Effectif Total | E4: Entrees | F4: Sorties | G4: Taux Rotation (%) | H4: Absentéisme (%) | I4: Heures Formation | J4: H Formation / Employe | K4: Cout Recrutement (FCFA) | L4: Satisfaction Moyenne
B5: SKM-001 | C5: Janvier 2025 | D5: 178 | E5: 5 | F5: 3 | H5: 0.055 | I5: 180 | K5: 350000 | L5: 3.7
B6: SKM-002 | C6: Fevrier 2025 | D6: 180 | E6: 4 | F6: 2 | H6: 0.07 | I6: 220 | K6: 280000 | L6: 3.8
B7: SKM-003 | C7: Mars 2025 | D7: 185 | E7: 8 | F7: 3 | H7: 0.065 | I7: 250 | K7: 520000 | L7: 3.9
B8: =IF(C8="","SKM-"&TEXT(COUNTA($C$5:C8),"000")) | G8: =IF(D8="","",F8/D8) | J8: =IF(D8="","",I8/D8)
B9: =IF(C9="","SKM-"&TEXT(COUNTA($C$5:C9),"000")) | G9: =IF(D9="","",F9/D9) | J9: =IF(D9="","",I9/D9)
B10: =IF(C10="","SKM-"&TEXT(COUNTA($C$5:C10),"000")) | G10: =IF(D10="","",F10/D10) | J10: =IF(D10="","",I10/D10)
B11: =IF(C11="","SKM-"&TEXT(COUNTA($C$5:C11),"000")) | G11: =IF(D11="","",F11/D11) | J11: =IF(D11="","",I11/D11)
B12: =IF(C12="","SKM-"&TEXT(COUNTA($C$5:C12),"000")) | G12: =IF(D12="","",F12/D12) | J12: =IF(D12="","",I12/D12)
B13: =IF(C13="","SKM-"&TEXT(COUNTA($C$5:C13),"000")) | G13: =IF(D13="","",F13/D13) | J13: =IF(D13="","",I13/D13)
B14: =IF(C14="","SKM-"&TEXT(COUNTA($C$5:C14),"000")) | G14: =IF(D14="","",F14/D14) | J14: =IF(D14="","",I14/D14)
B15: =IF(C15="","SKM-"&TEXT(COUNTA($C$5:C15),"000")) | G15: =IF(D15="","",F15/D15) | J15: =IF(D15="","",I15/D15)
B16: =IF(C16="","SKM-"&TEXT(COUNTA($C$5:C16),"000")) | G16: =IF(D16="","",F16/D16) | J16: =IF(D16="","",I16/D16)
B17: =IF(C17="","SKM-"&TEXT(COUNTA($C$5:C17),"000")) | G17: =IF(D17="","",F17/D17) | J17: =IF(D17="","",I17/D17)
B18: =IF(C18="","SKM-"&TEXT(COUNTA($C$5:C18),"000")) | G18: =IF(D18="","",F18/D18) | J18: =IF(D18="","",I18/D18)
B19: =IF(C19="","SKM-"&TEXT(COUNTA($C$5:C19),"000")) | G19: =IF(D19="","",F19/D19) | J19: =IF(D19="","",I19/D19)
... B107: =IF(C107="","SKM-"&TEXT(COUNTA($C$5:C107),"000")) | G107: =IF(D107="","",F107/D107) | J107: =IF(D107="","",I107/D107)
B109: INDICATEURS (mis a jour automatiquement)
B110: Mois suivis | D110: Rotation moy. (%) | F110: H form. / employe moy.
B111: =COUNTIF(B5:B104,"<>") | D111: =IFERROR(AVERAGE(G5:G104),0) | F111: =IFERROR(AVERAGE(J5:J104),0)

Sheet 13-Analyse Budget RH
B2: ANALYSE BUDGET RH
B3: TABLEAU DYNAMIQUE — Saisissez dans la prochaine ligne jaune. Les calculs se mettent a jour automatiquement.
B4: N° | C4: Categorie Budget | D4: Budget 2024 (FCFA) | E4: Budget 2025 (FCFA) | F4: Evolution (%) | G4: Realise T1 2025 (FCFA) | H4: Prorata T1 attendu (FCFA) | I4: Ecart T1 (FCFA) | J4: Statut | K4: Observations
B5: AB-001 | C5: Salaires & primes | D5: 88000000 | E5: 96000000 | G5: 24500000 | J5: En execution | K5: Hausse liee a revalorisation
B6: AB-002 | C6: Charges sociales | D6: 10500000 | E6: 11520000 | G6: 2940000 | J6: En execution | K6: Taux CNPS stable
B7: AB-003 | C7: Formation | D7: 3600000 | E7: 4800000 | G7: 1200000 | J7: En execution | K7: Doubler vs 2024
B8: AB-004 | C8: Recrutement | D8: 1800000 | E8: 2400000 | G8: 850000 | J8: En execution | K8: Hausse remplacements imprevus
B9: AB-005 | C9: Santé & sécurité | D9: 1500000 | E9: 1800000 | G9: 450000 | J9: En execution | K9: Visites medicales + securite
B10: =IF(C10="","AB-"&TEXT(COUNTA($C$5:C10),"000")) | F10: =IF(D10="","",E10/D10-1) | H10: =IF(E10="","",E10/4) | I10: =IF(OR(H10="",G10=""),"",H10-G10)
B11: =IF(C11="","AB-"&TEXT(COUNTA($C$5:C11),"000")) | F11: =IF(D11="","",E11/D11-1) | H11: =IF(E11="","",E11/4) | I11: =IF(OR(H11="",G11=""),"",H11-G11)
B12: =IF(C12="","AB-"&TEXT(COUNTA($C$5:C12),"000")) | F12: =IF(D12="","",E12/D12-1) | H12: =IF(E12="","",E12/4) | I12: =IF(OR(H12="",G12=""),"",H12-G12)
B13: =IF(C13="","AB-"&TEXT(COUNTA($C$5:C13),"000")) | F13: =IF(D13="","",E13/D13-1) | H13: =IF(E13="","",E13/4) | I13: =IF(OR(H13="",G13=""),"",H13-G13)
B14: =IF(C14="","AB-"&TEXT(COUNTA($C$5:C14),"000")) | F14: =IF(D14="","",E14/D14-1) | H14: =IF(E14="","",E14/4) | I14: =IF(OR(H14="",G14=""),"",H14-G14)
B15: =IF(C15="","AB-"&TEXT(COUNTA($C$5:C15),"000")) | F15: =IF(D15="","",E15/D15-1) | H15: =IF(E15="","",E15/4) | I15: =IF(OR(H15="",G15=""),"",H15-G15)
B16: =IF(C16="","AB-"&TEXT(COUNTA($C$5:C16),"000")) | F16: =IF(D16="","",E16/D16-1) | H16: =IF(E16="","",E16/4) | I16: =IF(OR(H16="",G16=""),"",H16-G16)
B17: =IF(C17="","AB-"&TEXT(COUNTA($C$5:C17),"000")) | F17: =IF(D17="","",E17/D17-1) | H17: =IF(E17="","",E17/4) | I17: =IF(OR(H17="",G17=""),"",H17-G17)
B18: =IF(C18="","AB-"&TEXT(COUNTA($C$5:C18),"000")) | F18: =IF(D18="","",E18/D18-1) | H18: =IF(E18="","",E18/4) | I18: =IF(OR(H18="",G18=""),"",H18-G18)
B19: =IF(C19="","AB-"&TEXT(COUNTA($C$5:C19),"000")) | F19: =IF(D19="","",E19/D19-1) | H19: =IF(E19="","",E19/4) | I19: =IF(OR(H19="",G19=""),"",H19-G19)
B20: =IF(C20="","AB-"&TEXT(COUNTA($C$5:C20),"000")) | F20: =IF(D20="","",E20/D20-1) | H20: =IF(E20="","",E20/4) | I20: =IF(OR(H20="",G20=""),"",H20-G20)
B21: =IF(C21="","AB-"&TEXT(COUNTA($C$5:C21),"000")) | F21: =IF(D21="","",E21/D21-1) | H21: =IF(E21="","",E21/4) | I21: =IF(OR(H21="",G21=""),"",H21-G21)
... B109: =IF(C109="","AB-"&TEXT(COUNTA($C$5:C109),"000")) | F109: =IF(D109="","",E109/D109-1) | H109: =IF(E109="","",E109/4) | I109: =IF(OR(H109="",G109=""),"",H109-G109)
B111: TOTAL | D111: =SUM(D5:D104) | E111: =SUM(E5:E104) | G111: =SUM(G5:G104)
B113: INDICATEURS (mis a jour automatiquement)
B114: Categories budget | D114: Budget total 2025 | F114: Ecart T1 total
B115: =COUNTIF(B5:B104,"<>") | D115: =SUM(E5:E104) | F115: =SUM(I5:I104)

Sheet 14-Suivi Plans d'Action
B2: SUIVI PLANS D'ACTION RH
B3: TABLEAU DYNAMIQUE — Saisissez dans la prochaine ligne jaune. Les calculs se mettent a jour automatiquement.
B4: N° | C4: Plan d'Action | D4: Axe Strategique | E4: Nb Actions Total | F4: Actions Terminees | G4: Actions En Cours | H4: Taux Realisation (%) | I4: Budget Alloue (FCFA) | J4: Budget Consomme (FCFA) | K4: Taux Consommation (%) | L4: Statut | M4: Observations
B5: SPA-001 | C5: Plan Retention 2025 | D5: Bien-Etre | E5: 12 | F5: 3 | G5: 7 | I5: 5000000 | J5: 1200000 | L5: En cours | M5: Q1: 3/12 actions terminees
B6: SPA-002 | C6: Digitalisation RH | D6: Performance | E6: 8 | F6: 2 | G6: 5 | I6: 12000000 | J6: 3600000 | L6: En cours | M6: SIRH cloud en phase 2
B7: SPA-003 | C7: Plan Formation | D7: Employabilite | E7: 15 | F7: 4 | G7: 9 | I7: 4800000 | J7: 1200000 | L7: En cours | M7: E-learning bien lance
B8: SPA-004 | C8: Plan Diversite | D8: Attractivite | E8: 6 | F8: 1 | G8: 4 | I8: 1500000 | J8: 300000 | L8: En cours | M8: Mentorat operationnel
B9: =IF(C9="","SPA-"&TEXT(COUNTA($C$5:C9),"000")) | H9: =IF(E9="","",F9/E9) | K9: =IF(I9="","",J9/I9)
B10: =IF(C10="","SPA-"&TEXT(COUNTA($C$5:C10),"000")) | H10: =IF(E10="","",F10/E10) | K10: =IF(I10="","",J10/I10)
B11: =IF(C11="","SPA-"&TEXT(COUNTA($C$5:C11),"000")) | H11: =IF(E11="","",F11/E11) | K11: =IF(I11="","",J11/I11)
B12: =IF(C12="","SPA-"&TEXT(COUNTA($C$5:C12),"000")) | H12: =IF(E12="","",F12/E12) | K12: =IF(I12="","",J12/I12)
B13: =IF(C13="","SPA-"&TEXT(COUNTA($C$5:C13),"000")) | H13: =IF(E13="","",F13/E13) | K13: =IF(I13="","",J13/I13)
B14: =IF(C14="","SPA-"&TEXT(COUNTA($C$5:C14),"000")) | H14: =IF(E14="","",F14/E14) | K14: =IF(I14="","",J14/I14)
B15: =IF(C15="","SPA-"&TEXT(COUNTA($C$5:C15),"000")) | H15: =IF(E15="","",F15/E15) | K15: =IF(I15="","",J15/I15)
B16: =IF(C16="","SPA-"&TEXT(COUNTA($C$5:C16),"000")) | H16: =IF(E16="","",F16/E16) | K16: =IF(I16="","",J16/I16)
B17: =IF(C17="","SPA-"&TEXT(COUNTA($C$5:C17),"000")) | H17: =IF(E17="","",F17/E17) | K17: =IF(I17="","",J17/I17)
B18: =IF(C18="","SPA-"&TEXT(COUNTA($C$5:C18),"000")) | H18: =IF(E18="","",F18/E18) | K18: =IF(I18="","",J18/I18)
B19: =IF(C19="","SPA-"&TEXT(COUNTA($C$5:C19),"000")) | H19: =IF(E19="","",F19/E19) | K19: =IF(I19="","",J19/I19)
B20: =IF(C20="","SPA-"&TEXT(COUNTA($C$5:C20),"000")) | H20: =IF(E20="","",F20/E20) | K20: =IF(I20="","",J20/I20)
... B108: =IF(C108="","SPA-"&TEXT(COUNTA($C$5:C108),"000")) | H108: =IF(E108="","",F108/E108) | K108: =IF(I108="","",J108/I108)
B110: INDICATEURS (mis a jour automatiquement)
B111: Plans suivis | D111: Taux real. moyen (%) | F111: Budget total (FCFA)
B112: =COUNTIF(B5:B104,"<>") | D112: =IFERROR(AVERAGE(H5:H104),0) | F112: =SUM(I5:I104)

Sheet 15-Historique Bilans Sociaux
B2: HISTORIQUE BILANS SOCIAUX
B3: TABLEAU DYNAMIQUE — Saisissez dans la prochaine ligne jaune. Les calculs se mettent a jour automatiquement.
B4: N° | C4: Annee | D4: Effectif Moyen | E4: Taux Rotation (%) | F4: Nb Formations | G4: H Formation / Employe | H4: Masse Salariale (M FCFA) | I4: Nb Accidents Travail | J4: Absentéisme (%) | K4: Taux Satisfaction | L4: Statut | M4: Observations
B5: HBS-001 | C5: 2022 | D5: 150 | E5: 0.25 | F5: 42 | G5: 5.6 | H5: 82 | I5: 12 | J5: 0.07 | K5: 3.2 | L5: Archive | M5: Premier bilan complet apres COVID
B6: HBS-002 | C6: 2023 | D6: 165 | E6: 0.24 | F6: 55 | G6: 6.7 | H6: 95 | I6: 10 | J6: 0.062 | K6: 3.4 | L6: Archive | M6: Debut plan digitalisation
B7: HBS-003 | C7: 2024 | D7: 178 | E7: 0.22 | F7: 68 | G7: 7.6 | H7: 105 | I7: 8 | J7: 0.058 | K7: 3.5 | L7: Archive | M7: Amelioration continue
B8: =IF(C8="","HBS-"&TEXT(COUNTA($C$5:C8),"000"))
B9: =IF(C9="","HBS-"&TEXT(COUNTA($C$5:C9),"000"))
B10: =IF(C10="","HBS-"&TEXT(COUNTA($C$5:C10),"000"))
B11: =IF(C11="","HBS-"&TEXT(COUNTA($C$5:C11),"000"))
B12: =IF(C12="","HBS-"&TEXT(COUNTA($C$5:C12),"000"))
B13: =IF(C13="","HBS-"&TEXT(COUNTA($C$5:C13),"000"))
B14: =IF(C14="","HBS-"&TEXT(COUNTA($C$5:C14),"000"))
B15: =IF(C15="","HBS-"&TEXT(COUNTA($C$5:C15),"000"))
B16: =IF(C16="","HBS-"&TEXT(COUNTA($C$5:C16),"000"))
B17: =IF(C17="","HBS-"&TEXT(COUNTA($C$5:C17),"000"))
B18: =IF(C18="","HBS-"&TEXT(COUNTA($C$5:C18),"000"))
B19: =IF(C19="","HBS-"&TEXT(COUNTA($C$5:C19),"000"))
... B107: =IF(C107="","HBS-"&TEXT(COUNTA($C$5:C107),"000"))
B109: INDICATEURS (mis a jour automatiquement)
B110: Bilans archivés | D110: Rotation moy. (%) | F110: Satisfaction moy.
B111: =COUNTIF(B5:B104,"<>") | D111: =IFERROR(AVERAGE(E5:E104),0) | F111: =IFERROR(AVERAGE(K5:K104),0)

Sheet 16-Calendrier Reporting RH
B2: CALENDRIER REPORTING RH
B3: TABLEAU DYNAMIQUE — Saisissez dans la prochaine ligne jaune. Les calculs se mettent a jour automatiquement.
B4: N° | C4: Rapport / Livrable | D4: Type | E4: Destinataire | F4: Frequence | G4: Date Prochaine Emission | H4: Delai Preparation (j) | I4: Responsable Preparation | J4: Statut | K4: Observations
B5: CR-001 | C5: Activite RH mensuelle | D5: Activite mensuelle | E5: DG | F5: Mensuel | G5: 45752 | H5: 5 | I5: DRH | J5: En cours | K5: Template automatise
B6: CR-002 | C6: Bilan trimestriel RH | D6: Bilan trimestriel | E6: Comite de direction | F6: Trimestriel | G6: 45757 | H6: 10 | I6: DRH | J6: En cours | K6: Donnees Q1 compilees
B7: CR-003 | C7: Bilan social annuel | D7: Bilan social annuel | E7: CSE / Representants du personnel | F7: Annuel | G7: 45838 | H7: 30 | I7: DRH | J7: En cours | K7: Compilation depuis janvier
B8: CR-004 | C8: Dashboard KPI temps reel | D8: Tableau de bord KPI | E8: DG | F8: Mensuel | G8: 45748 | H8: 2 | I8: Chef de service IT | J8: En cours | K8: Power BI connecte SIRH
B9: CR-005 | C9: Rapport paie mensuel | D9: Reporting DG | E9: DAF | F9: Mensuel | G9: 45750 | H9: 3 | I9: DAF | J9: En cours | K9: Automatise via Lucca
B10: =IF(C10="","CR-"&TEXT(COUNTA($C$5:C10),"000"))
B11: =IF(C11="","CR-"&TEXT(COUNTA($C$5:C11),"000"))
B12: =IF(C12="","CR-"&TEXT(COUNTA($C$5:C12),"000"))
B13: =IF(C13="","CR-"&TEXT(COUNTA($C$5:C13),"000"))
B14: =IF(C14="","CR-"&TEXT(COUNTA($C$5:C14),"000"))
B15: =IF(C15="","CR-"&TEXT(COUNTA($C$5:C15),"000"))
B16: =IF(C16="","CR-"&TEXT(COUNTA($C$5:C16),"000"))
B17: =IF(C17="","CR-"&TEXT(COUNTA($C$5:C17),"000"))
B18: =IF(C18="","CR-"&TEXT(COUNTA($C$5:C18),"000"))
B19: =IF(C19="","CR-"&TEXT(COUNTA($C$5:C19),"000"))
B20: =IF(C20="","CR-"&TEXT(COUNTA($C$5:C20),"000"))
B21: =IF(C21="","CR-"&TEXT(COUNTA($C$5:C21),"000"))
... B109: =IF(C109="","CR-"&TEXT(COUNTA($C$5:C109),"000"))
B111: INDICATEURS (mis a jour automatiquement)
B112: Rapports planifies | D112: Mensuels | F112: En cours
B113: =COUNTIF(B5:B104,"<>") | D113: =COUNTIF(F5:F104,"Mensuel") | F113: =COUNTIF(J5:J104,"En cours")

Sheet 17-Matrice Indicateurs RH
B2: MATRICE INDICATEURS RH
B3: TABLEAU DYNAMIQUE — Saisissez dans la prochaine ligne jaune. Les calculs se mettent a jour automatiquement.
B4: N° | C4: Indicateur | D4: Processus RH | E4: Categorie | F4: Frequence | G4: Source Donnees | H4: Seuil Alerte | I4: Proprietaire | J4: Utilise Dans | K4: Priorite | L4: Observations
B5: MI-001 | C5: Taux rotation global | D5: Gestion effectif | E5: Ratio | F5: Mensuel | G5: SIRH | H5: >15% | I5: DRH | J5: TdB Global, Reporting DG, Bilan social | K5: Haute | L5: Indicateur phare du service RH
B6: MI-002 | C6: Delai moyen embauche | D6: Recrutement | E6: Temps | F6: Mensuel | G6: ATS + SIRH | H6: >30j | I6: Assistante RH | J6: TdB Global, Reporting DG, Benchmark | K6: Haute | L6: Suivi hebdomadaire interne
B7: MI-003 | C7: Cout moyen recrutement | D7: Recrutement | E7: Financier | F7: Trimestriel | G7: Comptabilite + SIRH | H7: >200k FCFA | I7: DRH | J7: Reporting DG, Budget RH, Benchmark | K7: Moyenne | L7: Inclure cout indirect
B8: MI-004 | C8: H formation / employe | D8: Formation | E8: Ratio | F8: Trimestriel | G8: SIRH + LMS | H8: <15h | I8: DRH | J8: TdB Global, Bilan social, Feuille route | K8: Haute | L8: Objectif 20h en 2025
B9: MI-005 | C9: Score satisfaction | D9: Climat social | E9: Score | F9: Semestriel | G9: Enquetes internes | H9: <3.5 | I9: DRH | J9: TdB Global, Reporting DG, Benchmark | K9: Haute | L9: Enquete Q1: 3.8/5
B10: MI-006 | C10: Taux absentéisme | D10: Presence | E10: Ratio | F10: Mensuel | G10: SIRH + Paie | H10: >5% | I10: DRH | J10: TdB Global, Bilan social, Reporting DG | K10: Haute | L10: Pic fevrier lie a grippe
B11: =IF(C11="","MI-"&TEXT(COUNTA($C$5:C11),"000"))
B12: =IF(C12="","MI-"&TEXT(COUNTA($C$5:C12),"000"))
B13: =IF(C13="","MI-"&TEXT(COUNTA($C$5:C13),"000"))
B14: =IF(C14="","MI-"&TEXT(COUNTA($C$5:C14),"000"))
B15: =IF(C15="","MI-"&TEXT(COUNTA($C$5:C15),"000"))
B16: =IF(C16="","MI-"&TEXT(COUNTA($C$5:C16),"000"))
B17: =IF(C17="","MI-"&TEXT(COUNTA($C$5:C17),"000"))
B18: =IF(C18="","MI-"&TEXT(COUNTA($C$5:C18),"000"))
B19: =IF(C19="","MI-"&TEXT(COUNTA($C$5:C19),"000"))
B20: =IF(C20="","MI-"&TEXT(COUNTA($C$5:C20),"000"))
B21: =IF(C21="","MI-"&TEXT(COUNTA($C$5:C21),"000"))
B22: =IF(C22="","MI-"&TEXT(COUNTA($C$5:C22),"000"))
... B110: =IF(C110="","MI-"&TEXT(COUNTA($C$5:C110),"000"))
B112: INDICATEURS (mis a jour automatiquement)
B113: Indicateurs cartes | D113: Priorite haute | F113: Sources SIRH
B114: =COUNTIF(B5:B104,"<>") | D114: =COUNTIF(K5:K104,"Haute") | F114: =COUNTIF(H5:H104,"SIRH*")

Sheet 18-Suivi Objectifs Strategiques
B2: SUIVI OBJECTIFS STRATEGIQUES RH
B3: TABLEAU DYNAMIQUE — Saisissez dans la prochaine ligne jaune. Les calculs se mettent a jour automatiquement.
B4: N° | C4: Objectif Strategique | D4: Axe Strategique | E4: Indicateur | F4: Cible 2025 | G4: Q1 2025 | H4: Q2 2025 (prev.) | I4: Ecart Q1 vs Cible | J4: Statut | K4: Actions Correctives
B5: SO-001 | C5: Reduire rotation a 12% | D5: Bien-Etre | E5: Taux rotation | F5: <=12% | G5: 0.18 | H5: 0.15 | J5: En retard | K5: Mentorat + bonus retention + bien-etre
B6: SO-002 | C6: 20h formation / employe | D6: Employabilite | E6: H form. / employe | F6: >=20 | G6: 12.5 | H6: 16 | J6: En retard | K6: E-learning obligatoire mensuel
B7: SO-003 | C7: Score satisfaction >= 4.0 | D7: Climat social | E7: Score satisfaction | F7: >=4.0 | G7: 3.8 | H7: 3.9 | J7: En cours | K7: Renforcer CSE et evenements
B8: SO-004 | C8: 80% processus automatises | D8: Performance | E8: % processus auto. | F8: >=80% | G8: 0.45 | H8: 0.6 | J8: En cours | K8: SIRH cloud + Lucca + chatbot
B9: SO-005 | C9: 100% conformite RGPD | D9: Conformite | E9: % conformite audits | F9: 100% | G9: 0.9 | H9: 0.95 | J9: En cours | K9: Numeriser dossier medical + audit Q2
B10: =IF(C10="","SO-"&TEXT(COUNTA($C$5:C10),"000")) | I10: =IF(OR(F10="",G10=""),"",G10-F10)
B11: =IF(C11="","SO-"&TEXT(COUNTA($C$5:C11),"000")) | I11: =IF(OR(F11="",G11=""),"",G11-F11)
B12: =IF(C12="","SO-"&TEXT(COUNTA($C$5:C12),"000")) | I12: =IF(OR(F12="",G12=""),"",G12-F12)
B13: =IF(C13="","SO-"&TEXT(COUNTA($C$5:C13),"000")) | I13: =IF(OR(F13="",G13=""),"",G13-F13)
B14: =IF(C14="","SO-"&TEXT(COUNTA($C$5:C14),"000")) | I14: =IF(OR(F14="",G14=""),"",G14-F14)
B15: =IF(C15="","SO-"&TEXT(COUNTA($C$5:C15),"000")) | I15: =IF(OR(F15="",G15=""),"",G15-F15)
B16: =IF(C16="","SO-"&TEXT(COUNTA($C$5:C16),"000")) | I16: =IF(OR(F16="",G16=""),"",G16-F16)
B17: =IF(C17="","SO-"&TEXT(COUNTA($C$5:C17),"000")) | I17: =IF(OR(F17="",G17=""),"",G17-F17)
B18: =IF(C18="","SO-"&TEXT(COUNTA($C$5:C18),"000")) | I18: =IF(OR(F18="",G18=""),"",G18-F18)
B19: =IF(C19="","SO-"&TEXT(COUNTA($C$5:C19),"000")) | I19: =IF(OR(F19="",G19=""),"",G19-F19)
B20: =IF(C20="","SO-"&TEXT(COUNTA($C$5:C20),"000")) | I20: =IF(OR(F20="",G20=""),"",G20-F20)
B21: =IF(C21="","SO-"&TEXT(COUNTA($C$5:C21),"000")) | I21: =IF(OR(F21="",G21=""),"",G21-F21)
... B109: =IF(C109="","SO-"&TEXT(COUNTA($C$5:C109),"000")) | I109: =IF(OR(F109="",G109=""),"",G109-F109)
B111: INDICATEURS (mis a jour automatiquement)
B112: Objectifs strategiques | D112: En cours | F112: En retard
B113: =COUNTIF(B5:B104,"<>") | D113: =COUNTIF(J5:J104,"En cours") | F113: =COUNTIF(J5:J104,"En retard")

Sheet 19-Analyse Benchmarking RH
B2: ANALYSE BENCHMARKING RH
B3: TABLEAU DYNAMIQUE — Saisissez dans la prochaine ligne jaune. Les calculs se mettent a jour automatiquement.
B4: N° | C4: Indicateur | D4: Notre Hotel 2023 | E4: Notre Hotel 2024 | F4: Evolution Interne | G4: Moyenne Sectorielle 4* | H4: Ecart vs Secteur | I4: Meilleur Pratique | J4: Ecart vs Meilleur | K4: Statut | L4: Observations
B5: ABM-001 | C5: Taux rotation (%) | D5: 24 | E5: 18 | G5: 22 | I5: 10 | K5: Bon | L5: Bonne progression, objectif 12%
B6: ABM-002 | C6: Delai embauche (j) | D6: 42 | E6: 28 | G6: 35 | I6: 14 | K6: Bon | L6: ATS + IA accelenent le processus
B7: ABM-003 | C7: H form. / employe | D7: 5.6 | E7: 7.6 | G7: 8 | I7: 15 | K7: Insuffisant | L7: Rattrapage en cours via e-learning
B8: ABM-004 | C8: Satisfaction employes | D8: 3.2 | E8: 3.5 | G8: 3.4 | I8: 4.5 | K8: Bon | L8: Programme bien-etre porte ses fruits
B9: ABM-005 | C9: Absentéisme (%) | D9: 7.5 | E9: 5.8 | G9: 7 | I9: 3.5 | K9: Moyen | L9: Amelioration mais encore au-dessus meilleur
B10: =IF(C10="","ABM-"&TEXT(COUNTA($C$5:C10),"000")) | F10: =IF(OR(D10="",E10=""),"",E10-D10) | H10: =IF(OR(E10="",G10=""),"",E10-G10) | J10: =IF(OR(E10="",I10=""),"",E10-I10)
B11: =IF(C11="","ABM-"&TEXT(COUNTA($C$5:C11),"000")) | F11: =IF(OR(D11="",E11=""),"",E11-D11) | H11: =IF(OR(E11="",G11=""),"",E11-G11) | J11: =IF(OR(E11="",I11=""),"",E11-I11)
B12: =IF(C12="","ABM-"&TEXT(COUNTA($C$5:C12),"000")) | F12: =IF(OR(D12="",E12=""),"",E12-D12) | H12: =IF(OR(E12="",G12=""),"",E12-G12) | J12: =IF(OR(E12="",I12=""),"",E12-I12)
B13: =IF(C13="","ABM-"&TEXT(COUNTA($C$5:C13),"000")) | F13: =IF(OR(D13="",E13=""),"",E13-D13) | H13: =IF(OR(E13="",G13=""),"",E13-G13) | J13: =IF(OR(E13="",I13=""),"",E13-I13)
B14: =IF(C14="","ABM-"&TEXT(COUNTA($C$5:C14),"000")) | F14: =IF(OR(D14="",E14=""),"",E14-D14) | H14: =IF(OR(E14="",G14=""),"",E14-G14) | J14: =IF(OR(E14="",I14=""),"",E14-I14)
B15: =IF(C15="","ABM-"&TEXT(COUNTA($C$5:C15),"000")) | F15: =IF(OR(D15="",E15=""),"",E15-D15) | H15: =IF(OR(E15="",G15=""),"",E15-G15) | J15: =IF(OR(E15="",I15=""),"",E15-I15)
B16: =IF(C16="","ABM-"&TEXT(COUNTA($C$5:C16),"000")) | F16: =IF(OR(D16="",E16=""),"",E16-D16) | H16: =IF(OR(E16="",G16=""),"",E16-G16) | J16: =IF(OR(E16="",I16=""),"",E16-I16)
B17: =IF(C17="","ABM-"&TEXT(COUNTA($C$5:C17),"000")) | F17: =IF(OR(D17="",E17=""),"",E17-D17) | H17: =IF(OR(E17="",G17=""),"",E17-G17) | J17: =IF(OR(E17="",I17=""),"",E17-I17)
B18: =IF(C18="","ABM-"&TEXT(COUNTA($C$5:C18),"000")) | F18: =IF(OR(D18="",E18=""),"",E18-D18) | H18: =IF(OR(E18="",G18=""),"",E18-G18) | J18: =IF(OR(E18="",I18=""),"",E18-I18)
B19: =IF(C19="","ABM-"&TEXT(COUNTA($C$5:C19),"000")) | F19: =IF(OR(D19="",E19=""),"",E19-D19) | H19: =IF(OR(E19="",G19=""),"",E19-G19) | J19: =IF(OR(E19="",I19=""),"",E19-I19)
B20: =IF(C20="","ABM-"&TEXT(COUNTA($C$5:C20),"000")) | F20: =IF(OR(D20="",E20=""),"",E20-D20) | H20: =IF(OR(E20="",G20=""),"",E20-G20) | J20: =IF(OR(E20="",I20=""),"",E20-I20)
B21: =IF(C21="","ABM-"&TEXT(COUNTA($C$5:C21),"000")) | F21: =IF(OR(D21="",E21=""),"",E21-D21) | H21: =IF(OR(E21="",G21=""),"",E21-G21) | J21: =IF(OR(E21="",I21=""),"",E21-I21)
... B109: =IF(C109="","ABM-"&TEXT(COUNTA($C$5:C109),"000")) | F109: =IF(OR(D109="",E109=""),"",E109-D109) | H109: =IF(OR(E109="",G109=""),"",E109-G109) | J109: =IF(OR(E109="",I109=""),"",E109-I109)
B111: INDICATEURS (mis a jour automatiquement)
B112: Indicateurs benchmark | D112: Au-dessus secteur | F112: En dessous meilleur
B113: =COUNTIF(B5:B104,"<>") | D113: =COUNTIF(H5:H104,"<0") | F113: =COUNTIF(J5:J104,">0")
