Workbook

Sheet _Données Employés
B4: Matricule | C4: Civilité | D4: Nom | E4: Prénom | F4: Département | G4: Poste | H4: Salaire Base (FCFA)
B5: EMP-001 | C5: M. | D5: Nganou | E5: Clarisse | F5: Cuisine & Restauration | G5: Chef cuisinier | H5: 450000
B6: EMP-002 | C6: M. | D6: Tchinda | E6: Armand | F6: Réception & Front Office | G6: Réceptionniste | H6: 220000
B7: EMP-003 | C7: Mme | D7: Fotso | E7: Marguerite | F7: Finance & Comptabilité | G7: Comptable senior | H7: 380000
B8: EMP-004 | C8: M. | D8: Nkoulou | E8: Mbarga | F8: Étage & Housekeeping | G8: Gouvernant | H8: 195000
B9: EMP-005 | C9: M. | D9: Kamga | E9: Paul | F9: Maintenance | G9: Technicien maintenance | H9: 165000
B10: EMP-006 | C10: Mme | D10: Ngo | E10: Delphine | F10: Service Client | G10: Conseiller clientèle | H10: 160000
B11: EMP-007 | C11: M. | D11: Essomba | E11: Serge | F11: Maintenance | G11: Agent entretien | H11: 130000
B12: EMP-008 | C12: M. | D12: Tchouankou | E12: Paul | F12: Commercial | G12: Commercial | H12: 150000
B13: EMP-009 | C13: M. | D13: Fokam | E13: Eric | F13: Maintenance | G13: Technicien | H13: 140000
B14: EMP-010 | C14: M. | D14: Tagne | E14: René | F14: Cuisine & Restauration | G14: Plongeur | H14: 90000
B15: EMP-011 | C15: M. | D15: Bouba | E15: Ahmed | F15: Sécurité | G15: Agent Sécurité | H15: 120000
B16: EMP-012 | C16: Mme | D16: Awa | E16: Fatou | F16: Réception & Front Office | G16: Standardiste | H16: 155000
... B18: EMP-029 | C18: M. | D18: Kamga | E18: Patrice | F18: Sécurité | G18: Chef Sécurité | H18: 210000

Sheet 1-Tableau de Bord
B2: DOMAINE 8 — RELATIONS SOCIALES, SYNDICATS & INSTANCES REP.
B3: TABLEAU DE BORD — Vue synthetique de tous les indicateurs du domaine (mis a jour automatiquement)
B5: Syndicats actifs | E5: Delegues en mandat | H5: Reunions CSE tenues | K5: Accords en vigueur
B6: =COUNTIF('2-Registre Syndicats'!K:K,"Actif") | E6: =COUNTIF('3-Delegues du Personnel'!L:L,"En mandat") | H6: =COUNTIF('4-Comite d''Entreprise CSE'!M:M,"Tenue") | K6: =COUNTIFS('5-Protocoles Accords Coll.'!J:J,"En vigueur")+COUNTIFS('5-Protocoles Accords Coll.'!J:J,"Signe")
B9: Conflits en cours | E9: Negociations en cours | H9: Reclamations actives | K9: Procedures disciplinaires
B10: =COUNTIF('6-Greves & Conflits Sociaux'!M:M,"En cours")+COUNTIF('6-Greves & Conflits Sociaux'!M:M,"Signale") | E10: =COUNTIF('7-Negociations Collectives'!O:O,"En cours")+COUNTIF('7-Negociations Collectives'!O:O,"Planifiee") | H10: =COUNTIFS('8-Reclamations Personnel'!R:R,"Recue")+COUNTIFS('8-Reclamations Personnel'!R:R,"En cours d'instruction") | K10: =COUNTA('9-Procedures Disciplinaires'!B5:B104)
B13: Mediations en cours | E13: Cout conflits (FCFA) | H13: Heures syndicales ut. | K13: Mesures correct. en cours
B14: =COUNTIF('10-Mediation & Arbitrage'!L5:L104,"En cours") | E14: =SUM('6-Greves & Conflits Sociaux'!K5:K104) | H14: =SUM('12-Suivi Droit Syndical'!H5:H104) | K14: =COUNTIF('18-Suivi Mesures Correct.'!L5:L104,"En cours")
B18: RECLAMATIONS PAR TYPE & CONFLITS PAR DEPARTEMENT
B19: Departement | C19: Nb Conflits
B20: Cuisine | C20: =COUNTIF('6-Greves & Conflits Sociaux'!G5:G104,"*Cuisine*")
B21: Entretien | C21: =COUNTIF('6-Greves & Conflits Sociaux'!G5:G104,"*Entretien*")
B22: Reception | C22: =COUNTIF('6-Greves & Conflits Sociaux'!G5:G104,"*Reception*")
B23: Service Client | C23: =COUNTIF('6-Greves & Conflits Sociaux'!G5:G104,"*Service Client*")
B24: Sécurité | C24: =COUNTIF('6-Greves & Conflits Sociaux'!G5:G104,"*Securite*")
H26: Statut Reclamation | I26: Nb
H27: Cloturee | I27: =COUNTIF('8-Reclamations Personnel'!M5:M104,"Cloturee")
H28: En cours d'instruction | I28: =COUNTIF('8-Reclamations Personnel'!M5:M104,"En cours d'instruction")
H29: Recue | I29: =COUNTIF('8-Reclamations Personnel'!M5:M104,"Recue")
H30: Transferee N+1 | I30: =COUNTIF('8-Reclamations Personnel'!M5:M104,"Transferee N+1")
H31: Escaladee direction | I31: =COUNTIF('8-Reclamations Personnel'!M5:M104,"Escaladee direction")

Sheet _Lists
B1: departement | C1: poste_hotel | D1: type_syndicat | E1: type_instance | F1: statut_syndicat | G1: statut_delegue | H1: statut_reunion | I1: type_accord | J1: statut_accord | K1: type_conflit | L1: gravite_conflit | M1: statut_conflit | N1: type_nego | O1: statut_nego | P1: type_reclamation | Q1: gravite_reclamation | R1: statut_reclamation | S1: type_faute | T1: type_sanction | U1: statut_procedure | V1: type_mediation | W1: statut_mediation | X1: mois | Y1: annee | Z1: statut_rapport
B2: Direction Générale | C2: DG | D2: CSTT | E2: CSE | F2: Actif | G2: En mandat | H2: Planifiee | I2: Accord salarial | J2: En negociation | K2: Greve revendicative | L2: Faible | M2: En cours | N2: Negociation annuelle obligatoire (NAO) | O2: Planifiee | P2: Salaires & primes | Q2: Mineure | R2: Recue | S2: Absence injustifiee | T2: Avertissement oral | U2: Enquete ouverte | V2: Mediation interne RH | W2: Saisie | X2: Janvier | Y2: 2024 | Z2: Brouillon
B3: Service Client | C3: DRH | D3: CSA | E3: Delegues du Personnel | F3: Inactif | G3: Fin de mandat | H3: Tenue | I3: Accord d'entreprise | J3: Signe | K3: Grve de solidarite | L3: Moyen | M3: Resolu | N3: Negociation salariale | O3: En cours | P3: Conditions de travail | Q3: Moderee | R3: En cours d'instruction | S3: Retards repetes | T3: Avertissement ecrit | U3: Convocation envoyee | V3: Mediation par CSE | W3: En cours | X3: Fevrier | Y3: 2025 | Z3: Valide
B4: Finance & Comptabilité | C4: Assistante RH | D4: CSC | E4: CHSCT | F4: En cours de repres. | G4: Demissionnaire | H4: Reportee | I4: Convention collective | J4: Depose | K4: Conflit individuel | L4: Eleve | M4: En mediation | N4: Negociation temps de travail | O4: Terminee | P4: Harcelement | Q4: Grave | R4: Transferee N+1 | S4: Insolence | T4: Blame | U4: Entretien realise | V4: Conciliation inspecteur travail | W4: Terminee - Accord | X4: Mars | Y4: 2026 | Z4: Approuve
B5: Marketing & Communication | C5: DAF | D5: CGT-L | E5: Commission formation | F5: Dissous | G5: Revoque | H5: Annulee | I5: Protocole precontentieux | J5: En vigueur | K5: Conflit collectif | L5: Critique | M5: Echoue | N5: Negociation conditions de travail | O5: Echouee | P5: Discrimination | Q5: Tres grave | R5: Traitee | S5: Insubordination | T5: Mise a pied disciplinaire | U5: Decision notifiee | V5: Arbitrage tribunal | W5: Terminee - Echec | X5: Avril | Z5: Rejete
B6: Maintenance | C6: Comptable senior | D6: CFTC | E6: Commission logement | F6: Suspendu | G6: En attente election | H6: En preparation | I6: Accord de methode | J6: Expire | K6: Arret de travail | M6: Signale | N6: Negociation formation | O6: Reportee | P6: Horaires | R6: Rejetee | S6: Vol | T6: Mutation disciplinaire | U6: En recours | V6: Mediation externe | W6: Abandonnee | X6: Mai
B7: Commercial | C7: Chef Comptable | D7: CFDT | E7: Commission egalite professionnelle | I7: Accord sur les conditions de travail | J7: Denonce | K7: Manifestation | M7: Precontentieux | N7: Negociation egalite prof. | O7: Suspendue | P7: Conges | R7: En attente reponse | S7: Négligence grave | T7: Retrogradation | U7: Cloturee | W7: Reportee | X7: Juin
B8: Logistique & Approvisionnement | C8: Chef Marketing | D8: FO | I8: Avenant | J8: Rejete | K8: Picket de greve | M8: Jugement rendu | N8: Negociation exceptionnelle | P8: Securite | R8: Cloturee | S8: Rupture de confidentialite | T8: Licenciement pour faute | U8: Annulee | X8: Juillet
B9: Production | C9: Chef de service IT | D9: Syndicat autonome hotelier | P9: Relation avec N+1 | R9: Escaladee direction | S9: Violence verbale | T9: Licenciement pour faute grave | X9: Aout
B10: Réception & Front Office | C10: Technicien IT | D10: Syndicat des travailleurs du tourisme | P10: Logement | S10: Violence physique | X10: Septembre
B11: Cuisine & Restauration | C11: Chef Commercial | D11: Sans syndicat | P11: Transport | S11: Ivresse au travail | X11: Octobre
B12: Sécurité | C12: Agent Commercial | P12: Formation | S12: Non respect procedures securite | X12: Novembre
B13: Étage & Housekeeping | C13: Chef Logistique | S13: Fausse declaration | X13: Decembre
C14: Magasinier
C15: Chef Reception
C16: Receptionniste
C17: Concierge
C18: Chef Cuisine
C19: Sous-Chef
C20: Cuisinier
C21: Plongeur
C22: Chef Entretien
C23: Agent Entretien
C24: Chef Securite
C25: Agent Securite

Sheet 2-Registre Syndicats
B2: REGISTRE DES SYNDICATS (#87)
B3: TABLEAU DYNAMIQUE — Saisissez dans la prochaine ligne jaune. Les calculs se mettent a jour automatiquement.
B4: N° Syndicat | C4: Nom Syndicat | D4: Sigle | E4: Type | F4: Representant Local | G4: Contact | H4: Date Reconnaissance | I4: Nb Adherents | J4: Departement Principal | K4: Statut
B5: SYN-001 | C5: Confederation Syndicale des Travailleurs du Togo | D5: CSTT | E5: CSTT | F5: Koffi Amevi | G5: 690123456 | H5: 43174 | I5: 12 | J5: Cuisine & Restauration | K5: Actif
B6: SYN-002 | C6: Confederation Syndicale Autonome | D6: CSA | E6: CSA | F6: Mensah Kodjo | G6: 697654321 | H6: 43647 | I6: 8 | J6: Maintenance | K6: Actif
B7: SYN-003 | C7: Confederation Syndicale des Cadres | D7: CSC | E7: CSC | F7: Aguiar Maria | G7: 698111222 | H7: 43840 | I7: 5 | J7: Service Client | K7: Actif
B8: SYN-004 | C8: Syndicat Autonome des Hotels | D8: SAH | E8: Syndicat autonome hotelier | F8: Dossou Yves | G8: 690333444 | H8: 44367 | I8: 15 | J8: Réception & Front Office | K8: En cours de repres.
B9: SYN-005 | C9: Syndicat Travailleurs Tourisme | D9: STT | E9: Syndicat des travailleurs du tourisme | F9: Hounkpe Patrice | G9: 691555666 | H9: 43044 | I9: 3 | J9: Service Client | K9: Actif
B10: =IF(C10="","SYN-"&TEXT(COUNTA($C$5:C10),"000"))
B11: =IF(C11="","SYN-"&TEXT(COUNTA($C$5:C11),"000"))
B12: =IF(C12="","SYN-"&TEXT(COUNTA($C$5:C12),"000"))
B13: =IF(C13="","SYN-"&TEXT(COUNTA($C$5:C13),"000"))
B14: =IF(C14="","SYN-"&TEXT(COUNTA($C$5:C14),"000"))
B15: =IF(C15="","SYN-"&TEXT(COUNTA($C$5:C15),"000"))
B16: =IF(C16="","SYN-"&TEXT(COUNTA($C$5:C16),"000"))
B17: =IF(C17="","SYN-"&TEXT(COUNTA($C$5:C17),"000"))
B18: =IF(C18="","SYN-"&TEXT(COUNTA($C$5:C18),"000"))
B19: =IF(C19="","SYN-"&TEXT(COUNTA($C$5:C19),"000"))
B20: =IF(C20="","SYN-"&TEXT(COUNTA($C$5:C20),"000"))
B21: =IF(C21="","SYN-"&TEXT(COUNTA($C$5:C21),"000"))
... B109: =IF(C109="","SYN-"&TEXT(COUNTA($C$5:C109),"000"))
B111: TOTAL | I111: =SUM(I5:I104)
B113: INDICATEURS (mis a jour automatiquement)
B114: Syndicats enregistres | D114: Total adherents | F114: Syndicats actifs | H114: En cours repres.
B115: =COUNTIF(B5:B104,"<>") | D115: =SUM(I5:I104) | F115: =COUNTIF(K5:K104,"Actif") | H115: =COUNTIF(K5:K104,"En cours de repres.")

Sheet 3-Delegues du Personnel
B2: DELEGUES DU PERSONNEL (#88)
B3: TABLEAU DYNAMIQUE — Saisissez dans la prochaine ligne jaune. Les calculs se mettent a jour automatiquement.
B4: N° | C4: Matricule | D4: Nom Delegue | E4: Departement | F4: Poste | G4: Syndicat | H4: Mandat | I4: Debut Mandat | J4: Fin Mandat | K4: Nb Reunions | L4: Statut
B5: DP-001 | C5: EMP-010 | D5: =IF(C5="","",VLOOKUP(C5,'_Données Employés'!$B$5:$H$18,4,FALSE)&" "&VLOOKUP(C5,'_Données Employés'!$B$5:$H$18,5,FALSE)) | E5: =IF(C5="","",VLOOKUP(C5,'_Données Employés'!$B$5:$H$18,6,FALSE)) | F5: =IF(C5="","",VLOOKUP(C5,'_Données Employés'!$B$5:$H$18,7,FALSE)) | G5: CSTT | H5: 2eme mandat | I5: 45017 | J5: 46112 | K5: 24 | L5: En mandat
B6: DP-002 | C6: EMP-015 | D6: Mensah Kodjo | E6: Entretien & Maintenance | F6: Agent Entretien | G6: CSA | H6: 1er mandat | I6: 45383 | J6: 46477 | K6: 12 | L6: En mandat
B7: DP-003 | C7: EMP-022 | D7: Aguiar Maria | E7: Ressources Humaines | F7: Assistante RH | G7: CSC | H7: 1er mandat | I7: 45383 | J7: 46477 | K7: 10 | L7: En mandat
B8: DP-004 | C8: EMP-008 | D8: =IF(C8="","",VLOOKUP(C8,'_Données Employés'!$B$5:$H$18,4,FALSE)&" "&VLOOKUP(C8,'_Données Employés'!$B$5:$H$18,5,FALSE)) | E8: =IF(C8="","",VLOOKUP(C8,'_Données Employés'!$B$5:$H$18,6,FALSE)) | F8: =IF(C8="","",VLOOKUP(C8,'_Données Employés'!$B$5:$H$18,7,FALSE)) | G8: SAH | H8: 1er mandat | I8: 45383 | J8: 46477 | K8: 8 | L8: En mandat
B9: =IF(C9="","DP-"&TEXT(COUNTA($C$5:C9),"000"))
B10: =IF(C10="","DP-"&TEXT(COUNTA($C$5:C10),"000"))
B11: =IF(C11="","DP-"&TEXT(COUNTA($C$5:C11),"000"))
B12: =IF(C12="","DP-"&TEXT(COUNTA($C$5:C12),"000"))
B13: =IF(C13="","DP-"&TEXT(COUNTA($C$5:C13),"000"))
B14: =IF(C14="","DP-"&TEXT(COUNTA($C$5:C14),"000"))
B15: =IF(C15="","DP-"&TEXT(COUNTA($C$5:C15),"000"))
B16: =IF(C16="","DP-"&TEXT(COUNTA($C$5:C16),"000"))
B17: =IF(C17="","DP-"&TEXT(COUNTA($C$5:C17),"000"))
B18: =IF(C18="","DP-"&TEXT(COUNTA($C$5:C18),"000"))
B19: =IF(C19="","DP-"&TEXT(COUNTA($C$5:C19),"000"))
B20: =IF(C20="","DP-"&TEXT(COUNTA($C$5:C20),"000"))
... B108: =IF(C108="","DP-"&TEXT(COUNTA($C$5:C108),"000"))
B110: TOTAL | K110: =SUM(K5:K104)
B112: INDICATEURS (mis a jour automatiquement)
B113: Delegues enregistrés | D113: En mandat | F113: Total reunions | H113: Nb syndicats rep.
B114: =COUNTIF(B5:B104,"<>") | D114: =COUNTIF(L5:L104,"En mandat") | F114: =SUM(K5:K104) | H114: =SUMPRODUCT(1/COUNTIF(G5:G104,G5:G104&""))

Sheet 4-Comite d'Entreprise CSE
B2: COMITE D'ENTREPRISE / CSE (#89)
B3: TABLEAU DYNAMIQUE — Saisissez dans la prochaine ligne jaune. Les calculs se mettent a jour automatiquement.
B4: N° Reunion | C4: Type Instance | D4: Ordre du Jour | E4: Date Reunion | F4: Lieu | G4: Nb Participants | H4: Nb Absents | I4: Decisions Prises | J4: Suite a Donner | K4: Date Prochaine | L4: Rapporteur | M4: Statut
B5: CSE-001 | C5: CSE | D5: Budget social 2025 & oeuvres sociales | E5: 45677 | F5: Salle reunion A | G5: 12 | H5: 2 | I5: Validation budget 15M FCFA | J5: Suivi execution budget | K5: 45767 | L5: DRH Nganou | M5: Tenue
B6: CSE-002 | C6: CSE | D6: Conditions de travail saison haute | E6: 45731 | F6: Salle reunion A | G6: 10 | H6: 4 | I6: Heures sup. majorees 25% | J6: Negocier primes saison | K6: 45823 | L6: DRH Nganou | M6: Tenue
B7: CSE-003 | C7: CHSCT | D7: Audit securite cuisine & entretien | E7: 45757 | F7: Salle reunion B | G7: 8 | H7: 1 | I7: 3 actions correctives identifiees | J7: Plan action securite Q2 | K7: 45848 | L7: Chef Securite | M7: Tenue
B8: CSE-004 | C8: Commission formation | D8: Plan formation annuel 2025 | E8: 45693 | F8: Salle reunion A | G8: 6 | H8: 2 | I8: PAF valide 8.5M FCFA | J8: Lancer inscriptions T2 | K8: 45782 | L8: Assistante RH | M8: Tenue
B9: CSE-005 | C9: CSE | D9: Bilan oeuvres sociales 1er semestre | E9: 45856 | F9: Salle reunion A | G9: 11 | H9: 3 | I9: A reporter | J9: Preparer bilan S1 | K9: 45948 | L9: DRH Nganou | M9: Planifiee
B10: =IF(C10="","CSE-"&TEXT(COUNTA($C$5:C10),"000"))
B11: =IF(C11="","CSE-"&TEXT(COUNTA($C$5:C11),"000"))
B12: =IF(C12="","CSE-"&TEXT(COUNTA($C$5:C12),"000"))
B13: =IF(C13="","CSE-"&TEXT(COUNTA($C$5:C13),"000"))
B14: =IF(C14="","CSE-"&TEXT(COUNTA($C$5:C14),"000"))
B15: =IF(C15="","CSE-"&TEXT(COUNTA($C$5:C15),"000"))
B16: =IF(C16="","CSE-"&TEXT(COUNTA($C$5:C16),"000"))
B17: =IF(C17="","CSE-"&TEXT(COUNTA($C$5:C17),"000"))
B18: =IF(C18="","CSE-"&TEXT(COUNTA($C$5:C18),"000"))
B19: =IF(C19="","CSE-"&TEXT(COUNTA($C$5:C19),"000"))
B20: =IF(C20="","CSE-"&TEXT(COUNTA($C$5:C20),"000"))
B21: =IF(C21="","CSE-"&TEXT(COUNTA($C$5:C21),"000"))
... B109: =IF(C109="","CSE-"&TEXT(COUNTA($C$5:C109),"000"))
B111: TOTAL | G111: =SUM(G5:G104) | H111: =SUM(H5:H104)
B113: INDICATEURS (mis a jour automatiquement)
B114: Reunions | D114: Tenues | F114: Planifiees | H114: Taux participation (%)
B115: =COUNTIF(B5:B104,"<>") | D115: =COUNTIF(M5:M104,"Tenue") | F115: =COUNTIF(M5:M104,"Planifiee") | H115: =IFERROR(SUM(G5:G104)/(SUM(G5:G104)+SUM(H5:H104)),0)

Sheet 5-Protocoles Accords Coll.
B2: PROTOCOLES & ACCORDS COLLECTIFS (#90)
B3: TABLEAU DYNAMIQUE — Saisissez dans la prochaine ligne jaune. Les calculs se mettent a jour automatiquement.
B4: N° Accord | C4: Type Accord | D4: Objet / Titre | E4: Date Signature | F4: Partie Patronale | G4: Partie Syndicale | H4: Date Depot | I4: Date Application | J4: Duree (mois) | K4: Date Expiration | L4: Statut
B5: AC-001 | C5: Accord salarial | D5: Revalorisation salariale 2025 | E5: 45672 | F5: DG Fotso Paul | G5: CSTT + CSA | H5: 45677 | I5: 45689 | J5: 12 | K5: 46053 | L5: En vigueur
B6: AC-002 | C6: Accord d'entreprise | D6: Teletravail partiel IT | E6: 45536 | F6: DG Fotso Paul | G6: CSC | H6: 45550 | I6: 45566 | J6: 24 | K6: 46295 | L6: En vigueur
B7: AC-003 | C7: Convention collective | D7: Application CCT Hotelier | E7: 43891 | F7: Direction | G7: Ensemble syndicats | H7: 43900 | I7: 43922 | J7: 60 | K7: 45747 | L7: Expire
B8: AC-004 | C8: Protocole precontentieux | D8: Resolution conflit horaires | E8: 45787 | F8: DRH Nganou | G8: CSTT | H8: 45792 | I8: 45793 | J8: 6 | K8: 45976 | L8: En vigueur
B9: AC-005 | C9: Avenant | D9: Revision prime panier restauration | E9: 45717 | F9: DRH Nganou | G9: CSE | H9: 45721 | I9: 45748 | J9: 12 | K9: 46112 | L9: En vigueur
B10: =IF(C10="","AC-"&TEXT(COUNTA($C$5:C10),"000"))
B11: =IF(C11="","AC-"&TEXT(COUNTA($C$5:C11),"000"))
B12: =IF(C12="","AC-"&TEXT(COUNTA($C$5:C12),"000"))
B13: =IF(C13="","AC-"&TEXT(COUNTA($C$5:C13),"000"))
B14: =IF(C14="","AC-"&TEXT(COUNTA($C$5:C14),"000"))
B15: =IF(C15="","AC-"&TEXT(COUNTA($C$5:C15),"000"))
B16: =IF(C16="","AC-"&TEXT(COUNTA($C$5:C16),"000"))
B17: =IF(C17="","AC-"&TEXT(COUNTA($C$5:C17),"000"))
B18: =IF(C18="","AC-"&TEXT(COUNTA($C$5:C18),"000"))
B19: =IF(C19="","AC-"&TEXT(COUNTA($C$5:C19),"000"))
B20: =IF(C20="","AC-"&TEXT(COUNTA($C$5:C20),"000"))
B21: =IF(C21="","AC-"&TEXT(COUNTA($C$5:C21),"000"))
... B109: =IF(C109="","AC-"&TEXT(COUNTA($C$5:C109),"000"))
B111: INDICATEURS (mis a jour automatiquement)
B112: Accords enreg. | D112: En vigueur | F112: Signes | H112: Expires
B113: =COUNTIF(B5:B104,"<>") | D113: =COUNTIF(L5:L104,"En vigueur") | F113: =COUNTIF(L5:L104,"Signe") | H113: =COUNTIF(L5:L104,"Expire")

Sheet 6-Greves & Conflits Sociaux
B2: GREVES & CONFLITS SOCIAUX (#91)
B3: TABLEAU DYNAMIQUE — Saisissez dans la prochaine ligne jaune. Les calculs se mettent a jour automatiquement.
B4: N° Conflit | C4: Type Conflit | D4: Date Debut | E4: Date Fin | F4: Duree (jours) | G4: Departement Concerne | H4: Nb Participants | I4: Motif Principal | J4: Gravite | K4: Cout Estime (FCFA) | L4: Statut | M4: Resolution
B5: GRL-001 | C5: Greve revendicative | D5: 45698 | E5: 45700 | F5: 2 | G5: Cuisine & Restauration | H5: 8 | I5: Augmentation salariale | J5: Eleve | K5: 1200000 | L5: Resolu | M5: Accord salarial signe
B6: GRL-002 | C6: Arret de travail | D6: 45752 | E6: 45752 | F6: 1 | G6: Maintenance | H6: 4 | I6: Non paiement heures sup. | J6: Moyen | K6: 150000 | L6: Resolu | M6: Paiement effectue
B7: GRL-003 | C7: Conflit individuel | D7: 45797 | E7: 45823 | F7: 26 | G7: Réception & Front Office | H7: 1 | I7: Harcelement allege N+1 | J7: Grave | K7: 200000 | L7: En mediation | M7: Mediation CSE en cours
B8: GRL-004 | C8: Greve revendicative | D8: 45646 | E8: 45648 | F8: 2 | G8: Service Client | H8: 6 | I8: Prime de fin d'annee | J8: Moyen | K8: 800000 | L8: Resolu | M8: Prime versee a 100%
B9: GRL-005 | C9: Arret de travail | D9: 45836 | F9: 0 | G9: Cuisine & Restauration | H9: 5 | I9: Conditions securite cuisine | J9: Eleve | K9: 0 | L9: En cours | M9: En attente inspection
B10: =IF(C10="","GRL-"&TEXT(COUNTA($C$5:C10),"000")) | F10: =IF(D10="","",E10-D10)
B11: =IF(C11="","GRL-"&TEXT(COUNTA($C$5:C11),"000")) | F11: =IF(D11="","",E11-D11)
B12: =IF(C12="","GRL-"&TEXT(COUNTA($C$5:C12),"000")) | F12: =IF(D12="","",E12-D12)
B13: =IF(C13="","GRL-"&TEXT(COUNTA($C$5:C13),"000")) | F13: =IF(D13="","",E13-D13)
B14: =IF(C14="","GRL-"&TEXT(COUNTA($C$5:C14),"000")) | F14: =IF(D14="","",E14-D14)
B15: =IF(C15="","GRL-"&TEXT(COUNTA($C$5:C15),"000")) | F15: =IF(D15="","",E15-D15)
B16: =IF(C16="","GRL-"&TEXT(COUNTA($C$5:C16),"000")) | F16: =IF(D16="","",E16-D16)
B17: =IF(C17="","GRL-"&TEXT(COUNTA($C$5:C17),"000")) | F17: =IF(D17="","",E17-D17)
B18: =IF(C18="","GRL-"&TEXT(COUNTA($C$5:C18),"000")) | F18: =IF(D18="","",E18-D18)
B19: =IF(C19="","GRL-"&TEXT(COUNTA($C$5:C19),"000")) | F19: =IF(D19="","",E19-D19)
B20: =IF(C20="","GRL-"&TEXT(COUNTA($C$5:C20),"000")) | F20: =IF(D20="","",E20-D20)
B21: =IF(C21="","GRL-"&TEXT(COUNTA($C$5:C21),"000")) | F21: =IF(D21="","",E21-D21)
... B109: =IF(C109="","GRL-"&TEXT(COUNTA($C$5:C109),"000")) | F109: =IF(D109="","",E109-D109)
B111: TOTAL | H111: =SUM(H5:H104) | K111: =SUM(K5:K104)
B113: INDICATEURS (mis a jour automatiquement)
B114: Conflits enregistres | D114: Resolus | F114: En cours | H114: Cout total (FCFA)
B115: =COUNTIF(B5:B104,"<>") | D115: =COUNTIF(L5:L104,"Resolu") | F115: =COUNTIF(L5:L104,"En cours") | H115: =SUM(K5:K104)

Sheet 7-Negociations Collectives
B2: NEGOCIATIONS COLLECTIVES (#92)
B3: TABLEAU DYNAMIQUE — Saisissez dans la prochaine ligne jaune. Les calculs se mettent a jour automatiquement.
B4: N° Nego | C4: Type Negociation | D4: Objet | E4: Date Debut | F4: Date Fin | G4: Partie Patronale | H4: Syndicats Impliques | I4: Nb Sessions | J4: Resultat | K4: Accord Lie (N°) | L4: Statut
B5: NGO-001 | C5: NAO | D5: Negociation annuelle obligatoire 2025 | E5: 45667 | F5: 45731 | G5: DG + DRH | H5: CSTT, CSA, CSC | I5: 8 | J5: Augmentation 5% signee | K5: AC-001 | L5: Terminee
B6: NGO-002 | C6: Negociation salariale | D6: Revision grilles salariales | E6: 45748 | F6: 45807 | G6: DRH | H6: CSTT, SAH | I6: 5 | J6: En cours de discussion | L6: En cours
B7: NGO-003 | C7: Negociation temps de travail | D7: Amenagement horaires Ramadan | E7: 45703 | F7: 45716 | G7: DRH | H7: CSE | I7: 3 | J7: Horaires aménagés valides | L7: Terminee
B8: NGO-004 | C8: Negociation egalite prof. | D8: Ecart salarial homme/femme | E8: 45809 | G8: DRH | H8: CSC | I8: 2 | J8: Audit en cours | L8: En cours
B9: =IF(C9="","NGO-"&TEXT(COUNTA($C$5:C9),"000"))
B10: =IF(C10="","NGO-"&TEXT(COUNTA($C$5:C10),"000"))
B11: =IF(C11="","NGO-"&TEXT(COUNTA($C$5:C11),"000"))
B12: =IF(C12="","NGO-"&TEXT(COUNTA($C$5:C12),"000"))
B13: =IF(C13="","NGO-"&TEXT(COUNTA($C$5:C13),"000"))
B14: =IF(C14="","NGO-"&TEXT(COUNTA($C$5:C14),"000"))
B15: =IF(C15="","NGO-"&TEXT(COUNTA($C$5:C15),"000"))
B16: =IF(C16="","NGO-"&TEXT(COUNTA($C$5:C16),"000"))
B17: =IF(C17="","NGO-"&TEXT(COUNTA($C$5:C17),"000"))
B18: =IF(C18="","NGO-"&TEXT(COUNTA($C$5:C18),"000"))
B19: =IF(C19="","NGO-"&TEXT(COUNTA($C$5:C19),"000"))
B20: =IF(C20="","NGO-"&TEXT(COUNTA($C$5:C20),"000"))
... B108: =IF(C108="","NGO-"&TEXT(COUNTA($C$5:C108),"000"))
B110: TOTAL | I110: =SUM(I5:I104)
B112: INDICATEURS (mis a jour automatiquement)
B113: Negociations | D113: Terminees | F113: En cours | H113: Total sessions
B114: =COUNTIF(B5:B104,"<>") | D114: =COUNTIF(L5:L104,"Terminee") | F114: =COUNTIF(L5:L104,"En cours") | H114: =SUM(I5:I104)

Sheet 8-Reclamations Personnel
B2: RECLAMATIONS DU PERSONNEL (#93)
B3: TABLEAU DYNAMIQUE — Saisissez dans la prochaine ligne jaune. Les calculs se mettent a jour automatiquement.
B4: N° Reclamation | C4: Matricule | D4: Nom Employe | E4: Departement | F4: Poste | G4: Type Reclamation | H4: Description | I4: Date Reclamation | J4: Gravite | K4: Delai Traitement (j) | L4: Reponse Donnee | M4: Statut
B5: REC-001 | C5: EMP-010 | D5: =IF(C5="","",VLOOKUP(C5,'_Données Employés'!$B$5:$H$18,4,FALSE)&" "&VLOOKUP(C5,'_Données Employés'!$B$5:$H$18,5,FALSE)) | E5: =IF(C5="","",VLOOKUP(C5,'_Données Employés'!$B$5:$H$18,6,FALSE)) | F5: =IF(C5="","",VLOOKUP(C5,'_Données Employés'!$B$5:$H$18,7,FALSE)) | G5: Salaires & primes | H5: Non paiement prime de nuit decembre | I5: 45667 | J5: Moderee | K5: 5 | L5: Prime versee avec retroactivite | M5: Cloturee
B6: REC-002 | C6: EMP-009 | D6: =IF(C6="","",VLOOKUP(C6,'_Données Employés'!$B$5:$H$18,4,FALSE)&" "&VLOOKUP(C6,'_Données Employés'!$B$5:$H$18,5,FALSE)) | E6: =IF(C6="","",VLOOKUP(C6,'_Données Employés'!$B$5:$H$18,6,FALSE)) | F6: =IF(C6="","",VLOOKUP(C6,'_Données Employés'!$B$5:$H$18,7,FALSE)) | G6: Horaires | H6: Changement horaires sans preavis | I6: 45721 | J6: Mineure | K6: 3 | L6: Horaires revenus a l'initial | M6: Cloturee
B7: REC-003 | C7: EMP-025 | D7: Ngo Linda | E7: Service Client | F7: Conseiller | G7: Harcelement | H7: Attitudes inappropriées N+1 | I7: 45789 | J7: Tres grave | K7: 0 | M7: En cours d'instruction
B8: REC-004 | C8: EMP-030 | D8: Tchouanku Marc | E8: Reception & Front Office | F8: Receptionniste | G8: Conges | H8: Report conges annuels sans motif valable | I8: 45809 | J8: Moderee | K8: 7 | L8: Conges reprogrammés en aout | M8: Cloturee
B9: REC-005 | C9: EMP-012 | D9: =IF(C9="","",VLOOKUP(C9,'_Données Employés'!$B$5:$H$18,4,FALSE)&" "&VLOOKUP(C9,'_Données Employés'!$B$5:$H$18,5,FALSE)) | E9: =IF(C9="","",VLOOKUP(C9,'_Données Employés'!$B$5:$H$18,6,FALSE)) | F9: =IF(C9="","",VLOOKUP(C9,'_Données Employés'!$B$5:$H$18,7,FALSE)) | G9: Securite | H9: Absence d'EPI depuis 3 mois | I9: 45828 | J9: Grave | K9: 0 | M9: Recue
B10: =IF(C10="","REC-"&TEXT(COUNTA($C$5:C10),"000"))
B11: =IF(C11="","REC-"&TEXT(COUNTA($C$5:C11),"000"))
B12: =IF(C12="","REC-"&TEXT(COUNTA($C$5:C12),"000"))
B13: =IF(C13="","REC-"&TEXT(COUNTA($C$5:C13),"000"))
B14: =IF(C14="","REC-"&TEXT(COUNTA($C$5:C14),"000"))
B15: =IF(C15="","REC-"&TEXT(COUNTA($C$5:C15),"000"))
B16: =IF(C16="","REC-"&TEXT(COUNTA($C$5:C16),"000"))
B17: =IF(C17="","REC-"&TEXT(COUNTA($C$5:C17),"000"))
B18: =IF(C18="","REC-"&TEXT(COUNTA($C$5:C18),"000"))
B19: =IF(C19="","REC-"&TEXT(COUNTA($C$5:C19),"000"))
B20: =IF(C20="","REC-"&TEXT(COUNTA($C$5:C20),"000"))
B21: =IF(C21="","REC-"&TEXT(COUNTA($C$5:C21),"000"))
... B109: =IF(C109="","REC-"&TEXT(COUNTA($C$5:C109),"000"))
B111: INDICATEURS (mis a jour automatiquement)
B112: Reclamations | D112: Cloturees | F112: En cours | H112: Delai moyen (j)
B113: =COUNTIF(B5:B104,"<>") | D113: =COUNTIF(M5:M104,"Cloturee") | F113: =COUNTIF(M5:M104,"En cours d'instruction") | H113: =IFERROR(AVERAGE(K5:K104),0)

Sheet 9-Procedures Disciplinaires
B2: PROCEDURES DISCIPLINAIRES (#94)
B3: TABLEAU DYNAMIQUE — Saisissez dans la prochaine ligne jaune. Les calculs se mettent a jour automatiquement.
B4: N° | C4: Matricule | D4: Nom Employe | E4: Departement | F4: Poste | G4: Type Faute | H4: Date Faute | I4: Date Convocation | J4: Date Entretien | K4: Sanction Prononcee | L4: Observations | M4: Date Notification | N4: Statut
B5: DIS-001 | C5: EMP-033 | D5: Tamo Elvis | E5: Cuisine & Restauration | F5: Plongeur | G5: Absent sans autorisation | H5: 45818 | I5: 45820 | J5: 45823 | K5: Avertissement ecrit | L5: Premier avertissement | M5: 45824 | N5: Decision notifiee
B6: DIS-002 | C6: EMP-009 | D6: =IF(C6="","",VLOOKUP(C6,'_Données Employés'!$B$5:$H$18,4,FALSE)&" "&VLOOKUP(C6,'_Données Employés'!$B$5:$H$18,5,FALSE)) | E6: =IF(C6="","",VLOOKUP(C6,'_Données Employés'!$B$5:$H$18,6,FALSE)) | F6: =IF(C6="","",VLOOKUP(C6,'_Données Employés'!$B$5:$H$18,7,FALSE)) | G6: Retards repetes | H6: 45778 | I6: 45785 | J6: 45789 | K6: Avertissement oral | L6: 3 retards en 2 semaines | M6: 45789 | N6: Cloturee
B7: DIS-003 | C7: EMP-040 | D7: Kane Adama | E7: Securite | F7: Agent Securite | G7: Insubordination | H7: 45828 | I7: 45830 | J7: 45833 | K7: Mise a pied disciplinaire | L7: Refus d'obeir au N+1 | M7: 45834 | N7: En recours
B8: DIS-004 | C8: EMP-025 | D8: Ngo Linda | E8: Service Client | F8: Conseiller | G8: Négligence grave | H8: 45792 | I8: 45795 | J8: 45799 | K8: Blame | L8: Erreurs facturation repetees | M8: 45800 | N8: Cloturee
B9: =IF(C9="","DIS-"&TEXT(COUNTA($C$5:C9),"000"))
B10: =IF(C10="","DIS-"&TEXT(COUNTA($C$5:C10),"000"))
B11: =IF(C11="","DIS-"&TEXT(COUNTA($C$5:C11),"000"))
B12: =IF(C12="","DIS-"&TEXT(COUNTA($C$5:C12),"000"))
B13: =IF(C13="","DIS-"&TEXT(COUNTA($C$5:C13),"000"))
B14: =IF(C14="","DIS-"&TEXT(COUNTA($C$5:C14),"000"))
B15: =IF(C15="","DIS-"&TEXT(COUNTA($C$5:C15),"000"))
B16: =IF(C16="","DIS-"&TEXT(COUNTA($C$5:C16),"000"))
B17: =IF(C17="","DIS-"&TEXT(COUNTA($C$5:C17),"000"))
B18: =IF(C18="","DIS-"&TEXT(COUNTA($C$5:C18),"000"))
B19: =IF(C19="","DIS-"&TEXT(COUNTA($C$5:C19),"000"))
B20: =IF(C20="","DIS-"&TEXT(COUNTA($C$5:C20),"000"))
... B108: =IF(C108="","DIS-"&TEXT(COUNTA($C$5:C108),"000"))
B110: INDICATEURS (mis a jour automatiquement)
B111: Procedures | D111: Cloturees | F111: En recours | H111: Avertissements
B112: =COUNTIF(B5:B104,"<>") | D112: =COUNTIF(N5:N104,"Cloturee") | F112: =COUNTIF(N5:N104,"En recours") | H112: =COUNTIF(K5:K104,"*Avertissement*")

Sheet 10-Mediation & Arbitrage
B2: MEDIATION & ARBITRAGE (#95)
B3: TABLEAU DYNAMIQUE — Saisissez dans la prochaine ligne jaune. Les calculs se mettent a jour automatiquement.
B4: N° | C4: Type Mediation | D4: Partie 1 (Employe) | E4: Partie 2 (Employeur/autre) | F4: Objet du Litige | G4: Date Saisine | H4: Mediateur / Instance | I4: Nb Sessions | J4: Date Resolution | K4: Issue | L4: Statut
B5: MED-001 | C5: Mediation interne RH | D5: Ngo Linda | E5: Chef Service Client | F5: Harcelement allege | G5: 45792 | H5: DRH Nganou | I5: 3 | J5: 45818 | K5: Accord amiable - changement N+1 | L5: Terminee - Accord
B6: MED-002 | C6: Mediation par CSE | D6: Equipe cuisine (8 pers.) | E6: Direction | F6: Conditions securite cuisine | G6: 45809 | H6: DP Koffi Amevi | I6: 2 | L6: En cours
B7: MED-003 | C7: Conciliation inspecteur travail | D7: Kane Adama | E7: Direction | F7: Mise a pied contestee | G7: 45836 | H7: Inspecteur travail | I7: 1 | L7: Saisie
B8: MED-004 | C8: Mediation interne RH | D8: Tchouanku Marc | E8: Chef Reception | F8: Report conges non justifie | G8: 45813 | H8: Assistante RH | I8: 1 | J8: 45816 | K8: Conces recule - conges accordes | L8: Terminee - Accord
B9: =IF(C9="","MED-"&TEXT(COUNTA($C$5:C9),"000"))
B10: =IF(C10="","MED-"&TEXT(COUNTA($C$5:C10),"000"))
B11: =IF(C11="","MED-"&TEXT(COUNTA($C$5:C11),"000"))
B12: =IF(C12="","MED-"&TEXT(COUNTA($C$5:C12),"000"))
B13: =IF(C13="","MED-"&TEXT(COUNTA($C$5:C13),"000"))
B14: =IF(C14="","MED-"&TEXT(COUNTA($C$5:C14),"000"))
B15: =IF(C15="","MED-"&TEXT(COUNTA($C$5:C15),"000"))
B16: =IF(C16="","MED-"&TEXT(COUNTA($C$5:C16),"000"))
B17: =IF(C17="","MED-"&TEXT(COUNTA($C$5:C17),"000"))
B18: =IF(C18="","MED-"&TEXT(COUNTA($C$5:C18),"000"))
B19: =IF(C19="","MED-"&TEXT(COUNTA($C$5:C19),"000"))
B20: =IF(C20="","MED-"&TEXT(COUNTA($C$5:C20),"000"))
... B108: =IF(C108="","MED-"&TEXT(COUNTA($C$5:C108),"000"))
B110: TOTAL | I110: =SUM(I5:I104)
B112: INDICATEURS (mis a jour automatiquement)
B113: Mediations | D113: Resolues - Accord | F113: En cours | H113: Total sessions
B114: =COUNTIF(B5:B104,"<>") | D114: =COUNTIF(L5:L104,"Terminee - Accord") | F114: =COUNTIF(L5:L104,"En cours") | H114: =SUM(I5:I104)

Sheet 11-Rapports Instances Rep.
B2: RAPPORTS INSTANCES REPRESENTATIVES (#96)
B3: TABLEAU DYNAMIQUE — Saisissez dans la prochaine ligne jaune. Les calculs se mettent a jour automatiquement.
B4: N° Rapport | C4: Instance Concernee | D4: Titre Rapport | E4: Periode Debut | F4: Periode Fin | G4: Auteur | H4: Nb Reunions Citees | I4: Nb Decisions Suivies | J4: Recommandations | K4: Date Soumission | L4: Statut
B5: RIR-001 | C5: CSE | D5: Bilan annuel CSE 2024 | E5: 45292 | F5: 45657 | G5: DRH Nganou | H5: 6 | I5: 18 | J5: Renforcer communication oeuvres sociales | K5: 45687 | L5: Approuve
B6: RIR-002 | C6: CHSCT | D6: Rapport securite T1 2025 | E6: 45658 | F6: 45747 | G6: Chef Securite | H6: 2 | I6: 5 | J6: Equiper cuisine de detecteurs fumee | K6: 45762 | L6: Valide
B7: RIR-003 | C7: DP | D7: Rapport activite delegues S1 2025 | E7: 45658 | F7: 45838 | G7: DP Koffi Amevi | H7: 12 | I7: 8 | J7: Installer boite suggestions numerique | K7: 45848 | L7: Brouillon
B8: RIR-004 | C8: Commission formation | D8: Bilan formations T1 2025 | E8: 45658 | F8: 45747 | G8: Assistante RH | H8: 2 | I8: 12 | J8: Augmenter budget formation entretien | K8: 45767 | L8: Approuve
B9: =IF(C9="","RIR-"&TEXT(COUNTA($C$5:C9),"000"))
B10: =IF(C10="","RIR-"&TEXT(COUNTA($C$5:C10),"000"))
B11: =IF(C11="","RIR-"&TEXT(COUNTA($C$5:C11),"000"))
B12: =IF(C12="","RIR-"&TEXT(COUNTA($C$5:C12),"000"))
B13: =IF(C13="","RIR-"&TEXT(COUNTA($C$5:C13),"000"))
B14: =IF(C14="","RIR-"&TEXT(COUNTA($C$5:C14),"000"))
B15: =IF(C15="","RIR-"&TEXT(COUNTA($C$5:C15),"000"))
B16: =IF(C16="","RIR-"&TEXT(COUNTA($C$5:C16),"000"))
B17: =IF(C17="","RIR-"&TEXT(COUNTA($C$5:C17),"000"))
B18: =IF(C18="","RIR-"&TEXT(COUNTA($C$5:C18),"000"))
B19: =IF(C19="","RIR-"&TEXT(COUNTA($C$5:C19),"000"))
B20: =IF(C20="","RIR-"&TEXT(COUNTA($C$5:C20),"000"))
... B108: =IF(C108="","RIR-"&TEXT(COUNTA($C$5:C108),"000"))
B110: TOTAL | H110: =SUM(H5:H104) | I110: =SUM(I5:I104)
B112: INDICATEURS (mis a jour automatiquement)
B113: Rapports | D113: Approuves | F113: Brouillons | H113: Decisions suivies
B114: =COUNTIF(B5:B104,"<>") | D114: =COUNTIF(L5:L104,"Approuve") | F114: =COUNTIF(L5:L104,"Brouillon") | H114: =SUM(I5:I104)

Sheet 12-Suivi Droit Syndical
B2: SUIVI DROIT SYNDICAL
B3: TABLEAU DYNAMIQUE — Saisissez dans la prochaine ligne jaune. Les calculs se mettent a jour automatiquement.
B4: N° | C4: Matricule | D4: Nom Employe | E4: Departement | F4: Syndicat | G4: Heures Syndicales (mois) | H4: Heures Utilisees | I4: Solde Heures | J4: Observations
B5: DS-001 | C5: EMP-010 | D5: =IF(C5="","",VLOOKUP(C5,'_Données Employés'!$B$5:$H$18,4,FALSE)&" "&VLOOKUP(C5,'_Données Employés'!$B$5:$H$18,5,FALSE)) | E5: =IF(C5="","",VLOOKUP(C5,'_Données Employés'!$B$5:$H$18,6,FALSE)) | F5: CSTT | G5: 20 | H5: 14 | I5: =G5-H5 | J5: Heures reunion CSE incluses
B6: DS-002 | C6: EMP-015 | D6: Mensah Kodjo | E6: Entretien & Maintenance | F6: CSA | G6: 20 | H6: 10 | I6: =G6-H6 | J6: Heures negociation NAO
B7: DS-003 | C7: EMP-022 | D7: Aguiar Maria | E7: Ressources Humaines | F7: CSC | G7: 20 | H7: 8 | I7: =G7-H7
B8: DS-004 | C8: EMP-008 | D8: =IF(C8="","",VLOOKUP(C8,'_Données Employés'!$B$5:$H$18,4,FALSE)&" "&VLOOKUP(C8,'_Données Employés'!$B$5:$H$18,5,FALSE)) | E8: =IF(C8="","",VLOOKUP(C8,'_Données Employés'!$B$5:$H$18,6,FALSE)) | F8: SAH | G8: 20 | H8: 12 | I8: =G8-H8 | J8: Formation delegue
B9: DS-005 | C9: EMP-012 | D9: =IF(C9="","",VLOOKUP(C9,'_Données Employés'!$B$5:$H$18,4,FALSE)&" "&VLOOKUP(C9,'_Données Employés'!$B$5:$H$18,5,FALSE)) | E9: =IF(C9="","",VLOOKUP(C9,'_Données Employés'!$B$5:$H$18,6,FALSE)) | F9: CSTT | G9: 20 | H9: 4 | I9: =G9-H9 | J9: Peu d'activite syndicale ce mois
B10: =IF(C10="","DS-"&TEXT(COUNTA($C$5:C10),"000")) | I10: =IF(G10="","",G10-H10)
B11: =IF(C11="","DS-"&TEXT(COUNTA($C$5:C11),"000")) | I11: =IF(G11="","",G11-H11)
B12: =IF(C12="","DS-"&TEXT(COUNTA($C$5:C12),"000")) | I12: =IF(G12="","",G12-H12)
B13: =IF(C13="","DS-"&TEXT(COUNTA($C$5:C13),"000")) | I13: =IF(G13="","",G13-H13)
B14: =IF(C14="","DS-"&TEXT(COUNTA($C$5:C14),"000")) | I14: =IF(G14="","",G14-H14)
B15: =IF(C15="","DS-"&TEXT(COUNTA($C$5:C15),"000")) | I15: =IF(G15="","",G15-H15)
B16: =IF(C16="","DS-"&TEXT(COUNTA($C$5:C16),"000")) | I16: =IF(G16="","",G16-H16)
B17: =IF(C17="","DS-"&TEXT(COUNTA($C$5:C17),"000")) | I17: =IF(G17="","",G17-H17)
B18: =IF(C18="","DS-"&TEXT(COUNTA($C$5:C18),"000")) | I18: =IF(G18="","",G18-H18)
B19: =IF(C19="","DS-"&TEXT(COUNTA($C$5:C19),"000")) | I19: =IF(G19="","",G19-H19)
B20: =IF(C20="","DS-"&TEXT(COUNTA($C$5:C20),"000")) | I20: =IF(G20="","",G20-H20)
B21: =IF(C21="","DS-"&TEXT(COUNTA($C$5:C21),"000")) | I21: =IF(G21="","",G21-H21)
... B109: =IF(C109="","DS-"&TEXT(COUNTA($C$5:C109),"000")) | I109: =IF(G109="","",G109-H109)
B111: TOTAL | G111: =SUM(G5:G104) | H111: =SUM(H5:H104) | I111: =SUM(I5:I104)
B113: INDICATEURS (mis a jour automatiquement)
B114: Beneficiaires | D114: Total heures allouees | F114: Total heures utilisees | H114: Taux utilisation (%)
B115: =COUNTIF(B5:B104,"<>") | D115: =SUM(G5:G104) | F115: =SUM(H5:H104) | H115: =IFERROR(SUM(H5:H104)/SUM(G5:G104),0)

Sheet 13-Historique Accords
B2: HISTORIQUE DES ACCORDS
B3: TABLEAU DYNAMIQUE — Saisissez dans la prochaine ligne jaune. Les calculs se mettent a jour automatiquement.
B4: N° | C4: Accord | D4: Annee Signature | E4: Type | F4: Syndicats Signataires | G4: Objet Principal | H4: Duree (mois) | I4: Statut Actuel
B5: HA-001 | C5: AC-001 | D5: 2025 | E5: Accord salarial | F5: CSTT, CSA, CSC | G5: Revalorisation salariale 5% | H5: 12 | I5: En vigueur
B6: HA-002 | C6: AC-002 | D6: 2024 | E6: Accord d'entreprise | F6: CSC | G6: Teletravail partiel IT | H6: 24 | I6: En vigueur
B7: HA-003 | C7: AC-003 | D7: 2020 | E7: Convention collective | F7: Ensemble syndicats | G7: Application CCT Hotelier | H7: 60 | I7: Expire
B8: HA-004 | C8: AC-004 | D8: 2025 | E8: Protocole precontentieux | F8: CSTT | G8: Resolution conflit horaires | H8: 6 | I8: En vigueur
B9: HA-005 | C9: AC-005 | D9: 2025 | E9: Avenant | F9: CSE | G9: Revision prime panier | H9: 12 | I9: En vigueur
B10: HA-006 | C10: AC-OLD-001 | D10: 2022 | E10: Accord salarial | F10: CSTT, CSA | G10: Augmentation 4% 2022 | H10: 12 | I10: Expire
B11: HA-007 | C11: AC-OLD-002 | D11: 2023 | E11: Accord d'entreprise | F11: CSTT, CSA, CSC | G11: Prime transport 2023 | H11: 12 | I11: Expire
B12: =IF(C12="","HA-"&TEXT(COUNTA($C$5:C12),"000"))
B13: =IF(C13="","HA-"&TEXT(COUNTA($C$5:C13),"000"))
B14: =IF(C14="","HA-"&TEXT(COUNTA($C$5:C14),"000"))
B15: =IF(C15="","HA-"&TEXT(COUNTA($C$5:C15),"000"))
B16: =IF(C16="","HA-"&TEXT(COUNTA($C$5:C16),"000"))
B17: =IF(C17="","HA-"&TEXT(COUNTA($C$5:C17),"000"))
B18: =IF(C18="","HA-"&TEXT(COUNTA($C$5:C18),"000"))
B19: =IF(C19="","HA-"&TEXT(COUNTA($C$5:C19),"000"))
B20: =IF(C20="","HA-"&TEXT(COUNTA($C$5:C20),"000"))
B21: =IF(C21="","HA-"&TEXT(COUNTA($C$5:C21),"000"))
B22: =IF(C22="","HA-"&TEXT(COUNTA($C$5:C22),"000"))
B23: =IF(C23="","HA-"&TEXT(COUNTA($C$5:C23),"000"))
... B111: =IF(C111="","HA-"&TEXT(COUNTA($C$5:C111),"000"))
B113: INDICATEURS (mis a jour automatiquement)
B114: Accords historiques | D114: En vigueur | F114: Expires | H114: Duree moyenne (mois)
B115: =COUNTIF(B5:B104,"<>") | D115: =COUNTIF(I5:I104,"En vigueur") | F115: =COUNTIF(I5:I104,"Expire") | H115: =IFERROR(AVERAGE(H5:H104),0)

Sheet 14-Bilan Social Rel. Prof.
B2: BILAN SOCIAL - RELATIONS PROFESSIONNELLES
B3: TABLEAU DYNAMIQUE — Saisissez dans la prochaine ligne jaune. Les calculs se mettent a jour automatiquement.
B4: N° | C4: Indicateur | D4: Annee | E4: Departement | F4: Valeur | G4: Cible / Norme | H4: Ecart | I4: Tendance | J4: Commentaire
B5: BS-001 | C5: Taux syndicalisation (%) | D5: 2025 | E5: Tous | F5: 22 | G5: 30 | H5: -8 | I5: En hausse | J5: Campagne info prevue T3
B6: BS-002 | C6: Nb conflits sociaux | D6: 2025 | E6: Tous | F6: 5 | G6: 2 | H6: 3 | I6: En hausse | J6: 3 conflits lies aux salaires
B7: BS-003 | C7: Taux resolution conflits (%) | D7: 2025 | E7: Tous | F7: 80 | G7: 90 | H7: -10 | I7: Stable | J7: Mediation a renforcer
B8: BS-004 | C8: Nb reclamations / 100 employes | D8: 2025 | E8: Tous | F8: 8.5 | G8: 5 | H8: 3.5 | I8: En hausse | J8: Pic en mai-juin
B9: BS-005 | C9: Delai moyen traitement rec. (j) | D9: 2025 | E9: Tous | F9: 6.2 | G9: 5 | H9: 1.2 | I9: En baisse | J9: Amelioration vs 2024 (8.5j)
B10: BS-006 | C10: Nb procedures disciplinaires | D10: 2025 | E10: Tous | F10: 4 | G10: 3 | H10: 1 | I10: En hausse | J10: Recrutements S1 moins qualifies
B11: BS-007 | C11: Taux participation CSE (%) | D11: 2025 | E11: Tous | F11: 78 | G11: 80 | H11: -2 | I11: Stable | J11: Bon niveau de participation
B12: =IF(C12="","BS-"&TEXT(COUNTA($C$5:C12),"000")) | H12: =IF(G12="","",IF(G12=0,"",F12-G12))
B13: =IF(C13="","BS-"&TEXT(COUNTA($C$5:C13),"000")) | H13: =IF(G13="","",IF(G13=0,"",F13-G13))
B14: =IF(C14="","BS-"&TEXT(COUNTA($C$5:C14),"000")) | H14: =IF(G14="","",IF(G14=0,"",F14-G14))
B15: =IF(C15="","BS-"&TEXT(COUNTA($C$5:C15),"000")) | H15: =IF(G15="","",IF(G15=0,"",F15-G15))
B16: =IF(C16="","BS-"&TEXT(COUNTA($C$5:C16),"000")) | H16: =IF(G16="","",IF(G16=0,"",F16-G16))
B17: =IF(C17="","BS-"&TEXT(COUNTA($C$5:C17),"000")) | H17: =IF(G17="","",IF(G17=0,"",F17-G17))
B18: =IF(C18="","BS-"&TEXT(COUNTA($C$5:C18),"000")) | H18: =IF(G18="","",IF(G18=0,"",F18-G18))
B19: =IF(C19="","BS-"&TEXT(COUNTA($C$5:C19),"000")) | H19: =IF(G19="","",IF(G19=0,"",F19-G19))
B20: =IF(C20="","BS-"&TEXT(COUNTA($C$5:C20),"000")) | H20: =IF(G20="","",IF(G20=0,"",F20-G20))
B21: =IF(C21="","BS-"&TEXT(COUNTA($C$5:C21),"000")) | H21: =IF(G21="","",IF(G21=0,"",F21-G21))
B22: =IF(C22="","BS-"&TEXT(COUNTA($C$5:C22),"000")) | H22: =IF(G22="","",IF(G22=0,"",F22-G22))
B23: =IF(C23="","BS-"&TEXT(COUNTA($C$5:C23),"000")) | H23: =IF(G23="","",IF(G23=0,"",F23-G23))
... B111: =IF(C111="","BS-"&TEXT(COUNTA($C$5:C111),"000")) | H111: =IF(G111="","",IF(G111=0,"",F111-G111))
B113: INDICATEURS (mis a jour automatiquement)
B114: Indicateurs suivis | D114: Indicateurs sous cible | F114: Indicateurs dans norme | H114: Ecart moyen
B115: =COUNTIF(B5:B104,"<>") | D115: =COUNTIF(H5:H104,">0") | F115: =COUNTIF(H5:H104,"<=0") | H115: =IFERROR(AVERAGE(H5:H104),0)

Sheet 15-Reclamations par Mois
B2: SUIVI MENSUEL DES RECLAMATIONS
B3: TABLEAU DYNAMIQUE — Saisissez dans la prochaine ligne jaune. Les calculs se mettent a jour automatiquement.
B4: N° | C4: Mois | D4: Annee | E4: Nb Reclamations | F4: Nb Cloturees | G4: Nb En Cours | H4: Nb Escaladees | I4: Delai Moyen (j)
B5: RM-001 | C5: Janvier | D5: 2025 | E5: =COUNTA('8-Reclamations Personnel'!B5:B104) | F5: =COUNTIF('8-Reclamations Personnel'!R:R,"Traitee") | G5: 0 | H5: 0 | I5: 4.5
B6: RM-002 | C6: Fevrier | D6: 2025 | E6: =COUNTA('8-Reclamations Personnel'!B5:B104) | F6: =COUNTIF('8-Reclamations Personnel'!R:R,"Traitee") | G6: 0 | H6: 0 | I6: 3
B7: RM-003 | C7: Mars | D7: 2025 | E7: =COUNTA('8-Reclamations Personnel'!B5:B104) | F7: =COUNTIF('8-Reclamations Personnel'!R:R,"Traitee") | G7: 1 | H7: 1 | I7: 5.2
B8: RM-004 | C8: Avril | D8: 2025 | E8: =COUNTA('8-Reclamations Personnel'!B5:B104) | F8: =COUNTIF('8-Reclamations Personnel'!R:R,"Traitee") | G8: 0 | H8: 0 | I8: 4
B9: RM-005 | C9: Mai | D9: 2025 | E9: =COUNTA('8-Reclamations Personnel'!B5:B104) | F9: =COUNTIF('8-Reclamations Personnel'!R:R,"Traitee") | G9: 2 | H9: 1 | I9: 6.8
B10: RM-006 | C10: Juin | D10: 2025 | E10: =COUNTA('8-Reclamations Personnel'!B5:B104) | F10: =COUNTIF('8-Reclamations Personnel'!R:R,"Traitee") | G10: 3 | H10: 2 | I10: 7.5
B11: =IF(C11="","RM-"&TEXT(COUNTA($C$5:C11),"000"))
B12: =IF(C12="","RM-"&TEXT(COUNTA($C$5:C12),"000"))
B13: =IF(C13="","RM-"&TEXT(COUNTA($C$5:C13),"000"))
B14: =IF(C14="","RM-"&TEXT(COUNTA($C$5:C14),"000"))
B15: =IF(C15="","RM-"&TEXT(COUNTA($C$5:C15),"000"))
B16: =IF(C16="","RM-"&TEXT(COUNTA($C$5:C16),"000"))
B17: =IF(C17="","RM-"&TEXT(COUNTA($C$5:C17),"000"))
B18: =IF(C18="","RM-"&TEXT(COUNTA($C$5:C18),"000"))
B19: =IF(C19="","RM-"&TEXT(COUNTA($C$5:C19),"000"))
B20: =IF(C20="","RM-"&TEXT(COUNTA($C$5:C20),"000"))
B21: =IF(C21="","RM-"&TEXT(COUNTA($C$5:C21),"000"))
B22: =IF(C22="","RM-"&TEXT(COUNTA($C$5:C22),"000"))
... B110: =IF(C110="","RM-"&TEXT(COUNTA($C$5:C110),"000"))
B112: TOTAL | E112: =SUM(E5:E104) | F112: =SUM(F5:F104) | G112: =SUM(G5:G104) | H112: =SUM(H5:H104)
B114: INDICATEURS (mis a jour automatiquement)
B115: Mois suivis | D115: Total rec. | F115: Total cloturees | H115: Delai moyen global
B116: =COUNTIF(B5:B104,"<>") | D116: =SUM(E5:E104) | F116: =SUM(F5:F104) | H116: =IFERROR(AVERAGE(I5:I104),0)

Sheet 16-Calendrier Negociations
B2: CALENDRIER DES NEGOCIATIONS
B3: TABLEAU DYNAMIQUE — Saisissez dans la prochaine ligne jaune. Les calculs se mettent a jour automatiquement.
B4: N° | C4: Type Negociation | D4: Objet | E4: Date Prevue | F4: Lieu | G4: Responsable Cote Patronal | H4: Syndicats Invites | I4: Priorite | J4: Statut
B5: CN-001 | C5: NAO | D5: NAO 2026 - Salaires & conditions | E5: 45976 | F5: Salle A | G5: DG + DRH | H5: CSTT, CSA, CSC | I5: Haute | J5: Planifiee
B6: CN-002 | C6: Negociation egalite prof. | D6: Index egalite professionnelle | E6: 45889 | F6: Salle B | G6: DRH | H6: CSC | I6: Moyenne | J6: Planifiee
B7: CN-003 | C7: Negociation formation | D7: Plan formation 2026 | E7: 45931 | F7: Salle A | G7: DRH + Assistante | H7: CSE | I7: Moyenne | J7: Planifiee
B8: CN-004 | C8: Negociation salariale | D8: Grilles salariales 2026 | E8: 45992 | F8: Salle A | G8: DG + DRH | H8: CSTT, CSA, SAH | I8: Haute | J8: Planifiee
B9: =IF(C9="","CN-"&TEXT(COUNTA($C$5:C9),"000"))
B10: =IF(C10="","CN-"&TEXT(COUNTA($C$5:C10),"000"))
B11: =IF(C11="","CN-"&TEXT(COUNTA($C$5:C11),"000"))
B12: =IF(C12="","CN-"&TEXT(COUNTA($C$5:C12),"000"))
B13: =IF(C13="","CN-"&TEXT(COUNTA($C$5:C13),"000"))
B14: =IF(C14="","CN-"&TEXT(COUNTA($C$5:C14),"000"))
B15: =IF(C15="","CN-"&TEXT(COUNTA($C$5:C15),"000"))
B16: =IF(C16="","CN-"&TEXT(COUNTA($C$5:C16),"000"))
B17: =IF(C17="","CN-"&TEXT(COUNTA($C$5:C17),"000"))
B18: =IF(C18="","CN-"&TEXT(COUNTA($C$5:C18),"000"))
B19: =IF(C19="","CN-"&TEXT(COUNTA($C$5:C19),"000"))
B20: =IF(C20="","CN-"&TEXT(COUNTA($C$5:C20),"000"))
... B108: =IF(C108="","CN-"&TEXT(COUNTA($C$5:C108),"000"))
B110: INDICATEURS (mis a jour automatiquement)
B111: Negociations planifiees | D111: Planifiees | F111: En cours | H111: Haute priorite
B112: =COUNTIF(B5:B104,"<>") | D112: =COUNTIF(J5:J104,"Planifiee") | F112: =COUNTIF(J5:J104,"En cours") | H112: =COUNTIF(I5:I104,"Haute")

Sheet 17-PV Reunions Inst. Rep.
B2: PV REUNIONS - INSTANCES REPRESENTATIVES
B3: TABLEAU DYNAMIQUE — Saisissez dans la prochaine ligne jaune. Les calculs se mettent a jour automatiquement.
B4: N° PV | C4: Instance | D4: Date Reunion | E4: Nb Participants | F4: Ordre du Jour | G4: Decisions | H4: Action(s) a Suivre | I4: Responsable Suivi | J4: Echeance Suivi | K4: Statut Reunion
B5: PV-001 | C5: CSE | D5: 45677 | E5: 12 | F5: Budget social 2025 | G5: Budget valide 15M FCFA | H5: Suivi execution budget trimestriel | I5: DRH Nganou | J5: 45767 | K5: Tenue
B6: PV-002 | C6: CSE | D6: 45731 | E6: 10 | F6: Conditions saison haute | G6: Heures sup. majorees 25% | H6: Negocier primes saison haute | I6: DRH Nganou | J6: 45823 | K6: Tenue
B7: PV-003 | C7: CHSCT | D7: 45757 | E7: 8 | F7: Audit securite | G7: 3 actions correctives | H7: Plan action securite Q2 | I7: Chef Securite | J7: 45848 | K7: Tenue
B8: PV-004 | C8: Commission formation | D8: 45693 | E8: 6 | F8: PAF 2025 | G8: PAF valide 8.5M FCFA | H8: Lancer inscriptions T2 | I8: Assistante RH | J8: 45782 | K8: Tenue
B9: PV-005 | C9: CSE | D9: 45856 | E9: 0 | F9: Bilan oeuvres sociales S1 | H9: Preparer documents bilan | I9: DRH Nganou | J9: 45853 | K9: Planifiee
B10: =IF(C10="","PV-"&TEXT(COUNTA($C$5:C10),"000"))
B11: =IF(C11="","PV-"&TEXT(COUNTA($C$5:C11),"000"))
B12: =IF(C12="","PV-"&TEXT(COUNTA($C$5:C12),"000"))
B13: =IF(C13="","PV-"&TEXT(COUNTA($C$5:C13),"000"))
B14: =IF(C14="","PV-"&TEXT(COUNTA($C$5:C14),"000"))
B15: =IF(C15="","PV-"&TEXT(COUNTA($C$5:C15),"000"))
B16: =IF(C16="","PV-"&TEXT(COUNTA($C$5:C16),"000"))
B17: =IF(C17="","PV-"&TEXT(COUNTA($C$5:C17),"000"))
B18: =IF(C18="","PV-"&TEXT(COUNTA($C$5:C18),"000"))
B19: =IF(C19="","PV-"&TEXT(COUNTA($C$5:C19),"000"))
B20: =IF(C20="","PV-"&TEXT(COUNTA($C$5:C20),"000"))
B21: =IF(C21="","PV-"&TEXT(COUNTA($C$5:C21),"000"))
... B109: =IF(C109="","PV-"&TEXT(COUNTA($C$5:C109),"000"))
B111: TOTAL | E111: =SUM(E5:E104)
B113: INDICATEURS (mis a jour automatiquement)
B114: PV rediges | D114: Reunions tenues | F114: Actions en attente | H114: Participants moyen
B115: =COUNTIF(B5:B104,"<>") | D115: =COUNTIF(K5:K104,"Tenue") | F115: =COUNTIF(H5:H104,"<>") | H115: =IFERROR(AVERAGE(E5:E104),0)

Sheet 18-Suivi Mesures Correct.
B2: SUIVI DES MESURES CORRECTIVES
B3: TABLEAU DYNAMIQUE — Saisissez dans la prochaine ligne jaune. Les calculs se mettent a jour automatiquement.
B4: N° | C4: Source | D4: Instance / Origine | E4: Description Mesure | F4: Responsable | G4: Departement | H4: Date Lancement | I4: Echeance | J4: Avancement (%) | K4: Cout (FCFA) | L4: Statut
B5: MC-001 | C5: CSE reunion | D5: CSE | E5: Installer detecteurs fumee cuisine | F5: Chef Entretien | G5: Maintenance | H5: 45778 | I5: 45869 | J5: 80 | K5: 350000 | L5: En cours
B6: MC-002 | C6: CHSCT audit | D6: CHSCT | E6: Equiper agents EPI complets | F6: Chef Securite | G6: Sécurité | H6: 45762 | I6: 45838 | J6: 100 | K6: 500000 | L6: Cloturee
B7: MC-003 | C7: Greve fev. | D7: Negociation | E7: Reviser grille salariale cuisine | F7: DRH Nganou | G7: Service Client | H7: 45717 | I7: 45838 | J7: 100 | K7: 2400000 | L7: Cloturee
B8: MC-004 | C8: Reclamation REC-005 | D8: Reclamation | E8: Commander EPI securite | F8: Chef Logistique | G8: Logistique & Approvisionnement | H8: 45830 | I8: 45869 | J8: 30 | K8: 150000 | L8: En cours
B9: MC-005 | C9: Mediation MED-001 | D9: Mediation | E9: Changer N+1 service client | F9: DRH Nganou | G9: Service Client | H9: 45820 | I9: 45900 | J9: 0 | K9: 0 | L9: En cours
B10: =IF(C10="","MC-"&TEXT(COUNTA($C$5:C10),"000"))
B11: =IF(C11="","MC-"&TEXT(COUNTA($C$5:C11),"000"))
B12: =IF(C12="","MC-"&TEXT(COUNTA($C$5:C12),"000"))
B13: =IF(C13="","MC-"&TEXT(COUNTA($C$5:C13),"000"))
B14: =IF(C14="","MC-"&TEXT(COUNTA($C$5:C14),"000"))
B15: =IF(C15="","MC-"&TEXT(COUNTA($C$5:C15),"000"))
B16: =IF(C16="","MC-"&TEXT(COUNTA($C$5:C16),"000"))
B17: =IF(C17="","MC-"&TEXT(COUNTA($C$5:C17),"000"))
B18: =IF(C18="","MC-"&TEXT(COUNTA($C$5:C18),"000"))
B19: =IF(C19="","MC-"&TEXT(COUNTA($C$5:C19),"000"))
B20: =IF(C20="","MC-"&TEXT(COUNTA($C$5:C20),"000"))
B21: =IF(C21="","MC-"&TEXT(COUNTA($C$5:C21),"000"))
... B109: =IF(C109="","MC-"&TEXT(COUNTA($C$5:C109),"000"))
B111: TOTAL | K111: =SUM(K5:K104)
B113: INDICATEURS (mis a jour automatiquement)
B114: Mesures | D114: Cloturees | F114: En cours | H114: Cout total (FCFA)
B115: =COUNTIF(B5:B104,"<>") | D115: =COUNTIF(L5:L104,"Cloturee") | F115: =COUNTIF(L5:L104,"En cours") | H115: =SUM(K5:K104)
