Workbook

Sheet 1-Tableau de Bord
B2: DOMAINE 19 — INNOVATION RH & TRANSFORMATION DIGITALE
B3: TABLEAU DE BORD — Vue synthetique de tous les indicateurs du domaine (mis a jour automatiquement)
B5: Outils digitaux | E5: Processus automatises | H5: Cas d'usage IA | K5: Indicateurs analytics
B6: =COUNTIF('2-Inventaire Outils Digitaux'!B5:B104,"<>") | E6: =COUNTIF('3-Automatisation Processus RH'!B5:B104,"<>") | H6: =COUNTIF('4-Intelligence Artificielle RH'!B5:B104,"<>") | K6: =COUNTIF('5-Data Analytics RH'!B5:B104,"<>")
B9: Modules SIRH | E9: Modules e-learning | H9: Apps mobiles RH | K9: Chatbots / Assistants
B10: =COUNTIF('6-SIRH & Systemes Info'!B5:B104,"<>") | E10: =COUNTIF('7-Digital Learning & E-Learning'!B5:B104,"<>") | H10: =COUNTIF('8-Applications Mobiles RH'!B5:B104,"<>") | K10: =COUNTIF('9-Chatbots & Assistants RH'!B5:B104,"<>")
B13: Categories securisees | E13: Suivis veille tech | H13: Projets digitaux | K13: Budget licences (FCFA)
B14: =COUNTIF('10-Cybersecurite Donnees RH'!B5:B104,"<>") | E14: =COUNTIF('11-Veille Technologique RH'!B5:B104,"<>") | H14: =COUNTIF('12-Suivi Projets Digitaux'!B5:B104,"<>") | K14: =IFERROR(SUM('2-Inventaire Outils Digitaux'!H5:H104),0)
B18: PROJETS DIGITAUX PAR TYPE & OUTILS PAR STATUT DEPLOIEMENT
B19: Type Projet | C19: Nombre
B20: Infrastructure | C20: =COUNTIF('12-Suivi Projets Digitaux'!D5:D104,"Infrastructure")
B21: IA & Chatbot | C21: =COUNTIF('12-Suivi Projets Digitaux'!D5:D104,"IA & Chatbot")
B22: Application mobile | C22: =COUNTIF('12-Suivi Projets Digitaux'!D5:D104,"Application mobile")
B23: Automatisation | C23: =COUNTIF('12-Suivi Projets Digitaux'!D5:D104,"Automatisation")
B24: Analytics & BI | C24: =COUNTIF('12-Suivi Projets Digitaux'!D5:D104,"Analytics & BI")
B25: GED & Numerisation | C25: =COUNTIF('12-Suivi Projets Digitaux'!D5:D104,"GED & Numerisation")
H27: Statut Deploiement | I27: Nombre
H28: En production | I28: =COUNTIF('2-Inventaire Outils Digitaux'!L5:L104,"En production")
H29: Deploie | I29: =COUNTIF('2-Inventaire Outils Digitaux'!L5:L104,"Deploie")
H30: Test | I30: =COUNTIF('2-Inventaire Outils Digitaux'!L5:L104,"Test")
H31: En cours | I31: =COUNTIF('2-Inventaire Outils Digitaux'!L5:L104,"En cours")
H32: Planifie | I32: =COUNTIF('2-Inventaire Outils Digitaux'!L5:L104,"Planifie")
H33: Obsolete | I33: =COUNTIF('2-Inventaire Outils Digitaux'!L5:L104,"Obsolete")

Sheet _Lists
B1: departement | C1: poste_hotel | D1: type_outil_digital | E1: statut_deploiement | F1: niveau_automatisation | G1: type_ia | H1: niveau_maturite | I1: frequence_veille | J1: source_veille | K1: statut_innovation | L1: categorie_donnee_rh | M1: niveau_risque | N1: statut_adoption | O1: periode_analyse | P1: statut_action | Q1: statut_projet | R1: fournisseur_tech | S1: echelle_satisfaction | T1: categorie_outil_digital
B2: Direction Generale | C2: DG | D2: SIRH | E2: Planifie | F2: Manuel | G2: CV Screening | H2: Initial | I2: Quotidienne | J2: Blog tech | K2: Idee | L2: Donnees personnelles | M2: Critique | N2: Non commence | O2: Mensuel | P2: Planifiee | Q2: En cours | R2: SAP | S2: Tres insatisfait | T2: SIRH
B3: Service Client | C3: DRH | D3: Paie | E3: En cours | F3: Partiellement automatise | G3: Chatbot RH | H3: Reproductible | I3: Hebdomadaire | J3: Conference | K3: Etude de faisabilite | L3: Salaire & paie | M3: Eleve | N3: En cours d'adoption | O3: Trimestriel | P3: En cours | Q3: Termine | R3: Oracle | S3: Insatisfait | T3: Paie
B4: Finance & Comptabilité | C4: Assistante RH | D4: Recrutement | E4: Test | F4: Automatise | G4: Predictif turnover | H4: Defini | I4: Bimensuelle | J4: Webinaire | K4: Prototype | L4: Sante & medical | M4: Moyen | N4: Adopte | O4: Semestriel | P4: Terminee | Q4: En pause | R4: Workday | S4: Neutre | T4: Recrutement
B5: Marketing & Communication | C5: DAF | D5: Formation en ligne | E5: Deploie | F5: Totalement automatise | G5: Analytics avance | H5: Gere | I5: Mensuelle | J5: Fournisseur | K5: Test | L5: Performance | M5: Faible | N5: Maitrise | O5: Annuel | P5: Reportee | Q5: Abandonne | R5: Cegid | S5: Satisfait | T5: Formation
B6: Maintenance | C6: Comptable senior | D6: Gestion du temps | E6: En production | G6: Assistant virtuel | H6: Optimise | I6: Trimestrielle | J6: Benchmark concurrent | K6: Deploiement pilote | L6: Formation & competences | N6: Expert | P6: Annulee | Q6: En attente validation | R6: Lucca | S6: Tres satisfait | T6: Communication
B7: Commercial | C7: Chef Comptable | D7: Communication interne | E7: Obsolete | G7: Matching competences | J7: Publication academique | K7: Production | L7: Presence & conges | R7: BambooHR | T7: Collaboration
B8: Logistique & Approvisionnement | C8: Chef Marketing | D8: Analytics / BI | E8: Abandonne | G8: Analyse sentiment | J8: Reseaux sociaux | K8: Abandonne | L8: Recrutement | R8: HiBob | T8: Sécurité
B9: Cuisine & Restauration | C9: Chef de service IT | D9: Chatbot RH | G9: Autre | J9: Consultant | L9: Disciplinaire | R9: Personio | T9: Autre
B10: Réception & Front Office | C10: Technicien IT | D10: Application mobile | J10: Autre | L10: Autre | R10: Wittyfit
B11: Sécurité | C11: Chef Commercial | D11: GED (Gestion Electronique Docs) | R11: Pollen
B12: Étage & Housekeeping | C12: Agent Commercial | D12: Signature electronique | R12: Moc感和K
C13: Chef Reception | D13: Autre | R13: Developpement interne
C14: Receptionniste | R14: Open source
C15: Chef Cuisine | R15: Autre
C16: Chef Rangement
C17: Gouvernante
C18: Femme de chambre
C19: Agent Securite
C20: Chauffeur
C21: Agent Entretien
C22: Plongeur
C23: Serveur
C24: Barman
C25: Laveur vaisselle
C26: Agent de service
C27: Standardiste
C28: Bagagiste

Sheet 2-Inventaire Outils Digitaux
B2: INVENTAIRE OUTILS DIGITAUX RH (#157)
B3: TABLEAU DYNAMIQUE — Saisissez dans la prochaine ligne jaune. Les calculs se mettent a jour automatiquement.
B4: N° | C4: Nom Outil / Solution | D4: Type Outil | E4: Fournisseur | F4: Version | G4: Nb Utilisateurs Licences | H4: Cout Licence / an (FCFA) | I4: Date Installation | J4: Prochain Renouvellement | K4: Responsable IT | L4: Statut | M4: Observations
B5: OD-001 | C5: SIRH HotelPro | D5: SIRH | E5: Cegid | F5: v4.2 | G5: 15 | H5: 3600000 | I5: 45078 | J5: 46174 | K5: Chef de service IT | L5: En production | M5: Contrat maintenance inclus
B6: OD-002 | C6: Lucca Paie | D6: Paie | E6: Lucca | F6: Cloud | G6: 5 | H6: 1200000 | I6: 45306 | J6: 45672 | K6: Comptable senior | L6: En production | M6: Integration SIRH prevue T2
B7: OD-003 | C7: Welcome to the Jungle | D7: Recrutement | E7: WTJ | F7: SaaS | G7: 3 | H7: 600000 | I7: 45352 | J7: 45717 | K7: Assistante RH | L7: En production | M7: ATS integre avec multi-poste
B8: =IF(C8="","OD-"&TEXT(COUNTA($C$5:C8),"000"))
B9: =IF(C9="","OD-"&TEXT(COUNTA($C$5:C9),"000"))
B10: =IF(C10="","OD-"&TEXT(COUNTA($C$5:C10),"000"))
B11: =IF(C11="","OD-"&TEXT(COUNTA($C$5:C11),"000"))
B12: =IF(C12="","OD-"&TEXT(COUNTA($C$5:C12),"000"))
B13: =IF(C13="","OD-"&TEXT(COUNTA($C$5:C13),"000"))
B14: =IF(C14="","OD-"&TEXT(COUNTA($C$5:C14),"000"))
B15: =IF(C15="","OD-"&TEXT(COUNTA($C$5:C15),"000"))
B16: =IF(C16="","OD-"&TEXT(COUNTA($C$5:C16),"000"))
B17: =IF(C17="","OD-"&TEXT(COUNTA($C$5:C17),"000"))
B18: =IF(C18="","OD-"&TEXT(COUNTA($C$5:C18),"000"))
B19: =IF(C19="","OD-"&TEXT(COUNTA($C$5:C19),"000"))
... B107: =IF(C107="","OD-"&TEXT(COUNTA($C$5:C107),"000"))
B109: INDICATEURS (mis a jour automatiquement)
B110: Outils digitaux | D110: En production | F110: Budget licences (FCFA)
B111: =COUNTIF(B5:B104,"<>") | D111: =COUNTIF(L5:L104,"En production") | F111: =SUM(H5:H104)

Sheet 3-Automatisation Processus RH
B2: AUTOMATISATION PROCESSUS RH (#158)
B3: TABLEAU DYNAMIQUE — Saisissez dans la prochaine ligne jaune. Les calculs se mettent a jour automatiquement.
B4: N° | C4: Processus RH | D4: Niveau Automatisation | E4: Outil Utilise | F4: Etapes Manuel (avant) | G4: Etapes Automatisees (apres) | H4: Gain Temps (h/mois) | I4: Taux Erreur avant (%) | J4: Taux Erreur apres (%) | K4: Reduction Erreurs (pts) | L4: Responsable | M4: Statut
B5: AP-001 | C5: Gestion des conges | D5: Automatise | E5: SIRH HotelPro | F5: 8 | G5: 2 | H5: 12 | I5: 15 | J5: 2 | L5: DRH | M5: En production
B6: AP-002 | C6: Note de frais | D6: Partiellement automatise | E6: Lucca | F6: 6 | G6: 3 | H6: 6 | I6: 20 | J6: 8 | L6: DAF | M6: En cours
B7: AP-003 | C7: Onboarding employe | D7: Partiellement automatise | E7: SIRH + Email auto | F7: 12 | G7: 5 | H7: 18 | I7: 25 | J7: 10 | L7: Assistante RH | M7: Test
B8: =IF(C8="","AP-"&TEXT(COUNTA($C$5:C8),"000")) | K8: =IF(OR(I8="",J8=""),"",I8-J8)
B9: =IF(C9="","AP-"&TEXT(COUNTA($C$5:C9),"000")) | K9: =IF(OR(I9="",J9=""),"",I9-J9)
B10: =IF(C10="","AP-"&TEXT(COUNTA($C$5:C10),"000")) | K10: =IF(OR(I10="",J10=""),"",I10-J10)
B11: =IF(C11="","AP-"&TEXT(COUNTA($C$5:C11),"000")) | K11: =IF(OR(I11="",J11=""),"",I11-J11)
B12: =IF(C12="","AP-"&TEXT(COUNTA($C$5:C12),"000")) | K12: =IF(OR(I12="",J12=""),"",I12-J12)
B13: =IF(C13="","AP-"&TEXT(COUNTA($C$5:C13),"000")) | K13: =IF(OR(I13="",J13=""),"",I13-J13)
B14: =IF(C14="","AP-"&TEXT(COUNTA($C$5:C14),"000")) | K14: =IF(OR(I14="",J14=""),"",I14-J14)
B15: =IF(C15="","AP-"&TEXT(COUNTA($C$5:C15),"000")) | K15: =IF(OR(I15="",J15=""),"",I15-J15)
B16: =IF(C16="","AP-"&TEXT(COUNTA($C$5:C16),"000")) | K16: =IF(OR(I16="",J16=""),"",I16-J16)
B17: =IF(C17="","AP-"&TEXT(COUNTA($C$5:C17),"000")) | K17: =IF(OR(I17="",J17=""),"",I17-J17)
B18: =IF(C18="","AP-"&TEXT(COUNTA($C$5:C18),"000")) | K18: =IF(OR(I18="",J18=""),"",I18-J18)
B19: =IF(C19="","AP-"&TEXT(COUNTA($C$5:C19),"000")) | K19: =IF(OR(I19="",J19=""),"",I19-J19)
... B107: =IF(C107="","AP-"&TEXT(COUNTA($C$5:C107),"000")) | K107: =IF(OR(I107="",J107=""),"",I107-J107)
B109: INDICATEURS (mis a jour automatiquement)
B110: Processus documentes | D110: Gain temps total (h/m) | F110: Totalement auto.
B111: =COUNTIF(B5:B104,"<>") | D111: =SUM(H5:H104) | F111: =COUNTIF(D5:D104,"Totalement automatise")

Sheet 4-Intelligence Artificielle RH
B2: INTELLIGENCE ARTIFICIELLE RH (#159)
B3: TABLEAU DYNAMIQUE — Saisissez dans la prochaine ligne jaune. Les calculs se mettent a jour automatiquement.
B4: N° | C4: Cas d'Usage IA | D4: Type IA | E4: Departement Beneficiaire | F4: Description Cas Usage | G4: Outil / Plateforme | H4: Date Lancement | I4: Nb Candidats / Dossiers traites | J4: Taux Precision IA (%) | K4: Gain Temps (h/mois) | L4: Statut | M4: Observations
B5: IA-001 | C5: Pre-selection CV | D5: CV Screening | E5: Service Client | F5: IA analyse automatiquement les CV et classe les candidats par pertinence | G5: Welcome to the Jungle | H5: 45672 | I5: 340 | J5: 78.5 | K5: 20 | L5: Test | M5: Amelioration algo en cours
B6: IA-002 | C6: Prediction turnover | D6: Predictif turnover | E6: Service Client | F6: Model predictif identifie les employes a risque de depart | G6: SIRH HotelPro + Python | H6: 45717 | I6: 0 | J6: 72 | K6: 8 | L6: Prototype | M6: Donnees 2023-2024 entrainees
B7: IA-003 | C7: Chatbot RH employe | D7: Chatbot RH | E7: Tous les departements | F7: Assistant virtuel repond aux questions RH courantes (conges, paie, etc.) | G7: Custom GPT | H7: 45689 | I7: 125 | J7: 85 | K7: 15 | L7: Deploiement pilote | M7: Base connaissances 150 FAQ
B8: =IF(C8="","IA-"&TEXT(COUNTA($C$5:C8),"000"))
B9: =IF(C9="","IA-"&TEXT(COUNTA($C$5:C9),"000"))
B10: =IF(C10="","IA-"&TEXT(COUNTA($C$5:C10),"000"))
B11: =IF(C11="","IA-"&TEXT(COUNTA($C$5:C11),"000"))
B12: =IF(C12="","IA-"&TEXT(COUNTA($C$5:C12),"000"))
B13: =IF(C13="","IA-"&TEXT(COUNTA($C$5:C13),"000"))
B14: =IF(C14="","IA-"&TEXT(COUNTA($C$5:C14),"000"))
B15: =IF(C15="","IA-"&TEXT(COUNTA($C$5:C15),"000"))
B16: =IF(C16="","IA-"&TEXT(COUNTA($C$5:C16),"000"))
B17: =IF(C17="","IA-"&TEXT(COUNTA($C$5:C17),"000"))
B18: =IF(C18="","IA-"&TEXT(COUNTA($C$5:C18),"000"))
B19: =IF(C19="","IA-"&TEXT(COUNTA($C$5:C19),"000"))
... B107: =IF(C107="","IA-"&TEXT(COUNTA($C$5:C107),"000"))
B109: INDICATEURS (mis a jour automatiquement)
B110: Cas d'usage IA | D110: En production | F110: Dossiers traites IA
B111: =COUNTIF(B5:B104,"<>") | D111: =COUNTIF(L5:L104,"Production") | F111: =SUM(I5:I104)

Sheet 5-Data Analytics RH
B2: DATA ANALYTICS RH (#160)
B3: TABLEAU DYNAMIQUE — Saisissez dans la prochaine ligne jaune. Les calculs se mettent a jour automatiquement.
B4: N° | C4: Indicateur Analytique | D4: Source de Donnees | E4: Type Analyse | F4: Frequence | G4: Derniere MAJ | H4: Valeur Actuelle | I4: Valeur Precedente | J4: Evolution | K4: Objectif | L4: Statut | M4: Observations
B5: DA-001 | C5: Taux rotation global | D5: SIRH | E5: Descriptive | F5: Mensuel | G5: 45747 | H5: 0.18 | I5: 0.22 | K5: 0.12 | L5: En amelioration | M5: Baisse significative vs Q4 2024
B6: DA-002 | C6: Delai moyen recrutement (j) | D6: ATS + SIRH | E6: Descriptive | F6: Mensuel | G6: 45747 | H6: 28 | I6: 35 | K6: 21 | L6: En amelioration | M6: ATS + IA preselection accelere
B7: DA-003 | C7: Score engagement predictif | D7: SIRH + Enquetes | E7: Predictif | F7: Trimestriel | G7: 45731 | H7: 3.7 | I7: 3.5 | K7: 4.2 | L7: En amelioration | M7: Model ML en phase de calibration
B8: =IF(C8="","DA-"&TEXT(COUNTA($C$5:C8),"000")) | J8: =IF(OR(H8="",I8=""),"",H8-I8)
B9: =IF(C9="","DA-"&TEXT(COUNTA($C$5:C9),"000")) | J9: =IF(OR(H9="",I9=""),"",H9-I9)
B10: =IF(C10="","DA-"&TEXT(COUNTA($C$5:C10),"000")) | J10: =IF(OR(H10="",I10=""),"",H10-I10)
B11: =IF(C11="","DA-"&TEXT(COUNTA($C$5:C11),"000")) | J11: =IF(OR(H11="",I11=""),"",H11-I11)
B12: =IF(C12="","DA-"&TEXT(COUNTA($C$5:C12),"000")) | J12: =IF(OR(H12="",I12=""),"",H12-I12)
B13: =IF(C13="","DA-"&TEXT(COUNTA($C$5:C13),"000")) | J13: =IF(OR(H13="",I13=""),"",H13-I13)
B14: =IF(C14="","DA-"&TEXT(COUNTA($C$5:C14),"000")) | J14: =IF(OR(H14="",I14=""),"",H14-I14)
B15: =IF(C15="","DA-"&TEXT(COUNTA($C$5:C15),"000")) | J15: =IF(OR(H15="",I15=""),"",H15-I15)
B16: =IF(C16="","DA-"&TEXT(COUNTA($C$5:C16),"000")) | J16: =IF(OR(H16="",I16=""),"",H16-I16)
B17: =IF(C17="","DA-"&TEXT(COUNTA($C$5:C17),"000")) | J17: =IF(OR(H17="",I17=""),"",H17-I17)
B18: =IF(C18="","DA-"&TEXT(COUNTA($C$5:C18),"000")) | J18: =IF(OR(H18="",I18=""),"",H18-I18)
B19: =IF(C19="","DA-"&TEXT(COUNTA($C$5:C19),"000")) | J19: =IF(OR(H19="",I19=""),"",H19-I19)
... B107: =IF(C107="","DA-"&TEXT(COUNTA($C$5:C107),"000")) | J107: =IF(OR(H107="",I107=""),"",H107-I107)
B109: INDICATEURS (mis a jour automatiquement)
B110: Indicateurs analyses | D110: Analyses predictives | F110: En amelioration
B111: =COUNTIF(B5:B104,"<>") | D111: =COUNTIF(E5:E104,"Predictif") | F111: =COUNTIF(L5:L104,"En amelioration")

Sheet 6-SIRH & Systemes Info
B2: SIRH & SYSTEMES D'INFORMATION RH (#161)
B3: TABLEAU DYNAMIQUE — Saisissez dans la prochaine ligne jaune. Les calculs se mettent a jour automatiquement.
B4: N° | C4: Module SIRH | D4: Fonctionnalites Cles | E4: Utilisateurs Cles | F4: Date Mise en Service | G4: Derniere Mise a Jour | H4: Nb Pannes / Mois | I4: Temps Indisponibilite (h/m) | J4: Taux Disponibilite (%) | K4: Satisfaction Utilisateurs | L4: Statut | M4: Observations
B5: SIRH-001 | C5: Module Paie | D5: Calcul paie, bulletins, declarations CNPS | E5: DAF, Comptable senior, DRH | F5: 45078 | G5: 45703 | H5: 1 | I5: 2 | K5: Satisfait | L5: En production | M5: MAJ reglementaire mars 2025
B6: SIRH-002 | C6: Module Recrutement | D6: Offres, CV, entretiens, integration | E6: DRH, Assistante RH, Chefs service | F6: 45292 | G6: 45717 | H6: 0 | I6: 0 | K6: Tres satisfait | L6: En production | M6: Integration WTJ operationnelle
B7: SIRH-003 | C7: Module Temps & Activites | D7: Pointage, planning, conges, heures sup. | E7: Tous les managers | F7: 45444 | G7: 45677 | H7: 2 | I7: 4 | K7: Neutre | L7: En production | M7: App mobile en cours dev
B8: =IF(C8="","SIRH-"&TEXT(COUNTA($C$5:C8),"000")) | J8: =IF(I8="","",1-I8/160)
B9: =IF(C9="","SIRH-"&TEXT(COUNTA($C$5:C9),"000")) | J9: =IF(I9="","",1-I9/160)
B10: =IF(C10="","SIRH-"&TEXT(COUNTA($C$5:C10),"000")) | J10: =IF(I10="","",1-I10/160)
B11: =IF(C11="","SIRH-"&TEXT(COUNTA($C$5:C11),"000")) | J11: =IF(I11="","",1-I11/160)
B12: =IF(C12="","SIRH-"&TEXT(COUNTA($C$5:C12),"000")) | J12: =IF(I12="","",1-I12/160)
B13: =IF(C13="","SIRH-"&TEXT(COUNTA($C$5:C13),"000")) | J13: =IF(I13="","",1-I13/160)
B14: =IF(C14="","SIRH-"&TEXT(COUNTA($C$5:C14),"000")) | J14: =IF(I14="","",1-I14/160)
B15: =IF(C15="","SIRH-"&TEXT(COUNTA($C$5:C15),"000")) | J15: =IF(I15="","",1-I15/160)
B16: =IF(C16="","SIRH-"&TEXT(COUNTA($C$5:C16),"000")) | J16: =IF(I16="","",1-I16/160)
B17: =IF(C17="","SIRH-"&TEXT(COUNTA($C$5:C17),"000")) | J17: =IF(I17="","",1-I17/160)
B18: =IF(C18="","SIRH-"&TEXT(COUNTA($C$5:C18),"000")) | J18: =IF(I18="","",1-I18/160)
B19: =IF(C19="","SIRH-"&TEXT(COUNTA($C$5:C19),"000")) | J19: =IF(I19="","",1-I19/160)
... B107: =IF(C107="","SIRH-"&TEXT(COUNTA($C$5:C107),"000")) | J107: =IF(I107="","",1-I107/160)
B109: INDICATEURS (mis a jour automatiquement)
B110: Modules SIRH | D110: En production | F110: Pannes totales/mois
B111: =COUNTIF(B5:B104,"<>") | D111: =COUNTIF(L5:L104,"En production") | F111: =SUM(H5:H104)

Sheet 7-Digital Learning & E-Learning
B2: DIGITAL LEARNING & E-LEARNING (#162)
B3: TABLEAU DYNAMIQUE — Saisissez dans la prochaine ligne jaune. Les calculs se mettent a jour automatiquement.
B4: N° | C4: Module E-Learning | D4: Plateforme | E4: Categorie | F4: Nb Inscriptions | G4: Nb Completions | H4: Taux Completion (%) | I4: Duree Moyenne (min) | J4: Score Moyen Quiz | K4: Satisfaction Moyenne | L4: Date Lancement | M4: Statut
B5: EL-001 | C5: Accueil & Securite Hotel | D5: Moodle interne | E5: Sécurité | F5: 48 | G5: 42 | I5: 45 | J5: 82 | K5: 4.2 | L5: 45667 | M5: En production
B6: EL-002 | C6: Excel avanc pour RH | D6: LinkedIn Learning | E6: Bureautique | F6: 25 | G6: 18 | I6: 120 | J6: 75 | K6: 3.8 | L6: 45689 | M6: En production
B7: EL-003 | C7: Gestion conflits au travail | D7: Moodle interne | E7: Soft skills | F7: 30 | G7: 12 | I7: 60 | J7: 88 | K7: 4.5 | L7: 45717 | M7: En cours
B8: =IF(C8="","EL-"&TEXT(COUNTA($C$5:C8),"000")) | H8: =IF(F8="","",G8/F8)
B9: =IF(C9="","EL-"&TEXT(COUNTA($C$5:C9),"000")) | H9: =IF(F9="","",G9/F9)
B10: =IF(C10="","EL-"&TEXT(COUNTA($C$5:C10),"000")) | H10: =IF(F10="","",G10/F10)
B11: =IF(C11="","EL-"&TEXT(COUNTA($C$5:C11),"000")) | H11: =IF(F11="","",G11/F11)
B12: =IF(C12="","EL-"&TEXT(COUNTA($C$5:C12),"000")) | H12: =IF(F12="","",G12/F12)
B13: =IF(C13="","EL-"&TEXT(COUNTA($C$5:C13),"000")) | H13: =IF(F13="","",G13/F13)
B14: =IF(C14="","EL-"&TEXT(COUNTA($C$5:C14),"000")) | H14: =IF(F14="","",G14/F14)
B15: =IF(C15="","EL-"&TEXT(COUNTA($C$5:C15),"000")) | H15: =IF(F15="","",G15/F15)
B16: =IF(C16="","EL-"&TEXT(COUNTA($C$5:C16),"000")) | H16: =IF(F16="","",G16/F16)
B17: =IF(C17="","EL-"&TEXT(COUNTA($C$5:C17),"000")) | H17: =IF(F17="","",G17/F17)
B18: =IF(C18="","EL-"&TEXT(COUNTA($C$5:C18),"000")) | H18: =IF(F18="","",G18/F18)
B19: =IF(C19="","EL-"&TEXT(COUNTA($C$5:C19),"000")) | H19: =IF(F19="","",G19/F19)
... B107: =IF(C107="","EL-"&TEXT(COUNTA($C$5:C107),"000")) | H107: =IF(F107="","",G107/F107)
B109: INDICATEURS (mis a jour automatiquement)
B110: Modules e-learning | D110: Inscriptions totales | F110: Taux compl. moyen
B111: =COUNTIF(B5:B104,"<>") | D111: =SUM(F5:F104) | F111: =IFERROR(AVERAGE(H5:H104),0)

Sheet 8-Applications Mobiles RH
B2: APPLICATIONS MOBILES RH (#163)
B3: TABLEAU DYNAMIQUE — Saisissez dans la prochaine ligne jaune. Les calculs se mettent a jour automatiquement.
B4: N° | C4: Application Mobile RH | D4: Fonctionnalites | E4: OS Supportes | F4: Nb Telechargements | G4: Utilisateurs Actifs/mois | H4: Taux Utilisation (%) | I4: Derniere Version | J4: Date MAJ | K4: Nb Avis Negatifs | L4: Statut | M4: Observations
B5: MOB-001 | C5: HotelApp RH | D5: Conges, paie, pointage, annonces | E5: iOS, Android | F5: 180 | G5: 145 | I5: v2.3.1 | J5: 45731 | K5: 3 | L5: En production | M5: Maj bug pointage en cours
B6: MOB-002 | C6: Wittyfit Bien-Etre | D6: Sondages bien-etre, activites | E6: iOS, Android | F6: 120 | G6: 85 | I6: v1.8.0 | J6: 45716 | K6: 1 | L6: En production | M6: Integration SIRH prevue
B7: MOB-003 | C7: Papayrhum Notes frais | D7: Saisie notes frais, photo justificatifs | E7: iOS, Android | F7: 45 | G7: 30 | I7: v3.1 | J7: 45677 | K7: 5 | L7: En production | M7: Flux de validation a ameliorer
B8: =IF(C8="","MOB-"&TEXT(COUNTA($C$5:C8),"000")) | H8: =IF(F8="","",G8/F8)
B9: =IF(C9="","MOB-"&TEXT(COUNTA($C$5:C9),"000")) | H9: =IF(F9="","",G9/F9)
B10: =IF(C10="","MOB-"&TEXT(COUNTA($C$5:C10),"000")) | H10: =IF(F10="","",G10/F10)
B11: =IF(C11="","MOB-"&TEXT(COUNTA($C$5:C11),"000")) | H11: =IF(F11="","",G11/F11)
B12: =IF(C12="","MOB-"&TEXT(COUNTA($C$5:C12),"000")) | H12: =IF(F12="","",G12/F12)
B13: =IF(C13="","MOB-"&TEXT(COUNTA($C$5:C13),"000")) | H13: =IF(F13="","",G13/F13)
B14: =IF(C14="","MOB-"&TEXT(COUNTA($C$5:C14),"000")) | H14: =IF(F14="","",G14/F14)
B15: =IF(C15="","MOB-"&TEXT(COUNTA($C$5:C15),"000")) | H15: =IF(F15="","",G15/F15)
B16: =IF(C16="","MOB-"&TEXT(COUNTA($C$5:C16),"000")) | H16: =IF(F16="","",G16/F16)
B17: =IF(C17="","MOB-"&TEXT(COUNTA($C$5:C17),"000")) | H17: =IF(F17="","",G17/F17)
B18: =IF(C18="","MOB-"&TEXT(COUNTA($C$5:C18),"000")) | H18: =IF(F18="","",G18/F18)
B19: =IF(C19="","MOB-"&TEXT(COUNTA($C$5:C19),"000")) | H19: =IF(F19="","",G19/F19)
... B107: =IF(C107="","MOB-"&TEXT(COUNTA($C$5:C107),"000")) | H107: =IF(F107="","",G107/F107)
B109: INDICATEURS (mis a jour automatiquement)
B110: Apps mobiles RH | D110: Total telechargements | F110: Utilisateurs actifs/m
B111: =COUNTIF(B5:B104,"<>") | D111: =SUM(F5:F104) | F111: =SUM(G5:G104)

Sheet 9-Chatbots & Assistants RH
B2: CHATBOTS & ASSISTANTS RH (#164)
B3: TABLEAU DYNAMIQUE — Saisissez dans la prochaine ligne jaune. Les calculs se mettent a jour automatiquement.
B4: N° | C4: Chatbot / Assistant | D4: Type | E4: Cas d'Usage Principal | F4: Technologie | G4: Nb Questions / Mois | H4: Taux Resolution Auto (%) | I4: Satisfaction Utilisateur | J4: Base Connaissances (FAQ) | K4: Date Lancement | L4: Statut | M4: Observations
B5: CB-001 | C5: RH Assistant Hotel | D5: Chatbot RH | E5: Repondre aux questions RH courantes | F5: GPT-4 + RAG interne | G5: 450 | H5: 82 | I5: 4.1 | J5: 150 | K5: 45689 | L5: Deploiement pilote | M5: Test avec dept. reception
B6: CB-002 | C6: Onboarding Bot | D6: Assistant virtuel | E6: Guider les nouveaux employes | F6: Custom flow | G6: 30 | H6: 90 | I6: 4.5 | J6: 45 | K6: 45672 | L6: Test | M6: Parcours 7 jours integre
B7: CB-003 | C7: FAQ Paie Bot | D7: Chatbot RH | E7: Repondre aux questions sur la paie | F7: Dialogflow | G7: 120 | H7: 75 | I7: 3.6 | J7: 80 | K7: 45597 | L7: En production | M7: Basculement vers GPT-4 etudie
B8: =IF(C8="","CB-"&TEXT(COUNTA($C$5:C8),"000"))
B9: =IF(C9="","CB-"&TEXT(COUNTA($C$5:C9),"000"))
B10: =IF(C10="","CB-"&TEXT(COUNTA($C$5:C10),"000"))
B11: =IF(C11="","CB-"&TEXT(COUNTA($C$5:C11),"000"))
B12: =IF(C12="","CB-"&TEXT(COUNTA($C$5:C12),"000"))
B13: =IF(C13="","CB-"&TEXT(COUNTA($C$5:C13),"000"))
B14: =IF(C14="","CB-"&TEXT(COUNTA($C$5:C14),"000"))
B15: =IF(C15="","CB-"&TEXT(COUNTA($C$5:C15),"000"))
B16: =IF(C16="","CB-"&TEXT(COUNTA($C$5:C16),"000"))
B17: =IF(C17="","CB-"&TEXT(COUNTA($C$5:C17),"000"))
B18: =IF(C18="","CB-"&TEXT(COUNTA($C$5:C18),"000"))
B19: =IF(C19="","CB-"&TEXT(COUNTA($C$5:C19),"000"))
... B107: =IF(C107="","CB-"&TEXT(COUNTA($C$5:C107),"000"))
B109: INDICATEURS (mis a jour automatiquement)
B110: Chatbots / Assistants | D110: Questions/mois total | F110: Taux reso. moyen (%)
B111: =COUNTIF(B5:B104,"<>") | D111: =SUM(G5:G104) | F111: =IFERROR(AVERAGE(H5:H104),0)

Sheet 10-Cybersecurite Donnees RH
B2: CYBERSECURITE DONNEES RH (#165)
B3: TABLEAU DYNAMIQUE — Saisissez dans la prochaine ligne jaune. Les calculs se mettent a jour automatiquement.
B4: N° | C4: Categorie Donnee RH | D4: Systeme / Application | E4: Niveau de Risque | F4: Mesures de Securite | G4: Dernier Audit | H4: Date Prochain Audit | I4: Nb Incidents (12 mois) | J4: Conformite RGPD/Others | K4: Responsable Securite | L4: Statut | M4: Observations
B5: CS-001 | C5: Donnees personnelles | D5: SIRH HotelPro | E5: Critique | F5: Chiffrement AES-256, MFA, logs acces | G5: 45672 | H5: 45853 | I5: 0 | J5: Conforme | K5: Chef de service IT | L5: En production | M5: Audit externe Q1 OK
B6: CS-002 | C6: Salaire & paie | D6: Lucca Paie | E6: Critique | F6: Chiffrement, acces restreint DRH+DAF, backup quot. | G6: 45597 | H6: 45778 | I6: 0 | J6: Conforme | K6: DAF | L6: En production | M6: Sauvegarde CLOUD quotidienne
B7: CS-003 | C7: Sante & medical | D7: Dossier medical papier | E7: Eleve | F7: Armoire fermee, acces DRH unique | G7: 45444 | H7: 45809 | I7: 1 | J7: Non conforme | K7: DRH | L7: En mise en conformite | M7: Migration vers numerique prevue
B8: =IF(C8="","CS-"&TEXT(COUNTA($C$5:C8),"000"))
B9: =IF(C9="","CS-"&TEXT(COUNTA($C$5:C9),"000"))
B10: =IF(C10="","CS-"&TEXT(COUNTA($C$5:C10),"000"))
B11: =IF(C11="","CS-"&TEXT(COUNTA($C$5:C11),"000"))
B12: =IF(C12="","CS-"&TEXT(COUNTA($C$5:C12),"000"))
B13: =IF(C13="","CS-"&TEXT(COUNTA($C$5:C13),"000"))
B14: =IF(C14="","CS-"&TEXT(COUNTA($C$5:C14),"000"))
B15: =IF(C15="","CS-"&TEXT(COUNTA($C$5:C15),"000"))
B16: =IF(C16="","CS-"&TEXT(COUNTA($C$5:C16),"000"))
B17: =IF(C17="","CS-"&TEXT(COUNTA($C$5:C17),"000"))
B18: =IF(C18="","CS-"&TEXT(COUNTA($C$5:C18),"000"))
B19: =IF(C19="","CS-"&TEXT(COUNTA($C$5:C19),"000"))
... B107: =IF(C107="","CS-"&TEXT(COUNTA($C$5:C107),"000"))
B109: INDICATEURS (mis a jour automatiquement)
B110: Categories securisees | D110: Incidents totaux | F110: Conformes
B111: =COUNTIF(B5:B104,"<>") | D111: =SUM(I5:I104) | F111: =COUNTIF(J5:J104,"Conforme")

Sheet 11-Veille Technologique RH
B2: VEILLE TECHNOLOGIQUE RH (#166)
B3: TABLEAU DYNAMIQUE — Saisissez dans la prochaine ligne jaune. Les calculs se mettent a jour automatiquement.
B4: N° | C4: Sujet / Technologie | D4: Description | E4: Source Veille | F4: Frequence Suivi | G4: Impact Potentiel RH | H4: Date Decouverte | I4: Date Evaluation | J4: Priorite | K4: Statut | L4: Observations
B5: VT-001 | C5: IA Generative pour RH | D5: Utilisation de ChatGPT/Claude pour rediger offres, fiches poste, syntheses entretiens | E5: Blog tech, Conference HR Tech | F5: Hebdomadaire | G5: Eleve - Automatisation redaction | H5: 45566 | I5: 45672 | J5: Haute | K5: Etude de faisabilite | L5: POC en cours avec GPT-4
B6: VT-002 | C6: Blockchain pour verification diplomes | D6: Verification instantanee des diplomes et certifications candidats | E6: Publication academique | F6: Mensuelle | G6: Moyen - Securisation recrutement | H6: 45627 | J6: Moyenne | K6: Idee | L6: Technologie encore immature pour notre contexte
B7: VT-003 | C7: Reality augmentee formation | D7: Formation immersive via AR pour les postes operationnels (cuisine, menage) | E7: Conference HR Tech | F7: Trimestrielle | G7: Eleve - Amelioration formation | H7: 45667 | I7: 45748 | J7: Haute | K7: Etude de faisabilite | L7: Casque AR Oculus teste en fev 2025
B8: =IF(C8="","VT-"&TEXT(COUNTA($C$5:C8),"000"))
B9: =IF(C9="","VT-"&TEXT(COUNTA($C$5:C9),"000"))
B10: =IF(C10="","VT-"&TEXT(COUNTA($C$5:C10),"000"))
B11: =IF(C11="","VT-"&TEXT(COUNTA($C$5:C11),"000"))
B12: =IF(C12="","VT-"&TEXT(COUNTA($C$5:C12),"000"))
B13: =IF(C13="","VT-"&TEXT(COUNTA($C$5:C13),"000"))
B14: =IF(C14="","VT-"&TEXT(COUNTA($C$5:C14),"000"))
B15: =IF(C15="","VT-"&TEXT(COUNTA($C$5:C15),"000"))
B16: =IF(C16="","VT-"&TEXT(COUNTA($C$5:C16),"000"))
B17: =IF(C17="","VT-"&TEXT(COUNTA($C$5:C17),"000"))
B18: =IF(C18="","VT-"&TEXT(COUNTA($C$5:C18),"000"))
B19: =IF(C19="","VT-"&TEXT(COUNTA($C$5:C19),"000"))
... B107: =IF(C107="","VT-"&TEXT(COUNTA($C$5:C107),"000"))
B109: INDICATEURS (mis a jour automatiquement)
B110: Suivis veille tech | D110: Impact eleve | F110: En etude
B111: =COUNTIF(B5:B104,"<>") | D111: =COUNTIF(G5:G104,"Eleve*") | F111: =COUNTIF(K5:K104,"Etude*")

Sheet 12-Suivi Projets Digitaux
B2: SUIVI PROJETS DIGITAUX RH
B3: TABLEAU DYNAMIQUE — Saisissez dans la prochaine ligne jaune. Les calculs se mettent a jour automatiquement.
B4: N° | C4: Projet Digital RH | D4: Type Projet | E4: Responsable | F4: Date Debut | G4: Date Fin Prevue | H4: Budget Prevu (FCFA) | I4: Budget Consomme (FCFA) | J4: Taux Consommation (%) | K4: Jours Restants | L4: Statut | M4: Observations
B5: SPD-001 | C5: Migration SIRH cloud | D5: Infrastructure | E5: Chef de service IT | F5: 45658 | G5: 45930 | H5: 8000000 | I5: 3200000 | L5: En cours | M5: Phase 2/4 en cours
B6: SPD-002 | C6: Chatbot RH v2 | D6: IA & Chatbot | E6: DRH | F6: 45689 | G6: 45838 | H6: 1500000 | I6: 450000 | L6: En cours | M6: Integration GPT-4 terminee
B7: SPD-003 | C7: App Mobile Pointage | D7: Application mobile | E7: Chef de service IT | F7: 45717 | G7: 45869 | H7: 2000000 | I7: 200000 | L7: En cours | M7: Maquettes validees, dev en cours
B8: =IF(C8="","SPD-"&TEXT(COUNTA($C$5:C8),"000")) | J8: =IF(H8="","",I8/H8) | K8: =IF(G8="","",MAX(G8-TODAY(),0))
B9: =IF(C9="","SPD-"&TEXT(COUNTA($C$5:C9),"000")) | J9: =IF(H9="","",I9/H9) | K9: =IF(G9="","",MAX(G9-TODAY(),0))
B10: =IF(C10="","SPD-"&TEXT(COUNTA($C$5:C10),"000")) | J10: =IF(H10="","",I10/H10) | K10: =IF(G10="","",MAX(G10-TODAY(),0))
B11: =IF(C11="","SPD-"&TEXT(COUNTA($C$5:C11),"000")) | J11: =IF(H11="","",I11/H11) | K11: =IF(G11="","",MAX(G11-TODAY(),0))
B12: =IF(C12="","SPD-"&TEXT(COUNTA($C$5:C12),"000")) | J12: =IF(H12="","",I12/H12) | K12: =IF(G12="","",MAX(G12-TODAY(),0))
B13: =IF(C13="","SPD-"&TEXT(COUNTA($C$5:C13),"000")) | J13: =IF(H13="","",I13/H13) | K13: =IF(G13="","",MAX(G13-TODAY(),0))
B14: =IF(C14="","SPD-"&TEXT(COUNTA($C$5:C14),"000")) | J14: =IF(H14="","",I14/H14) | K14: =IF(G14="","",MAX(G14-TODAY(),0))
B15: =IF(C15="","SPD-"&TEXT(COUNTA($C$5:C15),"000")) | J15: =IF(H15="","",I15/H15) | K15: =IF(G15="","",MAX(G15-TODAY(),0))
B16: =IF(C16="","SPD-"&TEXT(COUNTA($C$5:C16),"000")) | J16: =IF(H16="","",I16/H16) | K16: =IF(G16="","",MAX(G16-TODAY(),0))
B17: =IF(C17="","SPD-"&TEXT(COUNTA($C$5:C17),"000")) | J17: =IF(H17="","",I17/H17) | K17: =IF(G17="","",MAX(G17-TODAY(),0))
B18: =IF(C18="","SPD-"&TEXT(COUNTA($C$5:C18),"000")) | J18: =IF(H18="","",I18/H18) | K18: =IF(G18="","",MAX(G18-TODAY(),0))
B19: =IF(C19="","SPD-"&TEXT(COUNTA($C$5:C19),"000")) | J19: =IF(H19="","",I19/H19) | K19: =IF(G19="","",MAX(G19-TODAY(),0))
... B107: =IF(C107="","SPD-"&TEXT(COUNTA($C$5:C107),"000")) | J107: =IF(H107="","",I107/H107) | K107: =IF(G107="","",MAX(G107-TODAY(),0))
B109: INDICATEURS (mis a jour automatiquement)
B110: Projets digitaux | D110: Budget total (FCFA) | F110: En cours
B111: =COUNTIF(B5:B104,"<>") | D111: =SUM(H5:H104) | F111: =COUNTIF(L5:L104,"En cours")

Sheet 13-Analyse ROI Outils Digitaux
B2: ANALYSE ROI OUTILS DIGITAUX
B3: TABLEAU DYNAMIQUE — Saisissez dans la prochaine ligne jaune. Les calculs se mettent a jour automatiquement.
B4: N° | C4: Outil Digital | D4: Investissement Initial (FCFA) | E4: Cout Annuel (FCFA) | F4: Gain Temps (h/an) | G4: Cout Heure RH (FCFA) | H4: Economie Temps (FCFA/an) | I4: Reduction Erreurs (%) | J4: Economie Erreurs (FCFA/an) | K4: ROI Annuel (%) | L4: Delai Recup. (mois) | M4: Observations | N4: Categorie Outil
B5: ROI-001 | C5: SIRH HotelPro | D5: 5000000 | E5: 3600000 | F5: 960 | G5: 5000 | I5: 0.1 | J5: 800000 | M5: ROI positif des la 2e annee | N5: SIRH
B6: ROI-002 | C6: Lucca Paie | D6: 500000 | E6: 1200000 | F6: 360 | G6: 5000 | I6: 0.15 | J6: 450000 | M6: Integration SIRH ameliorera le ROI | N6: Paie
B7: ROI-003 | C7: Chatbot RH | D7: 800000 | E7: 300000 | F7: 240 | G7: 5000 | I7: 0.08 | J7: 200000 | M7: Gain qualitatif non chiffre (satisfaction) | N7: Communication
B8: =IF(C8="","ROI-"&TEXT(COUNTA($C$5:C8),"000")) | H8: =IF(OR(F8="",G8=""),"",F8*G8) | J8: =IF(I8="","",D8*I8) | K8: =IF(OR(H8="",J8="",E8=""),"",(H8+J8-E8)/D8) | L8: =IF(OR(H8="",J8="",E8="",D8=""),"",IF((H8+J8-E8)<=0,"N/A",D8/((H8+J8-E8)/12)) | N8: Formation
B9: =IF(C9="","ROI-"&TEXT(COUNTA($C$5:C9),"000")) | H9: =IF(OR(F9="",G9=""),"",F9*G9) | J9: =IF(I9="","",D9*I9) | K9: =IF(OR(H9="",J9="",E9=""),"",(H9+J9-E9)/D9) | L9: =IF(OR(H9="",J9="",E9="",D9=""),"",IF((H9+J9-E9)<=0,"N/A",D9/((H9+J9-E9)/12)) | N9: SIRH
B10: =IF(C10="","ROI-"&TEXT(COUNTA($C$5:C10),"000")) | H10: =IF(OR(F10="",G10=""),"",F10*G10) | J10: =IF(I10="","",D10*I10) | K10: =IF(OR(H10="",J10="",E10=""),"",(H10+J10-E10)/D10) | L10: =IF(OR(H10="",J10="",E10="",D10=""),"",IF((H10+J10-E10)<=0,"N/A",D10/((H10+J10-E10)/12))
B11: =IF(C11="","ROI-"&TEXT(COUNTA($C$5:C11),"000")) | H11: =IF(OR(F11="",G11=""),"",F11*G11) | J11: =IF(I11="","",D11*I11) | K11: =IF(OR(H11="",J11="",E11=""),"",(H11+J11-E11)/D11) | L11: =IF(OR(H11="",J11="",E11="",D11=""),"",IF((H11+J11-E11)<=0,"N/A",D11/((H11+J11-E11)/12))
B12: =IF(C12="","ROI-"&TEXT(COUNTA($C$5:C12),"000")) | H12: =IF(OR(F12="",G12=""),"",F12*G12) | J12: =IF(I12="","",D12*I12) | K12: =IF(OR(H12="",J12="",E12=""),"",(H12+J12-E12)/D12) | L12: =IF(OR(H12="",J12="",E12="",D12=""),"",IF((H12+J12-E12)<=0,"N/A",D12/((H12+J12-E12)/12))
B13: =IF(C13="","ROI-"&TEXT(COUNTA($C$5:C13),"000")) | H13: =IF(OR(F13="",G13=""),"",F13*G13) | J13: =IF(I13="","",D13*I13) | K13: =IF(OR(H13="",J13="",E13=""),"",(H13+J13-E13)/D13) | L13: =IF(OR(H13="",J13="",E13="",D13=""),"",IF((H13+J13-E13)<=0,"N/A",D13/((H13+J13-E13)/12))
B14: =IF(C14="","ROI-"&TEXT(COUNTA($C$5:C14),"000")) | H14: =IF(OR(F14="",G14=""),"",F14*G14) | J14: =IF(I14="","",D14*I14) | K14: =IF(OR(H14="",J14="",E14=""),"",(H14+J14-E14)/D14) | L14: =IF(OR(H14="",J14="",E14="",D14=""),"",IF((H14+J14-E14)<=0,"N/A",D14/((H14+J14-E14)/12))
B15: =IF(C15="","ROI-"&TEXT(COUNTA($C$5:C15),"000")) | H15: =IF(OR(F15="",G15=""),"",F15*G15) | J15: =IF(I15="","",D15*I15) | K15: =IF(OR(H15="",J15="",E15=""),"",(H15+J15-E15)/D15) | L15: =IF(OR(H15="",J15="",E15="",D15=""),"",IF((H15+J15-E15)<=0,"N/A",D15/((H15+J15-E15)/12))
B16: =IF(C16="","ROI-"&TEXT(COUNTA($C$5:C16),"000")) | H16: =IF(OR(F16="",G16=""),"",F16*G16) | J16: =IF(I16="","",D16*I16) | K16: =IF(OR(H16="",J16="",E16=""),"",(H16+J16-E16)/D16) | L16: =IF(OR(H16="",J16="",E16="",D16=""),"",IF((H16+J16-E16)<=0,"N/A",D16/((H16+J16-E16)/12))
B17: =IF(C17="","ROI-"&TEXT(COUNTA($C$5:C17),"000")) | H17: =IF(OR(F17="",G17=""),"",F17*G17) | J17: =IF(I17="","",D17*I17) | K17: =IF(OR(H17="",J17="",E17=""),"",(H17+J17-E17)/D17) | L17: =IF(OR(H17="",J17="",E17="",D17=""),"",IF((H17+J17-E17)<=0,"N/A",D17/((H17+J17-E17)/12))
B18: =IF(C18="","ROI-"&TEXT(COUNTA($C$5:C18),"000")) | H18: =IF(OR(F18="",G18=""),"",F18*G18) | J18: =IF(I18="","",D18*I18) | K18: =IF(OR(H18="",J18="",E18=""),"",(H18+J18-E18)/D18) | L18: =IF(OR(H18="",J18="",E18="",D18=""),"",IF((H18+J18-E18)<=0,"N/A",D18/((H18+J18-E18)/12))
B19: =IF(C19="","ROI-"&TEXT(COUNTA($C$5:C19),"000")) | H19: =IF(OR(F19="",G19=""),"",F19*G19) | J19: =IF(I19="","",D19*I19) | K19: =IF(OR(H19="",J19="",E19=""),"",(H19+J19-E19)/D19) | L19: =IF(OR(H19="",J19="",E19="",D19=""),"",IF((H19+J19-E19)<=0,"N/A",D19/((H19+J19-E19)/12))
B20: =IF(C20="","ROI-"&TEXT(COUNTA($C$5:C20),"000")) | H20: =IF(OR(F20="",G20=""),"",F20*G20) | J20: =IF(I20="","",D20*I20) | K20: =IF(OR(H20="",J20="",E20=""),"",(H20+J20-E20)/D20) | L20: =IF(OR(H20="",J20="",E20="",D20=""),"",IF((H20+J20-E20)<=0,"N/A",D20/((H20+J20-E20)/12))
B21: =IF(C21="","ROI-"&TEXT(COUNTA($C$5:C21),"000")) | H21: =IF(OR(F21="",G21=""),"",F21*G21) | J21: =IF(I21="","",D21*I21) | K21: =IF(OR(H21="",J21="",E21=""),"",(H21+J21-E21)/D21) | L21: =IF(OR(H21="",J21="",E21="",D21=""),"",IF((H21+J21-E21)<=0,"N/A",D21/((H21+J21-E21)/12))
... B107: =IF(C107="","ROI-"&TEXT(COUNTA($C$5:C107),"000")) | H107: =IF(OR(F107="",G107=""),"",F107*G107) | J107: =IF(I107="","",D107*I107) | K107: =IF(OR(H107="",J107="",E107=""),"",(H107+J107-E107)/D107) | L107: =IF(OR(H107="",J107="",E107="",D107=""),"",IF((H107+J107-E107)<=0,"N/A",D107/((H107+J107-E107)/12))
B109: INDICATEURS (mis a jour automatiquement)
B110: Outils analyses ROI | D110: Investissement total | F110: ROI moyen (%)
B111: =COUNTIF(B5:B104,"<>") | D111: =SUM(D5:D104) | F111: =IFERROR(AVERAGE(K5:K104),0)

Sheet 14-Suivi Adoption Outils
B2: SUIVI ADOPTION OUTILS
B3: TABLEAU DYNAMIQUE — Saisissez dans la prochaine ligne jaune. Les calculs se mettent a jour automatiquement.
B4: N° | C4: Outil / Solution | D4: Population Cible | E4: Nb Utilisateurs Actifs | F4: Population Cible (Nb) | G4: Taux Adoption (%) | H4: Nb Formations Realisees | I4: Nb Tickets Support / Mois | J4: Satisfaction Moyenne | K4: Statut Adoption | L4: Observations
B5: ADO-001 | C5: SIRH HotelPro | D5: Cadres & RH | E5: 12 | F5: 15 | H5: 4 | I5: 8 | J5: 3.8 | K5: Maitrise | L5: Bonne adoption, quelques resistances
B6: ADO-002 | C6: Lucca Paie | D6: Finance & RH | E6: 5 | F6: 8 | H6: 2 | I6: 3 | J6: 4.2 | K6: Adopte | L6: Formation complementaire planifiee
B7: ADO-003 | C7: HotelApp RH | D7: Tous les employes | E7: 145 | F7: 200 | H7: 6 | I7: 15 | J7: 3.5 | K7: En cours d'adoption | L7: Campagne communication lancee
B8: =IF(C8="","ADO-"&TEXT(COUNTA($C$5:C8),"000")) | G8: =IF(F8="","",E8/F8)
B9: =IF(C9="","ADO-"&TEXT(COUNTA($C$5:C9),"000")) | G9: =IF(F9="","",E9/F9)
B10: =IF(C10="","ADO-"&TEXT(COUNTA($C$5:C10),"000")) | G10: =IF(F10="","",E10/F10)
B11: =IF(C11="","ADO-"&TEXT(COUNTA($C$5:C11),"000")) | G11: =IF(F11="","",E11/F11)
B12: =IF(C12="","ADO-"&TEXT(COUNTA($C$5:C12),"000")) | G12: =IF(F12="","",E12/F12)
B13: =IF(C13="","ADO-"&TEXT(COUNTA($C$5:C13),"000")) | G13: =IF(F13="","",E13/F13)
B14: =IF(C14="","ADO-"&TEXT(COUNTA($C$5:C14),"000")) | G14: =IF(F14="","",E14/F14)
B15: =IF(C15="","ADO-"&TEXT(COUNTA($C$5:C15),"000")) | G15: =IF(F15="","",E15/F15)
B16: =IF(C16="","ADO-"&TEXT(COUNTA($C$5:C16),"000")) | G16: =IF(F16="","",E16/F16)
B17: =IF(C17="","ADO-"&TEXT(COUNTA($C$5:C17),"000")) | G17: =IF(F17="","",E17/F17)
B18: =IF(C18="","ADO-"&TEXT(COUNTA($C$5:C18),"000")) | G18: =IF(F18="","",E18/F18)
B19: =IF(C19="","ADO-"&TEXT(COUNTA($C$5:C19),"000")) | G19: =IF(F19="","",E19/F19)
... B107: =IF(C107="","ADO-"&TEXT(COUNTA($C$5:C107),"000")) | G107: =IF(F107="","",E107/F107)
B109: INDICATEURS (mis a jour automatiquement)
B110: Outils suivis | D110: Taux adopt. moyen (%) | F110: Maitrises
B111: =COUNTIF(B5:B104,"<>") | D111: =IFERROR(AVERAGE(G5:G104),0) | F111: =COUNTIF(K5:K104,"Maitrise")

Sheet 15-Historique Deploiements
B2: HISTORIQUE DEPLOIEMENTS
B3: TABLEAU DYNAMIQUE — Saisissez dans la prochaine ligne jaune. Les calculs se mettent a jour automatiquement.
B4: N° | C4: Solution Deployee | D4: Type Outil | E4: Version Deployee | F4: Date Deploiement | G4: Responsable | H4: Nb Utilisateurs Impactes | I4: Nb Incidents Post-Dep. | J4: Duree Deploiement (j) | K4: Succes / Echec | L4: Statut | M4: Observations
B5: DEP-001 | C5: SIRH HotelPro v4.2 | D5: SIRH | E5: v4.2 | F5: 45703 | G5: Chef de service IT | H5: 45 | I5: 1 | J5: 3 | K5: Succes | L5: En production | M5: Correctif mineur jour J+2
B6: DEP-002 | C6: Lucca integration SIRH | D6: Paie | E6: v2.0 | F6: 45717 | G6: Technicien IT | H6: 8 | I6: 0 | J6: 1 | K6: Succes | L6: En production | M6: Migration donnees reussie
B7: DEP-003 | C7: HotelApp v2.3 | D7: Application mobile | E7: v2.3.1 | F7: 45726 | G7: Chef de service IT | H7: 180 | I7: 5 | J7: 2 | K7: Succes | L7: En production | M7: Bug pointage corrige en v2.3.1
B8: =IF(C8="","DEP-"&TEXT(COUNTA($C$5:C8),"000"))
B9: =IF(C9="","DEP-"&TEXT(COUNTA($C$5:C9),"000"))
B10: =IF(C10="","DEP-"&TEXT(COUNTA($C$5:C10),"000"))
B11: =IF(C11="","DEP-"&TEXT(COUNTA($C$5:C11),"000"))
B12: =IF(C12="","DEP-"&TEXT(COUNTA($C$5:C12),"000"))
B13: =IF(C13="","DEP-"&TEXT(COUNTA($C$5:C13),"000"))
B14: =IF(C14="","DEP-"&TEXT(COUNTA($C$5:C14),"000"))
B15: =IF(C15="","DEP-"&TEXT(COUNTA($C$5:C15),"000"))
B16: =IF(C16="","DEP-"&TEXT(COUNTA($C$5:C16),"000"))
B17: =IF(C17="","DEP-"&TEXT(COUNTA($C$5:C17),"000"))
B18: =IF(C18="","DEP-"&TEXT(COUNTA($C$5:C18),"000"))
B19: =IF(C19="","DEP-"&TEXT(COUNTA($C$5:C19),"000"))
... B107: =IF(C107="","DEP-"&TEXT(COUNTA($C$5:C107),"000"))
B109: INDICATEURS (mis a jour automatiquement)
B110: Deploiements | D110: Succes | F110: Incidents totaux
B111: =COUNTIF(B5:B104,"<>") | D111: =COUNTIF(K5:K104,"Succes") | F111: =SUM(I5:I104)

Sheet 16-Calendrier Transform. Dig.
B2: CALENDRIER TRANSFORMATION DIGITALE RH
B3: TABLEAU DYNAMIQUE — Saisissez dans la prochaine ligne jaune. Les calculs se mettent a jour automatiquement.
B4: N° | C4: Initiative Digitale | D4: Axe Transformation | E4: Description | F4: Priorite | G4: Date Debut | H4: Date Fin | I4: Responsable | J4: Budget (FCFA) | K4: Avancement (%) | L4: Statut | M4: Observations
B5: CT-001 | C5: Digitalisation dossier employe | D5: GED & Numerisation | E5: Scanner et numeriser tous les dossiers papiers existants | F5: Haute | G5: 45689 | H5: 45900 | I5: Assistante RH | J5: 500000 | K5: 0.35 | L5: En cours | M5: 500 dossiers sur 1500 traites
B6: CT-002 | C6: Automatisation onboarding | D6: Automatisation | E6: Parcours d'integration 100% digital avec e-signature | F6: Haute | G6: 45717 | H6: 45838 | I6: DRH | J6: 300000 | K6: 0.15 | L6: En cours | M6: Cahier des charges valide
B7: CT-003 | C7: Tableau de bord RH temps reel | D7: Analytics & BI | E7: Dashboard KPI RH avec Power BI connecte au SIRH | F7: Moyenne | G7: 45748 | H7: 45930 | I7: Chef de service IT | J7: 800000 | K7: 0 | L7: Planifiee | M7: Recrutement consultant BI en cours
B8: =IF(C8="","CT-"&TEXT(COUNTA($C$5:C8),"000"))
B9: =IF(C9="","CT-"&TEXT(COUNTA($C$5:C9),"000"))
B10: =IF(C10="","CT-"&TEXT(COUNTA($C$5:C10),"000"))
B11: =IF(C11="","CT-"&TEXT(COUNTA($C$5:C11),"000"))
B12: =IF(C12="","CT-"&TEXT(COUNTA($C$5:C12),"000"))
B13: =IF(C13="","CT-"&TEXT(COUNTA($C$5:C13),"000"))
B14: =IF(C14="","CT-"&TEXT(COUNTA($C$5:C14),"000"))
B15: =IF(C15="","CT-"&TEXT(COUNTA($C$5:C15),"000"))
B16: =IF(C16="","CT-"&TEXT(COUNTA($C$5:C16),"000"))
B17: =IF(C17="","CT-"&TEXT(COUNTA($C$5:C17),"000"))
B18: =IF(C18="","CT-"&TEXT(COUNTA($C$5:C18),"000"))
B19: =IF(C19="","CT-"&TEXT(COUNTA($C$5:C19),"000"))
... B107: =IF(C107="","CT-"&TEXT(COUNTA($C$5:C107),"000"))
B109: INDICATEURS (mis a jour automatiquement)
B110: Initiatives digitales | D110: Budget total (FCFA) | F110: En cours
B111: =COUNTIF(B5:B104,"<>") | D111: =SUM(J5:J104) | F111: =COUNTIF(L5:L104,"En cours")

Sheet 17-Matrice Outils & Processus
B2: MATRICE OUTILS & PROCESSUS RH
B3: TABLEAU DYNAMIQUE — Saisissez dans la prochaine ligne jaune. Les calculs se mettent a jour automatiquement.
B4: N° | C4: Processus RH | D4: Outil Principal | E4: Type Outil | F4: Niveau Integration | G4: Niveau Automatisation | H4: Niveau Satisfaction | I4: Points Forts | J4: Axes Amelioration | K4: Priorite Amelioration | L4: Observations
B5: MOP-001 | C5: Recrutement | D5: Welcome to the Jungle | E5: Recrutement | F5: Eleve | G5: Automatise | H5: Satisfait | I5: CV screening IA, multi-diffusion | J5: Integration SIRH a renforcer | K5: Haute | L5: Project integration Q2 2025
B6: MOP-002 | C6: Paie | D6: Lucca Paie | E6: Paie | F6: Moyen | G6: Automatise | H6: Tres satisfait | I6: Calcul automatique, declarations CNPS | J6: Integration SIRH en cours | K6: Haute | L6: Go-live prevu avril 2025
B7: MOP-003 | C7: Gestion conges | D7: SIRH HotelPro | E7: SIRH | F7: Eleve | G7: Automatise | H7: Satisfait | I7: Workflow validation, solde auto | J7: App mobile encore instable | K7: Moyenne | L7: MAJ app prevue v2.4
B8: MOP-004 | C8: Formation | D8: Moodle interne | E8: Formation en ligne | F8: Faible | G8: Partiellement automatise | H8: Neutre | I8: Contenu riche, accessible | J8: UX obsolete, pas de tracking SIRH | K8: Moyenne | L8: Migration vers Lucca Learning etudiee
B9: =IF(C9="","MOP-"&TEXT(COUNTA($C$5:C9),"000"))
B10: =IF(C10="","MOP-"&TEXT(COUNTA($C$5:C10),"000"))
B11: =IF(C11="","MOP-"&TEXT(COUNTA($C$5:C11),"000"))
B12: =IF(C12="","MOP-"&TEXT(COUNTA($C$5:C12),"000"))
B13: =IF(C13="","MOP-"&TEXT(COUNTA($C$5:C13),"000"))
B14: =IF(C14="","MOP-"&TEXT(COUNTA($C$5:C14),"000"))
B15: =IF(C15="","MOP-"&TEXT(COUNTA($C$5:C15),"000"))
B16: =IF(C16="","MOP-"&TEXT(COUNTA($C$5:C16),"000"))
B17: =IF(C17="","MOP-"&TEXT(COUNTA($C$5:C17),"000"))
B18: =IF(C18="","MOP-"&TEXT(COUNTA($C$5:C18),"000"))
B19: =IF(C19="","MOP-"&TEXT(COUNTA($C$5:C19),"000"))
B20: =IF(C20="","MOP-"&TEXT(COUNTA($C$5:C20),"000"))
... B108: =IF(C108="","MOP-"&TEXT(COUNTA($C$5:C108),"000"))
B110: INDICATEURS (mis a jour automatiquement)
B111: Processus cartes | D111: Automatises | F111: Priorite haute
B112: =COUNTIF(B5:B104,"<>") | D112: =COUNTIF(G5:G104,"Automatise") | F112: =COUNTIF(K5:K104,"Haute")

Sheet 18-Suivi Compet. Digitales RH
B2: SUIVI COMPETENCES DIGITALES RH
B3: TABLEAU DYNAMIQUE — Saisissez dans la prochaine ligne jaune. Les calculs se mettent a jour automatiquement.
B4: N° | C4: Employe | D4: Poste | E4: Departement | F4: Niveau Digital Global | G4: SIRH | H4: Bureautique Avance | I4: Data & Analytics | J4: IA & Automatisation | K4: Cybersecurite | L4: Plan Formation
B5: CD-001 | C5: M. Nkoulou | D5: DRH | E5: Service Client | F5: Avance | G5: Expert | H5: Avance | I5: Intermediaire | J5: Avance | K5: Intermediaire | L5: Formation Data Analytics Q2
B6: CD-002 | C6: Mme. Ngassa | D6: Assistante RH | E6: Service Client | F6: Intermediaire | G6: Maitrise | H6: Avance | I6: Debutant | J6: Debutant | K6: Intermediaire | L6: E-learning Data & IA en cours
B7: CD-003 | C7: M. Tchinda | D7: Chef serv. IT | E7: Informatique | F7: Expert | G7: Expert | H7: Expert | I7: Expert | J7: Expert | K7: Expert | L7: Formation certification securite
B8: =IF(C8="","CD-"&TEXT(COUNTA($C$5:C8),"000"))
B9: =IF(C9="","CD-"&TEXT(COUNTA($C$5:C9),"000"))
B10: =IF(C10="","CD-"&TEXT(COUNTA($C$5:C10),"000"))
B11: =IF(C11="","CD-"&TEXT(COUNTA($C$5:C11),"000"))
B12: =IF(C12="","CD-"&TEXT(COUNTA($C$5:C12),"000"))
B13: =IF(C13="","CD-"&TEXT(COUNTA($C$5:C13),"000"))
B14: =IF(C14="","CD-"&TEXT(COUNTA($C$5:C14),"000"))
B15: =IF(C15="","CD-"&TEXT(COUNTA($C$5:C15),"000"))
B16: =IF(C16="","CD-"&TEXT(COUNTA($C$5:C16),"000"))
B17: =IF(C17="","CD-"&TEXT(COUNTA($C$5:C17),"000"))
B18: =IF(C18="","CD-"&TEXT(COUNTA($C$5:C18),"000"))
B19: =IF(C19="","CD-"&TEXT(COUNTA($C$5:C19),"000"))
... B107: =IF(C107="","CD-"&TEXT(COUNTA($C$5:C107),"000"))
B109: INDICATEURS (mis a jour automatiquement)
B110: Employes evalues | D110: Niveau expert (SIRH) | F110: Niveau avance (global)
B111: =COUNTIF(B5:B104,"<>") | D111: =COUNTIF(G5:G104,"Expert") | F111: =COUNTIF(F5:F104,"Avance")

Sheet 19-Analyse Maturite Digitale
B2: ANALYSE MATURITE DIGITALE RH
B3: TABLEAU DYNAMIQUE — Saisissez dans la prochaine ligne jaune. Les calculs se mettent a jour automatiquement.
B4: N° | C4: Dimension Maturite | D4: Niveau Actuel | E4: Score (1-5) | F4: Niveau Cible | G4: Score Cible (1-5) | H4: Ecart | I4: Actions Cle | J4: Priorite | K4: Echeance | L4: Observations
B5: MD-001 | C5: Infrastructure digitale | D5: Defini | E5: 3 | F5: Gere | G5: 4 | I5: Cloud SIRH, VPN securise | J5: Haute | K5: T3 2025 | L5: Migration cloud en cours
B6: MD-002 | C6: Automatisation processus | D6: Reproductible | E6: 2 | F6: Gere | G6: 4 | I6: Automatiser conges, onboarding, notes frais | J6: Haute | K6: T4 2025 | L6: 3 processus cibles identifies
B7: MD-003 | C7: Data & Analytics RH | D7: Initial | E7: 1 | F7: Defini | G7: 3 | I7: Deployer BI, former equipe data | J7: Haute | K7: T2 2026 | L7: Recrutement consultant BI
B8: MD-004 | C8: IA & Innovation | D8: Initial | E8: 1 | F8: Reproductible | G8: 2 | I8: Chatbot, CV screening, prediction turnover | J8: Moyenne | K8: T1 2026 | L8: POC chatbot en cours
B9: MD-005 | C9: Securite & Conformite | D9: Defini | E9: 3 | F9: Gere | G9: 4 | I9: RGPD, chiffrement, audit continu | J9: Haute | K9: T3 2025 | L9: Audit externe Q1 conforme
B10: =IF(C10="","MD-"&TEXT(COUNTA($C$5:C10),"000")) | H10: =IF(OR(E10="",G10=""),"",G10-E10)
B11: =IF(C11="","MD-"&TEXT(COUNTA($C$5:C11),"000")) | H11: =IF(OR(E11="",G11=""),"",G11-E11)
B12: =IF(C12="","MD-"&TEXT(COUNTA($C$5:C12),"000")) | H12: =IF(OR(E12="",G12=""),"",G12-E12)
B13: =IF(C13="","MD-"&TEXT(COUNTA($C$5:C13),"000")) | H13: =IF(OR(E13="",G13=""),"",G13-E13)
B14: =IF(C14="","MD-"&TEXT(COUNTA($C$5:C14),"000")) | H14: =IF(OR(E14="",G14=""),"",G14-E14)
B15: =IF(C15="","MD-"&TEXT(COUNTA($C$5:C15),"000")) | H15: =IF(OR(E15="",G15=""),"",G15-E15)
B16: =IF(C16="","MD-"&TEXT(COUNTA($C$5:C16),"000")) | H16: =IF(OR(E16="",G16=""),"",G16-E16)
B17: =IF(C17="","MD-"&TEXT(COUNTA($C$5:C17),"000")) | H17: =IF(OR(E17="",G17=""),"",G17-E17)
B18: =IF(C18="","MD-"&TEXT(COUNTA($C$5:C18),"000")) | H18: =IF(OR(E18="",G18=""),"",G18-E18)
B19: =IF(C19="","MD-"&TEXT(COUNTA($C$5:C19),"000")) | H19: =IF(OR(E19="",G19=""),"",G19-E19)
B20: =IF(C20="","MD-"&TEXT(COUNTA($C$5:C20),"000")) | H20: =IF(OR(E20="",G20=""),"",G20-E20)
B21: =IF(C21="","MD-"&TEXT(COUNTA($C$5:C21),"000")) | H21: =IF(OR(E21="",G21=""),"",G21-E21)
... B109: =IF(C109="","MD-"&TEXT(COUNTA($C$5:C109),"000")) | H109: =IF(OR(E109="",G109=""),"",G109-E109)
B111: INDICATEURS (mis a jour automatiquement)
B112: Dimensions analysees | D112: Score moyen actuel | F112: Score moyen cible
B113: =COUNTIF(B5:B104,"<>") | D113: =IFERROR(AVERAGE(E5:E104),0) | F113: =IFERROR(AVERAGE(G5:G104),0)
