Workbook

Sheet F01 - _Données Collabor.
A2: DONNÉES COLLABORATEURS — Base de référence engagement
A3: TABLEAU DYNAMIQUE — Saisissez dans la zone prévue ci-dessous
A5: Matricule | B5: Nom | C5: Prénom | D5: Département | E5: Poste | F5: Score Engagement (%) | G5: Note Engagement (/5) | H5: Catégorie Engagement | I5: Genre
A6: COL-001 | B6: Koné | C6: Aminata | D6: Cuisine & Restauration | E6: Chef Pâtissier | F6: 78 | G6: 4.2 | H6: Très engagé | I6: F
A7: COL-002 | B7: Traoré | C7: Ibrahim | D7: Informatique | E7: DSI | F7: 85 | G7: 4.5 | H7: Très engagé | I7: M
A8: COL-003 | B8: Diallo | C8: Fatou | D8: Marketing & Communication | E8: Resp. Marketing | F8: 72 | G8: 3.8 | H8: Engagé | I8: F
A9: COL-004 | B9: Ouattara | C9: Moussa | D9: Finance & Comptabilité | E9: Comptable Senior | F9: 68 | G9: 3.5 | H9: Engagé | I9: M
A10: COL-005 | B10: Bamba | C10: Mariam | D10: Réception & Front Office | E10: Chef Réception | F10: 90 | G10: 4.8 | H10: Ambassadeur | I10: F
A11: COL-006 | B11: Coulibaly | C11: Adama | D11: Entretien & Maintenance | E11: Chef Entretien | F11: 55 | G11: 2.8 | H11: À surveiller | I11: M
A12: COL-007 | B12: Konan | C12: Yao | D12: Ressources Humaines | E12: DRH | F12: 82 | G12: 4 | H12: Très engagé | I12: M
A13: COL-008 | B13: Sangaré | C13: Awa | D13: Commercial | E13: Resp. Commercial | F13: 75 | G13: 3.9 | H13: Engagé | I13: F
A14: COL-009 | B14: Djibril | C14: Oumar | D14: Sécurité | E14: Chef Sécurité | F14: 60 | G14: 3 | H14: Neutre | I14: M
A15: COL-010 | B15: Yao | C15: Akissi | D15: Hébergement | E15: Gouvernante | F15: 88 | G15: 4.6 | H15: Très engagé | I15: F
A16: COL-011 | B16: N'Guessan | C16: Koffi | D16: Cuisine & Restauration | E16: Chef Cuisinier | F16: 80 | G16: 4.1 | H16: Très engagé | I16: M
A17: COL-012 | B17: Koffi | C17: Marie | D17: Service Client | E17: Resp. Service Client | F17: 70 | G17: 3.6 | H17: Engagé | I17: F
... A20: COL-015 | B20: N'Dri | C20: Fatou | D20: Animation & Loisirs | E20: Animatrice | F20: 76 | G20: 3.9 | H20: Engagé | I20: F

Sheet F02 - _Lists
A2: LISTES DE RÉFÉRENCE — Valeurs pour listes déroulantes
A3: TABLEAU DYNAMIQUE — Saisissez dans la zone prévue ci-dessous
A5: departements | B5: postes | C5: canaux | D5: types_evenement | E5: statuts_evenement | F5: statuts_action | G5: frequences | H5: priorites | I5: cibles | J5: types_enquete | K5: niveaux_satisfaction | L5: categories_suggestion | M5: statuts_suggestion | N5: niveaux_alerte | O5: types_alerte | P5: mois | Q5: trimestres | R5: tendances | S5: modes_paiement | T5: validations | U5: conformites | V5: engagement_niveaux | W5: periodicites_newsletter | X5: statuts_newsletter | Y5: types_poste_cvs
A6: Direction Générale | B6: DG | C6: Intranet | D6: Team building | E6: Planifié | F6: En attente | G6: Hebdomadaire | H6: Haute | I6: Tous | J6: Engagement global | K6: Très insatisfait | L6: Conditions de travail | M6: En attente | N6: Faible | O6: Rumeur | P6: Janvier 2025 | Q6: T1 2025 | R6: Hausse | S6: Virement | T6: Validé | U6: Conforme | V6: Ambassadeur | W6: Hebdomadaire | X6: Brouillon | Y6: Titulaire
A7: Ressources Humaines | B7: DRH | C7: Email interne | D7: Célébration | E7: En cours | F7: En cours | G7: Mensuelle | H7: Moyenne | I7: Cadres | J7: Climat social | K7: Insatisfait | L7: Rémunération | M7: Étudiée | N7: Moyen | O7: Mécontentement | P7: Février 2025 | Q7: T2 2025 | R7: Baisse | S7: Chèque | T7: En attente | U7: Partiellement conforme | V7: Très engagé | W7: Bimensuelle | X7: En revue | Y7: Suppléant
A8: Finance & Comptabilité | B8: DAF | C8: Affichage | D8: Formation informelle | E8: Terminé | F8: Terminé | G8: Trimestrielle | H8: Basse | I8: Non-cadres | J8: Satisfaction poste | K8: Neutre | L8: Formation | M8: Acceptée | N8: Élevé | O8: Conflit latent | P8: Mars 2025 | Q8: T3 2025 | R8: Stable | S8: Espèces | T8: Rejeté | U8: Non conforme | V8: Engagé | W8: Mensuelle | X8: Validé | Y8: Invité permanent
A9: Marketing & Communication | B9: DSI | C9: Réunion d'équipe | D9: Sport interne | E9: Annulé | F9: Reporté | G9: Semestrielle | I9: Département | J9: Qualité de vie travail | K9: Satisfait | L9: Communication | M9: Rejetée | N9: Critique | O9: Risque départ | P9: Avril 2025 | Q9: T4 2025 | T9: Non applicable | U9: En attente | V9: Neutre | W9: Trimestrielle | X9: Diffusé
A10: Informatique | B10: Resp. Marketing | C10: Newsletter | D10: Repas partagé | E10: Reporté | F10: Annulé | G10: Annuelle | I10: Nouveaux arrivants | J10: Communication interne | K10: Très satisfait | L10: Environnement | M10: Mise en oeuvre | O10: Tension interne | P10: Mai 2025 | V10: À surveiller | X10: Archivé
A11: Commercial | B11: Resp. Commercial | C11: Tablette digitale | D11: Atelier créatif | J11: Management | L11: Équipements | O11: Risque psychosocial | P11: Juin 2025 | V11: Désengagé
A12: Logistique & Approvisionnement | B12: Chef Logistique | C12: Application mobile | D12: Journée portes ouvertes | J12: Rémunération | L12: Horaires | P12: Juillet 2025
A13: Réception & Front Office | B13: Chef Réception | C13: Panneau d'affichage | D13: Soirée thématique | J13: Formation | L13: Relations collègues | P13: Août 2025
A14: Cuisine & Restauration | B14: Chef Cuisinier | C14: Réunion générale | L14: Management | P14: Septembre 2025
A15: Hébergement | B15: Chef Pâtissier | C15: Whatsapp groupe | L15: Sécurité | P15: Octobre 2025
A16: Entretien & Maintenance | B16: Comptable Senior | L16: Autre | P16: Novembre 2025
A17: Sécurité | B17: Chef Entretien | P17: Décembre 2025
A18: Service Client | B18: Chef Sécurité
A19: Animation & Loisirs | B19: Gouvernante
A20: Spa & Bien-être | B20: Resp. Service Client
B21: Animatrice
B22: Resp. Spa
B23: Agent Réception
B24: Agent Service Client
B25: Technicien

Sheet F03 - 1-Tableau de Bord
A2: DOMAINE 29 — COMMUNICATION INTERNE ET ENGAGEMENT COLLABORATEURS
A3: Tableau de Bord Synthétique — Engagement, communication et satisfaction
A5: INDICATEURS CLÉS
A6: Score Engagement Moyen | C6: Nb Suggestions Reçues | E6: Taux Participation Enquêtes | G6: Événements Réalisés (Année) | I6: Budget Communication Consommé | K6: Nb Newsletters Diffusées
A7: 75.6% | C7: 42 | E7: 87% | G7: 18 | I7: 62% | K7: 11
A9: ENGAGEMENT PAR DÉPARTEMENT | I9: CANAUX LES PLUS UTILISÉS
A10: Département | B10: Effectif | C10: Score Moyen | D10: Catégorie Majoritaire | E10: Nb Suggestions | I10: Canal | J10: Nb Publications | K10: Portée | L10: Interaction
A11: Cuisine & Restauration | B11: 2 | C11: 79 | D11: Très engagé | E11: 8 | I11: Intranet | J11: 45 | K11: 100% | L11: 62%
A12: Informatique | B12: 1 | C12: 85 | D12: Très engagé | E12: 6 | I12: Email interne | J12: 120 | K12: 100% | L12: 38%
A13: Marketing & Communication | B13: 1 | C13: 72 | D13: Engagé | E13: 5 | I13: Affichage | J13: 30 | K13: 85% | L13: N/A
A14: Finance & Comptabilité | B14: 1 | C14: 68 | D14: Engagé | E14: 3 | I14: Newsletter | J14: 11 | K14: 92% | L14: 55%
A15: Réception & Front Office | B15: 1 | C15: 90 | D15: Ambassadeur | E15: 7 | I15: Réunion d'équipe | J15: 48 | K15: Par département | L15: 78%
A16: Hébergement | B16: 1 | C16: 88 | D16: Très engagé | E16: 4 | I16: Tablette digitale | J16: 24 | K16: 65% | L16: 45%
A17: Entretien & Maintenance | B17: 1 | C17: 55 | D17: À surveiller | E17: 2
A18: Ressources Humaines | B18: 1 | C18: 82 | D18: Très engagé | E18: 3
A19: Commercial | B19: 1 | C19: 75 | D19: Engagé | E19: 2
A20: ACTIONS PLANIFIÉES
A21: Action | B21: Responsable | C21: Échéance | D21: Priorité | E21: Statut
A22: Lancer enquête engagement Q2 | B22: DRH | C22: 45748 | D22: Haute | E22: En cours
A23: Organiser team building annuel | B23: DRH / DG | C23: 45823 | D23: Haute | E23: Planifié
A24: Refonte intranet collaborateurs | B24: DSI / DRH | C24: 45808 | D24: Moyenne | E24: En cours
A25: Programme reconnaissance mensuel | B25: DRH | C25: 45717 | D25: Haute | E25: En cours

Sheet F04 - 2-Enquêtes Engagement
A2: 2-ENQUÊTES D'ENGAGEMENT
A3: TABLEAU DYNAMIQUE — Saisissez dans la zone prévue ci-dessous
A5: Code Enquête | B5: Type Enquête | C5: Période | D5: Date Lancement | E5: Date Clôture | F5: Nb Invités | G5: Nb Réponses | H5: Taux Participation (%) | I5: Score Moyen (/5) | J5: Statut | K5: Observations
A6: ENG-2025-T1 | B6: Engagement global | C6: T1 2025 | D6: 45672 | E6: 45687 | F6: 65 | G6: 57 | H6: =IF(OR(F6="",G6=""),"",IFERROR(G6/F6*100,0)) | I6: 4.1 | J6: Terminé | K6: Très bonne participation
A7: SAT-2025-T1 | B7: Satisfaction poste | C7: T1 2025 | D7: 45689 | E7: 45703 | F7: 65 | G7: 52 | H7: =IF(OR(F7="",G7=""),"",IFERROR(G7/F7*100,0)) | I7: 3.8 | J7: Terminé | K7: Baisse dans entretien
A8: COM-2025-T1 | B8: Communication interne | C8: T1 2025 | D8: 45717 | E8: 45730 | F8: 65 | G8: 48 | H8: =IF(OR(F8="",G8=""),"",IFERROR(G8/F8*100,0)) | I8: 3.5 | J8: Terminé | K8: Points d'amélioration identifiés
A9: ENG-2025-T2 | B9: Engagement global | C9: T2 2025 | D9: 45762 | E9: 45777 | F9: 68 | H9: =IF(OR(F9="",G9=""),"",IFERROR(G9/F9*100,0)) | J9: Planifié
A10: CLIM-2025-T2 | B10: Climat social | C10: T2 2025 | D10: 45778 | E10: 45792 | F10: 68 | H10: =IF(OR(F10="",G10=""),"",IFERROR(G10/F10*100,0)) | J10: Planifié
H11: =IF(OR(F11="",G11=""),"",IFERROR(G11/F11*100,0))
H12: =IF(OR(F12="",G12=""),"",IFERROR(G12/F12*100,0))
H13: =IF(OR(F13="",G13=""),"",IFERROR(G13/F13*100,0))
H14: =IF(OR(F14="",G14=""),"",IFERROR(G14/F14*100,0))
H15: =IF(OR(F15="",G15=""),"",IFERROR(G15/F15*100,0))
H16: =IF(OR(F16="",G16=""),"",IFERROR(G16/F16*100,0))
H17: =IF(OR(F17="",G17=""),"",IFERROR(G17/F17*100,0))
H18: =IF(OR(F18="",G18=""),"",IFERROR(G18/F18*100,0))
H19: =IF(OR(F19="",G19=""),"",IFERROR(G19/F19*100,0))
H20: =IF(OR(F20="",G20=""),"",IFERROR(G20/F20*100,0))
H21: =IF(OR(F21="",G21=""),"",IFERROR(G21/F21*100,0))
H22: =IF(OR(F22="",G22=""),"",IFERROR(G22/F22*100,0))
... H115: =IF(OR(F115="",G115=""),"",IFERROR(G115/F115*100,0))

Sheet F05 - 3-Plan Communication
A2: 3-PLAN DE COMMUNICATION INTERNE
A3: TABLEAU DYNAMIQUE — Saisissez dans la zone prévue ci-dessous
A5: Code Action | B5: Objectif Communication | C5: Cible | D5: Canal | E5: Fréquence | F5: Responsable | G5: Date Début | H5: Date Fin | I5: Budget (FCFA) | J5: Statut | K5: Indicateur Succès | L5: Résultat | M5: Observations
A6: =IF(B6="","",IF(COUNTA($A$6:A6)=0,"COM-ACT-"&TEXT(COUNTA($B$6:B6),"000"),"COM-ACT-"&TEXT(ROW()-5,"000"))) | B6: Informer sur la stratégie 2025 | C6: Tous | D6: Réunion générale | E6: Trimestrielle | F6: DG / DRH | G6: 45672 | H6: 46022 | I6: 50000 | J6: En cours | K6: Taux présence ≥ 80% | L6: 85%
A7: =IF(B7="","",IF(COUNTA($A$6:A7)=0,"COM-ACT-"&TEXT(COUNTA($B$6:B7),"000"),"COM-ACT-"&TEXT(ROW()-5,"000"))) | B7: Partager les résultats financiers | C7: Cadres | D7: Email interne | E7: Trimestrielle | F7: DAF | G7: 45689 | H7: 46022 | I7: 0 | J7: En cours | K7: Ouverture email ≥ 70% | L7: 72%
A8: =IF(B8="","",IF(COUNTA($A$6:A8)=0,"COM-ACT-"&TEXT(COUNTA($B$6:B8),"000"),"COM-ACT-"&TEXT(ROW()-5,"000"))) | B8: Animer la vie sociale | C8: Tous | D8: Affichage + Intranet | E8: Mensuelle | F8: DRH | G8: 45658 | H8: 46022 | I8: 200000 | J8: En cours | K8: 1 événement/mois | L8: En cours
A9: =IF(B9="","",IF(COUNTA($A$6:A9)=0,"COM-ACT-"&TEXT(COUNTA($B$6:B9),"000"),"COM-ACT-"&TEXT(ROW()-5,"000"))) | B9: Diffuser newsletter interne | C9: Tous | D9: Email + Intranet | E9: Mensuelle | F9: Resp. Marketing | G9: 45667 | H9: 46022 | I9: 120000 | J9: En cours | K9: Taux lecture ≥ 55% | L9: 58%
A10: =IF(B10="","",IF(COUNTA($A$6:A10)=0,"COM-ACT-"&TEXT(COUNTA($B$6:B10),"000"),"COM-ACT-"&TEXT(ROW()-5,"000"))) | B10: Sensibiliser QVT | C10: Tous | D10: Tablette digitale | E10: Mensuelle | F10: DRH / CSSCT | G10: 45717 | H10: 45930 | I10: 80000 | J10: Planifié | K10: Score QVT hausse 5%
A11: =IF(B11="","",IF(COUNTA($A$6:A11)=0,"COM-ACT-"&TEXT(COUNTA($B$6:B11),"000"),"COM-ACT-"&TEXT(ROW()-5,"000")))
A12: =IF(B12="","",IF(COUNTA($A$6:A12)=0,"COM-ACT-"&TEXT(COUNTA($B$6:B12),"000"),"COM-ACT-"&TEXT(ROW()-5,"000")))
A13: =IF(B13="","",IF(COUNTA($A$6:A13)=0,"COM-ACT-"&TEXT(COUNTA($B$6:B13),"000"),"COM-ACT-"&TEXT(ROW()-5,"000")))
A14: =IF(B14="","",IF(COUNTA($A$6:A14)=0,"COM-ACT-"&TEXT(COUNTA($B$6:B14),"000"),"COM-ACT-"&TEXT(ROW()-5,"000")))
A15: =IF(B15="","",IF(COUNTA($A$6:A15)=0,"COM-ACT-"&TEXT(COUNTA($B$6:B15),"000"),"COM-ACT-"&TEXT(ROW()-5,"000")))
A16: =IF(B16="","",IF(COUNTA($A$6:A16)=0,"COM-ACT-"&TEXT(COUNTA($B$6:B16),"000"),"COM-ACT-"&TEXT(ROW()-5,"000")))
A17: =IF(B17="","",IF(COUNTA($A$6:A17)=0,"COM-ACT-"&TEXT(COUNTA($B$6:B17),"000"),"COM-ACT-"&TEXT(ROW()-5,"000")))
A18: =IF(B18="","",IF(COUNTA($A$6:A18)=0,"COM-ACT-"&TEXT(COUNTA($B$6:B18),"000"),"COM-ACT-"&TEXT(ROW()-5,"000")))
A19: =IF(B19="","",IF(COUNTA($A$6:A19)=0,"COM-ACT-"&TEXT(COUNTA($B$6:B19),"000"),"COM-ACT-"&TEXT(ROW()-5,"000")))
A20: =IF(B20="","",IF(COUNTA($A$6:A20)=0,"COM-ACT-"&TEXT(COUNTA($B$6:B20),"000"),"COM-ACT-"&TEXT(ROW()-5,"000")))
A21: =IF(B21="","",IF(COUNTA($A$6:A21)=0,"COM-ACT-"&TEXT(COUNTA($B$6:B21),"000"),"COM-ACT-"&TEXT(ROW()-5,"000")))
A22: =IF(B22="","",IF(COUNTA($A$6:A22)=0,"COM-ACT-"&TEXT(COUNTA($B$6:B22),"000"),"COM-ACT-"&TEXT(ROW()-5,"000")))
... A115: =IF(B115="","",IF(COUNTA($A$6:A115)=0,"COM-ACT-"&TEXT(COUNTA($B$6:B115),"000"),"COM-ACT-"&TEXT(ROW()-5,"000")))

Sheet F06 - 4-Événements Internes
A2: 4-ÉVÉNEMENTS ET ANIMATIONS INTERNES
A3: TABLEAU DYNAMIQUE — Saisissez dans la zone prévue ci-dessous
A5: Code Événement | B5: Nom Événement | C5: Type | D5: Date | E5: Lieu | F5: Nb Participants | G5: Budget (FCFA) | H5: Coût Réel (FCFA) | I5: Satisfaction Moy. | J5: Statut | K5: Commentaire | L5: Observations
A6: =IF(B6="","",IF(COUNTA($A$6:A6)=0,"EVT-"&TEXT(COUNTA($B$6:B6),"000"),"EVT-"&TEXT(ROW()-5,"000"))) | B6: Kick-off Année 2025 | C6: Célébration | D6: 45667 | E6: Restaurant principal | F6: 62 | G6: 500000 | H6: =IF(G6="","",IFERROR(G6-F6,0)) | I6: 4.3 | J6: Terminé | K6: Excellente ambiance, DG très impliqué
A7: =IF(B7="","",IF(COUNTA($A$6:A7)=0,"EVT-"&TEXT(COUNTA($B$6:B7),"000"),"EVT-"&TEXT(ROW()-5,"000"))) | B7: Tournoi inter-départements | C7: Sport interne | D7: 45710 | E7: Terrain sport | F7: 45 | G7: 150000 | H7: =IF(G7="","",IFERROR(G7-F7,0)) | I7: 4.7 | J7: Terminé | K7: Participation record, ambiance conviviale
A8: =IF(B8="","",IF(COUNTA($A$6:A8)=0,"EVT-"&TEXT(COUNTA($B$6:B8),"000"),"EVT-"&TEXT(ROW()-5,"000"))) | B8: Atelier cuisine partagée | C8: Atelier créatif | D8: 45731 | E8: Cuisine principale | F8: 20 | G8: 80000 | H8: =IF(G8="","",IFERROR(G8-F8,0)) | I8: 4.5 | J8: Terminé | K8: Moment d'échange entre départements
A9: =IF(B9="","",IF(COUNTA($A$6:A9)=0,"EVT-"&TEXT(COUNTA($B$6:B9),"000"),"EVT-"&TEXT(ROW()-5,"000"))) | B9: Journée bien-être | C9: Team building | D9: 45767 | E9: Spa + Jardin | F9: 50 | G9: 300000 | H9: =IF(G9="","",IFERROR(G9-F9,0)) | J9: Planifié | K9: Activités spa, yoga et relaxation prévues
A10: =IF(B10="","",IF(COUNTA($A$6:A10)=0,"EVT-"&TEXT(COUNTA($B$6:B10),"000"),"EVT-"&TEXT(ROW()-5,"000"))) | B10: Soirée iftar | C10: Repas partagé | D10: 45736 | E10: Salle événementielle | F10: 58 | G10: 200000 | H10: =IF(G10="","",IFERROR(G10-F10,0)) | I10: 4.6 | J10: Terminé | K10: Moment fort de cohésion pendant ramadan
A11: =IF(B11="","",IF(COUNTA($A$6:A11)=0,"EVT-"&TEXT(COUNTA($B$6:B11),"000"),"EVT-"&TEXT(ROW()-5,"000"))) | H11: =IF(G11="","",IFERROR(G11-F11,0))
A12: =IF(B12="","",IF(COUNTA($A$6:A12)=0,"EVT-"&TEXT(COUNTA($B$6:B12),"000"),"EVT-"&TEXT(ROW()-5,"000"))) | H12: =IF(G12="","",IFERROR(G12-F12,0))
A13: =IF(B13="","",IF(COUNTA($A$6:A13)=0,"EVT-"&TEXT(COUNTA($B$6:B13),"000"),"EVT-"&TEXT(ROW()-5,"000"))) | H13: =IF(G13="","",IFERROR(G13-F13,0))
A14: =IF(B14="","",IF(COUNTA($A$6:A14)=0,"EVT-"&TEXT(COUNTA($B$6:B14),"000"),"EVT-"&TEXT(ROW()-5,"000"))) | H14: =IF(G14="","",IFERROR(G14-F14,0))
A15: =IF(B15="","",IF(COUNTA($A$6:A15)=0,"EVT-"&TEXT(COUNTA($B$6:B15),"000"),"EVT-"&TEXT(ROW()-5,"000"))) | H15: =IF(G15="","",IFERROR(G15-F15,0))
A16: =IF(B16="","",IF(COUNTA($A$6:A16)=0,"EVT-"&TEXT(COUNTA($B$6:B16),"000"),"EVT-"&TEXT(ROW()-5,"000"))) | H16: =IF(G16="","",IFERROR(G16-F16,0))
A17: =IF(B17="","",IF(COUNTA($A$6:A17)=0,"EVT-"&TEXT(COUNTA($B$6:B17),"000"),"EVT-"&TEXT(ROW()-5,"000"))) | H17: =IF(G17="","",IFERROR(G17-F17,0))
A18: =IF(B18="","",IF(COUNTA($A$6:A18)=0,"EVT-"&TEXT(COUNTA($B$6:B18),"000"),"EVT-"&TEXT(ROW()-5,"000"))) | H18: =IF(G18="","",IFERROR(G18-F18,0))
A19: =IF(B19="","",IF(COUNTA($A$6:A19)=0,"EVT-"&TEXT(COUNTA($B$6:B19),"000"),"EVT-"&TEXT(ROW()-5,"000"))) | H19: =IF(G19="","",IFERROR(G19-F19,0))
A20: =IF(B20="","",IF(COUNTA($A$6:A20)=0,"EVT-"&TEXT(COUNTA($B$6:B20),"000"),"EVT-"&TEXT(ROW()-5,"000"))) | H20: =IF(G20="","",IFERROR(G20-F20,0))
A21: =IF(B21="","",IF(COUNTA($A$6:A21)=0,"EVT-"&TEXT(COUNTA($B$6:B21),"000"),"EVT-"&TEXT(ROW()-5,"000"))) | H21: =IF(G21="","",IFERROR(G21-F21,0))
A22: =IF(B22="","",IF(COUNTA($A$6:A22)=0,"EVT-"&TEXT(COUNTA($B$6:B22),"000"),"EVT-"&TEXT(ROW()-5,"000"))) | H22: =IF(G22="","",IFERROR(G22-F22,0))
... A115: =IF(B115="","",IF(COUNTA($A$6:A115)=0,"EVT-"&TEXT(COUNTA($B$6:B115),"000"),"EVT-"&TEXT(ROW()-5,"000"))) | H115: =IF(G115="","",IFERROR(G115-F115,0))

Sheet F07 - 5-Canaux Communication
A2: 5-CANAUX DE COMMUNICATION
A3: TABLEAU DYNAMIQUE — Saisissez dans la zone prévue ci-dessous
A5: Canal | B5: Type Contenu | C5: Fréquence Diffusion | D5: Responsable | E5: Portée (nb personnes) | F5: Taux Interaction (%) | G5: Coût Mensuel (FCFA) | H5: Efficacité | I5: Dernière Mise à Jour | J5: Observations
A6: Intranet | B6: Informations générales | C6: Mensuelle | D6: DSI / DRH | E6: 65 | F6: 62 | G6: 50000 | H6: =IF(F6="","",IF(F6>=60,"Très efficace",IF(F6>=40,"Efficace",IF(F6>=20,"Modéré","Faible")))) | I6: 45716 | J6: =IF(G6="","",G6*12)
A7: Email interne | B7: Annonces officielles | C7: Hebdomadaire | D7: DRH | E7: 65 | F7: 38 | G7: 15000 | H7: =IF(F7="","",IF(F7>=60,"Très efficace",IF(F7>=40,"Efficace",IF(F7>=20,"Modéré","Faible")))) | I7: 45717 | J7: =IF(G7="","",G7*12)
A8: Affichage | B8: Informations légales, événements | C8: Mensuelle | D8: DRH | E8: 55 | G8: 10000 | H8: =IF(F8="","",IF(F8>=60,"Très efficace",IF(F8>=40,"Efficace",IF(F8>=20,"Modéré","Faible")))) | I8: 45703 | J8: =IF(G8="","",G8*12)
A9: Newsletter | B9: Actualités, succès, vie sociale | C9: Mensuelle | D9: Resp. Marketing | E9: 60 | F9: 55 | G9: 10000 | H9: =IF(F9="","",IF(F9>=60,"Très efficace",IF(F9>=40,"Efficace",IF(F9>=20,"Modéré","Faible")))) | I9: 45717 | J9: =IF(G9="","",G9*12)
A10: Tablette digitale | B10: Infographies, quiz, sondages | C10: Hebdomadaire | D10: DRH / DSI | E10: 42 | F10: 45 | G10: 25000 | H10: =IF(F10="","",IF(F10>=60,"Très efficace",IF(F10>=40,"Efficace",IF(F10>=20,"Modéré","Faible")))) | I10: 45721 | J10: =IF(G10="","",G10*12)
H11: =IF(F11="","",IF(F11>=60,"Très efficace",IF(F11>=40,"Efficace",IF(F11>=20,"Modéré","Faible")))) | J11: =IF(G11="","",G11*12)
H12: =IF(F12="","",IF(F12>=60,"Très efficace",IF(F12>=40,"Efficace",IF(F12>=20,"Modéré","Faible")))) | J12: =IF(G12="","",G12*12)
H13: =IF(F13="","",IF(F13>=60,"Très efficace",IF(F13>=40,"Efficace",IF(F13>=20,"Modéré","Faible")))) | J13: =IF(G13="","",G13*12)
H14: =IF(F14="","",IF(F14>=60,"Très efficace",IF(F14>=40,"Efficace",IF(F14>=20,"Modéré","Faible")))) | J14: =IF(G14="","",G14*12)
H15: =IF(F15="","",IF(F15>=60,"Très efficace",IF(F15>=40,"Efficace",IF(F15>=20,"Modéré","Faible")))) | J15: =IF(G15="","",G15*12)
H16: =IF(F16="","",IF(F16>=60,"Très efficace",IF(F16>=40,"Efficace",IF(F16>=20,"Modéré","Faible")))) | J16: =IF(G16="","",G16*12)
H17: =IF(F17="","",IF(F17>=60,"Très efficace",IF(F17>=40,"Efficace",IF(F17>=20,"Modéré","Faible")))) | J17: =IF(G17="","",G17*12)
H18: =IF(F18="","",IF(F18>=60,"Très efficace",IF(F18>=40,"Efficace",IF(F18>=20,"Modéré","Faible")))) | J18: =IF(G18="","",G18*12)
H19: =IF(F19="","",IF(F19>=60,"Très efficace",IF(F19>=40,"Efficace",IF(F19>=20,"Modéré","Faible")))) | J19: =IF(G19="","",G19*12)
H20: =IF(F20="","",IF(F20>=60,"Très efficace",IF(F20>=40,"Efficace",IF(F20>=20,"Modéré","Faible")))) | J20: =IF(G20="","",G20*12)
H21: =IF(F21="","",IF(F21>=60,"Très efficace",IF(F21>=40,"Efficace",IF(F21>=20,"Modéré","Faible")))) | J21: =IF(G21="","",G21*12)
H22: =IF(F22="","",IF(F22>=60,"Très efficace",IF(F22>=40,"Efficace",IF(F22>=20,"Modéré","Faible")))) | J22: =IF(G22="","",G22*12)
... H115: =IF(F115="","",IF(F115>=60,"Très efficace",IF(F115>=40,"Efficace",IF(F115>=20,"Modéré","Faible")))) | J115: =IF(G115="","",G115*12)

Sheet F08 - 6-Boîte à Idées
A2: 6-BOÎTE À IDÉES ET SUGGESTIONS
A3: TABLEAU DYNAMIQUE — Saisissez dans la zone prévue ci-dessous
A5: Code Suggestion | B5: Auteur | C5: Département | D5: Date Soumission | E5: Catégorie | F5: Description | G5: Statut | H5: Nb Soutiens | I5: Date Traitement | J5: Réponse RH | K5: Observations
A6: =IF(B6="","",IF(COUNTA($A$6:A6)=0,"SUG-"&TEXT(COUNTA($B$6:B6),"000"),"SUG-"&TEXT(ROW()-5,"000"))) | B6: Koné Aminata | C6: =IF(B6="","",VLOOKUP(B6,'F01 - _Données Collaborateurs'!$B$6:$F$20,5,FALSE)) | D6: 45677 | E6: Équipements | F6: Installer un four ventilé supplémentaire pour la pâtisserie | G6: Acceptée | H6: 8 | I6: 45703 | J6: Budget validé pour T2 2025 | K6: =IF(B6="","",IFERROR(VLOOKUP(B6,'F01 - _Données Collaborateurs'!$B$6:$H$20,6,FALSE),"")) | L6: =IF(I6="","",IF(I6-D6>15,"Traitement lent","Délai OK"))
A7: =IF(B7="","",IF(COUNTA($A$6:A7)=0,"SUG-"&TEXT(COUNTA($B$6:B7),"000"),"SUG-"&TEXT(ROW()-5,"000"))) | B7: Traoré Ibrahim | C7: =IF(B7="","",VLOOKUP(B7,'F01 - _Données Collaborateurs'!$B$6:$F$20,5,FALSE)) | D7: 45682 | E7: Communication | F7: Créer une application mobile pour les collaborateurs | G7: Étudiée | H7: 12 | J7: Étude de faisabilité en cours | K7: =IF(B7="","",IFERROR(VLOOKUP(B7,'F01 - _Données Collaborateurs'!$B$6:$H$20,6,FALSE),"")) | L7: =IF(I7="","",IF(I7-D7>15,"Traitement lent","Délai OK"))
A8: =IF(B8="","",IF(COUNTA($A$6:A8)=0,"SUG-"&TEXT(COUNTA($B$6:B8),"000"),"SUG-"&TEXT(ROW()-5,"000"))) | B8: Bamba Mariam | C8: =IF(B8="","",VLOOKUP(B8,'F01 - _Données Collaborateurs'!$B$6:$F$20,5,FALSE)) | D8: 45689 | E8: Conditions de travail | F8: Améliorer l'éclairage du comptoir réception nuit | G8: Mise en oeuvre | H8: 6 | I8: 45717 | J8: Intervention électricien programmée | K8: =IF(B8="","",IFERROR(VLOOKUP(B8,'F01 - _Données Collaborateurs'!$B$6:$H$20,6,FALSE),"")) | L8: =IF(I8="","",IF(I8-D8>15,"Traitement lent","Délai OK"))
A9: =IF(B9="","",IF(COUNTA($A$6:A9)=0,"SUG-"&TEXT(COUNTA($B$6:B9),"000"),"SUG-"&TEXT(ROW()-5,"000"))) | B9: Yao Akissi | C9: =IF(B9="","",VLOOKUP(B9,'F01 - _Données Collaborateurs'!$B$6:$F$20,5,FALSE)) | D9: 45698 | E9: Formation | F9: Formation gestion du stress pour les gouvernantes | G9: Acceptée | H9: 10 | I9: 45721 | J9: Session programmée avril 2025 | K9: =IF(B9="","",IFERROR(VLOOKUP(B9,'F01 - _Données Collaborateurs'!$B$6:$H$20,6,FALSE),"")) | L9: =IF(I9="","",IF(I9-D9>15,"Traitement lent","Délai OK"))
A10: =IF(B10="","",IF(COUNTA($A$6:A10)=0,"SUG-"&TEXT(COUNTA($B$6:B10),"000"),"SUG-"&TEXT(ROW()-5,"000"))) | B10: Coulibaly Adama | C10: =IF(B10="","",VLOOKUP(B10,'F01 - _Données Collaborateurs'!$B$6:$F$20,5,FALSE)) | D10: 45703 | E10: Sécurité | F10: Remplacer les extincteurs périmés étage 3 et 4 | G10: Acceptée | H10: 15 | I10: 45708 | J10: Commande urgente passée | K10: =IF(B10="","",IFERROR(VLOOKUP(B10,'F01 - _Données Collaborateurs'!$B$6:$H$20,6,FALSE),"")) | L10: =IF(I10="","",IF(I10-D10>15,"Traitement lent","Délai OK"))
A11: =IF(B11="","",IF(COUNTA($A$6:A11)=0,"SUG-"&TEXT(COUNTA($B$6:B11),"000"),"SUG-"&TEXT(ROW()-5,"000"))) | C11: =IF(B11="","",VLOOKUP(B11,'F01 - _Données Collaborateurs'!$B$6:$F$20,5,FALSE)) | K11: =IF(B11="","",IFERROR(VLOOKUP(B11,'F01 - _Données Collaborateurs'!$B$6:$H$20,6,FALSE),"")) | L11: =IF(I11="","",IF(I11-D11>15,"Traitement lent","Délai OK"))
A12: =IF(B12="","",IF(COUNTA($A$6:A12)=0,"SUG-"&TEXT(COUNTA($B$6:B12),"000"),"SUG-"&TEXT(ROW()-5,"000"))) | C12: =IF(B12="","",VLOOKUP(B12,'F01 - _Données Collaborateurs'!$B$6:$F$20,5,FALSE)) | K12: =IF(B12="","",IFERROR(VLOOKUP(B12,'F01 - _Données Collaborateurs'!$B$6:$H$20,6,FALSE),"")) | L12: =IF(I12="","",IF(I12-D12>15,"Traitement lent","Délai OK"))
A13: =IF(B13="","",IF(COUNTA($A$6:A13)=0,"SUG-"&TEXT(COUNTA($B$6:B13),"000"),"SUG-"&TEXT(ROW()-5,"000"))) | C13: =IF(B13="","",VLOOKUP(B13,'F01 - _Données Collaborateurs'!$B$6:$F$20,5,FALSE)) | K13: =IF(B13="","",IFERROR(VLOOKUP(B13,'F01 - _Données Collaborateurs'!$B$6:$H$20,6,FALSE),"")) | L13: =IF(I13="","",IF(I13-D13>15,"Traitement lent","Délai OK"))
A14: =IF(B14="","",IF(COUNTA($A$6:A14)=0,"SUG-"&TEXT(COUNTA($B$6:B14),"000"),"SUG-"&TEXT(ROW()-5,"000"))) | C14: =IF(B14="","",VLOOKUP(B14,'F01 - _Données Collaborateurs'!$B$6:$F$20,5,FALSE)) | K14: =IF(B14="","",IFERROR(VLOOKUP(B14,'F01 - _Données Collaborateurs'!$B$6:$H$20,6,FALSE),"")) | L14: =IF(I14="","",IF(I14-D14>15,"Traitement lent","Délai OK"))
A15: =IF(B15="","",IF(COUNTA($A$6:A15)=0,"SUG-"&TEXT(COUNTA($B$6:B15),"000"),"SUG-"&TEXT(ROW()-5,"000"))) | C15: =IF(B15="","",VLOOKUP(B15,'F01 - _Données Collaborateurs'!$B$6:$F$20,5,FALSE)) | K15: =IF(B15="","",IFERROR(VLOOKUP(B15,'F01 - _Données Collaborateurs'!$B$6:$H$20,6,FALSE),"")) | L15: =IF(I15="","",IF(I15-D15>15,"Traitement lent","Délai OK"))
A16: =IF(B16="","",IF(COUNTA($A$6:A16)=0,"SUG-"&TEXT(COUNTA($B$6:B16),"000"),"SUG-"&TEXT(ROW()-5,"000"))) | C16: =IF(B16="","",VLOOKUP(B16,'F01 - _Données Collaborateurs'!$B$6:$F$20,5,FALSE)) | K16: =IF(B16="","",IFERROR(VLOOKUP(B16,'F01 - _Données Collaborateurs'!$B$6:$H$20,6,FALSE),"")) | L16: =IF(I16="","",IF(I16-D16>15,"Traitement lent","Délai OK"))
A17: =IF(B17="","",IF(COUNTA($A$6:A17)=0,"SUG-"&TEXT(COUNTA($B$6:B17),"000"),"SUG-"&TEXT(ROW()-5,"000"))) | C17: =IF(B17="","",VLOOKUP(B17,'F01 - _Données Collaborateurs'!$B$6:$F$20,5,FALSE)) | K17: =IF(B17="","",IFERROR(VLOOKUP(B17,'F01 - _Données Collaborateurs'!$B$6:$H$20,6,FALSE),"")) | L17: =IF(I17="","",IF(I17-D17>15,"Traitement lent","Délai OK"))
A18: =IF(B18="","",IF(COUNTA($A$6:A18)=0,"SUG-"&TEXT(COUNTA($B$6:B18),"000"),"SUG-"&TEXT(ROW()-5,"000"))) | C18: =IF(B18="","",VLOOKUP(B18,'F01 - _Données Collaborateurs'!$B$6:$F$20,5,FALSE)) | K18: =IF(B18="","",IFERROR(VLOOKUP(B18,'F01 - _Données Collaborateurs'!$B$6:$H$20,6,FALSE),"")) | L18: =IF(I18="","",IF(I18-D18>15,"Traitement lent","Délai OK"))
A19: =IF(B19="","",IF(COUNTA($A$6:A19)=0,"SUG-"&TEXT(COUNTA($B$6:B19),"000"),"SUG-"&TEXT(ROW()-5,"000"))) | C19: =IF(B19="","",VLOOKUP(B19,'F01 - _Données Collaborateurs'!$B$6:$F$20,5,FALSE)) | K19: =IF(B19="","",IFERROR(VLOOKUP(B19,'F01 - _Données Collaborateurs'!$B$6:$H$20,6,FALSE),"")) | L19: =IF(I19="","",IF(I19-D19>15,"Traitement lent","Délai OK"))
A20: =IF(B20="","",IF(COUNTA($A$6:A20)=0,"SUG-"&TEXT(COUNTA($B$6:B20),"000"),"SUG-"&TEXT(ROW()-5,"000"))) | C20: =IF(B20="","",VLOOKUP(B20,'F01 - _Données Collaborateurs'!$B$6:$F$20,5,FALSE)) | K20: =IF(B20="","",IFERROR(VLOOKUP(B20,'F01 - _Données Collaborateurs'!$B$6:$H$20,6,FALSE),"")) | L20: =IF(I20="","",IF(I20-D20>15,"Traitement lent","Délai OK"))
A21: =IF(B21="","",IF(COUNTA($A$6:A21)=0,"SUG-"&TEXT(COUNTA($B$6:B21),"000"),"SUG-"&TEXT(ROW()-5,"000"))) | C21: =IF(B21="","",VLOOKUP(B21,'F01 - _Données Collaborateurs'!$B$6:$F$20,5,FALSE)) | K21: =IF(B21="","",IFERROR(VLOOKUP(B21,'F01 - _Données Collaborateurs'!$B$6:$H$20,6,FALSE),"")) | L21: =IF(I21="","",IF(I21-D21>15,"Traitement lent","Délai OK"))
A22: =IF(B22="","",IF(COUNTA($A$6:A22)=0,"SUG-"&TEXT(COUNTA($B$6:B22),"000"),"SUG-"&TEXT(ROW()-5,"000"))) | C22: =IF(B22="","",VLOOKUP(B22,'F01 - _Données Collaborateurs'!$B$6:$F$20,5,FALSE)) | K22: =IF(B22="","",IFERROR(VLOOKUP(B22,'F01 - _Données Collaborateurs'!$B$6:$H$20,6,FALSE),"")) | L22: =IF(I22="","",IF(I22-D22>15,"Traitement lent","Délai OK"))
... A115: =IF(B115="","",IF(COUNTA($A$6:A115)=0,"SUG-"&TEXT(COUNTA($B$6:B115),"000"),"SUG-"&TEXT(ROW()-5,"000"))) | C115: =IF(B115="","",VLOOKUP(B115,'F01 - _Données Collaborateurs'!$B$6:$F$20,5,FALSE)) | K115: =IF(B115="","",IFERROR(VLOOKUP(B115,'F01 - _Données Collaborateurs'!$B$6:$H$20,6,FALSE),"")) | L115: =IF(I115="","",IF(I115-D115>15,"Traitement lent","Délai OK"))

Sheet F09 - 7-Entretiens Individuels
A2: 7-ENTRETIENS INDIVIDUELS RÉGULIERS
A3: TABLEAU DYNAMIQUE — Saisissez dans la zone prévue ci-dessous
A5: Code Entretien | B5: Collaborateur | C5: Département | D5: Date Entretien | E5: Type | F5: Manager | G5: Score Satisfaction (/5) | H5: Points Forts | I5: Axes Amélioration | J5: Suivi | K5: Observations
A6: =IF(B6="","",IF(COUNTA($A$6:A6)=0,"ENT-"&TEXT(COUNTA($B$6:B6),"000"),"ENT-"&TEXT(ROW()-5,"000"))) | B6: Koné Aminata | C6: =IF(B6="","",VLOOKUP(B6,'F01 - _Données Collaborateurs'!$B$6:$F$20,5,FALSE)) | D6: 45677 | E6: Mensuel | F6: Chef Cuisinier | G6: 4 | H6: Créativité, leadership brigade | I6: Gestion du stress en période haute | J6: Formation gestion stress prévue | L6: =IF(B6="","",IFERROR(VLOOKUP(B6,'F01 - _Données Collaborateurs'!$B$6:$G$20,6,FALSE),"")) | M6: =IF(OR(G6="",L6=""),"",IFERROR(G6-L6/20*5,0))
A7: =IF(B7="","",IF(COUNTA($A$6:A7)=0,"ENT-"&TEXT(COUNTA($B$6:B7),"000"),"ENT-"&TEXT(ROW()-5,"000"))) | B7: Traoré Ibrahim | C7: =IF(B7="","",VLOOKUP(B7,'F01 - _Données Collaborateurs'!$B$6:$F$20,5,FALSE)) | D7: 45679 | E7: Mensuel | F7: DG | G7: 4.5 | H7: Expertise technique, disponibilité | I7: Délégation et accompagnement équipe | J7: Mentorat junior en place | L7: =IF(B7="","",IFERROR(VLOOKUP(B7,'F01 - _Données Collaborateurs'!$B$6:$G$20,6,FALSE),"")) | M7: =IF(OR(G7="",L7=""),"",IFERROR(G7-L7/20*5,0))
A8: =IF(B8="","",IF(COUNTA($A$6:A8)=0,"ENT-"&TEXT(COUNTA($B$6:B8),"000"),"ENT-"&TEXT(ROW()-5,"000"))) | B8: Bamba Mariam | C8: =IF(B8="","",VLOOKUP(B8,'F01 - _Données Collaborateurs'!$B$6:$F$20,5,FALSE)) | D8: 45682 | E8: Mensuel | F8: DRH | G8: 4.8 | H8: Excellente relation client, ponctualité | I8: Préparation concours interne | J8: Dossier en cours | L8: =IF(B8="","",IFERROR(VLOOKUP(B8,'F01 - _Données Collaborateurs'!$B$6:$G$20,6,FALSE),"")) | M8: =IF(OR(G8="",L8=""),"",IFERROR(G8-L8/20*5,0))
A9: =IF(B9="","",IF(COUNTA($A$6:A9)=0,"ENT-"&TEXT(COUNTA($B$6:B9),"000"),"ENT-"&TEXT(ROW()-5,"000"))) | B9: Coulibaly Adama | C9: =IF(B9="","",VLOOKUP(B9,'F01 - _Données Collaborateurs'!$B$6:$F$20,5,FALSE)) | D9: 45693 | E9: Mensuel | F9: Chef Entretien | G9: 3.2 | H9: Connaissance technique solide | I9: Motivation et communication | J9: Plan d'action en cours | L9: =IF(B9="","",IFERROR(VLOOKUP(B9,'F01 - _Données Collaborateurs'!$B$6:$G$20,6,FALSE),"")) | M9: =IF(OR(G9="",L9=""),"",IFERROR(G9-L9/20*5,0))
A10: =IF(B10="","",IF(COUNTA($A$6:A10)=0,"ENT-"&TEXT(COUNTA($B$6:B10),"000"),"ENT-"&TEXT(ROW()-5,"000"))) | B10: Djibril Oumar | C10: =IF(B10="","",VLOOKUP(B10,'F01 - _Données Collaborateurs'!$B$6:$F$20,5,FALSE)) | D10: 45698 | E10: Trimestriel | F10: DG | G10: 3 | H10: Rigueur, respect consignes | I10: Proactivité et initiative | J10: Objectif : 1 initiative/mois | L10: =IF(B10="","",IFERROR(VLOOKUP(B10,'F01 - _Données Collaborateurs'!$B$6:$G$20,6,FALSE),"")) | M10: =IF(OR(G10="",L10=""),"",IFERROR(G10-L10/20*5,0))
A11: =IF(B11="","",IF(COUNTA($A$6:A11)=0,"ENT-"&TEXT(COUNTA($B$6:B11),"000"),"ENT-"&TEXT(ROW()-5,"000"))) | C11: =IF(B11="","",VLOOKUP(B11,'F01 - _Données Collaborateurs'!$B$6:$F$20,5,FALSE)) | L11: =IF(B11="","",IFERROR(VLOOKUP(B11,'F01 - _Données Collaborateurs'!$B$6:$G$20,6,FALSE),"")) | M11: =IF(OR(G11="",L11=""),"",IFERROR(G11-L11/20*5,0))
A12: =IF(B12="","",IF(COUNTA($A$6:A12)=0,"ENT-"&TEXT(COUNTA($B$6:B12),"000"),"ENT-"&TEXT(ROW()-5,"000"))) | C12: =IF(B12="","",VLOOKUP(B12,'F01 - _Données Collaborateurs'!$B$6:$F$20,5,FALSE)) | L12: =IF(B12="","",IFERROR(VLOOKUP(B12,'F01 - _Données Collaborateurs'!$B$6:$G$20,6,FALSE),"")) | M12: =IF(OR(G12="",L12=""),"",IFERROR(G12-L12/20*5,0))
A13: =IF(B13="","",IF(COUNTA($A$6:A13)=0,"ENT-"&TEXT(COUNTA($B$6:B13),"000"),"ENT-"&TEXT(ROW()-5,"000"))) | C13: =IF(B13="","",VLOOKUP(B13,'F01 - _Données Collaborateurs'!$B$6:$F$20,5,FALSE)) | L13: =IF(B13="","",IFERROR(VLOOKUP(B13,'F01 - _Données Collaborateurs'!$B$6:$G$20,6,FALSE),"")) | M13: =IF(OR(G13="",L13=""),"",IFERROR(G13-L13/20*5,0))
A14: =IF(B14="","",IF(COUNTA($A$6:A14)=0,"ENT-"&TEXT(COUNTA($B$6:B14),"000"),"ENT-"&TEXT(ROW()-5,"000"))) | C14: =IF(B14="","",VLOOKUP(B14,'F01 - _Données Collaborateurs'!$B$6:$F$20,5,FALSE)) | L14: =IF(B14="","",IFERROR(VLOOKUP(B14,'F01 - _Données Collaborateurs'!$B$6:$G$20,6,FALSE),"")) | M14: =IF(OR(G14="",L14=""),"",IFERROR(G14-L14/20*5,0))
A15: =IF(B15="","",IF(COUNTA($A$6:A15)=0,"ENT-"&TEXT(COUNTA($B$6:B15),"000"),"ENT-"&TEXT(ROW()-5,"000"))) | C15: =IF(B15="","",VLOOKUP(B15,'F01 - _Données Collaborateurs'!$B$6:$F$20,5,FALSE)) | L15: =IF(B15="","",IFERROR(VLOOKUP(B15,'F01 - _Données Collaborateurs'!$B$6:$G$20,6,FALSE),"")) | M15: =IF(OR(G15="",L15=""),"",IFERROR(G15-L15/20*5,0))
A16: =IF(B16="","",IF(COUNTA($A$6:A16)=0,"ENT-"&TEXT(COUNTA($B$6:B16),"000"),"ENT-"&TEXT(ROW()-5,"000"))) | C16: =IF(B16="","",VLOOKUP(B16,'F01 - _Données Collaborateurs'!$B$6:$F$20,5,FALSE)) | L16: =IF(B16="","",IFERROR(VLOOKUP(B16,'F01 - _Données Collaborateurs'!$B$6:$G$20,6,FALSE),"")) | M16: =IF(OR(G16="",L16=""),"",IFERROR(G16-L16/20*5,0))
A17: =IF(B17="","",IF(COUNTA($A$6:A17)=0,"ENT-"&TEXT(COUNTA($B$6:B17),"000"),"ENT-"&TEXT(ROW()-5,"000"))) | C17: =IF(B17="","",VLOOKUP(B17,'F01 - _Données Collaborateurs'!$B$6:$F$20,5,FALSE)) | L17: =IF(B17="","",IFERROR(VLOOKUP(B17,'F01 - _Données Collaborateurs'!$B$6:$G$20,6,FALSE),"")) | M17: =IF(OR(G17="",L17=""),"",IFERROR(G17-L17/20*5,0))
A18: =IF(B18="","",IF(COUNTA($A$6:A18)=0,"ENT-"&TEXT(COUNTA($B$6:B18),"000"),"ENT-"&TEXT(ROW()-5,"000"))) | C18: =IF(B18="","",VLOOKUP(B18,'F01 - _Données Collaborateurs'!$B$6:$F$20,5,FALSE)) | L18: =IF(B18="","",IFERROR(VLOOKUP(B18,'F01 - _Données Collaborateurs'!$B$6:$G$20,6,FALSE),"")) | M18: =IF(OR(G18="",L18=""),"",IFERROR(G18-L18/20*5,0))
A19: =IF(B19="","",IF(COUNTA($A$6:A19)=0,"ENT-"&TEXT(COUNTA($B$6:B19),"000"),"ENT-"&TEXT(ROW()-5,"000"))) | C19: =IF(B19="","",VLOOKUP(B19,'F01 - _Données Collaborateurs'!$B$6:$F$20,5,FALSE)) | L19: =IF(B19="","",IFERROR(VLOOKUP(B19,'F01 - _Données Collaborateurs'!$B$6:$G$20,6,FALSE),"")) | M19: =IF(OR(G19="",L19=""),"",IFERROR(G19-L19/20*5,0))
A20: =IF(B20="","",IF(COUNTA($A$6:A20)=0,"ENT-"&TEXT(COUNTA($B$6:B20),"000"),"ENT-"&TEXT(ROW()-5,"000"))) | C20: =IF(B20="","",VLOOKUP(B20,'F01 - _Données Collaborateurs'!$B$6:$F$20,5,FALSE)) | L20: =IF(B20="","",IFERROR(VLOOKUP(B20,'F01 - _Données Collaborateurs'!$B$6:$G$20,6,FALSE),"")) | M20: =IF(OR(G20="",L20=""),"",IFERROR(G20-L20/20*5,0))
A21: =IF(B21="","",IF(COUNTA($A$6:A21)=0,"ENT-"&TEXT(COUNTA($B$6:B21),"000"),"ENT-"&TEXT(ROW()-5,"000"))) | C21: =IF(B21="","",VLOOKUP(B21,'F01 - _Données Collaborateurs'!$B$6:$F$20,5,FALSE)) | L21: =IF(B21="","",IFERROR(VLOOKUP(B21,'F01 - _Données Collaborateurs'!$B$6:$G$20,6,FALSE),"")) | M21: =IF(OR(G21="",L21=""),"",IFERROR(G21-L21/20*5,0))
A22: =IF(B22="","",IF(COUNTA($A$6:A22)=0,"ENT-"&TEXT(COUNTA($B$6:B22),"000"),"ENT-"&TEXT(ROW()-5,"000"))) | C22: =IF(B22="","",VLOOKUP(B22,'F01 - _Données Collaborateurs'!$B$6:$F$20,5,FALSE)) | L22: =IF(B22="","",IFERROR(VLOOKUP(B22,'F01 - _Données Collaborateurs'!$B$6:$G$20,6,FALSE),"")) | M22: =IF(OR(G22="",L22=""),"",IFERROR(G22-L22/20*5,0))
... A115: =IF(B115="","",IF(COUNTA($A$6:A115)=0,"ENT-"&TEXT(COUNTA($B$6:B115),"000"),"ENT-"&TEXT(ROW()-5,"000"))) | C115: =IF(B115="","",VLOOKUP(B115,'F01 - _Données Collaborateurs'!$B$6:$F$20,5,FALSE)) | L115: =IF(B115="","",IFERROR(VLOOKUP(B115,'F01 - _Données Collaborateurs'!$B$6:$G$20,6,FALSE),"")) | M115: =IF(OR(G115="",L115=""),"",IFERROR(G115-L115/20*5,0))

Sheet F10 - 8-Indic. Engage.Dépt
A2: 8-INDICATEURS D'ENGAGEMENT PAR DÉPARTEMENT
A3: TABLEAU DYNAMIQUE — Saisissez dans la zone prévue ci-dessous
A5: Département | B5: Effectif | C5: Score Engagement Moy. | D5: Nb Suggestions | E5: Taux Participation Enq. (%) | F5: Nb Départs Volontaires | G5: Taux Rotation (%) | H5: Nb Absences | I5: Score Climat Social (/5) | J5: Tendance | K5: Observations
A6: Cuisine & Restauration | B6: 2 | C6: =IF(A6="","",IFERROR(AVERAGEIF('F01 - _Données Collaborateurs'!$D$6:$D$20,A6,'F01 - _Données Collaborateurs'!$F$6:$F$20),0)) | D6: =IF(A6="","",IFERROR(COUNTIF('F08 - 6-Boîte à Idées'!$C$6:$C$115,A6),0)) | F6: =IF(A6="","",IFERROR(F6/B6*100,0)) | G6: =IF(A6="","",IFERROR(F6/B6*100,0)) | H6: 3 | K6: Bonne dynamique d'équipe
A7: Informatique | B7: 1 | C7: =IF(A7="","",IFERROR(AVERAGEIF('F01 - _Données Collaborateurs'!$D$6:$D$20,A7,'F01 - _Données Collaborateurs'!$F$6:$F$20),0)) | D7: =IF(A7="","",IFERROR(COUNTIF('F08 - 6-Boîte à Idées'!$C$6:$C$115,A7),0)) | F7: =IF(A7="","",IFERROR(F7/B7*100,0)) | G7: =IF(A7="","",IFERROR(F7/B7*100,0)) | H7: 1 | K7: Collaborateur très engagé
A8: Marketing & Communication | B8: 1 | C8: =IF(A8="","",IFERROR(AVERAGEIF('F01 - _Données Collaborateurs'!$D$6:$D$20,A8,'F01 - _Données Collaborateurs'!$F$6:$F$20),0)) | D8: =IF(A8="","",IFERROR(COUNTIF('F08 - 6-Boîte à Idées'!$C$6:$C$115,A8),0)) | F8: =IF(A8="","",IFERROR(F8/B8*100,0)) | G8: =IF(A8="","",IFERROR(F8/B8*100,0)) | H8: 2 | K8: Score communication attendu élevé
A9: Finance & Comptabilité | B9: 1 | C9: =IF(A9="","",IFERROR(AVERAGEIF('F01 - _Données Collaborateurs'!$D$6:$D$20,A9,'F01 - _Données Collaborateurs'!$F$6:$F$20),0)) | D9: =IF(A9="","",IFERROR(COUNTIF('F08 - 6-Boîte à Idées'!$C$6:$C$115,A9),0)) | F9: =IF(A9="","",IFERROR(F9/B9*100,0)) | G9: =IF(A9="","",IFERROR(F9/B9*100,0)) | H9: 4 | K9: Départ à analyser
A10: Réception & Front Office | B10: 1 | C10: =IF(A10="","",IFERROR(AVERAGEIF('F01 - _Données Collaborateurs'!$D$6:$D$20,A10,'F01 - _Données Collaborateurs'!$F$6:$F$20),0)) | D10: =IF(A10="","",IFERROR(COUNTIF('F08 - 6-Boîte à Idées'!$C$6:$C$115,A10),0)) | F10: =IF(A10="","",IFERROR(F10/B10*100,0)) | G10: =IF(A10="","",IFERROR(F10/B10*100,0)) | H10: 1 | K10: Ambassadrice de l'engagement
A11: Hébergement | B11: 1 | C11: =IF(A11="","",IFERROR(AVERAGEIF('F01 - _Données Collaborateurs'!$D$6:$D$20,A11,'F01 - _Données Collaborateurs'!$F$6:$F$20),0)) | D11: =IF(A11="","",IFERROR(COUNTIF('F08 - 6-Boîte à Idées'!$C$6:$C$115,A11),0)) | F11: =IF(A11="","",IFERROR(F11/B11*100,0)) | G11: =IF(A11="","",IFERROR(F11/B11*100,0)) | H11: 2 | K11: Excellente gouvernante
A12: Entretien & Maintenance | B12: 1 | C12: =IF(A12="","",IFERROR(AVERAGEIF('F01 - _Données Collaborateurs'!$D$6:$D$20,A12,'F01 - _Données Collaborateurs'!$F$6:$F$20),0)) | D12: =IF(A12="","",IFERROR(COUNTIF('F08 - 6-Boîte à Idées'!$C$6:$C$115,A12),0)) | F12: =IF(A12="","",IFERROR(F12/B12*100,0)) | G12: =IF(A12="","",IFERROR(F12/B12*100,0)) | H12: 6 | K12: Département à surveiller
A13: Ressources Humaines | B13: 1 | C13: =IF(A13="","",IFERROR(AVERAGEIF('F01 - _Données Collaborateurs'!$D$6:$D$20,A13,'F01 - _Données Collaborateurs'!$F$6:$F$20),0)) | D13: =IF(A13="","",IFERROR(COUNTIF('F08 - 6-Boîte à Idées'!$C$6:$C$115,A13),0)) | F13: =IF(A13="","",IFERROR(F13/B13*100,0)) | G13: =IF(A13="","",IFERROR(F13/B13*100,0)) | H13: 1 | K13: Référent engagement
A14: Commercial | B14: 1 | C14: =IF(A14="","",IFERROR(AVERAGEIF('F01 - _Données Collaborateurs'!$D$6:$D$20,A14,'F01 - _Données Collaborateurs'!$F$6:$F$20),0)) | D14: =IF(A14="","",IFERROR(COUNTIF('F08 - 6-Boîte à Idées'!$C$6:$C$115,A14),0)) | F14: =IF(A14="","",IFERROR(F14/B14*100,0)) | G14: =IF(A14="","",IFERROR(F14/B14*100,0)) | H14: 3 | K14: Stable
A15: Sécurité | B15: 1 | C15: =IF(A15="","",IFERROR(AVERAGEIF('F01 - _Données Collaborateurs'!$D$6:$D$20,A15,'F01 - _Données Collaborateurs'!$F$6:$F$20),0)) | D15: =IF(A15="","",IFERROR(COUNTIF('F08 - 6-Boîte à Idées'!$C$6:$C$115,A15),0)) | F15: =IF(A15="","",IFERROR(F15/B15*100,0)) | G15: =IF(A15="","",IFERROR(F15/B15*100,0)) | H15: 5 | K15: Rotation élevée à analyser
C16: =IF(A16="","",IFERROR(AVERAGEIF('F01 - _Données Collaborateurs'!$D$6:$D$20,A16,'F01 - _Données Collaborateurs'!$F$6:$F$20),0)) | D16: =IF(A16="","",IFERROR(COUNTIF('F08 - 6-Boîte à Idées'!$C$6:$C$115,A16),0)) | F16: =IF(A16="","",IFERROR(F16/B16*100,0)) | G16: =IF(A16="","",IFERROR(F16/B16*100,0))
C17: =IF(A17="","",IFERROR(AVERAGEIF('F01 - _Données Collaborateurs'!$D$6:$D$20,A17,'F01 - _Données Collaborateurs'!$F$6:$F$20),0)) | D17: =IF(A17="","",IFERROR(COUNTIF('F08 - 6-Boîte à Idées'!$C$6:$C$115,A17),0)) | F17: =IF(A17="","",IFERROR(F17/B17*100,0)) | G17: =IF(A17="","",IFERROR(F17/B17*100,0))
C18: =IF(A18="","",IFERROR(AVERAGEIF('F01 - _Données Collaborateurs'!$D$6:$D$20,A18,'F01 - _Données Collaborateurs'!$F$6:$F$20),0)) | D18: =IF(A18="","",IFERROR(COUNTIF('F08 - 6-Boîte à Idées'!$C$6:$C$115,A18),0)) | F18: =IF(A18="","",IFERROR(F18/B18*100,0)) | G18: =IF(A18="","",IFERROR(F18/B18*100,0))
C19: =IF(A19="","",IFERROR(AVERAGEIF('F01 - _Données Collaborateurs'!$D$6:$D$20,A19,'F01 - _Données Collaborateurs'!$F$6:$F$20),0)) | D19: =IF(A19="","",IFERROR(COUNTIF('F08 - 6-Boîte à Idées'!$C$6:$C$115,A19),0)) | F19: =IF(A19="","",IFERROR(F19/B19*100,0)) | G19: =IF(A19="","",IFERROR(F19/B19*100,0))
C20: =IF(A20="","",IFERROR(AVERAGEIF('F01 - _Données Collaborateurs'!$D$6:$D$20,A20,'F01 - _Données Collaborateurs'!$F$6:$F$20),0)) | D20: =IF(A20="","",IFERROR(COUNTIF('F08 - 6-Boîte à Idées'!$C$6:$C$115,A20),0)) | F20: =IF(A20="","",IFERROR(F20/B20*100,0)) | G20: =IF(A20="","",IFERROR(F20/B20*100,0))
C21: =IF(A21="","",IFERROR(AVERAGEIF('F01 - _Données Collaborateurs'!$D$6:$D$20,A21,'F01 - _Données Collaborateurs'!$F$6:$F$20),0)) | D21: =IF(A21="","",IFERROR(COUNTIF('F08 - 6-Boîte à Idées'!$C$6:$C$115,A21),0)) | F21: =IF(A21="","",IFERROR(F21/B21*100,0)) | G21: =IF(A21="","",IFERROR(F21/B21*100,0))
C22: =IF(A22="","",IFERROR(AVERAGEIF('F01 - _Données Collaborateurs'!$D$6:$D$20,A22,'F01 - _Données Collaborateurs'!$F$6:$F$20),0)) | D22: =IF(A22="","",IFERROR(COUNTIF('F08 - 6-Boîte à Idées'!$C$6:$C$115,A22),0)) | F22: =IF(A22="","",IFERROR(F22/B22*100,0)) | G22: =IF(A22="","",IFERROR(F22/B22*100,0))
C23: =IF(A23="","",IFERROR(AVERAGEIF('F01 - _Données Collaborateurs'!$D$6:$D$20,A23,'F01 - _Données Collaborateurs'!$F$6:$F$20),0)) | D23: =IF(A23="","",IFERROR(COUNTIF('F08 - 6-Boîte à Idées'!$C$6:$C$115,A23),0)) | F23: =IF(A23="","",IFERROR(F23/B23*100,0)) | G23: =IF(A23="","",IFERROR(F23/B23*100,0))
C24: =IF(A24="","",IFERROR(AVERAGEIF('F01 - _Données Collaborateurs'!$D$6:$D$20,A24,'F01 - _Données Collaborateurs'!$F$6:$F$20),0)) | D24: =IF(A24="","",IFERROR(COUNTIF('F08 - 6-Boîte à Idées'!$C$6:$C$115,A24),0)) | F24: =IF(A24="","",IFERROR(F24/B24*100,0)) | G24: =IF(A24="","",IFERROR(F24/B24*100,0))
C25: =IF(A25="","",IFERROR(AVERAGEIF('F01 - _Données Collaborateurs'!$D$6:$D$20,A25,'F01 - _Données Collaborateurs'!$F$6:$F$20),0)) | D25: =IF(A25="","",IFERROR(COUNTIF('F08 - 6-Boîte à Idées'!$C$6:$C$115,A25),0)) | F25: =IF(A25="","",IFERROR(F25/B25*100,0)) | G25: =IF(A25="","",IFERROR(F25/B25*100,0))
C26: =IF(A26="","",IFERROR(AVERAGEIF('F01 - _Données Collaborateurs'!$D$6:$D$20,A26,'F01 - _Données Collaborateurs'!$F$6:$F$20),0)) | D26: =IF(A26="","",IFERROR(COUNTIF('F08 - 6-Boîte à Idées'!$C$6:$C$115,A26),0)) | F26: =IF(A26="","",IFERROR(F26/B26*100,0)) | G26: =IF(A26="","",IFERROR(F26/B26*100,0))
C27: =IF(A27="","",IFERROR(AVERAGEIF('F01 - _Données Collaborateurs'!$D$6:$D$20,A27,'F01 - _Données Collaborateurs'!$F$6:$F$20),0)) | D27: =IF(A27="","",IFERROR(COUNTIF('F08 - 6-Boîte à Idées'!$C$6:$C$115,A27),0)) | F27: =IF(A27="","",IFERROR(F27/B27*100,0)) | G27: =IF(A27="","",IFERROR(F27/B27*100,0))
... C115: =IF(A115="","",IFERROR(AVERAGEIF('F01 - _Données Collaborateurs'!$D$6:$D$20,A115,'F01 - _Données Collaborateurs'!$F$6:$F$20),0)) | D115: =IF(A115="","",IFERROR(COUNTIF('F08 - 6-Boîte à Idées'!$C$6:$C$115,A115),0)) | F115: =IF(A115="","",IFERROR(F115/B115*100,0)) | G115: =IF(A115="","",IFERROR(F115/B115*100,0))

Sheet F11 - 9-Actions Amélior. QVT
A2: 9-ACTIONS D'AMÉLIORATION QVT
A3: TABLEAU DYNAMIQUE — Saisissez dans la zone prévue ci-dessous
A5: Code Action | B5: Action | C5: Département Concerné | D5: Origine | E5: Priorité | F5: Responsable | G5: Date Lancement | H5: Date Échéance | I5: Budget (FCFA) | J5: Statut | K5: Impact Mesuré | L5: Observations
A6: =IF(B6="","",IF(COUNTA($A$6:A6)=0,"QVT-"&TEXT(COUNTA($B$6:B6),"000"),"QVT-"&TEXT(ROW()-5,"000"))) | B6: Aménager espace de repos équipe cuisine | C6: Cuisine & Restauration | D6: Enquête engagement | E6: Haute | F6: DRH / Chef Cuisinier | G6: 45689 | H6: 45747 | I6: 500000 | J6: En cours | K6: Satisfaction +12% cuisine | L6: Travaux en cours
A7: =IF(B7="","",IF(COUNTA($A$6:A7)=0,"QVT-"&TEXT(COUNTA($B$6:B7),"000"),"QVT-"&TEXT(ROW()-5,"000"))) | B7: Programme reconnaissance mensuelle | C7: Tous | D7: Direction | E7: Haute | F7: DRH | G7: 45717 | H7: 46022 | I7: 600000 | J7: En cours | K7: Engagement +5% global | L7: 1er prix décerné mars
A8: =IF(B8="","",IF(COUNTA($A$6:A8)=0,"QVT-"&TEXT(COUNTA($B$6:B8),"000"),"QVT-"&TEXT(ROW()-5,"000"))) | B8: Formation gestion du stress | C8: Hébergement | D8: Entretien individuel | E8: Moyenne | F8: DRH | G8: 45762 | H8: 45777 | I8: 150000 | J8: Planifié | L8: Intervenant psychologue confirmé
A9: =IF(B9="","",IF(COUNTA($A$6:A9)=0,"QVT-"&TEXT(COUNTA($B$6:B9),"000"),"QVT-"&TEXT(ROW()-5,"000"))) | B9: Horaires flexibles vendredi entretien | C9: Entretien & Maintenance | D9: Suggestion collaborateur | E9: Moyenne | F9: DRH / Chef Entretien | G9: 45731 | H9: 45838 | I9: 0 | J9: En cours | K9: Absentéisme -20% | L9: Test sur 3 mois
A10: =IF(B10="","",IF(COUNTA($A$6:A10)=0,"QVT-"&TEXT(COUNTA($B$6:B10),"000"),"QVT-"&TEXT(ROW()-5,"000"))) | B10: Mise en place télétravail partiel DSI | C10: Informatique | D10: Enquête QVT | E10: Basse | F10: DSI / DRH | G10: 45778 | H10: 45900 | I10: 200000 | J10: Planifié | L10: Étude juridique en cours
A11: =IF(B11="","",IF(COUNTA($A$6:A11)=0,"QVT-"&TEXT(COUNTA($B$6:B11),"000"),"QVT-"&TEXT(ROW()-5,"000")))
A12: =IF(B12="","",IF(COUNTA($A$6:A12)=0,"QVT-"&TEXT(COUNTA($B$6:B12),"000"),"QVT-"&TEXT(ROW()-5,"000")))
A13: =IF(B13="","",IF(COUNTA($A$6:A13)=0,"QVT-"&TEXT(COUNTA($B$6:B13),"000"),"QVT-"&TEXT(ROW()-5,"000")))
A14: =IF(B14="","",IF(COUNTA($A$6:A14)=0,"QVT-"&TEXT(COUNTA($B$6:B14),"000"),"QVT-"&TEXT(ROW()-5,"000")))
A15: =IF(B15="","",IF(COUNTA($A$6:A15)=0,"QVT-"&TEXT(COUNTA($B$6:B15),"000"),"QVT-"&TEXT(ROW()-5,"000")))
A16: =IF(B16="","",IF(COUNTA($A$6:A16)=0,"QVT-"&TEXT(COUNTA($B$6:B16),"000"),"QVT-"&TEXT(ROW()-5,"000")))
A17: =IF(B17="","",IF(COUNTA($A$6:A17)=0,"QVT-"&TEXT(COUNTA($B$6:B17),"000"),"QVT-"&TEXT(ROW()-5,"000")))
A18: =IF(B18="","",IF(COUNTA($A$6:A18)=0,"QVT-"&TEXT(COUNTA($B$6:B18),"000"),"QVT-"&TEXT(ROW()-5,"000")))
A19: =IF(B19="","",IF(COUNTA($A$6:A19)=0,"QVT-"&TEXT(COUNTA($B$6:B19),"000"),"QVT-"&TEXT(ROW()-5,"000")))
A20: =IF(B20="","",IF(COUNTA($A$6:A20)=0,"QVT-"&TEXT(COUNTA($B$6:B20),"000"),"QVT-"&TEXT(ROW()-5,"000")))
A21: =IF(B21="","",IF(COUNTA($A$6:A21)=0,"QVT-"&TEXT(COUNTA($B$6:B21),"000"),"QVT-"&TEXT(ROW()-5,"000")))
A22: =IF(B22="","",IF(COUNTA($A$6:A22)=0,"QVT-"&TEXT(COUNTA($B$6:B22),"000"),"QVT-"&TEXT(ROW()-5,"000")))
... A115: =IF(B115="","",IF(COUNTA($A$6:A115)=0,"QVT-"&TEXT(COUNTA($B$6:B115),"000"),"QVT-"&TEXT(ROW()-5,"000")))

Sheet F12 - 10-Gest. Rumeurs Alertes
A2: 10-GESTION DES RUMEURS ET ALERTES
A3: TABLEAU DYNAMIQUE — Saisissez dans la zone prévue ci-dessous
A5: Code Alerte | B5: Type | C5: Niveau | D5: Source | E5: Date Détection | F5: Description | G5: Département Concerné | H5: Action Menee | I5: Date Résolution | J5: Statut | K5: Impact | L5: Observations
A6: =IF(B6="","",IF(COUNTA($A$6:A6)=0,"ALR-"&TEXT(COUNTA($B$6:B6),"000"),"ALR-"&TEXT(ROW()-5,"000"))) | B6: Rumeur | C6: Moyen | D6: Boîte à idées anonyme | E6: 45672 | F6: Rumeur de licenciements massifs en cuisine | G6: Cuisine & Restauration | H6: Communication officielle DG | I6: 45674 | J6: Résolu | K6: Faible | L6: Communiqué interne diffusé rapidement
A7: =IF(B7="","",IF(COUNTA($A$6:A7)=0,"ALR-"&TEXT(COUNTA($B$6:B7),"000"),"ALR-"&TEXT(ROW()-5,"000"))) | B7: Mécontentement | C7: Élevé | D7: Entretien manager | E7: 45689 | F7: Mécontentement équipe entretien sur les horaires | G7: Entretien & Maintenance | H7: Réunion d'équipe + révision planning | I7: 45703 | J7: Résolu | K7: Modéré | L7: Nouveau planning mis en place
A8: =IF(B8="","",IF(COUNTA($A$6:A8)=0,"ALR-"&TEXT(COUNTA($B$6:B8),"000"),"ALR-"&TEXT(ROW()-5,"000"))) | B8: Risque départ | C8: Élevé | D8: Entretien individuel | E8: 45698 | F8: Risque de départ gouvernante (opportunité concurrent) | G8: Hébergement | H8: Contre-proposition + reconnaissance | J8: En cours | K8: Élevé | L8: Suivi hebdomadaire mis en place
A9: =IF(B9="","",IF(COUNTA($A$6:A9)=0,"ALR-"&TEXT(COUNTA($B$6:B9),"000"),"ALR-"&TEXT(ROW()-5,"000"))) | B9: Tension interne | C9: Moyen | D9: Observation DRH | E9: 45708 | F9: Tension entre équipe sécurité et réception de nuit | G9: Sécurité | H9: Médiation DRH prévue | J9: En cours | K9: Modéré | L9: Réunion tripartite programmée
A10: =IF(B10="","",IF(COUNTA($A$6:A10)=0,"ALR-"&TEXT(COUNTA($B$6:B10),"000"),"ALR-"&TEXT(ROW()-5,"000")))
A11: =IF(B11="","",IF(COUNTA($A$6:A11)=0,"ALR-"&TEXT(COUNTA($B$6:B11),"000"),"ALR-"&TEXT(ROW()-5,"000")))
A12: =IF(B12="","",IF(COUNTA($A$6:A12)=0,"ALR-"&TEXT(COUNTA($B$6:B12),"000"),"ALR-"&TEXT(ROW()-5,"000")))
A13: =IF(B13="","",IF(COUNTA($A$6:A13)=0,"ALR-"&TEXT(COUNTA($B$6:B13),"000"),"ALR-"&TEXT(ROW()-5,"000")))
A14: =IF(B14="","",IF(COUNTA($A$6:A14)=0,"ALR-"&TEXT(COUNTA($B$6:B14),"000"),"ALR-"&TEXT(ROW()-5,"000")))
A15: =IF(B15="","",IF(COUNTA($A$6:A15)=0,"ALR-"&TEXT(COUNTA($B$6:B15),"000"),"ALR-"&TEXT(ROW()-5,"000")))
A16: =IF(B16="","",IF(COUNTA($A$6:A16)=0,"ALR-"&TEXT(COUNTA($B$6:B16),"000"),"ALR-"&TEXT(ROW()-5,"000")))
A17: =IF(B17="","",IF(COUNTA($A$6:A17)=0,"ALR-"&TEXT(COUNTA($B$6:B17),"000"),"ALR-"&TEXT(ROW()-5,"000")))
A18: =IF(B18="","",IF(COUNTA($A$6:A18)=0,"ALR-"&TEXT(COUNTA($B$6:B18),"000"),"ALR-"&TEXT(ROW()-5,"000")))
A19: =IF(B19="","",IF(COUNTA($A$6:A19)=0,"ALR-"&TEXT(COUNTA($B$6:B19),"000"),"ALR-"&TEXT(ROW()-5,"000")))
A20: =IF(B20="","",IF(COUNTA($A$6:A20)=0,"ALR-"&TEXT(COUNTA($B$6:B20),"000"),"ALR-"&TEXT(ROW()-5,"000")))
A21: =IF(B21="","",IF(COUNTA($A$6:A21)=0,"ALR-"&TEXT(COUNTA($B$6:B21),"000"),"ALR-"&TEXT(ROW()-5,"000")))
... A115: =IF(B115="","",IF(COUNTA($A$6:A115)=0,"ALR-"&TEXT(COUNTA($B$6:B115),"000"),"ALR-"&TEXT(ROW()-5,"000")))

Sheet F13 - 11-Newsletter Publicat.
A2: 11-NEWSLETTER ET PUBLICATIONS
A3: TABLEAU DYNAMIQUE — Saisissez dans la zone prévue ci-dessous
A5: Code Newsletter | B5: Titre | C5: Date Parution | D5: Périodicité | E5: Nb Pages | F5: Nb Destinataires | G5: Taux Ouverture (%) | H5: Taux Clic (%) | I5: Rédacteur | J5: Statut | K5: Thème Principal | L5: Observations
A6: =IF(B6="","",IF(COUNTA($A$6:A6)=0,"NWL-"&TEXT(COUNTA($B$6:B6),"000"),"NWL-"&TEXT(ROW()-5,"000"))) | B6: L'Essentiel - Janvier 2025 | C6: 45672 | D6: Mensuelle | E6: 4 | F6: 63 | G6: 68 | H6: 12 | I6: Resp. Marketing | J6: Diffusé | K6: Bilan 2024 et objectifs 2025 | L6: Record d'ouverture | M6: =IF(OR(G6="",H6=""),"",IFERROR(H6/G6*100,0)) | N6: =IF(G6="","",IF(G6>=65,"Excellente",IF(G6>=55,"Bonne",IF(G6>=45,"Correcte","Faible"))))
A7: =IF(B7="","",IF(COUNTA($A$6:A7)=0,"NWL-"&TEXT(COUNTA($B$6:B7),"000"),"NWL-"&TEXT(ROW()-5,"000"))) | B7: L'Essentiel - Février 2025 | C7: 45703 | D7: Mensuelle | E7: 3 | F7: 64 | G7: 62 | H7: 10 | I7: Resp. Marketing | J7: Diffusé | K7: Célébrations succès équipe | M7: =IF(OR(G7="",H7=""),"",IFERROR(H7/G7*100,0)) | N7: =IF(G7="","",IF(G7>=65,"Excellente",IF(G7>=55,"Bonne",IF(G7>=45,"Correcte","Faible"))))
A8: =IF(B8="","",IF(COUNTA($A$6:A8)=0,"NWL-"&TEXT(COUNTA($B$6:B8),"000"),"NWL-"&TEXT(ROW()-5,"000"))) | B8: L'Essentiel - Mars 2025 | C8: 45731 | D8: Mensuelle | E8: 4 | F8: 65 | I8: Resp. Marketing | J8: En revue | K8: Journée internationale de la femme | L8: Dossier spécial prévu | M8: =IF(OR(G8="",H8=""),"",IFERROR(H8/G8*100,0)) | N8: =IF(G8="","",IF(G8>=65,"Excellente",IF(G8>=55,"Bonne",IF(G8>=45,"Correcte","Faible"))))
A9: =IF(B9="","",IF(COUNTA($A$6:A9)=0,"NWL-"&TEXT(COUNTA($B$6:B9),"000"),"NWL-"&TEXT(ROW()-5,"000"))) | B9: L'Essentiel - Avril 2025 | D9: Mensuelle | I9: Resp. Marketing | J9: Brouillon | K9: QVT et bien-être au travail | M9: =IF(OR(G9="",H9=""),"",IFERROR(H9/G9*100,0)) | N9: =IF(G9="","",IF(G9>=65,"Excellente",IF(G9>=55,"Bonne",IF(G9>=45,"Correcte","Faible"))))
A10: =IF(B10="","",IF(COUNTA($A$6:A10)=0,"NWL-"&TEXT(COUNTA($B$6:B10),"000"),"NWL-"&TEXT(ROW()-5,"000"))) | M10: =IF(OR(G10="",H10=""),"",IFERROR(H10/G10*100,0)) | N10: =IF(G10="","",IF(G10>=65,"Excellente",IF(G10>=55,"Bonne",IF(G10>=45,"Correcte","Faible"))))
A11: =IF(B11="","",IF(COUNTA($A$6:A11)=0,"NWL-"&TEXT(COUNTA($B$6:B11),"000"),"NWL-"&TEXT(ROW()-5,"000"))) | M11: =IF(OR(G11="",H11=""),"",IFERROR(H11/G11*100,0)) | N11: =IF(G11="","",IF(G11>=65,"Excellente",IF(G11>=55,"Bonne",IF(G11>=45,"Correcte","Faible"))))
A12: =IF(B12="","",IF(COUNTA($A$6:A12)=0,"NWL-"&TEXT(COUNTA($B$6:B12),"000"),"NWL-"&TEXT(ROW()-5,"000"))) | M12: =IF(OR(G12="",H12=""),"",IFERROR(H12/G12*100,0)) | N12: =IF(G12="","",IF(G12>=65,"Excellente",IF(G12>=55,"Bonne",IF(G12>=45,"Correcte","Faible"))))
A13: =IF(B13="","",IF(COUNTA($A$6:A13)=0,"NWL-"&TEXT(COUNTA($B$6:B13),"000"),"NWL-"&TEXT(ROW()-5,"000"))) | M13: =IF(OR(G13="",H13=""),"",IFERROR(H13/G13*100,0)) | N13: =IF(G13="","",IF(G13>=65,"Excellente",IF(G13>=55,"Bonne",IF(G13>=45,"Correcte","Faible"))))
A14: =IF(B14="","",IF(COUNTA($A$6:A14)=0,"NWL-"&TEXT(COUNTA($B$6:B14),"000"),"NWL-"&TEXT(ROW()-5,"000"))) | M14: =IF(OR(G14="",H14=""),"",IFERROR(H14/G14*100,0)) | N14: =IF(G14="","",IF(G14>=65,"Excellente",IF(G14>=55,"Bonne",IF(G14>=45,"Correcte","Faible"))))
A15: =IF(B15="","",IF(COUNTA($A$6:A15)=0,"NWL-"&TEXT(COUNTA($B$6:B15),"000"),"NWL-"&TEXT(ROW()-5,"000"))) | M15: =IF(OR(G15="",H15=""),"",IFERROR(H15/G15*100,0)) | N15: =IF(G15="","",IF(G15>=65,"Excellente",IF(G15>=55,"Bonne",IF(G15>=45,"Correcte","Faible"))))
A16: =IF(B16="","",IF(COUNTA($A$6:A16)=0,"NWL-"&TEXT(COUNTA($B$6:B16),"000"),"NWL-"&TEXT(ROW()-5,"000"))) | M16: =IF(OR(G16="",H16=""),"",IFERROR(H16/G16*100,0)) | N16: =IF(G16="","",IF(G16>=65,"Excellente",IF(G16>=55,"Bonne",IF(G16>=45,"Correcte","Faible"))))
A17: =IF(B17="","",IF(COUNTA($A$6:A17)=0,"NWL-"&TEXT(COUNTA($B$6:B17),"000"),"NWL-"&TEXT(ROW()-5,"000"))) | M17: =IF(OR(G17="",H17=""),"",IFERROR(H17/G17*100,0)) | N17: =IF(G17="","",IF(G17>=65,"Excellente",IF(G17>=55,"Bonne",IF(G17>=45,"Correcte","Faible"))))
A18: =IF(B18="","",IF(COUNTA($A$6:A18)=0,"NWL-"&TEXT(COUNTA($B$6:B18),"000"),"NWL-"&TEXT(ROW()-5,"000"))) | M18: =IF(OR(G18="",H18=""),"",IFERROR(H18/G18*100,0)) | N18: =IF(G18="","",IF(G18>=65,"Excellente",IF(G18>=55,"Bonne",IF(G18>=45,"Correcte","Faible"))))
A19: =IF(B19="","",IF(COUNTA($A$6:A19)=0,"NWL-"&TEXT(COUNTA($B$6:B19),"000"),"NWL-"&TEXT(ROW()-5,"000"))) | M19: =IF(OR(G19="",H19=""),"",IFERROR(H19/G19*100,0)) | N19: =IF(G19="","",IF(G19>=65,"Excellente",IF(G19>=55,"Bonne",IF(G19>=45,"Correcte","Faible"))))
A20: =IF(B20="","",IF(COUNTA($A$6:A20)=0,"NWL-"&TEXT(COUNTA($B$6:B20),"000"),"NWL-"&TEXT(ROW()-5,"000"))) | M20: =IF(OR(G20="",H20=""),"",IFERROR(H20/G20*100,0)) | N20: =IF(G20="","",IF(G20>=65,"Excellente",IF(G20>=55,"Bonne",IF(G20>=45,"Correcte","Faible"))))
A21: =IF(B21="","",IF(COUNTA($A$6:A21)=0,"NWL-"&TEXT(COUNTA($B$6:B21),"000"),"NWL-"&TEXT(ROW()-5,"000"))) | M21: =IF(OR(G21="",H21=""),"",IFERROR(H21/G21*100,0)) | N21: =IF(G21="","",IF(G21>=65,"Excellente",IF(G21>=55,"Bonne",IF(G21>=45,"Correcte","Faible"))))
... A115: =IF(B115="","",IF(COUNTA($A$6:A115)=0,"NWL-"&TEXT(COUNTA($B$6:B115),"000"),"NWL-"&TEXT(ROW()-5,"000"))) | M115: =IF(OR(G115="",H115=""),"",IFERROR(H115/G115*100,0)) | N115: =IF(G115="","",IF(G115>=65,"Excellente",IF(G115>=55,"Bonne",IF(G115>=45,"Correcte","Faible"))))

Sheet F14 - 12-Comité Vie Sociale
A2: 12-COMITÉ DE VIE SOCIALE (CVS)
A3: TABLEAU DYNAMIQUE — Saisissez dans la zone prévue ci-dessous
A5: Code Réunion | B5: Date Réunion | C5: Type Réunion | D5: Nb Participants | E5: Ordre du Jour | F5: Décisions Prises | G5: Actions à Suivre | H5: Budget Discuté (FCFA) | I5: Prochaine Réunion | J5: Observations
A6: =IF(B6="","",IF(COUNTA($A$6:A6)=0,"CVS-"&TEXT(COUNTA($B$6:B6),"000"),"CVS-"&TEXT(ROW()-5,"000"))) | B6: 45677 | C6: Ordinaire | D6: 12 | E6: Bilan activités sociales Q4 2024, budget 2025 | F6: Validation budget 2M FCFA, 4 événements Q1 | G6: Programmer soirée iftar, préparer tournoi sport | H6: 500000 | I6: 45708 | J6: Quorum atteint, vote unanime | L6: =IF(B6="","",IFERROR(H6/1000000*100,0)) | M6: =IF(I6="","",IFERROR(I6-B6,0))
A7: =IF(B7="","",IF(COUNTA($A$6:A7)=0,"CVS-"&TEXT(COUNTA($B$6:B7),"000"),"CVS-"&TEXT(ROW()-5,"000"))) | B7: 45708 | C7: Extraordinaire | D7: 10 | E7: Aménagement espace repos, demande équipe cuisine | F7: Validation aménagement espace repos | G7: Demander devis travaux, prévoir inauguration mars | H7: 500000 | I7: 45736 | J7: Réunion urgente suite demande | L7: =IF(B7="","",IFERROR(H7/1000000*100,0)) | M7: =IF(I7="","",IFERROR(I7-B7,0))
A8: =IF(B8="","",IF(COUNTA($A$6:A8)=0,"CVS-"&TEXT(COUNTA($B$6:B8),"000"),"CVS-"&TEXT(ROW()-5,"000"))) | B8: 45736 | C8: Ordinaire | D8: 11 | E8: Bilan Q1, organisation fête fin d'année scolaire | F8: Validation fête scolaire, budget sorties famille | G8: Organiser sortie famille avril, réserver lieu | H8: 300000 | I8: 45767 | L8: =IF(B8="","",IFERROR(H8/1000000*100,0)) | M8: =IF(I8="","",IFERROR(I8-B8,0))
A9: =IF(B9="","",IF(COUNTA($A$6:A9)=0,"CVS-"&TEXT(COUNTA($B$6:B9),"000"),"CVS-"&TEXT(ROW()-5,"000"))) | L9: =IF(B9="","",IFERROR(H9/1000000*100,0)) | M9: =IF(I9="","",IFERROR(I9-B9,0))
A10: =IF(B10="","",IF(COUNTA($A$6:A10)=0,"CVS-"&TEXT(COUNTA($B$6:B10),"000"),"CVS-"&TEXT(ROW()-5,"000"))) | L10: =IF(B10="","",IFERROR(H10/1000000*100,0)) | M10: =IF(I10="","",IFERROR(I10-B10,0))
A11: =IF(B11="","",IF(COUNTA($A$6:A11)=0,"CVS-"&TEXT(COUNTA($B$6:B11),"000"),"CVS-"&TEXT(ROW()-5,"000"))) | L11: =IF(B11="","",IFERROR(H11/1000000*100,0)) | M11: =IF(I11="","",IFERROR(I11-B11,0))
A12: =IF(B12="","",IF(COUNTA($A$6:A12)=0,"CVS-"&TEXT(COUNTA($B$6:B12),"000"),"CVS-"&TEXT(ROW()-5,"000"))) | L12: =IF(B12="","",IFERROR(H12/1000000*100,0)) | M12: =IF(I12="","",IFERROR(I12-B12,0))
A13: =IF(B13="","",IF(COUNTA($A$6:A13)=0,"CVS-"&TEXT(COUNTA($B$6:B13),"000"),"CVS-"&TEXT(ROW()-5,"000"))) | L13: =IF(B13="","",IFERROR(H13/1000000*100,0)) | M13: =IF(I13="","",IFERROR(I13-B13,0))
A14: =IF(B14="","",IF(COUNTA($A$6:A14)=0,"CVS-"&TEXT(COUNTA($B$6:B14),"000"),"CVS-"&TEXT(ROW()-5,"000"))) | L14: =IF(B14="","",IFERROR(H14/1000000*100,0)) | M14: =IF(I14="","",IFERROR(I14-B14,0))
A15: =IF(B15="","",IF(COUNTA($A$6:A15)=0,"CVS-"&TEXT(COUNTA($B$6:B15),"000"),"CVS-"&TEXT(ROW()-5,"000"))) | L15: =IF(B15="","",IFERROR(H15/1000000*100,0)) | M15: =IF(I15="","",IFERROR(I15-B15,0))
A16: =IF(B16="","",IF(COUNTA($A$6:A16)=0,"CVS-"&TEXT(COUNTA($B$6:B16),"000"),"CVS-"&TEXT(ROW()-5,"000"))) | L16: =IF(B16="","",IFERROR(H16/1000000*100,0)) | M16: =IF(I16="","",IFERROR(I16-B16,0))
A17: =IF(B17="","",IF(COUNTA($A$6:A17)=0,"CVS-"&TEXT(COUNTA($B$6:B17),"000"),"CVS-"&TEXT(ROW()-5,"000"))) | L17: =IF(B17="","",IFERROR(H17/1000000*100,0)) | M17: =IF(I17="","",IFERROR(I17-B17,0))
A18: =IF(B18="","",IF(COUNTA($A$6:A18)=0,"CVS-"&TEXT(COUNTA($B$6:B18),"000"),"CVS-"&TEXT(ROW()-5,"000"))) | L18: =IF(B18="","",IFERROR(H18/1000000*100,0)) | M18: =IF(I18="","",IFERROR(I18-B18,0))
A19: =IF(B19="","",IF(COUNTA($A$6:A19)=0,"CVS-"&TEXT(COUNTA($B$6:B19),"000"),"CVS-"&TEXT(ROW()-5,"000"))) | L19: =IF(B19="","",IFERROR(H19/1000000*100,0)) | M19: =IF(I19="","",IFERROR(I19-B19,0))
A20: =IF(B20="","",IF(COUNTA($A$6:A20)=0,"CVS-"&TEXT(COUNTA($B$6:B20),"000"),"CVS-"&TEXT(ROW()-5,"000"))) | L20: =IF(B20="","",IFERROR(H20/1000000*100,0)) | M20: =IF(I20="","",IFERROR(I20-B20,0))
... A115: =IF(B115="","",IF(COUNTA($A$6:A115)=0,"CVS-"&TEXT(COUNTA($B$6:B115),"000"),"CVS-"&TEXT(ROW()-5,"000"))) | L115: =IF(B115="","",IFERROR(H115/1000000*100,0)) | M115: =IF(I115="","",IFERROR(I115-B115,0))

Sheet F15 - 13-Budget Communication
A2: 13-BUDGET COMMUNICATION INTERNE
A3: TABLEAU DYNAMIQUE — Saisissez dans la zone prévue ci-dessous
A5: Poste Budgétaire | B5: Trimestre | C5: Budget Prévu (FCFA) | D5: Dépenses Réalisées (FCFA) | E5: Engagé (FCFA) | F5: Reste à Engager (FCFA) | G5: Taux Consommation (%) | H5: Écart (FCFA) | I5: Observations
A6: Événements internes | B6: T1 2025 | C6: 400000 | F6: =IF(C6="","",C6-IFERROR(D6+E6,0)) | G6: =IF(C6="","",IFERROR((D6+E6)/C6*100,0)) | H6: =IF(C6="","",C6-IFERROR(D6+E6,0)) | I6: Kick-off, tournoi, atelier cuisine
A7: Événements internes | B7: T2 2025 | C7: 450000 | F7: =IF(C7="","",C7-IFERROR(D7+E7,0)) | G7: =IF(C7="","",IFERROR((D7+E7)/C7*100,0)) | H7: =IF(C7="","",C7-IFERROR(D7+E7,0)) | I7: Team building, journée bien-être
A8: Événements internes | B8: T3 2025 | C8: 350000 | F8: =IF(C8="","",C8-IFERROR(D8+E8,0)) | G8: =IF(C8="","",IFERROR((D8+E8)/C8*100,0)) | H8: =IF(C8="","",C8-IFERROR(D8+E8,0)) | I8: Basse saison, événements réduits
A9: Événements internes | B9: T4 2025 | C9: 500000 | F9: =IF(C9="","",C9-IFERROR(D9+E9,0)) | G9: =IF(C9="","",IFERROR((D9+E9)/C9*100,0)) | H9: =IF(C9="","",C9-IFERROR(D9+E9,0)) | I9: Fête de fin d'année
A10: Newsletter | B10: T1 2025 | C10: 30000 | F10: =IF(C10="","",C10-IFERROR(D10+E10,0)) | G10: =IF(C10="","",IFERROR((D10+E10)/C10*100,0)) | H10: =IF(C10="","",C10-IFERROR(D10+E10,0)) | I10: 3 numéros T1
A11: Newsletter | B11: T2 2025 | C11: 30000 | F11: =IF(C11="","",C11-IFERROR(D11+E11,0)) | G11: =IF(C11="","",IFERROR((D11+E11)/C11*100,0)) | H11: =IF(C11="","",C11-IFERROR(D11+E11,0)) | I11: 3 numéros T2
A12: Intranet et digital | B12: T1 2025 | C12: 100000 | F12: =IF(C12="","",C12-IFERROR(D12+E12,0)) | G12: =IF(C12="","",IFERROR((D12+E12)/C12*100,0)) | H12: =IF(C12="","",C12-IFERROR(D12+E12,0)) | I12: Maintenance + tablettes digitales
A13: Intranet et digital | B13: T2 2025 | C13: 150000 | F13: =IF(C13="","",C13-IFERROR(D13+E13,0)) | G13: =IF(C13="","",IFERROR((D13+E13)/C13*100,0)) | H13: =IF(C13="","",C13-IFERROR(D13+E13,0)) | I13: Refonte intranet
A14: Reconnaissance | B14: T1 2025 | C14: 150000 | F14: =IF(C14="","",C14-IFERROR(D14+E14,0)) | G14: =IF(C14="","",IFERROR((D14+E14)/C14*100,0)) | H14: =IF(C14="","",C14-IFERROR(D14+E14,0)) | I14: Prix mensuel + cadeaux
A15: Reconnaissance | B15: T2 2025 | C15: 150000 | F15: =IF(C15="","",C15-IFERROR(D15+E15,0)) | G15: =IF(C15="","",IFERROR((D15+E15)/C15*100,0)) | H15: =IF(C15="","",C15-IFERROR(D15+E15,0)) | I15: Programme recon. continué
A16: Formation communication | B16: T1 2025 | C16: 80000 | F16: =IF(C16="","",C16-IFERROR(D16+E16,0)) | G16: =IF(C16="","",IFERROR((D16+E16)/C16*100,0)) | H16: =IF(C16="","",C16-IFERROR(D16+E16,0)) | I16: Formation management
A17: Divers et imprévus | B17: T1 2025 | C17: 50000 | F17: =IF(C17="","",C17-IFERROR(D17+E17,0)) | G17: =IF(C17="","",IFERROR((D17+E17)/C17*100,0)) | H17: =IF(C17="","",C17-IFERROR(D17+E17,0)) | I17: Marge de sécurité
F18: =IF(C18="","",C18-IFERROR(D18+E18,0)) | G18: =IF(C18="","",IFERROR((D18+E18)/C18*100,0)) | H18: =IF(C18="","",C18-IFERROR(D18+E18,0))
F19: =IF(C19="","",C19-IFERROR(D19+E19,0)) | G19: =IF(C19="","",IFERROR((D19+E19)/C19*100,0)) | H19: =IF(C19="","",C19-IFERROR(D19+E19,0))
F20: =IF(C20="","",C20-IFERROR(D20+E20,0)) | G20: =IF(C20="","",IFERROR((D20+E20)/C20*100,0)) | H20: =IF(C20="","",C20-IFERROR(D20+E20,0))
F21: =IF(C21="","",C21-IFERROR(D21+E21,0)) | G21: =IF(C21="","",IFERROR((D21+E21)/C21*100,0)) | H21: =IF(C21="","",C21-IFERROR(D21+E21,0))
F22: =IF(C22="","",C22-IFERROR(D22+E22,0)) | G22: =IF(C22="","",IFERROR((D22+E22)/C22*100,0)) | H22: =IF(C22="","",C22-IFERROR(D22+E22,0))
F23: =IF(C23="","",C23-IFERROR(D23+E23,0)) | G23: =IF(C23="","",IFERROR((D23+E23)/C23*100,0)) | H23: =IF(C23="","",C23-IFERROR(D23+E23,0))
F24: =IF(C24="","",C24-IFERROR(D24+E24,0)) | G24: =IF(C24="","",IFERROR((D24+E24)/C24*100,0)) | H24: =IF(C24="","",C24-IFERROR(D24+E24,0))
F25: =IF(C25="","",C25-IFERROR(D25+E25,0)) | G25: =IF(C25="","",IFERROR((D25+E25)/C25*100,0)) | H25: =IF(C25="","",C25-IFERROR(D25+E25,0))
F26: =IF(C26="","",C26-IFERROR(D26+E26,0)) | G26: =IF(C26="","",IFERROR((D26+E26)/C26*100,0)) | H26: =IF(C26="","",C26-IFERROR(D26+E26,0))
F27: =IF(C27="","",C27-IFERROR(D27+E27,0)) | G27: =IF(C27="","",IFERROR((D27+E27)/C27*100,0)) | H27: =IF(C27="","",C27-IFERROR(D27+E27,0))
F28: =IF(C28="","",C28-IFERROR(D28+E28,0)) | G28: =IF(C28="","",IFERROR((D28+E28)/C28*100,0)) | H28: =IF(C28="","",C28-IFERROR(D28+E28,0))
F29: =IF(C29="","",C29-IFERROR(D29+E29,0)) | G29: =IF(C29="","",IFERROR((D29+E29)/C29*100,0)) | H29: =IF(C29="","",C29-IFERROR(D29+E29,0))
... F115: =IF(C115="","",C115-IFERROR(D115+E115,0)) | G115: =IF(C115="","",IFERROR((D115+E115)/C115*100,0)) | H115: =IF(C115="","",C115-IFERROR(D115+E115,0))

Sheet F16 - 14-Matrice Engag.×Dép.
A2: 14-MATRICE ENGAGEMENT × DÉPARTEMENTS
A3: TABLEAU DYNAMIQUE — Saisissez dans la zone prévue ci-dessous
A5: Département | B5: Moy. Année | C5: Janv. | D5: Fév. | E5: Mars | F5: Avr. | G5: Mai | H5: Juin | I5: Juil. | J5: Août | K5: Sept. | L5: Oct. | M5: Nov. | N5: Déc.
A6: Direction Générale | B6: =IFERROR(AVERAGE(C6:N6),0) | C6: 82 | D6: 82 | E6: 83 | F6: 83 | G6: 84 | H6: 84 | I6: 85 | J6: 85 | K6: 85 | L6: 86 | M6: 86 | N6: 87
A7: Ressources Humaines | B7: =IFERROR(AVERAGE(C7:N7),0) | C7: 80 | D7: 80 | E7: 81 | F7: 81 | G7: 82 | H7: 82 | I7: 83 | J7: 83 | K7: 83 | L7: 84 | M7: 84 | N7: 85
A8: Finance & Comptabilité | B8: =IFERROR(AVERAGE(C8:N8),0) | C8: 66 | D8: 66 | E8: 67 | F8: 67 | G8: 68 | H8: 68 | I8: 69 | J8: 69 | K8: 70 | L8: 70 | M8: 71 | N8: 71
A9: Marketing & Communication | B9: =IFERROR(AVERAGE(C9:N9),0) | C9: 70 | D9: 70 | E9: 71 | F9: 72 | G9: 72 | H9: 73 | I9: 73 | J9: 74 | K9: 74 | L9: 75 | M9: 75 | N9: 76
A10: Informatique | B10: =IFERROR(AVERAGE(C10:N10),0) | C10: 84 | D10: 84 | E10: 85 | F10: 85 | G10: 86 | H10: 86 | I10: 85 | J10: 85 | K10: 86 | L10: 87 | M10: 87 | N10: 88
A11: Commercial | B11: =IFERROR(AVERAGE(C11:N11),0) | C11: 73 | D11: 73 | E11: 74 | F11: 74 | G11: 75 | H11: 75 | I11: 76 | J11: 76 | K11: 76 | L11: 77 | M11: 77 | N11: 78
A12: Logistique & Approvisionnement | B12: =IFERROR(AVERAGE(C12:N12),0) | C12: 60 | D12: 60 | E12: 61 | F12: 61 | G12: 62 | H12: 62 | I12: 63 | J12: 63 | K12: 64 | L12: 64 | M12: 65 | N12: 65
A13: Réception & Front Office | B13: =IFERROR(AVERAGE(C13:N13),0) | C13: 88 | D13: 88 | E13: 89 | F13: 89 | G13: 90 | H13: 90 | I13: 91 | J13: 91 | K13: 91 | L13: 92 | M13: 92 | N13: 93
A14: Cuisine & Restauration | B14: =IFERROR(AVERAGE(C14:N14),0) | C14: 76 | D14: 77 | E14: 78 | F14: 79 | G14: 80 | H14: 81 | I14: 80 | J14: 79 | K14: 80 | L14: 81 | M14: 82 | N14: 83
A15: Hébergement | B15: =IFERROR(AVERAGE(C15:N15),0) | C15: 86 | D15: 86 | E15: 87 | F15: 87 | G15: 88 | H15: 88 | I15: 89 | J15: 89 | K15: 89 | L15: 90 | M15: 90 | N15: 91
A16: Entretien & Maintenance | B16: =IFERROR(AVERAGE(C16:N16),0) | C16: 52 | D16: 52 | E16: 53 | F16: 54 | G16: 55 | H16: 56 | I16: 56 | J16: 57 | K16: 58 | L16: 59 | M16: 60 | N16: 60
A17: Sécurité | B17: =IFERROR(AVERAGE(C17:N17),0) | C17: 58 | D17: 58 | E17: 59 | F17: 59 | G17: 60 | H17: 60 | I17: 61 | J17: 61 | K17: 62 | L17: 62 | M17: 63 | N17: 63
... A20: Spa & Bien-être | B20: =IFERROR(AVERAGE(C20:N20),0) | C20: 82 | D20: 82 | E20: 83 | F20: 83 | G20: 84 | H20: 84 | I20: 85 | J20: 85 | K20: 85 | L20: 86 | M20: 86 | N20: 87
A21: MOYENNE GÉNÉRALE | B21: =IFERROR(AVERAGE(B6:B20),0) | C21: =IFERROR(AVERAGE(C6:C20),0) | D21: =IFERROR(AVERAGE(D6:D20),0) | E21: =IFERROR(AVERAGE(E6:E20),0) | F21: =IFERROR(AVERAGE(F6:F20),0) | G21: =IFERROR(AVERAGE(G6:G20),0) | H21: =IFERROR(AVERAGE(H6:H20),0) | I21: =IFERROR(AVERAGE(I6:I20),0) | ... N21: =IFERROR(AVERAGE(N6:N20),0)

Sheet F17 - 15-Historique Enquêtes
A2: 15-HISTORIQUE DES ENQUÊTES
A3: TABLEAU DYNAMIQUE — Saisissez dans la zone prévue ci-dessous
A5: Enquête | B5: Département | C5: Période | D5: Date | E5: Score Global (/5) | F5: Score Communication (/5) | G5: Score Management (/5) | H5: Score QVT (/5) | I5: Nb Répondants | J5: Observations
A6: Engagement Q4 2024 | B6: Tous | C6: T4 2024 | D6: 45580 | E6: 3.9 | F6: 3.5 | G6: 4 | H6: 3.8 | I6: 58 | J6: Première enquête de référence | K6: =IF(E6="","",IFERROR(AVERAGE(E6:H6),0)) | L6: =IF(E6="","",IFERROR(E6-J6,0)) | M6: =IF(OR(E6="",C6="T4 2024"),"",IF(E6>4.0,"Positif",IF(E6>=3.5,"Neutre","Négatif"))) | N6: =IF(E6="","",IF(E6>=4.5,"Excellent",IF(E6>=4.0,"Très bon",IF(E6>=3.5,"Bon",IF(E6>=3.0,"Correct","Insuffisant")))))
A7: Engagement Q4 2024 | B7: Cuisine & Restauration | C7: T4 2024 | D7: 45580 | E7: 3.7 | F7: 3.2 | G7: 3.8 | H7: 3.5 | I7: 12 | J7: Score communication faible | K7: =IF(E7="","",IFERROR(AVERAGE(E7:H7),0)) | L7: =IF(E7="","",IFERROR(E7-J7,0)) | M7: =IF(OR(E7="",C7="T4 2024"),"",IF(E7>4.0,"Positif",IF(E7>=3.5,"Neutre","Négatif"))) | N7: =IF(E7="","",IF(E7>=4.5,"Excellent",IF(E7>=4.0,"Très bon",IF(E7>=3.5,"Bon",IF(E7>=3.0,"Correct","Insuffisant")))))
A8: Engagement Q4 2024 | B8: Réception & Front Office | C8: T4 2024 | D8: 45580 | E8: 4.4 | F8: 4.2 | G8: 4.5 | H8: 4.3 | I8: 8 | J8: Excellents résultats | K8: =IF(E8="","",IFERROR(AVERAGE(E8:H8),0)) | L8: =IF(E8="","",IFERROR(E8-J8,0)) | M8: =IF(OR(E8="",C8="T4 2024"),"",IF(E8>4.0,"Positif",IF(E8>=3.5,"Neutre","Négatif"))) | N8: =IF(E8="","",IF(E8>=4.5,"Excellent",IF(E8>=4.0,"Très bon",IF(E8>=3.5,"Bon",IF(E8>=3.0,"Correct","Insuffisant")))))
A9: Engagement Q1 2025 | B9: Tous | C9: T1 2025 | D9: 45672 | E9: 4.1 | F9: 3.8 | G9: 4.2 | H9: 4 | I9: 57 | J9: Hausse générale +0.2 | K9: =IF(E9="","",IFERROR(AVERAGE(E9:H9),0)) | L9: =IF(E9="","",IFERROR(E9-J9,0)) | M9: =IF(OR(E9="",C9="T4 2024"),"",IF(E9>4.0,"Positif",IF(E9>=3.5,"Neutre","Négatif"))) | N9: =IF(E9="","",IF(E9>=4.5,"Excellent",IF(E9>=4.0,"Très bon",IF(E9>=3.5,"Bon",IF(E9>=3.0,"Correct","Insuffisant")))))
A10: Satisfaction Q1 2025 | B10: Tous | C10: T1 2025 | D10: 45689 | E10: 3.8 | F10: 3.4 | G10: 3.9 | H10: 3.7 | I10: 52 | J10: Communication interne en amélioration | K10: =IF(E10="","",IFERROR(AVERAGE(E10:H10),0)) | L10: =IF(E10="","",IFERROR(E10-J10,0)) | M10: =IF(OR(E10="",C10="T4 2024"),"",IF(E10>4.0,"Positif",IF(E10>=3.5,"Neutre","Négatif"))) | N10: =IF(E10="","",IF(E10>=4.5,"Excellent",IF(E10>=4.0,"Très bon",IF(E10>=3.5,"Bon",IF(E10>=3.0,"Correct","Insuffisant")))))
A11: Communication Q1 2025 | B11: Tous | C11: T1 2025 | D11: 45717 | E11: 3.5 | F11: 3.5 | G11: 3.7 | H11: 3.3 | I11: 48 | J11: Canal intranet très apprécié | K11: =IF(E11="","",IFERROR(AVERAGE(E11:H11),0)) | L11: =IF(E11="","",IFERROR(E11-J11,0)) | M11: =IF(OR(E11="",C11="T4 2024"),"",IF(E11>4.0,"Positif",IF(E11>=3.5,"Neutre","Négatif"))) | N11: =IF(E11="","",IF(E11>=4.5,"Excellent",IF(E11>=4.0,"Très bon",IF(E11>=3.5,"Bon",IF(E11>=3.0,"Correct","Insuffisant")))))
K12: =IF(E12="","",IFERROR(AVERAGE(E12:H12),0)) | L12: =IF(E12="","",IFERROR(E12-J12,0)) | M12: =IF(OR(E12="",C12="T4 2024"),"",IF(E12>4.0,"Positif",IF(E12>=3.5,"Neutre","Négatif"))) | N12: =IF(E12="","",IF(E12>=4.5,"Excellent",IF(E12>=4.0,"Très bon",IF(E12>=3.5,"Bon",IF(E12>=3.0,"Correct","Insuffisant")))))
K13: =IF(E13="","",IFERROR(AVERAGE(E13:H13),0)) | L13: =IF(E13="","",IFERROR(E13-J13,0)) | M13: =IF(OR(E13="",C13="T4 2024"),"",IF(E13>4.0,"Positif",IF(E13>=3.5,"Neutre","Négatif"))) | N13: =IF(E13="","",IF(E13>=4.5,"Excellent",IF(E13>=4.0,"Très bon",IF(E13>=3.5,"Bon",IF(E13>=3.0,"Correct","Insuffisant")))))
K14: =IF(E14="","",IFERROR(AVERAGE(E14:H14),0)) | L14: =IF(E14="","",IFERROR(E14-J14,0)) | M14: =IF(OR(E14="",C14="T4 2024"),"",IF(E14>4.0,"Positif",IF(E14>=3.5,"Neutre","Négatif"))) | N14: =IF(E14="","",IF(E14>=4.5,"Excellent",IF(E14>=4.0,"Très bon",IF(E14>=3.5,"Bon",IF(E14>=3.0,"Correct","Insuffisant")))))
K15: =IF(E15="","",IFERROR(AVERAGE(E15:H15),0)) | L15: =IF(E15="","",IFERROR(E15-J15,0)) | M15: =IF(OR(E15="",C15="T4 2024"),"",IF(E15>4.0,"Positif",IF(E15>=3.5,"Neutre","Négatif"))) | N15: =IF(E15="","",IF(E15>=4.5,"Excellent",IF(E15>=4.0,"Très bon",IF(E15>=3.5,"Bon",IF(E15>=3.0,"Correct","Insuffisant")))))
K16: =IF(E16="","",IFERROR(AVERAGE(E16:H16),0)) | L16: =IF(E16="","",IFERROR(E16-J16,0)) | M16: =IF(OR(E16="",C16="T4 2024"),"",IF(E16>4.0,"Positif",IF(E16>=3.5,"Neutre","Négatif"))) | N16: =IF(E16="","",IF(E16>=4.5,"Excellent",IF(E16>=4.0,"Très bon",IF(E16>=3.5,"Bon",IF(E16>=3.0,"Correct","Insuffisant")))))
K17: =IF(E17="","",IFERROR(AVERAGE(E17:H17),0)) | L17: =IF(E17="","",IFERROR(E17-J17,0)) | M17: =IF(OR(E17="",C17="T4 2024"),"",IF(E17>4.0,"Positif",IF(E17>=3.5,"Neutre","Négatif"))) | N17: =IF(E17="","",IF(E17>=4.5,"Excellent",IF(E17>=4.0,"Très bon",IF(E17>=3.5,"Bon",IF(E17>=3.0,"Correct","Insuffisant")))))
K18: =IF(E18="","",IFERROR(AVERAGE(E18:H18),0)) | L18: =IF(E18="","",IFERROR(E18-J18,0)) | M18: =IF(OR(E18="",C18="T4 2024"),"",IF(E18>4.0,"Positif",IF(E18>=3.5,"Neutre","Négatif"))) | N18: =IF(E18="","",IF(E18>=4.5,"Excellent",IF(E18>=4.0,"Très bon",IF(E18>=3.5,"Bon",IF(E18>=3.0,"Correct","Insuffisant")))))
K19: =IF(E19="","",IFERROR(AVERAGE(E19:H19),0)) | L19: =IF(E19="","",IFERROR(E19-J19,0)) | M19: =IF(OR(E19="",C19="T4 2024"),"",IF(E19>4.0,"Positif",IF(E19>=3.5,"Neutre","Négatif"))) | N19: =IF(E19="","",IF(E19>=4.5,"Excellent",IF(E19>=4.0,"Très bon",IF(E19>=3.5,"Bon",IF(E19>=3.0,"Correct","Insuffisant")))))
K20: =IF(E20="","",IFERROR(AVERAGE(E20:H20),0)) | L20: =IF(E20="","",IFERROR(E20-J20,0)) | M20: =IF(OR(E20="",C20="T4 2024"),"",IF(E20>4.0,"Positif",IF(E20>=3.5,"Neutre","Négatif"))) | N20: =IF(E20="","",IF(E20>=4.5,"Excellent",IF(E20>=4.0,"Très bon",IF(E20>=3.5,"Bon",IF(E20>=3.0,"Correct","Insuffisant")))))
K21: =IF(E21="","",IFERROR(AVERAGE(E21:H21),0)) | L21: =IF(E21="","",IFERROR(E21-J21,0)) | M21: =IF(OR(E21="",C21="T4 2024"),"",IF(E21>4.0,"Positif",IF(E21>=3.5,"Neutre","Négatif"))) | N21: =IF(E21="","",IF(E21>=4.5,"Excellent",IF(E21>=4.0,"Très bon",IF(E21>=3.5,"Bon",IF(E21>=3.0,"Correct","Insuffisant")))))
K22: =IF(E22="","",IFERROR(AVERAGE(E22:H22),0)) | L22: =IF(E22="","",IFERROR(E22-J22,0)) | M22: =IF(OR(E22="",C22="T4 2024"),"",IF(E22>4.0,"Positif",IF(E22>=3.5,"Neutre","Négatif"))) | N22: =IF(E22="","",IF(E22>=4.5,"Excellent",IF(E22>=4.0,"Très bon",IF(E22>=3.5,"Bon",IF(E22>=3.0,"Correct","Insuffisant")))))
K23: =IF(E23="","",IFERROR(AVERAGE(E23:H23),0)) | L23: =IF(E23="","",IFERROR(E23-J23,0)) | M23: =IF(OR(E23="",C23="T4 2024"),"",IF(E23>4.0,"Positif",IF(E23>=3.5,"Neutre","Négatif"))) | N23: =IF(E23="","",IF(E23>=4.5,"Excellent",IF(E23>=4.0,"Très bon",IF(E23>=3.5,"Bon",IF(E23>=3.0,"Correct","Insuffisant")))))
... K115: =IF(E115="","",IFERROR(AVERAGE(E115:H115),0)) | L115: =IF(E115="","",IFERROR(E115-J115,0)) | M115: =IF(OR(E115="",C115="T4 2024"),"",IF(E115>4.0,"Positif",IF(E115>=3.5,"Neutre","Négatif"))) | N115: =IF(E115="","",IF(E115>=4.5,"Excellent",IF(E115>=4.0,"Très bon",IF(E115>=3.5,"Bon",IF(E115>=3.0,"Correct","Insuffisant")))))

Sheet F18 - 16-Calendrier Communic.
A2: 16-CALENDRIER DE COMMUNICATION
A3: TABLEAU DYNAMIQUE — Saisissez dans la zone prévue ci-dessous
A5: Action | B5: Type | C5: Canal | D5: Date Prévue | E5: Jours Restants | F5: Alertes | G5: Responsable | H5: Priorité | I5: Statut | J5: Observations
A6: Enquête engagement Q2 | B6: Enquête | C6: Intranet + Email | D6: 45762 | E6: =IF(D6="","",IFERROR(D6-TODAY(),0)) | F6: =IF(E6="","",IF(E6<7,"URGENT",IF(E6<15,"Attention",IF(E6<30,"À planifier","")))) | G6: DRH | H6: Haute | I6: Planifié | J6: Préparer questionnaire en mars
A7: Newsletter avril | B7: Newsletter | C7: Email | D7: 45748 | E7: =IF(D7="","",IFERROR(D7-TODAY(),0)) | F7: =IF(E7="","",IF(E7<7,"URGENT",IF(E7<15,"Attention",IF(E7<30,"À planifier","")))) | G7: Resp. Marketing | H7: Moyenne | I7: Brouillon | J7: Thème: QVT et bien-être
A8: Team building annuel | B8: Événement | C8: Présentiel | D8: 45823 | E8: =IF(D8="","",IFERROR(D8-TODAY(),0)) | F8: =IF(E8="","",IF(E8<7,"URGENT",IF(E8<15,"Attention",IF(E8<30,"À planifier","")))) | G8: DRH / DG | H8: Haute | I8: Planifié | J8: Lieu à confirmer
A9: Comité CVS Q2 | B9: Réunion | C9: Présentiel | D9: 45767 | E9: =IF(D9="","",IFERROR(D9-TODAY(),0)) | F9: =IF(E9="","",IF(E9<7,"URGENT",IF(E9<15,"Attention",IF(E9<30,"À planifier","")))) | G9: DRH | H9: Moyenne | I9: Planifié | J9: Bilan Q1 et prévisions Q2
A10: Formation management | B10: Formation | C10: Présentiel | D10: 45741 | E10: =IF(D10="","",IFERROR(D10-TODAY(),0)) | F10: =IF(E10="","",IF(E10<7,"URGENT",IF(E10<15,"Attention",IF(E10<30,"À planifier","")))) | G10: DRH / Cabinet | H10: Haute | I10: En cours | J10: 2 jours, 8 managers inscrits
E11: =IF(D11="","",IFERROR(D11-TODAY(),0)) | F11: =IF(E11="","",IF(E11<7,"URGENT",IF(E11<15,"Attention",IF(E11<30,"À planifier",""))))
E12: =IF(D12="","",IFERROR(D12-TODAY(),0)) | F12: =IF(E12="","",IF(E12<7,"URGENT",IF(E12<15,"Attention",IF(E12<30,"À planifier",""))))
E13: =IF(D13="","",IFERROR(D13-TODAY(),0)) | F13: =IF(E13="","",IF(E13<7,"URGENT",IF(E13<15,"Attention",IF(E13<30,"À planifier",""))))
E14: =IF(D14="","",IFERROR(D14-TODAY(),0)) | F14: =IF(E14="","",IF(E14<7,"URGENT",IF(E14<15,"Attention",IF(E14<30,"À planifier",""))))
E15: =IF(D15="","",IFERROR(D15-TODAY(),0)) | F15: =IF(E15="","",IF(E15<7,"URGENT",IF(E15<15,"Attention",IF(E15<30,"À planifier",""))))
E16: =IF(D16="","",IFERROR(D16-TODAY(),0)) | F16: =IF(E16="","",IF(E16<7,"URGENT",IF(E16<15,"Attention",IF(E16<30,"À planifier",""))))
E17: =IF(D17="","",IFERROR(D17-TODAY(),0)) | F17: =IF(E17="","",IF(E17<7,"URGENT",IF(E17<15,"Attention",IF(E17<30,"À planifier",""))))
E18: =IF(D18="","",IFERROR(D18-TODAY(),0)) | F18: =IF(E18="","",IF(E18<7,"URGENT",IF(E18<15,"Attention",IF(E18<30,"À planifier",""))))
E19: =IF(D19="","",IFERROR(D19-TODAY(),0)) | F19: =IF(E19="","",IF(E19<7,"URGENT",IF(E19<15,"Attention",IF(E19<30,"À planifier",""))))
E20: =IF(D20="","",IFERROR(D20-TODAY(),0)) | F20: =IF(E20="","",IF(E20<7,"URGENT",IF(E20<15,"Attention",IF(E20<30,"À planifier",""))))
E21: =IF(D21="","",IFERROR(D21-TODAY(),0)) | F21: =IF(E21="","",IF(E21<7,"URGENT",IF(E21<15,"Attention",IF(E21<30,"À planifier",""))))
E22: =IF(D22="","",IFERROR(D22-TODAY(),0)) | F22: =IF(E22="","",IF(E22<7,"URGENT",IF(E22<15,"Attention",IF(E22<30,"À planifier",""))))
... E115: =IF(D115="","",IFERROR(D115-TODAY(),0)) | F115: =IF(E115="","",IF(E115<7,"URGENT",IF(E115<15,"Attention",IF(E115<30,"À planifier",""))))

Sheet F19 - 17-TdB Financ. Commun.
A2: 17-TABLEAU DE BORD FINANCIER COMMUNICATION
A3: TABLEAU DYNAMIQUE — Saisissez dans la zone prévue ci-dessous
A5: Mois | B5: Événements (FCFA) | C5: Newsletter (FCFA) | D5: Intranet/Digital (FCFA) | E5: Reconnaissance (FCFA) | F5: Formation (FCFA) | G5: Total Coûts (FCFA) | H5: Budget Mensuel (FCFA) | I5: Variance (FCFA) | J5: Taux Réalisation (%) | K5: Observations
A6: Janvier 2025 | B6: 350000 | C6: 10000 | D6: 30000 | E6: 50000 | F6: 0 | G6: =SUM(B6:F6) | H6: 500000 | I6: =IF(H6="","",H6-G6) | J6: =IF(H6="","",IFERROR(G6/H6*100,0)) | K6: Kick-off + newsletter
A7: Février 2025 | B7: 142000 | C7: 10000 | D7: 25000 | E7: 50000 | F7: 0 | G7: =SUM(B7:F7) | H7: 420000 | I7: =IF(H7="","",H7-G7) | J7: =IF(H7="","",IFERROR(G7/H7*100,0)) | K7: Tournoi sportif
A8: Mars 2025 | B8: 278000 | C8: 10000 | D8: 30000 | E8: 50000 | F8: 80000 | G8: =SUM(B8:F8) | H8: 520000 | I8: =IF(H8="","",H8-G8) | J8: =IF(H8="","",IFERROR(G8/H8*100,0)) | K8: Atelier + iftar + formation
A9: Avril 2025 | B9: 0 | C9: 10000 | D9: 35000 | E9: 50000 | F9: 0 | G9: =SUM(B9:F9) | H9: 380000 | I9: =IF(H9="","",H9-G9) | J9: =IF(H9="","",IFERROR(G9/H9*100,0)) | K9: Journée bien-être
A10: Mai 2025 | B10: 150000 | C10: 10000 | D10: 30000 | E10: 50000 | F10: 0 | G10: =SUM(B10:F10) | H10: 400000 | I10: =IF(H10="","",H10-G10) | J10: =IF(H10="","",IFERROR(G10/H10*100,0)) | K10: Sortie famille
A11: Juin 2025 | B11: 400000 | C11: 10000 | D11: 40000 | E11: 50000 | F11: 0 | G11: =SUM(B11:F11) | H11: 650000 | I11: =IF(H11="","",H11-G11) | J11: =IF(H11="","",IFERROR(G11/H11*100,0)) | K11: Team building annuel
A12: Juillet 2025 | B12: 100000 | C12: 10000 | D12: 25000 | E12: 50000 | F12: 0 | G12: =SUM(B12:F12) | H12: 350000 | I12: =IF(H12="","",H12-G12) | J12: =IF(H12="","",IFERROR(G12/H12*100,0)) | K12: Basse saison
A13: Août 2025 | B13: 120000 | C13: 10000 | D13: 25000 | E13: 50000 | F13: 0 | G13: =SUM(B13:F13) | H13: 360000 | I13: =IF(H13="","",H13-G13) | J13: =IF(H13="","",IFERROR(G13/H13*100,0)) | K13: Basse saison
A14: Septembre 2025 | B14: 200000 | C14: 10000 | D14: 30000 | E14: 50000 | F14: 40000 | G14: =SUM(B14:F14) | H14: 480000 | I14: =IF(H14="","",H14-G14) | J14: =IF(H14="","",IFERROR(G14/H14*100,0)) | K14: Rentrée, formation
A15: Octobre 2025 | B15: 180000 | C15: 10000 | D15: 30000 | E15: 50000 | F15: 0 | G15: =SUM(B15:F15) | H15: 430000 | I15: =IF(H15="","",H15-G15) | J15: =IF(H15="","",IFERROR(G15/H15*100,0))
A16: Novembre 2025 | B16: 250000 | C16: 10000 | D16: 35000 | E16: 50000 | F16: 0 | G16: =SUM(B16:F16) | H16: 500000 | I16: =IF(H16="","",H16-G16) | J16: =IF(H16="","",IFERROR(G16/H16*100,0))
A17: Décembre 2025 | B17: 500000 | C17: 15000 | D17: 30000 | E17: 50000 | F17: 0 | G17: =SUM(B17:F17) | H17: 700000 | I17: =IF(H17="","",H17-G17) | J17: =IF(H17="","",IFERROR(G17/H17*100,0)) | K17: Fête de fin d'année

Sheet F20 - 18-Indic. Performance
A2: 18-INDICATEURS DE PERFORMANCE
A3: TABLEAU DYNAMIQUE — Saisissez dans la zone prévue ci-dessous
A5: Code Indicateur | B5: Indicateur | C5: Cible | D5: Valeur Actuelle | E5: Écart | F5: Tendance | G5: Période | H5: Responsable | I5: Commentaire | J5: Observations
A6: COM-01 | B6: Score engagement moyen | C6: ≥80% | D6: 75.6% | E6: =IF(C6="","",C6&" - "&D6) | F6: =IF(D6="","","Stable") | G6: T1 2025 | H6: DRH | I6: En progression constante | K6: =IF(D6="","",IF(OR(D6="87%",D6="100%",D6="62%",D6="18 (proj.)",D6="4.5/5",D6="12 jours",D6="42 (proj.)",D6="3.5/5"),"Atteint",IF(OR(D6="75.6%",D6="8%"),"En progression","En cours")))
A7: COM-02 | B7: Taux participation enquêtes | C7: ≥85% | D7: 87% | E7: =IF(C7="","",C7&" - "&D7) | F7: =IF(D7="","","Stable") | G7: T1 2025 | H7: DRH | I7: Objectif atteint | K7: =IF(D7="","",IF(OR(D7="87%",D7="100%",D7="62%",D7="18 (proj.)",D7="4.5/5",D7="12 jours",D7="42 (proj.)",D7="3.5/5"),"Atteint",IF(OR(D7="75.6%",D7="8%"),"En progression","En cours")))
A8: COM-03 | B8: Taux ouverture newsletter | C8: ≥60% | D8: 62% | E8: =IF(C8="","",C8&" - "&D8) | F8: =IF(D8="","","Stable") | G8: T1 2025 | H8: Resp. Marketing | I8: Léger dépassement cible | K8: =IF(D8="","",IF(OR(D8="87%",D8="100%",D8="62%",D8="18 (proj.)",D8="4.5/5",D8="12 jours",D8="42 (proj.)",D8="3.5/5"),"Atteint",IF(OR(D8="75.6%",D8="8%"),"En progression","En cours")))
A9: COM-04 | B9: Nb événements/an | C9: ≥12 | D9: 18 (proj.) | E9: =IF(C9="","",C9&" - "&D9) | F9: =IF(D9="","","Stable") | G9: 2025 | H9: DRH | I9: Objectif largement dépassé | K9: =IF(D9="","",IF(OR(D9="87%",D9="100%",D9="62%",D9="18 (proj.)",D9="4.5/5",D9="12 jours",D9="42 (proj.)",D9="3.5/5"),"Atteint",IF(OR(D9="75.6%",D9="8%"),"En progression","En cours")))
A10: COM-05 | B10: Taux rotation (communication) | C10: ≤10% | D10: 8% | E10: =IF(C10="","",C10&" - "&D10) | F10: =IF(D10="","","Stable") | G10: T1 2025 | H10: DRH | I10: Baisse par rapport 2024 | K10: =IF(D10="","",IF(OR(D10="87%",D10="100%",D10="62%",D10="18 (proj.)",D10="4.5/5",D10="12 jours",D10="42 (proj.)",D10="3.5/5"),"Atteint",IF(OR(D10="75.6%",D10="8%"),"En progression","En cours")))
A11: COM-06 | B11: Satisfaction événements | C11: ≥4.0/5 | D11: 4.5/5 | E11: =IF(C11="","",C11&" - "&D11) | F11: =IF(D11="","","Stable") | G11: T1 2025 | H11: DRH | I11: Excellente satisfaction | K11: =IF(D11="","",IF(OR(D11="87%",D11="100%",D11="62%",D11="18 (proj.)",D11="4.5/5",D11="12 jours",D11="42 (proj.)",D11="3.5/5"),"Atteint",IF(OR(D11="75.6%",D11="8%"),"En progression","En cours")))
A12: COM-07 | B12: Délai traitement suggestions | C12: ≤15 jours | D12: 12 jours | E12: =IF(C12="","",C12&" - "&D12) | F12: =IF(D12="","","Stable") | G12: T1 2025 | H12: DRH | I12: Délai moyen correct | K12: =IF(D12="","",IF(OR(D12="87%",D12="100%",D12="62%",D12="18 (proj.)",D12="4.5/5",D12="12 jours",D12="42 (proj.)",D12="3.5/5"),"Atteint",IF(OR(D12="75.6%",D12="8%"),"En progression","En cours")))
A13: COM-08 | B13: Budget communication consommé | C13: ±10% | D13: 62% | E13: =IF(C13="","",C13&" - "&D13) | F13: =IF(D13="","","Stable") | G13: T1 2025 | H13: DAF | I13: Dans enveloppe budgétaire | K13: =IF(D13="","",IF(OR(D13="87%",D13="100%",D13="62%",D13="18 (proj.)",D13="4.5/5",D13="12 jours",D13="42 (proj.)",D13="3.5/5"),"Atteint",IF(OR(D13="75.6%",D13="8%"),"En progression","En cours")))
A14: COM-09 | B14: Nb suggestions/an | C14: ≥30 | D14: 42 (proj.) | E14: =IF(C14="","",C14&" - "&D14) | F14: =IF(D14="","","Stable") | G14: 2025 | H14: DRH | I14: Fort engagement collaborateurs | K14: =IF(D14="","",IF(OR(D14="87%",D14="100%",D14="62%",D14="18 (proj.)",D14="4.5/5",D14="12 jours",D14="42 (proj.)",D14="3.5/5"),"Atteint",IF(OR(D14="75.6%",D14="8%"),"En progression","En cours")))
A15: COM-10 | B15: Score communication interne | C15: ≥3.5/5 | D15: 3.5/5 | E15: =IF(C15="","",C15&" - "&D15) | F15: =IF(D15="","","Stable") | G15: T1 2025 | H15: DRH | I15: Objectif atteint, marge de progrès | K15: =IF(D15="","",IF(OR(D15="87%",D15="100%",D15="62%",D15="18 (proj.)",D15="4.5/5",D15="12 jours",D15="42 (proj.)",D15="3.5/5"),"Atteint",IF(OR(D15="75.6%",D15="8%"),"En progression","En cours")))
A16: COM-11 | B16: Nb rumeurs traitées < 48h | C16: 100% | D16: 100% | E16: =IF(C16="","",C16&" - "&D16) | F16: =IF(D16="","","Stable") | G16: T1 2025 | H16: DRH | I16: Réactivité excellente | K16: =IF(D16="","",IF(OR(D16="87%",D16="100%",D16="62%",D16="18 (proj.)",D16="4.5/5",D16="12 jours",D16="42 (proj.)",D16="3.5/5"),"Atteint",IF(OR(D16="75.6%",D16="8%"),"En progression","En cours")))
A17: COM-12 | B17: Taux reconnaissance effectif | C17: 100% | D17: 87% | E17: =IF(C17="","",C17&" - "&D17) | F17: =IF(D17="","","Stable") | G17: T1 2025 | H17: DRH | I17: Programme en montée en charge | K17: =IF(D17="","",IF(OR(D17="87%",D17="100%",D17="62%",D17="18 (proj.)",D17="4.5/5",D17="12 jours",D17="42 (proj.)",D17="3.5/5"),"Atteint",IF(OR(D17="75.6%",D17="8%"),"En progression","En cours")))
E18: =IF(C18="","",C18&" - "&D18) | F18: =IF(D18="","","Stable") | K18: =IF(D18="","",IFERROR("En cours",""))
E19: =IF(C19="","",C19&" - "&D19) | F19: =IF(D19="","","Stable") | K19: =IF(D19="","",IFERROR("En cours",""))
E20: =IF(C20="","",C20&" - "&D20) | F20: =IF(D20="","","Stable") | K20: =IF(D20="","",IFERROR("En cours",""))
E21: =IF(C21="","",C21&" - "&D21) | F21: =IF(D21="","","Stable") | K21: =IF(D21="","",IFERROR("En cours",""))
E22: =IF(C22="","",C22&" - "&D22) | F22: =IF(D22="","","Stable") | K22: =IF(D22="","",IFERROR("En cours",""))
E23: =IF(C23="","",C23&" - "&D23) | F23: =IF(D23="","","Stable") | K23: =IF(D23="","",IFERROR("En cours",""))
E24: =IF(C24="","",C24&" - "&D24) | F24: =IF(D24="","","Stable") | K24: =IF(D24="","",IFERROR("En cours",""))
E25: =IF(C25="","",C25&" - "&D25) | F25: =IF(D25="","","Stable") | K25: =IF(D25="","",IFERROR("En cours",""))
E26: =IF(C26="","",C26&" - "&D26) | F26: =IF(D26="","","Stable") | K26: =IF(D26="","",IFERROR("En cours",""))
E27: =IF(C27="","",C27&" - "&D27) | F27: =IF(D27="","","Stable") | K27: =IF(D27="","",IFERROR("En cours",""))
E28: =IF(C28="","",C28&" - "&D28) | F28: =IF(D28="","","Stable") | K28: =IF(D28="","",IFERROR("En cours",""))
E29: =IF(C29="","",C29&" - "&D29) | F29: =IF(D29="","","Stable") | K29: =IF(D29="","",IFERROR("En cours",""))
... E115: =IF(C115="","",C115&" - "&D115) | F115: =IF(D115="","","Stable") | K115: =IF(D115="","",IFERROR("En cours",""))

Sheet F21 - 19-Exigences d'Audit
A2: 19-EXIGENCES D'AUDIT COMMUNICATION INTERNE
A3: TABLEAU DYNAMIQUE — Saisissez dans la zone prévue ci-dessous
A5: Code Exigence | B5: Exigence Audit | C5: Fréquence Vérification | D5: Responsable | E5: Dernière Vérification | F5: Conformité | G5: Commentaire | H5: Action Corrective | I5: Échéance Action | J5: Statut | K5: Observations
A6: AUD-COM-01 | B6: Tenue du registre des enquêtes d'engagement | C6: Annuelle | D6: DRH | E6: 45687 | F6: Conforme | G6: Registre à jour et complet | J6: Conforme | L6: =IF(E6="","",IFERROR(TODAY()-E6,0)) | M6: =IF(E6="","",IF(AND(F6="Conforme",L6>90),"À revérifier",IF(F6="Non conforme","ACTION URGENTE",IF(F6="Partiellement conforme","À suivre","OK")))) | N6: =IF(C6="","",IF(C6="Mensuelle",30,IF(C6="Trimestrielle",90,IF(C6="Semestrielle",180,IF(C6="Annuelle",365,IF(C6="Hebdomadaire",7,0))))))
A7: AUD-COM-02 | B7: Diffusion régulière de la communication officielle | C7: Semestrielle | D7: DRH | E7: 45716 | F7: Conforme | G7: Newsletter mensuelle diffusée régulièrement | J7: Conforme | L7: =IF(E7="","",IFERROR(TODAY()-E7,0)) | M7: =IF(E7="","",IF(AND(F7="Conforme",L7>90),"À revérifier",IF(F7="Non conforme","ACTION URGENTE",IF(F7="Partiellement conforme","À suivre","OK")))) | N7: =IF(C7="","",IF(C7="Mensuelle",30,IF(C7="Trimestrielle",90,IF(C7="Semestrielle",180,IF(C7="Annuelle",365,IF(C7="Hebdomadaire",7,0))))))
A8: AUD-COM-03 | B8: Respect du budget communication | C8: Trimestrielle | D8: DAF | E8: 45747 | F8: Conforme | G8: T1 dans enveloppe | J8: Conforme | L8: =IF(E8="","",IFERROR(TODAY()-E8,0)) | M8: =IF(E8="","",IF(AND(F8="Conforme",L8>90),"À revérifier",IF(F8="Non conforme","ACTION URGENTE",IF(F8="Partiellement conforme","À suivre","OK")))) | N8: =IF(C8="","",IF(C8="Mensuelle",30,IF(C8="Trimestrielle",90,IF(C8="Semestrielle",180,IF(C8="Annuelle",365,IF(C8="Hebdomadaire",7,0))))))
A9: AUD-COM-04 | B9: Traitement des suggestions sous 15 jours | C9: Mensuelle | D9: DRH | E9: 45716 | F9: Partiellement conforme | G9: 2 suggestions hors délai en janvier | H9: Relance automatique J+10 | I9: 45748 | J9: En cours | L9: =IF(E9="","",IFERROR(TODAY()-E9,0)) | M9: =IF(E9="","",IF(AND(F9="Conforme",L9>90),"À revérifier",IF(F9="Non conforme","ACTION URGENTE",IF(F9="Partiellement conforme","À suivre","OK")))) | N9: =IF(C9="","",IF(C9="Mensuelle",30,IF(C9="Trimestrielle",90,IF(C9="Semestrielle",180,IF(C9="Annuelle",365,IF(C9="Hebdomadaire",7,0))))))
A10: AUD-COM-05 | B10: Anonymat des enquêtes garanti | C10: Annuelle | D10: DSI / DRH | E10: 45672 | F10: Conforme | G10: Plateforme sécurisée vérifiée | J10: Conforme | L10: =IF(E10="","",IFERROR(TODAY()-E10,0)) | M10: =IF(E10="","",IF(AND(F10="Conforme",L10>90),"À revérifier",IF(F10="Non conforme","ACTION URGENTE",IF(F10="Partiellement conforme","À suivre","OK")))) | N10: =IF(C10="","",IF(C10="Mensuelle",30,IF(C10="Trimestrielle",90,IF(C10="Semestrielle",180,IF(C10="Annuelle",365,IF(C10="Hebdomadaire",7,0))))))
A11: AUD-COM-06 | B11: Organisation des réunions CVS | C11: Trimestrielle | D11: DRH | E11: 45736 | F11: Conforme | G11: 3 réunions tenues T1 | J11: Conforme | L11: =IF(E11="","",IFERROR(TODAY()-E11,0)) | M11: =IF(E11="","",IF(AND(F11="Conforme",L11>90),"À revérifier",IF(F11="Non conforme","ACTION URGENTE",IF(F11="Partiellement conforme","À suivre","OK")))) | N11: =IF(C11="","",IF(C11="Mensuelle",30,IF(C11="Trimestrielle",90,IF(C11="Semestrielle",180,IF(C11="Annuelle",365,IF(C11="Hebdomadaire",7,0))))))
A12: AUD-COM-07 | B12: Gestion et suivi des alertes et rumeurs | C12: Mensuelle | D12: DRH | E12: 45716 | F12: Conforme | G12: Processus opérationnel, 4 alertes traitées | J12: Conforme | L12: =IF(E12="","",IFERROR(TODAY()-E12,0)) | M12: =IF(E12="","",IF(AND(F12="Conforme",L12>90),"À revérifier",IF(F12="Non conforme","ACTION URGENTE",IF(F12="Partiellement conforme","À suivre","OK")))) | N12: =IF(C12="","",IF(C12="Mensuelle",30,IF(C12="Trimestrielle",90,IF(C12="Semestrielle",180,IF(C12="Annuelle",365,IF(C12="Hebdomadaire",7,0))))))
L13: =IF(E13="","",IFERROR(TODAY()-E13,0)) | M13: =IF(E13="","",IF(AND(F13="Conforme",L13>90),"À revérifier",IF(F13="Non conforme","ACTION URGENTE",IF(F13="Partiellement conforme","À suivre","OK")))) | N13: =IF(C13="","",IF(C13="Mensuelle",30,IF(C13="Trimestrielle",90,IF(C13="Semestrielle",180,IF(C13="Annuelle",365,IF(C13="Hebdomadaire",7,0))))))
L14: =IF(E14="","",IFERROR(TODAY()-E14,0)) | M14: =IF(E14="","",IF(AND(F14="Conforme",L14>90),"À revérifier",IF(F14="Non conforme","ACTION URGENTE",IF(F14="Partiellement conforme","À suivre","OK")))) | N14: =IF(C14="","",IF(C14="Mensuelle",30,IF(C14="Trimestrielle",90,IF(C14="Semestrielle",180,IF(C14="Annuelle",365,IF(C14="Hebdomadaire",7,0))))))
L15: =IF(E15="","",IFERROR(TODAY()-E15,0)) | M15: =IF(E15="","",IF(AND(F15="Conforme",L15>90),"À revérifier",IF(F15="Non conforme","ACTION URGENTE",IF(F15="Partiellement conforme","À suivre","OK")))) | N15: =IF(C15="","",IF(C15="Mensuelle",30,IF(C15="Trimestrielle",90,IF(C15="Semestrielle",180,IF(C15="Annuelle",365,IF(C15="Hebdomadaire",7,0))))))
L16: =IF(E16="","",IFERROR(TODAY()-E16,0)) | M16: =IF(E16="","",IF(AND(F16="Conforme",L16>90),"À revérifier",IF(F16="Non conforme","ACTION URGENTE",IF(F16="Partiellement conforme","À suivre","OK")))) | N16: =IF(C16="","",IF(C16="Mensuelle",30,IF(C16="Trimestrielle",90,IF(C16="Semestrielle",180,IF(C16="Annuelle",365,IF(C16="Hebdomadaire",7,0))))))
L17: =IF(E17="","",IFERROR(TODAY()-E17,0)) | M17: =IF(E17="","",IF(AND(F17="Conforme",L17>90),"À revérifier",IF(F17="Non conforme","ACTION URGENTE",IF(F17="Partiellement conforme","À suivre","OK")))) | N17: =IF(C17="","",IF(C17="Mensuelle",30,IF(C17="Trimestrielle",90,IF(C17="Semestrielle",180,IF(C17="Annuelle",365,IF(C17="Hebdomadaire",7,0))))))
L18: =IF(E18="","",IFERROR(TODAY()-E18,0)) | M18: =IF(E18="","",IF(AND(F18="Conforme",L18>90),"À revérifier",IF(F18="Non conforme","ACTION URGENTE",IF(F18="Partiellement conforme","À suivre","OK")))) | N18: =IF(C18="","",IF(C18="Mensuelle",30,IF(C18="Trimestrielle",90,IF(C18="Semestrielle",180,IF(C18="Annuelle",365,IF(C18="Hebdomadaire",7,0))))))
L19: =IF(E19="","",IFERROR(TODAY()-E19,0)) | M19: =IF(E19="","",IF(AND(F19="Conforme",L19>90),"À revérifier",IF(F19="Non conforme","ACTION URGENTE",IF(F19="Partiellement conforme","À suivre","OK")))) | N19: =IF(C19="","",IF(C19="Mensuelle",30,IF(C19="Trimestrielle",90,IF(C19="Semestrielle",180,IF(C19="Annuelle",365,IF(C19="Hebdomadaire",7,0))))))
L20: =IF(E20="","",IFERROR(TODAY()-E20,0)) | M20: =IF(E20="","",IF(AND(F20="Conforme",L20>90),"À revérifier",IF(F20="Non conforme","ACTION URGENTE",IF(F20="Partiellement conforme","À suivre","OK")))) | N20: =IF(C20="","",IF(C20="Mensuelle",30,IF(C20="Trimestrielle",90,IF(C20="Semestrielle",180,IF(C20="Annuelle",365,IF(C20="Hebdomadaire",7,0))))))
L21: =IF(E21="","",IFERROR(TODAY()-E21,0)) | M21: =IF(E21="","",IF(AND(F21="Conforme",L21>90),"À revérifier",IF(F21="Non conforme","ACTION URGENTE",IF(F21="Partiellement conforme","À suivre","OK")))) | N21: =IF(C21="","",IF(C21="Mensuelle",30,IF(C21="Trimestrielle",90,IF(C21="Semestrielle",180,IF(C21="Annuelle",365,IF(C21="Hebdomadaire",7,0))))))
L22: =IF(E22="","",IFERROR(TODAY()-E22,0)) | M22: =IF(E22="","",IF(AND(F22="Conforme",L22>90),"À revérifier",IF(F22="Non conforme","ACTION URGENTE",IF(F22="Partiellement conforme","À suivre","OK")))) | N22: =IF(C22="","",IF(C22="Mensuelle",30,IF(C22="Trimestrielle",90,IF(C22="Semestrielle",180,IF(C22="Annuelle",365,IF(C22="Hebdomadaire",7,0))))))
L23: =IF(E23="","",IFERROR(TODAY()-E23,0)) | M23: =IF(E23="","",IF(AND(F23="Conforme",L23>90),"À revérifier",IF(F23="Non conforme","ACTION URGENTE",IF(F23="Partiellement conforme","À suivre","OK")))) | N23: =IF(C23="","",IF(C23="Mensuelle",30,IF(C23="Trimestrielle",90,IF(C23="Semestrielle",180,IF(C23="Annuelle",365,IF(C23="Hebdomadaire",7,0))))))
L24: =IF(E24="","",IFERROR(TODAY()-E24,0)) | M24: =IF(E24="","",IF(AND(F24="Conforme",L24>90),"À revérifier",IF(F24="Non conforme","ACTION URGENTE",IF(F24="Partiellement conforme","À suivre","OK")))) | N24: =IF(C24="","",IF(C24="Mensuelle",30,IF(C24="Trimestrielle",90,IF(C24="Semestrielle",180,IF(C24="Annuelle",365,IF(C24="Hebdomadaire",7,0))))))
... L115: =IF(E115="","",IFERROR(TODAY()-E115,0)) | M115: =IF(E115="","",IF(AND(F115="Conforme",L115>90),"À revérifier",IF(F115="Non conforme","ACTION URGENTE",IF(F115="Partiellement conforme","À suivre","OK")))) | N115: =IF(C115="","",IF(C115="Mensuelle",30,IF(C115="Trimestrielle",90,IF(C115="Semestrielle",180,IF(C115="Annuelle",365,IF(C115="Hebdomadaire",7,0))))))
