Workbook

Sheet F01 - _Données Expatriés
A2: DONNÉES EXPATRIÉS — Base de référence mobilité internationale
A3: TABLEAU DYNAMIQUE — Saisissez dans la zone prévue ci-dessous
A5: Matricule | B5: Nom | C5: Prénom | D5: Nationalité | E5: Département | F5: Poste | G5: Statut Expat. | H5: Âge | I5: Genre | J5: Situation Fam. | K5: Nb Enfants
A6: EXP-001 | B6: Martin | C6: Jean-Pierre | D6: France | E6: Direction Générale | F6: DG Adjoint | G6: Expatrié | H6: 48 | I6: =IF(I6="","",I6) | J6: Célibataire | K6: 0
A7: EXP-002 | B7: Dupont | C7: Sophie | D7: France | E7: Finance & Comptabilité | F7: Contrôleur Financier | G7: Expatrié | H7: 42 | I7: =IF(I7="","",I7) | J7: Marié(e) | K7: 2
A8: EXP-003 | B8: Mueller | C8: Hans | D8: Allemagne | E8: Cuisine & Restauration | F8: Chef Exécutif | G8: Expatrié | H8: 55 | I8: =IF(I8="","",I8) | J8: Marié(e) | K8: 1
A9: EXP-004 | B9: Silva | C9: Ana | D9: Brésil | E9: Spa & Bien-être | F9: Directrice Spa | G9: Expatrié | H9: 38 | I9: =IF(I9="","",I9) | J9: Célibataire | K9: 0
A10: EXP-005 | B10: Kim | C10: Jin-woo | D10: Corée du Sud | E10: Informatique | F10: Expert IT Senior | G10: Détaché | H10: 35 | I10: =IF(I10="","",I10) | J10: Marié(e) | K10: 1
A11: EXP-006 | B11: Nakamura | C11: Yuki | D11: Japon | E11: Réception & Front Office | F11: Concierge Chef | G11: Expatrié | H11: 40 | I11: =IF(I11="","",I11) | J11: Célibataire | K11: 0
A12: EXP-007 | B12: Okafor | C12: Chidi | D12: Nigeria | E12: Ressources Humaines | F12: Resp. Formation Intl. | G12: Détaché | H12: 45 | I12: =IF(I12="","",I12) | J12: Marié(e) | K12: 3
A13: EXP-008 | B13: Leclerc | C13: Marc | D13: France | E13: Marketing & Communication | F13: Directeur Marketing | G13: Expatrié | H13: 50 | I13: =IF(I13="","",I13) | J13: Marié(e) | K13: 2
A14: EXP-009 | B14: Santos | C14: Carlos | D14: Portugal | E14: Hébergement | F14: Director of Rooms | G14: Expatrié | H14: 44 | I14: =IF(I14="","",I14) | J14: Marié(e) | K14: 1
A15: EXP-010 | B15: Chen | C15: Wei | D15: Chine | E15: Commerce | F15: Resp. Commercial Asie | G15: Détaché | H15: 37 | I15: =IF(I15="","",I15) | J15: Célibataire | K15: 0
A16: EXP-011 | B16: Dubois | C16: Claire | D16: Belgique | E16: Ressources Humaines | F16: DRH | G16: Expatrié | H16: 52 | I16: =IF(I16="","",I16) | J16: Marié(e) | K16: 2
A17: EXP-012 | B17: Mensah | C17: Kwame | D17: Ghana | E17: Sécurité | F17: Consultant Sécurité | G17: Détaché | H17: 39 | I17: =IF(I17="","",I17) | J17: Marié(e) | K17: 1
... A20: EXP-015 | B20: Johansson | C20: Erik | D20: Suède | E20: Entretien & Maintenance | F20: Ingénieur Technique | G20: Expatrié | H20: 47 | I20: =IF(I20="","",I20) | J20: Marié(e) | K20: 2

Sheet F02 - _Lists
A2: LISTES DE RÉFÉRENCE — Valeurs pour listes déroulantes
A3: TABLEAU DYNAMIQUE — Saisissez dans la zone prévue ci-dessous
A5: nationalites | B5: departements | C5: postes | D5: statuts_expat | E5: pays_origine | F5: pays_accueil | G5: types_visa | H5: types_permis | I5: statuts_visa | J5: statuts_contrat | K5: types_contrat | L5: niveaux_risque | M5: devises | N5: statuts_logement | O5: types_ecole | P5: regimes_fiscaux | Q5: statuts_medicaux | R5: statuts_reintegration | S5: modes_paiement | T5: priorites | U5: conformites | V5: statuts_action | W5: frequences | X5: mois | Y5: trimestres | Z5: validations | AA5: categories_indemnite | AB5: types_risque | AC5: situation_familiale | AD5: tendances
A6: Française | B6: Direction Générale | C6: DG Adjoint | D6: Expatrié | E6: France | F6: Côte d'Ivoire | G6: Travail | H6: Carte de séjour | I6: En cours | J6: Actif | K6: CDD Expatriation | L6: Faible | M6: EUR | N6: Fourni - Villa | O6: École française | P6: Régime impatrié | Q6: Apte | R6: Non commencé | S6: Virement international | T6: Haute | U6: Conforme | V6: En attente | W6: Mensuelle | X6: Janvier 2025 | Y6: T1 2025 | Z6: Validé | AA6: Prime d'expatriation | AB6: Santé / Épidémiologique | AC6: Célibataire | AD6: Hausse
A7: Allemande | B7: Ressources Humaines | C7: Contrôleur Financier | D7: Détaché | E7: Allemagne | F7: Sénégal | G7: Affaires | H7: Permis de travail A | I7: Accordé | J7: En négociation | K7: CDI Expatriation | L7: Modéré | M7: USD | N7: Fourni - Appartement | O7: École internationale | P7: Régime de droit commun | Q7: Apte avec restrictions | R7: En préparation | S7: Virement local | T7: Moyenne | U7: Partiellement conforme | V7: En cours | W7: Trimestrielle | X7: Février 2025 | Y7: T2 2025 | Z7: En attente | AA7: Indemnité logement | AB7: Sécurité physique | AC7: Marié(e) | AD7: Baisse
A8: Brésilienne | B8: Finance & Comptabilité | C8: Chef Exécutif | D8: Mission courte | E8: Brésil | F8: Cameroun | G8: Séjour longue durée | H8: Permis de travail B | I8: Refusé | J8: En prolongation | K8: Mission détachement | L8: Élevé | M8: XOF | N8: Indemnité logement | O8: École locale | P8: Convention fiscale | Q8: Inapte temporaire | R8: En cours | S8: Chèque | T8: Basse | U8: Non conforme | V8: Terminé | W8: Semestrielle | X8: Mars 2025 | Y8: T3 2025 | Z8: Rejeté | AA8: Indemnité scolarité | AB8: Instabilité politique | AC8: Concubin(e) | AD8: Stable
A9: Coréenne | B9: Marketing & Communication | C9: Directrice Spa | D9: Consultant intl. | E9: Corée du Sud | F9: Ghana | G9: Diplomatique | H9: Permis de travail C | I9: Renouvellement | J9: Expiré | K9: Consultation | L9: Critique | M9: GBP | N9: En recherche | O9: Enseignement à domicile | P9: Exonération partielle | Q9: En attente | R9: Terminé | S9: Espèces | U9: En attente | V9: Reporté | W9: Annuelle | X9: Avril 2025 | Y9: T4 2025 | Z9: Non applicable | AA9: Prime de difficulté | AB9: Risque naturel | AC9: Divorcé(e)
A10: Japonaise | B10: Informatique | C10: Expert IT Senior | D10: Stage intl. | E10: Japon | F10: Mali | G10: Humanitaire | H10: Exemption | I10: Expiré | J10: Résilié | K10: Prestation | M10: CHF | N10: N/A | O10: Université | P10: Non résident | Q10: Non vérifié | R10: Abandonné | S10: Mixte | U10: Non applicable | V10: Annulé | W10: Ponctuelle | X10: Mai 2025 | AA10: Indemnité voyage | AB10: Taux de change | AC10: Veuf(ve)
A11: Nigériane | B11: Commerce | C11: Concierge Chef | E11: Nigeria | F11: Burkina Faso | I11: Non requis | M11: JPY | X11: Juin 2025 | AA11: Prime d'installation | AB11: Conformité légale
A12: Portugaise | B12: Logistique & Approvisionnement | C12: Resp. Formation Intl. | E12: Portugal | F12: Guinée | M12: CNY | X12: Juillet 2025 | AA12: Indemnité rapatriement | AB12: Risque financier
A13: Chinoise | B13: Réception & Front Office | C13: Directeur Marketing | E13: Chine | F13: Maroc | M13: KRW | X13: Août 2025 | AA13: Prime de mobilité | AB13: Logistique / Transport
A14: Belge | B14: Cuisine & Restauration | C14: Director of Rooms | E14: Belgique | F14: Tunisie | M14: BRL | X14: Septembre 2025
A15: Ghanéenne | B15: Hébergement | C15: Resp. Commercial Asie | E15: Ghana | F15: Kenya | M15: MAD | X15: Octobre 2025
A16: Italienne | B16: Entretien & Maintenance | C16: DRH | E16: Italie | X16: Novembre 2025
A17: Marocaine | B17: Sécurité | C17: Consultant Sécurité | E17: Maroc | X17: Décembre 2025
A18: Suédoise | B18: Service Client | C18: Sommelier Chef | E18: Suède
A19: Américaine | B19: Animation & Loisirs | C19: Animatrice Multilingue | E19: États-Unis
A20: Britannique | B20: Spa & Bien-être | C20: Ingénieur Technique | E20: Royaume-Uni
A21: Canadienne | C21: Chef Réception | E21: Canada
A22: Suisse | C22: Resp. Service Client | E22: Suisse
A23: Ivoirienne | C23: Gouvernante | E23: Côte d'Ivoire
A24: Sénégalaise | C24: Agent Réception | E24: Sénégal
A25: Camerounaise | C25: Technicien | E25: Cameroun

Sheet F03 - 1-Tableau de Bord
A2: DOMAINE 30 — GESTION DES EXPATRIÉS ET MOBILITÉ INTERNATIONALE RH
A3: Tableau de Bord Synthétique — Expatriés, visas, indemnités et conformité
A5: INDICATEURS CLÉS
A6: Nb Expatriés Actifs | C6: Pays d'Origine Représentés | E6: Visas en Cours | G6: Budget Mobilité (M FCFA) | I6: Taux Conformité (%) | K6: Réintégrations Planifiées
A7: 15 | C7: 11 | E7: 3 | G7: 85.4 | I7: 93 | K7: 2
A9: RÉPARTITION PAR NATIONALITÉ | I9: VISA & PERMIS EN COURS
A10: Nationalité | B10: Effectif | C10: Statut Majoritaire | D10: Nb Enfants | E10: Coût Moyen Mens. (k€) | I10: Pays | J10: Nb En cours | K10: Nb Accordés | L10: Nb Expirés | M10: Alertes
A11: Française | B11: 4 | C11: Expatrié | D11: 6 | E11: 4.2 | I11: France | J11: 1 | K11: 3 | L11: 0 | M11: 0
A12: Allemande | B12: 1 | C12: Expatrié | D12: 1 | E12: 3.8 | I12: Allemagne | J12: 0 | K12: 1 | L12: 0 | M12: 0
A13: Coréenne | B13: 1 | C13: Détaché | D13: 1 | E13: 3.5 | I13: Corée du Sud | J13: 1 | K13: 0 | L13: 0 | M13: Renouvellement
A14: Japonaise | B14: 1 | C14: Expatrié | D14: 0 | E14: 3.9 | I14: Japon | J14: 0 | K14: 1 | L14: 0 | M14: 0
A15: Nigériane | B15: 1 | C15: Détaché | D15: 3 | E15: 2.8 | I15: Nigeria | J15: 0 | K15: 1 | L15: 0 | M15: 0
A16: Portugaise | B16: 1 | C16: Expatrié | D16: 1 | E16: 3.2 | I16: Portugal | J16: 1 | K16: 0 | L16: 0 | M16: Expiration 30j
A17: Chinoise | B17: 1 | C17: Détaché | D17: 0 | E17: 3.6
A18: Belge | B18: 1 | C18: Expatrié | D18: 2 | E18: 4
A19: Italienne | B19: 1 | C19: Expatrié | D19: 0 | E19: 3.3
A20: ACTIONS PLANIFIÉES
A21: Action | B21: Responsable | C21: Échéance | D21: Priorité | E21: Statut
A22: Renouveler visa Kim J. | B22: DRH | C22: 45762 | D22: Haute | E22: En cours
A23: Logement Dupont S. | B23: DRH / Logistique | C23: 45717 | D23: Haute | E23: En cours
A24: Audit fiscalité expat T1 | B24: DAF / Expert fiscal | C24: 45747 | D24: Moyenne | E24: En cours
A25: Préparer réintégration Martin | B25: DRH | C25: 45901 | D25: Basse | E25: Planifié

Sheet F04 - 2-Contrats Expat.
A2: 2-CONTRATS D'EXPATRIATION
A3: TABLEAU DYNAMIQUE — Saisissez dans la zone prévue ci-dessous
A5: Code Contrat | B5: Matricule Expat. | C5: Type Contrat | D5: Pays d'Origine | E5: Pays d'Accueil | F5: Date Début | G5: Date Fin | H5: Durée (mois) | I5: Salaire Base (FCFA) | J5: Devise Paie | K5: Statut | L5: Observations
A6: CEXP-001 | B6: EXP-001 | C6: CDI Expatriation | D6: France | E6: Côte d'Ivoire | F6: 44941 | G6: 46036 | H6: =IF(OR(F6="",G6=""),"",IFERROR((G6-F6)/30.44,0)) | I6: 4500000 | J6: EUR | K6: Actif | L6: Renouvellement prévu | M6: =IF(B6="","",IFERROR(VLOOKUP(B6,'F01 - _Données Expatriés'!$A$6:$K$20,2,FALSE)&" "&VLOOKUP(B6,'F01 - _Données Expatriés'!$A$6:$K$20,3,FALSE),"")) | N6: =IF(C6="","",IFERROR(COUNTIF($C$6:$C$115,C6),0))
A7: CEXP-002 | B7: EXP-002 | C7: CDD Expatriation | D7: France | E7: Côte d'Ivoire | F7: 45352 | G7: 46081 | H7: =IF(OR(F7="",G7=""),"",IFERROR((G7-F7)/30.44,0)) | I7: 3800000 | J7: EUR | K7: Actif | M7: =IF(B7="","",IFERROR(VLOOKUP(B7,'F01 - _Données Expatriés'!$A$6:$K$20,2,FALSE)&" "&VLOOKUP(B7,'F01 - _Données Expatriés'!$A$6:$K$20,3,FALSE),"")) | N7: =IF(C7="","",IFERROR(COUNTIF($C$6:$C$115,C7),0))
A8: CEXP-003 | B8: EXP-003 | C8: CDI Expatriation | D8: Allemagne | E8: Côte d'Ivoire | F8: 44713 | G8: 45808 | H8: =IF(OR(F8="",G8=""),"",IFERROR((G8-F8)/30.44,0)) | I8: 5200000 | J8: EUR | K8: En prolongation | L8: Prolongation 12 mois | M8: =IF(B8="","",IFERROR(VLOOKUP(B8,'F01 - _Données Expatriés'!$A$6:$K$20,2,FALSE)&" "&VLOOKUP(B8,'F01 - _Données Expatriés'!$A$6:$K$20,3,FALSE),"")) | N8: =IF(C8="","",IFERROR(COUNTIF($C$6:$C$115,C8),0))
A9: CEXP-004 | B9: EXP-005 | C9: Mission détachement | D9: Corée du Sud | E9: Côte d'Ivoire | F9: 45292 | G9: 46022 | H9: =IF(OR(F9="",G9=""),"",IFERROR((G9-F9)/30.44,0)) | I9: 4200000 | J9: KRW | K9: Actif | L9: Détachement 2 ans | M9: =IF(B9="","",IFERROR(VLOOKUP(B9,'F01 - _Données Expatriés'!$A$6:$K$20,2,FALSE)&" "&VLOOKUP(B9,'F01 - _Données Expatriés'!$A$6:$K$20,3,FALSE),"")) | N9: =IF(C9="","",IFERROR(COUNTIF($C$6:$C$115,C9),0))
A10: CEXP-005 | B10: EXP-007 | C10: Mission détachement | D10: Nigeria | E10: Côte d'Ivoire | F10: 45383 | G10: 45930 | H10: =IF(OR(F10="",G10=""),"",IFERROR((G10-F10)/30.44,0)) | I10: 2800000 | J10: XOF | K10: Actif | M10: =IF(B10="","",IFERROR(VLOOKUP(B10,'F01 - _Données Expatriés'!$A$6:$K$20,2,FALSE)&" "&VLOOKUP(B10,'F01 - _Données Expatriés'!$A$6:$K$20,3,FALSE),"")) | N10: =IF(C10="","",IFERROR(COUNTIF($C$6:$C$115,C10),0))
H11: =IF(OR(F11="",G11=""),"",IFERROR((G11-F11)/30.44,0)) | M11: =IF(B11="","",IFERROR(VLOOKUP(B11,'F01 - _Données Expatriés'!$A$6:$K$20,2,FALSE)&" "&VLOOKUP(B11,'F01 - _Données Expatriés'!$A$6:$K$20,3,FALSE),"")) | N11: =IF(C11="","",IFERROR(COUNTIF($C$6:$C$115,C11),0))
H12: =IF(OR(F12="",G12=""),"",IFERROR((G12-F12)/30.44,0)) | M12: =IF(B12="","",IFERROR(VLOOKUP(B12,'F01 - _Données Expatriés'!$A$6:$K$20,2,FALSE)&" "&VLOOKUP(B12,'F01 - _Données Expatriés'!$A$6:$K$20,3,FALSE),"")) | N12: =IF(C12="","",IFERROR(COUNTIF($C$6:$C$115,C12),0))
H13: =IF(OR(F13="",G13=""),"",IFERROR((G13-F13)/30.44,0)) | M13: =IF(B13="","",IFERROR(VLOOKUP(B13,'F01 - _Données Expatriés'!$A$6:$K$20,2,FALSE)&" "&VLOOKUP(B13,'F01 - _Données Expatriés'!$A$6:$K$20,3,FALSE),"")) | N13: =IF(C13="","",IFERROR(COUNTIF($C$6:$C$115,C13),0))
H14: =IF(OR(F14="",G14=""),"",IFERROR((G14-F14)/30.44,0)) | M14: =IF(B14="","",IFERROR(VLOOKUP(B14,'F01 - _Données Expatriés'!$A$6:$K$20,2,FALSE)&" "&VLOOKUP(B14,'F01 - _Données Expatriés'!$A$6:$K$20,3,FALSE),"")) | N14: =IF(C14="","",IFERROR(COUNTIF($C$6:$C$115,C14),0))
H15: =IF(OR(F15="",G15=""),"",IFERROR((G15-F15)/30.44,0)) | M15: =IF(B15="","",IFERROR(VLOOKUP(B15,'F01 - _Données Expatriés'!$A$6:$K$20,2,FALSE)&" "&VLOOKUP(B15,'F01 - _Données Expatriés'!$A$6:$K$20,3,FALSE),"")) | N15: =IF(C15="","",IFERROR(COUNTIF($C$6:$C$115,C15),0))
H16: =IF(OR(F16="",G16=""),"",IFERROR((G16-F16)/30.44,0)) | M16: =IF(B16="","",IFERROR(VLOOKUP(B16,'F01 - _Données Expatriés'!$A$6:$K$20,2,FALSE)&" "&VLOOKUP(B16,'F01 - _Données Expatriés'!$A$6:$K$20,3,FALSE),"")) | N16: =IF(C16="","",IFERROR(COUNTIF($C$6:$C$115,C16),0))
H17: =IF(OR(F17="",G17=""),"",IFERROR((G17-F17)/30.44,0)) | M17: =IF(B17="","",IFERROR(VLOOKUP(B17,'F01 - _Données Expatriés'!$A$6:$K$20,2,FALSE)&" "&VLOOKUP(B17,'F01 - _Données Expatriés'!$A$6:$K$20,3,FALSE),"")) | N17: =IF(C17="","",IFERROR(COUNTIF($C$6:$C$115,C17),0))
H18: =IF(OR(F18="",G18=""),"",IFERROR((G18-F18)/30.44,0)) | M18: =IF(B18="","",IFERROR(VLOOKUP(B18,'F01 - _Données Expatriés'!$A$6:$K$20,2,FALSE)&" "&VLOOKUP(B18,'F01 - _Données Expatriés'!$A$6:$K$20,3,FALSE),"")) | N18: =IF(C18="","",IFERROR(COUNTIF($C$6:$C$115,C18),0))
H19: =IF(OR(F19="",G19=""),"",IFERROR((G19-F19)/30.44,0)) | M19: =IF(B19="","",IFERROR(VLOOKUP(B19,'F01 - _Données Expatriés'!$A$6:$K$20,2,FALSE)&" "&VLOOKUP(B19,'F01 - _Données Expatriés'!$A$6:$K$20,3,FALSE),"")) | N19: =IF(C19="","",IFERROR(COUNTIF($C$6:$C$115,C19),0))
H20: =IF(OR(F20="",G20=""),"",IFERROR((G20-F20)/30.44,0)) | M20: =IF(B20="","",IFERROR(VLOOKUP(B20,'F01 - _Données Expatriés'!$A$6:$K$20,2,FALSE)&" "&VLOOKUP(B20,'F01 - _Données Expatriés'!$A$6:$K$20,3,FALSE),"")) | N20: =IF(C20="","",IFERROR(COUNTIF($C$6:$C$115,C20),0))
H21: =IF(OR(F21="",G21=""),"",IFERROR((G21-F21)/30.44,0)) | M21: =IF(B21="","",IFERROR(VLOOKUP(B21,'F01 - _Données Expatriés'!$A$6:$K$20,2,FALSE)&" "&VLOOKUP(B21,'F01 - _Données Expatriés'!$A$6:$K$20,3,FALSE),"")) | N21: =IF(C21="","",IFERROR(COUNTIF($C$6:$C$115,C21),0))
H22: =IF(OR(F22="",G22=""),"",IFERROR((G22-F22)/30.44,0)) | M22: =IF(B22="","",IFERROR(VLOOKUP(B22,'F01 - _Données Expatriés'!$A$6:$K$20,2,FALSE)&" "&VLOOKUP(B22,'F01 - _Données Expatriés'!$A$6:$K$20,3,FALSE),"")) | N22: =IF(C22="","",IFERROR(COUNTIF($C$6:$C$115,C22),0))
... H115: =IF(OR(F115="",G115=""),"",IFERROR((G115-F115)/30.44,0)) | M115: =IF(B115="","",IFERROR(VLOOKUP(B115,'F01 - _Données Expatriés'!$A$6:$K$20,2,FALSE)&" "&VLOOKUP(B115,'F01 - _Données Expatriés'!$A$6:$K$20,3,FALSE),"")) | N115: =IF(C115="","",IFERROR(COUNTIF($C$6:$C$115,C115),0))

Sheet F05 - 3-Visas et Permis
A2: 3-VISAS ET PERMIS DE TRAVAIL
A3: TABLEAU DYNAMIQUE — Saisissez dans la zone prévue ci-dessous
A5: Code Visa | B5: Matricule Expat. | C5: Type Visa | D5: Type Permis | E5: Date Demande | F5: Date Obtention | G5: Date Expiration | H5: Durée Validité (j.) | I5: Coût (FCFA) | J5: Statut | K5: Renouvellement Auto. | L5: Observations
A6: VISA-001 | B6: EXP-001 | C6: Travail | D6: Carte de séjour | E6: 44931 | F6: 44967 | G6: 45697 | H6: =IF(OR(G6="",F6=""),"",IFERROR(G6-F6,0)) | I6: 150000 | J6: En cours | K6: Oui | L6: Renouvellement en cours | M6: =IF(B6="","",IFERROR(VLOOKUP(B6,'F01 - _Données Expatriés'!$A$6:$K$20,2,FALSE)&" "&VLOOKUP(B6,'F01 - _Données Expatriés'!$A$6:$K$20,3,FALSE),"")) | N6: =IF(J6="","",IFERROR(COUNTIF($J$6:$J$115,J6),0))
A7: VISA-002 | B7: EXP-002 | C7: Travail | D7: Permis de travail A | E7: 45337 | F7: 45371 | G7: 46100 | H7: =IF(OR(G7="",F7=""),"",IFERROR(G7-F7,0)) | I7: 120000 | J7: Accordé | K7: Oui | M7: =IF(B7="","",IFERROR(VLOOKUP(B7,'F01 - _Données Expatriés'!$A$6:$K$20,2,FALSE)&" "&VLOOKUP(B7,'F01 - _Données Expatriés'!$A$6:$K$20,3,FALSE),"")) | N7: =IF(J7="","",IFERROR(COUNTIF($J$6:$J$115,J7),0))
A8: VISA-003 | B8: EXP-003 | C8: Travail | D8: Carte de séjour | E8: 44696 | F8: 44732 | G8: 45462 | H8: =IF(OR(G8="",F8=""),"",IFERROR(G8-F8,0)) | I8: 150000 | J8: En cours | K8: Oui | L8: Prolongation liée au contrat | M8: =IF(B8="","",IFERROR(VLOOKUP(B8,'F01 - _Données Expatriés'!$A$6:$K$20,2,FALSE)&" "&VLOOKUP(B8,'F01 - _Données Expatriés'!$A$6:$K$20,3,FALSE),"")) | N8: =IF(J8="","",IFERROR(COUNTIF($J$6:$J$115,J8),0))
A9: VISA-004 | B9: EXP-005 | C9: Travail | D9: Permis de travail B | E9: 45261 | F9: 45306 | G9: 45671 | H9: =IF(OR(G9="",F9=""),"",IFERROR(G9-F9,0)) | I9: 180000 | J9: Renouvellement | K9: Oui | L9: Délai critique | M9: =IF(B9="","",IFERROR(VLOOKUP(B9,'F01 - _Données Expatriés'!$A$6:$K$20,2,FALSE)&" "&VLOOKUP(B9,'F01 - _Données Expatriés'!$A$6:$K$20,3,FALSE),"")) | N9: =IF(J9="","",IFERROR(COUNTIF($J$6:$J$115,J9),0))
A10: VISA-005 | B10: EXP-010 | C10: Affaires | D10: Exemption | E10: 45444 | F10: 45453 | G10: 45817 | H10: =IF(OR(G10="",F10=""),"",IFERROR(G10-F10,0)) | I10: 50000 | J10: Accordé | K10: Non | M10: =IF(B10="","",IFERROR(VLOOKUP(B10,'F01 - _Données Expatriés'!$A$6:$K$20,2,FALSE)&" "&VLOOKUP(B10,'F01 - _Données Expatriés'!$A$6:$K$20,3,FALSE),"")) | N10: =IF(J10="","",IFERROR(COUNTIF($J$6:$J$115,J10),0))
H11: =IF(OR(G11="",F11=""),"",IFERROR(G11-F11,0)) | M11: =IF(B11="","",IFERROR(VLOOKUP(B11,'F01 - _Données Expatriés'!$A$6:$K$20,2,FALSE)&" "&VLOOKUP(B11,'F01 - _Données Expatriés'!$A$6:$K$20,3,FALSE),"")) | N11: =IF(J11="","",IFERROR(COUNTIF($J$6:$J$115,J11),0))
H12: =IF(OR(G12="",F12=""),"",IFERROR(G12-F12,0)) | M12: =IF(B12="","",IFERROR(VLOOKUP(B12,'F01 - _Données Expatriés'!$A$6:$K$20,2,FALSE)&" "&VLOOKUP(B12,'F01 - _Données Expatriés'!$A$6:$K$20,3,FALSE),"")) | N12: =IF(J12="","",IFERROR(COUNTIF($J$6:$J$115,J12),0))
H13: =IF(OR(G13="",F13=""),"",IFERROR(G13-F13,0)) | M13: =IF(B13="","",IFERROR(VLOOKUP(B13,'F01 - _Données Expatriés'!$A$6:$K$20,2,FALSE)&" "&VLOOKUP(B13,'F01 - _Données Expatriés'!$A$6:$K$20,3,FALSE),"")) | N13: =IF(J13="","",IFERROR(COUNTIF($J$6:$J$115,J13),0))
H14: =IF(OR(G14="",F14=""),"",IFERROR(G14-F14,0)) | M14: =IF(B14="","",IFERROR(VLOOKUP(B14,'F01 - _Données Expatriés'!$A$6:$K$20,2,FALSE)&" "&VLOOKUP(B14,'F01 - _Données Expatriés'!$A$6:$K$20,3,FALSE),"")) | N14: =IF(J14="","",IFERROR(COUNTIF($J$6:$J$115,J14),0))
H15: =IF(OR(G15="",F15=""),"",IFERROR(G15-F15,0)) | M15: =IF(B15="","",IFERROR(VLOOKUP(B15,'F01 - _Données Expatriés'!$A$6:$K$20,2,FALSE)&" "&VLOOKUP(B15,'F01 - _Données Expatriés'!$A$6:$K$20,3,FALSE),"")) | N15: =IF(J15="","",IFERROR(COUNTIF($J$6:$J$115,J15),0))
H16: =IF(OR(G16="",F16=""),"",IFERROR(G16-F16,0)) | M16: =IF(B16="","",IFERROR(VLOOKUP(B16,'F01 - _Données Expatriés'!$A$6:$K$20,2,FALSE)&" "&VLOOKUP(B16,'F01 - _Données Expatriés'!$A$6:$K$20,3,FALSE),"")) | N16: =IF(J16="","",IFERROR(COUNTIF($J$6:$J$115,J16),0))
H17: =IF(OR(G17="",F17=""),"",IFERROR(G17-F17,0)) | M17: =IF(B17="","",IFERROR(VLOOKUP(B17,'F01 - _Données Expatriés'!$A$6:$K$20,2,FALSE)&" "&VLOOKUP(B17,'F01 - _Données Expatriés'!$A$6:$K$20,3,FALSE),"")) | N17: =IF(J17="","",IFERROR(COUNTIF($J$6:$J$115,J17),0))
H18: =IF(OR(G18="",F18=""),"",IFERROR(G18-F18,0)) | M18: =IF(B18="","",IFERROR(VLOOKUP(B18,'F01 - _Données Expatriés'!$A$6:$K$20,2,FALSE)&" "&VLOOKUP(B18,'F01 - _Données Expatriés'!$A$6:$K$20,3,FALSE),"")) | N18: =IF(J18="","",IFERROR(COUNTIF($J$6:$J$115,J18),0))
H19: =IF(OR(G19="",F19=""),"",IFERROR(G19-F19,0)) | M19: =IF(B19="","",IFERROR(VLOOKUP(B19,'F01 - _Données Expatriés'!$A$6:$K$20,2,FALSE)&" "&VLOOKUP(B19,'F01 - _Données Expatriés'!$A$6:$K$20,3,FALSE),"")) | N19: =IF(J19="","",IFERROR(COUNTIF($J$6:$J$115,J19),0))
H20: =IF(OR(G20="",F20=""),"",IFERROR(G20-F20,0)) | M20: =IF(B20="","",IFERROR(VLOOKUP(B20,'F01 - _Données Expatriés'!$A$6:$K$20,2,FALSE)&" "&VLOOKUP(B20,'F01 - _Données Expatriés'!$A$6:$K$20,3,FALSE),"")) | N20: =IF(J20="","",IFERROR(COUNTIF($J$6:$J$115,J20),0))
H21: =IF(OR(G21="",F21=""),"",IFERROR(G21-F21,0)) | M21: =IF(B21="","",IFERROR(VLOOKUP(B21,'F01 - _Données Expatriés'!$A$6:$K$20,2,FALSE)&" "&VLOOKUP(B21,'F01 - _Données Expatriés'!$A$6:$K$20,3,FALSE),"")) | N21: =IF(J21="","",IFERROR(COUNTIF($J$6:$J$115,J21),0))
H22: =IF(OR(G22="",F22=""),"",IFERROR(G22-F22,0)) | M22: =IF(B22="","",IFERROR(VLOOKUP(B22,'F01 - _Données Expatriés'!$A$6:$K$20,2,FALSE)&" "&VLOOKUP(B22,'F01 - _Données Expatriés'!$A$6:$K$20,3,FALSE),"")) | N22: =IF(J22="","",IFERROR(COUNTIF($J$6:$J$115,J22),0))
... H115: =IF(OR(G115="",F115=""),"",IFERROR(G115-F115,0)) | M115: =IF(B115="","",IFERROR(VLOOKUP(B115,'F01 - _Données Expatriés'!$A$6:$K$20,2,FALSE)&" "&VLOOKUP(B115,'F01 - _Données Expatriés'!$A$6:$K$20,3,FALSE),"")) | N115: =IF(J115="","",IFERROR(COUNTIF($J$6:$J$115,J115),0))

Sheet F06 - 4-Indemnités Expat.
A2: 4-INDEMNITÉS D'EXPATRIATION
A3: TABLEAU DYNAMIQUE — Saisissez dans la zone prévue ci-dessous
A5: Code Indemnité | B5: Matricule Expat. | C5: Catégorie Indemnité | D5: Montant Brut (FCFA) | E5: Devise | F5: Taux Change | G5: Montant Converti (FCFA) | H5: Mois Versement | I5: Mode Paiement | J5: Statut | K5: Base Légale | L5: Observations
A6: IND-001 | B6: EXP-001 | C6: Prime d'expatriation | D6: 800000 | E6: EUR | F6: 655.96 | G6: =IF(OR(D6="",F6=""),"",IFERROR(D6*F6,0)) | H6: Janvier 2025 | I6: Virement international | J6: Validé | K6: Art. 12 CC Expatrié | M6: =IF(B6="","",IFERROR(VLOOKUP(B6,'F01 - _Données Expatriés'!$A$6:$K$20,2,FALSE)&" "&VLOOKUP(B6,'F01 - _Données Expatriés'!$A$6:$K$20,3,FALSE),"")) | N6: =IF(B6="","",IFERROR(SUMIF($B$6:$B$115,B6,$G$6:$G$115),0))
A7: IND-002 | B7: EXP-001 | C7: Indemnité logement | D7: 500000 | E7: EUR | F7: 655.96 | G7: =IF(OR(D7="",F7=""),"",IFERROR(D7*F7,0)) | H7: Janvier 2025 | I7: Virement international | J7: Validé | K7: Art. 8 CC Expatrié | M7: =IF(B7="","",IFERROR(VLOOKUP(B7,'F01 - _Données Expatriés'!$A$6:$K$20,2,FALSE)&" "&VLOOKUP(B7,'F01 - _Données Expatriés'!$A$6:$K$20,3,FALSE),"")) | N7: =IF(B7="","",IFERROR(SUMIF($B$6:$B$115,B7,$G$6:$G$115),0))
A8: IND-003 | B8: EXP-002 | C8: Prime d'expatriation | D8: 650000 | E8: EUR | F8: 655.96 | G8: =IF(OR(D8="",F8=""),"",IFERROR(D8*F8,0)) | H8: Janvier 2025 | I8: Virement international | J8: Validé | K8: Art. 12 CC Expatrié | M8: =IF(B8="","",IFERROR(VLOOKUP(B8,'F01 - _Données Expatriés'!$A$6:$K$20,2,FALSE)&" "&VLOOKUP(B8,'F01 - _Données Expatriés'!$A$6:$K$20,3,FALSE),"")) | N8: =IF(B8="","",IFERROR(SUMIF($B$6:$B$115,B8,$G$6:$G$115),0))
A9: IND-004 | B9: EXP-002 | C9: Indemnité scolarité | D9: 300000 | E9: EUR | F9: 655.96 | G9: =IF(OR(D9="",F9=""),"",IFERROR(D9*F9,0)) | H9: Janvier 2025 | I9: Virement international | J9: En attente | K9: Art. 15 CC Expatrié | L9: 2 enfants | M9: =IF(B9="","",IFERROR(VLOOKUP(B9,'F01 - _Données Expatriés'!$A$6:$K$20,2,FALSE)&" "&VLOOKUP(B9,'F01 - _Données Expatriés'!$A$6:$K$20,3,FALSE),"")) | N9: =IF(B9="","",IFERROR(SUMIF($B$6:$B$115,B9,$G$6:$G$115),0))
A10: IND-005 | B10: EXP-003 | C10: Prime de difficulté | D10: 400000 | E10: EUR | F10: 655.96 | G10: =IF(OR(D10="",F10=""),"",IFERROR(D10*F10,0)) | H10: Janvier 2025 | I10: Virement international | J10: Validé | K10: Art. 20 CC Expatrié | M10: =IF(B10="","",IFERROR(VLOOKUP(B10,'F01 - _Données Expatriés'!$A$6:$K$20,2,FALSE)&" "&VLOOKUP(B10,'F01 - _Données Expatriés'!$A$6:$K$20,3,FALSE),"")) | N10: =IF(B10="","",IFERROR(SUMIF($B$6:$B$115,B10,$G$6:$G$115),0))
G11: =IF(OR(D11="",F11=""),"",IFERROR(D11*F11,0)) | M11: =IF(B11="","",IFERROR(VLOOKUP(B11,'F01 - _Données Expatriés'!$A$6:$K$20,2,FALSE)&" "&VLOOKUP(B11,'F01 - _Données Expatriés'!$A$6:$K$20,3,FALSE),"")) | N11: =IF(B11="","",IFERROR(SUMIF($B$6:$B$115,B11,$G$6:$G$115),0))
G12: =IF(OR(D12="",F12=""),"",IFERROR(D12*F12,0)) | M12: =IF(B12="","",IFERROR(VLOOKUP(B12,'F01 - _Données Expatriés'!$A$6:$K$20,2,FALSE)&" "&VLOOKUP(B12,'F01 - _Données Expatriés'!$A$6:$K$20,3,FALSE),"")) | N12: =IF(B12="","",IFERROR(SUMIF($B$6:$B$115,B12,$G$6:$G$115),0))
G13: =IF(OR(D13="",F13=""),"",IFERROR(D13*F13,0)) | M13: =IF(B13="","",IFERROR(VLOOKUP(B13,'F01 - _Données Expatriés'!$A$6:$K$20,2,FALSE)&" "&VLOOKUP(B13,'F01 - _Données Expatriés'!$A$6:$K$20,3,FALSE),"")) | N13: =IF(B13="","",IFERROR(SUMIF($B$6:$B$115,B13,$G$6:$G$115),0))
G14: =IF(OR(D14="",F14=""),"",IFERROR(D14*F14,0)) | M14: =IF(B14="","",IFERROR(VLOOKUP(B14,'F01 - _Données Expatriés'!$A$6:$K$20,2,FALSE)&" "&VLOOKUP(B14,'F01 - _Données Expatriés'!$A$6:$K$20,3,FALSE),"")) | N14: =IF(B14="","",IFERROR(SUMIF($B$6:$B$115,B14,$G$6:$G$115),0))
G15: =IF(OR(D15="",F15=""),"",IFERROR(D15*F15,0)) | M15: =IF(B15="","",IFERROR(VLOOKUP(B15,'F01 - _Données Expatriés'!$A$6:$K$20,2,FALSE)&" "&VLOOKUP(B15,'F01 - _Données Expatriés'!$A$6:$K$20,3,FALSE),"")) | N15: =IF(B15="","",IFERROR(SUMIF($B$6:$B$115,B15,$G$6:$G$115),0))
G16: =IF(OR(D16="",F16=""),"",IFERROR(D16*F16,0)) | M16: =IF(B16="","",IFERROR(VLOOKUP(B16,'F01 - _Données Expatriés'!$A$6:$K$20,2,FALSE)&" "&VLOOKUP(B16,'F01 - _Données Expatriés'!$A$6:$K$20,3,FALSE),"")) | N16: =IF(B16="","",IFERROR(SUMIF($B$6:$B$115,B16,$G$6:$G$115),0))
G17: =IF(OR(D17="",F17=""),"",IFERROR(D17*F17,0)) | M17: =IF(B17="","",IFERROR(VLOOKUP(B17,'F01 - _Données Expatriés'!$A$6:$K$20,2,FALSE)&" "&VLOOKUP(B17,'F01 - _Données Expatriés'!$A$6:$K$20,3,FALSE),"")) | N17: =IF(B17="","",IFERROR(SUMIF($B$6:$B$115,B17,$G$6:$G$115),0))
G18: =IF(OR(D18="",F18=""),"",IFERROR(D18*F18,0)) | M18: =IF(B18="","",IFERROR(VLOOKUP(B18,'F01 - _Données Expatriés'!$A$6:$K$20,2,FALSE)&" "&VLOOKUP(B18,'F01 - _Données Expatriés'!$A$6:$K$20,3,FALSE),"")) | N18: =IF(B18="","",IFERROR(SUMIF($B$6:$B$115,B18,$G$6:$G$115),0))
G19: =IF(OR(D19="",F19=""),"",IFERROR(D19*F19,0)) | M19: =IF(B19="","",IFERROR(VLOOKUP(B19,'F01 - _Données Expatriés'!$A$6:$K$20,2,FALSE)&" "&VLOOKUP(B19,'F01 - _Données Expatriés'!$A$6:$K$20,3,FALSE),"")) | N19: =IF(B19="","",IFERROR(SUMIF($B$6:$B$115,B19,$G$6:$G$115),0))
G20: =IF(OR(D20="",F20=""),"",IFERROR(D20*F20,0)) | M20: =IF(B20="","",IFERROR(VLOOKUP(B20,'F01 - _Données Expatriés'!$A$6:$K$20,2,FALSE)&" "&VLOOKUP(B20,'F01 - _Données Expatriés'!$A$6:$K$20,3,FALSE),"")) | N20: =IF(B20="","",IFERROR(SUMIF($B$6:$B$115,B20,$G$6:$G$115),0))
G21: =IF(OR(D21="",F21=""),"",IFERROR(D21*F21,0)) | M21: =IF(B21="","",IFERROR(VLOOKUP(B21,'F01 - _Données Expatriés'!$A$6:$K$20,2,FALSE)&" "&VLOOKUP(B21,'F01 - _Données Expatriés'!$A$6:$K$20,3,FALSE),"")) | N21: =IF(B21="","",IFERROR(SUMIF($B$6:$B$115,B21,$G$6:$G$115),0))
G22: =IF(OR(D22="",F22=""),"",IFERROR(D22*F22,0)) | M22: =IF(B22="","",IFERROR(VLOOKUP(B22,'F01 - _Données Expatriés'!$A$6:$K$20,2,FALSE)&" "&VLOOKUP(B22,'F01 - _Données Expatriés'!$A$6:$K$20,3,FALSE),"")) | N22: =IF(B22="","",IFERROR(SUMIF($B$6:$B$115,B22,$G$6:$G$115),0))
... G115: =IF(OR(D115="",F115=""),"",IFERROR(D115*F115,0)) | M115: =IF(B115="","",IFERROR(VLOOKUP(B115,'F01 - _Données Expatriés'!$A$6:$K$20,2,FALSE)&" "&VLOOKUP(B115,'F01 - _Données Expatriés'!$A$6:$K$20,3,FALSE),"")) | N115: =IF(B115="","",IFERROR(SUMIF($B$6:$B$115,B115,$G$6:$G$115),0))

Sheet F07 - 5-Logement Expatriés
A2: 5-LOGEMENT EXPATRIÉS
A3: TABLEAU DYNAMIQUE — Saisissez dans la zone prévue ci-dessous
A5: Code Logement | B5: Matricule Expat. | C5: Type Logement | D5: Quartier | E5: Loyer Mensuel (FCFA) | F5: Charges (FCFA) | G5: Coût Total (FCFA) | H5: Surface (m²) | I5: Nb Chambres | J5: Meublé | K5: Date Entrée | L5: Date Sortie | M5: Observations
A6: LOG-001 | B6: EXP-001 | C6: Fourni - Villa | D6: Cocody Riviera | E6: 1200000 | F6: 150000 | G6: =IF(OR(E6="",F6=""),"",E6+F6) | H6: 250 | I6: 4 | J6: Oui | K6: 44941 | M6: =IF(B6="","",IFERROR(VLOOKUP(B6,'F01 - _Données Expatriés'!$A$6:$K$20,2,FALSE)&" "&VLOOKUP(B6,'F01 - _Données Expatriés'!$A$6:$K$20,3,FALSE),"")) | N6: =IF(C6="","",IFERROR(AVERAGEIF($C$6:$C$115,C6,$E$6:$E$115),0))
A7: LOG-002 | B7: EXP-002 | C7: Fourni - Appartement | D7: Plateau | E7: 800000 | F7: 100000 | G7: =IF(OR(E7="",F7=""),"",E7+F7) | H7: 150 | I7: 3 | J7: Oui | K7: 45352 | M7: =IF(B7="","",IFERROR(VLOOKUP(B7,'F01 - _Données Expatriés'!$A$6:$K$20,2,FALSE)&" "&VLOOKUP(B7,'F01 - _Données Expatriés'!$A$6:$K$20,3,FALSE),"")) | N7: =IF(C7="","",IFERROR(AVERAGEIF($C$6:$C$115,C7,$E$6:$E$115),0))
A8: LOG-003 | B8: EXP-003 | C8: Fourni - Villa | D8: Cocody Palmeraie | E8: 1500000 | F8: 200000 | G8: =IF(OR(E8="",F8=""),"",E8+F8) | H8: 300 | I8: 5 | J8: Oui | K8: 44713 | M8: =IF(B8="","",IFERROR(VLOOKUP(B8,'F01 - _Données Expatriés'!$A$6:$K$20,2,FALSE)&" "&VLOOKUP(B8,'F01 - _Données Expatriés'!$A$6:$K$20,3,FALSE),"")) | N8: =IF(C8="","",IFERROR(AVERAGEIF($C$6:$C$115,C8,$E$6:$E$115),0))
A9: LOG-004 | B9: EXP-004 | C9: Indemnité logement | D9: Marcory | E9: 0 | F9: 0 | G9: =IF(OR(E9="",F9=""),"",E9+F9) | H9: 0 | I9: 0 | J9: N/A | M9: =IF(B9="","",IFERROR(VLOOKUP(B9,'F01 - _Données Expatriés'!$A$6:$K$20,2,FALSE)&" "&VLOOKUP(B9,'F01 - _Données Expatriés'!$A$6:$K$20,3,FALSE),"")) | N9: =IF(C9="","",IFERROR(AVERAGEIF($C$6:$C$115,C9,$E$6:$E$115),0))
A10: LOG-005 | B10: EXP-005 | C10: Fourni - Appartement | D10: Zone 4 | E10: 600000 | F10: 80000 | G10: =IF(OR(E10="",F10=""),"",E10+F10) | H10: 120 | I10: 2 | J10: Oui | K10: 45292 | M10: =IF(B10="","",IFERROR(VLOOKUP(B10,'F01 - _Données Expatriés'!$A$6:$K$20,2,FALSE)&" "&VLOOKUP(B10,'F01 - _Données Expatriés'!$A$6:$K$20,3,FALSE),"")) | N10: =IF(C10="","",IFERROR(AVERAGEIF($C$6:$C$115,C10,$E$6:$E$115),0))
G11: =IF(OR(E11="",F11=""),"",E11+F11) | M11: =IF(B11="","",IFERROR(VLOOKUP(B11,'F01 - _Données Expatriés'!$A$6:$K$20,2,FALSE)&" "&VLOOKUP(B11,'F01 - _Données Expatriés'!$A$6:$K$20,3,FALSE),"")) | N11: =IF(C11="","",IFERROR(AVERAGEIF($C$6:$C$115,C11,$E$6:$E$115),0))
G12: =IF(OR(E12="",F12=""),"",E12+F12) | M12: =IF(B12="","",IFERROR(VLOOKUP(B12,'F01 - _Données Expatriés'!$A$6:$K$20,2,FALSE)&" "&VLOOKUP(B12,'F01 - _Données Expatriés'!$A$6:$K$20,3,FALSE),"")) | N12: =IF(C12="","",IFERROR(AVERAGEIF($C$6:$C$115,C12,$E$6:$E$115),0))
G13: =IF(OR(E13="",F13=""),"",E13+F13) | M13: =IF(B13="","",IFERROR(VLOOKUP(B13,'F01 - _Données Expatriés'!$A$6:$K$20,2,FALSE)&" "&VLOOKUP(B13,'F01 - _Données Expatriés'!$A$6:$K$20,3,FALSE),"")) | N13: =IF(C13="","",IFERROR(AVERAGEIF($C$6:$C$115,C13,$E$6:$E$115),0))
G14: =IF(OR(E14="",F14=""),"",E14+F14) | M14: =IF(B14="","",IFERROR(VLOOKUP(B14,'F01 - _Données Expatriés'!$A$6:$K$20,2,FALSE)&" "&VLOOKUP(B14,'F01 - _Données Expatriés'!$A$6:$K$20,3,FALSE),"")) | N14: =IF(C14="","",IFERROR(AVERAGEIF($C$6:$C$115,C14,$E$6:$E$115),0))
G15: =IF(OR(E15="",F15=""),"",E15+F15) | M15: =IF(B15="","",IFERROR(VLOOKUP(B15,'F01 - _Données Expatriés'!$A$6:$K$20,2,FALSE)&" "&VLOOKUP(B15,'F01 - _Données Expatriés'!$A$6:$K$20,3,FALSE),"")) | N15: =IF(C15="","",IFERROR(AVERAGEIF($C$6:$C$115,C15,$E$6:$E$115),0))
G16: =IF(OR(E16="",F16=""),"",E16+F16) | M16: =IF(B16="","",IFERROR(VLOOKUP(B16,'F01 - _Données Expatriés'!$A$6:$K$20,2,FALSE)&" "&VLOOKUP(B16,'F01 - _Données Expatriés'!$A$6:$K$20,3,FALSE),"")) | N16: =IF(C16="","",IFERROR(AVERAGEIF($C$6:$C$115,C16,$E$6:$E$115),0))
G17: =IF(OR(E17="",F17=""),"",E17+F17) | M17: =IF(B17="","",IFERROR(VLOOKUP(B17,'F01 - _Données Expatriés'!$A$6:$K$20,2,FALSE)&" "&VLOOKUP(B17,'F01 - _Données Expatriés'!$A$6:$K$20,3,FALSE),"")) | N17: =IF(C17="","",IFERROR(AVERAGEIF($C$6:$C$115,C17,$E$6:$E$115),0))
G18: =IF(OR(E18="",F18=""),"",E18+F18) | M18: =IF(B18="","",IFERROR(VLOOKUP(B18,'F01 - _Données Expatriés'!$A$6:$K$20,2,FALSE)&" "&VLOOKUP(B18,'F01 - _Données Expatriés'!$A$6:$K$20,3,FALSE),"")) | N18: =IF(C18="","",IFERROR(AVERAGEIF($C$6:$C$115,C18,$E$6:$E$115),0))
G19: =IF(OR(E19="",F19=""),"",E19+F19) | M19: =IF(B19="","",IFERROR(VLOOKUP(B19,'F01 - _Données Expatriés'!$A$6:$K$20,2,FALSE)&" "&VLOOKUP(B19,'F01 - _Données Expatriés'!$A$6:$K$20,3,FALSE),"")) | N19: =IF(C19="","",IFERROR(AVERAGEIF($C$6:$C$115,C19,$E$6:$E$115),0))
G20: =IF(OR(E20="",F20=""),"",E20+F20) | M20: =IF(B20="","",IFERROR(VLOOKUP(B20,'F01 - _Données Expatriés'!$A$6:$K$20,2,FALSE)&" "&VLOOKUP(B20,'F01 - _Données Expatriés'!$A$6:$K$20,3,FALSE),"")) | N20: =IF(C20="","",IFERROR(AVERAGEIF($C$6:$C$115,C20,$E$6:$E$115),0))
G21: =IF(OR(E21="",F21=""),"",E21+F21) | M21: =IF(B21="","",IFERROR(VLOOKUP(B21,'F01 - _Données Expatriés'!$A$6:$K$20,2,FALSE)&" "&VLOOKUP(B21,'F01 - _Données Expatriés'!$A$6:$K$20,3,FALSE),"")) | N21: =IF(C21="","",IFERROR(AVERAGEIF($C$6:$C$115,C21,$E$6:$E$115),0))
G22: =IF(OR(E22="",F22=""),"",E22+F22) | M22: =IF(B22="","",IFERROR(VLOOKUP(B22,'F01 - _Données Expatriés'!$A$6:$K$20,2,FALSE)&" "&VLOOKUP(B22,'F01 - _Données Expatriés'!$A$6:$K$20,3,FALSE),"")) | N22: =IF(C22="","",IFERROR(AVERAGEIF($C$6:$C$115,C22,$E$6:$E$115),0))
... G115: =IF(OR(E115="",F115=""),"",E115+F115) | M115: =IF(B115="","",IFERROR(VLOOKUP(B115,'F01 - _Données Expatriés'!$A$6:$K$20,2,FALSE)&" "&VLOOKUP(B115,'F01 - _Données Expatriés'!$A$6:$K$20,3,FALSE),"")) | N115: =IF(C115="","",IFERROR(AVERAGEIF($C$6:$C$115,C115,$E$6:$E$115),0))

Sheet F08 - 6-Scolarité Enfants
A2: 6-SCOLARITÉ ENFANTS D'EXPATRIÉS
A3: TABLEAU DYNAMIQUE — Saisissez dans la zone prévue ci-dessous
A5: Code Scol. | B5: Matricule Expat. | C5: Nom Enfant | D5: Âge Enfant | E5: Type École | F5: Nom Établissement | G5: Frais Scolarité (FCFA) | H5: Frais Inscription (FCFA) | I5: Coût Annuel (FCFA) | J5: Prise en Charge (%) | K5: Année Scolaire | L5: Statut | M5: Observations
A6: SCO-001 | B6: EXP-002 | C6: Dupont Lucas | D6: 8 | E6: École française | F6: Lycée Sainte-Marie | G6: 3500000 | H6: 250000 | I6: =IF(OR(G6="",H6=""),"",G6+H6) | J6: 80 | K6: 2024-2025 | L6: Validé | M6: =IF(B6="","",IFERROR(VLOOKUP(B6,'F01 - _Données Expatriés'!$A$6:$K$20,2,FALSE)&" "&VLOOKUP(B6,'F01 - _Données Expatriés'!$A$6:$K$20,3,FALSE),"")) | N6: =IF(B6="","",IFERROR(SUMIF($B$6:$B$115,B6,$I$6:$I$115),0))
A7: SCO-002 | B7: EXP-002 | C7: Dupont Emma | D7: 12 | E7: École internationale | F7: International School Abidjan | G7: 5500000 | H7: 400000 | I7: =IF(OR(G7="",H7=""),"",G7+H7) | J7: 80 | K7: 2024-2025 | L7: Validé | M7: =IF(B7="","",IFERROR(VLOOKUP(B7,'F01 - _Données Expatriés'!$A$6:$K$20,2,FALSE)&" "&VLOOKUP(B7,'F01 - _Données Expatriés'!$A$6:$K$20,3,FALSE),"")) | N7: =IF(B7="","",IFERROR(SUMIF($B$6:$B$115,B7,$I$6:$I$115),0))
A8: SCO-003 | B8: EXP-003 | C8: Mueller Anna | D8: 6 | E8: École allemande | F8: École Allemande Abidjan | G8: 4200000 | H8: 300000 | I8: =IF(OR(G8="",H8=""),"",G8+H8) | J8: 100 | K8: 2024-2025 | L8: Validé | M8: =IF(B8="","",IFERROR(VLOOKUP(B8,'F01 - _Données Expatriés'!$A$6:$K$20,2,FALSE)&" "&VLOOKUP(B8,'F01 - _Données Expatriés'!$A$6:$K$20,3,FALSE),"")) | N8: =IF(B8="","",IFERROR(SUMIF($B$6:$B$115,B8,$I$6:$I$115),0))
A9: SCO-004 | B9: EXP-007 | C9: Mensah Ade | D9: 10 | E9: École internationale | F9: International School Abidjan | G9: 5500000 | H9: 400000 | I9: =IF(OR(G9="",H9=""),"",G9+H9) | J9: 70 | K9: 2024-2025 | L9: Validé | M9: =IF(B9="","",IFERROR(VLOOKUP(B9,'F01 - _Données Expatriés'!$A$6:$K$20,2,FALSE)&" "&VLOOKUP(B9,'F01 - _Données Expatriés'!$A$6:$K$20,3,FALSE),"")) | N9: =IF(B9="","",IFERROR(SUMIF($B$6:$B$115,B9,$I$6:$I$115),0))
A10: SCO-005 | B10: EXP-007 | C10: Mensah Ngozi | D10: 7 | E10: École internationale | F10: International School Abidjan | G10: 5000000 | H10: 350000 | I10: =IF(OR(G10="",H10=""),"",G10+H10) | J10: 70 | K10: 2024-2025 | L10: Validé | M10: =IF(B10="","",IFERROR(VLOOKUP(B10,'F01 - _Données Expatriés'!$A$6:$K$20,2,FALSE)&" "&VLOOKUP(B10,'F01 - _Données Expatriés'!$A$6:$K$20,3,FALSE),"")) | N10: =IF(B10="","",IFERROR(SUMIF($B$6:$B$115,B10,$I$6:$I$115),0))
I11: =IF(OR(G11="",H11=""),"",G11+H11) | M11: =IF(B11="","",IFERROR(VLOOKUP(B11,'F01 - _Données Expatriés'!$A$6:$K$20,2,FALSE)&" "&VLOOKUP(B11,'F01 - _Données Expatriés'!$A$6:$K$20,3,FALSE),"")) | N11: =IF(B11="","",IFERROR(SUMIF($B$6:$B$115,B11,$I$6:$I$115),0))
I12: =IF(OR(G12="",H12=""),"",G12+H12) | M12: =IF(B12="","",IFERROR(VLOOKUP(B12,'F01 - _Données Expatriés'!$A$6:$K$20,2,FALSE)&" "&VLOOKUP(B12,'F01 - _Données Expatriés'!$A$6:$K$20,3,FALSE),"")) | N12: =IF(B12="","",IFERROR(SUMIF($B$6:$B$115,B12,$I$6:$I$115),0))
I13: =IF(OR(G13="",H13=""),"",G13+H13) | M13: =IF(B13="","",IFERROR(VLOOKUP(B13,'F01 - _Données Expatriés'!$A$6:$K$20,2,FALSE)&" "&VLOOKUP(B13,'F01 - _Données Expatriés'!$A$6:$K$20,3,FALSE),"")) | N13: =IF(B13="","",IFERROR(SUMIF($B$6:$B$115,B13,$I$6:$I$115),0))
I14: =IF(OR(G14="",H14=""),"",G14+H14) | M14: =IF(B14="","",IFERROR(VLOOKUP(B14,'F01 - _Données Expatriés'!$A$6:$K$20,2,FALSE)&" "&VLOOKUP(B14,'F01 - _Données Expatriés'!$A$6:$K$20,3,FALSE),"")) | N14: =IF(B14="","",IFERROR(SUMIF($B$6:$B$115,B14,$I$6:$I$115),0))
I15: =IF(OR(G15="",H15=""),"",G15+H15) | M15: =IF(B15="","",IFERROR(VLOOKUP(B15,'F01 - _Données Expatriés'!$A$6:$K$20,2,FALSE)&" "&VLOOKUP(B15,'F01 - _Données Expatriés'!$A$6:$K$20,3,FALSE),"")) | N15: =IF(B15="","",IFERROR(SUMIF($B$6:$B$115,B15,$I$6:$I$115),0))
I16: =IF(OR(G16="",H16=""),"",G16+H16) | M16: =IF(B16="","",IFERROR(VLOOKUP(B16,'F01 - _Données Expatriés'!$A$6:$K$20,2,FALSE)&" "&VLOOKUP(B16,'F01 - _Données Expatriés'!$A$6:$K$20,3,FALSE),"")) | N16: =IF(B16="","",IFERROR(SUMIF($B$6:$B$115,B16,$I$6:$I$115),0))
I17: =IF(OR(G17="",H17=""),"",G17+H17) | M17: =IF(B17="","",IFERROR(VLOOKUP(B17,'F01 - _Données Expatriés'!$A$6:$K$20,2,FALSE)&" "&VLOOKUP(B17,'F01 - _Données Expatriés'!$A$6:$K$20,3,FALSE),"")) | N17: =IF(B17="","",IFERROR(SUMIF($B$6:$B$115,B17,$I$6:$I$115),0))
I18: =IF(OR(G18="",H18=""),"",G18+H18) | M18: =IF(B18="","",IFERROR(VLOOKUP(B18,'F01 - _Données Expatriés'!$A$6:$K$20,2,FALSE)&" "&VLOOKUP(B18,'F01 - _Données Expatriés'!$A$6:$K$20,3,FALSE),"")) | N18: =IF(B18="","",IFERROR(SUMIF($B$6:$B$115,B18,$I$6:$I$115),0))
I19: =IF(OR(G19="",H19=""),"",G19+H19) | M19: =IF(B19="","",IFERROR(VLOOKUP(B19,'F01 - _Données Expatriés'!$A$6:$K$20,2,FALSE)&" "&VLOOKUP(B19,'F01 - _Données Expatriés'!$A$6:$K$20,3,FALSE),"")) | N19: =IF(B19="","",IFERROR(SUMIF($B$6:$B$115,B19,$I$6:$I$115),0))
I20: =IF(OR(G20="",H20=""),"",G20+H20) | M20: =IF(B20="","",IFERROR(VLOOKUP(B20,'F01 - _Données Expatriés'!$A$6:$K$20,2,FALSE)&" "&VLOOKUP(B20,'F01 - _Données Expatriés'!$A$6:$K$20,3,FALSE),"")) | N20: =IF(B20="","",IFERROR(SUMIF($B$6:$B$115,B20,$I$6:$I$115),0))
I21: =IF(OR(G21="",H21=""),"",G21+H21) | M21: =IF(B21="","",IFERROR(VLOOKUP(B21,'F01 - _Données Expatriés'!$A$6:$K$20,2,FALSE)&" "&VLOOKUP(B21,'F01 - _Données Expatriés'!$A$6:$K$20,3,FALSE),"")) | N21: =IF(B21="","",IFERROR(SUMIF($B$6:$B$115,B21,$I$6:$I$115),0))
I22: =IF(OR(G22="",H22=""),"",G22+H22) | M22: =IF(B22="","",IFERROR(VLOOKUP(B22,'F01 - _Données Expatriés'!$A$6:$K$20,2,FALSE)&" "&VLOOKUP(B22,'F01 - _Données Expatriés'!$A$6:$K$20,3,FALSE),"")) | N22: =IF(B22="","",IFERROR(SUMIF($B$6:$B$115,B22,$I$6:$I$115),0))
... I115: =IF(OR(G115="",H115=""),"",G115+H115) | M115: =IF(B115="","",IFERROR(VLOOKUP(B115,'F01 - _Données Expatriés'!$A$6:$K$20,2,FALSE)&" "&VLOOKUP(B115,'F01 - _Données Expatriés'!$A$6:$K$20,3,FALSE),"")) | N115: =IF(B115="","",IFERROR(SUMIF($B$6:$B$115,B115,$I$6:$I$115),0))

Sheet F09 - 7-Fiscalité Transfront.
A2: 7-FISCALITÉ TRANSFRONTALIÈRE
A3: TABLEAU DYNAMIQUE — Saisissez dans la zone prévue ci-dessous
A5: Code Fiscal | B5: Matricule Expat. | C5: Pays d'Impôt | D5: Régime Fiscal | E5: Revenu Imposable (FCFA) | F5: Impôt Local (FCFA) | G5: Impôt Étranger (FCFA) | H5: Crédit d'Impôt (FCFA) | I5: Impôt Net (FCFA) | J5: Convention Fiscale | K5: Taux Effectif (%) | L5: Année Fiscale | M5: Observations
A6: FISC-001 | B6: EXP-001 | C6: France / CI | D6: Régime impatrié | E6: 54000000 | F6: 4800000 | G6: 12000000 | H6: 12000000 | I6: =IF(OR(F6="",H6=""),"",MAX(F6-H6,0)) | J6: Oui | K6: =IF(OR(E6="",I6=""),"",IFERROR(I6/E6*100,0)) | L6: 2024 | M6: Convention franco-ivoirienne | N6: =IF(B6="","",IFERROR(VLOOKUP(B6,'F01 - _Données Expatriés'!$A$6:$K$20,2,FALSE)&" "&VLOOKUP(B6,'F01 - _Données Expatriés'!$A$6:$K$20,3,FALSE),""))
A7: FISC-002 | B7: EXP-002 | C7: France / CI | D7: Convention fiscale | E7: 45600000 | F7: 3600000 | G7: 9000000 | H7: 9000000 | I7: =IF(OR(F7="",H7=""),"",MAX(F7-H7,0)) | J7: Oui | K7: =IF(OR(E7="",I7=""),"",IFERROR(I7/E7*100,0)) | L7: 2024 | N7: =IF(B7="","",IFERROR(VLOOKUP(B7,'F01 - _Données Expatriés'!$A$6:$K$20,2,FALSE)&" "&VLOOKUP(B7,'F01 - _Données Expatriés'!$A$6:$K$20,3,FALSE),""))
A8: FISC-003 | B8: EXP-003 | C8: Allemagne / CI | D8: Régime impatrié | E8: 62400000 | F8: 5200000 | G8: 15000000 | H8: 15000000 | I8: =IF(OR(F8="",H8=""),"",MAX(F8-H8,0)) | J8: Oui | K8: =IF(OR(E8="",I8=""),"",IFERROR(I8/E8*100,0)) | L8: 2024 | M8: Exonération 8 ans | N8: =IF(B8="","",IFERROR(VLOOKUP(B8,'F01 - _Données Expatriés'!$A$6:$K$20,2,FALSE)&" "&VLOOKUP(B8,'F01 - _Données Expatriés'!$A$6:$K$20,3,FALSE),""))
A9: FISC-004 | B9: EXP-005 | C9: Corée du Sud / CI | D9: Convention fiscale | E9: 50400000 | F9: 4000000 | G9: 11000000 | H9: 11000000 | I9: =IF(OR(F9="",H9=""),"",MAX(F9-H9,0)) | J9: Oui | K9: =IF(OR(E9="",I9=""),"",IFERROR(I9/E9*100,0)) | L9: 2024 | N9: =IF(B9="","",IFERROR(VLOOKUP(B9,'F01 - _Données Expatriés'!$A$6:$K$20,2,FALSE)&" "&VLOOKUP(B9,'F01 - _Données Expatriés'!$A$6:$K$20,3,FALSE),""))
A10: FISC-005 | B10: EXP-008 | C10: France / CI | D10: Régime impatrié | E10: 60000000 | F10: 5000000 | G10: 13500000 | H10: 13500000 | I10: =IF(OR(F10="",H10=""),"",MAX(F10-H10,0)) | J10: Oui | K10: =IF(OR(E10="",I10=""),"",IFERROR(I10/E10*100,0)) | L10: 2024 | N10: =IF(B10="","",IFERROR(VLOOKUP(B10,'F01 - _Données Expatriés'!$A$6:$K$20,2,FALSE)&" "&VLOOKUP(B10,'F01 - _Données Expatriés'!$A$6:$K$20,3,FALSE),""))
I11: =IF(OR(F11="",H11=""),"",MAX(F11-H11,0)) | K11: =IF(OR(E11="",I11=""),"",IFERROR(I11/E11*100,0)) | N11: =IF(B11="","",IFERROR(VLOOKUP(B11,'F01 - _Données Expatriés'!$A$6:$K$20,2,FALSE)&" "&VLOOKUP(B11,'F01 - _Données Expatriés'!$A$6:$K$20,3,FALSE),""))
I12: =IF(OR(F12="",H12=""),"",MAX(F12-H12,0)) | K12: =IF(OR(E12="",I12=""),"",IFERROR(I12/E12*100,0)) | N12: =IF(B12="","",IFERROR(VLOOKUP(B12,'F01 - _Données Expatriés'!$A$6:$K$20,2,FALSE)&" "&VLOOKUP(B12,'F01 - _Données Expatriés'!$A$6:$K$20,3,FALSE),""))
I13: =IF(OR(F13="",H13=""),"",MAX(F13-H13,0)) | K13: =IF(OR(E13="",I13=""),"",IFERROR(I13/E13*100,0)) | N13: =IF(B13="","",IFERROR(VLOOKUP(B13,'F01 - _Données Expatriés'!$A$6:$K$20,2,FALSE)&" "&VLOOKUP(B13,'F01 - _Données Expatriés'!$A$6:$K$20,3,FALSE),""))
I14: =IF(OR(F14="",H14=""),"",MAX(F14-H14,0)) | K14: =IF(OR(E14="",I14=""),"",IFERROR(I14/E14*100,0)) | N14: =IF(B14="","",IFERROR(VLOOKUP(B14,'F01 - _Données Expatriés'!$A$6:$K$20,2,FALSE)&" "&VLOOKUP(B14,'F01 - _Données Expatriés'!$A$6:$K$20,3,FALSE),""))
I15: =IF(OR(F15="",H15=""),"",MAX(F15-H15,0)) | K15: =IF(OR(E15="",I15=""),"",IFERROR(I15/E15*100,0)) | N15: =IF(B15="","",IFERROR(VLOOKUP(B15,'F01 - _Données Expatriés'!$A$6:$K$20,2,FALSE)&" "&VLOOKUP(B15,'F01 - _Données Expatriés'!$A$6:$K$20,3,FALSE),""))
I16: =IF(OR(F16="",H16=""),"",MAX(F16-H16,0)) | K16: =IF(OR(E16="",I16=""),"",IFERROR(I16/E16*100,0)) | N16: =IF(B16="","",IFERROR(VLOOKUP(B16,'F01 - _Données Expatriés'!$A$6:$K$20,2,FALSE)&" "&VLOOKUP(B16,'F01 - _Données Expatriés'!$A$6:$K$20,3,FALSE),""))
I17: =IF(OR(F17="",H17=""),"",MAX(F17-H17,0)) | K17: =IF(OR(E17="",I17=""),"",IFERROR(I17/E17*100,0)) | N17: =IF(B17="","",IFERROR(VLOOKUP(B17,'F01 - _Données Expatriés'!$A$6:$K$20,2,FALSE)&" "&VLOOKUP(B17,'F01 - _Données Expatriés'!$A$6:$K$20,3,FALSE),""))
I18: =IF(OR(F18="",H18=""),"",MAX(F18-H18,0)) | K18: =IF(OR(E18="",I18=""),"",IFERROR(I18/E18*100,0)) | N18: =IF(B18="","",IFERROR(VLOOKUP(B18,'F01 - _Données Expatriés'!$A$6:$K$20,2,FALSE)&" "&VLOOKUP(B18,'F01 - _Données Expatriés'!$A$6:$K$20,3,FALSE),""))
I19: =IF(OR(F19="",H19=""),"",MAX(F19-H19,0)) | K19: =IF(OR(E19="",I19=""),"",IFERROR(I19/E19*100,0)) | N19: =IF(B19="","",IFERROR(VLOOKUP(B19,'F01 - _Données Expatriés'!$A$6:$K$20,2,FALSE)&" "&VLOOKUP(B19,'F01 - _Données Expatriés'!$A$6:$K$20,3,FALSE),""))
I20: =IF(OR(F20="",H20=""),"",MAX(F20-H20,0)) | K20: =IF(OR(E20="",I20=""),"",IFERROR(I20/E20*100,0)) | N20: =IF(B20="","",IFERROR(VLOOKUP(B20,'F01 - _Données Expatriés'!$A$6:$K$20,2,FALSE)&" "&VLOOKUP(B20,'F01 - _Données Expatriés'!$A$6:$K$20,3,FALSE),""))
I21: =IF(OR(F21="",H21=""),"",MAX(F21-H21,0)) | K21: =IF(OR(E21="",I21=""),"",IFERROR(I21/E21*100,0)) | N21: =IF(B21="","",IFERROR(VLOOKUP(B21,'F01 - _Données Expatriés'!$A$6:$K$20,2,FALSE)&" "&VLOOKUP(B21,'F01 - _Données Expatriés'!$A$6:$K$20,3,FALSE),""))
I22: =IF(OR(F22="",H22=""),"",MAX(F22-H22,0)) | K22: =IF(OR(E22="",I22=""),"",IFERROR(I22/E22*100,0)) | N22: =IF(B22="","",IFERROR(VLOOKUP(B22,'F01 - _Données Expatriés'!$A$6:$K$20,2,FALSE)&" "&VLOOKUP(B22,'F01 - _Données Expatriés'!$A$6:$K$20,3,FALSE),""))
... I115: =IF(OR(F115="",H115=""),"",MAX(F115-H115,0)) | K115: =IF(OR(E115="",I115=""),"",IFERROR(I115/E115*100,0)) | N115: =IF(B115="","",IFERROR(VLOOKUP(B115,'F01 - _Données Expatriés'!$A$6:$K$20,2,FALSE)&" "&VLOOKUP(B115,'F01 - _Données Expatriés'!$A$6:$K$20,3,FALSE),""))

Sheet F10 - 8-Préparation Départ
A2: 8-PRÉPARATION AU DÉPART
A3: TABLEAU DYNAMIQUE — Saisissez dans la zone prévue ci-dessous
A5: Code Prépa. | B5: Matricule Expat. | C5: Pays Destination | D5: Type Mission | E5: Date Départ Prévu | F5: Briefing Sécurité | G5: Visa Obtenu | H5: Logement Confirmé | I5: Assurance Rapatri. | J5: Formation Inter-cult. | K5: Enfant(s) Scolarisé(s) | L5: Kit Accueil Remis | M5: Statut Prépa. | N5: Observations
A6: PREP-001 | B6: EXP-001 | C6: Côte d'Ivoire | D6: Expatriation longue | E6: 44936 | F6: Oui | G6: Oui | H6: Oui | I6: Oui | J6: Oui | K6: N/A | L6: Oui | M6: Terminé | N6: =IF(A6="","",IF(AND(F6="Oui",G6="Oui",H6="Oui",I6="Oui",K6="Oui"),"COMPLET","INCOMPLET"))
A7: PREP-002 | B7: EXP-002 | C7: Côte d'Ivoire | D7: Expatriation longue | E7: 45342 | F7: Oui | G7: Oui | H7: Oui | I7: Oui | J7: Oui | K7: En cours | L7: Oui | M7: Terminé | N7: =IF(A7="","",IF(AND(F7="Oui",G7="Oui",H7="Oui",I7="Oui",K7="Oui"),"COMPLET","INCOMPLET"))
A8: PREP-003 | B8: EXP-005 | C8: Côte d'Ivoire | D8: Détachement | E8: 45275 | F8: Oui | G8: Oui | H8: Oui | I8: Oui | J8: Oui | K8: Oui | L8: Oui | M8: Terminé | N8: =IF(A8="","",IF(AND(F8="Oui",G8="Oui",H8="Oui",I8="Oui",K8="Oui"),"COMPLET","INCOMPLET"))
A9: PREP-004 | B9: EXP-015 | C9: Côte d'Ivoire | D9: Expatriation longue | E9: 45717 | F9: En cours | G9: En cours | H9: En cours | I9: Oui | J9: En cours | K9: En cours | L9: Non | M9: En cours | N9: =IF(A9="","",IF(AND(F9="Oui",G9="Oui",H9="Oui",I9="Oui",K9="Oui"),"COMPLET","INCOMPLET"))
A10: PREP-005 | B10: EXP-014 | C10: Côte d'Ivoire | D10: Détachement | E10: 45762 | F10: Non | G10: Non | H10: En cours | I10: Non | J10: Non | K10: N/A | L10: Non | M10: En attente | N10: =IF(A10="","",IF(AND(F10="Oui",G10="Oui",H10="Oui",I10="Oui",K10="Oui"),"COMPLET","INCOMPLET"))
N11: =IF(A11="","",IF(AND(F11="Oui",G11="Oui",H11="Oui",I11="Oui",K11="Oui"),"COMPLET","INCOMPLET"))
N12: =IF(A12="","",IF(AND(F12="Oui",G12="Oui",H12="Oui",I12="Oui",K12="Oui"),"COMPLET","INCOMPLET"))
N13: =IF(A13="","",IF(AND(F13="Oui",G13="Oui",H13="Oui",I13="Oui",K13="Oui"),"COMPLET","INCOMPLET"))
N14: =IF(A14="","",IF(AND(F14="Oui",G14="Oui",H14="Oui",I14="Oui",K14="Oui"),"COMPLET","INCOMPLET"))
N15: =IF(A15="","",IF(AND(F15="Oui",G15="Oui",H15="Oui",I15="Oui",K15="Oui"),"COMPLET","INCOMPLET"))
N16: =IF(A16="","",IF(AND(F16="Oui",G16="Oui",H16="Oui",I16="Oui",K16="Oui"),"COMPLET","INCOMPLET"))
N17: =IF(A17="","",IF(AND(F17="Oui",G17="Oui",H17="Oui",I17="Oui",K17="Oui"),"COMPLET","INCOMPLET"))
N18: =IF(A18="","",IF(AND(F18="Oui",G18="Oui",H18="Oui",I18="Oui",K18="Oui"),"COMPLET","INCOMPLET"))
N19: =IF(A19="","",IF(AND(F19="Oui",G19="Oui",H19="Oui",I19="Oui",K19="Oui"),"COMPLET","INCOMPLET"))
N20: =IF(A20="","",IF(AND(F20="Oui",G20="Oui",H20="Oui",I20="Oui",K20="Oui"),"COMPLET","INCOMPLET"))
N21: =IF(A21="","",IF(AND(F21="Oui",G21="Oui",H21="Oui",I21="Oui",K21="Oui"),"COMPLET","INCOMPLET"))
N22: =IF(A22="","",IF(AND(F22="Oui",G22="Oui",H22="Oui",I22="Oui",K22="Oui"),"COMPLET","INCOMPLET"))
... N115: =IF(A115="","",IF(AND(F115="Oui",G115="Oui",H115="Oui",I115="Oui",K115="Oui"),"COMPLET","INCOMPLET"))

Sheet F11 - 9-Suivi Médico-Social
A2: 9-SUIVI MÉDICO-SOCIAL EXPATRIÉS
A3: TABLEAU DYNAMIQUE — Saisissez dans la zone prévue ci-dessous
A5: Code Suivi | B5: Matricule Expat. | C5: Date Visite | D5: Médecin Ref. | E5: Statut Médical | F5: Vaccinations à Jour | G5: Certificat Médical | H5: Assurance Santé | I5: Couverture Famille | J5: Nb Consultations (année) | K5: Problème Santé | L5: Suivi Psychologique | M5: Observations
A6: MED-001 | B6: EXP-001 | C6: 45672 | D6: Dr. Koné | E6: Apte | F6: Oui | G6: Oui | H6: AXA Intl. | I6: Oui | J6: 3 | K6: Aucun | L6: Non | N6: =IF(A6="","",IF(AND(E6="Apte",F6="Oui",G6="Oui",I6="Oui"),"CONFORME","ACTION REQUISE"))
A7: MED-002 | B7: EXP-002 | C7: 45677 | D7: Dr. Koné | E7: Apte | F7: Oui | G7: Oui | H7: AXA Intl. | I7: Oui | J7: 5 | K7: Paludisme (traité) | L7: Non | N7: =IF(A7="","",IF(AND(E7="Apte",F7="Oui",G7="Oui",I7="Oui"),"CONFORME","ACTION REQUISE"))
A8: MED-003 | B8: EXP-003 | C8: 45667 | D8: Dr. Bamba | E8: Apte avec restrictions | F8: Oui | G8: Oui | H8: Allianz Worldwide | I8: Oui | J8: 4 | K8: Hypertension | L8: Non | N8: =IF(A8="","",IF(AND(E8="Apte",F8="Oui",G8="Oui",I8="Oui"),"CONFORME","ACTION REQUISE"))
A9: MED-004 | B9: EXP-005 | C9: 45693 | D9: Dr. Koné | E9: Apte | F9: Non | G9: Oui | H9: Samsung Life | I9: Oui | J9: 2 | K9: Aucun | L9: Oui | M9: Suivi mensuel | N9: =IF(A9="","",IF(AND(E9="Apte",F9="Oui",G9="Oui",I9="Oui"),"CONFORME","ACTION REQUISE"))
A10: MED-005 | B10: EXP-007 | C10: 45682 | D10: Dr. Touré | E10: Apte | F10: Oui | G10: Oui | H10: AXA Intl. | I10: Oui | J10: 6 | K10: Diabète type 2 | L10: Oui | N10: =IF(A10="","",IF(AND(E10="Apte",F10="Oui",G10="Oui",I10="Oui"),"CONFORME","ACTION REQUISE"))
N11: =IF(A11="","",IF(AND(E11="Apte",F11="Oui",G11="Oui",I11="Oui"),"CONFORME","ACTION REQUISE"))
N12: =IF(A12="","",IF(AND(E12="Apte",F12="Oui",G12="Oui",I12="Oui"),"CONFORME","ACTION REQUISE"))
N13: =IF(A13="","",IF(AND(E13="Apte",F13="Oui",G13="Oui",I13="Oui"),"CONFORME","ACTION REQUISE"))
N14: =IF(A14="","",IF(AND(E14="Apte",F14="Oui",G14="Oui",I14="Oui"),"CONFORME","ACTION REQUISE"))
N15: =IF(A15="","",IF(AND(E15="Apte",F15="Oui",G15="Oui",I15="Oui"),"CONFORME","ACTION REQUISE"))
N16: =IF(A16="","",IF(AND(E16="Apte",F16="Oui",G16="Oui",I16="Oui"),"CONFORME","ACTION REQUISE"))
N17: =IF(A17="","",IF(AND(E17="Apte",F17="Oui",G17="Oui",I17="Oui"),"CONFORME","ACTION REQUISE"))
N18: =IF(A18="","",IF(AND(E18="Apte",F18="Oui",G18="Oui",I18="Oui"),"CONFORME","ACTION REQUISE"))
N19: =IF(A19="","",IF(AND(E19="Apte",F19="Oui",G19="Oui",I19="Oui"),"CONFORME","ACTION REQUISE"))
N20: =IF(A20="","",IF(AND(E20="Apte",F20="Oui",G20="Oui",I20="Oui"),"CONFORME","ACTION REQUISE"))
N21: =IF(A21="","",IF(AND(E21="Apte",F21="Oui",G21="Oui",I21="Oui"),"CONFORME","ACTION REQUISE"))
N22: =IF(A22="","",IF(AND(E22="Apte",F22="Oui",G22="Oui",I22="Oui"),"CONFORME","ACTION REQUISE"))
... N115: =IF(A115="","",IF(AND(E115="Apte",F115="Oui",G115="Oui",I115="Oui"),"CONFORME","ACTION REQUISE"))

Sheet F12 - 10-Réintégration
A2: 10-RÉINTÉGRATION EXPATRIÉS
A3: TABLEAU DYNAMIQUE — Saisissez dans la zone prévue ci-dessous
A5: Code Réint. | B5: Matricule Expat. | C5: Date Fin Mission | D5: Pays Retour | E5: Poste Retour Proposé | F5: Aide Recherche Emploi | G5: Indemnité Rapatriement (FCFA) | H5: Formation Réadaptation | I5: Entretien Bilan | J5: Démarches Administratives | K5: Date Réintégration | L5: Statut Réintégration | M5: Observations
A6: REINT-001 | B6: EXP-001 | C6: 46036 | D6: France | E6: DG Adjoint France | F6: Oui | G6: 2000000 | H6: Planifié | I6: Planifié | J6: En cours | L6: En préparation | M6: 18 mois avant fin | N6: =IF(A6="","",IF(AND(F6="Oui",H6="Terminé",J6="Terminé"),"PRÊT","EN COURS"))
A7: REINT-002 | B7: EXP-003 | C7: 45808 | D7: Allemagne | E7: Chef Cuisinier Munich | F7: Oui | G7: 1500000 | H7: En cours | I7: Planifié | J7: Non commencé | L7: En préparation | N7: =IF(A7="","",IF(AND(F7="Oui",H7="Terminé",J7="Terminé"),"PRÊT","EN COURS"))
A8: REINT-003 | B8: EXP-012 | C8: 45900 | D8: Ghana | E8: Consultant Sécurité Accra | F8: Non | G8: 800000 | H8: Non commencé | I8: Non commencé | J8: Non commencé | L8: Non commencé | M8: Court terme | N8: =IF(A8="","",IF(AND(F8="Oui",H8="Terminé",J8="Terminé"),"PRÊT","EN COURS"))
N9: =IF(A9="","",IF(AND(F9="Oui",H9="Terminé",J9="Terminé"),"PRÊT","EN COURS"))
N10: =IF(A10="","",IF(AND(F10="Oui",H10="Terminé",J10="Terminé"),"PRÊT","EN COURS"))
N11: =IF(A11="","",IF(AND(F11="Oui",H11="Terminé",J11="Terminé"),"PRÊT","EN COURS"))
N12: =IF(A12="","",IF(AND(F12="Oui",H12="Terminé",J12="Terminé"),"PRÊT","EN COURS"))
N13: =IF(A13="","",IF(AND(F13="Oui",H13="Terminé",J13="Terminé"),"PRÊT","EN COURS"))
N14: =IF(A14="","",IF(AND(F14="Oui",H14="Terminé",J14="Terminé"),"PRÊT","EN COURS"))
N15: =IF(A15="","",IF(AND(F15="Oui",H15="Terminé",J15="Terminé"),"PRÊT","EN COURS"))
N16: =IF(A16="","",IF(AND(F16="Oui",H16="Terminé",J16="Terminé"),"PRÊT","EN COURS"))
N17: =IF(A17="","",IF(AND(F17="Oui",H17="Terminé",J17="Terminé"),"PRÊT","EN COURS"))
N18: =IF(A18="","",IF(AND(F18="Oui",H18="Terminé",J18="Terminé"),"PRÊT","EN COURS"))
N19: =IF(A19="","",IF(AND(F19="Oui",H19="Terminé",J19="Terminé"),"PRÊT","EN COURS"))
N20: =IF(A20="","",IF(AND(F20="Oui",H20="Terminé",J20="Terminé"),"PRÊT","EN COURS"))
... N115: =IF(A115="","",IF(AND(F115="Oui",H115="Terminé",J115="Terminé"),"PRÊT","EN COURS"))

Sheet F13 - 11-Budget Mobilité Intl
A2: 11-BUDGET MOBILITÉ INTERNATIONALE
A3: TABLEAU DYNAMIQUE — Saisissez dans la zone prévue ci-dessous
A5: Code Budget | B5: Poste Budgétaire | C5: Catégorie | D5: Montant Prévu (FCFA) | E5: Montant Consommé (FCFA) | F5: Taux Consommation (%) | G5: Mois | H5: Département | I5: Responsable | J5: Devise | K5: Statut | L5: Écart (FCFA) | M5: Observations
A6: BUD-EXP-001 | B6: Indemnités expatriation | C6: Prime expatriation | D6: 12000000 | E6: 8500000 | F6: =IF(OR(D6="",E6="",D6=0),"",IFERROR(E6/D6*100,0)) | G6: Février 2025 | H6: Tous | I6: DRH | J6: XOF | K6: En cours | L6: =IF(OR(D6="",E6=""),"",D6-E6) | M6: =IF(K6="","",IFERROR(COUNTIF($K$6:$K$115,K6),0)) | N6: =IF(H6="","",IFERROR(AVERAGEIF($H$6:$H$115,H6,$F$6:$F$115),0))
A7: BUD-EXP-002 | B7: Logement expatriés | C7: Loyer + charges | D7: 30000000 | E7: 21000000 | F7: =IF(OR(D7="",E7="",D7=0),"",IFERROR(E7/D7*100,0)) | G7: Février 2025 | H7: Tous | I7: DRH / Logistique | J7: XOF | K7: En cours | L7: =IF(OR(D7="",E7=""),"",D7-E7) | M7: =IF(K7="","",IFERROR(COUNTIF($K$6:$K$115,K7),0)) | N7: =IF(H7="","",IFERROR(AVERAGEIF($H$6:$H$115,H7,$F$6:$F$115),0))
A8: BUD-EXP-003 | B8: Scolarité enfants | C8: Frais scolaires | D8: 15000000 | E8: 12500000 | F8: =IF(OR(D8="",E8="",D8=0),"",IFERROR(E8/D8*100,0)) | G8: Février 2025 | H8: Tous | I8: DRH | J8: XOF | K8: En cours | L8: =IF(OR(D8="",E8=""),"",D8-E8) | M8: =IF(K8="","",IFERROR(COUNTIF($K$6:$K$115,K8),0)) | N8: =IF(H8="","",IFERROR(AVERAGEIF($H$6:$H$115,H8,$F$6:$F$115),0))
A9: BUD-EXP-004 | B9: Visas & permis | C9: Frais administratifs | D9: 3000000 | E9: 1800000 | F9: =IF(OR(D9="",E9="",D9=0),"",IFERROR(E9/D9*100,0)) | G9: Février 2025 | H9: Tous | I9: DRH | J9: XOF | K9: En cours | L9: =IF(OR(D9="",E9=""),"",D9-E9) | M9: =IF(K9="","",IFERROR(COUNTIF($K$6:$K$115,K9),0)) | N9: =IF(H9="","",IFERROR(AVERAGEIF($H$6:$H$115,H9,$F$6:$F$115),0))
A10: BUD-EXP-005 | B10: Fiscalité & juridique | C10: Conseil fiscal | D10: 5000000 | E10: 3200000 | F10: =IF(OR(D10="",E10="",D10=0),"",IFERROR(E10/D10*100,0)) | G10: Février 2025 | H10: Finance | I10: DAF | J10: XOF | K10: En cours | L10: =IF(OR(D10="",E10=""),"",D10-E10) | M10: =IF(K10="","",IFERROR(COUNTIF($K$6:$K$115,K10),0)) | N10: =IF(H10="","",IFERROR(AVERAGEIF($H$6:$H$115,H10,$F$6:$F$115),0))
F11: =IF(OR(D11="",E11="",D11=0),"",IFERROR(E11/D11*100,0)) | L11: =IF(OR(D11="",E11=""),"",D11-E11) | M11: =IF(K11="","",IFERROR(COUNTIF($K$6:$K$115,K11),0)) | N11: =IF(H11="","",IFERROR(AVERAGEIF($H$6:$H$115,H11,$F$6:$F$115),0))
F12: =IF(OR(D12="",E12="",D12=0),"",IFERROR(E12/D12*100,0)) | L12: =IF(OR(D12="",E12=""),"",D12-E12) | M12: =IF(K12="","",IFERROR(COUNTIF($K$6:$K$115,K12),0)) | N12: =IF(H12="","",IFERROR(AVERAGEIF($H$6:$H$115,H12,$F$6:$F$115),0))
F13: =IF(OR(D13="",E13="",D13=0),"",IFERROR(E13/D13*100,0)) | L13: =IF(OR(D13="",E13=""),"",D13-E13) | M13: =IF(K13="","",IFERROR(COUNTIF($K$6:$K$115,K13),0)) | N13: =IF(H13="","",IFERROR(AVERAGEIF($H$6:$H$115,H13,$F$6:$F$115),0))
F14: =IF(OR(D14="",E14="",D14=0),"",IFERROR(E14/D14*100,0)) | L14: =IF(OR(D14="",E14=""),"",D14-E14) | M14: =IF(K14="","",IFERROR(COUNTIF($K$6:$K$115,K14),0)) | N14: =IF(H14="","",IFERROR(AVERAGEIF($H$6:$H$115,H14,$F$6:$F$115),0))
F15: =IF(OR(D15="",E15="",D15=0),"",IFERROR(E15/D15*100,0)) | L15: =IF(OR(D15="",E15=""),"",D15-E15) | M15: =IF(K15="","",IFERROR(COUNTIF($K$6:$K$115,K15),0)) | N15: =IF(H15="","",IFERROR(AVERAGEIF($H$6:$H$115,H15,$F$6:$F$115),0))
F16: =IF(OR(D16="",E16="",D16=0),"",IFERROR(E16/D16*100,0)) | L16: =IF(OR(D16="",E16=""),"",D16-E16) | M16: =IF(K16="","",IFERROR(COUNTIF($K$6:$K$115,K16),0)) | N16: =IF(H16="","",IFERROR(AVERAGEIF($H$6:$H$115,H16,$F$6:$F$115),0))
F17: =IF(OR(D17="",E17="",D17=0),"",IFERROR(E17/D17*100,0)) | L17: =IF(OR(D17="",E17=""),"",D17-E17) | M17: =IF(K17="","",IFERROR(COUNTIF($K$6:$K$115,K17),0)) | N17: =IF(H17="","",IFERROR(AVERAGEIF($H$6:$H$115,H17,$F$6:$F$115),0))
F18: =IF(OR(D18="",E18="",D18=0),"",IFERROR(E18/D18*100,0)) | L18: =IF(OR(D18="",E18=""),"",D18-E18) | M18: =IF(K18="","",IFERROR(COUNTIF($K$6:$K$115,K18),0)) | N18: =IF(H18="","",IFERROR(AVERAGEIF($H$6:$H$115,H18,$F$6:$F$115),0))
F19: =IF(OR(D19="",E19="",D19=0),"",IFERROR(E19/D19*100,0)) | L19: =IF(OR(D19="",E19=""),"",D19-E19) | M19: =IF(K19="","",IFERROR(COUNTIF($K$6:$K$115,K19),0)) | N19: =IF(H19="","",IFERROR(AVERAGEIF($H$6:$H$115,H19,$F$6:$F$115),0))
F20: =IF(OR(D20="",E20="",D20=0),"",IFERROR(E20/D20*100,0)) | L20: =IF(OR(D20="",E20=""),"",D20-E20) | M20: =IF(K20="","",IFERROR(COUNTIF($K$6:$K$115,K20),0)) | N20: =IF(H20="","",IFERROR(AVERAGEIF($H$6:$H$115,H20,$F$6:$F$115),0))
F21: =IF(OR(D21="",E21="",D21=0),"",IFERROR(E21/D21*100,0)) | L21: =IF(OR(D21="",E21=""),"",D21-E21) | M21: =IF(K21="","",IFERROR(COUNTIF($K$6:$K$115,K21),0)) | N21: =IF(H21="","",IFERROR(AVERAGEIF($H$6:$H$115,H21,$F$6:$F$115),0))
F22: =IF(OR(D22="",E22="",D22=0),"",IFERROR(E22/D22*100,0)) | L22: =IF(OR(D22="",E22=""),"",D22-E22) | M22: =IF(K22="","",IFERROR(COUNTIF($K$6:$K$115,K22),0)) | N22: =IF(H22="","",IFERROR(AVERAGEIF($H$6:$H$115,H22,$F$6:$F$115),0))
... F115: =IF(OR(D115="",E115="",D115=0),"",IFERROR(E115/D115*100,0)) | L115: =IF(OR(D115="",E115=""),"",D115-E115) | M115: =IF(K115="","",IFERROR(COUNTIF($K$6:$K$115,K115),0)) | N115: =IF(H115="","",IFERROR(AVERAGEIF($H$6:$H$115,H115,$F$6:$F$115),0))

Sheet F14 - 12-Matrice Pays×Poste
A2: 12-MATRICE PAYS × POSTE — Répartition géographique
A3: TABLEAU DYNAMIQUE — Saisissez dans la zone prévue ci-dessous
A5: Poste | B5: France | C5: Allemagne | D5: Brésil | E5: Corée du Sud | F5: Japon | G5: Nigeria | H5: Portugal | I5: Chine | J5: Belgique | K5: Ghana | L5: Italie | M5: Maroc | N5: Suède
A6: DG Adjoint | B6: 1 | C6: 0 | D6: 0 | E6: 0 | F6: 0 | G6: 0 | H6: 0 | I6: 0 | J6: 0 | K6: 0 | L6: 0 | M6: 0 | N6: =IF(A6="",0,SUM(B6:M6))
A7: Contrôleur Financier | B7: 1 | C7: 0 | D7: 0 | E7: 0 | F7: 0 | G7: 0 | H7: 0 | I7: 0 | J7: 0 | K7: 0 | L7: 0 | M7: 0 | N7: =IF(A7="",0,SUM(B7:M7))
A8: Chef Exécutif | B8: 0 | C8: 1 | D8: 0 | E8: 0 | F8: 0 | G8: 0 | H8: 0 | I8: 0 | J8: 0 | K8: 0 | L8: 0 | M8: 0 | N8: =IF(A8="",0,SUM(B8:M8))
A9: Directrice Spa | B9: 0 | C9: 0 | D9: 1 | E9: 0 | F9: 0 | G9: 0 | H9: 0 | I9: 0 | J9: 0 | K9: 0 | L9: 0 | M9: 0 | N9: =IF(A9="",0,SUM(B9:M9))
A10: Expert IT Senior | B10: 0 | C10: 0 | D10: 0 | E10: 1 | F10: 0 | G10: 0 | H10: 0 | I10: 0 | J10: 0 | K10: 0 | L10: 0 | M10: 0 | N10: =IF(A10="",0,SUM(B10:M10))
A11: Concierge Chef | B11: 0 | C11: 0 | D11: 0 | E11: 0 | F11: 1 | G11: 0 | H11: 0 | I11: 0 | J11: 0 | K11: 0 | L11: 0 | M11: 0 | N11: =IF(A11="",0,SUM(B11:M11))
A12: Resp. Formation Intl. | B12: 0 | C12: 0 | D12: 0 | E12: 0 | F12: 0 | G12: 1 | H12: 0 | I12: 0 | J12: 0 | K12: 0 | L12: 0 | M12: 0 | N12: =IF(A12="",0,SUM(B12:M12))
A13: Directeur Marketing | B13: 1 | C13: 0 | D13: 0 | E13: 0 | F13: 0 | G13: 0 | H13: 0 | I13: 0 | J13: 0 | K13: 0 | L13: 0 | M13: 0 | N13: =IF(A13="",0,SUM(B13:M13))
A14: Director of Rooms | B14: 0 | C14: 0 | D14: 0 | E14: 0 | F14: 0 | G14: 0 | H14: 1 | I14: 0 | J14: 0 | K14: 0 | L14: 0 | M14: 0 | N14: =IF(A14="",0,SUM(B14:M14))
A15: Resp. Commercial Asie | B15: 0 | C15: 0 | D15: 0 | E15: 0 | F15: 0 | G15: 0 | H15: 0 | I15: 1 | J15: 0 | K15: 0 | L15: 0 | M15: 0 | N15: =IF(A15="",0,SUM(B15:M15))
A16: DRH | B16: 0 | C16: 0 | D16: 0 | E16: 0 | F16: 0 | G16: 0 | H16: 0 | I16: 0 | J16: 1 | K16: 0 | L16: 0 | M16: 0 | N16: =IF(A16="",0,SUM(B16:M16))
A17: Consultant Sécurité | B17: 0 | C17: 0 | D17: 0 | E17: 0 | F17: 0 | G17: 0 | H17: 0 | I17: 0 | J17: 0 | K17: 1 | L17: 0 | M17: 0 | N17: =IF(A17="",0,SUM(B17:M17))
... A20: Ingénieur Technique | B20: 0 | C20: 0 | D20: 0 | E20: 0 | F20: 0 | G20: 0 | H20: 0 | I20: 0 | J20: 0 | K20: 0 | L20: 0 | M20: 0 | N20: =IF(A20="",0,SUM(B20:M20))
N21: =IF(A21="",0,SUM(B21:M21))
N22: =IF(A22="",0,SUM(B22:M22))
N23: =IF(A23="",0,SUM(B23:M23))
N24: =IF(A24="",0,SUM(B24:M24))
N25: =IF(A25="",0,SUM(B25:M25))
N26: =IF(A26="",0,SUM(B26:M26))
N27: =IF(A27="",0,SUM(B27:M27))
N28: =IF(A28="",0,SUM(B28:M28))
N29: =IF(A29="",0,SUM(B29:M29))
N30: =IF(A30="",0,SUM(B30:M30))
N31: =IF(A31="",0,SUM(B31:M31))
N32: =IF(A32="",0,SUM(B32:M32))
... N115: =IF(A115="",0,SUM(B115:M115))

Sheet F15 - 13-Historique Missions
A2: 13-HISTORIQUE DES MISSIONS INTERNATIONALES
A3: TABLEAU DYNAMIQUE — Saisissez dans la zone prévue ci-dessous
A5: Code Mission | B5: Matricule Expat. | C5: Pays Origine | D5: Pays Destination | E5: Type Mission | F5: Date Début | G5: Date Fin | H5: Durée (jours) | I5: Objectif Mission | J5: Rapport Rendu | K5: Coût Total (FCFA) | L5: Évaluation | M5: Statut | N5: Observations
A6: MIS-001 | B6: EXP-001 | C6: France | D6: Côte d'Ivoire | E6: Expatriation | F6: 44941 | G6: 46036 | H6: =IF(OR(F6="",G6=""),"",IFERROR(G6-F6,0)) | I6: Direction adjointe hôtel | J6: Trimestriel | K6: 180000000 | L6: Satisfaisant | M6: En cours | N6: =IF(B6="","",IFERROR(VLOOKUP(B6,'F01 - _Données Expatriés'!$A$6:$K$20,2,FALSE)&" "&VLOOKUP(B6,'F01 - _Données Expatriés'!$A$6:$K$20,3,FALSE),""))
A7: MIS-002 | B7: EXP-008 | C7: France | D7: Côte d'Ivoire | E7: Expatriation | F7: 44621 | G7: 45716 | H7: =IF(OR(F7="",G7=""),"",IFERROR(G7-F7,0)) | I7: Déploiement stratégie marketing | J7: Mensuel | K7: 150000000 | L7: Très satisfaisant | M7: En cours | N7: =IF(B7="","",IFERROR(VLOOKUP(B7,'F01 - _Données Expatriés'!$A$6:$K$20,2,FALSE)&" "&VLOOKUP(B7,'F01 - _Données Expatriés'!$A$6:$K$20,3,FALSE),""))
A8: MIS-003 | B8: EXP-015 | C8: Suède | D8: Côte d'Ivoire | E8: Expatriation | F8: 44440 | G8: 45535 | H8: =IF(OR(F8="",G8=""),"",IFERROR(G8-F8,0)) | I8: Modernisation technique | J8: Trimestriel | K8: 200000000 | L8: Satisfaisant | M8: En prolongation | N8: =IF(B8="","",IFERROR(VLOOKUP(B8,'F01 - _Données Expatriés'!$A$6:$K$20,2,FALSE)&" "&VLOOKUP(B8,'F01 - _Données Expatriés'!$A$6:$K$20,3,FALSE),""))
H9: =IF(OR(F9="",G9=""),"",IFERROR(G9-F9,0)) | N9: =IF(B9="","",IFERROR(VLOOKUP(B9,'F01 - _Données Expatriés'!$A$6:$K$20,2,FALSE)&" "&VLOOKUP(B9,'F01 - _Données Expatriés'!$A$6:$K$20,3,FALSE),""))
H10: =IF(OR(F10="",G10=""),"",IFERROR(G10-F10,0)) | N10: =IF(B10="","",IFERROR(VLOOKUP(B10,'F01 - _Données Expatriés'!$A$6:$K$20,2,FALSE)&" "&VLOOKUP(B10,'F01 - _Données Expatriés'!$A$6:$K$20,3,FALSE),""))
H11: =IF(OR(F11="",G11=""),"",IFERROR(G11-F11,0)) | N11: =IF(B11="","",IFERROR(VLOOKUP(B11,'F01 - _Données Expatriés'!$A$6:$K$20,2,FALSE)&" "&VLOOKUP(B11,'F01 - _Données Expatriés'!$A$6:$K$20,3,FALSE),""))
H12: =IF(OR(F12="",G12=""),"",IFERROR(G12-F12,0)) | N12: =IF(B12="","",IFERROR(VLOOKUP(B12,'F01 - _Données Expatriés'!$A$6:$K$20,2,FALSE)&" "&VLOOKUP(B12,'F01 - _Données Expatriés'!$A$6:$K$20,3,FALSE),""))
H13: =IF(OR(F13="",G13=""),"",IFERROR(G13-F13,0)) | N13: =IF(B13="","",IFERROR(VLOOKUP(B13,'F01 - _Données Expatriés'!$A$6:$K$20,2,FALSE)&" "&VLOOKUP(B13,'F01 - _Données Expatriés'!$A$6:$K$20,3,FALSE),""))
H14: =IF(OR(F14="",G14=""),"",IFERROR(G14-F14,0)) | N14: =IF(B14="","",IFERROR(VLOOKUP(B14,'F01 - _Données Expatriés'!$A$6:$K$20,2,FALSE)&" "&VLOOKUP(B14,'F01 - _Données Expatriés'!$A$6:$K$20,3,FALSE),""))
H15: =IF(OR(F15="",G15=""),"",IFERROR(G15-F15,0)) | N15: =IF(B15="","",IFERROR(VLOOKUP(B15,'F01 - _Données Expatriés'!$A$6:$K$20,2,FALSE)&" "&VLOOKUP(B15,'F01 - _Données Expatriés'!$A$6:$K$20,3,FALSE),""))
H16: =IF(OR(F16="",G16=""),"",IFERROR(G16-F16,0)) | N16: =IF(B16="","",IFERROR(VLOOKUP(B16,'F01 - _Données Expatriés'!$A$6:$K$20,2,FALSE)&" "&VLOOKUP(B16,'F01 - _Données Expatriés'!$A$6:$K$20,3,FALSE),""))
H17: =IF(OR(F17="",G17=""),"",IFERROR(G17-F17,0)) | N17: =IF(B17="","",IFERROR(VLOOKUP(B17,'F01 - _Données Expatriés'!$A$6:$K$20,2,FALSE)&" "&VLOOKUP(B17,'F01 - _Données Expatriés'!$A$6:$K$20,3,FALSE),""))
H18: =IF(OR(F18="",G18=""),"",IFERROR(G18-F18,0)) | N18: =IF(B18="","",IFERROR(VLOOKUP(B18,'F01 - _Données Expatriés'!$A$6:$K$20,2,FALSE)&" "&VLOOKUP(B18,'F01 - _Données Expatriés'!$A$6:$K$20,3,FALSE),""))
H19: =IF(OR(F19="",G19=""),"",IFERROR(G19-F19,0)) | N19: =IF(B19="","",IFERROR(VLOOKUP(B19,'F01 - _Données Expatriés'!$A$6:$K$20,2,FALSE)&" "&VLOOKUP(B19,'F01 - _Données Expatriés'!$A$6:$K$20,3,FALSE),""))
H20: =IF(OR(F20="",G20=""),"",IFERROR(G20-F20,0)) | N20: =IF(B20="","",IFERROR(VLOOKUP(B20,'F01 - _Données Expatriés'!$A$6:$K$20,2,FALSE)&" "&VLOOKUP(B20,'F01 - _Données Expatriés'!$A$6:$K$20,3,FALSE),""))
... H115: =IF(OR(F115="",G115=""),"",IFERROR(G115-F115,0)) | N115: =IF(B115="","",IFERROR(VLOOKUP(B115,'F01 - _Données Expatriés'!$A$6:$K$20,2,FALSE)&" "&VLOOKUP(B115,'F01 - _Données Expatriés'!$A$6:$K$20,3,FALSE),""))

Sheet F16 - 14-Calendrier Mobilité
A2: 14-CALENDRIER MOBILITÉ INTERNATIONALE
A3: TABLEAU DYNAMIQUE — Saisissez dans la zone prévue ci-dessous
A5: Code Échéance | B5: Matricule Expat. | C5: Type Événement | D5: Description | E5: Date Échéance | F5: Fréquence | G5: Responsable | H5: Département | I5: Jours Restants | J5: Alerte | K5: Rappel Envoyé | L5: Statut | M5: Observations
A6: CAL-001 | B6: EXP-001 | C6: Renouvellement visa | D6: Carte de séjour expire | E6: 45697 | F6: Annuelle | G6: DRH | H6: Ressources Humaines | I6: =IF(E6="","",IFERROR(E6-TODAY(),0)) | J6: =IF(I6="","",IF(I6<0,"EXPIRÉ",IF(I6<=30,"URGENT",IF(I6<=90,"Bientôt","OK")))) | K6: Non | L6: En cours | N6: =IF(B6="","",IFERROR(VLOOKUP(B6,'F01 - _Données Expatriés'!$A$6:$K$20,2,FALSE)&" "&VLOOKUP(B6,'F01 - _Données Expatriés'!$A$6:$K$20,3,FALSE),""))
A7: CAL-002 | B7: EXP-002 | C7: Renouvellement bail | D7: Bail appartement | E7: 45717 | F7: Annuelle | G7: DRH / Logistique | H7: Logistique | I7: =IF(E7="","",IFERROR(E7-TODAY(),0)) | J7: =IF(I7="","",IF(I7<0,"EXPIRÉ",IF(I7<=30,"URGENT",IF(I7<=90,"Bientôt","OK")))) | K7: Non | L7: En cours | N7: =IF(B7="","",IFERROR(VLOOKUP(B7,'F01 - _Données Expatriés'!$A$6:$K$20,2,FALSE)&" "&VLOOKUP(B7,'F01 - _Données Expatriés'!$A$6:$K$20,3,FALSE),""))
A8: CAL-003 | B8: EXP-005 | C8: Renouvellement permis | D8: Permis travail B | E8: 45671 | F8: Annuelle | G8: DRH | H8: Ressources Humaines | I8: =IF(E8="","",IFERROR(E8-TODAY(),0)) | J8: =IF(I8="","",IF(I8<0,"EXPIRÉ",IF(I8<=30,"URGENT",IF(I8<=90,"Bientôt","OK")))) | K8: Oui | L8: En retard | M8: Urgent | N8: =IF(B8="","",IFERROR(VLOOKUP(B8,'F01 - _Données Expatriés'!$A$6:$K$20,2,FALSE)&" "&VLOOKUP(B8,'F01 - _Données Expatriés'!$A$6:$K$20,3,FALSE),""))
A9: CAL-004 | B9: EXP-003 | C9: Bilan médical annuel | D9: Visite médicale | E9: 45809 | F9: Annuelle | G9: DRH | H9: Ressources Humaines | I9: =IF(E9="","",IFERROR(E9-TODAY(),0)) | J9: =IF(I9="","",IF(I9<0,"EXPIRÉ",IF(I9<=30,"URGENT",IF(I9<=90,"Bientôt","OK")))) | K9: Non | L9: Planifié | N9: =IF(B9="","",IFERROR(VLOOKUP(B9,'F01 - _Données Expatriés'!$A$6:$K$20,2,FALSE)&" "&VLOOKUP(B9,'F01 - _Données Expatriés'!$A$6:$K$20,3,FALSE),""))
A10: CAL-005 | B10: EXP-007 | C10: Renouvellement contrat | D10: Fin mission détachement | E10: 45930 | F10: Ponctuelle | G10: DRH / DG | H10: Ressources Humaines | I10: =IF(E10="","",IFERROR(E10-TODAY(),0)) | J10: =IF(I10="","",IF(I10<0,"EXPIRÉ",IF(I10<=30,"URGENT",IF(I10<=90,"Bientôt","OK")))) | K10: Non | L10: Planifié | N10: =IF(B10="","",IFERROR(VLOOKUP(B10,'F01 - _Données Expatriés'!$A$6:$K$20,2,FALSE)&" "&VLOOKUP(B10,'F01 - _Données Expatriés'!$A$6:$K$20,3,FALSE),""))
I11: =IF(E11="","",IFERROR(E11-TODAY(),0)) | J11: =IF(I11="","",IF(I11<0,"EXPIRÉ",IF(I11<=30,"URGENT",IF(I11<=90,"Bientôt","OK")))) | N11: =IF(B11="","",IFERROR(VLOOKUP(B11,'F01 - _Données Expatriés'!$A$6:$K$20,2,FALSE)&" "&VLOOKUP(B11,'F01 - _Données Expatriés'!$A$6:$K$20,3,FALSE),""))
I12: =IF(E12="","",IFERROR(E12-TODAY(),0)) | J12: =IF(I12="","",IF(I12<0,"EXPIRÉ",IF(I12<=30,"URGENT",IF(I12<=90,"Bientôt","OK")))) | N12: =IF(B12="","",IFERROR(VLOOKUP(B12,'F01 - _Données Expatriés'!$A$6:$K$20,2,FALSE)&" "&VLOOKUP(B12,'F01 - _Données Expatriés'!$A$6:$K$20,3,FALSE),""))
I13: =IF(E13="","",IFERROR(E13-TODAY(),0)) | J13: =IF(I13="","",IF(I13<0,"EXPIRÉ",IF(I13<=30,"URGENT",IF(I13<=90,"Bientôt","OK")))) | N13: =IF(B13="","",IFERROR(VLOOKUP(B13,'F01 - _Données Expatriés'!$A$6:$K$20,2,FALSE)&" "&VLOOKUP(B13,'F01 - _Données Expatriés'!$A$6:$K$20,3,FALSE),""))
I14: =IF(E14="","",IFERROR(E14-TODAY(),0)) | J14: =IF(I14="","",IF(I14<0,"EXPIRÉ",IF(I14<=30,"URGENT",IF(I14<=90,"Bientôt","OK")))) | N14: =IF(B14="","",IFERROR(VLOOKUP(B14,'F01 - _Données Expatriés'!$A$6:$K$20,2,FALSE)&" "&VLOOKUP(B14,'F01 - _Données Expatriés'!$A$6:$K$20,3,FALSE),""))
I15: =IF(E15="","",IFERROR(E15-TODAY(),0)) | J15: =IF(I15="","",IF(I15<0,"EXPIRÉ",IF(I15<=30,"URGENT",IF(I15<=90,"Bientôt","OK")))) | N15: =IF(B15="","",IFERROR(VLOOKUP(B15,'F01 - _Données Expatriés'!$A$6:$K$20,2,FALSE)&" "&VLOOKUP(B15,'F01 - _Données Expatriés'!$A$6:$K$20,3,FALSE),""))
I16: =IF(E16="","",IFERROR(E16-TODAY(),0)) | J16: =IF(I16="","",IF(I16<0,"EXPIRÉ",IF(I16<=30,"URGENT",IF(I16<=90,"Bientôt","OK")))) | N16: =IF(B16="","",IFERROR(VLOOKUP(B16,'F01 - _Données Expatriés'!$A$6:$K$20,2,FALSE)&" "&VLOOKUP(B16,'F01 - _Données Expatriés'!$A$6:$K$20,3,FALSE),""))
I17: =IF(E17="","",IFERROR(E17-TODAY(),0)) | J17: =IF(I17="","",IF(I17<0,"EXPIRÉ",IF(I17<=30,"URGENT",IF(I17<=90,"Bientôt","OK")))) | N17: =IF(B17="","",IFERROR(VLOOKUP(B17,'F01 - _Données Expatriés'!$A$6:$K$20,2,FALSE)&" "&VLOOKUP(B17,'F01 - _Données Expatriés'!$A$6:$K$20,3,FALSE),""))
I18: =IF(E18="","",IFERROR(E18-TODAY(),0)) | J18: =IF(I18="","",IF(I18<0,"EXPIRÉ",IF(I18<=30,"URGENT",IF(I18<=90,"Bientôt","OK")))) | N18: =IF(B18="","",IFERROR(VLOOKUP(B18,'F01 - _Données Expatriés'!$A$6:$K$20,2,FALSE)&" "&VLOOKUP(B18,'F01 - _Données Expatriés'!$A$6:$K$20,3,FALSE),""))
I19: =IF(E19="","",IFERROR(E19-TODAY(),0)) | J19: =IF(I19="","",IF(I19<0,"EXPIRÉ",IF(I19<=30,"URGENT",IF(I19<=90,"Bientôt","OK")))) | N19: =IF(B19="","",IFERROR(VLOOKUP(B19,'F01 - _Données Expatriés'!$A$6:$K$20,2,FALSE)&" "&VLOOKUP(B19,'F01 - _Données Expatriés'!$A$6:$K$20,3,FALSE),""))
I20: =IF(E20="","",IFERROR(E20-TODAY(),0)) | J20: =IF(I20="","",IF(I20<0,"EXPIRÉ",IF(I20<=30,"URGENT",IF(I20<=90,"Bientôt","OK")))) | N20: =IF(B20="","",IFERROR(VLOOKUP(B20,'F01 - _Données Expatriés'!$A$6:$K$20,2,FALSE)&" "&VLOOKUP(B20,'F01 - _Données Expatriés'!$A$6:$K$20,3,FALSE),""))
I21: =IF(E21="","",IFERROR(E21-TODAY(),0)) | J21: =IF(I21="","",IF(I21<0,"EXPIRÉ",IF(I21<=30,"URGENT",IF(I21<=90,"Bientôt","OK")))) | N21: =IF(B21="","",IFERROR(VLOOKUP(B21,'F01 - _Données Expatriés'!$A$6:$K$20,2,FALSE)&" "&VLOOKUP(B21,'F01 - _Données Expatriés'!$A$6:$K$20,3,FALSE),""))
I22: =IF(E22="","",IFERROR(E22-TODAY(),0)) | J22: =IF(I22="","",IF(I22<0,"EXPIRÉ",IF(I22<=30,"URGENT",IF(I22<=90,"Bientôt","OK")))) | N22: =IF(B22="","",IFERROR(VLOOKUP(B22,'F01 - _Données Expatriés'!$A$6:$K$20,2,FALSE)&" "&VLOOKUP(B22,'F01 - _Données Expatriés'!$A$6:$K$20,3,FALSE),""))
... I115: =IF(E115="","",IFERROR(E115-TODAY(),0)) | J115: =IF(I115="","",IF(I115<0,"EXPIRÉ",IF(I115<=30,"URGENT",IF(I115<=90,"Bientôt","OK")))) | N115: =IF(B115="","",IFERROR(VLOOKUP(B115,'F01 - _Données Expatriés'!$A$6:$K$20,2,FALSE)&" "&VLOOKUP(B115,'F01 - _Données Expatriés'!$A$6:$K$20,3,FALSE),""))

Sheet F17 - 15-TdB Financ. Expat.
A2: 15-TABLEAU DE BORD FINANCIER EXPATRIÉ
A3: TABLEAU DYNAMIQUE — Saisissez dans la zone prévue ci-dessous
A5: Matricule Expat. | B5: Nom Complet | C5: Salaire Brut (FCFA) | D5: Prime Expatriation (FCFA) | E5: Indemnité Logement (FCFA) | F5: Indemnité Scolarité (FCFA) | G5: Autres Indemnités (FCFA) | H5: Rémunération Totale (FCFA) | I5: Cotisations Sociales (FCFA) | J5: Impôt (FCFA) | K5: Rémunération Nette (FCFA) | L5: Coût Employeur (FCFA) | M5: Mois | N5: Observations
A6: EXP-001 | B6: Martin Jean-Pierre | C6: 4500000 | D6: 800000 | E6: 500000 | F6: 0 | G6: 150000 | H6: =IF(A6="",0,SUM(C6:G6)) | I6: 450000 | J6: =IF(H6=0,"",IFERROR(ROUND(H6*0.2,0),0)) | K6: =IF(H6=0,"",IFERROR(H6-I6-J6,0)) | L6: =IF(H6=0,"",IFERROR(ROUND(H6*1.3,0),0)) | M6: Janvier 2025
A7: EXP-002 | B7: Dupont Sophie | C7: 3800000 | D7: 650000 | E7: 500000 | F7: 300000 | G7: 100000 | H7: =IF(A7="",0,SUM(C7:G7)) | I7: 380000 | J7: =IF(H7=0,"",IFERROR(ROUND(H7*0.2,0),0)) | K7: =IF(H7=0,"",IFERROR(H7-I7-J7,0)) | L7: =IF(H7=0,"",IFERROR(ROUND(H7*1.3,0),0)) | M7: Janvier 2025
A8: EXP-003 | B8: Mueller Hans | C8: 5200000 | D8: 800000 | E8: 600000 | F8: 350000 | G8: 200000 | H8: =IF(A8="",0,SUM(C8:G8)) | I8: 520000 | J8: =IF(H8=0,"",IFERROR(ROUND(H8*0.2,0),0)) | K8: =IF(H8=0,"",IFERROR(H8-I8-J8,0)) | L8: =IF(H8=0,"",IFERROR(ROUND(H8*1.3,0),0)) | M8: Janvier 2025
A9: EXP-005 | B9: Kim Jin-woo | C9: 4200000 | D9: 700000 | E9: 450000 | F9: 200000 | G9: 120000 | H9: =IF(A9="",0,SUM(C9:G9)) | I9: 420000 | J9: =IF(H9=0,"",IFERROR(ROUND(H9*0.2,0),0)) | K9: =IF(H9=0,"",IFERROR(H9-I9-J9,0)) | L9: =IF(H9=0,"",IFERROR(ROUND(H9*1.3,0),0)) | M9: Janvier 2025
H10: =IF(A10="",0,SUM(C10:G10)) | J10: =IF(H10=0,"",IFERROR(ROUND(H10*0.2,0),0)) | K10: =IF(H10=0,"",IFERROR(H10-I10-J10,0)) | L10: =IF(H10=0,"",IFERROR(ROUND(H10*1.3,0),0))
H11: =IF(A11="",0,SUM(C11:G11)) | J11: =IF(H11=0,"",IFERROR(ROUND(H11*0.2,0),0)) | K11: =IF(H11=0,"",IFERROR(H11-I11-J11,0)) | L11: =IF(H11=0,"",IFERROR(ROUND(H11*1.3,0),0))
H12: =IF(A12="",0,SUM(C12:G12)) | J12: =IF(H12=0,"",IFERROR(ROUND(H12*0.2,0),0)) | K12: =IF(H12=0,"",IFERROR(H12-I12-J12,0)) | L12: =IF(H12=0,"",IFERROR(ROUND(H12*1.3,0),0))
H13: =IF(A13="",0,SUM(C13:G13)) | J13: =IF(H13=0,"",IFERROR(ROUND(H13*0.2,0),0)) | K13: =IF(H13=0,"",IFERROR(H13-I13-J13,0)) | L13: =IF(H13=0,"",IFERROR(ROUND(H13*1.3,0),0))
H14: =IF(A14="",0,SUM(C14:G14)) | J14: =IF(H14=0,"",IFERROR(ROUND(H14*0.2,0),0)) | K14: =IF(H14=0,"",IFERROR(H14-I14-J14,0)) | L14: =IF(H14=0,"",IFERROR(ROUND(H14*1.3,0),0))
H15: =IF(A15="",0,SUM(C15:G15)) | J15: =IF(H15=0,"",IFERROR(ROUND(H15*0.2,0),0)) | K15: =IF(H15=0,"",IFERROR(H15-I15-J15,0)) | L15: =IF(H15=0,"",IFERROR(ROUND(H15*1.3,0),0))
H16: =IF(A16="",0,SUM(C16:G16)) | J16: =IF(H16=0,"",IFERROR(ROUND(H16*0.2,0),0)) | K16: =IF(H16=0,"",IFERROR(H16-I16-J16,0)) | L16: =IF(H16=0,"",IFERROR(ROUND(H16*1.3,0),0))
H17: =IF(A17="",0,SUM(C17:G17)) | J17: =IF(H17=0,"",IFERROR(ROUND(H17*0.2,0),0)) | K17: =IF(H17=0,"",IFERROR(H17-I17-J17,0)) | L17: =IF(H17=0,"",IFERROR(ROUND(H17*1.3,0),0))
H18: =IF(A18="",0,SUM(C18:G18)) | J18: =IF(H18=0,"",IFERROR(ROUND(H18*0.2,0),0)) | K18: =IF(H18=0,"",IFERROR(H18-I18-J18,0)) | L18: =IF(H18=0,"",IFERROR(ROUND(H18*1.3,0),0))
H19: =IF(A19="",0,SUM(C19:G19)) | J19: =IF(H19=0,"",IFERROR(ROUND(H19*0.2,0),0)) | K19: =IF(H19=0,"",IFERROR(H19-I19-J19,0)) | L19: =IF(H19=0,"",IFERROR(ROUND(H19*1.3,0),0))
H20: =IF(A20="",0,SUM(C20:G20)) | J20: =IF(H20=0,"",IFERROR(ROUND(H20*0.2,0),0)) | K20: =IF(H20=0,"",IFERROR(H20-I20-J20,0)) | L20: =IF(H20=0,"",IFERROR(ROUND(H20*1.3,0),0))
H21: =IF(A21="",0,SUM(C21:G21)) | J21: =IF(H21=0,"",IFERROR(ROUND(H21*0.2,0),0)) | K21: =IF(H21=0,"",IFERROR(H21-I21-J21,0)) | L21: =IF(H21=0,"",IFERROR(ROUND(H21*1.3,0),0))
... H115: =IF(A115="",0,SUM(C115:G115)) | J115: =IF(H115=0,"",IFERROR(ROUND(H115*0.2,0),0)) | K115: =IF(H115=0,"",IFERROR(H115-I115-J115,0)) | L115: =IF(H115=0,"",IFERROR(ROUND(H115*1.3,0),0))

Sheet F18 - 16-Indic. Performance
A2: 16-INDICATEURS DE PERFORMANCE MOBILITÉ INTERNATIONALE
A3: TABLEAU DYNAMIQUE — Saisissez dans la zone prévue ci-dessous
A5: Code Indicateur | B5: Indicateur | C5: Période | D5: Objectif | E5: Résultat | F5: Taux Atteinte (%) | G5: Tendance | H5: Responsable | I5: Département | J5: Statut | K5: Commentaire
A6: KPI-EXP-001 | B6: Taux conformité visas | C6: T1 2025 | D6: 100% | E6: 93% | F6: =IF(OR(D6="",E6=""),"",IFERROR(VALUE(SUBSTITUTE(E6,"%",""))/VALUE(SUBSTITUTE(D6,"%",""))*100,0)) | G6: Stable | H6: DRH | I6: Ressources Humaines | J6: En cours | K6: 2 renouvellements en retard | M6: =IF(G6="","",IFERROR(VLOOKUP(G6,'F01 - _Données Expatriés'!$F$6:$F$20,1,FALSE),"")) | N6: =IF(J6="","",IFERROR(COUNTIF($J$6:$J$115,J6),0))
A7: KPI-EXP-002 | B7: Délai moyen obtention visa (j.) | C7: T1 2025 | D7: 30 | E7: 35 | F7: =IF(OR(D7="",E7=""),"",IFERROR(VALUE(SUBSTITUTE(E7,"%",""))/VALUE(SUBSTITUTE(D7,"%",""))*100,0)) | G7: Hausse | H7: DRH | I7: Ressources Humaines | J7: En cours | K7: Retrait embassy | M7: =IF(G7="","",IFERROR(VLOOKUP(G7,'F01 - _Données Expatriés'!$F$6:$F$20,1,FALSE),"")) | N7: =IF(J7="","",IFERROR(COUNTIF($J$6:$J$115,J7),0))
A8: KPI-EXP-003 | B8: Satisfaction logement expatriés | C8: T1 2025 | D8: 80% | E8: 85% | F8: =IF(OR(D8="",E8=""),"",IFERROR(VALUE(SUBSTITUTE(E8,"%",""))/VALUE(SUBSTITUTE(D8,"%",""))*100,0)) | G8: Hausse | H8: DRH | I8: Logistique | J8: En cours | M8: =IF(G8="","",IFERROR(VLOOKUP(G8,'F01 - _Données Expatriés'!$F$6:$F$20,1,FALSE),"")) | N8: =IF(J8="","",IFERROR(COUNTIF($J$6:$J$115,J8),0))
A9: KPI-EXP-004 | B9: Budget mobilité respecté | C9: T1 2025 | D9: 100% | E9: 95% | F9: =IF(OR(D9="",E9=""),"",IFERROR(VALUE(SUBSTITUTE(E9,"%",""))/VALUE(SUBSTITUTE(D9,"%",""))*100,0)) | G9: Stable | H9: DAF | I9: Finance | J9: En cours | M9: =IF(G9="","",IFERROR(VLOOKUP(G9,'F01 - _Données Expatriés'!$F$6:$F$20,1,FALSE),"")) | N9: =IF(J9="","",IFERROR(COUNTIF($J$6:$J$115,J9),0))
A10: KPI-EXP-005 | B10: Taux réintégration réussie | C10: 2024 | D10: 90% | E10: 100% | F10: =IF(OR(D10="",E10=""),"",IFERROR(VALUE(SUBSTITUTE(E10,"%",""))/VALUE(SUBSTITUTE(D10,"%",""))*100,0)) | G10: Stable | H10: DRH | I10: Ressources Humaines | J10: Terminé | K10: 3 réintégrations réussies | M10: =IF(G10="","",IFERROR(VLOOKUP(G10,'F01 - _Données Expatriés'!$F$6:$F$20,1,FALSE),"")) | N10: =IF(J10="","",IFERROR(COUNTIF($J$6:$J$115,J10),0))
F11: =IF(OR(D11="",E11=""),"",IFERROR(VALUE(SUBSTITUTE(E11,"%",""))/VALUE(SUBSTITUTE(D11,"%",""))*100,0)) | M11: =IF(G11="","",IFERROR(VLOOKUP(G11,'F01 - _Données Expatriés'!$F$6:$F$20,1,FALSE),"")) | N11: =IF(J11="","",IFERROR(COUNTIF($J$6:$J$115,J11),0))
F12: =IF(OR(D12="",E12=""),"",IFERROR(VALUE(SUBSTITUTE(E12,"%",""))/VALUE(SUBSTITUTE(D12,"%",""))*100,0)) | M12: =IF(G12="","",IFERROR(VLOOKUP(G12,'F01 - _Données Expatriés'!$F$6:$F$20,1,FALSE),"")) | N12: =IF(J12="","",IFERROR(COUNTIF($J$6:$J$115,J12),0))
F13: =IF(OR(D13="",E13=""),"",IFERROR(VALUE(SUBSTITUTE(E13,"%",""))/VALUE(SUBSTITUTE(D13,"%",""))*100,0)) | M13: =IF(G13="","",IFERROR(VLOOKUP(G13,'F01 - _Données Expatriés'!$F$6:$F$20,1,FALSE),"")) | N13: =IF(J13="","",IFERROR(COUNTIF($J$6:$J$115,J13),0))
F14: =IF(OR(D14="",E14=""),"",IFERROR(VALUE(SUBSTITUTE(E14,"%",""))/VALUE(SUBSTITUTE(D14,"%",""))*100,0)) | M14: =IF(G14="","",IFERROR(VLOOKUP(G14,'F01 - _Données Expatriés'!$F$6:$F$20,1,FALSE),"")) | N14: =IF(J14="","",IFERROR(COUNTIF($J$6:$J$115,J14),0))
F15: =IF(OR(D15="",E15=""),"",IFERROR(VALUE(SUBSTITUTE(E15,"%",""))/VALUE(SUBSTITUTE(D15,"%",""))*100,0)) | M15: =IF(G15="","",IFERROR(VLOOKUP(G15,'F01 - _Données Expatriés'!$F$6:$F$20,1,FALSE),"")) | N15: =IF(J15="","",IFERROR(COUNTIF($J$6:$J$115,J15),0))
F16: =IF(OR(D16="",E16=""),"",IFERROR(VALUE(SUBSTITUTE(E16,"%",""))/VALUE(SUBSTITUTE(D16,"%",""))*100,0)) | M16: =IF(G16="","",IFERROR(VLOOKUP(G16,'F01 - _Données Expatriés'!$F$6:$F$20,1,FALSE),"")) | N16: =IF(J16="","",IFERROR(COUNTIF($J$6:$J$115,J16),0))
F17: =IF(OR(D17="",E17=""),"",IFERROR(VALUE(SUBSTITUTE(E17,"%",""))/VALUE(SUBSTITUTE(D17,"%",""))*100,0)) | M17: =IF(G17="","",IFERROR(VLOOKUP(G17,'F01 - _Données Expatriés'!$F$6:$F$20,1,FALSE),"")) | N17: =IF(J17="","",IFERROR(COUNTIF($J$6:$J$115,J17),0))
F18: =IF(OR(D18="",E18=""),"",IFERROR(VALUE(SUBSTITUTE(E18,"%",""))/VALUE(SUBSTITUTE(D18,"%",""))*100,0)) | M18: =IF(G18="","",IFERROR(VLOOKUP(G18,'F01 - _Données Expatriés'!$F$6:$F$20,1,FALSE),"")) | N18: =IF(J18="","",IFERROR(COUNTIF($J$6:$J$115,J18),0))
F19: =IF(OR(D19="",E19=""),"",IFERROR(VALUE(SUBSTITUTE(E19,"%",""))/VALUE(SUBSTITUTE(D19,"%",""))*100,0)) | M19: =IF(G19="","",IFERROR(VLOOKUP(G19,'F01 - _Données Expatriés'!$F$6:$F$20,1,FALSE),"")) | N19: =IF(J19="","",IFERROR(COUNTIF($J$6:$J$115,J19),0))
F20: =IF(OR(D20="",E20=""),"",IFERROR(VALUE(SUBSTITUTE(E20,"%",""))/VALUE(SUBSTITUTE(D20,"%",""))*100,0)) | M20: =IF(G20="","",IFERROR(VLOOKUP(G20,'F01 - _Données Expatriés'!$F$6:$F$20,1,FALSE),"")) | N20: =IF(J20="","",IFERROR(COUNTIF($J$6:$J$115,J20),0))
F21: =IF(OR(D21="",E21=""),"",IFERROR(VALUE(SUBSTITUTE(E21,"%",""))/VALUE(SUBSTITUTE(D21,"%",""))*100,0)) | M21: =IF(G21="","",IFERROR(VLOOKUP(G21,'F01 - _Données Expatriés'!$F$6:$F$20,1,FALSE),"")) | N21: =IF(J21="","",IFERROR(COUNTIF($J$6:$J$115,J21),0))
F22: =IF(OR(D22="",E22=""),"",IFERROR(VALUE(SUBSTITUTE(E22,"%",""))/VALUE(SUBSTITUTE(D22,"%",""))*100,0)) | M22: =IF(G22="","",IFERROR(VLOOKUP(G22,'F01 - _Données Expatriés'!$F$6:$F$20,1,FALSE),"")) | N22: =IF(J22="","",IFERROR(COUNTIF($J$6:$J$115,J22),0))
... F115: =IF(OR(D115="",E115=""),"",IFERROR(VALUE(SUBSTITUTE(E115,"%",""))/VALUE(SUBSTITUTE(D115,"%",""))*100,0)) | M115: =IF(G115="","",IFERROR(VLOOKUP(G115,'F01 - _Données Expatriés'!$F$6:$F$20,1,FALSE),"")) | N115: =IF(J115="","",IFERROR(COUNTIF($J$6:$J$115,J115),0))

Sheet F19 - 17-Risques Pays
A2: 17-ANALYSE DES RISQUES PAYS
A3: TABLEAU DYNAMIQUE — Saisissez dans la zone prévue ci-dessous
A5: Code Risque | B5: Pays Concerné | C5: Type Risque | D5: Niveau Risque | E5: Description | F5: Impact Potentiel | G5: Probabilité | H5: Mesure Prévention | I5: Plan Contingence | J5: Responsable Suivi | K5: Date Évaluation | L5: Statut | M5: Observations
A6: RISK-001 | B6: Côte d'Ivoire | C6: Santé / Épidémiologique | D6: Modéré | E6: Épidémie Dengue saisonnière | F6: Moyen | G6: Élevée | H6: Vaccination + moustiquaires | I6: Évacuation médicale | J6: DRH | K6: 45672 | L6: En cours | M6: Saison des pluies | N6: =IF(A6="","",IF(D6="Critique","ALERTE IMMÉDIATE",IF(D6="Élevé","SURVEILLANCE RENFORCÉE",IF(D6="Modéré","SUIVI STANDARD","FAIBLE"))))
A7: RISK-002 | B7: Côte d'Ivoire | C7: Instabilité politique | D7: Faible | E7: Élections locales 2025 | F7: Moyen | G7: Faible | H7: Veille sécuritaire | I7: Plan d'évacuation | J7: DG / DRH | K7: 45672 | L7: En cours | N7: =IF(A7="","",IF(D7="Critique","ALERTE IMMÉDIATE",IF(D7="Élevé","SURVEILLANCE RENFORCÉE",IF(D7="Modéré","SUIVI STANDARD","FAIBLE"))))
A8: RISK-003 | B8: Côte d'Ivoire | C8: Taux de change | D8: Élevé | E8: Volatilité EUR/XOF | F8: Élevé | G8: Modérée | H8: Couverture de change | I8: Indexation indemnités | J8: DAF | K8: 45689 | L8: En cours | M8: Pegged mais risque dépeg | N8: =IF(A8="","",IF(D8="Critique","ALERTE IMMÉDIATE",IF(D8="Élevé","SURVEILLANCE RENFORCÉE",IF(D8="Modéré","SUIVI STANDARD","FAIBLE"))))
A9: RISK-004 | B9: Global | C9: Conformité légale | D9: Modéré | E9: Changement réglementation immigration | F9: Élevé | G9: Modérée | H9: Veille juridique | I9: Avocat spécialisé | J9: DRH / Juridique | K9: 45672 | L9: En cours | N9: =IF(A9="","",IF(D9="Critique","ALERTE IMMÉDIATE",IF(D9="Élevé","SURVEILLANCE RENFORCÉE",IF(D9="Modéré","SUIVI STANDARD","FAIBLE"))))
N10: =IF(A10="","",IF(D10="Critique","ALERTE IMMÉDIATE",IF(D10="Élevé","SURVEILLANCE RENFORCÉE",IF(D10="Modéré","SUIVI STANDARD","FAIBLE"))))
N11: =IF(A11="","",IF(D11="Critique","ALERTE IMMÉDIATE",IF(D11="Élevé","SURVEILLANCE RENFORCÉE",IF(D11="Modéré","SUIVI STANDARD","FAIBLE"))))
N12: =IF(A12="","",IF(D12="Critique","ALERTE IMMÉDIATE",IF(D12="Élevé","SURVEILLANCE RENFORCÉE",IF(D12="Modéré","SUIVI STANDARD","FAIBLE"))))
N13: =IF(A13="","",IF(D13="Critique","ALERTE IMMÉDIATE",IF(D13="Élevé","SURVEILLANCE RENFORCÉE",IF(D13="Modéré","SUIVI STANDARD","FAIBLE"))))
N14: =IF(A14="","",IF(D14="Critique","ALERTE IMMÉDIATE",IF(D14="Élevé","SURVEILLANCE RENFORCÉE",IF(D14="Modéré","SUIVI STANDARD","FAIBLE"))))
N15: =IF(A15="","",IF(D15="Critique","ALERTE IMMÉDIATE",IF(D15="Élevé","SURVEILLANCE RENFORCÉE",IF(D15="Modéré","SUIVI STANDARD","FAIBLE"))))
N16: =IF(A16="","",IF(D16="Critique","ALERTE IMMÉDIATE",IF(D16="Élevé","SURVEILLANCE RENFORCÉE",IF(D16="Modéré","SUIVI STANDARD","FAIBLE"))))
N17: =IF(A17="","",IF(D17="Critique","ALERTE IMMÉDIATE",IF(D17="Élevé","SURVEILLANCE RENFORCÉE",IF(D17="Modéré","SUIVI STANDARD","FAIBLE"))))
N18: =IF(A18="","",IF(D18="Critique","ALERTE IMMÉDIATE",IF(D18="Élevé","SURVEILLANCE RENFORCÉE",IF(D18="Modéré","SUIVI STANDARD","FAIBLE"))))
N19: =IF(A19="","",IF(D19="Critique","ALERTE IMMÉDIATE",IF(D19="Élevé","SURVEILLANCE RENFORCÉE",IF(D19="Modéré","SUIVI STANDARD","FAIBLE"))))
N20: =IF(A20="","",IF(D20="Critique","ALERTE IMMÉDIATE",IF(D20="Élevé","SURVEILLANCE RENFORCÉE",IF(D20="Modéré","SUIVI STANDARD","FAIBLE"))))
N21: =IF(A21="","",IF(D21="Critique","ALERTE IMMÉDIATE",IF(D21="Élevé","SURVEILLANCE RENFORCÉE",IF(D21="Modéré","SUIVI STANDARD","FAIBLE"))))
... N115: =IF(A115="","",IF(D115="Critique","ALERTE IMMÉDIATE",IF(D115="Élevé","SURVEILLANCE RENFORCÉE",IF(D115="Modéré","SUIVI STANDARD","FAIBLE"))))

Sheet F20 - 18-Conformité Réglement.
A2: 18-CONFORMITÉ RÉGLEMENTAIRE EXPATRIATION
A3: TABLEAU DYNAMIQUE — Saisissez dans la zone prévue ci-dessous
A5: Code Exigence | B5: Source Réglementaire | C5: Exigence | D5: Domaine | E5: Statut Conformité | F5: Date Vérification | G5: Preuve / Document | H5: Responsable | I5: Action Corrective | J5: Échéance Action | K5: Commentaire
A6: CONF-001 | B6: Code Travail CI Art. 4 | C6: Autorisation de travail obligatoire | D6: Immigration | E6: Conforme | F6: =IF(A6="","",IFERROR(VLOOKUP(A6,'F01 - _Données Expatriés'!$A$6:$K$20,5,FALSE),"")) | G6: Autorisations dossier DRH | H6: DRH | I6: N/A | K6: Tous les expatriés couverts | L6: =IF(E6="Conforme","OK",IF(E6="Partiellement conforme","ACTION REQUISE",IF(E6="Non conforme","URGENT","")))
A7: CONF-002 | B7: Art. 18 Loi 95-643 | C7: Carte de séjour en cours de validité | D7: Immigration | E7: Partiellement conforme | F7: =IF(A7="","",IFERROR(VLOOKUP(A7,'F01 - _Données Expatriés'!$A$6:$K$20,5,FALSE),"")) | G7: Liste visas + dates | H7: DRH | I7: Renouveler visa EXP-005 | J7: 45703 | K7: 1 visa en retard | L7: =IF(E7="Conforme","OK",IF(E7="Partiellement conforme","ACTION REQUISE",IF(E7="Non conforme","URGENT","")))
A8: CONF-003 | B8: Convention fiscale fr. | C8: Déclaration revenus double imposition | D8: Fiscalité | E8: Conforme | F8: =IF(A8="","",IFERROR(VLOOKUP(A8,'F01 - _Données Expatriés'!$A$6:$K$20,5,FALSE),"")) | G8: Déclarations fiscales 2024 | H8: DAF | I8: N/A | L8: =IF(E8="Conforme","OK",IF(E8="Partiellement conforme","ACTION REQUISE",IF(E8="Non conforme","URGENT","")))
A9: CONF-004 | B9: Code Sécurité Sociale | C9: Affiliation assurance maladie expatriés | D9: Sécurité sociale | E9: Conforme | F9: =IF(A9="","",IFERROR(VLOOKUP(A9,'F01 - _Données Expatriés'!$A$6:$K$20,5,FALSE),"")) | G9: Contrats assurance | H9: DRH | I9: N/A | K9: Couverture internationale | L9: =IF(E9="Conforme","OK",IF(E9="Partiellement conforme","ACTION REQUISE",IF(E9="Non conforme","URGENT","")))
A10: CONF-005 | B10: Règlement intérieur | C10: Respect conditions logement fourni | D10: Logement | E10: Partiellement conforme | F10: =IF(A10="","",IFERROR(VLOOKUP(A10,'F01 - _Données Expatriés'!$A$6:$K$20,5,FALSE),"")) | G10: Rapports logement | H10: DRH / Logistique | I10: Mise à jour 2 logements | J10: 45747 | K10: Travaux en cours | L10: =IF(E10="Conforme","OK",IF(E10="Partiellement conforme","ACTION REQUISE",IF(E10="Non conforme","URGENT","")))
F11: =IF(A11="","",IFERROR(VLOOKUP(A11,'F01 - _Données Expatriés'!$A$6:$K$20,5,FALSE),"")) | L11: =IF(E11="Conforme","OK",IF(E11="Partiellement conforme","ACTION REQUISE",IF(E11="Non conforme","URGENT","")))
F12: =IF(A12="","",IFERROR(VLOOKUP(A12,'F01 - _Données Expatriés'!$A$6:$K$20,5,FALSE),"")) | L12: =IF(E12="Conforme","OK",IF(E12="Partiellement conforme","ACTION REQUISE",IF(E12="Non conforme","URGENT","")))
F13: =IF(A13="","",IFERROR(VLOOKUP(A13,'F01 - _Données Expatriés'!$A$6:$K$20,5,FALSE),"")) | L13: =IF(E13="Conforme","OK",IF(E13="Partiellement conforme","ACTION REQUISE",IF(E13="Non conforme","URGENT","")))
F14: =IF(A14="","",IFERROR(VLOOKUP(A14,'F01 - _Données Expatriés'!$A$6:$K$20,5,FALSE),"")) | L14: =IF(E14="Conforme","OK",IF(E14="Partiellement conforme","ACTION REQUISE",IF(E14="Non conforme","URGENT","")))
F15: =IF(A15="","",IFERROR(VLOOKUP(A15,'F01 - _Données Expatriés'!$A$6:$K$20,5,FALSE),"")) | L15: =IF(E15="Conforme","OK",IF(E15="Partiellement conforme","ACTION REQUISE",IF(E15="Non conforme","URGENT","")))
F16: =IF(A16="","",IFERROR(VLOOKUP(A16,'F01 - _Données Expatriés'!$A$6:$K$20,5,FALSE),"")) | L16: =IF(E16="Conforme","OK",IF(E16="Partiellement conforme","ACTION REQUISE",IF(E16="Non conforme","URGENT","")))
F17: =IF(A17="","",IFERROR(VLOOKUP(A17,'F01 - _Données Expatriés'!$A$6:$K$20,5,FALSE),"")) | L17: =IF(E17="Conforme","OK",IF(E17="Partiellement conforme","ACTION REQUISE",IF(E17="Non conforme","URGENT","")))
F18: =IF(A18="","",IFERROR(VLOOKUP(A18,'F01 - _Données Expatriés'!$A$6:$K$20,5,FALSE),"")) | L18: =IF(E18="Conforme","OK",IF(E18="Partiellement conforme","ACTION REQUISE",IF(E18="Non conforme","URGENT","")))
F19: =IF(A19="","",IFERROR(VLOOKUP(A19,'F01 - _Données Expatriés'!$A$6:$K$20,5,FALSE),"")) | L19: =IF(E19="Conforme","OK",IF(E19="Partiellement conforme","ACTION REQUISE",IF(E19="Non conforme","URGENT","")))
F20: =IF(A20="","",IFERROR(VLOOKUP(A20,'F01 - _Données Expatriés'!$A$6:$K$20,5,FALSE),"")) | L20: =IF(E20="Conforme","OK",IF(E20="Partiellement conforme","ACTION REQUISE",IF(E20="Non conforme","URGENT","")))
F21: =IF(A21="","",IFERROR(VLOOKUP(A21,'F01 - _Données Expatriés'!$A$6:$K$20,5,FALSE),"")) | L21: =IF(E21="Conforme","OK",IF(E21="Partiellement conforme","ACTION REQUISE",IF(E21="Non conforme","URGENT","")))
F22: =IF(A22="","",IFERROR(VLOOKUP(A22,'F01 - _Données Expatriés'!$A$6:$K$20,5,FALSE),"")) | L22: =IF(E22="Conforme","OK",IF(E22="Partiellement conforme","ACTION REQUISE",IF(E22="Non conforme","URGENT","")))
... F115: =IF(A115="","",IFERROR(VLOOKUP(A115,'F01 - _Données Expatriés'!$A$6:$K$20,5,FALSE),"")) | L115: =IF(E115="Conforme","OK",IF(E115="Partiellement conforme","ACTION REQUISE",IF(E115="Non conforme","URGENT","")))

Sheet F21 - 19-Exigences d'Audit
A2: 19-EXIGENCES D'AUDIT — MOBILITÉ INTERNATIONALE
A3: TABLEAU DYNAMIQUE — Saisissez dans la zone prévue ci-dessous
A5: Code Audit | B5: Référence Norme | C5: Exigence Audit | D5: Processus Concerné | E5: Preuve Requise | F5: Statut | G5: Date Audit | H5: Auditeur | I5: Constat | J5: Action Corrective | K5: Échéance | L5: Suivi | M5: Observations
A6: AUD-EXP-001 | B6: ISO 9001 §7.1.6 | C6: Compétences et formation expatriés | D6: Formation | E6: Plans formation + attestations | F6: =IF(A6="","",IFERROR(VLOOKUP(A6,'F01 - _Données Expatriés'!$A$6:$K$20,5,FALSE),"")) | G6: 45677 | H6: Auditeur Interne | I6: Aucun écart | J6: N/A | L6: Clos | M6: =IF(F6="Conforme","CLOS",IF(F6="Partiellement conforme","EN COURS",IF(F6="Non conforme","URGENT","")))
A7: AUD-EXP-002 | B7: ISO 9001 §8.6 | C7: Conformité légale immigration | D7: Immigration | E7: Autorisations + visas | F7: =IF(A7="","",IFERROR(VLOOKUP(A7,'F01 - _Données Expatriés'!$A$6:$K$20,5,FALSE),"")) | G7: 45679 | H7: Auditeur Interne | I7: 1 visa expiré | J7: Renouvellement immédiat | K7: 45703 | L7: En cours | M7: =IF(F7="Conforme","CLOS",IF(F7="Partiellement conforme","EN COURS",IF(F7="Non conforme","URGENT","")))
A8: AUD-EXP-003 | B8: ISO 14001 §6.1.2 | C8: Évaluation risques pays | D8: Sécurité | E8: Matrice risques + plans | F8: =IF(A8="","",IFERROR(VLOOKUP(A8,'F01 - _Données Expatriés'!$A$6:$K$20,5,FALSE),"")) | G8: 45682 | H8: Auditeur Interne | I8: Aucun écart | J8: N/A | L8: Clos | M8: =IF(F8="Conforme","CLOS",IF(F8="Partiellement conforme","EN COURS",IF(F8="Non conforme","URGENT","")))
A9: AUD-EXP-004 | B9: ISO 9001 §7.4 | C9: Contrats expatriation complets | D9: Juridique | E9: Contrats signés | F9: =IF(A9="","",IFERROR(VLOOKUP(A9,'F01 - _Données Expatriés'!$A$6:$K$20,5,FALSE),"")) | G9: 45685 | H9: Auditeur Interne | I9: Aucun écart | J9: N/A | L9: Clos | M9: =IF(F9="Conforme","CLOS",IF(F9="Partiellement conforme","EN COURS",IF(F9="Non conforme","URGENT","")))
F10: =IF(A10="","",IFERROR(VLOOKUP(A10,'F01 - _Données Expatriés'!$A$6:$K$20,5,FALSE),"")) | M10: =IF(F10="Conforme","CLOS",IF(F10="Partiellement conforme","EN COURS",IF(F10="Non conforme","URGENT","")))
F11: =IF(A11="","",IFERROR(VLOOKUP(A11,'F01 - _Données Expatriés'!$A$6:$K$20,5,FALSE),"")) | M11: =IF(F11="Conforme","CLOS",IF(F11="Partiellement conforme","EN COURS",IF(F11="Non conforme","URGENT","")))
F12: =IF(A12="","",IFERROR(VLOOKUP(A12,'F01 - _Données Expatriés'!$A$6:$K$20,5,FALSE),"")) | M12: =IF(F12="Conforme","CLOS",IF(F12="Partiellement conforme","EN COURS",IF(F12="Non conforme","URGENT","")))
F13: =IF(A13="","",IFERROR(VLOOKUP(A13,'F01 - _Données Expatriés'!$A$6:$K$20,5,FALSE),"")) | M13: =IF(F13="Conforme","CLOS",IF(F13="Partiellement conforme","EN COURS",IF(F13="Non conforme","URGENT","")))
F14: =IF(A14="","",IFERROR(VLOOKUP(A14,'F01 - _Données Expatriés'!$A$6:$K$20,5,FALSE),"")) | M14: =IF(F14="Conforme","CLOS",IF(F14="Partiellement conforme","EN COURS",IF(F14="Non conforme","URGENT","")))
F15: =IF(A15="","",IFERROR(VLOOKUP(A15,'F01 - _Données Expatriés'!$A$6:$K$20,5,FALSE),"")) | M15: =IF(F15="Conforme","CLOS",IF(F15="Partiellement conforme","EN COURS",IF(F15="Non conforme","URGENT","")))
F16: =IF(A16="","",IFERROR(VLOOKUP(A16,'F01 - _Données Expatriés'!$A$6:$K$20,5,FALSE),"")) | M16: =IF(F16="Conforme","CLOS",IF(F16="Partiellement conforme","EN COURS",IF(F16="Non conforme","URGENT","")))
F17: =IF(A17="","",IFERROR(VLOOKUP(A17,'F01 - _Données Expatriés'!$A$6:$K$20,5,FALSE),"")) | M17: =IF(F17="Conforme","CLOS",IF(F17="Partiellement conforme","EN COURS",IF(F17="Non conforme","URGENT","")))
F18: =IF(A18="","",IFERROR(VLOOKUP(A18,'F01 - _Données Expatriés'!$A$6:$K$20,5,FALSE),"")) | M18: =IF(F18="Conforme","CLOS",IF(F18="Partiellement conforme","EN COURS",IF(F18="Non conforme","URGENT","")))
F19: =IF(A19="","",IFERROR(VLOOKUP(A19,'F01 - _Données Expatriés'!$A$6:$K$20,5,FALSE),"")) | M19: =IF(F19="Conforme","CLOS",IF(F19="Partiellement conforme","EN COURS",IF(F19="Non conforme","URGENT","")))
F20: =IF(A20="","",IFERROR(VLOOKUP(A20,'F01 - _Données Expatriés'!$A$6:$K$20,5,FALSE),"")) | M20: =IF(F20="Conforme","CLOS",IF(F20="Partiellement conforme","EN COURS",IF(F20="Non conforme","URGENT","")))
F21: =IF(A21="","",IFERROR(VLOOKUP(A21,'F01 - _Données Expatriés'!$A$6:$K$20,5,FALSE),"")) | M21: =IF(F21="Conforme","CLOS",IF(F21="Partiellement conforme","EN COURS",IF(F21="Non conforme","URGENT","")))
... F115: =IF(A115="","",IFERROR(VLOOKUP(A115,'F01 - _Données Expatriés'!$A$6:$K$20,5,FALSE),"")) | M115: =IF(F115="Conforme","CLOS",IF(F115="Partiellement conforme","EN COURS",IF(F115="Non conforme","URGENT","")))
