Workbook

Sheet F01 - _Données Stagiaires
A2: DONNÉES STAGIAIRES — Base de référence
A3: TABLEAU DYNAMIQUE — Saisissez dans la zone prévue ci-dessous
A5: Matricule | B5: Nom | C5: Prénom | D5: Établissement | E5: Formation | F5: Département d'accueil | G5: Tuteur | H5: Date Début | I5: Date Fin | J5: Statut | K5: Indemnité (FCFA)
A6: STA-001 | B6: Koné | C6: Aminata | D6: FHB Abidjan | E6: HTM | F6: Cuisine & Restauration | G6: Chef Mbarga | H6: 45663 | I6: 45838 | J6: En cours | K6: 75000
A7: STA-002 | B7: Traoré | C7: Ibrahim | D7: INP-HB | E7: Informatique | F7: Informatique | G7: M. Bamba | H7: 45689 | I7: 45869 | J7: En cours | K7: 80000
A8: STA-003 | B8: Diallo | C8: Fatou | D8: EHESS Abidjan | E8: Marketing | F8: Marketing & Communication | G8: Mme Koffi | H8: 45672 | I8: 45762 | J8: En cours | K8: 70000
A9: STA-004 | B9: Ouattara | C9: Moussa | D9: Université FHB | E9: Comptabilité | F9: Finance & Comptabilité | G9: Mme Fotso | H9: 45536 | I9: 45716 | J9: Terminé | K9: 65000
A10: STA-005 | B10: Bamba | C10: Mariam | D10: ESP Annecy | E10: Cuisine | F10: Cuisine & Restauration | G10: Chef Mbarga | H10: 45717 | I10: 45900 | J10: Planifié | K10: 75000
A11: STA-006 | B11: Coulibaly | C11: Adama | D11: INP-HB | E11: Génie Civil | F11: Entretien & Maintenance | G11: M. Kamga | H11: 45663 | I11: 45838 | J11: En cours | K11: 70000
A12: STA-007 | B12: Konan | C12: Yao | D12: Université Cocody | E12: Droit | F12: Ressources Humaines | G12: M. N'Goran | H12: 45566 | I12: 45747 | J12: En cours | K12: 65000
A13: STA-008 | B13: Sangaré | C13: Awa | D13: Ecole Sup. Commerce | E13: Gestion | F13: Commercial | G13: M. Ekra | H13: 45703 | I13: 45853 | J13: En cours | K13: 70000
A14: STA-009 | B14: Djibril | C14: Oumar | D14: ISTC Abidjan | E14: Informatique | F14: Informatique | G14: M. Bamba | H14: 45444 | I14: 45657 | J14: Terminé | K14: 80000
A15: STA-010 | B15: Yao | C15: Akissi | D15: Université Bouaké | E15: HTM | F15: Réception & Front Office | G15: Mme Djomga | H15: 45663 | I15: 45838 | J15: En cours | K15: 65000

Sheet F02 - _Lists
A2: LISTES DE RÉFÉRENCE — Valeurs pour listes déroulantes
A3: TABLEAU DYNAMIQUE — Saisissez dans la zone prévue ci-dessous
A5: etablissements | B5: formations | C5: departements | D5: postes_stage | E5: types_stage | F5: statuts_stage | G5: evaluations | H5: recommandations | I5: niveaux_etude | J5: criteres_eval | K5: priorites | L5: conformites | M5: validations | N5: frequences | O5: mois | P5: trimestres | Q5: tendances | R5: annees | S5: modes_paiement | T5: origines | U5: notes_1_5 | V5: types_litige_stage | W5: etapes_integration | X5: statuts_post_stage
A6: FHB Abidjan | B6: HTM | C6: Direction Générale | D6: Assistant Réception | E6: Convention de stage | F6: En cours | G6: Excellent | H6: Embauche CDI recommandée | I6: BTS | J6: Assiduité | K6: Haute | L6: Conforme | M6: Validé | N6: Hebdomadaire | O6: Janvier 2024 | P6: T1 2025 | Q6: Hausse | R6: 2023 | S6: Virement | T6: Candidature spontanée | U6: 1 | V6: Non-respect convention | W6: Accueil administratif | X6: Embauché CDI
A7: INP-HB | B7: Comptabilité | C7: Ressources Humaines | D7: Assistant Cuisinier | E7: Alternance | F7: Terminé | G7: Très bon | H7: Renouvellement conseillé | I7: Licence | J7: Qualité du travail | K7: Moyenne | L7: Partiellement conforme | M7: En attente | N7: Mensuelle | O7: Février 2024 | P7: T2 2025 | Q7: Baisse | R7: 2024 | S7: Chèque | T7: École partenaire | U7: 2 | V7: Problème indemnité | W7: Visite des locaux | X7: Embauché CDD
A8: EHESS Abidjan | B8: Marketing | C8: Finance & Comptabilité | D8: Assistant Comptable | E8: Stage de découverte | F8: Planifié | G8: Bon | H8: À retenir | I8: Master 1 | J8: Intégration équipe | K8: Basse | L8: Non conforme | M8: Rejeté | N8: Trimestrielle | O8: Mars 2024 | P8: T3 2025 | Q8: Stable | R8: 2025 | S8: Espèces | T8: Ancien stagiaire | U8: 3 | V8: Absence injustifiée | W8: Présentation équipe | X8: En attente décision
A9: Université FHB | B9: Informatique | C9: Marketing & Communication | D9: Assistant Marketing | E9: Stage de fin d'études | F9: Annulé | G9: Satisfaisant | H9: Non recommandé | I9: Master 2 | J9: Respect consignes | L9: En attente | M9: Non applicable | N9: Semestrielle | O9: Avril 2024 | P9: T4 2025 | T9: Plateforme emploi | U9: 4 | V9: Conflit avec tuteur | W9: Formation sécurité | X9: Non retenu
A10: Université Cocody | B10: Cuisine | C10: Informatique | D10: Développeur Stagiaire | E10: Stage de perfectionnement | F10: Prolongé | G10: Insuffisant | I10: Ingénieur | J10: Initiative | N10: Annuelle | O10: Mai 2024 | T10: Réseau DRH | U10: 5 | V10: Harcèlement | W10: Briefing poste | X10: Retour études
A11: Université Bouaké | B11: Génie Civil | C11: Commercial | D11: Agent de Communication | F11: Abandonné | G11: Mauvais | I11: Doctorat | J11: Ponctualité | O11: Juin 2024 | T11: Salon étudiant | V11: Autre | W11: Suivi semaine 1 | X11: Autre établissement
A12: ESP Annecy | B12: Droit | C12: Logistique & Approvisionnement | D12: Assistant RH | I12: CAP/BEP | J12: Communication | O12: Juillet 2024 | W12: Bilan intégration
A13: ISTC Abidjan | B13: Gestion | C13: Réception & Front Office | D13: Assistant Commercial | I13: Bac | O13: Août 2024 | W13: Fin de période essai
A14: Ecole Sup. Commerce | B14: Communication | C14: Cuisine & Restauration | D14: Stagiaire Entretien | O14: Septembre 2024
A15: UFRSEG Abidjan | B15: Langues | C15: Hébergement | D15: Stagiaire Hébergement | O15: Octobre 2024
A16: Ecole Hôtelière d'Abidjan | B16: Ressources Humaines | C16: Entretien & Maintenance | D16: Assistant Finance | O16: Novembre 2024
B17: Logistique | C17: Sécurité | D17: Stagiaire Informatique | O17: Décembre 2024
B18: Finance | C18: Service Client | D18: Assistant Pâtissier
B19: Commerce International | C19: Animation & Loisirs | D19: Stagiaire Sécurité
B20: Tourisme | C20: Spa & Bien-être | D20: Stagiaire Service Client
B21: Management Hôtelier | D21: Stagiaire Spa
B22: Pâtisserie | D22: Assistant Événementiel
D23: Stagiaire Logistique

Sheet F03 - 1-Tableau de Bord
A2: DOMAINE 24 — GESTION DES STAGIAIRES ET ALTERNANTS
A3: Tableau de Bord Synthétique — Suivi des stagiaires, coûts et partenariats
A5: INDICATEURS CLÉS
A6: Total Stagiaires en Poste | C6: Coût Mensuel Indemnités | E6: Conventions Actives | G6: Taux de Satisfaction Moyen | I6: Taux de Transformation (stage→CDI) | K6: Établissements Partenaires
A7: 8 | C7: 560 000 | E7: 10 | G7: 82% | I7: 15% | K7: 11
A9: DISTRIBUTION PAR DÉPARTEMENT | I9: DISTRIBUTION PAR TYPE DE STAGE
A10: Département | B10: Nb Stagiaires | C10: Indemnité Totale (FCFA) | D10: % du Total | I10: Type de Stage | J10: Nb Stagiaires | K10: % du Total
A11: Cuisine & Restauration | B11: 2 | C11: 150000 | D11: 25% | I11: Convention de stage | J11: 5 | K11: 62.5%
A12: Informatique | B12: 2 | C12: 160000 | D12: 25% | I12: Stage de fin d'études | J12: 2 | K12: 25%
A13: Marketing & Communication | B13: 1 | C13: 70000 | D13: 12.5% | I13: Alternance | J13: 1 | K13: 12.5%
A14: Finance & Comptabilité | B14: 1 | C14: 65000 | D14: 12.5%
A15: Entretien & Maintenance | B15: 1 | C15: 70000 | D15: 12.5%
A16: Réception & Front Office | B16: 1 | C16: 65000 | D16: 12.5%
A17: DISTRIBUTION PAR ÉTABLISSEMENT | I17: ACTIONS PLANIFIÉES
A18: Établissement | B18: Nb Stagiaires | C18: Indemnité Moyenne (FCFA) | D18: Satisfaction | I18: Action | J18: Responsable | K18: Échéance | L18: Priorité | M18: Statut
A19: FHB Abidjan | B19: 1 | C19: 75000 | D19: Très bon | I19: Renouveler convention FHB Abidjan | J19: DRH | K19: 45747 | L19: Haute | M19: En cours
A20: INP-HB | B20: 2 | C20: 75000 | D20: Bon | I20: Organiser salon stage Q2 | J20: DRH / Communication | K20: 45762 | L20: Moyenne | M20: Planifié
A21: EHESS Abidjan | B21: 1 | C21: 70000 | D21: Bon | I21: Mettre en place portail stagiaires | J21: Informatique / DRH | K21: 45808 | L21: Haute | M21: En cours
A22: Université FHB | B22: 1 | C22: 65000 | D22: Satisfaisant | I22: Évaluer programme tutorat | J22: DRH | K22: 45838 | L22: Moyenne | M22: Planifié
A23: Université Cocody | B23: 1 | C23: 65000 | D23: Bon
A24: ISTC Abidjan | B24: 1 | C24: 80000 | D24: Excellent
A25: Autres | B25: 1 | C25: 70000 | D25: Bon

Sheet F04 - 2-Besoins en Stagiaires
A2: 2-BESOINS EN STAGIAIRES
A3: TABLEAU DYNAMIQUE — Saisissez dans la zone prévue ci-dessous
A5: Code Besoin | B5: Département | C5: Poste | D5: Type de Stage | E5: Nombre Requis | F5: Date Souhaitée | G5: Durée (mois) | H5: Priorité | I5: Justification | J5: Statut | K5: Tuteur Proposé | L5: Date Création | M5: Observations
A6: =IF(B6="","",IF(COUNTA($A$6:A6)=0,"BES-"&TEXT(COUNTA($B$6:B6),"000"),"BES-"&TEXT(ROW()-5,"000"))) | B6: Cuisine & Restauration | C6: Assistant Cuisinier | D6: Convention de stage | E6: 2 | F6: 45717 | G6: 6 | H6: Haute | I6: Renfort haute saison | J6: En cours | K6: Chef Mbarga | L6: 45672 | M6: Prévoir cuisine et pâtisserie
A7: =IF(B7="","",IF(COUNTA($A$6:A7)=0,"BES-"&TEXT(COUNTA($B$6:B7),"000"),"BES-"&TEXT(ROW()-5,"000"))) | B7: Informatique | C7: Développeur Stagiaire | D7: Stage de fin d'études | E7: 1 | F7: 45748 | G7: 4 | H7: Haute | I7: Projet refonte site web | J7: En cours | K7: M. Bamba | L7: 45677 | M7: Compétences web et mobile requises
A8: =IF(B8="","",IF(COUNTA($A$6:A8)=0,"BES-"&TEXT(COUNTA($B$6:B8),"000"),"BES-"&TEXT(ROW()-5,"000"))) | B8: Marketing & Communication | C8: Agent de Communication | D8: Convention de stage | E8: 1 | F8: 45731 | G8: 3 | H8: Moyenne | I8: Renfort campagne été | J8: Planifié | K8: Mme Koffi | L8: 45689 | M8: Profil créatif et rédactionnel
A9: =IF(B9="","",IF(COUNTA($A$6:A9)=0,"BES-"&TEXT(COUNTA($B$6:B9),"000"),"BES-"&TEXT(ROW()-5,"000"))) | B9: Hébergement | C9: Stagiaire Hébergement | D9: Stage de découverte | E9: 1 | F9: 45809 | G9: 2 | H9: Basse | I9: Découverte métier hôtellerie | J9: Planifié | K9: Mme Nganou | L9: 45698 | M9: Candidat lycéen ou BTS 1ère année
A10: =IF(B10="","",IF(COUNTA($A$6:A10)=0,"BES-"&TEXT(COUNTA($B$6:B10),"000"),"BES-"&TEXT(ROW()-5,"000"))) | B10: Finance & Comptabilité | C10: Assistant Comptable | D10: Alternance | E10: 1 | F10: 45901 | G10: 12 | H10: Moyenne | I10: Remplacement assistant en alternance | J10: Planifié | K10: Mme Fotso | L10: 45703 | M10: Convention tripartite à signer
A11: =IF(B11="","",IF(COUNTA($A$6:A11)=0,"BES-"&TEXT(COUNTA($B$6:B11),"000"),"BES-"&TEXT(ROW()-5,"000")))
A12: =IF(B12="","",IF(COUNTA($A$6:A12)=0,"BES-"&TEXT(COUNTA($B$6:B12),"000"),"BES-"&TEXT(ROW()-5,"000")))
A13: =IF(B13="","",IF(COUNTA($A$6:A13)=0,"BES-"&TEXT(COUNTA($B$6:B13),"000"),"BES-"&TEXT(ROW()-5,"000")))
A14: =IF(B14="","",IF(COUNTA($A$6:A14)=0,"BES-"&TEXT(COUNTA($B$6:B14),"000"),"BES-"&TEXT(ROW()-5,"000")))
A15: =IF(B15="","",IF(COUNTA($A$6:A15)=0,"BES-"&TEXT(COUNTA($B$6:B15),"000"),"BES-"&TEXT(ROW()-5,"000")))
A16: =IF(B16="","",IF(COUNTA($A$6:A16)=0,"BES-"&TEXT(COUNTA($B$6:B16),"000"),"BES-"&TEXT(ROW()-5,"000")))
A17: =IF(B17="","",IF(COUNTA($A$6:A17)=0,"BES-"&TEXT(COUNTA($B$6:B17),"000"),"BES-"&TEXT(ROW()-5,"000")))
A18: =IF(B18="","",IF(COUNTA($A$6:A18)=0,"BES-"&TEXT(COUNTA($B$6:B18),"000"),"BES-"&TEXT(ROW()-5,"000")))
A19: =IF(B19="","",IF(COUNTA($A$6:A19)=0,"BES-"&TEXT(COUNTA($B$6:B19),"000"),"BES-"&TEXT(ROW()-5,"000")))
A20: =IF(B20="","",IF(COUNTA($A$6:A20)=0,"BES-"&TEXT(COUNTA($B$6:B20),"000"),"BES-"&TEXT(ROW()-5,"000")))
A21: =IF(B21="","",IF(COUNTA($A$6:A21)=0,"BES-"&TEXT(COUNTA($B$6:B21),"000"),"BES-"&TEXT(ROW()-5,"000")))
A22: =IF(B22="","",IF(COUNTA($A$6:A22)=0,"BES-"&TEXT(COUNTA($B$6:B22),"000"),"BES-"&TEXT(ROW()-5,"000")))
... A115: =IF(B115="","",IF(COUNTA($A$6:A115)=0,"BES-"&TEXT(COUNTA($B$6:B115),"000"),"BES-"&TEXT(ROW()-5,"000")))

Sheet F05 - 3-Conventions de Stage
A2: 3-CONVENTIONS DE STAGE
A3: TABLEAU DYNAMIQUE — Saisissez dans la zone prévue ci-dessous
A5: Code Convention | B5: Nom Stagiaire | C5: Établissement | D5: Formation | E5: Type de Stage | F5: Département | G5: Poste | H5: Tuteur | I5: Date Début | J5: Date Fin | K5: Indemnité Mensuelle (FCFA) | L5: Statut | M5: Conformité
A6: CONV-2025-001 | B6: Koné Aminata | C6: =IF(B6="","",VLOOKUP(B6,'F01 - _Données Stagiaires'!$B$6:$K$15,4,FALSE)) | D6: =IF(B6="","",VLOOKUP(B6,'F01 - _Données Stagiaires'!$B$6:$K$15,5,FALSE)) | E6: Convention de stage | F6: Cuisine & Restauration | G6: Assistant Cuisinier | H6: Chef Mbarga | I6: 45663 | J6: 45838 | K6: 75000 | L6: En cours | M6: Conforme
A7: CONV-2025-002 | B7: Traoré Ibrahim | C7: =IF(B7="","",VLOOKUP(B7,'F01 - _Données Stagiaires'!$B$6:$K$15,4,FALSE)) | D7: =IF(B7="","",VLOOKUP(B7,'F01 - _Données Stagiaires'!$B$6:$K$15,5,FALSE)) | E7: Stage de fin d'études | F7: Informatique | G7: Développeur Stagiaire | H7: M. Bamba | I7: 45689 | J7: 45869 | K7: 80000 | L7: En cours | M7: Conforme
A8: CONV-2024-012 | B8: Ouattara Moussa | C8: =IF(B8="","",VLOOKUP(B8,'F01 - _Données Stagiaires'!$B$6:$K$15,4,FALSE)) | D8: =IF(B8="","",VLOOKUP(B8,'F01 - _Données Stagiaires'!$B$6:$K$15,5,FALSE)) | E8: Convention de stage | F8: Finance & Comptabilité | G8: Assistant Comptable | H8: Mme Fotso | I8: 45536 | J8: 45716 | K8: 65000 | L8: Terminé | M8: Conforme
A9: CONV-2024-015 | B9: Djibril Oumar | C9: =IF(B9="","",VLOOKUP(B9,'F01 - _Données Stagiaires'!$B$6:$K$15,4,FALSE)) | D9: =IF(B9="","",VLOOKUP(B9,'F01 - _Données Stagiaires'!$B$6:$K$15,5,FALSE)) | E9: Stage de fin d'études | F9: Informatique | G9: Stagiaire Informatique | H9: M. Bamba | I9: 45444 | J9: 45657 | K9: 80000 | L9: Terminé | M9: Conforme
A10: CONV-2025-003 | B10: Bamba Mariam | C10: =IF(B10="","",VLOOKUP(B10,'F01 - _Données Stagiaires'!$B$6:$K$15,4,FALSE)) | D10: =IF(B10="","",VLOOKUP(B10,'F01 - _Données Stagiaires'!$B$6:$K$15,5,FALSE)) | E10: Convention de stage | F10: Cuisine & Restauration | G10: Assistant Pâtissier | H10: Chef Mbarga | I10: 45717 | J10: 45900 | K10: 75000 | L10: Planifié | M10: En attente
C11: =IF(B11="","",VLOOKUP(B11,'F01 - _Données Stagiaires'!$B$6:$K$15,4,FALSE)) | D11: =IF(B11="","",VLOOKUP(B11,'F01 - _Données Stagiaires'!$B$6:$K$15,5,FALSE))
C12: =IF(B12="","",VLOOKUP(B12,'F01 - _Données Stagiaires'!$B$6:$K$15,4,FALSE)) | D12: =IF(B12="","",VLOOKUP(B12,'F01 - _Données Stagiaires'!$B$6:$K$15,5,FALSE))
C13: =IF(B13="","",VLOOKUP(B13,'F01 - _Données Stagiaires'!$B$6:$K$15,4,FALSE)) | D13: =IF(B13="","",VLOOKUP(B13,'F01 - _Données Stagiaires'!$B$6:$K$15,5,FALSE))
C14: =IF(B14="","",VLOOKUP(B14,'F01 - _Données Stagiaires'!$B$6:$K$15,4,FALSE)) | D14: =IF(B14="","",VLOOKUP(B14,'F01 - _Données Stagiaires'!$B$6:$K$15,5,FALSE))
C15: =IF(B15="","",VLOOKUP(B15,'F01 - _Données Stagiaires'!$B$6:$K$15,4,FALSE)) | D15: =IF(B15="","",VLOOKUP(B15,'F01 - _Données Stagiaires'!$B$6:$K$15,5,FALSE))
C16: =IF(B16="","",VLOOKUP(B16,'F01 - _Données Stagiaires'!$B$6:$K$15,4,FALSE)) | D16: =IF(B16="","",VLOOKUP(B16,'F01 - _Données Stagiaires'!$B$6:$K$15,5,FALSE))
C17: =IF(B17="","",VLOOKUP(B17,'F01 - _Données Stagiaires'!$B$6:$K$15,4,FALSE)) | D17: =IF(B17="","",VLOOKUP(B17,'F01 - _Données Stagiaires'!$B$6:$K$15,5,FALSE))
C18: =IF(B18="","",VLOOKUP(B18,'F01 - _Données Stagiaires'!$B$6:$K$15,4,FALSE)) | D18: =IF(B18="","",VLOOKUP(B18,'F01 - _Données Stagiaires'!$B$6:$K$15,5,FALSE))
C19: =IF(B19="","",VLOOKUP(B19,'F01 - _Données Stagiaires'!$B$6:$K$15,4,FALSE)) | D19: =IF(B19="","",VLOOKUP(B19,'F01 - _Données Stagiaires'!$B$6:$K$15,5,FALSE))
C20: =IF(B20="","",VLOOKUP(B20,'F01 - _Données Stagiaires'!$B$6:$K$15,4,FALSE)) | D20: =IF(B20="","",VLOOKUP(B20,'F01 - _Données Stagiaires'!$B$6:$K$15,5,FALSE))
C21: =IF(B21="","",VLOOKUP(B21,'F01 - _Données Stagiaires'!$B$6:$K$15,4,FALSE)) | D21: =IF(B21="","",VLOOKUP(B21,'F01 - _Données Stagiaires'!$B$6:$K$15,5,FALSE))
C22: =IF(B22="","",VLOOKUP(B22,'F01 - _Données Stagiaires'!$B$6:$K$15,4,FALSE)) | D22: =IF(B22="","",VLOOKUP(B22,'F01 - _Données Stagiaires'!$B$6:$K$15,5,FALSE))
... C115: =IF(B115="","",VLOOKUP(B115,'F01 - _Données Stagiaires'!$B$6:$K$15,4,FALSE)) | D115: =IF(B115="","",VLOOKUP(B115,'F01 - _Données Stagiaires'!$B$6:$K$15,5,FALSE))

Sheet F06 - 4-Suivi Présence Stag.
A2: 4-SUIVI PRÉSENCE STAGIAIRES
A3: TABLEAU DYNAMIQUE — Saisissez dans la zone prévue ci-dessous
A5: Matricule | B5: Nom | C5: Prénom | D5: Département | E5: Mois | F5: Jours Présents | G5: Jours Absents | H5: Jours Ouvrables | I5: Taux de Présence (%) | J5: Commentaire | K5: Observations
A6: STA-001 | B6: =IF(A6="","",VLOOKUP(A6,'F01 - _Données Stagiaires'!$A$6:$K$15,2,FALSE)) | C6: =IF(A6="","",VLOOKUP(A6,'F01 - _Données Stagiaires'!$A$6:$K$15,3,FALSE)) | D6: =IF(A6="","",VLOOKUP(A6,'F01 - _Données Stagiaires'!$A$6:$K$15,6,FALSE)) | E6: Janvier 2025 | F6: 20 | G6: 2 | H6: 22 | I6: =IF(H6="","",IFERROR(F6/H6*100,0)) | J6: 2 absences justifiées (maladie)
A7: STA-002 | B7: =IF(A7="","",VLOOKUP(A7,'F01 - _Données Stagiaires'!$A$6:$K$15,2,FALSE)) | C7: =IF(A7="","",VLOOKUP(A7,'F01 - _Données Stagiaires'!$A$6:$K$15,3,FALSE)) | D7: =IF(A7="","",VLOOKUP(A7,'F01 - _Données Stagiaires'!$A$6:$K$15,6,FALSE)) | E7: Février 2025 | F7: 19 | G7: 1 | H7: 20 | I7: =IF(H7="","",IFERROR(F7/H7*100,0)) | J7: 1 absence autorisée (rendez-vous administratif)
A8: STA-003 | B8: =IF(A8="","",VLOOKUP(A8,'F01 - _Données Stagiaires'!$A$6:$K$15,2,FALSE)) | C8: =IF(A8="","",VLOOKUP(A8,'F01 - _Données Stagiaires'!$A$6:$K$15,3,FALSE)) | D8: =IF(A8="","",VLOOKUP(A8,'F01 - _Données Stagiaires'!$A$6:$K$15,6,FALSE)) | E8: Janvier 2025 | F8: 21 | G8: 1 | H8: 22 | I8: =IF(H8="","",IFERROR(F8/H8*100,0)) | J8: Présence exemplaire
A9: STA-006 | B9: =IF(A9="","",VLOOKUP(A9,'F01 - _Données Stagiaires'!$A$6:$K$15,2,FALSE)) | C9: =IF(A9="","",VLOOKUP(A9,'F01 - _Données Stagiaires'!$A$6:$K$15,3,FALSE)) | D9: =IF(A9="","",VLOOKUP(A9,'F01 - _Données Stagiaires'!$A$6:$K$15,6,FALSE)) | E9: Février 2025 | F9: 18 | G9: 2 | H9: 20 | I9: =IF(H9="","",IFERROR(F9/H9*100,0)) | J9: Retards à justifier
A10: STA-007 | B10: =IF(A10="","",VLOOKUP(A10,'F01 - _Données Stagiaires'!$A$6:$K$15,2,FALSE)) | C10: =IF(A10="","",VLOOKUP(A10,'F01 - _Données Stagiaires'!$A$6:$K$15,3,FALSE)) | D10: =IF(A10="","",VLOOKUP(A10,'F01 - _Données Stagiaires'!$A$6:$K$15,6,FALSE)) | E10: Janvier 2025 | F10: 22 | G10: 0 | H10: 22 | I10: =IF(H10="","",IFERROR(F10/H10*100,0)) | J10: Assiduité parfaite
B11: =IF(A11="","",VLOOKUP(A11,'F01 - _Données Stagiaires'!$A$6:$K$15,2,FALSE)) | C11: =IF(A11="","",VLOOKUP(A11,'F01 - _Données Stagiaires'!$A$6:$K$15,3,FALSE)) | D11: =IF(A11="","",VLOOKUP(A11,'F01 - _Données Stagiaires'!$A$6:$K$15,6,FALSE)) | I11: =IF(H11="","",IFERROR(F11/H11*100,0))
B12: =IF(A12="","",VLOOKUP(A12,'F01 - _Données Stagiaires'!$A$6:$K$15,2,FALSE)) | C12: =IF(A12="","",VLOOKUP(A12,'F01 - _Données Stagiaires'!$A$6:$K$15,3,FALSE)) | D12: =IF(A12="","",VLOOKUP(A12,'F01 - _Données Stagiaires'!$A$6:$K$15,6,FALSE)) | I12: =IF(H12="","",IFERROR(F12/H12*100,0))
B13: =IF(A13="","",VLOOKUP(A13,'F01 - _Données Stagiaires'!$A$6:$K$15,2,FALSE)) | C13: =IF(A13="","",VLOOKUP(A13,'F01 - _Données Stagiaires'!$A$6:$K$15,3,FALSE)) | D13: =IF(A13="","",VLOOKUP(A13,'F01 - _Données Stagiaires'!$A$6:$K$15,6,FALSE)) | I13: =IF(H13="","",IFERROR(F13/H13*100,0))
B14: =IF(A14="","",VLOOKUP(A14,'F01 - _Données Stagiaires'!$A$6:$K$15,2,FALSE)) | C14: =IF(A14="","",VLOOKUP(A14,'F01 - _Données Stagiaires'!$A$6:$K$15,3,FALSE)) | D14: =IF(A14="","",VLOOKUP(A14,'F01 - _Données Stagiaires'!$A$6:$K$15,6,FALSE)) | I14: =IF(H14="","",IFERROR(F14/H14*100,0))
B15: =IF(A15="","",VLOOKUP(A15,'F01 - _Données Stagiaires'!$A$6:$K$15,2,FALSE)) | C15: =IF(A15="","",VLOOKUP(A15,'F01 - _Données Stagiaires'!$A$6:$K$15,3,FALSE)) | D15: =IF(A15="","",VLOOKUP(A15,'F01 - _Données Stagiaires'!$A$6:$K$15,6,FALSE)) | I15: =IF(H15="","",IFERROR(F15/H15*100,0))
B16: =IF(A16="","",VLOOKUP(A16,'F01 - _Données Stagiaires'!$A$6:$K$15,2,FALSE)) | C16: =IF(A16="","",VLOOKUP(A16,'F01 - _Données Stagiaires'!$A$6:$K$15,3,FALSE)) | D16: =IF(A16="","",VLOOKUP(A16,'F01 - _Données Stagiaires'!$A$6:$K$15,6,FALSE)) | I16: =IF(H16="","",IFERROR(F16/H16*100,0))
B17: =IF(A17="","",VLOOKUP(A17,'F01 - _Données Stagiaires'!$A$6:$K$15,2,FALSE)) | C17: =IF(A17="","",VLOOKUP(A17,'F01 - _Données Stagiaires'!$A$6:$K$15,3,FALSE)) | D17: =IF(A17="","",VLOOKUP(A17,'F01 - _Données Stagiaires'!$A$6:$K$15,6,FALSE)) | I17: =IF(H17="","",IFERROR(F17/H17*100,0))
B18: =IF(A18="","",VLOOKUP(A18,'F01 - _Données Stagiaires'!$A$6:$K$15,2,FALSE)) | C18: =IF(A18="","",VLOOKUP(A18,'F01 - _Données Stagiaires'!$A$6:$K$15,3,FALSE)) | D18: =IF(A18="","",VLOOKUP(A18,'F01 - _Données Stagiaires'!$A$6:$K$15,6,FALSE)) | I18: =IF(H18="","",IFERROR(F18/H18*100,0))
B19: =IF(A19="","",VLOOKUP(A19,'F01 - _Données Stagiaires'!$A$6:$K$15,2,FALSE)) | C19: =IF(A19="","",VLOOKUP(A19,'F01 - _Données Stagiaires'!$A$6:$K$15,3,FALSE)) | D19: =IF(A19="","",VLOOKUP(A19,'F01 - _Données Stagiaires'!$A$6:$K$15,6,FALSE)) | I19: =IF(H19="","",IFERROR(F19/H19*100,0))
B20: =IF(A20="","",VLOOKUP(A20,'F01 - _Données Stagiaires'!$A$6:$K$15,2,FALSE)) | C20: =IF(A20="","",VLOOKUP(A20,'F01 - _Données Stagiaires'!$A$6:$K$15,3,FALSE)) | D20: =IF(A20="","",VLOOKUP(A20,'F01 - _Données Stagiaires'!$A$6:$K$15,6,FALSE)) | I20: =IF(H20="","",IFERROR(F20/H20*100,0))
B21: =IF(A21="","",VLOOKUP(A21,'F01 - _Données Stagiaires'!$A$6:$K$15,2,FALSE)) | C21: =IF(A21="","",VLOOKUP(A21,'F01 - _Données Stagiaires'!$A$6:$K$15,3,FALSE)) | D21: =IF(A21="","",VLOOKUP(A21,'F01 - _Données Stagiaires'!$A$6:$K$15,6,FALSE)) | I21: =IF(H21="","",IFERROR(F21/H21*100,0))
B22: =IF(A22="","",VLOOKUP(A22,'F01 - _Données Stagiaires'!$A$6:$K$15,2,FALSE)) | C22: =IF(A22="","",VLOOKUP(A22,'F01 - _Données Stagiaires'!$A$6:$K$15,3,FALSE)) | D22: =IF(A22="","",VLOOKUP(A22,'F01 - _Données Stagiaires'!$A$6:$K$15,6,FALSE)) | I22: =IF(H22="","",IFERROR(F22/H22*100,0))
... B115: =IF(A115="","",VLOOKUP(A115,'F01 - _Données Stagiaires'!$A$6:$K$15,2,FALSE)) | C115: =IF(A115="","",VLOOKUP(A115,'F01 - _Données Stagiaires'!$A$6:$K$15,3,FALSE)) | D115: =IF(A115="","",VLOOKUP(A115,'F01 - _Données Stagiaires'!$A$6:$K$15,6,FALSE)) | I115: =IF(H115="","",IFERROR(F115/H115*100,0))

Sheet F07 - 5-Éval. Stagiaires
A2: 5-ÉVALUATION STAGIAIRES
A3: TABLEAU DYNAMIQUE — Saisissez dans la zone prévue ci-dessous
A5: Code Éval. | B5: Nom Stagiaire | C5: Département | D5: Critère | E5: Note (1-5) | F5: Commentaire | G5: Évaluateur | H5: Date Éval. | I5: Période | J5: Observations
A6: EVA-001 | B6: =IF(B6="","",VLOOKUP(B6,'F01 - _Données Stagiaires'!$B$6:$B$15,1,FALSE)) | C6: =IF(B6="","",VLOOKUP(B6,'F01 - _Données Stagiaires'!$B$6:$K$15,6,FALSE)) | D6: Assiduité | E6: 5 | F6: Toujours ponctuelle et présente | G6: Chef Mbarga | H6: 45731 | I6: Mensuelle
A7: EVA-002 | B7: =IF(B7="","",VLOOKUP(B7,'F01 - _Données Stagiaires'!$B$6:$B$15,1,FALSE)) | C7: =IF(B7="","",VLOOKUP(B7,'F01 - _Données Stagiaires'!$B$6:$K$15,6,FALSE)) | D7: Qualité du travail | E7: 4 | F7: Bon travail, en progression | G7: Chef Mbarga | H7: 45731 | I7: Mensuelle
A8: EVA-003 | B8: =IF(B8="","",VLOOKUP(B8,'F01 - _Données Stagiaires'!$B$6:$B$15,1,FALSE)) | C8: =IF(B8="","",VLOOKUP(B8,'F01 - _Données Stagiaires'!$B$6:$K$15,6,FALSE)) | D8: Initiative | E8: 5 | F8: Propose des solutions innovantes | G8: M. Bamba | H8: 45731 | I8: Mensuelle
A9: EVA-004 | B9: =IF(B9="","",VLOOKUP(B9,'F01 - _Données Stagiaires'!$B$6:$B$15,1,FALSE)) | C9: =IF(B9="","",VLOOKUP(B9,'F01 - _Données Stagiaires'!$B$6:$K$15,6,FALSE)) | D9: Communication | E9: 4 | F9: Bonne communication orale et écrite | G9: Mme Koffi | H9: 45731 | I9: Mensuelle
A10: EVA-005 | B10: =IF(B10="","",VLOOKUP(B10,'F01 - _Données Stagiaires'!$B$6:$B$15,1,FALSE)) | C10: =IF(B10="","",VLOOKUP(B10,'F01 - _Données Stagiaires'!$B$6:$K$15,6,FALSE)) | D10: Respect consignes | E10: 3 | F10: Doit améliorer l'attention aux procédures | G10: M. Kamga | H10: 45731 | I10: Mensuelle
B11: =IF(B11="","",VLOOKUP(B11,'F01 - _Données Stagiaires'!$B$6:$B$15,1,FALSE)) | C11: =IF(B11="","",VLOOKUP(B11,'F01 - _Données Stagiaires'!$B$6:$K$15,6,FALSE))
B12: =IF(B12="","",VLOOKUP(B12,'F01 - _Données Stagiaires'!$B$6:$B$15,1,FALSE)) | C12: =IF(B12="","",VLOOKUP(B12,'F01 - _Données Stagiaires'!$B$6:$K$15,6,FALSE))
B13: =IF(B13="","",VLOOKUP(B13,'F01 - _Données Stagiaires'!$B$6:$B$15,1,FALSE)) | C13: =IF(B13="","",VLOOKUP(B13,'F01 - _Données Stagiaires'!$B$6:$K$15,6,FALSE))
B14: =IF(B14="","",VLOOKUP(B14,'F01 - _Données Stagiaires'!$B$6:$B$15,1,FALSE)) | C14: =IF(B14="","",VLOOKUP(B14,'F01 - _Données Stagiaires'!$B$6:$K$15,6,FALSE))
B15: =IF(B15="","",VLOOKUP(B15,'F01 - _Données Stagiaires'!$B$6:$B$15,1,FALSE)) | C15: =IF(B15="","",VLOOKUP(B15,'F01 - _Données Stagiaires'!$B$6:$K$15,6,FALSE))
B16: =IF(B16="","",VLOOKUP(B16,'F01 - _Données Stagiaires'!$B$6:$B$15,1,FALSE)) | C16: =IF(B16="","",VLOOKUP(B16,'F01 - _Données Stagiaires'!$B$6:$K$15,6,FALSE))
B17: =IF(B17="","",VLOOKUP(B17,'F01 - _Données Stagiaires'!$B$6:$B$15,1,FALSE)) | C17: =IF(B17="","",VLOOKUP(B17,'F01 - _Données Stagiaires'!$B$6:$K$15,6,FALSE))
B18: =IF(B18="","",VLOOKUP(B18,'F01 - _Données Stagiaires'!$B$6:$B$15,1,FALSE)) | C18: =IF(B18="","",VLOOKUP(B18,'F01 - _Données Stagiaires'!$B$6:$K$15,6,FALSE))
B19: =IF(B19="","",VLOOKUP(B19,'F01 - _Données Stagiaires'!$B$6:$B$15,1,FALSE)) | C19: =IF(B19="","",VLOOKUP(B19,'F01 - _Données Stagiaires'!$B$6:$K$15,6,FALSE))
B20: =IF(B20="","",VLOOKUP(B20,'F01 - _Données Stagiaires'!$B$6:$B$15,1,FALSE)) | C20: =IF(B20="","",VLOOKUP(B20,'F01 - _Données Stagiaires'!$B$6:$K$15,6,FALSE))
B21: =IF(B21="","",VLOOKUP(B21,'F01 - _Données Stagiaires'!$B$6:$B$15,1,FALSE)) | C21: =IF(B21="","",VLOOKUP(B21,'F01 - _Données Stagiaires'!$B$6:$K$15,6,FALSE))
B22: =IF(B22="","",VLOOKUP(B22,'F01 - _Données Stagiaires'!$B$6:$B$15,1,FALSE)) | C22: =IF(B22="","",VLOOKUP(B22,'F01 - _Données Stagiaires'!$B$6:$K$15,6,FALSE))
... B115: =IF(B115="","",VLOOKUP(B115,'F01 - _Données Stagiaires'!$B$6:$B$15,1,FALSE)) | C115: =IF(B115="","",VLOOKUP(B115,'F01 - _Données Stagiaires'!$B$6:$K$15,6,FALSE))

Sheet F08 - 6-Plan d'Intégration
A2: 6-PLAN D'INTÉGRATION
A3: TABLEAU DYNAMIQUE — Saisissez dans la zone prévue ci-dessous
A5: Nom Stagiaire | B5: Département | C5: Étape | D5: Activité | E5: Responsable | F5: Date Début | G5: Date Fin | H5: Statut | I5: Commentaire | J5: Observations
A6: Koné Aminata | B6: Cuisine & Restauration | C6: Accueil administratif | D6: Remise badge et dossier | E6: DRH | F6: 45663 | G6: 45663 | H6: Terminé | I6: Dossier complet
A7: Koné Aminata | B7: Cuisine & Restauration | C7: Visite des locaux | D7: Visite cuisine, restaurant, réserve | E7: Chef Mbarga | F7: 45663 | G7: 45664 | H7: Terminé | I7: Visite complète effectuée
A8: Traoré Ibrahim | B8: Informatique | C8: Formation sécurité | D8: Sensibilisation SI et sécurité données | E8: M. Bamba | F8: 45689 | G8: 45689 | H8: Terminé | I8: Charte signée
A9: Bamba Mariam | B9: Cuisine & Restauration | C9: Briefing poste | D9: Présentation brigade et planning | E9: Chef Mbarga | F9: 45717 | G9: 45718 | H9: Planifié | I9: À programmer

Sheet F09 - 7-Gestion Tuteurs
A2: 7-GESTION TUTEURS
A3: TABLEAU DYNAMIQUE — Saisissez dans la zone prévue ci-dessous
A5: Matricule Tuteur | B5: Nom | C5: Prénom | D5: Département | E5: Poste | F5: Expérience (ans) | G5: Nb Stagiaires Encadrés | H5: Évaluation Moyenne | I5: Disponibilité | J5: Certification Tuteur | K5: Observations
A6: TUT-001 | B6: Mbarga | C6: Sylvie | D6: Cuisine & Restauration | E6: Chef Cuisinier | F6: 12 | G6: 3 | H6: 4.5 | I6: Disponible | J6: Validé | K6: Excellente tutrice, 3 stagiaires formés
A7: TUT-002 | B7: Bamba | C7: Koffi | D7: Informatique | E7: DSI | F7: 8 | G7: 2 | H7: 4 | I7: Disponible | J7: Validé | K7: Patient et pédagogue
A8: TUT-003 | B8: Koffi | C8: Marie | D8: Marketing & Communication | E8: Resp. Marketing | F8: 6 | G8: 1 | H8: 3.8 | I8: Partiellement disponible | J8: En attente | K8: Bonne communicante
A9: TUT-004 | B9: Fotso | C9: Marie | D9: Finance & Comptabilité | E9: Comptable Senior | F9: 10 | G9: 2 | H9: 4.2 | I9: Disponible | J9: Validé | K9: Expérience solide en tutorat
A10: TUT-005 | B10: Kamga | C10: Samuel | D10: Entretien & Maintenance | E10: Chef Entretien | F10: 7 | G10: 1 | H10: 3.5 | I10: Disponible | J10: Non applicable | K10: Première expérience tutorat

Sheet F10 - 8-Suivi Indemnités
A2: 8-SUIVI INDEMNITÉS STAGIAIRES
A3: TABLEAU DYNAMIQUE — Saisissez dans la zone prévue ci-dessous
A5: Code Paiement | B5: Nom Stagiaire | C5: Mois | D5: Montant Brut (FCFA) | E5: Retenues (FCFA) | F5: Montant Net (FCFA) | G5: Mode Paiement | H5: Date Paiement | I5: Statut | J5: Référence | K5: Observations
A6: PAY-2025-001 | B6: Koné Aminata | C6: Janvier 2025 | D6: 75000 | E6: =IF(D6="","",IFERROR(D6*0.015,0)) | F6: =IF(D6="","",D6-E6) | G6: Virement | H6: 45688 | I6: Validé | J6: VIR-2501-001
A7: PAY-2025-002 | B7: Traoré Ibrahim | C7: Janvier 2025 | D7: 80000 | E7: =IF(D7="","",IFERROR(D7*0.015,0)) | F7: =IF(D7="","",D7-E7) | G7: Virement | H7: 45688 | I7: Validé | J7: VIR-2501-002
A8: PAY-2025-003 | B8: Diallo Fatou | C8: Janvier 2025 | D8: 70000 | E8: =IF(D8="","",IFERROR(D8*0.015,0)) | F8: =IF(D8="","",D8-E8) | G8: Virement | H8: 45688 | I8: Validé | J8: VIR-2501-003
A9: PAY-2025-004 | B9: Coulibaly Adama | C9: Janvier 2025 | D9: 70000 | E9: =IF(D9="","",IFERROR(D9*0.015,0)) | F9: =IF(D9="","",D9-E9) | G9: Chèque | H9: 45688 | I9: En attente | J9: CHQ-2501-001
A10: PAY-2025-005 | B10: Konan Yao | C10: Février 2025 | D10: 65000 | E10: =IF(D10="","",IFERROR(D10*0.015,0)) | F10: =IF(D10="","",D10-E10) | G10: Virement | I10: En attente
E11: =IF(D11="","",IFERROR(D11*0.015,0)) | F11: =IF(D11="","",D11-E11)
E12: =IF(D12="","",IFERROR(D12*0.015,0)) | F12: =IF(D12="","",D12-E12)
E13: =IF(D13="","",IFERROR(D13*0.015,0)) | F13: =IF(D13="","",D13-E13)
E14: =IF(D14="","",IFERROR(D14*0.015,0)) | F14: =IF(D14="","",D14-E14)
E15: =IF(D15="","",IFERROR(D15*0.015,0)) | F15: =IF(D15="","",D15-E15)
E16: =IF(D16="","",IFERROR(D16*0.015,0)) | F16: =IF(D16="","",D16-E16)
E17: =IF(D17="","",IFERROR(D17*0.015,0)) | F17: =IF(D17="","",D17-E17)
E18: =IF(D18="","",IFERROR(D18*0.015,0)) | F18: =IF(D18="","",D18-E18)
E19: =IF(D19="","",IFERROR(D19*0.015,0)) | F19: =IF(D19="","",D19-E19)
E20: =IF(D20="","",IFERROR(D20*0.015,0)) | F20: =IF(D20="","",D20-E20)
E21: =IF(D21="","",IFERROR(D21*0.015,0)) | F21: =IF(D21="","",D21-E21)
E22: =IF(D22="","",IFERROR(D22*0.015,0)) | F22: =IF(D22="","",D22-E22)
... E115: =IF(D115="","",IFERROR(D115*0.015,0)) | F115: =IF(D115="","",D115-E115)

Sheet F11 - 9-Rapports de Stage
A2: 9-RAPPORTS DE STAGE
A3: TABLEAU DYNAMIQUE — Saisissez dans la zone prévue ci-dessous
A5: Code Rapport | B5: Nom Stagiaire | C5: Département | D5: Titre Rapport | E5: Date Soumission | F5: Qualité | G5: Note Globale | H5: Retour Tuteur | I5: Commentaire RH | J5: Observations
A6: RAP-2024-003 | B6: Ouattara Moussa | C6: =IF(B6="","",VLOOKUP(B6,'F01 - _Données Stagiaires'!$B$6:$K$15,6,FALSE)) | D6: Analyse des procédures comptables hôtelières | E6: 45703 | F6: Très bon | G6: 4 | H6: Travail sérieux et approfondi | I6: Profil à retenir pour un CDD
A7: RAP-2024-005 | B7: Djibril Oumar | C7: =IF(B7="","",VLOOKUP(B7,'F01 - _Données Stagiaires'!$B$6:$K$15,6,FALSE)) | D7: Mise en place d'un système de gestion des stocks | E7: 45667 | F7: Excellent | G7: 5 | H7: Projet innovant et fonctionnel | I7: Profil CDI fortement recommandé
A8: RAP-2024-001 | B8: Konan Yao | C8: =IF(B8="","",VLOOKUP(B8,'F01 - _Données Stagiaires'!$B$6:$K$15,6,FALSE)) | D8: Étude du processus de recrutement | E8: 45726 | F8: Bon | G8: 3 | H8: Bon travail de recherche | I8: À retenir pour futur besoin RH
A9: RAP-2025-001 | B9: Diallo Fatou | C9: =IF(B9="","",VLOOKUP(B9,'F01 - _Données Stagiaires'!$B$6:$K$15,6,FALSE)) | D9: Stratégie digitale pour l'hôtel | E9: 45736 | F9: Très bon | G9: 4 | H9: Excellente créativité
C10: =IF(B10="","",VLOOKUP(B10,'F01 - _Données Stagiaires'!$B$6:$K$15,6,FALSE))
C11: =IF(B11="","",VLOOKUP(B11,'F01 - _Données Stagiaires'!$B$6:$K$15,6,FALSE))
C12: =IF(B12="","",VLOOKUP(B12,'F01 - _Données Stagiaires'!$B$6:$K$15,6,FALSE))
C13: =IF(B13="","",VLOOKUP(B13,'F01 - _Données Stagiaires'!$B$6:$K$15,6,FALSE))
C14: =IF(B14="","",VLOOKUP(B14,'F01 - _Données Stagiaires'!$B$6:$K$15,6,FALSE))
C15: =IF(B15="","",VLOOKUP(B15,'F01 - _Données Stagiaires'!$B$6:$K$15,6,FALSE))
C16: =IF(B16="","",VLOOKUP(B16,'F01 - _Données Stagiaires'!$B$6:$K$15,6,FALSE))
C17: =IF(B17="","",VLOOKUP(B17,'F01 - _Données Stagiaires'!$B$6:$K$15,6,FALSE))
C18: =IF(B18="","",VLOOKUP(B18,'F01 - _Données Stagiaires'!$B$6:$K$15,6,FALSE))
C19: =IF(B19="","",VLOOKUP(B19,'F01 - _Données Stagiaires'!$B$6:$K$15,6,FALSE))
C20: =IF(B20="","",VLOOKUP(B20,'F01 - _Données Stagiaires'!$B$6:$K$15,6,FALSE))
C21: =IF(B21="","",VLOOKUP(B21,'F01 - _Données Stagiaires'!$B$6:$K$15,6,FALSE))
... C115: =IF(B115="","",VLOOKUP(B115,'F01 - _Données Stagiaires'!$B$6:$K$15,6,FALSE))

Sheet F12 - 10-Analyse Coûts Stages
A2: 10-ANALYSE COÛTS STAGES
A3: TABLEAU DYNAMIQUE — Saisissez dans la zone prévue ci-dessous
A5: Mois | B5: Nb Stagiaires | C5: Total Indemnités (FCFA) | D5: Coût Moyen/Stagiaire | E5: Budget Prévu (FCFA) | F5: Écart (FCFA) | G5: Taux Réalisation (%) | H5: Tendance | I5: Observations
A6: Janvier 2025 | B6: 8 | C6: =IFERROR(SUMIF('F10 - 8-Suivi Indemnités'!C:C,A6,'F10 - 8-Suivi Indemnités'!F:F),0) | D6: =IF(B6="","",IFERROR(C6/B6,0)) | E6: 600000 | F6: =IF(E6="","",E6-C6) | G6: =IF(E6="","",IFERROR(C6/E6*100,0)) | H6: =IF(G6="","",IF(G6>100,"Hausse",IF(G6<95,"Baisse","Stable"))) | I6: 8 stagiaires actifs ce mois
A7: Février 2025 | B7: 8 | C7: =IFERROR(SUMIF('F10 - 8-Suivi Indemnités'!C:C,A7,'F10 - 8-Suivi Indemnités'!F:F),0) | D7: =IF(B7="","",IFERROR(C7/B7,0)) | E7: 600000 | F7: =IF(E7="","",E7-C7) | G7: =IF(E7="","",IFERROR(C7/E7*100,0)) | H7: =IF(G7="","",IF(G7>100,"Hausse",IF(G7<95,"Baisse","Stable"))) | I7: Stable, pas de variation
A8: Mars 2025 | B8: 9 | C8: =IFERROR(SUMIF('F10 - 8-Suivi Indemnités'!C:C,A8,'F10 - 8-Suivi Indemnités'!F:F),0) | D8: =IF(B8="","",IFERROR(C8/B8,0)) | E8: 650000 | F8: =IF(E8="","",E8-C8) | G8: =IF(E8="","",IFERROR(C8/E8*100,0)) | H8: =IF(G8="","",IF(G8>100,"Hausse",IF(G8<95,"Baisse","Stable"))) | I8: Arrivée nouvelle stagiaire cuisine
A9: Avril 2025 | B9: 9 | C9: =IFERROR(SUMIF('F10 - 8-Suivi Indemnités'!C:C,A9,'F10 - 8-Suivi Indemnités'!F:F),0) | D9: =IF(B9="","",IFERROR(C9/B9,0)) | E9: 650000 | F9: =IF(E9="","",E9-C9) | G9: =IF(E9="","",IFERROR(C9/E9*100,0)) | H9: =IF(G9="","",IF(G9>100,"Hausse",IF(G9<95,"Baisse","Stable"))) | I9: Prévision stable
A10: Mai 2025 | B10: 8 | C10: =IFERROR(SUMIF('F10 - 8-Suivi Indemnités'!C:C,A10,'F10 - 8-Suivi Indemnités'!F:F),0) | D10: =IF(B10="","",IFERROR(C10/B10,0)) | E10: 600000 | F10: =IF(E10="","",E10-C10) | G10: =IF(E10="","",IFERROR(C10/E10*100,0)) | H10: =IF(G10="","",IF(G10>100,"Hausse",IF(G10<95,"Baisse","Stable"))) | I10: Départ d'un stagiaire
A11: Juin 2025 | B11: 7 | C11: =IFERROR(SUMIF('F10 - 8-Suivi Indemnités'!C:C,A11,'F10 - 8-Suivi Indemnités'!F:F),0) | D11: =IF(B11="","",IFERROR(C11/B11,0)) | E11: 550000 | F11: =IF(E11="","",E11-C11) | G11: =IF(E11="","",IFERROR(C11/E11*100,0)) | H11: =IF(G11="","",IF(G11>100,"Hausse",IF(G11<95,"Baisse","Stable"))) | I11: Fin de stage marketing
A12: Juillet 2025 | B12: 8 | C12: =IFERROR(SUMIF('F10 - 8-Suivi Indemnités'!C:C,A12,'F10 - 8-Suivi Indemnités'!F:F),0) | D12: =IF(B12="","",IFERROR(C12/B12,0)) | E12: 600000 | F12: =IF(E12="","",E12-C12) | G12: =IF(E12="","",IFERROR(C12/E12*100,0)) | H12: =IF(G12="","",IF(G12>100,"Hausse",IF(G12<95,"Baisse","Stable"))) | I12: Nouvelle arrivée prévue
A13: Août 2025 | B13: 8 | C13: =IFERROR(SUMIF('F10 - 8-Suivi Indemnités'!C:C,A13,'F10 - 8-Suivi Indemnités'!F:F),0) | D13: =IF(B13="","",IFERROR(C13/B13,0)) | E13: 600000 | F13: =IF(E13="","",E13-C13) | G13: =IF(E13="","",IFERROR(C13/E13*100,0)) | H13: =IF(G13="","",IF(G13>100,"Hausse",IF(G13<95,"Baisse","Stable"))) | I13: Haute saison
A14: Septembre 2025 | B14: 6 | C14: =IFERROR(SUMIF('F10 - 8-Suivi Indemnités'!C:C,A14,'F10 - 8-Suivi Indemnités'!F:F),0) | D14: =IF(B14="","",IFERROR(C14/B14,0)) | E14: 500000 | F14: =IF(E14="","",E14-C14) | G14: =IF(E14="","",IFERROR(C14/E14*100,0)) | H14: =IF(G14="","",IF(G14>100,"Hausse",IF(G14<95,"Baisse","Stable"))) | I14: Départs fin de stage
A15: Octobre 2025 | B15: 6 | C15: =IFERROR(SUMIF('F10 - 8-Suivi Indemnités'!C:C,A15,'F10 - 8-Suivi Indemnités'!F:F),0) | D15: =IF(B15="","",IFERROR(C15/B15,0)) | E15: 500000 | F15: =IF(E15="","",E15-C15) | G15: =IF(E15="","",IFERROR(C15/E15*100,0)) | H15: =IF(G15="","",IF(G15>100,"Hausse",IF(G15<95,"Baisse","Stable"))) | I15: Basse saison
A16: Novembre 2025 | B16: 7 | C16: =IFERROR(SUMIF('F10 - 8-Suivi Indemnités'!C:C,A16,'F10 - 8-Suivi Indemnités'!F:F),0) | D16: =IF(B16="","",IFERROR(C16/B16,0)) | E16: 550000 | F16: =IF(E16="","",E16-C16) | G16: =IF(E16="","",IFERROR(C16/E16*100,0)) | H16: =IF(G16="","",IF(G16>100,"Hausse",IF(G16<95,"Baisse","Stable"))) | I16: Reprise progressive
A17: Décembre 2025 | B17: 9 | C17: =IFERROR(SUMIF('F10 - 8-Suivi Indemnités'!C:C,A17,'F10 - 8-Suivi Indemnités'!F:F),0) | D17: =IF(B17="","",IFERROR(C17/B17,0)) | E17: 700000 | F17: =IF(E17="","",E17-C17) | G17: =IF(E17="","",IFERROR(C17/E17*100,0)) | H17: =IF(G17="","",IF(G17>100,"Hausse",IF(G17<95,"Baisse","Stable"))) | I17: Pic fêtes de fin d'année

Sheet F13 - 11-Partenariats Étab.
A2: 11-PARTENARIATS ÉTABLISSEMENTS
A3: TABLEAU DYNAMIQUE — Saisissez dans la zone prévue ci-dessous
A5: Établissement | B5: Contact | C5: Téléphone | D5: Email | E5: Type Partenariat | F5: Nb Stagiaires Reçus | G5: Satisfaction Moyenne | H5: Convention Active | I5: Date Renouvellement | J5: Commentaire | K5: Observations
A6: FHB Abidjan | B6: M. N'Guessan Aimé | C6: +225 07 12 34 56 | D6: stage@fhb.ci | E6: Convention cadre | F6: 5 | G6: 4.2 | H6: Validé | I6: 46203 | J6: Partenariat historique, très fiable
A7: INP-HB | B7: Mme Aka Béatrice | C7: +225 05 98 76 54 | D7: scolarite@inphb.ci | E7: Convention spécifique | F7: 4 | G7: 4 | H7: Validé | I7: 46022 | J7: Profils techniques de qualité
A8: EHESS Abidjan | B8: M. Touré Ibrahim | C8: +225 01 65 43 21 | D8: stage@ehess.ci | E8: Convention stage | F8: 2 | G8: 3.8 | H8: En attente | I8: 45930 | J8: Bons profils marketing et comm.
A9: ISTC Abidjan | B9: M. Konan Yves | C9: +225 07 88 77 66 | D9: info@istc.ci | E9: Convention cadre | F9: 3 | G9: 4.5 | H9: Validé | I9: 46112 | J9: Excellents profils en informatique
A10: Université Cocody | B10: Mme Diop Aminata | C10: +225 05 44 33 22 | D10: stage@univ-cocody.ci | E10: Convention stage | F10: 2 | G10: 3.5 | H10: En attente | I10: 45961 | J10: Partenariat à renforcer

Sheet F14 - 12-Suivi Post-Stage
A2: 12-SUIVI POST-STAGE
A3: TABLEAU DYNAMIQUE — Saisissez dans la zone prévue ci-dessous
A5: Nom Stagiaire | B5: Département | C5: Date Fin Stage | D5: Statut Post-Stage | E5: Date Embauche | F5: Poste Occupé | G5: Type Contrat | H5: Salaire (FCFA) | I5: Commentaire | J5: Observations
A6: Ouattara Moussa | B6: =IF(A6="","",VLOOKUP(A6,'F01 - _Données Stagiaires'!$B$6:$K$15,6,FALSE)) | C6: 45716 | D6: En attente décision | H6: 0 | I6: Profil intéressant, en discussion avec DAF
A7: Djibril Oumar | B7: =IF(A7="","",VLOOKUP(A7,'F01 - _Données Stagiaires'!$B$6:$K$15,6,FALSE)) | C7: 45657 | D7: Embauché CDI | E7: 45672 | F7: Technicien Informatique | G7: CDI | H7: 350000 | I7: Embauche suite excellent rapport de stage
A8: Konan Yao | B8: =IF(A8="","",VLOOKUP(A8,'F01 - _Données Stagiaires'!$B$6:$K$15,6,FALSE)) | C8: 45747 | D8: En attente décision | H8: 0 | I8: En attente validation poste disponible
A9: Sangaré Awa | B9: =IF(A9="","",VLOOKUP(A9,'F01 - _Données Stagiaires'!$B$6:$K$15,6,FALSE)) | C9: 45535 | D9: Non retenu | H9: 0 | I9: Profil ne correspond pas aux attentes actuelles
B10: =IF(A10="","",VLOOKUP(A10,'F01 - _Données Stagiaires'!$B$6:$K$15,6,FALSE))
B11: =IF(A11="","",VLOOKUP(A11,'F01 - _Données Stagiaires'!$B$6:$K$15,6,FALSE))
B12: =IF(A12="","",VLOOKUP(A12,'F01 - _Données Stagiaires'!$B$6:$K$15,6,FALSE))
B13: =IF(A13="","",VLOOKUP(A13,'F01 - _Données Stagiaires'!$B$6:$K$15,6,FALSE))
B14: =IF(A14="","",VLOOKUP(A14,'F01 - _Données Stagiaires'!$B$6:$K$15,6,FALSE))
B15: =IF(A15="","",VLOOKUP(A15,'F01 - _Données Stagiaires'!$B$6:$K$15,6,FALSE))
B16: =IF(A16="","",VLOOKUP(A16,'F01 - _Données Stagiaires'!$B$6:$K$15,6,FALSE))
B17: =IF(A17="","",VLOOKUP(A17,'F01 - _Données Stagiaires'!$B$6:$K$15,6,FALSE))
B18: =IF(A18="","",VLOOKUP(A18,'F01 - _Données Stagiaires'!$B$6:$K$15,6,FALSE))
B19: =IF(A19="","",VLOOKUP(A19,'F01 - _Données Stagiaires'!$B$6:$K$15,6,FALSE))
B20: =IF(A20="","",VLOOKUP(A20,'F01 - _Données Stagiaires'!$B$6:$K$15,6,FALSE))
B21: =IF(A21="","",VLOOKUP(A21,'F01 - _Données Stagiaires'!$B$6:$K$15,6,FALSE))
... B115: =IF(A115="","",VLOOKUP(A115,'F01 - _Données Stagiaires'!$B$6:$K$15,6,FALSE))

Sheet F15 - 13-Plannings Stages
A2: 13-PLANNINGS STAGES
A3: TABLEAU DYNAMIQUE — Saisissez dans la zone prévue ci-dessous
A5: Nom Stagiaire | B5: Département | C5: Lundi | D5: Mardi | E5: Mercredi | F5: Jeudi | G5: Vendredi | H5: Samedi | I5: Total Heures/Semaine | J5: Observations
A6: Koné Aminata | B6: Cuisine & Restauration | C6: 8 | D6: 8 | E6: 8 | F6: 8 | G6: 8 | H6: 4 | I6: =SUM(C6:H6) | J6: Planning brigade cuisine standard
A7: Traoré Ibrahim | B7: Informatique | C7: 8 | D7: 8 | E7: 8 | F7: 8 | G7: 8 | H7: 0 | I7: =SUM(C7:H7) | J7: Pas de travail le samedi
A8: Diallo Fatou | B8: Marketing & Communication | C8: 8 | D8: 8 | E8: 8 | F8: 8 | G8: 8 | H8: 0 | I8: =SUM(C8:H8) | J8: Horaires de bureau
A9: Coulibaly Adama | B9: Entretien & Maintenance | C9: 8 | D9: 8 | E9: 8 | F9: 8 | G9: 8 | H9: 4 | I9: =SUM(C9:H9) | J9: Rotation Samedi avec équipe
A10: Yao Akissi | B10: Réception & Front Office | C10: 8 | D10: 8 | E10: 8 | F10: 8 | G10: 8 | H10: 4 | I10: =SUM(C10:H10) | J10: Horaires réception 3 shifts
I11: =SUM(C11:H11)
I12: =SUM(C12:H12)
I13: =SUM(C13:H13)
I14: =SUM(C14:H14)
I15: =SUM(C15:H15)
I16: =SUM(C16:H16)
I17: =SUM(C17:H17)
I18: =SUM(C18:H18)
I19: =SUM(C19:H19)
I20: =SUM(C20:H20)
I21: =SUM(C21:H21)
I22: =SUM(C22:H22)
... I115: =SUM(C115:H115)

Sheet F16 - 14-Litiges Stages
A2: 14-GESTION LITIGES STAGES
A3: TABLEAU DYNAMIQUE — Saisissez dans la zone prévue ci-dessous
A5: Code Litige | B5: Nom Stagiaire | C5: Type Litige | D5: Date Signalement | E5: Description | F5: Priorité | G5: Statut | H5: Responsable Suivi | I5: Date Résolution | J5: Commentaire | K5: Observations
A6: LIT-STA-001 | B6: Sangaré Awa | C6: Non-respect convention | D6: 45488 | E6: Horaires dépassés sans compensation ni validation | F6: Moyenne | G6: Résolu | H6: DRH | I6: 45505 | J6: Convention amendée, horaires respectés depuis
A7: LIT-STA-002 | B7: Djibril Oumar | C7: Problème indemnité | D7: 45585 | E7: Retard de paiement indemnité octobre de 10 jours | F7: Haute | G7: Résolu | H7: DAF | I7: 45595 | J7: Paiement effectué avec régularisation
A8: LIT-STA-003 | B8: Konan Yao | C8: Conflit avec tuteur | D8: 45667 | E8: Différend sur les tâches assignées vs. convention | F8: Moyenne | G8: En cours | H8: DRH | J8: Médiation en cours entre stagiaire et tuteur

Sheet F17 - 15-Historique Stagiaires
A2: 15-HISTORIQUE STAGIAIRES
A3: TABLEAU DYNAMIQUE — Saisissez dans la zone prévue ci-dessous
A5: Nom | B5: Prénom | C5: Établissement | D5: Département | E5: Date Début | F5: Date Fin | G5: Durée (jours) | H5: Évaluation Finale | I5: Recommandation | J5: Statut | K5: Observations
A6: Ouattara | B6: Moussa | C6: Université FHB | D6: Finance & Comptabilité | E6: 45536 | F6: 45716 | G6: =IF(OR(E6="",F6=""),"",F6-E6) | H6: 4 | I6: =IF(H6="","",IF(H6>=4,"Embauche CDI recommandée",IF(H6>=3,"À retenir","Non recommandé"))) | J6: Terminé | K6: Stage de fin d'études, très bon niveau
A7: Djibril | B7: Oumar | C7: ISTC Abidjan | D7: Informatique | E7: 45444 | F7: 45657 | G7: =IF(OR(E7="",F7=""),"",F7-E7) | H7: 5 | I7: =IF(H7="","",IF(H7>=4,"Embauche CDI recommandée",IF(H7>=3,"À retenir","Non recommandé"))) | J7: Terminé | K7: Excellente performance, embauché CDI
A8: Sangaré | B8: Awa | C8: Ecole Sup. Commerce | D8: Commercial | E8: 45352 | F8: 45535 | G8: =IF(OR(E8="",F8=""),"",F8-E8) | H8: 2 | I8: =IF(H8="","",IF(H8>=4,"Embauche CDI recommandée",IF(H8>=3,"À retenir","Non recommandé"))) | J8: Terminé | K8: Stage décevant, litige en cours
A9: N'dri | B9: Fatou | C9: FHB Abidjan | D9: Hébergement | E9: 45170 | F9: 45350 | G9: =IF(OR(E9="",F9=""),"",F9-E9) | H9: 3 | I9: =IF(H9="","",IF(H9>=4,"Embauche CDI recommandée",IF(H9>=3,"À retenir","Non recommandé"))) | J9: Terminé | K9: Travail correct, pas de poste disponible
A10: Koffi | B10: Aristide | C10: INP-HB | D10: Cuisine & Restauration | E10: 45078 | F10: 45291 | G10: =IF(OR(E10="",F10=""),"",F10-E10) | H10: 4 | I10: =IF(H10="","",IF(H10>=4,"Embauche CDI recommandée",IF(H10>=3,"À retenir","Non recommandé"))) | J10: Terminé | K10: Bon cuisinier, parti chez concurrent
G11: =IF(OR(E11="",F11=""),"",F11-E11) | I11: =IF(H11="","",IF(H11>=4,"Embauche CDI recommandée",IF(H11>=3,"À retenir","Non recommandé")))
G12: =IF(OR(E12="",F12=""),"",F12-E12) | I12: =IF(H12="","",IF(H12>=4,"Embauche CDI recommandée",IF(H12>=3,"À retenir","Non recommandé")))
G13: =IF(OR(E13="",F13=""),"",F13-E13) | I13: =IF(H13="","",IF(H13>=4,"Embauche CDI recommandée",IF(H13>=3,"À retenir","Non recommandé")))
G14: =IF(OR(E14="",F14=""),"",F14-E14) | I14: =IF(H14="","",IF(H14>=4,"Embauche CDI recommandée",IF(H14>=3,"À retenir","Non recommandé")))
G15: =IF(OR(E15="",F15=""),"",F15-E15) | I15: =IF(H15="","",IF(H15>=4,"Embauche CDI recommandée",IF(H15>=3,"À retenir","Non recommandé")))
G16: =IF(OR(E16="",F16=""),"",F16-E16) | I16: =IF(H16="","",IF(H16>=4,"Embauche CDI recommandée",IF(H16>=3,"À retenir","Non recommandé")))
G17: =IF(OR(E17="",F17=""),"",F17-E17) | I17: =IF(H17="","",IF(H17>=4,"Embauche CDI recommandée",IF(H17>=3,"À retenir","Non recommandé")))
G18: =IF(OR(E18="",F18=""),"",F18-E18) | I18: =IF(H18="","",IF(H18>=4,"Embauche CDI recommandée",IF(H18>=3,"À retenir","Non recommandé")))
G19: =IF(OR(E19="",F19=""),"",F19-E19) | I19: =IF(H19="","",IF(H19>=4,"Embauche CDI recommandée",IF(H19>=3,"À retenir","Non recommandé")))
G20: =IF(OR(E20="",F20=""),"",F20-E20) | I20: =IF(H20="","",IF(H20>=4,"Embauche CDI recommandée",IF(H20>=3,"À retenir","Non recommandé")))
G21: =IF(OR(E21="",F21=""),"",F21-E21) | I21: =IF(H21="","",IF(H21>=4,"Embauche CDI recommandée",IF(H21>=3,"À retenir","Non recommandé")))
G22: =IF(OR(E22="",F22=""),"",F22-E22) | I22: =IF(H22="","",IF(H22>=4,"Embauche CDI recommandée",IF(H22>=3,"À retenir","Non recommandé")))
... G115: =IF(OR(E115="",F115=""),"",F115-E115) | I115: =IF(H115="","",IF(H115>=4,"Embauche CDI recommandée",IF(H115>=3,"À retenir","Non recommandé")))

Sheet F18 - 16-Calendrier Stages
A2: 16-CALENDRIER STAGES
A3: TABLEAU DYNAMIQUE — Saisissez dans la zone prévue ci-dessous
A5: Stagiaire | B5: Département | C5: Date Début | D5: Date Fin | E5: Jours Restants | F5: Alertes | G5: Événements | H5: Actions Requises | I5: Observations
A6: Koné Aminata | B6: Cuisine & Restauration | C6: 45663 | D6: 45838 | E6: =IF(D6="","",IFERROR(D6-TODAY(),0)) | F6: =IF(E6="","",IF(E6<15,"URGENT",IF(E6<30,"Attention",""))) | G6: Évaluation mi-parcours mars | H6: Planifier entretien tuteur
A7: Traoré Ibrahim | B7: Informatique | C7: 45689 | D7: 45869 | E7: =IF(D7="","",IFERROR(D7-TODAY(),0)) | F7: =IF(E7="","",IF(E7<15,"URGENT",IF(E7<30,"Attention",""))) | G7: Soutenance rapport juillet | H7: Préparer convention fin de stage
A8: Diallo Fatou | B8: Marketing & Communication | C8: 45672 | D8: 45762 | E8: =IF(D8="","",IFERROR(D8-TODAY(),0)) | F8: =IF(E8="","",IF(E8<15,"URGENT",IF(E8<30,"Attention",""))) | G8: Fin de stage proche | H8: Organiser bilan final
A9: Coulibaly Adama | B9: Entretien & Maintenance | C9: 45663 | D9: 45838 | E9: =IF(D9="","",IFERROR(D9-TODAY(),0)) | F9: =IF(E9="","",IF(E9<15,"URGENT",IF(E9<30,"Attention",""))) | G9: Formation sécurité à jour
A10: Konan Yao | B10: Ressources Humaines | C10: 45566 | D10: 45747 | E10: =IF(D10="","",IFERROR(D10-TODAY(),0)) | F10: =IF(E10="","",IF(E10<15,"URGENT",IF(E10<30,"Attention",""))) | G10: Fin de stage imminente | H10: Décider prolongation ou fin
E11: =IF(D11="","",IFERROR(D11-TODAY(),0)) | F11: =IF(E11="","",IF(E11<15,"URGENT",IF(E11<30,"Attention","")))
E12: =IF(D12="","",IFERROR(D12-TODAY(),0)) | F12: =IF(E12="","",IF(E12<15,"URGENT",IF(E12<30,"Attention","")))
E13: =IF(D13="","",IFERROR(D13-TODAY(),0)) | F13: =IF(E13="","",IF(E13<15,"URGENT",IF(E13<30,"Attention","")))
E14: =IF(D14="","",IFERROR(D14-TODAY(),0)) | F14: =IF(E14="","",IF(E14<15,"URGENT",IF(E14<30,"Attention","")))
E15: =IF(D15="","",IFERROR(D15-TODAY(),0)) | F15: =IF(E15="","",IF(E15<15,"URGENT",IF(E15<30,"Attention","")))
E16: =IF(D16="","",IFERROR(D16-TODAY(),0)) | F16: =IF(E16="","",IF(E16<15,"URGENT",IF(E16<30,"Attention","")))
E17: =IF(D17="","",IFERROR(D17-TODAY(),0)) | F17: =IF(E17="","",IF(E17<15,"URGENT",IF(E17<30,"Attention","")))
E18: =IF(D18="","",IFERROR(D18-TODAY(),0)) | F18: =IF(E18="","",IF(E18<15,"URGENT",IF(E18<30,"Attention","")))
E19: =IF(D19="","",IFERROR(D19-TODAY(),0)) | F19: =IF(E19="","",IF(E19<15,"URGENT",IF(E19<30,"Attention","")))
E20: =IF(D20="","",IFERROR(D20-TODAY(),0)) | F20: =IF(E20="","",IF(E20<15,"URGENT",IF(E20<30,"Attention","")))
E21: =IF(D21="","",IFERROR(D21-TODAY(),0)) | F21: =IF(E21="","",IF(E21<15,"URGENT",IF(E21<30,"Attention","")))
E22: =IF(D22="","",IFERROR(D22-TODAY(),0)) | F22: =IF(E22="","",IF(E22<15,"URGENT",IF(E22<30,"Attention","")))
... E115: =IF(D115="","",IFERROR(D115-TODAY(),0)) | F115: =IF(E115="","",IF(E115<15,"URGENT",IF(E115<30,"Attention","")))

Sheet F19 - 17-Matrice Stag×Dép
A2: 17-MATRICE STAGIAIRES × DÉPARTEMENTS
A3: TABLEAU DYNAMIQUE — Saisissez dans la zone prévue ci-dessous
A5: Département | B5: Total | C5: Janv. | D5: Fév. | E5: Mars | F5: Avr. | G5: Mai | H5: Juin | I5: Juil. | J5: Août | K5: Sept. | L5: Oct. | M5: Nov. | N5: Déc.
A6: Direction Générale | B6: =SUM(C6:N6) | C6: 0 | D6: 0 | E6: 0 | F6: 0 | G6: 0 | H6: 0 | I6: 0 | J6: 0 | K6: 0 | L6: 0 | M6: 0 | N6: 0
A7: Ressources Humaines | B7: =SUM(C7:N7) | C7: 1 | D7: 1 | E7: 1 | F7: 1 | G7: 1 | H7: 0 | I7: 0 | J7: 0 | K7: 0 | L7: 0 | M7: 1 | N7: 1
A8: Finance & Comptabilité | B8: =SUM(C8:N8) | C8: 1 | D8: 1 | E8: 1 | F8: 1 | G8: 1 | H8: 1 | I8: 1 | J8: 1 | K8: 1 | L8: 1 | M8: 1 | N8: 1
A9: Marketing & Communication | B9: =SUM(C9:N9) | C9: 1 | D9: 1 | E9: 1 | F9: 1 | G9: 1 | H9: 0 | I9: 1 | J9: 1 | K9: 1 | L9: 1 | M9: 1 | N9: 1
A10: Informatique | B10: =SUM(C10:N10) | C10: 1 | D10: 2 | E10: 2 | F10: 2 | G10: 2 | H10: 2 | I10: 2 | J10: 2 | K10: 1 | L10: 1 | M10: 1 | N10: 2
A11: Commercial | B11: =SUM(C11:N11) | C11: 1 | D11: 1 | E11: 1 | F11: 1 | G11: 1 | H11: 1 | I11: 0 | J11: 0 | K11: 0 | L11: 0 | M11: 1 | N11: 1
A12: Logistique & Approvisionnement | B12: =SUM(C12:N12) | C12: 0 | D12: 0 | E12: 0 | F12: 0 | G12: 0 | H12: 0 | I12: 0 | J12: 0 | K12: 0 | L12: 0 | M12: 0 | N12: 0
A13: Réception & Front Office | B13: =SUM(C13:N13) | C13: 1 | D13: 1 | E13: 1 | F13: 1 | G13: 1 | H13: 1 | I13: 1 | J13: 1 | K13: 1 | L13: 1 | M13: 1 | N13: 1
A14: Cuisine & Restauration | B14: =SUM(C14:N14) | C14: 2 | D14: 2 | E14: 3 | F14: 3 | G14: 2 | H14: 2 | I14: 2 | J14: 2 | K14: 1 | L14: 1 | M14: 2 | N14: 3
A15: Hébergement | B15: =SUM(C15:N15) | C15: 0 | D15: 0 | E15: 1 | F15: 1 | G15: 1 | H15: 1 | I15: 1 | J15: 1 | K15: 0 | L15: 0 | M15: 1 | N15: 1
A16: Entretien & Maintenance | B16: =SUM(C16:N16) | C16: 1 | D16: 1 | E16: 1 | F16: 1 | G16: 1 | H16: 1 | I16: 1 | J16: 1 | K16: 1 | L16: 1 | M16: 1 | N16: 1
A17: Sécurité | B17: =SUM(C17:N17) | C17: 0 | D17: 0 | E17: 0 | F17: 0 | G17: 0 | H17: 0 | I17: 0 | J17: 0 | K17: 0 | L17: 0 | M17: 0 | N17: 0
... A20: Spa & Bien-être | B20: =SUM(C20:N20) | C20: 0 | D20: 0 | E20: 0 | F20: 0 | G20: 0 | H20: 0 | I20: 0 | J20: 0 | K20: 0 | L20: 0 | M20: 0 | N20: 0
A21: TOTAL MENSUEL | B21: =SUM(B6:B20) | C21: =SUM(C6:C20) | D21: =SUM(D6:D20) | E21: =SUM(E6:E20) | F21: =SUM(F6:F20) | G21: =SUM(G6:G20) | H21: =SUM(H6:H20) | I21: =SUM(I6:I20) | ... N21: =SUM(N6:N20)

Sheet F20 - 18-TdB Financier Stages
A2: 18-TABLEAU DE BORD FINANCIER STAGES
A3: TABLEAU DYNAMIQUE — Saisissez dans la zone prévue ci-dessous
A5: Mois | B5: Indemnités Stagiaires | C5: Coûts Administratifs | D5: Coûts Formation | E5: Coûts Divers | F5: Total Coûts (FCFA) | G5: Budget (FCFA) | H5: Variance (FCFA) | I5: Taux Réalisation | J5: Observations
A6: Janvier 2025 | B6: 560000 | C6: 50000 | D6: 75000 | E6: 20000 | F6: =SUM(B6:E6) | G6: 750000 | H6: =IF(G6="","",G6-F6) | I6: =IF(G6="","",IFERROR(F6/G6*100,0)) | J6: Démarrage année, formation intégration
A7: Février 2025 | B7: 560000 | C7: 50000 | D7: 50000 | E7: 15000 | F7: =SUM(B7:E7) | G7: 720000 | H7: =IF(G7="","",G7-F7) | I7: =IF(G7="","",IFERROR(F7/G7*100,0)) | J7: Coûts stabilisés
A8: Mars 2025 | B8: 630000 | C8: 55000 | D8: 60000 | E8: 18000 | F8: =SUM(B8:E8) | G8: 800000 | H8: =IF(G8="","",G8-F8) | I8: =IF(G8="","",IFERROR(F8/G8*100,0)) | J8: Arrivée nouvelle stagiaire
A9: Avril 2025 | B9: 630000 | C9: 55000 | D9: 40000 | E9: 12000 | F9: =SUM(B9:E9) | G9: 780000 | H9: =IF(G9="","",G9-F9) | I9: =IF(G9="","",IFERROR(F9/G9*100,0)) | J9: Coûts formation réduits
A10: Mai 2025 | B10: 560000 | C10: 50000 | D10: 45000 | E10: 15000 | F10: =SUM(B10:E10) | G10: 720000 | H10: =IF(G10="","",G10-F10) | I10: =IF(G10="","",IFERROR(F10/G10*100,0)) | J10: Départ stagiaire marketing
A11: Juin 2025 | B11: 490000 | C11: 45000 | D11: 40000 | E11: 10000 | F11: =SUM(B11:E11) | G11: 630000 | H11: =IF(G11="","",G11-F11) | I11: =IF(G11="","",IFERROR(F11/G11*100,0)) | J11: Baisse prévue fin de stage
A12: Juillet 2025 | B12: 560000 | C12: 50000 | D12: 80000 | E12: 20000 | F12: =SUM(B12:E12) | G12: 760000 | H12: =IF(G12="","",G12-F12) | I12: =IF(G12="","",IFERROR(F12/G12*100,0)) | J12: Nouvelles arrivées, formations
A13: Août 2025 | B13: 560000 | C13: 50000 | D13: 50000 | E13: 15000 | F13: =SUM(B13:E13) | G13: 720000 | H13: =IF(G13="","",G13-F13) | I13: =IF(G13="","",IFERROR(F13/G13*100,0)) | J13: Haute saison, coûts stables
A14: Septembre 2025 | B14: 420000 | C14: 40000 | D14: 30000 | E14: 10000 | F14: =SUM(B14:E14) | G14: 550000 | H14: =IF(G14="","",G14-F14) | I14: =IF(G14="","",IFERROR(F14/G14*100,0)) | J14: Départs massifs fin de stage
A15: Octobre 2025 | B15: 420000 | C15: 40000 | D15: 35000 | E15: 12000 | F15: =SUM(B15:E15) | G15: 560000 | H15: =IF(G15="","",G15-F15) | I15: =IF(G15="","",IFERROR(F15/G15*100,0)) | J15: Basse saison
A16: Novembre 2025 | B16: 490000 | C16: 45000 | D16: 40000 | E16: 15000 | F16: =SUM(B16:E16) | G16: 630000 | H16: =IF(G16="","",G16-F16) | I16: =IF(G16="","",IFERROR(F16/G16*100,0)) | J16: Reprise
A17: Décembre 2025 | B17: 630000 | C17: 55000 | D17: 60000 | E17: 20000 | F17: =SUM(B17:E17) | G17: 820000 | H17: =IF(G17="","",G17-F17) | I17: =IF(G17="","",IFERROR(F17/G17*100,0)) | J17: Pic fêtes, max. stagiaires

Sheet F21 - 19-Indic. Performance
A2: 19-INDICATEURS PERFORMANCE
A3: TABLEAU DYNAMIQUE — Saisissez dans la zone prévue ci-dessous
A5: Code Indicateur | B5: Indicateur | C5: Cible | D5: Valeur Actuelle | E5: Écart | F5: Tendance | G5: Période | H5: Responsable | I5: Commentaire | J5: Observations
A6: STA-01 | B6: Taux de satisfaction | C6: ≥85% | D6: 82% | E6: =IF(C6="","",IFERROR(D6-C6,0)) | F6: =IF(E6="","",IF(E6>0,"Hausse","Baisse")) | G6: T1 2025 | H6: DRH | I6: Proche de la cible, actions en cours
A7: STA-02 | B7: Taux de transformation (stage→CDI) | C7: ≥20% | D7: 15% | E7: =IF(C7="","",IFERROR(D7-C7,0)) | F7: =IF(E7="","",IF(E7>0,"Hausse","Baisse")) | G7: T1 2025 | H7: DRH | I7: 2 embauches sur 13 stages en 2024
A8: STA-03 | B8: Délai moyen d'intégration | C8: ≤3 jours | D8: 2.5 jours | E8: =IF(C8="","",IFERROR(D8-C8,0)) | F8: =IF(E8="","",IF(E8>0,"Hausse","Baisse")) | G8: T1 2025 | H8: DRH | I8: Processus d'accueil bien rodé
A9: STA-04 | B9: Taux de présence | C9: ≥90% | D9: 93% | E9: =IF(C9="","",IFERROR(D9-C9,0)) | F9: =IF(E9="","",IF(E9>0,"Hausse","Baisse")) | G9: T1 2025 | H9: DRH | I9: Bon niveau d'assiduité
A10: STA-05 | B10: Coût moyen/stagiaire budget | C10: ±10% | D10: -5% | E10: =IF(C10="","",IFERROR(D10-C10,0)) | F10: =IF(E10="","",IF(E10>0,"Hausse","Baisse")) | G10: T1 2025 | H10: DAF | I10: Sous-budget, bonne gestion
A11: STA-06 | B11: Nb litiges | C11: ≤2/trimestre | D11: 1 | E11: =IF(C11="","",IFERROR(D11-C11,0)) | F11: =IF(E11="","",IF(E11>0,"Hausse","Baisse")) | G11: T1 2025 | H11: DRH | I11: 1 litige en cours de résolution
A12: STA-07 | B12: Taux conformité conventions | C12: 100% | D12: 95% | E12: =IF(C12="","",IFERROR(D12-C12,0)) | F12: =IF(E12="","",IF(E12>0,"Hausse","Baisse")) | G12: T1 2025 | H12: DRH | I12: 1 convention en attente de signature
A13: STA-08 | B13: Taux de recommandation | C13: ≥60% | D13: 55% | E13: =IF(C13="","",IFERROR(D13-C13,0)) | F13: =IF(E13="","",IF(E13>0,"Hausse","Baisse")) | G13: T1 2025 | H13: DRH | I13: En amélioration
A14: STA-09 | B14: Nb établissements partenaires | C14: ≥8 | D14: 11 | E14: =IF(C14="","",IFERROR(D14-C14,0)) | F14: =IF(E14="","",IF(E14>0,"Hausse","Baisse")) | G14: T1 2025 | H14: DRH | I14: Objectif dépassé
A15: STA-10 | B15: Délai paiement indemnités | C15: ≤5 jours | D15: 3 jours | E15: =IF(C15="","",IFERROR(D15-C15,0)) | F15: =IF(E15="","",IF(E15>0,"Hausse","Baisse")) | G15: T1 2025 | H15: DAF | I15: Processus de paiement fluide
