Workbook

Sheet _Données Employés
A1: Matricule | B1: Nom | C1: Prénom | D1: Département | E1: Poste | F1: Salaire Brut | G1: Genre | H1: Date Embauche
A2: EMP-001 | B2: Nganou | C2: Clarisse | D2: Cuisine & Restauration | E2: Chef | F2: 450000 | G2: F | H2: 2020-01-15
A3: EMP-002 | B3: Tagne | C3: René | D3: Réception & Front Office | E3: Réceptionniste | F3: 165000 | G3: H | H3: 2019-06-01
A4: EMP-003 | B4: Fotso | C4: Camille | D4: Cuisine & Restauration | E4: Cuisinier | F4: 180000 | G4: H | H4: 2021-03-10
A5: EMP-004 | B5: Tchinda | C5: Arlette | D5: Service Client | E5: Assistante RH | F5: 200000 | G5: F | H5: 2022-09-01
A6: EMP-005 | B6: Ngansop | C6: Sylvie | D6: Finance & Comptabilité | E6: Comptable senior | F6: 250000 | G6: F | H6: 2018-02-20
A7: EMP-006 | B7: Fokam | C7: Eric | D7: Réception & Front Office | E7: Chef Réception | F7: 280000 | G7: H | H7: 2017-08-15
A8: EMP-007 | B8: Tchouankou | C8: Paul | D8: Étage & Housekeeping | E8: Chef Étage | F8: 230000 | G8: H | H8: 2020-11-01
A9: EMP-008 | B9: Awa | C9: Fatou | D9: Commercial | E9: Agent Commercial | F9: 155000 | G9: F | H9: 2023-01-15
A10: EMP-009 | B10: Bouba | C10: Ahmed | D10: Cuisine & Restauration | E10: Sous-Chef | F10: 210000 | G10: H | H10: 2019-04-01
A11: EMP-010 | B11: Kamga | C11: Patrice | D11: Sécurité | E11: Chef Sécurité | F11: 210000 | G11: H | H11: 2021-07-01
A12: EMP-011 | B12: Ngo | C12: Delphine | D12: Marketing & Communication | E12: Chef Marketing | F12: 300000 | G12: F | H12: 2018-05-15
A13: EMP-012 | B13: Tamo | C13: Elvis | D13: Logistique & Approvisionnement | E13: Chef Logistique | F13: 240000 | G13: H | H13: 2022-03-01
... A15: EMP-014 | B15: Kane | C15: Adama | D15: Direction Générale | E15: DAF | F15: 350000 | G15: H | H15: 2016-01-10

Sheet 1-Tableau de Bord
B2: DOMAINE 17 — AUDIT, CONFORMITE LEGALE & CONTENTIEUX
B3: TABLEAU DE BORD — Vue synthetique de tous les indicateurs du domaine (mis a jour automatiquement)
B5: Exigences legales | E5: Echeances legales | H5: Dossiers contentieux | K5: Criteres audit
B6: =COUNTIF('2-Checklist Conformite Legale'!B5:B104,"<>") | E6: =COUNTIF('3-Calendrier Echeances Legales'!B5:B104,"<>") | H6: =COUNTIF('4-Suivi Contentieux'!B5:B104,"<>") | K6: =COUNTIF('5-Audit Interne RH'!B5:B104,"<>")
B9: Actions post-audit | E9: Assurances RH | H9: Mises en demeure | K9: Taux conformite
B10: =COUNTIF('6-Plans Action Post-Audit'!B5:B104,"<>") | E10: =COUNTIF('7-Gestion Assurances RH'!B5:B104,"<>") | H10: =COUNTIF('8-Registre Mises en Demeure'!B5:B104,"<>") | K10: =IFERROR(COUNTIF('2-Checklist Conformite Legale'!H5:H104,"Conforme")/COUNTIF('2-Checklist Conformite Legale'!B5:B104,"<>"),0)
B14: CONFORMITE PAR DOMAINE & RISQUES AUDIT
B15: Domaine | C15: Nb Exigences
B16: Droit du travail | C16: =COUNTIF('2-Checklist Conformite Legale'!D5:D104,"*Droit du travail*")
B17: CNPS | C17: =COUNTIF('2-Checklist Conformite Legale'!D5:D104,"*CNPS*")
B18: Code du travail | C18: =COUNTIF('2-Checklist Conformite Legale'!D5:D104,"*Code du travail*")
B19: Reglement interieur | C19: =COUNTIF('2-Checklist Conformite Legale'!D5:D104,"*Reglement interieur*")
B20: Normes HSE | C20: =COUNTIF('2-Checklist Conformite Legale'!D5:D104,"*Normes HSE*")
B21: Legislation fiscale | C21: =COUNTIF('2-Checklist Conformite Legale'!D5:D104,"*Legislation fiscale*")
H23: Statut Conformite | I23: Nombre
H24: Conforme | I24: =COUNTIF('2-Checklist Conformite Legale'!H5:H104,"Conforme")
H25: Partiellement conforme | I25: =COUNTIF('2-Checklist Conformite Legale'!H5:H104,"Partiellement conforme")
H26: Non conforme | I26: =COUNTIF('2-Checklist Conformite Legale'!H5:H104,"Non conforme")
H27: Non evalue | I27: =COUNTIF('2-Checklist Conformite Legale'!H5:H104,"Non evalue")

Sheet _Lists
B1: domaine_conformite | C1: statut_conformite | D1: type_echeance | E1: type_contentieux | F1: statut_procedure | G1: type_auditeur | H1: niveau_risque | I1: statut_action_audit | J1: type_assurance | K1: type_injonction | L1: emetteur_injonction | M1: statut_injonction | N1: priorite_action_conf | O1: poste_hotel | P1: departement | Q1: mois | R1: annee
B2: Droit du travail | C2: Conforme | D2: Mensuelle | E2: Prud'hommes | F2: En cours d'instruction | G2: Interne DRH | H2: Critique | I2: Planifiee | J2: AT - Accidents du travail | K2: Mise en demeure | L2: Inspection du travail | M2: En cours | N2: Haute | O2: DG | P2: Direction Générale | Q2: Janvier | R2: 2024
B3: Code du travail | C3: Non conforme | D3: Trimestrielle | E3: Tribunal de grande instance | F3: En attente audience | G3: Interne DG | H3: Eleve | I3: En cours | J3: Maladie professionnelle | K3: Injonction | L3: CNPS | M3: Traitee | N3: Moyenne | O3: DRH | P3: Service Client | Q3: Fevrier | R3: 2025
B4: Convention collective | C4: Partiellement conforme | D4: Semestrielle | E4: Tribunal correctionnel | F4: En negociation | G4: Externe - Cabinet audit | H4: Moyen | I4: Terminee | J4: Responsabilite civile employeur | K4: Avertissement | L4: Tribunal | M4: En attente reponse | N4: Basse | O4: Assistante RH | P4: Finance & Comptabilité | Q4: Mars | R4: 2026
B5: Reglement interieur | C5: En cours de mise en conformite | D5: Annuelle | E5: Arbitrage | F5: En mediation | G5: Externe - Inspecteur travail | H5: Faible | I5: Reportee | J5: Protection juridique | K5: Somation | L5: Ministere du travail | M5: En retard | O5: DAF | P5: Marketing & Communication | Q5: Avril
B6: Legislation sociale | C6: Non evalue | D6: Ponctuelle | E6: Mediation | F6: En conciliation | G6: Externe - Expert comptable | H6: Negligeable | I6: Annulee | J6: Deces - Invalidite | K6: Refere | L6: Organisme fiscal | M6: Contestee | O6: Comptable senior | P6: Informatique | Q6: Mai
B7: Normes HSE | C7: En cours d'evaluation | D7: Bisannuelle | E7: Conciliation | F7: En attente jugement | G7: Externe - CNPS | I7: En attente validation | J7: Medecine du travail | K7: Ordonnance tribunal | L7: Syndicat | M7: Resolue | O7: Chef Comptable | P7: Commercial | Q7: Juin
B8: Legislation fiscale | C8: Exempte | D8: Quinquennale | E8: Inspection travail | F8: Jugement rendu | G8: Mixte (interne + externe) | I8: Non demarree | J8: Assurance chomage | K8: Contravention | L8: Avocat partie adverse | M8: Escaladee | O8: Chef Marketing | P8: Logistique & Approvisionnement | Q8: Juillet
B9: Reglementation hoteliere | E9: Recours administratif | F9: En appel | J9: Prevoyance | K9: Procuration | L9: Medecin inspecteur | M9: Rejetee | O9: Chef de service IT | P9: Cuisine & Restauration | Q9: Aout
B10: Inspection du travail | F10: Abandonne | O10: Chef Commercial | P10: Réception & Front Office | Q10: Octobre
B11: Code penal social | F11: Reporte | O11: Agent Commercial | P11: Cuisine & Restauration | Q11: Novembre
B12: Autre | F12: En preparation | O12: Chef Logistique | P12: Maintenance | Q12: Decembre
O13: Magasinier | P13: Sécurité
O14: Chef Reception
O15: Receptionniste
O16: Concierge
O17: Chef Cuisine
O18: Sous-Chef
O19: Cuisinier
O20: Plongeur
O21: Chef Entretien
O22: Agent Entretien
O23: Chef Sécurité
O24: Agent Sécurité

Sheet 2-Checklist Conformite Legale
B2: CHECKLIST DE CONFORMITE LEGALE RH (#129)
B3: TABLEAU DYNAMIQUE — Saisissez dans la prochaine ligne jaune. Les calculs se mettent a jour automatiquement.
B4: N° | C4: Exigence Legale | D4: Domaine Conformite | E4: Texte de Reference | F4: Responsable | G4: Date Verification | H4: Statut Conformite | I4: Ecart Identifie | J4: Action Corrective | K4: Echeance Correction | L4: Statut
B5: CCL-001 | C5: Affichage reglement interieur | D5: Code du travail | E5: Art. L. 1311-1 Code Travail | F5: DRH | G5: 45787 | H5: Conforme | I5: Aucun | J5: Aucune requise | L5: Terminee
B6: CCL-002 | C6: Declaration CNPS mensuelle | D6: CNPS | E6: Art. 12 Convention CNPS | F6: Comptable senior | G6: 45813 | H6: Conforme | I6: Aucun | J6: Aucune requise | L6: Terminee
B7: CCL-003 | C7: Visite medicale embauche | D7: Droit du travail | E7: Art. L. 4624-1 Code Travail | F7: DRH | G7: 45797 | H7: Non conforme | I7: 3 agents sans visite | J7: Planifier visites | K7: 45853 | L7: En cours
B8: CCL-004 | C8: Delivrance fiche de paie | D8: Code du travail | E8: Art. L. 3243-1 Code Travail | F8: DAF | G8: 45809 | H8: Conforme | I8: Aucun | J8: Aucune requise | L8: Terminee
B9: CCL-005 | C9: Registre unique du personnel | D9: Droit du travail | E9: Art. L. 1221-13 Code Travail | F9: Assistante RH | G9: 45818 | H9: Partiellement conforme | I9: 2 contrats manquants | J9: Completer registre | K9: 45839 | L9: En cours
B10: =IF(C10="","CCL-"&TEXT(COUNTA($C$5:C10),"000"))
B11: =IF(C11="","CCL-"&TEXT(COUNTA($C$5:C11),"000"))
B12: =IF(C12="","CCL-"&TEXT(COUNTA($C$5:C12),"000"))
B13: =IF(C13="","CCL-"&TEXT(COUNTA($C$5:C13),"000"))
B14: =IF(C14="","CCL-"&TEXT(COUNTA($C$5:C14),"000"))
B15: =IF(C15="","CCL-"&TEXT(COUNTA($C$5:C15),"000"))
B16: =IF(C16="","CCL-"&TEXT(COUNTA($C$5:C16),"000"))
B17: =IF(C17="","CCL-"&TEXT(COUNTA($C$5:C17),"000"))
B18: =IF(C18="","CCL-"&TEXT(COUNTA($C$5:C18),"000"))
B19: =IF(C19="","CCL-"&TEXT(COUNTA($C$5:C19),"000"))
B20: =IF(C20="","CCL-"&TEXT(COUNTA($C$5:C20),"000"))
B21: =IF(C21="","CCL-"&TEXT(COUNTA($C$5:C21),"000"))
... B109: =IF(C109="","CCL-"&TEXT(COUNTA($C$5:C109),"000"))
B111: INDICATEURS (mis a jour automatiquement)
B112: Exigences suivies | D112: Conformes | F112: Non conformes | H112: Taux conformite
B113: =COUNTIF(B5:B104,"<>") | D113: =COUNTIF(H5:H104,"Conforme") | F113: =COUNTIF(H5:H104,"Non conforme")+COUNTIF(H5:H104,"Partiellement conforme") | H113: =IFERROR(COUNTIF(H5:H104,"Conforme")/COUNTIF(B5:B104,"<>"),0)

Sheet 3-Calendrier Echeances Legales
B2: CALENDRIER DES ECHEANCES LEGALES & DECLARATIVES (#130)
B3: TABLEAU DYNAMIQUE — Saisissez dans la prochaine ligne jaune. Les calculs se mettent a jour automatiquement.
B4: N° | C4: Obligation Legale | D4: Domaine | E4: Frequence | F4: Echeance Prochaine | G4: Jours Restants | H4: Responsable | I4: Montant Estime (FCFA) | J4: Date Declaration | K4: N° Reference | L4: Statut
B5: CEL-001 | C5: Declaration CNPS cotisations | D5: CNPS | E5: Mensuelle | F5: 45853 | H5: Comptable senior | I5: 2850000 | K5: CNPS-2025-06 | L5: En cours
B6: CEL-002 | C6: Bulletin de paie mensuel | D6: Droit du travail | E6: Mensuelle | F6: 45869 | H6: DAF | I6: 0 | L6: En cours
B7: CEL-003 | C7: Bilan social annuel | D7: Reglement interieur | E7: Annuelle | F7: 46112 | H7: DRH | I7: 0 | K7: BS-2025 | L7: En cours
B8: CEL-004 | C8: Taxe apprentissage | D8: Legislation fiscale | E8: Annuelle | F8: 45961 | H8: DAF | I8: 350000 | K8: TAXA-2025 | L8: En cours
B9: CEL-005 | C9: Visite medicale periodique | D9: Droit du travail | E9: Annuelle | F9: 45930 | H9: DRH | I9: 180000 | K9: VM-2025 | L9: En cours
B10: =IF(C10="","CEL-"&TEXT(COUNTA($C$5:C10),"000")) | G10: =IF(F10="","",F10-TODAY())
B11: =IF(C11="","CEL-"&TEXT(COUNTA($C$5:C11),"000")) | G11: =IF(F11="","",F11-TODAY())
B12: =IF(C12="","CEL-"&TEXT(COUNTA($C$5:C12),"000")) | G12: =IF(F12="","",F12-TODAY())
B13: =IF(C13="","CEL-"&TEXT(COUNTA($C$5:C13),"000")) | G13: =IF(F13="","",F13-TODAY())
B14: =IF(C14="","CEL-"&TEXT(COUNTA($C$5:C14),"000")) | G14: =IF(F14="","",F14-TODAY())
B15: =IF(C15="","CEL-"&TEXT(COUNTA($C$5:C15),"000")) | G15: =IF(F15="","",F15-TODAY())
B16: =IF(C16="","CEL-"&TEXT(COUNTA($C$5:C16),"000")) | G16: =IF(F16="","",F16-TODAY())
B17: =IF(C17="","CEL-"&TEXT(COUNTA($C$5:C17),"000")) | G17: =IF(F17="","",F17-TODAY())
B18: =IF(C18="","CEL-"&TEXT(COUNTA($C$5:C18),"000")) | G18: =IF(F18="","",F18-TODAY())
B19: =IF(C19="","CEL-"&TEXT(COUNTA($C$5:C19),"000")) | G19: =IF(F19="","",F19-TODAY())
B20: =IF(C20="","CEL-"&TEXT(COUNTA($C$5:C20),"000")) | G20: =IF(F20="","",F20-TODAY())
B21: =IF(C21="","CEL-"&TEXT(COUNTA($C$5:C21),"000")) | G21: =IF(F21="","",F21-TODAY())
... B109: =IF(C109="","CEL-"&TEXT(COUNTA($C$5:C109),"000")) | G109: =IF(F109="","",F109-TODAY())
B111: TOTAL | I111: =SUM(I5:I104)
B113: INDICATEURS (mis a jour automatiquement)
B114: Echeances suivies | D114: En retard | F114: A echeance < 30j | H114: Total estime (FCFA)
B115: =COUNTIF(B5:B104,"<>") | D115: =COUNTIF(G5:G104,"<"&0) | F115: =COUNTIF(G5:G104,"<"&30)-COUNTIF(G5:G104,"<"&0) | H115: =SUM(I5:I104)

Sheet 4-Suivi Contentieux
B2: SUIVI DES CONTENTIEUX & PRUDHOMMES (#131)
B3: TABLEAU DYNAMIQUE — Saisissez dans la prochaine ligne jaune. Les calculs se mettent a jour automatiquement.
B4: N° | C4: Partie Adverse | D4: Motif Litige | E4: Type Contentieux | F4: Date Ouverture | G4: Avocat / Conseiller | H4: Provision (FCFA) | I4: Demande (FCFA) | J4: Derniere Audience | K4: Prochaine Audience | L4: Statut
B5: SCN-001 | C5: M. Tchouanku J. | D5: Licenciement abusef | E5: Prud'hommes | F5: 45550 | G5: Me. Nganou & Associes | H5: 500000 | I5: 2000000 | J5: 45797 | K5: 45884 | L5: En attente audience
B6: SCN-002 | C6: Mme. Fotso A. | D6: Harclement moral | E6: Tribunal de grande instance | F6: 45667 | G6: Me. Mbarga | H6: 300000 | I6: 5000000 | K6: 45858 | L6: En cours d'instruction
B7: SCN-003 | C7: Syndicat des travailleurs | D7: Non paiement heures sup. | E7: Inspection travail | F7: 45717 | G7: Me. Nganou & Associes | H7: 200000 | I7: 1500000 | J7: 45818 | K7: 45910 | L7: En negociation
B8: SCN-004 | C8: M. Essomba P. | D8: Accident travail non declare | E8: CNPS | F8: 45767 | G8: Conseil interne DRH | H8: 100000 | I8: 800000 | J8: 45813 | L8: En mediation
B9: =IF(C9="","SCN-"&TEXT(COUNTA($C$5:C9),"000"))
B10: =IF(C10="","SCN-"&TEXT(COUNTA($C$5:C10),"000"))
B11: =IF(C11="","SCN-"&TEXT(COUNTA($C$5:C11),"000"))
B12: =IF(C12="","SCN-"&TEXT(COUNTA($C$5:C12),"000"))
B13: =IF(C13="","SCN-"&TEXT(COUNTA($C$5:C13),"000"))
B14: =IF(C14="","SCN-"&TEXT(COUNTA($C$5:C14),"000"))
B15: =IF(C15="","SCN-"&TEXT(COUNTA($C$5:C15),"000"))
B16: =IF(C16="","SCN-"&TEXT(COUNTA($C$5:C16),"000"))
B17: =IF(C17="","SCN-"&TEXT(COUNTA($C$5:C17),"000"))
B18: =IF(C18="","SCN-"&TEXT(COUNTA($C$5:C18),"000"))
B19: =IF(C19="","SCN-"&TEXT(COUNTA($C$5:C19),"000"))
B20: =IF(C20="","SCN-"&TEXT(COUNTA($C$5:C20),"000"))
... B108: =IF(C108="","SCN-"&TEXT(COUNTA($C$5:C108),"000"))
B110: TOTAL | H110: =SUM(H5:H104) | I110: =SUM(I5:I104)
B112: INDICATEURS (mis a jour automatiquement)
B113: Dossiers suivis | D113: Total provisions | F113: Total demandes | H113: En cours
B114: =COUNTIF(B5:B104,"<>") | D114: =SUM(H5:H104) | F114: =SUM(I5:I104) | H114: =COUNTIF(L5:L104,"En cours d'instruction")+COUNTIF(L5:L104,"En negociation")+COUNTIF(L5:L104,"En mediation")+COUNTIF(L5:L104,"En attente audience")

Sheet 5-Audit Interne RH
B2: AUDIT INTERNE RH — GRILLE D'AUDIT (#132)
B3: TABLEAU DYNAMIQUE — Saisissez dans la prochaine ligne jaune. Les calculs se mettent a jour automatiquement.
B4: N° | C4: Domaine Audite | D4: Critere d'Audit | E4: Reference Normative | F4: Type Auditeur | G4: Date Audit | H4: Score (1-5) | I4: Constat | J4: Risque | K4: Recommandation | L4: Statut
B5: AIR-001 | C5: Recrutement | D5: Respect delai recrutement | E5: Procedure RH Art. 3 | F5: Interne DRH | G5: 45762 | H5: 4 | I5: Delai moyen 28j, conforme | J5: Faible | K5: Maintenir le processus actuel | L5: Terminee
B6: AIR-002 | C6: Paie | D6: Exactitude calcul salaire | E6: Grille salariale V2.1 | F6: Externe - Expert comptable | G6: 45778 | H6: 2 | I6: 3 erreurs de calcul detectees | J6: Eleve | K6: Revoir formules et controls | L6: En cours
B7: AIR-003 | C7: Formation | D7: Taux de realisation plan formation | E7: Plan formation 2025 | F7: Interne DRH | G7: 45809 | H7: 3 | I7: 42% de realisation a mi-année | J7: Moyen | K7: Accelerer les formations T3-T4 | L7: En cours
B8: AIR-004 | C8: Sécurité travail | D8: Port EPI cuisine | E8: Norme HSE hotellerie | F8: Externe - Inspecteur travail | G8: 45797 | H8: 2 | I8: Non port systematique EPI | J8: Critique | K8: Formation obligatoire + sanction | L8: En cours
B9: AIR-005 | C9: Documentation | D9: Completude dossiers employes | E9: Procedure documentation | F9: Interne DRH | G9: 45818 | H9: 4 | I9: 85% dossiers complets | J9: Moyen | K9: Rattraper les 15% manquants | L9: En cours
B10: =IF(C10="","AIR-"&TEXT(COUNTA($C$5:C10),"000"))
B11: =IF(C11="","AIR-"&TEXT(COUNTA($C$5:C11),"000"))
B12: =IF(C12="","AIR-"&TEXT(COUNTA($C$5:C12),"000"))
B13: =IF(C13="","AIR-"&TEXT(COUNTA($C$5:C13),"000"))
B14: =IF(C14="","AIR-"&TEXT(COUNTA($C$5:C14),"000"))
B15: =IF(C15="","AIR-"&TEXT(COUNTA($C$5:C15),"000"))
B16: =IF(C16="","AIR-"&TEXT(COUNTA($C$5:C16),"000"))
B17: =IF(C17="","AIR-"&TEXT(COUNTA($C$5:C17),"000"))
B18: =IF(C18="","AIR-"&TEXT(COUNTA($C$5:C18),"000"))
B19: =IF(C19="","AIR-"&TEXT(COUNTA($C$5:C19),"000"))
B20: =IF(C20="","AIR-"&TEXT(COUNTA($C$5:C20),"000"))
B21: =IF(C21="","AIR-"&TEXT(COUNTA($C$5:C21),"000"))
... B109: =IF(C109="","AIR-"&TEXT(COUNTA($C$5:C109),"000"))
B111: INDICATEURS (mis a jour automatiquement)
B112: Criteres evalues | D112: Score moyen | F112: Risques critiques | H112: Audits termines
B113: =COUNTIF(B5:B104,"<>") | D113: =IFERROR(AVERAGE(H5:H104),0) | F113: =COUNTIF(J5:J104,"Critique") | H113: =COUNTIF(L5:L104,"Terminee")

Sheet 6-Plans Action Post-Audit
B2: SUIVI DES PLANS D'ACTION POST-AUDIT (#133)
B3: TABLEAU DYNAMIQUE — Saisissez dans la prochaine ligne jaune. Les calculs se mettent a jour automatiquement.
B4: N° | C4: Recommandation Audit | D4: Audit Source | E4: Action Corrective | F4: Responsable | G4: Priorite | H4: Date Debut | I4: Echeance | J4: Jours Restants | K4: Cout Estime (FCFA) | L4: Statut
B5: PAA-001 | C5: Revoir formules paie | D5: AIR-002 | E5: Corriger formules et mettre en place double controle | F5: DAF | G5: Haute | H5: 45782 | I5: 45869 | K5: 150000 | L5: En cours
B6: PAA-002 | C6: Formation EPI cuisine | D6: AIR-004 | E6: Session formation HSE obligatoire | F6: Chef Entretien | G6: Critique | H6: 45809 | I6: 45853 | K6: 75000 | L6: En cours
B7: PAA-003 | C7: Rattraper dossiers incomplets | D7: AIR-005 | E7: Relancer 15% employes pour pieces manquantes | F7: Assistante RH | G7: Moyenne | H7: 45823 | I7: 45930 | K7: 25000 | L7: En cours
B8: PAA-004 | C8: Accelerer formation 2025 | D8: AIR-003 | E8: Planifier sessions intensives T3-T4 | F8: DRH | G8: Moyenne | H8: 45839 | I8: 46006 | K8: 500000 | L8: Planifiee
B9: =IF(C9="","PAA-"&TEXT(COUNTA($C$5:C9),"000")) | J9: =IF(I9="","",I9-TODAY())
B10: =IF(C10="","PAA-"&TEXT(COUNTA($C$5:C10),"000")) | J10: =IF(I10="","",I10-TODAY())
B11: =IF(C11="","PAA-"&TEXT(COUNTA($C$5:C11),"000")) | J11: =IF(I11="","",I11-TODAY())
B12: =IF(C12="","PAA-"&TEXT(COUNTA($C$5:C12),"000")) | J12: =IF(I12="","",I12-TODAY())
B13: =IF(C13="","PAA-"&TEXT(COUNTA($C$5:C13),"000")) | J13: =IF(I13="","",I13-TODAY())
B14: =IF(C14="","PAA-"&TEXT(COUNTA($C$5:C14),"000")) | J14: =IF(I14="","",I14-TODAY())
B15: =IF(C15="","PAA-"&TEXT(COUNTA($C$5:C15),"000")) | J15: =IF(I15="","",I15-TODAY())
B16: =IF(C16="","PAA-"&TEXT(COUNTA($C$5:C16),"000")) | J16: =IF(I16="","",I16-TODAY())
B17: =IF(C17="","PAA-"&TEXT(COUNTA($C$5:C17),"000")) | J17: =IF(I17="","",I17-TODAY())
B18: =IF(C18="","PAA-"&TEXT(COUNTA($C$5:C18),"000")) | J18: =IF(I18="","",I18-TODAY())
B19: =IF(C19="","PAA-"&TEXT(COUNTA($C$5:C19),"000")) | J19: =IF(I19="","",I19-TODAY())
B20: =IF(C20="","PAA-"&TEXT(COUNTA($C$5:C20),"000")) | J20: =IF(I20="","",I20-TODAY())
... B108: =IF(C108="","PAA-"&TEXT(COUNTA($C$5:C108),"000")) | J108: =IF(I108="","",I108-TODAY())
B110: TOTAL | K110: =SUM(K5:K104)
B112: INDICATEURS (mis a jour automatiquement)
B113: Actions suivies | D113: En cours | F113: En retard | H113: Budget total
B114: =COUNTIF(B5:B104,"<>") | D114: =COUNTIF(L5:L104,"En cours") | F114: =COUNTIF(J5:J104,"<"&0) | H114: =SUM(K5:K104)

Sheet 7-Gestion Assurances RH
B2: GESTION DES ASSURANCES RH (#134)
B3: TABLEAU DYNAMIQUE — Saisissez dans la prochaine ligne jaune. Les calculs se mettent a jour automatiquement.
B4: N° | C4: Type Assurance | D4: Compagnie Assureur | E4: N° Police | F4: Date Debut Couverture | G4: Date Fin Couverture | H4: Prime Annuelle (FCFA) | I4: Effectif Couvert | J4: Cout par Employe | K4: Dernier Pmt | L4: Statut
B5: GAR-001 | C5: AT - Accidents du travail | D5: ACTIVA Assurances | E5: POL-AT-2024-001 | F5: 45474 | G5: 45838 | H5: 1200000 | I5: 89 | K5: 45672 | L5: En cours
B6: GAR-002 | C6: Responsabilite civile employeur | D6: AXA Cameroon | E6: POL-RCE-2025-001 | F6: 45658 | G6: 46022 | H6: 850000 | I6: 89 | K6: 45677 | L6: En cours
B7: GAR-003 | C7: Protection juridique | D7: SAAR Assurances | E7: POL-PJ-2025-001 | F7: 45658 | G7: 46022 | H7: 350000 | I7: 89 | K7: 45689 | L7: En cours
B8: GAR-004 | C8: Medecine du travail | D8: CNPS | E8: MED-TRAV-2025 | F8: 45658 | G8: 46022 | H8: 250000 | I8: 89 | K8: 45717 | L8: En cours
B9: GAR-005 | C9: Prevoyance deces/invalidite | D9: CNPS | E9: PREV-2025 | F9: 45658 | G9: 46022 | H9: 0 | I9: 89 | L9: En cours
B10: =IF(C10="","GAR-"&TEXT(COUNTA($C$5:C10),"000")) | J10: =IF(OR(H10="",I10=""),"",H10/I10)
B11: =IF(C11="","GAR-"&TEXT(COUNTA($C$5:C11),"000")) | J11: =IF(OR(H11="",I11=""),"",H11/I11)
B12: =IF(C12="","GAR-"&TEXT(COUNTA($C$5:C12),"000")) | J12: =IF(OR(H12="",I12=""),"",H12/I12)
B13: =IF(C13="","GAR-"&TEXT(COUNTA($C$5:C13),"000")) | J13: =IF(OR(H13="",I13=""),"",H13/I13)
B14: =IF(C14="","GAR-"&TEXT(COUNTA($C$5:C14),"000")) | J14: =IF(OR(H14="",I14=""),"",H14/I14)
B15: =IF(C15="","GAR-"&TEXT(COUNTA($C$5:C15),"000")) | J15: =IF(OR(H15="",I15=""),"",H15/I15)
B16: =IF(C16="","GAR-"&TEXT(COUNTA($C$5:C16),"000")) | J16: =IF(OR(H16="",I16=""),"",H16/I16)
B17: =IF(C17="","GAR-"&TEXT(COUNTA($C$5:C17),"000")) | J17: =IF(OR(H17="",I17=""),"",H17/I17)
B18: =IF(C18="","GAR-"&TEXT(COUNTA($C$5:C18),"000")) | J18: =IF(OR(H18="",I18=""),"",H18/I18)
B19: =IF(C19="","GAR-"&TEXT(COUNTA($C$5:C19),"000")) | J19: =IF(OR(H19="",I19=""),"",H19/I19)
B20: =IF(C20="","GAR-"&TEXT(COUNTA($C$5:C20),"000")) | J20: =IF(OR(H20="",I20=""),"",H20/I20)
B21: =IF(C21="","GAR-"&TEXT(COUNTA($C$5:C21),"000")) | J21: =IF(OR(H21="",I21=""),"",H21/I21)
... B109: =IF(C109="","GAR-"&TEXT(COUNTA($C$5:C109),"000")) | J109: =IF(OR(H109="",I109=""),"",H109/I109)
B111: TOTAL | H111: =SUM(H5:H104)
B113: INDICATEURS (mis a jour automatiquement)
B114: Assurances suivies | D114: Prime totale | F114: A renouveler < 90j
B115: =COUNTIF(B5:B104,"<>") | D115: =SUM(H5:H104) | F115: =COUNTIF(G5:G104,"<"&TODAY()+90)-COUNTIF(G5:G104,"<"&TODAY())

Sheet 8-Registre Mises en Demeure
B2: REGISTRE DES MISES EN DEMEURE & INJONCTIONS (#135)
B3: TABLEAU DYNAMIQUE — Saisissez dans la prochaine ligne jaune. Les calculs se mettent a jour automatiquement.
B4: N° | C4: Type Injonction | D4: Emetteur | E4: Objet | F4: Date Reception | G4: Delai Reponse (jours) | H4: Date Limite Reponse | I4: Responsable Traitement | J4: Reponse Envoyee | K4: Suite Donnee | L4: Statut
B5: MED-001 | C5: Mise en demeure | D5: Inspection du travail | E5: Non declaration accident travail M. Essomba | F5: 45772 | G5: 15 | I5: DRH | J5: Oui | K5: Declaration retroactive effectuee | L5: Traitee
B6: MED-002 | C6: Avertissement | D6: CNPS | E6: Retard paiement cotisations Mars 2025 | F6: 45787 | G6: 10 | I6: DAF | J6: Oui | K6: Paiement regularise + penalites | L6: Traitee
B7: MED-003 | C7: Somation | D7: Syndicat des travailleurs | E7: Non respect heures supplementaires cuisine | F7: 45805 | G7: 20 | I7: DRH + DG | J7: Oui | K7: Reunion negociation planifiee | L7: En negociation
B8: MED-004 | C8: Mise en demeure | D8: Medecin inspecteur | E8: Absence visite medicale pour 3 agents | F8: 45813 | G8: 15 | I8: DRH | J8: Non | L8: En retard
B9: =IF(C9="","MED-"&TEXT(COUNTA($C$5:C9),"000")) | H9: =IF(F9="","",F9+G9)
B10: =IF(C10="","MED-"&TEXT(COUNTA($C$5:C10),"000")) | H10: =IF(F10="","",F10+G10)
B11: =IF(C11="","MED-"&TEXT(COUNTA($C$5:C11),"000")) | H11: =IF(F11="","",F11+G11)
B12: =IF(C12="","MED-"&TEXT(COUNTA($C$5:C12),"000")) | H12: =IF(F12="","",F12+G12)
B13: =IF(C13="","MED-"&TEXT(COUNTA($C$5:C13),"000")) | H13: =IF(F13="","",F13+G13)
B14: =IF(C14="","MED-"&TEXT(COUNTA($C$5:C14),"000")) | H14: =IF(F14="","",F14+G14)
B15: =IF(C15="","MED-"&TEXT(COUNTA($C$5:C15),"000")) | H15: =IF(F15="","",F15+G15)
B16: =IF(C16="","MED-"&TEXT(COUNTA($C$5:C16),"000")) | H16: =IF(F16="","",F16+G16)
B17: =IF(C17="","MED-"&TEXT(COUNTA($C$5:C17),"000")) | H17: =IF(F17="","",F17+G17)
B18: =IF(C18="","MED-"&TEXT(COUNTA($C$5:C18),"000")) | H18: =IF(F18="","",F18+G18)
B19: =IF(C19="","MED-"&TEXT(COUNTA($C$5:C19),"000")) | H19: =IF(F19="","",F19+G19)
B20: =IF(C20="","MED-"&TEXT(COUNTA($C$5:C20),"000")) | H20: =IF(F20="","",F20+G20)
... B108: =IF(C108="","MED-"&TEXT(COUNTA($C$5:C108),"000")) | H108: =IF(F108="","",F108+G108)
B110: INDICATEURS (mis a jour automatiquement)
B111: Injonctions recues | D111: Traitees | F111: En retard | H111: Taux traitement
B112: =COUNTIF(B5:B104,"<>") | D112: =COUNTIF(L5:L104,"Traitee") | F112: =COUNTIF(L5:L104,"En retard") | H112: =IFERROR(COUNTIF(L5:L104,"Traitee")/COUNTIF(B5:B104,"<>"),0)
