Workbook

Sheet 1-Tableau de Bord
B2: DOMAINE 3 — TEMPS DE TRAVAIL & PLANIFICATION
B3: TABLEAU DE BORD — Vue synthetique de tous les indicateurs du domaine (mis a jour automatiquement)
B5: Employes planifies | E5: Heures prevues | H5: Heures effectives | K5: Ecart total (h)
B6: =COUNTIF('2-Planning Mensuel'!B5:B104,"<>") | E6: =SUM('2-Planning Mensuel'!AQ5:AQ104) | H6: =SUM('2-Planning Mensuel'!AR5:AR104) | K6: =SUM('2-Planning Mensuel'!AS5:AS104)
B9: Pointages saisis | E9: Retards detectes | H9: Anomalies pointage | K9: Pointages valides
B10: =COUNTIF('5-Pointage Journalier'!B5:B104,"<>") | E10: =COUNTIF('5-Pointage Journalier'!M5:M104,">0") | H10: =COUNTIF('5-Pointage Journalier'!N5:N104,"Anomalie detectee") | K10: =COUNTIF('5-Pointage Journalier'!N5:N104,"Valide")
B13: Total heures supp | E13: Heures bonifiees | H13: Cout HS total (FCFA) | K13: HS en attente
B14: =SUM('7-Heures Supplementaires'!I5:I104) | E14: =SUM('7-Heures Supplementaires'!L5:L104) | H14: =SUM('7-Heures Supplementaires'!M5:M104) | K14: =COUNTIF('7-Heures Supplementaires'!N5:N104,"En attente")
B17: Total heures nuit | E17: Heures WE/feries | H17: Cout WE/Feries (FCFA) | K17: Gardes effectuees
B18: =SUM('8-Heures Nuit'!K5:K104) | E18: =SUM('9-Heures WE & Feries'!I5:I104) | H18: =SUM('9-Heures WE & Feries'!L5:L104) | K18: =COUNTIF('4-Garde & Astreintes'!L5:L104,"Effectuee")
B21: Total ecarts | E21: Ecarts non traites | H21: Rapports d'audit | K21: Taux realisation moy.
B22: =COUNTIF('16-Ecarts Pointage'!B5:B104,"<>") | E22: =COUNTIF('16-Ecarts Pointage'!M5:M104,"En attente") | H22: =COUNTIF('18-Rapports & Audit Temps'!B5:B104,"<>") | K22: =IFERROR(AVERAGE('10-Compteurs Temps'!N5:N104),0)
B26: REPARTITION PAR DEPARTEMENT & TYPE D'HEURE
B27: Departement | C27: Heures Effectives | D27: Heures Supp
B28: Ressources Humaines | C28: =SUMIF('2-Planning Mensuel'!E5:E104,B28,'2-Planning Mensuel'!AR5:AR104) | D28: =SUMIF('7-Heures Supplementaires'!E5:E104,B28,'7-Heures Supplementaires'!I5:I104)
B29: Informatique | C29: =SUMIF('2-Planning Mensuel'!E5:E104,B29,'2-Planning Mensuel'!AR5:AR104) | D29: =SUMIF('7-Heures Supplementaires'!E5:E104,B29,'7-Heures Supplementaires'!I5:I104)
B30: Finance & Comptabilite | C30: =SUMIF('2-Planning Mensuel'!E5:E104,B30,'2-Planning Mensuel'!AR5:AR104) | D30: =SUMIF('7-Heures Supplementaires'!E5:E104,B30,'7-Heures Supplementaires'!I5:I104)
B31: Reception & Front Office | C31: =SUMIF('2-Planning Mensuel'!E5:E104,B31,'2-Planning Mensuel'!AR5:AR104) | D31: =SUMIF('7-Heures Supplementaires'!E5:E104,B31,'7-Heures Supplementaires'!I5:I104)
B32: Cuisine & Restauration | C32: =SUMIF('2-Planning Mensuel'!E5:E104,B32,'2-Planning Mensuel'!AR5:AR104) | D32: =SUMIF('7-Heures Supplementaires'!E5:E104,B32,'7-Heures Supplementaires'!I5:I104)
H42: Type Heure | I42: Total Heures
H43: Normales | I43: =SUM('6-Releve Heures'!G5:G104)
H44: Supplementaires | I44: =SUM('6-Releve Heures'!H5:H104)
H45: Nuit | I45: =SUM('6-Releve Heures'!I5:I104)
H46: Week-End/Feries | I46: =SUM('6-Releve Heures'!J5:J104)

Sheet _Données Employés
B4: Matricule | C4: Civilité | D4: Nom | E4: Prénom | F4: Département | G4: Poste | H4: Salaire Base (FCFA)
B5: EMP-001 | C5: M. | D5: Nganou | E5: Clarisse | F5: Cuisine & Restauration | G5: Chef cuisinier | H5: 450000
B6: EMP-002 | C6: M. | D6: Tchinda | E6: Armand | F6: Réception & Front Office | G6: Réceptionniste | H6: 220000
B7: EMP-003 | C7: Mme | D7: Fotso | E7: Marguerite | F7: Finance & Comptabilité | G7: Comptable senior | H7: 380000
B8: EMP-004 | C8: M. | D8: Nkoulou | E8: Mbarga | F8: Étage & Housekeeping | G8: Gouvernant | H8: 195000
B9: EMP-005 | C9: M. | D9: Kamga | E9: Paul | F9: Maintenance | G9: Technicien maintenance | H9: 165000
B10: EMP-006 | C10: Mme | D10: Ngo | E10: Delphine | F10: Service Client | G10: Conseiller clientèle | H10: 160000
B11: EMP-007 | C11: M. | D11: Essomba | E11: Serge | F11: Maintenance | G11: Agent entretien | H11: 130000
B12: EMP-008 | C12: M. | D12: Tchouankou | E12: Paul | F12: Commercial | G12: Commercial | H12: 150000
B13: EMP-009 | C13: M. | D13: Fokam | E13: Eric | F13: Maintenance | G13: Technicien | H13: 140000
B14: EMP-010 | C14: M. | D14: Tagne | E14: René | F14: Cuisine & Restauration | G14: Plongeur | H14: 90000
B15: EMP-011 | C15: M. | D15: Bouba | E15: Ahmed | F15: Sécurité | G15: Agent Sécurité | H15: 120000
B16: EMP-012 | C16: Mme | D16: Awa | E16: Fatou | F16: Réception & Front Office | G16: Standardiste | H16: 155000
... B18: EMP-029 | C18: M. | D18: Kamga | E18: Patrice | F18: Sécurité | G18: Chef Sécurité | H18: 210000

Sheet _Lists
B1: departement | C1: poste_hotel | D1: equipe | E1: type_planning | F1: jour_semaine | G1: type_garde | H1: statut_garde | I1: type_pointage | J1: statut_pointage | K1: motif_absence | L1: type_heure_supp | M1: taux_majoration | N1: periode_nuit | O1: type_conge_collectif | P1: statut_conge_collectif | Q1: service_affectation | R1: regime_horaire | S1: statut_regime | T1: type_ecart | U1: statut_ecart | V1: type_rapport | W1: statut_rapport | X1: mois | Y1: annee | Z1: periode_hebdo
B2: Direction Generale | C2: DG | D2: Equipe A | E2: Mensuel | F2: Lundi | G2: Garde de nuit | H2: Planifiee | I2: Badgeuse | J2: Valide | K2: Absent injustifie | L2: Heure supplementaire jour | M2: 15% | N2: 22h-06h | O2: Conges de Noel | P2: Planifie | Q2: Reception | R2: Temps plein 40h | S2: Actif | T2: Retard arrivee | U2: En attente | V2: Bilan mensuel | W2: Brouillon | X2: Janvier | Y2: 2024 | Z2: Semaine 1
B3: Ressources Humaines | C3: DRH | D3: Equipe B | E3: Hebdomadaire | F3: Mardi | G3: Astreinte telephone | H3: Effectuee | I3: Fiche manuelle | J3: En attente | K3: Retard injustifie | L3: Heure nuit supplementaire | M3: 25% | N3: 21h-05h | O3: Conges de Paques | P3: En cours | Q3: Restaurant | R3: Temps plein 45h | S3: En modification | T3: Depart anticipe | U3: Justifie | V3: Audit conges | W3: Valide | X3: Fevrier | Y3: 2025 | Z3: Semaine 2
B4: Finance & Comptabilite | C4: Assistante RH | D4: Equipe C | E4: Quinzaine | F4: Mercredi | G4: Astreinte deplacee | H4: Annulee | I4: Pointeur | J4: Anomalie detectee | K4: Depart anticipe | L4: Heure week-end | M4: 50% | N4: 20h-06h | O4: Fermeture annuelle | P4: Termine | Q4: Bar | R4: Temps partiel 20h | S4: Suspendu | T4: Absence non justifiee | U4: Non justifie | V4: Audit heures supp | W4: Approuve | X4: Mars | Y4: 2026 | Z4: Semaine 3
B5: Marketing & Communication | C5: DAF | D5: Equipe Jour | F5: Jeudi | G5: Permanence week-end | H5: En attente | I5: Application mobile | J5: Modifie | K5: Badge defaillant | L5: Heure feries | M5: 75% | O5: Pont | P5: Annule | Q5: Room Service | R5: Temps partiel 25h | T5: Double badgeage | U5: Traite | V5: Conformite horaires | W5: Rejete | X5: Avril | Z5: Semaine 4
B6: Informatique | C6: Comptable senior | D6: Equipe Nuit | F6: Vendredi | J6: Rejete | K6: Oubli badgeage | L6: Recoverable | M6: 100% | O6: Jour ferie | Q6: Conciergerie | R6: Temps partiel 30h | T6: Badge manquant | U6: Ignore | V6: Rapport anomalie | X6: Mai | Z6: Semaine 5
B7: Commercial | C7: Comptable junior | F7: Samedi | K7: Formation externe | O7: Fermeture exceptionnelle | Q7: Brasserie | R7: Forfait jour 173h/mois | T7: Heure supp non validee | V7: Bilan trimestriel | X7: Juin
B8: Logistique & Approvisionnement | C8: Chef Comptable | F8: Dimanche | K8: Mission | Q8: Piscine/Spa | R8: Forfait jour 218j/an | T8: Erreur pointeur | X8: Juillet
B9: Production | C9: Chef Marketing | Q9: Evenementiel | R9: Horaires rotatifs 3x8 | X9: Aout
B10: Service Client | C10: Chef de service IT | Q10: Nuit | R10: Horaires rotatifs 2x12 | X10: Septembre
B11: Reception & Front Office | C11: Technicien IT | Q11: Menage | R11: Equipe de nuit permanente | X11: Octobre
B12: Cuisine & Restauration | C12: Chef Commercial | Q12: Valet parking | X12: Novembre
B13: Entretien & Maintenance | C13: Agent Commercial | X13: Decembre
B14: Securite | C14: Chef Logistique
C15: Magasinier
C16: Chef Production
C17: Operateur de production
C18: Chef Service Client
C19: Conseiller Client
C20: Chef Reception
C21: Receptionniste
C22: Concierge
C23: Chef Cuisine
C24: Sous-Chef
C25: Cuisinier
C26: Plongeur
... C30: Agent Securite

Sheet 2-Planning Mensuel
B2: PLANNING MENSUEL — PROGRAMMATION TRAVAIL
B3: TABLEAU DYNAMIQUE — Saisissez dans la prochaine ligne jaune. Les calculs se mettent a jour automatiquement.
B4: N° Planning | C4: Matricule | D4: Nom Employe | E4: Departement | F4: Poste | G4: Mois | H4: Annee | I4: Jour 1 | J4: Jour 2 | K4: Jour 3 | L4: Jour 4 | M4: Jour 5 | N4: Jour 6 | O4: Jour 7 | P4: Jour 8 | Q4: Jour 9 | R4: Jour 10 | S4: Jour 11 | T4: Jour 12 | U4: Jour 13 | V4: Jour 14 | W4: Jour 15 | X4: Jour 16 | Y4: Jour 17 | Z4: Jour 18 | AA4: Jour 19 | AB4: Jour 20 | AC4: Jour 21 | AD4: Jour 22 | AE4: Jour 23 | AF4: Jour 24 | AG4: Jour 25 | AH4: Jour 26 | AI4: Jour 27 | AJ4: Jour 28 | AK4: Jour 29 | AL4: Jour 30 | AM4: Jour 31 | AN4: Total Jours Travaillés | AO4: Total Repos | AP4: Total Absences | AQ4: Heures Prevues | AR4: Heures Effectives | AS4: Ecart Heures | AT4: Statut
B5: PLM-001 | C5: EMP-001 | D5: =IF(C5="","",IFERROR(VLOOKUP(C5,'_Données Employés'!$B$5:$H$18,3,FALSE)&" "&VLOOKUP(C5,'_Données Employés'!$B$5:$H$18,4,FALSE),"")) | E5: =IF(C5="","",IFERROR(VLOOKUP(C5,'_Données Employés'!$B$5:$H$18,5,FALSE),"")) | F5: =IF(C5="","",IFERROR(VLOOKUP(C5,'_Données Employés'!$B$5:$H$18,6,FALSE),"")) | G5: Juin | H5: 2025 | I5: T | J5: T | K5: T | L5: T | M5: T | N5: R | O5: R | P5: T | Q5: T | R5: T | AN5: =IF(C5="","",COUNTIF(I5:AM5,"T")+COUNTIF(I5:AM5,"N")) | AO5: =IF(C5="","",COUNTIF(I5:AM5,"R")) | AP5: =IF(C5="","",COUNTIF(I5:AM5,"A")) | AQ5: =IF(C5="","",AN5*8) | AR5: =IF(C5="","",IFERROR(SUMIFS('6-Releve Heures'!K$5:K$104,'6-Releve Heures'!C$5:C$104,C5),0)) | AS5: =IF(C5="","",IFERROR(AR5-AQ5,0)) | AT5: Valide
B6: PLM-002 | C6: EMP-002 | D6: =IF(C6="","",IFERROR(VLOOKUP(C6,'_Données Employés'!$B$5:$H$18,3,FALSE)&" "&VLOOKUP(C6,'_Données Employés'!$B$5:$H$18,4,FALSE),"")) | E6: =IF(C6="","",IFERROR(VLOOKUP(C6,'_Données Employés'!$B$5:$H$18,5,FALSE),"")) | F6: =IF(C6="","",IFERROR(VLOOKUP(C6,'_Données Employés'!$B$5:$H$18,6,FALSE),"")) | G6: Juin | H6: 2025 | I6: T | J6: T | K6: T | L6: T | M6: T | N6: R | O6: R | P6: T | Q6: T | R6: T | AN6: =IF(C6="","",COUNTIF(I6:AM6,"T")+COUNTIF(I6:AM6,"N")) | AO6: =IF(C6="","",COUNTIF(I6:AM6,"R")) | AP6: =IF(C6="","",COUNTIF(I6:AM6,"A")) | AQ6: =IF(C6="","",AN6*8) | AR6: =IF(C6="","",IFERROR(SUMIFS('6-Releve Heures'!K$5:K$104,'6-Releve Heures'!C$5:C$104,C6),0)) | AS6: =IF(C6="","",IFERROR(AR6-AQ6,0)) | AT6: Valide
B7: PLM-003 | C7: EMP-003 | D7: =IF(C7="","",IFERROR(VLOOKUP(C7,'_Données Employés'!$B$5:$H$18,3,FALSE)&" "&VLOOKUP(C7,'_Données Employés'!$B$5:$H$18,4,FALSE),"")) | E7: =IF(C7="","",IFERROR(VLOOKUP(C7,'_Données Employés'!$B$5:$H$18,5,FALSE),"")) | F7: =IF(C7="","",IFERROR(VLOOKUP(C7,'_Données Employés'!$B$5:$H$18,6,FALSE),"")) | G7: Juin | H7: 2025 | I7: T | J7: T | K7: T | L7: A | M7: A | N7: R | O7: R | P7: T | Q7: T | R7: T | AN7: =IF(C7="","",COUNTIF(I7:AM7,"T")+COUNTIF(I7:AM7,"N")) | AO7: =IF(C7="","",COUNTIF(I7:AM7,"R")) | AP7: =IF(C7="","",COUNTIF(I7:AM7,"A")) | AQ7: =IF(C7="","",AN7*8) | AR7: =IF(C7="","",IFERROR(SUMIFS('6-Releve Heures'!K$5:K$104,'6-Releve Heures'!C$5:C$104,C7),0)) | AS7: =IF(C7="","",IFERROR(AR7-AQ7,0)) | AT7: Valide
B8: PLM-004 | C8: EMP-004 | D8: =IF(C8="","",IFERROR(VLOOKUP(C8,'_Données Employés'!$B$5:$H$18,3,FALSE)&" "&VLOOKUP(C8,'_Données Employés'!$B$5:$H$18,4,FALSE),"")) | E8: =IF(C8="","",IFERROR(VLOOKUP(C8,'_Données Employés'!$B$5:$H$18,5,FALSE),"")) | F8: =IF(C8="","",IFERROR(VLOOKUP(C8,'_Données Employés'!$B$5:$H$18,6,FALSE),"")) | G8: Juin | H8: 2025 | I8: N | J8: N | K8: N | L8: R | M8: R | N8: R | O8: R | P8: N | Q8: N | R8: N | AN8: =IF(C8="","",COUNTIF(I8:AM8,"T")+COUNTIF(I8:AM8,"N")) | AO8: =IF(C8="","",COUNTIF(I8:AM8,"R")) | AP8: =IF(C8="","",COUNTIF(I8:AM8,"A")) | AQ8: =IF(C8="","",AN8*8) | AR8: =IF(C8="","",IFERROR(SUMIFS('6-Releve Heures'!K$5:K$104,'6-Releve Heures'!C$5:C$104,C8),0)) | AS8: =IF(C8="","",IFERROR(AR8-AQ8,0)) | AT8: Valide
B9: PLM-005 | C9: EMP-005 | D9: =IF(C9="","",IFERROR(VLOOKUP(C9,'_Données Employés'!$B$5:$H$18,3,FALSE)&" "&VLOOKUP(C9,'_Données Employés'!$B$5:$H$18,4,FALSE),"")) | E9: =IF(C9="","",IFERROR(VLOOKUP(C9,'_Données Employés'!$B$5:$H$18,5,FALSE),"")) | F9: =IF(C9="","",IFERROR(VLOOKUP(C9,'_Données Employés'!$B$5:$H$18,6,FALSE),"")) | G9: Juin | H9: 2025 | I9: T | J9: T | K9: T | L9: T | M9: R | N9: R | O9: R | P9: T | Q9: T | R9: T | AN9: =IF(C9="","",COUNTIF(I9:AM9,"T")+COUNTIF(I9:AM9,"N")) | AO9: =IF(C9="","",COUNTIF(I9:AM9,"R")) | AP9: =IF(C9="","",COUNTIF(I9:AM9,"A")) | AQ9: =IF(C9="","",AN9*8) | AR9: =IF(C9="","",IFERROR(SUMIFS('6-Releve Heures'!K$5:K$104,'6-Releve Heures'!C$5:C$104,C9),0)) | AS9: =IF(C9="","",IFERROR(AR9-AQ9,0)) | AT9: Valide
B10: PLM-006 | C10: EMP-006 | D10: =IF(C10="","",IFERROR(VLOOKUP(C10,'_Données Employés'!$B$5:$H$18,3,FALSE)&" "&VLOOKUP(C10,'_Données Employés'!$B$5:$H$18,4,FALSE),"")) | E10: =IF(C10="","",IFERROR(VLOOKUP(C10,'_Données Employés'!$B$5:$H$18,5,FALSE),"")) | F10: =IF(C10="","",IFERROR(VLOOKUP(C10,'_Données Employés'!$B$5:$H$18,6,FALSE),"")) | G10: Juin | H10: 2025 | AN10: =IF(C10="","",COUNTIF(I10:AM10,"T")+COUNTIF(I10:AM10,"N")) | AO10: =IF(C10="","",COUNTIF(I10:AM10,"R")) | AP10: =IF(C10="","",COUNTIF(I10:AM10,"A")) | AQ10: =IF(C10="","",AN10*8) | AR10: =IF(C10="","",IFERROR(SUMIFS('6-Releve Heures'!K$5:K$104,'6-Releve Heures'!C$5:C$104,C10),0)) | AS10: =IF(C10="","",IFERROR(AR10-AQ10,0))
B11: PLM-007 | C11: EMP-007 | D11: =IF(C11="","",IFERROR(VLOOKUP(C11,'_Données Employés'!$B$5:$H$18,3,FALSE)&" "&VLOOKUP(C11,'_Données Employés'!$B$5:$H$18,4,FALSE),"")) | E11: =IF(C11="","",IFERROR(VLOOKUP(C11,'_Données Employés'!$B$5:$H$18,5,FALSE),"")) | F11: =IF(C11="","",IFERROR(VLOOKUP(C11,'_Données Employés'!$B$5:$H$18,6,FALSE),"")) | G11: Juin | H11: 2025 | AN11: =IF(C11="","",COUNTIF(I11:AM11,"T")+COUNTIF(I11:AM11,"N")) | AO11: =IF(C11="","",COUNTIF(I11:AM11,"R")) | AP11: =IF(C11="","",COUNTIF(I11:AM11,"A")) | AQ11: =IF(C11="","",AN11*8) | AR11: =IF(C11="","",IFERROR(SUMIFS('6-Releve Heures'!K$5:K$104,'6-Releve Heures'!C$5:C$104,C11),0)) | AS11: =IF(C11="","",IFERROR(AR11-AQ11,0))
B12: PLM-008 | C12: EMP-008 | D12: =IF(C12="","",IFERROR(VLOOKUP(C12,'_Données Employés'!$B$5:$H$18,3,FALSE)&" "&VLOOKUP(C12,'_Données Employés'!$B$5:$H$18,4,FALSE),"")) | E12: =IF(C12="","",IFERROR(VLOOKUP(C12,'_Données Employés'!$B$5:$H$18,5,FALSE),"")) | F12: =IF(C12="","",IFERROR(VLOOKUP(C12,'_Données Employés'!$B$5:$H$18,6,FALSE),"")) | G12: Juin | H12: 2025 | AN12: =IF(C12="","",COUNTIF(I12:AM12,"T")+COUNTIF(I12:AM12,"N")) | AO12: =IF(C12="","",COUNTIF(I12:AM12,"R")) | AP12: =IF(C12="","",COUNTIF(I12:AM12,"A")) | AQ12: =IF(C12="","",AN12*8) | AR12: =IF(C12="","",IFERROR(SUMIFS('6-Releve Heures'!K$5:K$104,'6-Releve Heures'!C$5:C$104,C12),0)) | AS12: =IF(C12="","",IFERROR(AR12-AQ12,0))
B13: PLM-009 | C13: EMP-009 | D13: =IF(C13="","",IFERROR(VLOOKUP(C13,'_Données Employés'!$B$5:$H$18,3,FALSE)&" "&VLOOKUP(C13,'_Données Employés'!$B$5:$H$18,4,FALSE),"")) | E13: =IF(C13="","",IFERROR(VLOOKUP(C13,'_Données Employés'!$B$5:$H$18,5,FALSE),"")) | F13: =IF(C13="","",IFERROR(VLOOKUP(C13,'_Données Employés'!$B$5:$H$18,6,FALSE),"")) | G13: Juin | H13: 2025 | AN13: =IF(C13="","",COUNTIF(I13:AM13,"T")+COUNTIF(I13:AM13,"N")) | AO13: =IF(C13="","",COUNTIF(I13:AM13,"R")) | AP13: =IF(C13="","",COUNTIF(I13:AM13,"A")) | AQ13: =IF(C13="","",AN13*8) | AR13: =IF(C13="","",IFERROR(SUMIFS('6-Releve Heures'!K$5:K$104,'6-Releve Heures'!C$5:C$104,C13),0)) | AS13: =IF(C13="","",IFERROR(AR13-AQ13,0))
B14: PLM-010 | C14: EMP-010 | D14: =IF(C14="","",IFERROR(VLOOKUP(C14,'_Données Employés'!$B$5:$H$18,3,FALSE)&" "&VLOOKUP(C14,'_Données Employés'!$B$5:$H$18,4,FALSE),"")) | E14: =IF(C14="","",IFERROR(VLOOKUP(C14,'_Données Employés'!$B$5:$H$18,5,FALSE),"")) | F14: =IF(C14="","",IFERROR(VLOOKUP(C14,'_Données Employés'!$B$5:$H$18,6,FALSE),"")) | G14: Juin | H14: 2025 | AN14: =IF(C14="","",COUNTIF(I14:AM14,"T")+COUNTIF(I14:AM14,"N")) | AO14: =IF(C14="","",COUNTIF(I14:AM14,"R")) | AP14: =IF(C14="","",COUNTIF(I14:AM14,"A")) | AQ14: =IF(C14="","",AN14*8) | AR14: =IF(C14="","",IFERROR(SUMIFS('6-Releve Heures'!K$5:K$104,'6-Releve Heures'!C$5:C$104,C14),0)) | AS14: =IF(C14="","",IFERROR(AR14-AQ14,0))
B15: PLM-011 | C15: EMP-011 | D15: =IF(C15="","",IFERROR(VLOOKUP(C15,'_Données Employés'!$B$5:$H$18,3,FALSE)&" "&VLOOKUP(C15,'_Données Employés'!$B$5:$H$18,4,FALSE),"")) | E15: =IF(C15="","",IFERROR(VLOOKUP(C15,'_Données Employés'!$B$5:$H$18,5,FALSE),"")) | F15: =IF(C15="","",IFERROR(VLOOKUP(C15,'_Données Employés'!$B$5:$H$18,6,FALSE),"")) | G15: Juin | H15: 2025 | AN15: =IF(C15="","",COUNTIF(I15:AM15,"T")+COUNTIF(I15:AM15,"N")) | AO15: =IF(C15="","",COUNTIF(I15:AM15,"R")) | AP15: =IF(C15="","",COUNTIF(I15:AM15,"A")) | AQ15: =IF(C15="","",AN15*8) | AR15: =IF(C15="","",IFERROR(SUMIFS('6-Releve Heures'!K$5:K$104,'6-Releve Heures'!C$5:C$104,C15),0)) | AS15: =IF(C15="","",IFERROR(AR15-AQ15,0))
B16: PLM-012 | C16: EMP-012 | D16: =IF(C16="","",IFERROR(VLOOKUP(C16,'_Données Employés'!$B$5:$H$18,3,FALSE)&" "&VLOOKUP(C16,'_Données Employés'!$B$5:$H$18,4,FALSE),"")) | E16: =IF(C16="","",IFERROR(VLOOKUP(C16,'_Données Employés'!$B$5:$H$18,5,FALSE),"")) | F16: =IF(C16="","",IFERROR(VLOOKUP(C16,'_Données Employés'!$B$5:$H$18,6,FALSE),"")) | G16: Juin | H16: 2025 | AN16: =IF(C16="","",COUNTIF(I16:AM16,"T")+COUNTIF(I16:AM16,"N")) | AO16: =IF(C16="","",COUNTIF(I16:AM16,"R")) | AP16: =IF(C16="","",COUNTIF(I16:AM16,"A")) | AQ16: =IF(C16="","",AN16*8) | AR16: =IF(C16="","",IFERROR(SUMIFS('6-Releve Heures'!K$5:K$104,'6-Releve Heures'!C$5:C$104,C16),0)) | AS16: =IF(C16="","",IFERROR(AR16-AQ16,0))
B17: PLM-028 | C17: EMP-028 | D17: =IF(C17="","",IFERROR(VLOOKUP(C17,'_Données Employés'!$B$5:$H$18,3,FALSE)&" "&VLOOKUP(C17,'_Données Employés'!$B$5:$H$18,4,FALSE),"")) | E17: =IF(C17="","",IFERROR(VLOOKUP(C17,'_Données Employés'!$B$5:$H$18,5,FALSE),"")) | F17: =IF(C17="","",IFERROR(VLOOKUP(C17,'_Données Employés'!$B$5:$H$18,6,FALSE),"")) | G17: Juin | H17: 2025 | AN17: =IF(C17="","",COUNTIF(I17:AM17,"T")+COUNTIF(I17:AM17,"N")) | AO17: =IF(C17="","",COUNTIF(I17:AM17,"R")) | AP17: =IF(C17="","",COUNTIF(I17:AM17,"A")) | AQ17: =IF(C17="","",AN17*8) | AR17: =IF(C17="","",IFERROR(SUMIFS('6-Releve Heures'!K$5:K$104,'6-Releve Heures'!C$5:C$104,C17),0)) | AS17: =IF(C17="","",IFERROR(AR17-AQ17,0))
B18: PLM-029 | C18: EMP-029 | D18: =IF(C18="","",IFERROR(VLOOKUP(C18,'_Données Employés'!$B$5:$H$18,3,FALSE)&" "&VLOOKUP(C18,'_Données Employés'!$B$5:$H$18,4,FALSE),"")) | E18: =IF(C18="","",IFERROR(VLOOKUP(C18,'_Données Employés'!$B$5:$H$18,5,FALSE),"")) | F18: =IF(C18="","",IFERROR(VLOOKUP(C18,'_Données Employés'!$B$5:$H$18,6,FALSE),"")) | G18: Juin | H18: 2025 | AN18: =IF(C18="","",COUNTIF(I18:AM18,"T")+COUNTIF(I18:AM18,"N")) | AO18: =IF(C18="","",COUNTIF(I18:AM18,"R")) | AP18: =IF(C18="","",COUNTIF(I18:AM18,"A")) | AQ18: =IF(C18="","",AN18*8) | AR18: =IF(C18="","",IFERROR(SUMIFS('6-Releve Heures'!K$5:K$104,'6-Releve Heures'!C$5:C$104,C18),0)) | AS18: =IF(C18="","",IFERROR(AR18-AQ18,0))
B19: =IF(C19="","PLM-"&TEXT(COUNTA($C$5:C19),"000")) | AN19: =IF(C19="","",COUNTIF(I19:AM19,"T")+COUNTIF(I19:AM19,"N")) | AO19: =IF(C19="","",COUNTIF(I19:AM19,"R")) | AP19: =IF(C19="","",COUNTIF(I19:AM19,"A")) | AQ19: =IF(C19="","",AN19*8) | AR19: =IF(C19="","",IFERROR(SUMIFS('6-Releve Heures'!K$5:K$104,'6-Releve Heures'!C$5:C$104,C19),0)) | AS19: =IF(C19="","",IFERROR(AR19-AQ19,0))
B20: =IF(C20="","PLM-"&TEXT(COUNTA($C$5:C20),"000")) | AN20: =IF(C20="","",COUNTIF(I20:AM20,"T")+COUNTIF(I20:AM20,"N")) | AO20: =IF(C20="","",COUNTIF(I20:AM20,"R")) | AP20: =IF(C20="","",COUNTIF(I20:AM20,"A")) | AQ20: =IF(C20="","",AN20*8) | AR20: =IF(C20="","",IFERROR(SUMIFS('6-Releve Heures'!K$5:K$104,'6-Releve Heures'!C$5:C$104,C20),0)) | AS20: =IF(C20="","",IFERROR(AR20-AQ20,0))
B21: =IF(C21="","PLM-"&TEXT(COUNTA($C$5:C21),"000")) | AN21: =IF(C21="","",COUNTIF(I21:AM21,"T")+COUNTIF(I21:AM21,"N")) | AO21: =IF(C21="","",COUNTIF(I21:AM21,"R")) | AP21: =IF(C21="","",COUNTIF(I21:AM21,"A")) | AQ21: =IF(C21="","",AN21*8) | AR21: =IF(C21="","",IFERROR(SUMIFS('6-Releve Heures'!K$5:K$104,'6-Releve Heures'!C$5:C$104,C21),0)) | AS21: =IF(C21="","",IFERROR(AR21-AQ21,0))
B22: =IF(C22="","PLM-"&TEXT(COUNTA($C$5:C22),"000")) | AN22: =IF(C22="","",COUNTIF(I22:AM22,"T")+COUNTIF(I22:AM22,"N")) | AO22: =IF(C22="","",COUNTIF(I22:AM22,"R")) | AP22: =IF(C22="","",COUNTIF(I22:AM22,"A")) | AQ22: =IF(C22="","",AN22*8) | AR22: =IF(C22="","",IFERROR(SUMIFS('6-Releve Heures'!K$5:K$104,'6-Releve Heures'!C$5:C$104,C22),0)) | AS22: =IF(C22="","",IFERROR(AR22-AQ22,0))
B23: =IF(C23="","PLM-"&TEXT(COUNTA($C$5:C23),"000")) | AN23: =IF(C23="","",COUNTIF(I23:AM23,"T")+COUNTIF(I23:AM23,"N")) | AO23: =IF(C23="","",COUNTIF(I23:AM23,"R")) | AP23: =IF(C23="","",COUNTIF(I23:AM23,"A")) | AQ23: =IF(C23="","",AN23*8) | AR23: =IF(C23="","",IFERROR(SUMIFS('6-Releve Heures'!K$5:K$104,'6-Releve Heures'!C$5:C$104,C23),0)) | AS23: =IF(C23="","",IFERROR(AR23-AQ23,0))
B24: =IF(C24="","PLM-"&TEXT(COUNTA($C$5:C24),"000")) | AN24: =IF(C24="","",COUNTIF(I24:AM24,"T")+COUNTIF(I24:AM24,"N")) | AO24: =IF(C24="","",COUNTIF(I24:AM24,"R")) | AP24: =IF(C24="","",COUNTIF(I24:AM24,"A")) | AQ24: =IF(C24="","",AN24*8) | AR24: =IF(C24="","",IFERROR(SUMIFS('6-Releve Heures'!K$5:K$104,'6-Releve Heures'!C$5:C$104,C24),0)) | AS24: =IF(C24="","",IFERROR(AR24-AQ24,0))
B25: =IF(C25="","PLM-"&TEXT(COUNTA($C$5:C25),"000")) | AN25: =IF(C25="","",COUNTIF(I25:AM25,"T")+COUNTIF(I25:AM25,"N")) | AO25: =IF(C25="","",COUNTIF(I25:AM25,"R")) | AP25: =IF(C25="","",COUNTIF(I25:AM25,"A")) | AQ25: =IF(C25="","",AN25*8) | AR25: =IF(C25="","",IFERROR(SUMIFS('6-Releve Heures'!K$5:K$104,'6-Releve Heures'!C$5:C$104,C25),0)) | AS25: =IF(C25="","",IFERROR(AR25-AQ25,0))
B26: =IF(C26="","PLM-"&TEXT(COUNTA($C$5:C26),"000")) | AN26: =IF(C26="","",COUNTIF(I26:AM26,"T")+COUNTIF(I26:AM26,"N")) | AO26: =IF(C26="","",COUNTIF(I26:AM26,"R")) | AP26: =IF(C26="","",COUNTIF(I26:AM26,"A")) | AQ26: =IF(C26="","",AN26*8) | AR26: =IF(C26="","",IFERROR(SUMIFS('6-Releve Heures'!K$5:K$104,'6-Releve Heures'!C$5:C$104,C26),0)) | AS26: =IF(C26="","",IFERROR(AR26-AQ26,0))
B27: =IF(C27="","PLM-"&TEXT(COUNTA($C$5:C27),"000")) | AN27: =IF(C27="","",COUNTIF(I27:AM27,"T")+COUNTIF(I27:AM27,"N")) | AO27: =IF(C27="","",COUNTIF(I27:AM27,"R")) | AP27: =IF(C27="","",COUNTIF(I27:AM27,"A")) | AQ27: =IF(C27="","",AN27*8) | AR27: =IF(C27="","",IFERROR(SUMIFS('6-Releve Heures'!K$5:K$104,'6-Releve Heures'!C$5:C$104,C27),0)) | AS27: =IF(C27="","",IFERROR(AR27-AQ27,0))
B28: =IF(C28="","PLM-"&TEXT(COUNTA($C$5:C28),"000")) | AN28: =IF(C28="","",COUNTIF(I28:AM28,"T")+COUNTIF(I28:AM28,"N")) | AO28: =IF(C28="","",COUNTIF(I28:AM28,"R")) | AP28: =IF(C28="","",COUNTIF(I28:AM28,"A")) | AQ28: =IF(C28="","",AN28*8) | AR28: =IF(C28="","",IFERROR(SUMIFS('6-Releve Heures'!K$5:K$104,'6-Releve Heures'!C$5:C$104,C28),0)) | AS28: =IF(C28="","",IFERROR(AR28-AQ28,0))
B29: =IF(C29="","PLM-"&TEXT(COUNTA($C$5:C29),"000")) | AN29: =IF(C29="","",COUNTIF(I29:AM29,"T")+COUNTIF(I29:AM29,"N")) | AO29: =IF(C29="","",COUNTIF(I29:AM29,"R")) | AP29: =IF(C29="","",COUNTIF(I29:AM29,"A")) | AQ29: =IF(C29="","",AN29*8) | AR29: =IF(C29="","",IFERROR(SUMIFS('6-Releve Heures'!K$5:K$104,'6-Releve Heures'!C$5:C$104,C29),0)) | AS29: =IF(C29="","",IFERROR(AR29-AQ29,0))
B30: =IF(C30="","PLM-"&TEXT(COUNTA($C$5:C30),"000")) | AN30: =IF(C30="","",COUNTIF(I30:AM30,"T")+COUNTIF(I30:AM30,"N")) | AO30: =IF(C30="","",COUNTIF(I30:AM30,"R")) | AP30: =IF(C30="","",COUNTIF(I30:AM30,"A")) | AQ30: =IF(C30="","",AN30*8) | AR30: =IF(C30="","",IFERROR(SUMIFS('6-Releve Heures'!K$5:K$104,'6-Releve Heures'!C$5:C$104,C30),0)) | AS30: =IF(C30="","",IFERROR(AR30-AQ30,0))
... B104: =IF(C104="","PLM-"&TEXT(COUNTA($C$5:C104),"000")) | AN104: =IF(C104="","",COUNTIF(I104:AM104,"T")+COUNTIF(I104:AM104,"N")) | AO104: =IF(C104="","",COUNTIF(I104:AM104,"R")) | AP104: =IF(C104="","",COUNTIF(I104:AM104,"A")) | AQ104: =IF(C104="","",AN104*8) | AR104: =IF(C104="","",IFERROR(SUMIFS('6-Releve Heures'!K$5:K$104,'6-Releve Heures'!C$5:C$104,C104),0)) | AS104: =IF(C104="","",IFERROR(AR104-AQ104,0))
B105: =IF(C105="","PLM-"&TEXT(COUNTA($C$5:C105),"000"))
B106: =IF(C106="","PLM-"&TEXT(COUNTA($C$5:C106),"000"))
B107: =IF(C107="","PLM-"&TEXT(COUNTA($C$5:C107),"000"))
B108: =IF(C108="","PLM-"&TEXT(COUNTA($C$5:C108),"000"))
B109: =IF(C109="","PLM-"&TEXT(COUNTA($C$5:C109),"000"))
B111: INDICATEURS (mis a jour automatiquement)
B112: Employes planifies | D112: Total heures prevues | F112: Total heures effectives | H112: Ecart total (h)
B113: =COUNTIF(B5:B104,"<>") | D113: =SUM(V5:V104) | F113: =SUM(W5:W104) | H113: =SUM(X5:X104)

Sheet 3-Planning Hebdomadaire
B2: PLANNING HEBDOMADAIRE — ROTATION SEMAINE
B3: TABLEAU DYNAMIQUE — Saisissez dans la prochaine ligne jaune. Les calculs se mettent a jour automatiquement.
B4: N° Hebdo | C4: Matricule | D4: Nom Employe | E4: Equipe | F4: Periode | G4: Lundi | H4: Mardi | I4: Mercredi | J4: Jeudi | K4: Vendredi | L4: Samedi | M4: Dimanche | N4: Total Heures Sem. | O4: Statut
B5: PH-001 | C5: EMP-004 | D5: =IF(C5="","",IFERROR(VLOOKUP(C5,'_Données Employés'!$B$5:$H$18,3,FALSE)&" "&VLOOKUP(C5,'_Données Employés'!$B$5:$H$18,4,FALSE),"")) | E5: Equipe A | F5: Semaine 1 | G5: 08h-16h | H5: 08h-16h | I5: 08h-16h | J5: =IF(C5="","",COUNTIF(I5:O5,"T")+COUNTIF(I5:O5,"N")) | K5: 08h-16h | L5: Repos | M5: Repos | N5: 40 | O5: Valide
B6: PH-002 | C6: EMP-005 | D6: =IF(C6="","",IFERROR(VLOOKUP(C6,'_Données Employés'!$B$5:$H$18,3,FALSE)&" "&VLOOKUP(C6,'_Données Employés'!$B$5:$H$18,4,FALSE),"")) | E6: Equipe B | F6: Semaine 1 | G6: 06h-14h | H6: 06h-14h | I6: 06h-14h | J6: =IF(C6="","",COUNTIF(I6:O6,"T")+COUNTIF(I6:O6,"N")) | K6: Repos | L6: 06h-14h | M6: 06h-14h | N6: 40 | O6: Valide
B7: PH-003 | C7: EMP-004 | D7: =IF(C7="","",IFERROR(VLOOKUP(C7,'_Données Employés'!$B$5:$H$18,3,FALSE)&" "&VLOOKUP(C7,'_Données Employés'!$B$5:$H$18,4,FALSE),"")) | E7: Equipe A | F7: Semaine 2 | G7: 14h-22h | H7: 14h-22h | I7: 14h-22h | J7: =IF(C7="","",COUNTIF(I7:O7,"T")+COUNTIF(I7:O7,"N")) | K7: 14h-22h | L7: Repos | M7: Repos | N7: 40 | O7: Valide
B8: PH-004 | C8: EMP-001 | D8: =IF(C8="","",IFERROR(VLOOKUP(C8,'_Données Employés'!$B$5:$H$18,3,FALSE)&" "&VLOOKUP(C8,'_Données Employés'!$B$5:$H$18,4,FALSE),"")) | E8: Equipe Jour | F8: Semaine 1 | G8: 08h-17h | H8: 08h-17h | I8: 08h-17h | J8: =IF(C8="","",COUNTIF(I8:O8,"T")+COUNTIF(I8:O8,"N")) | K8: 08h-17h | L8: Repos | M8: Repos | N8: 45 | O8: Valide
B9: PH-005 | C9: EMP-003 | D9: =IF(C9="","",IFERROR(VLOOKUP(C9,'_Données Employés'!$B$5:$H$18,3,FALSE)&" "&VLOOKUP(C9,'_Données Employés'!$B$5:$H$18,4,FALSE),"")) | E9: Equipe Jour | F9: Semaine 1 | G9: 08h-17h | H9: 08h-17h | I9: Absence | J9: =IF(C9="","",COUNTIF(I9:O9,"T")+COUNTIF(I9:O9,"N")) | K9: 08h-17h | L9: Repos | M9: Repos | N9: 36 | O9: Valide
B10: =IF(C10="","PH-"&TEXT(COUNTA($C$5:C10),"000")) | J10: =IF(C10="","",COUNTIF(I10:O10,"T")+COUNTIF(I10:O10,"N"))
B11: =IF(C11="","PH-"&TEXT(COUNTA($C$5:C11),"000")) | J11: =IF(C11="","",COUNTIF(I11:O11,"T")+COUNTIF(I11:O11,"N"))
B12: =IF(C12="","PH-"&TEXT(COUNTA($C$5:C12),"000")) | J12: =IF(C12="","",COUNTIF(I12:O12,"T")+COUNTIF(I12:O12,"N"))
B13: =IF(C13="","PH-"&TEXT(COUNTA($C$5:C13),"000")) | J13: =IF(C13="","",COUNTIF(I13:O13,"T")+COUNTIF(I13:O13,"N"))
B14: =IF(C14="","PH-"&TEXT(COUNTA($C$5:C14),"000")) | J14: =IF(C14="","",COUNTIF(I14:O14,"T")+COUNTIF(I14:O14,"N"))
B15: =IF(C15="","PH-"&TEXT(COUNTA($C$5:C15),"000")) | J15: =IF(C15="","",COUNTIF(I15:O15,"T")+COUNTIF(I15:O15,"N"))
B16: =IF(C16="","PH-"&TEXT(COUNTA($C$5:C16),"000")) | J16: =IF(C16="","",COUNTIF(I16:O16,"T")+COUNTIF(I16:O16,"N"))
B17: =IF(C17="","PH-"&TEXT(COUNTA($C$5:C17),"000")) | J17: =IF(C17="","",COUNTIF(I17:O17,"T")+COUNTIF(I17:O17,"N"))
B18: =IF(C18="","PH-"&TEXT(COUNTA($C$5:C18),"000")) | J18: =IF(C18="","",COUNTIF(I18:O18,"T")+COUNTIF(I18:O18,"N"))
B19: =IF(C19="","PH-"&TEXT(COUNTA($C$5:C19),"000")) | J19: =IF(C19="","",COUNTIF(I19:O19,"T")+COUNTIF(I19:O19,"N"))
B20: =IF(C20="","PH-"&TEXT(COUNTA($C$5:C20),"000")) | J20: =IF(C20="","",COUNTIF(I20:O20,"T")+COUNTIF(I20:O20,"N"))
B21: =IF(C21="","PH-"&TEXT(COUNTA($C$5:C21),"000")) | J21: =IF(C21="","",COUNTIF(I21:O21,"T")+COUNTIF(I21:O21,"N"))
... B104: =IF(C104="","PH-"&TEXT(COUNTA($C$5:C104),"000")) | J104: =IF(C104="","",COUNTIF(I104:O104,"T")+COUNTIF(I104:O104,"N"))
B105: =IF(C105="","PH-"&TEXT(COUNTA($C$5:C105),"000"))
B106: =IF(C106="","PH-"&TEXT(COUNTA($C$5:C106),"000"))
B107: =IF(C107="","PH-"&TEXT(COUNTA($C$5:C107),"000"))
B108: =IF(C108="","PH-"&TEXT(COUNTA($C$5:C108),"000"))
B109: =IF(C109="","PH-"&TEXT(COUNTA($C$5:C109),"000"))
B111: INDICATEURS (mis a jour automatiquement)
B112: Plannings hebdo | D112: Heures totales (h) | F112: Moyenne h/sem | H112: Plannings valides
B113: =COUNTIF(B5:B104,"<>") | D113: =SUM(N5:N104) | F113: =IFERROR(AVERAGE(N5:N104),0) | H113: =COUNTIF(O5:O104,"Valide")

Sheet 4-Garde & Astreintes
B2: GARDE & ASTREINTES
B3: TABLEAU DYNAMIQUE — Saisissez dans la prochaine ligne jaune. Les calculs se mettent a jour automatiquement.
B4: N° Garde | C4: Matricule | D4: Nom Employe | E4: Departement | F4: Poste | G4: Type Garde | H4: Date Debut | I4: Date Fin | J4: Duree (heures) | K4: Compensation (FCFA) | L4: Statut
B5: GAR-001 | C5: EMP-002 | D5: =IF(C5="","",IFERROR(VLOOKUP(C5,'_Données Employés'!$B$5:$H$18,3,FALSE)&" "&VLOOKUP(C5,'_Données Employés'!$B$5:$H$18,4,FALSE),"")) | E5: =IF(C5="","",IFERROR(VLOOKUP(C5,'_Données Employés'!$B$5:$H$18,5,FALSE),"")) | F5: =IF(C5="","",IFERROR(VLOOKUP(C5,'_Données Employés'!$B$5:$H$18,6,FALSE),"")) | G5: Astreinte telephone | H5: 45815 | I5: 45816 | J5: 24 | K5: 15000 | L5: Effectuee
B6: GAR-002 | C6: EMP-002 | D6: =IF(C6="","",IFERROR(VLOOKUP(C6,'_Données Employés'!$B$5:$H$18,3,FALSE)&" "&VLOOKUP(C6,'_Données Employés'!$B$5:$H$18,4,FALSE),"")) | E6: =IF(C6="","",IFERROR(VLOOKUP(C6,'_Données Employés'!$B$5:$H$18,5,FALSE),"")) | F6: =IF(C6="","",IFERROR(VLOOKUP(C6,'_Données Employés'!$B$5:$H$18,6,FALSE),"")) | G6: Astreinte telephone | H6: 45822 | I6: 45823 | J6: 24 | K6: 15000 | L6: Planifiee
B7: GAR-003 | C7: EMP-029 | D7: =IF(C7="","",IFERROR(VLOOKUP(C7,'_Données Employés'!$B$5:$H$18,3,FALSE)&" "&VLOOKUP(C7,'_Données Employés'!$B$5:$H$18,4,FALSE),"")) | E7: =IF(C7="","",IFERROR(VLOOKUP(C7,'_Données Employés'!$B$5:$H$18,5,FALSE),"")) | F7: =IF(C7="","",IFERROR(VLOOKUP(C7,'_Données Employés'!$B$5:$H$18,6,FALSE),"")) | G7: Garde de nuit | H7: 45809 | I7: 45838 | J7: 240 | K7: 120000 | L7: En cours
B8: GAR-004 | C8: EMP-028 | D8: =IF(C8="","",IFERROR(VLOOKUP(C8,'_Données Employés'!$B$5:$H$18,3,FALSE)&" "&VLOOKUP(C8,'_Données Employés'!$B$5:$H$18,4,FALSE),"")) | E8: =IF(C8="","",IFERROR(VLOOKUP(C8,'_Données Employés'!$B$5:$H$18,5,FALSE),"")) | F8: =IF(C8="","",IFERROR(VLOOKUP(C8,'_Données Employés'!$B$5:$H$18,6,FALSE),"")) | G8: Permanence week-end | H8: 45815 | I8: 45816 | J8: 16 | K8: 10000 | L8: Effectuee
B9: GAR-005 | C9: EMP-002 | D9: =IF(C9="","",IFERROR(VLOOKUP(C9,'_Données Employés'!$B$5:$H$18,3,FALSE)&" "&VLOOKUP(C9,'_Données Employés'!$B$5:$H$18,4,FALSE),"")) | E9: =IF(C9="","",IFERROR(VLOOKUP(C9,'_Données Employés'!$B$5:$H$18,5,FALSE),"")) | F9: =IF(C9="","",IFERROR(VLOOKUP(C9,'_Données Employés'!$B$5:$H$18,6,FALSE),"")) | G9: Astreinte deplacee | H9: 45829 | I9: 45830 | J9: 48 | K9: 35000 | L9: Planifiee
B10: =IF(C10="","GAR-"&TEXT(COUNTA($C$5:C10),"000"))
B11: =IF(C11="","GAR-"&TEXT(COUNTA($C$5:C11),"000"))
B12: =IF(C12="","GAR-"&TEXT(COUNTA($C$5:C12),"000"))
B13: =IF(C13="","GAR-"&TEXT(COUNTA($C$5:C13),"000"))
B14: =IF(C14="","GAR-"&TEXT(COUNTA($C$5:C14),"000"))
B15: =IF(C15="","GAR-"&TEXT(COUNTA($C$5:C15),"000"))
B16: =IF(C16="","GAR-"&TEXT(COUNTA($C$5:C16),"000"))
B17: =IF(C17="","GAR-"&TEXT(COUNTA($C$5:C17),"000"))
B18: =IF(C18="","GAR-"&TEXT(COUNTA($C$5:C18),"000"))
B19: =IF(C19="","GAR-"&TEXT(COUNTA($C$5:C19),"000"))
B20: =IF(C20="","GAR-"&TEXT(COUNTA($C$5:C20),"000"))
B21: =IF(C21="","GAR-"&TEXT(COUNTA($C$5:C21),"000"))
... B109: =IF(C109="","GAR-"&TEXT(COUNTA($C$5:C109),"000"))
B111: TOTAL | J111: =SUM(J5:J104) | K111: =SUM(K5:K104)
B113: INDICATEURS (mis a jour automatiquement)
B114: Total gardes | D114: Heures de garde | F114: Budget gardes (FCFA) | H114: Gardes effectuees
B115: =COUNTIF(B5:B104,"<>") | D115: =SUM(J5:J104) | F115: =SUM(K5:K104) | H115: =COUNTIF(L5:L104,"Effectuee")

Sheet 5-Pointage Journalier
B2: POINTAGE JOURNALIER
B3: TABLEAU DYNAMIQUE — Saisissez dans la prochaine ligne jaune. Les calculs se mettent a jour automatiquement.
B4: N° Pointage | C4: Matricule | D4: Nom Employe | E4: Departement | F4: Date | G4: Heure Arrivee | H4: Heure Depart | I4: Duree Travail (h) | J4: Pause Dejeuner (h) | K4: Heures Nettes (h) | L4: Mode Pointage | M4: Retard (min) | N4: Statut | O4: Observations
B5: PTJ-001 | C5: EMP-001 | D5: =IF(C5="","",IFERROR(VLOOKUP(C5,'_Données Employés'!$B$5:$H$18,3,FALSE)&" "&VLOOKUP(C5,'_Données Employés'!$B$5:$H$18,4,FALSE),"")) | E5: =IF(C5="","",IFERROR(VLOOKUP(C5,'_Données Employés'!$B$5:$H$18,5,FALSE),"")) | F5: 45810 | G5: 07h55 | H5: 17h10 | I5: 9.25 | J5: 1 | K5: 8.25 | L5: Badgeuse | M5: 0 | N5: Valide
B6: PTJ-002 | C6: EMP-002 | D6: =IF(C6="","",IFERROR(VLOOKUP(C6,'_Données Employés'!$B$5:$H$18,3,FALSE)&" "&VLOOKUP(C6,'_Données Employés'!$B$5:$H$18,4,FALSE),"")) | E6: =IF(C6="","",IFERROR(VLOOKUP(C6,'_Données Employés'!$B$5:$H$18,5,FALSE),"")) | F6: 45810 | G6: 08h15 | H6: 17h30 | I6: 9.25 | J6: 1 | K6: 8.25 | L6: Badgeuse | M6: 15 | N6: Valide | O6: Retard mineur
B7: PTJ-003 | C7: EMP-003 | D7: =IF(C7="","",IFERROR(VLOOKUP(C7,'_Données Employés'!$B$5:$H$18,3,FALSE)&" "&VLOOKUP(C7,'_Données Employés'!$B$5:$H$18,4,FALSE),"")) | E7: =IF(C7="","",IFERROR(VLOOKUP(C7,'_Données Employés'!$B$5:$H$18,5,FALSE),"")) | F7: 45810 | G7: 08h00 | H7: 17h05 | I7: 9.08 | J7: 1 | K7: 8.08 | L7: Badgeuse | M7: 0 | N7: Valide
B8: PTJ-004 | C8: EMP-004 | D8: =IF(C8="","",IFERROR(VLOOKUP(C8,'_Données Employés'!$B$5:$H$18,3,FALSE)&" "&VLOOKUP(C8,'_Données Employés'!$B$5:$H$18,4,FALSE),"")) | E8: =IF(C8="","",IFERROR(VLOOKUP(C8,'_Données Employés'!$B$5:$H$18,5,FALSE),"")) | F8: 45810 | G8: 06h00 | H8: 14h10 | I8: 8.17 | J8: 0.5 | K8: 7.67 | L8: Pointeur | M8: 0 | N8: Valide
B9: PTJ-005 | C9: EMP-005 | D9: =IF(C9="","",IFERROR(VLOOKUP(C9,'_Données Employés'!$B$5:$H$18,3,FALSE)&" "&VLOOKUP(C9,'_Données Employés'!$B$5:$H$18,4,FALSE),"")) | E9: =IF(C9="","",IFERROR(VLOOKUP(C9,'_Données Employés'!$B$5:$H$18,5,FALSE),"")) | F9: 45810 | I9: 0 | J9: 0 | K9: 0 | L9: Fiche manuelle | M9: 0 | N9: Anomalie detectee | O9: Absent - motif en attente
B10: =IF(C10="","PTJ-"&TEXT(COUNTA($C$5:C10),"000"))
B11: =IF(C11="","PTJ-"&TEXT(COUNTA($C$5:C11),"000"))
B12: =IF(C12="","PTJ-"&TEXT(COUNTA($C$5:C12),"000"))
B13: =IF(C13="","PTJ-"&TEXT(COUNTA($C$5:C13),"000"))
B14: =IF(C14="","PTJ-"&TEXT(COUNTA($C$5:C14),"000"))
B15: =IF(C15="","PTJ-"&TEXT(COUNTA($C$5:C15),"000"))
B16: =IF(C16="","PTJ-"&TEXT(COUNTA($C$5:C16),"000"))
B17: =IF(C17="","PTJ-"&TEXT(COUNTA($C$5:C17),"000"))
B18: =IF(C18="","PTJ-"&TEXT(COUNTA($C$5:C18),"000"))
B19: =IF(C19="","PTJ-"&TEXT(COUNTA($C$5:C19),"000"))
B20: =IF(C20="","PTJ-"&TEXT(COUNTA($C$5:C20),"000"))
B21: =IF(C21="","PTJ-"&TEXT(COUNTA($C$5:C21),"000"))
... B109: =IF(C109="","PTJ-"&TEXT(COUNTA($C$5:C109),"000"))
B111: TOTAL | I111: =SUM(I5:I104) | J111: =SUM(J5:J104) | K111: =SUM(K5:K104) | M111: =SUM(M5:M104)
B113: INDICATEURS (mis a jour automatiquement)
B114: Pointages saisis | D114: Heures totales | F114: Retards detectes | H114: Anomalies
B115: =COUNTIF(B5:B104,"<>") | D115: =SUM(K5:K104) | F115: =COUNTIF(M5:M104,">0") | H115: =COUNTIF(N5:N104,"Anomalie detectee")

Sheet 6-Releve Heures
B2: RELEVE HEBDOMADAIRE DES HEURES
B3: TABLEAU DYNAMIQUE — Saisissez dans la prochaine ligne jaune. Les calculs se mettent a jour automatiquement.
B4: N° Releve | C4: Matricule | D4: Nom Employe | E4: Departement | F4: Semaine | G4: Heures Normales | H4: Heures Supp | I4: Heures Nuit | J4: Heures Week-End | K4: Total Heures | L4: Ecart vs Prevu | M4: Statut
B5: RH-001 | C5: EMP-001 | D5: =IF(C5="","",IFERROR(VLOOKUP(C5,'_Données Employés'!$B$5:$H$18,3,FALSE)&" "&VLOOKUP(C5,'_Données Employés'!$B$5:$H$18,4,FALSE),"")) | E5: =IF(C5="","",IFERROR(VLOOKUP(C5,'_Données Employés'!$B$5:$H$18,5,FALSE),"")) | F5: Semaine 1 | G5: 45 | H5: 5 | I5: 0 | J5: 0 | K5: =IF(C5="","",IFERROR(G5+H5+I5+J5,0)) | L5: =IF(C5="","",IFERROR(K5-40,0)) | M5: Valide
B6: RH-002 | C6: EMP-002 | D6: =IF(C6="","",IFERROR(VLOOKUP(C6,'_Données Employés'!$B$5:$H$18,3,FALSE)&" "&VLOOKUP(C6,'_Données Employés'!$B$5:$H$18,4,FALSE),"")) | E6: =IF(C6="","",IFERROR(VLOOKUP(C6,'_Données Employés'!$B$5:$H$18,5,FALSE),"")) | F6: Semaine 1 | G6: 40 | H6: 0 | I6: 4 | J6: 8 | K6: =IF(C6="","",IFERROR(G6+H6+I6+J6,0)) | L6: =IF(C6="","",IFERROR(K6-40,0)) | M6: Valide
B7: RH-003 | C7: EMP-004 | D7: =IF(C7="","",IFERROR(VLOOKUP(C7,'_Données Employés'!$B$5:$H$18,3,FALSE)&" "&VLOOKUP(C7,'_Données Employés'!$B$5:$H$18,4,FALSE),"")) | E7: =IF(C7="","",IFERROR(VLOOKUP(C7,'_Données Employés'!$B$5:$H$18,5,FALSE),"")) | F7: Semaine 1 | G7: 40 | H7: 0 | I7: 16 | J7: 8 | K7: =IF(C7="","",IFERROR(G7+H7+I7+J7,0)) | L7: =IF(C7="","",IFERROR(K7-40,0)) | M7: Valide
B8: RH-004 | C8: EMP-005 | D8: =IF(C8="","",IFERROR(VLOOKUP(C8,'_Données Employés'!$B$5:$H$18,3,FALSE)&" "&VLOOKUP(C8,'_Données Employés'!$B$5:$H$18,4,FALSE),"")) | E8: =IF(C8="","",IFERROR(VLOOKUP(C8,'_Données Employés'!$B$5:$H$18,5,FALSE),"")) | F8: Semaine 1 | G8: 40 | H8: 8 | I8: 0 | J8: 8 | K8: =IF(C8="","",IFERROR(G8+H8+I8+J8,0)) | L8: =IF(C8="","",IFERROR(K8-40,0)) | M8: Valide
B9: RH-005 | C9: EMP-003 | D9: =IF(C9="","",IFERROR(VLOOKUP(C9,'_Données Employés'!$B$5:$H$18,3,FALSE)&" "&VLOOKUP(C9,'_Données Employés'!$B$5:$H$18,4,FALSE),"")) | E9: =IF(C9="","",IFERROR(VLOOKUP(C9,'_Données Employés'!$B$5:$H$18,5,FALSE),"")) | F9: Semaine 1 | G9: 36 | H9: 0 | I9: 0 | J9: 0 | K9: =IF(C9="","",IFERROR(G9+H9+I9+J9,0)) | L9: =IF(C9="","",IFERROR(K9-40,0)) | M9: Valide
B10: =IF(C10="","RH-"&TEXT(COUNTA($C$5:C10),"000")) | K10: =IF(C10="","",IFERROR(G10+H10+I10+J10,0)) | L10: =IF(C10="","",IFERROR(K10-40,0))
B11: =IF(C11="","RH-"&TEXT(COUNTA($C$5:C11),"000")) | K11: =IF(C11="","",IFERROR(G11+H11+I11+J11,0)) | L11: =IF(C11="","",IFERROR(K11-40,0))
B12: =IF(C12="","RH-"&TEXT(COUNTA($C$5:C12),"000")) | K12: =IF(C12="","",IFERROR(G12+H12+I12+J12,0)) | L12: =IF(C12="","",IFERROR(K12-40,0))
B13: =IF(C13="","RH-"&TEXT(COUNTA($C$5:C13),"000")) | K13: =IF(C13="","",IFERROR(G13+H13+I13+J13,0)) | L13: =IF(C13="","",IFERROR(K13-40,0))
B14: =IF(C14="","RH-"&TEXT(COUNTA($C$5:C14),"000")) | K14: =IF(C14="","",IFERROR(G14+H14+I14+J14,0)) | L14: =IF(C14="","",IFERROR(K14-40,0))
B15: =IF(C15="","RH-"&TEXT(COUNTA($C$5:C15),"000")) | K15: =IF(C15="","",IFERROR(G15+H15+I15+J15,0)) | L15: =IF(C15="","",IFERROR(K15-40,0))
B16: =IF(C16="","RH-"&TEXT(COUNTA($C$5:C16),"000")) | K16: =IF(C16="","",IFERROR(G16+H16+I16+J16,0)) | L16: =IF(C16="","",IFERROR(K16-40,0))
B17: =IF(C17="","RH-"&TEXT(COUNTA($C$5:C17),"000")) | K17: =IF(C17="","",IFERROR(G17+H17+I17+J17,0)) | L17: =IF(C17="","",IFERROR(K17-40,0))
B18: =IF(C18="","RH-"&TEXT(COUNTA($C$5:C18),"000")) | K18: =IF(C18="","",IFERROR(G18+H18+I18+J18,0)) | L18: =IF(C18="","",IFERROR(K18-40,0))
B19: =IF(C19="","RH-"&TEXT(COUNTA($C$5:C19),"000")) | K19: =IF(C19="","",IFERROR(G19+H19+I19+J19,0)) | L19: =IF(C19="","",IFERROR(K19-40,0))
B20: =IF(C20="","RH-"&TEXT(COUNTA($C$5:C20),"000")) | K20: =IF(C20="","",IFERROR(G20+H20+I20+J20,0)) | L20: =IF(C20="","",IFERROR(K20-40,0))
B21: =IF(C21="","RH-"&TEXT(COUNTA($C$5:C21),"000")) | K21: =IF(C21="","",IFERROR(G21+H21+I21+J21,0)) | L21: =IF(C21="","",IFERROR(K21-40,0))
... B104: =IF(C104="","RH-"&TEXT(COUNTA($C$5:C104),"000")) | K104: =IF(C104="","",IFERROR(G104+H104+I104+J104,0)) | L104: =IF(C104="","",IFERROR(K104-40,0))
B105: =IF(C105="","RH-"&TEXT(COUNTA($C$5:C105),"000")) | K105: =SUM(G105,H105,I105,J105) | L105: =IF(G105="","",K105-40)
B106: =IF(C106="","RH-"&TEXT(COUNTA($C$5:C106),"000")) | K106: =SUM(G106,H106,I106,J106) | L106: =IF(G106="","",K106-40)
B107: =IF(C107="","RH-"&TEXT(COUNTA($C$5:C107),"000")) | K107: =SUM(G107,H107,I107,J107) | L107: =IF(G107="","",K107-40)
B108: =IF(C108="","RH-"&TEXT(COUNTA($C$5:C108),"000")) | K108: =SUM(G108,H108,I108,J108) | L108: =IF(G108="","",K108-40)
B109: =IF(C109="","RH-"&TEXT(COUNTA($C$5:C109),"000")) | K109: =SUM(G109,H109,I109,J109) | L109: =IF(G109="","",K109-40)
B111: TOTAL | G111: =SUM(G5:G104) | H111: =SUM(H5:H104) | I111: =SUM(I5:I104) | J111: =SUM(J5:J104) | K111: =SUM(K5:K104) | L111: =SUM(L5:L104)
B113: INDICATEURS (mis a jour automatiquement)
B114: Releves saisis | D114: Total h. normales | F114: Total h. supplementaires | H114: Total h. nuit
B115: =COUNTIF(B5:B104,"<>") | D115: =SUM(G5:G104) | F115: =SUM(H5:H104) | H115: =SUM(I5:I104)

Sheet 7-Heures Supplementaires
B2: HEURES SUPPLEMENTAIRES — SUIVI & MAJORATIONS
B3: TABLEAU DYNAMIQUE — Saisissez dans la prochaine ligne jaune. Les calculs se mettent a jour automatiquement.
B4: N° HS | C4: Matricule | D4: Nom Employe | E4: Departement | F4: Date | G4: Heure Debut | H4: Heure Fin | I4: Nb Heures | J4: Type Heure Supp | K4: Taux Majoration | L4: Heures Bonifiees | M4: Montant (FCFA) | N4: Statut | O4: Validation
B5: HS-001 | C5: EMP-001 | D5: =IF(C5="","",IFERROR(VLOOKUP(C5,'_Données Employés'!$B$5:$H$18,3,FALSE)&" "&VLOOKUP(C5,'_Données Employés'!$B$5:$H$18,4,FALSE),"")) | E5: =IF(C5="","",IFERROR(VLOOKUP(C5,'_Données Employés'!$B$5:$H$18,5,FALSE),"")) | F5: 45813 | G5: 17h00 | H5: 19h30 | I5: 2.5 | J5: Heure supplementaire jour | K5: 25% | L5: =IF(OR(C5="",I5="",K5=""),"",IFERROR(I5*(1+IF(ISNUMBER(K5),K5,VALUE(SUBSTITUTE(K5,"%",""))/100)),0)) | M5: 7500 | N5: Valide | O5: Approuvee
B6: HS-002 | C6: EMP-002 | D6: =IF(C6="","",IFERROR(VLOOKUP(C6,'_Données Employés'!$B$5:$H$18,3,FALSE)&" "&VLOOKUP(C6,'_Données Employés'!$B$5:$H$18,4,FALSE),"")) | E6: =IF(C6="","",IFERROR(VLOOKUP(C6,'_Données Employés'!$B$5:$H$18,5,FALSE),"")) | F6: 45815 | G6: 22h00 | H6: 02h00 | I6: 4 | J6: Heure nuit supplementaire | K6: 50% | L6: =IF(OR(C6="",I6="",K6=""),"",IFERROR(I6*(1+IF(ISNUMBER(K6),K6,VALUE(SUBSTITUTE(K6,"%",""))/100)),0)) | M6: 18000 | N6: Valide | O6: Approuvee
B7: HS-003 | C7: EMP-004 | D7: =IF(C7="","",IFERROR(VLOOKUP(C7,'_Données Employés'!$B$5:$H$18,3,FALSE)&" "&VLOOKUP(C7,'_Données Employés'!$B$5:$H$18,4,FALSE),"")) | E7: =IF(C7="","",IFERROR(VLOOKUP(C7,'_Données Employés'!$B$5:$H$18,5,FALSE),"")) | F7: 45816 | G7: 08h00 | H7: 16h00 | I7: 8 | J7: Heure week-end | K7: 50% | L7: =IF(OR(C7="",I7="",K7=""),"",IFERROR(I7*(1+IF(ISNUMBER(K7),K7,VALUE(SUBSTITUTE(K7,"%",""))/100)),0)) | M7: 36000 | N7: Valide | O7: Approuvee
B8: HS-004 | C8: EMP-005 | D8: =IF(C8="","",IFERROR(VLOOKUP(C8,'_Données Employés'!$B$5:$H$18,3,FALSE)&" "&VLOOKUP(C8,'_Données Employés'!$B$5:$H$18,4,FALSE),"")) | E8: =IF(C8="","",IFERROR(VLOOKUP(C8,'_Données Employés'!$B$5:$H$18,5,FALSE),"")) | F8: 45818 | G8: 14h00 | H8: 18h00 | I8: 4 | J8: Heure supplementaire jour | K8: 25% | L8: =IF(OR(C8="",I8="",K8=""),"",IFERROR(I8*(1+IF(ISNUMBER(K8),K8,VALUE(SUBSTITUTE(K8,"%",""))/100)),0)) | M8: 15000 | N8: Valide | O8: Approuvee
B9: HS-005 | C9: EMP-001 | D9: =IF(C9="","",IFERROR(VLOOKUP(C9,'_Données Employés'!$B$5:$H$18,3,FALSE)&" "&VLOOKUP(C9,'_Données Employés'!$B$5:$H$18,4,FALSE),"")) | E9: =IF(C9="","",IFERROR(VLOOKUP(C9,'_Données Employés'!$B$5:$H$18,5,FALSE),"")) | F9: 45820 | G9: 17h00 | H9: 20h00 | I9: 3 | J9: Heure supplementaire jour | K9: 25% | L9: =IF(OR(C9="",I9="",K9=""),"",IFERROR(I9*(1+IF(ISNUMBER(K9),K9,VALUE(SUBSTITUTE(K9,"%",""))/100)),0)) | M9: 9000 | N9: En attente | O9: En attente
B10: =IF(C10="","HS-"&TEXT(COUNTA($C$5:C10),"000")) | L10: =IF(OR(C10="",I10="",K10=""),"",IFERROR(I10*(1+IF(ISNUMBER(K10),K10,VALUE(SUBSTITUTE(K10,"%",""))/100)),0))
B11: =IF(C11="","HS-"&TEXT(COUNTA($C$5:C11),"000")) | L11: =IF(OR(C11="",I11="",K11=""),"",IFERROR(I11*(1+IF(ISNUMBER(K11),K11,VALUE(SUBSTITUTE(K11,"%",""))/100)),0))
B12: =IF(C12="","HS-"&TEXT(COUNTA($C$5:C12),"000")) | L12: =IF(OR(C12="",I12="",K12=""),"",IFERROR(I12*(1+IF(ISNUMBER(K12),K12,VALUE(SUBSTITUTE(K12,"%",""))/100)),0))
B13: =IF(C13="","HS-"&TEXT(COUNTA($C$5:C13),"000")) | L13: =IF(OR(C13="",I13="",K13=""),"",IFERROR(I13*(1+IF(ISNUMBER(K13),K13,VALUE(SUBSTITUTE(K13,"%",""))/100)),0))
B14: =IF(C14="","HS-"&TEXT(COUNTA($C$5:C14),"000")) | L14: =IF(OR(C14="",I14="",K14=""),"",IFERROR(I14*(1+IF(ISNUMBER(K14),K14,VALUE(SUBSTITUTE(K14,"%",""))/100)),0))
B15: =IF(C15="","HS-"&TEXT(COUNTA($C$5:C15),"000")) | L15: =IF(OR(C15="",I15="",K15=""),"",IFERROR(I15*(1+IF(ISNUMBER(K15),K15,VALUE(SUBSTITUTE(K15,"%",""))/100)),0))
B16: =IF(C16="","HS-"&TEXT(COUNTA($C$5:C16),"000")) | L16: =IF(OR(C16="",I16="",K16=""),"",IFERROR(I16*(1+IF(ISNUMBER(K16),K16,VALUE(SUBSTITUTE(K16,"%",""))/100)),0))
B17: =IF(C17="","HS-"&TEXT(COUNTA($C$5:C17),"000")) | L17: =IF(OR(C17="",I17="",K17=""),"",IFERROR(I17*(1+IF(ISNUMBER(K17),K17,VALUE(SUBSTITUTE(K17,"%",""))/100)),0))
B18: =IF(C18="","HS-"&TEXT(COUNTA($C$5:C18),"000")) | L18: =IF(OR(C18="",I18="",K18=""),"",IFERROR(I18*(1+IF(ISNUMBER(K18),K18,VALUE(SUBSTITUTE(K18,"%",""))/100)),0))
B19: =IF(C19="","HS-"&TEXT(COUNTA($C$5:C19),"000")) | L19: =IF(OR(C19="",I19="",K19=""),"",IFERROR(I19*(1+IF(ISNUMBER(K19),K19,VALUE(SUBSTITUTE(K19,"%",""))/100)),0))
B20: =IF(C20="","HS-"&TEXT(COUNTA($C$5:C20),"000")) | L20: =IF(OR(C20="",I20="",K20=""),"",IFERROR(I20*(1+IF(ISNUMBER(K20),K20,VALUE(SUBSTITUTE(K20,"%",""))/100)),0))
B21: =IF(C21="","HS-"&TEXT(COUNTA($C$5:C21),"000")) | L21: =IF(OR(C21="",I21="",K21=""),"",IFERROR(I21*(1+IF(ISNUMBER(K21),K21,VALUE(SUBSTITUTE(K21,"%",""))/100)),0))
... B104: =IF(C104="","HS-"&TEXT(COUNTA($C$5:C104),"000")) | L104: =IF(OR(C104="",I104="",K104=""),"",IFERROR(I104*(1+IF(ISNUMBER(K104),K104,VALUE(SUBSTITUTE(K104,"%",""))/100)),0))
B105: =IF(C105="","HS-"&TEXT(COUNTA($C$5:C105),"000"))
B106: =IF(C106="","HS-"&TEXT(COUNTA($C$5:C106),"000"))
B107: =IF(C107="","HS-"&TEXT(COUNTA($C$5:C107),"000"))
B108: =IF(C108="","HS-"&TEXT(COUNTA($C$5:C108),"000"))
B109: =IF(C109="","HS-"&TEXT(COUNTA($C$5:C109),"000"))
B111: TOTAL | I111: =SUM(I5:I104) | L111: =SUM(L5:L104) | M111: =SUM(M5:M104)
B113: INDICATEURS (mis a jour automatiquement)
B114: Total demandes HS | D114: Total heures supp | F114: Heures bonifiees | H114: Cout total HS (FCFA)
B115: =COUNTIF(B5:B104,"<>") | D115: =SUM(I5:I104) | F115: =SUM(L5:L104) | H115: =SUM(M5:M104)

Sheet 8-Heures Nuit
B2: HEURES DE NUIT — SUIVI (22h-06h)
B3: TABLEAU DYNAMIQUE — Saisissez dans la prochaine ligne jaune. Les calculs se mettent a jour automatiquement.
B4: N° Nuit | C4: Matricule | D4: Nom Employe | E4: Departement | F4: Poste | G4: Date Debut | H4: Date Fin | I4: Heure Debut | J4: Heure Fin | K4: Nb Heures Nuit | L4: Periode Nuit | M4: Statut
B5: NI-001 | C5: EMP-029 | D5: =IF(C5="","",IFERROR(VLOOKUP(C5,'_Données Employés'!$B$5:$H$18,3,FALSE)&" "&VLOOKUP(C5,'_Données Employés'!$B$5:$H$18,4,FALSE),"")) | E5: =IF(C5="","",IFERROR(VLOOKUP(C5,'_Données Employés'!$B$5:$H$18,5,FALSE),"")) | F5: =IF(C5="","",IFERROR(VLOOKUP(C5,'_Données Employés'!$B$5:$H$18,6,FALSE),"")) | G5: 45809 | H5: 45810 | I5: 22h00 | J5: 06h00 | K5: 8 | L5: 22h-06h | M5: Effectuee
B6: NI-002 | C6: EMP-028 | D6: =IF(C6="","",IFERROR(VLOOKUP(C6,'_Données Employés'!$B$5:$H$18,3,FALSE)&" "&VLOOKUP(C6,'_Données Employés'!$B$5:$H$18,4,FALSE),"")) | E6: =IF(C6="","",IFERROR(VLOOKUP(C6,'_Données Employés'!$B$5:$H$18,5,FALSE),"")) | F6: =IF(C6="","",IFERROR(VLOOKUP(C6,'_Données Employés'!$B$5:$H$18,6,FALSE),"")) | G6: 45810 | H6: 45811 | I6: 22h00 | J6: 06h00 | K6: 8 | L6: 22h-06h | M6: Effectuee
B7: NI-003 | C7: EMP-002 | D7: =IF(C7="","",IFERROR(VLOOKUP(C7,'_Données Employés'!$B$5:$H$18,3,FALSE)&" "&VLOOKUP(C7,'_Données Employés'!$B$5:$H$18,4,FALSE),"")) | E7: =IF(C7="","",IFERROR(VLOOKUP(C7,'_Données Employés'!$B$5:$H$18,5,FALSE),"")) | F7: =IF(C7="","",IFERROR(VLOOKUP(C7,'_Données Employés'!$B$5:$H$18,6,FALSE),"")) | G7: 45815 | H7: 45816 | I7: 22h00 | J7: 02h00 | K7: 4 | L7: 22h-06h | M7: Effectuee
B8: NI-004 | C8: EMP-004 | D8: =IF(C8="","",IFERROR(VLOOKUP(C8,'_Données Employés'!$B$5:$H$18,3,FALSE)&" "&VLOOKUP(C8,'_Données Employés'!$B$5:$H$18,4,FALSE),"")) | E8: =IF(C8="","",IFERROR(VLOOKUP(C8,'_Données Employés'!$B$5:$H$18,5,FALSE),"")) | F8: =IF(C8="","",IFERROR(VLOOKUP(C8,'_Données Employés'!$B$5:$H$18,6,FALSE),"")) | G8: 45817 | H8: 45818 | I8: 22h00 | J8: 06h00 | K8: 8 | L8: 22h-06h | M8: Effectuee
B9: NI-005 | C9: EMP-029 | D9: =IF(C9="","",IFERROR(VLOOKUP(C9,'_Données Employés'!$B$5:$H$18,3,FALSE)&" "&VLOOKUP(C9,'_Données Employés'!$B$5:$H$18,4,FALSE),"")) | E9: =IF(C9="","",IFERROR(VLOOKUP(C9,'_Données Employés'!$B$5:$H$18,5,FALSE),"")) | F9: =IF(C9="","",IFERROR(VLOOKUP(C9,'_Données Employés'!$B$5:$H$18,6,FALSE),"")) | G9: 45816 | H9: 45817 | I9: 22h00 | J9: 06h00 | K9: 8 | L9: 22h-06h | M9: Effectuee
B10: =IF(C10="","NI-"&TEXT(COUNTA($C$5:C10),"000"))
B11: =IF(C11="","NI-"&TEXT(COUNTA($C$5:C11),"000"))
B12: =IF(C12="","NI-"&TEXT(COUNTA($C$5:C12),"000"))
B13: =IF(C13="","NI-"&TEXT(COUNTA($C$5:C13),"000"))
B14: =IF(C14="","NI-"&TEXT(COUNTA($C$5:C14),"000"))
B15: =IF(C15="","NI-"&TEXT(COUNTA($C$5:C15),"000"))
B16: =IF(C16="","NI-"&TEXT(COUNTA($C$5:C16),"000"))
B17: =IF(C17="","NI-"&TEXT(COUNTA($C$5:C17),"000"))
B18: =IF(C18="","NI-"&TEXT(COUNTA($C$5:C18),"000"))
B19: =IF(C19="","NI-"&TEXT(COUNTA($C$5:C19),"000"))
B20: =IF(C20="","NI-"&TEXT(COUNTA($C$5:C20),"000"))
B21: =IF(C21="","NI-"&TEXT(COUNTA($C$5:C21),"000"))
... B109: =IF(C109="","NI-"&TEXT(COUNTA($C$5:C109),"000"))
B111: TOTAL | K111: =SUM(K5:K104)
B113: INDICATEURS (mis a jour automatiquement)
B114: Total heures nuit | D114: Nuits effectuees | F114: Agents de nuit | H114: Moyenne h/nuit
B115: =SUM(K5:K104) | D115: =COUNTIF(M5:M104,"Effectuee") | F115: =COUNTA(C5:C104)-COUNTBLANK(C5:C104) | H115: =IFERROR(AVERAGE(K5:K104),0)

Sheet 9-Heures WE & Feries
B2: HEURES WEEK-END & JOURS FERIES
B3: TABLEAU DYNAMIQUE — Saisissez dans la prochaine ligne jaune. Les calculs se mettent a jour automatiquement.
B4: N° WEF | C4: Matricule | D4: Nom Employe | E4: Departement | F4: Poste | G4: Date | H4: Jour | I4: Nb Heures | J4: Taux Majoration | K4: Heures Bonifiees | L4: Montant (FCFA) | M4: Statut
B5: WEF-001 | C5: EMP-004 | D5: =IF(C5="","",IFERROR(VLOOKUP(C5,'_Données Employés'!$B$5:$H$18,3,FALSE)&" "&VLOOKUP(C5,'_Données Employés'!$B$5:$H$18,4,FALSE),"")) | E5: =IF(C5="","",IFERROR(VLOOKUP(C5,'_Données Employés'!$B$5:$H$18,5,FALSE),"")) | F5: =IF(C5="","",IFERROR(VLOOKUP(C5,'_Données Employés'!$B$5:$H$18,6,FALSE),"")) | G5: 45815 | H5: Samedi | I5: 8 | J5: 50% | K5: 12 | L5: 36000 | M5: Valide
B6: WEF-002 | C6: EMP-005 | D6: =IF(C6="","",IFERROR(VLOOKUP(C6,'_Données Employés'!$B$5:$H$18,3,FALSE)&" "&VLOOKUP(C6,'_Données Employés'!$B$5:$H$18,4,FALSE),"")) | E6: =IF(C6="","",IFERROR(VLOOKUP(C6,'_Données Employés'!$B$5:$H$18,5,FALSE),"")) | F6: =IF(C6="","",IFERROR(VLOOKUP(C6,'_Données Employés'!$B$5:$H$18,6,FALSE),"")) | G6: 45816 | H6: Dimanche | I6: 8 | J6: 75% | K6: 14 | L6: 42000 | M6: Valide
B7: WEF-003 | C7: EMP-029 | D7: =IF(C7="","",IFERROR(VLOOKUP(C7,'_Données Employés'!$B$5:$H$18,3,FALSE)&" "&VLOOKUP(C7,'_Données Employés'!$B$5:$H$18,4,FALSE),"")) | E7: =IF(C7="","",IFERROR(VLOOKUP(C7,'_Données Employés'!$B$5:$H$18,5,FALSE),"")) | F7: =IF(C7="","",IFERROR(VLOOKUP(C7,'_Données Employés'!$B$5:$H$18,6,FALSE),"")) | G7: 45809 | H7: Ferie | I7: 8 | J7: 100% | K7: 16 | L7: 48000 | M7: Valide
B8: WEF-004 | C8: EMP-028 | D8: =IF(C8="","",IFERROR(VLOOKUP(C8,'_Données Employés'!$B$5:$H$18,3,FALSE)&" "&VLOOKUP(C8,'_Données Employés'!$B$5:$H$18,4,FALSE),"")) | E8: =IF(C8="","",IFERROR(VLOOKUP(C8,'_Données Employés'!$B$5:$H$18,5,FALSE),"")) | F8: =IF(C8="","",IFERROR(VLOOKUP(C8,'_Données Employés'!$B$5:$H$18,6,FALSE),"")) | G8: 45815 | H8: Samedi | I8: 8 | J8: 50% | K8: 12 | L8: 36000 | M8: Valide
B9: WEF-005 | C9: EMP-002 | D9: =IF(C9="","",IFERROR(VLOOKUP(C9,'_Données Employés'!$B$5:$H$18,3,FALSE)&" "&VLOOKUP(C9,'_Données Employés'!$B$5:$H$18,4,FALSE),"")) | E9: =IF(C9="","",IFERROR(VLOOKUP(C9,'_Données Employés'!$B$5:$H$18,5,FALSE),"")) | F9: =IF(C9="","",IFERROR(VLOOKUP(C9,'_Données Employés'!$B$5:$H$18,6,FALSE),"")) | G9: 45816 | H9: Dimanche | I9: 4 | J9: 75% | K9: 7 | L9: 21000 | M9: En attente
B10: =IF(C10="","WEF-"&TEXT(COUNTA($C$5:C10),"000")) | K10: =IF(I10="","",I10*(1+SUBSTITUTE(J10,"%","")/100))
B11: =IF(C11="","WEF-"&TEXT(COUNTA($C$5:C11),"000")) | K11: =IF(I11="","",I11*(1+SUBSTITUTE(J11,"%","")/100))
B12: =IF(C12="","WEF-"&TEXT(COUNTA($C$5:C12),"000")) | K12: =IF(I12="","",I12*(1+SUBSTITUTE(J12,"%","")/100))
B13: =IF(C13="","WEF-"&TEXT(COUNTA($C$5:C13),"000")) | K13: =IF(I13="","",I13*(1+SUBSTITUTE(J13,"%","")/100))
B14: =IF(C14="","WEF-"&TEXT(COUNTA($C$5:C14),"000")) | K14: =IF(I14="","",I14*(1+SUBSTITUTE(J14,"%","")/100))
B15: =IF(C15="","WEF-"&TEXT(COUNTA($C$5:C15),"000")) | K15: =IF(I15="","",I15*(1+SUBSTITUTE(J15,"%","")/100))
B16: =IF(C16="","WEF-"&TEXT(COUNTA($C$5:C16),"000")) | K16: =IF(I16="","",I16*(1+SUBSTITUTE(J16,"%","")/100))
B17: =IF(C17="","WEF-"&TEXT(COUNTA($C$5:C17),"000")) | K17: =IF(I17="","",I17*(1+SUBSTITUTE(J17,"%","")/100))
B18: =IF(C18="","WEF-"&TEXT(COUNTA($C$5:C18),"000")) | K18: =IF(I18="","",I18*(1+SUBSTITUTE(J18,"%","")/100))
B19: =IF(C19="","WEF-"&TEXT(COUNTA($C$5:C19),"000")) | K19: =IF(I19="","",I19*(1+SUBSTITUTE(J19,"%","")/100))
B20: =IF(C20="","WEF-"&TEXT(COUNTA($C$5:C20),"000")) | K20: =IF(I20="","",I20*(1+SUBSTITUTE(J20,"%","")/100))
B21: =IF(C21="","WEF-"&TEXT(COUNTA($C$5:C21),"000")) | K21: =IF(I21="","",I21*(1+SUBSTITUTE(J21,"%","")/100))
... B109: =IF(C109="","WEF-"&TEXT(COUNTA($C$5:C109),"000")) | K109: =IF(I109="","",I109*(1+SUBSTITUTE(J109,"%","")/100))
B111: TOTAL | I111: =SUM(I5:I104) | K111: =SUM(K5:K104) | L111: =SUM(L5:L104)
B113: INDICATEURS (mis a jour automatiquement)
B114: Total heures WE/feries | D114: Heures bonifiees | F114: Cout total (FCFA) | H114: Dossiers valides
B115: =SUM(I5:I104) | D115: =SUM(K5:K104) | F115: =SUM(L5:L104) | H115: =COUNTIF(M5:M104,"Valide")

Sheet 10-Compteurs Temps
B2: COMPTEURS DE TEMPS — BANQUES D'HEURES
B3: TABLEAU DYNAMIQUE — Saisissez dans la prochaine ligne jaune. Les calculs se mettent a jour automatiquement.
B4: N° Compteur | C4: Matricule | D4: Nom Employe | E4: Departement | F4: Mois | G4: Annee | H4: Heures Theoriques | I4: Heures Effectives | J4: Heures Supp | K4: Heures Nuit | L4: Absences (h) | M4: Solde Heures | N4: Taux Realisation | O4: Statut
B5: CT-001 | C5: EMP-001 | D5: =IF(C5="","",IFERROR(VLOOKUP(C5,'_Données Employés'!$B$5:$H$18,3,FALSE)&" "&VLOOKUP(C5,'_Données Employés'!$B$5:$H$18,4,FALSE),"")) | E5: =IF(C5="","",IFERROR(VLOOKUP(C5,'_Données Employés'!$B$5:$H$18,5,FALSE),"")) | F5: Juin | G5: 2025 | H5: 173 | I5: =IF(C5="","",IFERROR(SUMIFS('6-Releve Heures'!K$5:K$104,'6-Releve Heures'!C$5:C$104,C5),0)) | J5: =IF(C5="","",IFERROR(SUMIFS('7-Heures Supplementaires'!I$5:I$104,'7-Heures Supplementaires'!C$5:C$104,C5),0)) | K5: =IF(C5="","",IFERROR(SUMIFS('8-Heures Nuit'!J$5:J$104,'8-Heures Nuit'!C$5:C$104,C5),0)) | L5: =IF(C5="","",IFERROR(SUMIFS('2-Planning Mensuel'!U$5:U$104,'2-Planning Mensuel'!C$5:C$104,C5)*8,0)) | M5: =IF(C5="","",IFERROR(I5-H5,0)) | N5: =IF(OR(C5="",H5=0,H5=""),"",IFERROR(I5/H5,0)) | O5: Valide
B6: CT-002 | C6: EMP-002 | D6: =IF(C6="","",IFERROR(VLOOKUP(C6,'_Données Employés'!$B$5:$H$18,3,FALSE)&" "&VLOOKUP(C6,'_Données Employés'!$B$5:$H$18,4,FALSE),"")) | E6: =IF(C6="","",IFERROR(VLOOKUP(C6,'_Données Employés'!$B$5:$H$18,5,FALSE),"")) | F6: Juin | G6: 2025 | H6: 173 | I6: =IF(C6="","",IFERROR(SUMIFS('6-Releve Heures'!K$5:K$104,'6-Releve Heures'!C$5:C$104,C6),0)) | J6: =IF(C6="","",IFERROR(SUMIFS('7-Heures Supplementaires'!I$5:I$104,'7-Heures Supplementaires'!C$5:C$104,C6),0)) | K6: =IF(C6="","",IFERROR(SUMIFS('8-Heures Nuit'!J$5:J$104,'8-Heures Nuit'!C$5:C$104,C6),0)) | L6: =IF(C6="","",IFERROR(SUMIFS('2-Planning Mensuel'!U$5:U$104,'2-Planning Mensuel'!C$5:C$104,C6)*8,0)) | M6: =IF(C6="","",IFERROR(I6-H6,0)) | N6: =IF(OR(C6="",H6=0,H6=""),"",IFERROR(I6/H6,0)) | O6: Valide
B7: CT-003 | C7: EMP-003 | D7: =IF(C7="","",IFERROR(VLOOKUP(C7,'_Données Employés'!$B$5:$H$18,3,FALSE)&" "&VLOOKUP(C7,'_Données Employés'!$B$5:$H$18,4,FALSE),"")) | E7: =IF(C7="","",IFERROR(VLOOKUP(C7,'_Données Employés'!$B$5:$H$18,5,FALSE),"")) | F7: Juin | G7: 2025 | H7: 173 | I7: =IF(C7="","",IFERROR(SUMIFS('6-Releve Heures'!K$5:K$104,'6-Releve Heures'!C$5:C$104,C7),0)) | J7: =IF(C7="","",IFERROR(SUMIFS('7-Heures Supplementaires'!I$5:I$104,'7-Heures Supplementaires'!C$5:C$104,C7),0)) | K7: =IF(C7="","",IFERROR(SUMIFS('8-Heures Nuit'!J$5:J$104,'8-Heures Nuit'!C$5:C$104,C7),0)) | L7: =IF(C7="","",IFERROR(SUMIFS('2-Planning Mensuel'!U$5:U$104,'2-Planning Mensuel'!C$5:C$104,C7)*8,0)) | M7: =IF(C7="","",IFERROR(I7-H7,0)) | N7: =IF(OR(C7="",H7=0,H7=""),"",IFERROR(I7/H7,0)) | O7: Valide
B8: CT-004 | C8: EMP-004 | D8: =IF(C8="","",IFERROR(VLOOKUP(C8,'_Données Employés'!$B$5:$H$18,3,FALSE)&" "&VLOOKUP(C8,'_Données Employés'!$B$5:$H$18,4,FALSE),"")) | E8: =IF(C8="","",IFERROR(VLOOKUP(C8,'_Données Employés'!$B$5:$H$18,5,FALSE),"")) | F8: Juin | G8: 2025 | H8: 173 | I8: =IF(C8="","",IFERROR(SUMIFS('6-Releve Heures'!K$5:K$104,'6-Releve Heures'!C$5:C$104,C8),0)) | J8: =IF(C8="","",IFERROR(SUMIFS('7-Heures Supplementaires'!I$5:I$104,'7-Heures Supplementaires'!C$5:C$104,C8),0)) | K8: =IF(C8="","",IFERROR(SUMIFS('8-Heures Nuit'!J$5:J$104,'8-Heures Nuit'!C$5:C$104,C8),0)) | L8: =IF(C8="","",IFERROR(SUMIFS('2-Planning Mensuel'!U$5:U$104,'2-Planning Mensuel'!C$5:C$104,C8)*8,0)) | M8: =IF(C8="","",IFERROR(I8-H8,0)) | N8: =IF(OR(C8="",H8=0,H8=""),"",IFERROR(I8/H8,0)) | O8: Valide
B9: CT-005 | C9: EMP-005 | D9: =IF(C9="","",IFERROR(VLOOKUP(C9,'_Données Employés'!$B$5:$H$18,3,FALSE)&" "&VLOOKUP(C9,'_Données Employés'!$B$5:$H$18,4,FALSE),"")) | E9: =IF(C9="","",IFERROR(VLOOKUP(C9,'_Données Employés'!$B$5:$H$18,5,FALSE),"")) | F9: Juin | G9: 2025 | H9: 173 | I9: =IF(C9="","",IFERROR(SUMIFS('6-Releve Heures'!K$5:K$104,'6-Releve Heures'!C$5:C$104,C9),0)) | J9: =IF(C9="","",IFERROR(SUMIFS('7-Heures Supplementaires'!I$5:I$104,'7-Heures Supplementaires'!C$5:C$104,C9),0)) | K9: =IF(C9="","",IFERROR(SUMIFS('8-Heures Nuit'!J$5:J$104,'8-Heures Nuit'!C$5:C$104,C9),0)) | L9: =IF(C9="","",IFERROR(SUMIFS('2-Planning Mensuel'!U$5:U$104,'2-Planning Mensuel'!C$5:C$104,C9)*8,0)) | M9: =IF(C9="","",IFERROR(I9-H9,0)) | N9: =IF(OR(C9="",H9=0,H9=""),"",IFERROR(I9/H9,0)) | O9: Valide
B10: CT-006 | C10: EMP-006 | D10: =IF(C10="","",IFERROR(VLOOKUP(C10,'_Données Employés'!$B$5:$H$18,3,FALSE)&" "&VLOOKUP(C10,'_Données Employés'!$B$5:$H$18,4,FALSE),"")) | E10: =IF(C10="","",IFERROR(VLOOKUP(C10,'_Données Employés'!$B$5:$H$18,5,FALSE),"")) | F10: Juin | G10: 2025 | H10: 173 | I10: =IF(C10="","",IFERROR(SUMIFS('6-Releve Heures'!K$5:K$104,'6-Releve Heures'!C$5:C$104,C10),0)) | J10: =IF(C10="","",IFERROR(SUMIFS('7-Heures Supplementaires'!I$5:I$104,'7-Heures Supplementaires'!C$5:C$104,C10),0)) | K10: =IF(C10="","",IFERROR(SUMIFS('8-Heures Nuit'!J$5:J$104,'8-Heures Nuit'!C$5:C$104,C10),0)) | L10: =IF(C10="","",IFERROR(SUMIFS('2-Planning Mensuel'!U$5:U$104,'2-Planning Mensuel'!C$5:C$104,C10)*8,0)) | M10: =IF(C10="","",IFERROR(I10-H10,0)) | N10: =IF(OR(C10="",H10=0,H10=""),"",IFERROR(I10/H10,0))
B11: CT-007 | C11: EMP-007 | D11: =IF(C11="","",IFERROR(VLOOKUP(C11,'_Données Employés'!$B$5:$H$18,3,FALSE)&" "&VLOOKUP(C11,'_Données Employés'!$B$5:$H$18,4,FALSE),"")) | E11: =IF(C11="","",IFERROR(VLOOKUP(C11,'_Données Employés'!$B$5:$H$18,5,FALSE),"")) | F11: Juin | G11: 2025 | H11: 173 | I11: =IF(C11="","",IFERROR(SUMIFS('6-Releve Heures'!K$5:K$104,'6-Releve Heures'!C$5:C$104,C11),0)) | J11: =IF(C11="","",IFERROR(SUMIFS('7-Heures Supplementaires'!I$5:I$104,'7-Heures Supplementaires'!C$5:C$104,C11),0)) | K11: =IF(C11="","",IFERROR(SUMIFS('8-Heures Nuit'!J$5:J$104,'8-Heures Nuit'!C$5:C$104,C11),0)) | L11: =IF(C11="","",IFERROR(SUMIFS('2-Planning Mensuel'!U$5:U$104,'2-Planning Mensuel'!C$5:C$104,C11)*8,0)) | M11: =IF(C11="","",IFERROR(I11-H11,0)) | N11: =IF(OR(C11="",H11=0,H11=""),"",IFERROR(I11/H11,0))
B12: CT-008 | C12: EMP-008 | D12: =IF(C12="","",IFERROR(VLOOKUP(C12,'_Données Employés'!$B$5:$H$18,3,FALSE)&" "&VLOOKUP(C12,'_Données Employés'!$B$5:$H$18,4,FALSE),"")) | E12: =IF(C12="","",IFERROR(VLOOKUP(C12,'_Données Employés'!$B$5:$H$18,5,FALSE),"")) | F12: Juin | G12: 2025 | H12: 173 | I12: =IF(C12="","",IFERROR(SUMIFS('6-Releve Heures'!K$5:K$104,'6-Releve Heures'!C$5:C$104,C12),0)) | J12: =IF(C12="","",IFERROR(SUMIFS('7-Heures Supplementaires'!I$5:I$104,'7-Heures Supplementaires'!C$5:C$104,C12),0)) | K12: =IF(C12="","",IFERROR(SUMIFS('8-Heures Nuit'!J$5:J$104,'8-Heures Nuit'!C$5:C$104,C12),0)) | L12: =IF(C12="","",IFERROR(SUMIFS('2-Planning Mensuel'!U$5:U$104,'2-Planning Mensuel'!C$5:C$104,C12)*8,0)) | M12: =IF(C12="","",IFERROR(I12-H12,0)) | N12: =IF(OR(C12="",H12=0,H12=""),"",IFERROR(I12/H12,0))
B13: CT-009 | C13: EMP-009 | D13: =IF(C13="","",IFERROR(VLOOKUP(C13,'_Données Employés'!$B$5:$H$18,3,FALSE)&" "&VLOOKUP(C13,'_Données Employés'!$B$5:$H$18,4,FALSE),"")) | E13: =IF(C13="","",IFERROR(VLOOKUP(C13,'_Données Employés'!$B$5:$H$18,5,FALSE),"")) | F13: Juin | G13: 2025 | H13: 173 | I13: =IF(C13="","",IFERROR(SUMIFS('6-Releve Heures'!K$5:K$104,'6-Releve Heures'!C$5:C$104,C13),0)) | J13: =IF(C13="","",IFERROR(SUMIFS('7-Heures Supplementaires'!I$5:I$104,'7-Heures Supplementaires'!C$5:C$104,C13),0)) | K13: =IF(C13="","",IFERROR(SUMIFS('8-Heures Nuit'!J$5:J$104,'8-Heures Nuit'!C$5:C$104,C13),0)) | L13: =IF(C13="","",IFERROR(SUMIFS('2-Planning Mensuel'!U$5:U$104,'2-Planning Mensuel'!C$5:C$104,C13)*8,0)) | M13: =IF(C13="","",IFERROR(I13-H13,0)) | N13: =IF(OR(C13="",H13=0,H13=""),"",IFERROR(I13/H13,0))
B14: CT-010 | C14: EMP-010 | D14: =IF(C14="","",IFERROR(VLOOKUP(C14,'_Données Employés'!$B$5:$H$18,3,FALSE)&" "&VLOOKUP(C14,'_Données Employés'!$B$5:$H$18,4,FALSE),"")) | E14: =IF(C14="","",IFERROR(VLOOKUP(C14,'_Données Employés'!$B$5:$H$18,5,FALSE),"")) | F14: Juin | G14: 2025 | H14: 173 | I14: =IF(C14="","",IFERROR(SUMIFS('6-Releve Heures'!K$5:K$104,'6-Releve Heures'!C$5:C$104,C14),0)) | J14: =IF(C14="","",IFERROR(SUMIFS('7-Heures Supplementaires'!I$5:I$104,'7-Heures Supplementaires'!C$5:C$104,C14),0)) | K14: =IF(C14="","",IFERROR(SUMIFS('8-Heures Nuit'!J$5:J$104,'8-Heures Nuit'!C$5:C$104,C14),0)) | L14: =IF(C14="","",IFERROR(SUMIFS('2-Planning Mensuel'!U$5:U$104,'2-Planning Mensuel'!C$5:C$104,C14)*8,0)) | M14: =IF(C14="","",IFERROR(I14-H14,0)) | N14: =IF(OR(C14="",H14=0,H14=""),"",IFERROR(I14/H14,0))
B15: CT-011 | C15: EMP-011 | D15: =IF(C15="","",IFERROR(VLOOKUP(C15,'_Données Employés'!$B$5:$H$18,3,FALSE)&" "&VLOOKUP(C15,'_Données Employés'!$B$5:$H$18,4,FALSE),"")) | E15: =IF(C15="","",IFERROR(VLOOKUP(C15,'_Données Employés'!$B$5:$H$18,5,FALSE),"")) | F15: Juin | G15: 2025 | H15: 173 | I15: =IF(C15="","",IFERROR(SUMIFS('6-Releve Heures'!K$5:K$104,'6-Releve Heures'!C$5:C$104,C15),0)) | J15: =IF(C15="","",IFERROR(SUMIFS('7-Heures Supplementaires'!I$5:I$104,'7-Heures Supplementaires'!C$5:C$104,C15),0)) | K15: =IF(C15="","",IFERROR(SUMIFS('8-Heures Nuit'!J$5:J$104,'8-Heures Nuit'!C$5:C$104,C15),0)) | L15: =IF(C15="","",IFERROR(SUMIFS('2-Planning Mensuel'!U$5:U$104,'2-Planning Mensuel'!C$5:C$104,C15)*8,0)) | M15: =IF(C15="","",IFERROR(I15-H15,0)) | N15: =IF(OR(C15="",H15=0,H15=""),"",IFERROR(I15/H15,0))
B16: CT-012 | C16: EMP-012 | D16: =IF(C16="","",IFERROR(VLOOKUP(C16,'_Données Employés'!$B$5:$H$18,3,FALSE)&" "&VLOOKUP(C16,'_Données Employés'!$B$5:$H$18,4,FALSE),"")) | E16: =IF(C16="","",IFERROR(VLOOKUP(C16,'_Données Employés'!$B$5:$H$18,5,FALSE),"")) | F16: Juin | G16: 2025 | H16: 173 | I16: =IF(C16="","",IFERROR(SUMIFS('6-Releve Heures'!K$5:K$104,'6-Releve Heures'!C$5:C$104,C16),0)) | J16: =IF(C16="","",IFERROR(SUMIFS('7-Heures Supplementaires'!I$5:I$104,'7-Heures Supplementaires'!C$5:C$104,C16),0)) | K16: =IF(C16="","",IFERROR(SUMIFS('8-Heures Nuit'!J$5:J$104,'8-Heures Nuit'!C$5:C$104,C16),0)) | L16: =IF(C16="","",IFERROR(SUMIFS('2-Planning Mensuel'!U$5:U$104,'2-Planning Mensuel'!C$5:C$104,C16)*8,0)) | M16: =IF(C16="","",IFERROR(I16-H16,0)) | N16: =IF(OR(C16="",H16=0,H16=""),"",IFERROR(I16/H16,0))
B17: CT-028 | C17: EMP-028 | D17: =IF(C17="","",IFERROR(VLOOKUP(C17,'_Données Employés'!$B$5:$H$18,3,FALSE)&" "&VLOOKUP(C17,'_Données Employés'!$B$5:$H$18,4,FALSE),"")) | E17: =IF(C17="","",IFERROR(VLOOKUP(C17,'_Données Employés'!$B$5:$H$18,5,FALSE),"")) | F17: Juin | G17: 2025 | H17: 173 | I17: =IF(C17="","",IFERROR(SUMIFS('6-Releve Heures'!K$5:K$104,'6-Releve Heures'!C$5:C$104,C17),0)) | J17: =IF(C17="","",IFERROR(SUMIFS('7-Heures Supplementaires'!I$5:I$104,'7-Heures Supplementaires'!C$5:C$104,C17),0)) | K17: =IF(C17="","",IFERROR(SUMIFS('8-Heures Nuit'!J$5:J$104,'8-Heures Nuit'!C$5:C$104,C17),0)) | L17: =IF(C17="","",IFERROR(SUMIFS('2-Planning Mensuel'!U$5:U$104,'2-Planning Mensuel'!C$5:C$104,C17)*8,0)) | M17: =IF(C17="","",IFERROR(I17-H17,0)) | N17: =IF(OR(C17="",H17=0,H17=""),"",IFERROR(I17/H17,0))
B18: CT-029 | C18: EMP-029 | D18: =IF(C18="","",IFERROR(VLOOKUP(C18,'_Données Employés'!$B$5:$H$18,3,FALSE)&" "&VLOOKUP(C18,'_Données Employés'!$B$5:$H$18,4,FALSE),"")) | E18: =IF(C18="","",IFERROR(VLOOKUP(C18,'_Données Employés'!$B$5:$H$18,5,FALSE),"")) | F18: Juin | G18: 2025 | H18: 173 | I18: =IF(C18="","",IFERROR(SUMIFS('6-Releve Heures'!K$5:K$104,'6-Releve Heures'!C$5:C$104,C18),0)) | J18: =IF(C18="","",IFERROR(SUMIFS('7-Heures Supplementaires'!I$5:I$104,'7-Heures Supplementaires'!C$5:C$104,C18),0)) | K18: =IF(C18="","",IFERROR(SUMIFS('8-Heures Nuit'!J$5:J$104,'8-Heures Nuit'!C$5:C$104,C18),0)) | L18: =IF(C18="","",IFERROR(SUMIFS('2-Planning Mensuel'!U$5:U$104,'2-Planning Mensuel'!C$5:C$104,C18)*8,0)) | M18: =IF(C18="","",IFERROR(I18-H18,0)) | N18: =IF(OR(C18="",H18=0,H18=""),"",IFERROR(I18/H18,0))
B19: =IF(C19="","CT-"&TEXT(COUNTA($C$5:C19),"000")) | I19: =IF(C19="","",IFERROR(SUMIFS('6-Releve Heures'!K$5:K$104,'6-Releve Heures'!C$5:C$104,C19),0)) | J19: =IF(C19="","",IFERROR(SUMIFS('7-Heures Supplementaires'!I$5:I$104,'7-Heures Supplementaires'!C$5:C$104,C19),0)) | K19: =IF(C19="","",IFERROR(SUMIFS('8-Heures Nuit'!J$5:J$104,'8-Heures Nuit'!C$5:C$104,C19),0)) | L19: =IF(C19="","",IFERROR(SUMIFS('2-Planning Mensuel'!U$5:U$104,'2-Planning Mensuel'!C$5:C$104,C19)*8,0)) | M19: =IF(C19="","",IFERROR(I19-H19,0)) | N19: =IF(OR(C19="",H19=0,H19=""),"",IFERROR(I19/H19,0))
B20: =IF(C20="","CT-"&TEXT(COUNTA($C$5:C20),"000")) | I20: =IF(C20="","",IFERROR(SUMIFS('6-Releve Heures'!K$5:K$104,'6-Releve Heures'!C$5:C$104,C20),0)) | J20: =IF(C20="","",IFERROR(SUMIFS('7-Heures Supplementaires'!I$5:I$104,'7-Heures Supplementaires'!C$5:C$104,C20),0)) | K20: =IF(C20="","",IFERROR(SUMIFS('8-Heures Nuit'!J$5:J$104,'8-Heures Nuit'!C$5:C$104,C20),0)) | L20: =IF(C20="","",IFERROR(SUMIFS('2-Planning Mensuel'!U$5:U$104,'2-Planning Mensuel'!C$5:C$104,C20)*8,0)) | M20: =IF(C20="","",IFERROR(I20-H20,0)) | N20: =IF(OR(C20="",H20=0,H20=""),"",IFERROR(I20/H20,0))
B21: =IF(C21="","CT-"&TEXT(COUNTA($C$5:C21),"000")) | I21: =IF(C21="","",IFERROR(SUMIFS('6-Releve Heures'!K$5:K$104,'6-Releve Heures'!C$5:C$104,C21),0)) | J21: =IF(C21="","",IFERROR(SUMIFS('7-Heures Supplementaires'!I$5:I$104,'7-Heures Supplementaires'!C$5:C$104,C21),0)) | K21: =IF(C21="","",IFERROR(SUMIFS('8-Heures Nuit'!J$5:J$104,'8-Heures Nuit'!C$5:C$104,C21),0)) | L21: =IF(C21="","",IFERROR(SUMIFS('2-Planning Mensuel'!U$5:U$104,'2-Planning Mensuel'!C$5:C$104,C21)*8,0)) | M21: =IF(C21="","",IFERROR(I21-H21,0)) | N21: =IF(OR(C21="",H21=0,H21=""),"",IFERROR(I21/H21,0))
B22: =IF(C22="","CT-"&TEXT(COUNTA($C$5:C22),"000")) | I22: =IF(C22="","",IFERROR(SUMIFS('6-Releve Heures'!K$5:K$104,'6-Releve Heures'!C$5:C$104,C22),0)) | J22: =IF(C22="","",IFERROR(SUMIFS('7-Heures Supplementaires'!I$5:I$104,'7-Heures Supplementaires'!C$5:C$104,C22),0)) | K22: =IF(C22="","",IFERROR(SUMIFS('8-Heures Nuit'!J$5:J$104,'8-Heures Nuit'!C$5:C$104,C22),0)) | L22: =IF(C22="","",IFERROR(SUMIFS('2-Planning Mensuel'!U$5:U$104,'2-Planning Mensuel'!C$5:C$104,C22)*8,0)) | M22: =IF(C22="","",IFERROR(I22-H22,0)) | N22: =IF(OR(C22="",H22=0,H22=""),"",IFERROR(I22/H22,0))
B23: =IF(C23="","CT-"&TEXT(COUNTA($C$5:C23),"000")) | I23: =IF(C23="","",IFERROR(SUMIFS('6-Releve Heures'!K$5:K$104,'6-Releve Heures'!C$5:C$104,C23),0)) | J23: =IF(C23="","",IFERROR(SUMIFS('7-Heures Supplementaires'!I$5:I$104,'7-Heures Supplementaires'!C$5:C$104,C23),0)) | K23: =IF(C23="","",IFERROR(SUMIFS('8-Heures Nuit'!J$5:J$104,'8-Heures Nuit'!C$5:C$104,C23),0)) | L23: =IF(C23="","",IFERROR(SUMIFS('2-Planning Mensuel'!U$5:U$104,'2-Planning Mensuel'!C$5:C$104,C23)*8,0)) | M23: =IF(C23="","",IFERROR(I23-H23,0)) | N23: =IF(OR(C23="",H23=0,H23=""),"",IFERROR(I23/H23,0))
B24: =IF(C24="","CT-"&TEXT(COUNTA($C$5:C24),"000")) | I24: =IF(C24="","",IFERROR(SUMIFS('6-Releve Heures'!K$5:K$104,'6-Releve Heures'!C$5:C$104,C24),0)) | J24: =IF(C24="","",IFERROR(SUMIFS('7-Heures Supplementaires'!I$5:I$104,'7-Heures Supplementaires'!C$5:C$104,C24),0)) | K24: =IF(C24="","",IFERROR(SUMIFS('8-Heures Nuit'!J$5:J$104,'8-Heures Nuit'!C$5:C$104,C24),0)) | L24: =IF(C24="","",IFERROR(SUMIFS('2-Planning Mensuel'!U$5:U$104,'2-Planning Mensuel'!C$5:C$104,C24)*8,0)) | M24: =IF(C24="","",IFERROR(I24-H24,0)) | N24: =IF(OR(C24="",H24=0,H24=""),"",IFERROR(I24/H24,0))
B25: =IF(C25="","CT-"&TEXT(COUNTA($C$5:C25),"000")) | I25: =IF(C25="","",IFERROR(SUMIFS('6-Releve Heures'!K$5:K$104,'6-Releve Heures'!C$5:C$104,C25),0)) | J25: =IF(C25="","",IFERROR(SUMIFS('7-Heures Supplementaires'!I$5:I$104,'7-Heures Supplementaires'!C$5:C$104,C25),0)) | K25: =IF(C25="","",IFERROR(SUMIFS('8-Heures Nuit'!J$5:J$104,'8-Heures Nuit'!C$5:C$104,C25),0)) | L25: =IF(C25="","",IFERROR(SUMIFS('2-Planning Mensuel'!U$5:U$104,'2-Planning Mensuel'!C$5:C$104,C25)*8,0)) | M25: =IF(C25="","",IFERROR(I25-H25,0)) | N25: =IF(OR(C25="",H25=0,H25=""),"",IFERROR(I25/H25,0))
B26: =IF(C26="","CT-"&TEXT(COUNTA($C$5:C26),"000")) | I26: =IF(C26="","",IFERROR(SUMIFS('6-Releve Heures'!K$5:K$104,'6-Releve Heures'!C$5:C$104,C26),0)) | J26: =IF(C26="","",IFERROR(SUMIFS('7-Heures Supplementaires'!I$5:I$104,'7-Heures Supplementaires'!C$5:C$104,C26),0)) | K26: =IF(C26="","",IFERROR(SUMIFS('8-Heures Nuit'!J$5:J$104,'8-Heures Nuit'!C$5:C$104,C26),0)) | L26: =IF(C26="","",IFERROR(SUMIFS('2-Planning Mensuel'!U$5:U$104,'2-Planning Mensuel'!C$5:C$104,C26)*8,0)) | M26: =IF(C26="","",IFERROR(I26-H26,0)) | N26: =IF(OR(C26="",H26=0,H26=""),"",IFERROR(I26/H26,0))
B27: =IF(C27="","CT-"&TEXT(COUNTA($C$5:C27),"000")) | I27: =IF(C27="","",IFERROR(SUMIFS('6-Releve Heures'!K$5:K$104,'6-Releve Heures'!C$5:C$104,C27),0)) | J27: =IF(C27="","",IFERROR(SUMIFS('7-Heures Supplementaires'!I$5:I$104,'7-Heures Supplementaires'!C$5:C$104,C27),0)) | K27: =IF(C27="","",IFERROR(SUMIFS('8-Heures Nuit'!J$5:J$104,'8-Heures Nuit'!C$5:C$104,C27),0)) | L27: =IF(C27="","",IFERROR(SUMIFS('2-Planning Mensuel'!U$5:U$104,'2-Planning Mensuel'!C$5:C$104,C27)*8,0)) | M27: =IF(C27="","",IFERROR(I27-H27,0)) | N27: =IF(OR(C27="",H27=0,H27=""),"",IFERROR(I27/H27,0))
B28: =IF(C28="","CT-"&TEXT(COUNTA($C$5:C28),"000")) | I28: =IF(C28="","",IFERROR(SUMIFS('6-Releve Heures'!K$5:K$104,'6-Releve Heures'!C$5:C$104,C28),0)) | J28: =IF(C28="","",IFERROR(SUMIFS('7-Heures Supplementaires'!I$5:I$104,'7-Heures Supplementaires'!C$5:C$104,C28),0)) | K28: =IF(C28="","",IFERROR(SUMIFS('8-Heures Nuit'!J$5:J$104,'8-Heures Nuit'!C$5:C$104,C28),0)) | L28: =IF(C28="","",IFERROR(SUMIFS('2-Planning Mensuel'!U$5:U$104,'2-Planning Mensuel'!C$5:C$104,C28)*8,0)) | M28: =IF(C28="","",IFERROR(I28-H28,0)) | N28: =IF(OR(C28="",H28=0,H28=""),"",IFERROR(I28/H28,0))
B29: =IF(C29="","CT-"&TEXT(COUNTA($C$5:C29),"000")) | I29: =IF(C29="","",IFERROR(SUMIFS('6-Releve Heures'!K$5:K$104,'6-Releve Heures'!C$5:C$104,C29),0)) | J29: =IF(C29="","",IFERROR(SUMIFS('7-Heures Supplementaires'!I$5:I$104,'7-Heures Supplementaires'!C$5:C$104,C29),0)) | K29: =IF(C29="","",IFERROR(SUMIFS('8-Heures Nuit'!J$5:J$104,'8-Heures Nuit'!C$5:C$104,C29),0)) | L29: =IF(C29="","",IFERROR(SUMIFS('2-Planning Mensuel'!U$5:U$104,'2-Planning Mensuel'!C$5:C$104,C29)*8,0)) | M29: =IF(C29="","",IFERROR(I29-H29,0)) | N29: =IF(OR(C29="",H29=0,H29=""),"",IFERROR(I29/H29,0))
B30: =IF(C30="","CT-"&TEXT(COUNTA($C$5:C30),"000")) | I30: =IF(C30="","",IFERROR(SUMIFS('6-Releve Heures'!K$5:K$104,'6-Releve Heures'!C$5:C$104,C30),0)) | J30: =IF(C30="","",IFERROR(SUMIFS('7-Heures Supplementaires'!I$5:I$104,'7-Heures Supplementaires'!C$5:C$104,C30),0)) | K30: =IF(C30="","",IFERROR(SUMIFS('8-Heures Nuit'!J$5:J$104,'8-Heures Nuit'!C$5:C$104,C30),0)) | L30: =IF(C30="","",IFERROR(SUMIFS('2-Planning Mensuel'!U$5:U$104,'2-Planning Mensuel'!C$5:C$104,C30)*8,0)) | M30: =IF(C30="","",IFERROR(I30-H30,0)) | N30: =IF(OR(C30="",H30=0,H30=""),"",IFERROR(I30/H30,0))
... B104: =IF(C104="","CT-"&TEXT(COUNTA($C$5:C104),"000")) | I104: =IF(C104="","",IFERROR(SUMIFS('6-Releve Heures'!K$5:K$104,'6-Releve Heures'!C$5:C$104,C104),0)) | J104: =IF(C104="","",IFERROR(SUMIFS('7-Heures Supplementaires'!I$5:I$104,'7-Heures Supplementaires'!C$5:C$104,C104),0)) | K104: =IF(C104="","",IFERROR(SUMIFS('8-Heures Nuit'!J$5:J$104,'8-Heures Nuit'!C$5:C$104,C104),0)) | L104: =IF(C104="","",IFERROR(SUMIFS('2-Planning Mensuel'!U$5:U$104,'2-Planning Mensuel'!C$5:C$104,C104)*8,0)) | M104: =IF(C104="","",IFERROR(I104-H104,0)) | N104: =IF(OR(C104="",H104=0,H104=""),"",IFERROR(I104/H104,0))
B105: =IF(C105="","CT-"&TEXT(COUNTA($C$5:C105),"000")) | M105: =IF(I105="","",I105-H105+J105-L105) | N105: =IF(H105="","",IF(H105=0,"",I105/H105))
B106: =IF(C106="","CT-"&TEXT(COUNTA($C$5:C106),"000")) | M106: =IF(I106="","",I106-H106+J106-L106) | N106: =IF(H106="","",IF(H106=0,"",I106/H106))
B107: =IF(C107="","CT-"&TEXT(COUNTA($C$5:C107),"000")) | M107: =IF(I107="","",I107-H107+J107-L107) | N107: =IF(H107="","",IF(H107=0,"",I107/H107))
B108: =IF(C108="","CT-"&TEXT(COUNTA($C$5:C108),"000")) | M108: =IF(I108="","",I108-H108+J108-L108) | N108: =IF(H108="","",IF(H108=0,"",I108/H108))
B109: =IF(C109="","CT-"&TEXT(COUNTA($C$5:C109),"000")) | M109: =IF(I109="","",I109-H109+J109-L109) | N109: =IF(H109="","",IF(H109=0,"",I109/H109))
B111: TOTAL | H111: =SUM(H5:H104) | I111: =SUM(I5:I104) | J111: =SUM(J5:J104) | K111: =SUM(K5:K104) | L111: =SUM(L5:L104) | M111: =SUM(M5:M104)
B113: INDICATEURS (mis a jour automatiquement)
B114: Compteurs actifs | D114: Total h. theoriques | F114: Total h. effectives | H114: Solde global (h)
B115: =COUNTIF(B5:B104,"<>") | D115: =SUM(H5:H104) | F115: =SUM(I5:I104) | H115: =SUM(M5:M104)

Sheet 11-Calendrier Feries
B2: CALENDRIER DES JOURS FERIES & EVENEMENTIELS
B3: TABLEAU DYNAMIQUE — Saisissez dans la prochaine ligne jaune. Les calculs se mettent a jour automatiquement.
B4: N° | C4: Jour Ferie | D4: Date | E4: Jour Semaine | F4: Type | G4: Ferme Hotel | H4: Statut
B5: F-001 | C5: Jour de l'An | D5: 45658 | E5: Mercredi | F5: Ferie officiel | G5: Oui | H5: Valide
B6: F-002 | C6: Fete de la Jeunesse | D6: 45699 | E6: Mardi | F6: Ferie officiel | G6: Non | H6: Valide
B7: F-003 | C7: Fete de la Femme | D7: 45724 | E7: Samedi | F7: Ferie officiel | G7: Non | H7: Valide
B8: F-004 | C8: Fete de Pques | D8: 45767 | E8: Dimanche | F8: Ferie religieux | G8: Non | H8: Valide
B9: F-005 | C9: Fete du Travail | D9: 45778 | E9: Jeudi | F9: Ferie officiel | G9: Oui | H9: Valide
B10: F-006 | C10: Fete Nationale | D10: 45797 | E10: Mardi | F10: Ferie officiel | G10: Oui | H10: Valide
B11: F-007 | C11: Ascension | D11: 45806 | E11: Jeudi | F11: Ferie religieux | G11: Non | H11: Valide
B12: F-008 | C12: Fete de Pentecote | D12: 45816 | E12: Dimanche | F12: Ferie religieux | G12: Non | H12: Valide
B13: F-009 | C13: Fete de l'Independance | D13: 45931 | E13: Mercredi | F13: Ferie officiel | G13: Oui | H13: Valide
B14: F-010 | C14: Noel | D14: 46016 | E14: Jeudi | F14: Ferie religieux | G14: Oui | H14: Valide
B15: =IF(C15="","F-"&TEXT(COUNTA($C$5:C15),"000"))
B16: =IF(C16="","F-"&TEXT(COUNTA($C$5:C16),"000"))
B17: =IF(C17="","F-"&TEXT(COUNTA($C$5:C17),"000"))
B18: =IF(C18="","F-"&TEXT(COUNTA($C$5:C18),"000"))
B19: =IF(C19="","F-"&TEXT(COUNTA($C$5:C19),"000"))
B20: =IF(C20="","F-"&TEXT(COUNTA($C$5:C20),"000"))
B21: =IF(C21="","F-"&TEXT(COUNTA($C$5:C21),"000"))
B22: =IF(C22="","F-"&TEXT(COUNTA($C$5:C22),"000"))
B23: =IF(C23="","F-"&TEXT(COUNTA($C$5:C23),"000"))
B24: =IF(C24="","F-"&TEXT(COUNTA($C$5:C24),"000"))
B25: =IF(C25="","F-"&TEXT(COUNTA($C$5:C25),"000"))
B26: =IF(C26="","F-"&TEXT(COUNTA($C$5:C26),"000"))
... B114: =IF(C114="","F-"&TEXT(COUNTA($C$5:C114),"000"))
B116: INDICATEURS (mis a jour automatiquement)
B117: Total jours feriés | D117: Hotel ferie | F117: Feries officiels | H117: Feries religieux
B118: =COUNTIF(B5:B104,"<>") | D118: =COUNTIF(G5:G104,"Oui") | F118: =COUNTIF(F5:F104,"Ferie officiel") | H118: =COUNTIF(F5:F104,"Ferie religieux")

Sheet 12-Roulement Equipes
B2: ROULEMENT DES EQUIPES
B3: TABLEAU DYNAMIQUE — Saisissez dans la prochaine ligne jaune. Les calculs se mettent a jour automatiquement.
B4: N° Rotation | C4: Matricule | D4: Nom Employe | E4: Departement | F4: Equipe Actuelle | G4: Type Rotation | H4: Date Debut Cycle | I4: Date Fin Cycle | J4: Duree Cycle (j) | K4: Prochaine Equipe | L4: Date Basculement | M4: Statut
B5: ROT-001 | C5: EMP-029 | D5: =IF(C5="","",IFERROR(VLOOKUP(C5,'_Données Employés'!$B$5:$H$18,3,FALSE)&" "&VLOOKUP(C5,'_Données Employés'!$B$5:$H$18,4,FALSE),"")) | E5: =IF(C5="","",IFERROR(VLOOKUP(C5,'_Données Employés'!$B$5:$H$18,5,FALSE),"")) | F5: Equipe A | G5: Horaires rotatifs 3x8 | H5: 45809 | I5: 45838 | J5: 30 | K5: Equipe B | L5: 45839 | M5: Actif
B6: ROT-002 | C6: EMP-028 | D6: =IF(C6="","",IFERROR(VLOOKUP(C6,'_Données Employés'!$B$5:$H$18,3,FALSE)&" "&VLOOKUP(C6,'_Données Employés'!$B$5:$H$18,4,FALSE),"")) | E6: =IF(C6="","",IFERROR(VLOOKUP(C6,'_Données Employés'!$B$5:$H$18,5,FALSE),"")) | F6: Equipe B | G6: Horaires rotatifs 3x8 | H6: 45809 | I6: 45838 | J6: 30 | K6: Equipe C | L6: 45839 | M6: Actif
B7: ROT-003 | C7: EMP-004 | D7: =IF(C7="","",IFERROR(VLOOKUP(C7,'_Données Employés'!$B$5:$H$18,3,FALSE)&" "&VLOOKUP(C7,'_Données Employés'!$B$5:$H$18,4,FALSE),"")) | E7: =IF(C7="","",IFERROR(VLOOKUP(C7,'_Données Employés'!$B$5:$H$18,5,FALSE),"")) | F7: Equipe Jour | G7: Equipe de nuit permanente | H7: 45809 | I7: 45823 | J7: 15 | K7: Equipe Nuit | L7: 45824 | M7: Actif
B8: ROT-004 | C8: EMP-005 | D8: =IF(C8="","",IFERROR(VLOOKUP(C8,'_Données Employés'!$B$5:$H$18,3,FALSE)&" "&VLOOKUP(C8,'_Données Employés'!$B$5:$H$18,4,FALSE),"")) | E8: =IF(C8="","",IFERROR(VLOOKUP(C8,'_Données Employés'!$B$5:$H$18,5,FALSE),"")) | F8: Equipe A | G8: Horaires rotatifs 2x12 | H8: 45809 | I8: 45838 | J8: 30 | K8: Equipe B | L8: 45839 | M8: Actif
B9: ROT-005 | C9: EMP-001 | D9: =IF(C9="","",IFERROR(VLOOKUP(C9,'_Données Employés'!$B$5:$H$18,3,FALSE)&" "&VLOOKUP(C9,'_Données Employés'!$B$5:$H$18,4,FALSE),"")) | E9: =IF(C9="","",IFERROR(VLOOKUP(C9,'_Données Employés'!$B$5:$H$18,5,FALSE),"")) | F9: Equipe Jour | G9: Temps plein 45h | H9: 45658 | J9: 180 | K9: Equipe Jour | L9: 45839 | M9: Actif
B10: =IF(C10="","ROT-"&TEXT(COUNTA($C$5:C10),"000"))
B11: =IF(C11="","ROT-"&TEXT(COUNTA($C$5:C11),"000"))
B12: =IF(C12="","ROT-"&TEXT(COUNTA($C$5:C12),"000"))
B13: =IF(C13="","ROT-"&TEXT(COUNTA($C$5:C13),"000"))
B14: =IF(C14="","ROT-"&TEXT(COUNTA($C$5:C14),"000"))
B15: =IF(C15="","ROT-"&TEXT(COUNTA($C$5:C15),"000"))
B16: =IF(C16="","ROT-"&TEXT(COUNTA($C$5:C16),"000"))
B17: =IF(C17="","ROT-"&TEXT(COUNTA($C$5:C17),"000"))
B18: =IF(C18="","ROT-"&TEXT(COUNTA($C$5:C18),"000"))
B19: =IF(C19="","ROT-"&TEXT(COUNTA($C$5:C19),"000"))
B20: =IF(C20="","ROT-"&TEXT(COUNTA($C$5:C20),"000"))
B21: =IF(C21="","ROT-"&TEXT(COUNTA($C$5:C21),"000"))
... B109: =IF(C109="","ROT-"&TEXT(COUNTA($C$5:C109),"000"))
B111: INDICATEURS (mis a jour automatiquement)
B112: Employes en rotation | D112: Rotations actives | F112: Equipe A | H112: Equipe Nuit
B113: =COUNTIF(B5:B104,"<>") | D113: =COUNTIF(M5:M104,"Actif") | F113: =COUNTIF(F5:F104,"Equipe A") | H113: =COUNTIF(K5:K104,"Equipe Nuit")

Sheet 13-Conges Collectif
B2: PLANNING DES CONGES COLLECTIFS
B3: TABLEAU DYNAMIQUE — Saisissez dans la prochaine ligne jaune. Les calculs se mettent a jour automatiquement.
B4: N° Collectif | C4: Type Conge | D4: Date Debut | E4: Date Fin | F4: Nb Jours | G4: Departements Concernes | H4: Nb Employes | I4: Services Maintenus | J4: Motif | K4: Statut
B5: CC-001 | C5: Conges de Noel | D5: 46015 | E5: 46022 | F5: 6 | G5: Tous sauf Securite | H5: 45 | I5: Securite, Room Service | J5: Fermeture annuelle | K5: Planifie
B6: CC-002 | C6: Pont | D6: 45796 | E6: 45797 | F6: 1 | G6: Tous sauf Reception et Securite | H6: 38 | I6: Reception, Securite, Room Service | J6: Fete Nationale | K6: Planifie
B7: CC-003 | C7: Jour ferie | D7: 45658 | E7: 45658 | F7: 1 | G7: Tous sauf Securite et Reception | H7: 40 | I7: Securite, Reception, Room Service | J7: Jour de l'An | K7: Termine
B8: CC-004 | C8: Fermeture exceptionnelle | D8: 45880 | E8: 45884 | F8: 3 | G8: Production | H8: 12 | I8: Aucun | J8: Maintenance usine | K8: Planifie
B9: CC-005 | C9: Conges de Paques | D9: 45765 | E9: 45768 | F9: 2 | G9: Tous sauf Reception, Securite, Cuisine | H9: 30 | I9: Reception, Securite, Restaurant, Room Service | J9: Feries religieux | K9: Termine
B10: =IF(C10="","CC-"&TEXT(COUNTA($C$5:C10),"000")) | F10: =IF(D10="","",E10-D10+1)
B11: =IF(C11="","CC-"&TEXT(COUNTA($C$5:C11),"000")) | F11: =IF(D11="","",E11-D11+1)
B12: =IF(C12="","CC-"&TEXT(COUNTA($C$5:C12),"000")) | F12: =IF(D12="","",E12-D12+1)
B13: =IF(C13="","CC-"&TEXT(COUNTA($C$5:C13),"000")) | F13: =IF(D13="","",E13-D13+1)
B14: =IF(C14="","CC-"&TEXT(COUNTA($C$5:C14),"000")) | F14: =IF(D14="","",E14-D14+1)
B15: =IF(C15="","CC-"&TEXT(COUNTA($C$5:C15),"000")) | F15: =IF(D15="","",E15-D15+1)
B16: =IF(C16="","CC-"&TEXT(COUNTA($C$5:C16),"000")) | F16: =IF(D16="","",E16-D16+1)
B17: =IF(C17="","CC-"&TEXT(COUNTA($C$5:C17),"000")) | F17: =IF(D17="","",E17-D17+1)
B18: =IF(C18="","CC-"&TEXT(COUNTA($C$5:C18),"000")) | F18: =IF(D18="","",E18-D18+1)
B19: =IF(C19="","CC-"&TEXT(COUNTA($C$5:C19),"000")) | F19: =IF(D19="","",E19-D19+1)
B20: =IF(C20="","CC-"&TEXT(COUNTA($C$5:C20),"000")) | F20: =IF(D20="","",E20-D20+1)
B21: =IF(C21="","CC-"&TEXT(COUNTA($C$5:C21),"000")) | F21: =IF(D21="","",E21-D21+1)
... B109: =IF(C109="","CC-"&TEXT(COUNTA($C$5:C109),"000")) | F109: =IF(D109="","",E109-D109+1)
B111: TOTAL | F111: =SUM(F5:F104) | H111: =SUM(H5:H104)
B113: INDICATEURS (mis a jour automatiquement)
B114: Total conges collectifs | D114: Jours de fermeture | F114: Employes concernes (max) | H114: Planifies
B115: =COUNTIF(B5:B104,"<>") | D115: =SUM(F5:F104) | F115: =MAX(H5:H104) | H115: =COUNTIF(K5:K104,"Planifie")

Sheet 14-Tableau Service
B2: TABLEAU D'AFFECTATION PAR SERVICE
B3: TABLEAU DYNAMIQUE — Saisissez dans la prochaine ligne jaune. Les calculs se mettent a jour automatiquement.
B4: N° Affectation | C4: Matricule | D4: Nom Employe | E4: Service | F4: Fonction Service | G4: Equipe | H4: Date Debut | I4: Date Fin | J4: Horaire | K4: Jours/Semaine | L4: Statut | M4: Observations
B5: SVC-001 | C5: EMP-004 | D5: =IF(C5="","",IFERROR(VLOOKUP(C5,'_Données Employés'!$B$5:$H$18,3,FALSE)&" "&VLOOKUP(C5,'_Données Employés'!$B$5:$H$18,4,FALSE),"")) | E5: =IF(C5="","",IFERROR(VLOOKUP(C5,'_Données Employés'!$B$5:$H$18,5,FALSE),"")) | F5: =IF(C5="","",IFERROR(VLOOKUP(C5,'_Données Employés'!$B$5:$H$18,6,FALSE),"")) | G5: Equipe Jour | H5: 45658 | J5: 06h-14h | K5: 5 | L5: Actif | M5: Pont management
B6: SVC-002 | C6: EMP-028 | D6: =IF(C6="","",IFERROR(VLOOKUP(C6,'_Données Employés'!$B$5:$H$18,3,FALSE)&" "&VLOOKUP(C6,'_Données Employés'!$B$5:$H$18,4,FALSE),"")) | E6: =IF(C6="","",IFERROR(VLOOKUP(C6,'_Données Employés'!$B$5:$H$18,5,FALSE),"")) | F6: =IF(C6="","",IFERROR(VLOOKUP(C6,'_Données Employés'!$B$5:$H$18,6,FALSE),"")) | G6: Equipe A | H6: 45717 | J6: 07h-15h | K6: 6 | L6: Actif
B7: SVC-003 | C7: EMP-005 | D7: =IF(C7="","",IFERROR(VLOOKUP(C7,'_Données Employés'!$B$5:$H$18,3,FALSE)&" "&VLOOKUP(C7,'_Données Employés'!$B$5:$H$18,4,FALSE),"")) | E7: =IF(C7="","",IFERROR(VLOOKUP(C7,'_Données Employés'!$B$5:$H$18,5,FALSE),"")) | F7: =IF(C7="","",IFERROR(VLOOKUP(C7,'_Données Employés'!$B$5:$H$18,6,FALSE),"")) | G7: Equipe A | H7: 45748 | J7: 06h-14h | K7: 6 | L7: Actif | M7: Spécialité grillades
B8: SVC-004 | C8: EMP-001 | D8: =IF(C8="","",IFERROR(VLOOKUP(C8,'_Données Employés'!$B$5:$H$18,3,FALSE)&" "&VLOOKUP(C8,'_Données Employés'!$B$5:$H$18,4,FALSE),"")) | E8: =IF(C8="","",IFERROR(VLOOKUP(C8,'_Données Employés'!$B$5:$H$18,5,FALSE),"")) | F8: =IF(C8="","",IFERROR(VLOOKUP(C8,'_Données Employés'!$B$5:$H$18,6,FALSE),"")) | G8: Equipe Jour | H8: 45809 | J8: 08h-17h | K8: 5 | L8: Actif | M8: Formation en cours
B9: SVC-005 | C9: EMP-029 | D9: =IF(C9="","",IFERROR(VLOOKUP(C9,'_Données Employés'!$B$5:$H$18,3,FALSE)&" "&VLOOKUP(C9,'_Données Employés'!$B$5:$H$18,4,FALSE),"")) | E9: =IF(C9="","",IFERROR(VLOOKUP(C9,'_Données Employés'!$B$5:$H$18,5,FALSE),"")) | F9: =IF(C9="","",IFERROR(VLOOKUP(C9,'_Données Employés'!$B$5:$H$18,6,FALSE),"")) | G9: Equipe Nuit | H9: 45292 | J9: 22h-06h | K9: 5 | L9: Actif | M9: Chef sécurité
B10: =IF(C10="","SVC-"&TEXT(COUNTA($C$5:C10),"000"))
B11: =IF(C11="","SVC-"&TEXT(COUNTA($C$5:C11),"000"))
B12: =IF(C12="","SVC-"&TEXT(COUNTA($C$5:C12),"000"))
B13: =IF(C13="","SVC-"&TEXT(COUNTA($C$5:C13),"000"))
B14: =IF(C14="","SVC-"&TEXT(COUNTA($C$5:C14),"000"))
B15: =IF(C15="","SVC-"&TEXT(COUNTA($C$5:C15),"000"))
B16: =IF(C16="","SVC-"&TEXT(COUNTA($C$5:C16),"000"))
B17: =IF(C17="","SVC-"&TEXT(COUNTA($C$5:C17),"000"))
B18: =IF(C18="","SVC-"&TEXT(COUNTA($C$5:C18),"000"))
B19: =IF(C19="","SVC-"&TEXT(COUNTA($C$5:C19),"000"))
B20: =IF(C20="","SVC-"&TEXT(COUNTA($C$5:C20),"000"))
B21: =IF(C21="","SVC-"&TEXT(COUNTA($C$5:C21),"000"))
... B109: =IF(C109="","SVC-"&TEXT(COUNTA($C$5:C109),"000"))
B111: INDICATEURS (mis a jour automatiquement)
B112: Affectations actives | D112: Services couverts | F112: Equipe Nuit | H112: Equipe Jour
B113: =COUNTIF(B5:B104,"<>") | D113: =COUNTA(E5:E104)-SUMPRODUCT(--(COUNTIF(E5:E104,E5:E104)>1)) | F113: =COUNTIF(G5:G104,"Equipe Nuit") | H113: =COUNTIF(G5:G104,"Equipe Jour")

Sheet 15-Regimes Horaires
B2: REGIMES HORAIRES — CONFIGURATION
B3: TABLEAU DYNAMIQUE — Saisissez dans la prochaine ligne jaune. Les calculs se mettent a jour automatiquement.
B4: N° Regime | C4: Designation | D4: Type Regime | E4: Heures Hebdo | F4: Heures Mensuelles | G4: Horaire Type | H4: Pause Dejeuner | I4: Jours/Semaine | J4: Nb Postes | K4: Majoration Nuit | L4: Statut
B5: REG-001 | C5: Standard jour | D5: Temps plein 40h | E5: 40 | F5: 173.3 | G5: 08h-17h | H5: 1h (12h-13h) | I5: 5 | J5: 25 | K5: 25% | L5: Actif
B6: REG-002 | C6: Standard etendu | D6: Temps plein 45h | E6: 45 | F6: 195 | G6: 08h-18h | H6: 1h (12h-13h) | I6: 5 | J6: 15 | K6: 25% | L6: Actif
B7: REG-003 | C7: Mi-temps 20h | D7: Temps partiel 20h | E7: 20 | F7: 86.7 | G7: 08h-12h | H7: 0h | I7: 5 | J7: 8 | K7: 0% | L7: Actif
B8: REG-004 | C8: Mi-temps 25h | D8: Temps partiel 25h | E8: 25 | F8: 108.3 | G8: 08h-13h | H8: 0.5h (12h-12h30) | I8: 5 | J8: 5 | K8: 0% | L8: Actif
B9: REG-005 | C9: Rotation 3x8 | D9: Horaires rotatifs 3x8 | E9: 40 | F9: 173.3 | G9: 06-14/14-22/22-06 | H9: 0.5h | I9: 5 | J9: 30 | K9: 50% | L9: Actif
B10: REG-006 | C10: Rotation 2x12 | D10: Horaires rotatifs 2x12 | E10: 42 | F10: 182 | G10: 06-18/18-06 | H10: 1h | I10: 3.5 | J10: 12 | K10: 50% | L10: Actif
B11: REG-007 | C11: Nuit permanente | D11: Equipe de nuit permanente | E11: 35 | F11: 151.7 | G11: 22h-06h | H11: 0h | I11: 5 | J11: 10 | K11: 50% | L11: Actif
B12: REG-008 | C12: Forfait jour 173h | D12: Forfait jour 173h/mois | E12: 0 | F12: 173 | G12: Libre (forfait) | H12: 1h | I12: 5 | J12: 10 | K12: 0% | L12: Actif
B13: =IF(C13="","REG-"&TEXT(COUNTA($C$5:C13),"000"))
B14: =IF(C14="","REG-"&TEXT(COUNTA($C$5:C14),"000"))
B15: =IF(C15="","REG-"&TEXT(COUNTA($C$5:C15),"000"))
B16: =IF(C16="","REG-"&TEXT(COUNTA($C$5:C16),"000"))
B17: =IF(C17="","REG-"&TEXT(COUNTA($C$5:C17),"000"))
B18: =IF(C18="","REG-"&TEXT(COUNTA($C$5:C18),"000"))
B19: =IF(C19="","REG-"&TEXT(COUNTA($C$5:C19),"000"))
B20: =IF(C20="","REG-"&TEXT(COUNTA($C$5:C20),"000"))
B21: =IF(C21="","REG-"&TEXT(COUNTA($C$5:C21),"000"))
B22: =IF(C22="","REG-"&TEXT(COUNTA($C$5:C22),"000"))
B23: =IF(C23="","REG-"&TEXT(COUNTA($C$5:C23),"000"))
B24: =IF(C24="","REG-"&TEXT(COUNTA($C$5:C24),"000"))
... B112: =IF(C112="","REG-"&TEXT(COUNTA($C$5:C112),"000"))
B114: TOTAL | J114: =SUM(J5:J104)
B116: INDICATEURS (mis a jour automatiquement)
B117: Regimes configures | D117: Total postes couverts | F117: Regimes actifs | H117: Temps partiel
B118: =COUNTIF(B5:B104,"<>") | D118: =SUM(J5:J104) | F118: =COUNTIF(L5:L104,"Actif") | H118: =COUNTIF(D5:D104,"Temps partiel 20h")+COUNTIF(D5:D104,"Temps partiel 25h")+COUNTIF(D5:D104,"Temps partiel 30h")

Sheet 16-Ecarts Pointage
B2: ECARTS DE POINTAGE — ANOMALIES DETECTEES
B3: TABLEAU DYNAMIQUE — Saisissez dans la prochaine ligne jaune. Les calculs se mettent a jour automatiquement.
B4: N° Ecart | C4: Matricule | D4: Nom Employe | E4: Departement | F4: Date | G4: Type Ecart | H4: Description | I4: Heure Constatee | J4: Duree Ecart (min) | K4: Justification | L4: Date Traitement | M4: Statut
B5: EC-001 | C5: EMP-005 | D5: =IF(C5="","",IFERROR(VLOOKUP(C5,'_Données Employés'!$B$5:$H$18,3,FALSE)&" "&VLOOKUP(C5,'_Données Employés'!$B$5:$H$18,4,FALSE),"")) | E5: =IF(C5="","",IFERROR(VLOOKUP(C5,'_Données Employés'!$B$5:$H$18,5,FALSE),"")) | F5: 45810 | G5: Absence non justifiee | H5: Aucun badgeage constate | I5: 08h00 | J5: 480 | M5: En attente
B6: EC-002 | C6: EMP-002 | D6: =IF(C6="","",IFERROR(VLOOKUP(C6,'_Données Employés'!$B$5:$H$18,3,FALSE)&" "&VLOOKUP(C6,'_Données Employés'!$B$5:$H$18,4,FALSE),"")) | E6: =IF(C6="","",IFERROR(VLOOKUP(C6,'_Données Employés'!$B$5:$H$18,5,FALSE),"")) | F6: 45810 | G6: Retard arrivee | H6: Arrivee a 08h15 au lieu de 08h00 | I6: 08h15 | J6: 15 | K6: Retard transport | L6: 45811 | M6: Justifie
B7: EC-003 | C7: EMP-003 | D7: =IF(C7="","",IFERROR(VLOOKUP(C7,'_Données Employés'!$B$5:$H$18,3,FALSE)&" "&VLOOKUP(C7,'_Données Employés'!$B$5:$H$18,4,FALSE),"")) | E7: =IF(C7="","",IFERROR(VLOOKUP(C7,'_Données Employés'!$B$5:$H$18,5,FALSE),"")) | F7: 45812 | G7: Depart anticipe | H7: Depart a 16h00 pour rdv medical | I7: 16h00 | J7: 60 | K7: Certificat medical fourni | L7: 45813 | M7: Traite
B8: EC-004 | C8: EMP-004 | D8: =IF(C8="","",IFERROR(VLOOKUP(C8,'_Données Employés'!$B$5:$H$18,3,FALSE)&" "&VLOOKUP(C8,'_Données Employés'!$B$5:$H$18,4,FALSE),"")) | E8: =IF(C8="","",IFERROR(VLOOKUP(C8,'_Données Employés'!$B$5:$H$18,5,FALSE),"")) | F8: 45815 | G8: Heure supp non validee | H8: Heures week-end non autorisees par N+1 | I8: 08h00 | J8: 480 | K8: Autorisation a posteriori | M8: En attente
B9: EC-005 | C9: EMP-001 | D9: =IF(C9="","",IFERROR(VLOOKUP(C9,'_Données Employés'!$B$5:$H$18,3,FALSE)&" "&VLOOKUP(C9,'_Données Employés'!$B$5:$H$18,4,FALSE),"")) | E9: =IF(C9="","",IFERROR(VLOOKUP(C9,'_Données Employés'!$B$5:$H$18,5,FALSE),"")) | F9: 45817 | G9: Oubli badgeage | H9: Badgeage matin et midi manquants | I9: 08h00 | J9: 540 | K9: Pointage manuel confirme par N+1 | L9: 45818 | M9: Traite
B10: =IF(C10="","EC-"&TEXT(COUNTA($C$5:C10),"000"))
B11: =IF(C11="","EC-"&TEXT(COUNTA($C$5:C11),"000"))
B12: =IF(C12="","EC-"&TEXT(COUNTA($C$5:C12),"000"))
B13: =IF(C13="","EC-"&TEXT(COUNTA($C$5:C13),"000"))
B14: =IF(C14="","EC-"&TEXT(COUNTA($C$5:C14),"000"))
B15: =IF(C15="","EC-"&TEXT(COUNTA($C$5:C15),"000"))
B16: =IF(C16="","EC-"&TEXT(COUNTA($C$5:C16),"000"))
B17: =IF(C17="","EC-"&TEXT(COUNTA($C$5:C17),"000"))
B18: =IF(C18="","EC-"&TEXT(COUNTA($C$5:C18),"000"))
B19: =IF(C19="","EC-"&TEXT(COUNTA($C$5:C19),"000"))
B20: =IF(C20="","EC-"&TEXT(COUNTA($C$5:C20),"000"))
B21: =IF(C21="","EC-"&TEXT(COUNTA($C$5:C21),"000"))
... B109: =IF(C109="","EC-"&TEXT(COUNTA($C$5:C109),"000"))
B111: INDICATEURS (mis a jour automatiquement)
B112: Total ecarts | D112: Ecarts en attente | F112: Ecarts justifies | H112: Non justifies
B113: =COUNTIF(B5:B104,"<>") | D113: =COUNTIF(M5:M104,"En attente") | F113: =COUNTIF(M5:M104,"Justifie") | H113: =COUNTIF(M5:M104,"Non justifie")

Sheet 17-Bilan Mensuel Temps
B2: BILAN MENSUEL DU TEMPS DE TRAVAIL
B3: TABLEAU DYNAMIQUE — Saisissez dans la prochaine ligne jaune. Les calculs se mettent a jour automatiquement.
B4: N° Bilan | C4: Departement | D4: Mois | E4: Annee | F4: Effectif | G4: Heures Theoriques | H4: Heures Effectives | I4: Heures Supp | J4: Heures Nuit | K4: Heures WE/Feries | L4: Absences (j) | M4: Retards | N4: Taux Presence | O4: Ecart Global (h) | P4: Cout Supp (FCFA) | Q4: Statut
B5: BMT-001 | C5: Ressources Humaines | D5: Juin | E5: 2025 | F5: =IF(C5="","",IFERROR(COUNTIFS('10-Compteurs Temps'!E$5:E$104,C5,'10-Compteurs Temps'!F$5:F$104,D5,'10-Compteurs Temps'!G$5:G$104,E5),0)) | G5: =IF(C5="","",IFERROR(SUMIFS('10-Compteurs Temps'!H$5:H$104,'10-Compteurs Temps'!E$5:E$104,C5,'10-Compteurs Temps'!F$5:F$104,D5,'10-Compteurs Temps'!G$5:G$104,E5),0)) | H5: =IF(C5="","",IFERROR(SUMIFS('10-Compteurs Temps'!I$5:I$104,'10-Compteurs Temps'!E$5:E$104,C5,'10-Compteurs Temps'!F$5:F$104,D5,'10-Compteurs Temps'!G$5:G$104,E5),0)) | I5: =IF(C5="","",IFERROR(SUMIFS('10-Compteurs Temps'!J$5:J$104,'10-Compteurs Temps'!E$5:E$104,C5,'10-Compteurs Temps'!F$5:F$104,D5,'10-Compteurs Temps'!G$5:G$104,E5),0)) | J5: =IF(C5="","",IFERROR(SUMIFS('10-Compteurs Temps'!K$5:K$104,'10-Compteurs Temps'!E$5:E$104,C5,'10-Compteurs Temps'!F$5:F$104,D5,'10-Compteurs Temps'!G$5:G$104,E5),0)) | K5: =IF(C5="","",IFERROR(SUMIFS('9-Heures WE & Feries'!I$5:I$104,'9-Heures WE & Feries'!E$5:E$104,C5),0)) | L5: =IF(C5="","",IFERROR(SUMIFS('10-Compteurs Temps'!L$5:L$104,'10-Compteurs Temps'!E$5:E$104,C5,'10-Compteurs Temps'!F$5:F$104,D5,'10-Compteurs Temps'!G$5:G$104,E5)/8,0)) | M5: 3 | N5: =IF(OR(C5="",G5=0,G5=""),"",IFERROR(H5/G5,0)) | O5: =IF(C5="","",IFERROR(H5-G5,0)) | P5: =IF(C5="","",IFERROR(SUMIFS('7-Heures Supplementaires'!M$5:M$104,'7-Heures Supplementaires'!E$5:E$104,C5),0)) | Q5: Valide
B6: BMT-002 | C6: Informatique | D6: Juin | E6: 2025 | F6: =IF(C6="","",IFERROR(COUNTIFS('10-Compteurs Temps'!E$5:E$104,C6,'10-Compteurs Temps'!F$5:F$104,D6,'10-Compteurs Temps'!G$5:G$104,E6),0)) | G6: =IF(C6="","",IFERROR(SUMIFS('10-Compteurs Temps'!H$5:H$104,'10-Compteurs Temps'!E$5:E$104,C6,'10-Compteurs Temps'!F$5:F$104,D6,'10-Compteurs Temps'!G$5:G$104,E6),0)) | H6: =IF(C6="","",IFERROR(SUMIFS('10-Compteurs Temps'!I$5:I$104,'10-Compteurs Temps'!E$5:E$104,C6,'10-Compteurs Temps'!F$5:F$104,D6,'10-Compteurs Temps'!G$5:G$104,E6),0)) | I6: =IF(C6="","",IFERROR(SUMIFS('10-Compteurs Temps'!J$5:J$104,'10-Compteurs Temps'!E$5:E$104,C6,'10-Compteurs Temps'!F$5:F$104,D6,'10-Compteurs Temps'!G$5:G$104,E6),0)) | J6: =IF(C6="","",IFERROR(SUMIFS('10-Compteurs Temps'!K$5:K$104,'10-Compteurs Temps'!E$5:E$104,C6,'10-Compteurs Temps'!F$5:F$104,D6,'10-Compteurs Temps'!G$5:G$104,E6),0)) | K6: =IF(C6="","",IFERROR(SUMIFS('9-Heures WE & Feries'!I$5:I$104,'9-Heures WE & Feries'!E$5:E$104,C6),0)) | L6: =IF(C6="","",IFERROR(SUMIFS('10-Compteurs Temps'!L$5:L$104,'10-Compteurs Temps'!E$5:E$104,C6,'10-Compteurs Temps'!F$5:F$104,D6,'10-Compteurs Temps'!G$5:G$104,E6)/8,0)) | M6: 2 | N6: =IF(OR(C6="",G6=0,G6=""),"",IFERROR(H6/G6,0)) | O6: =IF(C6="","",IFERROR(H6-G6,0)) | P6: =IF(C6="","",IFERROR(SUMIFS('7-Heures Supplementaires'!M$5:M$104,'7-Heures Supplementaires'!E$5:E$104,C6),0)) | Q6: Valide
B7: BMT-003 | C7: Finance & Comptabilite | D7: Juin | E7: 2025 | F7: =IF(C7="","",IFERROR(COUNTIFS('10-Compteurs Temps'!E$5:E$104,C7,'10-Compteurs Temps'!F$5:F$104,D7,'10-Compteurs Temps'!G$5:G$104,E7),0)) | G7: =IF(C7="","",IFERROR(SUMIFS('10-Compteurs Temps'!H$5:H$104,'10-Compteurs Temps'!E$5:E$104,C7,'10-Compteurs Temps'!F$5:F$104,D7,'10-Compteurs Temps'!G$5:G$104,E7),0)) | H7: =IF(C7="","",IFERROR(SUMIFS('10-Compteurs Temps'!I$5:I$104,'10-Compteurs Temps'!E$5:E$104,C7,'10-Compteurs Temps'!F$5:F$104,D7,'10-Compteurs Temps'!G$5:G$104,E7),0)) | I7: =IF(C7="","",IFERROR(SUMIFS('10-Compteurs Temps'!J$5:J$104,'10-Compteurs Temps'!E$5:E$104,C7,'10-Compteurs Temps'!F$5:F$104,D7,'10-Compteurs Temps'!G$5:G$104,E7),0)) | J7: =IF(C7="","",IFERROR(SUMIFS('10-Compteurs Temps'!K$5:K$104,'10-Compteurs Temps'!E$5:E$104,C7,'10-Compteurs Temps'!F$5:F$104,D7,'10-Compteurs Temps'!G$5:G$104,E7),0)) | K7: =IF(C7="","",IFERROR(SUMIFS('9-Heures WE & Feries'!I$5:I$104,'9-Heures WE & Feries'!E$5:E$104,C7),0)) | L7: =IF(C7="","",IFERROR(SUMIFS('10-Compteurs Temps'!L$5:L$104,'10-Compteurs Temps'!E$5:E$104,C7,'10-Compteurs Temps'!F$5:F$104,D7,'10-Compteurs Temps'!G$5:G$104,E7)/8,0)) | M7: 1 | N7: =IF(OR(C7="",G7=0,G7=""),"",IFERROR(H7/G7,0)) | O7: =IF(C7="","",IFERROR(H7-G7,0)) | P7: =IF(C7="","",IFERROR(SUMIFS('7-Heures Supplementaires'!M$5:M$104,'7-Heures Supplementaires'!E$5:E$104,C7),0)) | Q7: Valide
B8: BMT-004 | C8: Reception & Front Office | D8: Juin | E8: 2025 | F8: =IF(C8="","",IFERROR(COUNTIFS('10-Compteurs Temps'!E$5:E$104,C8,'10-Compteurs Temps'!F$5:F$104,D8,'10-Compteurs Temps'!G$5:G$104,E8),0)) | G8: =IF(C8="","",IFERROR(SUMIFS('10-Compteurs Temps'!H$5:H$104,'10-Compteurs Temps'!E$5:E$104,C8,'10-Compteurs Temps'!F$5:F$104,D8,'10-Compteurs Temps'!G$5:G$104,E8),0)) | H8: =IF(C8="","",IFERROR(SUMIFS('10-Compteurs Temps'!I$5:I$104,'10-Compteurs Temps'!E$5:E$104,C8,'10-Compteurs Temps'!F$5:F$104,D8,'10-Compteurs Temps'!G$5:G$104,E8),0)) | I8: =IF(C8="","",IFERROR(SUMIFS('10-Compteurs Temps'!J$5:J$104,'10-Compteurs Temps'!E$5:E$104,C8,'10-Compteurs Temps'!F$5:F$104,D8,'10-Compteurs Temps'!G$5:G$104,E8),0)) | J8: =IF(C8="","",IFERROR(SUMIFS('10-Compteurs Temps'!K$5:K$104,'10-Compteurs Temps'!E$5:E$104,C8,'10-Compteurs Temps'!F$5:F$104,D8,'10-Compteurs Temps'!G$5:G$104,E8),0)) | K8: =IF(C8="","",IFERROR(SUMIFS('9-Heures WE & Feries'!I$5:I$104,'9-Heures WE & Feries'!E$5:E$104,C8),0)) | L8: =IF(C8="","",IFERROR(SUMIFS('10-Compteurs Temps'!L$5:L$104,'10-Compteurs Temps'!E$5:E$104,C8,'10-Compteurs Temps'!F$5:F$104,D8,'10-Compteurs Temps'!G$5:G$104,E8)/8,0)) | M8: 5 | N8: =IF(OR(C8="",G8=0,G8=""),"",IFERROR(H8/G8,0)) | O8: =IF(C8="","",IFERROR(H8-G8,0)) | P8: =IF(C8="","",IFERROR(SUMIFS('7-Heures Supplementaires'!M$5:M$104,'7-Heures Supplementaires'!E$5:E$104,C8),0)) | Q8: Valide
B9: BMT-005 | C9: Cuisine & Restauration | D9: Juin | E9: 2025 | F9: =IF(C9="","",IFERROR(COUNTIFS('10-Compteurs Temps'!E$5:E$104,C9,'10-Compteurs Temps'!F$5:F$104,D9,'10-Compteurs Temps'!G$5:G$104,E9),0)) | G9: =IF(C9="","",IFERROR(SUMIFS('10-Compteurs Temps'!H$5:H$104,'10-Compteurs Temps'!E$5:E$104,C9,'10-Compteurs Temps'!F$5:F$104,D9,'10-Compteurs Temps'!G$5:G$104,E9),0)) | H9: =IF(C9="","",IFERROR(SUMIFS('10-Compteurs Temps'!I$5:I$104,'10-Compteurs Temps'!E$5:E$104,C9,'10-Compteurs Temps'!F$5:F$104,D9,'10-Compteurs Temps'!G$5:G$104,E9),0)) | I9: =IF(C9="","",IFERROR(SUMIFS('10-Compteurs Temps'!J$5:J$104,'10-Compteurs Temps'!E$5:E$104,C9,'10-Compteurs Temps'!F$5:F$104,D9,'10-Compteurs Temps'!G$5:G$104,E9),0)) | J9: =IF(C9="","",IFERROR(SUMIFS('10-Compteurs Temps'!K$5:K$104,'10-Compteurs Temps'!E$5:E$104,C9,'10-Compteurs Temps'!F$5:F$104,D9,'10-Compteurs Temps'!G$5:G$104,E9),0)) | K9: =IF(C9="","",IFERROR(SUMIFS('9-Heures WE & Feries'!I$5:I$104,'9-Heures WE & Feries'!E$5:E$104,C9),0)) | L9: =IF(C9="","",IFERROR(SUMIFS('10-Compteurs Temps'!L$5:L$104,'10-Compteurs Temps'!E$5:E$104,C9,'10-Compteurs Temps'!F$5:F$104,D9,'10-Compteurs Temps'!G$5:G$104,E9)/8,0)) | M9: 8 | N9: =IF(OR(C9="",G9=0,G9=""),"",IFERROR(H9/G9,0)) | O9: =IF(C9="","",IFERROR(H9-G9,0)) | P9: =IF(C9="","",IFERROR(SUMIFS('7-Heures Supplementaires'!M$5:M$104,'7-Heures Supplementaires'!E$5:E$104,C9),0)) | Q9: Valide
B10: =IF(C10="","BMT-"&TEXT(COUNTA($C$5:C10),"000")) | F10: =IF(C10="","",IFERROR(COUNTIFS('10-Compteurs Temps'!E$5:E$104,C10,'10-Compteurs Temps'!F$5:F$104,D10,'10-Compteurs Temps'!G$5:G$104,E10),0)) | G10: =IF(C10="","",IFERROR(SUMIFS('10-Compteurs Temps'!H$5:H$104,'10-Compteurs Temps'!E$5:E$104,C10,'10-Compteurs Temps'!F$5:F$104,D10,'10-Compteurs Temps'!G$5:G$104,E10),0)) | H10: =IF(C10="","",IFERROR(SUMIFS('10-Compteurs Temps'!I$5:I$104,'10-Compteurs Temps'!E$5:E$104,C10,'10-Compteurs Temps'!F$5:F$104,D10,'10-Compteurs Temps'!G$5:G$104,E10),0)) | I10: =IF(C10="","",IFERROR(SUMIFS('10-Compteurs Temps'!J$5:J$104,'10-Compteurs Temps'!E$5:E$104,C10,'10-Compteurs Temps'!F$5:F$104,D10,'10-Compteurs Temps'!G$5:G$104,E10),0)) | J10: =IF(C10="","",IFERROR(SUMIFS('10-Compteurs Temps'!K$5:K$104,'10-Compteurs Temps'!E$5:E$104,C10,'10-Compteurs Temps'!F$5:F$104,D10,'10-Compteurs Temps'!G$5:G$104,E10),0)) | K10: =IF(C10="","",IFERROR(SUMIFS('9-Heures WE & Feries'!I$5:I$104,'9-Heures WE & Feries'!E$5:E$104,C10),0)) | L10: =IF(C10="","",IFERROR(SUMIFS('10-Compteurs Temps'!L$5:L$104,'10-Compteurs Temps'!E$5:E$104,C10,'10-Compteurs Temps'!F$5:F$104,D10,'10-Compteurs Temps'!G$5:G$104,E10)/8,0)) | N10: =IF(OR(C10="",G10=0,G10=""),"",IFERROR(H10/G10,0)) | O10: =IF(C10="","",IFERROR(H10-G10,0)) | P10: =IF(C10="","",IFERROR(SUMIFS('7-Heures Supplementaires'!M$5:M$104,'7-Heures Supplementaires'!E$5:E$104,C10),0))
B11: =IF(C11="","BMT-"&TEXT(COUNTA($C$5:C11),"000")) | F11: =IF(C11="","",IFERROR(COUNTIFS('10-Compteurs Temps'!E$5:E$104,C11,'10-Compteurs Temps'!F$5:F$104,D11,'10-Compteurs Temps'!G$5:G$104,E11),0)) | G11: =IF(C11="","",IFERROR(SUMIFS('10-Compteurs Temps'!H$5:H$104,'10-Compteurs Temps'!E$5:E$104,C11,'10-Compteurs Temps'!F$5:F$104,D11,'10-Compteurs Temps'!G$5:G$104,E11),0)) | H11: =IF(C11="","",IFERROR(SUMIFS('10-Compteurs Temps'!I$5:I$104,'10-Compteurs Temps'!E$5:E$104,C11,'10-Compteurs Temps'!F$5:F$104,D11,'10-Compteurs Temps'!G$5:G$104,E11),0)) | I11: =IF(C11="","",IFERROR(SUMIFS('10-Compteurs Temps'!J$5:J$104,'10-Compteurs Temps'!E$5:E$104,C11,'10-Compteurs Temps'!F$5:F$104,D11,'10-Compteurs Temps'!G$5:G$104,E11),0)) | J11: =IF(C11="","",IFERROR(SUMIFS('10-Compteurs Temps'!K$5:K$104,'10-Compteurs Temps'!E$5:E$104,C11,'10-Compteurs Temps'!F$5:F$104,D11,'10-Compteurs Temps'!G$5:G$104,E11),0)) | K11: =IF(C11="","",IFERROR(SUMIFS('9-Heures WE & Feries'!I$5:I$104,'9-Heures WE & Feries'!E$5:E$104,C11),0)) | L11: =IF(C11="","",IFERROR(SUMIFS('10-Compteurs Temps'!L$5:L$104,'10-Compteurs Temps'!E$5:E$104,C11,'10-Compteurs Temps'!F$5:F$104,D11,'10-Compteurs Temps'!G$5:G$104,E11)/8,0)) | N11: =IF(OR(C11="",G11=0,G11=""),"",IFERROR(H11/G11,0)) | O11: =IF(C11="","",IFERROR(H11-G11,0)) | P11: =IF(C11="","",IFERROR(SUMIFS('7-Heures Supplementaires'!M$5:M$104,'7-Heures Supplementaires'!E$5:E$104,C11),0))
B12: =IF(C12="","BMT-"&TEXT(COUNTA($C$5:C12),"000")) | F12: =IF(C12="","",IFERROR(COUNTIFS('10-Compteurs Temps'!E$5:E$104,C12,'10-Compteurs Temps'!F$5:F$104,D12,'10-Compteurs Temps'!G$5:G$104,E12),0)) | G12: =IF(C12="","",IFERROR(SUMIFS('10-Compteurs Temps'!H$5:H$104,'10-Compteurs Temps'!E$5:E$104,C12,'10-Compteurs Temps'!F$5:F$104,D12,'10-Compteurs Temps'!G$5:G$104,E12),0)) | H12: =IF(C12="","",IFERROR(SUMIFS('10-Compteurs Temps'!I$5:I$104,'10-Compteurs Temps'!E$5:E$104,C12,'10-Compteurs Temps'!F$5:F$104,D12,'10-Compteurs Temps'!G$5:G$104,E12),0)) | I12: =IF(C12="","",IFERROR(SUMIFS('10-Compteurs Temps'!J$5:J$104,'10-Compteurs Temps'!E$5:E$104,C12,'10-Compteurs Temps'!F$5:F$104,D12,'10-Compteurs Temps'!G$5:G$104,E12),0)) | J12: =IF(C12="","",IFERROR(SUMIFS('10-Compteurs Temps'!K$5:K$104,'10-Compteurs Temps'!E$5:E$104,C12,'10-Compteurs Temps'!F$5:F$104,D12,'10-Compteurs Temps'!G$5:G$104,E12),0)) | K12: =IF(C12="","",IFERROR(SUMIFS('9-Heures WE & Feries'!I$5:I$104,'9-Heures WE & Feries'!E$5:E$104,C12),0)) | L12: =IF(C12="","",IFERROR(SUMIFS('10-Compteurs Temps'!L$5:L$104,'10-Compteurs Temps'!E$5:E$104,C12,'10-Compteurs Temps'!F$5:F$104,D12,'10-Compteurs Temps'!G$5:G$104,E12)/8,0)) | N12: =IF(OR(C12="",G12=0,G12=""),"",IFERROR(H12/G12,0)) | O12: =IF(C12="","",IFERROR(H12-G12,0)) | P12: =IF(C12="","",IFERROR(SUMIFS('7-Heures Supplementaires'!M$5:M$104,'7-Heures Supplementaires'!E$5:E$104,C12),0))
B13: =IF(C13="","BMT-"&TEXT(COUNTA($C$5:C13),"000")) | F13: =IF(C13="","",IFERROR(COUNTIFS('10-Compteurs Temps'!E$5:E$104,C13,'10-Compteurs Temps'!F$5:F$104,D13,'10-Compteurs Temps'!G$5:G$104,E13),0)) | G13: =IF(C13="","",IFERROR(SUMIFS('10-Compteurs Temps'!H$5:H$104,'10-Compteurs Temps'!E$5:E$104,C13,'10-Compteurs Temps'!F$5:F$104,D13,'10-Compteurs Temps'!G$5:G$104,E13),0)) | H13: =IF(C13="","",IFERROR(SUMIFS('10-Compteurs Temps'!I$5:I$104,'10-Compteurs Temps'!E$5:E$104,C13,'10-Compteurs Temps'!F$5:F$104,D13,'10-Compteurs Temps'!G$5:G$104,E13),0)) | I13: =IF(C13="","",IFERROR(SUMIFS('10-Compteurs Temps'!J$5:J$104,'10-Compteurs Temps'!E$5:E$104,C13,'10-Compteurs Temps'!F$5:F$104,D13,'10-Compteurs Temps'!G$5:G$104,E13),0)) | J13: =IF(C13="","",IFERROR(SUMIFS('10-Compteurs Temps'!K$5:K$104,'10-Compteurs Temps'!E$5:E$104,C13,'10-Compteurs Temps'!F$5:F$104,D13,'10-Compteurs Temps'!G$5:G$104,E13),0)) | K13: =IF(C13="","",IFERROR(SUMIFS('9-Heures WE & Feries'!I$5:I$104,'9-Heures WE & Feries'!E$5:E$104,C13),0)) | L13: =IF(C13="","",IFERROR(SUMIFS('10-Compteurs Temps'!L$5:L$104,'10-Compteurs Temps'!E$5:E$104,C13,'10-Compteurs Temps'!F$5:F$104,D13,'10-Compteurs Temps'!G$5:G$104,E13)/8,0)) | N13: =IF(OR(C13="",G13=0,G13=""),"",IFERROR(H13/G13,0)) | O13: =IF(C13="","",IFERROR(H13-G13,0)) | P13: =IF(C13="","",IFERROR(SUMIFS('7-Heures Supplementaires'!M$5:M$104,'7-Heures Supplementaires'!E$5:E$104,C13),0))
B14: =IF(C14="","BMT-"&TEXT(COUNTA($C$5:C14),"000")) | F14: =IF(C14="","",IFERROR(COUNTIFS('10-Compteurs Temps'!E$5:E$104,C14,'10-Compteurs Temps'!F$5:F$104,D14,'10-Compteurs Temps'!G$5:G$104,E14),0)) | G14: =IF(C14="","",IFERROR(SUMIFS('10-Compteurs Temps'!H$5:H$104,'10-Compteurs Temps'!E$5:E$104,C14,'10-Compteurs Temps'!F$5:F$104,D14,'10-Compteurs Temps'!G$5:G$104,E14),0)) | H14: =IF(C14="","",IFERROR(SUMIFS('10-Compteurs Temps'!I$5:I$104,'10-Compteurs Temps'!E$5:E$104,C14,'10-Compteurs Temps'!F$5:F$104,D14,'10-Compteurs Temps'!G$5:G$104,E14),0)) | I14: =IF(C14="","",IFERROR(SUMIFS('10-Compteurs Temps'!J$5:J$104,'10-Compteurs Temps'!E$5:E$104,C14,'10-Compteurs Temps'!F$5:F$104,D14,'10-Compteurs Temps'!G$5:G$104,E14),0)) | J14: =IF(C14="","",IFERROR(SUMIFS('10-Compteurs Temps'!K$5:K$104,'10-Compteurs Temps'!E$5:E$104,C14,'10-Compteurs Temps'!F$5:F$104,D14,'10-Compteurs Temps'!G$5:G$104,E14),0)) | K14: =IF(C14="","",IFERROR(SUMIFS('9-Heures WE & Feries'!I$5:I$104,'9-Heures WE & Feries'!E$5:E$104,C14),0)) | L14: =IF(C14="","",IFERROR(SUMIFS('10-Compteurs Temps'!L$5:L$104,'10-Compteurs Temps'!E$5:E$104,C14,'10-Compteurs Temps'!F$5:F$104,D14,'10-Compteurs Temps'!G$5:G$104,E14)/8,0)) | N14: =IF(OR(C14="",G14=0,G14=""),"",IFERROR(H14/G14,0)) | O14: =IF(C14="","",IFERROR(H14-G14,0)) | P14: =IF(C14="","",IFERROR(SUMIFS('7-Heures Supplementaires'!M$5:M$104,'7-Heures Supplementaires'!E$5:E$104,C14),0))
B15: =IF(C15="","BMT-"&TEXT(COUNTA($C$5:C15),"000")) | F15: =IF(C15="","",IFERROR(COUNTIFS('10-Compteurs Temps'!E$5:E$104,C15,'10-Compteurs Temps'!F$5:F$104,D15,'10-Compteurs Temps'!G$5:G$104,E15),0)) | G15: =IF(C15="","",IFERROR(SUMIFS('10-Compteurs Temps'!H$5:H$104,'10-Compteurs Temps'!E$5:E$104,C15,'10-Compteurs Temps'!F$5:F$104,D15,'10-Compteurs Temps'!G$5:G$104,E15),0)) | H15: =IF(C15="","",IFERROR(SUMIFS('10-Compteurs Temps'!I$5:I$104,'10-Compteurs Temps'!E$5:E$104,C15,'10-Compteurs Temps'!F$5:F$104,D15,'10-Compteurs Temps'!G$5:G$104,E15),0)) | I15: =IF(C15="","",IFERROR(SUMIFS('10-Compteurs Temps'!J$5:J$104,'10-Compteurs Temps'!E$5:E$104,C15,'10-Compteurs Temps'!F$5:F$104,D15,'10-Compteurs Temps'!G$5:G$104,E15),0)) | J15: =IF(C15="","",IFERROR(SUMIFS('10-Compteurs Temps'!K$5:K$104,'10-Compteurs Temps'!E$5:E$104,C15,'10-Compteurs Temps'!F$5:F$104,D15,'10-Compteurs Temps'!G$5:G$104,E15),0)) | K15: =IF(C15="","",IFERROR(SUMIFS('9-Heures WE & Feries'!I$5:I$104,'9-Heures WE & Feries'!E$5:E$104,C15),0)) | L15: =IF(C15="","",IFERROR(SUMIFS('10-Compteurs Temps'!L$5:L$104,'10-Compteurs Temps'!E$5:E$104,C15,'10-Compteurs Temps'!F$5:F$104,D15,'10-Compteurs Temps'!G$5:G$104,E15)/8,0)) | N15: =IF(OR(C15="",G15=0,G15=""),"",IFERROR(H15/G15,0)) | O15: =IF(C15="","",IFERROR(H15-G15,0)) | P15: =IF(C15="","",IFERROR(SUMIFS('7-Heures Supplementaires'!M$5:M$104,'7-Heures Supplementaires'!E$5:E$104,C15),0))
B16: =IF(C16="","BMT-"&TEXT(COUNTA($C$5:C16),"000")) | F16: =IF(C16="","",IFERROR(COUNTIFS('10-Compteurs Temps'!E$5:E$104,C16,'10-Compteurs Temps'!F$5:F$104,D16,'10-Compteurs Temps'!G$5:G$104,E16),0)) | G16: =IF(C16="","",IFERROR(SUMIFS('10-Compteurs Temps'!H$5:H$104,'10-Compteurs Temps'!E$5:E$104,C16,'10-Compteurs Temps'!F$5:F$104,D16,'10-Compteurs Temps'!G$5:G$104,E16),0)) | H16: =IF(C16="","",IFERROR(SUMIFS('10-Compteurs Temps'!I$5:I$104,'10-Compteurs Temps'!E$5:E$104,C16,'10-Compteurs Temps'!F$5:F$104,D16,'10-Compteurs Temps'!G$5:G$104,E16),0)) | I16: =IF(C16="","",IFERROR(SUMIFS('10-Compteurs Temps'!J$5:J$104,'10-Compteurs Temps'!E$5:E$104,C16,'10-Compteurs Temps'!F$5:F$104,D16,'10-Compteurs Temps'!G$5:G$104,E16),0)) | J16: =IF(C16="","",IFERROR(SUMIFS('10-Compteurs Temps'!K$5:K$104,'10-Compteurs Temps'!E$5:E$104,C16,'10-Compteurs Temps'!F$5:F$104,D16,'10-Compteurs Temps'!G$5:G$104,E16),0)) | K16: =IF(C16="","",IFERROR(SUMIFS('9-Heures WE & Feries'!I$5:I$104,'9-Heures WE & Feries'!E$5:E$104,C16),0)) | L16: =IF(C16="","",IFERROR(SUMIFS('10-Compteurs Temps'!L$5:L$104,'10-Compteurs Temps'!E$5:E$104,C16,'10-Compteurs Temps'!F$5:F$104,D16,'10-Compteurs Temps'!G$5:G$104,E16)/8,0)) | N16: =IF(OR(C16="",G16=0,G16=""),"",IFERROR(H16/G16,0)) | O16: =IF(C16="","",IFERROR(H16-G16,0)) | P16: =IF(C16="","",IFERROR(SUMIFS('7-Heures Supplementaires'!M$5:M$104,'7-Heures Supplementaires'!E$5:E$104,C16),0))
B17: =IF(C17="","BMT-"&TEXT(COUNTA($C$5:C17),"000")) | F17: =IF(C17="","",IFERROR(COUNTIFS('10-Compteurs Temps'!E$5:E$104,C17,'10-Compteurs Temps'!F$5:F$104,D17,'10-Compteurs Temps'!G$5:G$104,E17),0)) | G17: =IF(C17="","",IFERROR(SUMIFS('10-Compteurs Temps'!H$5:H$104,'10-Compteurs Temps'!E$5:E$104,C17,'10-Compteurs Temps'!F$5:F$104,D17,'10-Compteurs Temps'!G$5:G$104,E17),0)) | H17: =IF(C17="","",IFERROR(SUMIFS('10-Compteurs Temps'!I$5:I$104,'10-Compteurs Temps'!E$5:E$104,C17,'10-Compteurs Temps'!F$5:F$104,D17,'10-Compteurs Temps'!G$5:G$104,E17),0)) | I17: =IF(C17="","",IFERROR(SUMIFS('10-Compteurs Temps'!J$5:J$104,'10-Compteurs Temps'!E$5:E$104,C17,'10-Compteurs Temps'!F$5:F$104,D17,'10-Compteurs Temps'!G$5:G$104,E17),0)) | J17: =IF(C17="","",IFERROR(SUMIFS('10-Compteurs Temps'!K$5:K$104,'10-Compteurs Temps'!E$5:E$104,C17,'10-Compteurs Temps'!F$5:F$104,D17,'10-Compteurs Temps'!G$5:G$104,E17),0)) | K17: =IF(C17="","",IFERROR(SUMIFS('9-Heures WE & Feries'!I$5:I$104,'9-Heures WE & Feries'!E$5:E$104,C17),0)) | L17: =IF(C17="","",IFERROR(SUMIFS('10-Compteurs Temps'!L$5:L$104,'10-Compteurs Temps'!E$5:E$104,C17,'10-Compteurs Temps'!F$5:F$104,D17,'10-Compteurs Temps'!G$5:G$104,E17)/8,0)) | N17: =IF(OR(C17="",G17=0,G17=""),"",IFERROR(H17/G17,0)) | O17: =IF(C17="","",IFERROR(H17-G17,0)) | P17: =IF(C17="","",IFERROR(SUMIFS('7-Heures Supplementaires'!M$5:M$104,'7-Heures Supplementaires'!E$5:E$104,C17),0))
B18: =IF(C18="","BMT-"&TEXT(COUNTA($C$5:C18),"000")) | F18: =IF(C18="","",IFERROR(COUNTIFS('10-Compteurs Temps'!E$5:E$104,C18,'10-Compteurs Temps'!F$5:F$104,D18,'10-Compteurs Temps'!G$5:G$104,E18),0)) | G18: =IF(C18="","",IFERROR(SUMIFS('10-Compteurs Temps'!H$5:H$104,'10-Compteurs Temps'!E$5:E$104,C18,'10-Compteurs Temps'!F$5:F$104,D18,'10-Compteurs Temps'!G$5:G$104,E18),0)) | H18: =IF(C18="","",IFERROR(SUMIFS('10-Compteurs Temps'!I$5:I$104,'10-Compteurs Temps'!E$5:E$104,C18,'10-Compteurs Temps'!F$5:F$104,D18,'10-Compteurs Temps'!G$5:G$104,E18),0)) | I18: =IF(C18="","",IFERROR(SUMIFS('10-Compteurs Temps'!J$5:J$104,'10-Compteurs Temps'!E$5:E$104,C18,'10-Compteurs Temps'!F$5:F$104,D18,'10-Compteurs Temps'!G$5:G$104,E18),0)) | J18: =IF(C18="","",IFERROR(SUMIFS('10-Compteurs Temps'!K$5:K$104,'10-Compteurs Temps'!E$5:E$104,C18,'10-Compteurs Temps'!F$5:F$104,D18,'10-Compteurs Temps'!G$5:G$104,E18),0)) | K18: =IF(C18="","",IFERROR(SUMIFS('9-Heures WE & Feries'!I$5:I$104,'9-Heures WE & Feries'!E$5:E$104,C18),0)) | L18: =IF(C18="","",IFERROR(SUMIFS('10-Compteurs Temps'!L$5:L$104,'10-Compteurs Temps'!E$5:E$104,C18,'10-Compteurs Temps'!F$5:F$104,D18,'10-Compteurs Temps'!G$5:G$104,E18)/8,0)) | N18: =IF(OR(C18="",G18=0,G18=""),"",IFERROR(H18/G18,0)) | O18: =IF(C18="","",IFERROR(H18-G18,0)) | P18: =IF(C18="","",IFERROR(SUMIFS('7-Heures Supplementaires'!M$5:M$104,'7-Heures Supplementaires'!E$5:E$104,C18),0))
B19: =IF(C19="","BMT-"&TEXT(COUNTA($C$5:C19),"000")) | F19: =IF(C19="","",IFERROR(COUNTIFS('10-Compteurs Temps'!E$5:E$104,C19,'10-Compteurs Temps'!F$5:F$104,D19,'10-Compteurs Temps'!G$5:G$104,E19),0)) | G19: =IF(C19="","",IFERROR(SUMIFS('10-Compteurs Temps'!H$5:H$104,'10-Compteurs Temps'!E$5:E$104,C19,'10-Compteurs Temps'!F$5:F$104,D19,'10-Compteurs Temps'!G$5:G$104,E19),0)) | H19: =IF(C19="","",IFERROR(SUMIFS('10-Compteurs Temps'!I$5:I$104,'10-Compteurs Temps'!E$5:E$104,C19,'10-Compteurs Temps'!F$5:F$104,D19,'10-Compteurs Temps'!G$5:G$104,E19),0)) | I19: =IF(C19="","",IFERROR(SUMIFS('10-Compteurs Temps'!J$5:J$104,'10-Compteurs Temps'!E$5:E$104,C19,'10-Compteurs Temps'!F$5:F$104,D19,'10-Compteurs Temps'!G$5:G$104,E19),0)) | J19: =IF(C19="","",IFERROR(SUMIFS('10-Compteurs Temps'!K$5:K$104,'10-Compteurs Temps'!E$5:E$104,C19,'10-Compteurs Temps'!F$5:F$104,D19,'10-Compteurs Temps'!G$5:G$104,E19),0)) | K19: =IF(C19="","",IFERROR(SUMIFS('9-Heures WE & Feries'!I$5:I$104,'9-Heures WE & Feries'!E$5:E$104,C19),0)) | L19: =IF(C19="","",IFERROR(SUMIFS('10-Compteurs Temps'!L$5:L$104,'10-Compteurs Temps'!E$5:E$104,C19,'10-Compteurs Temps'!F$5:F$104,D19,'10-Compteurs Temps'!G$5:G$104,E19)/8,0)) | N19: =IF(OR(C19="",G19=0,G19=""),"",IFERROR(H19/G19,0)) | O19: =IF(C19="","",IFERROR(H19-G19,0)) | P19: =IF(C19="","",IFERROR(SUMIFS('7-Heures Supplementaires'!M$5:M$104,'7-Heures Supplementaires'!E$5:E$104,C19),0))
B20: =IF(C20="","BMT-"&TEXT(COUNTA($C$5:C20),"000")) | F20: =IF(C20="","",IFERROR(COUNTIFS('10-Compteurs Temps'!E$5:E$104,C20,'10-Compteurs Temps'!F$5:F$104,D20,'10-Compteurs Temps'!G$5:G$104,E20),0)) | G20: =IF(C20="","",IFERROR(SUMIFS('10-Compteurs Temps'!H$5:H$104,'10-Compteurs Temps'!E$5:E$104,C20,'10-Compteurs Temps'!F$5:F$104,D20,'10-Compteurs Temps'!G$5:G$104,E20),0)) | H20: =IF(C20="","",IFERROR(SUMIFS('10-Compteurs Temps'!I$5:I$104,'10-Compteurs Temps'!E$5:E$104,C20,'10-Compteurs Temps'!F$5:F$104,D20,'10-Compteurs Temps'!G$5:G$104,E20),0)) | I20: =IF(C20="","",IFERROR(SUMIFS('10-Compteurs Temps'!J$5:J$104,'10-Compteurs Temps'!E$5:E$104,C20,'10-Compteurs Temps'!F$5:F$104,D20,'10-Compteurs Temps'!G$5:G$104,E20),0)) | J20: =IF(C20="","",IFERROR(SUMIFS('10-Compteurs Temps'!K$5:K$104,'10-Compteurs Temps'!E$5:E$104,C20,'10-Compteurs Temps'!F$5:F$104,D20,'10-Compteurs Temps'!G$5:G$104,E20),0)) | K20: =IF(C20="","",IFERROR(SUMIFS('9-Heures WE & Feries'!I$5:I$104,'9-Heures WE & Feries'!E$5:E$104,C20),0)) | L20: =IF(C20="","",IFERROR(SUMIFS('10-Compteurs Temps'!L$5:L$104,'10-Compteurs Temps'!E$5:E$104,C20,'10-Compteurs Temps'!F$5:F$104,D20,'10-Compteurs Temps'!G$5:G$104,E20)/8,0)) | N20: =IF(OR(C20="",G20=0,G20=""),"",IFERROR(H20/G20,0)) | O20: =IF(C20="","",IFERROR(H20-G20,0)) | P20: =IF(C20="","",IFERROR(SUMIFS('7-Heures Supplementaires'!M$5:M$104,'7-Heures Supplementaires'!E$5:E$104,C20),0))
B21: =IF(C21="","BMT-"&TEXT(COUNTA($C$5:C21),"000")) | F21: =IF(C21="","",IFERROR(COUNTIFS('10-Compteurs Temps'!E$5:E$104,C21,'10-Compteurs Temps'!F$5:F$104,D21,'10-Compteurs Temps'!G$5:G$104,E21),0)) | G21: =IF(C21="","",IFERROR(SUMIFS('10-Compteurs Temps'!H$5:H$104,'10-Compteurs Temps'!E$5:E$104,C21,'10-Compteurs Temps'!F$5:F$104,D21,'10-Compteurs Temps'!G$5:G$104,E21),0)) | H21: =IF(C21="","",IFERROR(SUMIFS('10-Compteurs Temps'!I$5:I$104,'10-Compteurs Temps'!E$5:E$104,C21,'10-Compteurs Temps'!F$5:F$104,D21,'10-Compteurs Temps'!G$5:G$104,E21),0)) | I21: =IF(C21="","",IFERROR(SUMIFS('10-Compteurs Temps'!J$5:J$104,'10-Compteurs Temps'!E$5:E$104,C21,'10-Compteurs Temps'!F$5:F$104,D21,'10-Compteurs Temps'!G$5:G$104,E21),0)) | J21: =IF(C21="","",IFERROR(SUMIFS('10-Compteurs Temps'!K$5:K$104,'10-Compteurs Temps'!E$5:E$104,C21,'10-Compteurs Temps'!F$5:F$104,D21,'10-Compteurs Temps'!G$5:G$104,E21),0)) | K21: =IF(C21="","",IFERROR(SUMIFS('9-Heures WE & Feries'!I$5:I$104,'9-Heures WE & Feries'!E$5:E$104,C21),0)) | L21: =IF(C21="","",IFERROR(SUMIFS('10-Compteurs Temps'!L$5:L$104,'10-Compteurs Temps'!E$5:E$104,C21,'10-Compteurs Temps'!F$5:F$104,D21,'10-Compteurs Temps'!G$5:G$104,E21)/8,0)) | N21: =IF(OR(C21="",G21=0,G21=""),"",IFERROR(H21/G21,0)) | O21: =IF(C21="","",IFERROR(H21-G21,0)) | P21: =IF(C21="","",IFERROR(SUMIFS('7-Heures Supplementaires'!M$5:M$104,'7-Heures Supplementaires'!E$5:E$104,C21),0))
... B104: =IF(C104="","BMT-"&TEXT(COUNTA($C$5:C104),"000")) | F104: =IF(C104="","",IFERROR(COUNTIFS('10-Compteurs Temps'!E$5:E$104,C104,'10-Compteurs Temps'!F$5:F$104,D104,'10-Compteurs Temps'!G$5:G$104,E104),0)) | G104: =IF(C104="","",IFERROR(SUMIFS('10-Compteurs Temps'!H$5:H$104,'10-Compteurs Temps'!E$5:E$104,C104,'10-Compteurs Temps'!F$5:F$104,D104,'10-Compteurs Temps'!G$5:G$104,E104),0)) | H104: =IF(C104="","",IFERROR(SUMIFS('10-Compteurs Temps'!I$5:I$104,'10-Compteurs Temps'!E$5:E$104,C104,'10-Compteurs Temps'!F$5:F$104,D104,'10-Compteurs Temps'!G$5:G$104,E104),0)) | I104: =IF(C104="","",IFERROR(SUMIFS('10-Compteurs Temps'!J$5:J$104,'10-Compteurs Temps'!E$5:E$104,C104,'10-Compteurs Temps'!F$5:F$104,D104,'10-Compteurs Temps'!G$5:G$104,E104),0)) | J104: =IF(C104="","",IFERROR(SUMIFS('10-Compteurs Temps'!K$5:K$104,'10-Compteurs Temps'!E$5:E$104,C104,'10-Compteurs Temps'!F$5:F$104,D104,'10-Compteurs Temps'!G$5:G$104,E104),0)) | K104: =IF(C104="","",IFERROR(SUMIFS('9-Heures WE & Feries'!I$5:I$104,'9-Heures WE & Feries'!E$5:E$104,C104),0)) | L104: =IF(C104="","",IFERROR(SUMIFS('10-Compteurs Temps'!L$5:L$104,'10-Compteurs Temps'!E$5:E$104,C104,'10-Compteurs Temps'!F$5:F$104,D104,'10-Compteurs Temps'!G$5:G$104,E104)/8,0)) | N104: =IF(OR(C104="",G104=0,G104=""),"",IFERROR(H104/G104,0)) | O104: =IF(C104="","",IFERROR(H104-G104,0)) | P104: =IF(C104="","",IFERROR(SUMIFS('7-Heures Supplementaires'!M$5:M$104,'7-Heures Supplementaires'!E$5:E$104,C104),0))
B105: =IF(C105="","BMT-"&TEXT(COUNTA($C$5:C105),"000")) | N105: =IF(G105="","",IF(G105=0,"",(H105+I105)/G105)) | O105: =IF(H105="","",H105-G105+I105+J105+K105-L105*8)
B106: =IF(C106="","BMT-"&TEXT(COUNTA($C$5:C106),"000")) | N106: =IF(G106="","",IF(G106=0,"",(H106+I106)/G106)) | O106: =IF(H106="","",H106-G106+I106+J106+K106-L106*8)
B107: =IF(C107="","BMT-"&TEXT(COUNTA($C$5:C107),"000")) | N107: =IF(G107="","",IF(G107=0,"",(H107+I107)/G107)) | O107: =IF(H107="","",H107-G107+I107+J107+K107-L107*8)
B108: =IF(C108="","BMT-"&TEXT(COUNTA($C$5:C108),"000")) | N108: =IF(G108="","",IF(G108=0,"",(H108+I108)/G108)) | O108: =IF(H108="","",H108-G108+I108+J108+K108-L108*8)
B109: =IF(C109="","BMT-"&TEXT(COUNTA($C$5:C109),"000")) | N109: =IF(G109="","",IF(G109=0,"",(H109+I109)/G109)) | O109: =IF(H109="","",H109-G109+I109+J109+K109-L109*8)
B111: TOTAL | F111: =SUM(F5:F104) | G111: =SUM(G5:G104) | H111: =SUM(H5:H104) | I111: =SUM(I5:I104) | J111: =SUM(J5:J104) | K111: =SUM(K5:K104) | L111: =SUM(L5:L104) | M111: =SUM(M5:M104) | P111: =SUM(P5:P104)
B113: INDICATEURS (mis a jour automatiquement)
B114: Bilans mensuels | D114: Total heures eff. | F114: Total h. supp | H114: Cout total supp (FCFA)
B115: =COUNTIF(B5:B104,"<>") | D115: =SUM(H5:H104) | F115: =SUM(I5:I104) | H115: =SUM(P5:P104)

Sheet 18-Rapports & Audit Temps
B2: RAPPORTS & AUDIT DU TEMPS DE TRAVAIL
B3: TABLEAU DYNAMIQUE — Saisissez dans la prochaine ligne jaune. Les calculs se mettent a jour automatiquement.
B4: N° Rapport | C4: Type Rapport | D4: Titre | E4: Periode Debut | F4: Periode Fin | G4: Departement | H4: Auteur | I4: Anomalies Detectees | J4: Ecart Financier (FCFA) | K4: Recommandations | L4: Statut
B5: RAP-001 | C5: Bilan mensuel | D5: Bilan Temps Juin 2025 | E5: 45809 | F5: 45838 | G5: Tous | H5: DRH Nganou | I5: 15 | J5: 75000 | K5: Renforcer controles pointage service nuit | L5: Valide
B6: RAP-002 | C6: Audit heures supp | D6: Audit HS Q2 2025 | E6: 45748 | F6: 45838 | G6: Reception & Front Office | H6: Chef Comptable | I6: 8 | J6: 120000 | K6: Revoir plannings equipe nuit reception | L6: Valide
B7: RAP-003 | C7: Conformite horaires | D7: Controle conformite Juin | E7: 45809 | F7: 45838 | G7: Cuisine & Restauration | H7: Assistante RH | I7: 22 | J7: 45000 | K7: Former equipe sur regles pointage | L7: Approuve
B8: RAP-004 | C8: Rapport anomalie | D8: Rapport ecarts pointage semaine 24 | E8: 45817 | F8: 45823 | G8: Informatique | H8: Chef de service IT | I8: 3 | J8: 0 | K8: Remplacer badgeuse defaillante | L8: Brouillon
B9: RAP-005 | C9: Bilan trimestriel | D9: Bilan Temps T2 2025 | E9: 45748 | F9: 45838 | G9: Tous | H9: DRH Nganou | I9: 48 | J9: 240000 | K9: Generaliser pointeur mobile | L9: Brouillon
B10: =IF(C10="","RAP-"&TEXT(COUNTA($C$5:C10),"000"))
B11: =IF(C11="","RAP-"&TEXT(COUNTA($C$5:C11),"000"))
B12: =IF(C12="","RAP-"&TEXT(COUNTA($C$5:C12),"000"))
B13: =IF(C13="","RAP-"&TEXT(COUNTA($C$5:C13),"000"))
B14: =IF(C14="","RAP-"&TEXT(COUNTA($C$5:C14),"000"))
B15: =IF(C15="","RAP-"&TEXT(COUNTA($C$5:C15),"000"))
B16: =IF(C16="","RAP-"&TEXT(COUNTA($C$5:C16),"000"))
B17: =IF(C17="","RAP-"&TEXT(COUNTA($C$5:C17),"000"))
B18: =IF(C18="","RAP-"&TEXT(COUNTA($C$5:C18),"000"))
B19: =IF(C19="","RAP-"&TEXT(COUNTA($C$5:C19),"000"))
B20: =IF(C20="","RAP-"&TEXT(COUNTA($C$5:C20),"000"))
B21: =IF(C21="","RAP-"&TEXT(COUNTA($C$5:C21),"000"))
... B109: =IF(C109="","RAP-"&TEXT(COUNTA($C$5:C109),"000"))
B111: TOTAL | I111: =SUM(I5:I104) | J111: =SUM(J5:J104)
B113: INDICATEURS (mis a jour automatiquement)
B114: Total rapports | D114: Anomalies totales | F114: Ecart financier (FCFA) | H114: Rapports approuves
B115: =COUNTIF(B5:B104,"<>") | D115: =SUM(I5:I104) | F115: =SUM(J5:J104) | H115: =COUNTIF(L5:L104,"Approuve")
