Workbook

Sheet 1-Tableau de Bord
B2: DOMAINE 7 — EVALUATION & GESTION DE LA PERFORMANCE
B3: TABLEAU DE BORD — Vue synthetique de tous les indicateurs du domaine (mis a jour automatiquement)
B5: Evaluations annuelles | E5: Note moyenne (/20) | H5: Objectifs definis | K5: Objectifs atteints
B6: =COUNTIF('2-Grille Evaluation Annuelle'!B5:B104,"<>") | E6: =IFERROR(AVERAGE('2-Grille Evaluation Annuelle'!K5:K104),0) | H6: =COUNTIF('3-Objectifs Individuels SMART'!B5:B104,"<>") | K6: =COUNTIF('3-Objectifs Individuels SMART'!M5:M104,"Atteint")+COUNTIF('3-Objectifs Individuels SMART'!M5:M104,"Depasse")
B9: Entretiens realises | E9: Evaluations essai | H9: Evaluations 360 | K9: KPI individuels
B10: =COUNTIF('4-Entretiens Annuels Eval.'!B5:B104,"<>") | E10: =COUNTIF('5-Evaluation a l''Essai'!B5:B104,"<>") | H10: =COUNTIF('6-Evaluation 360 Degres'!B5:B104,"<>") | K10: =COUNTIF('7-KPI Individuels Employes'!B5:B104,"<>")
B13: PAP actifs | E13: Primes (FCFA) | H13: Score global moyen | K13: PAP en cours
B14: =COUNTIF('8-Plan Amelioration (PAP)'!B5:B104,"<>") | E14: =SUM('10-Primes Performance Merite'!K5:K104) | H14: =IFERROR(AVERAGE('11-TdB Individuel Performance'!M5:M104),0) | K14: =COUNTIF('8-Plan Amelioration (PAP)'!M5:M104,"En cours")
B18: PERFORMANCE PAR SERVICE & DISTRIBUTION DES NOTES
B19: Service | C19: Note Moy. (/20)
B20: RH | C20: =IFERROR(AVERAGEIF('12-Bilan Performance par Svc'!C5:C104,"*RH*",'12-Bilan Performance par Svc'!F5:F104),0)
B21: Informatique | C21: =IFERROR(AVERAGEIF('12-Bilan Performance par Svc'!C5:C104,"*Informatique*",'12-Bilan Performance par Svc'!F5:F104),0)
B22: Finance | C22: =IFERROR(AVERAGEIF('12-Bilan Performance par Svc'!C5:C104,"*Finance*",'12-Bilan Performance par Svc'!F5:F104),0)
B23: Reception | C23: =IFERROR(AVERAGEIF('12-Bilan Performance par Svc'!C5:C104,"*Reception*",'12-Bilan Performance par Svc'!F5:F104),0)
B24: Cuisine | C24: =IFERROR(AVERAGEIF('12-Bilan Performance par Svc'!C5:C104,"*Cuisine*",'12-Bilan Performance par Svc'!F5:F104),0)
B25: Entretien | C25: =IFERROR(AVERAGEIF('12-Bilan Performance par Svc'!C5:C104,"*Entretien*",'12-Bilan Performance par Svc'!F5:F104),0)
B26: Securite | C26: =IFERROR(AVERAGEIF('12-Bilan Performance par Svc'!C5:C104,"*Securite*",'12-Bilan Performance par Svc'!F5:F104),0)
H28: Classement | I28: Nb Employes
H29: A - Excellent | I29: =COUNTIF('9-Classement Employes'!H5:H104,"A - Excellent")
H30: B - Tres bon | I30: =COUNTIF('9-Classement Employes'!H5:H104,"B - Tres bon")
H31: C - Bon | I31: =COUNTIF('9-Classement Employes'!H5:H104,"C - Bon")
H32: D - Moyen | I32: =COUNTIF('9-Classement Employes'!H5:H104,"D - Moyen")
H33: E - Insuffisant | I33: =COUNTIF('9-Classement Employes'!H5:H104,"E - Insuffisant")

Sheet _Lists
B1: departement | C1: poste_hotel | D1: note_echelon | E1: type_evaluation | F1: statut_evaluation | G1: periode_essai | H1: decision_essai | I1: niveau_objectif | J1: categorie_objectif | K1: statut_objectif | L1: type_plan_amelioration | M1: statut_pap | N1: classement | O1: type_prime | P1: mois | Q1: annee | R1: statut_rapport | S1: jour_semaine
B2: Direction Generale | C2: DG | D2: Insuffisant | E2: Evaluation annuelle | F2: Planifiee | G2: 1 mois | H2: Confirmation | I2: Strategique | J2: Qualite service | K2: Non demarre | L2: Formation ciblee | M2: En elaboration | N2: A - Excellent | O2: Prime de rendement | P2: Janvier | Q2: 2024 | R2: Brouillon | S2: Oui
B3: Ressources Humaines | C3: DRH | D3: Moyen | E3: Evaluation a l'essai | F3: En cours | G3: 2 mois | H3: Prolongation essai | I3: Operationnel | J3: Productivite | K3: En cours | L3: Coaching individuel | M3: En cours | N3: B - Tres bon | O3: Prime d'anciennete | P3: Fevrier | Q3: 2025 | R3: Valide | S3: Non
B4: Finance & Comptabilite | C4: Assistante RH | D4: Satisfaisant | E4: Evaluation 360 degres | F4: Completee | G4: 3 mois | H4: Rupture essai | I4: Individuel | J4: Competence technique | K4: Atteint | L4: Mentorat | M4: Termine | N4: C - Bon | O4: Prime de merite | P4: Mars | Q4: 2026 | R4: Approuve
B5: Marketing & Communication | C5: DAF | D5: Bon | E5: Evaluation de mi-parcours | F5: Annulee | G5: 6 mois | H5: Changement de poste | J5: Savoir-etre | K5: Depasse | L5: Rotation de poste | M5: Abandonne | N5: D - Moyen | O5: Prime d'equipe | P5: Avril | R5: Rejete
B6: Informatique | C6: Comptable senior | D6: Tres bon | E6: Evaluation exceptionnelle | F6: En attente N+1 | G6: Probation indefinite | H6: En attente | J6: Securite | K6: Non atteint | L6: Suivi renforce | M6: En attente validation | N6: E - Insuffisant | O6: Prime exceptionnelle | P6: Mai
B7: Commercial | C7: Chef Comptable | D7: Excellent | F7: Validee DRH | J7: Budget / Cout | K7: Reporte | L7: Plan de charge adapte | O7: Prime fidélisation | P7: Juin
B8: Logistique & Approvisionnement | C8: Chef Marketing | J8: Fidélisation client | P8: Juillet
B9: Production | C9: Chef de service IT | P9: Aout
B10: Service Client | C10: Technicien IT | P10: Septembre
B11: Reception & Front Office | C11: Chef Commercial | P11: Octobre
B12: Cuisine & Restauration | C12: Agent Commercial | P12: Novembre
B13: Entretien & Maintenance | C13: Chef Logistique | P13: Decembre
B14: Securite | C14: Magasinier
C15: Chef Reception
C16: Receptionniste
C17: Concierge
C18: Chef Cuisine
C19: Sous-Chef
C20: Cuisinier
C21: Plongeur
C22: Chef Entretien
C23: Agent Entretien
C24: Chef Securite
C25: Agent Securite

Sheet 2-Grille Evaluation Annuelle
B2: GRILLE D'EVALUATION ANNUELLE (#76)
B3: TABLEAU DYNAMIQUE — Saisissez dans la prochaine ligne jaune. Les calculs se mettent a jour automatiquement.
B4: N° Eval | C4: Matricule | D4: Nom Employe | E4: Departement | F4: Poste | G4: Annee | H4: Competence Tech. (/20) | I4: Savoir-Etre (/20) | J4: Productivite (/20) | K4: Note Globale (/20) | L4: Appreciation | M4: Statut
B5: EV-001 | C5: EMP-2025-001 | D5: Nganou Clarisse | E5: Ressources Humaines | F5: DRH | G5: 2025 | H5: 17 | I5: 18 | J5: 16 | K5: 17 | L5: Tres bon | M5: Completee
B6: EV-002 | C6: EMP-2025-002 | D6: Tchinda Armand | E6: Informatique | F6: Chef de service IT | G6: 2025 | H6: 19 | I6: 16 | J6: 18 | K6: 17.7 | L6: Tres bon | M6: Completee
B7: EV-003 | C7: EMP-2025-003 | D7: Fotso Marguerite | E7: Finance & Comptabilite | F7: Comptable senior | G7: 2025 | H7: 18 | I7: 17 | J7: 17 | K7: 17.3 | L7: Tres bon | M7: Completee
B8: EV-004 | C8: EMP-2025-004 | D8: Ouedraogo Ibrahim | E8: Reception & Front Office | F8: Receptionniste | G8: 2025 | H8: 15 | I8: 19 | J8: 14 | K8: 16 | L8: Bon | M8: En cours
B9: EV-005 | C9: EMP-2025-020 | D9: Tagne Rene | E9: Cuisine & Restauration | F9: Cuisinier | G9: 2025 | H9: 14 | I9: 12 | J9: 13 | K9: 13 | L9: Moyen | M9: Planifiee
B10: =IF(C10="","EV-"&TEXT(COUNTA($C$5:C10),"000")) | K10: =IF(H10="","",ROUND((H10+I10+J10)/3,1))
B11: =IF(C11="","EV-"&TEXT(COUNTA($C$5:C11),"000")) | K11: =IF(H11="","",ROUND((H11+I11+J11)/3,1))
B12: =IF(C12="","EV-"&TEXT(COUNTA($C$5:C12),"000")) | K12: =IF(H12="","",ROUND((H12+I12+J12)/3,1))
B13: =IF(C13="","EV-"&TEXT(COUNTA($C$5:C13),"000")) | K13: =IF(H13="","",ROUND((H13+I13+J13)/3,1))
B14: =IF(C14="","EV-"&TEXT(COUNTA($C$5:C14),"000")) | K14: =IF(H14="","",ROUND((H14+I14+J14)/3,1))
B15: =IF(C15="","EV-"&TEXT(COUNTA($C$5:C15),"000")) | K15: =IF(H15="","",ROUND((H15+I15+J15)/3,1))
B16: =IF(C16="","EV-"&TEXT(COUNTA($C$5:C16),"000")) | K16: =IF(H16="","",ROUND((H16+I16+J16)/3,1))
B17: =IF(C17="","EV-"&TEXT(COUNTA($C$5:C17),"000")) | K17: =IF(H17="","",ROUND((H17+I17+J17)/3,1))
B18: =IF(C18="","EV-"&TEXT(COUNTA($C$5:C18),"000")) | K18: =IF(H18="","",ROUND((H18+I18+J18)/3,1))
B19: =IF(C19="","EV-"&TEXT(COUNTA($C$5:C19),"000")) | K19: =IF(H19="","",ROUND((H19+I19+J19)/3,1))
B20: =IF(C20="","EV-"&TEXT(COUNTA($C$5:C20),"000")) | K20: =IF(H20="","",ROUND((H20+I20+J20)/3,1))
B21: =IF(C21="","EV-"&TEXT(COUNTA($C$5:C21),"000")) | K21: =IF(H21="","",ROUND((H21+I21+J21)/3,1))
... B109: =IF(C109="","EV-"&TEXT(COUNTA($C$5:C109),"000")) | K109: =IF(H109="","",ROUND((H109+I109+J109)/3,1))
B111: INDICATEURS (mis a jour automatiquement)
B112: Evaluations | D112: Note moyenne globale | F112: Note max | H112: Note min
B113: =COUNTIF(B5:B104,"<>") | D113: =IFERROR(AVERAGE(K5:K104),0) | F113: =IFERROR(MAX(K5:K104),0) | H113: =IFERROR(MIN(K5:K104),0)

Sheet 3-Objectifs Individuels SMART
B2: OBJECTIFS INDIVIDUELS SMART (#77)
B3: TABLEAU DYNAMIQUE — Saisissez dans la prochaine ligne jaune. Les calculs se mettent a jour automatiquement.
B4: N° Objectif | C4: Matricule | D4: Nom Employe | E4: Departement | F4: Poste | G4: Libelle Objectif | H4: Categorie | I4: Indicateur (KPI) | J4: Cible | K4: Resultat | L4: Taux Atteinte (%) | M4: Statut
B5: OBJ-001 | C5: EMP-2025-001 | D5: Nganou Clarisse | E5: Ressources Humaines | F5: DRH | G5: Reduire turnover a 8% | H5: Budget / Cout | I5: Taux turnover (%) | J5: 8% | K5: 9.2% | L5: 0 | M5: Non atteint
B6: OBJ-002 | C6: EMP-2025-001 | D6: Nganou Clarisse | E6: Ressources Humaines | F6: DRH | G6: 100% entretiens annuels realises | H6: Productivite | I6: Nb entretiens / effectif | J6: 100% | K6: 85% | L6: 85 | M6: Non atteint
B7: OBJ-003 | C7: EMP-2025-002 | D7: Tchinda Armand | E7: Informatique | F7: Chef de service IT | G7: Taux disponibilite reseau >99% | H7: Competence technique | I7: Uptime reseau (%) | J7: 99% | K7: 99.5% | L7: 100 | M7: Depasse
B8: OBJ-004 | C8: EMP-2025-004 | D8: Ouedraogo Ibrahim | E8: Reception & Front Office | F8: Receptionniste | G8: Satisfaction client > 90% | H8: Qualite service | I8: Score satisfaction (%) | J8: 90% | K8: 92% | L8: 102 | M8: Depasse
B9: OBJ-005 | C9: EMP-2025-020 | D9: Tagne Rene | E9: Cuisine & Restauration | F9: Cuisinier | G9: Zero non conformite HACCP | H9: Securite | I9: Nb non conformites | J9: 0 | K9: 2 | L9: 0 | M9: Non atteint
B10: =IF(C10="","OBJ-"&TEXT(COUNTA($C$5:C10),"000"))
B11: =IF(C11="","OBJ-"&TEXT(COUNTA($C$5:C11),"000"))
B12: =IF(C12="","OBJ-"&TEXT(COUNTA($C$5:C12),"000"))
B13: =IF(C13="","OBJ-"&TEXT(COUNTA($C$5:C13),"000"))
B14: =IF(C14="","OBJ-"&TEXT(COUNTA($C$5:C14),"000"))
B15: =IF(C15="","OBJ-"&TEXT(COUNTA($C$5:C15),"000"))
B16: =IF(C16="","OBJ-"&TEXT(COUNTA($C$5:C16),"000"))
B17: =IF(C17="","OBJ-"&TEXT(COUNTA($C$5:C17),"000"))
B18: =IF(C18="","OBJ-"&TEXT(COUNTA($C$5:C18),"000"))
B19: =IF(C19="","OBJ-"&TEXT(COUNTA($C$5:C19),"000"))
B20: =IF(C20="","OBJ-"&TEXT(COUNTA($C$5:C20),"000"))
B21: =IF(C21="","OBJ-"&TEXT(COUNTA($C$5:C21),"000"))
... B109: =IF(C109="","OBJ-"&TEXT(COUNTA($C$5:C109),"000"))
B111: INDICATEURS (mis a jour automatiquement)
B112: Objectifs definis | D112: Atteints | F112: Non atteints | H112: Taux atteinte moyen
B113: =COUNTIF(B5:B104,"<>") | D113: =COUNTIF(M5:M104,"Atteint")+COUNTIF(M5:M104,"Depasse") | F113: =COUNTIF(M5:M104,"Non atteint") | H113: =IFERROR(AVERAGE(L5:L104),0)

Sheet 4-Entretiens Annuels Eval.
B2: ENTRETIENS ANNUELS D'EVALUATION (#78)
B3: TABLEAU DYNAMIQUE — Saisissez dans la prochaine ligne jaune. Les calculs se mettent a jour automatiquement.
B4: N° Entretien | C4: Matricule | D4: Nom Employe | E4: Departement | F4: Poste | G4: Annee | H4: Date Entretien | I4: Evaluateur | J4: Note Globale (/20) | K4: Statut
B5: ENT-001 | C5: EMP-2025-001 | D5: Nganou Clarisse | E5: Ressources Humaines | F5: DRH | G5: 2025 | H5: 45823 | I5: DG | J5: 17 | K5: Completee
B6: ENT-002 | C6: EMP-2025-002 | D6: Tchinda Armand | E6: Informatique | F6: Chef de service IT | G6: 2025 | H6: 45826 | I6: DAF | J6: 17.7 | K6: Completee
B7: ENT-003 | C7: EMP-2025-003 | D7: Fotso Marguerite | E7: Finance & Comptabilite | F7: Comptable senior | G7: 2025 | H7: 45828 | I7: DAF | J7: 17.3 | K7: Completee
B8: ENT-004 | C8: EMP-2025-004 | D8: Ouedraogo Ibrahim | E8: Reception & Front Office | F8: Receptionniste | G8: 2025 | H8: 45840 | I8: Chef Reception | J8: 0 | K8: Planifiee
B9: ENT-005 | C9: EMP-2025-020 | D9: Tagne Rene | E9: Cuisine & Restauration | F9: Cuisinier | G9: 2025 | H9: 45843 | I9: Chef Cuisine | J9: 0 | K9: Planifiee
B10: =IF(C10="","ENT-"&TEXT(COUNTA($C$5:C10),"000"))
B11: =IF(C11="","ENT-"&TEXT(COUNTA($C$5:C11),"000"))
B12: =IF(C12="","ENT-"&TEXT(COUNTA($C$5:C12),"000"))
B13: =IF(C13="","ENT-"&TEXT(COUNTA($C$5:C13),"000"))
B14: =IF(C14="","ENT-"&TEXT(COUNTA($C$5:C14),"000"))
B15: =IF(C15="","ENT-"&TEXT(COUNTA($C$5:C15),"000"))
B16: =IF(C16="","ENT-"&TEXT(COUNTA($C$5:C16),"000"))
B17: =IF(C17="","ENT-"&TEXT(COUNTA($C$5:C17),"000"))
B18: =IF(C18="","ENT-"&TEXT(COUNTA($C$5:C18),"000"))
B19: =IF(C19="","ENT-"&TEXT(COUNTA($C$5:C19),"000"))
B20: =IF(C20="","ENT-"&TEXT(COUNTA($C$5:C20),"000"))
B21: =IF(C21="","ENT-"&TEXT(COUNTA($C$5:C21),"000"))
... B109: =IF(C109="","ENT-"&TEXT(COUNTA($C$5:C109),"000"))
B111: INDICATEURS (mis a jour automatiquement)
B112: Entretiens | D112: Realises | F112: Planifies | H112: Note moyenne (/20)
B113: =COUNTIF(B5:B104,"<>") | D113: =COUNTIF(K5:K104,"Completee") | F113: =COUNTIF(K5:K104,"Planifiee") | H113: =IFERROR(AVERAGE(J5:J104),0)

Sheet 5-Evaluation a l'Essai
B2: EVALUATION A L'ESSAI (#79)
B3: TABLEAU DYNAMIQUE — Saisissez dans la prochaine ligne jaune. Les calculs se mettent a jour automatiquement.
B4: N° | C4: Matricule | D4: Nom Employe | E4: Departement | F4: Poste | G4: Date Entree | H4: Duree Essai | I4: Date Fin Essai | J4: Note (/20) | K4: Decision | L4: Statut
B5: ESS-001 | C5: EMP-2025-031 | D5: Nkoulou Maxime | E5: Reception & Front Office | F5: Receptionniste | G5: 45748 | H5: 3 mois | I5: 45838 | J5: 16.5 | K5: Confirmation | L5: Completee
B6: ESS-002 | C6: EMP-2025-032 | D6: Mba Carine | E6: Service Client | F6: Conseiller | G6: 45778 | H6: 3 mois | I6: 45869 | J6: 12 | K6: Prolongation essai | L6: En cours
B7: ESS-003 | C7: EMP-2025-033 | D7: Tamo Elvis | E7: Cuisine & Restauration | F7: Plongeur | G7: 45792 | H7: 2 mois | I7: 45852 | J7: 8 | K7: Rupture essai | L7: Completee
B8: ESS-004 | C8: EMP-2025-034 | D8: Fomba Aminata | E8: Entretien & Maintenance | F8: Agent Entretien | G8: 45809 | H8: 3 mois | I8: 45900 | J8: 0 | K8: En attente | L8: En cours
B9: =IF(C9="","ESS-"&TEXT(COUNTA($C$5:C9),"000"))
B10: =IF(C10="","ESS-"&TEXT(COUNTA($C$5:C10),"000"))
B11: =IF(C11="","ESS-"&TEXT(COUNTA($C$5:C11),"000"))
B12: =IF(C12="","ESS-"&TEXT(COUNTA($C$5:C12),"000"))
B13: =IF(C13="","ESS-"&TEXT(COUNTA($C$5:C13),"000"))
B14: =IF(C14="","ESS-"&TEXT(COUNTA($C$5:C14),"000"))
B15: =IF(C15="","ESS-"&TEXT(COUNTA($C$5:C15),"000"))
B16: =IF(C16="","ESS-"&TEXT(COUNTA($C$5:C16),"000"))
B17: =IF(C17="","ESS-"&TEXT(COUNTA($C$5:C17),"000"))
B18: =IF(C18="","ESS-"&TEXT(COUNTA($C$5:C18),"000"))
B19: =IF(C19="","ESS-"&TEXT(COUNTA($C$5:C19),"000"))
B20: =IF(C20="","ESS-"&TEXT(COUNTA($C$5:C20),"000"))
... B108: =IF(C108="","ESS-"&TEXT(COUNTA($C$5:C108),"000"))
B110: INDICATEURS (mis a jour automatiquement)
B111: Evaluations essai | D111: Confirmees | F111: Ruptures | H111: Note moyenne (/20)
B112: =COUNTIF(B5:B104,"<>") | D112: =COUNTIF(K5:K104,"Confirmation") | F112: =COUNTIF(K5:K104,"Rupture essai") | H112: =IFERROR(AVERAGE(J5:J104),0)

Sheet 6-Evaluation 360 Degres
B2: EVALUATION 360 DEGRES (#80)
B3: TABLEAU DYNAMIQUE — Saisissez dans la prochaine ligne jaune. Les calculs se mettent a jour automatiquement.
B4: N° | C4: Matricule | D4: Nom Evaluate | E4: Departement | F4: Poste | G4: Annee | H4: Auto-evaluation (/20) | I4: N+1 (/20) | J4: Collaborateurs (/20) | K4: Note 360 Moyenne (/20)
B5: 360-001 | C5: EMP-2025-001 | D5: Nganou Clarisse | E5: Ressources Humaines | F5: DRH | G5: 2025 | H5: 18 | I5: 17 | J5: 16 | K5: 17
B6: 360-002 | C6: EMP-2025-002 | D6: Tchinda Armand | E6: Informatique | F6: Chef de service IT | G6: 2025 | H6: 18 | I6: 17 | J6: 19 | K6: 18
B7: 360-003 | C7: EMP-2025-004 | D7: Ouedraogo Ibrahim | E7: Reception & Front Office | F7: Receptionniste | G7: 2025 | H7: 17 | I7: 16 | J7: 15 | K7: 16
B8: 360-004 | C8: EMP-2025-020 | D8: Tagne Rene | E8: Cuisine & Restauration | F8: Cuisinier | G8: 2025 | H8: 16 | I8: 12 | J8: 14 | K8: 14
B9: 360-005 | C9: EMP-2025-005 | D9: Diallo Moussa | E9: Cuisine & Restauration | F9: Chef Cuisine | G9: 2025 | H9: 17 | I9: 16 | J9: 17 | K9: 16.7
B10: =IF(C10="","360-"&TEXT(COUNTA($C$5:C10),"000")) | K10: =IF(H10="","",ROUND((H10+I10+J10)/3,1))
B11: =IF(C11="","360-"&TEXT(COUNTA($C$5:C11),"000")) | K11: =IF(H11="","",ROUND((H11+I11+J11)/3,1))
B12: =IF(C12="","360-"&TEXT(COUNTA($C$5:C12),"000")) | K12: =IF(H12="","",ROUND((H12+I12+J12)/3,1))
B13: =IF(C13="","360-"&TEXT(COUNTA($C$5:C13),"000")) | K13: =IF(H13="","",ROUND((H13+I13+J13)/3,1))
B14: =IF(C14="","360-"&TEXT(COUNTA($C$5:C14),"000")) | K14: =IF(H14="","",ROUND((H14+I14+J14)/3,1))
B15: =IF(C15="","360-"&TEXT(COUNTA($C$5:C15),"000")) | K15: =IF(H15="","",ROUND((H15+I15+J15)/3,1))
B16: =IF(C16="","360-"&TEXT(COUNTA($C$5:C16),"000")) | K16: =IF(H16="","",ROUND((H16+I16+J16)/3,1))
B17: =IF(C17="","360-"&TEXT(COUNTA($C$5:C17),"000")) | K17: =IF(H17="","",ROUND((H17+I17+J17)/3,1))
B18: =IF(C18="","360-"&TEXT(COUNTA($C$5:C18),"000")) | K18: =IF(H18="","",ROUND((H18+I18+J18)/3,1))
B19: =IF(C19="","360-"&TEXT(COUNTA($C$5:C19),"000")) | K19: =IF(H19="","",ROUND((H19+I19+J19)/3,1))
B20: =IF(C20="","360-"&TEXT(COUNTA($C$5:C20),"000")) | K20: =IF(H20="","",ROUND((H20+I20+J20)/3,1))
B21: =IF(C21="","360-"&TEXT(COUNTA($C$5:C21),"000")) | K21: =IF(H21="","",ROUND((H21+I21+J21)/3,1))
... B109: =IF(C109="","360-"&TEXT(COUNTA($C$5:C109),"000")) | K109: =IF(H109="","",ROUND((H109+I109+J109)/3,1))
B111: INDICATEURS (mis a jour automatiquement)
B112: Evaluations 360 | D112: Note 360 moyenne | F112: Note max | H112: Ecart auto vs N+1
B113: =COUNTIF(B5:B104,"<>") | D113: =IFERROR(AVERAGE(K5:K104),0) | F113: =IFERROR(MAX(K5:K104),0) | H113: =IFERROR(AVERAGE(H5:H104)-AVERAGE(I5:I104),0)

Sheet 7-KPI Individuels Employes
B2: SUIVI DES KPI INDIVIDUELS (#81)
B3: TABLEAU DYNAMIQUE — Saisissez dans la prochaine ligne jaune. Les calculs se mettent a jour automatiquement.
B4: N° | C4: Matricule | D4: Nom Employe | E4: Departement | F4: Poste | G4: Indicateur KPI | H4: Cible | I4: Resultat Reel | J4: Ecart | K4: Taux Realisation (%)
B5: KPI-001 | C5: EMP-2025-001 | D5: Nganou Clarisse | E5: Ressources Humaines | F5: DRH | G5: Taux turnover annuel | H5: < 8% | I5: 9.2% | J5: +1.2 pts | K5: 85
B6: KPI-002 | C6: EMP-2025-002 | D6: Tchinda Armand | E6: Informatique | F6: Chef de service IT | G6: Disponibilite reseau | H6: > 99% | I6: 99.5% | J6: +0.5 pts | K6: 100
B7: KPI-003 | C7: EMP-2025-004 | D7: Ouedraogo Ibrahim | E7: Reception & Front Office | F7: Receptionniste | G7: Satisfaction client | H7: > 90% | I7: 92% | J7: +2 pts | K7: 102
B8: KPI-004 | C8: EMP-2025-020 | D8: Tagne Rene | E8: Cuisine & Restauration | F8: Cuisinier | G8: Non conformites HACCP | H8: 0 | I8: 2 | J8: +2 | K8: 0
B9: KPI-005 | C9: EMP-2025-005 | D9: Diallo Moussa | E9: Cuisine & Restauration | F9: Chef Cuisine | G9: Cout food / CA restauration | H9: < 35% | I9: 33% | J9: -2 pts | K9: 106
B10: =IF(C10="","KPI-"&TEXT(COUNTA($C$5:C10),"000"))
B11: =IF(C11="","KPI-"&TEXT(COUNTA($C$5:C11),"000"))
B12: =IF(C12="","KPI-"&TEXT(COUNTA($C$5:C12),"000"))
B13: =IF(C13="","KPI-"&TEXT(COUNTA($C$5:C13),"000"))
B14: =IF(C14="","KPI-"&TEXT(COUNTA($C$5:C14),"000"))
B15: =IF(C15="","KPI-"&TEXT(COUNTA($C$5:C15),"000"))
B16: =IF(C16="","KPI-"&TEXT(COUNTA($C$5:C16),"000"))
B17: =IF(C17="","KPI-"&TEXT(COUNTA($C$5:C17),"000"))
B18: =IF(C18="","KPI-"&TEXT(COUNTA($C$5:C18),"000"))
B19: =IF(C19="","KPI-"&TEXT(COUNTA($C$5:C19),"000"))
B20: =IF(C20="","KPI-"&TEXT(COUNTA($C$5:C20),"000"))
B21: =IF(C21="","KPI-"&TEXT(COUNTA($C$5:C21),"000"))
... B109: =IF(C109="","KPI-"&TEXT(COUNTA($C$5:C109),"000"))
B111: INDICATEURS (mis a jour automatiquement)
B112: KPI suivis | D112: Taux realisation moyen | F112: KPI atteints (>90%) | H112: KPI critiques (<50%)
B113: =COUNTIF(B5:B104,"<>") | D113: =IFERROR(AVERAGE(K5:K104),0) | F113: =COUNTIF(K5:K104,">=90") | H113: =COUNTIF(K5:K104,"<50")

Sheet 8-Plan Amelioration (PAP)
B2: PLAN D'AMELIORATION DE LA PERFORMANCE - PAP (#82)
B3: TABLEAU DYNAMIQUE — Saisissez dans la prochaine ligne jaune. Les calculs se mettent a jour automatiquement.
B4: N° PAP | C4: Matricule | D4: Nom Employe | E4: Departement | F4: Poste | G4: Points Faibles Identifies | H4: Type Action | I4: Action Concrete | J4: Echeance | K4: Evaluateur | L4: Avancement (%) | M4: Statut
B5: PAP-001 | C5: EMP-2025-020 | D5: Tagne Rene | E5: Cuisine & Restauration | F5: Cuisinier | G5: Non conformites HACCP repetees | H5: Formation ciblee | I5: Formation HACCP niveau 2 + suivi hebdo | J5: 45930 | K5: Chef Cuisine | L5: 40 | M5: En cours
B6: PAP-002 | C6: EMP-2025-032 | D6: Mba Carine | E6: Service Client | F6: Conseiller | G6: Accueil clients insuffisant a l'essai | H6: Coaching individuel | I6: Coaching 2h/semaine avec N+1 + observation | J6: 45900 | K6: Chef Service Client | L6: 60 | M6: En cours
B7: PAP-003 | C7: EMP-2025-001 | D7: Nganou Clarisse | E7: Ressources Humaines | F7: DRH | G7: Turnover superieur a l'objectif | H7: Suivi renforce | I7: Entretiens individuels mensuels + plan retention | J7: 46022 | K7: DG | L7: 50 | M7: En cours
B8: PAP-004 | C8: EMP-2025-018 | D8: Fokam Eric | E8: Entretien & Maintenance | F8: Agent Entretien | G8: Retards repetes | H8: Suivi renforce | I8: Pointage quotidien + entretien RH | J8: 45884 | K8: Chef Entretien | L8: 80 | M8: En cours
B9: =IF(C9="","PAP-"&TEXT(COUNTA($C$5:C9),"000"))
B10: =IF(C10="","PAP-"&TEXT(COUNTA($C$5:C10),"000"))
B11: =IF(C11="","PAP-"&TEXT(COUNTA($C$5:C11),"000"))
B12: =IF(C12="","PAP-"&TEXT(COUNTA($C$5:C12),"000"))
B13: =IF(C13="","PAP-"&TEXT(COUNTA($C$5:C13),"000"))
B14: =IF(C14="","PAP-"&TEXT(COUNTA($C$5:C14),"000"))
B15: =IF(C15="","PAP-"&TEXT(COUNTA($C$5:C15),"000"))
B16: =IF(C16="","PAP-"&TEXT(COUNTA($C$5:C16),"000"))
B17: =IF(C17="","PAP-"&TEXT(COUNTA($C$5:C17),"000"))
B18: =IF(C18="","PAP-"&TEXT(COUNTA($C$5:C18),"000"))
B19: =IF(C19="","PAP-"&TEXT(COUNTA($C$5:C19),"000"))
B20: =IF(C20="","PAP-"&TEXT(COUNTA($C$5:C20),"000"))
... B108: =IF(C108="","PAP-"&TEXT(COUNTA($C$5:C108),"000"))
B110: INDICATEURS (mis a jour automatiquement)
B111: PAP suivis | D111: Avancement moyen | F111: En cours | H111: Termines
B112: =COUNTIF(B5:B104,"<>") | D112: =IFERROR(AVERAGE(L5:L104),0) | F112: =COUNTIF(M5:M104,"En cours") | H112: =COUNTIF(M5:M104,"Termine")

Sheet 9-Classement Employes
B2: CLASSEMENT DES EMPLOYES (#83)
B3: TABLEAU DYNAMIQUE — Saisissez dans la prochaine ligne jaune. Les calculs se mettent a jour automatiquement.
B4: N° | C4: Matricule | D4: Nom Employe | E4: Departement | F4: Poste | G4: Annee | H4: Note Globale (/20) | I4: Classement | J4: Decision RH
B5: CL-001 | C5: EMP-2025-002 | D5: Tchinda Armand | E5: Informatique | F5: Chef de service IT | G5: 2025 | H5: 17.7 | I5: A - Excellent | J5: Promotion envisagee
B6: CL-002 | C6: EMP-2025-001 | D6: Nganou Clarisse | E6: Ressources Humaines | F6: DRH | G6: 2025 | H6: 17 | I6: A - Excellent | J6: Maintien + prime
B7: CL-003 | C7: EMP-2025-003 | D7: Fotso Marguerite | E7: Finance & Comptabilite | F7: Comptable senior | G7: 2025 | H7: 17.3 | I7: B - Tres bon | J7: Maintien + augmentation
B8: CL-004 | C8: EMP-2025-004 | D8: Ouedraogo Ibrahim | E8: Reception & Front Office | F8: Receptionniste | G8: 2025 | H8: 16 | I8: C - Bon | J8: Maintien
B9: CL-005 | C9: EMP-2025-020 | D9: Tagne Rene | E9: Cuisine & Restauration | F9: Cuisinier | G9: 2025 | H9: 13 | I9: D - Moyen | J9: PAP obligatoire
B10: =IF(C10="","CL-"&TEXT(COUNTA($C$5:C10),"000"))
B11: =IF(C11="","CL-"&TEXT(COUNTA($C$5:C11),"000"))
B12: =IF(C12="","CL-"&TEXT(COUNTA($C$5:C12),"000"))
B13: =IF(C13="","CL-"&TEXT(COUNTA($C$5:C13),"000"))
B14: =IF(C14="","CL-"&TEXT(COUNTA($C$5:C14),"000"))
B15: =IF(C15="","CL-"&TEXT(COUNTA($C$5:C15),"000"))
B16: =IF(C16="","CL-"&TEXT(COUNTA($C$5:C16),"000"))
B17: =IF(C17="","CL-"&TEXT(COUNTA($C$5:C17),"000"))
B18: =IF(C18="","CL-"&TEXT(COUNTA($C$5:C18),"000"))
B19: =IF(C19="","CL-"&TEXT(COUNTA($C$5:C19),"000"))
B20: =IF(C20="","CL-"&TEXT(COUNTA($C$5:C20),"000"))
B21: =IF(C21="","CL-"&TEXT(COUNTA($C$5:C21),"000"))
... B109: =IF(C109="","CL-"&TEXT(COUNTA($C$5:C109),"000"))
B111: INDICATEURS (mis a jour automatiquement)
B112: Employes classes | D112: Note moyenne (/20) | F112: Cat. A (Excellent) | H112: Cat. E (Insuffisant)
B113: =COUNTIF(B5:B104,"<>") | D113: =IFERROR(AVERAGE(H5:H104),0) | F113: =COUNTIF(I5:I104,"A*") | H113: =COUNTIF(I5:I104,"E*")

Sheet 10-Primes Performance Merite
B2: PRIMES DE PERFORMANCE & DE MERITE (#84)
B3: TABLEAU DYNAMIQUE — Saisissez dans la prochaine ligne jaune. Les calculs se mettent a jour automatiquement.
B4: N° | C4: Matricule | D4: Nom Employe | E4: Departement | F4: Poste | G4: Type Prime | H4: Annee | I4: Base Calcul (FCFA) | J4: Taux (%) | K4: Montant Prime (FCFA) | L4: Statut Paiement
B5: PRM-001 | C5: EMP-2025-002 | D5: Tchinda Armand | E5: Informatique | F5: Chef de service IT | G5: Prime de merite | H5: 2025 | I5: 250000 | J5: 15 | K5: 37500 | L5: En cours
B6: PRM-002 | C6: EMP-2025-001 | D6: Nganou Clarisse | E6: Ressources Humaines | F6: DRH | G6: Prime de rendement | H6: 2025 | I6: 350000 | J6: 12 | K6: 42000 | L6: En cours
B7: PRM-003 | C7: EMP-2025-003 | D7: Fotso Marguerite | E7: Finance & Comptabilite | F7: Comptable senior | G7: Prime de merite | H7: 2025 | I7: 200000 | J7: 10 | K7: 20000 | L7: En cours
B8: PRM-004 | C8: EMP-2025-005 | D8: Diallo Moussa | E8: Cuisine & Restauration | F8: Chef Cuisine | G8: Prime d'equipe | H8: 2025 | I8: 220000 | J8: 8 | K8: 17600 | L8: En attente
B9: PRM-005 | C9: EMP-2025-020 | D9: Tagne Rene | E9: Cuisine & Restauration | F9: Cuisinier | G9: Prime de rendement | H9: 2025 | I9: 120000 | J9: 0 | K9: 0 | L9: Non eligible
B10: =IF(C10="","PRM-"&TEXT(COUNTA($C$5:C10),"000")) | K10: =IF(I10="","",I10*J10)
B11: =IF(C11="","PRM-"&TEXT(COUNTA($C$5:C11),"000")) | K11: =IF(I11="","",I11*J11)
B12: =IF(C12="","PRM-"&TEXT(COUNTA($C$5:C12),"000")) | K12: =IF(I12="","",I12*J12)
B13: =IF(C13="","PRM-"&TEXT(COUNTA($C$5:C13),"000")) | K13: =IF(I13="","",I13*J13)
B14: =IF(C14="","PRM-"&TEXT(COUNTA($C$5:C14),"000")) | K14: =IF(I14="","",I14*J14)
B15: =IF(C15="","PRM-"&TEXT(COUNTA($C$5:C15),"000")) | K15: =IF(I15="","",I15*J15)
B16: =IF(C16="","PRM-"&TEXT(COUNTA($C$5:C16),"000")) | K16: =IF(I16="","",I16*J16)
B17: =IF(C17="","PRM-"&TEXT(COUNTA($C$5:C17),"000")) | K17: =IF(I17="","",I17*J17)
B18: =IF(C18="","PRM-"&TEXT(COUNTA($C$5:C18),"000")) | K18: =IF(I18="","",I18*J18)
B19: =IF(C19="","PRM-"&TEXT(COUNTA($C$5:C19),"000")) | K19: =IF(I19="","",I19*J19)
B20: =IF(C20="","PRM-"&TEXT(COUNTA($C$5:C20),"000")) | K20: =IF(I20="","",I20*J20)
B21: =IF(C21="","PRM-"&TEXT(COUNTA($C$5:C21),"000")) | K21: =IF(I21="","",I21*J21)
... B109: =IF(C109="","PRM-"&TEXT(COUNTA($C$5:C109),"000")) | K109: =IF(I109="","",I109*J109)
B111: TOTAL | I111: =SUM(I5:I104) | K111: =SUM(K5:K104)
B113: INDICATEURS (mis a jour automatiquement)
B114: Primes attribuees | D114: Montant total (FCFA) | F114: Prime moyenne (FCFA) | H114: Non eligibles
B115: =COUNTIF(B5:B104,"<>") | D115: =SUM(K5:K104) | F115: =IFERROR(AVERAGE(K5:K104),0) | H115: =COUNTIF(L5:L104,"Non eligible")

Sheet 11-TdB Individuel Performance
B2: TABLEAU DE BORD INDIVIDUEL DE PERFORMANCE (#85)
B3: TABLEAU DYNAMIQUE — Saisissez dans la prochaine ligne jaune. Les calculs se mettent a jour automatiquement.
B4: N° | C4: Matricule | D4: Nom Employe | E4: Departement | F4: Poste | G4: Annee | H4: Note Annuelle (/20) | I4: Note 360 (/20) | J4: Nb Objectifs Atteints | K4: Nb Objectifs Total | L4: Taux Objectifs (%) | M4: Score Global Perf.
B5: PERF-001 | C5: EMP-2025-001 | D5: Nganou Clarisse | E5: Ressources Humaines | F5: DRH | G5: 2025 | H5: 17 | I5: 17 | J5: 3 | K5: 4 | L5: 75 | M5: 85
B6: PERF-002 | C6: EMP-2025-002 | D6: Tchinda Armand | E6: Informatique | F6: Chef de service IT | G6: 2025 | H6: 17.7 | I6: 18 | J6: 3 | K6: 3 | L6: 100 | M6: 95
B7: PERF-003 | C7: EMP-2025-003 | D7: Fotso Marguerite | E7: Finance & Comptabilite | F7: Comptable senior | G7: 2025 | H7: 17.3 | I7: 0 | J7: 2 | K7: 3 | L7: 67 | M7: 78
B8: PERF-004 | C8: EMP-2025-004 | D8: Ouedraogo Ibrahim | E8: Reception & Front Office | F8: Receptionniste | G8: 2025 | H8: 16 | I8: 16 | J8: 2 | K8: 2 | L8: 100 | M8: 88
B9: PERF-005 | C9: EMP-2025-020 | D9: Tagne Rene | E9: Cuisine & Restauration | F9: Cuisinier | G9: 2025 | H9: 13 | I9: 14 | J9: 0 | K9: 3 | L9: 0 | M9: 45
B10: =IF(C10="","PERF-"&TEXT(COUNTA($C$5:C10),"000")) | L10: =IF(K10="","",IF(K10=0,"",J10/K10))
B11: =IF(C11="","PERF-"&TEXT(COUNTA($C$5:C11),"000")) | L11: =IF(K11="","",IF(K11=0,"",J11/K11))
B12: =IF(C12="","PERF-"&TEXT(COUNTA($C$5:C12),"000")) | L12: =IF(K12="","",IF(K12=0,"",J12/K12))
B13: =IF(C13="","PERF-"&TEXT(COUNTA($C$5:C13),"000")) | L13: =IF(K13="","",IF(K13=0,"",J13/K13))
B14: =IF(C14="","PERF-"&TEXT(COUNTA($C$5:C14),"000")) | L14: =IF(K14="","",IF(K14=0,"",J14/K14))
B15: =IF(C15="","PERF-"&TEXT(COUNTA($C$5:C15),"000")) | L15: =IF(K15="","",IF(K15=0,"",J15/K15))
B16: =IF(C16="","PERF-"&TEXT(COUNTA($C$5:C16),"000")) | L16: =IF(K16="","",IF(K16=0,"",J16/K16))
B17: =IF(C17="","PERF-"&TEXT(COUNTA($C$5:C17),"000")) | L17: =IF(K17="","",IF(K17=0,"",J17/K17))
B18: =IF(C18="","PERF-"&TEXT(COUNTA($C$5:C18),"000")) | L18: =IF(K18="","",IF(K18=0,"",J18/K18))
B19: =IF(C19="","PERF-"&TEXT(COUNTA($C$5:C19),"000")) | L19: =IF(K19="","",IF(K19=0,"",J19/K19))
B20: =IF(C20="","PERF-"&TEXT(COUNTA($C$5:C20),"000")) | L20: =IF(K20="","",IF(K20=0,"",J20/K20))
B21: =IF(C21="","PERF-"&TEXT(COUNTA($C$5:C21),"000")) | L21: =IF(K21="","",IF(K21=0,"",J21/K21))
... B109: =IF(C109="","PERF-"&TEXT(COUNTA($C$5:C109),"000")) | L109: =IF(K109="","",IF(K109=0,"",J109/K109))
B111: TOTAL | J111: =SUM(J5:J104) | K111: =SUM(K5:K104)
B113: INDICATEURS (mis a jour automatiquement)
B114: Employes suivis | D114: Score global moyen | F114: Score max | H114: Score min
B115: =COUNTIF(B5:B104,"<>") | D115: =IFERROR(AVERAGE(M5:M104),0) | F115: =IFERROR(MAX(M5:M104),0) | H115: =IFERROR(MIN(M5:M104),0)

Sheet 12-Bilan Performance par Svc
B2: BILAN DE PERFORMANCE PAR SERVICE (#86)
B3: TABLEAU DYNAMIQUE — Saisissez dans la prochaine ligne jaune. Les calculs se mettent a jour automatiquement.
B4: N° | C4: Departement | D4: Annee | E4: Effectif | F4: Note Moyenne (/20) | G4: Nb Objectifs Atteints | H4: Nb Objectifs Total | I4: Taux Atteinte Obj. (%) | J4: Nb PAP Actifs
B5: BPD-001 | C5: Ressources Humaines | D5: 2025 | E5: 5 | F5: 17 | G5: 6 | H5: 8 | I5: 75 | J5: 1
B6: BPD-002 | C6: Informatique | D6: 2025 | E6: 3 | F6: 17.7 | G6: 5 | H6: 5 | I6: 100 | J6: 0
B7: BPD-003 | C7: Finance & Comptabilite | D7: 2025 | E7: 4 | F7: 16.8 | G7: 5 | H7: 7 | I7: 71 | J7: 0
B8: BPD-004 | C8: Reception & Front Office | D8: 2025 | E8: 6 | F8: 15.5 | G8: 8 | H8: 10 | I8: 80 | J8: 1
B9: BPD-005 | C9: Cuisine & Restauration | D9: 2025 | E9: 8 | F9: 13.8 | G9: 6 | H9: 12 | I9: 50 | J9: 2
B10: BPD-006 | C10: Entretien & Maintenance | D10: 2025 | E10: 6 | F10: 14.2 | G10: 4 | H10: 8 | I10: 50 | J10: 1
B11: BPD-007 | C11: Securite | D11: 2025 | E11: 4 | F11: 15 | G11: 3 | H11: 6 | I11: 50 | J11: 0
B12: =IF(C12="","BPD-"&TEXT(COUNTA($C$5:C12),"000")) | I12: =IF(H12="","",IF(H12=0,"",G12/H12))
B13: =IF(C13="","BPD-"&TEXT(COUNTA($C$5:C13),"000")) | I13: =IF(H13="","",IF(H13=0,"",G13/H13))
B14: =IF(C14="","BPD-"&TEXT(COUNTA($C$5:C14),"000")) | I14: =IF(H14="","",IF(H14=0,"",G14/H14))
B15: =IF(C15="","BPD-"&TEXT(COUNTA($C$5:C15),"000")) | I15: =IF(H15="","",IF(H15=0,"",G15/H15))
B16: =IF(C16="","BPD-"&TEXT(COUNTA($C$5:C16),"000")) | I16: =IF(H16="","",IF(H16=0,"",G16/H16))
B17: =IF(C17="","BPD-"&TEXT(COUNTA($C$5:C17),"000")) | I17: =IF(H17="","",IF(H17=0,"",G17/H17))
B18: =IF(C18="","BPD-"&TEXT(COUNTA($C$5:C18),"000")) | I18: =IF(H18="","",IF(H18=0,"",G18/H18))
B19: =IF(C19="","BPD-"&TEXT(COUNTA($C$5:C19),"000")) | I19: =IF(H19="","",IF(H19=0,"",G19/H19))
B20: =IF(C20="","BPD-"&TEXT(COUNTA($C$5:C20),"000")) | I20: =IF(H20="","",IF(H20=0,"",G20/H20))
B21: =IF(C21="","BPD-"&TEXT(COUNTA($C$5:C21),"000")) | I21: =IF(H21="","",IF(H21=0,"",G21/H21))
B22: =IF(C22="","BPD-"&TEXT(COUNTA($C$5:C22),"000")) | I22: =IF(H22="","",IF(H22=0,"",G22/H22))
B23: =IF(C23="","BPD-"&TEXT(COUNTA($C$5:C23),"000")) | I23: =IF(H23="","",IF(H23=0,"",G23/H23))
... B111: =IF(C111="","BPD-"&TEXT(COUNTA($C$5:C111),"000")) | I111: =IF(H111="","",IF(H111=0,"",G111/H111))
B113: TOTAL | E113: =SUM(E5:E104) | G113: =SUM(G5:G104) | H113: =SUM(H5:H104) | J113: =SUM(J5:J104)
B115: INDICATEURS (mis a jour automatiquement)
B116: Services suivis | D116: Note moyenne hotel (/20) | F116: Taux atteinte moyen | H116: PAP totaux actifs
B117: =COUNTIF(B5:B104,"<>") | D117: =IFERROR(AVERAGE(F5:F104),0) | F117: =IFERROR(AVERAGE(I5:I104),0) | H117: =SUM(J5:J104)

Sheet 13-Historique Eval. Employe
B2: HISTORIQUE DES EVALUATIONS PAR EMPLOYE
B3: TABLEAU DYNAMIQUE — Saisissez dans la prochaine ligne jaune. Les calculs se mettent a jour automatiquement.
B4: N° | C4: Matricule | D4: Nom Employe | E4: Departement | F4: Annee | G4: Note Annuelle (/20) | H4: Classement | I4: Evolution vs N-1 | J4: Prime Obtenue (FCFA)
B5: HE-001 | C5: EMP-2025-001 | D5: Nganou Clarisse | E5: Ressources Humaines | F5: 2025 | G5: 17 | H5: A - Excellent | I5: +1.2 | J5: 42000
B6: HE-001 | C6: EMP-2025-001 | D6: Nganou Clarisse | E6: Ressources Humaines | F6: 2024 | G6: 15.8 | H6: B - Tres bon | I6: +0.8 | J6: 35000
B7: HE-002 | C7: EMP-2025-002 | D7: Tchinda Armand | E7: Informatique | F7: 2025 | G7: 17.7 | H7: A - Excellent | I7: +1.0 | J7: 37500
B8: HE-002 | C8: EMP-2025-002 | D8: Tchinda Armand | E8: Informatique | F8: 2024 | G8: 16.7 | H8: B - Tres bon | I8: +0.5 | J8: 28000
B9: HE-003 | C9: EMP-2025-020 | D9: Tagne Rene | E9: Cuisine & Restauration | F9: 2025 | G9: 13 | H9: D - Moyen | I9: -2.0 | J9: 0
B10: =IF(C10="","HE-"&TEXT(COUNTA($C$5:C10),"000"))
B11: =IF(C11="","HE-"&TEXT(COUNTA($C$5:C11),"000"))
B12: =IF(C12="","HE-"&TEXT(COUNTA($C$5:C12),"000"))
B13: =IF(C13="","HE-"&TEXT(COUNTA($C$5:C13),"000"))
B14: =IF(C14="","HE-"&TEXT(COUNTA($C$5:C14),"000"))
B15: =IF(C15="","HE-"&TEXT(COUNTA($C$5:C15),"000"))
B16: =IF(C16="","HE-"&TEXT(COUNTA($C$5:C16),"000"))
B17: =IF(C17="","HE-"&TEXT(COUNTA($C$5:C17),"000"))
B18: =IF(C18="","HE-"&TEXT(COUNTA($C$5:C18),"000"))
B19: =IF(C19="","HE-"&TEXT(COUNTA($C$5:C19),"000"))
B20: =IF(C20="","HE-"&TEXT(COUNTA($C$5:C20),"000"))
B21: =IF(C21="","HE-"&TEXT(COUNTA($C$5:C21),"000"))
... B109: =IF(C109="","HE-"&TEXT(COUNTA($C$5:C109),"000"))
B111: INDICATEURS (mis a jour automatiquement)
B112: Lignes historique | D112: Note moyenne globale | F112: Total primes (FCFA) | H112: Evolution moyenne
B113: =COUNTIF(B5:B104,"<>") | D113: =IFERROR(AVERAGE(G5:G104),0) | F113: =SUM(J5:J104) | H113: =IFERROR(AVERAGE(I5:I104),0)

Sheet 14-Suivi Essai Mensuel
B2: SUIVI MENSUEL DES EVALUATIONS A L'ESSAI
B3: TABLEAU DYNAMIQUE — Saisissez dans la prochaine ligne jaune. Les calculs se mettent a jour automatiquement.
B4: N° | C4: Mois | D4: Annee | E4: Nb Entrees Essai | F4: Nb Evaluations Realisees | G4: Nb Confirmations | H4: Nb Ruptures | I4: Nb Prolongations
B5: SEM-001 | C5: Janvier | D5: 2025 | E5: 3 | F5: 0 | G5: 0 | H5: 0 | I5: 0
B6: SEM-002 | C6: Fevrier | D6: 2025 | E6: 2 | F6: 1 | G6: 1 | H6: 0 | I6: 0
B7: SEM-003 | C7: Mars | D7: 2025 | E7: 1 | F7: 2 | G7: 1 | H7: 1 | I7: 0
B8: SEM-004 | C8: Avril | D8: 2025 | E8: 2 | F8: 0 | G8: 0 | H8: 0 | I8: 0
B9: SEM-005 | C9: Mai | D9: 2025 | E9: 3 | F9: 0 | G9: 0 | H9: 0 | I9: 0
B10: SEM-006 | C10: Juin | D10: 2025 | E10: 1 | F10: 1 | G10: 0 | H10: 0 | I10: 1
B11: =IF(C11="","SEM-"&TEXT(COUNTA($C$5:C11),"000"))
B12: =IF(C12="","SEM-"&TEXT(COUNTA($C$5:C12),"000"))
B13: =IF(C13="","SEM-"&TEXT(COUNTA($C$5:C13),"000"))
B14: =IF(C14="","SEM-"&TEXT(COUNTA($C$5:C14),"000"))
B15: =IF(C15="","SEM-"&TEXT(COUNTA($C$5:C15),"000"))
B16: =IF(C16="","SEM-"&TEXT(COUNTA($C$5:C16),"000"))
B17: =IF(C17="","SEM-"&TEXT(COUNTA($C$5:C17),"000"))
B18: =IF(C18="","SEM-"&TEXT(COUNTA($C$5:C18),"000"))
B19: =IF(C19="","SEM-"&TEXT(COUNTA($C$5:C19),"000"))
B20: =IF(C20="","SEM-"&TEXT(COUNTA($C$5:C20),"000"))
B21: =IF(C21="","SEM-"&TEXT(COUNTA($C$5:C21),"000"))
B22: =IF(C22="","SEM-"&TEXT(COUNTA($C$5:C22),"000"))
... B110: =IF(C110="","SEM-"&TEXT(COUNTA($C$5:C110),"000"))
B112: TOTAL | E112: =SUM(E5:E104) | F112: =SUM(F5:F104) | G112: =SUM(G5:G104) | H112: =SUM(H5:H104) | I112: =SUM(I5:I104)
B114: INDICATEURS (mis a jour automatiquement)
B115: Mois suivis | D115: Total entrees essai | F115: Total confirmations | H115: Total ruptures
B116: =COUNTIF(B5:B104,"<>") | D116: =SUM(E5:E104) | F116: =SUM(G5:G104) | H116: =SUM(H5:H104)

Sheet 15-Formation & Performance
B2: LIEN FORMATION / PERFORMANCE
B3: TABLEAU DYNAMIQUE — Saisissez dans la prochaine ligne jaune. Les calculs se mettent a jour automatiquement.
B4: N° | C4: Matricule | D4: Nom Employe | E4: Departement | F4: Formation Suivie | G4: Note Avant (/20) | H4: Note Apres (/20) | I4: Progression (pts) | J4: Impact PAP Lie
B5: FP-001 | C5: EMP-2025-020 | D5: Tagne Rene | E5: Cuisine & Restauration | F5: HACCP Niveau 1 | G5: 13 | H5: 14.5 | I5: 1.5 | J5: Oui
B6: FP-002 | C6: EMP-2025-032 | D6: Mba Carine | E6: Service Client | F6: Gestion conflits clients | G6: 12 | H6: 14 | I6: 2 | J6: Oui
B7: FP-003 | C7: EMP-2025-002 | D7: Tchinda Armand | E7: Informatique | F7: Management d'equipe | G7: 17.7 | H7: 18.5 | I7: 0.8 | J7: Non
B8: FP-004 | C8: EMP-2025-018 | D8: Fokam Eric | E8: Entretien & Maintenance | F8: Securite CVC | G8: 14 | H8: 15 | I8: 1 | J8: Oui
B9: =IF(C9="","FP-"&TEXT(COUNTA($C$5:C9),"000")) | I9: =IF(G9="","",IF(H9="","",ROUND(H9-G9,1)))
B10: =IF(C10="","FP-"&TEXT(COUNTA($C$5:C10),"000")) | I10: =IF(G10="","",IF(H10="","",ROUND(H10-G10,1)))
B11: =IF(C11="","FP-"&TEXT(COUNTA($C$5:C11),"000")) | I11: =IF(G11="","",IF(H11="","",ROUND(H11-G11,1)))
B12: =IF(C12="","FP-"&TEXT(COUNTA($C$5:C12),"000")) | I12: =IF(G12="","",IF(H12="","",ROUND(H12-G12,1)))
B13: =IF(C13="","FP-"&TEXT(COUNTA($C$5:C13),"000")) | I13: =IF(G13="","",IF(H13="","",ROUND(H13-G13,1)))
B14: =IF(C14="","FP-"&TEXT(COUNTA($C$5:C14),"000")) | I14: =IF(G14="","",IF(H14="","",ROUND(H14-G14,1)))
B15: =IF(C15="","FP-"&TEXT(COUNTA($C$5:C15),"000")) | I15: =IF(G15="","",IF(H15="","",ROUND(H15-G15,1)))
B16: =IF(C16="","FP-"&TEXT(COUNTA($C$5:C16),"000")) | I16: =IF(G16="","",IF(H16="","",ROUND(H16-G16,1)))
B17: =IF(C17="","FP-"&TEXT(COUNTA($C$5:C17),"000")) | I17: =IF(G17="","",IF(H17="","",ROUND(H17-G17,1)))
B18: =IF(C18="","FP-"&TEXT(COUNTA($C$5:C18),"000")) | I18: =IF(G18="","",IF(H18="","",ROUND(H18-G18,1)))
B19: =IF(C19="","FP-"&TEXT(COUNTA($C$5:C19),"000")) | I19: =IF(G19="","",IF(H19="","",ROUND(H19-G19,1)))
B20: =IF(C20="","FP-"&TEXT(COUNTA($C$5:C20),"000")) | I20: =IF(G20="","",IF(H20="","",ROUND(H20-G20,1)))
... B108: =IF(C108="","FP-"&TEXT(COUNTA($C$5:C108),"000")) | I108: =IF(G108="","",IF(H108="","",ROUND(H108-G108,1)))
B110: INDICATEURS (mis a jour automatiquement)
B111: Formations liees | D111: Progression moyenne (pts) | F111: Liees a un PAP | H111: Progression max
B112: =COUNTIF(B5:B104,"<>") | D112: =IFERROR(AVERAGE(I5:I104),0) | F112: =COUNTIF(J5:J104,"Oui") | H112: =IFERROR(MAX(I5:I104),0)

Sheet 16-Objectifs par Trimestre
B2: SUIVI DES OBJECTIFS PAR TRIMESTRE
B3: TABLEAU DYNAMIQUE — Saisissez dans la prochaine ligne jaune. Les calculs se mettent a jour automatiquement.
B4: N° | C4: Departement | D4: Annee | E4: Trimestre | F4: Nb Objectifs Definis | G4: Nb Atteints | H4: Nb En Cours | I4: Taux Atteinte (%)
B5: OT-001 | C5: Ressources Humaines | D5: 2025 | E5: T1 | F5: 8 | G5: 5 | H5: 3 | I5: 63
B6: OT-002 | C6: Ressources Humaines | D6: 2025 | E6: T2 | F6: 6 | G6: 4 | H6: 2 | I6: 67
B7: OT-003 | C7: Informatique | D7: 2025 | E7: T1 | F7: 5 | G7: 5 | H7: 0 | I7: 100
B8: OT-004 | C8: Informatique | D8: 2025 | E8: T2 | F8: 4 | G8: 3 | H8: 1 | I8: 75
B9: OT-005 | C9: Cuisine & Restauration | D9: 2025 | E9: T1 | F9: 12 | G9: 6 | H9: 4 | I9: 50
B10: OT-006 | C10: Cuisine & Restauration | D10: 2025 | E10: T2 | F10: 10 | G10: 5 | H10: 3 | I10: 50
B11: =IF(C11="","OT-"&TEXT(COUNTA($C$5:C11),"000")) | I11: =IF(F11="","",IF(F11=0,"",G11/F11))
B12: =IF(C12="","OT-"&TEXT(COUNTA($C$5:C12),"000")) | I12: =IF(F12="","",IF(F12=0,"",G12/F12))
B13: =IF(C13="","OT-"&TEXT(COUNTA($C$5:C13),"000")) | I13: =IF(F13="","",IF(F13=0,"",G13/F13))
B14: =IF(C14="","OT-"&TEXT(COUNTA($C$5:C14),"000")) | I14: =IF(F14="","",IF(F14=0,"",G14/F14))
B15: =IF(C15="","OT-"&TEXT(COUNTA($C$5:C15),"000")) | I15: =IF(F15="","",IF(F15=0,"",G15/F15))
B16: =IF(C16="","OT-"&TEXT(COUNTA($C$5:C16),"000")) | I16: =IF(F16="","",IF(F16=0,"",G16/F16))
B17: =IF(C17="","OT-"&TEXT(COUNTA($C$5:C17),"000")) | I17: =IF(F17="","",IF(F17=0,"",G17/F17))
B18: =IF(C18="","OT-"&TEXT(COUNTA($C$5:C18),"000")) | I18: =IF(F18="","",IF(F18=0,"",G18/F18))
B19: =IF(C19="","OT-"&TEXT(COUNTA($C$5:C19),"000")) | I19: =IF(F19="","",IF(F19=0,"",G19/F19))
B20: =IF(C20="","OT-"&TEXT(COUNTA($C$5:C20),"000")) | I20: =IF(F20="","",IF(F20=0,"",G20/F20))
B21: =IF(C21="","OT-"&TEXT(COUNTA($C$5:C21),"000")) | I21: =IF(F21="","",IF(F21=0,"",G21/F21))
B22: =IF(C22="","OT-"&TEXT(COUNTA($C$5:C22),"000")) | I22: =IF(F22="","",IF(F22=0,"",G22/F22))
... B110: =IF(C110="","OT-"&TEXT(COUNTA($C$5:C110),"000")) | I110: =IF(F110="","",IF(F110=0,"",G110/F110))
B112: TOTAL | F112: =SUM(F5:F104) | G112: =SUM(G5:G104) | H112: =SUM(H5:H104)
B114: INDICATEURS (mis a jour automatiquement)
B115: Lignes suivies | D115: Total objectifs definis | F115: Taux atteinte global | H115: Total en cours
B116: =COUNTIF(B5:B104,"<>") | D116: =SUM(F5:F104) | F116: =IFERROR(SUM(G5:G104)/SUM(F5:F104),0) | H116: =SUM(H5:H104)

Sheet 17-Rapports Evaluation
B2: RAPPORTS D'EVALUATION DE LA PERFORMANCE
B3: TABLEAU DYNAMIQUE — Saisissez dans la prochaine ligne jaune. Les calculs se mettent a jour automatiquement.
B4: N° Rapport | C4: Type Rapport | D4: Titre | E4: Periode Debut | F4: Periode Fin | G4: Departement | H4: Auteur | I4: Note Moyenne (/20) | J4: Nb Evaluations | K4: Recommandations | L4: Statut
B5: RE-001 | C5: Bilan annuel | D5: Bilan evaluations 2024 | E5: 45292 | F5: 45657 | G5: Tous | H5: DRH Nganou | I5: 15.8 | J5: 42 | K5: Renforcer accompagnement Cuisine | L5: Approuve
B6: RE-002 | C6: Bilan trimestriel | D6: Bilan performance T2 2025 | E6: 45748 | F6: 45838 | G6: Tous | H6: Assistante RH | I6: 16.2 | J6: 38 | K6: Prioriser formations service client | L6: Valide
B7: RE-003 | C7: Rapport essai | D7: Bilan essais T1 2025 | E7: 45658 | F7: 45747 | G7: Tous | H7: DRH Nganou | I7: 14.5 | J7: 6 | K7: Ameliorer processus integration | L7: Brouillon
B8: =IF(C8="","RE-"&TEXT(COUNTA($C$5:C8),"000"))
B9: =IF(C9="","RE-"&TEXT(COUNTA($C$5:C9),"000"))
B10: =IF(C10="","RE-"&TEXT(COUNTA($C$5:C10),"000"))
B11: =IF(C11="","RE-"&TEXT(COUNTA($C$5:C11),"000"))
B12: =IF(C12="","RE-"&TEXT(COUNTA($C$5:C12),"000"))
B13: =IF(C13="","RE-"&TEXT(COUNTA($C$5:C13),"000"))
B14: =IF(C14="","RE-"&TEXT(COUNTA($C$5:C14),"000"))
B15: =IF(C15="","RE-"&TEXT(COUNTA($C$5:C15),"000"))
B16: =IF(C16="","RE-"&TEXT(COUNTA($C$5:C16),"000"))
B17: =IF(C17="","RE-"&TEXT(COUNTA($C$5:C17),"000"))
B18: =IF(C18="","RE-"&TEXT(COUNTA($C$5:C18),"000"))
B19: =IF(C19="","RE-"&TEXT(COUNTA($C$5:C19),"000"))
... B107: =IF(C107="","RE-"&TEXT(COUNTA($C$5:C107),"000"))
B109: TOTAL | J109: =SUM(J5:J104)
B111: INDICATEURS (mis a jour automatiquement)
B112: Total rapports | D112: Evaluations couvertes | F112: Note moyenne rapports | H112: Approuves
B113: =COUNTIF(B5:B104,"<>") | D113: =SUM(J5:J104) | F113: =IFERROR(AVERAGE(I5:I104),0) | H113: =COUNTIF(L5:L104,"Approuve")

Sheet 18-Decisions RH Post-Eval.
B2: DECISIONS RH POST-EVALUATION
B3: TABLEAU DYNAMIQUE — Saisissez dans la prochaine ligne jaune. Les calculs se mettent a jour automatiquement.
B4: N° | C4: Matricule | D4: Nom Employe | E4: Departement | F4: Annee | G4: Note Globale (/20) | H4: Decision RH | I4: Montant Associate (FCFA) | J4: Date Mise en Oeuvre
B5: DEC-001 | C5: EMP-2025-002 | D5: Tchinda Armand | E5: Informatique | F5: 2025 | G5: 17.7 | H5: Promotion + prime merite | I5: 37500 | J5: 45839
B6: DEC-002 | C6: EMP-2025-001 | D6: Nganou Clarisse | E6: Ressources Humaines | F6: 2025 | G6: 17 | H6: Maintien + prime rendement | I6: 42000 | J6: 45839
B7: DEC-003 | C7: EMP-2025-003 | D7: Fotso Marguerite | E7: Finance & Comptabilite | F7: 2025 | G7: 17.3 | H7: Augmentation salariale 5% | I7: 10000 | J7: 45839
B8: DEC-004 | C8: EMP-2025-020 | D8: Tagne Rene | E8: Cuisine & Restauration | F8: 2025 | G8: 13 | H8: PAP obligatoire + pas de prime | I8: 0 | J8: 45828
B9: DEC-005 | C9: EMP-2025-033 | D9: Tamo Elvis | E9: Cuisine & Restauration | F9: 2025 | G9: 8 | H9: Rupture periode essai | I9: 0 | J9: 45853
B10: =IF(C10="","DEC-"&TEXT(COUNTA($C$5:C10),"000"))
B11: =IF(C11="","DEC-"&TEXT(COUNTA($C$5:C11),"000"))
B12: =IF(C12="","DEC-"&TEXT(COUNTA($C$5:C12),"000"))
B13: =IF(C13="","DEC-"&TEXT(COUNTA($C$5:C13),"000"))
B14: =IF(C14="","DEC-"&TEXT(COUNTA($C$5:C14),"000"))
B15: =IF(C15="","DEC-"&TEXT(COUNTA($C$5:C15),"000"))
B16: =IF(C16="","DEC-"&TEXT(COUNTA($C$5:C16),"000"))
B17: =IF(C17="","DEC-"&TEXT(COUNTA($C$5:C17),"000"))
B18: =IF(C18="","DEC-"&TEXT(COUNTA($C$5:C18),"000"))
B19: =IF(C19="","DEC-"&TEXT(COUNTA($C$5:C19),"000"))
B20: =IF(C20="","DEC-"&TEXT(COUNTA($C$5:C20),"000"))
B21: =IF(C21="","DEC-"&TEXT(COUNTA($C$5:C21),"000"))
... B109: =IF(C109="","DEC-"&TEXT(COUNTA($C$5:C109),"000"))
B111: TOTAL | I111: =SUM(I5:I104)
B113: INDICATEURS (mis a jour automatiquement)
B114: Decisions prises | D114: Cout total decisions (FCFA) | F114: Promotions | H114: Ruptures
B115: =COUNTIF(B5:B104,"<>") | D115: =SUM(I5:I104) | F115: =COUNTIF(H5:H104,"*Promotion*") | H115: =COUNTIF(H5:H104,"*Rupture*")
