Workbook

Sheet 1-Tableau de Bord
B2: DOMAINE 2 — GESTION ADMINISTRATIVE DU PERSONNEL
B3: TABLEAU DE BORD — Vue synthetique de tous les indicateurs du domaine (mis a jour automatiquement)
B5: Effectif Total | E5: Employes actifs | H5: Cadres | K5: CDI
B6: =COUNTIF('2-Fiche Employe'!B5:B104,"<>") | E6: =COUNTIF('2-Fiche Employe'!T5:T104,"Actif") | H6: =COUNTIF('2-Fiche Employe'!Q5:Q104,"Cadre") | K6: =COUNTIF('2-Fiche Employe'!P5:P104,"CDI")
B9: Contrats en vigueur | E9: Masse salariale brute | H9: Avenants en attente | K9: CDD/Interim
B10: =COUNTIF('3-Contrats Travail'!H5:H104,"En vigueur") | E10: =SUM('3-Contrats Travail'!I5:I104) | H10: =COUNTIF('4-Avenants Contrat'!L5:L104,"En attente") | K10: =COUNTIF('3-Contrats Travail'!E5:E104,"CDD")+COUNTIF('3-Contrats Travail'!E5:E104,"Interim")
B13: Documents valides | E13: A renouveler | H13: Permis valides | K13: Rappels en retard
B14: =COUNTIF('5-Suivi Documents'!I5:I104,"Valide") | E14: =COUNTIF('5-Suivi Documents'!I5:I104,"A renouveler") | H14: =COUNTIF('15-Autorisations Permis'!J5:J104,"Valide") | K14: =COUNTIF('18-Rappels Admin'!I5:I104,"En retard")
B17: Absences (total jours) | E17: Conges approuves | H17: Heures supp totales | K17: Taux presence moy.
B18: =SUM('10-Absences Maladie'!H5:H104) | E18: =COUNTIF('8-Conges Annuels'!J5:J104,"Approuve") | H18: =SUM('11-Heures Supplementaires'!G5:G104) | K18: =IFERROR(AVERAGE('12-Pointage Presence'!J5:J104),0)
B21: Total net paye (FCFA) | E21: Total cotisations | H21: Declarations en retard | K21: Dossiers departs clos
B22: =SUM('13-Fiches de Paie'!H5:H104) | E22: =SUM('13-Fiches de Paie'!G5:G104) | H22: =COUNTIF('14-Declarations Sociales'!I5:I104,"En retard") | K22: =COUNTIF('16-Dossiers Departs'!K5:K104,"Clos")
B26: REPARTITION PAR DEPARTEMENT ET STATUT
B27: Departement | C27: Effectif
B28: Direction Generale | C28: =COUNTIF('2-Fiche Employe'!N5:N104,B28)
B29: Service Client | C29: =COUNTIF('2-Fiche Employe'!N5:N104,B29)
B30: Finance & Comptabilité | C30: =COUNTIF('2-Fiche Employe'!N5:N104,B30)
B31: Marketing & Communication | C31: =COUNTIF('2-Fiche Employe'!N5:N104,B31)
B32: Maintenance | C32: =COUNTIF('2-Fiche Employe'!N5:N104,B32)
B33: Commercial | C33: =COUNTIF('2-Fiche Employe'!N5:N104,B33)
B34: Logistique & Approvisionnement | C34: =COUNTIF('2-Fiche Employe'!N5:N104,B34)
B35: Cuisine & Restauration | C35: =COUNTIF('2-Fiche Employe'!N5:N104,B35)
B36: Service Client | C36: =COUNTIF('2-Fiche Employe'!N5:N104,B36)
B37: Réception & Front Office | C37: =COUNTIF('2-Fiche Employe'!N5:N104,B37)
B38: Cuisine & Restauration | C38: =COUNTIF('2-Fiche Employe'!N5:N104,B38)
B39: Maintenance | C39: =COUNTIF('2-Fiche Employe'!N5:N104,B39)
B40: Sécurité | C40: =COUNTIF('2-Fiche Employe'!N5:N104,B40)
H42: Type Contrat | I42: Nombre
H43: CDI | I43: =COUNTIF('2-Fiche Employe'!P5:P104,H43)
H44: CDD | I44: =COUNTIF('2-Fiche Employe'!P5:P104,H44)
H45: Stage | I45: =COUNTIF('2-Fiche Employe'!P5:P104,H45)
H46: Interim | I46: =COUNTIF('2-Fiche Employe'!P5:P104,H46)
H47: Alternance | I47: =COUNTIF('2-Fiche Employe'!P5:P104,H47)
H48: Freelance | I48: =COUNTIF('2-Fiche Employe'!P5:P104,H48)
B51: Prêts en cours | E51: Total avances (FCFA) | H51: Sanctions année | K51: Visites à planifier
B52: =COUNTIF('19-Prets Avances Salaire'!O5:O104,"En cours") | E52: =SUMPRODUCT(('19-Prets Avances Salaire'!F5:F104<>"")*'19-Prets Avances Salaire'!F5:F104) | H52: =COUNTA('20-Sanctions Disciplinaires'!C5:C104) | K52: =COUNTIF('21-Visites Medicales'!I5:I104,"<=30")-COUNTIF('21-Visites Medicales'!I5:I104,"<0")
B55: Taux présence moy. (%) | E55: Total retards (min) | H55: Heures supp mensuelles | K55: Indemnités départs (FCFA)
B56: =IFERROR(AVERAGE('22-Planning Mensuel Presence'!L5:L104),0) | E56: =SUM('22-Planning Mensuel Presence'!J5:J104) | H56: =SUM('22-Planning Mensuel Presence'!K5:K104) | K56: =SUM('16-Dossiers Departs'!L5:L104)
B59: Type Sanction | C59: Nombre
B60: Avertissement oral | C60: =COUNTIF('20-Sanctions Disciplinaires'!E5:E104,B60)
B61: Avertissement écrit | C61: =COUNTIF('20-Sanctions Disciplinaires'!E5:E104,B61)
B62: Blâme | C62: =COUNTIF('20-Sanctions Disciplinaires'!E5:E104,B62)
B63: Suspension | C63: =COUNTIF('20-Sanctions Disciplinaires'!E5:E104,B63)
B64: Mise à pied | C64: =COUNTIF('20-Sanctions Disciplinaires'!E5:E104,B64)
B67: Type Prêt | C67: Montant Total
B68: Avance salaire | C68: =SUMPRODUCT(('19-Prets Avances Salaire'!E5:E104=B68)*'19-Prets Avances Salaire'!F5:F104)
B69: Prêt social | C69: =SUMPRODUCT(('19-Prets Avances Salaire'!E5:E104=B69)*'19-Prets Avances Salaire'!F5:F104)
B70: Prêt logement | C70: =SUMPRODUCT(('19-Prets Avances Salaire'!E5:E104=B70)*'19-Prets Avances Salaire'!F5:F104)
B71: Prêt urgence | C71: =SUMPRODUCT(('19-Prets Avances Salaire'!E5:E104=B71)*'19-Prets Avances Salaire'!F5:F104)
B72: Prêt formation | C72: =SUMPRODUCT(('19-Prets Avances Salaire'!E5:E104=B72)*'19-Prets Avances Salaire'!F5:F104)

Sheet 2-Fiche Employe
B2: FICHE EMPLOYE — REPERTOIRE DU PERSONNEL
B3: TABLEAU DYNAMIQUE — Saisissez dans la prochaine ligne jaune. Les calculs se mettent a jour automatiquement.
B4: N° Matricule | C4: Civilité | D4: Nom | E4: Prénom | F4: Date Naissance | G4: Lieu Naissance | H4: Genre | I4: Nationalité | J4: Situation Familiale | K4: N° Téléphone | L4: Email | M4: Adresse | N4: Département | O4: Poste | P4: Type Contrat | Q4: Catégorie | R4: Régime Travail | S4: Date Embauche | T4: Ancienneté (ans) | U4: Statut
B5: EMP-001 | C5: M. | D5: Nganou | E5: Clarisse | F5: 32217 | G5: Douala | H5: Feminin | I5: Camerounaise | J5: Marie(e) | K5: 699123456 | L5: c.nganou@hotel.com | M5: Douala Bonapriso | N5: Service Client | O5: DRH | P5: CDI | Q5: Cadre | R5: Temps plein | S5: 43845 | T5: =IF(S5="","",IFERROR((TODAY()-S5)/365.25,0)) | U5: Actif
B6: EMP-002 | C6: M. | D6: Tchinda | E6: Armand | F6: 33807 | G6: Yaoundé | H6: Masculin | I6: Camerounaise | J6: Celibataire | K6: 677234567 | L6: a.tchinda@hotel.com | M6: Douala Makepe | N6: Maintenance | O6: Chef de service IT | P6: CDI | Q6: Cadre | R6: Temps plein | S6: 43617 | T6: =IF(S6="","",IFERROR((TODAY()-S6)/365.25,0)) | U6: Actif
B7: EMP-003 | C7: Mme | D7: Fotso | E7: Marguerite | F7: 31359 | G7: Bafoussam | H7: Feminin | I7: Camerounaise | J7: Divorce(e) | K7: 698345678 | L7: m.fotso@hotel.com | M7: Douala Akwa | N7: Finance & Comptabilité | O7: Comptable senior | P7: CDI | Q7: Cadre | R7: Temps plein | S7: 42795 | T7: =IF(S7="","",IFERROR((TODAY()-S7)/365.25,0)) | U7: Actif
B8: EMP-004 | C8: M. | D8: Ouedraogo | E8: Ibrahim | F8: 34744 | G8: Garoua | H8: Masculin | I8: Camerounaise | J8: Celibataire | K8: 690456789 | L8: i.ouedraogo@hotel.com | M8: Douala Deido | N8: Logistique & Approvisionnement | O8: Magasinier | P8: CDI | Q8: Employe | R8: Temps plein | S8: 44454 | T8: =IF(S8="","",IFERROR((TODAY()-S8)/365.25,0)) | U8: Actif
B9: EMP-005 | C9: M. | D9: Diallo | E9: Moussa | F9: 33054 | G9: Maroua | H9: Masculin | I9: Camerounaise | J9: Marie(e) | K9: 677567890 | L9: m.diallo@hotel.com | M9: Douala Bonaberi | N9: Cuisine & Restauration | O9: Operateur de production | P9: Interim | Q9: Ouvrier | R9: Temps plein | S9: 45383 | T9: =IF(S9="","",IFERROR((TODAY()-S9)/365.25,0)) | U9: Actif
B10: =IF(C10="","EMP-"&TEXT(COUNTA($C$5:C10),"000")) | T10: =IF(S10="","",IFERROR((TODAY()-S10)/365.25,0))
B11: =IF(C11="","EMP-"&TEXT(COUNTA($C$5:C11),"000")) | T11: =IF(S11="","",IFERROR((TODAY()-S11)/365.25,0))
B12: =IF(C12="","EMP-"&TEXT(COUNTA($C$5:C12),"000")) | T12: =IF(S12="","",IFERROR((TODAY()-S12)/365.25,0))
B13: =IF(C13="","EMP-"&TEXT(COUNTA($C$5:C13),"000")) | T13: =IF(S13="","",IFERROR((TODAY()-S13)/365.25,0))
B14: =IF(C14="","EMP-"&TEXT(COUNTA($C$5:C14),"000")) | T14: =IF(S14="","",IFERROR((TODAY()-S14)/365.25,0))
B15: =IF(C15="","EMP-"&TEXT(COUNTA($C$5:C15),"000")) | T15: =IF(S15="","",IFERROR((TODAY()-S15)/365.25,0))
B16: =IF(C16="","EMP-"&TEXT(COUNTA($C$5:C16),"000")) | T16: =IF(S16="","",IFERROR((TODAY()-S16)/365.25,0))
B17: =IF(C17="","EMP-"&TEXT(COUNTA($C$5:C17),"000")) | T17: =IF(S17="","",IFERROR((TODAY()-S17)/365.25,0))
B18: =IF(C18="","EMP-"&TEXT(COUNTA($C$5:C18),"000")) | T18: =IF(S18="","",IFERROR((TODAY()-S18)/365.25,0))
B19: =IF(C19="","EMP-"&TEXT(COUNTA($C$5:C19),"000")) | T19: =IF(S19="","",IFERROR((TODAY()-S19)/365.25,0))
B20: =IF(C20="","EMP-"&TEXT(COUNTA($C$5:C20),"000")) | T20: =IF(S20="","",IFERROR((TODAY()-S20)/365.25,0))
B21: =IF(C21="","EMP-"&TEXT(COUNTA($C$5:C21),"000")) | T21: =IF(S21="","",IFERROR((TODAY()-S21)/365.25,0))
... B104: =IF(C104="","EMP-"&TEXT(COUNTA($C$5:C104),"000")) | T104: =IF(S104="","",IFERROR((TODAY()-S104)/365.25,0))
B105: =IF(C105="","EMP-"&TEXT(COUNTA($C$5:C105),"000"))
B106: =IF(C106="","EMP-"&TEXT(COUNTA($C$5:C106),"000"))
B107: =IF(C107="","EMP-"&TEXT(COUNTA($C$5:C107),"000"))
B108: =IF(C108="","EMP-"&TEXT(COUNTA($C$5:C108),"000"))
B109: =IF(C109="","EMP-"&TEXT(COUNTA($C$5:C109),"000"))
B111: INDICATEURS (mis a jour automatiquement)
B112: Effectif total | D112: Employes actifs | F112: Cadres | H112: CDI
B113: =COUNTIF(B5:B104,"<>") | D113: =COUNTIF(T5:T104,"Actif") | F113: =COUNTIF(Q5:Q104,"Cadre") | H113: =COUNTIF(P5:P104,"CDI")

Sheet 3-Contrats Travail
B2: CONTRATS DE TRAVAIL
B3: TABLEAU DYNAMIQUE — Saisissez dans la prochaine ligne jaune. Les calculs se mettent a jour automatiquement.
B4: N° Contrat | C4: Matricule | D4: Nom Employé | E4: Type Contrat | F4: Date Début | G4: Date Fin | H4: Durée (mois) | I4: Jours Restants | J4: Statut | K4: Salaire Brut (FCFA) | L4: Régime Travail | M4: Lieu Travail | N4: Observations
B5: CTR-2025-001 | C5: EMP-001 | D5: Nganou Clarisse | E5: CDI | F5: 43845 | H5: =IF(OR(F5="",G5=""),"",IFERROR((G5-F5)/30.44,0)) | I5: =IF(G5="","",IFERROR(MAX(G5-TODAY(),0),0)) | J5: En vigueur | K5: 450000 | L5: Temps plein | M5: Siège Douala | N5: Contrat initial
B6: CTR-2025-002 | C6: EMP-002 | D6: Tchinda Armand | E6: CDI | F6: 43617 | H6: =IF(OR(F6="",G6=""),"",IFERROR((G6-F6)/30.44,0)) | I6: =IF(G6="","",IFERROR(MAX(G6-TODAY(),0),0)) | J6: En vigueur | K6: 420000 | L6: Temps plein | M6: Siège Douala | N6: Contrat initial
B7: CTR-2025-003 | C7: EMP-003 | D7: Fotso Marguerite | E7: CDI | F7: 42795 | H7: =IF(OR(F7="",G7=""),"",IFERROR((G7-F7)/30.44,0)) | I7: =IF(G7="","",IFERROR(MAX(G7-TODAY(),0),0)) | J7: En vigueur | K7: 380000 | L7: Temps plein | M7: Siège Douala | N7: Contrat initial
B8: CTR-2025-004 | C8: EMP-004 | D8: Nkoulou Mbarga | E8: CDI | F8: 44454 | H8: =IF(OR(F8="",G8=""),"",IFERROR((G8-F8)/30.44,0)) | I8: =IF(G8="","",IFERROR(MAX(G8-TODAY(),0),0)) | J8: En vigueur | K8: 180000 | L8: Temps plein | M8: Entrepôt Douala | N8: Contrat initial
B9: CTR-2025-005 | C9: EMP-005 | D9: Kamga Paul | E9: Interim | F9: 45383 | G9: 45747 | H9: =IF(OR(F9="",G9=""),"",IFERROR((G9-F9)/30.44,0)) | I9: =IF(G9="","",IFERROR(MAX(G9-TODAY(),0),0)) | J9: En vigueur | K9: 130000 | L9: Temps plein | M9: Atelier Douala | N9: CDD 12 mois via Manpower
B10: =IF(C10="","CTR-"&TEXT(COUNTA($C$5:C10),"000")) | H10: =IF(OR(F10="",G10=""),"",IFERROR((G10-F10)/30.44,0)) | I10: =IF(G10="","",IFERROR(MAX(G10-TODAY(),0),0))
B11: =IF(C11="","CTR-"&TEXT(COUNTA($C$5:C11),"000")) | H11: =IF(OR(F11="",G11=""),"",IFERROR((G11-F11)/30.44,0)) | I11: =IF(G11="","",IFERROR(MAX(G11-TODAY(),0),0))
B12: =IF(C12="","CTR-"&TEXT(COUNTA($C$5:C12),"000")) | H12: =IF(OR(F12="",G12=""),"",IFERROR((G12-F12)/30.44,0)) | I12: =IF(G12="","",IFERROR(MAX(G12-TODAY(),0),0))
B13: =IF(C13="","CTR-"&TEXT(COUNTA($C$5:C13),"000")) | H13: =IF(OR(F13="",G13=""),"",IFERROR((G13-F13)/30.44,0)) | I13: =IF(G13="","",IFERROR(MAX(G13-TODAY(),0),0))
B14: =IF(C14="","CTR-"&TEXT(COUNTA($C$5:C14),"000")) | H14: =IF(OR(F14="",G14=""),"",IFERROR((G14-F14)/30.44,0)) | I14: =IF(G14="","",IFERROR(MAX(G14-TODAY(),0),0))
B15: =IF(C15="","CTR-"&TEXT(COUNTA($C$5:C15),"000")) | H15: =IF(OR(F15="",G15=""),"",IFERROR((G15-F15)/30.44,0)) | I15: =IF(G15="","",IFERROR(MAX(G15-TODAY(),0),0))
B16: =IF(C16="","CTR-"&TEXT(COUNTA($C$5:C16),"000")) | H16: =IF(OR(F16="",G16=""),"",IFERROR((G16-F16)/30.44,0)) | I16: =IF(G16="","",IFERROR(MAX(G16-TODAY(),0),0))
B17: =IF(C17="","CTR-"&TEXT(COUNTA($C$5:C17),"000")) | H17: =IF(OR(F17="",G17=""),"",IFERROR((G17-F17)/30.44,0)) | I17: =IF(G17="","",IFERROR(MAX(G17-TODAY(),0),0))
B18: =IF(C18="","CTR-"&TEXT(COUNTA($C$5:C18),"000")) | H18: =IF(OR(F18="",G18=""),"",IFERROR((G18-F18)/30.44,0)) | I18: =IF(G18="","",IFERROR(MAX(G18-TODAY(),0),0))
B19: =IF(C19="","CTR-"&TEXT(COUNTA($C$5:C19),"000")) | H19: =IF(OR(F19="",G19=""),"",IFERROR((G19-F19)/30.44,0)) | I19: =IF(G19="","",IFERROR(MAX(G19-TODAY(),0),0))
B20: =IF(C20="","CTR-"&TEXT(COUNTA($C$5:C20),"000")) | H20: =IF(OR(F20="",G20=""),"",IFERROR((G20-F20)/30.44,0)) | I20: =IF(G20="","",IFERROR(MAX(G20-TODAY(),0),0))
B21: =IF(C21="","CTR-"&TEXT(COUNTA($C$5:C21),"000")) | H21: =IF(OR(F21="",G21=""),"",IFERROR((G21-F21)/30.44,0)) | I21: =IF(G21="","",IFERROR(MAX(G21-TODAY(),0),0))
... B104: =IF(C104="","CTR-"&TEXT(COUNTA($C$5:C104),"000")) | H104: =IF(OR(F104="",G104=""),"",IFERROR((G104-F104)/30.44,0)) | I104: =IF(G104="","",IFERROR(MAX(G104-TODAY(),0),0))
B105: =IF(C105="","CTR-"&TEXT(COUNTA($C$5:C105),"000"))
B106: =IF(C106="","CTR-"&TEXT(COUNTA($C$5:C106),"000"))
B107: =IF(C107="","CTR-"&TEXT(COUNTA($C$5:C107),"000"))
B108: =IF(C108="","CTR-"&TEXT(COUNTA($C$5:C108),"000"))
B109: =IF(C109="","CTR-"&TEXT(COUNTA($C$5:C109),"000"))
B111: TOTAL | K111: =SUM(I5:I104)
B113: INDICATEURS (mis a jour automatiquement)
B114: Total contrats | D114: En vigueur | F114: Masse salariale brute
B115: =COUNTIF(B5:B104,"<>") | D115: =COUNTIF(H5:H104,"En vigueur") | F115: =SUM(I5:I104)

Sheet 4-Avenants Contrat
B2: AVENANTS AU CONTRAT
B3: TABLEAU DYNAMIQUE — Saisissez dans la prochaine ligne jaune. Les calculs se mettent a jour automatiquement.
B4: N° Avenant | C4: N° Contrat | D4: Matricule | E4: Nom Employé | F4: Date Avenant | G4: Type Modification | H4: Ancienne Valeur | I4: Nouvelle Valeur | J4: Motif | K4: Date Effet | L4: Statut
B5: AV-2025-001 | C5: CTR-2025-001 | D5: EMP-001 | E5: Nganou Clarisse | F5: 45301 | G5: Modification salariale | H5: 400 000 FCFA | I5: 450 000 FCFA | J5: Promotion | K5: 45292 | L5: Approuve
B6: AV-2025-002 | C6: CTR-2025-002 | D6: EMP-002 | E6: Tchinda Armand | F6: 45078 | G6: Changement poste | H6: Technicien IT | I6: Chef de service IT | J6: Promotion interne | K6: 45078 | L6: Approuve
B7: AV-2025-003 | C7: CTR-2025-001 | D7: EMP-001 | E7: Nganou Clarisse | F7: 45717 | G7: Modification salariale | H7: 450 000 FCFA | I7: 500 000 FCFA | J7: Augmentation annuelle | K7: 45717 | L7: En attente
B8: =IF(C8="","AV-"&TEXT(COUNTA($C$5:C8),"000"))
B9: =IF(C9="","AV-"&TEXT(COUNTA($C$5:C9),"000"))
B10: =IF(C10="","AV-"&TEXT(COUNTA($C$5:C10),"000"))
B11: =IF(C11="","AV-"&TEXT(COUNTA($C$5:C11),"000"))
B12: =IF(C12="","AV-"&TEXT(COUNTA($C$5:C12),"000"))
B13: =IF(C13="","AV-"&TEXT(COUNTA($C$5:C13),"000"))
B14: =IF(C14="","AV-"&TEXT(COUNTA($C$5:C14),"000"))
B15: =IF(C15="","AV-"&TEXT(COUNTA($C$5:C15),"000"))
B16: =IF(C16="","AV-"&TEXT(COUNTA($C$5:C16),"000"))
B17: =IF(C17="","AV-"&TEXT(COUNTA($C$5:C17),"000"))
B18: =IF(C18="","AV-"&TEXT(COUNTA($C$5:C18),"000"))
B19: =IF(C19="","AV-"&TEXT(COUNTA($C$5:C19),"000"))
... B107: =IF(C107="","AV-"&TEXT(COUNTA($C$5:C107),"000"))
B109: INDICATEURS (mis a jour automatiquement)
B110: Total avenants | D110: En attente
B111: =COUNTIF(B5:B104,"<>") | D111: =COUNTIF(L5:L104,"En attente")

Sheet 5-Suivi Documents
B2: SUIVI DES DOCUMENTS DU PERSONNEL
B3: TABLEAU DYNAMIQUE — Saisissez dans la prochaine ligne jaune. Les calculs se mettent a jour automatiquement.
B4: N° | C4: Matricule | D4: Nom Employé | E4: Type Document | F4: N° Document | G4: Date Émission | H4: Date Expiration | I4: Jours Restants | J4: Statut | K4: Lieu Dépôt | L4: Notes
B5: DOC-001 | C5: EMP-001 | D5: Nganou Clarisse | E5: CNI | F5: 123456789 | G5: 44576 | H5: 46402 | I5: =IF(H5="","",IFERROR(MAX(H5-TODAY(),0),0)) | J5: Valide | K5: RH Central | L5: CNI 5 ans
B6: DOC-002 | C6: EMP-001 | D6: Nganou Clarisse | E6: Attestation CNPS | F6: CNPS-78901 | G6: 45658 | H6: 46022 | I6: =IF(H6="","",IFERROR(MAX(H6-TODAY(),0),0)) | J6: Valide | K6: RH Central | L6: Attestation annuelle
B7: DOC-003 | C7: EMP-002 | D7: Tchinda Armand | E7: Passeport | F7: AB123456 | G7: 44357 | H7: 48009 | I7: =IF(H7="","",IFERROR(MAX(H7-TODAY(),0),0)) | J7: Valide | K7: RH Central | L7: Passeport 10 ans
B8: DOC-004 | C8: EMP-003 | D8: Fotso Marguerite | E8: Certificat medical | F8: CM-2025-034 | G8: 45662 | H8: 46027 | I8: =IF(H8="","",IFERROR(MAX(H8-TODAY(),0),0)) | J8: Valide | K8: Service medical | L8: Visite annuelle
B9: DOC-005 | C9: EMP-004 | D9: Nkoulou Mbarga | E9: CNI | F9: 987654321 | G9: 44075 | H9: 45901 | I9: =IF(H9="","",IFERROR(MAX(H9-TODAY(),0),0)) | J9: A renouveler | K9: RH Central | L9: Expiration sous 3 mois
B10: =IF(C10="","DOC-"&TEXT(COUNTA($C$5:C10),"000")) | I10: =IF(H10="","",IFERROR(MAX(H10-TODAY(),0),0))
B11: =IF(C11="","DOC-"&TEXT(COUNTA($C$5:C11),"000")) | I11: =IF(H11="","",IFERROR(MAX(H11-TODAY(),0),0))
B12: =IF(C12="","DOC-"&TEXT(COUNTA($C$5:C12),"000")) | I12: =IF(H12="","",IFERROR(MAX(H12-TODAY(),0),0))
B13: =IF(C13="","DOC-"&TEXT(COUNTA($C$5:C13),"000")) | I13: =IF(H13="","",IFERROR(MAX(H13-TODAY(),0),0))
B14: =IF(C14="","DOC-"&TEXT(COUNTA($C$5:C14),"000")) | I14: =IF(H14="","",IFERROR(MAX(H14-TODAY(),0),0))
B15: =IF(C15="","DOC-"&TEXT(COUNTA($C$5:C15),"000")) | I15: =IF(H15="","",IFERROR(MAX(H15-TODAY(),0),0))
B16: =IF(C16="","DOC-"&TEXT(COUNTA($C$5:C16),"000")) | I16: =IF(H16="","",IFERROR(MAX(H16-TODAY(),0),0))
B17: =IF(C17="","DOC-"&TEXT(COUNTA($C$5:C17),"000")) | I17: =IF(H17="","",IFERROR(MAX(H17-TODAY(),0),0))
B18: =IF(C18="","DOC-"&TEXT(COUNTA($C$5:C18),"000")) | I18: =IF(H18="","",IFERROR(MAX(H18-TODAY(),0),0))
B19: =IF(C19="","DOC-"&TEXT(COUNTA($C$5:C19),"000")) | I19: =IF(H19="","",IFERROR(MAX(H19-TODAY(),0),0))
B20: =IF(C20="","DOC-"&TEXT(COUNTA($C$5:C20),"000")) | I20: =IF(H20="","",IFERROR(MAX(H20-TODAY(),0),0))
B21: =IF(C21="","DOC-"&TEXT(COUNTA($C$5:C21),"000")) | I21: =IF(H21="","",IFERROR(MAX(H21-TODAY(),0),0))
... B104: =IF(C104="","DOC-"&TEXT(COUNTA($C$5:C104),"000")) | I104: =IF(H104="","",IFERROR(MAX(H104-TODAY(),0),0))
B105: =IF(C105="","DOC-"&TEXT(COUNTA($C$5:C105),"000"))
B106: =IF(C106="","DOC-"&TEXT(COUNTA($C$5:C106),"000"))
B107: =IF(C107="","DOC-"&TEXT(COUNTA($C$5:C107),"000"))
B108: =IF(C108="","DOC-"&TEXT(COUNTA($C$5:C108),"000"))
B109: =IF(C109="","DOC-"&TEXT(COUNTA($C$5:C109),"000"))
B111: INDICATEURS (mis a jour automatiquement)
B112: Total documents | D112: Valides | F112: A renouveler | H112: Expire
B113: =COUNTIF(B5:B104,"<>") | D113: =COUNTIF(I5:I104,"Valide") | F113: =COUNTIF(I5:I104,"A renouveler") | H113: =COUNTIF(I5:I104,"Expire")

Sheet 6-Donnees Bancaires
B2: DONNEES BANCAIRES DU PERSONNEL
B3: TABLEAU DYNAMIQUE — Saisissez dans la prochaine ligne jaune. Les calculs se mettent a jour automatiquement.
B4: N° | C4: Matricule | D4: Nom Employé | E4: Banque | F4: Agence | G4: RIB | H4: Compte Principal | I4: Date Mise à Jour | J4: Statut
B5: BAN-001 | C5: EMP-001 | D5: Nganou Clarisse | E5: SGBC | F5: Agence Akwa | G5: 10201 0001 23456789012 76 | H5: Oui | I5: 45444 | J5: Actif
B6: BAN-002 | C6: EMP-002 | D6: Tchinda Armand | E6: AFRILAND First Bank | F6: Agence Bonapriso | G6: 20001 0002 34567890123 45 | H6: Oui | I6: 45366 | J6: Actif
B7: BAN-003 | C7: EMP-003 | D7: Fotso Marguerite | E7: BICEC | F7: Agence Makepe | G7: 30001 0003 45678901234 89 | H7: Oui | I7: 45250 | J7: Actif
B8: BAN-004 | C8: EMP-004 | D8: Nkoulou Mbarga | E8: ECOBANK | F8: Agence Deido | G8: 40001 0004 56789012345 12 | H8: Oui | I8: 45301 | J8: Actif
B9: BAN-005 | C9: EMP-005 | D9: Kamga Paul | E9: UBA | F9: Agence Bonaberi | G9: 50001 0005 67890123456 78 | H9: Oui | I9: 45383 | J9: Actif
B10: =IF(C10="","BAN-"&TEXT(COUNTA($C$5:C10),"000"))
B11: =IF(C11="","BAN-"&TEXT(COUNTA($C$5:C11),"000"))
B12: =IF(C12="","BAN-"&TEXT(COUNTA($C$5:C12),"000"))
B13: =IF(C13="","BAN-"&TEXT(COUNTA($C$5:C13),"000"))
B14: =IF(C14="","BAN-"&TEXT(COUNTA($C$5:C14),"000"))
B15: =IF(C15="","BAN-"&TEXT(COUNTA($C$5:C15),"000"))
B16: =IF(C16="","BAN-"&TEXT(COUNTA($C$5:C16),"000"))
B17: =IF(C17="","BAN-"&TEXT(COUNTA($C$5:C17),"000"))
B18: =IF(C18="","BAN-"&TEXT(COUNTA($C$5:C18),"000"))
B19: =IF(C19="","BAN-"&TEXT(COUNTA($C$5:C19),"000"))
B20: =IF(C20="","BAN-"&TEXT(COUNTA($C$5:C20),"000"))
B21: =IF(C21="","BAN-"&TEXT(COUNTA($C$5:C21),"000"))
... B109: =IF(C109="","BAN-"&TEXT(COUNTA($C$5:C109),"000"))
B111: INDICATEURS (mis a jour automatiquement)
B112: Total comptes | D112: Comptes actifs | F112: A verifier
B113: =COUNTIF(B5:B104,"<>") | D113: =COUNTIF(J5:J104,"Actif") | F113: =COUNTIF(J5:J104,"A verifier")

Sheet 7-Mutuelle Prevoyance
B2: MUTUELLE & PREVOYANCE
B3: TABLEAU DYNAMIQUE — Saisissez dans la prochaine ligne jaune. Les calculs se mettent a jour automatiquement.
B4: N° | C4: Matricule | D4: Nom Employé | E4: Organisme | F4: N° Adhérent | G4: Date Adhésion | H4: Couverture | I4: Personnes à Charge | J4: Cotisation Mensuelle (FCFA) | K4: Cotis. Annuelle (FCFA) | L4: Statut
B5: MUT-001 | C5: EMP-001 | D5: Nganou Clarisse | E5: CNPS | F5: CNPS-EMP-001 | G5: 43845 | H5: Sante + Retraite | I5: 3 | J5: 45000 | K5: =IF(J5="","",IFERROR(J5*12,0)) | L5: Actif
B6: MUT-002 | C6: EMP-002 | D6: Tchinda Armand | E6: CNPS | F6: CNPS-EMP-002 | G6: 43617 | H6: Sante + Retraite | I6: 1 | J6: 42000 | K6: =IF(J6="","",IFERROR(J6*12,0)) | L6: Actif
B7: MUT-003 | C7: EMP-003 | D7: Fotso Marguerite | E7: Allianz Cameroon | F7: ALZ-789012 | G7: 44197 | H7: Complete | I7: 2 | J7: 65000 | K7: =IF(J7="","",IFERROR(J7*12,0)) | L7: Actif
B8: MUT-004 | C8: EMP-004 | D8: Nkoulou Mbarga | E8: CNPS | F8: CNPS-EMP-004 | G8: 44454 | H8: Sante | I8: 0 | J8: 18000 | K8: =IF(J8="","",IFERROR(J8*12,0)) | L8: Actif
B9: MUT-005 | C9: EMP-005 | D9: Kamga Paul | E9: CNPS | F9: CNPS-EMP-005 | G9: 45383 | H9: Sante | I9: 4 | J9: 15000 | K9: =IF(J9="","",IFERROR(J9*12,0)) | L9: Actif
B10: =IF(C10="","MUT-"&TEXT(COUNTA($C$5:C10),"000")) | K10: =IF(J10="","",IFERROR(J10*12,0))
B11: =IF(C11="","MUT-"&TEXT(COUNTA($C$5:C11),"000")) | K11: =IF(J11="","",IFERROR(J11*12,0))
B12: =IF(C12="","MUT-"&TEXT(COUNTA($C$5:C12),"000")) | K12: =IF(J12="","",IFERROR(J12*12,0))
B13: =IF(C13="","MUT-"&TEXT(COUNTA($C$5:C13),"000")) | K13: =IF(J13="","",IFERROR(J13*12,0))
B14: =IF(C14="","MUT-"&TEXT(COUNTA($C$5:C14),"000")) | K14: =IF(J14="","",IFERROR(J14*12,0))
B15: =IF(C15="","MUT-"&TEXT(COUNTA($C$5:C15),"000")) | K15: =IF(J15="","",IFERROR(J15*12,0))
B16: =IF(C16="","MUT-"&TEXT(COUNTA($C$5:C16),"000")) | K16: =IF(J16="","",IFERROR(J16*12,0))
B17: =IF(C17="","MUT-"&TEXT(COUNTA($C$5:C17),"000")) | K17: =IF(J17="","",IFERROR(J17*12,0))
B18: =IF(C18="","MUT-"&TEXT(COUNTA($C$5:C18),"000")) | K18: =IF(J18="","",IFERROR(J18*12,0))
B19: =IF(C19="","MUT-"&TEXT(COUNTA($C$5:C19),"000")) | K19: =IF(J19="","",IFERROR(J19*12,0))
B20: =IF(C20="","MUT-"&TEXT(COUNTA($C$5:C20),"000")) | K20: =IF(J20="","",IFERROR(J20*12,0))
B21: =IF(C21="","MUT-"&TEXT(COUNTA($C$5:C21),"000")) | K21: =IF(J21="","",IFERROR(J21*12,0))
... B104: =IF(C104="","MUT-"&TEXT(COUNTA($C$5:C104),"000")) | K104: =IF(J104="","",IFERROR(J104*12,0))
B105: =IF(C105="","MUT-"&TEXT(COUNTA($C$5:C105),"000"))
B106: =IF(C106="","MUT-"&TEXT(COUNTA($C$5:C106),"000"))
B107: =IF(C107="","MUT-"&TEXT(COUNTA($C$5:C107),"000"))
B108: =IF(C108="","MUT-"&TEXT(COUNTA($C$5:C108),"000"))
B109: =IF(C109="","MUT-"&TEXT(COUNTA($C$5:C109),"000"))
B111: TOTAL | J111: =SUM(J5:J104)
B113: INDICATEURS (mis a jour automatiquement)
B114: Total adhesions | D114: Adhesions actives | F114: Cotisations totales/mois
B115: =COUNTIF(B5:B104,"<>") | D115: =COUNTIF(K5:K104,"Actif") | F115: =SUM(J5:J104)

Sheet 8-Conges Annuels
B2: DEMANDES DE CONGES
B3: TABLEAU DYNAMIQUE — Saisissez dans la prochaine ligne jaune. Les calculs se mettent a jour automatiquement.
B4: N° | C4: Matricule | D4: Nom Employé | E4: Type Congé | F4: Date Début | G4: Date Fin | H4: Nombre Jours | I4: Motif | J4: Statut | K4: Date Approbation | L4: Approbateur
B5: CONG-001 | C5: EMP-001 | D5: Nganou Clarisse | E5: Annuel | F5: 45852 | G5: 45866 | H5: 15 | I5: Vacances famille | J5: Approuve | K5: 45828 | L5: DG Nkoulou
B6: CONG-002 | C6: EMP-002 | D6: Tchinda Armand | E6: Annuel | F6: 45870 | G6: 45879 | H6: 10 | I6: Repos | J6: En attente | L6: DG Nkoulou
B7: CONG-003 | C7: EMP-003 | D7: Fotso Marguerite | E7: Exceptionnel | F7: 45782 | G7: 45784 | H7: 3 | I7: Evenement familial | J7: Approuve | K7: 45778 | L7: DRH Nganou
B8: CONG-004 | C8: EMP-004 | D8: Nkoulou Mbarga | E8: Annuel | F8: 45901 | G8: 45914 | H8: 14 | I8: Vacances | J8: En attente | L8: Chef service Ouedraogo
B9: =IF(C9="","CONG-"&TEXT(COUNTA($C$5:C9),"000")) | H9: =IF(OR(G9="",F9=""),"",G9-F9+1)
B10: =IF(C10="","CONG-"&TEXT(COUNTA($C$5:C10),"000")) | H10: =IF(OR(G10="",F10=""),"",G10-F10+1)
B11: =IF(C11="","CONG-"&TEXT(COUNTA($C$5:C11),"000")) | H11: =IF(OR(G11="",F11=""),"",G11-F11+1)
B12: =IF(C12="","CONG-"&TEXT(COUNTA($C$5:C12),"000")) | H12: =IF(OR(G12="",F12=""),"",G12-F12+1)
B13: =IF(C13="","CONG-"&TEXT(COUNTA($C$5:C13),"000")) | H13: =IF(OR(G13="",F13=""),"",G13-F13+1)
B14: =IF(C14="","CONG-"&TEXT(COUNTA($C$5:C14),"000")) | H14: =IF(OR(G14="",F14=""),"",G14-F14+1)
B15: =IF(C15="","CONG-"&TEXT(COUNTA($C$5:C15),"000")) | H15: =IF(OR(G15="",F15=""),"",G15-F15+1)
B16: =IF(C16="","CONG-"&TEXT(COUNTA($C$5:C16),"000")) | H16: =IF(OR(G16="",F16=""),"",G16-F16+1)
B17: =IF(C17="","CONG-"&TEXT(COUNTA($C$5:C17),"000")) | H17: =IF(OR(G17="",F17=""),"",G17-F17+1)
B18: =IF(C18="","CONG-"&TEXT(COUNTA($C$5:C18),"000")) | H18: =IF(OR(G18="",F18=""),"",G18-F18+1)
B19: =IF(C19="","CONG-"&TEXT(COUNTA($C$5:C19),"000")) | H19: =IF(OR(G19="",F19=""),"",G19-F19+1)
B20: =IF(C20="","CONG-"&TEXT(COUNTA($C$5:C20),"000")) | H20: =IF(OR(G20="",F20=""),"",G20-F20+1)
... B108: =IF(C108="","CONG-"&TEXT(COUNTA($C$5:C108),"000")) | H108: =IF(OR(G108="",F108=""),"",G108-F108+1)
B110: INDICATEURS (mis a jour automatiquement)
B111: Total demandes | D111: Approuvées | F111: En attente | H111: Total jours demandés
B112: =COUNTIF(B5:B104,"<>") | D112: =COUNTIF(J5:J104,"Approuve") | F112: =COUNTIF(J5:J104,"En attente") | H112: =SUM(H5:H104)

Sheet 9-Solde Conges
B2: SOLDE DE CONGES PAR EMPLOYE
B3: TABLEAU DYNAMIQUE — Saisissez dans la prochaine ligne jaune. Les calculs se mettent a jour automatiquement.
B4: Matricule | C4: Nom Employé | D4: Droit Annuel (jrs) | E4: Congés Pris (jrs) | F4: Solde Disponible (jrs) | G4: Congés en Cours (jrs) | H4: Report N-1 (jrs) | I4: Taux Utilisation (%) | J4: Statut
B5: EMP-001 | C5: =IFERROR(VLOOKUP(B5,'2-Fiche Employe'!B5:D104,3,FALSE),"") | D5: 26 | E5: =SUMIFS('8-Conges Annuels'!H5:H104,'8-Conges Annuels'!C5:C104,B5,'8-Conges Annuels'!J5:J104,"Approuve") | G5: =SUMIFS('8-Conges Annuels'!H5:H104,'8-Conges Annuels'!C5:C104,B5,'8-Conges Annuels'!J5:J104,"En cours") | H5: 2 | J5: A jour
B6: EMP-002 | C6: =IFERROR(VLOOKUP(B6,'2-Fiche Employe'!B5:D104,3,FALSE),"") | D6: 26 | E6: =SUMIFS('8-Conges Annuels'!H5:H104,'8-Conges Annuels'!C5:C104,B6,'8-Conges Annuels'!J5:J104,"Approuve") | G6: =SUMIFS('8-Conges Annuels'!H5:H104,'8-Conges Annuels'!C5:C104,B6,'8-Conges Annuels'!J5:J104,"En cours") | H6: 0 | J6: A jour
B7: EMP-003 | C7: =IFERROR(VLOOKUP(B7,'2-Fiche Employe'!B5:D104,3,FALSE),"") | D7: 26 | E7: =SUMIFS('8-Conges Annuels'!H5:H104,'8-Conges Annuels'!C5:C104,B7,'8-Conges Annuels'!J5:J104,"Approuve") | G7: =SUMIFS('8-Conges Annuels'!H5:H104,'8-Conges Annuels'!C5:C104,B7,'8-Conges Annuels'!J5:J104,"En cours") | H7: 5 | J7: A jour
B8: EMP-004 | C8: =IFERROR(VLOOKUP(B8,'2-Fiche Employe'!B5:D104,3,FALSE),"") | D8: 26 | E8: =SUMIFS('8-Conges Annuels'!H5:H104,'8-Conges Annuels'!C5:C104,B8,'8-Conges Annuels'!J5:J104,"Approuve") | G8: =SUMIFS('8-Conges Annuels'!H5:H104,'8-Conges Annuels'!C5:C104,B8,'8-Conges Annuels'!J5:J104,"En cours") | H8: 0 | J8: A jour
B9: EMP-005 | C9: =IFERROR(VLOOKUP(B9,'2-Fiche Employe'!B5:D104,3,FALSE),"") | D9: 22 | E9: =SUMIFS('8-Conges Annuels'!H5:H104,'8-Conges Annuels'!C5:C104,B9,'8-Conges Annuels'!J5:J104,"Approuve") | G9: =SUMIFS('8-Conges Annuels'!H5:H104,'8-Conges Annuels'!C5:C104,B9,'8-Conges Annuels'!J5:J104,"En cours") | H9: 0 | J9: A jour
C10: =IFERROR(VLOOKUP(B10,'2-Fiche Employe'!B5:D104,3,FALSE),"") | E10: =IF(B10="","",SUMIFS('8-Conges Annuels'!H5:H104,'8-Conges Annuels'!C5:C104,B10,'8-Conges Annuels'!J5:J104,"Approuve")) | F10: =IF(B10="","",D10-E10-G10+H10) | G10: =IF(B10="","",SUMIFS('8-Conges Annuels'!H5:H104,'8-Conges Annuels'!C5:C104,B10,'8-Conges Annuels'!J5:J104,"En cours")) | I10: =IF(B10="","",IFERROR(E10/D10,0))
C11: =IFERROR(VLOOKUP(B11,'2-Fiche Employe'!B5:D104,3,FALSE),"") | E11: =IF(B11="","",SUMIFS('8-Conges Annuels'!H5:H104,'8-Conges Annuels'!C5:C104,B11,'8-Conges Annuels'!J5:J104,"Approuve")) | F11: =IF(B11="","",D11-E11-G11+H11) | G11: =IF(B11="","",SUMIFS('8-Conges Annuels'!H5:H104,'8-Conges Annuels'!C5:C104,B11,'8-Conges Annuels'!J5:J104,"En cours")) | I11: =IF(B11="","",IFERROR(E11/D11,0))
C12: =IFERROR(VLOOKUP(B12,'2-Fiche Employe'!B5:D104,3,FALSE),"") | E12: =IF(B12="","",SUMIFS('8-Conges Annuels'!H5:H104,'8-Conges Annuels'!C5:C104,B12,'8-Conges Annuels'!J5:J104,"Approuve")) | F12: =IF(B12="","",D12-E12-G12+H12) | G12: =IF(B12="","",SUMIFS('8-Conges Annuels'!H5:H104,'8-Conges Annuels'!C5:C104,B12,'8-Conges Annuels'!J5:J104,"En cours")) | I12: =IF(B12="","",IFERROR(E12/D12,0))
C13: =IFERROR(VLOOKUP(B13,'2-Fiche Employe'!B5:D104,3,FALSE),"") | E13: =IF(B13="","",SUMIFS('8-Conges Annuels'!H5:H104,'8-Conges Annuels'!C5:C104,B13,'8-Conges Annuels'!J5:J104,"Approuve")) | F13: =IF(B13="","",D13-E13-G13+H13) | G13: =IF(B13="","",SUMIFS('8-Conges Annuels'!H5:H104,'8-Conges Annuels'!C5:C104,B13,'8-Conges Annuels'!J5:J104,"En cours")) | I13: =IF(B13="","",IFERROR(E13/D13,0))
C14: =IFERROR(VLOOKUP(B14,'2-Fiche Employe'!B5:D104,3,FALSE),"") | E14: =IF(B14="","",SUMIFS('8-Conges Annuels'!H5:H104,'8-Conges Annuels'!C5:C104,B14,'8-Conges Annuels'!J5:J104,"Approuve")) | F14: =IF(B14="","",D14-E14-G14+H14) | G14: =IF(B14="","",SUMIFS('8-Conges Annuels'!H5:H104,'8-Conges Annuels'!C5:C104,B14,'8-Conges Annuels'!J5:J104,"En cours")) | I14: =IF(B14="","",IFERROR(E14/D14,0))
C15: =IFERROR(VLOOKUP(B15,'2-Fiche Employe'!B5:D104,3,FALSE),"") | E15: =IF(B15="","",SUMIFS('8-Conges Annuels'!H5:H104,'8-Conges Annuels'!C5:C104,B15,'8-Conges Annuels'!J5:J104,"Approuve")) | F15: =IF(B15="","",D15-E15-G15+H15) | G15: =IF(B15="","",SUMIFS('8-Conges Annuels'!H5:H104,'8-Conges Annuels'!C5:C104,B15,'8-Conges Annuels'!J5:J104,"En cours")) | I15: =IF(B15="","",IFERROR(E15/D15,0))
C16: =IFERROR(VLOOKUP(B16,'2-Fiche Employe'!B5:D104,3,FALSE),"") | E16: =IF(B16="","",SUMIFS('8-Conges Annuels'!H5:H104,'8-Conges Annuels'!C5:C104,B16,'8-Conges Annuels'!J5:J104,"Approuve")) | F16: =IF(B16="","",D16-E16-G16+H16) | G16: =IF(B16="","",SUMIFS('8-Conges Annuels'!H5:H104,'8-Conges Annuels'!C5:C104,B16,'8-Conges Annuels'!J5:J104,"En cours")) | I16: =IF(B16="","",IFERROR(E16/D16,0))
C17: =IFERROR(VLOOKUP(B17,'2-Fiche Employe'!B5:D104,3,FALSE),"") | E17: =IF(B17="","",SUMIFS('8-Conges Annuels'!H5:H104,'8-Conges Annuels'!C5:C104,B17,'8-Conges Annuels'!J5:J104,"Approuve")) | F17: =IF(B17="","",D17-E17-G17+H17) | G17: =IF(B17="","",SUMIFS('8-Conges Annuels'!H5:H104,'8-Conges Annuels'!C5:C104,B17,'8-Conges Annuels'!J5:J104,"En cours")) | I17: =IF(B17="","",IFERROR(E17/D17,0))
C18: =IFERROR(VLOOKUP(B18,'2-Fiche Employe'!B5:D104,3,FALSE),"") | E18: =IF(B18="","",SUMIFS('8-Conges Annuels'!H5:H104,'8-Conges Annuels'!C5:C104,B18,'8-Conges Annuels'!J5:J104,"Approuve")) | F18: =IF(B18="","",D18-E18-G18+H18) | G18: =IF(B18="","",SUMIFS('8-Conges Annuels'!H5:H104,'8-Conges Annuels'!C5:C104,B18,'8-Conges Annuels'!J5:J104,"En cours")) | I18: =IF(B18="","",IFERROR(E18/D18,0))
C19: =IFERROR(VLOOKUP(B19,'2-Fiche Employe'!B5:D104,3,FALSE),"") | E19: =IF(B19="","",SUMIFS('8-Conges Annuels'!H5:H104,'8-Conges Annuels'!C5:C104,B19,'8-Conges Annuels'!J5:J104,"Approuve")) | F19: =IF(B19="","",D19-E19-G19+H19) | G19: =IF(B19="","",SUMIFS('8-Conges Annuels'!H5:H104,'8-Conges Annuels'!C5:C104,B19,'8-Conges Annuels'!J5:J104,"En cours")) | I19: =IF(B19="","",IFERROR(E19/D19,0))
C20: =IFERROR(VLOOKUP(B20,'2-Fiche Employe'!B5:D104,3,FALSE),"") | E20: =IF(B20="","",SUMIFS('8-Conges Annuels'!H5:H104,'8-Conges Annuels'!C5:C104,B20,'8-Conges Annuels'!J5:J104,"Approuve")) | F20: =IF(B20="","",D20-E20-G20+H20) | G20: =IF(B20="","",SUMIFS('8-Conges Annuels'!H5:H104,'8-Conges Annuels'!C5:C104,B20,'8-Conges Annuels'!J5:J104,"En cours")) | I20: =IF(B20="","",IFERROR(E20/D20,0))
C21: =IFERROR(VLOOKUP(B21,'2-Fiche Employe'!B5:D104,3,FALSE),"") | E21: =IF(B21="","",SUMIFS('8-Conges Annuels'!H5:H104,'8-Conges Annuels'!C5:C104,B21,'8-Conges Annuels'!J5:J104,"Approuve")) | F21: =IF(B21="","",D21-E21-G21+H21) | G21: =IF(B21="","",SUMIFS('8-Conges Annuels'!H5:H104,'8-Conges Annuels'!C5:C104,B21,'8-Conges Annuels'!J5:J104,"En cours")) | I21: =IF(B21="","",IFERROR(E21/D21,0))
C22: =IFERROR(VLOOKUP(B22,'2-Fiche Employe'!B5:D104,3,FALSE),"") | E22: =IF(B22="","",SUMIFS('8-Conges Annuels'!H5:H104,'8-Conges Annuels'!C5:C104,B22,'8-Conges Annuels'!J5:J104,"Approuve")) | F22: =IF(B22="","",D22-E22-G22+H22) | G22: =IF(B22="","",SUMIFS('8-Conges Annuels'!H5:H104,'8-Conges Annuels'!C5:C104,B22,'8-Conges Annuels'!J5:J104,"En cours")) | I22: =IF(B22="","",IFERROR(E22/D22,0))
C23: =IFERROR(VLOOKUP(B23,'2-Fiche Employe'!B5:D104,3,FALSE),"") | E23: =IF(B23="","",SUMIFS('8-Conges Annuels'!H5:H104,'8-Conges Annuels'!C5:C104,B23,'8-Conges Annuels'!J5:J104,"Approuve")) | F23: =IF(B23="","",D23-E23-G23+H23) | G23: =IF(B23="","",SUMIFS('8-Conges Annuels'!H5:H104,'8-Conges Annuels'!C5:C104,B23,'8-Conges Annuels'!J5:J104,"En cours")) | I23: =IF(B23="","",IFERROR(E23/D23,0))
C24: =IFERROR(VLOOKUP(B24,'2-Fiche Employe'!B5:D104,3,FALSE),"") | E24: =IF(B24="","",SUMIFS('8-Conges Annuels'!H5:H104,'8-Conges Annuels'!C5:C104,B24,'8-Conges Annuels'!J5:J104,"Approuve")) | F24: =IF(B24="","",D24-E24-G24+H24) | G24: =IF(B24="","",SUMIFS('8-Conges Annuels'!H5:H104,'8-Conges Annuels'!C5:C104,B24,'8-Conges Annuels'!J5:J104,"En cours")) | I24: =IF(B24="","",IFERROR(E24/D24,0))
C25: =IFERROR(VLOOKUP(B25,'2-Fiche Employe'!B5:D104,3,FALSE),"") | E25: =IF(B25="","",SUMIFS('8-Conges Annuels'!H5:H104,'8-Conges Annuels'!C5:C104,B25,'8-Conges Annuels'!J5:J104,"Approuve")) | F25: =IF(B25="","",D25-E25-G25+H25) | G25: =IF(B25="","",SUMIFS('8-Conges Annuels'!H5:H104,'8-Conges Annuels'!C5:C104,B25,'8-Conges Annuels'!J5:J104,"En cours")) | I25: =IF(B25="","",IFERROR(E25/D25,0))
C26: =IFERROR(VLOOKUP(B26,'2-Fiche Employe'!B5:D104,3,FALSE),"") | E26: =IF(B26="","",SUMIFS('8-Conges Annuels'!H5:H104,'8-Conges Annuels'!C5:C104,B26,'8-Conges Annuels'!J5:J104,"Approuve")) | F26: =IF(B26="","",D26-E26-G26+H26) | G26: =IF(B26="","",SUMIFS('8-Conges Annuels'!H5:H104,'8-Conges Annuels'!C5:C104,B26,'8-Conges Annuels'!J5:J104,"En cours")) | I26: =IF(B26="","",IFERROR(E26/D26,0))
C27: =IFERROR(VLOOKUP(B27,'2-Fiche Employe'!B5:D104,3,FALSE),"") | E27: =IF(B27="","",SUMIFS('8-Conges Annuels'!H5:H104,'8-Conges Annuels'!C5:C104,B27,'8-Conges Annuels'!J5:J104,"Approuve")) | F27: =IF(B27="","",D27-E27-G27+H27) | G27: =IF(B27="","",SUMIFS('8-Conges Annuels'!H5:H104,'8-Conges Annuels'!C5:C104,B27,'8-Conges Annuels'!J5:J104,"En cours")) | I27: =IF(B27="","",IFERROR(E27/D27,0))
C28: =IFERROR(VLOOKUP(B28,'2-Fiche Employe'!B5:D104,3,FALSE),"") | E28: =IF(B28="","",SUMIFS('8-Conges Annuels'!H5:H104,'8-Conges Annuels'!C5:C104,B28,'8-Conges Annuels'!J5:J104,"Approuve")) | F28: =IF(B28="","",D28-E28-G28+H28) | G28: =IF(B28="","",SUMIFS('8-Conges Annuels'!H5:H104,'8-Conges Annuels'!C5:C104,B28,'8-Conges Annuels'!J5:J104,"En cours")) | I28: =IF(B28="","",IFERROR(E28/D28,0))
C29: =IFERROR(VLOOKUP(B29,'2-Fiche Employe'!B5:D104,3,FALSE),"") | E29: =IF(B29="","",SUMIFS('8-Conges Annuels'!H5:H104,'8-Conges Annuels'!C5:C104,B29,'8-Conges Annuels'!J5:J104,"Approuve")) | F29: =IF(B29="","",D29-E29-G29+H29) | G29: =IF(B29="","",SUMIFS('8-Conges Annuels'!H5:H104,'8-Conges Annuels'!C5:C104,B29,'8-Conges Annuels'!J5:J104,"En cours")) | I29: =IF(B29="","",IFERROR(E29/D29,0))
C30: =IFERROR(VLOOKUP(B30,'2-Fiche Employe'!B5:D104,3,FALSE),"") | E30: =IF(B30="","",SUMIFS('8-Conges Annuels'!H5:H104,'8-Conges Annuels'!C5:C104,B30,'8-Conges Annuels'!J5:J104,"Approuve")) | F30: =IF(B30="","",D30-E30-G30+H30) | G30: =IF(B30="","",SUMIFS('8-Conges Annuels'!H5:H104,'8-Conges Annuels'!C5:C104,B30,'8-Conges Annuels'!J5:J104,"En cours")) | I30: =IF(B30="","",IFERROR(E30/D30,0))
C31: =IFERROR(VLOOKUP(B31,'2-Fiche Employe'!B5:D104,3,FALSE),"") | E31: =IF(B31="","",SUMIFS('8-Conges Annuels'!H5:H104,'8-Conges Annuels'!C5:C104,B31,'8-Conges Annuels'!J5:J104,"Approuve")) | F31: =IF(B31="","",D31-E31-G31+H31) | G31: =IF(B31="","",SUMIFS('8-Conges Annuels'!H5:H104,'8-Conges Annuels'!C5:C104,B31,'8-Conges Annuels'!J5:J104,"En cours")) | I31: =IF(B31="","",IFERROR(E31/D31,0))
C32: =IFERROR(VLOOKUP(B32,'2-Fiche Employe'!B5:D104,3,FALSE),"") | E32: =IF(B32="","",SUMIFS('8-Conges Annuels'!H5:H104,'8-Conges Annuels'!C5:C104,B32,'8-Conges Annuels'!J5:J104,"Approuve")) | F32: =IF(B32="","",D32-E32-G32+H32) | G32: =IF(B32="","",SUMIFS('8-Conges Annuels'!H5:H104,'8-Conges Annuels'!C5:C104,B32,'8-Conges Annuels'!J5:J104,"En cours")) | I32: =IF(B32="","",IFERROR(E32/D32,0))
C33: =IFERROR(VLOOKUP(B33,'2-Fiche Employe'!B5:D104,3,FALSE),"") | E33: =IF(B33="","",SUMIFS('8-Conges Annuels'!H5:H104,'8-Conges Annuels'!C5:C104,B33,'8-Conges Annuels'!J5:J104,"Approuve")) | F33: =IF(B33="","",D33-E33-G33+H33) | G33: =IF(B33="","",SUMIFS('8-Conges Annuels'!H5:H104,'8-Conges Annuels'!C5:C104,B33,'8-Conges Annuels'!J5:J104,"En cours")) | I33: =IF(B33="","",IFERROR(E33/D33,0))
C34: =IFERROR(VLOOKUP(B34,'2-Fiche Employe'!B5:D104,3,FALSE),"") | E34: =IF(B34="","",SUMIFS('8-Conges Annuels'!H5:H104,'8-Conges Annuels'!C5:C104,B34,'8-Conges Annuels'!J5:J104,"Approuve")) | F34: =IF(B34="","",D34-E34-G34+H34) | G34: =IF(B34="","",SUMIFS('8-Conges Annuels'!H5:H104,'8-Conges Annuels'!C5:C104,B34,'8-Conges Annuels'!J5:J104,"En cours")) | I34: =IF(B34="","",IFERROR(E34/D34,0))
C35: =IFERROR(VLOOKUP(B35,'2-Fiche Employe'!B5:D104,3,FALSE),"") | E35: =IF(B35="","",SUMIFS('8-Conges Annuels'!H5:H104,'8-Conges Annuels'!C5:C104,B35,'8-Conges Annuels'!J5:J104,"Approuve")) | F35: =IF(B35="","",D35-E35-G35+H35) | G35: =IF(B35="","",SUMIFS('8-Conges Annuels'!H5:H104,'8-Conges Annuels'!C5:C104,B35,'8-Conges Annuels'!J5:J104,"En cours")) | I35: =IF(B35="","",IFERROR(E35/D35,0))
C36: =IFERROR(VLOOKUP(B36,'2-Fiche Employe'!B5:D104,3,FALSE),"") | E36: =IF(B36="","",SUMIFS('8-Conges Annuels'!H5:H104,'8-Conges Annuels'!C5:C104,B36,'8-Conges Annuels'!J5:J104,"Approuve")) | F36: =IF(B36="","",D36-E36-G36+H36) | G36: =IF(B36="","",SUMIFS('8-Conges Annuels'!H5:H104,'8-Conges Annuels'!C5:C104,B36,'8-Conges Annuels'!J5:J104,"En cours")) | I36: =IF(B36="","",IFERROR(E36/D36,0))
C37: =IFERROR(VLOOKUP(B37,'2-Fiche Employe'!B5:D104,3,FALSE),"") | E37: =IF(B37="","",SUMIFS('8-Conges Annuels'!H5:H104,'8-Conges Annuels'!C5:C104,B37,'8-Conges Annuels'!J5:J104,"Approuve")) | F37: =IF(B37="","",D37-E37-G37+H37) | G37: =IF(B37="","",SUMIFS('8-Conges Annuels'!H5:H104,'8-Conges Annuels'!C5:C104,B37,'8-Conges Annuels'!J5:J104,"En cours")) | I37: =IF(B37="","",IFERROR(E37/D37,0))
C38: =IFERROR(VLOOKUP(B38,'2-Fiche Employe'!B5:D104,3,FALSE),"") | E38: =IF(B38="","",SUMIFS('8-Conges Annuels'!H5:H104,'8-Conges Annuels'!C5:C104,B38,'8-Conges Annuels'!J5:J104,"Approuve")) | F38: =IF(B38="","",D38-E38-G38+H38) | G38: =IF(B38="","",SUMIFS('8-Conges Annuels'!H5:H104,'8-Conges Annuels'!C5:C104,B38,'8-Conges Annuels'!J5:J104,"En cours")) | I38: =IF(B38="","",IFERROR(E38/D38,0))
C39: =IFERROR(VLOOKUP(B39,'2-Fiche Employe'!B5:D104,3,FALSE),"") | E39: =IF(B39="","",SUMIFS('8-Conges Annuels'!H5:H104,'8-Conges Annuels'!C5:C104,B39,'8-Conges Annuels'!J5:J104,"Approuve")) | F39: =IF(B39="","",D39-E39-G39+H39) | G39: =IF(B39="","",SUMIFS('8-Conges Annuels'!H5:H104,'8-Conges Annuels'!C5:C104,B39,'8-Conges Annuels'!J5:J104,"En cours")) | I39: =IF(B39="","",IFERROR(E39/D39,0))
C40: =IFERROR(VLOOKUP(B40,'2-Fiche Employe'!B5:D104,3,FALSE),"") | E40: =IF(B40="","",SUMIFS('8-Conges Annuels'!H5:H104,'8-Conges Annuels'!C5:C104,B40,'8-Conges Annuels'!J5:J104,"Approuve")) | F40: =IF(B40="","",D40-E40-G40+H40) | G40: =IF(B40="","",SUMIFS('8-Conges Annuels'!H5:H104,'8-Conges Annuels'!C5:C104,B40,'8-Conges Annuels'!J5:J104,"En cours")) | I40: =IF(B40="","",IFERROR(E40/D40,0))
C41: =IFERROR(VLOOKUP(B41,'2-Fiche Employe'!B5:D104,3,FALSE),"") | E41: =IF(B41="","",SUMIFS('8-Conges Annuels'!H5:H104,'8-Conges Annuels'!C5:C104,B41,'8-Conges Annuels'!J5:J104,"Approuve")) | F41: =IF(B41="","",D41-E41-G41+H41) | G41: =IF(B41="","",SUMIFS('8-Conges Annuels'!H5:H104,'8-Conges Annuels'!C5:C104,B41,'8-Conges Annuels'!J5:J104,"En cours")) | I41: =IF(B41="","",IFERROR(E41/D41,0))
C42: =IFERROR(VLOOKUP(B42,'2-Fiche Employe'!B5:D104,3,FALSE),"") | E42: =IF(B42="","",SUMIFS('8-Conges Annuels'!H5:H104,'8-Conges Annuels'!C5:C104,B42,'8-Conges Annuels'!J5:J104,"Approuve")) | F42: =IF(B42="","",D42-E42-G42+H42) | G42: =IF(B42="","",SUMIFS('8-Conges Annuels'!H5:H104,'8-Conges Annuels'!C5:C104,B42,'8-Conges Annuels'!J5:J104,"En cours")) | I42: =IF(B42="","",IFERROR(E42/D42,0))
C43: =IFERROR(VLOOKUP(B43,'2-Fiche Employe'!B5:D104,3,FALSE),"") | E43: =IF(B43="","",SUMIFS('8-Conges Annuels'!H5:H104,'8-Conges Annuels'!C5:C104,B43,'8-Conges Annuels'!J5:J104,"Approuve")) | F43: =IF(B43="","",D43-E43-G43+H43) | G43: =IF(B43="","",SUMIFS('8-Conges Annuels'!H5:H104,'8-Conges Annuels'!C5:C104,B43,'8-Conges Annuels'!J5:J104,"En cours")) | I43: =IF(B43="","",IFERROR(E43/D43,0))
C44: =IFERROR(VLOOKUP(B44,'2-Fiche Employe'!B5:D104,3,FALSE),"") | E44: =IF(B44="","",SUMIFS('8-Conges Annuels'!H5:H104,'8-Conges Annuels'!C5:C104,B44,'8-Conges Annuels'!J5:J104,"Approuve")) | F44: =IF(B44="","",D44-E44-G44+H44) | G44: =IF(B44="","",SUMIFS('8-Conges Annuels'!H5:H104,'8-Conges Annuels'!C5:C104,B44,'8-Conges Annuels'!J5:J104,"En cours")) | I44: =IF(B44="","",IFERROR(E44/D44,0))
C45: =IFERROR(VLOOKUP(B45,'2-Fiche Employe'!B5:D104,3,FALSE),"") | E45: =IF(B45="","",SUMIFS('8-Conges Annuels'!H5:H104,'8-Conges Annuels'!C5:C104,B45,'8-Conges Annuels'!J5:J104,"Approuve")) | F45: =IF(B45="","",D45-E45-G45+H45) | G45: =IF(B45="","",SUMIFS('8-Conges Annuels'!H5:H104,'8-Conges Annuels'!C5:C104,B45,'8-Conges Annuels'!J5:J104,"En cours")) | I45: =IF(B45="","",IFERROR(E45/D45,0))
C46: =IFERROR(VLOOKUP(B46,'2-Fiche Employe'!B5:D104,3,FALSE),"") | E46: =IF(B46="","",SUMIFS('8-Conges Annuels'!H5:H104,'8-Conges Annuels'!C5:C104,B46,'8-Conges Annuels'!J5:J104,"Approuve")) | F46: =IF(B46="","",D46-E46-G46+H46) | G46: =IF(B46="","",SUMIFS('8-Conges Annuels'!H5:H104,'8-Conges Annuels'!C5:C104,B46,'8-Conges Annuels'!J5:J104,"En cours")) | I46: =IF(B46="","",IFERROR(E46/D46,0))
C47: =IFERROR(VLOOKUP(B47,'2-Fiche Employe'!B5:D104,3,FALSE),"") | E47: =IF(B47="","",SUMIFS('8-Conges Annuels'!H5:H104,'8-Conges Annuels'!C5:C104,B47,'8-Conges Annuels'!J5:J104,"Approuve")) | F47: =IF(B47="","",D47-E47-G47+H47) | G47: =IF(B47="","",SUMIFS('8-Conges Annuels'!H5:H104,'8-Conges Annuels'!C5:C104,B47,'8-Conges Annuels'!J5:J104,"En cours")) | I47: =IF(B47="","",IFERROR(E47/D47,0))
C48: =IFERROR(VLOOKUP(B48,'2-Fiche Employe'!B5:D104,3,FALSE),"") | E48: =IF(B48="","",SUMIFS('8-Conges Annuels'!H5:H104,'8-Conges Annuels'!C5:C104,B48,'8-Conges Annuels'!J5:J104,"Approuve")) | F48: =IF(B48="","",D48-E48-G48+H48) | G48: =IF(B48="","",SUMIFS('8-Conges Annuels'!H5:H104,'8-Conges Annuels'!C5:C104,B48,'8-Conges Annuels'!J5:J104,"En cours")) | I48: =IF(B48="","",IFERROR(E48/D48,0))
C49: =IFERROR(VLOOKUP(B49,'2-Fiche Employe'!B5:D104,3,FALSE),"") | E49: =IF(B49="","",SUMIFS('8-Conges Annuels'!H5:H104,'8-Conges Annuels'!C5:C104,B49,'8-Conges Annuels'!J5:J104,"Approuve")) | F49: =IF(B49="","",D49-E49-G49+H49) | G49: =IF(B49="","",SUMIFS('8-Conges Annuels'!H5:H104,'8-Conges Annuels'!C5:C104,B49,'8-Conges Annuels'!J5:J104,"En cours")) | I49: =IF(B49="","",IFERROR(E49/D49,0))
C50: =IFERROR(VLOOKUP(B50,'2-Fiche Employe'!B5:D104,3,FALSE),"") | E50: =IF(B50="","",SUMIFS('8-Conges Annuels'!H5:H104,'8-Conges Annuels'!C5:C104,B50,'8-Conges Annuels'!J5:J104,"Approuve")) | F50: =IF(B50="","",D50-E50-G50+H50) | G50: =IF(B50="","",SUMIFS('8-Conges Annuels'!H5:H104,'8-Conges Annuels'!C5:C104,B50,'8-Conges Annuels'!J5:J104,"En cours")) | I50: =IF(B50="","",IFERROR(E50/D50,0))
C51: =IFERROR(VLOOKUP(B51,'2-Fiche Employe'!B5:D104,3,FALSE),"") | E51: =IF(B51="","",SUMIFS('8-Conges Annuels'!H5:H104,'8-Conges Annuels'!C5:C104,B51,'8-Conges Annuels'!J5:J104,"Approuve")) | F51: =IF(B51="","",D51-E51-G51+H51) | G51: =IF(B51="","",SUMIFS('8-Conges Annuels'!H5:H104,'8-Conges Annuels'!C5:C104,B51,'8-Conges Annuels'!J5:J104,"En cours")) | I51: =IF(B51="","",IFERROR(E51/D51,0))
C52: =IFERROR(VLOOKUP(B52,'2-Fiche Employe'!B5:D104,3,FALSE),"") | E52: =IF(B52="","",SUMIFS('8-Conges Annuels'!H5:H104,'8-Conges Annuels'!C5:C104,B52,'8-Conges Annuels'!J5:J104,"Approuve")) | F52: =IF(B52="","",D52-E52-G52+H52) | G52: =IF(B52="","",SUMIFS('8-Conges Annuels'!H5:H104,'8-Conges Annuels'!C5:C104,B52,'8-Conges Annuels'!J5:J104,"En cours")) | I52: =IF(B52="","",IFERROR(E52/D52,0))
C53: =IFERROR(VLOOKUP(B53,'2-Fiche Employe'!B5:D104,3,FALSE),"") | E53: =IF(B53="","",SUMIFS('8-Conges Annuels'!H5:H104,'8-Conges Annuels'!C5:C104,B53,'8-Conges Annuels'!J5:J104,"Approuve")) | F53: =IF(B53="","",D53-E53-G53+H53) | G53: =IF(B53="","",SUMIFS('8-Conges Annuels'!H5:H104,'8-Conges Annuels'!C5:C104,B53,'8-Conges Annuels'!J5:J104,"En cours")) | I53: =IF(B53="","",IFERROR(E53/D53,0))
C54: =IFERROR(VLOOKUP(B54,'2-Fiche Employe'!B5:D104,3,FALSE),"") | E54: =IF(B54="","",SUMIFS('8-Conges Annuels'!H5:H104,'8-Conges Annuels'!C5:C104,B54,'8-Conges Annuels'!J5:J104,"Approuve")) | F54: =IF(B54="","",D54-E54-G54+H54) | G54: =IF(B54="","",SUMIFS('8-Conges Annuels'!H5:H104,'8-Conges Annuels'!C5:C104,B54,'8-Conges Annuels'!J5:J104,"En cours")) | I54: =IF(B54="","",IFERROR(E54/D54,0))
C55: =IFERROR(VLOOKUP(B55,'2-Fiche Employe'!B5:D104,3,FALSE),"") | E55: =IF(B55="","",SUMIFS('8-Conges Annuels'!H5:H104,'8-Conges Annuels'!C5:C104,B55,'8-Conges Annuels'!J5:J104,"Approuve")) | F55: =IF(B55="","",D55-E55-G55+H55) | G55: =IF(B55="","",SUMIFS('8-Conges Annuels'!H5:H104,'8-Conges Annuels'!C5:C104,B55,'8-Conges Annuels'!J5:J104,"En cours")) | I55: =IF(B55="","",IFERROR(E55/D55,0))
C56: =IFERROR(VLOOKUP(B56,'2-Fiche Employe'!B5:D104,3,FALSE),"") | E56: =IF(B56="","",SUMIFS('8-Conges Annuels'!H5:H104,'8-Conges Annuels'!C5:C104,B56,'8-Conges Annuels'!J5:J104,"Approuve")) | F56: =IF(B56="","",D56-E56-G56+H56) | G56: =IF(B56="","",SUMIFS('8-Conges Annuels'!H5:H104,'8-Conges Annuels'!C5:C104,B56,'8-Conges Annuels'!J5:J104,"En cours")) | I56: =IF(B56="","",IFERROR(E56/D56,0))
C57: =IFERROR(VLOOKUP(B57,'2-Fiche Employe'!B5:D104,3,FALSE),"") | E57: =IF(B57="","",SUMIFS('8-Conges Annuels'!H5:H104,'8-Conges Annuels'!C5:C104,B57,'8-Conges Annuels'!J5:J104,"Approuve")) | F57: =IF(B57="","",D57-E57-G57+H57) | G57: =IF(B57="","",SUMIFS('8-Conges Annuels'!H5:H104,'8-Conges Annuels'!C5:C104,B57,'8-Conges Annuels'!J5:J104,"En cours")) | I57: =IF(B57="","",IFERROR(E57/D57,0))
C58: =IFERROR(VLOOKUP(B58,'2-Fiche Employe'!B5:D104,3,FALSE),"") | E58: =IF(B58="","",SUMIFS('8-Conges Annuels'!H5:H104,'8-Conges Annuels'!C5:C104,B58,'8-Conges Annuels'!J5:J104,"Approuve")) | F58: =IF(B58="","",D58-E58-G58+H58) | G58: =IF(B58="","",SUMIFS('8-Conges Annuels'!H5:H104,'8-Conges Annuels'!C5:C104,B58,'8-Conges Annuels'!J5:J104,"En cours")) | I58: =IF(B58="","",IFERROR(E58/D58,0))
C59: =IFERROR(VLOOKUP(B59,'2-Fiche Employe'!B5:D104,3,FALSE),"") | E59: =IF(B59="","",SUMIFS('8-Conges Annuels'!H5:H104,'8-Conges Annuels'!C5:C104,B59,'8-Conges Annuels'!J5:J104,"Approuve")) | F59: =IF(B59="","",D59-E59-G59+H59) | G59: =IF(B59="","",SUMIFS('8-Conges Annuels'!H5:H104,'8-Conges Annuels'!C5:C104,B59,'8-Conges Annuels'!J5:J104,"En cours")) | I59: =IF(B59="","",IFERROR(E59/D59,0))
C60: =IFERROR(VLOOKUP(B60,'2-Fiche Employe'!B5:D104,3,FALSE),"") | E60: =IF(B60="","",SUMIFS('8-Conges Annuels'!H5:H104,'8-Conges Annuels'!C5:C104,B60,'8-Conges Annuels'!J5:J104,"Approuve")) | F60: =IF(B60="","",D60-E60-G60+H60) | G60: =IF(B60="","",SUMIFS('8-Conges Annuels'!H5:H104,'8-Conges Annuels'!C5:C104,B60,'8-Conges Annuels'!J5:J104,"En cours")) | I60: =IF(B60="","",IFERROR(E60/D60,0))
C61: =IFERROR(VLOOKUP(B61,'2-Fiche Employe'!B5:D104,3,FALSE),"") | E61: =IF(B61="","",SUMIFS('8-Conges Annuels'!H5:H104,'8-Conges Annuels'!C5:C104,B61,'8-Conges Annuels'!J5:J104,"Approuve")) | F61: =IF(B61="","",D61-E61-G61+H61) | G61: =IF(B61="","",SUMIFS('8-Conges Annuels'!H5:H104,'8-Conges Annuels'!C5:C104,B61,'8-Conges Annuels'!J5:J104,"En cours")) | I61: =IF(B61="","",IFERROR(E61/D61,0))
C62: =IFERROR(VLOOKUP(B62,'2-Fiche Employe'!B5:D104,3,FALSE),"") | E62: =IF(B62="","",SUMIFS('8-Conges Annuels'!H5:H104,'8-Conges Annuels'!C5:C104,B62,'8-Conges Annuels'!J5:J104,"Approuve")) | F62: =IF(B62="","",D62-E62-G62+H62) | G62: =IF(B62="","",SUMIFS('8-Conges Annuels'!H5:H104,'8-Conges Annuels'!C5:C104,B62,'8-Conges Annuels'!J5:J104,"En cours")) | I62: =IF(B62="","",IFERROR(E62/D62,0))
C63: =IFERROR(VLOOKUP(B63,'2-Fiche Employe'!B5:D104,3,FALSE),"") | E63: =IF(B63="","",SUMIFS('8-Conges Annuels'!H5:H104,'8-Conges Annuels'!C5:C104,B63,'8-Conges Annuels'!J5:J104,"Approuve")) | F63: =IF(B63="","",D63-E63-G63+H63) | G63: =IF(B63="","",SUMIFS('8-Conges Annuels'!H5:H104,'8-Conges Annuels'!C5:C104,B63,'8-Conges Annuels'!J5:J104,"En cours")) | I63: =IF(B63="","",IFERROR(E63/D63,0))
C64: =IFERROR(VLOOKUP(B64,'2-Fiche Employe'!B5:D104,3,FALSE),"") | E64: =IF(B64="","",SUMIFS('8-Conges Annuels'!H5:H104,'8-Conges Annuels'!C5:C104,B64,'8-Conges Annuels'!J5:J104,"Approuve")) | F64: =IF(B64="","",D64-E64-G64+H64) | G64: =IF(B64="","",SUMIFS('8-Conges Annuels'!H5:H104,'8-Conges Annuels'!C5:C104,B64,'8-Conges Annuels'!J5:J104,"En cours")) | I64: =IF(B64="","",IFERROR(E64/D64,0))
C65: =IFERROR(VLOOKUP(B65,'2-Fiche Employe'!B5:D104,3,FALSE),"") | E65: =IF(B65="","",SUMIFS('8-Conges Annuels'!H5:H104,'8-Conges Annuels'!C5:C104,B65,'8-Conges Annuels'!J5:J104,"Approuve")) | F65: =IF(B65="","",D65-E65-G65+H65) | G65: =IF(B65="","",SUMIFS('8-Conges Annuels'!H5:H104,'8-Conges Annuels'!C5:C104,B65,'8-Conges Annuels'!J5:J104,"En cours")) | I65: =IF(B65="","",IFERROR(E65/D65,0))
C66: =IFERROR(VLOOKUP(B66,'2-Fiche Employe'!B5:D104,3,FALSE),"") | E66: =IF(B66="","",SUMIFS('8-Conges Annuels'!H5:H104,'8-Conges Annuels'!C5:C104,B66,'8-Conges Annuels'!J5:J104,"Approuve")) | F66: =IF(B66="","",D66-E66-G66+H66) | G66: =IF(B66="","",SUMIFS('8-Conges Annuels'!H5:H104,'8-Conges Annuels'!C5:C104,B66,'8-Conges Annuels'!J5:J104,"En cours")) | I66: =IF(B66="","",IFERROR(E66/D66,0))
C67: =IFERROR(VLOOKUP(B67,'2-Fiche Employe'!B5:D104,3,FALSE),"") | E67: =IF(B67="","",SUMIFS('8-Conges Annuels'!H5:H104,'8-Conges Annuels'!C5:C104,B67,'8-Conges Annuels'!J5:J104,"Approuve")) | F67: =IF(B67="","",D67-E67-G67+H67) | G67: =IF(B67="","",SUMIFS('8-Conges Annuels'!H5:H104,'8-Conges Annuels'!C5:C104,B67,'8-Conges Annuels'!J5:J104,"En cours")) | I67: =IF(B67="","",IFERROR(E67/D67,0))
C68: =IFERROR(VLOOKUP(B68,'2-Fiche Employe'!B5:D104,3,FALSE),"") | E68: =IF(B68="","",SUMIFS('8-Conges Annuels'!H5:H104,'8-Conges Annuels'!C5:C104,B68,'8-Conges Annuels'!J5:J104,"Approuve")) | F68: =IF(B68="","",D68-E68-G68+H68) | G68: =IF(B68="","",SUMIFS('8-Conges Annuels'!H5:H104,'8-Conges Annuels'!C5:C104,B68,'8-Conges Annuels'!J5:J104,"En cours")) | I68: =IF(B68="","",IFERROR(E68/D68,0))
C69: =IFERROR(VLOOKUP(B69,'2-Fiche Employe'!B5:D104,3,FALSE),"") | E69: =IF(B69="","",SUMIFS('8-Conges Annuels'!H5:H104,'8-Conges Annuels'!C5:C104,B69,'8-Conges Annuels'!J5:J104,"Approuve")) | F69: =IF(B69="","",D69-E69-G69+H69) | G69: =IF(B69="","",SUMIFS('8-Conges Annuels'!H5:H104,'8-Conges Annuels'!C5:C104,B69,'8-Conges Annuels'!J5:J104,"En cours")) | I69: =IF(B69="","",IFERROR(E69/D69,0))
C70: =IFERROR(VLOOKUP(B70,'2-Fiche Employe'!B5:D104,3,FALSE),"") | E70: =IF(B70="","",SUMIFS('8-Conges Annuels'!H5:H104,'8-Conges Annuels'!C5:C104,B70,'8-Conges Annuels'!J5:J104,"Approuve")) | F70: =IF(B70="","",D70-E70-G70+H70) | G70: =IF(B70="","",SUMIFS('8-Conges Annuels'!H5:H104,'8-Conges Annuels'!C5:C104,B70,'8-Conges Annuels'!J5:J104,"En cours")) | I70: =IF(B70="","",IFERROR(E70/D70,0))
C71: =IFERROR(VLOOKUP(B71,'2-Fiche Employe'!B5:D104,3,FALSE),"") | E71: =IF(B71="","",SUMIFS('8-Conges Annuels'!H5:H104,'8-Conges Annuels'!C5:C104,B71,'8-Conges Annuels'!J5:J104,"Approuve")) | F71: =IF(B71="","",D71-E71-G71+H71) | G71: =IF(B71="","",SUMIFS('8-Conges Annuels'!H5:H104,'8-Conges Annuels'!C5:C104,B71,'8-Conges Annuels'!J5:J104,"En cours")) | I71: =IF(B71="","",IFERROR(E71/D71,0))
C72: =IFERROR(VLOOKUP(B72,'2-Fiche Employe'!B5:D104,3,FALSE),"") | E72: =IF(B72="","",SUMIFS('8-Conges Annuels'!H5:H104,'8-Conges Annuels'!C5:C104,B72,'8-Conges Annuels'!J5:J104,"Approuve")) | F72: =IF(B72="","",D72-E72-G72+H72) | G72: =IF(B72="","",SUMIFS('8-Conges Annuels'!H5:H104,'8-Conges Annuels'!C5:C104,B72,'8-Conges Annuels'!J5:J104,"En cours")) | I72: =IF(B72="","",IFERROR(E72/D72,0))
C73: =IFERROR(VLOOKUP(B73,'2-Fiche Employe'!B5:D104,3,FALSE),"") | E73: =IF(B73="","",SUMIFS('8-Conges Annuels'!H5:H104,'8-Conges Annuels'!C5:C104,B73,'8-Conges Annuels'!J5:J104,"Approuve")) | F73: =IF(B73="","",D73-E73-G73+H73) | G73: =IF(B73="","",SUMIFS('8-Conges Annuels'!H5:H104,'8-Conges Annuels'!C5:C104,B73,'8-Conges Annuels'!J5:J104,"En cours")) | I73: =IF(B73="","",IFERROR(E73/D73,0))
C74: =IFERROR(VLOOKUP(B74,'2-Fiche Employe'!B5:D104,3,FALSE),"") | E74: =IF(B74="","",SUMIFS('8-Conges Annuels'!H5:H104,'8-Conges Annuels'!C5:C104,B74,'8-Conges Annuels'!J5:J104,"Approuve")) | F74: =IF(B74="","",D74-E74-G74+H74) | G74: =IF(B74="","",SUMIFS('8-Conges Annuels'!H5:H104,'8-Conges Annuels'!C5:C104,B74,'8-Conges Annuels'!J5:J104,"En cours")) | I74: =IF(B74="","",IFERROR(E74/D74,0))
C75: =IFERROR(VLOOKUP(B75,'2-Fiche Employe'!B5:D104,3,FALSE),"") | E75: =IF(B75="","",SUMIFS('8-Conges Annuels'!H5:H104,'8-Conges Annuels'!C5:C104,B75,'8-Conges Annuels'!J5:J104,"Approuve")) | F75: =IF(B75="","",D75-E75-G75+H75) | G75: =IF(B75="","",SUMIFS('8-Conges Annuels'!H5:H104,'8-Conges Annuels'!C5:C104,B75,'8-Conges Annuels'!J5:J104,"En cours")) | I75: =IF(B75="","",IFERROR(E75/D75,0))
C76: =IFERROR(VLOOKUP(B76,'2-Fiche Employe'!B5:D104,3,FALSE),"") | E76: =IF(B76="","",SUMIFS('8-Conges Annuels'!H5:H104,'8-Conges Annuels'!C5:C104,B76,'8-Conges Annuels'!J5:J104,"Approuve")) | F76: =IF(B76="","",D76-E76-G76+H76) | G76: =IF(B76="","",SUMIFS('8-Conges Annuels'!H5:H104,'8-Conges Annuels'!C5:C104,B76,'8-Conges Annuels'!J5:J104,"En cours")) | I76: =IF(B76="","",IFERROR(E76/D76,0))
C77: =IFERROR(VLOOKUP(B77,'2-Fiche Employe'!B5:D104,3,FALSE),"") | E77: =IF(B77="","",SUMIFS('8-Conges Annuels'!H5:H104,'8-Conges Annuels'!C5:C104,B77,'8-Conges Annuels'!J5:J104,"Approuve")) | F77: =IF(B77="","",D77-E77-G77+H77) | G77: =IF(B77="","",SUMIFS('8-Conges Annuels'!H5:H104,'8-Conges Annuels'!C5:C104,B77,'8-Conges Annuels'!J5:J104,"En cours")) | I77: =IF(B77="","",IFERROR(E77/D77,0))
C78: =IFERROR(VLOOKUP(B78,'2-Fiche Employe'!B5:D104,3,FALSE),"") | E78: =IF(B78="","",SUMIFS('8-Conges Annuels'!H5:H104,'8-Conges Annuels'!C5:C104,B78,'8-Conges Annuels'!J5:J104,"Approuve")) | F78: =IF(B78="","",D78-E78-G78+H78) | G78: =IF(B78="","",SUMIFS('8-Conges Annuels'!H5:H104,'8-Conges Annuels'!C5:C104,B78,'8-Conges Annuels'!J5:J104,"En cours")) | I78: =IF(B78="","",IFERROR(E78/D78,0))
C79: =IFERROR(VLOOKUP(B79,'2-Fiche Employe'!B5:D104,3,FALSE),"") | E79: =IF(B79="","",SUMIFS('8-Conges Annuels'!H5:H104,'8-Conges Annuels'!C5:C104,B79,'8-Conges Annuels'!J5:J104,"Approuve")) | F79: =IF(B79="","",D79-E79-G79+H79) | G79: =IF(B79="","",SUMIFS('8-Conges Annuels'!H5:H104,'8-Conges Annuels'!C5:C104,B79,'8-Conges Annuels'!J5:J104,"En cours")) | I79: =IF(B79="","",IFERROR(E79/D79,0))
C80: =IFERROR(VLOOKUP(B80,'2-Fiche Employe'!B5:D104,3,FALSE),"") | E80: =IF(B80="","",SUMIFS('8-Conges Annuels'!H5:H104,'8-Conges Annuels'!C5:C104,B80,'8-Conges Annuels'!J5:J104,"Approuve")) | F80: =IF(B80="","",D80-E80-G80+H80) | G80: =IF(B80="","",SUMIFS('8-Conges Annuels'!H5:H104,'8-Conges Annuels'!C5:C104,B80,'8-Conges Annuels'!J5:J104,"En cours")) | I80: =IF(B80="","",IFERROR(E80/D80,0))
C81: =IFERROR(VLOOKUP(B81,'2-Fiche Employe'!B5:D104,3,FALSE),"") | E81: =IF(B81="","",SUMIFS('8-Conges Annuels'!H5:H104,'8-Conges Annuels'!C5:C104,B81,'8-Conges Annuels'!J5:J104,"Approuve")) | F81: =IF(B81="","",D81-E81-G81+H81) | G81: =IF(B81="","",SUMIFS('8-Conges Annuels'!H5:H104,'8-Conges Annuels'!C5:C104,B81,'8-Conges Annuels'!J5:J104,"En cours")) | I81: =IF(B81="","",IFERROR(E81/D81,0))
C82: =IFERROR(VLOOKUP(B82,'2-Fiche Employe'!B5:D104,3,FALSE),"") | E82: =IF(B82="","",SUMIFS('8-Conges Annuels'!H5:H104,'8-Conges Annuels'!C5:C104,B82,'8-Conges Annuels'!J5:J104,"Approuve")) | F82: =IF(B82="","",D82-E82-G82+H82) | G82: =IF(B82="","",SUMIFS('8-Conges Annuels'!H5:H104,'8-Conges Annuels'!C5:C104,B82,'8-Conges Annuels'!J5:J104,"En cours")) | I82: =IF(B82="","",IFERROR(E82/D82,0))
C83: =IFERROR(VLOOKUP(B83,'2-Fiche Employe'!B5:D104,3,FALSE),"") | E83: =IF(B83="","",SUMIFS('8-Conges Annuels'!H5:H104,'8-Conges Annuels'!C5:C104,B83,'8-Conges Annuels'!J5:J104,"Approuve")) | F83: =IF(B83="","",D83-E83-G83+H83) | G83: =IF(B83="","",SUMIFS('8-Conges Annuels'!H5:H104,'8-Conges Annuels'!C5:C104,B83,'8-Conges Annuels'!J5:J104,"En cours")) | I83: =IF(B83="","",IFERROR(E83/D83,0))
C84: =IFERROR(VLOOKUP(B84,'2-Fiche Employe'!B5:D104,3,FALSE),"") | E84: =IF(B84="","",SUMIFS('8-Conges Annuels'!H5:H104,'8-Conges Annuels'!C5:C104,B84,'8-Conges Annuels'!J5:J104,"Approuve")) | F84: =IF(B84="","",D84-E84-G84+H84) | G84: =IF(B84="","",SUMIFS('8-Conges Annuels'!H5:H104,'8-Conges Annuels'!C5:C104,B84,'8-Conges Annuels'!J5:J104,"En cours")) | I84: =IF(B84="","",IFERROR(E84/D84,0))
C85: =IFERROR(VLOOKUP(B85,'2-Fiche Employe'!B5:D104,3,FALSE),"") | E85: =IF(B85="","",SUMIFS('8-Conges Annuels'!H5:H104,'8-Conges Annuels'!C5:C104,B85,'8-Conges Annuels'!J5:J104,"Approuve")) | F85: =IF(B85="","",D85-E85-G85+H85) | G85: =IF(B85="","",SUMIFS('8-Conges Annuels'!H5:H104,'8-Conges Annuels'!C5:C104,B85,'8-Conges Annuels'!J5:J104,"En cours")) | I85: =IF(B85="","",IFERROR(E85/D85,0))
C86: =IFERROR(VLOOKUP(B86,'2-Fiche Employe'!B5:D104,3,FALSE),"") | E86: =IF(B86="","",SUMIFS('8-Conges Annuels'!H5:H104,'8-Conges Annuels'!C5:C104,B86,'8-Conges Annuels'!J5:J104,"Approuve")) | F86: =IF(B86="","",D86-E86-G86+H86) | G86: =IF(B86="","",SUMIFS('8-Conges Annuels'!H5:H104,'8-Conges Annuels'!C5:C104,B86,'8-Conges Annuels'!J5:J104,"En cours")) | I86: =IF(B86="","",IFERROR(E86/D86,0))
C87: =IFERROR(VLOOKUP(B87,'2-Fiche Employe'!B5:D104,3,FALSE),"") | E87: =IF(B87="","",SUMIFS('8-Conges Annuels'!H5:H104,'8-Conges Annuels'!C5:C104,B87,'8-Conges Annuels'!J5:J104,"Approuve")) | F87: =IF(B87="","",D87-E87-G87+H87) | G87: =IF(B87="","",SUMIFS('8-Conges Annuels'!H5:H104,'8-Conges Annuels'!C5:C104,B87,'8-Conges Annuels'!J5:J104,"En cours")) | I87: =IF(B87="","",IFERROR(E87/D87,0))
C88: =IFERROR(VLOOKUP(B88,'2-Fiche Employe'!B5:D104,3,FALSE),"") | E88: =IF(B88="","",SUMIFS('8-Conges Annuels'!H5:H104,'8-Conges Annuels'!C5:C104,B88,'8-Conges Annuels'!J5:J104,"Approuve")) | F88: =IF(B88="","",D88-E88-G88+H88) | G88: =IF(B88="","",SUMIFS('8-Conges Annuels'!H5:H104,'8-Conges Annuels'!C5:C104,B88,'8-Conges Annuels'!J5:J104,"En cours")) | I88: =IF(B88="","",IFERROR(E88/D88,0))
C89: =IFERROR(VLOOKUP(B89,'2-Fiche Employe'!B5:D104,3,FALSE),"") | E89: =IF(B89="","",SUMIFS('8-Conges Annuels'!H5:H104,'8-Conges Annuels'!C5:C104,B89,'8-Conges Annuels'!J5:J104,"Approuve")) | F89: =IF(B89="","",D89-E89-G89+H89) | G89: =IF(B89="","",SUMIFS('8-Conges Annuels'!H5:H104,'8-Conges Annuels'!C5:C104,B89,'8-Conges Annuels'!J5:J104,"En cours")) | I89: =IF(B89="","",IFERROR(E89/D89,0))
C90: =IFERROR(VLOOKUP(B90,'2-Fiche Employe'!B5:D104,3,FALSE),"") | E90: =IF(B90="","",SUMIFS('8-Conges Annuels'!H5:H104,'8-Conges Annuels'!C5:C104,B90,'8-Conges Annuels'!J5:J104,"Approuve")) | F90: =IF(B90="","",D90-E90-G90+H90) | G90: =IF(B90="","",SUMIFS('8-Conges Annuels'!H5:H104,'8-Conges Annuels'!C5:C104,B90,'8-Conges Annuels'!J5:J104,"En cours")) | I90: =IF(B90="","",IFERROR(E90/D90,0))
C91: =IFERROR(VLOOKUP(B91,'2-Fiche Employe'!B5:D104,3,FALSE),"") | E91: =IF(B91="","",SUMIFS('8-Conges Annuels'!H5:H104,'8-Conges Annuels'!C5:C104,B91,'8-Conges Annuels'!J5:J104,"Approuve")) | F91: =IF(B91="","",D91-E91-G91+H91) | G91: =IF(B91="","",SUMIFS('8-Conges Annuels'!H5:H104,'8-Conges Annuels'!C5:C104,B91,'8-Conges Annuels'!J5:J104,"En cours")) | I91: =IF(B91="","",IFERROR(E91/D91,0))
C92: =IFERROR(VLOOKUP(B92,'2-Fiche Employe'!B5:D104,3,FALSE),"") | E92: =IF(B92="","",SUMIFS('8-Conges Annuels'!H5:H104,'8-Conges Annuels'!C5:C104,B92,'8-Conges Annuels'!J5:J104,"Approuve")) | F92: =IF(B92="","",D92-E92-G92+H92) | G92: =IF(B92="","",SUMIFS('8-Conges Annuels'!H5:H104,'8-Conges Annuels'!C5:C104,B92,'8-Conges Annuels'!J5:J104,"En cours")) | I92: =IF(B92="","",IFERROR(E92/D92,0))
C93: =IFERROR(VLOOKUP(B93,'2-Fiche Employe'!B5:D104,3,FALSE),"") | E93: =IF(B93="","",SUMIFS('8-Conges Annuels'!H5:H104,'8-Conges Annuels'!C5:C104,B93,'8-Conges Annuels'!J5:J104,"Approuve")) | F93: =IF(B93="","",D93-E93-G93+H93) | G93: =IF(B93="","",SUMIFS('8-Conges Annuels'!H5:H104,'8-Conges Annuels'!C5:C104,B93,'8-Conges Annuels'!J5:J104,"En cours")) | I93: =IF(B93="","",IFERROR(E93/D93,0))
C94: =IFERROR(VLOOKUP(B94,'2-Fiche Employe'!B5:D104,3,FALSE),"") | E94: =IF(B94="","",SUMIFS('8-Conges Annuels'!H5:H104,'8-Conges Annuels'!C5:C104,B94,'8-Conges Annuels'!J5:J104,"Approuve")) | F94: =IF(B94="","",D94-E94-G94+H94) | G94: =IF(B94="","",SUMIFS('8-Conges Annuels'!H5:H104,'8-Conges Annuels'!C5:C104,B94,'8-Conges Annuels'!J5:J104,"En cours")) | I94: =IF(B94="","",IFERROR(E94/D94,0))
C95: =IFERROR(VLOOKUP(B95,'2-Fiche Employe'!B5:D104,3,FALSE),"") | E95: =IF(B95="","",SUMIFS('8-Conges Annuels'!H5:H104,'8-Conges Annuels'!C5:C104,B95,'8-Conges Annuels'!J5:J104,"Approuve")) | F95: =IF(B95="","",D95-E95-G95+H95) | G95: =IF(B95="","",SUMIFS('8-Conges Annuels'!H5:H104,'8-Conges Annuels'!C5:C104,B95,'8-Conges Annuels'!J5:J104,"En cours")) | I95: =IF(B95="","",IFERROR(E95/D95,0))
C96: =IFERROR(VLOOKUP(B96,'2-Fiche Employe'!B5:D104,3,FALSE),"") | E96: =IF(B96="","",SUMIFS('8-Conges Annuels'!H5:H104,'8-Conges Annuels'!C5:C104,B96,'8-Conges Annuels'!J5:J104,"Approuve")) | F96: =IF(B96="","",D96-E96-G96+H96) | G96: =IF(B96="","",SUMIFS('8-Conges Annuels'!H5:H104,'8-Conges Annuels'!C5:C104,B96,'8-Conges Annuels'!J5:J104,"En cours")) | I96: =IF(B96="","",IFERROR(E96/D96,0))
C97: =IFERROR(VLOOKUP(B97,'2-Fiche Employe'!B5:D104,3,FALSE),"") | E97: =IF(B97="","",SUMIFS('8-Conges Annuels'!H5:H104,'8-Conges Annuels'!C5:C104,B97,'8-Conges Annuels'!J5:J104,"Approuve")) | F97: =IF(B97="","",D97-E97-G97+H97) | G97: =IF(B97="","",SUMIFS('8-Conges Annuels'!H5:H104,'8-Conges Annuels'!C5:C104,B97,'8-Conges Annuels'!J5:J104,"En cours")) | I97: =IF(B97="","",IFERROR(E97/D97,0))
C98: =IFERROR(VLOOKUP(B98,'2-Fiche Employe'!B5:D104,3,FALSE),"") | E98: =IF(B98="","",SUMIFS('8-Conges Annuels'!H5:H104,'8-Conges Annuels'!C5:C104,B98,'8-Conges Annuels'!J5:J104,"Approuve")) | F98: =IF(B98="","",D98-E98-G98+H98) | G98: =IF(B98="","",SUMIFS('8-Conges Annuels'!H5:H104,'8-Conges Annuels'!C5:C104,B98,'8-Conges Annuels'!J5:J104,"En cours")) | I98: =IF(B98="","",IFERROR(E98/D98,0))
C99: =IFERROR(VLOOKUP(B99,'2-Fiche Employe'!B5:D104,3,FALSE),"") | E99: =IF(B99="","",SUMIFS('8-Conges Annuels'!H5:H104,'8-Conges Annuels'!C5:C104,B99,'8-Conges Annuels'!J5:J104,"Approuve")) | F99: =IF(B99="","",D99-E99-G99+H99) | G99: =IF(B99="","",SUMIFS('8-Conges Annuels'!H5:H104,'8-Conges Annuels'!C5:C104,B99,'8-Conges Annuels'!J5:J104,"En cours")) | I99: =IF(B99="","",IFERROR(E99/D99,0))
C100: =IFERROR(VLOOKUP(B100,'2-Fiche Employe'!B5:D104,3,FALSE),"") | E100: =IF(B100="","",SUMIFS('8-Conges Annuels'!H5:H104,'8-Conges Annuels'!C5:C104,B100,'8-Conges Annuels'!J5:J104,"Approuve")) | F100: =IF(B100="","",D100-E100-G100+H100) | G100: =IF(B100="","",SUMIFS('8-Conges Annuels'!H5:H104,'8-Conges Annuels'!C5:C104,B100,'8-Conges Annuels'!J5:J104,"En cours")) | I100: =IF(B100="","",IFERROR(E100/D100,0))
C101: =IFERROR(VLOOKUP(B101,'2-Fiche Employe'!B5:D104,3,FALSE),"") | E101: =IF(B101="","",SUMIFS('8-Conges Annuels'!H5:H104,'8-Conges Annuels'!C5:C104,B101,'8-Conges Annuels'!J5:J104,"Approuve")) | F101: =IF(B101="","",D101-E101-G101+H101) | G101: =IF(B101="","",SUMIFS('8-Conges Annuels'!H5:H104,'8-Conges Annuels'!C5:C104,B101,'8-Conges Annuels'!J5:J104,"En cours")) | I101: =IF(B101="","",IFERROR(E101/D101,0))
...

Sheet 10-Absences Maladie
B2: ABSENCES & MALADIE
B3: TABLEAU DYNAMIQUE — Saisissez dans la prochaine ligne jaune. Les calculs se mettent a jour automatiquement.
B4: N° | C4: Matricule | D4: Nom Employé | E4: Type Absence | F4: Date Début | G4: Date Fin | H4: Durée (jours) | I4: Justificatif | J4: Statut | K4: Motif | L4: Observations
B5: ABS-001 | C5: EMP-003 | D5: Fotso Marguerite | E5: Maladie | F5: 45698 | G5: 45702 | H5: 5 | I5: Oui | J5: Justifiee | K5: Grippe | L5: Certificat medical remis
B6: ABS-002 | C6: EMP-005 | D6: Kamga Paul | E6: Accident travail | F6: 45736 | G6: 45741 | H6: 6 | I6: Oui | J6: Approuvee | K6: Blessure atelier | L6: Dossier CNPS ouvert
B7: ABS-003 | C7: EMP-004 | D7: Nkoulou Mbarga | E7: Permission exceptionnelle | F7: 45749 | G7: 45749 | H7: 1 | I7: Non | J7: Approuvee | K7: Demarches admin
B8: =IF(C8="","ABS-"&TEXT(COUNTA($C$5:C8),"000")) | H8: =IF(OR(G8="",F8=""),"",G8-F8+1)
B9: =IF(C9="","ABS-"&TEXT(COUNTA($C$5:C9),"000")) | H9: =IF(OR(G9="",F9=""),"",G9-F9+1)
B10: =IF(C10="","ABS-"&TEXT(COUNTA($C$5:C10),"000")) | H10: =IF(OR(G10="",F10=""),"",G10-F10+1)
B11: =IF(C11="","ABS-"&TEXT(COUNTA($C$5:C11),"000")) | H11: =IF(OR(G11="",F11=""),"",G11-F11+1)
B12: =IF(C12="","ABS-"&TEXT(COUNTA($C$5:C12),"000")) | H12: =IF(OR(G12="",F12=""),"",G12-F12+1)
B13: =IF(C13="","ABS-"&TEXT(COUNTA($C$5:C13),"000")) | H13: =IF(OR(G13="",F13=""),"",G13-F13+1)
B14: =IF(C14="","ABS-"&TEXT(COUNTA($C$5:C14),"000")) | H14: =IF(OR(G14="",F14=""),"",G14-F14+1)
B15: =IF(C15="","ABS-"&TEXT(COUNTA($C$5:C15),"000")) | H15: =IF(OR(G15="",F15=""),"",G15-F15+1)
B16: =IF(C16="","ABS-"&TEXT(COUNTA($C$5:C16),"000")) | H16: =IF(OR(G16="",F16=""),"",G16-F16+1)
B17: =IF(C17="","ABS-"&TEXT(COUNTA($C$5:C17),"000")) | H17: =IF(OR(G17="",F17=""),"",G17-F17+1)
B18: =IF(C18="","ABS-"&TEXT(COUNTA($C$5:C18),"000")) | H18: =IF(OR(G18="",F18=""),"",G18-F18+1)
B19: =IF(C19="","ABS-"&TEXT(COUNTA($C$5:C19),"000")) | H19: =IF(OR(G19="",F19=""),"",G19-F19+1)
... B107: =IF(C107="","ABS-"&TEXT(COUNTA($C$5:C107),"000")) | H107: =IF(OR(G107="",F107=""),"",G107-F107+1)
B109: INDICATEURS (mis a jour automatiquement)
B110: Total absences | D110: Justifiées | F110: Non justifiées | H110: Total jours absences
B111: =COUNTIF(B5:B104,"<>") | D111: =COUNTIF(J5:J104,"Justifiee") | F111: =COUNTIF(J5:J104,"Non justifiee") | H111: =SUM(H5:H104)

Sheet 11-Heures Supplementaires
B2: HEURES SUPPLEMENTAIRES
B3: TABLEAU DYNAMIQUE — Saisissez dans la prochaine ligne jaune. Les calculs se mettent a jour automatiquement.
B4: N° | C4: Matricule | D4: Nom Employé | E4: Semaine | F4: Heures Normales | G4: Heures Supp | H4: Taux Majoration | I4: Montant (FCFA) | J4: Montant Calculé (FCFA) | K4: Statut | L4: Validé Par
B5: HS-001 | C5: EMP-005 | D5: Kamga Paul | E5: S12-2025 | F5: 40 | G5: 8 | H5: 125% | J5: =IF(OR(G5="",H5=""),"",IFERROR(G5*2000,0)) | K5: Validee | L5: Chef Diallo
B6: HS-002 | C6: EMP-005 | D6: Kamga Paul | E6: S13-2025 | F6: 40 | G6: 12 | H6: 150% | J6: =IF(OR(G6="",H6=""),"",IFERROR(G6*2000,0)) | K6: Validee | L6: Chef Diallo
B7: HS-003 | C7: EMP-004 | D7: Nkoulou Mbarga | E7: S13-2025 | F7: 40 | G7: 6 | H7: 125% | J7: =IF(OR(G7="",H7=""),"",IFERROR(G7*2000,0)) | K7: En attente | L7: Superviseur
B8: HS-004 | C8: EMP-002 | D8: Tchinda Armand | E8: S14-2025 | F8: 40 | G8: 4 | H8: 150% | J8: =IF(OR(G8="",H8=""),"",IFERROR(G8*2000,0)) | K8: En attente | L8: DRH Nganou
B9: =IF(C9="","HS-"&TEXT(COUNTA($C$5:C9),"000")) | J9: =IF(OR(G9="",H9=""),"",IFERROR(G9*2000,0))
B10: =IF(C10="","HS-"&TEXT(COUNTA($C$5:C10),"000")) | J10: =IF(OR(G10="",H10=""),"",IFERROR(G10*2000,0))
B11: =IF(C11="","HS-"&TEXT(COUNTA($C$5:C11),"000")) | J11: =IF(OR(G11="",H11=""),"",IFERROR(G11*2000,0))
B12: =IF(C12="","HS-"&TEXT(COUNTA($C$5:C12),"000")) | J12: =IF(OR(G12="",H12=""),"",IFERROR(G12*2000,0))
B13: =IF(C13="","HS-"&TEXT(COUNTA($C$5:C13),"000")) | J13: =IF(OR(G13="",H13=""),"",IFERROR(G13*2000,0))
B14: =IF(C14="","HS-"&TEXT(COUNTA($C$5:C14),"000")) | J14: =IF(OR(G14="",H14=""),"",IFERROR(G14*2000,0))
B15: =IF(C15="","HS-"&TEXT(COUNTA($C$5:C15),"000")) | J15: =IF(OR(G15="",H15=""),"",IFERROR(G15*2000,0))
B16: =IF(C16="","HS-"&TEXT(COUNTA($C$5:C16),"000")) | J16: =IF(OR(G16="",H16=""),"",IFERROR(G16*2000,0))
B17: =IF(C17="","HS-"&TEXT(COUNTA($C$5:C17),"000")) | J17: =IF(OR(G17="",H17=""),"",IFERROR(G17*2000,0))
B18: =IF(C18="","HS-"&TEXT(COUNTA($C$5:C18),"000")) | J18: =IF(OR(G18="",H18=""),"",IFERROR(G18*2000,0))
B19: =IF(C19="","HS-"&TEXT(COUNTA($C$5:C19),"000")) | J19: =IF(OR(G19="",H19=""),"",IFERROR(G19*2000,0))
B20: =IF(C20="","HS-"&TEXT(COUNTA($C$5:C20),"000")) | J20: =IF(OR(G20="",H20=""),"",IFERROR(G20*2000,0))
... B104: =IF(C104="","HS-"&TEXT(COUNTA($C$5:C104),"000")) | J104: =IF(OR(G104="",H104=""),"",IFERROR(G104*2000,0))
B105: =IF(C105="","HS-"&TEXT(COUNTA($C$5:C105),"000"))
B106: =IF(C106="","HS-"&TEXT(COUNTA($C$5:C106),"000"))
B107: =IF(C107="","HS-"&TEXT(COUNTA($C$5:C107),"000"))
B108: =IF(C108="","HS-"&TEXT(COUNTA($C$5:C108),"000"))
B110: TOTAL | G110: =SUM(G5:G104) | I110: =SUM(I5:I104)
B112: INDICATEURS (mis a jour automatiquement)
B113: Total heures supp | D113: Montant total (FCFA) | F113: En attente validation
B114: =SUM(G5:G104) | D114: =SUM(I5:I104) | F114: =COUNTIF(J5:J104,"En attente")

Sheet 12-Pointage Presence
B2: POINTAGE & PRESENCE HEBDOMADAIRE
B3: TABLEAU DYNAMIQUE — Saisissez dans la prochaine ligne jaune. Les calculs se mettent a jour automatiquement.
B4: N° | C4: Matricule | D4: Nom Employé | E4: Semaine | F4: Jours Présents | G4: Jours Absents | H4: Retards (min) | I4: Heures Supp | J4: Taux Présence (%) | K4: Observations
B5: PNT-001 | C5: EMP-001 | D5: Nganou Clarisse | E5: S12-2025 | F5: 5 | G5: 0 | H5: 0 | I5: 0
B6: PNT-002 | C6: EMP-002 | D6: Tchinda Armand | E6: S12-2025 | F6: 5 | G6: 0 | H6: 30 | I6: 4 | K6: Retard lundi 30 min
B7: PNT-003 | C7: EMP-003 | D7: Fotso Marguerite | E7: S12-2025 | F7: 3 | G7: 2 | H7: 0 | I7: 0 | K7: Absence maladie
B8: PNT-004 | C8: EMP-004 | D8: Nkoulou Mbarga | E8: S12-2025 | F8: 5 | G8: 0 | H8: 0 | I8: 6 | K8: 6h supp jeudi
B9: PNT-005 | C9: EMP-005 | D9: Kamga Paul | E9: S12-2025 | F9: 5 | G9: 0 | H9: 15 | I9: 8 | K9: Retard 15 min mercredi
B10: =IF(C10="","PNT-"&TEXT(COUNTA($C$5:C10),"000")) | J10: =IF(F10="","",IFERROR(F10/(F10+G10),0))
B11: =IF(C11="","PNT-"&TEXT(COUNTA($C$5:C11),"000")) | J11: =IF(F11="","",IFERROR(F11/(F11+G11),0))
B12: =IF(C12="","PNT-"&TEXT(COUNTA($C$5:C12),"000")) | J12: =IF(F12="","",IFERROR(F12/(F12+G12),0))
B13: =IF(C13="","PNT-"&TEXT(COUNTA($C$5:C13),"000")) | J13: =IF(F13="","",IFERROR(F13/(F13+G13),0))
B14: =IF(C14="","PNT-"&TEXT(COUNTA($C$5:C14),"000")) | J14: =IF(F14="","",IFERROR(F14/(F14+G14),0))
B15: =IF(C15="","PNT-"&TEXT(COUNTA($C$5:C15),"000")) | J15: =IF(F15="","",IFERROR(F15/(F15+G15),0))
B16: =IF(C16="","PNT-"&TEXT(COUNTA($C$5:C16),"000")) | J16: =IF(F16="","",IFERROR(F16/(F16+G16),0))
B17: =IF(C17="","PNT-"&TEXT(COUNTA($C$5:C17),"000")) | J17: =IF(F17="","",IFERROR(F17/(F17+G17),0))
B18: =IF(C18="","PNT-"&TEXT(COUNTA($C$5:C18),"000")) | J18: =IF(F18="","",IFERROR(F18/(F18+G18),0))
B19: =IF(C19="","PNT-"&TEXT(COUNTA($C$5:C19),"000")) | J19: =IF(F19="","",IFERROR(F19/(F19+G19),0))
B20: =IF(C20="","PNT-"&TEXT(COUNTA($C$5:C20),"000")) | J20: =IF(F20="","",IFERROR(F20/(F20+G20),0))
B21: =IF(C21="","PNT-"&TEXT(COUNTA($C$5:C21),"000")) | J21: =IF(F21="","",IFERROR(F21/(F21+G21),0))
... B109: =IF(C109="","PNT-"&TEXT(COUNTA($C$5:C109),"000")) | J109: =IF(F109="","",IFERROR(F109/(F109+G109),0))
B111: INDICATEURS (mis a jour automatiquement)
B112: Total lignes | D112: Taux présence moyen | F112: Total retards (min)
B113: =COUNTIF(B5:B104,"<>") | D113: =IFERROR(AVERAGE(J5:J104),0) | F113: =SUM(H5:H104)

Sheet 13-Fiches de Paie
B2: FICHES DE PAIE
B3: TABLEAU DYNAMIQUE — Saisissez dans la prochaine ligne jaune. Les calculs se mettent a jour automatiquement.
B4: N° | C4: Matricule | D4: Nom Employé | E4: Mois | F4: Salaire Brut (FCFA) | G4: Cotisations (FCFA) | H4: Taux Charges (%) | I4: Net à Payer (FCFA) | J4: Mode Paiement | K4: Date Paiement | L4: Statut
B5: PAIE-001 | C5: EMP-001 | D5: Nganou Clarisse | E5: Janvier 2025 | F5: 450000 | G5: 67500 | H5: =IF(F5="","",IFERROR(G5/F5,0)) | J5: Virement bancaire | K5: 45688 | L5: Payee
B6: PAIE-002 | C6: EMP-002 | D6: Tchinda Armand | E6: Janvier 2025 | F6: 420000 | G6: 63000 | H6: =IF(F6="","",IFERROR(G6/F6,0)) | J6: Virement bancaire | K6: 45688 | L6: Payee
B7: PAIE-003 | C7: EMP-003 | D7: Fotso Marguerite | E7: Janvier 2025 | F7: 380000 | G7: 57000 | H7: =IF(F7="","",IFERROR(G7/F7,0)) | J7: Virement bancaire | K7: 45688 | L7: Payee
B8: PAIE-004 | C8: EMP-004 | D8: Nkoulou Mbarga | E8: Janvier 2025 | F8: 180000 | G8: 27000 | H8: =IF(F8="","",IFERROR(G8/F8,0)) | J8: Virement bancaire | K8: 45688 | L8: Payee
B9: PAIE-005 | C9: EMP-005 | D9: Kamga Paul | E9: Janvier 2025 | F9: 130000 | G9: 19500 | H9: =IF(F9="","",IFERROR(G9/F9,0)) | J9: Virement bancaire | K9: 45688 | L9: Payee
B10: PAIE-006 | C10: EMP-001 | D10: Nganou Clarisse | E10: Fevrier 2025 | F10: 450000 | G10: 67500 | H10: =IF(F10="","",IFERROR(G10/F10,0)) | J10: Virement bancaire | K10: 45716 | L10: Payee
B11: PAIE-007 | C11: EMP-002 | D11: Tchinda Armand | E11: Fevrier 2025 | F11: 420000 | G11: 63000 | H11: =IF(F11="","",IFERROR(G11/F11,0)) | J11: Virement bancaire | K11: 45716 | L11: Payee
B12: =IF(C12="","PAIE-"&TEXT(COUNTA($C$5:C12),"000")) | H12: =IF(F12="","",IFERROR(G12/F12,0)) | I12: =IF(F12="","",F12-G12)
B13: =IF(C13="","PAIE-"&TEXT(COUNTA($C$5:C13),"000")) | H13: =IF(F13="","",IFERROR(G13/F13,0)) | I13: =IF(F13="","",F13-G13)
B14: =IF(C14="","PAIE-"&TEXT(COUNTA($C$5:C14),"000")) | H14: =IF(F14="","",IFERROR(G14/F14,0)) | I14: =IF(F14="","",F14-G14)
B15: =IF(C15="","PAIE-"&TEXT(COUNTA($C$5:C15),"000")) | H15: =IF(F15="","",IFERROR(G15/F15,0)) | I15: =IF(F15="","",F15-G15)
B16: =IF(C16="","PAIE-"&TEXT(COUNTA($C$5:C16),"000")) | H16: =IF(F16="","",IFERROR(G16/F16,0)) | I16: =IF(F16="","",F16-G16)
B17: =IF(C17="","PAIE-"&TEXT(COUNTA($C$5:C17),"000")) | H17: =IF(F17="","",IFERROR(G17/F17,0)) | I17: =IF(F17="","",F17-G17)
B18: =IF(C18="","PAIE-"&TEXT(COUNTA($C$5:C18),"000")) | H18: =IF(F18="","",IFERROR(G18/F18,0)) | I18: =IF(F18="","",F18-G18)
B19: =IF(C19="","PAIE-"&TEXT(COUNTA($C$5:C19),"000")) | H19: =IF(F19="","",IFERROR(G19/F19,0)) | I19: =IF(F19="","",F19-G19)
B20: =IF(C20="","PAIE-"&TEXT(COUNTA($C$5:C20),"000")) | H20: =IF(F20="","",IFERROR(G20/F20,0)) | I20: =IF(F20="","",F20-G20)
B21: =IF(C21="","PAIE-"&TEXT(COUNTA($C$5:C21),"000")) | H21: =IF(F21="","",IFERROR(G21/F21,0)) | I21: =IF(F21="","",F21-G21)
B22: =IF(C22="","PAIE-"&TEXT(COUNTA($C$5:C22),"000")) | H22: =IF(F22="","",IFERROR(G22/F22,0)) | I22: =IF(F22="","",F22-G22)
B23: =IF(C23="","PAIE-"&TEXT(COUNTA($C$5:C23),"000")) | H23: =IF(F23="","",IFERROR(G23/F23,0)) | I23: =IF(F23="","",F23-G23)
... B104: =IF(C104="","PAIE-"&TEXT(COUNTA($C$5:C104),"000")) | H104: =IF(F104="","",IFERROR(G104/F104,0)) | I104: =IF(F104="","",F104-G104)
B105: =IF(C105="","PAIE-"&TEXT(COUNTA($C$5:C105),"000")) | I105: =IF(F105="","",F105-G105)
B106: =IF(C106="","PAIE-"&TEXT(COUNTA($C$5:C106),"000")) | I106: =IF(F106="","",F106-G106)
B107: =IF(C107="","PAIE-"&TEXT(COUNTA($C$5:C107),"000")) | I107: =IF(F107="","",F107-G107)
B108: =IF(C108="","PAIE-"&TEXT(COUNTA($C$5:C108),"000")) | I108: =IF(F108="","",F108-G108)
B109: =IF(C109="","PAIE-"&TEXT(COUNTA($C$5:C109),"000")) | I109: =IF(F109="","",F109-G109)
B110: =IF(C110="","PAIE-"&TEXT(COUNTA($C$5:C110),"000")) | I110: =IF(F110="","",F110-G110)
B111: =IF(C111="","PAIE-"&TEXT(COUNTA($C$5:C111),"000")) | I111: =IF(F111="","",F111-G111)
B113: TOTAL | F113: =SUM(F5:F104) | G113: =SUM(G5:G104) | I113: =SUM(H5:H104)
B115: INDICATEURS (mis a jour automatiquement)
B116: Total fiches | D116: Masse salariale brute | F116: Total cotisations | I116: Total net payé
B117: =COUNTIF(B5:B104,"<>") | D117: =SUM(F5:F104) | F117: =SUM(G5:G104) | I117: =SUM(H5:H104)

Sheet 14-Declarations Sociales
B2: DECLARATIONS SOCIALES & FISCALES
B3: TABLEAU DYNAMIQUE — Saisissez dans la prochaine ligne jaune. Les calculs se mettent a jour automatiquement.
B4: N° | C4: Organisme | D4: Type Déclaration | E4: Période | F4: Montant (FCFA) | G4: Date Soumission | H4: Date Échéance | I4: Statut | J4: Nombre Salariés | K4: Observations
B5: DECL-001 | C5: CNPS | D5: Mensuelle | E5: Janvier 2025 | F5: 285000 | G5: 45672 | H5: 45703 | I5: Soumise | J5: 5 | K5: Cotisations employeurs + salaries
B6: DECL-002 | C6: Direction des impots | D6: Mensuelle | E6: Janvier 2025 | F6: 120000 | G6: 45677 | H6: 45703 | I6: Soumise | J6: 5 | K6: IR sur salaires
B7: DECL-003 | C7: CNPS | D7: Mensuelle | E7: Fevrier 2025 | F7: 285000 | G7: 45703 | H7: 45731 | I7: En retard | J7: 5 | K7: Retard de soumission
B8: DECL-004 | C8: Mutuelle entreprise | D8: Trimestrielle | E8: T1 2025 | F8: 185000 | H8: 45777 | I8: En attente | J8: 3 | K8: Previsionnelle
B9: =IF(C9="","DECL-"&TEXT(COUNTA($C$5:C9),"000"))
B10: =IF(C10="","DECL-"&TEXT(COUNTA($C$5:C10),"000"))
B11: =IF(C11="","DECL-"&TEXT(COUNTA($C$5:C11),"000"))
B12: =IF(C12="","DECL-"&TEXT(COUNTA($C$5:C12),"000"))
B13: =IF(C13="","DECL-"&TEXT(COUNTA($C$5:C13),"000"))
B14: =IF(C14="","DECL-"&TEXT(COUNTA($C$5:C14),"000"))
B15: =IF(C15="","DECL-"&TEXT(COUNTA($C$5:C15),"000"))
B16: =IF(C16="","DECL-"&TEXT(COUNTA($C$5:C16),"000"))
B17: =IF(C17="","DECL-"&TEXT(COUNTA($C$5:C17),"000"))
B18: =IF(C18="","DECL-"&TEXT(COUNTA($C$5:C18),"000"))
B19: =IF(C19="","DECL-"&TEXT(COUNTA($C$5:C19),"000"))
B20: =IF(C20="","DECL-"&TEXT(COUNTA($C$5:C20),"000"))
... B108: =IF(C108="","DECL-"&TEXT(COUNTA($C$5:C108),"000"))
B110: TOTAL | F110: =SUM(F5:F104)
B112: INDICATEURS (mis a jour automatiquement)
B113: Total déclarations | D113: Soumises | F113: En retard | H113: Montant total (FCFA)
B114: =COUNTIF(B5:B104,"<>") | D114: =COUNTIF(I5:I104,"Soumise") | F114: =COUNTIF(I5:I104,"En retard") | H114: =SUM(F5:F104)

Sheet 15-Autorisations Permis
B2: AUTORISATIONS & PERMIS DE TRAVAIL
B3: TABLEAU DYNAMIQUE — Saisissez dans la prochaine ligne jaune. Les calculs se mettent a jour automatiquement.
B4: N° | C4: Matricule | D4: Nom Employé | E4: Type Permis | F4: N° Permis | G4: Date Délivrance | H4: Date Expiration | I4: Autorité | J4: Statut | K4: Jours Restants
B5: PERM-001 | C5: EMP-001 | D5: Nganou Clarisse | E5: Attestation CNPS | F5: CNPS-78901 | G5: 45658 | H5: 46022 | I5: CNPS | J5: Valide
B6: PERM-002 | C6: EMP-002 | D6: Tchinda Armand | E6: Passeport | F6: AB123456 | G6: 44357 | H6: 48009 | I6: DGSN | J6: Valide
B7: PERM-003 | C7: EMP-004 | D7: Nkoulou Mbarga | E7: CNI | F7: 987654321 | G7: 44075 | H7: 45901 | I7: DGSN | J7: A renouveler
B8: PERM-004 | C8: EMP-003 | D8: Fotso Marguerite | E8: Receve fiscal | F8: RF-2025-045 | G8: 45667 | H8: 46022 | I8: Direction des impots | J8: Valide
B9: =IF(C9="","PERM-"&TEXT(COUNTA($C$5:C9),"000")) | K9: =IF(H9="","",MAX(H9-TODAY(),0))
B10: =IF(C10="","PERM-"&TEXT(COUNTA($C$5:C10),"000")) | K10: =IF(H10="","",MAX(H10-TODAY(),0))
B11: =IF(C11="","PERM-"&TEXT(COUNTA($C$5:C11),"000")) | K11: =IF(H11="","",MAX(H11-TODAY(),0))
B12: =IF(C12="","PERM-"&TEXT(COUNTA($C$5:C12),"000")) | K12: =IF(H12="","",MAX(H12-TODAY(),0))
B13: =IF(C13="","PERM-"&TEXT(COUNTA($C$5:C13),"000")) | K13: =IF(H13="","",MAX(H13-TODAY(),0))
B14: =IF(C14="","PERM-"&TEXT(COUNTA($C$5:C14),"000")) | K14: =IF(H14="","",MAX(H14-TODAY(),0))
B15: =IF(C15="","PERM-"&TEXT(COUNTA($C$5:C15),"000")) | K15: =IF(H15="","",MAX(H15-TODAY(),0))
B16: =IF(C16="","PERM-"&TEXT(COUNTA($C$5:C16),"000")) | K16: =IF(H16="","",MAX(H16-TODAY(),0))
B17: =IF(C17="","PERM-"&TEXT(COUNTA($C$5:C17),"000")) | K17: =IF(H17="","",MAX(H17-TODAY(),0))
B18: =IF(C18="","PERM-"&TEXT(COUNTA($C$5:C18),"000")) | K18: =IF(H18="","",MAX(H18-TODAY(),0))
B19: =IF(C19="","PERM-"&TEXT(COUNTA($C$5:C19),"000")) | K19: =IF(H19="","",MAX(H19-TODAY(),0))
B20: =IF(C20="","PERM-"&TEXT(COUNTA($C$5:C20),"000")) | K20: =IF(H20="","",MAX(H20-TODAY(),0))
... B108: =IF(C108="","PERM-"&TEXT(COUNTA($C$5:C108),"000")) | K108: =IF(H108="","",MAX(H108-TODAY(),0))
B110: INDICATEURS (mis a jour automatiquement)
B111: Total permis | D111: Valides | F111: A renouveler | H111: Expire
B112: =COUNTIF(B5:B104,"<>") | D112: =COUNTIF(J5:J104,"Valide") | F112: =COUNTIF(J5:J104,"A renouveler") | H112: =COUNTIF(J5:J104,"Expire")

Sheet 16-Dossiers Departs
B2: DOSSIERS DE DEPART
B3: TABLEAU DYNAMIQUE — Saisissez dans la prochaine ligne jaune. Les calculs se mettent a jour automatiquement.
B4: N° | C4: Matricule | D4: Nom Employé | E4: Date Départ | F4: Motif Départ | G4: Date Notification | H4: Solde Congés (jrs) | I4: Dernier Salaire (FCFA) | J4: Indemnité (FCFA) | K4: Documents Remis | L4: Statut Dossier
B5: DEP-001 | C5: EMP-2024-012 | D5: Kamga Jean | E5: 45716 | F5: Demission | G5: 45672 | H5: 8 | I5: 320000 | J5: =IF(I5="","",IFERROR(I5*0.5,0)) | K5: Attestation, Certificat, Solde tout compte | L5: Clos
B6: DEP-002 | C6: EMP-2024-015 | D6: Biyong Paul | E6: 45747 | F6: Fin de CDD | G6: 45717 | H6: 0 | I6: 165000 | J6: =IF(I6="","",IFERROR(I6*0.5,0)) | K6: Attestation, Certificat | L6: En cours
B7: DEP-003 | C7: EMP-2023-003 | D7: Ngo Mballa Marie | E7: 45657 | F7: Retraite | G7: 45566 | H7: 20 | I7: 520000 | J7: =IF(I7="","",IFERROR(I7*0.5,0)) | K7: Tous documents remis | L7: Clos
B8: =IF(C8="","DEP-"&TEXT(COUNTA($C$5:C8),"000")) | J8: =IF(I8="","",IFERROR(I8*0.5,0))
B9: =IF(C9="","DEP-"&TEXT(COUNTA($C$5:C9),"000")) | J9: =IF(I9="","",IFERROR(I9*0.5,0))
B10: =IF(C10="","DEP-"&TEXT(COUNTA($C$5:C10),"000")) | J10: =IF(I10="","",IFERROR(I10*0.5,0))
B11: =IF(C11="","DEP-"&TEXT(COUNTA($C$5:C11),"000")) | J11: =IF(I11="","",IFERROR(I11*0.5,0))
B12: =IF(C12="","DEP-"&TEXT(COUNTA($C$5:C12),"000")) | J12: =IF(I12="","",IFERROR(I12*0.5,0))
B13: =IF(C13="","DEP-"&TEXT(COUNTA($C$5:C13),"000")) | J13: =IF(I13="","",IFERROR(I13*0.5,0))
B14: =IF(C14="","DEP-"&TEXT(COUNTA($C$5:C14),"000")) | J14: =IF(I14="","",IFERROR(I14*0.5,0))
B15: =IF(C15="","DEP-"&TEXT(COUNTA($C$5:C15),"000")) | J15: =IF(I15="","",IFERROR(I15*0.5,0))
B16: =IF(C16="","DEP-"&TEXT(COUNTA($C$5:C16),"000")) | J16: =IF(I16="","",IFERROR(I16*0.5,0))
B17: =IF(C17="","DEP-"&TEXT(COUNTA($C$5:C17),"000")) | J17: =IF(I17="","",IFERROR(I17*0.5,0))
B18: =IF(C18="","DEP-"&TEXT(COUNTA($C$5:C18),"000")) | J18: =IF(I18="","",IFERROR(I18*0.5,0))
B19: =IF(C19="","DEP-"&TEXT(COUNTA($C$5:C19),"000")) | J19: =IF(I19="","",IFERROR(I19*0.5,0))
... B104: =IF(C104="","DEP-"&TEXT(COUNTA($C$5:C104),"000")) | J104: =IF(I104="","",IFERROR(I104*0.5,0))
B105: =IF(C105="","DEP-"&TEXT(COUNTA($C$5:C105),"000"))
B106: =IF(C106="","DEP-"&TEXT(COUNTA($C$5:C106),"000"))
B107: =IF(C107="","DEP-"&TEXT(COUNTA($C$5:C107),"000"))
B109: TOTAL | I109: =SUM(I5:I104)
B111: INDICATEURS (mis a jour automatiquement)
B112: Total départs | D112: Dossiers clos | F112: En cours
B113: =COUNTIF(B5:B104,"<>") | D113: =COUNTIF(K5:K104,"Clos") | F113: =COUNTIF(K5:K104,"En cours")

Sheet 17-Archivage Documents
B2: ARCHIVAGE DES DOCUMENTS
B3: TABLEAU DYNAMIQUE — Saisissez dans la prochaine ligne jaune. Les calculs se mettent a jour automatiquement.
B4: N° | C4: Matricule | D4: Nom Employé | E4: Type Document | F4: Date Archive | G4: Lieu Stockage | H4: Durée Conservation | I4: Responsable | J4: Observations
B5: ARCH-001 | C5: EMP-2024-012 | D5: Kamga Jean | E5: Dossier complet | F5: 45731 | G5: Archive physique Salle B | H5: 5 ans | I5: Nganou Clarisse | J5: Depart fevrier 2025
B6: ARCH-002 | C6: EMP-2023-003 | D6: Ngo Mballa Marie | E6: Dossier complet | F6: 45667 | G6: Archive physique Salle B | H6: Illimitee | I6: Nganou Clarisse | J6: Retraite decembre 2024
B7: ARCH-003 | C7: EMP-001 | D7: Nganou Clarisse | E7: Contrat initial | F7: 43862 | G7: Archive numerique RH | H7: Illimitee | I7: DRH | J7: Contrat CDI 2020
B8: =IF(C8="","ARCH-"&TEXT(COUNTA($C$5:C8),"000"))
B9: =IF(C9="","ARCH-"&TEXT(COUNTA($C$5:C9),"000"))
B10: =IF(C10="","ARCH-"&TEXT(COUNTA($C$5:C10),"000"))
B11: =IF(C11="","ARCH-"&TEXT(COUNTA($C$5:C11),"000"))
B12: =IF(C12="","ARCH-"&TEXT(COUNTA($C$5:C12),"000"))
B13: =IF(C13="","ARCH-"&TEXT(COUNTA($C$5:C13),"000"))
B14: =IF(C14="","ARCH-"&TEXT(COUNTA($C$5:C14),"000"))
B15: =IF(C15="","ARCH-"&TEXT(COUNTA($C$5:C15),"000"))
B16: =IF(C16="","ARCH-"&TEXT(COUNTA($C$5:C16),"000"))
B17: =IF(C17="","ARCH-"&TEXT(COUNTA($C$5:C17),"000"))
B18: =IF(C18="","ARCH-"&TEXT(COUNTA($C$5:C18),"000"))
B19: =IF(C19="","ARCH-"&TEXT(COUNTA($C$5:C19),"000"))
... B107: =IF(C107="","ARCH-"&TEXT(COUNTA($C$5:C107),"000"))
B109: INDICATEURS (mis a jour automatiquement)
B110: Total archives | D110: Archives numeriques | F110: Archives physiques
B111: =COUNTIF(B5:B104,"<>") | D111: =COUNTIF(G5:G104,"Archive numerique RH") | F111: =COUNTIF(G5:G104,"Archive physique Salle B")

Sheet 18-Rappels Admin
B2: RAPPELS ADMINISTRATIFS
B3: TABLEAU DYNAMIQUE — Saisissez dans la prochaine ligne jaune. Les calculs se mettent a jour automatiquement.
B4: N° | C4: Matricule | D4: Nom Employé | E4: Type Rappel | F4: Description | G4: Date Échéance | H4: Jours Restants | I4: Statut | J4: Responsable Suivi | K4: Action Requise
B5: RAP-001 | C5: EMP-004 | D5: Nkoulou Mbarga | E5: Expiration document | F5: Renouvellement CNI avant sept 2025 | G5: 45901 | I5: En attente | J5: DRH Nganou | K5: Prendre rdv mairie
B6: RAP-002 | C6: EMP-005 | D6: Kamga Paul | E6: Renouvellement contrat | F6: CDD expire 31 mars 2025 | G6: 45731 | I6: En retard | J6: DRH Nganou | K6: Decider renouvellement ou fin
B7: RAP-003 | C7: EMP-002 | D7: Tchinda Armand | E7: Bilan periodique | F7: Entretien annuel 2025 | G7: 45838 | I7: En attente | J7: DRH Nganou | K7: Planifier entretien
B8: RAP-004 | C8: EMP-001 | D8: Nganou Clarisse | E8: Expiration document | F8: Attestation CNPS a renouveler dec 2025 | G8: 45992 | I8: En attente | J8: Assistante RH | K8: Preparer demande CNPS
B9: =IF(C9="","RAP-"&TEXT(COUNTA($C$5:C9),"000")) | H9: =IF(G9="","",MAX(G9-TODAY(),0))
B10: =IF(C10="","RAP-"&TEXT(COUNTA($C$5:C10),"000")) | H10: =IF(G10="","",MAX(G10-TODAY(),0))
B11: =IF(C11="","RAP-"&TEXT(COUNTA($C$5:C11),"000")) | H11: =IF(G11="","",MAX(G11-TODAY(),0))
B12: =IF(C12="","RAP-"&TEXT(COUNTA($C$5:C12),"000")) | H12: =IF(G12="","",MAX(G12-TODAY(),0))
B13: =IF(C13="","RAP-"&TEXT(COUNTA($C$5:C13),"000")) | H13: =IF(G13="","",MAX(G13-TODAY(),0))
B14: =IF(C14="","RAP-"&TEXT(COUNTA($C$5:C14),"000")) | H14: =IF(G14="","",MAX(G14-TODAY(),0))
B15: =IF(C15="","RAP-"&TEXT(COUNTA($C$5:C15),"000")) | H15: =IF(G15="","",MAX(G15-TODAY(),0))
B16: =IF(C16="","RAP-"&TEXT(COUNTA($C$5:C16),"000")) | H16: =IF(G16="","",MAX(G16-TODAY(),0))
B17: =IF(C17="","RAP-"&TEXT(COUNTA($C$5:C17),"000")) | H17: =IF(G17="","",MAX(G17-TODAY(),0))
B18: =IF(C18="","RAP-"&TEXT(COUNTA($C$5:C18),"000")) | H18: =IF(G18="","",MAX(G18-TODAY(),0))
B19: =IF(C19="","RAP-"&TEXT(COUNTA($C$5:C19),"000")) | H19: =IF(G19="","",MAX(G19-TODAY(),0))
B20: =IF(C20="","RAP-"&TEXT(COUNTA($C$5:C20),"000")) | H20: =IF(G20="","",MAX(G20-TODAY(),0))
... B108: =IF(C108="","RAP-"&TEXT(COUNTA($C$5:C108),"000")) | H108: =IF(G108="","",MAX(G108-TODAY(),0))
B110: INDICATEURS (mis a jour automatiquement)
B111: Total rappels | D111: En attente | F111: En retard | H111: Traites
B112: =COUNTIF(B5:B104,"<>") | D112: =COUNTIF(I5:I104,"En attente") | F112: =COUNTIF(I5:I104,"En retard") | H112: =COUNTIF(I5:I104,"Traite")

Sheet 19-Prets Avances Salaire
B2: 19-Prets Avances Salaire
B4: N° | C4: Matricule | D4: Nom Employé | E4: Département | F4: Type Prêt | G4: Montant Demandé (FCFA) | H4: Montant Accordé (FCFA) | I4: Taux Intérêt (%) | J4: Mensualité (FCFA) | K4: Durée (mois) | L4: Date Demande | M4: Date Début Remb. | N4: Mois Restants | O4: Solde Restant (FCFA) | P4: Statut | Q4: Observations
B5: PRT-001 | C5: EMP-001 | D5: Nkoumou Paul | E5: Direction Generale | F5: Avance salaire | G5: 50000 | H5: 50000 | I5: 0 | J5: 50000 | K5: 1 | L5: 2025-01-15 | M5: 2025-02-01 | N5: 0 | O5: 0 | P5: Solde | Q5: Déduit fév. 2025
B6: PRT-002 | C6: EMP-003 | D6: Mbarga Jean | E6: Finance & Comptabilité | F6: Prêt social | G6: 200000 | H6: 200000 | I6: 2 | J6: 34440 | K6: 6 | L6: 2025-02-10 | M6: 2025-03-01 | N6: 4 | O6: 137760 | P6: En cours | Q6: Remb. mensuel auto
B7: PRT-003 | C7: EMP-005 | D7: Tchinda Marie | E7: Service Client | F7: Avance salaire | G7: 30000 | H7: 30000 | I7: 0 | J7: 30000 | K7: 1 | L7: 2025-03-05 | M7: 2025-04-01 | N7: 0 | O7: 0 | P7: Solde | Q7: Déduit avr. 2025
B8: PRT-004 | C8: EMP-007 | D8: Nganou Andre | E8: Cuisine & Restauration | F8: Prêt logement | G8: 500000 | H8: 500000 | I8: 1.5 | J8: 42870 | K8: 12 | L8: 2025-01-20 | M8: 2025-02-01 | N8: 10 | O8: 428700 | P8: En cours | Q8: Prêt CT
B9: PRT-005 | C9: EMP-010 | D9: Fotso Camille | E9: Réception & Front Office | F9: Avance salaire | G9: 40000 | H9: 40000 | I9: 0 | J9: 40000 | K9: 1 | L9: 2025-04-01 | M9: 2025-05-01 | N9: 0 | O9: 0 | P9: Solde | Q9: Déduit mai 2025
B10: =IF(C10="","PRT"&TEXT(COUNTA($C$5:C10),"000")) | N10: =IF(L10="","",IFERROR(MAX(0,(K10+J10)-MONTH(TODAY())-12*YEAR(TODAY())+MONTH(L10)+12*YEAR(L10)),0)) | O10: =IF(H10="","",IFERROR(I10*M10,0))
B11: =IF(C11="","PRT"&TEXT(COUNTA($C$5:C11),"000")) | N11: =IF(L11="","",IFERROR(MAX(0,(K11+J11)-MONTH(TODAY())-12*YEAR(TODAY())+MONTH(L11)+12*YEAR(L11)),0)) | O11: =IF(H11="","",IFERROR(I11*M11,0))
B12: =IF(C12="","PRT"&TEXT(COUNTA($C$5:C12),"000")) | N12: =IF(L12="","",IFERROR(MAX(0,(K12+J12)-MONTH(TODAY())-12*YEAR(TODAY())+MONTH(L12)+12*YEAR(L12)),0)) | O12: =IF(H12="","",IFERROR(I12*M12,0))
B13: =IF(C13="","PRT"&TEXT(COUNTA($C$5:C13),"000")) | N13: =IF(L13="","",IFERROR(MAX(0,(K13+J13)-MONTH(TODAY())-12*YEAR(TODAY())+MONTH(L13)+12*YEAR(L13)),0)) | O13: =IF(H13="","",IFERROR(I13*M13,0))
B14: =IF(C14="","PRT"&TEXT(COUNTA($C$5:C14),"000")) | N14: =IF(L14="","",IFERROR(MAX(0,(K14+J14)-MONTH(TODAY())-12*YEAR(TODAY())+MONTH(L14)+12*YEAR(L14)),0)) | O14: =IF(H14="","",IFERROR(I14*M14,0))
B15: =IF(C15="","PRT"&TEXT(COUNTA($C$5:C15),"000")) | N15: =IF(L15="","",IFERROR(MAX(0,(K15+J15)-MONTH(TODAY())-12*YEAR(TODAY())+MONTH(L15)+12*YEAR(L15)),0)) | O15: =IF(H15="","",IFERROR(I15*M15,0))
B16: =IF(C16="","PRT"&TEXT(COUNTA($C$5:C16),"000")) | N16: =IF(L16="","",IFERROR(MAX(0,(K16+J16)-MONTH(TODAY())-12*YEAR(TODAY())+MONTH(L16)+12*YEAR(L16)),0)) | O16: =IF(H16="","",IFERROR(I16*M16,0))
B17: =IF(C17="","PRT"&TEXT(COUNTA($C$5:C17),"000")) | N17: =IF(L17="","",IFERROR(MAX(0,(K17+J17)-MONTH(TODAY())-12*YEAR(TODAY())+MONTH(L17)+12*YEAR(L17)),0)) | O17: =IF(H17="","",IFERROR(I17*M17,0))
B18: =IF(C18="","PRT"&TEXT(COUNTA($C$5:C18),"000")) | N18: =IF(L18="","",IFERROR(MAX(0,(K18+J18)-MONTH(TODAY())-12*YEAR(TODAY())+MONTH(L18)+12*YEAR(L18)),0)) | O18: =IF(H18="","",IFERROR(I18*M18,0))
B19: =IF(C19="","PRT"&TEXT(COUNTA($C$5:C19),"000")) | N19: =IF(L19="","",IFERROR(MAX(0,(K19+J19)-MONTH(TODAY())-12*YEAR(TODAY())+MONTH(L19)+12*YEAR(L19)),0)) | O19: =IF(H19="","",IFERROR(I19*M19,0))
B20: =IF(C20="","PRT"&TEXT(COUNTA($C$5:C20),"000")) | N20: =IF(L20="","",IFERROR(MAX(0,(K20+J20)-MONTH(TODAY())-12*YEAR(TODAY())+MONTH(L20)+12*YEAR(L20)),0)) | O20: =IF(H20="","",IFERROR(I20*M20,0))
B21: =IF(C21="","PRT"&TEXT(COUNTA($C$5:C21),"000")) | N21: =IF(L21="","",IFERROR(MAX(0,(K21+J21)-MONTH(TODAY())-12*YEAR(TODAY())+MONTH(L21)+12*YEAR(L21)),0)) | O21: =IF(H21="","",IFERROR(I21*M21,0))
... B104: =IF(C104="","PRT"&TEXT(COUNTA($C$5:C104),"000")) | N104: =IF(L104="","",IFERROR(MAX(0,(K104+J104)-MONTH(TODAY())-12*YEAR(TODAY())+MONTH(L104)+12*YEAR(L104)),0)) | O104: =IF(H104="","",IFERROR(I104*M104,0))
B106: KPI Total Prêts (FCFA) | C106: KPI Encours (FCFA) | D106: KPI Dossiers Actifs | E106: KPI En Retard
B107: =SUMPRODUCT((F5:F104<>"")*F5:F104) | C107: =SUM(N5:N104) | D107: =COUNTIF(O5:O104,"En cours") | E107: =COUNTIF(O5:O104,"En retard")

Sheet 20-Sanctions Disciplinaires
B2: 20-Sanctions Disciplinaires
B4: N° | C4: Matricule | D4: Nom Employé | E4: Département | F4: Type Sanction | G4: Faute Commise | H4: Date Faute | I4: Date Notification | J4: Date Exécution | K4: Durée Suspension (jrs) | L4: Observations | M4: Statut | N4: Validé Par
B5: SAN-001 | C5: EMP-012 | D5: Kamga Pierre | E5: Service Client | F5: Avertissement oral | G5: Retard répété (3 fois en 1 semaine) | H5: 2025-02-15 | I5: 2025-02-16 | J5: 2025-02-16 | K5: 0 | L5: Premier avertissement | M5: Exécutee | N5: Chef de service
B6: SAN-002 | C6: EMP-018 | D6: Ekode Simon | E6: Cuisine & Restauration | F6: Avertissement écrit | G6: Non-respect des normes d'hygiène | H6: 2025-03-01 | I6: 2025-03-02 | J6: 2025-03-02 | K6: 0 | L6: Rappel des procédures HACCP | M6: Exécutee | N6: Chef cuisine
B7: SAN-003 | C7: EMP-025 | D7: Bouba Amina | E7: Logistique & Approvisionnement | F7: Blâme | G7: Absence injustifiée de 2 jours | H7: 2025-03-20 | I7: 2025-03-21 | K7: 0 | L7: En attente de justification | M7: En cours | N7: DRH
B8: SAN-004 | C8: EMP-030 | D8: Hassan Moussa | E8: Sécurité | F8: Suspension | G8: Abandon de poste pendant service | H8: 2025-04-05 | I8: 2025-04-06 | J8: 2025-04-06 | K8: 3 | L8: Suspension avec retenue de salaire | M8: Exécutee | N8: Directeur general
B9: SAN-005 | C9: EMP-042 | D9: Tchouankou Marc | E9: Maintenance | F9: Mise à pied | G9: Vol de matériel hôtelier | H9: 2025-04-20 | I9: 2025-04-21 | J9: 2025-04-22 | K9: 0 | L9: Procédure disciplinaire complète | M9: Exécutee | N9: Directeur general
B10: =IF(C10="","SAN"&TEXT(COUNTA($C$5:C10),"000"))
B11: =IF(C11="","SAN"&TEXT(COUNTA($C$5:C11),"000"))
B12: =IF(C12="","SAN"&TEXT(COUNTA($C$5:C12),"000"))
B13: =IF(C13="","SAN"&TEXT(COUNTA($C$5:C13),"000"))
B14: =IF(C14="","SAN"&TEXT(COUNTA($C$5:C14),"000"))
B15: =IF(C15="","SAN"&TEXT(COUNTA($C$5:C15),"000"))
B16: =IF(C16="","SAN"&TEXT(COUNTA($C$5:C16),"000"))
B17: =IF(C17="","SAN"&TEXT(COUNTA($C$5:C17),"000"))
B18: =IF(C18="","SAN"&TEXT(COUNTA($C$5:C18),"000"))
B19: =IF(C19="","SAN"&TEXT(COUNTA($C$5:C19),"000"))
B20: =IF(C20="","SAN"&TEXT(COUNTA($C$5:C20),"000"))
B21: =IF(C21="","SAN"&TEXT(COUNTA($C$5:C21),"000"))
... B104: =IF(C104="","SAN"&TEXT(COUNTA($C$5:C104),"000"))
B106: KPI Total Sanctions | C106: KPI Avertissements | D106: KPI Suspensions | E106: KPI En Cours
B107: =COUNTA(C5:C104) | C107: =COUNTIF(E5:E104,"Avertissement oral")+COUNTIF(E5:E104,"Avertissement écrit") | D107: =COUNTIF(E5:E104,"Suspension") | E107: =COUNTIF(L5:L104,"En cours")

Sheet 21-Visites Medicales
B2: 21-Visites Medicales
B4: N° | C4: Matricule | D4: Nom Employé | E4: Département | F4: Type Visite | G4: Médecin / Structure | H4: Date Visite | I4: Date Prochaine Visite | J4: Jours Restants | K4: Résultat | L4: Aptitude | M4: Restrictions | N4: Coût (FCFA) | O4: Pris en Charge | P4: Observations
B5: VIS-001 | C5: EMP-001 | D5: Nkoumou Paul | E5: Direction Generale | F5: Visite embauche | G5: Dr. Nganou - CMP Douala | H5: 2024-01-10 | I5: 2025-01-10 | J5: 0 | K5: Normal | L5: Apte | M5: Aucune | N5: 15000 | O5: Oui | P5: Bilan complet OK
B6: VIS-002 | C6: EMP-003 | D6: Mbarga Jean | E6: Finance & Comptabilité | F6: Visite périodique | G6: Dr. Fotso - Clinique Bastos | H6: 2025-03-15 | I6: 2026-03-15 | J6: 0 | K6: Normal | L6: Apte | M6: Aucune | N6: 20000 | O6: Oui | P6: RAS
B7: VIS-003 | C7: EMP-008 | D7: Djoumessi Francoise | E7: Cuisine & Restauration | F7: Visite reprise | G7: Dr. Nganou - CMP Douala | H7: 2025-04-01 | I7: 2025-10-01 | J7: 0 | K7: Convalescence | L7: Apte avec restrictions | M7: Port de charge limité 10kg | N7: 25000 | O7: Oui | P7: Reprise après congé maternité
B8: VIS-004 | C8: EMP-015 | D8: Ngassa Brice | E8: Maintenance | F8: Visite embauche | G8: Dr. Tchinda - Hôpital Laquintinie | H8: 2025-05-01 | I8: 2026-05-01 | J8: 0 | K8: Normal | L8: Apte | M8: Port EPI obligatoire | N8: 15000 | O8: Non | P8: Exposition produits chimiques
B9: VIS-005 | C9: EMP-020 | D9: Atangana Sarah | E9: Service Client | F9: Visite périodique | G9: Dr. Fotso - Clinique Bastos | H9: 2025-02-20 | I9: 2026-02-20 | J9: 0 | K9: Normal | L9: Apte | M9: Aucune | N9: 20000 | O9: Oui | P9: RAS
B10: =IF(C10="","VIS"&TEXT(COUNTA($C$5:C10),"000")) | J10: =IF(H10="","",IFERROR(MAX(H10-TODAY(),0),0))
B11: =IF(C11="","VIS"&TEXT(COUNTA($C$5:C11),"000")) | J11: =IF(H11="","",IFERROR(MAX(H11-TODAY(),0),0))
B12: =IF(C12="","VIS"&TEXT(COUNTA($C$5:C12),"000")) | J12: =IF(H12="","",IFERROR(MAX(H12-TODAY(),0),0))
B13: =IF(C13="","VIS"&TEXT(COUNTA($C$5:C13),"000")) | J13: =IF(H13="","",IFERROR(MAX(H13-TODAY(),0),0))
B14: =IF(C14="","VIS"&TEXT(COUNTA($C$5:C14),"000")) | J14: =IF(H14="","",IFERROR(MAX(H14-TODAY(),0),0))
B15: =IF(C15="","VIS"&TEXT(COUNTA($C$5:C15),"000")) | J15: =IF(H15="","",IFERROR(MAX(H15-TODAY(),0),0))
B16: =IF(C16="","VIS"&TEXT(COUNTA($C$5:C16),"000")) | J16: =IF(H16="","",IFERROR(MAX(H16-TODAY(),0),0))
B17: =IF(C17="","VIS"&TEXT(COUNTA($C$5:C17),"000")) | J17: =IF(H17="","",IFERROR(MAX(H17-TODAY(),0),0))
B18: =IF(C18="","VIS"&TEXT(COUNTA($C$5:C18),"000")) | J18: =IF(H18="","",IFERROR(MAX(H18-TODAY(),0),0))
B19: =IF(C19="","VIS"&TEXT(COUNTA($C$5:C19),"000")) | J19: =IF(H19="","",IFERROR(MAX(H19-TODAY(),0),0))
B20: =IF(C20="","VIS"&TEXT(COUNTA($C$5:C20),"000")) | J20: =IF(H20="","",IFERROR(MAX(H20-TODAY(),0),0))
B21: =IF(C21="","VIS"&TEXT(COUNTA($C$5:C21),"000")) | J21: =IF(H21="","",IFERROR(MAX(H21-TODAY(),0),0))
... B104: =IF(C104="","VIS"&TEXT(COUNTA($C$5:C104),"000")) | J104: =IF(H104="","",IFERROR(MAX(H104-TODAY(),0),0))
B106: KPI Total Visites | C106: KPI Visites à Venir (30j) | D106: KPI Inaptes | E106: KPI Coût Total (FCFA)
B107: =COUNTA(C5:C104) | C107: =COUNTIF(I5:I104,"<="&30)-COUNTIF(I5:I104,"<0") | D107: =COUNTIF(K5:K104,"Inapte temporaire")+COUNTIF(K5:K104,"Inapte définitif") | E107: =SUM(M5:M104)

Sheet 22-Planning Mensuel Presence
B2: 22-Planning Mensuel Presence
B4: N° | C4: Matricule | D4: Nom Employé | E4: Département | F4: Poste | G4: Mois | H4: Jours Ouvrables | I4: Jours Présents | J4: Jours Absents | K4: Retards (min) | L4: Heures Supp | M4: Taux Présence (%) | N4: Commentaire
B5: PLN-001 | C5: EMP-001 | D5: Nkoumou Paul | E5: Direction Generale | F5: Directeur General | G5: Janvier 2025 | H5: 22 | I5: 22 | J5: 0 | K5: 0 | L5: 0 | M5: 1
B6: PLN-002 | C6: EMP-003 | D6: Mbarga Jean | E6: Finance & Comptabilité | F6: Comptable Senior | G6: Janvier 2025 | H6: 22 | I6: 21 | J6: 1 | K6: 15 | L6: 4 | M6: 0.95 | N6: 1 jour maladie justifié
B7: PLN-003 | C7: EMP-005 | D7: Tchinda Marie | E7: Service Client | F7: Charge de Recrutement | G7: Janvier 2025 | H7: 22 | I7: 22 | J7: 0 | K7: 0 | L7: 2 | M7: 1
B8: PLN-004 | C8: EMP-007 | D8: Nganou Andre | E8: Cuisine & Restauration | F8: Chef cuisinier | G8: Janvier 2025 | H8: 22 | I8: 20 | J8: 2 | K8: 45 | L8: 12 | M8: 0.91 | N8: 2 jours formation
B9: PLN-005 | C9: EMP-010 | D9: Fotso Camille | E9: Réception & Front Office | F9: Receptionniste | G9: Janvier 2025 | H9: 22 | I9: 21 | J9: 1 | K9: 0 | L9: 6 | M9: 0.95 | N9: 1 jour congé annuel
B10: =IF(C10="","PLN"&TEXT(COUNTA($C$5:C10),"000")) | M10: =IF(H10="","",IFERROR(I10/H10,0))
B11: =IF(C11="","PLN"&TEXT(COUNTA($C$5:C11),"000")) | M11: =IF(H11="","",IFERROR(I11/H11,0))
B12: =IF(C12="","PLN"&TEXT(COUNTA($C$5:C12),"000")) | M12: =IF(H12="","",IFERROR(I12/H12,0))
B13: =IF(C13="","PLN"&TEXT(COUNTA($C$5:C13),"000")) | M13: =IF(H13="","",IFERROR(I13/H13,0))
B14: =IF(C14="","PLN"&TEXT(COUNTA($C$5:C14),"000")) | M14: =IF(H14="","",IFERROR(I14/H14,0))
B15: =IF(C15="","PLN"&TEXT(COUNTA($C$5:C15),"000")) | M15: =IF(H15="","",IFERROR(I15/H15,0))
B16: =IF(C16="","PLN"&TEXT(COUNTA($C$5:C16),"000")) | M16: =IF(H16="","",IFERROR(I16/H16,0))
B17: =IF(C17="","PLN"&TEXT(COUNTA($C$5:C17),"000")) | M17: =IF(H17="","",IFERROR(I17/H17,0))
B18: =IF(C18="","PLN"&TEXT(COUNTA($C$5:C18),"000")) | M18: =IF(H18="","",IFERROR(I18/H18,0))
B19: =IF(C19="","PLN"&TEXT(COUNTA($C$5:C19),"000")) | M19: =IF(H19="","",IFERROR(I19/H19,0))
B20: =IF(C20="","PLN"&TEXT(COUNTA($C$5:C20),"000")) | M20: =IF(H20="","",IFERROR(I20/H20,0))
B21: =IF(C21="","PLN"&TEXT(COUNTA($C$5:C21),"000")) | M21: =IF(H21="","",IFERROR(I21/H21,0))
... B104: =IF(C104="","PLN"&TEXT(COUNTA($C$5:C104),"000")) | M104: =IF(H104="","",IFERROR(I104/H104,0))
B106: KPI Taux Présence Moy. | C106: KPI Total Retards (min) | D106: KPI Total Heures Supp | E106: KPI Employés 100%
B107: =IFERROR(AVERAGE(L5:L104),0) | C107: =SUM(J5:J104) | D107: =SUM(K5:K104) | E107: =COUNTIF(L5:L104,1)

Sheet _Lists
B1: civilite | C1: genre | D1: situation_fam | E1: nationalite | F1: statut_employe | G1: type_contrat | H1: categorie_salarie | I1: regime_travail | J1: departement | K1: statut_contrat | L1: type_avenant | M1: type_document | N1: statut_document | O1: lieu_depot | P1: banque | Q1: statut_rib | R1: organisme_prevo | S1: couverture | T1: statut_adhesion | U1: type_conge | V1: statut_conge | W1: type_absence | X1: statut_absence | Y1: statut_heures | Z1: taux_majoration | AA1: statut_paie | AB1: mode_paie | AC1: organisme_social | AD1: type_declaration | AE1: statut_declaration | AF1: type_permit | AG1: statut_permit | AH1: autorite | AI1: motif_depart | AJ1: statut_dossier | AK1: duree_conservation | AL1: motif_rappel | AM1: statut_rappel | AN1: oui_non | AO1: poste_hotel | AP1: semaine | AQ1: statut_solde | AR1: statut_solde_conge | AS1: type_pret | AT1: statut_pret | AU1: type_sanction | AV1: statut_sanction | AW1: type_visite | AX1: aptitude | AY1: oui_non_2
B2: M. | C2: Masculin | D2: Celibataire | E2: Camerounaise | F2: Actif | G2: CDI | H2: Cadre | I2: Temps plein | J2: Direction Generale | K2: En vigueur | L2: Modification salariale | M2: CNI | N2: Valide | O2: RH Central | P2: SGBC | Q2: Actif | R2: CNPS | S2: Sante | T2: Actif | U2: Annuel | V2: En attente | W2: Maladie | X2: Justifiee | Y2: En attente | Z2: 100% | AA2: Generee | AB2: Virement bancaire | AC2: CNPS | AD2: Mensuelle | AE2: Soumise | AF2: Permis de travail | AG2: Valide | AH2: MINTSS | AI2: Demission | AJ2: En cours | AK2: 1 an | AL2: Expiration document | AM2: En attente | AN2: Oui | AO2: Receptionniste | AP2: S01-2025 | AQ2: A jour | AR2: A jour | AS2: Avance salaire | AT2: En attente | AU2: Avertissement oral | AV2: En cours | AW2: Visite embauche | AX2: Apte | AY2: Oui
B3: Mme | C3: Feminin | D3: Marie(e) | E3: Tchadienne | F3: En conge | G3: CDD | H3: Agent de maitrise | I3: Temps partiel | J3: Service Client | K3: Echu | L3: Changement poste | M3: Passeport | N3: A renouveler | O3: Service du personnel | P3: BICEC | Q3: Inactif | R3: Mutuelle entreprise | S3: Sante + Deces | T3: En attente | U3: Maternite | V3: Approuve | W3: Accident travail | X3: Non justifiee | Y3: Validee | Z3: 125% | AA3: Validee | AB3: Cheque | AC3: CNP | AD3: Trimestrielle | AE3: En retard | AF3: Carte de sejour | AG3: En renouvellement | AH3: DGSN | AI3: Licenciement | AJ3: Clos | AK3: 3 ans | AL3: Renouvellement contrat | AM3: Traite | AN3: Non | AO3: Concierge | AP3: S02-2025 | AQ3: A mettre a jour | AR3: A mettre a jour | AS3: Prêt social | AT3: Approuve | AU3: Avertissement écrit | AV3: Exécutee | AW3: Visite périodique | AX3: Apte avec restrictions | AY3: Non
B4: Mlle | D4: Divorce(e) | E4: Nigeriane | F4: En arret maladie | G4: Stage | H4: Employe | I4: Horaires amenages | J4: Finance & Comptabilité | K4: Resilie | L4: Passage temps partiel | M4: Attestation de travail | N4: Expire | O4: Direction | P4: AFRILAND First Bank | Q4: A verifier | R4: Assurance groupe | S4: Sante + Retraite | T4: Resilie | U4: Paternite | V4: Refuse | W4: Congé maternite | X4: En attente | Y4: Rejetee | Z4: 150% | AA4: Payee | AB4: Especes | AC4: Direction des impots | AD4: Annuelle | AE4: Validee | AF4: Visa de travail | AG4: Expire | AH4: Ministere de l'Interieur | AI4: Fin de CDD | AJ4: En attente piece | AK4: 5 ans | AL4: Echeance periode essai | AM4: En retard | AO4: Chef cuisinier | AP4: S03-2025 | AQ4: En attente validation | AR4: En attente validation | AS4: Prêt logement | AT4: En cours | AU4: Blâme | AV4: Contestee | AW4: Visite reprise | AX4: Inapte temporaire | AY4: Partiel
D5: Veuf(ve) | E5: Ghanéenne | F5: Suspendu | G5: Interim | H5: Ouvrier | I5: Forfait jours | J5: Marketing & Communication | K5: Suspendu | L5: Renouvellement | M5: Certificat medical | N5: En cours | O5: Archive physique | P5: ECOBANK | Q5: Cloture | R5: Allianz Cameroon | S5: Complete | T5: Suspendu | U5: Sans solde | V5: Pris | W5: Congé paternite | X5: Approuvee | Y5: Payee | Z5: 200% | AA5: En retard | AC5: Mutuelle | AD5: Exceptionnelle | AE5: Rejetee | AF5: Autorisation d'exercice | AG5: Rejete | AH5: Prefecture | AI5: Retraite | AJ5: Transmis | AK5: 10 ans | AL5: Bilan periodique | AM5: Annule | AO5: Cuisinier | AP5: S04-2025 | AQ5: Solde negatif | AR5: Solde negatif | AS5: Prêt urgence | AT5: Solde | AU5: Suspension | AV5: Annulee | AW5: Visite de pré-retraite | AX5: Inapte définitif
E6: Congolaise | F6: Depart programme | G6: Alternance | H6: Stagiaire | J6: Maintenance | K6: Renouvele | L6: Modification horaire | M6: Diplome | N6: Manquant | O6: Archive numerique | P6: SGBE | R6: AXA Congo | S6: Famille | U6: Exceptionnel | V6: Annule | W6: Permission exceptionnelle | X6: Rejetee | AA6: Annulee | AC6: Autre | AE6: En attente | AF6: Receve fiscal | AG6: En traitement | AH6: Mairie | AI6: Deces | AJ6: Solde | AK6: Illimitee | AL6: Audit externe | AO6: Serveur | AP6: S05-2025 | AR6: Exhaustif | AS6: Prêt formation | AT6: Refuse | AU6: Mise à pied | AV6: En attente | AW6: Visite occasionnelle
E7: Ivoirienne | F7: Departi | G7: Freelance | J7: Commercial | L7: Changement departement | M7: CV | O7: Cabinet comptable | P7: UBA | R7: SANLAM | S7: Individuelle | U7: Maladie | W7: Absence injustifiee | AH7: Autre | AI7: Mutation | AJ7: Litige | AL7: Renouvellement permis | AO7: Barman | AP7: S06-2025 | AT7: En retard | AU7: Rétrogradation
E8: Senegalaise | J8: Logistique & Approvisionnement | L8: Autre | M8: Photo d'identite | P8: BAC | R8: Autre | U8: Formation | W8: Mission | AI8: Commun accord | AL8: Autre | AO8: Gouvernante | AP8: S07-2025 | AU8: Licenciement
E9: Autre | J9: Cuisine & Restauration | M9: Extrait casier judiciaire | P9: Standard Chartered | W9: Formation | AI9: Abandon de poste | AO9: Femme de chambre | AP9: S08-2025
J10: Service Client | M10: Permis de travail | P10: Citibank | AO10: Agent de securite | AP10: S09-2025
J11: Réception & Front Office | M11: Carte de sejour | P11: Autre | AO11: Technicien maintenance | AP11: S10-2025
J12: Cuisine & Restauration | M12: Attestation CNPS | AO12: Comptable | AP12: S11-2025
J13: Maintenance | M13: Attestation impots | AO13: Agent d'accueil | AP13: S12-2025
J14: Sécurité | M14: RIB | AO14: Laveur de vaisselle | AP14: S13-2025
M15: Certificat de stage | AO15: Plongeur | AP15: S14-2025
M16: Autre | AO16: Jardinier | AP16: S15-2025
AO17: Chauffeur | AP17: S16-2025
AO18: Standardiste | AP18: S17-2025
AO19: Directeur general | AP19: S18-2025
AO20: DRH | AP20: S19-2025
AO21: Chef de service | AP21: S20-2025
AO22: Superviseur | AP22: S21-2025
AP23: S22-2025
AP24: S23-2025
AP25: S24-2025
AP26: S25-2025
AP27: S26-2025
AP28: S27-2025
AP29: S28-2025
AP30: S29-2025
AP31: S30-2025
AP32: S31-2025
AP33: S32-2025
AP34: S33-2025
... AP53: S52-2025
