Workbook

Sheet _Données Employés
B4: Matricule | C4: Civilité | D4: Nom | E4: Prénom | F4: Département | G4: Poste | H4: Salaire Base (FCFA)
B5: EMP-001 | C5: M. | D5: Nganou | E5: Clarisse | F5: Cuisine & Restauration | G5: Chef cuisinier | H5: 450000
B6: EMP-002 | C6: M. | D6: Tchinda | E6: Armand | F6: Réception & Front Office | G6: Réceptionniste | H6: 220000
B7: EMP-003 | C7: Mme | D7: Fotso | E7: Marguerite | F7: Finance & Comptabilité | G7: Comptable senior | H7: 380000
B8: EMP-004 | C8: M. | D8: Nkoulou | E8: Mbarga | F8: Étage & Housekeeping | G8: Gouvernant | H8: 195000
B9: EMP-005 | C9: M. | D9: Kamga | E9: Paul | F9: Maintenance | G9: Technicien maintenance | H9: 165000
B10: EMP-006 | C10: Mme | D10: Ngo | E10: Delphine | F10: Service Client | G10: Conseiller clientèle | H10: 160000
B11: EMP-007 | C11: M. | D11: Essomba | E11: Serge | F11: Maintenance | G11: Agent entretien | H11: 130000
B12: EMP-008 | C12: M. | D12: Tchouankou | E12: Paul | F12: Commercial | G12: Commercial | H12: 150000
B13: EMP-009 | C13: M. | D13: Fokam | E13: Eric | F13: Maintenance | G13: Technicien | H13: 140000
B14: EMP-010 | C14: M. | D14: Tagne | E14: René | F14: Cuisine & Restauration | G14: Plongeur | H14: 90000
B15: EMP-011 | C15: M. | D15: Bouba | E15: Ahmed | F15: Sécurité | G15: Agent Sécurité | H15: 120000
B16: EMP-012 | C16: Mme | D16: Awa | E16: Fatou | F16: Réception & Front Office | G16: Standardiste | H16: 155000
... B18: EMP-029 | C18: M. | D18: Kamga | E18: Patrice | F18: Sécurité | G18: Chef Sécurité | H18: 210000

Sheet 1-Tableau de Bord
B2: DOMAINE 13 — COMMUNICATION RH & MARQUE EMPLOYEUR
B3: TABLEAU DE BORD — Vue synthetique de tous les indicateurs du domaine (mis a jour automatiquement)
B5: Communications internes | E5: Initiatives ME | H5: Posts reseaux sociaux | K5: Candidatures spontanees
B6: =COUNTIF('2-Communication Interne'!B5:B104,"<>") | E6: =COUNTIF('3-Marque Employeur'!B5:B104,"<>") | H6: =COUNTIF('4-Reseaux Sociaux RH'!B5:B104,"<>") | K6: =COUNTIF('5-Candidatures Spontanees'!B5:B104,"<>")
B9: Ambassadeurs marque | E9: Enquetes climat | H9: Newsletters | K9: Articles journal
B10: =COUNTIF('6-Ambassadeurs Marque'!B5:B104,"<>") | E10: =COUNTIF('7-Enquete Climat Social'!B5:B104,"<>") | H10: =COUNTIF('8-Newsletter Interne'!B5:B104,"<>") | K10: =COUNTIF('9-Journal Interne'!B5:B104,"<>")
B13: Evenements RH | E13: Indicateurs ME | H13: Campagnes com. | K13: Vues totales (RS)
B14: =COUNTIF('10-Evenements RH'!B5:B104,"<>") | E14: =COUNTIF('11-Indic. Marque Employeur'!B5:B104,"<>") | H14: =COUNTIF('12-Suivi Camp. Communication'!B5:B104,"<>") | K14: =IFERROR(SUM('4-Reseaux Sociaux RH'!H5:H104),0)
B18: COMMUNICATION PAR TYPE & EVENEMENTS PAR STATUT
B19: Type Communication | C19: Nombre
B20: Annonce | C20: =COUNTIF('2-Communication Interne'!D5:D104,"Annonce")
B21: Information | C21: =COUNTIF('2-Communication Interne'!D5:D104,"Information")
B22: Consultation | C22: =COUNTIF('2-Communication Interne'!D5:D104,"Consultation")
B23: Evenement | C23: =COUNTIF('2-Communication Interne'!D5:D104,"Evenement")
B24: Formation | C24: =COUNTIF('2-Communication Interne'!D5:D104,"Formation")
B25: Sondage | C25: =COUNTIF('2-Communication Interne'!D5:D104,"Sondage")
B26: Alerte | C26: =COUNTIF('2-Communication Interne'!D5:D104,"Alerte")
B27: Felicitation | C27: =COUNTIF('2-Communication Interne'!D5:D104,"Felicitation")
H29: Statut Evenement | I29: Nombre
H30: En preparation | I30: =COUNTIF('10-Evenements RH'!L5:L104,"En preparation")
H31: Planifie | I31: =COUNTIF('10-Evenements RH'!L5:L104,"Planifie")
H32: En cours | I32: =COUNTIF('10-Evenements RH'!L5:L104,"En cours")
H33: Termine | I33: =COUNTIF('10-Evenements RH'!L5:L104,"Termine")
H34: Annule | I34: =COUNTIF('10-Evenements RH'!L5:L104,"Annule")
H35: Reporte | I35: =COUNTIF('10-Evenements RH'!L5:L104,"Reporte")

Sheet _Lists
B1: departement | C1: poste_hotel | D1: type_communication | E1: canal_communication | F1: statut_communication | G1: type_contenu_me | H1: plateforme_sociale | I1: statut_candidature | J1: source_candidat | K1: niveau_ambassadeur | L1: type_evenement_rh | M1: statut_evenement | N1: frequence_newsletter | O1: rubrique_journal | P1: statut_publication | Q1: type_enquete | R1: statut_enquete | S1: echelle_satisfaction | T1: statut_action
B2: Direction Générale | C2: DG | D2: Annonce | E2: Email | F2: Brouillon | G2: Temoignage employe | H2: LinkedIn | I2: Recue | J2: LinkedIn | K2: Bronze | L2: Semaine d'integration | M2: En preparation | N2: Hebdomadaire | O2: Edito Direction | P2: Brouillon | Q2: Climat social | R2: En preparation | S2: Tres insatisfait | T2: Planifiee
B3: Service Client | C3: DRH | D3: Information | E3: Affichage | F3: En cours de validation | G3: Video institutionnelle | H3: Facebook | I3: En cours d'analyse | J3: Site web hotel | K3: Argent | L3: Team building | M3: Planifie | N3: Bimensuelle | O3: Vie des equipes | P3: En cours de redaction | Q3: Satisfaction employes | R3: En cours | S3: Insatisfait | T3: En cours
B4: Finance & Comptabilité | C4: Assistante RH | D4: Consultation | E4: Intranet | F4: Valide | G4: Article blog | H4: Instagram | I4: Entretien planifie | J4: Bouche a oreille | K4: Or | L4: Celebration anniversaire | M4: En cours | N4: Mensuelle | O4: Formation | P4: En relecture | Q4: Engagement | R4: Cloturee | S4: Neutre | T4: Terminee
B5: Marketing & Communication | C5: DAF | D5: Sondage | E5: Reunion | F5: Diffusee | G5: Post LinkedIn | H5: Twitter / X | I5: Entretien realise | J5: Reseaux sociaux | K5: Platine | L5: Depart a la retraite | M5: Termine | N5: Trimestrielle | O5: Mobilite & Carriere | P5: Valide | Q5: Bien-etre au travail | R5: En analyse | S5: Satisfait | T5: Reportee
B6: Maintenance | C6: Comptable senior | D6: Formation | E6: Newsletter | F6: Archivée | G6: Post Instagram | H6: TikTok | I6: En attente decision | J6: Evenement carriere | L6: Gala employes | M6: Annule | N6: Ponctuelle | O6: Sante & Securite | P6: Publie | Q6: Qualite de vie au travail | R6: Resultats publies | S6: Tres satisfait | T6: Annulee
B7: Commercial | C7: Chef Comptable | D7: Evenement | E7: Reseaux sociaux | G7: Post Facebook | H7: YouTube | I7: Retenue | J7: Cabinet de recrutement | L7: Sport inter-services | M7: Reporte | O7: Culture & Loisirs | P7: Archive | Q7: RSE & developpement durable | R7: Archivee
B8: Logistique & Approvisionnement | C8: Chef Marketing | D8: Alerte | E8: Panneau d'affichage | G8: Story | H8: Site web carriere | I8: Non retenue | J8: Ecole / Universite | L8: Atelier bien-etre | O8: Felicitations | Q8: Communication interne
B9: Cuisine & Restauration | C9: Chef de service IT | D9: Rappel | E9: SMS / WhatsApp | G9: Carriere & opportunites | H9: Glassdoor | I9: En attente poste | J9: Spontanée | L9: Forme ouverte | O9: Brèves RH | Q9: Conditions de travail
B10: Réception & Front Office | C10: Technicien IT | D10: Felicitation | E10: Note de service | G10: Culture d'entreprise | H10: Indeed | I10: Archivée | J10: Autre | L10: Portes ouvertes | O10: Temoignages | Q10: Formation
B11: Sécurité | C11: Chef Commercial | D11: Remerciement | E11: Affichage digital | G11: Avantages sociaux | H11: Autre | L11: Conference interne | O11: Annonces | Q11: Autre
B12: Étage & Housekeeping | C12: Agent Commercial | D12: Orientation | G12: Formation & developpement | L12: Brainstorming
C13: Chef Logistique | G13: Evenement equipe | L13: Autre
C14: Agent Logistique | G14: Behind the scenes
C15: Chef Production | G15: Infographie
C16: Responsable Service Client | G16: Autre
C17: Conseiller Client
C18: Chef Reception
C19: Receptionniste
C20: Chef Cuisine
C21: Cuisinier
C22: Plongeur
C23: Chef Entretien
C24: Technicien Maintenance
C25: Agent Securite
C26: Stagiaire RH
C27: Stagiaire
C28: Autre

Sheet 2-Communication Interne
B2: COMMUNICATION INTERNE (#137)
B3: TABLEAU DYNAMIQUE — Saisissez dans la prochaine ligne jaune. Les calculs se mettent a jour automatiquement.
B4: N° | C4: Titre Communication | D4: Type | E4: Canal | F4: Emetteur | G4: Cible / Destinataire | H4: Date Emission | I4: Contenu Resume | J4: Statut
B5: COM-001 | C5: Nouvelle politique conges 2025 | D5: Information | E5: Email | F5: DRH | G5: Tous les employes | H5: 45672 | I5: Mise a jour des plafonds de conges annuels | J5: Diffusee
B6: COM-002 | C6: Semaine de l'integration Q1 | D6: Evenement | E6: Affichage | F6: DRH | G6: Nouveaux employes | H6: 45689 | I6: Programme d'accueil et visite des services | J6: En cours de validation
B7: COM-003 | C7: Resultats enquete climat 2024 | D7: Consultation | E7: Reunion | F7: Direction | G7: Cadres et managers | H7: 45682 | I7: Presentation des resultats et plan d'action | J7: Valide
B8: =IF(C8="","COM-"&TEXT(COUNTA($C$5:C8),"000"))
B9: =IF(C9="","COM-"&TEXT(COUNTA($C$5:C9),"000"))
B10: =IF(C10="","COM-"&TEXT(COUNTA($C$5:C10),"000"))
B11: =IF(C11="","COM-"&TEXT(COUNTA($C$5:C11),"000"))
B12: =IF(C12="","COM-"&TEXT(COUNTA($C$5:C12),"000"))
B13: =IF(C13="","COM-"&TEXT(COUNTA($C$5:C13),"000"))
B14: =IF(C14="","COM-"&TEXT(COUNTA($C$5:C14),"000"))
B15: =IF(C15="","COM-"&TEXT(COUNTA($C$5:C15),"000"))
B16: =IF(C16="","COM-"&TEXT(COUNTA($C$5:C16),"000"))
B17: =IF(C17="","COM-"&TEXT(COUNTA($C$5:C17),"000"))
B18: =IF(C18="","COM-"&TEXT(COUNTA($C$5:C18),"000"))
B19: =IF(C19="","COM-"&TEXT(COUNTA($C$5:C19),"000"))
... B107: =IF(C107="","COM-"&TEXT(COUNTA($C$5:C107),"000"))
B109: INDICATEURS (mis a jour automatiquement)
B110: Communications suivies | D110: Diffusees | F110: En attente validation
B111: =COUNTIF(B5:B104,"<>") | D111: =COUNTIF(J5:J104,"Diffusee") | F111: =COUNTIF(J5:J104,"En cours de validation")

Sheet 3-Marque Employeur
B2: MARQUE EMPLOYEUR (#138)
B3: TABLEAU DYNAMIQUE — Saisissez dans la prochaine ligne jaune. Les calculs se mettent a jour automatiquement.
B4: N° | C4: Initiative ME | D4: Type Contenu | E4: Objectif | F4: Responsable | G4: Date Lancement | H4: Date Fin | I4: Cible | J4: Budget (FCFA) | K4: Statut
B5: ME-001 | C5: Campagne talents 2025 | D5: Video institutionnelle | E5: Attirer de nouveaux talents | F5: Chef Marketing | G5: 45667 | H5: 45838 | I5: Jeunes diplomes | J5: 1500000 | K5: En cours
B6: ME-002 | C6: Temoignages employes | D6: Temoignage employe | E6: Renforcer la credibilite ME | F6: DRH | G6: 45689 | H6: 46022 | I6: Candidats potentiels | J6: 500000 | K6: En cours
B7: ME-003 | C7: Classement meilleur employeur | D7: Article blog | E7: Ameliorer e-reputation | F7: Chef Marketing | G7: 45731 | H7: 45853 | I7: Public large | J7: 300000 | K7: En preparation
B8: =IF(C8="","ME-"&TEXT(COUNTA($C$5:C8),"000"))
B9: =IF(C9="","ME-"&TEXT(COUNTA($C$5:C9),"000"))
B10: =IF(C10="","ME-"&TEXT(COUNTA($C$5:C10),"000"))
B11: =IF(C11="","ME-"&TEXT(COUNTA($C$5:C11),"000"))
B12: =IF(C12="","ME-"&TEXT(COUNTA($C$5:C12),"000"))
B13: =IF(C13="","ME-"&TEXT(COUNTA($C$5:C13),"000"))
B14: =IF(C14="","ME-"&TEXT(COUNTA($C$5:C14),"000"))
B15: =IF(C15="","ME-"&TEXT(COUNTA($C$5:C15),"000"))
B16: =IF(C16="","ME-"&TEXT(COUNTA($C$5:C16),"000"))
B17: =IF(C17="","ME-"&TEXT(COUNTA($C$5:C17),"000"))
B18: =IF(C18="","ME-"&TEXT(COUNTA($C$5:C18),"000"))
B19: =IF(C19="","ME-"&TEXT(COUNTA($C$5:C19),"000"))
... B107: =IF(C107="","ME-"&TEXT(COUNTA($C$5:C107),"000"))
B109: INDICATEURS (mis a jour automatiquement)
B110: Initiatives ME | D110: Budget total (FCFA) | F110: En cours
B111: =COUNTIF(B5:B104,"<>") | D111: =SUM(J5:J104) | F111: =COUNTIF(K5:K104,"En cours")

Sheet 4-Reseaux Sociaux RH
B2: RESEAUX SOCIAUX RH (#139)
B3: TABLEAU DYNAMIQUE — Saisissez dans la prochaine ligne jaune. Les calculs se mettent a jour automatiquement.
B4: N° | C4: Plateforme | D4: Type de Post | E4: Titre du Post | F4: Date Publication | G4: Auteur | H4: Vues | I4: Likes / Reactions | J4: Partages | K4: Commentaires | L4: Clics Lien
B5: RS-001 | C5: LinkedIn | D5: Post LinkedIn | E5: Nous recrutons un Chef Reception | F5: 45698 | G5: DRH | H5: 2500 | I5: 180 | J5: 45 | K5: 22 | L5: 35
B6: RS-002 | C6: Facebook | D6: Post Facebook | E6: Decouvrez notre equipe Cuisine | F6: 45700 | G6: Chef Marketing | H6: 4500 | I6: 320 | J6: 80 | K6: 55 | L6: 20
B7: RS-003 | C7: Instagram | D7: Story | E7: Journee type Receptionniste | F7: 45702 | G7: Chef Marketing | H7: 3200 | I7: 210 | J7: 40 | K7: 18 | L7: 15
B8: =IF(C8="","RS-"&TEXT(COUNTA($C$5:C8),"000")) | M8: =IF(H8="","",(I8+J8+K8)/H8)
B9: =IF(C9="","RS-"&TEXT(COUNTA($C$5:C9),"000")) | M9: =IF(H9="","",(I9+J9+K9)/H9)
B10: =IF(C10="","RS-"&TEXT(COUNTA($C$5:C10),"000")) | M10: =IF(H10="","",(I10+J10+K10)/H10)
B11: =IF(C11="","RS-"&TEXT(COUNTA($C$5:C11),"000")) | M11: =IF(H11="","",(I11+J11+K11)/H11)
B12: =IF(C12="","RS-"&TEXT(COUNTA($C$5:C12),"000")) | M12: =IF(H12="","",(I12+J12+K12)/H12)
B13: =IF(C13="","RS-"&TEXT(COUNTA($C$5:C13),"000")) | M13: =IF(H13="","",(I13+J13+K13)/H13)
B14: =IF(C14="","RS-"&TEXT(COUNTA($C$5:C14),"000")) | M14: =IF(H14="","",(I14+J14+K14)/H14)
B15: =IF(C15="","RS-"&TEXT(COUNTA($C$5:C15),"000")) | M15: =IF(H15="","",(I15+J15+K15)/H15)
B16: =IF(C16="","RS-"&TEXT(COUNTA($C$5:C16),"000")) | M16: =IF(H16="","",(I16+J16+K16)/H16)
B17: =IF(C17="","RS-"&TEXT(COUNTA($C$5:C17),"000")) | M17: =IF(H17="","",(I17+J17+K17)/H17)
B18: =IF(C18="","RS-"&TEXT(COUNTA($C$5:C18),"000")) | M18: =IF(H18="","",(I18+J18+K18)/H18)
B19: =IF(C19="","RS-"&TEXT(COUNTA($C$5:C19),"000")) | M19: =IF(H19="","",(I19+J19+K19)/H19)
... B107: =IF(C107="","RS-"&TEXT(COUNTA($C$5:C107),"000")) | M107: =IF(H107="","",(I107+J107+K107)/H107)
B109: INDICATEURS (mis a jour automatiquement)
B110: Publications | D110: Vues totales | F110: Engagement moyen
B111: =COUNTIF(B5:B104,"<>") | D111: =SUM(H5:H104) | F111: =IFERROR(AVERAGE(M5:M104),0)

Sheet 5-Candidatures Spontanees
B2: CANDIDATURES SPONTANEES (#140)
B3: TABLEAU DYNAMIQUE — Saisissez dans la prochaine ligne jaune. Les calculs se mettent a jour automatiquement.
B4: N° | C4: Nom Candidat | D4: Prenom | E4: Poste Souhaite | F4: Departement | G4: Email | H4: Telephone | I4: Date Reception | J4: Source | K4: Statut | L4: Observations
B5: CSP-001 | C5: Nkoulou | D5: Patrice | E5: Chef Reception | F5: Réception & Front Office | G5: p.nkoulou@email.com | H5: 698123456 | I5: 45693 | J5: Spontanée | K5: En cours d'analyse | L5: CV complet, 5 ans experience hotel
B6: CSP-002 | C6: Mbarga | D6: Sophie | E6: Assistante RH | F6: Service Client | G6: s.mbarga@email.com | H6: 695789012 | I6: 45696 | J6: Site web hotel | K6: En attente poste | L6: Bonne experience admin
B7: CSP-003 | C7: Nganou | D7: Jean | E7: Cuisinier | F7: Cuisine & Restauration | G7: j.nganou@email.com | H7: 693456789 | I7: 45700 | J7: Bouche a oreille | K7: Entretien planifie | L7: Specialise cuisine camerounaise
B8: =IF(C8="","CSP-"&TEXT(COUNTA($C$5:C8),"000"))
B9: =IF(C9="","CSP-"&TEXT(COUNTA($C$5:C9),"000"))
B10: =IF(C10="","CSP-"&TEXT(COUNTA($C$5:C10),"000"))
B11: =IF(C11="","CSP-"&TEXT(COUNTA($C$5:C11),"000"))
B12: =IF(C12="","CSP-"&TEXT(COUNTA($C$5:C12),"000"))
B13: =IF(C13="","CSP-"&TEXT(COUNTA($C$5:C13),"000"))
B14: =IF(C14="","CSP-"&TEXT(COUNTA($C$5:C14),"000"))
B15: =IF(C15="","CSP-"&TEXT(COUNTA($C$5:C15),"000"))
B16: =IF(C16="","CSP-"&TEXT(COUNTA($C$5:C16),"000"))
B17: =IF(C17="","CSP-"&TEXT(COUNTA($C$5:C17),"000"))
B18: =IF(C18="","CSP-"&TEXT(COUNTA($C$5:C18),"000"))
B19: =IF(C19="","CSP-"&TEXT(COUNTA($C$5:C19),"000"))
... B107: =IF(C107="","CSP-"&TEXT(COUNTA($C$5:C107),"000"))
B109: INDICATEURS (mis a jour automatiquement)
B110: Candidatures recues | D110: En attente | F110: Retenues
B111: =COUNTIF(B5:B104,"<>") | D111: =COUNTIF(K5:K104,"En attente*")+COUNTIF(K5:K104,"En cours*") | F111: =COUNTIF(K5:K104,"Retenue")

Sheet 6-Ambassadeurs Marque
B2: AMBASSADEURS MARQUE (#141)
B3: TABLEAU DYNAMIQUE — Saisissez dans la prochaine ligne jaune. Les calculs se mettent a jour automatiquement.
B4: N° | C4: Nom Employe | D4: Poste | E4: Departement | F4: Anciennete (ans) | G4: Niveau Ambassadeur | H4: Reseaux Sociaux Actifs | I4: Nb Posts Publies | J4: Nb Partages ME | K4: Score Impact | L4: Date Nomination
B5: AMB-001 | C5: Fotsing | D5: Chef Reception | E5: Réception & Front Office | F5: 7 | G5: Or | H5: LinkedIn, Instagram | I5: 24 | J5: 18 | L5: 45444
B6: AMB-002 | C6: Tchinda | D6: Chef Cuisine | E6: Cuisine & Restauration | F6: 10 | G6: Platine | H6: LinkedIn, Facebook | I6: 35 | J6: 30 | L6: 45184
B7: AMB-003 | C7: Kamga | D7: Responsable SAV | E7: Service Client | F7: 4 | G7: Argent | H7: LinkedIn | I7: 12 | J7: 8 | L7: 45667
B8: =IF(C8="","AMB-"&TEXT(COUNTA($C$5:C8),"000")) | K8: =IF(I8="","",I8*3+J8*5)
B9: =IF(C9="","AMB-"&TEXT(COUNTA($C$5:C9),"000")) | K9: =IF(I9="","",I9*3+J9*5)
B10: =IF(C10="","AMB-"&TEXT(COUNTA($C$5:C10),"000")) | K10: =IF(I10="","",I10*3+J10*5)
B11: =IF(C11="","AMB-"&TEXT(COUNTA($C$5:C11),"000")) | K11: =IF(I11="","",I11*3+J11*5)
B12: =IF(C12="","AMB-"&TEXT(COUNTA($C$5:C12),"000")) | K12: =IF(I12="","",I12*3+J12*5)
B13: =IF(C13="","AMB-"&TEXT(COUNTA($C$5:C13),"000")) | K13: =IF(I13="","",I13*3+J13*5)
B14: =IF(C14="","AMB-"&TEXT(COUNTA($C$5:C14),"000")) | K14: =IF(I14="","",I14*3+J14*5)
B15: =IF(C15="","AMB-"&TEXT(COUNTA($C$5:C15),"000")) | K15: =IF(I15="","",I15*3+J15*5)
B16: =IF(C16="","AMB-"&TEXT(COUNTA($C$5:C16),"000")) | K16: =IF(I16="","",I16*3+J16*5)
B17: =IF(C17="","AMB-"&TEXT(COUNTA($C$5:C17),"000")) | K17: =IF(I17="","",I17*3+J17*5)
B18: =IF(C18="","AMB-"&TEXT(COUNTA($C$5:C18),"000")) | K18: =IF(I18="","",I18*3+J18*5)
B19: =IF(C19="","AMB-"&TEXT(COUNTA($C$5:C19),"000")) | K19: =IF(I19="","",I19*3+J19*5)
... B107: =IF(C107="","AMB-"&TEXT(COUNTA($C$5:C107),"000")) | K107: =IF(I107="","",I107*3+J107*5)
B109: INDICATEURS (mis a jour automatiquement)
B110: Ambassadeurs | D110: Total posts | F110: Score moyen
B111: =COUNTIF(B5:B104,"<>") | D111: =SUM(I5:I104) | F111: =IFERROR(AVERAGE(K5:K104),0)

Sheet 7-Enquete Climat Social
B2: ENQUETE CLIMAT SOCIAL (#142)
B3: TABLEAU DYNAMIQUE — Saisissez dans la prochaine ligne jaune. Les calculs se mettent a jour automatiquement.
B4: N° | C4: Titre Enquete | D4: Type Enquete | E4: Periode | F4: Date Lancement | G4: Date Cloture | H4: Nb Invites | I4: Nb Reponses | J4: Taux Participation (%) | K4: Score Global / 5 | L4: Statut | M4: Plan Action Suivi
B5: ENC-001 | C5: Climat social 2024 | D5: Climat social | E5: Annuelle 2024 | F5: 45566 | G5: 45596 | H5: 150 | I5: 128 | K5: 3.8 | L5: Resultats publies | M5: Plan action Q1 2025 en cours
B6: ENC-002 | C6: Satisfaction employes Q1 | D6: Satisfaction employes | E6: T1 2025 | F6: 45717 | G6: 45731 | H6: 160 | I6: 0 | L6: En preparation
B7: ENC-003 | C7: Bien-etre au travail | D7: Bien-etre au travail | E7: T2 2025 | F7: 45778 | G7: 45797 | H7: 160 | I7: 0 | L7: En preparation | M7: Prevu pour juin 2025
B8: =IF(C8="","ENC-"&TEXT(COUNTA($C$5:C8),"000")) | J8: =IF(OR(H8="",I8=""),"",I8/H8)
B9: =IF(C9="","ENC-"&TEXT(COUNTA($C$5:C9),"000")) | J9: =IF(OR(H9="",I9=""),"",I9/H9)
B10: =IF(C10="","ENC-"&TEXT(COUNTA($C$5:C10),"000")) | J10: =IF(OR(H10="",I10=""),"",I10/H10)
B11: =IF(C11="","ENC-"&TEXT(COUNTA($C$5:C11),"000")) | J11: =IF(OR(H11="",I11=""),"",I11/H11)
B12: =IF(C12="","ENC-"&TEXT(COUNTA($C$5:C12),"000")) | J12: =IF(OR(H12="",I12=""),"",I12/H12)
B13: =IF(C13="","ENC-"&TEXT(COUNTA($C$5:C13),"000")) | J13: =IF(OR(H13="",I13=""),"",I13/H13)
B14: =IF(C14="","ENC-"&TEXT(COUNTA($C$5:C14),"000")) | J14: =IF(OR(H14="",I14=""),"",I14/H14)
B15: =IF(C15="","ENC-"&TEXT(COUNTA($C$5:C15),"000")) | J15: =IF(OR(H15="",I15=""),"",I15/H15)
B16: =IF(C16="","ENC-"&TEXT(COUNTA($C$5:C16),"000")) | J16: =IF(OR(H16="",I16=""),"",I16/H16)
B17: =IF(C17="","ENC-"&TEXT(COUNTA($C$5:C17),"000")) | J17: =IF(OR(H17="",I17=""),"",I17/H17)
B18: =IF(C18="","ENC-"&TEXT(COUNTA($C$5:C18),"000")) | J18: =IF(OR(H18="",I18=""),"",I18/H18)
B19: =IF(C19="","ENC-"&TEXT(COUNTA($C$5:C19),"000")) | J19: =IF(OR(H19="",I19=""),"",I19/H19)
... B107: =IF(C107="","ENC-"&TEXT(COUNTA($C$5:C107),"000")) | J107: =IF(OR(H107="",I107=""),"",I107/H107)
B109: INDICATEURS (mis a jour automatiquement)
B110: Enquetes | D110: Taux reponse moyen | F110: Score moyen / 5
B111: =COUNTIF(B5:B104,"<>") | D111: =IFERROR(AVERAGE(J5:J104),0) | F111: =IFERROR(AVERAGE(K5:K104),0)

Sheet 8-Newsletter Interne
B2: NEWSLETTER INTERNE (#143)
B3: TABLEAU DYNAMIQUE — Saisissez dans la prochaine ligne jaune. Les calculs se mettent a jour automatiquement.
B4: N° | C4: Titre Newsletter | D4: Frequence | E4: Numero Edition | F4: Date Envoi | G4: Redacteur | H4: Nb Destinataires | I4: Taux Ouverture (%) | J4: Taux Clic (%) | K4: Rubriques | L4: Statut
B5: NWS-001 | C5: Actu RH - Janvier 2025 | D5: Mensuelle | E5: Ed. 48 | F5: 45687 | G5: DRH | H5: 155 | I5: 0.72 | J5: 0.35 | K5: Edito, Formations, Felicitations | L5: Publie
B6: NWS-002 | C6: Actu RH - Fevrier 2025 | D6: Mensuelle | E6: Ed. 49 | F6: 45716 | G6: DRH | H6: 158 | I6: 0.68 | J6: 0.3 | K6: Vie equipes, Sante, Brèves RH | L6: En cours de redaction
B7: NWS-003 | C7: Speciale Integration Q1 | D7: Ponctuelle | E7: Ed. Spec. | F7: 45731 | G7: Assistante RH | H7: 160 | K7: Orientation, Temoignages, Planning | L7: En preparation
B8: =IF(C8="","NWS-"&TEXT(COUNTA($C$5:C8),"000"))
B9: =IF(C9="","NWS-"&TEXT(COUNTA($C$5:C9),"000"))
B10: =IF(C10="","NWS-"&TEXT(COUNTA($C$5:C10),"000"))
B11: =IF(C11="","NWS-"&TEXT(COUNTA($C$5:C11),"000"))
B12: =IF(C12="","NWS-"&TEXT(COUNTA($C$5:C12),"000"))
B13: =IF(C13="","NWS-"&TEXT(COUNTA($C$5:C13),"000"))
B14: =IF(C14="","NWS-"&TEXT(COUNTA($C$5:C14),"000"))
B15: =IF(C15="","NWS-"&TEXT(COUNTA($C$5:C15),"000"))
B16: =IF(C16="","NWS-"&TEXT(COUNTA($C$5:C16),"000"))
B17: =IF(C17="","NWS-"&TEXT(COUNTA($C$5:C17),"000"))
B18: =IF(C18="","NWS-"&TEXT(COUNTA($C$5:C18),"000"))
B19: =IF(C19="","NWS-"&TEXT(COUNTA($C$5:C19),"000"))
... B107: =IF(C107="","NWS-"&TEXT(COUNTA($C$5:C107),"000"))
B109: INDICATEURS (mis a jour automatiquement)
B110: Newsletters | D110: Taux ouverture moy. | F110: Taux clic moyen
B111: =COUNTIF(B5:B104,"<>") | D111: =IFERROR(AVERAGE(I5:I104),0) | F111: =IFERROR(AVERAGE(J5:J104),0)

Sheet 9-Journal Interne
B2: JOURNAL INTERNE (#144)
B3: TABLEAU DYNAMIQUE — Saisissez dans la prochaine ligne jaune. Les calculs se mettent a jour automatiquement.
B4: N° | C4: Titre Article | D4: Rubrique | E4: Auteur | F4: Date Soumission | G4: Date Publication | H4: Nb Pages | I4: Nb Lectures Estimees | J4: Statut | K4: Commentaire Edition
B5: JRN-001 | C5: Nos nouveaux talents de l'annee | D5: Temoignages | E5: DRH | F5: 45667 | G5: 45677 | H5: 2 | I5: 120 | J5: Publie | K5: Excellente presentation
B6: JRN-002 | C6: Guide securite cuisine mise a jour | D6: Sante & Securite | E6: Chef Entretien | F6: 45689 | G6: 45698 | H6: 1 | I6: 95 | J6: Publie | K6: A afficher en cuisine
B7: JRN-003 | C7: Resultats foot inter-services | D7: Culture & Loisirs | E7: Chef Commercial | F7: 45703 | H7: 1 | J7: En relecture | K7: Photos a ajouter
B8: =IF(C8="","JRN-"&TEXT(COUNTA($C$5:C8),"000"))
B9: =IF(C9="","JRN-"&TEXT(COUNTA($C$5:C9),"000"))
B10: =IF(C10="","JRN-"&TEXT(COUNTA($C$5:C10),"000"))
B11: =IF(C11="","JRN-"&TEXT(COUNTA($C$5:C11),"000"))
B12: =IF(C12="","JRN-"&TEXT(COUNTA($C$5:C12),"000"))
B13: =IF(C13="","JRN-"&TEXT(COUNTA($C$5:C13),"000"))
B14: =IF(C14="","JRN-"&TEXT(COUNTA($C$5:C14),"000"))
B15: =IF(C15="","JRN-"&TEXT(COUNTA($C$5:C15),"000"))
B16: =IF(C16="","JRN-"&TEXT(COUNTA($C$5:C16),"000"))
B17: =IF(C17="","JRN-"&TEXT(COUNTA($C$5:C17),"000"))
B18: =IF(C18="","JRN-"&TEXT(COUNTA($C$5:C18),"000"))
B19: =IF(C19="","JRN-"&TEXT(COUNTA($C$5:C19),"000"))
... B107: =IF(C107="","JRN-"&TEXT(COUNTA($C$5:C107),"000"))
B109: INDICATEURS (mis a jour automatiquement)
B110: Articles | D110: Publies | F110: Lectures totales
B111: =COUNTIF(B5:B104,"<>") | D111: =COUNTIF(J5:J104,"Publie") | F111: =SUM(I5:I104)

Sheet 10-Evenements RH
B2: EVENEMENTS RH (#145)
B3: TABLEAU DYNAMIQUE — Saisissez dans la prochaine ligne jaune. Les calculs se mettent a jour automatiquement.
B4: N° | C4: Nom Evenement | D4: Type | E4: Date Debut | F4: Date Fin | G4: Lieu | H4: Organisateur | I4: Nb Participants | J4: Budget (FCFA) | K4: Cout Reel (FCFA) | L4: Statut | M4: Observations
B5: EVT-001 | C5: Team building annuel | D5: Team building | E5: 45731 | F5: 45732 | G5: Plage de Kribi | H5: DRH | I5: 80 | J5: 2000000 | L5: En preparation | M5: Transport et restauration prevus
B6: EVT-002 | C6: Celebration 10 ans hotel | D6: Gala employes | E6: 45828 | F6: 45828 | G6: Salle principale | H6: Direction | I6: 150 | J6: 5000000 | L6: Planifie | M6: Prestations en cours de negociation
B7: EVT-003 | C7: Semaine bien-etre | D7: Atelier bien-etre | E7: 45754 | F7: 45758 | G7: Salle formation | H7: DRH | I7: 40 | J7: 500000 | L7: En preparation | M7: Intervenants externes confirmes
B8: =IF(C8="","EVT-"&TEXT(COUNTA($C$5:C8),"000"))
B9: =IF(C9="","EVT-"&TEXT(COUNTA($C$5:C9),"000"))
B10: =IF(C10="","EVT-"&TEXT(COUNTA($C$5:C10),"000"))
B11: =IF(C11="","EVT-"&TEXT(COUNTA($C$5:C11),"000"))
B12: =IF(C12="","EVT-"&TEXT(COUNTA($C$5:C12),"000"))
B13: =IF(C13="","EVT-"&TEXT(COUNTA($C$5:C13),"000"))
B14: =IF(C14="","EVT-"&TEXT(COUNTA($C$5:C14),"000"))
B15: =IF(C15="","EVT-"&TEXT(COUNTA($C$5:C15),"000"))
B16: =IF(C16="","EVT-"&TEXT(COUNTA($C$5:C16),"000"))
B17: =IF(C17="","EVT-"&TEXT(COUNTA($C$5:C17),"000"))
B18: =IF(C18="","EVT-"&TEXT(COUNTA($C$5:C18),"000"))
B19: =IF(C19="","EVT-"&TEXT(COUNTA($C$5:C19),"000"))
... B107: =IF(C107="","EVT-"&TEXT(COUNTA($C$5:C107),"000"))
B109: INDICATEURS (mis a jour automatiquement)
B110: Evenements | D110: Budget total | F110: Participants totaux
B111: =COUNTIF(B5:B104,"<>") | D111: =SUM(J5:J104) | F111: =SUM(I5:I104)

Sheet 11-Indic. Marque Employeur
B2: INDICATEURS MARQUE EMPLOYEUR (#146)
B3: TABLEAU DYNAMIQUE — Saisissez dans la prochaine ligne jaune. Les calculs se mettent a jour automatiquement.
B4: N° | C4: Indicateur | D4: Description | E4: Valeur Cible | F4: Valeur Actuelle | G4: Ecart | H4: Tendance | I4: Frequence Mesure | J4: Responsable | K4: Date Mesure | L4: Statut
B5: IME-001 | C5: Taux recommandation employes (eNPS) | D5: Score eNPS obtenu via enquete | E5: 50 | F5: 42 | H5: En hausse | I5: Trimestrielle | J5: DRH | K5: 45688 | L5: En cours
B6: IME-002 | C6: Nb candidatures spontanees / mois | D6: Volume de candidatures recues | E6: 15 | F6: 12 | H6: Stable | I6: Mensuelle | J6: DRH | K6: 45716 | L6: En cours
B7: IME-003 | C7: Taux visites page carrieres | D7: % visiteurs vs total trafic site | E7: 0.15 | F7: 0.12 | H7: En hausse | I7: Mensuelle | J7: Chef Marketing | K7: 45716 | L7: En cours
B8: IME-004 | C8: Taux retention 1ere annee | D8: % nouveaux embauches encore en poste a 1 an | E8: 0.85 | F8: 0.8 | H8: En hausse | I8: Annuelle | J8: DRH | K8: 45672 | L8: En cours
B9: =IF(C9="","IME-"&TEXT(COUNTA($C$5:C9),"000")) | G9: =IF(OR(E9="",F9=""),"",F9-E9)
B10: =IF(C10="","IME-"&TEXT(COUNTA($C$5:C10),"000")) | G10: =IF(OR(E10="",F10=""),"",F10-E10)
B11: =IF(C11="","IME-"&TEXT(COUNTA($C$5:C11),"000")) | G11: =IF(OR(E11="",F11=""),"",F11-E11)
B12: =IF(C12="","IME-"&TEXT(COUNTA($C$5:C12),"000")) | G12: =IF(OR(E12="",F12=""),"",F12-E12)
B13: =IF(C13="","IME-"&TEXT(COUNTA($C$5:C13),"000")) | G13: =IF(OR(E13="",F13=""),"",F13-E13)
B14: =IF(C14="","IME-"&TEXT(COUNTA($C$5:C14),"000")) | G14: =IF(OR(E14="",F14=""),"",F14-E14)
B15: =IF(C15="","IME-"&TEXT(COUNTA($C$5:C15),"000")) | G15: =IF(OR(E15="",F15=""),"",F15-E15)
B16: =IF(C16="","IME-"&TEXT(COUNTA($C$5:C16),"000")) | G16: =IF(OR(E16="",F16=""),"",F16-E16)
B17: =IF(C17="","IME-"&TEXT(COUNTA($C$5:C17),"000")) | G17: =IF(OR(E17="",F17=""),"",F17-E17)
B18: =IF(C18="","IME-"&TEXT(COUNTA($C$5:C18),"000")) | G18: =IF(OR(E18="",F18=""),"",F18-E18)
B19: =IF(C19="","IME-"&TEXT(COUNTA($C$5:C19),"000")) | G19: =IF(OR(E19="",F19=""),"",F19-E19)
B20: =IF(C20="","IME-"&TEXT(COUNTA($C$5:C20),"000")) | G20: =IF(OR(E20="",F20=""),"",F20-E20)
... B108: =IF(C108="","IME-"&TEXT(COUNTA($C$5:C108),"000")) | G108: =IF(OR(E108="",F108=""),"",F108-E108)
B110: INDICATEURS (mis a jour automatiquement)
B111: Indicateurs suivis | D111: Objectifs atteints | F111: Sous objectif
B112: =COUNTIF(B5:B104,"<>") | D112: =COUNTIF(G5:G104,">="&0) | F112: =COUNTIF(G5:G104,"<"&0)

Sheet 12-Suivi Camp. Communication
B2: SUIVI CAMPAGNES COMMUNICATION
B3: TABLEAU DYNAMIQUE — Saisissez dans la prochaine ligne jaune. Les calculs se mettent a jour automatiquement.
B4: N° | C4: Campagne | D4: Objectif | E4: Canal | F4: Date Lancement | G4: Date Fin | H4: Public Cible | I4: Portee (nb personnes) | J4: Nb Interactions | K4: Taux Conversion (%) | L4: Cout (FCFA) | M4: ROI Estime (%)
B5: SCC-001 | C5: Recrutement saison ete | D5: 20 recrutements CDD | E5: Multi-canal | F5: 45717 | G5: 45777 | H5: Etudiants, jeunes actifs | I5: 5000 | J5: 320 | L5: 800000
B6: SCC-002 | C6: Promotion offres CDI | D6: 10 recrutements CDI | E6: LinkedIn | F6: 45703 | G6: 45747 | H6: Professionnels hotel | I6: 8000 | J6: 450 | L6: 600000
B7: SCC-003 | C7: Image employeur | D7: Augmenter eNPS de 10 pts | E7: Reseaux sociaux | F7: 45658 | G7: 45838 | H7: Grand public | I7: 15000 | J7: 2800 | L7: 1200000
B8: =IF(C8="","SCC-"&TEXT(COUNTA($C$5:C8),"000")) | K8: =IF(I8="","",J8/I8) | M8: =IF(OR(J8="",L8=""),"",(J8*50000-L8)/L8)
B9: =IF(C9="","SCC-"&TEXT(COUNTA($C$5:C9),"000")) | K9: =IF(I9="","",J9/I9) | M9: =IF(OR(J9="",L9=""),"",(J9*50000-L9)/L9)
B10: =IF(C10="","SCC-"&TEXT(COUNTA($C$5:C10),"000")) | K10: =IF(I10="","",J10/I10) | M10: =IF(OR(J10="",L10=""),"",(J10*50000-L10)/L10)
B11: =IF(C11="","SCC-"&TEXT(COUNTA($C$5:C11),"000")) | K11: =IF(I11="","",J11/I11) | M11: =IF(OR(J11="",L11=""),"",(J11*50000-L11)/L11)
B12: =IF(C12="","SCC-"&TEXT(COUNTA($C$5:C12),"000")) | K12: =IF(I12="","",J12/I12) | M12: =IF(OR(J12="",L12=""),"",(J12*50000-L12)/L12)
B13: =IF(C13="","SCC-"&TEXT(COUNTA($C$5:C13),"000")) | K13: =IF(I13="","",J13/I13) | M13: =IF(OR(J13="",L13=""),"",(J13*50000-L13)/L13)
B14: =IF(C14="","SCC-"&TEXT(COUNTA($C$5:C14),"000")) | K14: =IF(I14="","",J14/I14) | M14: =IF(OR(J14="",L14=""),"",(J14*50000-L14)/L14)
B15: =IF(C15="","SCC-"&TEXT(COUNTA($C$5:C15),"000")) | K15: =IF(I15="","",J15/I15) | M15: =IF(OR(J15="",L15=""),"",(J15*50000-L15)/L15)
B16: =IF(C16="","SCC-"&TEXT(COUNTA($C$5:C16),"000")) | K16: =IF(I16="","",J16/I16) | M16: =IF(OR(J16="",L16=""),"",(J16*50000-L16)/L16)
B17: =IF(C17="","SCC-"&TEXT(COUNTA($C$5:C17),"000")) | K17: =IF(I17="","",J17/I17) | M17: =IF(OR(J17="",L17=""),"",(J17*50000-L17)/L17)
B18: =IF(C18="","SCC-"&TEXT(COUNTA($C$5:C18),"000")) | K18: =IF(I18="","",J18/I18) | M18: =IF(OR(J18="",L18=""),"",(J18*50000-L18)/L18)
B19: =IF(C19="","SCC-"&TEXT(COUNTA($C$5:C19),"000")) | K19: =IF(I19="","",J19/I19) | M19: =IF(OR(J19="",L19=""),"",(J19*50000-L19)/L19)
... B107: =IF(C107="","SCC-"&TEXT(COUNTA($C$5:C107),"000")) | K107: =IF(I107="","",J107/I107) | M107: =IF(OR(J107="",L107=""),"",(J107*50000-L107)/L107)
B109: INDICATEURS (mis a jour automatiquement)
B110: Campagnes actives | D110: Portee totale | F110: Cout total (FCFA)
B111: =COUNTIF(B5:B104,"<>") | D111: =SUM(I5:I104) | F111: =SUM(L5:L104)

Sheet 13-Taux Engag. Reseaux Soc.
B2: TAUX ENGAGEMENT RESEAUX SOCIAUX
B3: TABLEAU DYNAMIQUE — Saisissez dans la prochaine ligne jaune. Les calculs se mettent a jour automatiquement.
B4: N° | C4: Plateforme | D4: Abonnes / Followers | E4: Nb Posts Mois | F4: Vues Totales | G4: Likes Total | H4: Commentaires Total | I4: Partages Total | J4: Taux Engagement Moy. (%) | K4: Evolution Abonnes (%) | L4: Meilleur Post
B5: ENG-001 | C5: LinkedIn | D5: 4200 | E5: 12 | F5: 35000 | G5: 2100 | H5: 180 | I5: 95 | K5: 0.05 | L5: Recrutement Chef Cuisin
B6: ENG-002 | C6: Facebook | D6: 8500 | E6: 8 | F6: 45000 | G6: 3200 | H6: 450 | I6: 280 | K6: 0.03 | L6: Video equipe Cuisine
B7: ENG-003 | C7: Instagram | D7: 3100 | E7: 15 | F7: 28000 | G7: 1800 | H7: 120 | I7: 60 | K7: 0.08 | L7: Story journee Reception
B8: =IF(C8="","ENG-"&TEXT(COUNTA($C$5:C8),"000")) | J8: =IF(F8="","",(G8+H8+I8)/F8)
B9: =IF(C9="","ENG-"&TEXT(COUNTA($C$5:C9),"000")) | J9: =IF(F9="","",(G9+H9+I9)/F9)
B10: =IF(C10="","ENG-"&TEXT(COUNTA($C$5:C10),"000")) | J10: =IF(F10="","",(G10+H10+I10)/F10)
B11: =IF(C11="","ENG-"&TEXT(COUNTA($C$5:C11),"000")) | J11: =IF(F11="","",(G11+H11+I11)/F11)
B12: =IF(C12="","ENG-"&TEXT(COUNTA($C$5:C12),"000")) | J12: =IF(F12="","",(G12+H12+I12)/F12)
B13: =IF(C13="","ENG-"&TEXT(COUNTA($C$5:C13),"000")) | J13: =IF(F13="","",(G13+H13+I13)/F13)
B14: =IF(C14="","ENG-"&TEXT(COUNTA($C$5:C14),"000")) | J14: =IF(F14="","",(G14+H14+I14)/F14)
B15: =IF(C15="","ENG-"&TEXT(COUNTA($C$5:C15),"000")) | J15: =IF(F15="","",(G15+H15+I15)/F15)
B16: =IF(C16="","ENG-"&TEXT(COUNTA($C$5:C16),"000")) | J16: =IF(F16="","",(G16+H16+I16)/F16)
B17: =IF(C17="","ENG-"&TEXT(COUNTA($C$5:C17),"000")) | J17: =IF(F17="","",(G17+H17+I17)/F17)
B18: =IF(C18="","ENG-"&TEXT(COUNTA($C$5:C18),"000")) | J18: =IF(F18="","",(G18+H18+I18)/F18)
B19: =IF(C19="","ENG-"&TEXT(COUNTA($C$5:C19),"000")) | J19: =IF(F19="","",(G19+H19+I19)/F19)
... B107: =IF(C107="","ENG-"&TEXT(COUNTA($C$5:C107),"000")) | J107: =IF(F107="","",(G107+H107+I107)/F107)
B109: INDICATEURS (mis a jour automatiquement)
B110: Plateformes suivies | D110: Total abonnes | F110: Engagement moyen
B111: =COUNTIF(B5:B104,"<>") | D111: =SUM(D5:D104) | F111: =IFERROR(AVERAGE(J5:J104),0)

Sheet 14-Analyse Cand. Spontanees
B2: ANALYSE CANDIDATURES SPONTANEES
B3: TABLEAU DYNAMIQUE — Saisissez dans la prochaine ligne jaune. Les calculs se mettent a jour automatiquement.
B4: N° | C4: Mois | D4: Nb Candidatures Recues | E4: Nb Entretiens Realises | F4: Nb Recrutements | G4: Taux Transformation (%) | H4: Duree Moy. Processus (j) | I4: Poste le Plus Demande | J4: Source Principale
B5: ACS-001 | C5: Janvier 2025 | D5: 12 | E5: 5 | F5: 2 | H5: 18 | I5: Receptionniste | J5: Site web hotel
B6: ACS-002 | C6: Fevrier 2025 | D6: 15 | E6: 7 | F6: 3 | H6: 15 | I6: Cuisinier | J6: LinkedIn
B7: ACS-003 | C7: Mars 2025 | D7: 8 | E7: 4 | F7: 1 | H7: 22 | I7: Technicien IT | J7: Bouche a oreille
B8: =IF(C8="","ACS-"&TEXT(COUNTA($C$5:C8),"000")) | G8: =IF(D8="","",F8/D8)
B9: =IF(C9="","ACS-"&TEXT(COUNTA($C$5:C9),"000")) | G9: =IF(D9="","",F9/D9)
B10: =IF(C10="","ACS-"&TEXT(COUNTA($C$5:C10),"000")) | G10: =IF(D10="","",F10/D10)
B11: =IF(C11="","ACS-"&TEXT(COUNTA($C$5:C11),"000")) | G11: =IF(D11="","",F11/D11)
B12: =IF(C12="","ACS-"&TEXT(COUNTA($C$5:C12),"000")) | G12: =IF(D12="","",F12/D12)
B13: =IF(C13="","ACS-"&TEXT(COUNTA($C$5:C13),"000")) | G13: =IF(D13="","",F13/D13)
B14: =IF(C14="","ACS-"&TEXT(COUNTA($C$5:C14),"000")) | G14: =IF(D14="","",F14/D14)
B15: =IF(C15="","ACS-"&TEXT(COUNTA($C$5:C15),"000")) | G15: =IF(D15="","",F15/D15)
B16: =IF(C16="","ACS-"&TEXT(COUNTA($C$5:C16),"000")) | G16: =IF(D16="","",F16/D16)
B17: =IF(C17="","ACS-"&TEXT(COUNTA($C$5:C17),"000")) | G17: =IF(D17="","",F17/D17)
B18: =IF(C18="","ACS-"&TEXT(COUNTA($C$5:C18),"000")) | G18: =IF(D18="","",F18/D18)
B19: =IF(C19="","ACS-"&TEXT(COUNTA($C$5:C19),"000")) | G19: =IF(D19="","",F19/D19)
... B107: =IF(C107="","ACS-"&TEXT(COUNTA($C$5:C107),"000")) | G107: =IF(D107="","",F107/D107)
B109: INDICATEURS (mis a jour automatiquement)
B110: Total candidatures | D110: Total recrutements | F110: Taux transfo. moyen
B111: =SUM(D5:D104) | D111: =SUM(F5:F104) | F111: =IFERROR(AVERAGE(G5:G104),0)

Sheet 15-Hist. Evenements RH
B2: HISTORIQUE EVENEMENTS RH
B3: TABLEAU DYNAMIQUE — Saisissez dans la prochaine ligne jaune. Les calculs se mettent a jour automatiquement.
B4: N° | C4: Evenement | D4: Type | E4: Date | F4: Nb Participants Reels | G4: Nb Participants Prevus | H4: Taux Participation (%) | I4: Budget Prevu (FCFA) | J4: Cout Reel (FCFA) | K4: Ecart Budget (FCFA) | L4: Satisfaction Moy. / 5 | M4: Observations
B5: HEV-001 | C5: Team building Q4 2024 | D5: Team building | E5: 45611 | F5: 65 | G5: 70 | I5: 1500000 | J5: 1350000 | L5: 4.2 | M5: Tres bonne ambiance
B6: HEV-002 | C6: Gala fin d'annee 2024 | D6: Gala employes | E6: 45646 | F6: 120 | G6: 130 | I6: 3500000 | J6: 3200000 | L6: 4.5 | M6: Animation musicale reussie
B7: HEV-003 | C7: Semaine integration Janv. | D7: Semaine d'integration | E7: 45663 | F7: 8 | G7: 8 | I7: 200000 | J7: 180000 | L7: 4 | M7: Nouveaux integrates
B8: =IF(C8="","HEV-"&TEXT(COUNTA($C$5:C8),"000")) | H8: =IF(G8="","",F8/G8) | K8: =IF(I8="","",I8-J8)
B9: =IF(C9="","HEV-"&TEXT(COUNTA($C$5:C9),"000")) | H9: =IF(G9="","",F9/G9) | K9: =IF(I9="","",I9-J9)
B10: =IF(C10="","HEV-"&TEXT(COUNTA($C$5:C10),"000")) | H10: =IF(G10="","",F10/G10) | K10: =IF(I10="","",I10-J10)
B11: =IF(C11="","HEV-"&TEXT(COUNTA($C$5:C11),"000")) | H11: =IF(G11="","",F11/G11) | K11: =IF(I11="","",I11-J11)
B12: =IF(C12="","HEV-"&TEXT(COUNTA($C$5:C12),"000")) | H12: =IF(G12="","",F12/G12) | K12: =IF(I12="","",I12-J12)
B13: =IF(C13="","HEV-"&TEXT(COUNTA($C$5:C13),"000")) | H13: =IF(G13="","",F13/G13) | K13: =IF(I13="","",I13-J13)
B14: =IF(C14="","HEV-"&TEXT(COUNTA($C$5:C14),"000")) | H14: =IF(G14="","",F14/G14) | K14: =IF(I14="","",I14-J14)
B15: =IF(C15="","HEV-"&TEXT(COUNTA($C$5:C15),"000")) | H15: =IF(G15="","",F15/G15) | K15: =IF(I15="","",I15-J15)
B16: =IF(C16="","HEV-"&TEXT(COUNTA($C$5:C16),"000")) | H16: =IF(G16="","",F16/G16) | K16: =IF(I16="","",I16-J16)
B17: =IF(C17="","HEV-"&TEXT(COUNTA($C$5:C17),"000")) | H17: =IF(G17="","",F17/G17) | K17: =IF(I17="","",I17-J17)
B18: =IF(C18="","HEV-"&TEXT(COUNTA($C$5:C18),"000")) | H18: =IF(G18="","",F18/G18) | K18: =IF(I18="","",I18-J18)
B19: =IF(C19="","HEV-"&TEXT(COUNTA($C$5:C19),"000")) | H19: =IF(G19="","",F19/G19) | K19: =IF(I19="","",I19-J19)
... B107: =IF(C107="","HEV-"&TEXT(COUNTA($C$5:C107),"000")) | H107: =IF(G107="","",F107/G107) | K107: =IF(I107="","",I107-J107)
B109: INDICATEURS (mis a jour automatiquement)
B110: Evenements realises | D110: Participants totaux | F110: Satisfaction moyenne
B111: =COUNTIF(B5:B104,"<>") | D111: =SUM(F5:F104) | F111: =IFERROR(AVERAGE(L5:L104),0)

Sheet 16-Calendrier Communication
B2: CALENDRIER COMMUNICATION
B3: TABLEAU DYNAMIQUE — Saisissez dans la prochaine ligne jaune. Les calculs se mettent a jour automatiquement.
B4: N° | C4: Action Communication | D4: Type | E4: Canal | F4: Date Prevue | G4: Responsable | H4: Public Cible | I4: Statut | J4: Rappel
B5: CAL-001 | C5: Envoi newsletter mars | D5: Information | E5: Email | F5: 45744 | G5: DRH | H5: Tous les employes | I5: Planifie | J5: 25/03/2025
B6: CAL-002 | C6: Post LinkedIn offres saison | D6: Recrutement | E6: LinkedIn | F6: 45717 | G6: Chef Marketing | H6: Jeunes diplomes | I6: En cours | J6: 28/02/2025
B7: CAL-003 | C7: Affichage nouveau reglement | D7: Annonce | E7: Panneau d'affichage | F7: 45726 | G7: DRH | H7: Tous les employes | I7: Planifie | J7: 07/03/2025
B8: CAL-004 | C8: Sondage satisfaction Q1 | D8: Consultation | E8: Intranet | F8: 45731 | G8: DRH | H8: Tous les employes | I8: Planifie | J8: 12/03/2025
B9: =IF(C9="","CAL-"&TEXT(COUNTA($C$5:C9),"000"))
B10: =IF(C10="","CAL-"&TEXT(COUNTA($C$5:C10),"000"))
B11: =IF(C11="","CAL-"&TEXT(COUNTA($C$5:C11),"000"))
B12: =IF(C12="","CAL-"&TEXT(COUNTA($C$5:C12),"000"))
B13: =IF(C13="","CAL-"&TEXT(COUNTA($C$5:C13),"000"))
B14: =IF(C14="","CAL-"&TEXT(COUNTA($C$5:C14),"000"))
B15: =IF(C15="","CAL-"&TEXT(COUNTA($C$5:C15),"000"))
B16: =IF(C16="","CAL-"&TEXT(COUNTA($C$5:C16),"000"))
B17: =IF(C17="","CAL-"&TEXT(COUNTA($C$5:C17),"000"))
B18: =IF(C18="","CAL-"&TEXT(COUNTA($C$5:C18),"000"))
B19: =IF(C19="","CAL-"&TEXT(COUNTA($C$5:C19),"000"))
B20: =IF(C20="","CAL-"&TEXT(COUNTA($C$5:C20),"000"))
... B108: =IF(C108="","CAL-"&TEXT(COUNTA($C$5:C108),"000"))
B110: INDICATEURS (mis a jour automatiquement)
B111: Actions planifiees | D111: En cours | F111: Planifiees
B112: =COUNTIF(B5:B104,"<>") | D112: =COUNTIF(I5:I104,"En cours") | F112: =COUNTIF(I5:I104,"Planifie")

Sheet 17-Matrice Canaux Comm.
B2: MATRICE CANAUX COMMUNICATION
B3: TABLEAU DYNAMIQUE — Saisissez dans la prochaine ligne jaune. Les calculs se mettent a jour automatiquement.
B4: N° | C4: Canal | D4: Type Communication | E4: Public Cible | F4: Frequence | G4: Portee Estimee | H4: Cout par Envoi (FCFA) | I4: Efficacite (%) | J4: Derniere Utilisation | K4: Observations
B5: MCC-001 | C5: Email | D5: Annonce, Information | E5: Tous employes | F5: Hebdomadaire | G5: 160 | H5: 0 | I5: 0.72 | J5: 45716 | K5: Canal principal, taux ouverture bon
B6: MCC-002 | C6: Affichage | D6: Annonce, Rappel | E6: Tous employes | F6: Ponctuelle | G6: 160 | H6: 5000 | I6: 0.6 | J6: 45703 | K6: Panneau hall principal
B7: MCC-003 | C7: LinkedIn | D7: Recrutement, ME | E7: Candidats | F7: Hebdomadaire | G7: 8000 | H7: 2000 | I7: 0.45 | J7: 45716 | K7: Meilleur canal recrutement
B8: MCC-004 | C8: WhatsApp | D8: Alerte, Rappel | E8: Tous employes | F8: Ponctuelle | G8: 150 | H8: 0 | I8: 0.85 | J8: 45708 | K8: Tres rapide, taux lecture eleve
B9: =IF(C9="","MCC-"&TEXT(COUNTA($C$5:C9),"000"))
B10: =IF(C10="","MCC-"&TEXT(COUNTA($C$5:C10),"000"))
B11: =IF(C11="","MCC-"&TEXT(COUNTA($C$5:C11),"000"))
B12: =IF(C12="","MCC-"&TEXT(COUNTA($C$5:C12),"000"))
B13: =IF(C13="","MCC-"&TEXT(COUNTA($C$5:C13),"000"))
B14: =IF(C14="","MCC-"&TEXT(COUNTA($C$5:C14),"000"))
B15: =IF(C15="","MCC-"&TEXT(COUNTA($C$5:C15),"000"))
B16: =IF(C16="","MCC-"&TEXT(COUNTA($C$5:C16),"000"))
B17: =IF(C17="","MCC-"&TEXT(COUNTA($C$5:C17),"000"))
B18: =IF(C18="","MCC-"&TEXT(COUNTA($C$5:C18),"000"))
B19: =IF(C19="","MCC-"&TEXT(COUNTA($C$5:C19),"000"))
B20: =IF(C20="","MCC-"&TEXT(COUNTA($C$5:C20),"000"))
... B108: =IF(C108="","MCC-"&TEXT(COUNTA($C$5:C108),"000"))
B110: INDICATEURS (mis a jour automatiquement)
B111: Canaux actifs | D111: Portee cumulee | F111: Efficacite moyenne
B112: =COUNTIF(B5:B104,"<>") | D112: =SUM(G5:G104) | F112: =IFERROR(AVERAGE(I5:I104),0)

Sheet 18-Suivi Ambassadeurs
B2: SUIVI AMBASSADEURS
B3: TABLEAU DYNAMIQUE — Saisissez dans la prochaine ligne jaune. Les calculs se mettent a jour automatiquement.
B4: N° | C4: Ambassadeur | D4: Departement | E4: Niveau | F4: Posts Ce Mois | G4: Partages Ce Mois | H4: Reach Ce Mois | I4: Score Impact Mensuel | J4: Score Impact Cumul | K4: Evolution Niveau | L4: Date Evaluation
B5: SUA-001 | C5: Tchinda | D5: Cuisine & Restauration | E5: Platine | F5: 4 | G5: 3 | H5: 2500 | K5: Maintien | L5: 45716
B6: SUA-002 | C6: Fotsing | D6: Réception & Front Office | E6: Or | F6: 3 | G6: 2 | H6: 1800 | K6: En hausse | L6: 45716
B7: SUA-003 | C7: Kamga | D7: Service Client | E7: Argent | F7: 2 | G7: 1 | H7: 800 | K7: En hausse | L7: 45716
B8: =IF(C8="","SUA-"&TEXT(COUNTA($C$5:C8),"000")) | I8: =IF(F8="","",F8*3+G8*5) | J8: =IF(I8="","",I8)
B9: =IF(C9="","SUA-"&TEXT(COUNTA($C$5:C9),"000")) | I9: =IF(F9="","",F9*3+G9*5) | J9: =IF(I9="","",I9)
B10: =IF(C10="","SUA-"&TEXT(COUNTA($C$5:C10),"000")) | I10: =IF(F10="","",F10*3+G10*5) | J10: =IF(I10="","",I10)
B11: =IF(C11="","SUA-"&TEXT(COUNTA($C$5:C11),"000")) | I11: =IF(F11="","",F11*3+G11*5) | J11: =IF(I11="","",I11)
B12: =IF(C12="","SUA-"&TEXT(COUNTA($C$5:C12),"000")) | I12: =IF(F12="","",F12*3+G12*5) | J12: =IF(I12="","",I12)
B13: =IF(C13="","SUA-"&TEXT(COUNTA($C$5:C13),"000")) | I13: =IF(F13="","",F13*3+G13*5) | J13: =IF(I13="","",I13)
B14: =IF(C14="","SUA-"&TEXT(COUNTA($C$5:C14),"000")) | I14: =IF(F14="","",F14*3+G14*5) | J14: =IF(I14="","",I14)
B15: =IF(C15="","SUA-"&TEXT(COUNTA($C$5:C15),"000")) | I15: =IF(F15="","",F15*3+G15*5) | J15: =IF(I15="","",I15)
B16: =IF(C16="","SUA-"&TEXT(COUNTA($C$5:C16),"000")) | I16: =IF(F16="","",F16*3+G16*5) | J16: =IF(I16="","",I16)
B17: =IF(C17="","SUA-"&TEXT(COUNTA($C$5:C17),"000")) | I17: =IF(F17="","",F17*3+G17*5) | J17: =IF(I17="","",I17)
B18: =IF(C18="","SUA-"&TEXT(COUNTA($C$5:C18),"000")) | I18: =IF(F18="","",F18*3+G18*5) | J18: =IF(I18="","",I18)
B19: =IF(C19="","SUA-"&TEXT(COUNTA($C$5:C19),"000")) | I19: =IF(F19="","",F19*3+G19*5) | J19: =IF(I19="","",I19)
... B107: =IF(C107="","SUA-"&TEXT(COUNTA($C$5:C107),"000")) | I107: =IF(F107="","",F107*3+G107*5) | J107: =IF(I107="","",I107)
B109: INDICATEURS (mis a jour automatiquement)
B110: Ambassadeurs actifs | D110: Posts total mois | F110: Reach total mois
B111: =COUNTIF(B5:B104,"<>") | D111: =SUM(F5:F104) | F111: =SUM(H5:H104)

Sheet 19-Analyse Result. Enquetes
B2: ANALYSE RESULTATS ENQUETES
B3: TABLEAU DYNAMIQUE — Saisissez dans la prochaine ligne jaune. Les calculs se mettent a jour automatiquement.
B4: N° | C4: Enquete | D4: Axe / Theme | E4: Nb Reponses | F4: Score Moyen / 5 | G4: Score Precedent / 5 | H4: Evolution (pts) | I4: Nb Commentaires Positifs | J4: Nb Commentaires Negatifs | K4: Action Corrective | L4: Statut Action
B5: ARE-001 | C5: Climat social 2024 | D5: Relations avec le manager | E5: 128 | F5: 3.9 | G5: 3.7 | I5: 45 | J5: 12 | K5: Formation managers communication | L5: En cours
B6: ARE-002 | C6: Climat social 2024 | D6: Conditions de travail | E6: 128 | F6: 3.5 | G6: 3.4 | I6: 30 | J6: 25 | K6: Audit equipements cuisine | L6: Planifie
B7: ARE-003 | C7: Climat social 2024 | D7: Equilibre vie pro/perso | E7: 128 | F7: 3.2 | G7: 3 | I7: 22 | J7: 35 | K7: Flexibilite horaires test | L7: En cours
B8: ARE-004 | C8: Climat social 2024 | D8: Reconnaissance au travail | E8: 128 | F8: 4.1 | G8: 3.8 | I8: 55 | J8: 8 | K8: Programme employe du mois | L8: Termine
B9: =IF(C9="","ARE-"&TEXT(COUNTA($C$5:C9),"000")) | H9: =IF(OR(F9="",G9=""),"",F9-G9)
B10: =IF(C10="","ARE-"&TEXT(COUNTA($C$5:C10),"000")) | H10: =IF(OR(F10="",G10=""),"",F10-G10)
B11: =IF(C11="","ARE-"&TEXT(COUNTA($C$5:C11),"000")) | H11: =IF(OR(F11="",G11=""),"",F11-G11)
B12: =IF(C12="","ARE-"&TEXT(COUNTA($C$5:C12),"000")) | H12: =IF(OR(F12="",G12=""),"",F12-G12)
B13: =IF(C13="","ARE-"&TEXT(COUNTA($C$5:C13),"000")) | H13: =IF(OR(F13="",G13=""),"",F13-G13)
B14: =IF(C14="","ARE-"&TEXT(COUNTA($C$5:C14),"000")) | H14: =IF(OR(F14="",G14=""),"",F14-G14)
B15: =IF(C15="","ARE-"&TEXT(COUNTA($C$5:C15),"000")) | H15: =IF(OR(F15="",G15=""),"",F15-G15)
B16: =IF(C16="","ARE-"&TEXT(COUNTA($C$5:C16),"000")) | H16: =IF(OR(F16="",G16=""),"",F16-G16)
B17: =IF(C17="","ARE-"&TEXT(COUNTA($C$5:C17),"000")) | H17: =IF(OR(F17="",G17=""),"",F17-G17)
B18: =IF(C18="","ARE-"&TEXT(COUNTA($C$5:C18),"000")) | H18: =IF(OR(F18="",G18=""),"",F18-G18)
B19: =IF(C19="","ARE-"&TEXT(COUNTA($C$5:C19),"000")) | H19: =IF(OR(F19="",G19=""),"",F19-G19)
B20: =IF(C20="","ARE-"&TEXT(COUNTA($C$5:C20),"000")) | H20: =IF(OR(F20="",G20=""),"",F20-G20)
... B108: =IF(C108="","ARE-"&TEXT(COUNTA($C$5:C108),"000")) | H108: =IF(OR(F108="",G108=""),"",F108-G108)
B110: INDICATEURS (mis a jour automatiquement)
B111: Axes analyses | D111: Score moyen global | F111: Actions en cours
B112: =COUNTIF(B5:B104,"<>") | D112: =IFERROR(AVERAGE(F5:F104),0) | F112: =COUNTIF(L5:L104,"En cours")
